Workbook

Sheet Version_Control
A1: VERSION CONTROL — RetainKit
A3: Version | B3: Date | C3: Author | D3: Change | E3: Status
A4: v001-v004 | B4: 2026-09-05 | C4: Claude for Senthil/KP | D4: Lineage: marketplace master (868 entries) -> portfolio plan (12 products) -> this product selected for wave-1 | E4: Released
A5: v005 | B5: 2026-09-05 19:34 | C5: Claude for Senthil/KP | D5: Full product workbook for RetainKit on Shopify App Store: spec, screen inventory, 100+ story backlog, live sprint board, 18-month financial model (editable assumptions), GTM execution tasks, platform launch checklist, metric targets, risk register | E5: Released
A6: v006 | B6: 2026-09-10 22:05 | C6: Claude for Senthil/KP | D6: S1 Foundation executed under D13 (100% automation coverage): ST-051/052/055/056 developed + tested (40 tests, 100% stmt/branch/func/line). Added Sprint_Tracker_Log and Traceability_Matrix sheets; Full_Backlog statuses and Sprint_Board Done counts updated. | E6: Released
A7: v007 | B7: 2026-09-10 22:15 | C7: Claude for Senthil/KP | D7: S2 executed under D13: ST-001/002/003/004/053/054 developed + tested (33 new tests; suite 73/73, 100% stmt/branch/func/line, hard gate). Review request engine part 1: defaults setup, rules customisation, eligibility+scheduling+send with retry paths, review capture, re-install restore, role permission matrix. Tracker + traceability updated. | E7: Released
A8: v008 | B8: 2026-09-10 22:20 | C8: Claude for Senthil/KP | D8: S3 executed under D13: ST-005..010, ST-011..014, ST-085 developed + tested (47 new tests; suite 120/120, 100% stmt/branch/func/line, hard gate). Engine part 2: embedded admin session-token verification, metrics/trends, audited permission gate, pause-without-data-loss, CSV + competitor import, notifications with per-type mute. Points ledger skeleton: defaults, validated rules, earn/balance/redeem, platform sync retry paths. ST-085 coverage gate satisfied at 100% (supersedes >=70%). | E8: Released
A9: v009 | B9: 2026-09-10 22:28 | C9: Claude for Senthil/KP | D9: S4 executed under D13: ST-015..020, ST-071, ST-072, ST-086 developed + tested (27 new tests; suite 147/147, 100% stmt/branch/func/line). Ledger completion: embedded session-token gateway, ledger metrics/trends, gated+audited admin ops (new adjust_points permission for owner/admin), feature-scoped pause without data loss, points CSV/competitor import to opening-balance txns, ledger notification types. Telemetry: activation funnel dashboard, release-tagged error tracking with spike alerts. ST-086: E2E smoke suite (full merchant journey across real modules) + GitHub Actions deploy-smoke workflow. MVP loop usable end-to-end internally (S4 exit criteria, code level). | E9: Released
A10: v010 | B10: 2026-09-10 22:52 | C10: Claude for Senthil/KP | D10: S5 executed under D13: ST-021..030, ST-078, ST-079 developed + tested (36 new tests; suite 183/183, 100% stmt/branch/func/line). Win-back flows: defaults/validated rules, lapsed detection, multi-step flows with channel rotation, step sends with retry paths, conversion recording with pending-step cancellation, embedded gateway, metrics (win-back rate), gated+audited admin, feature pause extended, customer CSV/competitor import, notification types. Alpha hardening: first-run checklist with aha-in-<1-day tracking, empty states for all 9 screens each naming the next action. Internal alpha ready at code level (S5 exit criteria). | E10: Released
A11: v011 | B11: 2026-09-10 23:09 | C11: Claude for Senthil/KP | D11: S6 executed under D13: ST-031..040, ST-057..059 developed + tested (31 new tests; suite 214/214, 100% stmt/branch/func/line). Billing: 14-day no-card trial with countdown banner, exact mid-cycle proration (upgrade charge / downgrade credit / no-change), billing router using Shopify Billing API where mandated (pending-confirmation lifecycle) with Stripe fallback for direct channel, full subscription lifecycle (subscribe/confirm/changePlan/cancel, resubscribe after cancel). Analytics: config defaults + validation, cross-pillar dashboard composer with per-widget retry/degradation (dashboard always renders), embedded gateway, gated view/export with audit, usage metrics, historical CSV/competitor import, feature pause + notification types. S6 exit criteria met at code level: can charge a test customer; upgrade/downgrade paths work. | E11: Released
A12: v012 | B12: 2026-09-11 08:20 | C12: Claude for Senthil/KP | D12: S7 executed under D13: ST-060..064 developed + tested (16 new tests; suite 230/230, 100% stmt/branch/func/line across 19 modules). Dunning: idempotent failure recording, emails on days 0/3/5 with catch-up (max 3), read-only after 7-day grace, payment restores. Plan limits: silent <80%, upgrade prompt at 80%, hard block at 100% (blocked requests not counted). Invoices: sequential numbering, GST/VAT computation with tax-id, downloadable text receipts, validation. Cancellation: save-offer (20%/3mo) before every cancel, accept retains, decline records validated exit survey then cancels via owning provider. ST-064: least-privilege SCOPES.md (4 scopes -> shipped features, no speculative scopes) + CI validator. Gate catches this sprint: SCOPES.md separator-row assertion + unexercised CancellationFlow default clock. | E12: Released
A13: v013 | B13: 2026-09-11 12:52 | C13: Claude for Senthil/KP | D13: S8 executed under D13 - biggest sprint (22 stories, 87 pts): ST-041..050 Klaviyo/Meta audience sync (defaults, 4-segment builder always excluding opt-outs, platform x segment push engine with per-job retry paths, embedded gateway with run/log, metrics with success rate, gated admin, feature pause, CSV/competitor import, notifications). E6: DATA_FLOWS.md retention doc + CI validator; AES-256-GCM secrets vault (ciphertext-only at rest, tamper-detecting, rotation) + https enforcement; hash-chained tamper-evident audit log with query; circuit breaker (closed/open/half-open, fail-fast, trial) + Retry-After-aware backoff. E7: feature-usage heatmap, weekly metrics email, account health score with bands+reasons, CSV/JSONL metrics export, configurable alert thresholds. EQ: p95 latency budgets per surface, load test driving the REAL engine+ledger at 5x launch traffic (300 req, 0 errors, p95 within budget), zero-downtime blue/green deployer (traffic never leaves a healthy version). 41 new tests; suite 271/271, 100% x4 across 23 modules. | E13: Released
A14: v014 | D14: PLANNED: S9 Marketplace review prep (ST-068, ST-069, ST-089, ST-090, ST-091, ST-093, ST-094) | E14: Planned
A15: v014 | B15: 2026-09-13 10:23 | C15: Claude for Senthil/KP | D15: S9 REVIEW PREP + FIRST ADVERSARIAL COLD REVIEW + EXTERNAL VERIFICATION SWEEP. Built: ST-069 export/delete-my-data, ST-090 backup+restore drill (sha256, ship-block), ST-091 chaos degradation with merchant comms; ST-068 SECURITY_EVIDENCE.md and ST-089 structural WCAG audit shipped as explicit halves; ST-093 listing copy A/B and ST-094 asset plan Drafted. Cold review found 9 defects in code at 100% coverage (F-RK01..09) — headline: both CSV importers reset every unsubscribe to subscribed, and three separate read-only/expiry states were enforced nowhere. Verification sweep vs live Shopify docs found 3 live-blocking gaps (VER-RK01..06) — headline: the three MANDATORY compliance webhooks did not exist, an automatic App Store rejection, while gate row LC-4 had read "In progress" since v001. New Review_Findings sheet holds all 18 rows for disposition. Code v014: 14 suites / 339 tests at 100% on all four metrics, zero pragmas. 85/100 stories Done-in-code (346/399 pts). | E15: Released
A16: v015 | B16: 2026-09-13 10:34 | C16: Claude for Senthil/KP | D16: ARTIFACT-GAP AUDIT. 6 gaps, 2 CRITICAL — GAP-RK1 no HTTP application existed behind any route shopify.app.toml declared (this session wrote that manifest at 10:23 and the routes did not exist until 10:34); GAP-RK2 no database schema behind the backup drill, retention sweep or the 12 registry domains. Fixed with an async-safe router, a 7-route app, 3 ordered migrations cascading from shops, npm build/start/migrate, CI build+migration gates, and an executable SETUP.md. VER-RK07 found while building: the app proxy signature scheme is not the OAuth HMAC scheme. Code v015: 15 suites / 374 tests at 100% zero pragmas. Story position deliberately unchanged at 85/100 (346/399) — this is infrastructure, not story flips. | E16: Released
A17: v016 | B17: 2026-09-13 10:43 | C17: Claude for Senthil/KP | D17: S10 EXECUTED — all 7 remaining sandbox-codeable stories. ST-080 help centre: 15 launch articles with ranked search (keyword matches outrank title, title outranks body, because merchants search symptoms not headings). ST-081 built-in chat with a business-hours SLA engine — a Friday-evening message is due Monday morning, and breaches are surfaced so the 4-hour promise is measurable rather than decorative; the chat-vendor decision is now OPTIONAL (DR-7 to ratify). ST-095 pricing page and ST-096 trust page GENERATED from billing PLANS, DATA_FLOWS and REQUESTED_SCOPES, each with a drift gate that fires on over- or under-claiming. ST-084 incident template that REFUSES to publish an update with no impact or action statement. ST-083 demo mode isolated by construction — it will not seed any shop outside the demo- namespace (MeetSync M-F16 class, prevented rather than fixed). ST-097 submission dry-run that reports READY on the automated half only and never on a human or external item. Three new public routes (/pricing, /trust, /help). Code v016: 16 suites / 404 tests at 100% on all four metrics, zero pragmas. 90/100 stories Done-in-code (362/399 pts, 90.7%) — 5 of the 7 flip to Done-in-code, ST-083 is code-complete pending video capture and ST-097 stays In progress pending the external reviewer, so the honest count is 5 not 7. SANDBOX-CODEABLE BACKLOG NOW ZERO except ST-082/098/099/100. | E17: Released
A18: v017 | B18: 2026-09-13 10:59 | C18: Claude for Senthil/KP | D18: S11/S12 EXECUTED — the last four backlog stories. ST-082 review ask gated on the aha moment and refused, with a named reason, whenever asking would be rude or useless (open support ticket, active incident, read-only shop, within the 90-day cooldown, or already reviewed). ST-098 launch runbook written as CODE so its rollback triggers reference the same LATENCY_BUDGETS_MS the monitor enforces — tuning a budget tunes the trigger in the same edit; it holds while any operator step is outstanding and never reports proceed on a step with no wired check, and ROLLBACK_NOTES names what a rollback cannot undo (a completed customer redaction must never be restored by a database snapshot). ST-099 SEO iteration with a 100-impression thin-data floor, returning a thin-data report rather than suggestions. ST-100 10-slot partner tracker whose exit maths states plainly that filling all ten slots does not meet G-02 and that reviews satisfy the S11 exit, not the completion gate (VoiceBridge F-V13 class, prevented). RETAINKIT CODE PHASE COMPLETE — backlog zero; sixth product to reach it after TeleField, VoiceBridge, FlowCast, ShiftDesk and EngageOS. Code v017: 17 suites / 430 tests at 100% on all four metrics, zero pragmas. 94/100 stories Done-in-code (372/399 pts, 93.2%); the remaining 6 are ST-068 pen-test, ST-083 video capture, ST-089 accessibility manual half, ST-093/094 copy pick and asset capture, ST-097 external reviewer — every one of them Senthil's. | E18: Released
A19: v018 | B19: 2026-09-13 11:04 | C19: Claude for Senthil/KP | D19: R-K10 CLOSED IN CODE — Postgres adapters behind the store interfaces. PgTokenStore (encrypts before the value leaves the process, so the plaintext token never appears in a query the database could log), PgStateStore (single-use AND time-limited in one DELETE ... RETURNING, so two concurrent callbacks cannot both consume the same state), PgComplianceRequestStore, PgTrialStore, PgSubscriptionStore, PgDunningStore, and a PgDomainAdapter per data domain with an explicit table/customer-column map. Every caller value is a bound parameter and a test proves it by pushing a SQL-injection string through every adapter. New SCHEMA DRIFT GATE parses migrations/*.sql and fails if an adapter names a table or column the schema does not create; it also asserts every customer-bearing table cascades from shops, and that compliance_requests deliberately does NOT — it is the proof of erasure and must outlive the shop row. Two defects found by writing the adapters: migration 004 (the subscriptions table shipped without the provider, subscription_id and confirmation_url columns SubscriptionRecord has always carried) and F-RK10 / migration 005 — customer_consent had no email column, so a privacy request carrying ONLY an email (a shape Shopify documents and our handler has always accepted) would have matched zero rows while the app recorded the request as completed. A reported erasure that erased nothing is worse than a failed one. Both fixed by new migrations rather than edits to shipped ones. Code v018: 18 suites / 456 tests at 100% on all four metrics, zero pragmas. Story position unchanged at 94/100 (372/399) — infrastructure, not story flips. HONESTY: these adapters are schema-checked, NOT server-tested; no Postgres was available. The constant PG_ADAPTER_VERIFICATION_STATUS says so in the code and a test asserts the wording. | E19: Released
A20: v019 | B20: 2026-09-13 11:09 | C20: Claude for Senthil/KP | D20: HANDOVER-REDUCTION PASS — three items that each cut Senthil's dev-store session, built after I had wrongly said nothing sandbox-buildable remained. (1) PERSISTENCE IS NOW AUTOMATIC: chosen from DATABASE_URL, and if DATABASE_URL is set without a SQL client the app REFUSES TO START rather than quietly writing to memory against a configured database — the dangerous failure is the quiet one, an app that looks healthy and loses everything on restart. Token encryption key derived from the app secret via sha256 with a domain-separated label, overridable. (2) SCRIPTED VERIFICATION SWEEP (npm run sweep): 8 automated checks incl. an API-version check that catches an old slot still serving, a forged-webhook check that fails loudly if the app accepts an unsigned webhook, and reachability of the pricing and trust pages the listing requires; exits non-zero on failure and lists the 5 operator steps rather than counting them as passed. SETUP.md now runs the sweep as step 7. (3) REVIEW_PACK.md for the external second reviewer (ST-097): names where to look first, lists every known open item so the reviewer does not rediscover them, and asks specifically for the defect class every review of this codebase has actually found — a published promise with nothing enforcing it. Code v019: 19 suites / 469 tests at 100% on all four metrics, zero pragmas. Story position unchanged at 94/100 (372/399). | E20: Released

Sheet ReadMe_Scope
A1: RetainKit — Post-purchase retention suite: reviews capture, loyalty points, win-back flows in one app
A3: PLATFORM: Shopify App Store | CATEGORY: Customer Retention / Loyalty
A4: PROBLEM: Merchants stitch 3-4 apps (reviews+loyalty+email) with double billing and broken data flow
A5: DIFFERENTIATION: Single retention data model; Built-for-Shopify quality badge target; usage-based pricing
A6: ICP: DTC merchants $100k-$10M GMV, 1-20 staff, Shopify/Shopify Plus, currently paying for 2+ point apps
A8: HOW TO USE: Full_Backlog is the single source of truth (edit Status column during execution). Sprint_Board recalculates points per sprint automatically. Financial_Model assumptions (yellow) are editable — the 18-month build recalculates. Launch_Checklist is the platform-specific gate before submission. All costs/timelines are market-standard estimates; verify platform terms (fees/review rules) during S0.
A10: STACK ASSUMPTION (market standard): TypeScript/Node or platform-mandated runtime, React frontends, Postgres, hosted on AWS/GCP/platform FaaS as required, GitHub Actions CI, PostHog + Sentry telemetry, Intercom-class support.

Sheet Product_Spec
A1: PRODUCT SPEC
A3: Module (feature) | B3: Scope in MVP | C3: Out of scope (v1) | D3: Non-functional requirements
A4: Review request engine | B4: Review request engine: end-to-end happy path + edge cases + permissions | C4: Advanced automation, AI beyond listed, multi-language beyond launch set | D4: p95 <500ms API / <2s UI loads
A5: Points & rewards ledger | B5: Points & rewards ledger: end-to-end happy path + edge cases + permissions | C5: Advanced automation, AI beyond listed, multi-language beyond launch set | D5: 99.5% monthly uptime
A6: Win-back email/WhatsApp flows | B6: Win-back email/WhatsApp flows: end-to-end happy path + edge cases + permissions | C6: Advanced automation, AI beyond listed, multi-language beyond launch set | D6: WCAG AA
A7: Analytics dashboard | B7: Analytics dashboard: end-to-end happy path + edge cases + permissions | C7: Advanced automation, AI beyond listed, multi-language beyond launch set | D7: SOC2-track controls
A8: Klaviyo/Meta audience sync | B8: Klaviyo/Meta audience sync: end-to-end happy path + edge cases + permissions | C8: Advanced automation, AI beyond listed, multi-language beyond launch set | D8: Rate-limit safe (backoff+queue)
A10: Persona | B10: Jobs-to-be-done
A11: Store owner (SMB) | B11: Owns P&L, buys in <7 days, price-sensitive, decides from reviews + free trial
A12: E-com manager (mid-market) | B12: Runs 5-15 apps, cares about support SLA and data export
A13: Agency partner | B13: Installs across client portfolio; wants partner rev share + multi-store admin

Sheet Screens_Wireframes
A1: SCREEN INVENTORY (attach Figma links in col E during S0)
A3: # | B3: Screen | C3: Purpose | D3: Key elements | E3: Wireframe link
A4: 1 | B4: Onboarding / first-run | C4: Reach aha in <1 day | D4: Checklist, sample data toggle, connect steps
A5: 2 | B5: Home dashboard | C5: Daily habit surface | D5: KPI cards, activity feed, alerts
A6: 3 | B6: Review request engine workspace | C6: Core value surface | D6: List+detail, bulk actions, status chips
A7: 4 | B7: Points & rewards ledger builder | C7: Configure second pillar | D7: Rule builder, preview, test mode
A8: 5 | B8: Win-back email/WhatsApp flows view | C8: Differentiator surface | D8: Timeline/visual, export
A9: 6 | B9: Settings & team | C9: Roles, notifications, data | D9: Role matrix, API keys, danger zone
A10: 7 | B10: Billing | C10: Plan/trial/invoices | D10: Plan cards, usage meter, invoices
A11: 8 | B11: Analytics | C11: Prove ROI | D11: Funnel, cohort, export
A12: 9 | B12: Help & support | C12: Deflect + assist | D12: Search, chat, status

Sheet Full_Backlog
A1: FULL BACKLOG
A3: ID | B3: Epic | C3: Story | D3: Points | E3: Priority | F3: Sprint | G3: Status
A4: ST-001 | B4: F1 | C4: As a Store owner, I can set up Review request engine with sensible defaults in one screen | D4: 5 | E4: P0 | F4: S2 | G4: Done
A5: ST-002 | B5: F1 | C5: As a Store owner, the Review request engine happy path completes without documentation | D5: 8 | E5: P0 | F5: S2 | G5: Done
A6: ST-003 | B6: F1 | C6: As a E-com manager, I can customise Review request engine rules/conditions for my workflow | D6: 5 | E6: P1 | F6: S2 | G6: Done
A7: ST-004 | B7: F1 | C7: As a user, Review request engine shows clear errors and retry paths on platform API failures | D7: 3 | E7: P0 | F7: S2 | G7: Done
A8: ST-005 | B8: F1 | C8: As a Agency partner, Review request engine works on the embedded Shopify admin app surface end-to-end | D8: 5 | E8: P0 | F8: S3 | G8: Done
A9: ST-006 | B9: F1 | C9: As a E-com manager, I can see Review request engine performance metrics and trends | D9: 3 | E9: P1 | F9: S3 | G9: Done
A10: ST-007 | B10: F1 | C10: As a user, Review request engine respects role permissions and audit logging | D10: 3 | E10: P1 | F10: S3 | G10: Done
A11: ST-008 | B11: F1 | C11: As a Store owner, I can pause/disable Review request engine without data loss | D11: 2 | E11: P2 | F11: S3 | G11: Done
A12: ST-009 | B12: F1 | C12: As a E-com manager, I can import/migrate existing data into Review request engine (CSV + competitor importer) | D12: 5 | E12: P1 | F12: S3 | G12: Done
A13: ST-010 | B13: F1 | C13: As a user, I get notifications (in-app + email) for key Review request engine events with per-type mute | D13: 3 | E13: P2 | F13: S3 | G13: Done
A14: ST-011 | B14: F2 | C14: As a Store owner, I can set up Points & rewards ledger with sensible defaults in one screen | D14: 5 | E14: P0 | F14: S3 | G14: Done
A15: ST-012 | B15: F2 | C15: As a Store owner, the Points & rewards ledger happy path completes without documentation | D15: 8 | E15: P0 | F15: S3 | G15: Done
... A103: ST-100 | B103: EL | C103: First 10 design-partner reviews scheduled | D103: 2 | E103: P1 | F103: S11 | G103: Done
A105: Total stories: 100. Epics: F1-F5 = product features; E1 install, E5 billing, E6 compliance, E7 telemetry, E8 onboarding/docs/support, EQ quality. Edit Status (Backlog/In progress/Done) during execution.

Sheet Sprint_Board
A1: SPRINT BOARD — live counts from Full_Backlog
A3: Sprint | B3: Focus | C3: Stories | D3: Points | E3: Done | F3: Exit criteria
A4: S0 | B4: Discovery & Design (2 wks) | C4: =COUNTIF(Full_Backlog!F4:F103,"S0") -> 0 | D4: =SUMIF(Full_Backlog!F4:F103,"S0",Full_Backlog!D4:D103) -> 0 | E4: =COUNTIFS(Full_Backlog!F4:F103,"S0",Full_Backlog!G4:G103,"Done") -> 0 | F4: PRD signed off; prototype tested with 5 target users
A5: S1 | B5: Foundation (2 wks) | C5: =COUNTIF(Full_Backlog!F4:F103,"S1") -> 4 | D5: =SUMIF(Full_Backlog!F4:F103,"S1",Full_Backlog!D4:D103) -> 13 | E5: =COUNTIFS(Full_Backlog!F4:F103,"S1",Full_Backlog!G4:G103,"Done") -> 4 | F5: App installs cleanly in dev store/org; telemetry firing
A6: S2 | B6: Core feature Review request engine - part 1 | C6: =COUNTIF(Full_Backlog!F4:F103,"S2") -> 6 | D6: =SUMIF(Full_Backlog!F4:F103,"S2",Full_Backlog!D4:D103) -> 29 | E6: =COUNTIFS(Full_Backlog!F4:F103,"S2",Full_Backlog!G4:G103,"Done") -> 6 | F6: Review request engine happy path demoable
A7: S3 | B7: Core feature Review request engine - part 2 + Points & rewards ledger start | C7: =COUNTIF(Full_Backlog!F4:F103,"S3") -> 11 | D7: =SUMIF(Full_Backlog!F4:F103,"S3",Full_Backlog!D4:D103) -> 47 | E7: =COUNTIFS(Full_Backlog!F4:F103,"S3",Full_Backlog!G4:G103,"Done") -> 11 | F7: Review request engine complete with tests; Points & rewards ledger skeleton
A8: S4 | B8: Core feature Points & rewards ledger | C8: =COUNTIF(Full_Backlog!F4:F103,"S4") -> 9 | D8: =SUMIF(Full_Backlog!F4:F103,"S4",Full_Backlog!D4:D103) -> 34 | E8: =COUNTIFS(Full_Backlog!F4:F103,"S4",Full_Backlog!G4:G103,"Done") -> 9 | F8: MVP loop usable end-to-end internally
A9: S5 | B9: Feature Win-back email/WhatsApp flows + alpha hardening | C9: =COUNTIF(Full_Backlog!F4:F103,"S5") -> 12 | D9: =SUMIF(Full_Backlog!F4:F103,"S5",Full_Backlog!D4:D103) -> 50 | E9: =COUNTIFS(Full_Backlog!F4:F103,"S5",Full_Backlog!G4:G103,"Done") -> 12 | F9: Internal alpha: team dogfoods daily
A10: S6 | B10: Billing + Analytics dashboard | C10: =COUNTIF(Full_Backlog!F4:F103,"S6") -> 13 | D10: =SUMIF(Full_Backlog!F4:F103,"S6",Full_Backlog!D4:D103) -> 60 | E10: =COUNTIFS(Full_Backlog!F4:F103,"S6",Full_Backlog!G4:G103,"Done") -> 13 | F10: Can charge a test customer; upgrade/downgrade paths work
A11: S7 | B11: Private beta (design partners) | C11: =COUNTIF(Full_Backlog!F4:F103,"S7") -> 5 | D11: =SUMIF(Full_Backlog!F4:F103,"S7",Full_Backlog!D4:D103) -> 15 | E11: =COUNTIFS(Full_Backlog!F4:F103,"S7",Full_Backlog!G4:G103,"Done") -> 5 | F11: 3+ partners active weekly; NPS pulse >30
A12: S8 | B12: Beta iteration + Klaviyo/Meta audience sync | C12: =COUNTIF(Full_Backlog!F4:F103,"S8") -> 22 | D12: =SUMIF(Full_Backlog!F4:F103,"S8",Full_Backlog!D4:D103) -> 87 | E12: =COUNTIFS(Full_Backlog!F4:F103,"S8",Full_Backlog!G4:G103,"Done") -> 22 | F12: Retention of beta cohort week-over-week >60%
A13: S9 | B13: Marketplace review prep | C13: =COUNTIF(Full_Backlog!F4:F103,"S9") -> 7 | D13: =SUMIF(Full_Backlog!F4:F103,"S9",Full_Backlog!D4:D103) -> 30 | E13: =COUNTIFS(Full_Backlog!F4:F103,"S9",Full_Backlog!G4:G103,"Done") -> 3 | F13: Review submission accepted into queue
A14: S10 | B14: Review remediation + docs | C14: =COUNTIF(Full_Backlog!F4:F103,"S10") -> 7 | D14: =SUMIF(Full_Backlog!F4:F103,"S10",Full_Backlog!D4:D103) -> 24 | E14: =COUNTIFS(Full_Backlog!F4:F103,"S10",Full_Backlog!G4:G103,"Done") -> 5 | F14: Marketplace approval obtained (or final remediation cycle)
A15: S11 | B15: Launch | C15: =COUNTIF(Full_Backlog!F4:F103,"S11") -> 3 | D15: =SUMIF(Full_Backlog!F4:F103,"S11",Full_Backlog!D4:D103) -> 8 | E15: =COUNTIFS(Full_Backlog!F4:F103,"S11",Full_Backlog!G4:G103,"Done") -> 3 | F15: First 10 installs; first 3 reviews; activation >40%
A16: S12 | B16: Iterate & scale decision | C16: =COUNTIF(Full_Backlog!F4:F103,"S12") -> 1 | D16: =SUMIF(Full_Backlog!F4:F103,"S12",Full_Backlog!D4:D103) -> 2 | E16: =COUNTIFS(Full_Backlog!F4:F103,"S12",Full_Backlog!G4:G103,"Done") -> 1 | F16: Growth model doc with CAC/LTV first estimates
B17: TOTAL | C17: =SUM(C4:C16) -> 100 | D17: =SUM(D4:D16) -> 399
B18: Velocity check: points/sprint S2-S8 should sit within 30-45 for a 4-6 person team; rebalance Sprint column in backlog if a sprint exceeds capacity.

Sheet Financial_Model
A1: 18-MONTH FINANCIAL MODEL — Shopify: installs-led PLG (edit yellow assumptions)
A3: Assumption | B3: Value
A4: Installs/mo (month 1) | B4: 40
A5: Monthly growth of that | B5: 0.15
A6: Free->paid % | B6: 0.12
A7: ARPU $/mo | B7: 35
A8: Monthly churn | B8: 0.04
A9: Marketplace fee | B9: 0
A10: Team cost month 1 (India-lean $) | B10: 22000
A11: Cost growth/mo | B11: 0.03
A12: Fee note: 0% marketplace fee first $1M lifetime rev/yr
A14: Line | B14: M1 | C14: M2 | D14: M3 | E14: M4 | F14: M5 | G14: M6 | H14: M7 | I14: M8 | J14: M9 | K14: M10 | L14: M11 | M14: M12 | N14: M13 | O14: M14 | P14: M15 | Q14: M16 | R14: M17 | S14: M18
A15: Leads/installs | B15: =$B$4 -> 40 | C15: =B15*(1+$B$5) -> 46 | D15: =C15*(1+$B$5) -> 52.9 | E15: =D15*(1+$B$5) -> 60.835 | F15: =E15*(1+$B$5) -> 69.96025 | G15: =F15*(1+$B$5) -> 80.454288 | H15: =G15*(1+$B$5) -> 92.522431 | I15: =H15*(1+$B$5) -> 106.4008 | J15: =I15*(1+$B$5) -> 122.36091 | ... S15: =R15*(1+$B$5) -> 430.45056
A16: New paying | B16: =ROUND(B15*$B$6,1) -> 4.8 | C16: =ROUND(C15*$B$6,1) -> 5.5 | D16: =ROUND(D15*$B$6,1) -> 6.3 | E16: =ROUND(E15*$B$6,1) -> 7.3 | F16: =ROUND(F15*$B$6,1) -> 8.4 | G16: =ROUND(G15*$B$6,1) -> 9.7 | H16: =ROUND(H15*$B$6,1) -> 11.1 | I16: =ROUND(I15*$B$6,1) -> 12.8 | ... S16: =ROUND(S15*$B$6,1) -> 51.7
A17: Paying accounts | B17: =B16 -> 4.8 | C17: =ROUND(B17*(1-$B$8)+C16,1) -> 10.1 | D17: =ROUND(C17*(1-$B$8)+D16,1) -> 16 | E17: =ROUND(D17*(1-$B$8)+E16,1) -> 22.7 | F17: =ROUND(E17*(1-$B$8)+F16,1) -> 30.2 | G17: =ROUND(F17*(1-$B$8)+G16,1) -> 38.7 | H17: =ROUND(G17*(1-$B$8)+H16,1) -> 48.3 | I17: =ROUND(H17*(1-$B$8)+I16,1) -> 59.2 | J17: =ROUND(I17*(1-$B$8)+J16,1) -> 71.5 | ... S17: =ROUND(R17*(1-$B$8)+S16,1) -> 300.6
A18: MRR (net of fee) | B18: =ROUND(B17*$B$7*(1-$B$9),0) -> 168 | C18: =ROUND(C17*$B$7*(1-$B$9),0) -> 354 | D18: =ROUND(D17*$B$7*(1-$B$9),0) -> 560 | E18: =ROUND(E17*$B$7*(1-$B$9),0) -> 795 | F18: =ROUND(F17*$B$7*(1-$B$9),0) -> 1057 | G18: =ROUND(G17*$B$7*(1-$B$9),0) -> 1355 | H18: =ROUND(H17*$B$7*(1-$B$9),0) -> 1691 | I18: =ROUND(I17*$B$7*(1-$B$9),0) -> 2072 | ... S18: =ROUND(S17*$B$7*(1-$B$9),0) -> 10521
A19: Team cost | B19: =$B$10 -> 22000 | C19: =ROUND(B19*(1+$B$11),0) -> 22660 | D19: =ROUND(C19*(1+$B$11),0) -> 23340 | E19: =ROUND(D19*(1+$B$11),0) -> 24040 | F19: =ROUND(E19*(1+$B$11),0) -> 24761 | G19: =ROUND(F19*(1+$B$11),0) -> 25504 | H19: =ROUND(G19*(1+$B$11),0) -> 26269 | I19: =ROUND(H19*(1+$B$11),0) -> 27057 | J19: =ROUND(I19*(1+$B$11),0) -> 27869 | ... S19: =ROUND(R19*(1+$B$11),0) -> 36362
A20: Net cash/mo | B20: =B18-B19 -> -21832 | C20: =C18-C19 -> -22306 | D20: =D18-D19 -> -22780 | E20: =E18-E19 -> -23245 | F20: =F18-F19 -> -23704 | G20: =G18-G19 -> -24149 | H20: =H18-H19 -> -24578 | I20: =I18-I19 -> -24985 | ... S20: =S18-S19 -> -25841
A21: Cumulative | B21: =B20 -> -21832 | C21: =B21+C20 -> -44138 | D21: =C21+D20 -> -66918 | E21: =D21+E20 -> -90163 | F21: =E21+F20 -> -113867 | G21: =F21+G20 -> -138016 | H21: =G21+H20 -> -162594 | I21: =H21+I20 -> -187579 | J21: =I21+J20 -> -212945 | ... S21: =R21+S20 -> -449016
A23: Reading: churn applies before adds; MRR nets the marketplace fee; costs use India-lean base from Team_Roles_Budget (v004). Breakeven = first month Net cash ≥ 0. This is a planning model, not a forecast — replace assumptions with S7-S8 beta actuals.

Sheet GTM_Execution
A1: GTM EXECUTION TASKS
A3: Phase | B3: Task | C3: Owner (role) | D3: Target sprint
A4: Pre-launch | B4: Positioning doc + message house (problem/promise/proof) | C4: Founder | D4: S7
A5: Pre-launch | B5: Listing SEO: keyword study in marketplace search + title/intro drafts | C5: Growth | D5: S8
A6: Pre-launch | B6: 10 design-partner mini case snippets with metric proof | C6: Founder | D6: S8
A7: Pre-launch | B7: 5 comparison/alternative pages drafted | C7: Growth | D7: S9
A8: Pre-launch | B8: Screenshots (5) + 2-min demo video produced | C8: Design | D8: S9
A9: Launch | B9: Listing live + launch post + video published | C9: Growth | D9: S11
A10: Launch | B10: Founder outreach: 100 named ICP accounts, 3-touch sequence | C10: Founder | D10: S11
A11: Launch | B11: Community value-posts (3 relevant communities) | C11: Founder | D11: S11
A12: Launch | B12: Review-generation program on (in-app ask post-aha) | C12: Eng | D12: S11
A13: Post-launch | B13: Weekly SEO/how-to content cadence starts | C13: Growth | D13: S12
A14: Post-launch | B14: Marketplace paid placement pilot (where offered) | C14: Growth | D14: S12
... A16: Post-launch | B16: G2/Capterra profiles + first 10 reviews | C16: Growth | D16: S12+

Sheet Launch_Checklist
A1: PLATFORM LAUNCH CHECKLIST — Shopify App Store
A3: # | B3: Item | C3: Status
A4: 1 | B4: Shopify Partners account + production app created | C4: Open
A5: 2 | B5: App listing draft (name, 100-char intro, key benefits, 3+ screenshots 1600x900, demo video) | C5: Open
A6: 3 | B6: GraphQL-only compliance verified (no deprecated REST calls) | C6: Open
A7: 4 | B7: Mandatory GDPR webhooks (customers/redact, shop/redact, customers/data_request) tested | C7: Open
A8: 5 | B8: Protected customer data access justification submitted | C8: Open
A9: 6 | B9: Billing API plans + test charges validated | C9: Open
A10: 7 | B10: App Bridge session token auth passes review checklist | C10: Open
A11: 8 | B11: Performance: admin surface p75 LCP under Shopify guidance | C11: Open
A12: 9 | B12: Support email + privacy policy + data-processing terms live | C12: Open
A13: 10 | B13: Built-for-Shopify criteria gap review (target within 2 quarters) | C13: Open
A14: LC-K1 | B14: Protected customer data approval (Level 1 + Level 2) requested and granted in the Partner Dashboard | C14: Open — Senthil. Gates the listing and every customer read on a non-dev store; start now, it has vendor-style lead time.
A15: LC-K2 | B15: Mandatory compliance webhooks verified live via Shopify CLI webhook trigger | C15: Code done 13 Sep; live trigger needs the dev store. Note: shop/redact only fires 48h after a real uninstall.
A16: LC-K3 | B16: Run SETUP.md end to end on a dev store (npm ci -> build -> migrate -> start -> install -> webhook triggers -> proxy check) | C16: Ready — the app side is executable; needs your Partners account, tunnel and store.
A17: LC-K4 | B17: Build Postgres adapters behind the store interfaces | C17: Open — schema exists in migrations/; blocks any multi-process deploy.
A18: LC-K5 | B18: Run npm run sweep against the dev store and archive the output as evidence | C18: Open — Senthil. Automated half is scripted; 5 steps are yours (install, CLI webhook triggers, Partner Dashboard delivery check, storefront proxy).
A19: LC-K6 | B19: Send REVIEW_PACK.md to an external second reviewer | C19: Open — Senthil. ST-097 cannot close without someone other than the author looking.

Sheet Metrics_Targets
A1: METRIC TARGETS (first 12 months post-launch)
A3: Metric | B3: M1 | C3: M3 | D3: M6 | E3: M12 | F3: Notes
A4: Installs/signups cumulative | B4: varies | C4: 3x M1 | D4: 8x M1 | E4: 20x M1 | F4: Drive via listing SEO + outbound
A5: Activation % (24h) | B5: 30% | C5: 40% | D5: 45% | E5: 50% | F5: Onboarding iterations S12+
A6: Trial→paid % | B6: baseline | C6: +2pts | D6: +4pts | E6: +6pts | F6: Pricing test at S12
A7: Rating | B7: 4.5+ | C7: 4.6+ | D7: 4.7+ | E7: 4.7+ | F7: Review program + support speed
A8: MRR | B8: first $ | C8: 3x | D8: 8x | E8: 20x | F8: Model sheet has the math
A9: Logo churn/mo | B9: <5% | C9: <4% | D9: <3% | E9: <3% | F9: Health-score saves

Sheet Risk_Register
A1: PRODUCT RISK REGISTER
A3: Risk | B3: Impact | C3: Likelihood | D3: Mitigation
A4: Shopify tightens Built-for-Shopify bar or checkout/extension APIs | B4: High | C4: Medium | D4: Track dev changelog monthly; abstain from deprecated surfaces
A5: Klaviyo/Yotpo bundle retention features free | B5: High | C5: Medium | D5: Niche positioning (price band + simplicity); speed
A6: Review-app category saturation drives CAC up | B6: Medium | C6: High | D6: Lead with loyalty+winback combo, not reviews alone
A7: R-K7 | B7: Protected customer data approval gates the listing and all non-dev-store customer reads | C7: High / Medium | D7: Request now via Partner Dashboard; code already tolerates the pre-approval null state (VER-RK03).
A8: R-K8 | B8: A gate row can read "In progress" for days while the feature it names does not exist (LC-4 compliance webhooks) | C8: High / High | D8: Gate rows must cite a file and a test. Manifest drift gate now fails the build if config and code disagree.
A9: R-K10 | B9: In-memory stores are still the only implementation, so caps, purges and entitlement are process-local | C9: High / High | D9: Schema shipped; adapters not. Largest artifact-vs-code divergence. Matches MeetSync OBS-M3.
A10: R-K11 | B10: Postgres adapters have never run against a live server; ON CONFLICT targets, the interval cast and BYTEA round-trip are unverified | C10: Medium / High | D10: First live run is the real test. Recorded in code as PG_ADAPTER_VERIFICATION_STATUS.

Sheet Sprint_Tracker_Log
A1: SPRINT TRACKER LOG — RetainKit (append one row per working session)
A3: Entry | B3: Date/Time | C3: Sprint | D3: Stories touched | E3: Activity | F3: Outcome / evidence | G3: Decision refs | H3: Next action
A4: L-001 | B4: 2026-09-05 19:34 | C4: Pre-S0 | D4: — | E4: v005 workbook baselined: spec, 100-story backlog, sprint board, financial model, GTM, launch checklist, risks | F4: claude_v005_retainkit_shopify_product_workbook_20260905_1934.xlsx | G4: — | H4: Open S0 or apply portfolio D13
A5: L-002 | B5: 2026-09-10 22:05 | C5: S1 | D5: ST-051, ST-052, ST-055, ST-056 | E5: D13 applied (discovery parked; 100% automation coverage gate). S1 Foundation developed: OAuth install flow, uninstall webhook + scheduled deletion, token-rotation-safe API wrapper, install telemetry w/ source attribution. Jest suite written per module. | F5: 40/40 tests passed; coverage 100% statements/branches/functions/lines on all 4 modules (jest coverageThreshold hard gate = 100). Code: retainkit/src + retainkit/tests. | G5: D13 | H5: S1 exit gate: install in live dev store + telemetry firing (needs Shopify partner dev store — Senthil action). Then open S2.
A6: L-003 | B6: 2026-09-10 22:15 | C6: S2 | D6: ST-001, ST-002, ST-003, ST-004, ST-053, ST-054 | E6: S2 Review request engine part 1 developed: defaults setup service (one-call), rule customisation with validation, delivered-order eligibility + scheduling, send with exponential-backoff retry and explicit user retry paths, review capture, re-install restoration within retention window, owner/admin/member permission matrix. | F6: 33 new tests; full suite 73/73 passed; coverage 100% statements/branches/functions/lines across all 7 modules (jest hard gate). Code: retainkit/src + retainkit/tests. | G6: D13 | H6: S2 exit gate: Review request engine happy path demoable (needs UI shell + dev store — pending). Open S3: engine part 2 + Points & rewards ledger skeleton.
A7: L-004 | B7: 2026-09-10 22:20 | C7: S3 | D7: ST-005..ST-010, ST-011..ST-014, ST-085 | E7: S3 developed: App Bridge session-token (JWT HS256) verification + embedded detection; engine metrics summary/trend with zero-guarded conversion; audited permission gate (both outcomes logged); pause/resume with sends suppressed and requests retained; CSV review import with row-level rejection reasons + competitor header mapper; in-app+email notifications with per-type mute. Points ledger skeleton: config defaults/validation, earn-floor/balance/redeem with unit rules, platform balance sync with retry semantics. | F7: 47 new tests; full suite 120/120 passed; coverage 100% statements/branches/functions/lines across all 11 modules. ST-085 evidenced by jest coverageThreshold=100 (D13 supersedes >=70% wording). Gate restructure: AuditedGate rewritten from try/catch to can()-based check to eliminate an unreachable branch. | G7: D13 | H7: S3 exit criteria met at code level (engine complete with tests; ledger skeleton). Open S4: ledger completion + activation funnel/error telemetry + E2E smoke (ST-086 needs CI env - flag).
A8: L-005 | B8: 2026-09-10 22:28 | C8: S4 | D8: ST-015..ST-020, ST-071, ST-072, ST-086 | E8: Points ledger completed: embedded gateway (shop always derived from verified session token, never client input), ledger point metrics with liability + zero-guarded redemption rate, permission-gated audited rule updates and manual adjustments (Action matrix extended with adjust_points for owner/admin), feature-scoped pause (engine and ledger pausable independently, data retained), points CSV + competitor import writing opening-balance transactions, points_adjusted/redemption_completed notification types. Growth telemetry: install->setup->aha->habit funnel with unique-shop conversion, error tracker with release tagging and rolling-window spike alerts. E2E smoke: 10-step full merchant journey over real modules (only platform edges simulated) + deploy-smoke GitHub Actions workflow + npm run test:smoke. | F8: 27 new tests; full suite 147/147 passed; coverage 100% statements/branches/functions/lines across all 13 modules, clean on first run. Matrix extension propagated to ST-054 matrix test (owner 8 actions, admin 6, member 2). | G8: D13 | H8: S4 exit criteria met at code level (MVP loop usable end-to-end internally - evidenced by E2E smoke). CI workflow needs wiring to the real GitHub repo (Senthil action). Open S5: Win-back flows + alpha hardening (12 stories, 50 pts).
A9: L-006 | B9: 2026-09-10 22:52 | C9: S5 | D9: ST-021..ST-030, ST-078, ST-079 | E9: Win-back suite built on the established F1/F2 patterns: rules with defaults + validation (lapse window, 1-5 step delays, email/WhatsApp channels, discount cap), lapsed-customer detection (skips opt-outs/recent buyers/already-in-flow), flow scheduling with channel rotation, step sends with the standard exponential-backoff retry semantics, conversion recording that cancels pending steps, embedded session-token gateway, win-back-rate metrics + trend, gated/audited rule updates and manual step triggers, feature-pause extended to winback_flows, customer CSV + competitor (Email/Last Purchase) import feeding detection end-to-end. Alpha hardening: 5-item first-run checklist with idempotent start, aha = reviews configured + first test send, <1-day tracking; empty-state registry covering all 9 workbook screens, each with a next-action CTA. | F9: 36 new tests; full suite 183/183 passed; coverage 100% statements/branches/functions/lines across all 15 modules, clean on first run. | G9: D13 | H9: S5 exit criteria (internal alpha: team dogfoods daily) requires live dev-store deployment - Senthil action. Open S6: Billing + Analytics (13 stories, 60 pts) incl. Shopify Billing API vs Stripe fallback (ST-059).
A10: L-007 | B10: 2026-09-10 23:09 | C10: S6 | D10: ST-031..ST-040, ST-057, ST-058, ST-059 | E10: Billing built: TrialService (idempotent no-card start, day-countdown banner incl. singular/expired states); pure proration calculator (validated inputs, rounded to cents, charge_now/credit_balance/no_change); BillingRouter mandating Shopify Billing API for app-store channel (appSubscriptionCreate -> pending_confirmation -> confirm callback) with Stripe fallback activating immediately; SubscriptionService lifecycle with double-subscribe guard and resubscribe-after-cancel. Analytics built: config defaults/validation (widgets, range, refresh), DashboardComposer aggregating all four pillar widgets with per-widget retry semantics so one failing source degrades alone and the dashboard always renders, embedded gateway, view/export gated behind view_analytics/export_data with audit, usage metrics with export rate, historical metrics CSV + competitor import, feature pause + weekly_report_ready/export_completed notifications. | F10: 31 new tests; full suite 214/214 passed; coverage 100% x4 across all 18 modules. Gate catch: unknown-header branch of the analytics competitor mapper initially unexercised (99.79% branches) - build failed, test added, clean. | G10: D13 | H10: S6 exit met at code level. Open S7: dunning/limits/invoices/cancellation + least-privilege doc (5 stories, 15 pts). Live test charge needs dev store + Partners app (Senthil).
A11: L-008 | B11: 2026-09-11 08:20 | C11: S7 | D11: ST-060, ST-061, ST-062, ST-063, ST-064 | E11: Billing part 2: DunningService (idempotent failure record; emails on days 0/3/5 with single-run catch-up capped at 3; read-only mode after 7-day grace; payment clears and restores). PlanLimitService as the enforcement point before every send (silent below 80%, upgrade prompt from 80%, hard block at 100% with blocked requests not counted). InvoiceService (sequential INV-YYYY-NNNN per shop, GST/VAT computed with cent rounding, optional tax id, downloadable plain-text receipt omitting absent lines, amount/rate validation). CancellationFlow (requireActive guard added to SubscriptionService; save-offer 20%/3mo always shown first; accept retains + records outcome; decline validates reason enum, records exit survey, cancels via owning provider). ST-064: REQUESTED_SCOPES map (read_orders, read_customers, write_customers, write_marketing_events) each justified against shipped features only, rendered to SCOPES.md and enforced by validateScopeMap() in the suite. | F11: 16 new tests; full suite 230/230 passed; coverage 100% x4 across all 19 modules. Two gate catches: markdown separator row broke the doc line-count assertion (test corrected), and CancellationFlow default clock unexercised (95.6% functions) - covered. | G11: D13 | H11: S7 (private-beta billing scope) code-complete. Open S8: Beta iteration - 22 stories incl. Klaviyo/Meta sync (F5), encryption/audit/rate-limit evidence (E6), heatmap + weekly email (E7), help docs (E8), performance budget (ST-087/088). Design-partner recruitment (S7 exit: 3+ partners active) = Senthil action.
A12: L-009 | B12: 2026-09-11 12:52 | C12: S8 | D12: ST-041..050, ST-065..067, ST-070, ST-073..077, ST-087, ST-088, ST-092 | E12: F5 audience sync complete on the established feature pattern; E6 security hardening with REAL cryptography (AES-256-GCM vault proving ciphertext-at-rest + tamper detection; sha256 hash-chained audit trail detecting modification and deletion; circuit breaker with fail-fast and half-open trial; https-only enforcement; DATA_FLOWS.md published with per-store retention). E7 ops telemetry (heatmap, weekly email, health score, exports, alert thresholds). EQ: latency budgets, 5x load test executed against the real review engine + points ledger in-suite (300 requests, 0 errors, p95 <= 50ms in-memory budget), blue/green deployer verified to never serve an unhealthy build. | F12: 41 new tests; full suite 271/271 passed; 100% x4 across all 23 modules. Gate catches: two default-clock arrows (WeeklyMetricsEmail, CircuitBreaker) constructed but never invoked - both covered. | G12: D13 | H12: Open S9: Marketplace review prep (ST-068, ST-069, ST-089, ST-090, ST-091, ST-093, ST-094). Live Klaviyo/Meta API credentials + LCP measurement need real accounts (Senthil).
A13: E001 | B13: 2026-09-10 22:05 | C13: — | D13: RETAINKIT BUILD DIRECTED — Senthil instruction 22:05: continue work as per sprint from the v005 product workbook, with sprint tracker + traceability and 100% automation testing on all code. D13 (portfolio-wide: discovery parked, dev proceeds at 100% coverage) applied; D15 sequencing mode (multiple concurrent builds vs order swap) remains Senthil's open portfolio decision. | E13: D13, D15 | F13: RetainKit S1 opened | G13: — | H13: S1 build
A14: E002 | B14: 2026-09-10 22:05 | C14: S1 | D14: S1 FOUNDATION BUILT (TypeScript/Node per v005 stack): ST-051 OAuth install (shop-domain validation, HMAC + state verification, code exchange, token persist, welcome landing); ST-052 uninstall webhook (base64 HMAC, immediate token purge, retention-scheduled deletion); ST-055 rotation-safe token manager (401 -> refresh -> persist -> single retry, second 401 raises re-auth); ST-056 install telemetry with listing/search/referral attribution. D13 GATE: 40 tests, 100% x4, jest coverageThreshold hard-set. Product workbook v006 released with Sprint_Tracker_Log + Traceability_Matrix sheets added. | E14: ST-051/052/055/056; v006 | F14: 4 stories Done-in-code (13 pts) | G14: Live dev-store install = Senthil + Shopify Partners account | H14: E003
... A30: E018 | B30: 2026-09-13 11:09 | C30: Post-code | D30: HANDOVER-REDUCTION PASS — automatic persistence selection that refuses to degrade silently, a scripted verification sweep (npm run sweep) replacing prose steps, and REVIEW_PACK.md for the external reviewer. Correction logged: at 11:04 I said nothing sandbox-buildable remained; these three were, and each removes work from Senthil rather than adding product surface. | E30: src/sweep.ts; src/http/wiring.ts; REVIEW_PACK.md; bin/sweep.js | F30: 19 suites / 469 tests at 100% zero pragmas; story position unchanged | G30: None new. ST-097 stays In progress — a pack for a reviewer is not a review. | H30: E019 — live evidence

Sheet Traceability_Matrix
A1: TRACEABILITY MATRIX — Story -> Code -> Test -> Coverage (updated per sprint)
A3: Story ID | B3: Epic | C3: Requirement (story) | D3: Sprint | E3: Module | F3: Source file | G3: Test file | H3: # Tests | I3: Coverage Stmt/Branch/Func/Line | J3: Test result | K3: Status
A4: ST-051 | B4: E1 | C4: Marketplace OAuth install completes and lands on welcome state in <2 min | D4: S1 | E4: OAuth install | F4: src/oauth.ts | G4: tests/oauth.test.ts | H4: 17 | I4: 100% / 100% / 100% / 100% | J4: PASS (2026-09-10 22:05) | K4: Done
A5: ST-052 | B5: E1 | C5: Uninstall webhook removes tokens, schedules data deletion per policy | D5: S1 | E5: Uninstall lifecycle | F5: src/uninstall.ts | G5: tests/foundation.test.ts | H5: 8 | I5: 100% / 100% / 100% / 100% | J5: PASS (2026-09-10 22:05) | K5: Done
A6: ST-055 | B6: E1 | C6: Session/token refresh survives platform token rotation | D6: S1 | E6: Token rotation safety | F6: src/tokenRefresh.ts | G6: tests/foundation.test.ts | H6: 4 | I6: 100% / 100% / 100% / 100% | J6: PASS (2026-09-10 22:05) | K6: Done
A7: ST-056 | B7: E1 | C7: Install telemetry: source attribution (listing/search/referral) captured | D7: S1 | E7: Install telemetry | F7: src/telemetry.ts | G7: tests/foundation.test.ts | H7: 11 | I7: 100% / 100% / 100% / 100% | J7: PASS (2026-09-10 22:05) | K7: Done
A8: ST-001 | B8: F1 | C8: As a Store owner, I can set up Review request engine with sensible defaults in one screen | D8: S2 | E8: Review settings (defaults) | F8: src/reviewSettings.ts | G8: tests/s2.test.ts | H8: 3 | I8: 100% / 100% / 100% / 100% | J8: PASS (2026-09-10 22:15) | K8: Done
A9: ST-002 | B9: F1 | C9: As a Store owner, the Review request engine happy path completes without documentation | D9: S2 | E9: Review request engine core | F9: src/reviewEngine.ts | G9: tests/s2.test.ts | H9: 7 | I9: 100% / 100% / 100% / 100% | J9: PASS (2026-09-10 22:15) | K9: Done
A10: ST-003 | B10: F1 | C10: As a E-com manager, I can customise Review request engine rules/conditions for my workflow | D10: S2 | E10: Rule customisation + validation | F10: src/reviewSettings.ts | G10: tests/s2.test.ts | H10: 9 | I10: 100% / 100% / 100% / 100% | J10: PASS (2026-09-10 22:15) | K10: Done
A11: ST-004 | B11: F1 | C11: As a user, Review request engine shows clear errors and retry paths on platform API failures | D11: S2 | E11: Error handling + retry paths | F11: src/reviewEngine.ts | G11: tests/s2.test.ts | H11: 5 | I11: 100% / 100% / 100% / 100% | J11: PASS (2026-09-10 22:15) | K11: Done
A12: ST-053 | B12: E1 | C12: Re-install restores account within retention window | D12: S2 | E12: Re-install restoration | F12: src/accountLifecycle.ts | G12: tests/s2.test.ts | H12: 5 | I12: 100% / 100% / 100% / 100% | J12: PASS (2026-09-10 22:15) | K12: Done
A13: ST-054 | B13: E1 | C13: Multi-user roles: owner/admin/member permission matrix enforced | D13: S2 | E13: Role permission matrix | F13: src/accountLifecycle.ts | G13: tests/s2.test.ts | H13: 4 | I13: 100% / 100% / 100% / 100% | J13: PASS (2026-09-10 22:15) | K13: Done
A14: ST-005 | B14: F1 | C14: As a Agency partner, Review request engine works on the embedded Shopify admin app surface end-to-end | D14: S3 | E14: Embedded admin surface | F14: src/embeddedApp.ts | G14: tests/s3.test.ts | H14: 11 | I14: 100% / 100% / 100% / 100% | J14: PASS (2026-09-10 22:20) | K14: Done
A15: ST-006 | B15: F1 | C15: As a E-com manager, I can see Review request engine performance metrics and trends | D15: S3 | E15: Engine metrics + trends | F15: src/engineOps.ts | G15: tests/s3.test.ts | H15: 5 | I15: 100% / 100% / 100% / 100% | J15: PASS (2026-09-10 22:20) | K15: Done
... A85: ST-092 | B85: EQ | C85: Zero-downtime deploy verified (blue/green or rolling) | D85: S8 | E85: Zero-downtime blue/green deploy | F85: src/opsQuality.ts | G85: tests/s8-ops.test.ts | H85: 2 | I85: 100% / 100% / 100% / 100% | J85: PASS (2026-09-11 12:52) | K85: Done
A87: Coverage gate: jest coverageThreshold global 100/100/100/100 (build fails below 100%) per portfolio decision D13, superseding ST-085 >=70% gate. Suite total this version: 271 tests, all passing (S1: 40, S2: 33, S3: 47, S4: 27, S5: 36, S6: 31, S7: 16, S8: 41). Backlog stories not yet in a completed sprint are added here as their sprint executes.
A88: ST-069 | B88: E6 | C88: Data export + delete-my-data self-serve | D88: S9 | E88: Privacy / tenant data | F88: src/privacy.ts; src/tenantData.ts | G88: tests/s9.test.ts | H88: 13 | I88: 100% / 100% / 100% / 100% | J88: PASS (2026-09-13 10:23) | K88: Done
A89: ST-090 | B89: EQ | C89: Backup + restore drill executed | D89: S9 | E89: Ops resilience | F89: src/opsResilience.ts | G89: tests/s9.test.ts | H89: 6 | I89: 100% / 100% / 100% / 100% | J89: PASS (2026-09-13 10:23) | K89: Done
A90: ST-091 | B90: EQ | C90: Chaos test: platform API outage degrades gracefully with user comms | D90: S9 | E90: Ops resilience | F90: src/opsResilience.ts | G90: tests/s9.test.ts | H90: 4 | I90: 100% / 100% / 100% / 100% | J90: PASS (2026-09-13 10:23) | K90: Done
A91: ST-068 | B91: E6 | C91: Pen-test (or platform-required evidence) completed and archived | D91: S9 | E91: Security evidence | F91: SECURITY_EVIDENCE.md | G91: tests/s9.test.ts (referenced controls) | H91: 0 | I91: n/a — document | J91: SANDBOX HALF ONLY (2026-09-13 10:23) | K91: In progress
A92: ST-089 | B92: EQ | C92: Accessibility WCAG AA pass on primary flows | D92: S9 | E92: Screen shells + audit | F92: src/screens.ts | G92: tests/s9-a11y.test.ts | H92: 10 | I92: 100% / 100% / 100% / 100% | J92: PASS automated half (2026-09-13 10:23) | K92: In progress
A93: ST-093 | B93: EL | C93: Marketplace listing copy A + B variants drafted and reviewed | D93: S9 | E93: Listing collateral | F93: LISTING_COPY.md | G93: n/a | H93: 0 | I93: n/a — document | J93: DRAFTED (2026-09-13 10:23) | K93: Drafted
A94: ST-094 | B94: EL | C94: 5 screenshots + 2-min demo video meet platform asset specs | D94: S9 | E94: Listing collateral | F94: ASSET_PLAN.md | G94: n/a | H94: 0 | I94: n/a — document | J94: DRAFTED (2026-09-13 10:23) | K94: Drafted
A95: LC-4 | B95: E6 | C95: MANDATORY compliance webhooks: customers/data_request, customers/redact, shop/redact | D95: S9 | E95: Compliance webhooks | F95: src/compliance.ts; shopify.app.toml | G95: tests/s9.test.ts; tests/s9-manifest.test.ts | H95: 17 | I95: 100% / 100% / 100% / 100% | J95: PASS (2026-09-13 10:23) | K95: Done-in-code
A96: GAP-RK1 | B96: E1 | C96: HTTP application behind every route the manifest declares | D96: S9 | E96: HTTP layer | F96: src/http/router.ts; app.ts; wiring.ts; bin/start.js | G96: tests/s10-http.test.ts | H96: 34 | I96: 100% / 100% / 100% / 100% | J96: PASS (2026-09-13 10:34) | K96: Done-in-code
A97: GAP-RK2 | B97: E6 | C97: Database schema behind backup, retention sweep and the 12 data domains | D97: S9 | E97: Schema | F97: migrations/001-003; bin/migrate.js | G97: npm run migrate:dry (CI gate) | H97: 0 | I97: n/a — SQL | J97: PARSE VERIFIED (2026-09-13 10:34) | K97: Done-in-code
A98: VER-RK07 | B98: E1 | C98: App proxy signature verification (distinct scheme from OAuth HMAC) | D98: S9 | E98: Proxy auth | F98: src/http/proxyAuth.ts | G98: tests/s10-http.test.ts | H98: 5 | I98: 100% / 100% / 100% / 100% | J98: PASS (2026-09-13 10:34) | K98: Done-in-code
A99: ST-080 | B99: E8 | C99: Help center with 15 launch articles + search | D99: S10 | E99: Help centre | F99: src/support.ts | G99: tests/s10.test.ts | H99: 6 | I99: 100% / 100% / 100% / 100% | J99: PASS (2026-09-13 10:43) | K99: Done-in-code
... A111: SW-RK | B111: E7 | C111: Scripted live verification sweep (8 automated + 5 operator steps) | D111: Post-code | E111: Sweep | F111: src/sweep.ts; bin/sweep.js | G111: tests/s13-sweep.test.ts | H111: 8 | I111: 100% / 100% / 100% / 100% | J111: PASS (2026-09-13 11:09) | K111: Done-in-code

Sheet Review_Findings
A1: REVIEW FINDINGS — cold review pass 1 + external verification sweep, 13 Sep 2026
A2: Every FIXED row has a pinned regression test. Every OPEN row needs a Senthil disposition. Coverage was 100% throughout and caught none of these.
A4: ID | B4: Type | C4: Module | D4: Finding | E4: Impact | F4: Status / Disposition
A5: F-RK01 | B5: Defect | C5: winbackOps.ts, audienceSyncOps.ts | D5: Both CSV importers hardcoded optedOut:false, discarding any opt-out column in the source file. | E5: SEVERE. The importer exists so merchants migrate off a competitor — the file it reads is exactly the file carrying the unsubscribes. Every one was reset to subscribed, and the first win-back run would have mailed them. Marketing-consent breach and a failure of Shopify’s requirement to apply opt-out decisions. | F5: FIXED — new src/consent.ts. An import must carry an opted_out column or a recorded merchant attestation; consent is never inferred. Provenance stored with every import.
A6: F-RK02 | B6: Defect | C6: billingOps.ts | D6: Dunning computed mode="read_only" after the grace window and nothing in the app ever consulted it. | E6: A shop whose payment failed kept full write access indefinitely. The state was real; the enforcement was not. | F6: FIXED — src/entitlement.ts + AuditedGate wiring. Writes blocked, reads never blocked, billing stays reachable, refusal reason audit-logged.
A7: F-RK03 | B7: Defect | C7: billing.ts | D7: TrialStatus.expired fed a banner and nothing else. | E7: A merchant could let the 14-day trial lapse and keep sending forever. Same class as VoiceBridge F-V03. | F7: FIXED — resolved through the same entitlement gate.
A8: F-RK04 | B8: Defect | C8: billingOps.ts | D8: Dunning sent three emails and flipped to read-only without ever re-attempting the charge. | E8: Most failed card payments succeed on retry. The app was emailing merchants about a problem it had the means to fix, then punishing them for it. Same class as VoiceBridge F-V02 / OnCall F-005. | F8: FIXED — PaymentRecovery port; a successful retry clears dunning and sends no email.
A9: F-RK05 | B9: Defect | C9: reviewEngine.ts, winback.ts | D9: Consent was checked at scheduling time only. Review requests sit for the configured delay (default 7 days) and win-back flows run for weeks. | E9: A customer who opted out inside that window still received the message. Scheduling-time eligibility is not consent at send time. | F9: FIXED — ConsentCheck re-read immediately before every send; review request suppressed, remaining win-back steps cancelled and the flow closed.
A10: F-RK06 | B10: Defect | C10: security.ts | D10: No Retry-After parser existed anywhere, while the backoff helper took milliseconds. Shopify sends Retry-After in seconds. | E10: The first caller wiring a real HTTP response would have passed 2 into a ms parameter and retried 1000x too fast into an already rate-limited endpoint. Same class as TestPulse F-TP08. | F10: FIXED — parseRetryAfterHeader() handles seconds, fractional seconds, absolute dates and junk; plus full jitter and a 60s cap (closes portfolio OBS-001 for this product).
A11: F-RK07 | B11: Defect | C11: (absent) | D11: No single inventory of stored data existed, so deletion paths each carried their own list of stores. | E11: This is exactly how TestPulse F-TP01 and VoiceBridge F-V01/F-V08 breached published retention policies — one path swept less than another. | F11: FIXED — TenantDataRegistry with a completeness gate; a new module that skips its deletion adapter fails the suite.
A12: F-RK08 | B12: Defect | C12: (absent) | D12: Self-serve deletion was irreversible with no confirmation step. | E12: A misclick would have destroyed a merchant’s account data. | F12: FIXED — two-phase request/confirm with a 15-minute token TTL.
A13: F-RK09 | B13: Defect | C13: (absent) | D13: No backup/restore drill existed, so the backup story rested on an assumption. | E13: A backup never restored is not a backup. Divergence would have been discovered during an incident. | F13: FIXED — drill runs in code with sha256 integrity verification; divergence sets shipBlock.
A14: VER-RK01 | B14: Verification | C14: (all) | D14: No Shopify API version pinned anywhere in src/. | E14: LIVE-BLOCKING. Shopify falls forward retired versions to the oldest supported one — behaviour changes underneath the app with no error. | F14: FIXED — 2026-07 pinned, drift check against the 12-month support window. 2026-10 lands 1 Oct 2026.
A15: VER-RK02 | B15: Verification | C15: (all) | D15: No endpoint builder; REST Admin has been legacy since 1 Oct 2024. | E15: Building on REST would fail Built-for-Shopify and the LC-3 gate. | F15: FIXED — graphqlEndpoint() emits versioned GraphQL Admin URLs only.
... A30: F-RK10 | B30: Defect | C30: store/pg.ts + schema | D30: customer_consent had no email column, and no other table stored one. Shopify’s customers/redact and customers/data_request payloads can identify a customer by email alone — a shape the handler has always accepted. | E30: An email-only privacy request would have matched zero rows while the app recorded the request as completed. A reported erasure that erased nothing is worse than a failed one, because nobody goes looking. | F30: FIXED — migration 005 adds customer_consent.email with an index; the adapter matches on either identifier. Pinned by two regressions. Found only because a coverage gap made an unreachable branch visible.
