Workbook

Sheet Daily Tracker
A1: Sl: No: | B1: Noted Date | C1: Noted Time | D1: Noted Day | E1: Category | F1: Task Details | G1: Priority | H1: Actual Start Day | I1: Actual Start Date | J1: Actual Start Time | K1: Actual End Day | L1: Actual End Date | M1: Actual End Time | N1: Status | O1: Remarks / Notes | P1: Next Action | Q1: Follow-up Date
A2: 1 | B2: 46213 | C2: 0.58333333 | D2: =VLOOKUP( WEEKDAY(B2) ,Lookup!$A$2:$B$8,2,FALSE) -> Friday | E2: Hiring | F2: Menaga and Jaya Sudha whatsapp msg preparation | G2: High | H2: =VLOOKUP( WEEKDAY(I2) ,Lookup!$A$2:$B$8,2,FALSE) -> Friday | I2: 46213 | J2: 0.59722222 | K2: =VLOOKUP( WEEKDAY(L2) ,Lookup!$A$2:$B$8,2,FALSE) -> Friday | L2: 46213 | M2: 0.61111111 | N2: Completed partially | O2: Msg Shared in group | P2: After the approval need to share directly | Q2: 46214
A3: =A2+1 -> 2 | B3: 46213 | C3: 0.58333333 | D3: =VLOOKUP( WEEKDAY(B3) ,Lookup!$A$2:$B$8,2,FALSE) -> Friday | E3: Documentation | F3: Create a master sheet and Put together all the links | G3: High | H3: =VLOOKUP( WEEKDAY(I3) ,Lookup!$A$2:$B$8,2,FALSE) -> Friday | I3: 46213 | K3: =VLOOKUP( WEEKDAY(L3) ,Lookup!$A$2:$B$8,2,FALSE) -> Friday | L3: 46213
A4: =A3+1 -> 3 | B4: 46213 | C4: 0.45833333 | D4: =VLOOKUP( WEEKDAY(B4) ,Lookup!$A$2:$B$8,2,FALSE) -> Friday | E4: Company Registration | F4: Talk to Renu Chennai | G4: High | H4: =VLOOKUP( WEEKDAY(I4) ,Lookup!$A$2:$B$8,2,FALSE) -> Friday | I4: 46213 | J4: 0.66666667 | K4: =VLOOKUP( WEEKDAY(L4) ,Lookup!$A$2:$B$8,2,FALSE) -> Friday | L4: 46213 | O4: She is Refering her Auditor cum Auditor friend as she handles only GST | Q4: 46214
A5: =A4+1 -> 4 | B5: 46214 | D5: =VLOOKUP( WEEKDAY(B5) ,Lookup!$A$2:$B$8,2,FALSE) -> Saturday | E5: Web Site Design | F5: Cute Pay Website Design, Need to check the UI and Speak to them | H5: =VLOOKUP( WEEKDAY(I5) ,Lookup!$A$2:$B$8,2,FALSE) -> Friday | I5: 46213 | K5: =VLOOKUP( WEEKDAY(L5) ,Lookup!$A$2:$B$8,2,FALSE) -> Friday | L5: 46213
A6: =A5+1 -> 5 | B6: 46214 | D6: =VLOOKUP( WEEKDAY(B6) ,Lookup!$A$2:$B$8,2,FALSE) -> Saturday | E6: Web Site Design | F6: Jacob for branding ans suggestion for UI from Cute Pay | H6: =VLOOKUP( WEEKDAY(I6) ,Lookup!$A$2:$B$8,2,FALSE) -> Friday | I6: 46213 | K6: =VLOOKUP( WEEKDAY(L6) ,Lookup!$A$2:$B$8,2,FALSE) -> Friday | L6: 46213
A7: =A6+1 -> 6 | B7: 46214 | C7: 0.45833333 | D7: =VLOOKUP( WEEKDAY(B7) ,Lookup!$A$2:$B$8,2,FALSE) -> Saturday | E7: Company Registration | F7: Renu Akka ask friend number and speak to auditor | H7: =VLOOKUP( WEEKDAY(I7) ,Lookup!$A$2:$B$8,2,FALSE) -> Saturday | I7: 46214 | J7: 0.45833333 | K7: =VLOOKUP( WEEKDAY(L7) ,Lookup!$A$2:$B$8,2,FALSE) -> Saturday
A8: =A7+1 -> 7 | B8: 46214 | C8: 0.45833333 | D8: =VLOOKUP( WEEKDAY(B8) ,Lookup!$A$2:$B$8,2,FALSE) -> Saturday | E8: Company Registration | F8: Auditir Bala Murugan previously Registered Auditort | H8: =VLOOKUP( WEEKDAY(I8) ,Lookup!$A$2:$B$8,2,FALSE) -> Saturday | I8: 46214 | J8: 0.46875 | K8: =VLOOKUP( WEEKDAY(L8) ,Lookup!$A$2:$B$8,2,FALSE) -> Saturday | L8: 46214 | M8: 0.47916667 | N8: COmpleted | O8: Actual to Move to Jageedeswari akka, as we wan to support womens | P8: NIl
A9: =A8+1 -> 8 | B9: 46215 | D9: =VLOOKUP( WEEKDAY(B9) ,Lookup!$A$2:$B$8,2,FALSE) -> Sunday | E9: Interview | F9: jayashree Interview for Customer Support | G9: High | H9: =VLOOKUP( WEEKDAY(I9) ,Lookup!$A$2:$B$8,2,FALSE) -> Friday | I9: 46213 | J9: 0.59722222 | K9: =VLOOKUP( WEEKDAY(L9) ,Lookup!$A$2:$B$8,2,FALSE) -> Sunday | L9: 46215 | M9: 0.61458333 | N9: COmpleted | O9: Suitable for Customer Support Executive
A10: =A9+1 -> 9 | B10: 46215 | C10: 0.58333333 | D10: =VLOOKUP( WEEKDAY(B10) ,Lookup!$A$2:$B$8,2,FALSE) -> Sunday | E10: Learnings | F10: Public Speaking class Completde | G10: Medium | H10: =VLOOKUP( WEEKDAY(I10) ,Lookup!$A$2:$B$8,2,FALSE) -> Sunday | I10: 46215 | J10: 0.45833333 | K10: =VLOOKUP( WEEKDAY(L10) ,Lookup!$A$2:$B$8,2,FALSE) -> Sunday | L10: 46215 | M10: 0.58333333
A11: =A10+1 -> 10 | B11: 46215 | C11: 0.45833333 | D11: =VLOOKUP( WEEKDAY(B11) ,Lookup!$A$2:$B$8,2,FALSE) -> Sunday | E11: Interview | F11: Recuritments Preparations | H11: =VLOOKUP( WEEKDAY(I11) ,Lookup!$A$2:$B$8,2,FALSE) -> Sunday | I11: 46215 | J11: 0.58333333 | K11: =VLOOKUP( WEEKDAY(L11) ,Lookup!$A$2:$B$8,2,FALSE) -> Sunday | L11: 46215 | M11: 0.60069444 | N11: Completed
A12: =A11+1 -> 11 | B12: 46215 | C12: 0.45833333 | D12: =VLOOKUP( WEEKDAY(B12) ,Lookup!$A$2:$B$8,2,FALSE) -> Sunday | E12: Interview | F12: Swetha | H12: =VLOOKUP( WEEKDAY(I12) ,Lookup!$A$2:$B$8,2,FALSE) -> Sunday | I12: 46215 | J12: 0.6875 | K12: =VLOOKUP( WEEKDAY(L12) ,Lookup!$A$2:$B$8,2,FALSE) -> Sunday | L12: 46215
A13: =A12+1 -> 12 | B13: 46215 | C13: 0.45833333 | D13: =VLOOKUP( WEEKDAY(B13) ,Lookup!$A$2:$B$8,2,FALSE) -> Sunday | E13: Interview | F13: Subu lakshmi | H13: =VLOOKUP( WEEKDAY(I13) ,Lookup!$A$2:$B$8,2,FALSE) -> Sunday | I13: 46215 | K13: =VLOOKUP( WEEKDAY(L13) ,Lookup!$A$2:$B$8,2,FALSE) -> Sunday | L13: 46215
A14: =A13+1 -> 13 | B14: 46215 | C14: 0.45833333 | D14: =VLOOKUP( WEEKDAY(B14) ,Lookup!$A$2:$B$8,2,FALSE) -> Sunday | F14: Google | H14: =VLOOKUP( WEEKDAY(I14) ,Lookup!$A$2:$B$8,2,FALSE) -> Sunday | I14: 46215 | K14: =VLOOKUP( WEEKDAY(L14) ,Lookup!$A$2:$B$8,2,FALSE) -> Sunday | L14: 46215
A15: =A14+1 -> 14 | B15: 46216 | C15: 0.45833333 | D15: =VLOOKUP( WEEKDAY(B15) ,Lookup!$A$2:$B$8,2,FALSE) -> Monday | E15: Interview | F15: Swetha | H15: =VLOOKUP( WEEKDAY(I15) ,Lookup!$A$2:$B$8,2,FALSE) -> Monday | I15: 46216 | J15: 0.47916667 | K15: =VLOOKUP( WEEKDAY(L15) ,Lookup!$A$2:$B$8,2,FALSE) -> Monday | L15: 46216
A16: =A15+1 -> 15 | B16: 46216 | C16: 0.45833333 | D16: =VLOOKUP( WEEKDAY(B16) ,Lookup!$A$2:$B$8,2,FALSE) -> Monday | E16: Learning | F16: BPO training | H16: =VLOOKUP( WEEKDAY(I16) ,Lookup!$A$2:$B$8,2,FALSE) -> Monday | I16: 46216 | J16: 0.5 | K16: =VLOOKUP( WEEKDAY(L16) ,Lookup!$A$2:$B$8,2,FALSE) -> Monday | L16: 46216
A17: =A16+1 -> 16 | B17: 46216 | C17: 0.4375 | D17: =VLOOKUP( WEEKDAY(B17) ,Lookup!$A$2:$B$8,2,FALSE) -> Monday | E17: Documentation | F17: Informed Princy to document the Call recording software absorvation and Hostel in tambaram | H17: =VLOOKUP( WEEKDAY(I17) ,Lookup!$A$2:$B$8,2,FALSE) -> Monday | I17: 46216 | K17: =VLOOKUP( WEEKDAY(L17) ,Lookup!$A$2:$B$8,2,FALSE) -> Monday | L17: 46216
A18: =A17+1 -> 17 | B18: 46216 | C18: 0.4375 | D18: =VLOOKUP( WEEKDAY(B18) ,Lookup!$A$2:$B$8,2,FALSE) -> Monday | E18: Website | F18: Cute Pay check the status of teh website, logo and company profile | H18: =VLOOKUP( WEEKDAY(I18) ,Lookup!$A$2:$B$8,2,FALSE) -> Monday | I18: 46216 | K18: =VLOOKUP( WEEKDAY(L18) ,Lookup!$A$2:$B$8,2,FALSE) -> Monday | L18: 46216
A19: =A18+1 -> 18 | B19: 46216 | C19: 0.60416667 | D19: =VLOOKUP( WEEKDAY(B19) ,Lookup!$A$2:$B$8,2,FALSE) -> Monday | E19: Training Session | F19: Jaya Shree, Swetha, Subu lakshmi, Princy shedule not confirmed, Muthulakshmi will check the recording | H19: =VLOOKUP( WEEKDAY(I19) ,Lookup!$A$2:$B$8,2,FALSE) -> Monday | I19: 46216 | J19: 0.79166667 | K19: =VLOOKUP( WEEKDAY(L19) ,Lookup!$A$2:$B$8,2,FALSE) -> Monday | L19: 46216
A20: =A19+1 -> 19 | B20: 46217 | C20: 0.41666667 | D20: =VLOOKUP( WEEKDAY(B20) ,Lookup!$A$2:$B$8,2,FALSE) -> Tuesday | E20: training Session | F20: Training Record check | H20: =VLOOKUP( WEEKDAY(I20) ,Lookup!$A$2:$B$8,2,FALSE) -> Tuesday | I20: 46217 | K20: =VLOOKUP( WEEKDAY(L20) ,Lookup!$A$2:$B$8,2,FALSE) -> Tuesday | L20: 46217
A21: =A20+1 -> 20 | B21: 46218 | C21: 0.4375 | D21: =VLOOKUP( WEEKDAY(B21) ,Lookup!$A$2:$B$8,2,FALSE) -> Wednesday | E21: Website | F21: Need to share abous Us, Service and other details | H21: =VLOOKUP( WEEKDAY(I21) ,Lookup!$A$2:$B$8,2,FALSE) -> Wednesday | I21: 46218 | K21: =VLOOKUP( WEEKDAY(L21) ,Lookup!$A$2:$B$8,2,FALSE) -> Wednesday | L21: 46218
A22: =A21+1 -> 21 | B22: 46218 | C22: 0.4375 | D22: =VLOOKUP( WEEKDAY(B22) ,Lookup!$A$2:$B$8,2,FALSE) -> Wednesday | E22: Training Session | H22: =VLOOKUP( WEEKDAY(I22) ,Lookup!$A$2:$B$8,2,FALSE) -> Wednesday | I22: 46218 | K22: =VLOOKUP( WEEKDAY(L22) ,Lookup!$A$2:$B$8,2,FALSE) -> Wednesday | L22: 46218
A23: =A22+1 -> 22 | B23: 46218 | C23: 0.4375 | D23: =VLOOKUP( WEEKDAY(B23) ,Lookup!$A$2:$B$8,2,FALSE) -> Wednesday | E23: website | F23: Create Instagram Page, face book page, linkedin page and twitter | H23: =VLOOKUP( WEEKDAY(I23) ,Lookup!$A$2:$B$8,2,FALSE) -> Wednesday | I23: 46218 | K23: =VLOOKUP( WEEKDAY(L23) ,Lookup!$A$2:$B$8,2,FALSE) -> Wednesday | L23: 46218
A24: =A23+1 -> 23 | B24: 46219 | C24: 0.51388889 | D24: =VLOOKUP( WEEKDAY(B24) ,Lookup!$A$2:$B$8,2,FALSE) -> Thursday | F24: Today send another set of datas | H24: =VLOOKUP( WEEKDAY(I24) ,Lookup!$A$2:$B$8,2,FALSE) -> Thursday | I24: 46219 | K24: =VLOOKUP( WEEKDAY(L24) ,Lookup!$A$2:$B$8,2,FALSE) -> Thursday | L24: 46219
A25: =A24+1 -> 24 | B25: 46220 | D25: =VLOOKUP( WEEKDAY(B25) ,Lookup!$A$2:$B$8,2,FALSE) -> Friday | E25: chithirai Event | F25: Chennai travel | H25: =VLOOKUP( WEEKDAY(I25) ,Lookup!$A$2:$B$8,2,FALSE) -> Friday | I25: 46220 | K25: =VLOOKUP( WEEKDAY(L25) ,Lookup!$A$2:$B$8,2,FALSE) -> Friday | L25: 46220
A26: =A25+1 -> 25 | B26: 46221 | D26: =VLOOKUP( WEEKDAY(B26) ,Lookup!$A$2:$B$8,2,FALSE) -> Saturday | E26: chithirai Event | F26: chithirai Event | H26: =VLOOKUP( WEEKDAY(I26) ,Lookup!$A$2:$B$8,2,FALSE) -> Saturday | I26: 46221 | K26: =VLOOKUP( WEEKDAY(L26) ,Lookup!$A$2:$B$8,2,FALSE) -> Saturday | L26: 46221
A27: =A26+1 -> 26 | B27: 46222 | D27: =VLOOKUP( WEEKDAY(B27) ,Lookup!$A$2:$B$8,2,FALSE) -> Sunday | E27: chithirai Event | F27: Return to Tirunelveli from Chennai | H27: =VLOOKUP( WEEKDAY(I27) ,Lookup!$A$2:$B$8,2,FALSE) -> Sunday | I27: 46222 | K27: =VLOOKUP( WEEKDAY(L27) ,Lookup!$A$2:$B$8,2,FALSE) -> Sunday | L27: 46222
A28: =A27+1 -> 27 | B28: 46223 | C28: 0.41666667 | D28: =VLOOKUP( WEEKDAY(B28) ,Lookup!$A$2:$B$8,2,FALSE) -> Monday | E28: Asset purchase | F28: laptop Collect | G28: High | H28: =VLOOKUP( WEEKDAY(I28) ,Lookup!$A$2:$B$8,2,FALSE) -> Monday | I28: 46223 | K28: =VLOOKUP( WEEKDAY(L28) ,Lookup!$A$2:$B$8,2,FALSE) -> Monday | L28: 46223 | M28: 10:5
A29: =A28+1 -> 28 | B29: 46223 | C29: 0.41666667 | D29: =VLOOKUP( WEEKDAY(B29) ,Lookup!$A$2:$B$8,2,FALSE) -> Monday | E29: Client Followup | F29: Send a reminder whatsapp msg to i met at chithirai event | H29: =VLOOKUP( WEEKDAY(I29) ,Lookup!$A$2:$B$8,2,FALSE) -> Monday | I29: 46223 | K29: =VLOOKUP( WEEKDAY(L29) ,Lookup!$A$2:$B$8,2,FALSE) -> Monday | L29: 46223 | O29: whatsapp msg
A30: =A29+1 -> 29 | B30: 46223 | C30: 0.41666667 | D30: =VLOOKUP( WEEKDAY(B30) ,Lookup!$A$2:$B$8,2,FALSE) -> Monday | E30: Asset purchase | F30: Laptop Setup | H30: =VLOOKUP( WEEKDAY(I30) ,Lookup!$A$2:$B$8,2,FALSE) -> Monday | I30: 46223 | J30: 0.47916667 | K30: =VLOOKUP( WEEKDAY(L30) ,Lookup!$A$2:$B$8,2,FALSE) -> Monday | L30: 46223 | M30: 0.53472222 | N30: completed
A31: =A30+1 -> 30 | B31: 46223 | C31: 0.41666667 | D31: =VLOOKUP( WEEKDAY(B31) ,Lookup!$A$2:$B$8,2,FALSE) -> Monday | E31: Software Analysis | F31: TeleCMI Purchase | H31: =VLOOKUP( WEEKDAY(I31) ,Lookup!$A$2:$B$8,2,FALSE) -> Monday | I31: 46223 | K31: =VLOOKUP( WEEKDAY(L31) ,Lookup!$A$2:$B$8,2,FALSE) -> Monday | L31: 46223
A32: =A31+1 -> 31 | B32: 46223 | C32: 0.41666667 | D32: =VLOOKUP( WEEKDAY(B32) ,Lookup!$A$2:$B$8,2,FALSE) -> Monday | E32: Software Analysis | F32: Other call recording Software need to check | H32: =VLOOKUP( WEEKDAY(I32) ,Lookup!$A$2:$B$8,2,FALSE) -> Monday | I32: 46223 | K32: =VLOOKUP( WEEKDAY(L32) ,Lookup!$A$2:$B$8,2,FALSE) -> Monday | L32: 46223
A33: =A32+1 -> 32 | B33: 46223 | C33: 0.41666667 | D33: =VLOOKUP( WEEKDAY(B33) ,Lookup!$A$2:$B$8,2,FALSE) -> Monday | E33: Software Analysis | F33: CRM Software need to check | H33: =VLOOKUP( WEEKDAY(I33) ,Lookup!$A$2:$B$8,2,FALSE) -> Monday | I33: 46223 | K33: =VLOOKUP( WEEKDAY(L33) ,Lookup!$A$2:$B$8,2,FALSE) -> Monday | L33: 46223
A34: =A33+1 -> 33 | B34: 46223 | C34: 0.41666667 | D34: =VLOOKUP( WEEKDAY(B34) ,Lookup!$A$2:$B$8,2,FALSE) -> Monday | E34: Software Analysis | F34: Vsanth Ticket management, Chennai Event demo need to check | H34: =VLOOKUP( WEEKDAY(I34) ,Lookup!$A$2:$B$8,2,FALSE) -> Monday | I34: 46223 | K34: =VLOOKUP( WEEKDAY(L34) ,Lookup!$A$2:$B$8,2,FALSE) -> Monday | L34: 46223
A35: =A34+1 -> 34 | B35: 46223 | C35: 0.41666667 | D35: =VLOOKUP( WEEKDAY(B35) ,Lookup!$A$2:$B$8,2,FALSE) -> Monday | E35: Hiring | F35: Selvi 9years experience candidate need to interview | H35: =VLOOKUP( WEEKDAY(I35) ,Lookup!$A$2:$B$8,2,FALSE) -> Monday | I35: 46223 | K35: =VLOOKUP( WEEKDAY(L35) ,Lookup!$A$2:$B$8,2,FALSE) -> Monday | L35: 46223
A36: =A35+1 -> 35 | B36: 46223 | C36: 0.41666667 | D36: =VLOOKUP( WEEKDAY(B36) ,Lookup!$A$2:$B$8,2,FALSE) -> Monday | E36: Hiring | F36: Employees Schedule Confirmation | H36: =VLOOKUP( WEEKDAY(I36) ,Lookup!$A$2:$B$8,2,FALSE) -> Monday | I36: 46223 | J36: 0.54861111 | K36: =VLOOKUP( WEEKDAY(L36) ,Lookup!$A$2:$B$8,2,FALSE) -> Monday | L36: 46223 | M36: 0.55972222 | N36: completed | O36: Whatsa app
A37: =A36+1 -> 36 | B37: 46223 | C37: 0.41666667 | D37: =VLOOKUP( WEEKDAY(B37) ,Lookup!$A$2:$B$8,2,FALSE) -> Monday | E37: Training (Incoming Call) | F37: Rajiv Taljeras team | H37: =VLOOKUP( WEEKDAY(I37) ,Lookup!$A$2:$B$8,2,FALSE) -> Monday | I37: 46223 | J37: 0.46527778 | K37: =VLOOKUP( WEEKDAY(L37) ,Lookup!$A$2:$B$8,2,FALSE) -> Monday | L37: 46223 | M37: 0.47222222 | N37: Completed
A38: =A37+1 -> 37 | B38: 46223 | D38: =VLOOKUP( WEEKDAY(B38) ,Lookup!$A$2:$B$8,2,FALSE) -> Monday | E38: friendly call (Incoming call) | F38: Falmora Ragi chennai event participants | H38: =VLOOKUP( WEEKDAY(I38) ,Lookup!$A$2:$B$8,2,FALSE) -> Monday | I38: 46223 | J38: 0.57291667 | K38: =VLOOKUP( WEEKDAY(L38) ,Lookup!$A$2:$B$8,2,FALSE) -> Monday | L38: 46223 | M38: 0.57986111 | N38: Completed
A39: =A38+1 -> 38 | B39: 46223 | C39: 0.59027778 | D39: =VLOOKUP( WEEKDAY(B39) ,Lookup!$A$2:$B$8,2,FALSE) -> Monday | F39: Call center pricing analysis | H39: =VLOOKUP( WEEKDAY(I39) ,Lookup!$A$2:$B$8,2,FALSE) -> Monday | I39: 46223 | J39: 0.6 | K39: =VLOOKUP( WEEKDAY(L39) ,Lookup!$A$2:$B$8,2,FALSE) -> Monday | L39: 46223
A40: =A39+1 -> 39 | B40: 46223 | C40: 0.63541667 | D40: =VLOOKUP( WEEKDAY(B40) ,Lookup!$A$2:$B$8,2,FALSE) -> Monday | E40: Mentoring Session | F40: Senthil Anna call regarding client pricing and general discussion | H40: =VLOOKUP( WEEKDAY(I40) ,Lookup!$A$2:$B$8,2,FALSE) -> Monday | I40: 46223 | J40: 0.63541667 | K40: =VLOOKUP( WEEKDAY(L40) ,Lookup!$A$2:$B$8,2,FALSE) -> Monday | L40: 46223 | M40: 0.82986111 | N40: Completed
A41: =A40+1 -> 40 | B41: 46223 | C41: 0.875 | D41: =VLOOKUP( WEEKDAY(B41) ,Lookup!$A$2:$B$8,2,FALSE) -> Monday | E41: Chithirai Chennai Event: Transcript | F41: Initially tried Perplexity but stopped in Mid half do started to download and convert Mpeg to MP3 and upload in sarvai Ai and got the transcipt | H41: =VLOOKUP( WEEKDAY(I41) ,Lookup!$A$2:$B$8,2,FALSE) -> Monday | I41: 46223 | J41: 0.875 | K41: =VLOOKUP( WEEKDAY(L41) ,Lookup!$A$2:$B$8,2,FALSE) -> Monday | L41: 46223 | M41: 0.94444444 | N41: Completed
A42: =A41+1 -> 41 | B42: 46223 | C42: 0.95138889 | D42: =VLOOKUP( WEEKDAY(B42) ,Lookup!$A$2:$B$8,2,FALSE) -> Monday | E42: Planner | F42: Planning and Dailyy planner =sheet updated | H42: =VLOOKUP( WEEKDAY(I42) ,Lookup!$A$2:$B$8,2,FALSE) -> Monday | I42: 46223 | J42: 0.45138889 | K42: =VLOOKUP( WEEKDAY(L42) ,Lookup!$A$2:$B$8,2,FALSE) -> Monday | L42: 46223 | M42: 0.9375
A43: =A42+1 -> 42 | B43: 46224 | C43: 0.42361111 | D43: =VLOOKUP( WEEKDAY(B43) ,Lookup!$A$2:$B$8,2,FALSE) -> Tuesday | E43: Planner | F43: Palnner Sheet Updated | H43: =VLOOKUP( WEEKDAY(I43) ,Lookup!$A$2:$B$8,2,FALSE) -> Tuesday | I43: 46224 | J43: 0.42361111 | K43: =VLOOKUP( WEEKDAY(L43) ,Lookup!$A$2:$B$8,2,FALSE) -> Tuesday | L43: 46224 | M43: 0.43402778
A44: =A43+1 -> 43 | B44: 46224 | C44: 0.43472222 | D44: =VLOOKUP( WEEKDAY(B44) ,Lookup!$A$2:$B$8,2,FALSE) -> Tuesday | E44: Personal Incoming call | F44: Parvathy regading Bairava school Issue, they send outside of the class room because he made lot of noise in class room | H44: =VLOOKUP( WEEKDAY(I44) ,Lookup!$A$2:$B$8,2,FALSE) -> Tuesday | I44: 46224 | J44: 0.43472222 | K44: =VLOOKUP( WEEKDAY(L44) ,Lookup!$A$2:$B$8,2,FALSE) -> Tuesday | L44: 46224 | M44: 0.44305556 | N44: Completed
A45: =A44+1 -> 44 | B45: 46224 | C45: 0.44444444 | D45: =VLOOKUP( WEEKDAY(B45) ,Lookup!$A$2:$B$8,2,FALSE) -> Tuesday | E45: Personal Incoming call | F45: Arefa Trainer regarding Bairava School Issue | H45: =VLOOKUP( WEEKDAY(I45) ,Lookup!$A$2:$B$8,2,FALSE) -> Tuesday | I45: 46224 | J45: 0.44861111 | K45: =VLOOKUP( WEEKDAY(L45) ,Lookup!$A$2:$B$8,2,FALSE) -> Tuesday | L45: 46224 | M45: 0.46180556 | N45: Completed
A46: =A45+1 -> 45 | B46: 46224 | C46: 0.47222222 | D46: =VLOOKUP( WEEKDAY(B46) ,Lookup!$A$2:$B$8,2,FALSE) -> Tuesday | E46: Recording Software Purchase | F46: TeleCMI Ravindar for 2 agents purchase called | H46: =VLOOKUP( WEEKDAY(I46) ,Lookup!$A$2:$B$8,2,FALSE) -> Tuesday | I46: 46224 | K46: =VLOOKUP( WEEKDAY(L46) ,Lookup!$A$2:$B$8,2,FALSE) -> Tuesday | L46: 46224
A47: =A46+1 -> 46 | B47: 46224 | C47: 0.47569444 | D47: =VLOOKUP( WEEKDAY(B47) ,Lookup!$A$2:$B$8,2,FALSE) -> Tuesday | E47: BPO training | F47: BPO training class ned to attend, Tried Pradeep call not picked | H47: =VLOOKUP( WEEKDAY(I47) ,Lookup!$A$2:$B$8,2,FALSE) -> Tuesday | I47: 46224 | K47: =VLOOKUP( WEEKDAY(L47) ,Lookup!$A$2:$B$8,2,FALSE) -> Tuesday | L47: 46224
A48: =A47+1 -> 47 | B48: 46224 | C48: 0 | D48: =VLOOKUP( WEEKDAY(B48) ,Lookup!$A$2:$B$8,2,FALSE) -> Tuesday | E48: Hiring - Preparation | F48: Selvi 9years experience candidate need to interview | H48: =VLOOKUP( WEEKDAY(I48) ,Lookup!$A$2:$B$8,2,FALSE) -> Tuesday | I48: 46224 | J48: 0 | K48: =VLOOKUP( WEEKDAY(L48) ,Lookup!$A$2:$B$8,2,FALSE) -> Tuesday | L48: 46224 | M48: 0.017361111
A49: =A48+1 -> 48 | B49: 46224 | C49: 0.017361111 | D49: =VLOOKUP( WEEKDAY(B49) ,Lookup!$A$2:$B$8,2,FALSE) -> Tuesday | E49: Hiring - Google Meet link | F49: Googel Meet Link Created | H49: =VLOOKUP( WEEKDAY(I49) ,Lookup!$A$2:$B$8,2,FALSE) -> Tuesday | I49: 46224 | J49: 0.027777778 | K49: =VLOOKUP( WEEKDAY(L49) ,Lookup!$A$2:$B$8,2,FALSE) -> Tuesday | L49: 46224 | M49: 0.020833333
A50: =A49+1 -> 49 | B50: 46224 | C50: 0.020833333 | D50: =VLOOKUP( WEEKDAY(B50) ,Lookup!$A$2:$B$8,2,FALSE) -> Tuesday | E50: Hiring - Interview | F50: Interview | H50: =VLOOKUP( WEEKDAY(I50) ,Lookup!$A$2:$B$8,2,FALSE) -> Tuesday | I50: 46224 | J50: 0.020833333 | K50: =VLOOKUP( WEEKDAY(L50) ,Lookup!$A$2:$B$8,2,FALSE) -> Tuesday | L50: 46224 | M50: 0.54166667
A51: =A50+1 -> 50 | B51: 46224 | C51: 0.5625 | D51: =VLOOKUP( WEEKDAY(B51) ,Lookup!$A$2:$B$8,2,FALSE) -> Tuesday | E51: Hiring - Preparation | F51: Jothi Prakash Diabetic Patient, Viestage, Parvathy Reference, Amutha akka product eduthu pannura company | H51: =VLOOKUP( WEEKDAY(I51) ,Lookup!$A$2:$B$8,2,FALSE) -> Tuesday | I51: 46224 | J51: 0.5625 | K51: =VLOOKUP( WEEKDAY(L51) ,Lookup!$A$2:$B$8,2,FALSE) -> Tuesday | L51: 46224 | M51: 0.5625
A52: =A51+1 -> 51 | B52: 46224 | C52: 0.079861111 | D52: =VLOOKUP( WEEKDAY(B52) ,Lookup!$A$2:$B$8,2,FALSE) -> Tuesday | E52: Hiring - Google Meet link | F52: Googel Meet Link Created | H52: =VLOOKUP( WEEKDAY(I52) ,Lookup!$A$2:$B$8,2,FALSE) -> Tuesday | I52: 46224 | J52: 0.57638889 | K52: =VLOOKUP( WEEKDAY(L52) ,Lookup!$A$2:$B$8,2,FALSE) -> Tuesday | L52: 46224 | M52: 0.57638889
A53: =A52+1 -> 52 | B53: 46224 | C53: 0.079861111 | D53: =VLOOKUP( WEEKDAY(B53) ,Lookup!$A$2:$B$8,2,FALSE) -> Tuesday | E53: Hiring - Interview | F53: Interview | H53: =VLOOKUP( WEEKDAY(I53) ,Lookup!$A$2:$B$8,2,FALSE) -> Tuesday | I53: 46224 | J53: 0.58333333 | K53: =VLOOKUP( WEEKDAY(L53) ,Lookup!$A$2:$B$8,2,FALSE) -> Tuesday | L53: 46224 | M53: 0.59722222
A54: =A53+1 -> 53 | B54: 46224 | C54: 0.59722222 | D54: =VLOOKUP( WEEKDAY(B54) ,Lookup!$A$2:$B$8,2,FALSE) -> Tuesday | E54: Lunch | F54: Lunch | H54: =VLOOKUP( WEEKDAY(I54) ,Lookup!$A$2:$B$8,2,FALSE) -> Tuesday | I54: 46224 | J54: 0.59722222 | K54: =VLOOKUP( WEEKDAY(L54) ,Lookup!$A$2:$B$8,2,FALSE) -> Tuesday | L54: 46224 | M54: 0.625
A55: =A54+1 -> 54 | B55: 46224 | C55: 0.625 | D55: =VLOOKUP( WEEKDAY(B55) ,Lookup!$A$2:$B$8,2,FALSE) -> Tuesday | E55: Incoming call | F55: Senthil Anna call | H55: =VLOOKUP( WEEKDAY(I55) ,Lookup!$A$2:$B$8,2,FALSE) -> Tuesday | I55: 46224 | J55: 0.625 | K55: =VLOOKUP( WEEKDAY(L55) ,Lookup!$A$2:$B$8,2,FALSE) -> Tuesday | L55: 46224 | M55: 0.64583333
A56: =A55+1 -> 55 | B56: 46224 | C56: 0.64583333 | D56: =VLOOKUP( WEEKDAY(B56) ,Lookup!$A$2:$B$8,2,FALSE) -> Tuesday | E56: Incoming call | F56: Tata tele Service | H56: =VLOOKUP( WEEKDAY(I56) ,Lookup!$A$2:$B$8,2,FALSE) -> Tuesday | I56: 46224 | J56: 0.64583333 | K56: =VLOOKUP( WEEKDAY(L56) ,Lookup!$A$2:$B$8,2,FALSE) -> Tuesday | L56: 46224 | M56: 0.65625
A57: =A56+1 -> 56 | B57: 46224 | C57: 0.65972222 | D57: =VLOOKUP( WEEKDAY(B57) ,Lookup!$A$2:$B$8,2,FALSE) -> Tuesday | E57: Incoming call | F57: Bajaj Finance, 24000 pay pannuna NDC issue pannuren sollranga | H57: =VLOOKUP( WEEKDAY(I57) ,Lookup!$A$2:$B$8,2,FALSE) -> Tuesday | I57: 46224 | J57: 0.65972222 | K57: =VLOOKUP( WEEKDAY(L57) ,Lookup!$A$2:$B$8,2,FALSE) -> Tuesday | L57: 46224 | M57: 0.66666667
A58: =A57+1 -> 57 | B58: 46224 | C58: 0.16666667 | D58: =VLOOKUP( WEEKDAY(B58) ,Lookup!$A$2:$B$8,2,FALSE) -> Tuesday | E58: Documentation | F58: Move all the Palm Era group to Archieve | G58: Medium | H58: =VLOOKUP( WEEKDAY(I58) ,Lookup!$A$2:$B$8,2,FALSE) -> Tuesday | I58: 46224 | J58: 0.66666667 | K58: =VLOOKUP( WEEKDAY(L58) ,Lookup!$A$2:$B$8,2,FALSE) -> Tuesday | L58: 46224 | M58: 0.68055556
A59: =A58+1 -> 58 | B59: 46224 | C59: 0.16666667 | D59: =VLOOKUP( WEEKDAY(B59) ,Lookup!$A$2:$B$8,2,FALSE) -> Tuesday | E59: Employee | F59: Subu Lakshmi call asked sim for call training purpose | H59: =VLOOKUP( WEEKDAY(I59) ,Lookup!$A$2:$B$8,2,FALSE) -> Tuesday | I59: 46224 | J59: 0.68055556 | K59: =VLOOKUP( WEEKDAY(L59) ,Lookup!$A$2:$B$8,2,FALSE) -> Tuesday | L59: 46224 | M59: 0.68402778
A60: =A59+1 -> 59 | B60: 46224 | C60: 0.6875 | D60: =VLOOKUP( WEEKDAY(B60) ,Lookup!$A$2:$B$8,2,FALSE) -> Tuesday | E60: Mentoring Session | F60: Senthil Anna call | H60: =VLOOKUP( WEEKDAY(I60) ,Lookup!$A$2:$B$8,2,FALSE) -> Tuesday | I60: 46224 | J60: 0.6875 | K60: =VLOOKUP( WEEKDAY(L60) ,Lookup!$A$2:$B$8,2,FALSE) -> Tuesday | L60: 46224 | M60: 6.30 Pm
A61: =A60+1 -> 60 | B61: 46224 | C61: 0.89583333 | D61: =VLOOKUP( WEEKDAY(B61) ,Lookup!$A$2:$B$8,2,FALSE) -> Tuesday | E61: Mentoring Session | F61: Bhuvana Annie call | H61: =VLOOKUP( WEEKDAY(I61) ,Lookup!$A$2:$B$8,2,FALSE) -> Tuesday | I61: 46224 | J61: 0.89583333 | K61: =VLOOKUP( WEEKDAY(L61) ,Lookup!$A$2:$B$8,2,FALSE) -> Tuesday | L61: 46224 | M61: 0.9375
A62: =A61+1 -> 61 | B62: 46224 | C62: 0.9375 | D62: =VLOOKUP( WEEKDAY(B62) ,Lookup!$A$2:$B$8,2,FALSE) -> Tuesday | E62: Scheduling | F62: Planner and Daily tracker updation | H62: =VLOOKUP( WEEKDAY(I62) ,Lookup!$A$2:$B$8,2,FALSE) -> Tuesday | I62: 46224 | J62: 0.9375 | K62: =VLOOKUP( WEEKDAY(L62) ,Lookup!$A$2:$B$8,2,FALSE) -> Tuesday | L62: 46224 | M62: 0.96875
A63: =A62+1 -> 62 | B63: 46225 | C63: 0.43055556 | D63: =VLOOKUP( WEEKDAY(B63) ,Lookup!$A$2:$B$8,2,FALSE) -> Wednesday | E63: Accounts | F63: At Team main accounts need to be updated | H63: =VLOOKUP( WEEKDAY(I63) ,Lookup!$A$2:$B$8,2,FALSE) -> Wednesday | I63: 46225 | J63: 0.4375 | K63: =VLOOKUP( WEEKDAY(L63) ,Lookup!$A$2:$B$8,2,FALSE) -> Tuesday | L63: 46224 | M63: 0.48611111
A64: =A63+1 -> 63 | B64: 46225 | C64: 0.48611111 | D64: =VLOOKUP( WEEKDAY(B64) ,Lookup!$A$2:$B$8,2,FALSE) -> Wednesday | E64: Software | F64: Asked for queartely but they mentioned not possible | H64: =VLOOKUP( WEEKDAY(I64) ,Lookup!$A$2:$B$8,2,FALSE) -> Wednesday | I64: 46225 | J64: 0.48611111 | K64: =VLOOKUP( WEEKDAY(L64) ,Lookup!$A$2:$B$8,2,FALSE) -> Wednesday | L64: 46225 | M64: 0.49305556
A65: =A64+1 -> 64 | B65: 46225 | C65: 0.49305556 | D65: =VLOOKUP( WEEKDAY(B65) ,Lookup!$A$2:$B$8,2,FALSE) -> Wednesday | E65: Team Lead | F65: Selvi Team Lead informed to check the call recording software | H65: =VLOOKUP( WEEKDAY(I65) ,Lookup!$A$2:$B$8,2,FALSE) -> Wednesday | I65: 46225 | J65: 0.49305556 | K65: =VLOOKUP( WEEKDAY(L65) ,Lookup!$A$2:$B$8,2,FALSE) -> Wednesday | L65: 46225 | M65: 0.5
A66: =A65+1 -> 65 | B66: 46225 | C66: 0.5 | D66: =VLOOKUP( WEEKDAY(B66) ,Lookup!$A$2:$B$8,2,FALSE) -> Wednesday | E66: Pricing Calculation Analysis | F66: https://www.magellan-solutions.com/blog/calculate-cost-per-call/ | H66: =VLOOKUP( WEEKDAY(I66) ,Lookup!$A$2:$B$8,2,FALSE) -> Wednesday | I66: 46225 | J66: 0.5 | K66: =VLOOKUP( WEEKDAY(L66) ,Lookup!$A$2:$B$8,2,FALSE) -> Wednesday | L66: 46225 | M66: 0.53125
A67: =A66+1 -> 66 | B67: 46225 | C67: 0.53125 | D67: =VLOOKUP( WEEKDAY(B67) ,Lookup!$A$2:$B$8,2,FALSE) -> Wednesday | E67: Personal Incoming call | F67: Jenolin about her twin kids and chennai event details | H67: =VLOOKUP( WEEKDAY(I67) ,Lookup!$A$2:$B$8,2,FALSE) -> Wednesday | I67: 46225 | J67: 0.53125 | K67: =VLOOKUP( WEEKDAY(L67) ,Lookup!$A$2:$B$8,2,FALSE) -> Wednesday | L67: 46225 | M67: 0.54861111
A68: =A67+1 -> 67 | B68: 46225 | C68: 0.54861111 | D68: =VLOOKUP( WEEKDAY(B68) ,Lookup!$A$2:$B$8,2,FALSE) -> Wednesday | E68: Training | F68: BPO Training Class | H68: =VLOOKUP( WEEKDAY(I68) ,Lookup!$A$2:$B$8,2,FALSE) -> Wednesday | I68: 46225 | J68: 0.55902778 | K68: =VLOOKUP( WEEKDAY(L68) ,Lookup!$A$2:$B$8,2,FALSE) -> Wednesday | L68: 46225 | M68: 0.57291667
A69: =A68+1 -> 68 | B69: 46225 | C69: 0.57291667 | D69: =VLOOKUP( WEEKDAY(B69) ,Lookup!$A$2:$B$8,2,FALSE) -> Wednesday | E69: Incoming call | F69: Rem Lead : Selvi regarding the My operator and zoho book pricing | H69: =VLOOKUP( WEEKDAY(I69) ,Lookup!$A$2:$B$8,2,FALSE) -> Wednesday | I69: 46225 | J69: 0.57291667 | K69: =VLOOKUP( WEEKDAY(L69) ,Lookup!$A$2:$B$8,2,FALSE) -> Wednesday | L69: 46225 | M69: 0.57986111
A70: =A69+1 -> 69 | B70: 46225 | C70: 0.58333333 | D70: =VLOOKUP( WEEKDAY(B70) ,Lookup!$A$2:$B$8,2,FALSE) -> Wednesday | E70: Break | F70: Lunch | H70: =VLOOKUP( WEEKDAY(I70) ,Lookup!$A$2:$B$8,2,FALSE) -> Wednesday | I70: 46225 | J70: 0.58333333 | K70: =VLOOKUP( WEEKDAY(L70) ,Lookup!$A$2:$B$8,2,FALSE) -> Wednesday | L70: 46225 | M70: 0.60416667
A71: =A70+1 -> 70 | B71: 46225 | C71: 0.60416667 | D71: =VLOOKUP( WEEKDAY(B71) ,Lookup!$A$2:$B$8,2,FALSE) -> Wednesday | E71: Analysis | F71: https://www.magellan-solutions.com/blog/calculate-cost-per-call/ | H71: =VLOOKUP( WEEKDAY(I71) ,Lookup!$A$2:$B$8,2,FALSE) -> Wednesday | I71: 46225 | J71: 0.60416667 | K71: =VLOOKUP( WEEKDAY(L71) ,Lookup!$A$2:$B$8,2,FALSE) -> Wednesday | L71: 46225 | M71: 0.625
A72: =A71+1 -> 71 | B72: 46225 | C72: 0.625 | D72: =VLOOKUP( WEEKDAY(B72) ,Lookup!$A$2:$B$8,2,FALSE) -> Wednesday | F72: Creating sales proposal | H72: =VLOOKUP( WEEKDAY(I72) ,Lookup!$A$2:$B$8,2,FALSE) -> Wednesday | I72: 46225 | J72: 0.625 | K72: =VLOOKUP( WEEKDAY(L72) ,Lookup!$A$2:$B$8,2,FALSE) -> Wednesday | L72: 46225 | M72: 0.67708333
A73: =A72+1 -> 72 | B73: 46225 | C73: 0.67708333 | D73: =VLOOKUP( WEEKDAY(B73) ,Lookup!$A$2:$B$8,2,FALSE) -> Wednesday | E73: Break | F73: tea Break | H73: =VLOOKUP( WEEKDAY(I73) ,Lookup!$A$2:$B$8,2,FALSE) -> Wednesday | I73: 46225 | J73: 0.67708333 | K73: =VLOOKUP( WEEKDAY(L73) ,Lookup!$A$2:$B$8,2,FALSE) -> Wednesday | L73: 46225 | M73: 0.6875
A74: =A73+1 -> 73 | B74: 46225 | C74: 0.6875 | D74: =VLOOKUP( WEEKDAY(B74) ,Lookup!$A$2:$B$8,2,FALSE) -> Wednesday | F74: Sales Proposal | H74: =VLOOKUP( WEEKDAY(I74) ,Lookup!$A$2:$B$8,2,FALSE) -> Wednesday | I74: 46225 | J74: 0.6875 | K74: =VLOOKUP( WEEKDAY(L74) ,Lookup!$A$2:$B$8,2,FALSE) -> Wednesday | L74: 46225 | M74: 0.74305556
A75: =A74+1 -> 74 | B75: 46225 | C75: 0.74305556 | D75: =VLOOKUP( WEEKDAY(B75) ,Lookup!$A$2:$B$8,2,FALSE) -> Wednesday | F75: Senthil Anna Call | H75: =VLOOKUP( WEEKDAY(I75) ,Lookup!$A$2:$B$8,2,FALSE) -> Wednesday | I75: 46225 | J75: 0.74305556 | K75: =VLOOKUP( WEEKDAY(L75) ,Lookup!$A$2:$B$8,2,FALSE) -> Wednesday | L75: 46225 | M75: 0.79861111
A76: =A75+1 -> 75 | B76: 46225 | C76: 0.86458333 | D76: =VLOOKUP( WEEKDAY(B76) ,Lookup!$A$2:$B$8,2,FALSE) -> Wednesday | E76: Research | F76: Check all the previous Chithirai Follow up calls | G76: High | H76: =VLOOKUP( WEEKDAY(I76) ,Lookup!$A$2:$B$8,2,FALSE) -> Wednesday | I76: 46225 | J76: 0.86458333 | K76: =VLOOKUP( WEEKDAY(L76) ,Lookup!$A$2:$B$8,2,FALSE) -> Wednesday | L76: 46225 | M76: 0.875
A77: =A76+1 -> 76 | B77: 46225 | C77: 0.875 | D77: =VLOOKUP( WEEKDAY(B77) ,Lookup!$A$2:$B$8,2,FALSE) -> Wednesday | E77: Research | F77: Prepare subha previous work experience | G77: High | H77: =VLOOKUP( WEEKDAY(I77) ,Lookup!$A$2:$B$8,2,FALSE) -> Wednesday | I77: 46225 | J77: 0.875 | K77: =VLOOKUP( WEEKDAY(L77) ,Lookup!$A$2:$B$8,2,FALSE) -> Wednesday | L77: 46225 | M77: 0.89583333
A78: =A77+1 -> 77 | B78: 46225 | C78: 0.89583333 | D78: =VLOOKUP( WEEKDAY(B78) ,Lookup!$A$2:$B$8,2,FALSE) -> Wednesday | E78: Research | F78: Services Subha worked on her experience | G78: High | H78: =VLOOKUP( WEEKDAY(I78) ,Lookup!$A$2:$B$8,2,FALSE) -> Wednesday | I78: 46225 | J78: 0.89583333 | K78: =VLOOKUP( WEEKDAY(L78) ,Lookup!$A$2:$B$8,2,FALSE) -> Wednesday | L78: 46225 | M78: 0.90277778
A79: =A78+1 -> 78 | B79: 46225 | C79: 0.90277778 | D79: =VLOOKUP( WEEKDAY(B79) ,Lookup!$A$2:$B$8,2,FALSE) -> Wednesday | E79: Research | F79: Industries where BPO can give service | G79: High | H79: =VLOOKUP( WEEKDAY(I79) ,Lookup!$A$2:$B$8,2,FALSE) -> Wednesday | I79: 46225 | J79: 0.90277778 | K79: =VLOOKUP( WEEKDAY(L79) ,Lookup!$A$2:$B$8,2,FALSE) -> Wednesday | L79: 46225 | M79: 0.91666667
A80: =A79+1 -> 79 | B80: 46225 | C80: 0.91666667 | D80: =VLOOKUP( WEEKDAY(B80) ,Lookup!$A$2:$B$8,2,FALSE) -> Wednesday | E80: Pricing | F80: Cost calculation for Starter, standard, premium | G80: High | H80: =VLOOKUP( WEEKDAY(I80) ,Lookup!$A$2:$B$8,2,FALSE) -> Wednesday | I80: 46225 | J80: 0.91666667 | K80: =VLOOKUP( WEEKDAY(L80) ,Lookup!$A$2:$B$8,2,FALSE) -> Wednesday | L80: 46225 | M80: 0.96180556
A81: =A80+1 -> 80 | B81: 46226 | C81: 0.38541667 | D81: =VLOOKUP( WEEKDAY(B81) ,Lookup!$A$2:$B$8,2,FALSE) -> Thursday | E81: Tracker | F81: Updated the Pending time sheet, daily tracker, planner | G81: High | H81: =VLOOKUP( WEEKDAY(I81) ,Lookup!$A$2:$B$8,2,FALSE) -> Thursday | I81: 46226 | J81: 0.38541667 | K81: =VLOOKUP( WEEKDAY(L81) ,Lookup!$A$2:$B$8,2,FALSE) -> Thursday | L81: 46226 | M81: 0.40625
A82: =A81+1 -> 81 | B82: 46226 | C82: 0.40625 | D82: =VLOOKUP( WEEKDAY(B82) ,Lookup!$A$2:$B$8,2,FALSE) -> Thursday | E82: Technical Issue | F82: Particularly in Time sheet The bottom sheet name is not visible when the column hides only the bottom sheet name is displaying | H82: =VLOOKUP( WEEKDAY(I82) ,Lookup!$A$2:$B$8,2,FALSE) -> Thursday | I82: 46226 | J82: 0.40625 | K82: =VLOOKUP( WEEKDAY(L82) ,Lookup!$A$2:$B$8,2,FALSE) -> Thursday | L82: 46226 | M82: 0.42708333 | N82: Holding | O82: Taking so much time so holding moved to New sheet
A83: =A82+1 -> 82 | B83: 46226 | C83: 0.42708333 | D83: =VLOOKUP( WEEKDAY(B83) ,Lookup!$A$2:$B$8,2,FALSE) -> Thursday | E83: QUestion Preparation | F83: Auditor Question preparation regarding name change issue and what are all the things we consider for a company | H83: =VLOOKUP( WEEKDAY(I83) ,Lookup!$A$2:$B$8,2,FALSE) -> Thursday | I83: 46226 | J83: 0.42708333 | K83: =VLOOKUP( WEEKDAY(L83) ,Lookup!$A$2:$B$8,2,FALSE) -> Thursday | L83: 46226 | M83: 0.45833333 | N83: Compled | O83: https://docs.google.com/spreadsheets/d/1BX1arbiV9XQvbCuUtAJIHWUkeA-NH-pXHAf1W1kwv68/edit?usp=sharing
A84: =A83+1 -> 83 | B84: 46226 | C84: 0.45833333 | D84: =VLOOKUP( WEEKDAY(B84) ,Lookup!$A$2:$B$8,2,FALSE) -> Thursday | E84: Break | F84: tea Break | H84: =VLOOKUP( WEEKDAY(I84) ,Lookup!$A$2:$B$8,2,FALSE) -> Thursday | I84: 46226 | J84: 0.45833333 | K84: =VLOOKUP( WEEKDAY(L84) ,Lookup!$A$2:$B$8,2,FALSE) -> Thursday | L84: 46226 | M84: 0.46875
A85: =A84+1 -> 84 | B85: 46226 | C85: 0.46875 | D85: =VLOOKUP( WEEKDAY(B85) ,Lookup!$A$2:$B$8,2,FALSE) -> Thursday | E85: Software Analysis | F85: My operator for call recording | H85: =VLOOKUP( WEEKDAY(I85) ,Lookup!$A$2:$B$8,2,FALSE) -> Thursday | I85: 46226 | J85: 0.46875 | K85: =VLOOKUP( WEEKDAY(L85) ,Lookup!$A$2:$B$8,2,FALSE) -> Thursday | L85: 46226 | M85: 0.47916667 | O85: Create a New Audio and Audio Shared in Software Analysis group
A86: =A85+1 -> 85 | B86: 46226 | C86: 0.47916667 | D86: =VLOOKUP( WEEKDAY(B86) ,Lookup!$A$2:$B$8,2,FALSE) -> Thursday | E86: Team Lead | F86: Confirmed through Whatsapp that she is available to join the demo | H86: =VLOOKUP( WEEKDAY(I86) ,Lookup!$A$2:$B$8,2,FALSE) -> Thursday | I86: 46226 | J86: 0.47916667 | K86: =VLOOKUP( WEEKDAY(L86) ,Lookup!$A$2:$B$8,2,FALSE) -> Thursday | L86: 46226 | M86: 0.48611111
A87: =A86+1 -> 86 | B87: 46226 | C87: 0.48611111 | D87: =VLOOKUP( WEEKDAY(B87) ,Lookup!$A$2:$B$8,2,FALSE) -> Thursday | E87: Break | H87: =VLOOKUP( WEEKDAY(I87) ,Lookup!$A$2:$B$8,2,FALSE) -> Thursday | I87: 46226 | J87: 0.48611111 | K87: =VLOOKUP( WEEKDAY(L87) ,Lookup!$A$2:$B$8,2,FALSE) -> Thursday | L87: 46226 | M87: 0
A88: =A87+1 -> 87 | B88: 46226 | C88: 0.5 | D88: =VLOOKUP( WEEKDAY(B88) ,Lookup!$A$2:$B$8,2,FALSE) -> Thursday | E88: Demo | F88: My Operator Call Recording software demo | H88: =VLOOKUP( WEEKDAY(I88) ,Lookup!$A$2:$B$8,2,FALSE) -> Thursday | I88: 46226 | J88: 0.5 | K88: =VLOOKUP( WEEKDAY(L88) ,Lookup!$A$2:$B$8,2,FALSE) -> Thursday | L88: 46226 | M88: 0.51388889 | N88: Completed
A89: =A88+1 -> 88 | B89: 46226 | C89: 0.51388889 | D89: =VLOOKUP( WEEKDAY(B89) ,Lookup!$A$2:$B$8,2,FALSE) -> Thursday | E89: Incomig Call | F89: Team Lead Selvi call regarding the My Operator | H89: =VLOOKUP( WEEKDAY(I89) ,Lookup!$A$2:$B$8,2,FALSE) -> Thursday | I89: 46226 | J89: 0.51388889 | K89: =VLOOKUP( WEEKDAY(L89) ,Lookup!$A$2:$B$8,2,FALSE) -> Thursday | L89: 46226 | M89: 0.52083333
A90: =A89+1 -> 89 | B90: 46226 | C90: 0.52083333 | D90: =VLOOKUP( WEEKDAY(B90) ,Lookup!$A$2:$B$8,2,FALSE) -> Thursday | E90: Break | H90: =VLOOKUP( WEEKDAY(I90) ,Lookup!$A$2:$B$8,2,FALSE) -> Saturday | K90: =VLOOKUP( WEEKDAY(L90) ,Lookup!$A$2:$B$8,2,FALSE) -> Saturday
A91: =A90+1 -> 90 | B91: 46226 | C91: 0.54513889 | D91: =VLOOKUP( WEEKDAY(B91) ,Lookup!$A$2:$B$8,2,FALSE) -> Thursday | E91: Incoming call | F91: Senthil Anna Call | H91: =VLOOKUP( WEEKDAY(I91) ,Lookup!$A$2:$B$8,2,FALSE) -> Thursday | I91: 46226 | J91: 0.54513889 | K91: =VLOOKUP( WEEKDAY(L91) ,Lookup!$A$2:$B$8,2,FALSE) -> Thursday | L91: 46226 | M91: 0.58333333
A92: =A91+1 -> 91 | B92: 46226 | C92: 0.58333333 | D92: =VLOOKUP( WEEKDAY(B92) ,Lookup!$A$2:$B$8,2,FALSE) -> Thursday | E92: Break | H92: =VLOOKUP( WEEKDAY(I92) ,Lookup!$A$2:$B$8,2,FALSE) -> Saturday | K92: =VLOOKUP( WEEKDAY(L92) ,Lookup!$A$2:$B$8,2,FALSE) -> Saturday
A93: =A92+1 -> 92 | B93: 46226 | C93: 0.59375 | D93: =VLOOKUP( WEEKDAY(B93) ,Lookup!$A$2:$B$8,2,FALSE) -> Thursday | E93: Finance | F93: Karthiga HDFC Bank Credit card and cibil score | H93: =VLOOKUP( WEEKDAY(I93) ,Lookup!$A$2:$B$8,2,FALSE) -> Thursday | I93: 46226 | J93: 0.59375 | K93: =VLOOKUP( WEEKDAY(L93) ,Lookup!$A$2:$B$8,2,FALSE) -> Thursday | L93: 46226 | M93: 0.60416667
A94: =A93+1 -> 93 | B94: 46226 | C94: 0.60416667 | D94: =VLOOKUP( WEEKDAY(B94) ,Lookup!$A$2:$B$8,2,FALSE) -> Thursday | F94: Break | H94: =VLOOKUP( WEEKDAY(I94) ,Lookup!$A$2:$B$8,2,FALSE) -> Thursday | I94: 46226 | J94: 0.60416667 | K94: =VLOOKUP( WEEKDAY(L94) ,Lookup!$A$2:$B$8,2,FALSE) -> Thursday | L94: 46226 | M94: 0.75
A95: =A94+1 -> 94 | B95: 46226 | C95: 0.75 | D95: =VLOOKUP( WEEKDAY(B95) ,Lookup!$A$2:$B$8,2,FALSE) -> Thursday | E95: Mentoring | F95: Bhuvana Annie call preparation | H95: =VLOOKUP( WEEKDAY(I95) ,Lookup!$A$2:$B$8,2,FALSE) -> Thursday | I95: 46226 | J95: 0.75 | K95: =VLOOKUP( WEEKDAY(L95) ,Lookup!$A$2:$B$8,2,FALSE) -> Thursday | L95: 46226 | M95: 0.79166667
A96: =A95+1 -> 95 | B96: 46226 | C96: 0.79166667 | D96: =VLOOKUP( WEEKDAY(B96) ,Lookup!$A$2:$B$8,2,FALSE) -> Thursday | E96: Mentoring | F96: Google Meet | H96: =VLOOKUP( WEEKDAY(I96) ,Lookup!$A$2:$B$8,2,FALSE) -> Thursday | I96: 46226 | J96: 0.79166667 | K96: =VLOOKUP( WEEKDAY(L96) ,Lookup!$A$2:$B$8,2,FALSE) -> Thursday | L96: 46226 | M96: 0.81597222
A97: =A96+1 -> 96 | B97: 46226 | C97: 0.81597222 | D97: =VLOOKUP( WEEKDAY(B97) ,Lookup!$A$2:$B$8,2,FALSE) -> Thursday | F97: Break | H97: =VLOOKUP( WEEKDAY(I97) ,Lookup!$A$2:$B$8,2,FALSE) -> Thursday | I97: 46226 | J97: 0.81597222 | K97: =VLOOKUP( WEEKDAY(L97) ,Lookup!$A$2:$B$8,2,FALSE) -> Thursday | L97: 46226 | M97: 0.9375
A98: =A97+1 -> 97 | B98: 46226 | C98: 0.9375 | D98: =VLOOKUP( WEEKDAY(B98) ,Lookup!$A$2:$B$8,2,FALSE) -> Thursday | E98: Planner | F98: Update the planner and daily planner | H98: =VLOOKUP( WEEKDAY(I98) ,Lookup!$A$2:$B$8,2,FALSE) -> Thursday | I98: 46226 | J98: 0.9375 | K98: =VLOOKUP( WEEKDAY(L98) ,Lookup!$A$2:$B$8,2,FALSE) -> Thursday | L98: 46226 | M98: 0.95138889
A99: =A98+1 -> 98 | B99: 46227 | C99: 0.39583333 | D99: =VLOOKUP( WEEKDAY(B99) ,Lookup!$A$2:$B$8,2,FALSE) -> Friday | E99: Bank Work | F99: HDFC Bank Karthiga Mathan Anna Friend: Regarding Credit card, credit card applied with 25000 fixed deposit, we can use 20,000 after that it will increase based on our performance, Current account and salary account details check, While checking refered a KTC Nagar Auditor Vignesh for Cancellation the old MSME and applying New MSME and GST, he will check with the MSME for the drawback for the cancellation and what source to apply for Startup funds, Shared Adhar and Pan card for checking | H99: =VLOOKUP( WEEKDAY(I99) ,Lookup!$A$2:$B$8,2,FALSE) -> Friday | I99: 46227 | J99: 9.30 Am | K99: =VLOOKUP( WEEKDAY(L99) ,Lookup!$A$2:$B$8,2,FALSE) -> Friday | L99: 46227 | M99: 0.47222222
A100: =A99+1 -> 99 | B100: 46227 | C100: 0.47222222 | D100: =VLOOKUP( WEEKDAY(B100) ,Lookup!$A$2:$B$8,2,FALSE) -> Friday | E100: Srilanka Event | F100: Eswari Call regarding Srilanka Event for Visa and team Discount | H100: =VLOOKUP( WEEKDAY(I100) ,Lookup!$A$2:$B$8,2,FALSE) -> Friday | I100: 46227 | J100: 0.47222222 | K100: =VLOOKUP( WEEKDAY(L100) ,Lookup!$A$2:$B$8,2,FALSE) -> Friday | L100: 46227 | M100: 0.47916667
...

Sheet Over All Planner
A1: Sl. No. | B1: Noted Start Date | C1: Noted Start Time | D1: Noted Time Spend | E1: Noted End Date | F1: Noted End Time | G1: Day | H1: Category | I1: Task / Activity | J1: Priority | K1: PlanStart Date | L1: PlanStart Time | M1: PlanEnd Date | N1: PlanEnd Time | O1: Status | P1: Remarks / Notes | Q1: Next Action | R1: Follow-up Date
A2: 1 | B2: 46223 | C2: 0.41666667 | G2: Monday | H2: Software Analysis | I2: TeleCMI Purchase | K2: 46224 | M2: 46224 | P2: Need to Purchase 2 agents, and check all the features
A3: 2 | B3: 46223 | C3: 0.41666667 | G3: Monday | H3: Software Analysis | I3: Other call recording Software need to check
A4: 3 | B4: 46223 | C4: 0.41666667 | G4: Monday | H4: Software Analysis | I4: CRM Software need to check
A5: 4 | B5: 46223 | C5: 0.41666667 | G5: Monday | H5: Software Analysis | I5: Vsanth Ticket management, Chennai Event demo need to check
A6: 5 | B6: 46223 | C6: 0.78819444 | E6: 46223 | F6: 0.79166667 | G6: Monday | H6: Hiring | I6: Selvi 9years experience candidate need to prepare for Interview, Google sheet, Folder, Timing confirmation | K6: 46224 | L6: 0 | M6: 46224 | N6: 0.017361111
A7: 6 | B7: 46223 | C7: 0.41666667 | G7: Monday | H7: Hiring | I7: Selvi 9years experience candidate need to interview | K7: 46224 | L7: 0.020833333 | M7: 46224 | N7: 0.54166667 | P7: Need to check the availability time
A8: 7 | B8: 46223 | C8: 0.41666667 | G8: Monday | H8: Training (Incoming Call) | I8: Rajiv Taljeras team | O8: Future Planning
A9: 8 | B9: 46223 | C9: 0.41666667 | G9: Monday | H9: Pricing | I9: Pricing fro Client need to work out
A10: 9 | B10: 46223 | C10: 0.60902778 | G10: Monday | H10: Documentation | I10: Company mail Id
A11: 10 | B11: 46223 | C11: 0.62847222 | G11: Monday | H11: Mentoring | I11: Bhuvana Annie call preparation
A12: 11 | B12: 46223 | C12: 0.75694444 | G12: Monday | H12: Accounts | I12: Chithirai Events Expense need to be corrected details in the pending
A13: 12 | B13: 46223 | C13: 0.77430556 | G13: Monday | H13: Accounts | I13: Need to check how a gmail is placed in desktop | J13: Low
A14: 13 | B14: 46223 | C14: 0.77430556 | G14: Monday | H14: Accounts | I14: Main Accounts update form july 10th 2026
A15: 14 | B15: 46223 | C15: 0.89583333 | D15: 2 MInutes | E15: 46223 | F15: 0.89585648 | G15: Monday | H15: Transcript | I15: Sarvam Ai: Chithirai Chennai Event Transcription | J15: Medium | K15: 46223 | L15: 0.88194444 | M15: 46223 | N15: 0.44444444 | O15: Completed | P15: Initially started with Perplexity, But perplexity record stopped unexpectedly, so again download the file and convert to MP3 file using online free converter and upload the document | Q15: Nil | R15: Nil
A16: 15 | B16: 46223 | C16: 0.94791667 | D16: 2 MInutes | E16: 46223 | F16: 0.94930556 | G16: Monday | I16: Organise File and Folders in Laptop (Book Mark)
A17: 16 | B17: 46223 | C17: 0.95138889 | D17: 2 MInutes | E17: 46223 | F17: 0.95277778 | G17: Monday | I17: Move all the Palm Era group to Archieve
A18: 17 | B18: 46223 | C18: 0.96527778 | D18: 2 MInutes | E18: 46223 | F18: 0.96736111 | G18: Monday | H18: Scheduling | I18: Need to talk to all the telecallers, Pesi romba nal achu, enna pannittu irukanga, avanga current situation ennan kekanum
A19: 18 | B19: 46224 | C19: 0.42361111 | D19: 2 Minutes | E19: 46224 | F19: 0.425 | G19: Tuesday | H19: Marketing | I19: Personal Branding | J19: Medium | K19: 46224 | L19: 0.425
A20: 19 | B20: 46224 | C20: 0.42708333 | D20: 2 Minutes | E20: 46224 | F20: 0.43055556 | G20: Tuesday | H20: Marketing | I20: Social Media Marketing: Instagram, Facebook and Linkedin | J20: Medium | K20: 46224 | L20: 0.43055556
A21: 20 | B21: 46224 | C21: 0.43055556 | D21: 2 Minutes | E21: 46224 | F21: 0.43402778 | G21: Tuesday | H21: Technical | I21: Need to Check while sharing the screen the google meet disconnects, yesterday call with bhuvana annies the issue occurs 2 times | J21: High | K21: 46224 | L21: 0.43402778
A22: 21 | B22: 46224 | C22: 0.44097222 | D22: 2 Minutes | E22: 46224 | F22: 0.46111111 | G22: Tuesday | H22: Technical | I22: Subha BPO training class need to Plan | J22: Medium | K22: 46224 | L22: 0.46111111
A23: 22 | B23: 46224 | C23: 0.78125 | D23: 2 Minutes | E23: 46224 | F23: 0.78263889 | G23: Tuesday | H23: Documentation | I23: Auditor Kitta pesanum , Before that prepare set of question | J23: High | K23: 46226 | L23: 0.41666667 | M23: 46226 | N23: 0.42708333 | O23: https://docs.google.com/spreadsheets/d/1BX1arbiV9XQvbCuUtAJIHWUkeA-NH-pXHAf1W1kwv68/edit?usp=sharing
A24: 23 | B24: 46224 | C24: 0.78263889 | D24: 2 Minutes | E24: 46224 | F24: 0.78402778 | G24: Tuesday | H24: Documentation | I24: Chatgptla Whatsapp Notes pottu analyse pannanum | J24: High | K24: 46224 | L24: 0.78402778
A25: 24 | B25: 46224 | C25: 0.78402778 | D25: 2 Minutes | E25: 46224 | F25: 0.78541667 | G25: Tuesday | H25: Research | I25: Check Previous sheet for Pricing and resources | J25: High | K25: 46224 | L25: 0.78541667
A26: 25 | B26: 46224 | C26: 0.94444444 | D26: 2 Minutes | E26: 46224 | F26: 0.94583333 | G26: Tuesday | H26: Research | I26: Compare BNI, JCI, Rotary, and other association | J26: Medium | K26: 46224 | L26: 0.94583333
A27: 26 | B27: 46224 | C27: 0.94444444 | D27: 2 Minutes | E27: 46224 | F27: 0.94583333 | G27: Tuesday | H27: Research | I27: Analyse the website for price calculation https://www.magellan-solutions.com/blog/calculate-cost-per-call/ | J27: High | K27: 46224 | L27: 0.94583333
A28: 27 | B28: 46224 | C28: 0.94444444 | D28: 2 Minutes | E28: 46224 | F28: 0.94583333 | G28: Tuesday | H28: Research | I28: Target Audience List | J28: High | K28: 46224 | L28: 0.94583333
A29: 28 | B29: 46224 | C29: 0.95138889 | D29: 1 MInutes | E29: 46224 | F29: 0.95277778 | G29: Tuesday | H29: Research | I29: Set of Questions for Client Requirement Checking | J29: Medium | K29: 46224 | L29: 0.95277778
A30: 29 | B30: 46225 | C30: 0.86458333 | D30: 1 MInutes | E30: 46225 | F30: 0.86597222 | G30: Wednesday | H30: Research | I30: Check all the previous Chithirai Follow up calls | J30: High | K30: 46225 | L30: 0.86597222 | M30: 46225 | N30: 0.875
A31: 30 | B31: 46225 | C31: 0.86597222 | D31: 1 MInutes | E31: 46225 | F31: 0.86736111 | G31: Wednesday | H31: Research | I31: Prepare subha previous work experience | J31: High | K31: 46225 | L31: 0.875 | M31: 46225 | N31: 0.89583333
A32: 31 | B32: 46225 | C32: 0.86736111 | D32: 1 MInutes | E32: 46225 | F32: 0.86944444 | G32: Wednesday | H32: Research | I32: Services Subha worked on her experience | J32: High | K32: 46225 | L32: 0.89583333 | M32: 46225 | N32: 0.90277778
A33: 32 | B33: 46225 | C33: 0.86944444 | D33: 1 MInutes | E33: 46225 | F33: 0.87083333 | G33: Wednesday | H33: Research | I33: Industries where BPO can give service | J33: High | K33: 46225 | L33: 0.90277778 | M33: 46225 | N33: 0.91666667
A34: 33 | B34: 46225 | C34: 0.91666667 | E34: 46225 | F34: 0.91805556 | G34: Wednesday | H34: Pricing | I34: Cost calculation for Starter, standard, premium | K34: 46225 | L34: 0.91666667 | M34: 46225 | N34: 0.96180556
A35: 34 | B35: 46226 | C35: 0.40625 | E35: 46226 | F35: 0.40694444 | G35: Thursday | H35: Client | I35: Sales Proposal
A36: 35 | B36: 46226 | C36: 0.40694444 | E36: 46226 | F36: 0.40763889 | G36: Thursday | H36: Marketing | I36: Digital Marketing
A37: 36 | B37: 46226 | C37: 0.40763889 | E37: 46226 | F37: 0.40833333 | G37: Thursday | H37: Marketing | I37: Website followup and finalise
A38: 37 | B38: 46226 | C38: 0.9375 | E38: 46226 | F38: 0.93888889 | G38: Thursday | H38: Finance | I38: HDFC Bank Direct visit | K38: 46227 | L38: 0.38541667 | M38: 46227 | N38: 0.42708333
A39: 38 | B39: 46226 | C39: 0.93888889 | E39: 46226 | F39: 0.94027778 | G39: Thursday | H39: Asset : Post Paid Sim Purchase | I39: Airtel Office -> Post Paid Sim to get fancy number to display in website and marketing activities post
A40: 39 | B40: 46226 | C40: 0.94027778 | E40: 46226 | F40: 0.94166667 | G40: Thursday | H40: Hiring : Appointment | I40: Tead lead Selvi Requirt, Monthly Salary will be 18000 initially, after 3 months the salary will be revised
A41: 40 | B41: 46226 | C41: 0.94166667 | E41: 46226 | F41: 0.94305556 | G41: Thursday | H41: Software : Purchase | I41: My operator to be finalised tomorrow
A42: 41 | B42: 46226 | C42: 0.94305556 | E42: 46226 | F42: 0.94444444 | G42: Thursday | H42: Marketing | I42: Website content to be finalised tomorrow
A43: 42 | B43: 46226 | C43: 0.94444444 | E43: 46226 | F43: 0.94583333 | G43: Thursday | H43: Registration | I43: Auditor call about registration and other prepared questions
A44: 43 | B44: 46226 | C44: 0.94583333 | E44: 46226 | F44: 0.94722222 | G44: Thursday | H44: Mentoring | I44: Bhuvana Annie Call Preparation Industry and the services,
A45: 44 | B45: 46226 | C45: 0.94722222 | E45: 46226 | F45: 0.94861111 | G45: Thursday | H45: Scheduling | I45: Call with Telecallers, take Individual call, and check there available time and challeges if any
A46: 45 | B46: 46226 | C46: 0.94861111 | E46: 46226 | F46: 0.95 | G46: Thursday | H46: Mentoring | I46: Bhuvana Annie Call Preparation Industry and the services,
A47: 46 | B47: 46226 | C47: 0.95 | E47: 46226 | F47: 0.95138889 | G47: Thursday | H47: Mentoring | I47: Bhuvana Annie call
A48: 47 | B48: 46227 | C48: 0.75 | E48: 46227 | F48: 0.75347222 | G48: Friday | H48: Documentation | I48: Rental Agreement for Spaco Co work space
A49: 48 | B49: 46228 | C49: 0.75 | E49: 46228 | G49: Saturday | H49: mentoring | I49: HR Skill Attribute 3 days Boot camp 25th to 27th July
A50: 49 | B50: 46229 | C50: 0.90625 | E50: 46229 | G50: Sunday | I50: Skill Attribute Analyse and workout
B51: 46229 | C51: 0.90625 | E51: 46229 | G51: Sunday | I51: RA Business school for Content Creation
B52: 46229 | C52: 0.90833333 | E52: 46229 | G52: Sunday | I52: Create a group and folder and share all the details in the group
B53: 46230 | C53: 0.43402778 | E53: 46230 | G53: Monday | I53: Commmercial Communication Rock Sir, regarding Yes Membership and IVR Service
B54: 46230 | C54: 0.43402778 | E54: 46230 | G54: Monday | I54: Muthu kulathur regarding WFH data entry project | K54: 46230 | L54: 0.43402778 | M54: 46231 | N54: 0.52777778
G55: Tuesday | I55: Aura Gold Anand Sir, Reagrding My operator as he is already using this software
G56: Tuesday | I56: Check Subu Lakshmi Telecaller as she allready mentioned that she have experience in medical billing
G57: Tuesday | I57: Telecaller Subu Lakshmi call not attend, share the msg that you send the resume with details regarding previous experience in Medical billing
B58: 46233 | C58: 0.41666667 | D58: Thursday | E58: 46233 | G58: Thursday | I58: Lakshmi Krishna Naturals, Facing issue in labelling and becoming trend in Instagram, so they need custome support, the outlet is in samathanapuram so planning to visit directly and pitch the BPO
B59: 46233 | C59: 0.41666667 | D59: Thursday | E59: 46233 | G59: Thursday | I59: Tele CRM Demo
B60: 46233 | C60: 0.41666667 | D60: Thursday | E60: 46233 | G60: Thursday | I60: Mani Megalai for Social Media Marketing
B61: 46233 | C61: 0.41666667 | D61: Thursday | E61: 46233 | G61: Thursday | I61: Tesing ISM Data technology in chatgpt how it will be profit, how many entries a individual can made,
B62: 46233 | C62: 0.41666667 | D62: Thursday | E62: 46233 | G62: Thursday | I62: Website content checking

Sheet Daily Planner
A1: Sl: No: | B1: Date | C1: Time | D1: Day | E1: Category | F1: Details | G1: Priority | H1: Planned Start Date | I1: Planned Start Time | J1: Planned End Date | K1: Planned End Time | L1: Status | M1: Remarks / Notes | N1: Next Action | O1: Follow-up Date
A2: 1 | B2: 46224 | C2: 0.41666667 | D2: =VLOOKUP( WEEKDAY(B2) ,Lookup!$A$2:$B$8,2,FALSE) -> Tuesday | E2: Hiring | F2: Selvi 9years experience candidate need to prepare for Interview, Google sheet, Folder, Timing confirmation | G2: High | H2: 46224 | I2: 0.4375 | J2: 46224 | K2: 0.45833333
A3: 2 | B3: 46224 | C3: 0.41666667 | D3: =VLOOKUP( WEEKDAY(B3) ,Lookup!$A$2:$B$8,2,FALSE) -> Tuesday | E3: Hiring | F3: Selvi 9years experience candidate need to interview | G3: High | H3: 46224 | I3: 0.45833333 | J3: 46224 | K3: 0.47916667
A4: 3 | B4: 46224 | C4: 0.41666667 | D4: =VLOOKUP( WEEKDAY(B4) ,Lookup!$A$2:$B$8,2,FALSE) -> Tuesday | E4: Scheduling | F4: Need to talk to all the telecallers, Pesi romba nal achu, enna pannittu irukanga, avanga current situation ennan kekanum | G4: High | H4: 46224 | I4: 0.47916667 | J4: 46224 | K4: 0.58333333
A5: 4 | B5: 46224 | C5: 0.41666667 | D5: =VLOOKUP( WEEKDAY(B5) ,Lookup!$A$2:$B$8,2,FALSE) -> Tuesday | E5: Documentation | F5: Organise File and Folders in Laptop (Book Mark) | G5: High | H5: 46224 | I5: 0.58333333 | J5: 46224 | K5: 0.60416667
A6: 5 | B6: 46224 | C6: 0.41666667 | D6: =VLOOKUP( WEEKDAY(B6) ,Lookup!$A$2:$B$8,2,FALSE) -> Tuesday | E6: Documentation | F6: Move all the Palm Era group to Archieve | G6: Medium | H6: 46224 | I6: 2.30Pm | J6: 46224 | K6: 0.625
A7: 6 | B7: 46224 | C7: 0.41666667 | D7: =VLOOKUP( WEEKDAY(B7) ,Lookup!$A$2:$B$8,2,FALSE) -> Tuesday | E7: Mentoring | F7: Bhuvana Annie call preparation | G7: High | H7: 46224 | I7: 0.625 | J7: 46224 | K7: 0.66666667
A8: 7 | B8: 46224 | C8: 0.47569444 | D8: =VLOOKUP( WEEKDAY(B8) ,Lookup!$A$2:$B$8,2,FALSE) -> Tuesday | E8: BPO training | F8: BPO training daily class | G8: Medium | H8: 46224 | I8: 0.66666667 | J8: 46224 | K8: 0.70833333 | M8: Pradeep in travel, so call training moved to tomorrow
A9: 8 | B9: 46224 | C9: 0.41666667 | D9: =VLOOKUP( WEEKDAY(B9) ,Lookup!$A$2:$B$8,2,FALSE) -> Tuesday | E9: Pricing | F9: Pricing fro Client need to work out | G9: High | H9: 46224 | I9: 0.70833333 | J9: 46224 | K9: 0.75
A10: 9 | B10: 46225 | C10: 0.41666667 | D10: =VLOOKUP( WEEKDAY(B10) ,Lookup!$A$2:$B$8,2,FALSE) -> Wednesday | E10: Research | F10: Analyse the website for price calculation https://www.magellan-solutions.com/blog/calculate-cost-per-call/ | G10: High | H10: 46225 | I10: 0.41666667 | J10: 46225 | K10: 0.45833333
A11: 10 | B11: 46225 | C11: 0.41666667 | D11: =VLOOKUP( WEEKDAY(B11) ,Lookup!$A$2:$B$8,2,FALSE) -> Wednesday | E11: Reserach | F11: Prepare Set of Questions for Auditor for Name change, pricing, and what are all the things a company will face | G11: High | H11: 46225 | I11: 0.45833333 | J11: 22-Ju;-2026 | K11: 0.47916667
A12: 11 | B12: 46225 | C12: 0.41666667 | D12: =VLOOKUP( WEEKDAY(B12) ,Lookup!$A$2:$B$8,2,FALSE) -> Wednesday | E12: Research | F12: Talk to Auditor Jagadeswari, Allan Cowork space, Santhi (Chithirai Chennai Participants) | G12: High | H12: 46225 | I12: 0.47916667 | J12: 46225 | K12: 0.010416667
A13: 12 | B13: 46225 | C13: 0.41666667 | D13: =VLOOKUP( WEEKDAY(B13) ,Lookup!$A$2:$B$8,2,FALSE) -> Wednesday | E13: Hiring | F13: Requirt selvi telecalling tomorrow, Assign Market research for call recording tools | G13: Medium | H13: 46225 | I13: 0.51041667 | J13: 46225 | K13: 0.54166667
A14: 13 | B14: 46225 | C14: 0.41666667 | D14: =VLOOKUP( WEEKDAY(B14) ,Lookup!$A$2:$B$8,2,FALSE) -> Wednesday | E14: Training | F14: Subha BPO Training class | G14: Medium | H14: 46225 | I14: 0.54166667 | J14: 46225 | K14: 0.58333333
A15: 14 | B15: 46225 | C15: 0.41666667 | D15: =VLOOKUP( WEEKDAY(B15) ,Lookup!$A$2:$B$8,2,FALSE) -> Wednesday | E15: Schedule | F15: Call with Telecallers, take Individual call, and check there available time and challeges if any | G15: High | H15: 46225 | I15: 0.58333333 | J15: 46225 | K15: 0.66666667
A16: 15 | B16: 46225 | C16: 0.41666667 | D16: =VLOOKUP( WEEKDAY(B16) ,Lookup!$A$2:$B$8,2,FALSE) -> Wednesday | E16: Documentation | F16: Organise File and Folders in Laptop (Book Mark) | G16: High | H16: 46225 | I16: 0.66666667 | J16: 46225 | K16: 0.70833333
A17: 16 | B17: 46225 | C17: 0.41666667 | D17: =VLOOKUP( WEEKDAY(B17) ,Lookup!$A$2:$B$8,2,FALSE) -> Wednesday | E17: Mentoring | F17: Bhuvana Annie call preparation | G17: High | H17: 46225 | I17: 0.70833333 | J17: 46225 | K17: 0.75
A18: 17 | B18: 46225 | C18: 0.41666667 | D18: =VLOOKUP( WEEKDAY(B18) ,Lookup!$A$2:$B$8,2,FALSE) -> Wednesday | E18: Documentation | F18: Chithirai participants list update in sheet | G18: Medium | H18: 46225 | I18: 0.75 | J18: 46225 | K18: 0.77083333
A19: 18 | B19: 46225 | C19: 0.42708333 | D19: =VLOOKUP( WEEKDAY(B19) ,Lookup!$A$2:$B$8,2,FALSE) -> Wednesday | E19: Accounts | F19: Main Accounts Sheet Update | G19: High | H19: 46225 | I19: 0.43055556 | J19: 46225 | K19: 0.45833333 | L19: Completed
A20: 19 | B20: 46226 | C20: 0.41666667 | D20: =VLOOKUP( WEEKDAY(B20) ,Lookup!$A$2:$B$8,2,FALSE) -> Thursday | E20: Reserach | F20: Prepare Set of Questions for Auditor for Name change, pricing, and what are all the things a company will face | G20: High | H20: 46226 | I20: 0.39583333 | J20: 46226 | K20: 0.41666667
A21: 20 | B21: 46226 | C21: 0.41666667 | D21: =VLOOKUP( WEEKDAY(B21) ,Lookup!$A$2:$B$8,2,FALSE) -> Thursday | E21: Research | F21: Talk to Auditor Jagadeswari, Allan Cowork space, Santhi (Chithirai Chennai Participants) | G21: High | H21: 46226 | I21: 0.41666667 | J21: 46226 | K21: 0.42708333 | L21: Completed | M21: https://docs.google.com/spreadsheets/d/1BX1arbiV9XQvbCuUtAJIHWUkeA-NH-pXHAf1W1kwv68/edit?usp=sharing
A22: 21 | B22: 46226 | C22: 0.41666667 | D22: =VLOOKUP( WEEKDAY(B22) ,Lookup!$A$2:$B$8,2,FALSE) -> Thursday | E22: Scheduling | F22: Call with Telecallers, take Individual call, and check there available time and challeges if any | G22: High | H22: 46226 | I22: 0.42708333 | J22: 46226 | K22: 0
A23: 22 | B23: 46226 | C23: 0.41666667 | D23: =VLOOKUP( WEEKDAY(B23) ,Lookup!$A$2:$B$8,2,FALSE) -> Thursday | E23: Research | F23: Chithirai participants list update in sheet | G23: High | H23: 46226 | I23: 0 | J23: 46226 | K23: 0.54166667
A24: 23 | B24: 46226 | C24: 0.41666667 | D24: =VLOOKUP( WEEKDAY(B24) ,Lookup!$A$2:$B$8,2,FALSE) -> Thursday | E24: Research | F24: Call Recording software finalise tomorrow | G24: High | H24: 46226 | I24: 0.54166667 | J24: 46226 | K24: 0.58333333
A25: 24 | B25: 46226 | C25: 0.41666667 | D25: =VLOOKUP( WEEKDAY(B25) ,Lookup!$A$2:$B$8,2,FALSE) -> Thursday | E25: Cibil Score | F25: Kathika , Mathan Anna Friend Need to check for Bajaj Finance closing and Credit Card | G25: High | H25: 46226 | I25: 0.58333333 | J25: 46226 | K25: 0.59375 | L25: Completed
A26: 25 | B26: 46226 | C26: 0.41666667 | D26: =VLOOKUP( WEEKDAY(B26) ,Lookup!$A$2:$B$8,2,FALSE) -> Thursday | E26: Social Media Manager | F26: Manimegai Social Media Manager Need to talk regarding Linkedin, Facebook and Instagram | G26: High | H26: 46226 | I26: 0.59375 | J26: 46226 | K26: 0.625
A27: 26 | B27: 46226 | C27: 0.41666667 | D27: =VLOOKUP( WEEKDAY(B27) ,Lookup!$A$2:$B$8,2,FALSE) -> Thursday | E27: BPO training | F27: BPO training daily class | G27: Medium | H27: 46226 | I27: 0.625 | J27: 46226 | K27: 0.66666667
A28: 27 | B28: 46227 | C28: 0.38541667 | D28: =VLOOKUP( WEEKDAY(B28) ,Lookup!$A$2:$B$8,2,FALSE) -> Friday | E28: Finance | F28: HDFC Bank Direct visit | H28: 46227 | I28: 0.38541667 | J28: 46227 | K28: 0.42708333 | L28: Completed
A29: 28 | B29: 46227 | C29: 0.38541667 | D29: =VLOOKUP( WEEKDAY(B29) ,Lookup!$A$2:$B$8,2,FALSE) -> Friday | E29: Asset : Post Paid Sim Purchase | F29: Airtel Office -> Post Paid Sim to get fancy number to display in website and marketing activities post | H29: 46227 | I29: 0.42708333 | J29: 46227 | K29: 0.45833333
A30: 29 | B30: 46227 | C30: 0.38541667 | D30: =VLOOKUP( WEEKDAY(B30) ,Lookup!$A$2:$B$8,2,FALSE) -> Friday | E30: Hiring : Appointment | F30: Tead lead Selvi Requirt, Monthly Salary will be 18000 initially, after 3 months the salary will be revised | H30: 46227 | I30: 0.45833333 | J30: 46227 | K30: 0.47916667
A31: 30 | B31: 46227 | C31: 0.38541667 | D31: =VLOOKUP( WEEKDAY(B31) ,Lookup!$A$2:$B$8,2,FALSE) -> Friday | E31: Software : Purchase | F31: My operator to be finalised tomorrow | H31: 46227 | I31: 0.47916667 | J31: 46227 | K31: 0
A32: 31 | B32: 46227 | C32: 0.38541667 | D32: =VLOOKUP( WEEKDAY(B32) ,Lookup!$A$2:$B$8,2,FALSE) -> Friday | E32: Marketing | F32: Website content to be finalised tomorrow | H32: 46227 | I32: 0 | J32: 46227 | K32: 0.58333333
A33: 32 | B33: 46227 | C33: 0.38541667 | D33: =VLOOKUP( WEEKDAY(B33) ,Lookup!$A$2:$B$8,2,FALSE) -> Friday | E33: Registration | F33: Auditor call about registration and other prepared questions | H33: 46227 | I33: 0.58333333 | J33: 46227 | K33: 0.60416667 | L33: Completed
A34: 33 | B34: 46227 | C34: 0.38541667 | D34: =VLOOKUP( WEEKDAY(B34) ,Lookup!$A$2:$B$8,2,FALSE) -> Friday | E34: Mentoring | F34: Bhuvana Annie Call Preparation Industry and the services, | H34: 46227 | I34: 0.60416667 | J34: 46227 | K34: 0.6875
A35: 34 | B35: 46227 | C35: 0.38541667 | D35: =VLOOKUP( WEEKDAY(B35) ,Lookup!$A$2:$B$8,2,FALSE) -> Friday | E35: Scheduling | F35: Call with Telecallers, take Individual call, and check there available time and challeges if any | H35: 46227 | I35: 0.6875 | J35: 46227 | K35: 0.77083333
A36: 35 | B36: 46227 | C36: 0.38541667 | D36: =VLOOKUP( WEEKDAY(B36) ,Lookup!$A$2:$B$8,2,FALSE) -> Friday | E36: Mentoring | F36: Bhuvana Annie Call Preparation Industry and the services, | H36: 46227 | I36: 0.77083333 | J36: 46227 | K36: 0.79166667
A37: 36 | B37: 46227 | C37: 0.38541667 | D37: =VLOOKUP( WEEKDAY(B37) ,Lookup!$A$2:$B$8,2,FALSE) -> Friday | E37: Mentoring | F37: Bhuvana Annie call | H37: 46227 | I37: 0.79166667 | J37: 46227 | K37: 0.8125
A38: 37 | B38: 46227 | C38: 0.38541667 | D38: =VLOOKUP( WEEKDAY(B38) ,Lookup!$A$2:$B$8,2,FALSE) -> Friday | E38: Documentation | F38: Rental Agreement for Spaco Co work space | H38: 46227 | I38: 0.76041667 | J38: 46227 | K38: 0.76388889
A39: 38 | B39: 46228 | C39: 0.38541667 | D39: =VLOOKUP( WEEKDAY(B39) ,Lookup!$A$2:$B$8,2,FALSE) -> Saturday | E39: Hiring | F39: Hire Selvi Tomorrow | H39: 46228 | I39: 0.91666667 | J39: 46228 | K39: 0.9375
A40: 39 | B40: 46228 | C40: 0.38541667 | D40: =VLOOKUP( WEEKDAY(B40) ,Lookup!$A$2:$B$8,2,FALSE) -> Saturday | E40: Training | F40: Check Bounvoice again, and start training with bounvoice tomorrow before that speak to the employees | H40: 46228 | I40: 0.9375 | J40: 46228 | K40: 0.5
A41: 40 | B41: 46228 | C41: 0.38541667 | D41: =VLOOKUP( WEEKDAY(B41) ,Lookup!$A$2:$B$8,2,FALSE) -> Saturday | E41: Documentation | F41: Chithirai participants list update in sheet | H41: 46228 | I41: 0.5 | J41: 46228 | K41: 0.54166667
A42: 41 | B42: 46228 | C42: 0.38541667 | D42: =VLOOKUP( WEEKDAY(B42) ,Lookup!$A$2:$B$8,2,FALSE) -> Saturday | E42: Client Auaction | F42: Chithirai participant pulse check and how the market pricing and requirements | H42: 46228 | I42: 0.54166667 | J42: 46228 | K42: 0.625
A43: 42 | B43: 46228 | C43: 0.38541667 | D43: =VLOOKUP( WEEKDAY(B43) ,Lookup!$A$2:$B$8,2,FALSE) -> Saturday | E43: Marketing | F43: Complete the Pending website content works | H43: 46228 | I43: 0.625 | J43: 46228 | K43: 0.66666667
A44: 43 | B44: 46228 | C44: 0.38541667 | D44: =VLOOKUP( WEEKDAY(B44) ,Lookup!$A$2:$B$8,2,FALSE) -> Saturday | E44: Marketing | F44: Plan for social media pages | H44: 46228 | I44: 0.66666667 | J44: 46228 | K44: 0.70833333
A45: 44 | B45: 46228 | C45: 0.38541667 | D45: =VLOOKUP( WEEKDAY(B45) ,Lookup!$A$2:$B$8,2,FALSE) -> Saturday | E45: Mentoring | F45: BPO training daily class | H45: 46228 | I45: 0.70833333 | J45: 46228 | K45: 0.75
A46: 45 | B46: 46228 | C46: 0.38541667 | D46: =VLOOKUP( WEEKDAY(B46) ,Lookup!$A$2:$B$8,2,FALSE) -> Saturday | E46: Mentoring | F46: HR Skill Attribute 3 days Boot camp | H46: 46228 | I46: 0.75 | K46: 0.875
A47: 46 | B47: 46230 | C47: 0.4375 | D47: =VLOOKUP( WEEKDAY(B47) ,Lookup!$A$2:$B$8,2,FALSE) -> Monday | E47: Course | F47: Rd Business School Personal Branding
A48: 47 | B48: 46230 | C48: 0.4375 | D48: =VLOOKUP( WEEKDAY(B48) ,Lookup!$A$2:$B$8,2,FALSE) -> Monday | E48: IVR Software Analysis | F48: Commmercial Communication Rock Sir, regarding Yes Membership and IVR Service | H48: 46230 | I48: 0.57291667 | J48: 46230 | K48: 0.57430556
A49: 48 | B49: 46230 | C49: 0.4375 | D49: =VLOOKUP( WEEKDAY(B49) ,Lookup!$A$2:$B$8,2,FALSE) -> Monday | E49: Recuritments | F49: Muthu kulathur regarding WFH data entry project | H49: 46230 | I49: 0.58472222 | J49: 46230 | K49: 0.59027778
A50: 49 | B50: 46230 | C50: 0.4375 | D50: =VLOOKUP( WEEKDAY(B50) ,Lookup!$A$2:$B$8,2,FALSE) -> Monday | E50: IVR Software Analysis | F50: Aura Gold Anand Sir, Reagrding My operator as he is already using this software | H50: 46230 | I50: 0.57638889 | J50: 46230 | K50: 0.57777778
A51: 50 | B51: 46231 | C51: 0.47916667 | D51: =VLOOKUP( WEEKDAY(B51) ,Lookup!$A$2:$B$8,2,FALSE) -> Tuesday | E51: Company Visit | F51: ISM Data tenkasi Muthu planning to meet tomorrow regarding vendor | H51: 46231 | I51: 0.47916667 | J51: 46231 | K51: 0.52777778
A52: 51 | B52: 46231 | C52: 0.47916667 | D52: =VLOOKUP( WEEKDAY(B52) ,Lookup!$A$2:$B$8,2,FALSE) -> Tuesday | E52: Documentation | F52: Need to speak to auditor regarding Client Agreement and Employee agreement | H52: 46231 | I52: 0.79166667 | J52: 46231 | K52: 0.80208333
A53: 52 | B53: 46232 | C53: 0.46319444 | D53: =VLOOKUP( WEEKDAY(B53) ,Lookup!$A$2:$B$8,2,FALSE) -> Wednesday | E53: Documentation | F53: Co Work space Rental agreement and EB Bill Need to check | H53: 46232 | I53: 0.42708333
A54: 53 | B54: 46232 | C54: 0.46319444 | D54: =VLOOKUP( WEEKDAY(B54) ,Lookup!$A$2:$B$8,2,FALSE) -> Wednesday | E54: Marketing | F54: Karunya Team Digital Marketing need to check | H54: 46232 | I54: 0.71875 | J54: 46232 | K54: 0.72222222
A55: 54 | B55: 46232 | C55: 0.46319444 | D55: =VLOOKUP( WEEKDAY(B55) ,Lookup!$A$2:$B$8,2,FALSE) -> Wednesday | E55: Vendor | F55: ISM Data Technology need to check for E book and Voice Process | H55: 46232 | I55: 0.47916667
A56: 55 | B56: 46232 | C56: 0.46319444 | D56: =VLOOKUP( WEEKDAY(B56) ,Lookup!$A$2:$B$8,2,FALSE) -> Wednesday | E56: Marketing | F56: Mani megalai for Digital MArketing
A57: 56 | B57: 46232 | C57: 0.46319444 | D57: =VLOOKUP( WEEKDAY(B57) ,Lookup!$A$2:$B$8,2,FALSE) -> Wednesday | E57: Marketing | F57: Women Empowerement Madurai Event Need to Check
A58: 57 | B58: 46232 | C58: 0.46319444 | D58: =VLOOKUP( WEEKDAY(B58) ,Lookup!$A$2:$B$8,2,FALSE) -> Wednesday | E58: Client Auaction | F58: Call to Ravi International to confirm the pricing and next step | H58: 46232 | I58: 0.72222222 | J58: 46232 | K58: 0.72569444
A59: 58 | B59: 46232 | C59: 0.46319444 | D59: =VLOOKUP( WEEKDAY(B59) ,Lookup!$A$2:$B$8,2,FALSE) -> Wednesday | E59: Client Auaction | F59: Call to Hepziba to confirm the pricing and next step | H59: 46232 | I59: 0.72569444 | J59: 46232 | K59: 0.72916667
A60: 59 | B60: 46232 | C60: 0.46319444 | D60: =VLOOKUP( WEEKDAY(B60) ,Lookup!$A$2:$B$8,2,FALSE) -> Wednesday | E60: Client Auaction | F60: Call to Elavaran Chitti Export regarding English Telecallers | H60: 46232 | I60: 0.22916667
A61: 60 | B61: 46232 | C61: 0.46319444 | D61: =VLOOKUP( WEEKDAY(B61) ,Lookup!$A$2:$B$8,2,FALSE) -> Wednesday | E61: Hiring | F61: Check swetha, Ramani for Data entry (Medical billing work) | H61: HOLD
A62: 61 | B62: 46233 | C62: 0.41666667 | D62: =VLOOKUP( WEEKDAY(B62) ,Lookup!$A$2:$B$8,2,FALSE) -> Thursday | E62: Client Auaction | F62: Lakshmi Krishna Naturals, Facing issue in labelling and becoming trend in Instagram, so they need custome support, the outlet is in samathanapuram so planning to visit directly and pitch the BPO | H62: 46232 | I62: 0.41666667 | J62: 46232 | K62: 0.45833333
A63: 63 | B63: 46233 | C63: 0.5 | D63: =VLOOKUP( WEEKDAY(B63) ,Lookup!$A$2:$B$8,2,FALSE) -> Thursday | E63: Software Analysis | F63: Tele CRM Demo | H63: 46233 | I63: 0.5 | J63: 46233 | K63: 0.55208333
A64: 64 | B64: 46233 | C64: 0.5625 | D64: =VLOOKUP( WEEKDAY(B64) ,Lookup!$A$2:$B$8,2,FALSE) -> Thursday | E64: Hiring | F64: Mani Megalai for Social Media Marketing | H64: 46223 | I64: 0.5625 | J64: 46223 | K64: 0.57291667
A65: 65 | B65: 46233 | C65: 0.57291667 | D65: =VLOOKUP( WEEKDAY(B65) ,Lookup!$A$2:$B$8,2,FALSE) -> Thursday | E65: Data Entry project | F65: Tesing ISM Data technology in chatgpt how it will be profit, how many entries a individual can made, | H65: 46223 | I65: 0.57291667 | J65: 46223 | K65: 0.66666667
A66: 66 | B66: 46233 | C66: 0.66666667 | D66: =VLOOKUP( WEEKDAY(B66) ,Lookup!$A$2:$B$8,2,FALSE) -> Thursday | E66: Marketing | F66: Website content checking | H66: 46223 | I66: 0.66666667 | J66: 46223 | K66: 0.74305556
A67: 67 | B67: 46233 | C67: 0.74305556 | D67: =VLOOKUP( WEEKDAY(B67) ,Lookup!$A$2:$B$8,2,FALSE) -> Thursday | E67: Networking | F67: Searched the networking platform and explore | H67: 46223 | I67: 0.74305556 | J67: 46223 | K67: 0.78472222
A68: 68 | B68: 46233 | C68: 0.78472222 | D68: =VLOOKUP( WEEKDAY(B68) ,Lookup!$A$2:$B$8,2,FALSE) -> Thursday | E68: Time sheet | F68: Update the Pending Sheet | H68: 46223 | I68: 0.78472222 | J68: 46223 | K68: 0.79513889
A69: 69 | B69: 46234 | C69: 0.41666667 | D69: =VLOOKUP( WEEKDAY(B69) ,Lookup!$A$2:$B$8,2,FALSE) -> Friday | E69: Digital Marketing | F69: Search Digial MArketing Partner | H69: 46234 | I69: 0.41666667 | J69: 46234 | K69: 0.47916667
A70: 70 | B70: 46234 | C70: 0.41666667 | D70: =VLOOKUP( WEEKDAY(B70) ,Lookup!$A$2:$B$8,2,FALSE) -> Friday | E70: Software | F70: Tele CRM recording and Doubts clarification | H70: 46234 | I70: 0.47916667 | J70: 46234 | K70: 0.64583333
A71: 71 | B71: 46234 | C71: 0.41666667 | D71: =VLOOKUP( WEEKDAY(B71) ,Lookup!$A$2:$B$8,2,FALSE) -> Friday | E71: Client Auaction | F71: Lakshmi Krishna Naturals appointment check | H71: 46234 | I71: 0.66666667 | J71: 46234 | K71: 0.67013889
A72: 72 | B72: 46234 | C72: 0.41666667 | D72: =VLOOKUP( WEEKDAY(B72) ,Lookup!$A$2:$B$8,2,FALSE) -> Friday | E72: Client Auaction | F72: Follow Happy Ending and Penniyam Academy | H72: 46234 | I72: 0.67013889 | J72: 46234 | K72: 0.67361111
A73: 73 | B73: 46234 | C73: 0.41666667 | D73: =VLOOKUP( WEEKDAY(B73) ,Lookup!$A$2:$B$8,2,FALSE) -> Friday | E73: Documentation | F73: Follow Auditor regarding GST, Agreement and Finance Advisor | H73: 46234 | I73: 0.84027778 | J73: 46234 | K73: 0.91666667
A74: 74 | B74: 46234 | C74: 0.41666667 | D74: =VLOOKUP( WEEKDAY(B74) ,Lookup!$A$2:$B$8,2,FALSE) -> Friday | E74: Hiring | F74: Talk with Princy, Subhu Lakshmi regarding Medical billing work
A75: 75 | D75: =VLOOKUP( WEEKDAY(B75) ,Lookup!$A$2:$B$8,2,FALSE) -> Saturday | F75: Madurai Event: Women Professional Connect
A76: 76 | B76: 46237 | C76: 0.95833333 | D76: =VLOOKUP( WEEKDAY(B76) ,Lookup!$A$2:$B$8,2,FALSE) -> Monday | F76: Finalise the service page for website
A77: 77 | B77: 46237 | C77: 0.95833333 | D77: =VLOOKUP( WEEKDAY(B77) ,Lookup!$A$2:$B$8,2,FALSE) -> Monday | F77: HDFC Current account opening
A78: 78 | B78: 46237 | C78: 0.95833333 | D78: =VLOOKUP( WEEKDAY(B78) ,Lookup!$A$2:$B$8,2,FALSE) -> Monday | F78: Auditor Kitta pesanum
A79: 79 | B79: 46237 | C79: 0.95833333 | D79: =VLOOKUP( WEEKDAY(B79) ,Lookup!$A$2:$B$8,2,FALSE) -> Monday | F79: ISM Data Technology group create and training
A80: 80 | B80: 46237 | C80: 0.95833333 | D80: =VLOOKUP( WEEKDAY(B80) ,Lookup!$A$2:$B$8,2,FALSE) -> Monday | F80: Tamilpreneur COimbatore networking tomorrow need to check is possible to attend tomorrow
A81: 81 | B81: 46237 | C81: 0.95833333 | D81: =VLOOKUP( WEEKDAY(B81) ,Lookup!$A$2:$B$8,2,FALSE) -> Monday | F81: Digital Change Maker Orientation classs 12clk
A82: 82 | B82: 46237 | C82: 0.95833333 | D82: =VLOOKUP( WEEKDAY(B82) ,Lookup!$A$2:$B$8,2,FALSE) -> Monday | F82: 25+ AI tools Mastery Class Orientation in 9 PM
A83: 83 | B83: 46237 | C83: 0.79166667 | D83: =VLOOKUP( WEEKDAY(B83) ,Lookup!$A$2:$B$8,2,FALSE) -> Monday | F83: DIgital Chage Makers Class 7 Pm Every Monday
A84: 84 | B84: 46238 | C84: 0.95833333 | D84: =VLOOKUP( WEEKDAY(B84) ,Lookup!$A$2:$B$8,2,FALSE) -> Tuesday | F84: Airtel Post paid Sim
A85: 85 | B85: 46238 | C85: 0.95833333 | D85: =VLOOKUP( WEEKDAY(B85) ,Lookup!$A$2:$B$8,2,FALSE) -> Tuesday | F85: Socail Media Page completion
A86: 86 | B86: 46238 | C86: 0.95833333 | D86: =VLOOKUP( WEEKDAY(B86) ,Lookup!$A$2:$B$8,2,FALSE) -> Tuesday | F86: Having one medical billing Id but Manimegalai and Subu Lakshmi both are willing and both have 1 year experience in Medial billing
A87: 87 | B87: 46238 | C87: 0.95833333 | D87: =VLOOKUP( WEEKDAY(B87) ,Lookup!$A$2:$B$8,2,FALSE) -> Tuesday | F87: Need to Complete 2 assignments in Digital video Making, having lot of videos to learn so focusing in video making to create my nichec and video strategics
A88: 88

Sheet Index

Sheet Time Sheet
A1: Date | B1: Name | C1: From Home to Office | D1: CO Work Space Check In | E1: CO Work Space Check Out | F1: From Office to Home | G1: Home Work Start time | H1: Home Work End time
A2: 46224 | B2: Thilaga Subha S | C2: 0.40694444 | D2: 0.42083333 | E2: 0.80694444 | F2: 0.83333333 | G2: 0.86458333 | H2: 0.96875
A3: 46225 | B3: Thilaga Subha S | C3: 0.40625 | D3: 0.42638889 | E3: 0.81597222 | F3: 0.82986111 | G3: 0.86458333 | H3: 0.96527778
A4: 46226 | B4: Thilaga Subha S | C4: NIL | D4: NIL | E4: NIl | F4: Nil | G4: 0.38541667 | H4: 0.95138889
A5: 46227 | B5: Thilaga Subha S | C5: 0.39583333 | D5: 0.47222222 | E5: 0.825 | F5: 0.84375 | G5: 0.91666667 | H5: 0.9375
A6: 46228 | B6: Thilaga Subha S | C6: 0.38194444 | D6: 0.40277778 | E6: 0.70833333 | F6: 0.73611111 | G6: 0.75 | H6: 0.88888889
A7: 46229 | B7: Thilaga Subha S | C7: NIL | D7: NIL | E7: NIL | F7: NIL | G7: 0.39583333 | H7: 0
A8: 46229 | B8: Thilaga Subha S | C8: NIL | D8: NIL | E8: NIL | F8: NIL | G8: 0.57291667 | H8: 0.625
A9: 46229 | B9: Thilaga Subha S | C9: NIL | D9: NIL | E9: NIL | F9: NIL | G9: 0.75 | H9: 0.89583333
A10: 46229 | B10: Thilaga Subha S | C10: NIL | D10: NIL | E10: NIL | F10: NIL | G10: 0.94791667 | H10: 0.59375
A11: 46230 | B11: Thilaga Subha S | C11: 0.92013889 | D11: 0.93472222 | E11: 0.72986111 | F11: 0.73472222 | G11: 0.75694444 | H11: 0.925
A12: 46231 | B12: Thilaga Subha S | C12: 10:20 Pm (ISM Data Technology Tenkasi) | D12: 11:40 (ISM Data technology) | E12: 12:50 PM(ISM Data Technology) | F12: 2:20:00 PM(Reached Home) | G12: 0.70833333 | H12: 0.013888889
A13: 46232 | B13: Thilaga Subha S | C13: 0.40625 | D13: 0.41944444 | E13: 0.83333333 | F13: 0.86458333 | G13: 0.88888889 | H13: 0.99305556
A14: 46233 | B14: Thilaga Subha S | C14: 0.39444444 | D14: 0.48958333 | E14: 0.80555556 | F14: 0.81944444
A15: 46234 | B15: Thilaga Subha S | C15: 0.39236111 | D15: 0.40972222 | E15: 0.77430556 | F15: 0.79166667 | G15: 0.79166667 | H15: 0.89583333
A16: 46235 | B16: Thilaga Subha S | C16: 7:20:00 AM (Madurai Women professional Meet) | F16: 6.50 PM | G16: 0.79166667 | H16: 0.90277778
A17: 46236 | B17: Thilaga Subha S | G17: 0.45138889 | H17: 0.90972222
A18: 46237 | B18: Thilaga Subha S | C18: 0.42708333 | D18: 0.44444444 | E18: 0.77083333 | F18: 0.79166667 | G18: 0.79166667 | H18: 0.95833333
A19: 46238 | B19: Thilaga Subha S | C19: 0.38888889 | D19: 0.41319444 | E19: 0.75 | F19: 0.78472222 | G19: 0.92708333 | H19: 0.95833333
A20: 46239 | B20: Thilaga Subha S | C20: 0.35416667 | D20: 0.37152778

Sheet Lookup
A2: 1 | B2: Sunday
A3: =A2+1 -> 2 | B3: Monday
A4: =A3+1 -> 3 | B4: Tuesday
A5: =A4+1 -> 4 | B5: Wednesday
A6: =A5+1 -> 5 | B6: Thursday
A7: =A6+1 -> 6 | B7: Friday
A8: =A7+1 -> 7 | B8: Saturday
