Workbook

Sheet Version_Control
A1: VERSION CONTROL — ShiftDesk Sprint Tracker & Traceability
A2: File naming: claude_v<NNN>_<proper file name>_YYYYMMDD_HHMI. Companion workbook lineage: v005 (baseline) -> v045 (session 40) -> v046 (session 41, this release). Codebase lineage: v0.11.0 (code phase complete) -> v0.13.x (runtime wiring) -> v0.14.0 (review V001 remediation).
A3: Version | B3: Date/Time | C3: Author | D3: Change Description | E3: Status
A4: v001 | B4: 2026-09-10 23:03 | C4: Claude for Senthil/KP | D4: THIS FILE — Live execution tracker for ShiftDesk (portfolio rank per v004 plan, wave-1; Microsoft Teams App Store / AppSource). Consolidates both 10 Sep build sessions (22:26 v006, 22:54 v007) into: event-level Sprint_Tracker_Log (E001-E016), per-sprint build boards S1-S8, 100-story Traceability_Matrix with evidence, live Sprint_Status_Rollup, RAID, and D7 completion Gate_Checklist. | E4: Released
A5: v002 | B5: 2026-09-10 23:10 | C5: Claude for Senthil/KP | D5: Session 3 logged (E017-E018): live-sweep readiness pack — Teams manifest v1.17 + icons, typed config loader, 12-step scripted verification sweep, 30-min dev tenant guide (sideload path needs no Partner Center, so dev verification can start same-day). Companion workbook at v008. Gate LC-2 advanced to manifest-ready. | E5: Released
A6: v003 | B6: 2026-09-11 08:20 | C6: Claude for Senthil/KP | D6: Session 4 logged (E019-E020): ops parity pack — k6 5x load harness (ST-088), blue/green deploy workflow with approval-gated switch (ST-092), scripted backup/restore drill with RTO/RPO pass bar (ST-090); three stories Backlog -> Drafted; traceability + rollup reflect workbook v009. Gate LC-8 advanced to harness-scripted. | E6: Released
A7: v004 | B7: 2026-09-11 12:51 | C7: Claude for Senthil/KP | D7: Session 5 logged (E021-E022): adversarial cold-review pass 1 — 6 defects fixed with regressions, F-007/F-008 open for Senthil disposition, F-009 evidence-discipline finding closed by building the ST-066 crypto module; REVIEW_PACK.md for external second reviewer. Companion workbook v010 adds Review_Findings sheet. 20 suites / 94 tests at 100%. | E7: Released
A8: v005 | B8: 2026-09-11 20:30 | C8: Claude for Senthil/KP | D8: Session 6 logged (E023-E025): cold-review pass 2 complete (F-010..F-013 fixed with regressions, OBS-SD1 for disposition; 10 defects total across passes — coverage proves execution, not correctness) + completion wave taking the last 5 backlog stories to sandbox ceiling. SHIFTDESK CODE PHASE COMPLETE — backlog zero, fourth product (after TeleField, VoiceBridge, FlowCast). Companion workbook v011; codebase v0.11.0 at 22 suites / 109 tests, 100% zero pragmas. | E8: Released
A9: v006 | B9: 2026-09-13 09:52 | C9: Claude for Senthil/KP | D9: Session 7 logged (E026-E027): external verification sweep against live Microsoft documentation plus artifact-gap audit — VER-SD01/02 store-blocking, VER-SD08 live-blocking tab handshake gap, VER-SD03/04/06 corrections (incl. reopening LC-5 which had been marked Done on an overstated permission model), VER-SD05 verified-correct pinned, VER-SD07 naming noted. Companion workbook v012; 24 suites / 120 tests at 100% zero pragmas; story counts unchanged (correctness release). | E9: Released
A10: v007 | B10: 2026-09-13 10:01 | C10: Claude for Senthil/KP | D10: Session 8 logged (E028-E029): artifact-gap audit round 2 — GAP-SD1 (three declared static tabs with no page behind them, live-blocking) closed by building the web/ tab layer; GAP-SD2 (three advertised bot commands with no handler) closed by botRouter; GAP-SD3 package hygiene; GAP-SD4 ST-094 partially unblocked by a headless-verified 1366x768 demo capture surface. Companion workbook v013; 26 suites / 145 tests at 100% across src/ and web/. | E10: Released
A11: v008 | B11: 2026-09-13 10:24 | C11: Claude for Senthil/KP | D11: Session 9 logged (E030-E031): cold-review pass 3 over the session 5-8 code that had never been reviewed — 6 defects fixed with pinned regressions (F-014..F-019) and OBS-SD2 closed. Headline F-016: the tab API validated the SSO token then never sent it. Companion workbook v014; 27 suites / 151 tests at 100% zero pragmas; story counts unchanged. | E11: Released
A12: v009 | B12: 2026-09-13 10:37 | C12: Claude for Senthil/KP | D12: Session 10 logged (E032-E033): artifact-gap audit round 3 — GAP-SD5 live-blocking (no HTTP server; three of five tab paths and the bot messaging endpoint unserved) closed with src/server.ts + src/bootstrap.ts and a client-vs-server parity test; OBS-SD3 closed. Companion workbook v015; 29 suites / 163 tests at 100% zero pragmas; story counts unchanged. | E12: Released
A13: v010 | B13: 2026-09-13 10:42 | C13: Claude for Senthil/KP | D13: Session 11 logged (E034-E035): verification sweep 2 over the bot transport seam — VER-SD09/SD10 live-blocking (Connector JWT + Activity payload; ack-then-send rather than replying in the HTTP body), VER-SD11 identity from the activity, VER-SD12 conversationUpdate welcome + ack/dedupe for non-message activities. Both live-blockers were introduced by session 10 and caught one session later. Companion workbook v016; 30 suites / 174 tests at 100% zero pragmas; story counts unchanged. | E13: Released
A14: v011 | B14: 2026-09-13 10:57 | C14: Claude for Senthil/KP | D14: Session 12 logged (E036-E037): verification sweep 3 over the tab SSO seam — VER-SD13 live-blocking (the tab was sending a hardcoded placeholder token while the manifest declared SSO) closed with the real acquisition and validation flow; VER-SD14 missing Expose-an-API setup step documented. Companion workbook v017; 31 suites / 181 tests at 100% zero pragmas; story counts unchanged. | E14: Released
... A43: v040 | B43: 2026-09-20 16:40 | C43: Claude for Senthil/KP | D43: Session 41 logged (E084-E093): independent review V001 actioned in full. All 20 P-series findings dispositioned and all three CRITICALs closed in code (P-001 Entra JWKS verification, P-002 Connector JWT verification, P-003 durability wired with a real Postgres tier). The review's 47-story S13-S20 plan is admitted to the tracker in full — eight new build boards, Traceability rows SD201-SD247, rollup extended to 147 stories and a by-status block with a reconciliation check. 36 stories built this session, 11 stay at "To do — Senthil" under new decision D-SD8 with their artefacts prepared and their points intact. New decisions D-SD7 (three-tier quality gate), D-SD8 (human-gated stories), D-SD9 (production is the unset default). New RAID R-S17..R-S21 and A-S4; R-S2 rewritten for the free first-party overlap. New gates LC-11 Fulfillment, LC-12 residency/legal, LC-13 durability. Companion workbook v046; codebase v0.14.0 at 68 suites / 552 tests, 100% statements-branches-functions-lines with zero pragmas, plus 9/9 real-Postgres integration tests and a passing backup/restore drill. Own goals F-071..F-074 recorded, including two defects in the release gate itself (F-073 the build never emitted the tab page; F-074 the wiring job named a test file that does not exist). | E43: Released
A44: v041 | D44: PLANNED: opens on whichever comes first — the cold review of this session's S13-S20 code (R-S21), or the first real sweep report from the dev tenant. | E44: Planned

Sheet Sprint_Tracker_Log
A1: SPRINT TRACKER LOG — every execution event, newest last
A2: ID | B2: Date/Time | C2: Sprint | D2: What happened | E2: Refs | F2: State changes | G2: Blockers | H2: Next
A3: E001 | B3: 2026-09-10 22:26 | C3: — | D3: BUILD OPENED — Senthil instruction 22:26: continue work as per sprint from workbook v005; sprint tracker + traceability + development + 100% automation testing (D13). Eighth concurrent build under D15-pending. | E3: D13,D15,v005 | F3: ShiftDesk S1 opened | G3: None | H3: E002
A4: E002 | B4: 2026-09-10 22:26 | C4: S1 | D4: S1 FOUNDATION BUILT (TypeScript/Node + React per v005 ReadMe stack): install/uninstall/reinstall lifecycle with 30-day retention window, token rotation survival, source attribution; PlatformGateway (backoff + circuit breaker) as the mock/live seam. | E4: ST-052,ST-053*,ST-055,ST-056 | F4: 3 S1 stories Done (8 pts); ST-051 code-complete pending live | G4: Live Teams dev-store install = Senthil (Partner Center) | H4: E003
A5: E003 | B5: 2026-09-10 22:26 | C5: S2 | D5: S2 HANDOVER PT 1: defaults setup, happy path with acknowledgement flow, custom rules, error/retry surfaces, role matrix (owner/admin/member) enforced server-side. | E5: ST-001..004,ST-053,ST-054 | F5: 6 S2 stories Done (29 pts) | G5: None | H5: E004
A6: E004 | B6: 2026-09-10 22:26 | C6: S3 | D6: S3 HANDOVER PT 2 + APPROVALS START: metrics/trends, permissions+audit, pause without data loss, CSV import, per-type-mute notifications; approvals policy skeleton; D13 coverage gate story delivered at 100% (supersedes >=70% wording). | E6: ST-006..014,ST-085 | F6: 10 S3 stories Done (44 pts); ST-005 pending live surface | G6: None | H6: E005
A7: E005 | B7: 2026-09-10 22:26 | C7: S4 | D7: S4 APPROVALS COMPLETE: auto-approve threshold, blocked categories, needs-review routing, preview/test mode; funnel events + error tracking with release tags; E2E smoke suite through API dispatcher. | E7: ST-016..020,ST-071,ST-072,ST-086 | F7: 8 S4 stories Done (29 pts); ST-015 pending live | G7: None | H7: E006
A8: E006 | B8: 2026-09-10 22:26 | C8: S5 | D8: S5 CHECKLISTS + ALPHA HARDENING: create/tick/progress/CSV export; first-run checklist to aha (<1 day design), empty states on every screen. | E8: ST-021..024,ST-026..030,ST-078,ST-079 | F8: 11 S5 stories Done (42 pts); ST-025 pending live | G8: Live dogfooding needs installed tenant | H8: E007
A9: E007 | B9: 2026-09-10 22:26 | C9: S6 | D9: S6 BILLING + KUDOS: 14-day no-card trial with countdown banner, mid-cycle proration, marketplace-vs-Stripe rail decision point (mocked transactable API), kudos + leaderboard + self-kudos block. | E9: ST-031..034,ST-036..040,ST-057,ST-058 | F9: 11 S6 stories Done (48 pts); ST-035,ST-059 pending live | G9: Marketplace billing API needs Partner Center offer | H9: E008
A10: E008 | B10: 2026-09-10 22:26 | C10: S7 | D10: S7 BILLING HARDENING + COMPLIANCE DOC: 7-day grace -> 3 dunning emails -> read-only, 80/100% limit prompts, GST/VAT invoices, save-offer cancellation + exit survey; least-privilege scope map doc (CI-tested vs SCOPE_MAP). | E10: ST-060..064 | F10: 5 S7 stories Done (15 pts) | G10: Design partners = human-dependent (S7 exit) | H10: E009
A11: E009 | B11: 2026-09-10 22:26 | C11: S8 | D11: S8 MANAGER DASHBOARD + PLATFORM QUALITY: KPI aggregation, trends, open items; retention policy doc, audit log, rate-limit backoff + circuit breaker with graceful-degrade user comms, latency budgets (api 500ms / bot 800ms / ui 2s), heatmap, health scores, configurable alerts, weekly metrics email, CSV export. | E11: ST-041..044,ST-046..050,ST-065..067,ST-069,ST-070,ST-073..077,ST-087,ST-091 | F11: 18 S8 stories Done (69 pts); ST-045,ST-066 pending live | G11: Zero-downtime deploy (ST-092) needs live infra | H11: E010
A12: E010 | B12: 2026-09-10 22:26 | C12: — | D12: D13 TEST GATE MET (SESSION 1) — 15 Jest suites / 67 tests; 100% statements, branches, functions, lines enforced via jest.config.js coverageThreshold; TypeScript strict, tsc --noEmit clean; GitHub Actions CI. | E12: D13 | F12: Evidence in Traceability col K | G12: None | H12: E011
A13: E011 | B13: 2026-09-10 22:26 | C13: — | D13: WORKBOOK v006 RELEASED (22:26) — Full_Backlog statuses (75 Done / 8 pending live / 1 in progress / 16 backlog), Sprint_Tracker_Log + Traceability_Matrix sheets added, Sprint_Board live COUNTIFS verified, recalc 169 formulas 0 errors. Source zip delivered. | E13: v006 | F13: Session 1 closed | G13: Senthil-gated items listed E016 | H13: E012
... A19: E017 | B19: 2026-09-10 23:10 | C19: S1/S9 | D19: LIVE-SWEEP READINESS BUILT — teams-app/manifest.json (v1.17: bot with command list, 3 static tabs, permissions, valid-domain placeholders) + generated color/outline icons, sideload-ready zip recipe; src/config.ts typed env loader (fail-fast, redacted print); src/liveSweep.ts 12-step orchestrator mapped to every pending-live story; content/dev-tenant-setup-guide.md 30-min path. | E19: ST-051,ST-005,ST-015,ST-025,ST-052..055 | F19: LC-2 -> manifest-ready; S1-07 reduced to wiring-only | G19: Dev tenant + Entra app registration = Senthil | H19: E018
A20: E018
A21: E019 | B21: 2026-09-11 08:20 | C21: S9/S11 | D21: OPS PARITY PACK — load/k6-load-sweep.js (ramp 0->500 VUs = 5x expected, thresholds mirror perf.ts budgets, traffic mix 50/20/15/10/5), .github/workflows/deploy.yml blue/green (gate -> green -> smoke -> approval-gated switch, blue warm 24h), ops/backup-restore-drill.md (sentinel-row method, RTO<60m/RPO<15m, sweep 12/12 pass bar). | E21: ST-088,ST-090,ST-092 | F21: 3 stories Backlog -> Drafted; backlog now 5 (all external) | G21: Execution live-gated (staging infra + Postgres) | H21: E020
A22: E020 | B22: 2026-09-11 08:20 | C22: — | D22: D13 GATE RE-VERIFIED — 18 suites / 85 tests, 100% x4 unchanged (no src changes; ops artifacts only). Workbook v009 + tracker v003 released. ShiftDesk position: 75 Done / 9 pending live / 2 in progress / 9 drafted / 5 backlog; every remaining item is Senthil-gated or live-gated per Action Board v002 sitting order (dev tenant = same-day win). | E22: D13,v009 | F22: Tracker at v003 | G22: Dev tenant + Entra registration = 30-min same-day win | H22: v004
A23: E021 | B23: 2026-09-11 12:51 | C23: S9 | D23: COLD-REVIEW PASS 1 — six defects found in own code and FIXED with pinned regressions: F-001 billing had no payment-recovery path (grace/read-only was terminal), F-002 duplicate install webhook overwrote tenant data, F-003 unbounded error/notification ledgers -> FIFO 10k, F-004 backoff computed but never applied -> injectable sleeper wired, F-005 negative/zero amounts auto-approved -> AMOUNT_INVALID, F-006 checklist CSV export unquoted -> RFC-4180. Plus F-009 corrective: ST-066 evidence had overstated — src/crypto.ts (AES-256-GCM, tamper rejection, SecretsVault redacted dump + rotation) now actually built. | E23: F-001..F-006,F-009,ST-066 | F23: Review_Findings sheet added to workbook v010; ST-066 evidence now truthful | G23: F-007 (breaker half-open) + F-008 (audit persistence) = Senthil dispositions | H23: E022
A24: E022 | B24: 2026-09-11 12:51 | C24: — | D24: D13 GATE HELD + REVIEW_PACK.md issued for external second reviewer (ST-097 stays In progress — same-AI review not independent; pack lists claims to verify + adversarial probes incl. the naive CSV importer flagged for pass 2). 20 suites / 94 tests, 100% x4, zero pragmas. Workbook v010 + tracker v004 released. | E24: ST-097,v010 | F24: Tracker at v004 | G24: External reviewer + dispositions + dev tenant = Senthil | H24: v005
A25: E023 | B25: 2026-09-11 20:30 | C25: S9 | D25: COLD-REVIEW PASS 2 (modules pass 1 skipped) — F-010 importer was naive comma-split, RFC-4180 parser wired (closes RAID R-S7); F-011 alert ledger unbounded + duplicate spam -> dedupe + cap 1000; F-012 latency samples unbounded -> rolling 10k window; F-013 trial banner shown to paying/grace accounts -> trial-state-only. OBS-SD1 (pause blocks creates but not completes) logged for disposition. Review COMPLETE across all modules: 10 defects total found in code shipped at 100% coverage — F-V14 lesson holds here too. | E25: F-010..F-013,OBS-SD1,R-S7 | F25: R-S7 closed; Review_Findings sheet extended | G25: OBS-SD1 = Senthil disposition | H25: E024
A26: E024 | B26: 2026-09-11 20:30 | C26: S7-S12 | D26: COMPLETION WAVE (sibling-validated) — ST-081 built-in chat + 4-business-hour SLA engine (business-minutes clock, breach detection, ranked queue; vendor decision now OPTIONAL, D-SD4 flagged); ST-100 10-slot partner tracker with stale-nudge + honest exit math (G-02 counts only paying strangers); ST-099 SEO iteration engine (thin-data floor 100 impressions); ST-080 ranked help search + manifest gate over the 15 articles; ST-068 SECURITY_EVIDENCE.md sandbox half; ST-094 ASSET_PLAN.md 5-shot list; ST-095 pricing drift gate binding content to billing.ts PLANS. | E26: ST-068,080,081,094,095,099,100 | F26: 5 backlog stories -> ceiling; BACKLOG ZERO | G26: Pen-test vendor, asset capture, partner outreach = Senthil | H26: E025
A27: E025 | B27: 2026-09-11 20:30 | C27: — | D27: SHIFTDESK CODE PHASE COMPLETE — fourth product to backlog zero (TeleField 12:47, VoiceBridge 13:32, FlowCast 15:27, ShiftDesk 20:30). Position: 75 Done / 13 code-complete pending live / 3 in progress / 9 drafted / 0 backlog. Codebase v0.11.0: 22 suites / 109 tests, 100% x4, zero pragmas. No further code sprints planned. Remaining chain all Senthil/live: dev tenant + Entra (30-min, flips 9+ stories via 12-step sweep) -> Partner Center + attestation -> dispositions (F-007/F-008/OBS-SD1) -> external reviewer (REVIEW_PACK.md) -> pen-test vendor -> copy A/B + asset capture -> launch runbook + partner outreach; D15 + D-SD1..4 ratifications open. | E27: D15,v011 | F27: Tracker at v005; v006 opens on live evidence | G27: All remaining = Senthil | H27: v006
A28: E026 | B28: 2026-09-13 09:52 | C28: S9 | D28: EXTERNAL VERIFICATION SWEEP (ShiftDesk first) — checked our assumptions against live Microsoft docs. VER-SD01 STORE-BLOCKING: asset plan said 1920x1080, real spec is 1366x768 / <=1,024KB / min 3 max 5 / mobile shot mandatory / video as YouTube-Vimeo URL. VER-SD02 STORE-BLOCKING: manifest schema v1.17, current is v1.19 (1.18 never existed) and submission requires the latest. VER-SD03: deprecated top-level permissions block removed. VER-SD04: permission model corrected from org-wide Graph .All scopes to resource-specific consent (Send/Read.Group + TeamMember.Read.Group) — and the manifest had NO RSC block, so the bot could not have posted without @mention; gate LC-5 had been marked Done on that overstated doc and is now reopened-and-corrected. VER-SD06: outline icon re-cropped edge-to-edge. VER-SD05 verified-correct (botId/webApplicationInfo match, 192x192 colour icon, 3% fee) and pinned so it cannot drift. VER-SD07: AppSource now presented as Microsoft Marketplace — GTM copy note only. | E28: VER-SD01..07,ST-064,ST-094,LC-5 | F28: Review_Findings extended in workbook v012; ASSET_PLAN + scope doc rewritten | G28: Live consent screen + asset capture still need the dev tenant | H28: E027
A29: E027 | B29: 2026-09-13 09:52 | C29: S9 | D29: ARTIFACT-GAP AUDIT — VER-SD08 LIVE-BLOCKING: the manifest declared three static tabs but nothing in the codebase ever performed the TeamsJS handshake; a contentUrl page that never calls app.initialize()/notifySuccess renders a blank error-less tab in Teams. Invisible to 109 passing tests — same class as the sibling SDK gaps. Built src/teamsClient.ts boundary (initialize, context validation, theme propagation, notifySuccess/notifyFailure, explicit user-facing error when the script is absent) with 5 tests over every path; live sweep extended 12 -> 14 steps (RSC consent + tab handshake) and the dev-tenant guide gains the bootstrap step. 24 suites / 120 tests at 100% zero pragmas; story counts deliberately unchanged — correctness release, no new stories. | E29: VER-SD08,ST-005/015/025/035/045 | F29: Tracker at v006 | G29: Dev tenant remains the single highest-leverage unlock | H29: v007
A30: E028 | B30: 2026-09-13 10:01 | C30: S2-S5 | D30: GAP-SD1 LIVE-BLOCKING CLOSED — the manifest had declared three static tabs since session 3 with no page behind them; session 7 built the TeamsJS boundary but not the tab itself, so installing would have shown three broken tabs. Built web/: TabShell (bootstrap -> entity routing -> the real screens, with loading/error phases), typed TabApi over an injected fetcher (unauthenticated / 403 / outage each mapped to a distinct human message), entry.tsx mount reading ?entity=, index.html loading TeamsJS BEFORE tab.js, esbuild build script emitting web-dist/. 20 new tests including unmount-while-in-flight on both success and failure paths. GAP-SD3: bundles moved out of the store package; contents now asserted as exactly manifest + two icons. | E30: GAP-SD1,GAP-SD3,ST-005/015/025/035/045 | F30: Five surface stories now full-stack — only in-client render pending | G30: Live tenant still required to prove in-client render (R-S8) | H30: E029
A31: E029 | B31: 2026-09-13 10:01 | C31: S9 | D31: GAP-SD2 CLOSED — the manifest advertised /handover, /approve and /checklist in its commandLists, but no code parsed or handled a bot command; every advertised command would have returned nothing. Built src/botRouter.ts over the existing dispatcher: @mention-chip stripping, slash and case normalisation, handover/ack/approve/checklist/kudos/help, explicit usage text for all ten malformed forms, and distinct replies for permission denial vs validation failure. GAP-SD4: web-dist/demo.html capture surface (fixed 1366x768, canned data, verified rendering headless) makes listing shots 1/3/4 draftable BEFORE the tenant exists — ST-094 Drafted -> In progress; finals still come from the live client since the store requires accurate UI. 26 suites / 145 tests at 100% across src/ and web/, zero pragmas. | E31: GAP-SD2,GAP-SD4,ST-094 | F31: Tracker at v007 | G31: Dev tenant remains the single unlock | H31: v008
A32: E030 | B32: 2026-09-13 10:24 | C32: S9 | D32: COLD-REVIEW PASS 3 — the code written in sessions 5-8 (web tab layer, bot router, chat/partners/SEO/help modules, config, crypto) had never been adversarially reviewed; the portfolio lesson says new code needs its own pass. Six defects found and fixed with pinned regressions. F-016 (High): TabApi read the SSO token, checked it was non-null, and never sent it — every tab API call would have been unauthenticated in production; the suite passed because the fetcher was injected and no test ever asserted on headers, the same "computed but never applied" class as F-004. F-014: Infinity and 1e999 passed the "amount > 0" guard added in pass 1. F-015: the checklist parser filtered empty segments before assigning the title, so a missing title silently promoted task 1 — a wrong artifact rather than an error. F-017: bootstrap was not idempotent. F-018: internal codes like SELF_KUDOS_NOT_ALLOWED were shown verbatim to frontline staff. F-019: SHIFTDESK_TRIAL_DAYS was validated then ignored by a hard-coded 14. | E32: F-014..F-019 | F32: Review_Findings extended in workbook v014 | G32: None — all fixed in-session | H32: E031
... A85: E083 | B85: 2026-09-13 23:14 | C85: S1/S8 | D85: RUNTIME WIRING AUDIT 3 — the pattern says look at the newest wiring first, so I looked at my own from last session. F-068: the install-count seeding computed the set of existing tenants, logged the number, and never told the observer, which is constructed inside makeServer and was unreachable from the entry point. F-067 was reported as fixed and was not — the exact pattern I spent that session documenting, committed while documenting it. makeServer now returns a seed function that calls the observer it owns. F-069: nothing ever populated the role directory; even with the Graph runtime supplied by F-066, no code called setInstaller or warm, so the installer was never owner and team owners were never admins — the directory could be built and stayed empty, which is why F-062 and F-066 together still did not produce a working admin. The install hook now registers the installer and team and warms the cache, logging whether it loaded, handling a personal-scope install, and reporting a Graph outage rather than leaving an empty directory. F-070: every error was tagged with a hardcoded release "dev", so ST-072 and the runbook rollback signal could not distinguish builds; the release now comes from configuration and is named in the runbook as a pre-launch step. OBS-SD11: the encrypted store did not forward listAll, so an encrypted deployment would have lost boot-time seeding — listAll is now part of the repository contract rather than optional, so no decorator can drop it. | E85: F-068,F-069,F-070,OBS-SD11 | F85: Three consecutive sessions have found the previous session's wiring incomplete | G85: Dev tenant + D-SD5/D-SD6 + encryption choice | H85: v040
A87: * ST-053 (re-install restore) built and tested in S1 foundation though scheduled S2 in the backlog — recorded once, in its backlog sprint, in the rollup.
A88: E084 | B88: 2026-09-20 11:02 | C88: — | D88: SESSION 41 OPENED — Senthil instruction 11:02: go through the independent review document, update code + sprint tracker + traceability, produce next-version zip and workbooks. "do all .. enterprise grade .. dont shrink the scope .. keep all tasks in sprint tracker". Review received as ShiftDesk_Review_V001: 20 P-series findings (3 CRITICAL), 8 D-series decisions, an 8-sprint 47-story plan (266 pts) and an enterprise scorecard rating identity, durability and compliance at Absent. | E88: Review V001, v045, v039 | F88: S13-S20 opened; 47 SD stories admitted to the tracker | G88: None | H88: E085
A89: E085 | B89: 2026-09-20 12:10 | C89: S13 | D89: S13 TRUST BOUNDARIES BUILT — P-001 and P-002, two of the three CRITICALs, closed: JWKS-backed Entra verification (metadata discovery, kid selection, one bounded refresh per unknown kid, RS256 only) and Connector JWT verification with serviceUrl binding. Dev bypass fenced by SHIFTDESK_ENV with production as the unset default (D-SD9). Body cap, per-tenant and per-IP token buckets, per-surface security headers. F-007 closed with the half-open breaker probe. | E89: SD201-SD207, P-001, P-002, P-007, P-008, F-007 | F89: 7 stories built; 38 pts | G89: None | H89: E086
A90: E086 | B90: 2026-09-20 13:05 | C90: S14 | D90: S14 DURABILITY BUILT — P-003, the third CRITICAL, closed. pg moved into dependencies and wired in the entry point; production refuses an in-memory store and refuses a DATABASE_URL with no client; migration runner under an advisory lock with checksum refusal. A real Postgres 16 was provisioned in-session (port 55432), so the integration tier and the backup/restore drill are results: 9/9 integration tests green, drill PASS at RPO 0s / RTO 0s against the 15 min / 60 min bar. OBS-SD4 closed — the SQL fake is no longer the only store under test. | E90: SD208-SD215, P-003, P-004, P-005, P-020, OBS-SD4 | F90: 8 stories built; 36 pts | G90: None | H90: E087
A91: E087 | B91: 2026-09-20 13:50 | C91: S15 | D91: S15 SCALE BUILT — whole-module snapshots replaced by per-record persistence with node-scoped ids and a one-time migration from legacy snapshot rows; windowed hydration proven at 100k records inside the 500ms API p95 budget on real Postgres; audit trail paginated by cursor and streamed; F-008 closed by an enforcer that sweeps the published retention numbers by kind and age; key rotation with an enc:v2:<keyId> envelope and a re-seal sweep, closing OBS-SD8. OBS-SD9 closes with the snapshots. SD219/SD220 remain owed: no staging, no number. | E91: SD216-SD221, P-006, F-008, OBS-SD8, OBS-SD9 | F91: 5 built, 2 owed to Senthil; 34 pts | G91: Staging infrastructure for the k6 sweep (LC-8) | H91: E088
A92: E088 | B92: 2026-09-20 14:25 | C92: S16 | D92: S16 TEAMS-NATIVE BUILT — Adaptive Cards 1.5 for handover, acknowledgement, approval decision and checklist tick with Action.Execute and invoke handling; conversation references persisted so the product can speak first (the central promise the review found unimplemented), with 403-uninstalled forgetting the conversation and 429/5xx retrying; configurable channel tab with a config page; manifest-to-router command parity in both directions; en-GB and es-ES catalogues with a missing key throwing rather than rendering blank. F-072 found here: two strings were frozen at import so setLocale had no effect. | E92: SD222-SD227, P-009, P-010, P-011, P-012, F-072 | F92: 3 done, 3 pending live, 1 owed (mobile pass) | G92: Live Teams clients for card rendering and the mobile screenshot (VER-SD01) | H92: E089
A93: E089 | B93: 2026-09-20 15:00 | C93: S17 | D93: S17 GOVERNANCE BUILT — P-013 closed as far as code can: four customer regions with a boot-time residency assertion that throws RESIDENCY_MISMATCH before serving; DPA, subprocessor register, retention schedule and residency statement generated from the same constants the product enforces, bound by test so page and code cannot drift; KMS key custody via Key Vault and managed identity with production refusing a plain-env key; incident response runbook with the severity ladder bound to the alert rules. Export and delete surfaced in Settings, audited, streamed. | E93: SD228-SD233, P-013, P-014, F-029 | F93: 3 done, 2 pending live, 1 drafted, 1 owed | G93: Two live tenants for consent; a real vault; the tabletop | H93: E090
A94: E090 | B94: 2026-09-20 15:20 | C94: S18 | D94: S18 ASSURANCE — the evidence half only, honestly. M365 certification control map and SOC 2 readiness map in code, each control naming an evidence path that a test proves exists — which is how three SOC 2 process controls with no executable evidence were caught and bound to real suites rather than waved through. Per-screen manual accessibility script written so the audit is a checklist, not an exploration. Pen test, Publisher Attestation, SOC 2 engagement and the manual a11y pass stay at "To do — Senthil" per D-SD8: four of five items in this sprint cannot be done from a sandbox. | E94: SD234-SD238, LC-3, LC-7, R-S6, D-05 | F94: 1 done, 4 owed to Senthil | G94: Vendor engagement, Partner Center, audit budget, a screen reader | H94: E091
A95: E091 | B95: 2026-09-20 15:45 | C95: S19 | D95: S19 COMMERCIAL AND OBSERVABILITY BUILT — Marketplace SaaS Fulfillment API v2: token resolution, activate, the five webhook actions idempotent on activityId, seat reconciliation with a drift alert, Entra and shared-secret webhook authentication. Sentry-envelope and PostHog-capture sinks with a pinned PII scrubber and tenant hashing. 99.5% SLO stated as 216 minutes a month with eleven alert rules, each carrying the finding that justifies it. Deploy workflow: real provider CLI calls, migrations before the swap, green smoke, rollback job — the echo placeholders P-020 named are gone. | E95: SD239-SD243, P-019, P-020, F-070, D-05, LC-6 | F95: 2 done, 2 pending live, 1 owed | G95: A live transactable offer; a real sink DSN; the subscription for one rollback | H95: E092
A96: E092 | B96: 2026-09-20 16:05 | C96: S20 | D96: S20 DEMAND — the modelling and the copy, not the answer. Financial model repaired: cash in, cash out, runway, per-site pricing beside per-seat, and either a breakeven month or the funding requirement stated outright (P-018/D-01). Positioning rewritten explicitly against free first-party Approvals and Planner rather than around them (D-04), and R-S2 in the RAID rewritten to say the overlap is the commercial risk. The 15 discovery interviews and the 5 paid pilots stay owed: they are the programme gate, and D13 parked interviews portfolio-wide. | E96: SD244-SD247, P-018, D-01, D-04, R4, G-02 | F96: 2 done/drafted, 2 owed to Senthil | G96: Senthil: 15 interviews, 5 signed pilots | H96: E093
A97: E093 | B97: 2026-09-20 16:40 | C97: — | D97: D-SD7 THREE-TIER GATE MET AND RELEASE CLOSED — tier 1: 68 unit suites / 555 tests, 100% statements, branches, functions and lines with zero pragmas; tier 2: 9/9 real-Postgres integration tests; tier 3: the production-seam assertion passes and the same check refuses to boot a mis-wired deployment. tsc --noEmit clean, bundles build. Four own goals recorded rather than hidden: F-071 (the pg driver parses JSONB while the repository parsed text), F-072 (frozen i18n strings), and — found by rerunning the whole suite on a cleaned tree at release time — F-073 (the build never copied the tab page into the build directory, so a clean checkout serves 404 at /tab/, and CI hid it by testing without building) and F-074 (the tier-3 wiring job named a test file that has never existed, so the gate D-SD7 rests on was exiting "no tests found"). Source zip v046 (227 files), tracker v040, workbook v046. | E97: D13, D-SD7, F-071..F-074, v046, v040 | F97: Session 41 closed; 47 SD stories on the tracker, 36 built, 11 owed | G97: The 11 D-SD8 items are Senthil-gated | H97: —

Sheet Decisions
A1: DECISIONS (tracker scope)
A2: ID | B2: Decision | C2: Rationale | D2: Decided by | E2: Status
A3: D13 | B3: (Portfolio-wide) Discovery interviews parked; development proceeds with 100% automation test coverage on all code (supersedes >=70% gate in ST-085 wording). | C3: Senthil 10 Sep 20:45; applied to ShiftDesk per 22:26 continue instruction. | D3: Senthil | E3: LOCKED
A4: D15 | B4: ShiftDesk build opened 10 Sep 22:26 as the eighth concurrent build while RevRescue rank-1 gate unmet. Sequencing mode — hold-serial vs formal-parallel — pending. | C4: Consolidated in portfolio action board (23:03 file); every build carries the same flag. | D4: Senthil (mode ratification pending) | E4: OPEN — pick (a) or (b)
A5: D-SD1 | B5: Stack = TypeScript/Node + React per v005 ReadMe stack assumption; platform transport (Bot Framework/Graph, marketplace billing API) mocked at the PlatformGateway seam. | C5: Sandbox has no Microsoft credentials; seam keeps live swap wiring-only. Matches accepted precedent on the other seven builds. | D5: Claude — flagged | E5: OPEN for ratification
A6: D-SD2 | B6: Status vocabulary: Done / Code-complete pending live / In progress / Drafted / Backlog. Rollup "Done" counts Done only — pending-live is never claimed as Done. | C6: Honesty bar carried from FlowCast/TeleField trackers. | D6: Claude — flagged | E6: OPEN for ratification
A7: D-SD3 | B7: Checklist creation set to admin-level permission (module.configure), not member. | C7: Surfaced by E2E permission test during S5; consistent with ops-director/IT-admin personas in Product_Spec. | D7: Claude — flagged | E7: OPEN for ratification
A8: D-SD4 | B8: Built-in chat + 4-business-hour SLA engine satisfies ST-081 as shipped; third-party chat vendor becomes OPTIONAL (adopt only if preferred at launch). | C8: Matches OnCall/FlowCast precedent; removes a vendor decision from the critical path. | D8: Claude — flagged | E8: OPEN for ratification
A9: D-SD5 | B9: ChannelMessage.Send.Group dropped from the requested RSC scopes: bot replies use the Bot Connector, not Graph, so the scope had no consumer. | C9: Fewer permissions on the consent screen, cleaner store review, and the scope can return with any future proactive-Graph feature that actually needs it. | D9: Claude — flagged | E9: OPEN for ratification
A10: D-SD6 | B10: settings.roles removed from the permission matrix: roles are derived from Teams team ownership (src/graphMembers.ts) and ShiftDesk assigns none, so the permission guarded no operation. | C10: An unenforced permission misleads anyone reading the Settings screen or the security documentation. It returns if in-product role assignment is ever built. | D10: Claude — flagged | E10: OPEN for ratification
A11: D-SD7 | B11: Quality is gated in three tiers, not one: (1) 100% unit coverage on the domain, (2) a real-Postgres integration tier, (3) a production-seam wiring assertion that also runs at boot. A release is not green until all three are. | C11: The review's P-017 said it plainly: 371 tests at 100% coverage coexisted with no identity verification, no durability and no wiring — coverage measured execution of the code that existed, not the existence of the code that mattered. Tier 2 catches what a fake store cannot (F-071 was found the hour it was added); tier 3 catches a module that is built, tested and never constructed (the F-036/F-062 class, five times over). | D11: Claude — flagged | E11: OPEN for ratification
A12: D-SD8 | B12: Eleven of the 47 review stories are irreducibly human or live-gated (SD219, SD220, SD226, SD228, SD234, SD235, SD237, SD238, SD240, SD244, SD247). They stay on the tracker at "To do — Senthil" with their artefacts prepared, and are never restated as Done, Drafted or pending-live. | C12: Scope was not shrunk: every one keeps its points, its acceptance criterion and its row in the rollup, so the denominator tells the truth. What Claude can do for them — harness, script, scope pack, interview instrument, evidence map — is built; what needs a Partner Center account, a phone, a vendor, a budget or a customer is named as owed rather than absorbed. | D12: Claude — flagged | E12: OPEN for ratification
A13: D-SD9 | B13: SHIFTDESK_ENV unset now means production, not dev. Any non-production implementation constructed outside dev makes the process refuse to serve. | C13: The old default failed open: a deployment that forgot one environment variable ran with the dev token bypass, the in-memory store and a plain-env key, and looked healthy doing it. Nine test suites had to be corrected to the new default, which is itself the evidence that the old one was load-bearing. | D13: Claude — flagged | E13: OPEN for ratification

Sheet S1_Build_Board
A1: S1 BUILD BOARD — Foundation (2 wks) — exit: app installs cleanly in dev store/org; telemetry firing
A2: Foundation infra + E1 stories. Executed 10 Sep 2026 22:26 (session 1, workbook v006).
A3: ID | B3: Item | C3: Story ref | D3: Points | E3: Owner | F3: Status | G3: Notes / Evidence
A4: S1-01 | B4: Repo scaffold + CI with 100% coverage gate (D13) | C4: — | D4: 2 | E4: Claude | F4: Done | G4: jest coverageThreshold 100x4; .github/workflows/ci.yml; tsc strict. E002/E010
A5: S1-02 | B5: Install -> welcome state logic + timing telemetry | C5: ST-051 | D5: 5 | E5: Claude | F5: Code-complete pending live | G5: src/install.ts; live dev-store install needed for <2 min evidence. E002
A6: S1-03 | B6: Uninstall webhook: token wipe + 30-day deletion schedule + purge sweep | C6: ST-052 | D6: 3 | E6: Claude | F6: Done | G6: src/install.ts uninstallWebhook/purgeExpired — tests incl. expiry edges. E002
A7: S1-04 | B7: Rotation-safe token refresh | C7: ST-055 | D7: 3 | E7: Claude | F7: Done | G7: src/platformGateway.ts TokenStore — stale/current paths tested. E002
A8: S1-05 | B8: Install telemetry source attribution (listing/search/referral) | C8: ST-056 | D8: 2 | E8: Claude | F8: Done | G8: src/install.ts telemetry events. E002
A9: S1-06 | B9: Rate-limit backoff + circuit breaker seam (mock/live boundary) | C9: ST-070 base | D9: 2 | E9: Claude | F9: Done | G9: src/platformGateway.ts — retry, exhaustion, breaker, reset all tested. E002
A10: S1-07 | B10: Install cleanly in REAL Teams dev tenant (Partner Center + manifest upload) | C10: ST-051 live | D10: 3 | E10: Senthil + Claude | F10: To do | G10: Needs Partner Center enrollment + dev tenant; evidence: install screenshot + telemetry row.
A11: S1-08 | B11: Staging env + secrets vault; Postgres adapter behind repositories | C11: — | D11: 2 | E11: Senthil + Claude | F11: To do | G11: Provision after S1-07; domain code untouched (R-S4).

Sheet S2_Build_Board
A1: S2 BUILD BOARD — Core feature Shift handover threads pt 1 — exit: happy path demoable
A2: Backlog stories scheduled S2. Executed 10 Sep 2026 22:26 (session 1, workbook v006); session-2 deltas noted.
A3: ID | B3: Item | C3: Story ref | D3: Points | E3: Owner | F3: Status | G3: Notes / Evidence
A4: S2-01 | B4: As a Ops director, I can set up Shift handover threads with sensible defaults in one screen | C4: ST-001 | D4: 5 | E4: Claude | F4: Done | G4: Built + covered at 100% this session
A5: S2-02 | B5: As a Ops director, the Shift handover threads happy path completes without documentation | C5: ST-002 | D5: 8 | E5: Claude | F5: Done | G5: Built + covered at 100% this session
A6: S2-03 | B6: As a IT admin, I can customise Shift handover threads rules/conditions for my workflow | C6: ST-003 | D6: 5 | E6: Claude | F6: Done | G6: Built + covered at 100% this session
A7: S2-04 | B7: As a user, Shift handover threads shows clear errors and retry paths on platform API failures | C7: ST-004 | D7: 3 | E7: Claude | F7: Done | G7: Built + covered at 100% this session
A8: S2-05 | B8: Re-install restores account within retention window | C8: ST-053 | D8: 3 | E8: Claude | F8: Done | G8: Built + covered at 100% this session
A9: S2-06 | B9: Multi-user roles: owner/admin/member permission matrix enforced | C9: ST-054 | D9: 5 | E9: Claude | F9: Done | G9: Built + covered at 100% this session

Sheet S3_Build_Board
A1: S3 BUILD BOARD — Handover pt 2 + Approvals start — exit: handover complete with tests; approvals skeleton
A2: Backlog stories scheduled S3. Executed 10 Sep 2026 22:26 (session 1, workbook v006); session-2 deltas noted.
A3: ID | B3: Item | C3: Story ref | D3: Points | E3: Owner | F3: Status | G3: Notes / Evidence
A4: S3-01 | B4: As a Frontline supervisor, Shift handover threads works on the Teams tab + bot surface end-to-end | C4: ST-005 | D4: 5 | E4: Claude | F4: Code-complete pending live | G4: UI + logic done; live Teams tab/bot surface validation pending
A5: S3-02 | B5: As a IT admin, I can see Shift handover threads performance metrics and trends | C5: ST-006 | D5: 3 | E5: Claude | F5: Done | G5: Built + covered at 100% this session
A6: S3-03 | B6: As a user, Shift handover threads respects role permissions and audit logging | C6: ST-007 | D6: 3 | E6: Claude | F6: Done | G6: Built + covered at 100% this session
A7: S3-04 | B7: As a Ops director, I can pause/disable Shift handover threads without data loss | C7: ST-008 | D7: 2 | E7: Claude | F7: Done | G7: Built + covered at 100% this session
A8: S3-05 | B8: As a IT admin, I can import/migrate existing data into Shift handover threads (CSV + competitor importer) | C8: ST-009 | D8: 5 | E8: Claude | F8: Done | G8: Built + covered at 100% this session
A9: S3-06 | B9: As a user, I get notifications (in-app + email) for key Shift handover threads events with per-type mute | C9: ST-010 | D9: 3 | E9: Claude | F9: Done | G9: Built + covered at 100% this session
A10: S3-07 | B10: As a Ops director, I can set up Approval workflows with sensible defaults in one screen | C10: ST-011 | D10: 5 | E10: Claude | F10: Done | G10: Built + covered at 100% this session
A11: S3-08 | B11: As a Ops director, the Approval workflows happy path completes without documentation | C11: ST-012 | D11: 8 | E11: Claude | F11: Done | G11: Built + covered at 100% this session
A12: S3-09 | B12: As a IT admin, I can customise Approval workflows rules/conditions for my workflow | C12: ST-013 | D12: 5 | E12: Claude | F12: Done | G12: Built + covered at 100% this session
A13: S3-10 | B13: As a user, Approval workflows shows clear errors and retry paths on platform API failures | C13: ST-014 | D13: 3 | E13: Claude | F13: Done | G13: Built + covered at 100% this session
A14: S3-11 | B14: Unit+integration test coverage gate ≥70% on core modules | C14: ST-085 | D14: 5 | E14: Claude | F14: Done | G14: Built + covered at 100% this session

Sheet S4_Build_Board
A1: S4 BUILD BOARD — Approval workflows — exit: MVP loop usable end-to-end internally
A2: Backlog stories scheduled S4. Executed 10 Sep 2026 22:26 (session 1, workbook v006); session-2 deltas noted.
A3: ID | B3: Item | C3: Story ref | D3: Points | E3: Owner | F3: Status | G3: Notes / Evidence
A4: S4-01 | B4: As a Frontline supervisor, Approval workflows works on the Teams tab + bot surface end-to-end | C4: ST-015 | D4: 5 | E4: Claude | F4: Code-complete pending live | G4: UI + logic done; live Teams tab/bot surface validation pending
A5: S4-02 | B5: As a IT admin, I can see Approval workflows performance metrics and trends | C5: ST-016 | D5: 3 | E5: Claude | F5: Done | G5: Built + covered at 100% this session
A6: S4-03 | B6: As a user, Approval workflows respects role permissions and audit logging | C6: ST-017 | D6: 3 | E6: Claude | F6: Done | G6: Built + covered at 100% this session
A7: S4-04 | B7: As a Ops director, I can pause/disable Approval workflows without data loss | C7: ST-018 | D7: 2 | E7: Claude | F7: Done | G7: Built + covered at 100% this session
A8: S4-05 | B8: As a IT admin, I can import/migrate existing data into Approval workflows (CSV + competitor importer) | C8: ST-019 | D8: 5 | E8: Claude | F8: Done | G8: Built + covered at 100% this session
A9: S4-06 | B9: As a user, I get notifications (in-app + email) for key Approval workflows events with per-type mute | C9: ST-020 | D9: 3 | E9: Claude | F9: Done | G9: Built + covered at 100% this session
A10: S4-07 | B10: Activation funnel events (install->setup->aha->habit) in one dashboard | C10: ST-071 | D10: 5 | E10: Claude | F10: Done | G10: Built + covered at 100% this session
A11: S4-08 | B11: Error tracking with release tagging; alert on error-rate spike | C11: ST-072 | D11: 3 | E11: Claude | F11: Done | G11: Built + covered at 100% this session
A12: S4-09 | B12: E2E smoke suite runs on every deploy | C12: ST-086 | D12: 5 | E12: Claude | F12: Done | G12: Built + covered at 100% this session

Sheet S5_Build_Board
A1: S5 BUILD BOARD — Digital checklists + alpha hardening — exit: internal alpha, team dogfoods daily
A2: Backlog stories scheduled S5. Executed 10 Sep 2026 22:26 (session 1, workbook v006); session-2 deltas noted.
A3: ID | B3: Item | C3: Story ref | D3: Points | E3: Owner | F3: Status | G3: Notes / Evidence
A4: S5-01 | B4: As a Ops director, I can set up Digital checklists with sensible defaults in one screen | C4: ST-021 | D4: 5 | E4: Claude | F4: Done | G4: Built + covered at 100% this session
A5: S5-02 | B5: As a Ops director, the Digital checklists happy path completes without documentation | C5: ST-022 | D5: 8 | E5: Claude | F5: Done | G5: Built + covered at 100% this session
A6: S5-03 | B6: As a IT admin, I can customise Digital checklists rules/conditions for my workflow | C6: ST-023 | D6: 5 | E6: Claude | F6: Done | G6: Built + covered at 100% this session
A7: S5-04 | B7: As a user, Digital checklists shows clear errors and retry paths on platform API failures | C7: ST-024 | D7: 3 | E7: Claude | F7: Done | G7: Built + covered at 100% this session
A8: S5-05 | B8: As a Frontline supervisor, Digital checklists works on the Teams tab + bot surface end-to-end | C8: ST-025 | D8: 5 | E8: Claude | F8: Code-complete pending live | G8: UI + logic done; live Teams tab/bot surface validation pending
A9: S5-06 | B9: As a IT admin, I can see Digital checklists performance metrics and trends | C9: ST-026 | D9: 3 | E9: Claude | F9: Done | G9: Built + covered at 100% this session
A10: S5-07 | B10: As a user, Digital checklists respects role permissions and audit logging | C10: ST-027 | D10: 3 | E10: Claude | F10: Done | G10: Built + covered at 100% this session
A11: S5-08 | B11: As a Ops director, I can pause/disable Digital checklists without data loss | C11: ST-028 | D11: 2 | E11: Claude | F11: Done | G11: Built + covered at 100% this session
A12: S5-09 | B12: As a IT admin, I can import/migrate existing data into Digital checklists (CSV + competitor importer) | C12: ST-029 | D12: 5 | E12: Claude | F12: Done | G12: Built + covered at 100% this session
A13: S5-10 | B13: As a user, I get notifications (in-app + email) for key Digital checklists events with per-type mute | C13: ST-030 | D13: 3 | E13: Claude | F13: Done | G13: Built + covered at 100% this session
A14: S5-11 | B14: First-run checklist reaches aha-moment in <1 day | C14: ST-078 | D14: 5 | E14: Claude | F14: Done | G14: Built + covered at 100% this session
A15: S5-12 | B15: Empty states teach next action on every screen | C15: ST-079 | D15: 3 | E15: Claude | F15: Done | G15: Built + covered at 100% this session

Sheet S6_Build_Board
A1: S6 BUILD BOARD — Billing + Kudos — exit: can charge a test customer; up/downgrade paths work
A2: Backlog stories scheduled S6. Executed 10 Sep 2026 22:26 (session 1, workbook v006); session-2 deltas noted.
A3: ID | B3: Item | C3: Story ref | D3: Points | E3: Owner | F3: Status | G3: Notes / Evidence
A4: S6-01 | B4: As a Ops director, I can set up Kudos/recognition with sensible defaults in one screen | C4: ST-031 | D4: 5 | E4: Claude | F4: Done | G4: Built + covered at 100% this session
A5: S6-02 | B5: As a Ops director, the Kudos/recognition happy path completes without documentation | C5: ST-032 | D5: 8 | E5: Claude | F5: Done | G5: Built + covered at 100% this session
A6: S6-03 | B6: As a IT admin, I can customise Kudos/recognition rules/conditions for my workflow | C6: ST-033 | D6: 5 | E6: Claude | F6: Done | G6: Built + covered at 100% this session
A7: S6-04 | B7: As a user, Kudos/recognition shows clear errors and retry paths on platform API failures | C7: ST-034 | D7: 3 | E7: Claude | F7: Done | G7: Built + covered at 100% this session
A8: S6-05 | B8: As a Frontline supervisor, Kudos/recognition works on the Teams tab + bot surface end-to-end | C8: ST-035 | D8: 5 | E8: Claude | F8: Code-complete pending live | G8: UI + logic done; live Teams tab/bot surface validation pending
A9: S6-06 | B9: As a IT admin, I can see Kudos/recognition performance metrics and trends | C9: ST-036 | D9: 3 | E9: Claude | F9: Done | G9: Built + covered at 100% this session
A10: S6-07 | B10: As a user, Kudos/recognition respects role permissions and audit logging | C10: ST-037 | D10: 3 | E10: Claude | F10: Done | G10: Built + covered at 100% this session
A11: S6-08 | B11: As a Ops director, I can pause/disable Kudos/recognition without data loss | C11: ST-038 | D11: 2 | E11: Claude | F11: Done | G11: Built + covered at 100% this session
A12: S6-09 | B12: As a IT admin, I can import/migrate existing data into Kudos/recognition (CSV + competitor importer) | C12: ST-039 | D12: 5 | E12: Claude | F12: Done | G12: Built + covered at 100% this session
A13: S6-10 | B13: As a user, I get notifications (in-app + email) for key Kudos/recognition events with per-type mute | C13: ST-040 | D13: 3 | E13: Claude | F13: Done | G13: Built + covered at 100% this session
A14: S6-11 | B14: 14-day trial without card; banner shows days remaining | C14: ST-057 | D14: 5 | E14: Claude | F14: Done | G14: Built + covered at 100% this session
A15: S6-12 | B15: Upgrade/downgrade mid-cycle prorates correctly | C15: ST-058 | D15: 5 | E15: Claude | F15: Done | G15: Built + covered at 100% this session
A16: S6-13 | B16: Marketplace billing API used where mandated; external Stripe fallback elsewhere | C16: ST-059 | D16: 8 | E16: Claude | F16: Code-complete pending live | G16: Billing logic done; marketplace transactable API mocked

Sheet S7_Build_Board
A1: S7 BUILD BOARD — Private beta (design partners) — exit: 3+ partners active weekly; NPS pulse >30
A2: Backlog stories scheduled S7. Executed 10 Sep 2026 22:26 (session 1, workbook v006); session-2 deltas noted.
A3: ID | B3: Item | C3: Story ref | D3: Points | E3: Owner | F3: Status | G3: Notes / Evidence
A4: S7-01 | B4: Failed payment: 7-day grace, 3 dunning emails, then read-only mode | C4: ST-060 | D4: 3 | E4: Claude | F4: Done | G4: Built + covered at 100% this session
A5: S7-02 | B5: Plan limits enforced with upgrade prompts at 80%/100% | C5: ST-061 | D5: 3 | E5: Claude | F5: Done | G5: Built + covered at 100% this session
A6: S7-03 | B6: Invoices/receipts downloadable; GST/VAT fields supported | C6: ST-062 | D6: 3 | E6: Claude | F6: Done | G6: Built + covered at 100% this session
A7: S7-04 | B7: Cancellation flow with save-offer and exit survey | C7: ST-063 | D7: 3 | E7: Claude | F7: Done | G7: Built + covered at 100% this session
A8: S7-05 | B8: Scopes requested map 1:1 to shipped features (least privilege doc) | C8: ST-064 | D8: 3 | E8: Claude | F8: Done | G8: Built + covered at 100% this session

Sheet S8_Build_Board
A1: S8 BUILD BOARD — Beta iteration + Manager dashboard — exit: beta cohort WoW retention >60%
A2: Backlog stories scheduled S8. Executed 10 Sep 2026 22:26 (session 1, workbook v006); session-2 deltas noted.
A3: ID | B3: Item | C3: Story ref | D3: Points | E3: Owner | F3: Status | G3: Notes / Evidence
A4: S8-01 | B4: As a Ops director, I can set up Manager dashboard with sensible defaults in one screen | C4: ST-041 | D4: 5 | E4: Claude | F4: Done | G4: Built + covered at 100% this session
A5: S8-02 | B5: As a Ops director, the Manager dashboard happy path completes without documentation | C5: ST-042 | D5: 8 | E5: Claude | F5: Done | G5: Built + covered at 100% this session
A6: S8-03 | B6: As a IT admin, I can customise Manager dashboard rules/conditions for my workflow | C6: ST-043 | D6: 5 | E6: Claude | F6: Done | G6: Built + covered at 100% this session
A7: S8-04 | B7: As a user, Manager dashboard shows clear errors and retry paths on platform API failures | C7: ST-044 | D7: 3 | E7: Claude | F7: Done | G7: Built + covered at 100% this session
A8: S8-05 | B8: As a Frontline supervisor, Manager dashboard works on the Teams tab + bot surface end-to-end | C8: ST-045 | D8: 5 | E8: Claude | F8: Code-complete pending live | G8: UI + logic done; live Teams tab/bot surface validation pending
A9: S8-06 | B9: As a IT admin, I can see Manager dashboard performance metrics and trends | C9: ST-046 | D9: 3 | E9: Claude | F9: Done | G9: Built + covered at 100% this session
A10: S8-07 | B10: As a user, Manager dashboard respects role permissions and audit logging | C10: ST-047 | D10: 3 | E10: Claude | F10: Done | G10: Built + covered at 100% this session
A11: S8-08 | B11: As a Ops director, I can pause/disable Manager dashboard without data loss | C11: ST-048 | D11: 2 | E11: Claude | F11: Done | G11: Built + covered at 100% this session
A12: S8-09 | B12: As a IT admin, I can import/migrate existing data into Manager dashboard (CSV + competitor importer) | C12: ST-049 | D12: 5 | E12: Claude | F12: Done | G12: Built + covered at 100% this session
A13: S8-10 | B13: As a user, I get notifications (in-app + email) for key Manager dashboard events with per-type mute | C13: ST-050 | D13: 3 | E13: Claude | F13: Done | G13: Built + covered at 100% this session
A14: S8-11 | B14: Data-flow diagram + retention policy published | C14: ST-065 | D14: 3 | E14: Claude | F14: Done | G14: Built + covered at 100% this session
A15: S8-12 | B15: Encryption at rest + in transit verified; secrets in vault | C15: ST-066 | D15: 5 | E15: Claude | F15: Code-complete pending live | G15: Vault/encryption pattern coded; live infra verification pending
... A25: S8-22 | B25: Zero-downtime deploy verified (blue/green or rolling) | C25: ST-092 | D25: 3 | E25: Claude | F25: To do | G25: Blue-green verify on live infra

Sheet S13_Build_Board
A1: S13 BUILD BOARD — Trust boundaries for real (7 stories, 38 pts) — exit: a Teams dev tenant loads the tab with a real Entra token and the bot answers a real message, with the dev bypass disabled
A2: Mandatory — blocks all live work. Executed 20 Sep 2026 (session 41, codebase v0.14.0). Every story in this board was built this session; the three CRITICALs from the review (P-001, P-002, P-003) close here and in S14.
A3: ID | B3: Item | C3: Story ref | D3: Points | E3: Owner | F3: Status | G3: Acceptance criterion (machine-checkable) | H3: Notes / Evidence
A4: S13-01 | B4: JWKS-backed Entra signature verification for tab SSO | C4: SD201 | D4: 8 | E4: Claude | F4: Done | G4: Real verifier fetches/caches Entra OpenID metadata, selects by kid, rejects wrong-kid, expired, alg=none and tampered tokens; wired from scripts/serve.ts | H4: Closes P-001. Code: src/jwt.ts + src/jwks.ts + src/entraVerifier.ts. Tests: tests/trustBoundaries.test.ts. RS256 only; unknown kid triggers at most one metadata refresh per minRefreshGapMs with a single in-flight fetch. Rejection reasons counted, not swallowed. Constructed by name in compose().
A5: S13-02 | B5: Bot Connector JWT verification | C5: SD202 | D5: 8 | E5: Claude | F5: Done | G5: Activity accepted only when issuer, audience (bot app id), serviceUrl binding and signature validate; valid-signature/wrong-serviceUrl rejected | H5: Closes P-002. Code: src/connectorAuth.ts. Tests: tests/trustBoundaries.test.ts. Issuer pinned to https://api.botframework.com, audience = bot app id, serviceUrl bound to the activity and re-checked against the host allowlist, 300s skew.
A6: S13-03 | B6: Dev bypass fenced by environment | C6: SD203 | D6: 3 | E6: Claude | F6: Done | G6: Dev token only honoured when SHIFTDESK_ENV=dev; boot throws if set in production | H6: Closes P-001. Code: src/config.ts + scripts/serve.ts NON_PRODUCTION_IMPLEMENTATIONS. Tests: tests/trustBoundaries.test.ts + tests/config.test.ts. environment unset now means production, not dev — the safe default. compose() refuses to serve when any dev-only implementation appears outside dev.
A7: S13-04 | B7: Production-seam wiring assertion | C7: SD204 | D7: 5 | E7: Claude | F7: Done | G7: Test walks the entry point and fails if any production seam has no non-test implementation constructed | H7: Closes P-017 / P-016. Code: scripts/serve.ts compose() returns a named seams record. Tests: tests/serve.test.ts + tests/v046Closeout.test.ts. Third tier of D-SD7. The same check runs at boot, so a mis-wired deployment refuses to serve rather than serving insecurely.
A8: S13-05 | B8: Request hardening: body cap + rate limits | C8: SD205 | D8: 8 | E8: Claude | F8: Done | G8: 413 over cap; per-tenant and per-IP token bucket returning 429 with Retry-After | H8: Closes P-007. Code: src/requestGuard.ts + src/server.ts. Tests: tests/requestHardening.test.ts. readBodyCapped throws mid-stream rather than buffering to the cap. clientAddress honours X-Forwarded-For only when trustProxy is set.
A9: S13-06 | B9: Security headers on every surface | C9: SD206 | D9: 3 | E9: Claude | F9: Done | G9: CSP frame-ancestors for Teams hosts, HSTS, nosniff, Referrer-Policy asserted per surface | H9: Closes P-008. Code: src/securityHeaders.ts. Tests: tests/requestHardening.test.ts. securityHeaders('tab') allows the Teams frame ancestors and the TeamsJS CDN origin; securityHeaders('api') allows neither.
A10: S13-07 | B10: Circuit breaker half-open probe | C10: SD207 | D10: 3 | E10: Claude | F10: Done | G10: Cooldown probe closes on success, re-opens on failure, no operator action; ops alert on open | H10: Closes F-007. Code: src/platformGateway.ts. Tests: tests/platformGateway.test.ts + src/slo.ts ALERT_RULES. Closes F-007, open since the first cold review. Breaker-open is one of the eleven alert rules, each carrying the finding that justifies it.

Sheet S14_Build_Board
A1: S14 BUILD BOARD — Durability for real (8 stories, 36 pts) — exit: restart, two-instance and restore drills run green in CI against real Postgres, unattended
A2: Mandatory — blocks store submission. Executed 20 Sep 2026 (session 41). A real Postgres 16 instance was provisioned in-session, so the integration tier and the backup drill are results rather than plans.
A3: ID | B3: Item | C3: Story ref | D3: Points | E3: Owner | F3: Status | G3: Acceptance criterion (machine-checkable) | H3: Notes / Evidence
A4: S14-01 | B4: Postgres client wired in the entry point | C4: SD208 | D4: 5 | E4: Claude | F4: Done | G4: pg in dependencies, pool from DATABASE_URL, banner reports durable=true | H4: Closes P-003. Code: src/pgClient.ts + package.json dependencies. Tests: tests/v046Branches.test.ts + tests/integration/postgres.integration.test.ts. pg moved from optional to dependencies. poolOptionsFor() is pure and decides TLS by host, so it is testable without a database. F-071 found here.
A5: S14-02 | B5: Refuse to serve non-durably in production | C5: SD209 | D5: 3 | E5: Claude | F5: Done | G5: Boot fails when production and store is in-memory | H5: Closes P-003. Code: src/bootstrap.ts repositoryFor + src/config.ts. Tests: tests/trustBoundaries.test.ts + tests/bootstrap.test.ts. Also refuses the inverse mistake: a DATABASE_URL with no client supplied is an error, not a silent fall back to memory.
A6: S14-03 | B6: Migration runner | C6: SD210 | D6: 5 | E6: Claude | F6: Done | G6: Idempotent ordered migrations recorded in schema_migrations, run on boot and in deploy | H6: Closes P-003. Code: src/migrations.ts + scripts/migrate.ts + migrations/003_record_indexes.sql. Tests: tests/v046Edges.test.ts + integration test 1. Advisory lock 0x53444d47 serialises concurrent boots; a checksum mismatch on an applied file refuses to run rather than diverging. Verified against real Postgres 16.
A7: S14-04 | B7: Real-Postgres integration tier in CI | C7: SD211 | D7: 8 | E7: Claude | F7: Done | G7: Contract and lifecycle suites run against a Postgres service container; JSONB and index behaviour proven | H7: Closes OBS-SD4 / P-017. Code: jest.integration.config.js + .github/workflows/ci.yml job 2. Tests: tests/integration/postgres.integration.test.ts (9 tests). Closes OBS-SD4 ("the SQL fake is not a database"). Ran for real this session against Postgres 16 on port 55432: 9/9 green.
A8: S14-05 | B8: Fix list() version projection | C8: SD212 | D8: 2 | E8: Claude | F8: Done | G8: version selected and returned; guarded write from a listed row succeeds | H8: Closes P-005. Code: src/repository.ts. Tests: integration test 2. Proven on a real store, where the defect lived: the SQL fake could not have shown it.
A9: S14-06 | B9: One repository, one registry | C9: SD213 | D9: 5 | E9: Claude | F9: Done | G9: Scheduled purge removes data the server was serving and evicts its cache | H9: Closes P-004 / P-015. Code: src/bootstrap.ts sharedStateFor/lifecycleFor. Tests: tests/bootstrap.test.ts + integration test 9. One repository, one registry, one persister per process — the split instances behind P-004 cannot be constructed any more.
A10: S14-07 | B10: Restart and blue/green durability tests in CI | C10: SD214 | D10: 5 | E10: Claude | F10: Done | G10: Write, kill, restart, read back; two instances, conflicting writes converge via 409 | H10: Closes P-003. Code: src/persistence.ts refresh/loadWindow. Tests: integration tests 3 and 4. The restart drill discards the process, not just the cache. Two-instance convergence needed staleAfterMs refresh in TenantRegistry.ensure to be true.
A11: S14-08 | B11: Backup/restore automation with numbers | C11: SD215 | D11: 3 | E11: Claude | F11: Done | G11: Scripted dump/restore in CI; RPO <= 15 min, RTO <= 60 min asserted and published | H11: Closes P-020. Code: ops/backup-restore-drill.sh + npm run backup:drill. Tests: ops/backup-drill-report.json. Ran for real this session: pg_dump/pg_restore into shiftdesk_restore, row counts compared. PASS with RPO 0s and RTO 0s against the 15 min / 60 min bar.

Sheet S15_Build_Board
A1: S15 BUILD BOARD — Scale and data model (6 stories, 34 pts) — exit: 5x load sweep passes on staging with per-record persistence and published numbers
A2: Mandatory — closes LC-8 once SD219 runs. Executed 20 Sep 2026 (session 41). Whole-module snapshots are gone; OBS-SD9 closes with them.
A3: ID | B3: Item | C3: Story ref | D3: Points | E3: Owner | F3: Status | G3: Acceptance criterion (machine-checkable) | H3: Notes / Evidence
A4: S15-01 | B4: Per-record persistence replacing module snapshots | C4: SD216 | D4: 13 | E4: Claude | F4: Done | G4: One record per item; concurrent writes on different instances both succeed; migration from snapshot rows tested | H4: Closes P-006. Code: src/persistence.ts + src/moduleBase.ts dirty set. Tests: integration tests 4 and 5. Closes OBS-SD9 as well. Legacy whole-module snapshot rows convert to per-record rows on first hydrate, exactly once; node-scoped ids keep two instances from colliding.
A5: S15-02 | B5: Bounded working set and windowed hydration | C5: SD217 | D5: 5 | E5: Claude | F5: Done | G5: Tenant with 100k records hydrates within the p95 budget | H5: Closes P-006. Code: src/persistence.ts loadWindow + migrations/003_record_indexes.sql. Tests: integration test 6. Run at 100k records on real Postgres inside the 500ms API p95 budget. Expression indexes make the window a keyset read, not a table scan.
A6: S15-03 | B6: Audit pagination and retention enforcement | C6: SD218 | D6: 5 | E6: Claude | F6: Done | G6: Cursor-paginated audit query; retention classes enforced by the sweep; streamed export | H6: Closes F-008. Code: src/repository.ts DurableAuditLog.page/stream + src/retentionEnforcer.ts. Tests: integration test 7 + tests/governance.test.ts. Closes F-008, open since the first cold review. The published retention numbers are now the numbers the sweep enforces, by kind and age, from the same hourly scheduler.
A7: S15-04 | B7: Run the k6 5x load sweep on staging | C7: SD219 | D7: 5 | E7: Senthil + Claude | F7: To do — Senthil | G7: api p95 <500ms, bot p95 <800ms, failures <1%; report committed as LC-8 evidence | H7: Closes P-006. Code: load/k6-load-sweep.js (harness ready). Tests: load/EVIDENCE.md (awaiting a real run). Needs staging infrastructure. The harness and the pass bar are scripted; nobody can claim the number until the sweep runs. LC-8 stays open.
A8: S15-05 | B8: Latency and conflict SLO evidence | C8: SD220 | D8: 3 | E8: Senthil + Claude | F8: To do — Senthil | G8: Latency report and 409 rate captured during the sweep, both under budget | H8: Closes P-006. Code: src/perf.ts + src/slo.ts sloReport. Tests: load/EVIDENCE.md. Instrumentation is in place and the report renders; the evidence is a by-product of SD219 and arrives with it.
A9: S15-06 | B9: Key rotation with key-id envelope | C9: SD221 | D9: 3 | E9: Claude | F9: Done | G9: enc:v2:<keyId> envelope, read-through for previous keys, re-encrypt sweep | H9: Closes OBS-SD8 / P-014. Code: src/encryptedRepository.ts KeyRing + reencrypt(). Tests: tests/encryptedRepository.test.ts + integration test 8. Closes OBS-SD8. Old enc:v1 rows still read; the sweep re-seals them under the current key id. Round-tripped through real JSONB.

Sheet S16_Build_Board
A1: S16 BUILD BOARD — Teams-native experience (6 stories, 40 pts) — exit: end-to-end handover completed on Teams mobile using cards, with the acknowledgement nudge arriving proactively
A2: Parallel with S17. Executed 20 Sep 2026 (session 41). Card rendering and proactive delivery are live-client facts, so they stay pending-live however good the tests are.
A3: ID | B3: Item | C3: Story ref | D3: Points | E3: Owner | F3: Status | G3: Acceptance criterion (machine-checkable) | H3: Notes / Evidence
A4: S16-01 | B4: Adaptive Cards for the four core flows | C4: SD222 | D4: 13 | E4: Claude | F4: Code-complete pending live | G4: Cards with action buttons for handover, acknowledge, approval decision, checklist tick; invoke handled and acked; schema-validated | H4: Closes P-009. Code: src/adaptiveCards.ts + src/botTransport.ts invoke handling. Tests: tests/teamsNative.test.ts. Cards are schema-validated and the invoke path is acked, but how a card renders is only knowable in a live client. Text stays as the fallback every card carries.
A5: S16-02 | B5: Proactive messaging and activity feed | C5: SD223 | D5: 8 | E5: Claude | F5: Code-complete pending live | G5: Conversation references persisted; unacknowledged handover pushes a channel card and a feed notification; 403-uninstalled handled | H5: Closes P-009 / P-015. Code: src/proactive.ts ConversationStore + ProactiveMessenger. Tests: tests/teamsNative.test.ts. The product promise the review found unimplemented. 403 forgets the conversation; 429/5xx retry with backoff. A real push needs a real tenant.
A6: S16-03 | B6: Team/channel configurable tab | C6: SD224 | D6: 8 | E6: Claude | F6: Code-complete pending live | G6: Configurable tab in team scope with config page; shared handover board renders in-channel | H6: Closes P-010. Code: teams-app/manifest.json configurableTabs + web/configEntry.tsx + web/config.html. Tests: tests/manifest.test.ts + tests/teamsNative.test.ts. Manifest, config page and save handshake all ship; in-channel rendering is a live-client fact.
A7: S16-04 | B7: Command list parity | C7: SD225 | D7: 2 | E7: Claude | F7: Done | G7: Manifest advertises exactly what botRouter handles; parity test fails on drift | H7: Closes P-011. Code: teams-app/manifest.json (8 commands). Tests: tests/manifest.test.ts. Two-way: a command in the manifest with no handler fails, and a handler missing from the manifest fails.
A8: S16-05 | B8: Mobile pass on live Teams clients | C8: SD226 | D8: 5 | E8: Senthil | F8: To do — Senthil | G8: iOS and Android walkthrough of the five store-screenshot flows; required mobile screenshot captured live | H8: Closes VER-SD01. Code: ASSET_PLAN.md flow list + web/demo.tsx capture surface. Tests: ops/accessibility-audit-script.md. Store-blocking (VER-SD01). The walkthrough script and the five flows are prepared; only a person with the app sideloaded on a phone can do it.
A9: S16-06 | B9: i18n scaffold and first launch locale | C9: SD227 | D9: 4 | E9: Claude | F9: Done | G9: All user-facing strings in a catalogue; test bans hard-coded user-facing strings | H9: Closes P-012. Code: src/i18n.ts (en-GB, es-ES) + teams-app/es-ES.json + localizationInfo. Tests: tests/teamsNative.test.ts. A missing key throws I18N_KEY_MISSING rather than rendering blank. F-072 found here: two strings were frozen at import so setLocale had no effect.

Sheet S17_Build_Board
A1: S17 BUILD BOARD — Enterprise admin and governance (6 stories, 32 pts) — exit: an IT-admin dry run (install, consent, rollout, export, delete) completed by someone who did not build it
A2: Parallel with S16. Executed 20 Sep 2026 (session 41). The legal documents are generated from code constants and bound by test, so page and product cannot drift.
A3: ID | B3: Item | C3: Story ref | D3: Points | E3: Owner | F3: Status | G3: Acceptance criterion (machine-checkable) | H3: Notes / Evidence
A4: S17-01 | B4: Admin consent and tenant-wide rollout in 2 tenants | C4: SD228 | D4: 8 | E4: Senthil | F4: To do — Senthil | G4: Recorded consent and rollout walkthrough; consent screen matches the least-privilege doc exactly | H4: Closes LC-4 / LC-5. Code: content/admin-deployment-guide.md + SCOPE_MAP. Tests: tests/manifest.test.ts + tests/privacy.test.ts. Needs two live tenants. The scope map is pinned to its consumer files by test, so the doc cannot drift from what consent will show.
A5: S17-02 | B5: Data residency configuration | C5: SD229 | D5: 5 | E5: Claude | F5: Done | G5: Region-scoped config and store URL; boot asserts region/store agreement | H5: Closes P-013. Code: src/residency.ts assertResidency + src/config.ts region. Tests: tests/governance.test.ts. Four customer regions plus a CI region. A store host outside the declared region throws RESIDENCY_MISMATCH at boot, before serving a request.
A6: S17-03 | B6: DPA, subprocessor register, retention schedule published | C6: SD230 | D6: 5 | E6: Claude | F6: Done | G6: Documents published and a test asserts they match privacy.retentionPolicy() | H6: Closes P-013. Code: src/residency.ts generators + content/legal/*.md (4 documents). Tests: tests/governance.test.ts. The documents are generated from the constants, so a retention class added in code cannot go missing from the customer-facing schedule.
A7: S17-04 | B7: Self-serve export and delete, admin-visible | C7: SD231 | D7: 5 | E7: Claude | F7: Code-complete pending live | G7: Owner-only streamed export and delete with receipt, surfaced in Settings, audited, tested over HTTP with a real store | H7: Closes F-029. Code: src/bootstrap.ts dataRightsFor + src/server.ts dataRightsRoute + src/ui/screens.tsx. Tests: tests/privacy.test.ts + tests/server.test.ts. Streamed NDJSON export and delete-with-receipt are wired and audited over HTTP; the AC asks for that over a real store, which arrives with the staging environment.
A8: S17-05 | B8: KMS-backed key custody | C8: SD232 | D8: 5 | E8: Claude | F8: Code-complete pending live | G8: Keys from managed KMS at boot; production refuses plain-env keys | H8: Closes P-014. Code: src/keySource.ts AzureKeyVaultKeyProvider + managedIdentityToken. Tests: tests/governance.test.ts + tests/config.test.ts. Production already refuses a plain env key. The Key Vault path is coded against the documented API but has never spoken to a real vault.
A9: S17-06 | B9: Incident response and breach notification runbook | C9: SD233 | D9: 4 | E9: Senthil + Claude | F9: Drafted | G9: Roles, severity ladder, 72-hour notification path, comms templates; tabletop recorded | H9: Closes P-013. Code: ops/incident-response-runbook.md. Tests: tests/governance.test.ts (severity ladder bound to ALERT_RULES). Runbook written and bound to the alert rules by test. The tabletop exercise is a human activity and is not claimed.

Sheet S18_Build_Board
A1: S18 BUILD BOARD — Assurance and certification (5 stories, 30 pts) — exit: attestation submitted, pen-test Highs closed, accessibility audit signed
A2: Procurement starts in S13 — long lead. Executed 20 Sep 2026 (session 41) for the evidence half only: four of five items here are irreducibly human and are not claimed.
A3: ID | B3: Item | C3: Story ref | D3: Points | E3: Owner | F3: Status | G3: Acceptance criterion (machine-checkable) | H3: Notes / Evidence
A4: S18-01 | B4: Third-party penetration test and remediation | C4: SD234 | D4: 8 | E4: Senthil | F4: To do — Senthil | G4: External test on staging; all High/Critical closed and retested | H4: Closes LC-3. Code: SECURITY_EVIDENCE.md scope pack. Tests: —. Needs a staging environment and a vendor engagement. The scope pack and the surface inventory are prepared so the engagement can start without a discovery phase.
A5: S18-02 | B5: Microsoft 365 Publisher Attestation submitted | C5: SD235 | D5: 5 | E5: Senthil | F5: To do — Senthil | G5: Submitted and accepted in Partner Center | H5: Closes LC-3. Code: ops/m365-certification-pack.md. Tests: tests/governance.test.ts (evidence paths exist). Partner Center account required. Every answer the attestation asks for is drafted in the pack.
A6: S18-03 | B6: M365 Certification evidence pack assembled | C6: SD236 | D6: 8 | E6: Claude | F6: Done | G6: Data handling, security, account management and compliance evidence mapped to the certification framework | H6: Closes LC-3. Code: src/compliance.ts M365_CONTROLS + ops/m365-certification-pack.md. Tests: tests/governance.test.ts. Each control names an evidence path, and the test fails if the path does not exist — the discipline that caught three controls with no executable evidence behind them.
A7: S18-04 | B7: SOC 2 Type I readiness | C7: SD237 | D7: 5 | E7: Senthil | F7: To do — Senthil | G7: Controls mapped, compliance automation live, audit firm engaged; budget $15k-$50k audit fee and ~6 months observation for Type II | H7: Closes D-05. Code: src/compliance.ts SOC2_CONTROLS + ops/soc2-readiness-map.md. Tests: tests/governance.test.ts. The mapping and the automation are in code; engaging a firm and paying the fee are Senthil decisions with a real budget attached.
A8: S18-05 | B8: Manual WCAG AA and screen-reader audit on live tabs | C8: SD238 | D8: 4 | E8: Senthil | F8: To do — Senthil | G8: Keyboard-only and NVDA/VoiceOver pass on all nine screens in the live client | H8: Closes LC-7 / R-S6. Code: ops/accessibility-audit-script.md (per-screen script). Tests: tests/a11y.test.tsx (automated net stays). Closes R-S6, open since session 1. jest-axe cannot hear a screen reader; the script makes the manual pass a checklist rather than an exploration.

Sheet S19_Build_Board
A1: S19 BUILD BOARD — Commercial machinery and observability (5 stories, 32 pts) — exit: a test customer transacts through the marketplace and the entitlement is enforced end to end
A2: Precedes launch. Executed 20 Sep 2026 (session 41). Fulfillment API v2 is built against the documented contract; a real transaction needs a live offer.
A3: ID | B3: Item | C3: Story ref | D3: Points | E3: Owner | F3: Status | G3: Acceptance criterion (machine-checkable) | H3: Notes / Evidence
A4: S19-01 | B4: Marketplace SaaS Fulfillment integration | C4: SD239 | D4: 13 | E4: Claude | F4: Code-complete pending live | G4: Token resolution plus idempotent activate/change/suspend/reinstate/unsubscribe webhooks; seat reconciliation with drift alert | H4: Closes P-019 / LC-6. Code: src/fulfillment.ts + src/server.ts handleMarketplaceWebhook. Tests: tests/commercial.test.ts. Fulfillment API v2 against the documented contract, idempotent on activityId, with Entra and shared-secret webhook authentication. A real transaction needs a live offer.
A5: S19-02 | B5: Transactable offer with private offers configured | C5: SD240 | D5: 5 | E5: Senthil | F5: To do — Senthil | G5: Offer live in Partner Center; private-offer path tested with a pilot customer | H5: Closes LC-6. Code: content/pricing-faq.md + fulfillment plan mapping. Tests: tests/commercial.test.ts (plan ids bound to entitlements). Partner Center work. Plan identifiers are bound to the entitlement table by test, so the offer and the code cannot disagree once it exists.
A6: S19-03 | B6: Real error and product analytics wiring | C6: SD241 | D6: 5 | E6: Claude | F6: Code-complete pending live | G6: Release-tagged Sentry and PostHog receiving scrubbed events; deliberate error visible in dashboard | H6: Closes F-070. Code: src/telemetrySink.ts HttpTelemetrySink + scrub/tenantHash. Tests: tests/observability.test.ts. Sentry-envelope and PostHog-capture shapes are built and the scrubber is pinned by test; no sink URL is configured, so nothing has been seen in a dashboard.
A7: S19-04 | B7: SLO, error budget and alerting | C7: SD242 | D7: 5 | E7: Claude | F7: Done | G7: 99.5% SLO with error budget; alerts on breaker-open, 409 rate, store failure, dunning failure, retention failure; on-call runbook | H7: Closes D-05. Code: src/slo.ts (11 ALERT_RULES) + ops/incident-response-runbook.md. Tests: tests/observability.test.ts + tests/governance.test.ts. 99.5% is 216 minutes a month, stated as a number rather than a nine. Every rule carries a because field naming the finding that justifies it.
A8: S19-05 | B8: Deploy pipeline made real | C8: SD243 | D8: 4 | E8: Senthil + Claude | F8: Code-complete pending live | G8: Provider CLI replaces echo steps; migrations before swap; automated green smoke; one rollback executed | H8: Closes P-020. Code: .github/workflows/deploy.yml (az commands, migrate-before-swap, smoke, rollback job). Tests: tests/reviewPack.test.ts (no echo placeholders remain). The echo placeholders are gone and the ordering is right. Executing one rollback needs the subscription.

Sheet S20_Build_Board
A1: S20 BUILD BOARD — Demand validation and go/no-go (4 stories, 24 pts) — exit: G-01/G-02 become achievable on evidence, or kill criteria fire
A2: Programme gate. Executed 20 Sep 2026 (session 41) for the model repair and the repositioning copy. The interviews and the five paid pilots are the gate, and no code substitutes for them.
A3: ID | B3: Item | C3: Story ref | D3: Points | E3: Owner | F3: Status | G3: Acceptance criterion (machine-checkable) | H3: Notes / Evidence
A4: S20-01 | B4: 15 discovery interviews in regulated frontline sectors | C4: SD244 | D4: 8 | E4: Senthil | F4: To do — Senthil | G4: Transcripts plus synthesis on how handover evidence is produced today and what audit failure costs; unparks D13 | H4: Closes R4. Code: —. Tests: —. The one item no amount of code can substitute for. D13 parked interviews portfolio-wide; this is where that decision comes back.
A5: S20-02 | B5: Reposition to the auditable-evidence wedge | C5: SD245 | D5: 5 | E5: Senthil + Claude | F5: Drafted | G5: Listing copy, one-pager and comparison pages rewritten explicitly against free Approvals and Planner; tested in 10 of 15 calls | H5: Closes D-04. Code: content/listing-copy-A.md + content/listing-copy-B.md + content/positioning-onepager.md. Tests: tests/completionWave.test.ts + tests/reviewPack.test.ts. Copy rewritten against the free first-party overlap rather than around it. Whether the wedge lands is answered in the SD244 calls, not by the copy.
A6: S20-03 | B6: Pricing re-test and model repair | C6: SD246 | D6: 5 | E6: Claude | F6: Done | G6: Per-site pricing modelled; cash-in/runway row added; real breakeven month or explicit funding requirement | H6: Closes P-018 / D-01. Code: product workbook v046 Financial_Model. Tests: workbook recalculation, 0 errors. The model now shows cash in, cash out, runway and either a breakeven month or the funding requirement stated outright. Per-site pricing modelled beside per-seat.
A7: S20-04 | B7: 5 paid pilots with signed order forms | C7: SD247 | D7: 6 | E7: Senthil | F7: To do — Senthil | G7: Five paying tenants; activation and week-4 retention measured through the wired funnel | H7: Closes G-02. Code: src/telemetry.ts funnel (wired at the boundary since session 24). Tests: tests/observability.test.ts. The funnel that would measure this is real and wired. The five customers are not, and G-02 counts only paying strangers.

Sheet Traceability_Matrix
A1: TRACEABILITY MATRIX — 147 stories: module -> epic -> story -> code -> test -> evidence
A2: Rows 4-103: the original 100 ST stories (workbook v005 Full_Backlog). Rows 104-150: the 47 SD stories from the independent review sprint plan S13-S20, every one carried here whether built, drafted or owed to Senthil (D-SD8) — none dropped. Rollup formulas read cols E/G/J over rows 4-150.
A3: Story ID | B3: Epic | C3: Module / feature | D3: Story | E3: Points | F3: Priority | G3: Sprint | H3: Primary screen | I3: Verification | J3: Status | K3: Evidence
A4: ST-001 | B4: F1 | C4: Shift handover threads | D4: As a Ops director, I can set up Shift handover threads with sensible defaults in one screen | E4: 5 | F4: P0 | G4: S2 | H4: SCR-3 Handover workspace | I4: Jest 100% cov + E2E smoke | J4: Done | K4: src/handover.ts + src/moduleBase.ts | tests/features.test.ts + tests/moduleBase.test.ts | Built + covered at 100% this session
A5: ST-002 | B5: F1 | C5: Shift handover threads | D5: As a Ops director, the Shift handover threads happy path completes without documentation | E5: 8 | F5: P0 | G5: S2 | H5: SCR-3 Handover workspace | I5: Jest 100% cov + E2E smoke | J5: Done | K5: src/handover.ts + src/moduleBase.ts | tests/features.test.ts + tests/moduleBase.test.ts | Built + covered at 100% this session
A6: ST-003 | B6: F1 | C6: Shift handover threads | D6: As a IT admin, I can customise Shift handover threads rules/conditions for my workflow | E6: 5 | F6: P1 | G6: S2 | H6: SCR-3 Handover workspace | I6: Jest 100% cov + E2E smoke | J6: Done | K6: src/handover.ts + src/moduleBase.ts | tests/features.test.ts + tests/moduleBase.test.ts | Built + covered at 100% this session
A7: ST-004 | B7: F1 | C7: Shift handover threads | D7: As a user, Shift handover threads shows clear errors and retry paths on platform API failures | E7: 3 | F7: P0 | G7: S2 | H7: SCR-3 Handover workspace | I7: Jest 100% cov + E2E smoke | J7: Done | K7: src/handover.ts + src/moduleBase.ts | tests/features.test.ts + tests/moduleBase.test.ts | Built + covered at 100% this session
A8: ST-005 | B8: F1 | C8: Shift handover threads | D8: As a Frontline supervisor, Shift handover threads works on the Teams tab + bot surface end-to-end | E8: 5 | F8: P0 | G8: S3 | H8: SCR-3 Handover workspace | I8: Tests pass; live verification pending | J8: Code-complete pending live | K8: src/ui/screens.tsx + web/TabShell.tsx + web/entry.tsx | tests/tab.test.tsx | tab surface full-stack (GAP-SD1); in-client render pending
A9: ST-006 | B9: F1 | C9: Shift handover threads | D9: As a IT admin, I can see Shift handover threads performance metrics and trends | E9: 3 | F9: P1 | G9: S3 | H9: SCR-3 Handover workspace | I9: Jest 100% cov + E2E smoke | J9: Done | K9: src/handover.ts + src/moduleBase.ts | tests/features.test.ts + tests/moduleBase.test.ts | Built + covered at 100% this session
A10: ST-007 | B10: F1 | C10: Shift handover threads | D10: As a user, Shift handover threads respects role permissions and audit logging | E10: 3 | F10: P1 | G10: S3 | H10: SCR-3 Handover workspace | I10: Jest 100% cov + E2E smoke | J10: Done | K10: src/handover.ts + src/moduleBase.ts | tests/features.test.ts + tests/moduleBase.test.ts | Built + covered at 100% this session
A11: ST-008 | B11: F1 | C11: Shift handover threads | D11: As a Ops director, I can pause/disable Shift handover threads without data loss | E11: 2 | F11: P2 | G11: S3 | H11: SCR-3 Handover workspace | I11: Jest 100% cov + E2E smoke | J11: Done | K11: src/handover.ts + src/moduleBase.ts | tests/features.test.ts + tests/moduleBase.test.ts | Built + covered at 100% this session
A12: ST-009 | B12: F1 | C12: Shift handover threads | D12: As a IT admin, I can import/migrate existing data into Shift handover threads (CSV + competitor importer) | E12: 5 | F12: P1 | G12: S3 | H12: SCR-3 Handover workspace | I12: Jest 100% cov + E2E smoke | J12: Done | K12: src/handover.ts + src/moduleBase.ts | tests/features.test.ts + tests/moduleBase.test.ts | Built + covered at 100% this session
A13: ST-010 | B13: F1 | C13: Shift handover threads | D13: As a user, I get notifications (in-app + email) for key Shift handover threads events with per-type mute | E13: 3 | F13: P2 | G13: S3 | H13: SCR-3 Handover workspace | I13: Jest 100% cov + E2E smoke | J13: Done | K13: src/handover.ts + src/moduleBase.ts | tests/features.test.ts + tests/moduleBase.test.ts | Built + covered at 100% this session
A14: ST-011 | B14: F2 | C14: Approval workflows | D14: As a Ops director, I can set up Approval workflows with sensible defaults in one screen | E14: 5 | F14: P0 | G14: S3 | H14: SCR-4 Approval builder | I14: Jest 100% cov + E2E smoke | J14: Done | K14: src/approvals.ts + src/moduleBase.ts | tests/features.test.ts + tests/moduleBase.test.ts | Built + covered at 100% this session
A15: ST-012 | B15: F2 | C15: Approval workflows | D15: As a Ops director, the Approval workflows happy path completes without documentation | E15: 8 | F15: P0 | G15: S3 | H15: SCR-4 Approval builder | I15: Jest 100% cov + E2E smoke | J15: Done | K15: src/approvals.ts + src/moduleBase.ts | tests/features.test.ts + tests/moduleBase.test.ts | Built + covered at 100% this session
... A150: SD247 | B150: E20 | C150: Demand validation and go/no-go | D150: 5 paid pilots with signed order forms | E150: 6 | F150: P0 | G150: S20 | H150: (marketplace listing) | I150: Live evidence required (D-SD8) | J150: To do — Senthil | K150: Closes G-02. Code: src/telemetry.ts funnel (wired at the boundary since session 24) | Tests: tests/observability.test.ts | The funnel that would measure this is real and wired. The five customers are not, and G-02 counts only paying strangers.

Sheet Sprint_Status_Rollup
A1: SPRINT STATUS ROLLUP — live formulas over Traceability_Matrix
A2: Do not edit computed cells. 'Done' counts status = Done only (D-SD2): code-complete-pending-live, drafted, to-do and backlog are deliberately excluded. Ranges cover Traceability_Matrix rows 4-150 (147 stories: 100 ST + 47 SD).
A3: Sprint | B3: Focus | C3: Stories | D3: Points | E3: Done | F3: Done points | G3: % points done | H3: RAG (manual) | I3: Exit criteria
A4: S1 | B4: Foundation (2 wks) | C4: =COUNTIF(Traceability_Matrix!$G$4:$G$150,"S1") | D4: =SUMIF(Traceability_Matrix!$G$4:$G$150,"S1",Traceability_Matrix!$E$4:$E$150) | E4: =COUNTIFS(Traceability_Matrix!$G$4:$G$150,"S1",Traceability_Matrix!$J$4:$J$150,"Done") | F4: =SUMIFS(Traceability_Matrix!$E$4:$E$150,Traceability_Matrix!$G$4:$G$150,"S1",Traceability_Matrix!$J$4:$J$150,"Done") | G4: =IFERROR(F4/D4,0) | H4: AMBER — 3/4 stories done-in-code + infra; live install pending (Senthil) | I4: App installs cleanly in dev store/org; telemetry firing
A5: S2 | B5: Handover threads pt 1 | C5: =COUNTIF(Traceability_Matrix!$G$4:$G$150,"S2") | D5: =SUMIF(Traceability_Matrix!$G$4:$G$150,"S2",Traceability_Matrix!$E$4:$E$150) | E5: =COUNTIFS(Traceability_Matrix!$G$4:$G$150,"S2",Traceability_Matrix!$J$4:$J$150,"Done") | F5: =SUMIFS(Traceability_Matrix!$E$4:$E$150,Traceability_Matrix!$G$4:$G$150,"S2",Traceability_Matrix!$J$4:$J$150,"Done") | G5: =IFERROR(F5/D5,0) | H5: GREEN — all 6 done | I5: Handover happy path demoable
A6: S3 | B6: Handover pt 2 + Approvals start | C6: =COUNTIF(Traceability_Matrix!$G$4:$G$150,"S3") | D6: =SUMIF(Traceability_Matrix!$G$4:$G$150,"S3",Traceability_Matrix!$E$4:$E$150) | E6: =COUNTIFS(Traceability_Matrix!$G$4:$G$150,"S3",Traceability_Matrix!$J$4:$J$150,"Done") | F6: =SUMIFS(Traceability_Matrix!$E$4:$E$150,Traceability_Matrix!$G$4:$G$150,"S3",Traceability_Matrix!$J$4:$J$150,"Done") | G6: =IFERROR(F6/D6,0) | H6: GREEN — 10/11; live surface story pending | I6: Handover complete with tests; approvals skeleton
A7: S4 | B7: Approval workflows | C7: =COUNTIF(Traceability_Matrix!$G$4:$G$150,"S4") | D7: =SUMIF(Traceability_Matrix!$G$4:$G$150,"S4",Traceability_Matrix!$E$4:$E$150) | E7: =COUNTIFS(Traceability_Matrix!$G$4:$G$150,"S4",Traceability_Matrix!$J$4:$J$150,"Done") | F7: =SUMIFS(Traceability_Matrix!$E$4:$E$150,Traceability_Matrix!$G$4:$G$150,"S4",Traceability_Matrix!$J$4:$J$150,"Done") | G7: =IFERROR(F7/D7,0) | H7: GREEN — 8/9; live surface story pending | I7: MVP loop usable end-to-end internally
A8: S5 | B8: Checklists + alpha hardening | C8: =COUNTIF(Traceability_Matrix!$G$4:$G$150,"S5") | D8: =SUMIF(Traceability_Matrix!$G$4:$G$150,"S5",Traceability_Matrix!$E$4:$E$150) | E8: =COUNTIFS(Traceability_Matrix!$G$4:$G$150,"S5",Traceability_Matrix!$J$4:$J$150,"Done") | F8: =SUMIFS(Traceability_Matrix!$E$4:$E$150,Traceability_Matrix!$G$4:$G$150,"S5",Traceability_Matrix!$J$4:$J$150,"Done") | G8: =IFERROR(F8/D8,0) | H8: AMBER — code done; live dogfooding pending | I8: Internal alpha: team dogfoods daily
A9: S6 | B9: Billing + Kudos | C9: =COUNTIF(Traceability_Matrix!$G$4:$G$150,"S6") | D9: =SUMIF(Traceability_Matrix!$G$4:$G$150,"S6",Traceability_Matrix!$E$4:$E$150) | E9: =COUNTIFS(Traceability_Matrix!$G$4:$G$150,"S6",Traceability_Matrix!$J$4:$J$150,"Done") | F9: =SUMIFS(Traceability_Matrix!$E$4:$E$150,Traceability_Matrix!$G$4:$G$150,"S6",Traceability_Matrix!$J$4:$J$150,"Done") | G9: =IFERROR(F9/D9,0) | H9: AMBER — billing logic done; marketplace rail live pending | I9: Can charge a test customer; up/downgrade paths work
A10: S7 | B10: Private beta (design partners) | C10: =COUNTIF(Traceability_Matrix!$G$4:$G$150,"S7") | D10: =SUMIF(Traceability_Matrix!$G$4:$G$150,"S7",Traceability_Matrix!$E$4:$E$150) | E10: =COUNTIFS(Traceability_Matrix!$G$4:$G$150,"S7",Traceability_Matrix!$J$4:$J$150,"Done") | F10: =SUMIFS(Traceability_Matrix!$E$4:$E$150,Traceability_Matrix!$G$4:$G$150,"S7",Traceability_Matrix!$J$4:$J$150,"Done") | G10: =IFERROR(F10/D10,0) | H10: AMBER — all code done; partners = human-dependent | I10: 3+ partners active weekly; NPS pulse >30
A11: S8 | B11: Beta iteration + Manager dashboard | C11: =COUNTIF(Traceability_Matrix!$G$4:$G$150,"S8") | D11: =SUMIF(Traceability_Matrix!$G$4:$G$150,"S8",Traceability_Matrix!$E$4:$E$150) | E11: =COUNTIFS(Traceability_Matrix!$G$4:$G$150,"S8",Traceability_Matrix!$J$4:$J$150,"Done") | F11: =SUMIFS(Traceability_Matrix!$E$4:$E$150,Traceability_Matrix!$G$4:$G$150,"S8",Traceability_Matrix!$J$4:$J$150,"Done") | G11: =IFERROR(F11/D11,0) | H11: AMBER — 18/22; live infra items remain | I11: Beta cohort WoW retention >60%
A12: S9 | B12: Marketplace review prep | C12: =COUNTIF(Traceability_Matrix!$G$4:$G$150,"S9") | D12: =SUMIF(Traceability_Matrix!$G$4:$G$150,"S9",Traceability_Matrix!$E$4:$E$150) | E12: =COUNTIFS(Traceability_Matrix!$G$4:$G$150,"S9",Traceability_Matrix!$J$4:$J$150,"Done") | F12: =SUMIFS(Traceability_Matrix!$E$4:$E$150,Traceability_Matrix!$G$4:$G$150,"S9",Traceability_Matrix!$J$4:$J$150,"Done") | G12: =IFERROR(F12/D12,0) | H12: AMBER — a11y automated + dry-run done; pen test + assets open | I12: Review submission accepted into queue
A13: S10 | B13: Review remediation + docs | C13: =COUNTIF(Traceability_Matrix!$G$4:$G$150,"S10") | D13: =SUMIF(Traceability_Matrix!$G$4:$G$150,"S10",Traceability_Matrix!$E$4:$E$150) | E13: =COUNTIFS(Traceability_Matrix!$G$4:$G$150,"S10",Traceability_Matrix!$J$4:$J$150,"Done") | F13: =SUMIFS(Traceability_Matrix!$E$4:$E$150,Traceability_Matrix!$G$4:$G$150,"S10",Traceability_Matrix!$J$4:$J$150,"Done") | G13: =IFERROR(F13/D13,0) | H13: AMBER — content drafted, publishing pending | I13: Marketplace approval obtained
A14: S11 | B14: Launch | C14: =COUNTIF(Traceability_Matrix!$G$4:$G$150,"S11") | D14: =SUMIF(Traceability_Matrix!$G$4:$G$150,"S11",Traceability_Matrix!$E$4:$E$150) | E14: =COUNTIFS(Traceability_Matrix!$G$4:$G$150,"S11",Traceability_Matrix!$J$4:$J$150,"Done") | F14: =SUMIFS(Traceability_Matrix!$E$4:$E$150,Traceability_Matrix!$G$4:$G$150,"S11",Traceability_Matrix!$J$4:$J$150,"Done") | G14: =IFERROR(F14/D14,0) | H14: RED — listing + installs gate everything | I14: First 10 installs; first 3 reviews; activation >40%
A15: S12 | B15: Iterate & scale decision | C15: =COUNTIF(Traceability_Matrix!$G$4:$G$150,"S12") | D15: =SUMIF(Traceability_Matrix!$G$4:$G$150,"S12",Traceability_Matrix!$E$4:$E$150) | E15: =COUNTIFS(Traceability_Matrix!$G$4:$G$150,"S12",Traceability_Matrix!$J$4:$J$150,"Done") | F15: =SUMIFS(Traceability_Matrix!$E$4:$E$150,Traceability_Matrix!$G$4:$G$150,"S12",Traceability_Matrix!$J$4:$J$150,"Done") | G15: =IFERROR(F15/D15,0) | H15: RED — not started | I15: Growth model doc with CAC/LTV first estimates
A16: S13 | B16: Trust boundaries for real | C16: =COUNTIF(Traceability_Matrix!$G$4:$G$150,"S13") | D16: =SUMIF(Traceability_Matrix!$G$4:$G$150,"S13",Traceability_Matrix!$E$4:$E$150) | E16: =COUNTIFS(Traceability_Matrix!$G$4:$G$150,"S13",Traceability_Matrix!$J$4:$J$150,"Done") | F16: =SUMIFS(Traceability_Matrix!$E$4:$E$150,Traceability_Matrix!$G$4:$G$150,"S13",Traceability_Matrix!$J$4:$J$150,"Done") | G16: =IFERROR(F16/D16,0) | H16: GREEN — 7/7 Done; the three trust CRITICALs are closed in code and asserted at boot | I16: A teams dev tenant loads the tab with a real entra token and the bot answers a real message, with the dev bypass disabled
A17: S14 | B17: Durability for real | C17: =COUNTIF(Traceability_Matrix!$G$4:$G$150,"S14") | D17: =SUMIF(Traceability_Matrix!$G$4:$G$150,"S14",Traceability_Matrix!$E$4:$E$150) | E17: =COUNTIFS(Traceability_Matrix!$G$4:$G$150,"S14",Traceability_Matrix!$J$4:$J$150,"Done") | F17: =SUMIFS(Traceability_Matrix!$E$4:$E$150,Traceability_Matrix!$G$4:$G$150,"S14",Traceability_Matrix!$J$4:$J$150,"Done") | G17: =IFERROR(F17/D17,0) | H17: GREEN — 8/8 Done; proven against a real Postgres 16, not a fake; drill PASS at RPO 0s / RTO 0s | I17: Restart, two-instance and restore drills run green in ci against real postgres, unattended
A18: S15 | B18: Scale and data model | C18: =COUNTIF(Traceability_Matrix!$G$4:$G$150,"S15") | D18: =SUMIF(Traceability_Matrix!$G$4:$G$150,"S15",Traceability_Matrix!$E$4:$E$150) | E18: =COUNTIFS(Traceability_Matrix!$G$4:$G$150,"S15",Traceability_Matrix!$J$4:$J$150,"Done") | F18: =SUMIFS(Traceability_Matrix!$E$4:$E$150,Traceability_Matrix!$G$4:$G$150,"S15",Traceability_Matrix!$J$4:$J$150,"Done") | G18: =IFERROR(F18/D18,0) | H18: AMBER — 4/6 Done; SD219/SD220 need staging infrastructure before any number can be claimed (LC-8) | I18: 5x load sweep passes on staging with per-record persistence and published numbers
A19: S16 | B19: Teams-native experience | C19: =COUNTIF(Traceability_Matrix!$G$4:$G$150,"S16") | D19: =SUMIF(Traceability_Matrix!$G$4:$G$150,"S16",Traceability_Matrix!$E$4:$E$150) | E19: =COUNTIFS(Traceability_Matrix!$G$4:$G$150,"S16",Traceability_Matrix!$J$4:$J$150,"Done") | F19: =SUMIFS(Traceability_Matrix!$E$4:$E$150,Traceability_Matrix!$G$4:$G$150,"S16",Traceability_Matrix!$J$4:$J$150,"Done") | G19: =IFERROR(F19/D19,0) | H19: AMBER — 2/6 Done; cards, proactive push and the channel tab are live-client facts; the mobile pass is Senthil (VER-SD01) | I19: End-to-end handover completed on teams mobile using cards, with the acknowledgement nudge arriving proactively
A20: S17 | B20: Enterprise admin and governance | C20: =COUNTIF(Traceability_Matrix!$G$4:$G$150,"S17") | D20: =SUMIF(Traceability_Matrix!$G$4:$G$150,"S17",Traceability_Matrix!$E$4:$E$150) | E20: =COUNTIFS(Traceability_Matrix!$G$4:$G$150,"S17",Traceability_Matrix!$J$4:$J$150,"Done") | F20: =SUMIFS(Traceability_Matrix!$E$4:$E$150,Traceability_Matrix!$G$4:$G$150,"S17",Traceability_Matrix!$J$4:$J$150,"Done") | G20: =IFERROR(F20/D20,0) | H20: AMBER — 2/6 Done; consent in two tenants, a real vault and the tabletop remain | I20: An it-admin dry run (install, consent, rollout, export, delete) completed by someone who did not build it
A21: S18 | B21: Assurance and certification | C21: =COUNTIF(Traceability_Matrix!$G$4:$G$150,"S18") | D21: =SUMIF(Traceability_Matrix!$G$4:$G$150,"S18",Traceability_Matrix!$E$4:$E$150) | E21: =COUNTIFS(Traceability_Matrix!$G$4:$G$150,"S18",Traceability_Matrix!$J$4:$J$150,"Done") | F21: =SUMIFS(Traceability_Matrix!$E$4:$E$150,Traceability_Matrix!$G$4:$G$150,"S18",Traceability_Matrix!$J$4:$J$150,"Done") | G21: =IFERROR(F21/D21,0) | H21: RED — 1/5 Done; four of five items are irreducibly human: pen test, attestation, SOC 2 engagement, manual a11y | I21: Attestation submitted, pen-test highs closed, accessibility audit signed
A22: S19 | B22: Commercial machinery and observability | C22: =COUNTIF(Traceability_Matrix!$G$4:$G$150,"S19") | D22: =SUMIF(Traceability_Matrix!$G$4:$G$150,"S19",Traceability_Matrix!$E$4:$E$150) | E22: =COUNTIFS(Traceability_Matrix!$G$4:$G$150,"S19",Traceability_Matrix!$J$4:$J$150,"Done") | F22: =SUMIFS(Traceability_Matrix!$E$4:$E$150,Traceability_Matrix!$G$4:$G$150,"S19",Traceability_Matrix!$J$4:$J$150,"Done") | G22: =IFERROR(F22/D22,0) | H22: RED — 1/5 Done; fulfillment and the sinks are built; a real transaction and a real DSN are not | I22: A test customer transacts through the marketplace and the entitlement is enforced end to end
A23: S20 | B23: Demand validation and go/no-go | C23: =COUNTIF(Traceability_Matrix!$G$4:$G$150,"S20") | D23: =SUMIF(Traceability_Matrix!$G$4:$G$150,"S20",Traceability_Matrix!$E$4:$E$150) | E23: =COUNTIFS(Traceability_Matrix!$G$4:$G$150,"S20",Traceability_Matrix!$J$4:$J$150,"Done") | F23: =SUMIFS(Traceability_Matrix!$E$4:$E$150,Traceability_Matrix!$G$4:$G$150,"S20",Traceability_Matrix!$J$4:$J$150,"Done") | G23: =IFERROR(F23/D23,0) | H23: RED — 1/4 Done; the interviews and the five paid pilots are the programme gate and no code substitutes | I23: G-01/g-02 become achievable on evidence, or kill criteria fire
A24: TOTAL | B24: (S1-S20) | C24: =SUM(C4:C23) | D24: =SUM(D4:D23) | E24: =SUM(E4:E23) | F24: =SUM(F4:F23) | G24: =IFERROR(F24/D24,0)
A26: BY STATUS (all 147 stories)
A27: Done | B27: stories / points | C27: =COUNTIF(Traceability_Matrix!$J$4:$J$150,"Done") | D27: =SUMIF(Traceability_Matrix!$J$4:$J$150,"Done",Traceability_Matrix!$E$4:$E$150)
A28: Code-complete pending live | B28: stories / points | C28: =COUNTIF(Traceability_Matrix!$J$4:$J$150,"Code-complete pending live") | D28: =SUMIF(Traceability_Matrix!$J$4:$J$150,"Code-complete pending live",Traceability_Matrix!$E$4:$E$150)
A29: In progress | B29: stories / points | C29: =COUNTIF(Traceability_Matrix!$J$4:$J$150,"In progress") | D29: =SUMIF(Traceability_Matrix!$J$4:$J$150,"In progress",Traceability_Matrix!$E$4:$E$150)
A30: Drafted | B30: stories / points | C30: =COUNTIF(Traceability_Matrix!$J$4:$J$150,"Drafted") | D30: =SUMIF(Traceability_Matrix!$J$4:$J$150,"Drafted",Traceability_Matrix!$E$4:$E$150)
A31: To do — Senthil | B31: stories / points | C31: =COUNTIF(Traceability_Matrix!$J$4:$J$150,"To do — Senthil") | D31: =SUMIF(Traceability_Matrix!$J$4:$J$150,"To do — Senthil",Traceability_Matrix!$E$4:$E$150)
A32: To do | B32: stories / points | C32: =COUNTIF(Traceability_Matrix!$J$4:$J$150,"To do") | D32: =SUMIF(Traceability_Matrix!$J$4:$J$150,"To do",Traceability_Matrix!$E$4:$E$150)
A33: Backlog | B33: stories / points | C33: =COUNTIF(Traceability_Matrix!$J$4:$J$150,"Backlog") | D33: =SUMIF(Traceability_Matrix!$J$4:$J$150,"Backlog",Traceability_Matrix!$E$4:$E$150)
A35: CHECK | B35: status rows must sum to the matrix row count, and points must sum to the sprint total | C35: =IF(AND(SUM(C27:C33)=COUNTA(Traceability_Matrix!$A$4:$A$150),SUM(D27:D33)=D24),"OK","MISMATCH")

Sheet RAID_Carryover
A1: RAID — seeded from workbook v005 Risk_Register + build findings
A2: ID | B2: Type | C2: Raised | D2: Item | E2: Status | F2: Notes / Mitigation
A3: R-S1 | B3: Risk | C3: v005 | D3: Teams store certification loops exceed 2 cycles (Medium/High) | E3: Open | F3: Pre-submission consult; validation checklist owner in S8; dry-run already recorded in Launch_Checklist (ST-097).
A4: R-S2 | B4: Risk | C4: v005 | D4: Microsoft ships native Shifts upgrades (High/Medium) — and, per review finding D-04, already ships Approvals and Planner free inside Microsoft 365, so the real competitor is zero marginal cost rather than a future release | E4: Open — repositioned | F4: Repositioned onto the auditable-evidence wedge: retained, queryable handover evidence with an audit trail, which the free first-party tools do not produce. Listing copy, one-pager and comparison pages rewritten explicitly against Approvals and Planner (SD245); per-site pricing modelled so the price is not a per-seat tax on top of a suite the customer already owns (SD246). The wedge is tested in the SD244 interviews before launch spend.
A5: R-S3 | B5: Risk | C5: v005 | D5: Enterprise sales cycle starves cash before S12 (High/Medium) | E5: Open | F5: Pilot pricing; design-partner LOIs by S7; per-frontline-seat wedge under WFM suites.
A6: R-S4 | B6: Constraint | C6: 22:26 | D6: Sandbox has no Postgres/Microsoft credentials — persistence in-memory behind typed repositories; Bot Framework/Graph + marketplace billing mocked at PlatformGateway seam | E6: Corrected | F6: The "typed repositories" this entry claimed did not exist until session 15 (GAP-SD8). Seam now built with in-memory and Postgres implementations under one contract suite; the live swap really is wiring plus a migration run.
A7: R-S5 | B7: Risk | C7: 22:26 | D7: Teams manifest/SSO validation rules assumed from public guidelines; not yet validated against a live tenant | E7: Open | F7: Verify at S1-07 with Partner Center + dev tenant; self-check drafted in Launch_Checklist #2.
A8: R-S6 | B8: Risk | C8: 22:54 | D8: WCAG evidence is automated-only (jest-axe, 9 screens); Teams store requires accessibility on live tab surfaces | E8: Open | F8: Manual audit on live UI after S1-07; a11y suite stays as CI regression net.
A9: A-S1 | B9: Assumption | C9: 22:26 | D9: D13 (interviews parked, 100% coverage) applies to ShiftDesk as portfolio-wide | E9: Open | F9: Per Senthil 20:45/22:26 instructions; S0 activities re-enter at workbook v-next if interviews resume.
A10: A-S2 | B10: Assumption | C10: 22:26 | D10: D15 mode (hold-serial vs formal-parallel) pending across eight concurrent builds | E10: Open | F10: Senthil to ratify; consolidated in portfolio action board (23:03).
A11: A-S3 | B11: Assumption | C11: 22:54 | D11: 3% Microsoft transactable fee + AppSource private offers per v005 financial model | E11: Open | F11: Verify fee terms during Partner Center offer setup (Launch_Checklist #6).
A12: R-S7 | B12: Risk | C12: 12:51 | D12: CSV importer (moduleBase.importCsv) is naive comma-split — quoted fields with commas would mis-parse on import; flagged as cold-review pass-2 candidate | E12: Closed | F12: F-010 pass-2 fix: RFC-4180 parser in importCsv, regression pinned (tests/reviewPass2.test.ts).
A13: R-S8 | B13: Risk | C13: 13/09 09:52 | D13: Sandbox cannot prove in-client behaviour: the TeamsJS handshake, RSC consent screen, and tab rendering are verifiable only inside a real Teams client (VER-SD08 was invisible to a 100%-covered suite) | E13: Open | F13: 14-step live sweep on the dev tenant is the proving instrument; treat its report as the evidence of record for the 9 pending-live stories.
... A27: A-S4 | B27: Assumption | C27: 20/09 13:05 | D27: Microsoft Fulfillment API v2, Entra OpenID metadata, Bot Connector issuer/audience rules and Key Vault managed-identity flows were implemented from vendor documentation, not against live endpoints. | E27: Open | F27: Same class as R-S12, which is why that risk exists: every one of these seams gets a documentation sweep and a live verification before it is called done. SD228/SD232/SD239/SD240 are the verification stories.

Sheet Gate_Checklist
A1: COMPLETION GATE (D7) — ShiftDesk is DONE only when every row closes
A2: R2: code complete counts for nothing. Gate decision = Senthil, on evidence Claude prepares.
A3: ID | B3: Gate item | C3: Source | D3: Status
A4: G-01 | B4: App LISTED on Microsoft Teams App Store / AppSource (approved + published) | C4: D7 / R2 | D4: Open
A5: G-02 | B5: 10 PAYING installs from strangers | C5: D7 / R2 | D5: Open
A6: G-03 | B6: S12 kill criteria evaluated with evidence pack | C6: D7 / R3 | D6: Open
A7: G-04 | B7: Kill/continue decision recorded by Senthil | C7: R5 / D10 | D7: Open
A8: G-05 | B8: On CONTINUE: next-rank build authorised; ShiftDesk enters run-mode | C8: N4 / R1 | D8: Open
A9: LC-1 | B9: Partner Center enrollment + publisher verification | C9: v005 LC #1 | D9: Open — Senthil
A10: LC-2 | B10: Teams store validation self-check (manifest, SSO, bot responsiveness) | C10: v005 LC #2 | D10: Manifest v1.19 with configurable channel tab, 8 commands and localizationInfo; command parity and manifest-vs-code assertions in CI. Live tenant validation pending (SD226).
A11: LC-3 | B11: M365 App Compliance: Publisher Attestation submitted | C11: v005 LC #3 | D11: Evidence pack assembled (SD236) and SOC 2 readiness mapped (SD237 map), each control bound to an existing evidence path by test. Submission itself open — Senthil (SD235).
A12: LC-4 | B12: Entra ID SSO + admin consent tested in 2 tenants | C12: v005 LC #4 | D12: Blocked — needs 2 live tenants (SD228). Scope map pinned to consumer files by test so the consent screen cannot exceed the documented ask.
A13: LC-5 | B13: Graph permissions minimal + documented | C13: v005 LC #5 | D13: REOPENED then corrected (VER-SD04): was Done on an overstated org-wide scope doc; now RSC-scoped + test-pinned, live consent verification pending
A14: LC-6 | B14: AppSource transactable offer configured (3% fee, private offers) | C14: v005 LC #6 | D14: Open — Senthil (Partner Center)
... A21: LC-13 | B21: Durability proven: restart, two-instance and backup/restore drills green against real Postgres | C21: Review P-003 / SD211, SD214, SD215 | D21: Done — 9/9 integration tests and a drill report at RPO 0s / RTO 0s. Staging repeat expected once infrastructure exists.
