Workbook

Sheet Cover
A1: FlowCast (Xero) — Version Detail & Manual Test Workbook
A3: Document | B3: claude_V001_MoPr03-flowcast_xero_versiondetail_manualtest_20260920_1059.xlsx
A4: Project code | B4: 003-MoPr03-flowcast_xero (marketplace portfolio rank 12, Xero App Store)
A5: Document version | B5: V001
A6: Date / time | B6: 20 September 2026, 10:59 BST
A7: Author | B7: Claude for Senthil/KP
A8: Status | B8: Released — for Senthil review; test results columns are blank and yellow until executed
A9: Purpose | B9: One place that records, for every version of the product workbook (v001–v036) and the sprint tracker (v001–v024): what was done, why it was done, and the evidence; which versions are pending and why; and a manual test pack — several positive and negative cases per code-bearing version — with step-by-step instructions, expected results and space to record actuals.
A10: Source artefacts | B10: Product workbook v036 Version_Control · Sprint tracker v024 Version_Control, Traceability_Matrix, Review_Findings, External_Review_FC/PPX · flowcast_v036_codebase_and_docs.zip (code v0.30.0, RELEASE_NOTES_v034/v035/v036, gates/README.md) · Perplexity V001 and ChatGPT V001 reviews
A11: Companion document | B11: claude_v001_MoPr03-flowcast_xero_product_explainer_20260920_1059 (.docx / .html) with the four diagrams
A12: Test environment (sandbox) | B12: Node 22, npm 10; unzip flowcast_v036_codebase_and_docs.zip; cd flowcast; npm ci. No Xero organisation, no Postgres, no Stripe. Live cases are written in full and marked BLOCKED with the blocker named.
A13: Result vocabulary | B13: Pass · Fail · Blocked (needs an environment or decision named in the case) · Not run
A14: Sheets | B14: Version_Control · Context · How_To_Use · Summary · Version_Detail · Pending_Versions · Manual_Test_Cases · Test_Execution_Log · Test_Traceability · Defect_Log · Sign_Off · Glossary

Sheet Version_Control
A1: VERSION CONTROL — this workbook
A2: File naming: claude_V<NNN>_<name>_YYYYMMDD_HHMI. Nothing is deleted between versions; superseded rows are marked.
A4: Version | B4: Date/Time | C4: Author | D4: Change description | E4: Status
A5: V001 | B5: 2026-09-20 10:59 | C5: Claude for Senthil/KP | D5: First release. Version_Detail for workbook v001–v036 and tracker v001–v024; Pending_Versions; 91 manual test cases across 28 versions (positive + negative; sandbox-runnable, live cases marked BLOCKED); execution log, traceability, defect log, sign-off, glossary. Results not yet executed. | E5: Released
A6: V002 | B6: PLANNED | C6: — | D6: Opens on the first test execution pass (results recorded), or on workbook v037 / tracker v025. | E6: Planned

Sheet Context
A1: CONTEXT
A2: FlowCast is a Xero App Store product: 13-week cash forecast with traffic lights, scenario sliders, invoice-chasing nudges, bank-feed anomaly alerts and an accountant multi-client portal. It was built in a sandbox between 5 and 20 September 2026 under D13 (100% automated coverage, zero pragmas) through 36 product-workbook versions and 24 tracker versions, with two independent external AI reviews.
A3: Two facts sit side by side. The automated evidence is strong: 49 Jest suites / 719 tests at 100% on statements, branches, functions and lines; 14 gate files whose 15 mutations each reintroduce a real shipped defect and make the gate fail. And nothing — no version, no test — has ever run against a real Xero organisation, a real Postgres cluster or two real nodes.
A4: This workbook therefore separates three things carefully. Version_Detail records what each version changed and WHY (the finding, decision or review that caused it). Pending_Versions records what has not happened and the exact blocker. Manual_Test_Cases gives a human a repeatable way to confirm each version's claims — most in the sandbox today, the rest written out and marked BLOCKED so the first live day has a script.
A5: Status vocabulary (D-F2): Done = code + 100% tests + a gate that fails under the original defect. Code-complete — pending live = the same but only provable against a live org. Drafted = a document exists, unpublished. Not started = nothing exists. The story baseline stays at 77/100 Done by Senthil's instruction of 20 Sep 2026; every correction since sits on the enhancement pool with a stated reason.
A6: Manual testing here means: a person follows the steps, observes, and records. The automated suite is itself one of the things under test (the "the suite passes" cases), because an external reviewer once could not run it and rightly refused to accept the numbers (FC-R005).

Sheet How_To_Use
A1: HOW TO USE THIS WORKBOOK
A2: Summary | B2: Live counts (formulas) over Manual_Test_Cases and Test_Execution_Log. Do not type into it.
A3: Version_Detail | B3: One row per version (workbook v001–v036, then tracker v001–v024). Read left to right: what, why, evidence, code version, test cases that cover it. Filter by Artefact or Type.
A4: Pending_Versions | B4: Versions and work packages that do not exist yet, with the reason and who unblocks them. When one opens, move nothing — add the released row to Version_Detail and mark this row "Opened in <version>".
A5: Manual_Test_Cases | B5: The test pack. One row per case; a version has several. Columns: ID, Version, Story/Finding it verifies, Title, Type (Positive/Negative), Mode (Sandbox / Live — BLOCKED / Doc review), Preconditions, Steps (numbered, one action per line), Expected result, then the YELLOW columns you fill in: Actual result, Result (Pass/Fail/Blocked/Not run — drop-down), Tester, Date, Defect ID, Notes.
A6: Test_Execution_Log | B6: Append one row per execution run (a case can be run many times). Reference the case ID; the Summary counts the latest status per case from Manual_Test_Cases, not from this log.
A7: Test_Traceability | B7: Case → version → story / finding → gate. Use it to answer "what covers PPX-02?" or "which cases must re-run when v037 ships?".
A8: Defect_Log | B8: Anything a manual case finds that the suite did not. Give it an MT-nnn id, link the case, and — when it is fixed — the version that fixed it and the regression test added. Never delete a row.
A9: Sign_Off | B9: Per version: who executed, who reviewed, verdict. Blank until executed.
A10: Sandbox setup (once) | B10: 1. unzip flowcast_v036_codebase_and_docs.zip && cd flowcast 2. npm ci 3. npx tsc --noEmit 4. npm test (expect 49 suites / 719 tests, 100% on four metrics) 5. npm run prove:gates (expect 15 PROVED). Older versions are tested through the current code: a case for v014 checks that v014's regression tests still exist and pass in v036, because every fix has been carried forward and nothing was deleted.
A11: Sandbox server | B11: export XERO_CLIENT_ID=x XERO_CLIENT_SECRET=y XERO_WEBHOOK_KEY=k OAUTH_REDIRECT_URI=https://localhost/cb BASE_URL=https://localhost BILLING_REGION=UK RELEASE=v036 FLOWCAST_OPERATOR_TOKEN=op FLOWCAST_DATA_KEY=$(node -e "console.log(require('crypto').randomBytes(32).toString('base64'))") NODE_ENV=development PORT=3000 && npm run build && npm start. Development mode boots without DATABASE_URL (in-memory store, single-process lock, per-process budget) and /health reports that honestly.
A12: Live cases | B12: Marked "Live — BLOCKED" with the blocker in Preconditions (Xero dev org, Postgres, Stripe, pen-test vendor, a decision). Record them as Blocked, never as Pass. They become the first-day script when the blocker clears.
A13: Rule | B13: A Pass needs the observed value written in Actual result. "As expected" is not an observation.

Sheet Summary
A1: SUMMARY — live counts over Manual_Test_Cases (do not edit)
A3: Version | B3: Cases | C3: Positive | D3: Negative | E3: Sandbox | F3: Live — BLOCKED | G3: Pass | H3: Fail | I3: Blocked | J3: Not run
A4: v008 | B4: =COUNTIF(Manual_Test_Cases!$B$5:$B$95,A4) -> 4 | C4: =COUNTIFS(Manual_Test_Cases!$B$5:$B$95,A4,Manual_Test_Cases!$E$5:$E$95,"Positive") -> 2 | D4: =COUNTIFS(Manual_Test_Cases!$B$5:$B$95,A4,Manual_Test_Cases!$E$5:$E$95,"Negative") -> 2 | E4: =COUNTIFS(Manual_Test_Cases!$B$5:$B$95,A4,Manual_Test_Cases!$F$5:$F$95,"Sandbox") -> 4 | F4: =COUNTIFS(Manual_Test_Cases!$B$5:$B$95,A4,Manual_Test_Cases!$F$5:$F$95,"Live — BLOCKED") -> 0 | G4: =COUNTIFS(Manual_Test_Cases!$B$5:$B$95,A4,Manual_Test_Cases!$K$5:$K$95,"Pass") -> 0 | H4: =COUNTIFS(Manual_Test_Cases!$B$5:$B$95,A4,Manual_Test_Cases!$K$5:$K$95,"Fail") -> 0 | I4: =COUNTIFS(Manual_Test_Cases!$B$5:$B$95,A4,Manual_Test_Cases!$K$5:$K$95,"Blocked") -> 0 | J4: =COUNTIFS(Manual_Test_Cases!$B$5:$B$95,A4,Manual_Test_Cases!$K$5:$K$95,"Not run") -> 4
A5: v009 | B5: =COUNTIF(Manual_Test_Cases!$B$5:$B$95,A5) -> 3 | C5: =COUNTIFS(Manual_Test_Cases!$B$5:$B$95,A5,Manual_Test_Cases!$E$5:$E$95,"Positive") -> 2 | D5: =COUNTIFS(Manual_Test_Cases!$B$5:$B$95,A5,Manual_Test_Cases!$E$5:$E$95,"Negative") -> 1 | E5: =COUNTIFS(Manual_Test_Cases!$B$5:$B$95,A5,Manual_Test_Cases!$F$5:$F$95,"Sandbox") -> 2 | F5: =COUNTIFS(Manual_Test_Cases!$B$5:$B$95,A5,Manual_Test_Cases!$F$5:$F$95,"Live — BLOCKED") -> 0 | G5: =COUNTIFS(Manual_Test_Cases!$B$5:$B$95,A5,Manual_Test_Cases!$K$5:$K$95,"Pass") -> 0 | H5: =COUNTIFS(Manual_Test_Cases!$B$5:$B$95,A5,Manual_Test_Cases!$K$5:$K$95,"Fail") -> 0 | I5: =COUNTIFS(Manual_Test_Cases!$B$5:$B$95,A5,Manual_Test_Cases!$K$5:$K$95,"Blocked") -> 0 | J5: =COUNTIFS(Manual_Test_Cases!$B$5:$B$95,A5,Manual_Test_Cases!$K$5:$K$95,"Not run") -> 3
A6: v010 | B6: =COUNTIF(Manual_Test_Cases!$B$5:$B$95,A6) -> 3 | C6: =COUNTIFS(Manual_Test_Cases!$B$5:$B$95,A6,Manual_Test_Cases!$E$5:$E$95,"Positive") -> 3 | D6: =COUNTIFS(Manual_Test_Cases!$B$5:$B$95,A6,Manual_Test_Cases!$E$5:$E$95,"Negative") -> 0 | E6: =COUNTIFS(Manual_Test_Cases!$B$5:$B$95,A6,Manual_Test_Cases!$F$5:$F$95,"Sandbox") -> 3 | F6: =COUNTIFS(Manual_Test_Cases!$B$5:$B$95,A6,Manual_Test_Cases!$F$5:$F$95,"Live — BLOCKED") -> 0 | G6: =COUNTIFS(Manual_Test_Cases!$B$5:$B$95,A6,Manual_Test_Cases!$K$5:$K$95,"Pass") -> 0 | H6: =COUNTIFS(Manual_Test_Cases!$B$5:$B$95,A6,Manual_Test_Cases!$K$5:$K$95,"Fail") -> 0 | I6: =COUNTIFS(Manual_Test_Cases!$B$5:$B$95,A6,Manual_Test_Cases!$K$5:$K$95,"Blocked") -> 0 | J6: =COUNTIFS(Manual_Test_Cases!$B$5:$B$95,A6,Manual_Test_Cases!$K$5:$K$95,"Not run") -> 3
A7: v011 | B7: =COUNTIF(Manual_Test_Cases!$B$5:$B$95,A7) -> 4 | C7: =COUNTIFS(Manual_Test_Cases!$B$5:$B$95,A7,Manual_Test_Cases!$E$5:$E$95,"Positive") -> 3 | D7: =COUNTIFS(Manual_Test_Cases!$B$5:$B$95,A7,Manual_Test_Cases!$E$5:$E$95,"Negative") -> 1 | E7: =COUNTIFS(Manual_Test_Cases!$B$5:$B$95,A7,Manual_Test_Cases!$F$5:$F$95,"Sandbox") -> 3 | F7: =COUNTIFS(Manual_Test_Cases!$B$5:$B$95,A7,Manual_Test_Cases!$F$5:$F$95,"Live — BLOCKED") -> 1 | G7: =COUNTIFS(Manual_Test_Cases!$B$5:$B$95,A7,Manual_Test_Cases!$K$5:$K$95,"Pass") -> 0 | H7: =COUNTIFS(Manual_Test_Cases!$B$5:$B$95,A7,Manual_Test_Cases!$K$5:$K$95,"Fail") -> 0 | I7: =COUNTIFS(Manual_Test_Cases!$B$5:$B$95,A7,Manual_Test_Cases!$K$5:$K$95,"Blocked") -> 0 | J7: =COUNTIFS(Manual_Test_Cases!$B$5:$B$95,A7,Manual_Test_Cases!$K$5:$K$95,"Not run") -> 4
A8: v012 | B8: =COUNTIF(Manual_Test_Cases!$B$5:$B$95,A8) -> 3 | C8: =COUNTIFS(Manual_Test_Cases!$B$5:$B$95,A8,Manual_Test_Cases!$E$5:$E$95,"Positive") -> 3 | D8: =COUNTIFS(Manual_Test_Cases!$B$5:$B$95,A8,Manual_Test_Cases!$E$5:$E$95,"Negative") -> 0 | E8: =COUNTIFS(Manual_Test_Cases!$B$5:$B$95,A8,Manual_Test_Cases!$F$5:$F$95,"Sandbox") -> 2 | F8: =COUNTIFS(Manual_Test_Cases!$B$5:$B$95,A8,Manual_Test_Cases!$F$5:$F$95,"Live — BLOCKED") -> 1 | G8: =COUNTIFS(Manual_Test_Cases!$B$5:$B$95,A8,Manual_Test_Cases!$K$5:$K$95,"Pass") -> 0 | H8: =COUNTIFS(Manual_Test_Cases!$B$5:$B$95,A8,Manual_Test_Cases!$K$5:$K$95,"Fail") -> 0 | I8: =COUNTIFS(Manual_Test_Cases!$B$5:$B$95,A8,Manual_Test_Cases!$K$5:$K$95,"Blocked") -> 0 | J8: =COUNTIFS(Manual_Test_Cases!$B$5:$B$95,A8,Manual_Test_Cases!$K$5:$K$95,"Not run") -> 3
A9: v013 | B9: =COUNTIF(Manual_Test_Cases!$B$5:$B$95,A9) -> 3 | C9: =COUNTIFS(Manual_Test_Cases!$B$5:$B$95,A9,Manual_Test_Cases!$E$5:$E$95,"Positive") -> 1 | D9: =COUNTIFS(Manual_Test_Cases!$B$5:$B$95,A9,Manual_Test_Cases!$E$5:$E$95,"Negative") -> 2 | E9: =COUNTIFS(Manual_Test_Cases!$B$5:$B$95,A9,Manual_Test_Cases!$F$5:$F$95,"Sandbox") -> 2 | F9: =COUNTIFS(Manual_Test_Cases!$B$5:$B$95,A9,Manual_Test_Cases!$F$5:$F$95,"Live — BLOCKED") -> 1 | G9: =COUNTIFS(Manual_Test_Cases!$B$5:$B$95,A9,Manual_Test_Cases!$K$5:$K$95,"Pass") -> 0 | H9: =COUNTIFS(Manual_Test_Cases!$B$5:$B$95,A9,Manual_Test_Cases!$K$5:$K$95,"Fail") -> 0 | I9: =COUNTIFS(Manual_Test_Cases!$B$5:$B$95,A9,Manual_Test_Cases!$K$5:$K$95,"Blocked") -> 0 | J9: =COUNTIFS(Manual_Test_Cases!$B$5:$B$95,A9,Manual_Test_Cases!$K$5:$K$95,"Not run") -> 3
A10: v014 | B10: =COUNTIF(Manual_Test_Cases!$B$5:$B$95,A10) -> 4 | C10: =COUNTIFS(Manual_Test_Cases!$B$5:$B$95,A10,Manual_Test_Cases!$E$5:$E$95,"Positive") -> 3 | D10: =COUNTIFS(Manual_Test_Cases!$B$5:$B$95,A10,Manual_Test_Cases!$E$5:$E$95,"Negative") -> 1 | E10: =COUNTIFS(Manual_Test_Cases!$B$5:$B$95,A10,Manual_Test_Cases!$F$5:$F$95,"Sandbox") -> 4 | F10: =COUNTIFS(Manual_Test_Cases!$B$5:$B$95,A10,Manual_Test_Cases!$F$5:$F$95,"Live — BLOCKED") -> 0 | G10: =COUNTIFS(Manual_Test_Cases!$B$5:$B$95,A10,Manual_Test_Cases!$K$5:$K$95,"Pass") -> 0 | H10: =COUNTIFS(Manual_Test_Cases!$B$5:$B$95,A10,Manual_Test_Cases!$K$5:$K$95,"Fail") -> 0 | I10: =COUNTIFS(Manual_Test_Cases!$B$5:$B$95,A10,Manual_Test_Cases!$K$5:$K$95,"Blocked") -> 0 | J10: =COUNTIFS(Manual_Test_Cases!$B$5:$B$95,A10,Manual_Test_Cases!$K$5:$K$95,"Not run") -> 4
A11: v015 | B11: =COUNTIF(Manual_Test_Cases!$B$5:$B$95,A11) -> 4 | C11: =COUNTIFS(Manual_Test_Cases!$B$5:$B$95,A11,Manual_Test_Cases!$E$5:$E$95,"Positive") -> 3 | D11: =COUNTIFS(Manual_Test_Cases!$B$5:$B$95,A11,Manual_Test_Cases!$E$5:$E$95,"Negative") -> 1 | E11: =COUNTIFS(Manual_Test_Cases!$B$5:$B$95,A11,Manual_Test_Cases!$F$5:$F$95,"Sandbox") -> 4 | F11: =COUNTIFS(Manual_Test_Cases!$B$5:$B$95,A11,Manual_Test_Cases!$F$5:$F$95,"Live — BLOCKED") -> 0 | G11: =COUNTIFS(Manual_Test_Cases!$B$5:$B$95,A11,Manual_Test_Cases!$K$5:$K$95,"Pass") -> 0 | H11: =COUNTIFS(Manual_Test_Cases!$B$5:$B$95,A11,Manual_Test_Cases!$K$5:$K$95,"Fail") -> 0 | I11: =COUNTIFS(Manual_Test_Cases!$B$5:$B$95,A11,Manual_Test_Cases!$K$5:$K$95,"Blocked") -> 0 | J11: =COUNTIFS(Manual_Test_Cases!$B$5:$B$95,A11,Manual_Test_Cases!$K$5:$K$95,"Not run") -> 4
A12: v016 | B12: =COUNTIF(Manual_Test_Cases!$B$5:$B$95,A12) -> 3 | C12: =COUNTIFS(Manual_Test_Cases!$B$5:$B$95,A12,Manual_Test_Cases!$E$5:$E$95,"Positive") -> 3 | D12: =COUNTIFS(Manual_Test_Cases!$B$5:$B$95,A12,Manual_Test_Cases!$E$5:$E$95,"Negative") -> 0 | E12: =COUNTIFS(Manual_Test_Cases!$B$5:$B$95,A12,Manual_Test_Cases!$F$5:$F$95,"Sandbox") -> 3 | F12: =COUNTIFS(Manual_Test_Cases!$B$5:$B$95,A12,Manual_Test_Cases!$F$5:$F$95,"Live — BLOCKED") -> 0 | G12: =COUNTIFS(Manual_Test_Cases!$B$5:$B$95,A12,Manual_Test_Cases!$K$5:$K$95,"Pass") -> 0 | H12: =COUNTIFS(Manual_Test_Cases!$B$5:$B$95,A12,Manual_Test_Cases!$K$5:$K$95,"Fail") -> 0 | I12: =COUNTIFS(Manual_Test_Cases!$B$5:$B$95,A12,Manual_Test_Cases!$K$5:$K$95,"Blocked") -> 0 | J12: =COUNTIFS(Manual_Test_Cases!$B$5:$B$95,A12,Manual_Test_Cases!$K$5:$K$95,"Not run") -> 3
A13: v017 | B13: =COUNTIF(Manual_Test_Cases!$B$5:$B$95,A13) -> 2 | C13: =COUNTIFS(Manual_Test_Cases!$B$5:$B$95,A13,Manual_Test_Cases!$E$5:$E$95,"Positive") -> 2 | D13: =COUNTIFS(Manual_Test_Cases!$B$5:$B$95,A13,Manual_Test_Cases!$E$5:$E$95,"Negative") -> 0 | E13: =COUNTIFS(Manual_Test_Cases!$B$5:$B$95,A13,Manual_Test_Cases!$F$5:$F$95,"Sandbox") -> 2 | F13: =COUNTIFS(Manual_Test_Cases!$B$5:$B$95,A13,Manual_Test_Cases!$F$5:$F$95,"Live — BLOCKED") -> 0 | G13: =COUNTIFS(Manual_Test_Cases!$B$5:$B$95,A13,Manual_Test_Cases!$K$5:$K$95,"Pass") -> 0 | H13: =COUNTIFS(Manual_Test_Cases!$B$5:$B$95,A13,Manual_Test_Cases!$K$5:$K$95,"Fail") -> 0 | I13: =COUNTIFS(Manual_Test_Cases!$B$5:$B$95,A13,Manual_Test_Cases!$K$5:$K$95,"Blocked") -> 0 | J13: =COUNTIFS(Manual_Test_Cases!$B$5:$B$95,A13,Manual_Test_Cases!$K$5:$K$95,"Not run") -> 2
A14: v018 | B14: =COUNTIF(Manual_Test_Cases!$B$5:$B$95,A14) -> 4 | C14: =COUNTIFS(Manual_Test_Cases!$B$5:$B$95,A14,Manual_Test_Cases!$E$5:$E$95,"Positive") -> 2 | D14: =COUNTIFS(Manual_Test_Cases!$B$5:$B$95,A14,Manual_Test_Cases!$E$5:$E$95,"Negative") -> 2 | E14: =COUNTIFS(Manual_Test_Cases!$B$5:$B$95,A14,Manual_Test_Cases!$F$5:$F$95,"Sandbox") -> 4 | F14: =COUNTIFS(Manual_Test_Cases!$B$5:$B$95,A14,Manual_Test_Cases!$F$5:$F$95,"Live — BLOCKED") -> 0 | G14: =COUNTIFS(Manual_Test_Cases!$B$5:$B$95,A14,Manual_Test_Cases!$K$5:$K$95,"Pass") -> 0 | H14: =COUNTIFS(Manual_Test_Cases!$B$5:$B$95,A14,Manual_Test_Cases!$K$5:$K$95,"Fail") -> 0 | I14: =COUNTIFS(Manual_Test_Cases!$B$5:$B$95,A14,Manual_Test_Cases!$K$5:$K$95,"Blocked") -> 0 | J14: =COUNTIFS(Manual_Test_Cases!$B$5:$B$95,A14,Manual_Test_Cases!$K$5:$K$95,"Not run") -> 4
A15: v019 | B15: =COUNTIF(Manual_Test_Cases!$B$5:$B$95,A15) -> 3 | C15: =COUNTIFS(Manual_Test_Cases!$B$5:$B$95,A15,Manual_Test_Cases!$E$5:$E$95,"Positive") -> 2 | D15: =COUNTIFS(Manual_Test_Cases!$B$5:$B$95,A15,Manual_Test_Cases!$E$5:$E$95,"Negative") -> 1 | E15: =COUNTIFS(Manual_Test_Cases!$B$5:$B$95,A15,Manual_Test_Cases!$F$5:$F$95,"Sandbox") -> 3 | F15: =COUNTIFS(Manual_Test_Cases!$B$5:$B$95,A15,Manual_Test_Cases!$F$5:$F$95,"Live — BLOCKED") -> 0 | G15: =COUNTIFS(Manual_Test_Cases!$B$5:$B$95,A15,Manual_Test_Cases!$K$5:$K$95,"Pass") -> 0 | H15: =COUNTIFS(Manual_Test_Cases!$B$5:$B$95,A15,Manual_Test_Cases!$K$5:$K$95,"Fail") -> 0 | I15: =COUNTIFS(Manual_Test_Cases!$B$5:$B$95,A15,Manual_Test_Cases!$K$5:$K$95,"Blocked") -> 0 | J15: =COUNTIFS(Manual_Test_Cases!$B$5:$B$95,A15,Manual_Test_Cases!$K$5:$K$95,"Not run") -> 3
... A31: v036 | B31: =COUNTIF(Manual_Test_Cases!$B$5:$B$95,A31) -> 21 | C31: =COUNTIFS(Manual_Test_Cases!$B$5:$B$95,A31,Manual_Test_Cases!$E$5:$E$95,"Positive") -> 14 | D31: =COUNTIFS(Manual_Test_Cases!$B$5:$B$95,A31,Manual_Test_Cases!$E$5:$E$95,"Negative") -> 7 | E31: =COUNTIFS(Manual_Test_Cases!$B$5:$B$95,A31,Manual_Test_Cases!$F$5:$F$95,"Sandbox") -> 18 | F31: =COUNTIFS(Manual_Test_Cases!$B$5:$B$95,A31,Manual_Test_Cases!$F$5:$F$95,"Live — BLOCKED") -> 3 | G31: =COUNTIFS(Manual_Test_Cases!$B$5:$B$95,A31,Manual_Test_Cases!$K$5:$K$95,"Pass") -> 0 | H31: =COUNTIFS(Manual_Test_Cases!$B$5:$B$95,A31,Manual_Test_Cases!$K$5:$K$95,"Fail") -> 0 | I31: =COUNTIFS(Manual_Test_Cases!$B$5:$B$95,A31,Manual_Test_Cases!$K$5:$K$95,"Blocked") -> 0 | J31: =COUNTIFS(Manual_Test_Cases!$B$5:$B$95,A31,Manual_Test_Cases!$K$5:$K$95,"Not run") -> 21
A32: TOTAL | B32: =SUM(B4:B31) -> 91 | C32: =SUM(C4:C31) -> 62 | D32: =SUM(D4:D31) -> 29 | E32: =SUM(E4:E31) -> 81 | F32: =SUM(F4:F31) -> 8 | G32: =SUM(G4:G31) -> 0 | H32: =SUM(H4:H31) -> 0 | I32: =SUM(I4:I31) -> 0 | J32: =SUM(J4:J31) -> 91
A34: Execution progress (% of cases with a Pass/Fail/Blocked recorded) | B34: =IFERROR(ROUND((G32+H32+I32)/B32*100,1),0) -> 0
A35: Versions covered by at least one case | B35: 28 | C35: (hardcoded count of distinct versions in the pack, V001)
A36: Doc-only versions (v001–v004, v007, v031) have no manual case by design: their artefacts are checked by the Doc review cases of the version that superseded them.

Sheet Version_Detail
A1: VERSION DETAIL — every version, what was done and why
A2: Product workbook v001–v036 followed by sprint tracker v001–v025. Descriptions are verbatim from each artefact's Version_Control; "Why" is the trigger recorded in the tracker log.
A4: Artefact | B4: Version | C4: Date/Time | D4: Type | E4: What was done (verbatim) | F4: Why it was done | G4: Code version | H4: Manual cases | I4: Status | J4: Evidence / where to look
A5: Product workbook | B5: v001-v004 | C5: 2026-09-05 | D5: Planning | E5: Lineage: marketplace master (868 entries) -> portfolio plan (12 products) -> wave-1 (RetainKit/ShiftDesk/EngageOS, v005) -> this product selected for wave-3 | F5: Portfolio selection: FlowCast chosen for wave 3 from the 868-entry marketplace master. | G5: — | H5: See Test_Traceability (filter Version) | I5: Released | J5: tracker v024 Version_Control / Release_Build_Boards; RELEASE_NOTES_v001-v004.md where present
A6: Product workbook | B6: v007 | C6: 2026-09-05 19:50 | D6: Product workbook | E6: Full product workbook for FlowCast on Xero App Store: spec, screen inventory, 100+ story backlog, live sprint board, 18-month financial model (editable assumptions), GTM execution tasks, platform launch checklist, metric targets, risk register | F6: Senthil directive to produce the full product workbook before any code (spec, backlog, model, GTM, checklist). | G6: — | H6: See Test_Traceability (filter Version) | I6: Released | J6: tracker v024 Version_Control / Release_Build_Boards; RELEASE_NOTES_v007.md where present
A7: Product workbook | B7: v008 | C7: 2026-09-10 22:01 | D7: Code | E7: Sprint_Tracker_Log + Traceability_Matrix sheets added; D13 100% coverage gate applied (ST-085 amended); S1 foundation + code-completable S2-S8 stories built in TypeScript with 11 Jest suites / 120 tests at 100% stmts/branches/funcs/lines; Full_Backlog statuses updated (58 Done, 4 pending-live, 2 in progress); portfolio D15 note logged | F7: D13 applied: build the code-completable stories with 100% coverage; tracker + traceability created by directive. | G7: 0.1.x | H7: See Test_Traceability (filter Version) | I7: Released | J7: tracker v024 Version_Control / Release_Build_Boards; RELEASE_NOTES_v008.md where present
A8: Product workbook | B8: v009 | C8: 2026-09-10 22:20 | D8: Code | E8: UI surfaces (5 React screens + MetricsPanel) with Xero deep links; ST-003 rule builder; notifications w/ per-type mute; pause toggles; portal rules; per-feature metrics/trends; CI workflow (ST-086). 13 suites / 148 tests at 100% coverage incl. components; statuses now 74 Done / 5 pending-live / 21 backlog | F8: Complete the feature surfaces and CI so every story has a screen or a metric. | G8: 0.2.x | H8: See Test_Traceability (filter Version) | I8: Released | J8: tracker v024 Version_Control / Release_Build_Boards; RELEASE_NOTES_v009.md where present
A9: Product workbook | B9: v010 | C9: 2026-09-10 22:27 | D9: Code + content | E9: Reliability + a11y code (latency budgets, degradation comms, jest-axe WCAG pass), demo-data mode, scenario/portal notification events; 12 content artifacts (15 help articles, chat SLA, video script, listing copy A/B, asset specs, pricing, trust page, dry-run gap report, 3 runbooks). 14 suites/155 tests at 100%. Dry-run found webhook build gap -> v011 | F9: Reliability, accessibility and launch content so the listing can be assembled without a live environment. | G9: 0.3.x | H9: See Test_Traceability (filter Version) | I9: Released | J9: tracker v024 Version_Control / Release_Build_Boards; RELEASE_NOTES_v010.md where present
A10: Product workbook | B10: v011 | C10: 2026-09-10 22:51 | D10: Code | E10: Content webhooks built (dry-run gap #4): signature verify, fast-ack idempotent queue, retry/dead-letter/heal, payment->cancel-nudges mapping; bank-txn 15-min polling (platform has no such webhook). Launch_Checklist statuses updated honestly. 15 suites / 170 tests at 100%. Sandbox work exhausted — remaining items need Senthil | F10: Submission dry-run gap #4: content webhooks were uncoded; Xero has no bank-txn webhook so polling is the substitute (D-F4). | G10: 0.4.x | H10: See Test_Traceability (filter Version) | I10: Released | J10: tracker v024 Version_Control / Release_Build_Boards; RELEASE_NOTES_v011.md where present
A11: Product workbook | B11: v012 | C11: 2026-09-10 22:56 | D11: Code | E11: Per-tenant 60/min rate limiter; 20-client + 12-month QA drills executed (found+fixed batch-isolation anomaly blind spot via detectWithHistory); k6 load harness (5x); blue/green deploy workflow; HTTP wiring layer. 16 suites / 182 tests at 100%. Backlog down to 4 (all require live infra/humans) | F11: Launch checklist items 3/7/8: rate limiting, QA drills; the 12-month drill found a real anomaly-detection blind spot. | G11: 0.5.x | H11: See Test_Traceability (filter Version) | I11: Released | J11: tracker v024 Version_Control / Release_Build_Boards; RELEASE_NOTES_v012.md where present
A12: Product workbook | B12: v013 | C12: 2026-09-10 23:03 | D12: Code + docs | E12: Live-sweep readiness: typed config loader + .env.example, 30-min dev-org setup guide, 12-step scripted verification sweep. Portfolio action board issued as separate workbook. 17 suites / 186 tests at 100% | F12: Make the live sweep executable: typed config, dev-org guide, scripted 12-step sweep. | G12: 0.6.x | H12: See Test_Traceability (filter Version) | I12: Released | J12: tracker v024 Version_Control / Release_Build_Boards; RELEASE_NOTES_v013.md where present
A13: Product workbook | B13: v014 | C13: 2026-09-11 11:09 | D13: Cold review + fixes | E13: Cold-review pass 1: 5 defects found + fixed with regression tests (F-001 unbounded webhook idempotency ledger -> FIFO 10k; F-002 signed-but-malformed payload crashed fast-ack -> guarded parse; F-003 rate-limiter idle tenants never evicted -> prune(); F-004 duplicate anomaly repeated per txn with 3+ matches -> deduped; F-005 nudgesPerMonth had no cycle-scoped counter/reset -> UsageCycle built). ST-066 encryption at rest built (AES-256-GCM envelope, SecretsVault boundary, token sealing, TLS assertion, self-verifying evidence drill). Security evidence pack (sandbox half of ST-068) + REVIEW_PACK.md for external second reviewer. 18 suites / 207 tests at 100% zero pragmas; tsc clean. Review_Findings sheet added for Senthil dispositions | F13: First cold review: read the code as a stranger; 5 defects (F-001..F-005) and encryption at rest (ST-066). | G13: 0.7.x | H13: See Test_Traceability (filter Version) | I13: Released | J13: tracker v024 Version_Control / Release_Build_Boards; RELEASE_NOTES_v014.md where present
A14: Product workbook | B14: v015 | C14: 2026-09-11 12:47 | D14: Cold review + fixes | E14: Cold-review pass 2 (the 10 modules pass 1 did not deep-read): 4 defects found + fixed with regressions — F-006 nudge planner re-sent the same tier daily (no sent-history) -> SentHistory, tier fires once, test-mode not recorded, failed sends retried; F-007 purgeExpired flagged accounts but never deleted the record -> record deleted (data deletion honoured), purged status removed; F-008 non-finite platform dates silently dropped items from the forecast -> validated with clear errors, plus traffic light now judged on displayed rounded balance; F-009 monthly scenario cost omitted its 4th occurrence inside the 13-week horizon (week 13) -> 4 occurrences, optimism bias removed. 2 observations logged without fix (no backoff jitter; unlimited half-open breaker probes). 2 pre-existing assertions updated (one encoded F-009). 19 suites / 219 tests at 100% zero pragmas; tsc clean. Cold review COMPLETE across all 27 modules | F14: Cold review of the 10 modules pass 1 did not deep-read: 4 defects (F-006..F-009), each an optimism or duplication bias. | G14: 0.8.x | H14: See Test_Traceability (filter Version) | I14: Released | J14: tracker v024 Version_Control / Release_Build_Boards; RELEASE_NOTES_v015.md where present
A15: Product workbook | B15: v016 | C15: 2026-09-11 15:27 | D15: Code | E15: CODE-PHASE-COMPLETION WAVE (sibling-validated TeleField/VoiceBridge pattern): ST-081 built-in chat + 4-business-hour SLA engine (business-hours math skips weekends/out-of-hours; queue sorts tightest deadline; chat-vendor decision now OPTIONAL — D-F6); ST-099 listing SEO iteration engine sandbox half (promote/keyword/demote rules with 100-impression thin-data floor; live half needs post-launch search-term data); ST-100 10-slot design-partner tracker (stale-nudge at 7 days; honest exit math separates reviews from G-02 paying strangers); ST-080 ranked help-center search over the 15 launch articles (manifest test-gated against docs/help); ST-095 pricing plan-matrix generated from billing.ts single source + DRIFT GATE test binding the published page to the enforced constants. 20 suites / 243 tests at 100% zero pragmas; tsc clean. FLOWCAST CODE PHASE COMPLETE — backlog zero, no further code sprints planned | F15: Code-phase-completion wave (sibling pattern): everything buildable without a live org built. | G15: 0.9.x | H15: See Test_Traceability (filter Version) | I15: Released | J15: tracker v024 Version_Control / Release_Build_Boards; RELEASE_NOTES_v016.md where present
... A60: Sprint tracker | B60: v024 | C60: 2026-09-20 10:14 | D60: Tracker release | E60: PERPLEXITY V001 RESPONSE, sprint E6, Wave P1 (workbook v036, code v0.30.0). Was planned to open on DEC-F16/DEC-F17 or the dev org; opened instead on the second independent review (Perplexity, 16 Sep 19:18), which found three BLOCKER code defects on the live path (PPX-01 forecast had no production data path; PPX-02 supplier bills mixed into receivables; PPX-03 billing rail on a deprecated channel) plus 7 more. Wave P1 executed in sandbox: P1-1..P1-7, 6 new gates + method-level reachability, 15 mutations proved. Per Senthil 10:17: nothing deleted, no story re-statused, billing rail left in place (PPX-D4 logged), all artefacts to next version. New sheet External_Review_PPX. 49 suites / 719 tests at 100%. New findings E6-F1..E6-F6 (boot composition) — see RAID R-F14..R-F19. | F60: Companion release to the workbook version named in the description. | G60: — | H60: — | I60: Released | J60: tracker v024 Version_Control
A61: Sprint tracker | B61: v025 | C61: PLANNED: opens on PPX-D1..D6 dispositions, sprint P1-8 (boot composition, expiring KNOWN_GAPS 31 Oct 2026), or the Xero dev org | D61: Tracker release | F61: Companion release to the workbook version named in the description. | G61: — | H61: — | I61: Planned | J61: tracker v024 Version_Control

Sheet Pending_Versions
A1: PENDING VERSIONS AND WORK — what does not exist yet, and why
A2: When an item opens, add its released row to Version_Detail and mark this row "Opened in <version>". Never delete.
A4: Item | B4: Kind | C4: Status | D4: Scope | E4: Who unblocks | F4: Reason it is pending | G4: Reference
A5: Workbook v037 / tracker v025 | B5: Next release | C5: Pending | D5: Opens on a Senthil decision (PPX-D1..D6, DEC-F16/F17), sprint P1-8, or the first live run. | E5: Senthil | F5: No sandbox-codeable work is left that does not need a decision or the dev org, except P1-8. | G5: tracker v024 Version_Control v025 row
A6: P1-8 boot composition (21 pts) | B6: Sprint | C6: Not started | D6: Durable store never written for installs; tenant state not rehydrated; webhook worker never started and drained rows never deleted; uninstall webhook not routed; canRequest dead. | E6: Senthil "go" → Claude | F6: KNOWN_GAPS R-F14..R-F17 expire 31 Oct 2026 — the suite goes red until this ships. | G6: E6-F3..F6; Handover #21
A7: Wave P2 closed loop (84 pts) | B7: Sprint(s) | C7: Blocked — decision | D7: Shortfall attribution, collections copilot, recovered-cash attribution, practice-OS depth. | E7: Senthil (PPX-D2 / DEC-F16) | F7: Reviewer recommends building the spine now; standing decision holds it. | G7: P2-1..P2-4; E6-01..E6-04
A8: Wave P3 enterprise-grade (76 pts) | B8: Sprint(s) | C8: Not started | D8: Application shell ×2 (bundler, routing, session, screens), tenancy/SSO/RBAC/audit chain, OpenTelemetry + SLOs. | E8: Claude (no blocker) | F8: Sequenced after P1 by the reviewer; ui/* KNOWN_GAPS expire 31 Dec 2026. | G8: P3-1..P3-4; PPX-07
A9: Wave P4 commercial (24 pts) | B9: Sprint | C9: Blocked — decision | D9: Rebuild financial model (Stripe-only, real referral mechanics, £45–£199 tiers); positioning + listing copy; retire xero_marketplace rail. | E9: Senthil (PPX-D3, PPX-D4, DEC-F16) | F9: Model and rail deliberately untouched on 20 Sep by instruction. | G9: P4-1, P4-2; PA-11
A10: Wave P5 human-blocked (60 pts) | B10: Live | C10: Blocked — environment | D10: Live Xero certification E2E, live billing, pen test, KMS custody, release signing, design partners, multi-node chaos, RPO/RTO drill. | E10: Senthil | F10: Cannot be simulated; the live cases in Manual_Test_Cases are the script. | G10: E7-01..E7-04; Handover #1–#6
A11: Email / notification transport | B11: Vendor + sprint | C11: Blocked — decision | D11: No transport in src; nudges, dunning, trial expiry, anomaly alerts have logic and no delivery. | E11: Senthil (vendor) | F11: Boot reports the gap to stderr rather than faking a sender. | G11: E6-F2; R-F21; Handover #22
A12: Xero dev org + live sweep | B12: Environment | C12: Blocked — Senthil | D12: Registers the app, runs the 12-step verification sweep, flips 16 "code-complete — pending live" stories. | E12: Senthil (~30 min) | F12: Every live test case in this workbook waits on it. | G12: Handover #1; verification-sweep.md
A13: Human second review of ST-097 | B13: Review | C13: Blocked — decision | D13: Whether an independent AI review closes ST-097 or a human is still required before submission. | E13: Senthil (DEC-F17 / PPX-D6) | F13: Both AI reviews found blockers the author missed. | G13: ST-097; External_Review_PPX
A14: Platform assumptions re-verification | B14: Recurring | C14: Due ~19 Dec 2026 | D14: Every entry in docs/platform-assumptions.json ages out at its staleness budget; CI fails until a human re-verifies against Xero's pages. | E14: Claude / Senthil | F14: By design: PPX-03 went six months stale silently. | G14: platformDriftGate; PA-01..PA-11

Sheet Manual_Test_Cases
A1: MANUAL TEST CASES — several per code-bearing version; positive and negative
A2: Fill only the yellow columns. Result is a drop-down. A Pass needs an observed value in Actual result. Live cases are recorded as Blocked until the blocker clears.
A4: Case ID | B4: Version | C4: Story / finding verified | D4: Title | E4: Type | F4: Mode | G4: Preconditions | H4: Steps (one action per line) | I4: Expected result | J4: Actual result | K4: Result | L4: Tester | M4: Date | N4: Defect ID | O4: Notes
A5: TC-v008-01 | B5: v008 | C5: ST-001, ST-002, ST-004 | D5: Forecast engine computes 13 weeks with traffic lights | E5: Positive | F5: Sandbox | G5: Sandbox set up per How_To_Use (npm ci done, `npm test` green once). | H5: 1. cd flowcast 2. npx jest tests/forecastEngine.test.ts --verbose 3. Read the test names printed and the summary line | I5: All tests pass; names include happy-path 13-week computation, amber/red thresholds and defaultInput. Coverage line for forecastEngine.ts shows 100/100/100/100. | K5: Not run
A6: TC-v008-02 | B6: v008 | C6: ST-004 / F-008 | D6: Non-finite due date is rejected with a named error, never silently dropped | E6: Negative | F6: Sandbox | G6: Sandbox set up per How_To_Use (npm ci done, `npm test` green once). | H6: 1. cd flowcast 2. node -e "const {computeForecast}=require('./dist/forecastEngine'); try{computeForecast({openingBalance:100,invoices:[{id:'x',amount:10,dueDate:NaN,payProbability:1}],outflows:[],weekStart:0})}catch(e){console.log(e.message)}" (run `npm run build` first if dist/ is absent) | I6: Prints "FORECAST_INVALID: invoice x dueDate is not a finite date". No forecast is returned. | K6: Not run
A7: TC-v008-03 | B7: v008 | C7: ST-004 | D7: Negative invoice amount is rejected | E7: Negative | F7: Sandbox | G7: Sandbox set up per How_To_Use (npm ci done, `npm test` green once). | H7: 1. As TC-v008-02 but with amount:-5 and dueDate:0 | I7: Prints "FORECAST_INVALID: invoice x amount < 0". | K7: Not run
A8: TC-v008-04 | B8: v008 | C8: D13 / ST-085 | D8: Whole suite at 100% on all four metrics with zero pragmas | E8: Positive | F8: Sandbox | G8: Sandbox set up per How_To_Use (npm ci done, `npm test` green once). | H8: 1. cd flowcast 2. npm test 3. grep -rn "istanbul ignore" src/ ; echo exit=$? | I8: Summary shows 49 suites / 719 tests passed; the "All files" row reads 100 | 100 | 100 | 100; grep prints nothing and exit=1. | K8: Not run
A9: TC-v009-01 | B9: v009 | C9: ST-003, ST-006 | D9: Forecast rules flag min-balance and week-drop violations | E9: Positive | F9: Sandbox | G9: Sandbox set up per How_To_Use (npm ci done, `npm test` green once). | H9: 1. cd flowcast 2. npx jest tests/rulesNotificationsMetrics.test.ts --verbose 3. Read the test names printed and the summary line | I9: Rule tests pass including week_drop_pct with week 1 and non-positive prior skipped. | K9: Not run
A10: TC-v009-02 | B10: v009 | C10: ST-003 | D10: Invalid rule threshold is rejected | E10: Negative | F10: Sandbox | G10: Sandbox set up per How_To_Use (npm ci done, `npm test` green once). | H10: 1. node -e "const {validateRule}=require('./dist/forecastRules'); try{validateRule({type:'week_drop_pct',threshold:-1})}catch(e){console.log(e.message)}" | I10: A named validation error is printed (rule refused); no silent acceptance. | K10: Not run
A11: TC-v009-03 | B11: v009 | C11: ST-086 | D11: CI workflow enforces the 100% gate and every gate file | E11: Positive | F11: Doc review | G11: Zip unpacked. | H11: 1. Open .github/workflows/ci.yml 2. Confirm steps: npm ci, tsc --noEmit, jest --coverage, each named gate test, prove:gates, audit, evidence + verify:evidence, pragma grep | I11: All steps present; the six E6 gates listed (dataPath, invoiceType, currency, platformLimits, platformDrift, forecastRealism). | K11: Not run
A12: TC-v010-01 | B12: v010 | C12: ST-089 | D12: Accessibility: axe reports zero violations on all UI surfaces | E12: Positive | F12: Sandbox | G12: Sandbox set up per How_To_Use (npm ci done, `npm test` green once). | H12: 1. cd flowcast 2. npx jest tests/ui --verbose 3. Read the test names printed and the summary line | I12: UI suites pass; jest-axe assertions report no violations for the 7 surfaces. | K12: Not run
A13: TC-v010-02 | B13: v010 | C13: ST-091 | D13: Degradation banner reflects breaker state honestly | E13: Positive | F13: Sandbox | G13: Sandbox set up per How_To_Use (npm ci done, `npm test` green once). | H13: 1. cd flowcast 2. npx jest tests/chaosReview.test.ts --verbose 3. Read the test names printed and the summary line | I13: Tests mapping breaker open/half-open/closed to banner level pass. | K13: Not run
A14: TC-v010-03 | B14: v010 | C14: ST-083 | D14: Demo data mode produces a deterministic red-week arc | E14: Positive | F14: Sandbox | G14: Sandbox set up per How_To_Use (npm ci done, `npm test` green once). `npm run build` done. | H14: 1. node -e "const {demoTenant}=require('./dist/demoData'); const {computeForecast}=require('./dist/forecastEngine'); const t=demoTenant(Date.UTC(2026,8,21)); console.log(computeForecast(t.forecast,5000).map(x=>x.light).join(','))" 2. Run it twice | I14: Both runs print exactly: green,green,green,green,green,green,amber,amber,red,red,red,red,red (verified 20 Sep 2026 in the sandbox). | K14: Not run
A15: TC-v011-01 | B15: v011 | C15: WBH-001 / VER-001 | D15: Webhook signature verification: valid signature → empty 200, bad → empty 401 | E15: Positive | F15: Sandbox | G15: Sandbox server running per How_To_Use (development mode, no DATABASE_URL, operator token "op"). | H15: 1. BODY='{"events":[]}' 2. SIG=$(node -e "console.log(require('crypto').createHmac('sha256','k').update(process.argv[1]).digest('base64'))" "$BODY") 3. curl -s -i -X POST localhost:3000/webhooks/xero -H "x-xero-signature: $SIG" -d "$BODY" 4. curl -s -i -X POST localhost:3000/webhooks/xero -H "x-xero-signature: bad" -d "$BODY" | I15: Step 3: HTTP 200 with an EMPTY body and security headers. Step 4: HTTP 401 with an EMPTY body (Xero rejects any body — VER-001). | K15: Not run
A16: TC-v011-02 | B16: v011 | C16: F-002 | D16: Signed but malformed JSON does not crash the fast-ack path | E16: Negative | F16: Sandbox | G16: Sandbox server running per How_To_Use (development mode, no DATABASE_URL, operator token "op"). | H16: 1. BODY='not json' 2. Sign it as in TC-v011-01 3. POST it | I16: A 4xx/200 response is returned and the server keeps serving /health afterwards (curl localhost:3000/health → {"ok":true}). | K16: Not run
... A95: TC-v036-21 | B95: v036 | C95: PPX-03 live | D95: XASS deprecation confirmed in the partner portal | E95: Positive | F95: Live — BLOCKED | G95: BLOCKED: needs the App Store partner account (Handover #4). | H95: 1. Open the partner portal billing section 2. Confirm no in-store subscription option is offered for new apps | I95: Confirms PA-11 contradicted status; feeds PPX-D4. | K95: Not run

Sheet Test_Execution_Log
A1: TEST EXECUTION LOG — one row per run
A2: Append only. Example row shows the expected format; replace it with real runs.
A4: Run ID | B4: Date/Time | C4: Case ID | D4: Version under test | E4: Environment | F4: Tester | G4: Result | H4: Observed | I4: Defect ID | J4: Duration (min)
A5: RUN-001 | B5: 2026-09-2x hh:mm | C5: TC-v008-04 | D5: v036 (code 0.30.0) | E5: Sandbox, Node 22.22 | F5: (name) | G5: Not run | H5: EXAMPLE ROW — e.g. "49 suites / 719 tests; All files 100|100|100|100; grep exit=1" | J5: 3

Sheet Test_Traceability
A1: TEST TRACEABILITY — case → version → story/finding → gate
A2: Filter by Version to get the re-run set for a release; filter by Story/finding to answer "what covers X?".
A4: Case ID | B4: Version | C4: Story / finding | D4: Title | E4: Mode | F4: Automated gate that also covers it | G4: Evidence class
A5: TC-v008-01 | B5: v008 | C5: ST-001, ST-002, ST-004 | D5: Forecast engine computes 13 weeks with traffic lights | E5: Sandbox | F5: — | G5: Sandbox suite
A6: TC-v008-02 | B6: v008 | C6: ST-004 / F-008 | D6: Non-finite due date is rejected with a named error, never silently dropped | E6: Sandbox | F6: — | G6: Sandbox suite
A7: TC-v008-03 | B7: v008 | C7: ST-004 | D7: Negative invoice amount is rejected | E7: Sandbox | F7: — | G7: Sandbox suite
A8: TC-v008-04 | B8: v008 | C8: D13 / ST-085 | D8: Whole suite at 100% on all four metrics with zero pragmas | E8: Sandbox | F8: — | G8: Sandbox suite
A9: TC-v009-01 | B9: v009 | C9: ST-003, ST-006 | D9: Forecast rules flag min-balance and week-drop violations | E9: Sandbox | F9: — | G9: Sandbox suite
A10: TC-v009-02 | B10: v009 | C10: ST-003 | D10: Invalid rule threshold is rejected | E10: Sandbox | F10: — | G10: Sandbox suite
A11: TC-v009-03 | B11: v009 | C11: ST-086 | D11: CI workflow enforces the 100% gate and every gate file | E11: Doc review | F11: — | G11: Document
A12: TC-v010-01 | B12: v010 | C12: ST-089 | D12: Accessibility: axe reports zero violations on all UI surfaces | E12: Sandbox | F12: — | G12: Sandbox suite
A13: TC-v010-02 | B13: v010 | C13: ST-091 | D13: Degradation banner reflects breaker state honestly | E13: Sandbox | F13: — | G13: Sandbox suite
A14: TC-v010-03 | B14: v010 | C14: ST-083 | D14: Demo data mode produces a deterministic red-week arc | E14: Sandbox | F14: — | G14: Sandbox suite
A15: TC-v011-01 | B15: v011 | C15: WBH-001 / VER-001 | D15: Webhook signature verification: valid signature → empty 200, bad → empty 401 | E15: Sandbox | F15: supplyChainGate (stale-claim) | G15: Sandbox suite
... A95: TC-v036-21 | B95: v036 | C95: PPX-03 live | D95: XASS deprecation confirmed in the partner portal | E95: Live — BLOCKED | F95: platformDriftGate | G95: Live sweep

Sheet Defect_Log
A1: DEFECT LOG — found by manual execution
A2: MT-nnn ids. Never delete; a fixed defect gets the fixing version and the regression test that pins it.
A4: Defect ID | B4: Found by case | C4: Date | D4: Version found | E4: Severity | F4: Description | G4: Steps to reproduce | H4: Status | I4: Fixed in version | J4: Regression test | K4: Notes
A5: MT-000 | B5: TC-v036-03 | C5: 2026-09-20 | D5: v036 | E5: Info | F5: EXAMPLE ROW — GET /api/forecast returns 502 for an uninstalled tenant; by design (honest refusal, no fixture fallback). Not a defect; recorded to show the format. | G5: See TC-v036-03 step 3 | H5: Closed — by design | I5: — | J5: tests/forecastDataPath.test.ts "upstream Xero failure is a 502" | K5: Replace this row with real defects

Sheet Sign_Off
A1: SIGN-OFF — per version
A2: Verdict: Accepted / Accepted with defects / Rejected / Blocked. Blank until executed.
A4: Version | B4: Cases run | C4: Executed by / date | D4: Reviewed by / date | E4: Verdict | F4: Comments
A5: v008
A6: v009
A7: v010
A8: v011
A9: v012
A10: v013
A11: v014
A12: v015
A13: v016
A14: v017
A15: v018
A16: v019
... A32: v036

Sheet Glossary
A1: GLOSSARY
A4: Term | B4: Meaning
A5: D13 | B5: Portfolio rule: 100% automated coverage on all four metrics, zero pragmas; discovery interviews parked.
A6: D-F2 vocabulary | B6: Done / Code-complete — pending live / Drafted / In progress / Not started — see Context.
A7: Gate | B7: A Jest test that fails the build when a class of shipped defect is reintroduced. "Proved" = prove-gates.js reintroduced the real defect and the gate failed.
A8: prove:gates | B8: npm script running gates/prove-gates.js: 15 mutations against real source; exit 0 only when all PROVED.
A9: Enhancement pool | B9: Second point pool (D-F7) for corrective work from reviews, keeping the 399-point baseline honest.
A10: PPX-nn / FC-Rnnn / E6-Fn | B10: Findings from Perplexity V001 / ChatGPT V001 / sprint E6 respectively.
A11: KNOWN_GAP | B11: Reachability-gate exemption naming a RAID risk and an expiry date; the build fails when the date passes.
A12: Live sweep | B12: The 12-step scripted verification against a real Xero dev org (docs/live-sweep/verification-sweep.md). Not yet run.
A13: Operator session | B13: x-flowcast-operator token + x-flowcast-tenant header → owner session for the forecast routes. Not a user login (THREAT_MODEL.md E6 addendum).
A14: XASS | B14: Xero App Store Subscriptions — in-store billing, deprecated by Xero effective March 2026 (PPX-03).
A15: Sandbox / Live — BLOCKED / Doc review | B15: Test modes: runnable today in the unzipped code; written in full but needs an environment or decision; a reading check of an artefact.
