Workbook

Sheet Version_Control
A1: VERSION CONTROL — QuoteFlow Sprint Tracker & Traceability
A2: File naming: claude_v<NNN>_<proper file name>_YYYYMMDD_HHMI. Companion to the product workbook lineage claude_v006..v009_quoteflow_hubspot_product_workbook.
A3: Version | B3: Date/Time | C3: Author | D3: Change Description | E3: Status
A4: v001 | B4: 2026-09-10 23:09 | C4: Claude for Senthil/KP | D4: THIS FILE — Live execution tracker for QuoteFlow (HubSpot App Marketplace, portfolio wave-2): event-level sprint log E001..E014 for S1/S2/S3, decisions register, per-sprint build boards (S1/S2/S3), 100-story traceability with per-story evidence citing product-workbook versions (S1=v007 22:03, S2=v008 22:19, S3=v009 22:52), live sprint status rollup (formulas), RAID, and the D7 completion gate. Source of story truth: v009 Full_Backlog. | E4: Released
A5: v002 | B5: 2026-09-11 08:17 | C5: Claude for Senthil/KP | D5: S4 EXECUTED (Approval chains part 2 + telemetry + smoke, 9 stories / 34 pts): events E015..E021 appended; S4_Build_Board added; 9 traceability rows Done with v010 evidence (30/100 total, 123/399 pts); rollup S4 RAG GREEN; Decisions DQ4 updated with the failed live-Postgres attempt, DQ6/DQ7 added (feature-pause + spike semantics); RAID R-Q4 attempt-evidenced, R-Q9 added (smoke deploy hook assumption). Companion product workbook: v010 (2026-09-11 08:17). | E5: Released
A6: v003 | D6: PLANNED: S5 execution entries (E-signature + alpha hardening, 12 stories / 50 pts); live-verification evidence (R-Q5/R-Q6) when Senthil provides dev-portal access; Postgres retry log | E6: Planned
A7: v003 | B7: 2026-09-11 08:52 | C7: Claude for Senthil/KP | D7: S5 EXECUTED (E-signature + alpha hardening, 12 stories / 50 pts — largest sprint): events E022..E028; S5_Build_Board added; 12 traceability rows Done with v011 evidence (42/100 stories, 173/399 pts, 43.4%); rollup S5 GREEN; Decisions +DQ8 (public signer surface — token IS the identity, validate-then-mint) +DQ9 (esign pause never-strand + settings snapshot-at-creation) + DQ5 note (signer link delivery rides the email provider; API returns signerLinks meanwhile); RAID R-Q7 note extended to signer outreach. Companion product workbook: v011 (2026-09-11 08:52). | E7: Released
A8: v004 | D8: PLANNED: S6 execution entries (Billing + Quote analytics, 13 stories / 60 pts); Postgres retry log; live-verification evidence when R-Q5/R-Q6 unblock | E8: Planned
A9: v004 | B9: 2026-09-11 12:47 | C9: Claude for Senthil/KP | D9: S6 EXECUTED (Quote analytics + Billing, 13 stories / 60 pts): events E029..E035; S6_Build_Board added; 13 traceability rows Done with v012 evidence (55/100 stories, 233/399 pts, 58.4%); rollup S6 GREEN; Decisions +DQ10 (analytics pause blocks dashboards NEVER capture; capture setup-independent) +DQ11 (per-portal channel routing marketplace/HubSpot vs direct/Stripe; failure persists nothing; 30d proration w/ net<=0 no-call rule); RAID +R-Q10 (billing provider live credentials — Senthil). Companion product workbook: v012 (2026-09-11 12:47). | E9: Released
A10: v005 | D10: PLANNED: S7 execution entries (Beta cohort ST-073..077, 5 stories / 15 pts); live-verification evidence when R-Q5/R-Q6/R-Q10 unblock | E10: Planned
A11: v005 | B11: 2026-09-13 10:26 | C11: Claude for Senthil/KP | D11: S7 EXECUTED (billing hardening + least-privilege scopes, 5 stories / 15 pts): events E036..E042; S7_Build_Board added; 5 traceability rows Done with v013 evidence (60/100 stories, 248/399 pts, 62.2%); rollup S7 GREEN; Decisions +DQ12 (billing read-only is a WRITE gate only — reads and exports survive dunning and cancellation) +DQ13 (scopes validated in code: registry + two-way audit + generated disclosure); scope-drift note added to RAID. Companion product workbook: v013 (2026-09-13 10:26). | E11: Released
A12: v006 | D12: PLANNED: S8 execution entries (Deal/line-item sync + beta iteration, 22 stories / 87 pts — largest remaining sprint) | E12: Planned
A13: v006 | B13: 2026-09-13 10:38 | C13: Claude for Senthil/KP | D13: S8 EXECUTED (largest sprint — 22 stories / 87 pts across F5 sync, E6 trust, E7 founder ops, EQ performance): events E043..E050; S8_Build_Board added; 22 traceability rows Done with v014 evidence (82/100 stories, 335/399 pts, 84.0%); rollup S8 GREEN; Decisions +DQ14 (idempotency key + queue-on-pause) +DQ15 (generated trust doc, unmet controls published as partial with owners) +DQ16 (circuit breaker in front of platform writes); RAID +R-Q11 (vault + at-rest provisioning). Companion product workbook: v014 (2026-09-13 10:38). | E13: Released
A14: v007 | D14: PLANNED: S9 execution entries (Marketplace review prep, 7 stories / 30 pts) | E14: Planned
A15: v007 | B15: 2026-09-13 10:56 | C15: Claude for Senthil/KP | D15: S9 EXECUTED (Marketplace review prep, 7 stories / 30 pts — 5 Done, 2 Partial): events E051..E058; S9_Build_Board added; 7 traceability rows updated with v015 evidence; rollup S9 AMBER (two stories carry external dependencies); Decisions +DQ17 (two-step token-confirmed deletion, export always available) +DQ18 (review evidence generated and asserted, never narrated); RAID +R-Q12 (external penetration test). Defect L-062 logged: the restore drill destroyed non-restorable sources. Companion product workbook: v015 (2026-09-13 10:56). | E15: Released
A16: v008 | D16: PLANNED: S10 execution entries (Review remediation + docs, 7 stories / 24 pts) | E16: Planned
A17: v008 | B17: 2026-09-13 11:11 | C17: Claude for Senthil/KP | D17: S10 EXECUTED (Launch surfaces, 7 stories / 24 pts, all Done): events E059..E065; S10_Build_Board added; 7 traceability rows Done with v016 evidence (94/100 stories, 376/399 pts strictly-Done); rollup S10 GREEN; Decisions +DQ19 (customer-facing pages generated from product constants) +DQ20 (support SLA measured in business hours; unanswered-past-due counts as breach) +DQ21 (submission dry-run reads live state, human-needed items are manual blockers not passes). Companion product workbook: v016 (2026-09-13 11:11). | E17: Released
A18: v009 | D18: PLANNED: S11 execution entries (Launch — 3 stories / 8 pts) | E18: Planned
A19: v009 | B19: 2026-09-13 11:25 | C19: Claude for Senthil/KP | D19: S11 EXECUTED (Launch, 3 stories / 8 pts, all Done): events E066..E071; S11_Build_Board added; 3 traceability rows Done with v017 evidence (97/100 stories, 384/399 pts strictly-Done); rollup S11 GREEN-with-note (preflight returns no_go on billing stubs, R-Q10); Decisions +DQ22 (review ask fires only when the portal is demonstrably happy; no review-gating) +DQ23 (runbook executable, every step verifiable) +DQ24 (partner pipeline counts scheduled, not intentions). Companion product workbook: v017 (2026-09-13 11:25). | E19: Released
A20: v010 | D20: PLANNED: S12 execution entries (Iterate & scale decision — 1 story / 2 pts) — final sprint | E20: Planned
A21: v010 | B21: 2026-09-13 11:34 | C21: Claude for Senthil/KP | D21: S12 EXECUTED + PROGRAMME CLOSE (1 story / 2 pts): events E072..E077; S12_Build_Board added; ST-099 traceability row Done with v018 evidence; rollup S12 GREEN; Decisions +DQ25 (SEO may never propose an unsupported claim). FINAL: 12 sprints, 98/100 stories Done + 2 Partial, 386/399 points, 397 tests / 26 suites at 100% x4 on 49 source files. Companion product workbook: v018 (2026-09-13 11:34), which carries the Programme_Closeout sheet. | E21: Released
A22: — | D22: No further sprints planned. Next work is the six external items in Programme_Closeout (workbook v018), none of which are code. | E22: Closed
A23: v011 | B23: 2026-09-13 11:51 | C23: Claude for Senthil/KP | D23: COLD REVIEW PASS 1 (QuoteFlow's first): events E078..E082; 8 defects fixed with pinned regressions, four critical (delete-my-data leaving records, no runnable entrypoint, unsigned caller-declared identity, expired trial granting perpetual free use); Review_Findings sheet in product workbook v019 carries the full table plus the two sibling classes verified absent; lesson L-Q1 logged. Suite 397 -> 410 tests / 27 suites at 100% x4. Story position unchanged 98 Done / 2 Partial — correctness release. | E23: Released
A24: v012 | D24: PLANNED: cold review pass 2 over the modules pass 1 did not reach, plus an artifact-gap audit (no DB schema exists behind the published retention policy — stores are still in-memory, R-Q4) | E24: Planned
A25: v012 | B25: 2026-09-13 12:03 | C25: Claude for Senthil/KP | D25: COLD REVIEW PASS 2 + artifact-gap audit: events E083..E087; 6 findings fixed (F-Q09 retention policy never enforced — CRITICAL, F-Q10 redaction control with no call sites, F-Q11 breaker on writes only, F-Q12 no deploy workflow, F-Q13 no DB schema, F-Q14 future-dated signatures); +DQ26 (every fix ships with a drift gate, not just a regression); lesson L-Q2. Suite 410 -> 424 tests / 28 suites at 100% x4. Story position unchanged 98 Done / 2 Partial. Full detail: product workbook v020 Review_Findings. | E25: Released
A26: v013 | D26: PLANNED: pass 3 (the surfaces pass 1 and 2 did not reach — help/support/public/founder modules read adversarially), and the Postgres adapter behind the new schema (R-Q4 code half) | E26: Planned
A27: v013 | B27: 2026-09-13 16:25 | C27: Claude for Senthil/KP | D27: COLD REVIEW PASS 3: events E088..E091; 3 findings fixed (F-Q15 status page wired to constants, F-Q16 preflight readiness hardcoded, F-Q17 CRITICAL nine vendor-only surfaces reachable with tenant RBAC); +DQ27 (vendor surfaces gated on an operator token and fail closed); lesson L-Q3. Suite 424 -> 428 tests / 28 suites at 100% x4. Running total 17 defects across three passes. Story position unchanged 98 Done / 2 Partial. Detail: product workbook v021 Review_Findings. | E27: Released
A28: v014 | D28: PLANNED: Postgres adapter behind the pass-2 migrations (R-Q4 code half) with a store-contract suite run against both in-memory and pg | E28: Planned
A29: v014 | B29: 2026-09-13 16:36 | C29: Claude for Senthil/KP | D29: R-Q4 CODE HALF: events E092..E094; Postgres adapters for audit/analytics/sync behind the pass-2 migrations, proved by a store-contract suite executed against both in-memory and real SQL on an in-process Postgres with the real migrations, including two durability tests; +DQ28 (a persistence adapter is only accepted when the same contract suite passes against both implementations); R-Q13 opened (synchronous store interfaces force a write-through cache and a single writer). Suite 428 -> 439 tests / 29 suites at 100% x4. | E29: Released
A30: v015 | D30: PLANNED: adapt the remaining six stores using the contract-suite pattern; R-Q13 async interface migration; live Postgres run of the contract suite once an instance exists | E30: Planned
A31: v015 | B31: 2026-09-13 16:41 | C31: Claude for Senthil/KP | D31: POSTGRES ADAPTERS PART 2: events E095..E097; the remaining six stores adapted, so all nine now have a Postgres implementation proved against a real engine; NEW DEFECT F-Q18 (catalog bundles, pricing rules and pause flags had no tables - the pass-2 drift gate checked store granularity, not field); migration 005 added; +DQ29 (a store adapter must round-trip every record type the interface exposes, asserted field by field). Suite 439 -> 457 tests / 30 suites at 100% x4. R-Q13 still open. | E31: Released
A32: v016 | D32: PLANNED: R-Q13 async store interfaces (multi-instance safety); live Postgres run of both contract suites once an instance exists; wire the adapters into index.ts behind a DATABASE_URL switch | E32: Planned
A33: v016 | B33: 2026-09-13 16:53 | C33: Claude for Senthil/KP | D33: POSTGRES BOOT WIRING: events E098..E100; buildStores() selects the backend from DATABASE_URL and reports it, server.ts runs migrations then starts, portals hydrate once per process; the real app is now driven over HTTP against Postgres-backed stores and a second process on the same database sees the data. +DQ30 (a persistence backend must be selectable at boot, report itself, and be proved by driving the real app end to end). Named gap: approvals still in-memory. Suite 457 -> 465 tests / 31 suites at 100% x4. R-Q13 open. | E33: Released
A34: v017 | D34: PLANNED: PgApprovalStore (the last in-memory store); R-Q13 async interfaces; live Postgres run of all three suites once an instance exists | E34: Planned
A35: v017 | B35: 2026-09-13 17:23 | C35: Claude for Senthil/KP | D35: R-Q14 CLOSED: events E101..E102; PgApprovalStore written and wired, contract suite extended to chains and requests, and pgBoot proves an approval decision survives a restart through the real HTTP flow. Every store the product writes to is now durable. RAID R-Q14 closed; R-Q13 remains open. Suite 465 -> 466 tests / 31 suites at 100% x4. | E35: Released
A36: v018 | D36: PLANNED: R-Q13 async store interfaces (multi-instance safety) and a live Postgres run of all four suites | E36: Planned
A37: v018 | B37: 2026-09-13 17:30 | C37: Claude for Senthil/KP | D37: WRITER LEASE (R-Q13 mitigation): events E103..E104; migration 006 plus a lease an instance must hold to write, so a second instance is refused at startup instead of diverging silently; +DQ31 (where a constraint cannot yet be removed, enforce it so breaking it fails loudly). R-Q13 remains OPEN for the async migration itself - its dangerous half is closed. Suite 466 -> 472 tests / 32 suites at 100% x4. | E37: Released
A38: v019 | D38: PLANNED: R-Q13 proper (async store interfaces, ~40 call sites) as a dedicated phase; live Postgres run of all five suites | E38: Planned
A39: v019 | B39: 2026-09-13 18:48 | C39: Claude for Senthil/KP | D39: R-Q13 PHASE 1: events E105..E106; the async cascade done once - PortalDataSource, PrivacyService, BackupService and RetentionService plus six routes are async, with no behaviour change (472 tests still green at 100% x4). +DQ32 (stage a large migration so every checkpoint is green). Phase 2 (per-store async, dropping the write-through caches) open. | E39: Released
A40: v020 | D40: PLANNED: R-Q13 phase 2 - convert the nine stores to async and drop the write-through caches, one store at a time | E40: Planned
A41: v020 | B41: 2026-09-13 18:59 | C41: Claude for Senthil/KP | D41: R-Q13 PHASE 2 STORE 1/9 (review state): events E107..E109; ReviewStore async with the Pg write-through cache removed, proved by two running instances sharing one database with no restart; self-inflicted ?? -on-a-promise regression caught by the coverage gate and fixed; +DQ33 (when a store read becomes async, re-check every ?? and ?. applied to it). Suite 472 -> 473 tests / 32 suites at 100% x4. Eight stores remain. | E41: Released
A42: v021 | D42: PLANNED: phase 2 stores 2-9 (signatures, support, audit, sync, analytics, approvals, billing, notifications, catalog - smallest ripple first); live Postgres run | E42: Planned
A43: v021 | B43: 2026-09-13 19:33 | C43: Claude for Senthil/KP | D43: R-Q13 PHASE 2 STORE 2/9 (support conversations): events E110..E111; SupportStore and SupportService async, PgSupportStore rewritten cache-free, six routes awaited and guarded, DQ33 applied to every ?? and ?. on a support read. Suite unchanged at 473 tests / 32 suites, 100% x4 - correct for a conversion that changes no behaviour. Seven stores remain. | E43: Released
A44: v022 | D44: PLANNED: phase 2 stores 3-9 (signatures, audit, approvals, sync, analytics, catalog, notifications, billing); the writer lease can become advisory once all nine are done; live Postgres run | E44: Planned
A45: v022 | B45: 2026-09-13 19:41 | C45: Claude for Senthil/KP | D45: R-Q13 PHASE 2 CORRECTION + PLAN: events E112..E113; corrected the v029 claim that each remaining store is local work (true for 2 of 9, false for 7), measured every cascade, and published a risk-sequenced migration plan gated by a test so it cannot become aspirational. +DQ34 (a plan that outlives a session must be asserted against the code). Suite 473 -> 474 tests / 32 suites at 100% x4. | E45: Released
A46: v023 | B46: 2026-09-13 19:56 | C46: Claude for Senthil/KP | D46: R-Q13 PHASE 2 STORE 3/9 (approvals): events E114..E115; store, service and cache-free Pg adapter plus the CRM card and checklist readers; two un-awaited-promise defects found and fixed during the mechanical pass; migration plan corrected to note that even the self-contained store had a tail. Suite held at 474 tests / 32 suites, 100% x4. Six stores remain. | E46: Released
A47: v024 | B47: 2026-09-13 20:08 | C47: Claude for Senthil/KP | D47: R-Q13 PHASE 2 STORE 4/9 (sync): event E116; store, service, cache-free Pg adapter for runs (including the fleet-wide failure count behind the public status page), retention sweeper, export source and eight routes. Adapter settings deliberately stay in memory and that choice is documented in the plan. Suite held at 474 tests / 32 suites at 100% x4. Five stores remain: audit, signatures+analytics together, notifications, billing, catalog last. | E47: Released
A48: v025 | B48: 2026-09-13 20:26 | C48: Claude for Senthil/KP | D48: R-Q13 PHASE 2 STORE 5/9 (audit): event E117; store, record() helper, retention sweeper, export source and cache-free Pg adapter converted, with 23 route handlers becoming guarded async. +DQ35 (audit writes are awaited, never fire-and-forget). Suite held at 474 tests / 32 suites at 100% x4. Four stores remain: signatures+analytics together, notifications, billing, catalog last. | E48: Released
A49: v026 | B49: 2026-09-13 22:46 | C49: Claude for Senthil/KP | D49: ATTEMPT ABANDONED, TREE RESTORED: events E118..E119. Store 6+7 (signatures+analytics) source converted cleanly but ~200 test call sites did not; repo-wide regex broke supertest chains and the suite bottomed out at 15 failed / 17 passed. Tree restored from the 20:26 artifact and re-verified at 474 tests / 32 suites / 100% x4. +DQ36 (convert src first, then one suite at a time, never a pattern across all tests). Stores 1-5 converted; 6-9 pending. | E49: Released
A50: v027 | D50: PLANNED: retry stores 6+7 with the DQ36 method in a fresh session (s5 and s6 are the large suites); then notifications, billing, catalog last | E50: Planned

Sheet Sprint_Tracker_Log
A1: SPRINT TRACKER LOG — every execution event, newest last
A2: Refs cite product-workbook tracker entries (L-001..L-021), decisions (D..), stories (ST-..). One row per event; versions are the workbook releases that carry the evidence.
A3: ID | B3: Date/Time | C3: Sprint | D3: What happened | E3: Refs | F3: State changes | G3: Blockers | H3: Next
A4: E001 | B4: 2026-09-10 22:03 | C4: — | D4: QuoteFlow build opened from v006 product workbook on continue signal. D13 applied (portfolio-wide: discovery interviews parked, dev proceeds under 100% automation coverage on ALL code); ST-085 gate text amended from >=70% to 100% in backlog. | E4: D13; L-001; v007 | F4: S1 opened; ST-085 re-scoped | G4: None | H4: E002
A5: E002 | B5: 2026-09-10 22:03 | C5: S1 | D5: S1 FOUNDATION BUILT (TypeScript/Node 22/Express 4, strict tsc): OAuth install -> welcome (ST-051), uninstall webhook with HubSpot v3 HMAC + replay guard + retention-scheduled deletion (ST-052), rotation-safe token refresh with 60s expiry skew (ST-055), install source telemetry (ST-056). Workbook v007 released 22:03 with Sprint_Tracker_Log + Traceability_Matrix sheets added. | E5: ST-051/052/055/056; L-002..L-003; v007 | F5: 4 S1 stories Done-in-code (13 pts) | G5: None | H5: E003
A6: E003 | B6: 2026-09-10 22:03 | C6: S1 | D6: D13 TEST GATE MET — 56 automated tests / 3 suites (unit + supertest HTTP integration), 100% stmt/branch/func/line on every source file; jest coverageThreshold 100x4 fails any build below. | E6: D13; L-004; test-run.log 20260910_2203 | F6: Evidence into Traceability col K | G6: None | H6: E004
A7: E004 | B7: 2026-09-10 22:03 | C7: S1 | D7: S1 CLOSED 4/4 (13/13 pts). Exit criterion "app installs cleanly; telemetry firing" code-verified via integration tests; LIVE dev-portal install verification remains open (needs Senthil: dev portal app + client ID/secret) — same pattern as RevRescue live Stripe install. | E7: L-005..L-006 | F7: Cumulative 4/100 stories, 13/399 pts | G7: Live install = Senthil + dev portal | H7: E005
A8: E005 | B8: 2026-09-10 22:19 | C8: S2 | D8: S2 OPENED on continue signal: Price book + bundles part 1 — ST-001..004 + ST-053 re-install restore + ST-054 role matrix (6 stories, 29 pts). | E8: L-008; v008 | F8: S2 in build | G8: None | H8: E006
A9: E006 | B9: 2026-09-10 22:19 | C9: S2 | D9: S2 BUILT: catalog domain (books/items/bundles/rules, portal-isolated), one-call idempotent defaults, best-rule pricing engine (minQty/customerTier, largest discount wins, verified 804.60+672.60=1477.20), typed AppError + PlatformClient backoff (429/5xx retry -> retryable 503; 401 re-auth), re-install restore cancelling pending deletion + retention purge executor, owner>admin>member RBAC on every /api route with first-user-owner bootstrap. Workbook v008 released 22:19. | E9: ST-001..004/053/054; L-009; v008 | F9: 6 S2 stories Done-in-code (29 pts) | G9: None | H9: E007
A10: E007 | B10: 2026-09-10 22:19 | C10: S2 | D10: D13 TEST GATE HELD — suite 56 -> 103 tests / 5 suites, 100% x4 on all 16 source files; E2E-over-HTTP: defaults -> detail -> priced quote; uninstall webhook -> re-install -> "data restored" welcome. | E10: D13; L-010; test-run.log 20260910_2219 | F10: Evidence into Traceability col K | G10: None | H10: E008
A11: E008 | B11: 2026-09-10 22:19 | C11: S2 | D11: S2 CLOSED 6/6 (29/29 pts). Decision locked: /api identity is header-based (X-QF-Portal-Id/X-QF-User-Id) until the HubSpot-signed CRM-card surface lands in S3 (ST-005). | E11: L-011..L-013; DQ2 | F11: Cumulative 10/100, 42/399 | G11: None | H11: E009
A12: E009 | B12: 2026-09-10 22:52 | C12: S3 | D12: S3 OPENED on continue signal: Price book part 2 (ST-005..010) + Approval chains start (ST-011..014) + ST-085 gate story — 11 stories, 47 pts (largest sprint so far). | E12: L-014; v009 | F12: S3 in build | G12: None | H12: E010
A13: E010 | B13: 2026-09-10 22:52 | C13: S3 | D13: S3 BUILT: HubSpot-signed GET /crm-card + /ui/quote iframe shell (paused-aware card), metrics service (aggregates + 7-day UTC trend), audit log on all 14 mutating routes, pause/resume gating writes only, CSV import (generic + rivalcpq competitor formats, quoted-field parser, row-level errors, SKU dedupe), notifications (in-app+email, per-type mute, failed-email retry), approval chains (one-call default "Discounts over 15% need manager approval", validated custom chains, strict-> triggers, step-snapshot requests, approve/reject walk with approver fan-out). DeletionExecutor now purges all five stores. Workbook v009 released 22:52. | E13: ST-005..014/085; L-015; v009 | F13: 11 S3 stories Done-in-code (47 pts) | G13: None | H13: E011
A14: E011 | B14: 2026-09-10 22:52 | C14: S3 | D14: D13 TEST GATE HELD — suite 103 -> 150 tests / 7 suites, 100% x4 on all 24 source files, EXIT=0. E2E-over-HTTP: signed card reflects catalog+pause; pause 409s writes/keeps reads; import->quote; mute suppresses; failed email 502-retryable then healed; discounted quote -> pending -> approvers notified -> approved -> requester notified. | E14: D13; L-016; ST-085; test-run.log 20260910_2252 | F14: ST-085 marked Done with evidence | G14: None | H14: E012
... A122: E119 | B122: 2026-09-13 22:46 | C122: R-Q13 | D122: TREE RESTORED AND RE-VERIFIED at 474 tests / 32 suites / 100% x4 from quoteflow_asyncphase2e_codebase_20260913_2026.zip. This is DQ32 working as designed: staging the migration so every checkpoint is green meant a failed attempt could be discarded whole without losing the five converted stores. DQ36 locked - convert src/ to a clean tsc first, then fix ONE SUITE AT A TIME compiling after each, never a pattern across all of tests/, biggest suite first, and treat overrun as the signal to keep the checkpoint rather than hurry. Also recorded: stores 1-5 worked with pattern passes because their test surfaces were small, which was luck rather than method - do not infer method from the easy cases. | E122: L-128; DQ36 | F122: 474 tests green | G122: Retry 6+7 in a fresh session | H122: -

Sheet Decisions
A1: DECISIONS (tracker scope)
A2: Portfolio decisions keep their D-numbers; QuoteFlow-local decisions are DQ-numbered. Product-workbook tracker refs in Rationale.
A3: ID | B3: Decision | C3: Rationale | D3: Decided by | E3: Status
A4: D13 | B4: (Portfolio-wide) Discovery interviews parked; development proceeds with 100% automation test coverage on ALL code — hard jest threshold, build fails below 100x4. | C4: Senthil 10 Sep 20:45; applied to QuoteFlow at 22:03 (L-001); ST-085 amended in backlog | D4: Senthil | E4: LOCKED
A5: DQ1 | B5: S1+ stack = TypeScript/Node 22/Express 4/Jest per v006 ReadMe stack assumption; strict tsc. | C5: Follows workbook stack line; consistent with the rest of the portfolio builds | D5: Claude — flagged for ratification | E5: OPEN
A6: DQ2 | B6: /api identity is header-based (X-QF-Portal-Id/X-QF-User-Id, first-user-owner bootstrap); the HubSpot-SIGNED surface is GET /crm-card (v3 HMAC). Extending signed identity to /api rides with the S4+ UI-extension work. | C6: L-011 (S2) partially resolved by ST-005 in S3 — card surface signed; API headers remain until UI extension auth lands | D6: Claude — flagged | E6: OPEN
A7: DQ3 | B7: Approval requests snapshot chain steps at creation; decisions read the snapshot. Trigger thresholds are strict (>): a 15% discount does not trip the 15% default chain. | C7: L-017 — in-flight requests immune to chain edits/deletes; removes unreachable error branch; boundary documented in tests | D7: Claude | E7: LOCKED
A8: DQ4 | B8: Postgres adapter deferred to S4; in-memory stores behind CatalogStore/AuditStore/NotificationStore/ApprovalStore + Purgeable interfaces remain the tested reference. | C8: L-018 — no live Postgres in build env; an unexecuted adapter would violate the honest-status rule. UPDATE 11 Sep 08:17 (L-024): live install attempted — apt mirror 404s + sandbox timeout, PG_ABSENT verified; deferral stands with evidence. | D8: Claude | E8: LOCKED
A9: DQ5 | B9: Email transport is an injected EmailSender with a no-op production default until a provider (Postmark-class) is wired with GTM plumbing; notification code paths (sent/failed/retry) fully tested against a mutable fake. | C9: Email delivery is a provider integration (noop sender in dev); notification records + retry endpoint are real. UPDATE 11 Sep 08:52: signer link delivery for e-sign envelopes rides the same provider decision — the API returns signerLinks so the UI can share links meanwhile. | D9: Claude — flagged | E9: OPEN
A10: DQ6 | B10: Feature-scoped pause (ST-018): pausing approvals blocks NEW requests only; decisions on already-pending requests remain allowed so in-flight approvals never strand. Global pause blocks both features. | C10: S4 build (E017); prevents stuck approvals during maintenance windows; tested both directions | D10: Claude | E10: LOCKED
A11: DQ7 | B11: Error-spike semantics (ST-072): threshold 5 server errors in a rolling 15-min window; one error_spike notification per episode to every admin/owner; episode resets when the window rolls clean. | C11: S4 build (E017); avoids alert storms while guaranteeing a signal; constants exported for tuning | D11: Claude | E11: LOCKED
A12: DQ8 | B12: Public signer surface: the token IS the identity — /api identity middleware is bypassed for /api/esign/sign/*; signer actions audited as signer:<email>. Tokens are minted only after ALL signers validate (no token burn on invalid input; found and fixed in build). Production tokens are crypto.randomUUID via injected generator. | C12: S5 build (E024); guessable or burned tokens would break the feature; regression-tested | D12: Claude | E12: LOCKED
A13: DQ9 | B13: Esign pause blocks NEW envelopes only — sent links keep signing (DQ6 never-strand, now covering pricebook/approvals/esign). Envelope behaviour snapshots settings at creation; later settings changes never mutate in-flight envelopes. | C13: S5 build (E025); protects external signers mid-flow; tested over HTTP while paused | D13: Claude | E13: LOCKED
A14: DQ10 | B14: Analytics pause blocks dashboards (summary/trends/export 409) but NEVER event capture — capture gating would create history gaps, i.e. data loss (ST-038 forbids). Capture is setup-independent: events record before defaults; alerts only fire once settings exist. Deliberate inversion of the DQ6 write-gate. | C14: S6 build (E031); proved over HTTP: paused-time quote visible after resume | D14: Claude | E14: LOCKED
... A40: DQ36 | B40: In a store-by-store async migration: convert src/ to a clean tsc first, then fix test suites one at a time, compiling after each. Never run a text pattern across all of tests/. Do the biggest suite first, and treat overrun as the signal to keep the green checkpoint rather than to hurry. | C40: Abandoned store 6+7 attempt (E118); repo-wide regex broke 16 files of supertest chains and cost the whole attempt | D40: Claude | E40: LOCKED

Sheet S1_Build_Board
A1: S1 BUILD BOARD — Foundation — exit: app installs cleanly in dev store/org; telemetry firing
A2: Backlog stories ST-051/052/055/056 (13 pts) + foundation infrastructure. Evidence version: product workbook v007 (22:03), codebase zip quoteflow_s1_foundation_20260910_2203.zip.
A3: ID | B3: Item | C3: Story ref | D3: Points | E3: Owner | F3: Status | G3: Notes / Evidence
A4: S1-01 | B4: Repo scaffold + strict tsc + jest with 100% coverage gate (D13) | C4: — | D4: 2 | E4: Claude | F4: Done | G4: jest.config.js coverageThreshold {stmts,branch,funcs,lines}=100; E001/E003.
A5: S1-02 | B5: Env config with secrets validation | C5: — | D5: 1 | E5: Claude | F5: Done | G5: src/config.ts — 6 tests; missing-var failures explicit.
A6: S1-03 | B6: Token store + deletion queue (adapter seam for Postgres) | C6: — | D6: 2 | E6: Claude | F6: Done | G6: src/store/tokenStore.ts, src/store/deletionQueue.ts; DQ4 constraint logged as R-Q4.
A7: S1-04 | B7: OAuth install flow -> welcome state | C7: ST-051 | D7: 5 | E7: Claude | F7: Done | G7: DONE-IN-CODE 22:03 — src/services/oauth.ts buildAuthorizeUrl/completeInstall, GET /install + /oauth/callback; state carries source+ts. v007.
A8: S1-05 | B8: Uninstall webhook: HMAC verify, token wipe, retention-scheduled deletion | C8: ST-052 | D8: 3 | E8: Claude | F8: Done | G8: DONE-IN-CODE 22:03 — src/webhooks/signature.ts (HubSpot v3 HMAC method+uri+body+timestamp, replay guard), src/services/uninstall.ts; retentionDays=30. v007.
A9: S1-06 | B9: Token refresh surviving platform rotation | C9: ST-055 | D9: 3 | E9: Claude | F9: Done | G9: DONE-IN-CODE 22:03 — src/services/tokenManager.ts: 60s expiry skew, rotation persisted, 5xx retry, 401 re-install path; 9 unit cases. v007.
A10: S1-07 | B10: Install telemetry with source attribution | C10: ST-056 | D10: 2 | E10: Claude | F10: Done | G10: DONE-IN-CODE 22:03 — src/services/telemetry.ts + normaliseSource bucketing hostile inputs; attribution round-trips OAuth state. v007.
A11: S1-08 | B11: D13 automation gate: 56 tests / 3 suites, 100% x4 | C11: — | D11: 2 | E11: Claude | F11: Pass | G11: test-run.log 20260910_2203; threshold enforced. E003.
A12: S1-09 | B12: LIVE dev-portal install verification | C12: ST-051 | D12: 0 | E12: Senthil | F12: Open | G12: Needs HubSpot dev portal app + client ID/secret; code-verified only. E004 / R-Q5.

Sheet S2_Build_Board
A1: S2 BUILD BOARD — Price book + bundles part 1 — exit: happy path demoable
A2: Stories ST-001..004 + ST-053/054 (29 pts). Evidence version: product workbook v008 (22:19), codebase zip quoteflow_s2_codebase_20260910_2219.zip.
A3: ID | B3: Item | C3: Story ref | D3: Points | E3: Owner | F3: Status | G3: Notes / Evidence
A4: S2-01 | B4: Catalog domain: books/items/bundles/rules, portal isolation | C4: — | D4: 3 | E4: Claude | F4: Done | G4: src/domain/catalog.ts; defensive copies; purge seam. v008.
A5: S2-02 | B5: One-call sensible defaults (idempotent) | C5: ST-001 | D5: 5 | E5: Claude | F5: Done | G5: DONE-IN-CODE 22:19 — Standard Price Book USD + 3 items + Starter bundle 10% + volume rule; POST /api/pricebooks/defaults 201/200. v008.
A6: S2-03 | B6: Happy-path pricing engine end-to-end | C6: ST-002 | D6: 8 | E6: Claude | F6: Done | G6: DONE-IN-CODE 22:19 — priceQuote: bundle=component sum x (1-disc), round2; verified 804.60+672.60=1477.20 over HTTP. v008.
A7: S2-04 | B7: Customisable rules (minQty/customerTier, best-wins) | C7: ST-003 | D7: 5 | E7: Claude | F7: Done | G7: DONE-IN-CODE 22:19 — validation matrix + largest-discount-wins with deterministic ties. v008.
A8: S2-05 | B8: Typed errors + platform backoff client | C8: ST-004 | D8: 3 | E8: Claude | F8: Done | G8: DONE-IN-CODE 22:19 — AppError{code,status,retryable,retryAfterMs}; PlatformClient 429/5xx backoff [100,200] -> retryable 503; 401 re-auth. v008.
A9: S2-06 | B9: Re-install restore within retention window | C9: ST-053 | D9: 3 | E9: Claude | F9: Done | G9: DONE-IN-CODE 22:19 — completeInstall cancels pending deletion -> "Your previous data was restored."; DeletionExecutor purges past window. v008.
A10: S2-07 | B10: RBAC owner>admin>member on every /api route | C10: ST-054 | D10: 5 | E10: Claude | F10: Done | G10: DONE-IN-CODE 22:19 — permission matrix + first-user-owner bootstrap + /api/users management; DQ2 identity decision. v008.
A11: S2-08 | B11: D13 gate: 103 tests / 5 suites, 100% x4 on 16 files | C11: — | D11: 2 | E11: Claude | F11: Pass | G11: test-run.log 20260910_2219. E007.

Sheet S3_Build_Board
A1: S3 BUILD BOARD — Price book part 2 + Approval chains start — exit: price book complete with tests; approvals skeleton
A2: Stories ST-005..010 + ST-011..014 + ST-085 (47 pts). Evidence version: product workbook v009 (22:52), codebase zip quoteflow_s3_codebase_20260910_2252.zip.
A3: ID | B3: Item | C3: Story ref | D3: Points | E3: Owner | F3: Status | G3: Notes / Evidence
A4: S3-01 | B4: HubSpot-signed CRM card + /ui/quote iframe shell | C4: ST-005 | D4: 5 | E4: Claude | F4: Done | G4: DONE-IN-CODE 22:52 — GET /crm-card v3-HMAC-verified (empty-body GET), card JSON w/ books/default/status + New-quote IFRAME action; paused-aware. Live HubSpot fetch open (R-Q6). v009.
A5: S3-02 | B5: Metrics + 7-day trend | C5: ST-006 | D5: 3 | E5: Claude | F5: Done | G5: DONE-IN-CODE 22:52 — quote log; quotes/total/avg/discounted-line% + UTC byDay; GET /api/metrics (admin); verified 731.60 across 2 quotes. v009.
A6: S3-03 | B6: Audit logging on every mutating /api action | C6: ST-007 | D6: 3 | E6: Claude | F6: Done | G6: DONE-IN-CODE 22:52 — record() on 14 mutating routes (actor+action+target+time); GET /api/audit. v009.
A7: S3-04 | B7: Pause/disable without data loss | C7: ST-008 | D7: 2 | E7: Claude | F7: Done | G7: DONE-IN-CODE 22:52 — requireActive gates quote pricing/import/approval requests w/ 409 FEATURE_PAUSED; reads + data untouched; resume instant. v009.
A8: S3-05 | B8: CSV + competitor import | C8: ST-009 | D8: 5 | E8: Claude | F8: Done | G8: DONE-IN-CODE 22:52 — quoted-field CSV parser; generic + rivalcpq header maps; row-level errors; case-insensitive SKU dedupe incl. within-file. v009.
A9: S3-06 | B9: Notifications: in-app + email, per-type mute, retry | C9: ST-010 | D9: 3 | E9: Claude | F9: Done | G9: DONE-IN-CODE 22:52 — 5 event types; muted type produces nothing; failed email kept + POST retry-email (502 retryable while transport down, heals to sent). v009.
A10: S3-07 | B10: Approval chain defaults in one call | C10: ST-011 | D10: 5 | E10: Claude | F10: Done | G10: DONE-IN-CODE 22:52 — "Discounts over 15% need manager approval", admin step, idempotent. v009.
A11: S3-08 | B11: Approvals happy path without documentation | C11: ST-012 | D11: 8 | E11: Claude | F11: Done | G11: DONE-IN-CODE 22:52 — request prices quote, strict-> trigger eval, first matching chain, auto-approve fallback; approve/reject walk; approver fan-out + requester notification. v009.
A12: S3-09 | B12: Customisable chain rules/conditions | C12: ST-013 | D12: 5 | E12: Claude | F12: Done | G12: DONE-IN-CODE 22:52 — discountPctAbove (0,1) / totalAbove>0 triggers, admin|owner steps, 10-case validation matrix; DQ3 step snapshot. v009.
A13: S3-10 | B13: Approvals clear errors + retry paths | C13: ST-014 | D13: 3 | E13: Claude | F13: Done | G13: DONE-IN-CODE 22:52 — typed 400/403/404/409 (DECISION_INVALID, STEP_ROLE, NOT_FOUND, ALREADY_DECIDED) + 502-retryable email retry. v009.
A14: S3-11 | B14: D13 coverage-gate story evidenced | C14: ST-085 | D14: 5 | E14: Claude | F14: Done | G14: DONE-IN-CODE 22:52 — threshold 100x4 enforced since S1; run 20260910_2252 = 150 tests / 7 suites, All files 100|100|100|100, EXIT=0. v009.
A15: S3-12 | B15: Postgres adapter | C15: — | D15: 0 | E15: Claude | F15: Deferred | G15: DQ4/L-018 — deferred to S4 honestly; store interfaces are the seam. v010 plan.

Sheet S4_Build_Board
A1: S4 BUILD BOARD — Approval chains part 2 + telemetry + smoke — exit: MVP loop usable end-to-end internally
A2: Stories ST-015..020 + ST-071/072 + ST-086 (34 pts). Evidence version: product workbook v010 (2026-09-11 08:17), codebase zip quoteflow_s4_codebase_20260911_0817.zip.
A3: ID | B3: Item | C3: Story ref | D3: Points | E3: Owner | F3: Status | G3: Notes / Evidence
A4: S4-01 | B4: Approvals on the signed CRM card + /ui/approvals shell | C4: ST-015 | D4: 5 | E4: Claude | F4: Done | G4: DONE-IN-CODE 08:17 — Pending-approvals NUMBER prop + Approvals IFRAME action; shell page. Live HubSpot fetch open (R-Q6). v010.
A5: S4-02 | B5: Approvals metrics + 7-day trend | C5: ST-016 | D5: 3 | E5: Claude | F5: Done | G5: DONE-IN-CODE 08:17 — status mix, auto-approval %, avgDecisionMs (verified 5000ms over HTTP); GET /api/approvals/metrics. v010.
A6: S4-03 | B6: Approvals permissions + audit hardening | C6: ST-017 | D6: 3 | E6: Claude | F6: Done | G6: DONE-IN-CODE 08:17 — decision audit target id:outcome; GET /api/audit?action= prefix filter. v010.
A7: S4-04 | B7: Feature-scoped pause without data loss | C7: ST-018 | D7: 2 | E7: Claude | F7: Done | G7: DONE-IN-CODE 08:17 — pricebook|approvals pause independently; pending decisions stay open (DQ6); FEATURE_INVALID 400. v010.
A8: S4-05 | B8: Chain CSV + competitor import | C8: ST-019 | D8: 5 | E8: Claude | F8: Done | G8: DONE-IN-CODE 08:17 — generic + rivalcpq, % / fraction thresholds, pipe steps, row-level errors; NaN guard bug-fix on createChain. v010.
A9: S4-06 | B9: Approval reminder nudge with per-type mute | C9: ST-020 | D9: 3 | E9: Claude | F9: Done | G9: DONE-IN-CODE 08:17 — approval_reminder type; requester-only, pending-only; fan-out honours mutes. v010.
A10: S4-07 | B10: Activation funnel dashboard endpoint | C10: ST-071 | D10: 5 | E10: Claude | F10: Done | G10: DONE-IN-CODE 08:17 — install->setup->aha->habit(10 quotes); markers wired into oauth/defaults/quotes; GET /api/funnel. v010.
A11: S4-08 | B11: Error tracking + release tagging + spike alert | C11: ST-072 | D11: 3 | E11: Claude | F11: Done | G11: DONE-IN-CODE 08:17 — APP_RELEASE tag; sendError records every error; 5-in-15min spike notifies admins once per episode (DQ7); GET /api/errors. v010.
A12: S4-09 | B12: E2E smoke suite on every deploy | C12: ST-086 | D12: 5 | E12: Claude | F12: Done | G12: DONE-IN-CODE 08:17 — tests/smoke.test.ts full journey; npm run test:smoke; CI smoke-on-deploy job on main. v010.
A13: S4-10 | B13: Postgres adapter (deferred-in from S3) | C13: — | D13: 0 | E13: Claude | F13: Blocked | G13: Live install attempted: apt mirror 404s + timeout, PG_ABSENT verified (E016/L-024). Needs working mirror or container DB — carried to S5.

Sheet S5_Build_Board
A1: S5 BUILD BOARD — E-signature + alpha hardening — exit: internal alpha, team dogfoods daily
A2: Stories ST-021..030 + ST-078/079 (50 pts). Evidence version: product workbook v011 (2026-09-11 08:52), codebase zip quoteflow_s5_codebase_20260911_0852.zip.
A3: ID | B3: Item | C3: Story ref | D3: Points | E3: Owner | F3: Status | G3: Notes / Evidence
A4: S5-01 | B4: One-call esign defaults | C4: ST-021 | D4: 5 | E4: Claude | F4: Done | G4: DONE-IN-CODE 08:52 — 14d/3d/require-all/decline-on, idempotent; teaching 404 pre-setup. v011.
A5: S5-02 | B5: Happy path: envelope -> token links -> sign -> completed | C5: ST-022 | D5: 8 | E5: Claude | F5: Done | G5: DONE-IN-CODE 08:52 — public /api/esign/sign/:token (identity bypass, DQ8); validate-then-mint tokens; sha256 doc hash. v011.
A6: S5-03 | B6: Customisable settings | C6: ST-023 | D6: 5 | E6: Claude | F6: Done | G6: DONE-IN-CODE 08:52 — validation matrix; snapshot-at-creation semantics (DQ9). v011.
A7: S5-04 | B7: Clear errors + retry paths | C7: ST-024 | D7: 3 | E7: Claude | F7: Done | G7: DONE-IN-CODE 08:52 — EXPIRED 410 lazy+sticky w/ re-send hint, VOIDED/DECLINED/ALREADY_SIGNED/TOKEN_INVALID/DECLINE_DISABLED. v011.
A8: S5-05 | B8: CRM card + signer shell surface | C8: ST-025 | D8: 5 | E8: Claude | F8: Done | G8: DONE-IN-CODE 08:52 — Awaiting-signature count 1->0 proved; /ui/sign shell. Live HubSpot fetch open (R-Q6). v011.
A9: S5-06 | B9: Esign metrics + trends | C9: ST-026 | D9: 3 | E9: Claude | F9: Done | G9: DONE-IN-CODE 08:52 — 40% completion / avg 3000ms mix; expiry recount at +20d. v011.
A10: S5-07 | B10: Permissions + signer-identity audit | C10: ST-027 | D10: 3 | E10: Claude | F10: Done | G10: DONE-IN-CODE 08:52 — esign:read/send/manage; audit actor signer:<email>. v011.
A11: S5-08 | B11: Pause without data loss | C11: ST-028 | D11: 2 | E11: Claude | F11: Done | G11: DONE-IN-CODE 08:52 — new envelopes 409 while paused; sent links keep signing (DQ9). v011.
A12: S5-09 | B12: CSV + rivalsign import | C12: ST-029 | D12: 5 | E12: Claude | F12: Done | G12: DONE-IN-CODE 08:52 — row-level errors, ragged-row tolerant; imported rows land in list + metrics. v011.
A13: S5-10 | B13: Envelope notifications w/ per-type mute | C13: ST-030 | D13: 3 | E13: Claude | F13: Done | G13: DONE-IN-CODE 08:52 — envelope_sent/signed/declined; mute framework covers them. v011.
A14: S5-11 | B14: First-run checklist | C14: ST-078 | D14: 5 | E14: Claude | F14: Done | G14: DONE-IN-CODE 08:52 — 7 live-derived items w/ exact next call; 14% -> 100% over real HTTP actions. v011.
A15: S5-12 | B15: Empty states teach next action | C15: ST-079 | D15: 3 | E15: Claude | F15: Done | G15: DONE-IN-CODE 08:52 — emptyState on all five lists; drops when populated. v011.

Sheet S6_Build_Board
A1: S6 BUILD BOARD — Quote analytics + Billing — exit: can charge a test customer; upgrade/downgrade paths work
A2: Stories ST-031..040 + ST-057/058/059 (60 pts). Evidence version: product workbook v012 (2026-09-11 12:47), codebase zip quoteflow_s6_codebase_20260911_1247.zip.
A3: ID | B3: Item | C3: Story ref | D3: Points | E3: Owner | F3: Status | G3: Notes / Evidence
A4: S6-01 | B4: One-call analytics defaults | C4: ST-031 | D4: 5 | E4: Claude | F4: Done | G4: DONE-IN-CODE 12:47 — idempotent; teaching 404 pre-setup. v012.
A5: S6-02 | B5: Summary dashboard happy path | C5: ST-032 | D5: 8 | E5: Claude | F5: Done | G5: DONE-IN-CODE 12:47 — pipeline/discount/win-rate/large/stale/pace; exact-math units. v012.
A6: S6-03 | B6: Customisable analytics settings | C6: ST-033 | D6: 5 | E6: Claude | F6: Done | G6: DONE-IN-CODE 12:47 — 11-case validation matrix. v012.
A7: S6-04 | B7: Typed errors + export | C7: ST-034 | D7: 3 | E7: Claude | F7: Done | G7: DONE-IN-CODE 12:47 — pre-setup 404s over HTTP; CSV/JSON; EXPORT_FORMAT_INVALID. v012.
A8: S6-05 | B8: Card + UI extension surface | C8: ST-035 | D8: 5 | E8: Claude | F8: Done | G8: DONE-IN-CODE 12:47 — Quotes(7d) on signed card; Analytics action; shell. Live fetch open (R-Q6). v012.
A9: S6-06 | B9: Trends | C9: ST-036 | D9: 3 | E9: Claude | F9: Done | G9: DONE-IN-CODE 12:47 — 7d buckets, top discounters, wonValue7d. v012.
A10: S6-07 | B10: Permissions + audit | C10: ST-037 | D10: 3 | E10: Claude | F10: Done | G10: DONE-IN-CODE 12:47 — read (member) / manage (admin); four audited actions. v012.
A11: S6-08 | B11: Pause without data loss | C11: ST-038 | D11: 2 | E11: Claude | F11: Done | G11: DONE-IN-CODE 12:47 — DQ10: dashboards 409, capture continues; paused-time quote visible after resume. v012.
A12: S6-09 | B12: History import | C12: ST-039 | D12: 5 | E12: Claude | F12: Done | G12: DONE-IN-CODE 12:47 — generic+rivaliq; column-order independent; ragged tolerant. v012.
A13: S6-10 | B13: Alerts w/ per-type mute | C13: ST-040 | D13: 3 | E13: Claude | F13: Done | G13: DONE-IN-CODE 12:47 — discount_alert + goal_reached (fires exactly once); mute proved. v012.
A14: S6-11 | B14: 14-day card-free trial | C14: ST-057 | D14: 5 | E14: Claude | F14: Done | G14: DONE-IN-CODE 12:47 — seeded at install; countdown banner; lazy expiry flip. v012.
A15: S6-12 | B15: Prorated plan changes | C15: ST-058 | D15: 5 | E15: Claude | F15: Done | G15: DONE-IN-CODE 12:47 — exact cents up/down; net<=0 no provider call; clamps. v012.
A16: S6-13 | B16: Marketplace vs Stripe routing | C16: ST-059 | D16: 8 | E16: Claude | F16: Done | G16: DONE-IN-CODE 12:47 — channel-routed; failure 502 persists nothing. Live credentials open (R-Q10). v012.

Sheet S7_Build_Board
A1: S7 BUILD BOARD — Billing hardening + least-privilege scopes — exit: private beta with design partners
A2: Stories ST-060..064 (15 pts). Evidence version: product workbook v013 (2026-09-13 10:26), codebase zip quoteflow_s7_codebase_20260913_1026.zip.
A3: ID | B3: Item | C3: Story ref | D3: Points | E3: Owner | F3: Status | G3: Notes / Evidence
A4: S7-01 | B4: Failed payment: grace, dunning, read-only | C4: ST-060 | D4: 3 | E4: Claude | F4: Done | G4: DONE-IN-CODE 10:26 — 7d grace, 3 notices max one/day, lazy+sticky lapse, recovery re-charge; reads survive (DQ12). v013.
A5: S7-02 | B5: Plan limits with 80/100% prompts | C5: ST-061 | D5: 3 | E5: Claude | F5: Done | G5: DONE-IN-CODE 10:26 — Pro 200 / Scale 2000; warning once per crossing; 402 on all three quote paths; floored pct. v013.
A6: S7-03 | B6: Invoices/receipts with GST-VAT fields | C6: ST-062 | D6: 3 | E6: Claude | F6: Done | G6: DONE-IN-CODE 10:26 — auto-issued on every positive charge; tax profile applied at issue; text receipts. v013.
A7: S7-04 | B7: Cancellation with save-offer + exit survey | C7: ST-063 | D7: 3 | E7: Claude | F7: Done | G7: DONE-IN-CODE 10:26 — offer-before-accept guard, fixed reason set, cancelled portals still read/export. v013.
A8: S7-05 | B8: Least-privilege scope map | C8: ST-064 | D8: 3 | E8: Claude | F8: Done | G8: DONE-IN-CODE 10:26 — registry + two-way audit + generated disclosure; leastPrivilege asserted vs real config (DQ13). v013.

Sheet S8_Build_Board
A1: S8 BUILD BOARD — Deal sync + trust + founder ops + performance — exit: beta iteration complete, sync shipped
A2: 22 stories / 87 pts across F5, E6, E7 and EQ. Evidence: product workbook v014 (2026-09-13 10:38), codebase zip quoteflow_s8_codebase_20260913_1038.zip.
A3: ID | B3: Item | C3: Story ref | D3: Points | E3: Owner | F3: Status | G3: Notes / Evidence
A4: S8-01 | B4: Sync defaults | C4: ST-041 | D4: 5 | E4: Claude | F4: Done | G4: DONE-IN-CODE 10:38 — idempotent defaults, teaching 404. v014.
A5: S8-02 | B5: Sync happy path (idempotent push) | C5: ST-042 | D5: 8 | E5: Claude | F5: Done | G5: DONE-IN-CODE 10:38 — replace/append + amount; repeat push writes nothing (DQ14). v014.
A6: S8-03 | B6: Sync rules and conditions | C6: ST-043 | D6: 5 | E6: Claude | F6: Done | G6: DONE-IN-CODE 10:38 — mode/strategy/amount/skipStages/minTotal, all skip paths write nothing. v014.
A7: S8-04 | B7: Errors + retry paths | C7: ST-044 | D7: 3 | E7: Claude | F7: Done | G7: DONE-IN-CODE 10:38 — 502 + admin alert + retry w/ supersede. v014.
A8: S8-05 | B8: Card / UI extension surface | C8: ST-045 | D8: 5 | E8: Claude | F8: Done | G8: DONE-IN-CODE 10:38 — /ui/sync shell; billing read-only gate. Live fetch open (R-Q6). v014.
A9: S8-06 | B9: Sync metrics + trends | C9: ST-046 | D9: 3 | E9: Claude | F9: Done | G9: DONE-IN-CODE 10:38 — mix, success rate, topErrors, real durations. v014.
A10: S8-07 | B10: Permissions + audit | C10: ST-047 | D10: 3 | E10: Claude | F10: Done | G10: DONE-IN-CODE 10:38 — sync:read/push/manage; four audited actions. v014.
A11: S8-08 | B11: Pause without data loss | C11: ST-048 | D11: 2 | E11: Claude | F11: Done | G11: DONE-IN-CODE 10:38 — queue-and-drain (DQ14), nothing written while paused. v014.
A12: S8-09 | B12: Sync history import | C12: ST-049 | D12: 5 | E12: Claude | F12: Done | G12: DONE-IN-CODE 10:38 — generic+rivalsync, 6-row error matrix, ragged tolerant. v014.
A13: S8-10 | B13: Sync notifications | C13: ST-050 | D13: 3 | E13: Claude | F13: Done | G13: DONE-IN-CODE 10:38 — sync_failed admin fan-out + sync_completed. v014.
A14: S8-11 | B14: Data-flow diagram + retention | C14: ST-065 | D14: 3 | E14: Claude | F14: Done | G14: DONE-IN-CODE 10:38 — 7 stores declared as data, asserted by tests (DQ15). v014.
A15: S8-12 | B15: Encryption + secrets posture | C15: ST-066 | D15: 5 | E15: Claude | F15: Partial | G15: CODE DONE 10:38 — controls published; SEC-03 vault and SEC-04 at-rest reported PARTIAL, owner Senthil (R-Q11). v014.
... A25: S8-22 | B25: Zero-downtime deploy verified | C25: ST-092 | D25: 3 | E25: Claude | F25: Done | G25: DONE-IN-CODE 10:38 — /ready 503 on drain, /health green, in-flight completes. v014.

Sheet S9_Build_Board
A1: S9 BUILD BOARD — Marketplace review prep — exit: submission-ready evidence pack
A2: 7 stories / 30 pts. Evidence: product workbook v015 (2026-09-13 10:56), codebase zip quoteflow_s9_codebase_20260913_1056.zip.
A3: ID | B3: Item | C3: Story ref | D3: Points | E3: Owner | F3: Status | G3: Notes / Evidence
A4: S9-01 | B4: Pen-test evidence archived | C4: ST-068 | D4: 8 | E4: Claude + Senthil | F4: Partial | G4: CODE DONE 10:56 — 10 abuse cases (8 automated / 1 manual / 1 external); pack states no external pen test commissioned. R-Q12 opened. v015.
A5: S9-02 | B5: Data export + delete-my-data self-serve | C5: ST-069 | D5: 5 | E5: Claude | F5: Done | G5: DONE-IN-CODE 10:56 — full bundle + manifest; two-step token-confirmed deletion w/ receipt (DQ17). v015.
A6: S9-03 | B6: WCAG AA pass on primary flows | C6: ST-089 | D6: 3 | E6: Claude | F6: Done | G6: DONE-IN-CODE 10:56 — all 5 shells pass 11 automated AA rules; checker tested against broken HTML. Manual audit scoped out explicitly. v015.
A7: S9-04 | B7: Backup + restore drill executed | C7: ST-090 | D7: 3 | E7: Claude | F7: Done | G7: DONE-IN-CODE 10:56 — round-trip byte-compare; skipped sources surfaced; lossy source detected. Drill data-loss defect found and fixed (L-062). v015.
A8: S9-05 | B8: Chaos: platform outage degrades gracefully | C8: ST-091 | D8: 3 | E8: Claude | F8: Done | G8: DONE-IN-CODE 10:56 — six properties asserted incl. signer never stranded, no partial state, readiness stays green. v015.
A9: S9-06 | B9: Listing copy A + B variants | C9: ST-093 | D9: 3 | E9: Claude | F9: Done | G9: DONE-IN-CODE 10:56 — two full variants, every claim maps to a Done story, length limits asserted. v015.
A10: S9-07 | B10: 5 screenshots + 2-min demo video | C10: ST-094 | D10: 5 | E10: Claude + Senthil | F10: Partial | G10: BRIEF DONE 10:56 — specs, 5-shot list, timed 1:55 script, checklist. CAPTURE blocked on live install (R-Q5). v015.

Sheet S10_Build_Board
A1: S10 BUILD BOARD — Launch surfaces: docs, support, public pages — exit: submission-ready
A2: 7 stories / 24 pts. Evidence: product workbook v016 (2026-09-13 11:11), codebase zip quoteflow_s10_codebase_20260913_1111.zip.
A3: ID | B3: Item | C3: Story ref | D3: Points | E3: Owner | F3: Status | G3: Notes / Evidence
A4: S10-01 | B4: Help centre: 15 articles + search | C4: ST-080 | D4: 5 | E4: Claude | F4: Done | G4: DONE-IN-CODE 11:11 — public endpoints; ranked search; feature-coverage test means shipping without docs fails the build. v016.
A5: S10-02 | B5: In-app chat with <4 business-hr response | C5: ST-081 | D5: 3 | E5: Claude | F5: Done | G5: DONE-IN-CODE 11:11 — business-hours SLA (DQ20), deflection articles at open, overdue counted. Staffing the queue is operational. v016.
A6: S10-03 | B6: Demo video + interactive sandbox mode | C6: ST-083 | D6: 5 | E6: Claude | F6: Done | G6: DONE-IN-CODE 11:11 — sandbox seeds realistic data, double-seed refused. Video script delivered in S9 brief; recording needs live install (R-Q5). v016.
A7: S10-04 | B7: Status page + incident comms template | C7: ST-084 | D7: 2 | E7: Claude | F7: Done | G7: DONE-IN-CODE 11:11 — live-signal component roll-up; four pre-written templates. v016.
A8: S10-05 | B8: Pricing page/plan matrix + FAQ | C8: ST-095 | D8: 3 | E8: Claude | F8: Done | G8: DONE-IN-CODE 11:11 — generated from PLANS (DQ19); 7-entry FAQ; values asserted against billing constants. v016.
A9: S10-06 | B9: Security/trust page live | C9: ST-096 | D9: 3 | E9: Claude | F9: Done | G9: DONE-IN-CODE 11:11 — generated from DATA_FLOW/SCOPE_REGISTRY/SECURITY_CONTROLS; subprocessors listed; unmet controls published with owners. v016.
A10: S10-07 | B10: Submission dry-run by second reviewer | C10: ST-097 | D10: 3 | E10: Claude | F10: Done | G10: DONE-IN-CODE 11:11 — 14 checklist items read from live state; 12 pass / 0 fail / 2 manual (DQ21). v016.

Sheet S11_Build_Board
A1: S11 BUILD BOARD — Launch — exit: live on the marketplace
A2: 3 stories / 8 pts. Evidence: product workbook v017 (2026-09-13 11:25), codebase zip quoteflow_s11_codebase_20260913_1125.zip.
A3: ID | B3: Item | C3: Story ref | D3: Points | E3: Owner | F3: Status | G3: Notes / Evidence
A4: S11-01 | B4: In-app review ask after aha-moment | C4: ST-082 | D4: 3 | E4: Claude | F4: Done | G4: DONE-IN-CODE 11:25 — happy-portal gates, lifetime cap, permanent decline, no review-gating (DQ22). v017.
A5: S11-02 | B5: Launch-day runbook: monitoring, rollback, comms | C5: ST-098 | D5: 3 | E5: Claude | F5: Done | G5: DONE-IN-CODE 11:25 — live preflight incl. real restore drill, 7 verified rollback steps (77 min), comms tree (DQ23). v017.
A6: S11-03 | B6: First 10 design-partner reviews scheduled | C6: ST-100 | D6: 2 | E6: Claude | F6: Done | G6: DONE-IN-CODE 11:25 — pipeline + outreach sequence; counts scheduled not intentions (DQ24). Contacting real partners is Senthil. v017.

Sheet S12_Build_Board
A1: S12 BUILD BOARD — Iterate & scale decision — exit: growth model with first CAC/LTV estimates
A2: 1 story / 2 pts. Evidence: product workbook v018 (2026-09-13 11:34), codebase zip quoteflow_s12_codebase_20260913_1134.zip. Note: the board exit criterion mentions a CAC/LTV growth model; the backlog carries only ST-099 for S12, and the backlog is the single source of truth — no growth model was invented to match the criterion.
A3: ID | B3: Item | C3: Story ref | D3: Points | E3: Owner | F3: Status | G3: Notes / Evidence
A4: S12-01 | B4: Listing SEO iteration 1 from search-term data | C4: ST-099 | D4: 2 | E4: Claude | F4: Done | G4: DONE-IN-CODE 11:34 — import + five-verdict classification + ranked recommendations; unsupported demand excluded from copy (DQ25); substring-matching defect found and fixed. Iteration against REAL numbers needs post-launch console data (R-Q5/R-Q10). v018.

Sheet Review_Pass1_Board
A1: COLD REVIEW PASS 1 — fix board (13 Sep 2026 11:51)
A2: Full finding detail is on the Review_Findings sheet of product workbook v019. Code: quoteflow_review1_codebase_20260913_1151.zip.
A3: Ref | B3: Severity | C3: Area | D3: Status | E3: Regression test
A4: F-Q01 | B4: CRITICAL | C4: Privacy / backup — delete-my-data left 3 sources behind | D4: Fixed | E4: review1 F-Q01 + S9 assertions 8->11
A5: F-Q02 | B5: CRITICAL | C5: Deployability — no entrypoint, no npm start | D5: Fixed | E5: review1 F-Q02
A6: F-Q03 | B6: CRITICAL | C6: Identity — unsigned caller-declared headers | D6: Fixed | E6: review1 F-Q03 (4 rejection paths)
A7: F-Q04 | B7: CRITICAL | C7: Billing — expired trial not read-only | D7: Fixed | E7: review1 F-Q04
A8: F-Q05 | B8: HIGH | C8: OAuth — callback accepted any state | D8: Fixed | E8: review1 F-Q05
A9: F-Q06 | B9: HIGH | C9: HTTP — async handler rejections hang the request | D9: Fixed | E9: review1 F-Q06
A10: F-Q07 | B10: MEDIUM | C10: Tenancy — SEO corpus shared across portals | D10: Fixed | E10: review1 F-Q07
A11: F-Q08 | B11: MEDIUM | C11: Memory — unbounded ledgers | D11: Fixed | E11: review1 F-Q08

Sheet Review_Pass2_Board
A1: COLD REVIEW PASS 2 — published claims vs code, and missing artifacts (13 Sep 2026 12:03)
A2: Full detail on the Review_Findings sheet of product workbook v020. Code: quoteflow_review2_codebase_20260913_1203.zip.
A3: Ref | B3: Severity | C3: Area | D3: Status | E3: Gate shipped with the fix
A4: F-Q09 | B4: CRITICAL | C4: Retention — published schedule enforced by nothing | D4: Fixed | E4: Drift gate: sweepers must equal the published age-bounded stores
A5: F-Q10 | B5: HIGH | C5: Redaction control with zero call sites (SEC-05) | D5: Fixed | E5: Regression on error-route and telemetry-prop redaction
A6: F-Q11 | B6: MEDIUM | C6: Circuit breaker on writes only despite ST-070 claim | D6: Fixed | E6: Regression: open breaker means reads never reach the platform
A7: F-Q12 | B7: MEDIUM | C7: No deploy workflow behind the rollback runbook | D7: Fixed | E7: Order gate: drain precedes cutover precedes verify
A8: F-Q13 | B8: MEDIUM | C8: No DB schema behind retention / backup / at-rest claims | D8: Fixed | E8: Drift gate: every published store has a table + cascade + sweep index
A9: F-Q14 | B9: MEDIUM | C9: Future-dated signatures replayable forever | D9: Fixed | E9: Regression: beyond-skew refused, modest skew tolerated

Sheet Review_Pass3_Board
A1: COLD REVIEW PASS 3 - surfaces wired to constants, and a tenancy boundary (13 Sep 2026 16:25)
A2: Detail on Review_Findings in product workbook v021. Code: quoteflow_review3_codebase_20260913_1625.zip.
A3: Ref | B3: Severity | C3: Area | D3: Status | E3: Gate shipped with the fix
A4: F-Q15 | B4: HIGH | C4: Public status page wired to hardcoded false/0 | D4: Fixed | E4: Regression: real failed run degrades, open breaker escalates to outage
A5: F-Q16 | B5: MEDIUM | C5: Preflight readiness hardcoded true | D5: Fixed | E5: Regression: draining flips PRE-03 and the decision to no_go
A6: F-Q17 | B6: CRITICAL | C6: Nine vendor surfaces reachable with tenant RBAC | D6: Fixed | E6: Regression: tenant creds refused, wrong same-length token refused, unset = closed

Sheet Traceability_Matrix
A1: TRACEABILITY MATRIX — 100 stories: module -> epic -> story -> sprint -> verification -> evidence
A2: Source: v009 Full_Backlog (single source of truth). Status "Done" = Done-in-code under the D13 100% gate; Evidence cites the product-workbook version + test run carrying the proof. Rollup formulas read cols E/G/J.
A3: Story ID | B3: Epic | C3: Module / feature | D3: Story | E3: Points | F3: Priority | G3: Sprint | H3: Primary screen | I3: Verification | J3: Status | K3: Evidence
A4: ST-001 | B4: F1 | C4: Price book + bundles | D4: As a Sales manager, I can set up Price book + bundles with sensible defaults in one screen | E4: 5 | F4: P0 | G4: S2 | H4: SCR-3 Price book workspace | I4: Automated: unit + HTTP integration (supertest) | J4: Done | K4: v008 22:19 — priceBookService.setupDefaults idempotent + POST /api/pricebooks/defaults; s2 + s2api suites; 100% x4 (run 2219)
A5: ST-002 | B5: F1 | C5: Price book + bundles | D5: As a Sales manager, the Price book + bundles happy path completes without documentation | E5: 8 | F5: P0 | G5: S2 | H5: SCR-3 Price book workspace | I5: Automated: unit + HTTP integration (supertest) | J5: Done | K5: v008 22:19 — priceQuote engine (bundle maths 804.60+672.60=1477.20) + quotes/price E2E over HTTP; 100% x4 (run 2219)
A6: ST-003 | B6: F1 | C6: Price book + bundles | D6: As a RevOps, I can customise Price book + bundles rules/conditions for my workflow | E6: 5 | F6: P1 | G6: S2 | H6: SCR-3 Price book workspace | I6: Automated: unit + HTTP integration (supertest) | J6: Done | K6: v008 22:19 — addRule validation + best-discount-wins engine; 7-case matrix + tiered HTTP quote; 100% x4 (run 2219)
A7: ST-004 | B7: F1 | C7: Price book + bundles | D7: As a user, Price book + bundles shows clear errors and retry paths on platform API failures | E7: 3 | F7: P0 | G7: S2 | H7: SCR-3 Price book workspace | I7: Automated: unit + HTTP integration (supertest) | J7: Done | K7: v008 22:19 — AppError + PlatformClient backoff [100,200]; 6 unit + 7 HTTP platform/check cases; 100% x4 (run 2219)
A8: ST-005 | B8: F1 | C8: Price book + bundles | D8: As a Rep, Price book + bundles works on the HubSpot CRM card + UI extension surface end-to-end | E8: 5 | F8: P0 | G8: S3 | H8: SCR-3 Price book workspace | I8: Automated: unit + HTTP integration (supertest) | J8: Done | K8: v009 22:52 — crmCard.ts + signed GET /crm-card + /ui/quote shell; unsigned 401/bad-ids 400/happy/paused HTTP cases; 100% x4 (run 2252). Live HubSpot fetch OPEN (R-Q6)
A9: ST-006 | B9: F1 | C9: Price book + bundles | D9: As a RevOps, I can see Price book + bundles performance metrics and trends | E9: 3 | F9: P1 | G9: S3 | H9: SCR-3 Price book workspace | I9: Automated: unit + HTTP integration (supertest) | J9: Done | K9: v009 22:52 — metricsService aggregates + 7-day UTC trend + GET /api/metrics; bucket-boundary units + 731.60 HTTP case; 100% x4 (run 2252)
A10: ST-007 | B10: F1 | C10: Price book + bundles | D10: As a user, Price book + bundles respects role permissions and audit logging | E10: 3 | F10: P1 | G10: S3 | H10: SCR-3 Price book workspace | I10: Automated: unit + HTTP integration (supertest) | J10: Done | K10: v009 22:52 — audit.ts + record() on 14 mutating routes + GET /api/audit; actor/target HTTP assertions; 100% x4 (run 2252)
A11: ST-008 | B11: F1 | C11: Price book + bundles | D11: As a Sales manager, I can pause/disable Price book + bundles without data loss | E11: 2 | F11: P2 | G11: S3 | H11: SCR-3 Price book workspace | I11: Automated: unit + HTTP integration (supertest) | J11: Done | K11: v009 22:52 — catalog paused flag + requireActive 409 gate + settings routes; writes-blocked/reads-intact/resume E2E; 100% x4 (run 2252)
A12: ST-009 | B12: F1 | C12: Price book + bundles | D12: As a RevOps, I can import/migrate existing data into Price book + bundles (CSV + competitor importer) | E12: 5 | F12: P1 | G12: S3 | H12: SCR-3 Price book workspace | I12: Automated: unit + HTTP integration (supertest) | J12: Done | K12: v009 22:52 — importService quoted-CSV parser + generic/rivalcpq maps + row-level errors; 6-row error matrix + import->quote E2E; 100% x4 (run 2252)
A13: ST-010 | B13: F1 | C13: Price book + bundles | D13: As a user, I get notifications (in-app + email) for key Price book + bundles events with per-type mute | E13: 3 | F13: P2 | G13: S3 | H13: SCR-3 Price book workspace | I13: Automated: unit + HTTP integration (supertest) | J13: Done | K13: v009 22:52 — notifications domain+service (per-type mute, failed-email retry) + 5 routes; mute-suppression + 502-retryable->healed E2E; 100% x4 (run 2252)
A14: ST-011 | B14: F2 | C14: Approval chains | D14: As a Sales manager, I can set up Approval chains with sensible defaults in one screen | E14: 5 | F14: P0 | G14: S3 | H14: SCR-4 Approval chains builder | I14: Automated: unit + HTTP integration (supertest) | J14: Done | K14: v009 22:52 — approvalService.setupDefaults (15% admin chain, idempotent) + defaults route; 201/200 + member-403 cases; 100% x4 (run 2252)
A15: ST-012 | B15: F2 | C15: Approval chains | D15: As a Sales manager, the Approval chains happy path completes without documentation | E15: 8 | F15: P0 | G15: S3 | H15: SCR-4 Approval chains builder | I15: Automated: unit + HTTP integration (supertest) | J15: Done | K15: v009 22:52 — requestApproval strict-> eval + decide walk + fan-out; full E2E pending->notified->approved->requester-notified; 100% x4 (run 2252)
... A103: ST-100 | B103: EL | C103: Launch & listing | D103: First 10 design-partner reviews scheduled | E103: 2 | F103: P1 | G103: S11 | H103: — (marketplace listing) | I103: Automated: unit + HTTP integration (supertest) | J103: Done | K103: v017 11:25 — identified/contacted count as 0 scheduled; target flips onTrack at 10; 100% x4 (run 1125)

Sheet Sprint_Status_Rollup
A1: SPRINT STATUS ROLLUP — live formulas over Traceability_Matrix
A2: Do not edit computed cells. 'Done' counts Done-in-code under D13. RAG is manual.
A3: Sprint | B3: Focus | C3: Stories | D3: Points | E3: Done | F3: Done points | G3: % points done | H3: RAG (manual) | I3: Exit criteria
A4: S1 | B4: Foundation (2 wks) | C4: =COUNTIF(Traceability_Matrix!$G$4:$G$103,"S1") -> 4 | D4: =SUMIF(Traceability_Matrix!$G$4:$G$103,"S1",Traceability_Matrix!$E$4:$E$103) -> 13 | E4: =COUNTIFS(Traceability_Matrix!$G$4:$G$103,"S1",Traceability_Matrix!$J$4:$J$103,"Done") -> 4 | F4: =SUMIFS(Traceability_Matrix!$E$4:$E$103,Traceability_Matrix!$G$4:$G$103,"S1",Traceability_Matrix!$J$4:$J$103,"Done") -> 13 | G4: =IFERROR(SUMIFS(Traceability_Matrix!$E$4:$E$103,Traceability_Matrix!$G$4:$G$103,"S1",Traceability_Matrix!$J$4:$J$103,"Done")/SUMIF(Traceability_Matrix!$G$4:$G$103,"S1",Traceability_Matrix!$E$4:$E$103),0) -> 1 | H4: GREEN — 4/4 done-in-code; live install pending (R-Q5) | I4: App installs cleanly in dev store/org; telemetry firing
A5: S2 | B5: Core feature Price book + bundles - part 1 | C5: =COUNTIF(Traceability_Matrix!$G$4:$G$103,"S2") -> 6 | D5: =SUMIF(Traceability_Matrix!$G$4:$G$103,"S2",Traceability_Matrix!$E$4:$E$103) -> 29 | E5: =COUNTIFS(Traceability_Matrix!$G$4:$G$103,"S2",Traceability_Matrix!$J$4:$J$103,"Done") -> 6 | F5: =SUMIFS(Traceability_Matrix!$E$4:$E$103,Traceability_Matrix!$G$4:$G$103,"S2",Traceability_Matrix!$J$4:$J$103,"Done") -> 29 | G5: =IFERROR(SUMIFS(Traceability_Matrix!$E$4:$E$103,Traceability_Matrix!$G$4:$G$103,"S2",Traceability_Matrix!$J$4:$J$103,"Done")/SUMIF(Traceability_Matrix!$G$4:$G$103,"S2",Traceability_Matrix!$E$4:$E$103),0) -> 1 | H5: GREEN — 6/6 done-in-code; happy path E2E-proven | I5: Price book + bundles happy path demoable
A6: S3 | B6: Core feature Price book + bundles - part 2 + Approval chains start | C6: =COUNTIF(Traceability_Matrix!$G$4:$G$103,"S3") -> 11 | D6: =SUMIF(Traceability_Matrix!$G$4:$G$103,"S3",Traceability_Matrix!$E$4:$E$103) -> 47 | E6: =COUNTIFS(Traceability_Matrix!$G$4:$G$103,"S3",Traceability_Matrix!$J$4:$J$103,"Done") -> 11 | F6: =SUMIFS(Traceability_Matrix!$E$4:$E$103,Traceability_Matrix!$G$4:$G$103,"S3",Traceability_Matrix!$J$4:$J$103,"Done") -> 47 | G6: =IFERROR(SUMIFS(Traceability_Matrix!$E$4:$E$103,Traceability_Matrix!$G$4:$G$103,"S3",Traceability_Matrix!$J$4:$J$103,"Done")/SUMIF(Traceability_Matrix!$G$4:$G$103,"S3",Traceability_Matrix!$E$4:$E$103),0) -> 1 | H6: GREEN — 11/11 done-in-code; live CRM card fetch pending (R-Q6) | I6: Price book + bundles complete with tests; Approval chains skeleton
A7: S4 | B7: Core feature Approval chains | C7: =COUNTIF(Traceability_Matrix!$G$4:$G$103,"S4") -> 9 | D7: =SUMIF(Traceability_Matrix!$G$4:$G$103,"S4",Traceability_Matrix!$E$4:$E$103) -> 34 | E7: =COUNTIFS(Traceability_Matrix!$G$4:$G$103,"S4",Traceability_Matrix!$J$4:$J$103,"Done") -> 9 | F7: =SUMIFS(Traceability_Matrix!$E$4:$E$103,Traceability_Matrix!$G$4:$G$103,"S4",Traceability_Matrix!$J$4:$J$103,"Done") -> 34 | G7: =IFERROR(SUMIFS(Traceability_Matrix!$E$4:$E$103,Traceability_Matrix!$G$4:$G$103,"S4",Traceability_Matrix!$J$4:$J$103,"Done")/SUMIF(Traceability_Matrix!$G$4:$G$103,"S4",Traceability_Matrix!$E$4:$E$103),0) -> 1 | H7: GREEN — 9/9 done-in-code; smoke suite = MVP loop; Postgres carried (R-Q4) | I7: MVP loop usable end-to-end internally
A8: S5 | B8: Feature E-signature + alpha hardening | C8: =COUNTIF(Traceability_Matrix!$G$4:$G$103,"S5") -> 12 | D8: =SUMIF(Traceability_Matrix!$G$4:$G$103,"S5",Traceability_Matrix!$E$4:$E$103) -> 50 | E8: =COUNTIFS(Traceability_Matrix!$G$4:$G$103,"S5",Traceability_Matrix!$J$4:$J$103,"Done") -> 12 | F8: =SUMIFS(Traceability_Matrix!$E$4:$E$103,Traceability_Matrix!$G$4:$G$103,"S5",Traceability_Matrix!$J$4:$J$103,"Done") -> 50 | G8: =IFERROR(SUMIFS(Traceability_Matrix!$E$4:$E$103,Traceability_Matrix!$G$4:$G$103,"S5",Traceability_Matrix!$J$4:$J$103,"Done")/SUMIF(Traceability_Matrix!$G$4:$G$103,"S5",Traceability_Matrix!$E$4:$E$103),0) -> 1 | H8: GREEN — 12/12 done-in-code; e-sign loop smoke-verified; live dogfood needs deployment (R-Q5) | I8: Internal alpha: team dogfoods daily
A9: S6 | B9: Billing + Quote analytics | C9: =COUNTIF(Traceability_Matrix!$G$4:$G$103,"S6") -> 13 | D9: =SUMIF(Traceability_Matrix!$G$4:$G$103,"S6",Traceability_Matrix!$E$4:$E$103) -> 60 | E9: =COUNTIFS(Traceability_Matrix!$G$4:$G$103,"S6",Traceability_Matrix!$J$4:$J$103,"Done") -> 13 | F9: =SUMIFS(Traceability_Matrix!$E$4:$E$103,Traceability_Matrix!$G$4:$G$103,"S6",Traceability_Matrix!$J$4:$J$103,"Done") -> 60 | G9: =IFERROR(SUMIFS(Traceability_Matrix!$E$4:$E$103,Traceability_Matrix!$G$4:$G$103,"S6",Traceability_Matrix!$J$4:$J$103,"Done")/SUMIF(Traceability_Matrix!$G$4:$G$103,"S6",Traceability_Matrix!$E$4:$E$103),0) -> 1 | H9: GREEN — 13/13 done-in-code; smoke charges + upgrades a test portal; live charging needs R-Q10 credentials | I9: Can charge a test customer; upgrade/downgrade paths work
A10: S7 | B10: Private beta (design partners) | C10: =COUNTIF(Traceability_Matrix!$G$4:$G$103,"S7") -> 5 | D10: =SUMIF(Traceability_Matrix!$G$4:$G$103,"S7",Traceability_Matrix!$E$4:$E$103) -> 15 | E10: =COUNTIFS(Traceability_Matrix!$G$4:$G$103,"S7",Traceability_Matrix!$J$4:$J$103,"Done") -> 5 | F10: =SUMIFS(Traceability_Matrix!$E$4:$E$103,Traceability_Matrix!$G$4:$G$103,"S7",Traceability_Matrix!$J$4:$J$103,"Done") -> 15 | G10: =IFERROR(SUMIFS(Traceability_Matrix!$E$4:$E$103,Traceability_Matrix!$G$4:$G$103,"S7",Traceability_Matrix!$J$4:$J$103,"Done")/SUMIF(Traceability_Matrix!$G$4:$G$103,"S7",Traceability_Matrix!$E$4:$E$103),0) -> 1 | H10: GREEN — 5/5 done-in-code; full paying-customer billing lifecycle + scope disclosure exercised; partner recruitment external (R-Q5) | I10: 3+ partners active weekly; NPS pulse >30
A11: S8 | B11: Beta iteration + Deal/line-item sync | C11: =COUNTIF(Traceability_Matrix!$G$4:$G$103,"S8") -> 22 | D11: =SUMIF(Traceability_Matrix!$G$4:$G$103,"S8",Traceability_Matrix!$E$4:$E$103) -> 87 | E11: =COUNTIFS(Traceability_Matrix!$G$4:$G$103,"S8",Traceability_Matrix!$J$4:$J$103,"Done") -> 21 | F11: =SUMIFS(Traceability_Matrix!$E$4:$E$103,Traceability_Matrix!$G$4:$G$103,"S8",Traceability_Matrix!$J$4:$J$103,"Done") -> 82 | G11: =IFERROR(SUMIFS(Traceability_Matrix!$E$4:$E$103,Traceability_Matrix!$G$4:$G$103,"S8",Traceability_Matrix!$J$4:$J$103,"Done")/SUMIF(Traceability_Matrix!$G$4:$G$103,"S8",Traceability_Matrix!$E$4:$E$103),0) -> 0.94252874 | H11: GREEN — 22/22 done-in-code; sync loop smoke-verified with idempotency; ST-066 encryption posture partial pending vault/at-rest provisioning (R-Q11) | I11: Retention of beta cohort week-over-week >60%
A12: S9 | B12: Marketplace review prep | C12: =COUNTIF(Traceability_Matrix!$G$4:$G$103,"S9") -> 7 | D12: =SUMIF(Traceability_Matrix!$G$4:$G$103,"S9",Traceability_Matrix!$E$4:$E$103) -> 30 | E12: =COUNTIFS(Traceability_Matrix!$G$4:$G$103,"S9",Traceability_Matrix!$J$4:$J$103,"Done") -> 5 | F12: =SUMIFS(Traceability_Matrix!$E$4:$E$103,Traceability_Matrix!$G$4:$G$103,"S9",Traceability_Matrix!$J$4:$J$103,"Done") -> 17 | G12: =IFERROR(SUMIFS(Traceability_Matrix!$E$4:$E$103,Traceability_Matrix!$G$4:$G$103,"S9",Traceability_Matrix!$J$4:$J$103,"Done")/SUMIF(Traceability_Matrix!$G$4:$G$103,"S9",Traceability_Matrix!$E$4:$E$103),0) -> 0.56666667 | H12: AMBER — 5/7 Done; ST-068 needs a commissioned external pen test (R-Q12) and ST-094 needs a live install to capture assets (R-Q5). All code-side work complete and tested. | I12: Review submission accepted into queue
A13: S10 | B13: Review remediation + docs | C13: =COUNTIF(Traceability_Matrix!$G$4:$G$103,"S10") -> 7 | D13: =SUMIF(Traceability_Matrix!$G$4:$G$103,"S10",Traceability_Matrix!$E$4:$E$103) -> 24 | E13: =COUNTIFS(Traceability_Matrix!$G$4:$G$103,"S10",Traceability_Matrix!$J$4:$J$103,"Done") -> 7 | F13: =SUMIFS(Traceability_Matrix!$E$4:$E$103,Traceability_Matrix!$G$4:$G$103,"S10",Traceability_Matrix!$J$4:$J$103,"Done") -> 24 | G13: =IFERROR(SUMIFS(Traceability_Matrix!$E$4:$E$103,Traceability_Matrix!$G$4:$G$103,"S10",Traceability_Matrix!$J$4:$J$103,"Done")/SUMIF(Traceability_Matrix!$G$4:$G$103,"S10",Traceability_Matrix!$E$4:$E$103),0) -> 1 | H13: GREEN — 7/7 done-in-code; submission dry-run reports 12 pass / 0 fail / 2 manual against live state | I13: Marketplace approval obtained (or final remediation cycle)
A14: S11 | B14: Launch | C14: =COUNTIF(Traceability_Matrix!$G$4:$G$103,"S11") -> 3 | D14: =SUMIF(Traceability_Matrix!$G$4:$G$103,"S11",Traceability_Matrix!$E$4:$E$103) -> 8 | E14: =COUNTIFS(Traceability_Matrix!$G$4:$G$103,"S11",Traceability_Matrix!$J$4:$J$103,"Done") -> 3 | F14: =SUMIFS(Traceability_Matrix!$E$4:$E$103,Traceability_Matrix!$G$4:$G$103,"S11",Traceability_Matrix!$J$4:$J$103,"Done") -> 8 | G14: =IFERROR(SUMIFS(Traceability_Matrix!$E$4:$E$103,Traceability_Matrix!$G$4:$G$103,"S11",Traceability_Matrix!$J$4:$J$103,"Done")/SUMIF(Traceability_Matrix!$G$4:$G$103,"S11",Traceability_Matrix!$E$4:$E$103),0) -> 1 | H14: GREEN (code) — 3/3 done-in-code. Launch itself is BLOCKED: preflight returns no_go on PRE-07 because billing runs against stubs (R-Q10). Supply live credentials and the preflight goes green. | I14: First 10 installs; first 3 reviews; activation >40%
A15: S12 | B15: Iterate & scale decision | C15: =COUNTIF(Traceability_Matrix!$G$4:$G$103,"S12") -> 1 | D15: =SUMIF(Traceability_Matrix!$G$4:$G$103,"S12",Traceability_Matrix!$E$4:$E$103) -> 2 | E15: =COUNTIFS(Traceability_Matrix!$G$4:$G$103,"S12",Traceability_Matrix!$J$4:$J$103,"Done") -> 1 | F15: =SUMIFS(Traceability_Matrix!$E$4:$E$103,Traceability_Matrix!$G$4:$G$103,"S12",Traceability_Matrix!$J$4:$J$103,"Done") -> 2 | G15: =IFERROR(SUMIFS(Traceability_Matrix!$E$4:$E$103,Traceability_Matrix!$G$4:$G$103,"S12",Traceability_Matrix!$J$4:$J$103,"Done")/SUMIF(Traceability_Matrix!$G$4:$G$103,"S12",Traceability_Matrix!$E$4:$E$103),0) -> 1 | H15: GREEN — 1/1 done-in-code. Engine and guards shipped; iteration against real search-term data needs the listing live (R-Q5/R-Q10). | I15: Growth model doc with CAC/LTV first estimates
B16: TOTAL | C16: =SUM(C4:C15) -> 100 | D16: =SUM(D4:D15) -> 399 | E16: =SUM(E4:E15) -> 97 | F16: =SUM(F4:F15) -> 381

Sheet RAID_Carryover
A1: RAID — seeded from v006/v009 Risk_Register + build findings
A2: ID | B2: Type | C2: Raised | D2: Item | E2: Status | F2: Notes / Mitigation
A3: R-Q1 | B3: Risk | C3: v006 | D3: HubSpot ships native CPQ upgrades to close the gap (High/Medium) | E3: Open | F3: Depth on approvals + e-sign; certified-app trust moat (Launch_Checklist #5)
A4: R-Q2 | B4: Risk | C4: v006 | D4: Portal API rate limits throttle bulk quote ops (Medium/Medium) | E4: Open | F4: PlatformClient backoff shipped S2 (ST-004); queue + batch architecture from S4+; load test at ST-088
A5: R-Q3 | B5: Risk | C5: v006 | D5: SMB price sensitivity caps ARPU (Medium/High) | E5: Open | F5: Per-quote-sender pricing; annual plan push; pricing test at S12
A6: R-Q4 | B6: Constraint | C6: 22:19 | D6: Sandbox has no Postgres — persistence is in-memory behind store interfaces | E6: Open | F6: DQ4/L-018: adapter deferred; L-024 (11 Sep): live apt install attempted — mirror 404s + timeout, PG_ABSENT verified. Needs working mirror or container DB; carried to S5. Interfaces unchanged. UPDATE 13 Sep 16:36: schema delivered in review pass 2 and adapters for audit/analytics/sync delivered now, proved against a real Postgres engine in tests. Outstanding: a live instance, the remaining six stores, and R-Q13.
A7: R-Q5 | B7: Dependency | C7: 22:03 | D7: LIVE dev-portal install verification (S1 exit criterion) needs Senthil | E7: Open | F7: HubSpot dev portal app + client ID/secret; code-verified via integration tests meanwhile (E004)
A8: R-Q6 | B8: Dependency | C8: 22:52 | D8: LIVE CRM card fetch from a real HubSpot portal (ST-005 surface) needs Senthil | E8: Open | F8: Same dev-portal setup as R-Q5; signed-request handling already proven in automation
A9: R-Q7 | B9: Constraint | C9: 22:52 | D9: Email transport is a no-op default until a provider is wired | E9: Open | F9: DQ5: sent/failed/retry paths fully tested against mutable fake; provider lands with GTM plumbing S5 note: signer outreach (envelope links + reminders) rides the same provider — API returns signerLinks meanwhile (DQ5 update).
A10: R-Q8 | B10: Risk | C10: 22:19 | D10: /api identity header-based until HubSpot-signed identity extends beyond the card surface | E10: Open | F10: DQ2: signed CRM card shipped S3; UI-extension auth rides S4+; risk is spoofed headers in any pre-launch shared deployment — do not expose /api publicly before then
A11: A-Q1 | B11: Assumption | C11: 22:03 | D11: D13 (interviews parked, 100% coverage) applies portfolio-wide incl. QuoteFlow | E11: Open | F11: Per Senthil 20:45 instruction; S0 activities (PRD sign-off, prototype tests) remain formally unclosed
A12: A-Q2 | B12: Assumption | C12: 08:17 | D12: CI smoke-on-deploy job treats pushes to main as the deploy trigger (ST-086) | E12: Open | F12: Wire to the real deploy pipeline hook when hosting lands (S8 zero-downtime work, ST-092)
A13: R-Q10 | B13: Risk | C13: Live billing needs provider credentials: HubSpot marketplace listing approval (app-monetization access) for the marketplace channel and Stripe API keys for the direct channel. Until then charging is verified against provider stubs + asserted API URLs only. | D13: Open | E13: Senthil | F13: Opened S6 close (12:47). Code paths fully tested; swap stubs for live keys and re-run smoke. S7 note: dunning, recovery and invoice issue paths are all provider-stubbed too — the same credential swap covers them.
... A17: R-Q14 | B17: Issue | C17: Approval chains and requests are still in-memory. The tables exist (migration 002) but no adapter writes them, so approval requests do not survive a restart even on the Postgres backend. | D17: Closed | E17: Next code phase | F17: Closed 13 Sep 17:23: PgApprovalStore written and wired; an approval decision is proved to survive a restart through the real HTTP flow.

Sheet Gate_Checklist
A1: COMPLETION GATE (D7) — QuoteFlow is DONE only when every row passes
A2: R2: code complete counts for nothing. Gate decision = Senthil.
A3: ID | B3: Gate item | C3: Source | D3: Status
A4: G-01 | B4: App LISTED on HubSpot App Marketplace (approved + published) | C4: D7 / R2 | D4: Open
A5: G-02 | B5: 10 PAYING installs from strangers | C5: D7 / R2 | D5: Open
A6: G-03 | B6: S12 kill criteria evaluated with evidence pack | C6: D7 / R3 | D6: Open
A7: G-04 | B7: Kill/continue decision recorded by Senthil | C7: R5 / D10 | D7: Open
A8: G-05 | B8: On CONTINUE: next-rank build authorised; QuoteFlow enters run mode | C8: N4 / R1 | D8: Open
