Workbook

Sheet Cover
A1: ShiftDesk for Microsoft Teams — Version Detail and Manual Test Specification
A3: Document title | B3: Version Detail and Manual Test Specification
A4: Product | B4: ShiftDesk for Microsoft Teams (shift handovers, approvals, digital checklists, kudos, manager dashboard)
A5: Product code | B5: 002-MoPr09-shiftdesk_teams
A6: Document id | B6: claude_V001_MoPr09-shiftdesk_teams_versiondetail_manualtest_20260920_1715
A7: Document version | B7: V001
A8: Document status | B8: Released for review
A9: Issued | B9: 20 September 2026, 17:15
A10: Prepared by | B10: Claude (Opus 5), for Senthil / KP
A11: Reviewed by | B11: (open — Senthil)
A12: Approved by | B12: (open — Senthil; see Signoff sheet)
A13: Covers releases | B13: v001 (10 Sep 2026) to v040 (20 Sep 2026), plus the pending release v041
A14: Codebase at issue | B14: v0.14.0 — 68 unit suites / 555 tests at 100% statements, branches, functions and lines; 9/9 real-Postgres integration tests; backup/restore drill PASS
... A18: Retention | B18: Keep for the life of the product plus 7 years, as the build evidence behind any store submission or audit question.
A20: READ THIS FIRST
A21: What this document is for | B21: Two questions, answered release by release: what was done and why, and how a human can verify it by hand. The automated suite proves the code executes; these cases are what a person walks through when the automated suite is exactly the thing they do not trust.
A22: The honesty rule it follows | B22: Status vocabulary per tracker decision D-SD2, extended by D-SD8: "Done" means verified, "Code-complete pending live" means the code is finished and the proof needs a real tenant, and "To do — Senthil" means no amount of code closes it. Nothing here is marked Done because it compiles.
A23: Where the numbers come from | B23: Every count on the Test_Summary sheet is a live formula over Test_Cases. Nothing is typed in twice.

Sheet Context
A1: CONTEXT — the product, the programme and the two documents this one sits beside
A2: HOW TO USE THIS SHEET — Read top to bottom once. It explains what ShiftDesk is, who it is for, how the release numbering works, and which document answers which question. If you only need to run tests, go straight to How_To_Use and then Test_Cases.
A4: Topic | B4: Detail
A5: What the product does | B5: ShiftDesk runs inside Microsoft Teams and gives a frontline team five things: shift handover threads that produce a retained, queryable record; approval workflows with thresholds and blocked categories; digital checklists; kudos and recognition; and a manager dashboard over the lot. It installs as a Teams app with tabs and a bot, uses Entra ID single sign-on, and stores tenant data in PostgreSQL.
A6: Who it is for | B6: Ops directors, IT admins and frontline supervisors in regulated frontline sectors — the shifts where an inspector can ask "show me the handover record for the night of the 14th" and somebody has to produce it.
A7: The commercial wedge | B7: Two of the three original pillars overlap Microsoft apps the customer already has free (Approvals, Planner task publishing). The independent review was blunt about this. The product is therefore positioned on the one thing those tools do not produce: auditable handover evidence. That repositioning is release v040, story SD245.
A8: How releases are numbered | B8: Two separate ladders, deliberately. This document uses the TRACKER release ladder v001-v041: one entry per working session, each with its own evidence. The codebase has its own semantic version (v0.1.0 to v0.14.0) and the product workbook has its own (v005 to v046). The Version_Detail sheet maps them.
A9: What a release contains | B9: Almost never only features. The dominant pattern across 41 releases is: build, then audit what was built, then find that something built earlier was never wired in, then fix that and pin it with a test. Twenty-four of the forty released versions are audits, reviews or verification sweeps rather than feature work. That is not inefficiency; it is what the evidence says the code needed.
A10: Current state in one line | B10: The product is code-complete and three-tier test-verified in a sandbox. It has never run in a real Microsoft tenant. Nothing has been sold.
A11: Why that distinction matters | B11: The gate for this product (D7/R2) is not "code complete". It is: listed on the Teams store, and ten paying installs from strangers. Both are open. Every claim in this document is scoped to the evidence behind it so that distinction never blurs.
A12: The three companion documents | B12: Sprint tracker v040 — the execution record: 147 stories, per-sprint boards, RAID, gates. Product workbook v046 — the commercial record: backlog, financial model, risks, launch checklist. Source zip v046 — the code, with REVIEW_PACK.md as the findings register. This document — release-by-release reasoning plus the manual test specification.
A13: Independent review V001 | B13: On 16 September an external reviewer verified the build (it passed) and then rated identity, durability, scale and compliance as Absent in the shipped entry point: three CRITICAL defects meant the production configuration had no working authentication and no durable store. Release v040 actioned all 20 findings. That review is the reason this document exists in this shape.
A14: Defect numbering | B14: F-nnn are defects found by our own review passes and audits (F-001 to F-074). P-nnn are the independent reviewer's findings (P-001 to P-020). VER-SDnn came from vendor-documentation sweeps, GAP-SDnn from artefact-gap audits, OBS-SDnn are accepted observations. D-SDn are decisions.
A15: Who owns what | B15: Claude: code, tests, documents, evidence preparation. Senthil: every decision, every purchase, every live-tenant action, and the go/no-go. Eleven of the forty-seven review stories are Senthil-owned and are listed as such rather than absorbed.

Sheet How_To_Use
A1: HOW TO USE THIS DOCUMENT — what each sheet is for, who uses it, and in what order
A2: HOW TO USE THIS SHEET — This is the index. Work down the "Read in this order" column the first time. Every other sheet repeats its own instructions in row 2, so you never have to come back here.
A4: # | B4: Sheet | C4: What it answers | D4: Who uses it | E4: How to use it | F4: Read in this order
A5: 1 | B5: Cover | C5: What this document is, which versions it covers, who prepared and approved it | D5: Anyone | E5: Check the document version and issue date match what you were sent. Note the companion documents — this one does not repeat their content. | F5: 1
A6: 2 | B6: Context | C6: What the product is, how releases are numbered, what state the product is actually in | D6: New reader, reviewer, auditor | E6: Read once, start to finish. It is the shortest honest briefing on the product in the whole document set. | F6: 2
A7: 3 | B7: How_To_Use | C7: Which sheet answers which question | D7: Anyone | E7: You are here. Use the last column as a reading order. | F7: 3
A8: 4 | B8: Version_Control | C8: The change history of THIS document | D8: Reviewer, auditor | E8: Every reissue adds a row. Never edit a released row — supersede it. | F8: 4
A9: 5 | B9: Version_Detail | C9: For each release: what was done, why it was done, what came out of it, and its status | D9: Senthil, reviewer, auditor | E9: One row per release, oldest first. The "Why it was done" column is the point of the sheet: it is the reason the work happened, not a restatement of the work. | F9: 5
A10: 6 | B10: Pending_Versions | C10: What is NOT done, why, who owns it and what would unblock it | D10: Senthil | E10: Read every row. Each names the single thing that has to exist before the work can start. Nothing here can be closed by writing code. | F10: 6
A11: 7 | B11: Version_Steps | C11: The step-by-step of each release, in the order it happened | D11: Reviewer, auditor | E11: Use it to reconstruct a release, or to see the working method: audits and reviews run to a repeated shape and this sheet shows it. | F11: 7
A12: 8 | B12: Test_Cases | C12: How a human verifies each release by hand, positively and negatively | D12: Tester | E12: Filter by Version to test one release, or by Executable to find what you can run today. Fill Actual result, Status, Tester and Date as you go. Do not edit the Expected result column. | F12: 8
A13: 9 | B13: Test_Execution_Log | C13: Which test run happened when, against what build, with what outcome | D13: Test lead | E13: One row per execution cycle. Copy the case ids that failed into the Failed cases column and raise them in Defect_Log. | F13: 9
A14: 10 | B14: RTM | C14: Which test covers which release, story and finding — and which findings have no test | D14: Auditor, reviewer | E14: The reverse map of Test_Cases. Use it to answer "what proves finding F-029 is fixed?" in one lookup. | F14: 10
A15: 11 | B15: Defect_Log | C15: Every defect found, where it came from and how it was closed | D15: Reviewer, auditor | E15: Read the Origin column: the pattern in this product is that defects came from audits of already-"done" work, not from feature development. | F15: 11
A16: 12 | B16: Test_Summary | C16: Counts and coverage, computed live from Test_Cases | D16: Senthil, test lead | E16: Do not type in this sheet. Every number is a formula. If a count looks wrong, the data on Test_Cases is wrong. | F16: 12
... A19: 15 | B19: Signoff | C19: Who accepted this document and on what basis | D19: Senthil | E19: Sign only the rows you have actually checked. An unsigned row is more useful than a signed one that was not read. | F19: Last

Sheet Version_Control
A1: VERSION CONTROL — change history of this document
A2: HOW TO USE THIS SHEET — Add a row for every reissue: never overwrite a released row. Version ids are V001, V002 ... and the file name carries the same id plus the issue timestamp, so a file on disk can always be matched to a row here.
A4: Document version | B4: Date / time | C4: Author | D4: Change description | E4: Sections affected | F4: Status
A5: V001 | B5: 2026-09-20 17:15 | C5: Claude for Senthil/KP | D5: First issue. Created at Senthil's request on 20 Sep 17:15 alongside the pictorial product explainer. Covers releases v001-v040 with the reason for each, the pending release v041 with the reason it is pending, a step-by-step reconstruction of every release, and 199 manual test cases (positive and negative) mapped to releases, stories and findings. Front matter, glossary, requirements traceability matrix, defect log, execution log, live summary, assumptions and sign-off included to market convention. | E5: All — first issue | F5: Released
A6: V002 | D6: PLANNED: reissue when release v041 closes — the cold review of the S13-S20 code, or the first real dev-tenant sweep, whichever lands first. v041 moves from Pending_Versions to Version_Detail, its four blocked cases become executable, and their results are recorded. | F6: Planned

Sheet Version_Detail
A1: VERSION DETAIL — every released version: what was done, why it was done, what came of it
A2: HOW TO USE THIS SHEET — One row per release, oldest first. Columns E and F are the substance: E is what happened, F is why it happened at all. Column H gives the verification status using the D-SD2 vocabulary explained on the Cover sheet. Use column J to jump to the step-by-step on Version_Steps and the cases on Test_Cases.
A4: Release | B4: Date / time | C4: Session | D4: Category | E4: What was done | F4: Why it was done | G4: Outcome / evidence | H4: Verification status | I4: Codebase | J4: Test cases
A5: v001 | B5: 2026-09-10 23:03 | C5: S1-S2 | D5: BUILD | E5: Foundation through S8 consolidated into one tracker | F5: Senthil instruction 10 Sep 22:26: continue per the v005 sprint plan with a sprint tracker, traceability and 100% automation coverage (D13). The product had eight sprints of code and no execution record. | G5: 75 stories Done, 8 code-complete pending live, 15 Jest suites / 67 tests at 100% | H5: Released — verified in sandbox | I5: v0.6.0 | J5: 5 cases
A6: v002 | B6: 2026-09-10 23:10 | C6: S3 | D6: BUILD | E6: Live-sweep readiness pack: manifest v1.17, icons, typed config loader, 12-step sweep, dev-tenant guide | F6: Nothing could be installed in a real tenant: no manifest package existed, so no story could ever leave "pending live". Sideloading needs no Partner Center, so this unblocked same-day verification. | G6: Gate LC-2 advanced to manifest-ready | H6: Released — verified in sandbox | I6: v0.6.1 | J6: 3 cases
A7: v003 | B7: 2026-09-11 08:20 | C7: S4 | D7: BUILD | E7: Ops parity pack: k6 5x load harness, blue/green deploy workflow, scripted backup/restore drill | F7: Three launch-checklist items (load, deploy, backup) were prose. A checklist item with no executable behind it cannot be evidence. | G7: ST-088/090/092 moved Backlog to Drafted; Gate LC-8 harness-scripted | H7: Released — verified in sandbox | I7: v0.6.2 | J7: 3 cases
A8: v004 | B8: 2026-09-11 12:51 | C8: S5 | D8: REVIEW | E8: Adversarial cold-review pass 1 over the S1-S8 code | F8: 100% coverage had never been tested against an adversary. Coverage proves execution, not correctness, and the product had never been read by anyone looking for defects. | G8: 6 defects fixed with regressions (F-001..F-006); F-007/F-008 raised for disposition; F-009 evidence-discipline finding closed | H8: Released — verified in sandbox | I8: v0.7.0 | J8: 5 cases
A9: v005 | B9: 2026-09-11 20:30 | C9: S6 | D9: REVIEW | E9: Cold-review pass 2 plus the completion wave taking the last backlog stories to sandbox ceiling | F9: Pass 1 found six defects in code that was already "done", so a second pass was warranted before declaring the code phase complete. | G9: F-010..F-013 fixed; backlog zero; 22 suites / 109 tests at 100% | H9: Released — verified in sandbox | I9: v0.11.0 | J9: 4 cases
A10: v006 | B10: 2026-09-13 09:52 | C10: S7 | D10: VERIFY | E10: External verification sweep against live Microsoft documentation, plus artifact-gap audit round 1 | F10: Every Teams-platform behaviour had been written from assumption. A store-blocking mistake is cheapest to find against the vendor documentation, not in a review queue. | G10: VER-SD01/02 store-blocking and VER-SD08 live-blocking raised; LC-5 reopened on an overstated permission model | H10: Released — verified in sandbox | I10: v0.11.1 | J10: 3 cases
A11: v007 | B11: 2026-09-13 10:01 | C11: S8 | D11: GAP | E11: Artifact-gap audit round 2: the web tab layer and the bot command router | F11: The manifest declared three static tabs and advertised bot commands with nothing behind either. A manifest promise with no implementation is a store rejection and a broken install. | G11: GAP-SD1 and GAP-SD2 closed; 26 suites / 145 tests | H11: Released — verified in sandbox | I11: v0.11.2 | J11: 4 cases
A12: v008 | B12: 2026-09-13 10:24 | C12: S9 | D12: REVIEW | E12: Cold-review pass 3 over the sessions 5-8 code that had never been reviewed | F12: New code is the least-reviewed code. Twelve modules had shipped at 100% coverage since the last review pass. | G12: F-014..F-019 fixed; headline F-016: the tab API validated the SSO token then never sent it | H12: Released — verified in sandbox | I12: v0.11.3 | J12: 4 cases
A13: v009 | B13: 2026-09-13 10:37 | C13: S10 | D13: GAP | E13: Artifact-gap audit round 3: the HTTP server and bootstrap | F13: Three of five tab paths and the bot messaging endpoint had no server behind them. The client called a server that did not exist. | G13: GAP-SD5 closed with src/server.ts + src/bootstrap.ts and a client-vs-server parity test | H13: Released — verified in sandbox | I13: v0.11.4 | J13: 4 cases
A14: v010 | B14: 2026-09-13 10:42 | C14: S11 | D14: VERIFY | E14: Verification sweep 2 over the bot transport seam | F14: The bot endpoint built one session earlier was written from assumption: authentication, payload shape and reply mechanism were all guesses, and its own tests passed. | G14: VER-SD09/SD10 live-blockers closed (Connector JWT, ack-then-send); VER-SD11/SD12 closed | H14: Released — verified in sandbox | I14: v0.11.5 | J14: 4 cases
A15: v011 | B15: 2026-09-13 10:57 | C15: S12 | D15: VERIFY | E15: Verification sweep 3 over the tab SSO seam | F15: Same class as the bot seam one session earlier: the tab was sending a hardcoded placeholder token while the manifest declared SSO. | G15: VER-SD13 live-blocker closed with real acquisition and validation; VER-SD14 documented | H15: Released — verified in sandbox | I15: v0.11.6 | J15: 4 cases
... A44: v040 | B44: 2026-09-20 16:40 | C44: S41 | D44: REVIEW | E44: Independent review V001 actioned in full: 47-story S13-S20 remediation programme | F44: An external reviewer rated identity, durability, scale and compliance as Absent while the tracker showed a code-complete product at 100% coverage. Three CRITICAL defects meant the shipped entry point had no working authentication and no durable store. | G44: 36 of 47 stories built; 3 CRITICALs closed; real-Postgres tier and backup drill run for real; 68 suites / 555 tests at 100%; F-071..F-074 recorded | H44: Released — verified in sandbox + real Postgres | I44: v0.14.0 | J44: 35 cases
A46: READING THE CATEGORY COLUMN: BUILD = new capability. REVIEW = adversarial cold review of code already called done. AUDIT = a single named property examined across the whole product (tenancy, deletion, authorization, billing, multi-instance, dependency failure, wiring, deliverability). VERIFY = a sweep against vendor documentation or a live artefact. GAP = a promise made in the manifest or a document with nothing implementing it. Twenty-four of the forty released versions are REVIEW, AUDIT, VERIFY or GAP. The lesson the tracker records (R-S10, R-S14, R-S21) is that in this codebase the defect was almost never a wrong algorithm — it was a correct module that nothing called.

Sheet Pending_Versions
A1: PENDING — what is not done, why it is not done, and the one thing that would unblock it
A2: HOW TO USE THIS SHEET — Every row names a blocker in column D and the single unblocking action in column E. Read column D before asking why something is not finished: in every case it is access, money, a person or a customer, not effort. Nothing on this sheet can be closed by writing code.
A4: Item | B4: Type | C4: What it is | D4: Why it is pending | E4: What unblocks it | F4: Owner | G4: Cost / lead time | H4: Blocks
A5: v041 | B5: Release | C5: The next release of the tracker and this document | D5: It opens on whichever comes first: the cold review of the S13-S20 code written in v040, or the first real sweep report from a dev tenant. Neither has happened. Opening it now would mean writing a release note about work that has not been done. | E5: Either Claude runs the v040 cold review (no external dependency — this can start immediately), or Senthil sideloads the app in a dev tenant and runs the sweep. | F5: Claude / Senthil | G5: Review: one session. Sweep: half a day once a tenant exists. | H5: Nothing — but R-S21 says the v040 code is the least-reviewed code in the product
A6: SD226 | B6: Story — live | C6: Mobile pass on live iOS and Android Teams clients, including the store-required mobile screenshot | D6: Requires the app sideloaded on a physical phone signed into a Microsoft 365 tenant. A sandbox cannot render a Teams mobile client, and the store submission is blocked without the screenshot (VER-SD01). | E6: Senthil sideloads the package on a phone and walks the five flows in ASSET_PLAN.md. | F6: Senthil | G6: ~2 hours once a tenant exists | H6: Store submission (G-01)
A7: SD228 | B7: Story — live | C7: Admin consent and tenant-wide rollout verified in two tenants | D7: Needs two live Microsoft 365 tenants with an administrator willing to grant consent. The consent screen cannot be observed any other way, and it must match the least-privilege document exactly. | E7: Senthil provides two tenants and performs the install-consent-rollout walkthrough. | F7: Senthil | G7: ~half a day | H7: LC-4, LC-5
A8: SD219 / SD220 | B8: Story — infra | C8: The k6 5x load sweep and its latency/conflict evidence, run on staging | D8: There is no staging environment. The harness and the pass bar are scripted and the instrumentation is real, but a performance number that has not been measured is not a number. | E8: Provision staging (App Service + Postgres) and run npm run sweep plus the k6 profile. | F8: Senthil + Claude | G8: Azure staging: hours to provision, then ~1 hour to run | H8: LC-8
A9: SD231 / SD232 | B9: Story — infra | C9: Data rights over HTTP against a real store, and KMS-backed key custody against a real vault | D9: Both halves are built and unit-tested, and production already refuses a plain-environment key. Neither has spoken to a real Azure Key Vault or run against a hosted database, because neither exists yet. | E9: Same staging environment as above, plus a Key Vault and a managed identity. | F9: Senthil + Claude | G9: Hours, alongside staging | H9: Trust page publication (D-07)
A10: SD233 | B10: Story — human | C10: Incident-response tabletop exercise | D10: The runbook is written and bound to the alert rules by test. A tabletop is a rehearsal with people in it; writing a transcript of one nobody attended would be a lie in an audit file. | E10: Senthil schedules 90 minutes with whoever would actually be on call. | F10: Senthil | G10: 90 minutes | H10: M365 certification evidence quality
A11: SD234 | B11: Story — procurement | C11: Third-party penetration test with all High and Critical findings closed and retested | D11: Needs a staging environment to test against and a vendor engagement with a budget. The scope pack and surface inventory are prepared so the engagement starts without a discovery phase. | E11: Senthil engages a vendor once staging exists. | F11: Senthil | G11: Typically £4k-£15k, 2-4 weeks including retest | H11: LC-3, store review confidence
A12: SD235 | B12: Story — procurement | C12: Microsoft 365 Publisher Attestation submitted and accepted | D12: Requires a Partner Center account with publisher verification. Every answer the attestation asks for is drafted in ops/m365-certification-pack.md; none of it can be submitted without the account. | E12: Senthil completes Partner Center enrollment (LC-1) and submits. | F12: Senthil | G12: Enrollment fee plus ~1 week of review | H12: LC-3, LC-1
A13: SD237 | B13: Story — procurement | C13: SOC 2 Type I readiness with an audit firm engaged | D13: The control mapping and the compliance automation are in code. Engaging a firm is a purchase decision with a real budget, and Type II additionally needs an observation window that cannot be shortened. | E13: Senthil engages an audit firm. | F13: Senthil | G13: $15k-$50k audit fee; ~6 months observation for Type II | H13: Enterprise procurement above ~500 seats
A14: SD238 | B14: Story — human | C14: Manual WCAG AA and screen-reader audit on the live tabs | D14: jest-axe passes on all nine screens and cannot hear a screen reader. Keyboard-only and NVDA/VoiceOver passes have to be performed by a person in a live client. Closes R-S6, open since the first session. | E14: Senthil (or a tester) works through ops/accessibility-audit-script.md in a live tenant. | F14: Senthil | G14: ~half a day | H14: LC-7, store accessibility expectations
A15: SD240 | B15: Story — procurement | C15: Transactable AppSource offer live, with the private-offer path tested on a pilot | D15: Partner Center work. The fulfillment integration is built and the plan identifiers are bound to the entitlement table by test, so the offer and the code cannot disagree once it exists — but there is no offer. | E15: Senthil configures the transactable offer in Partner Center. | F15: Senthil | G15: Days of Partner Center review; 3% marketplace fee thereafter | H15: LC-6, LC-11, G-02
... A19: Trust page publication | B19: Content | C19: content/security-trust-page.md going live | D19: Held deliberately per review finding D-07. Its claims were true only of a configuration nobody was running. It now describes what the code does, and it publishes when a deployment actually runs durably with KMS custody — not before. | E19: Publish once staging runs with a real store and vault (SD231/SD232). | F19: Senthil | G19: Minutes, once the conditions hold | H19: Nothing — it is a gate on us, not on anyone else
A21: THE ONE-LINE VERSION: eleven of the forty-seven review stories, and the whole product gate, are waiting on four things that money and access buy — a Microsoft tenant, a staging environment, a Partner Center account and a budget — plus two things only customers can give: fifteen conversations and five signatures.

Sheet Version_Steps
A1: VERSION STEPS — how each release was actually executed, in order
A2: HOW TO USE THIS SHEET — One block per release, in order, oldest first. Steps are numbered within the release. Use this to reconstruct what happened, to repeat the method on a new release, or to audit whether a release did what its note claims. The step shapes repeat by category because the working method is deliberate, not improvised.
A4: Release | B4: Step | C4: Action | D4: Why this step | E4: Output of the step
A5: v001 | B5: 1 | C5: Confirm the instruction and the scope for the session, and record it as an event in the tracker log. | D5: A release with no recorded instruction cannot be audited later, and scope creep inside a session is invisible without it. | E5: A tracker log event (E-nnn) naming the instruction and the scope.
B6: 2 | C6: Read the current state: the backlog rows in scope, the code they claim, and the tests that pin them. | D6: The product's recurring defect is a module that exists and is never called, so the starting question is always what is really wired. | E6: A written list of what exists versus what is claimed.
B7: 3 | C7: Build the capability, smallest honest slice first, with the test written against the behaviour rather than the implementation. | D7: A test coupled to implementation detail passes through a refactor that breaks the product. | E7: New or changed modules under src/ or web/.
B8: 4 | C8: Wire it at the boundary — a real request must drive it, not only a unit test. | D8: Findings F-036, F-039, F-062 and F-063 were all correct modules nothing constructed. Wiring is part of building, not a later step. | E8: Construction in the entry point plus a boundary test that proves a request reaches it.
B9: 5 | C9: Run the full gate: typecheck, unit suite at 100%, and from v040 the integration and seam tiers too. | D9: The gate is the only thing standing between a green feeling and a green build. | E9: A clean gate run, or a defect to fix before the release closes.
B10: 6 | C10: Update the tracker, traceability and companion workbook, then release and deliver the artefacts. | D10: Evidence that is not written down where the reader will look for it is not evidence (finding F-009). | E10: Tracker version row, traceability rows, source zip, workbook.
B11: 7 | C11: RELEASE-SPECIFIC: Foundation through S8 consolidated into one tracker. | D11: Senthil instruction 10 Sep 22:26: continue per the v005 sprint plan with a sprint tracker, traceability and 100% automation coverage (D13). The product had eight sprints of code and no execution record. | E11: 75 stories Done, 8 code-complete pending live, 15 Jest suites / 67 tests at 100%
A12: v002 | B12: 1 | C12: Confirm the instruction and the scope for the session, and record it as an event in the tracker log. | D12: A release with no recorded instruction cannot be audited later, and scope creep inside a session is invisible without it. | E12: A tracker log event (E-nnn) naming the instruction and the scope.
B13: 2 | C13: Read the current state: the backlog rows in scope, the code they claim, and the tests that pin them. | D13: The product's recurring defect is a module that exists and is never called, so the starting question is always what is really wired. | E13: A written list of what exists versus what is claimed.
B14: 3 | C14: Build the capability, smallest honest slice first, with the test written against the behaviour rather than the implementation. | D14: A test coupled to implementation detail passes through a refactor that breaks the product. | E14: New or changed modules under src/ or web/.
B15: 4 | C15: Wire it at the boundary — a real request must drive it, not only a unit test. | D15: Findings F-036, F-039, F-062 and F-063 were all correct modules nothing constructed. Wiring is part of building, not a later step. | E15: Construction in the entry point plus a boundary test that proves a request reaches it.
B16: 5 | C16: Run the full gate: typecheck, unit suite at 100%, and from v040 the integration and seam tiers too. | D16: The gate is the only thing standing between a green feeling and a green build. | E16: A clean gate run, or a defect to fix before the release closes.
B17: 6 | C17: Update the tracker, traceability and companion workbook, then release and deliver the artefacts. | D17: Evidence that is not written down where the reader will look for it is not evidence (finding F-009). | E17: Tracker version row, traceability rows, source zip, workbook.
B18: 7 | C18: RELEASE-SPECIFIC: Live-sweep readiness pack: manifest v1.17, icons, typed config loader, 12-step sweep, dev-tenant guide. | D18: Nothing could be installed in a real tenant: no manifest package existed, so no story could ever leave "pending live". Sideloading needs no Partner Center, so this unblocked same-day verification. | E18: Gate LC-2 advanced to manifest-ready
A19: v003 | B19: 1 | C19: Confirm the instruction and the scope for the session, and record it as an event in the tracker log. | D19: A release with no recorded instruction cannot be audited later, and scope creep inside a session is invisible without it. | E19: A tracker log event (E-nnn) naming the instruction and the scope.
B20: 2 | C20: Read the current state: the backlog rows in scope, the code they claim, and the tests that pin them. | D20: The product's recurring defect is a module that exists and is never called, so the starting question is always what is really wired. | E20: A written list of what exists versus what is claimed.
B21: 3 | C21: Build the capability, smallest honest slice first, with the test written against the behaviour rather than the implementation. | D21: A test coupled to implementation detail passes through a refactor that breaks the product. | E21: New or changed modules under src/ or web/.
B22: 4 | C22: Wire it at the boundary — a real request must drive it, not only a unit test. | D22: Findings F-036, F-039, F-062 and F-063 were all correct modules nothing constructed. Wiring is part of building, not a later step. | E22: Construction in the entry point plus a boundary test that proves a request reaches it.
B23: 5 | C23: Run the full gate: typecheck, unit suite at 100%, and from v040 the integration and seam tiers too. | D23: The gate is the only thing standing between a green feeling and a green build. | E23: A clean gate run, or a defect to fix before the release closes.
B24: 6 | C24: Update the tracker, traceability and companion workbook, then release and deliver the artefacts. | D24: Evidence that is not written down where the reader will look for it is not evidence (finding F-009). | E24: Tracker version row, traceability rows, source zip, workbook.
B25: 7 | C25: RELEASE-SPECIFIC: Ops parity pack: k6 5x load harness, blue/green deploy workflow, scripted backup/restore drill. | D25: Three launch-checklist items (load, deploy, backup) were prose. A checklist item with no executable behind it cannot be evidence. | E25: ST-088/090/092 moved Backlog to Drafted; Gate LC-8 harness-scripted
A26: v004 | B26: 1 | C26: Freeze the scope: name the sessions whose code has never been reviewed, and read nothing else. | D26: A review with unbounded scope becomes a skim. New code is the least-reviewed code (R-S10). | E26: A named module list for the pass.
B27: 2 | C27: Read each module adversarially, asking what input would make it do the wrong thing, not whether it looks correct. | D27: Every defect found this way had a passing test over it already. | E27: A candidate defect list.
B28: 3 | C28: Reproduce each candidate as a failing test before touching the code. | D28: A defect without a failing test is an opinion, and a fix without one regresses silently. | E28: Failing tests, one per confirmed defect.
B29: 4 | C29: Fix, and keep the regression test pinned in a pass-specific suite so its origin stays visible. | D29: The suite name is the audit trail: tests/reviewPass4.test.ts says when and why the assertion exists. | E29: F-nnn entries fixed with named regressions.
B30: 5 | C30: Record anything not fixed as an explicit open finding with a disposition owner, rather than fixing it quietly or dropping it. | D30: F-007 and F-008 stayed open for weeks under their own ids. That is honest; silence would not have been. | E30: Open findings with owners.
B31: 6 | C31: Rerun the full gate and release, with the defect count in the release note. | D31: The count belongs in the note because a release that fixed six defects is not the same artefact as one that fixed none. | E31: Released version with the findings recorded.
B32: 7 | C32: RELEASE-SPECIFIC: Adversarial cold-review pass 1 over the S1-S8 code. | D32: 100% coverage had never been tested against an adversary. Coverage proves execution, not correctness, and the product had never been read by anyone looking for defects. | E32: 6 defects fixed with regressions (F-001..F-006); F-007/F-008 raised for disposition; F-009 evidence-discipline finding closed
A33: v005 | B33: 1 | C33: Freeze the scope: name the sessions whose code has never been reviewed, and read nothing else. | D33: A review with unbounded scope becomes a skim. New code is the least-reviewed code (R-S10). | E33: A named module list for the pass.
B34: 2 | C34: Read each module adversarially, asking what input would make it do the wrong thing, not whether it looks correct. | D34: Every defect found this way had a passing test over it already. | E34: A candidate defect list.
B35: 3 | C35: Reproduce each candidate as a failing test before touching the code. | D35: A defect without a failing test is an opinion, and a fix without one regresses silently. | E35: Failing tests, one per confirmed defect.
B36: 4 | C36: Fix, and keep the regression test pinned in a pass-specific suite so its origin stays visible. | D36: The suite name is the audit trail: tests/reviewPass4.test.ts says when and why the assertion exists. | E36: F-nnn entries fixed with named regressions.
B37: 5 | C37: Record anything not fixed as an explicit open finding with a disposition owner, rather than fixing it quietly or dropping it. | D37: F-007 and F-008 stayed open for weeks under their own ids. That is honest; silence would not have been. | E37: Open findings with owners.
B38: 6 | C38: Rerun the full gate and release, with the defect count in the release note. | D38: The count belongs in the note because a release that fixed six defects is not the same artefact as one that fixed none. | E38: Released version with the findings recorded.
B39: 7 | C39: RELEASE-SPECIFIC: Cold-review pass 2 plus the completion wave taking the last backlog stories to sandbox ceiling. | D39: Pass 1 found six defects in code that was already "done", so a second pass was warranted before declaring the code phase complete. | E39: F-010..F-013 fixed; backlog zero; 22 suites / 109 tests at 100%
A40: v006 | B40: 1 | C40: Choose the seam that was most recently written from assumption rather than from vendor documentation. | D40: The bot transport and the tab SSO seam were each wrong in three ways and their own tests passed (R-S12). | E40: The seam under verification.
B41: 2 | C41: Read the vendor documentation for that seam properly, and write down what it actually requires. | D41: Guessing an authentication or payload contract produces code that is confidently wrong. | E41: A requirement list quoted from the documentation.
B42: 3 | C42: Compare the shipped code against each requirement, one line at a time. | D42: This is where VER-SD09, VER-SD10 and VER-SD13 came from — all live-blocking, none visible to the suite. | E42: VER-SDnn findings with severity.
B43: 4 | C43: Correct the code and pin the requirement with an assertion on the outbound shape, not only the inbound handling. | D43: Asserting what we send is how a wrong header or a wrong reply mechanism gets caught. | E43: Transport-level assertions.
B44: 5 | C44: Record anything only a live client can settle, and route it to the live sweep rather than claiming it. | D44: R-S8 exists because the sandbox cannot prove in-client behaviour, and pretending otherwise would be the worst failure available. | E44: Sweep steps and pending-live stories.
B45: 6 | C45: Rerun the gate and release. | D45: Unchanged discipline regardless of release type. | E45: Released version.
B46: 7 | C46: RELEASE-SPECIFIC: External verification sweep against live Microsoft documentation, plus artifact-gap audit round 1. | D46: Every Teams-platform behaviour had been written from assumption. A store-blocking mistake is cheapest to find against the vendor documentation, not in a review queue. | E46: VER-SD01/02 store-blocking and VER-SD08 live-blocking raised; LC-5 reopened on an overstated permission model
A47: v007 | B47: 1 | C47: List every promise the product makes outside its code: manifest declarations, documented commands, published claims, RAID assertions. | D47: A promise with nothing behind it is a store rejection or a broken install, and it is invisible to a coverage gate. | E47: A promise inventory.
B48: 2 | C48: For each promise, find the implementation. Not the intention — the file. | D48: GAP-SD1, GAP-SD2, GAP-SD5, GAP-SD6 and GAP-SD8 were all promises with no file behind them, one of them repeated in RAID for fourteen sessions. | E48: A gap list with severity.
B49: 3 | C49: Build the missing implementation, or withdraw the promise explicitly as a decision. | D49: Withdrawing is legitimate and cheaper — D-SD5 dropped an unused permission rather than inventing a consumer for it. | E49: New modules, or a recorded D-SDn decision.
B50: 4 | C50: Bind promise to implementation with a contract test that fails on drift in either direction. | D50: The manifest-versus-code assertions exist so that no future manifest promise can ship without an implementation. | E50: Two-way contract tests.
B51: 5 | C51: Rerun the gate and release. | D51: Unchanged discipline regardless of release type. | E51: Released version.
B52: 6 | C52: RELEASE-SPECIFIC: Artifact-gap audit round 2: the web tab layer and the bot command router. | D52: The manifest declared three static tabs and advertised bot commands with nothing behind either. A manifest promise with no implementation is a store rejection and a broken install. | E52: GAP-SD1 and GAP-SD2 closed; 26 suites / 145 tests
A53: v008 | B53: 1 | C53: Freeze the scope: name the sessions whose code has never been reviewed, and read nothing else. | D53: A review with unbounded scope becomes a skim. New code is the least-reviewed code (R-S10). | E53: A named module list for the pass.
B54: 2 | C54: Read each module adversarially, asking what input would make it do the wrong thing, not whether it looks correct. | D54: Every defect found this way had a passing test over it already. | E54: A candidate defect list.
B55: 3 | C55: Reproduce each candidate as a failing test before touching the code. | D55: A defect without a failing test is an opinion, and a fix without one regresses silently. | E55: Failing tests, one per confirmed defect.
B56: 4 | C56: Fix, and keep the regression test pinned in a pass-specific suite so its origin stays visible. | D56: The suite name is the audit trail: tests/reviewPass4.test.ts says when and why the assertion exists. | E56: F-nnn entries fixed with named regressions.
B57: 5 | C57: Record anything not fixed as an explicit open finding with a disposition owner, rather than fixing it quietly or dropping it. | D57: F-007 and F-008 stayed open for weeks under their own ids. That is honest; silence would not have been. | E57: Open findings with owners.
B58: 6 | C58: Rerun the full gate and release, with the defect count in the release note. | D58: The count belongs in the note because a release that fixed six defects is not the same artefact as one that fixed none. | E58: Released version with the findings recorded.
B59: 7 | C59: RELEASE-SPECIFIC: Cold-review pass 3 over the sessions 5-8 code that had never been reviewed. | D59: New code is the least-reviewed code. Twelve modules had shipped at 100% coverage since the last review pass. | E59: F-014..F-019 fixed; headline F-016: the tab API validated the SSO token then never sent it
A60: v009 | B60: 1 | C60: List every promise the product makes outside its code: manifest declarations, documented commands, published claims, RAID assertions. | D60: A promise with nothing behind it is a store rejection or a broken install, and it is invisible to a coverage gate. | E60: A promise inventory.
B61: 2 | C61: For each promise, find the implementation. Not the intention — the file. | D61: GAP-SD1, GAP-SD2, GAP-SD5, GAP-SD6 and GAP-SD8 were all promises with no file behind them, one of them repeated in RAID for fourteen sessions. | E61: A gap list with severity.
B62: 3 | C62: Build the missing implementation, or withdraw the promise explicitly as a decision. | D62: Withdrawing is legitimate and cheaper — D-SD5 dropped an unused permission rather than inventing a consumer for it. | E62: New modules, or a recorded D-SDn decision.
B63: 4 | C63: Bind promise to implementation with a contract test that fails on drift in either direction. | D63: The manifest-versus-code assertions exist so that no future manifest promise can ship without an implementation. | E63: Two-way contract tests.
B64: 5 | C64: Rerun the gate and release. | D64: Unchanged discipline regardless of release type. | E64: Released version.
B65: 6 | C65: RELEASE-SPECIFIC: Artifact-gap audit round 3: the HTTP server and bootstrap. | D65: Three of five tab paths and the bot messaging endpoint had no server behind them. The client called a server that did not exist. | E65: GAP-SD5 closed with src/server.ts + src/bootstrap.ts and a client-vs-server parity test
A66: v010 | B66: 1 | C66: Choose the seam that was most recently written from assumption rather than from vendor documentation. | D66: The bot transport and the tab SSO seam were each wrong in three ways and their own tests passed (R-S12). | E66: The seam under verification.
B67: 2 | C67: Read the vendor documentation for that seam properly, and write down what it actually requires. | D67: Guessing an authentication or payload contract produces code that is confidently wrong. | E67: A requirement list quoted from the documentation.
B68: 3 | C68: Compare the shipped code against each requirement, one line at a time. | D68: This is where VER-SD09, VER-SD10 and VER-SD13 came from — all live-blocking, none visible to the suite. | E68: VER-SDnn findings with severity.
B69: 4 | C69: Correct the code and pin the requirement with an assertion on the outbound shape, not only the inbound handling. | D69: Asserting what we send is how a wrong header or a wrong reply mechanism gets caught. | E69: Transport-level assertions.
B70: 5 | C70: Record anything only a live client can settle, and route it to the live sweep rather than claiming it. | D70: R-S8 exists because the sandbox cannot prove in-client behaviour, and pretending otherwise would be the worst failure available. | E70: Sweep steps and pending-live stories.
B71: 6 | C71: Rerun the gate and release. | D71: Unchanged discipline regardless of release type. | E71: Released version.
B72: 7 | C72: RELEASE-SPECIFIC: Verification sweep 2 over the bot transport seam. | D72: The bot endpoint built one session earlier was written from assumption: authentication, payload shape and reply mechanism were all guesses, and its own tests passed. | E72: VER-SD09/SD10 live-blockers closed (Connector JWT, ack-then-send); VER-SD11/SD12 closed
A73: v011 | B73: 1 | C73: Choose the seam that was most recently written from assumption rather than from vendor documentation. | D73: The bot transport and the tab SSO seam were each wrong in three ways and their own tests passed (R-S12). | E73: The seam under verification.
B74: 2 | C74: Read the vendor documentation for that seam properly, and write down what it actually requires. | D74: Guessing an authentication or payload contract produces code that is confidently wrong. | E74: A requirement list quoted from the documentation.
B75: 3 | C75: Compare the shipped code against each requirement, one line at a time. | D75: This is where VER-SD09, VER-SD10 and VER-SD13 came from — all live-blocking, none visible to the suite. | E75: VER-SDnn findings with severity.
B76: 4 | C76: Correct the code and pin the requirement with an assertion on the outbound shape, not only the inbound handling. | D76: Asserting what we send is how a wrong header or a wrong reply mechanism gets caught. | E76: Transport-level assertions.
B77: 5 | C77: Record anything only a live client can settle, and route it to the live sweep rather than claiming it. | D77: R-S8 exists because the sandbox cannot prove in-client behaviour, and pretending otherwise would be the worst failure available. | E77: Sweep steps and pending-live stories.
B78: 6 | C78: Rerun the gate and release. | D78: Unchanged discipline regardless of release type. | E78: Released version.
B79: 7 | C79: RELEASE-SPECIFIC: Verification sweep 3 over the tab SSO seam. | D79: Same class as the bot seam one session earlier: the tab was sending a hardcoded placeholder token while the manifest declared SSO. | E79: VER-SD13 live-blocker closed with real acquisition and validation; VER-SD14 documented
A80: v012 | B80: 1 | C80: List every promise the product makes outside its code: manifest declarations, documented commands, published claims, RAID assertions. | D80: A promise with nothing behind it is a store rejection or a broken install, and it is invisible to a coverage gate. | E80: A promise inventory.
B81: 2 | C81: For each promise, find the implementation. Not the intention — the file. | D81: GAP-SD1, GAP-SD2, GAP-SD5, GAP-SD6 and GAP-SD8 were all promises with no file behind them, one of them repeated in RAID for fourteen sessions. | E81: A gap list with severity.
B82: 3 | C82: Build the missing implementation, or withdraw the promise explicitly as a decision. | D82: Withdrawing is legitimate and cheaper — D-SD5 dropped an unused permission rather than inventing a consumer for it. | E82: New modules, or a recorded D-SDn decision.
B83: 4 | C83: Bind promise to implementation with a contract test that fails on drift in either direction. | D83: The manifest-versus-code assertions exist so that no future manifest promise can ship without an implementation. | E83: Two-way contract tests.
B84: 5 | C84: Rerun the gate and release. | D84: Unchanged discipline regardless of release type. | E84: Released version.
B85: 6 | C85: RELEASE-SPECIFIC: Artifact-gap audit round 4: Graph membership consumed, unused scope dropped. | D85: TeamMember.Read.Group was requested and documented but never consumed, and every role resolver was a stub. Requesting a permission you do not use fails store review and misleads the consent screen. | E85: GAP-SD6 closed with src/graphMembers.ts; GAP-SD7 dropped as D-SD5; scopes bound to consumer files by test
A86: v013 | B86: 1 | C86: Freeze the scope: name the sessions whose code has never been reviewed, and read nothing else. | D86: A review with unbounded scope becomes a skim. New code is the least-reviewed code (R-S10). | E86: A named module list for the pass.
B87: 2 | C87: Read each module adversarially, asking what input would make it do the wrong thing, not whether it looks correct. | D87: Every defect found this way had a passing test over it already. | E87: A candidate defect list.
B88: 3 | C88: Reproduce each candidate as a failing test before touching the code. | D88: A defect without a failing test is an opinion, and a fix without one regresses silently. | E88: Failing tests, one per confirmed defect.
B89: 4 | C89: Fix, and keep the regression test pinned in a pass-specific suite so its origin stays visible. | D89: The suite name is the audit trail: tests/reviewPass4.test.ts says when and why the assertion exists. | E89: F-nnn entries fixed with named regressions.
B90: 5 | C90: Record anything not fixed as an explicit open finding with a disposition owner, rather than fixing it quietly or dropping it. | D90: F-007 and F-008 stayed open for weeks under their own ids. That is honest; silence would not have been. | E90: Open findings with owners.
B91: 6 | C91: Rerun the full gate and release, with the defect count in the release note. | D91: The count belongs in the note because a release that fixed six defects is not the same artefact as one that fixed none. | E91: Released version with the findings recorded.
B92: 7 | C92: RELEASE-SPECIFIC: Cold-review pass 4 over the sessions 10-13 integration code. | D92: The integration layer written in the previous four sessions had never been reviewed, and integration seams are where the defects live. | E92: F-020..F-024 fixed, including tenant-arbitrary install/trial and deduped failed Connector sends
A93: v014 | B93: 1 | C93: List every promise the product makes outside its code: manifest declarations, documented commands, published claims, RAID assertions. | D93: A promise with nothing behind it is a store rejection or a broken install, and it is invisible to a coverage gate. | E93: A promise inventory.
B94: 2 | C94: For each promise, find the implementation. Not the intention — the file. | D94: GAP-SD1, GAP-SD2, GAP-SD5, GAP-SD6 and GAP-SD8 were all promises with no file behind them, one of them repeated in RAID for fourteen sessions. | E94: A gap list with severity.
B95: 3 | C95: Build the missing implementation, or withdraw the promise explicitly as a decision. | D95: Withdrawing is legitimate and cheaper — D-SD5 dropped an unused permission rather than inventing a consumer for it. | E95: New modules, or a recorded D-SDn decision.
B96: 4 | C96: Bind promise to implementation with a contract test that fails on drift in either direction. | D96: The manifest-versus-code assertions exist so that no future manifest promise can ship without an implementation. | E96: Two-way contract tests.
B97: 5 | C97: Rerun the gate and release. | D97: Unchanged discipline regardless of release type. | E97: Released version.
B98: 6 | C98: RELEASE-SPECIFIC: Artifact-gap audit round 5: the repository seam actually built. | D98: RAID R-S4 had claimed "typed repositories" since session 1 and they did not exist: all state was in bare Maps. The durability story rested on a sentence. | E98: GAP-SD8 closed with a repository seam, Postgres implementation, migration SQL, durable audit log and tenant purge
A99: v015 | B99: 1 | C99: List every promise the product makes outside its code: manifest declarations, documented commands, published claims, RAID assertions. | D99: A promise with nothing behind it is a store rejection or a broken install, and it is invisible to a coverage gate. | E99: A promise inventory.
B100: 2 | C100: For each promise, find the implementation. Not the intention — the file. | D100: GAP-SD1, GAP-SD2, GAP-SD5, GAP-SD6 and GAP-SD8 were all promises with no file behind them, one of them repeated in RAID for fourteen sessions. | E100: A gap list with severity.
B101: 3 | C101: Build the missing implementation, or withdraw the promise explicitly as a decision. | D101: Withdrawing is legitimate and cheaper — D-SD5 dropped an unused permission rather than inventing a consumer for it. | E101: New modules, or a recorded D-SDn decision.
...

Sheet Test_Cases
A1: MANUAL TEST CASES — 199 cases across 41 releases, positive and negative
A2: HOW TO USE THIS SHEET — Filter column B to test one release, or column J to find what is executable today. Work the steps in column G in order and compare with column H. Fill columns L-O as you go; leave H alone. A case whose Executable column says "No" cannot be run from a sandbox and the reason is stated — record it as Blocked rather than Pass.
A4: Case id | B4: Release | C4: Covers (story / finding) | D4: Test case name | E4: Type | F4: Priority | G4: Preconditions | H4: Test steps (in order) | I4: Expected result | J4: Automated evidence | K4: Executable now | L4: Status | M4: Actual result | N4: Tester | O4: Date run
A5: TC-001-01 | B5: v001 | C5: ST-051..056 | D5: Install creates a tenant in the welcome state | E5: Positive | F5: High | G5: App not installed for tenant T1 | H5: 1. POST the Teams install webhook for tenant T1. 2. Read the tenant record. 3. Read the telemetry stream. | I5: Tenant T1 exists, state = welcome, install event recorded once with its source attribution. | J5: tests/install.test.ts | K5: Yes — sandbox | L5: Not run
A6: TC-001-02 | B6: v001 | C6: ST-051..056 | D6: A repeated install webhook does not wipe the tenant | E6: Negative | F6: Critical | G6: Tenant T1 installed with 3 handovers | H6: 1. POST the identical install webhook for T1 a second time. 2. List handovers for T1. | I6: The existing account is returned untouched, all 3 handovers remain, and one install_duplicate_ignored telemetry row is written. No data loss (F-002). | J6: tests/install.test.ts | K6: Yes — sandbox | L6: Not run
A7: TC-001-03 | B7: v001 | C7: ST-051..056 | D7: Uninstall schedules deletion 30 days out rather than deleting immediately | E7: Positive | F7: High | G7: Tenant T1 installed | H7: 1. POST the uninstall webhook for T1. 2. Read the deletion schedule. 3. Attempt to read T1 data. | I7: A purge is scheduled 30 days ahead, tokens are wiped, and the data is still restorable inside the window. | J7: tests/install.test.ts | K7: Yes — sandbox | L7: Not run
A8: TC-001-04 | B8: v001 | C8: ST-051..056 | D8: Re-install inside the retention window restores the account | E8: Positive | F8: High | G8: T1 uninstalled 5 days ago | H8: 1. POST the install webhook for T1. 2. List handovers for T1. | I8: The scheduled purge is cancelled and the prior data is visible again. | J8: tests/tenantLifecycle.test.ts | K8: Yes — sandbox | L8: Not run
A9: TC-001-05 | B9: v001 | C9: ST-051..056 | D9: A rotated platform token is refreshed rather than failing the call | E9: Positive | F9: Medium | G9: Token store holds a stale token | H9: 1. Force the gateway to make a call with a stale token. 2. Observe the retry. | I9: The token is refreshed once and the call succeeds; no user-visible error. | J9: tests/platformGateway.test.ts | K9: Yes — sandbox | L9: Not run
A10: TC-002-01 | B10: v002 | C10: ST-093, LC-2 | D10: The app package validates against the store manifest rules | E10: Positive | F10: High | G10: Repo built | H10: 1. Run npm run package with all substitution values supplied. 2. Unzip the produced archive. | I10: manifest.json, both icons and the localisation file sit at the archive root; schema and size rules pass. | J10: tests/packageApp.test.ts | K10: Yes — sandbox | L10: Not run
A11: TC-002-02 | B11: v002 | C11: ST-093, LC-2 | D11: Packaging refuses to produce a package with a placeholder left in | E11: Negative | F11: High | G11: BASE_DOMAIN unset | H11: 1. Run npm run package without BASE_DOMAIN. | I11: The command fails and names the missing value: "missing value for BASE_DOMAIN". No archive is produced. | J11: tests/packageApp.test.ts | K11: Yes — sandbox | L11: Not run
A12: TC-002-03 | B12: v002 | C12: ST-093, LC-2 | D12: Typed config loader rejects a malformed environment | E12: Negative | F12: Medium | G12: None | H12: 1. Set SHIFTDESK_BODY_LIMIT to "abc". 2. Start the process. | I12: Boot fails with CONFIG_INVALID naming the variable, rather than silently using a default. | J12: tests/config.test.ts | K12: Yes — sandbox | L12: Not run
A13: TC-003-01 | B13: v003 | C13: ST-088/090/092, LC-8 | D13: The k6 harness runs the 5x profile and applies its thresholds | E13: Positive | F13: Medium | G13: k6 installed, target URL reachable | H13: 1. Run the k6 sweep against a target. 2. Read the summary. | I13: The run reports api p95, bot p95 and failure rate against the declared thresholds and exits non-zero on breach. | J13: load/k6-load-sweep.js | K13: No — needs staging (SD219) | L13: Blocked
A14: TC-003-02 | B14: v003 | C14: ST-088/090/092, LC-8 | D14: The backup drill fails when the restore target is not empty | E14: Negative | F14: High | G14: Restore database contains rows | H14: 1. Point RESTORE_URL at a non-empty database. 2. Run npm run backup:drill. | I14: The drill refuses rather than restoring over existing data, and the report is not overwritten with a pass. | J14: ops/backup-restore-drill.sh | K14: Yes — sandbox | L14: Not run
A15: TC-003-03 | B15: v003 | C15: ST-088/090/092, LC-8 | D15: The deploy workflow requires an approval before switching traffic | E15: Positive | F15: Medium | G15: Workflow file present | H15: 1. Inspect the deploy workflow job graph. | I15: The traffic switch is gated on an approval environment and runs after migrations. | J15: .github/workflows/deploy.yml | K15: Yes — sandbox | L15: Not run
A16: TC-004-01 | B16: v004 | C16: F-001..F-006 | D16: A recovered payment returns a read-only account to active | E16: Positive | F16: Critical | G16: Tenant in read_only after 3 dunning notices | H16: 1. Call paymentRecovered() for the tenant. 2. Attempt a write. 3. Read the dunning counter. | I16: State returns to active, the write succeeds, and the dunning counter and grace start are reset (F-001). | J16: tests/billing.test.ts | K16: Yes — sandbox | L16: Not run
... A203: TC-041-04 | B203: v041 | C203: SD219/220/226/228/240 | D203: A test customer transacts through the marketplace end to end | E203: Positive | F203: Critical | G203: Transactable offer live | H203: 1. Purchase through the offer. 2. Resolve and activate. 3. Verify entitlement enforcement. | I203: The subscription activates and the entitlement gates writes correctly (SD240, LC-6/LC-11). | J203: tests/commercial.test.ts | K203: No — needs a Partner Center offer | L203: Blocked

Sheet Test_Execution_Log
A1: TEST EXECUTION LOG — one row per execution cycle
A2: HOW TO USE THIS SHEET — Add a row each time someone works through a set of cases. Record the build under test, the environment, which cases were in scope and what happened. The first row is the automated evidence run that backs this issue of the document; manual cycles follow it.
A4: Run id | B4: Date | C4: Executed by | D4: Build / version under test | E4: Environment | F4: Cases in scope | G4: Pass | H4: Fail | I4: Blocked | J4: Outcome / notes
A5: RUN-001 | B5: 2026-09-20 | C5: Claude (automated tiers) | D5: v0.14.0 / release v040 | E5: Sandbox + real PostgreSQL 16 (local, port 55432) | F5: Automated equivalents of the sandbox-executable cases | G5: 555 | H5: 0 | I5: 0 | J5: Tier 1: 68 unit suites / 555 tests green at 100% statements, branches, functions and lines with zero pragmas. Tier 2: 9/9 real-Postgres integration tests. Tier 3: production-seam wiring assertion green. Backup/restore drill PASS with RPO 0s and RTO 0s against a 15 min / 60 min bar. This run is the automated backing for the manual cases marked "Yes — sandbox"; it is not a substitute for walking them.
A6: RUN-002 | C6: (open) | E6: Manual, sandbox | F6: All cases where Executable = Yes | J6: PLANNED — the first human pass over this specification. Expect it to find at least one case where the expected result is written wrongly; that is a finding about this document and belongs in Defect_Log too.
A7: RUN-003 | C7: (open — Senthil) | E7: Live Microsoft 365 dev tenant | F7: The four v041 cases plus every case marked Partial | J7: BLOCKED — needs a dev tenant with the app sideloaded. This is the run that turns eleven pending-live stories into evidence.

Sheet RTM
A1: REQUIREMENTS TRACEABILITY MATRIX — release to coverage, and the cases that prove it
A2: HOW TO USE THIS SHEET — The reverse of Test_Cases: start from a release or a finding and see what proves it. Column E counts the cases with a live formula, so a release that loses its cases shows a zero here rather than quietly disappearing.
A4: Release | B4: Category | C4: What it delivered | D4: Covers (story / finding ids) | E4: Manual cases | F4: Positive | G4: Negative | H4: Automated evidence | I4: Status
A5: v001 | B5: BUILD | C5: Foundation through S8 consolidated into one tracker | D5: ST-051..056 | E5: =COUNTIF(Test_Cases!$B$5:$B$203,"v001") | F5: =COUNTIFS(Test_Cases!$B$5:$B$203,"v001",Test_Cases!$E$5:$E$203,"Positive") | G5: =COUNTIFS(Test_Cases!$B$5:$B$203,"v001",Test_Cases!$E$5:$E$203,"Negative") | H5: Unit suite at 100% | I5: Released — verified in sandbox
A6: v002 | B6: BUILD | C6: Live-sweep readiness pack: manifest v1.17, icons, typed config loader, 12-step sweep, dev-tenant guide | D6: ST-093, LC-2 | E6: =COUNTIF(Test_Cases!$B$5:$B$203,"v002") | F6: =COUNTIFS(Test_Cases!$B$5:$B$203,"v002",Test_Cases!$E$5:$E$203,"Positive") | G6: =COUNTIFS(Test_Cases!$B$5:$B$203,"v002",Test_Cases!$E$5:$E$203,"Negative") | H6: Unit suite at 100% | I6: Released — verified in sandbox
A7: v003 | B7: BUILD | C7: Ops parity pack: k6 5x load harness, blue/green deploy workflow, scripted backup/restore drill | D7: ST-088/090/092, LC-8 | E7: =COUNTIF(Test_Cases!$B$5:$B$203,"v003") | F7: =COUNTIFS(Test_Cases!$B$5:$B$203,"v003",Test_Cases!$E$5:$E$203,"Positive") | G7: =COUNTIFS(Test_Cases!$B$5:$B$203,"v003",Test_Cases!$E$5:$E$203,"Negative") | H7: Unit suite at 100% | I7: Released — verified in sandbox
A8: v004 | B8: REVIEW | C8: Adversarial cold-review pass 1 over the S1-S8 code | D8: F-001..F-006 | E8: =COUNTIF(Test_Cases!$B$5:$B$203,"v004") | F8: =COUNTIFS(Test_Cases!$B$5:$B$203,"v004",Test_Cases!$E$5:$E$203,"Positive") | G8: =COUNTIFS(Test_Cases!$B$5:$B$203,"v004",Test_Cases!$E$5:$E$203,"Negative") | H8: Unit suite at 100% | I8: Released — verified in sandbox
A9: v005 | B9: REVIEW | C9: Cold-review pass 2 plus the completion wave taking the last backlog stories to sandbox ceiling | D9: F-010..F-013 | E9: =COUNTIF(Test_Cases!$B$5:$B$203,"v005") | F9: =COUNTIFS(Test_Cases!$B$5:$B$203,"v005",Test_Cases!$E$5:$E$203,"Positive") | G9: =COUNTIFS(Test_Cases!$B$5:$B$203,"v005",Test_Cases!$E$5:$E$203,"Negative") | H9: Unit suite at 100% | I9: Released — verified in sandbox
A10: v006 | B10: VERIFY | C10: External verification sweep against live Microsoft documentation, plus artifact-gap audit round 1 | D10: VER-SD01..08 | E10: =COUNTIF(Test_Cases!$B$5:$B$203,"v006") | F10: =COUNTIFS(Test_Cases!$B$5:$B$203,"v006",Test_Cases!$E$5:$E$203,"Positive") | G10: =COUNTIFS(Test_Cases!$B$5:$B$203,"v006",Test_Cases!$E$5:$E$203,"Negative") | H10: Unit suite at 100% | I10: Released — verified in sandbox
A11: v007 | B11: GAP | C11: Artifact-gap audit round 2: the web tab layer and the bot command router | D11: GAP-SD1/2/3 | E11: =COUNTIF(Test_Cases!$B$5:$B$203,"v007") | F11: =COUNTIFS(Test_Cases!$B$5:$B$203,"v007",Test_Cases!$E$5:$E$203,"Positive") | G11: =COUNTIFS(Test_Cases!$B$5:$B$203,"v007",Test_Cases!$E$5:$E$203,"Negative") | H11: Unit suite at 100% | I11: Released — verified in sandbox
A12: v008 | B12: REVIEW | C12: Cold-review pass 3 over the sessions 5-8 code that had never been reviewed | D12: F-014..F-019 | E12: =COUNTIF(Test_Cases!$B$5:$B$203,"v008") | F12: =COUNTIFS(Test_Cases!$B$5:$B$203,"v008",Test_Cases!$E$5:$E$203,"Positive") | G12: =COUNTIFS(Test_Cases!$B$5:$B$203,"v008",Test_Cases!$E$5:$E$203,"Negative") | H12: Unit suite at 100% | I12: Released — verified in sandbox
A13: v009 | B13: GAP | C13: Artifact-gap audit round 3: the HTTP server and bootstrap | D13: GAP-SD5 | E13: =COUNTIF(Test_Cases!$B$5:$B$203,"v009") | F13: =COUNTIFS(Test_Cases!$B$5:$B$203,"v009",Test_Cases!$E$5:$E$203,"Positive") | G13: =COUNTIFS(Test_Cases!$B$5:$B$203,"v009",Test_Cases!$E$5:$E$203,"Negative") | H13: Unit suite at 100% | I13: Released — verified in sandbox
A14: v010 | B14: VERIFY | C14: Verification sweep 2 over the bot transport seam | D14: VER-SD09..12 | E14: =COUNTIF(Test_Cases!$B$5:$B$203,"v010") | F14: =COUNTIFS(Test_Cases!$B$5:$B$203,"v010",Test_Cases!$E$5:$E$203,"Positive") | G14: =COUNTIFS(Test_Cases!$B$5:$B$203,"v010",Test_Cases!$E$5:$E$203,"Negative") | H14: Unit suite at 100% | I14: Released — verified in sandbox
A15: v011 | B15: VERIFY | C15: Verification sweep 3 over the tab SSO seam | D15: VER-SD13/14 | E15: =COUNTIF(Test_Cases!$B$5:$B$203,"v011") | F15: =COUNTIFS(Test_Cases!$B$5:$B$203,"v011",Test_Cases!$E$5:$E$203,"Positive") | G15: =COUNTIFS(Test_Cases!$B$5:$B$203,"v011",Test_Cases!$E$5:$E$203,"Negative") | H15: Unit suite at 100% | I15: Released — verified in sandbox
A16: v012 | B16: GAP | C16: Artifact-gap audit round 4: Graph membership consumed, unused scope dropped | D16: GAP-SD6/7, D-SD5 | E16: =COUNTIF(Test_Cases!$B$5:$B$203,"v012") | F16: =COUNTIFS(Test_Cases!$B$5:$B$203,"v012",Test_Cases!$E$5:$E$203,"Positive") | G16: =COUNTIFS(Test_Cases!$B$5:$B$203,"v012",Test_Cases!$E$5:$E$203,"Negative") | H16: Unit suite at 100% | I16: Released — verified in sandbox
A17: v013 | B17: REVIEW | C17: Cold-review pass 4 over the sessions 10-13 integration code | D17: F-020..F-024 | E17: =COUNTIF(Test_Cases!$B$5:$B$203,"v013") | F17: =COUNTIFS(Test_Cases!$B$5:$B$203,"v013",Test_Cases!$E$5:$E$203,"Positive") | G17: =COUNTIFS(Test_Cases!$B$5:$B$203,"v013",Test_Cases!$E$5:$E$203,"Negative") | H17: Unit suite at 100% | I17: Released — verified in sandbox
A18: v014 | B18: GAP | C18: Artifact-gap audit round 5: the repository seam actually built | D18: GAP-SD8 | E18: =COUNTIF(Test_Cases!$B$5:$B$203,"v014") | F18: =COUNTIFS(Test_Cases!$B$5:$B$203,"v014",Test_Cases!$E$5:$E$203,"Positive") | G18: =COUNTIFS(Test_Cases!$B$5:$B$203,"v014",Test_Cases!$E$5:$E$203,"Negative") | H18: Unit suite at 100% | I18: Released — verified in sandbox
A19: v015 | B19: GAP | C19: Persistence slice 1: snapshot/restore on the service core wired through HTTP | D19: GAP-SD8b | E19: =COUNTIF(Test_Cases!$B$5:$B$203,"v015") | F19: =COUNTIFS(Test_Cases!$B$5:$B$203,"v015",Test_Cases!$E$5:$E$203,"Positive") | G19: =COUNTIFS(Test_Cases!$B$5:$B$203,"v015",Test_Cases!$E$5:$E$203,"Negative") | H19: Unit suite at 100% | I19: Released — verified in sandbox
A20: v016 | B20: BUILD | C20: Persistence slice 2: billing, install and support chat survive a restart | D20: OBS-SD5a, F-025 | E20: =COUNTIF(Test_Cases!$B$5:$B$203,"v016") | F20: =COUNTIFS(Test_Cases!$B$5:$B$203,"v016",Test_Cases!$E$5:$E$203,"Positive") | G20: =COUNTIFS(Test_Cases!$B$5:$B$203,"v016",Test_Cases!$E$5:$E$203,"Negative") | H20: Unit suite at 100% | I20: Released — verified in sandbox
A21: v017 | B21: AUDIT | C21: Multi-tenancy audit | D21: F-026..F-028 | E21: =COUNTIF(Test_Cases!$B$5:$B$203,"v017") | F21: =COUNTIFS(Test_Cases!$B$5:$B$203,"v017",Test_Cases!$E$5:$E$203,"Positive") | G21: =COUNTIFS(Test_Cases!$B$5:$B$203,"v017",Test_Cases!$E$5:$E$203,"Negative") | H21: Unit suite at 100% | I21: Released — verified in sandbox
A22: v018 | B22: AUDIT | C22: Data-deletion audit | D22: F-029 | E22: =COUNTIF(Test_Cases!$B$5:$B$203,"v018") | F22: =COUNTIFS(Test_Cases!$B$5:$B$203,"v018",Test_Cases!$E$5:$E$203,"Positive") | G22: =COUNTIFS(Test_Cases!$B$5:$B$203,"v018",Test_Cases!$E$5:$E$203,"Negative") | H22: Unit suite at 100% | I22: Released — verified in sandbox
A23: v019 | B23: AUDIT | C23: Authorization audit | D23: F-030, D-SD6 | E23: =COUNTIF(Test_Cases!$B$5:$B$203,"v019") | F23: =COUNTIFS(Test_Cases!$B$5:$B$203,"v019",Test_Cases!$E$5:$E$203,"Positive") | G23: =COUNTIFS(Test_Cases!$B$5:$B$203,"v019",Test_Cases!$E$5:$E$203,"Negative") | H23: Unit suite at 100% | I23: Released — verified in sandbox
A24: v020 | B24: AUDIT | C24: Billing-integrity audit | D24: F-031..F-033 | E24: =COUNTIF(Test_Cases!$B$5:$B$203,"v020") | F24: =COUNTIFS(Test_Cases!$B$5:$B$203,"v020",Test_Cases!$E$5:$E$203,"Positive") | G24: =COUNTIFS(Test_Cases!$B$5:$B$203,"v020",Test_Cases!$E$5:$E$203,"Negative") | H24: Unit suite at 100% | I24: Released — verified in sandbox
A25: v021 | B25: AUDIT | C25: Notification delivery and latency instrumentation | D25: F-034/F-035 | E25: =COUNTIF(Test_Cases!$B$5:$B$203,"v021") | F25: =COUNTIFS(Test_Cases!$B$5:$B$203,"v021",Test_Cases!$E$5:$E$203,"Positive") | G25: =COUNTIFS(Test_Cases!$B$5:$B$203,"v021",Test_Cases!$E$5:$E$203,"Negative") | H25: Unit suite at 100% | I25: Released — verified in sandbox
A26: v022 | B26: AUDIT | C26: Telemetry and audit wiring | D26: F-036/F-037 | E26: =COUNTIF(Test_Cases!$B$5:$B$203,"v022") | F26: =COUNTIFS(Test_Cases!$B$5:$B$203,"v022",Test_Cases!$E$5:$E$203,"Positive") | G26: =COUNTIFS(Test_Cases!$B$5:$B$203,"v022",Test_Cases!$E$5:$E$203,"Negative") | H26: Unit suite at 100% | I26: Released — verified in sandbox
A27: v023 | B27: AUDIT | C27: Systematic wiring audit of all 112 exports | D27: F-038..F-040 | E27: =COUNTIF(Test_Cases!$B$5:$B$203,"v023") | F27: =COUNTIFS(Test_Cases!$B$5:$B$203,"v023",Test_Cases!$E$5:$E$203,"Positive") | G27: =COUNTIFS(Test_Cases!$B$5:$B$203,"v023",Test_Cases!$E$5:$E$203,"Negative") | H27: Unit suite at 100% | I27: Released — verified in sandbox
A28: v024 | B28: BUILD | C28: Encryption at rest resolved both ways, trust page rewritten | D28: F-040, OBS-SD8 | E28: =COUNTIF(Test_Cases!$B$5:$B$203,"v024") | F28: =COUNTIFS(Test_Cases!$B$5:$B$203,"v024",Test_Cases!$E$5:$E$203,"Positive") | G28: =COUNTIFS(Test_Cases!$B$5:$B$203,"v024",Test_Cases!$E$5:$E$203,"Negative") | H28: Unit suite at 100% | I28: Released — verified in sandbox
A29: v025 | B29: REVIEW | C29: Cold-review pass 5 over the sessions 18-25 modules | D29: F-041..F-045 | E29: =COUNTIF(Test_Cases!$B$5:$B$203,"v025") | F29: =COUNTIFS(Test_Cases!$B$5:$B$203,"v025",Test_Cases!$E$5:$E$203,"Positive") | G29: =COUNTIFS(Test_Cases!$B$5:$B$203,"v025",Test_Cases!$E$5:$E$203,"Negative") | H29: Unit suite at 100% | I29: Released — verified in sandbox
A30: v026 | B30: AUDIT | C30: Multi-instance audit | D30: F-046 | E30: =COUNTIF(Test_Cases!$B$5:$B$203,"v026") | F30: =COUNTIFS(Test_Cases!$B$5:$B$203,"v026",Test_Cases!$E$5:$E$203,"Positive") | G30: =COUNTIFS(Test_Cases!$B$5:$B$203,"v026",Test_Cases!$E$5:$E$203,"Negative") | H30: Unit suite at 100% | I30: Released — verified in sandbox
A31: v027 | B31: AUDIT | C31: Dependency-failure audit | D31: F-047/F-048 | E31: =COUNTIF(Test_Cases!$B$5:$B$203,"v027") | F31: =COUNTIFS(Test_Cases!$B$5:$B$203,"v027",Test_Cases!$E$5:$E$203,"Positive") | G31: =COUNTIFS(Test_Cases!$B$5:$B$203,"v027",Test_Cases!$E$5:$E$203,"Negative") | H31: Unit suite at 100% | I31: Released — verified in sandbox
A32: v028 | B32: REVIEW | C32: Cold-review pass 6 over sessions 26-28 | D32: F-049..F-051 | E32: =COUNTIF(Test_Cases!$B$5:$B$203,"v028") | F32: =COUNTIFS(Test_Cases!$B$5:$B$203,"v028",Test_Cases!$E$5:$E$203,"Positive") | G32: =COUNTIFS(Test_Cases!$B$5:$B$203,"v028",Test_Cases!$E$5:$E$203,"Negative") | H32: Unit suite at 100% | I32: Released — verified in sandbox
A33: v029 | B33: BUILD | C33: Live-day preparation: the automated half of the sweep made executable | D33: ST-096 | E33: =COUNTIF(Test_Cases!$B$5:$B$203,"v029") | F33: =COUNTIFS(Test_Cases!$B$5:$B$203,"v029",Test_Cases!$E$5:$E$203,"Positive") | G33: =COUNTIFS(Test_Cases!$B$5:$B$203,"v029",Test_Cases!$E$5:$E$203,"Negative") | H33: Unit suite at 100% | I33: Released — verified in sandbox
A34: v030 | B34: BUILD | C34: Six more sweep steps automated behind capability gates | D34: F-052 | E34: =COUNTIF(Test_Cases!$B$5:$B$203,"v030") | F34: =COUNTIFS(Test_Cases!$B$5:$B$203,"v030",Test_Cases!$E$5:$E$203,"Positive") | G34: =COUNTIFS(Test_Cases!$B$5:$B$203,"v030",Test_Cases!$E$5:$E$203,"Negative") | H34: Unit suite at 100% | I34: Released — verified in sandbox
A35: v031 | B35: BUILD | C35: Packaging automated with manifest validation | D35: GAP-SD3 | E35: =COUNTIF(Test_Cases!$B$5:$B$203,"v031") | F35: =COUNTIFS(Test_Cases!$B$5:$B$203,"v031",Test_Cases!$E$5:$E$203,"Positive") | G35: =COUNTIFS(Test_Cases!$B$5:$B$203,"v031",Test_Cases!$E$5:$E$203,"Negative") | H35: Unit suite at 100% | I35: Released — verified in sandbox
A36: v032 | B36: AUDIT | C36: Deliverability audit from a clean install | D36: F-053/054/056 | E36: =COUNTIF(Test_Cases!$B$5:$B$203,"v032") | F36: =COUNTIFS(Test_Cases!$B$5:$B$203,"v032",Test_Cases!$E$5:$E$203,"Positive") | G36: =COUNTIFS(Test_Cases!$B$5:$B$203,"v032",Test_Cases!$E$5:$E$203,"Negative") | H36: Unit suite at 100% | I36: Released — verified in sandbox
A37: v033 | B37: AUDIT | C37: Clean-checkout rehearsal of the full delivery | D37: F-057 | E37: =COUNTIF(Test_Cases!$B$5:$B$203,"v033") | F37: =COUNTIFS(Test_Cases!$B$5:$B$203,"v033",Test_Cases!$E$5:$E$203,"Positive") | G37: =COUNTIFS(Test_Cases!$B$5:$B$203,"v033",Test_Cases!$E$5:$E$203,"Negative") | H37: Unit suite at 100% | I37: Released — verified in sandbox
A38: v034 | B38: AUDIT | C38: The tab URLs actually served | D38: F-058 | E38: =COUNTIF(Test_Cases!$B$5:$B$203,"v034") | F38: =COUNTIFS(Test_Cases!$B$5:$B$203,"v034",Test_Cases!$E$5:$E$203,"Positive") | G38: =COUNTIFS(Test_Cases!$B$5:$B$203,"v034",Test_Cases!$E$5:$E$203,"Negative") | H38: Unit suite at 100% | I38: Released — verified in sandbox
A39: v035 | B39: AUDIT | C39: The bot endpoint actually wired | D39: F-059 | E39: =COUNTIF(Test_Cases!$B$5:$B$203,"v035") | F39: =COUNTIFS(Test_Cases!$B$5:$B$203,"v035",Test_Cases!$E$5:$E$203,"Positive") | G39: =COUNTIFS(Test_Cases!$B$5:$B$203,"v035",Test_Cases!$E$5:$E$203,"Negative") | H39: Unit suite at 100% | I39: Released — verified in sandbox
A40: v036 | B40: AUDIT | C40: Lifecycle hooks and the retention scheduler wired | D40: F-060/F-061 | E40: =COUNTIF(Test_Cases!$B$5:$B$203,"v036") | F40: =COUNTIFS(Test_Cases!$B$5:$B$203,"v036",Test_Cases!$E$5:$E$203,"Positive") | G40: =COUNTIFS(Test_Cases!$B$5:$B$203,"v036",Test_Cases!$E$5:$E$203,"Negative") | H40: Unit suite at 100% | I40: Released — verified in sandbox
A41: v037 | B41: AUDIT | C41: Runtime wiring audit of the shipped entry point | D41: F-062..F-064 | E41: =COUNTIF(Test_Cases!$B$5:$B$203,"v037") | F41: =COUNTIFS(Test_Cases!$B$5:$B$203,"v037",Test_Cases!$E$5:$E$203,"Positive") | G41: =COUNTIFS(Test_Cases!$B$5:$B$203,"v037",Test_Cases!$E$5:$E$203,"Negative") | H41: Unit suite at 100% | I41: Released — verified in sandbox
A42: v038 | B42: AUDIT | C42: Identity, directory and seeding corrections | D42: F-065..F-067 | E42: =COUNTIF(Test_Cases!$B$5:$B$203,"v038") | F42: =COUNTIFS(Test_Cases!$B$5:$B$203,"v038",Test_Cases!$E$5:$E$203,"Positive") | G42: =COUNTIFS(Test_Cases!$B$5:$B$203,"v038",Test_Cases!$E$5:$E$203,"Negative") | H42: Unit suite at 100% | I42: Released — verified in sandbox
A43: v039 | B43: AUDIT | C43: Verification that the previous session's fixes reached the runtime | D43: F-068..F-070, OBS-SD11 | E43: =COUNTIF(Test_Cases!$B$5:$B$203,"v039") | F43: =COUNTIFS(Test_Cases!$B$5:$B$203,"v039",Test_Cases!$E$5:$E$203,"Positive") | G43: =COUNTIFS(Test_Cases!$B$5:$B$203,"v039",Test_Cases!$E$5:$E$203,"Negative") | H43: Unit suite at 100% | I43: Released — verified in sandbox
A44: v040 | B44: REVIEW | C44: Independent review V001 actioned in full: 47-story S13-S20 remediation programme | D44: SD201-SD247, P-001..P-020, F-071..F-074 | E44: =COUNTIF(Test_Cases!$B$5:$B$203,"v040") | F44: =COUNTIFS(Test_Cases!$B$5:$B$203,"v040",Test_Cases!$E$5:$E$203,"Positive") | G44: =COUNTIFS(Test_Cases!$B$5:$B$203,"v040",Test_Cases!$E$5:$E$203,"Negative") | H44: Unit suite at 100% + real-Postgres tier | I44: Released — verified in sandbox + real Postgres
A45: v041 | B45: PENDING | C45: Next release — opens on the v040 cold review or the first dev-tenant sweep | D45: SD219/220/226/228/240 | E45: =COUNTIF(Test_Cases!$B$5:$B$203,"v041") | F45: =COUNTIFS(Test_Cases!$B$5:$B$203,"v041",Test_Cases!$E$5:$E$203,"Positive") | G45: =COUNTIFS(Test_Cases!$B$5:$B$203,"v041",Test_Cases!$E$5:$E$203,"Negative") | H45: — | I45: Pending — see Pending_Versions
A46: TOTAL | E46: =SUM(E5:E45) | F46: =SUM(F5:F45) | G46: =SUM(G5:G45)
A48: EVERY RELEASE HAS AT LEAST ONE CASE, AND EVERY CRITICAL FINDING HAS A NEGATIVE ONE. That is the rule this sheet enforces by eye: a release with cases only in the Positive column has not been tested, it has been demonstrated.

Sheet Defect_Log
A1: DEFECT LOG — every defect of consequence, where it came from and how it closed
A2: HOW TO USE THIS SHEET — Read the Origin column first. The pattern matters more than any single row: in this product the defect was almost never a wrong algorithm, it was a correct module that nothing called, and it was found by an audit of work already called done. Severity is as assessed at the time.
A4: Defect id | B4: Release found | C4: Severity | D4: Origin | E4: What was wrong | F4: Why the tests did not catch it | G4: How it was closed | H4: Status
A5: F-002 | B5: v004 | C5: High | D5: Cold review pass 1 | E5: A duplicate Teams install webhook overwrote the existing tenant — full data loss on a repeated platform event. | F5: Nobody had written a test for the second install. Coverage was 100% of the paths that existed, and that path existed only in production. | G5: install() made idempotent; the duplicate is returned untouched and counted. | H5: Closed
A6: F-007 | B6: v004 | C6: Medium | D6: Cold review pass 1 | E6: The circuit breaker had no half-open probe: once open it stayed open until an operator called reset(). | F6: It was a design gap, not a code error. Tests asserted the documented behaviour, which was itself wrong. | G6: Held open deliberately for weeks under its own id, then closed in v040 as story SD207 with a cooldown probe and an ops alert. | H6: Closed in v040
A7: F-008 | B7: v004 | C7: Low | D7: Cold review pass 1 | E7: The audit log grew without bound in memory, and capping it would truncate a compliance trail. | F7: Correct behaviour was genuinely unclear, so it was recorded rather than guessed. | G7: Closed in v040 as SD218: durable, cursor-paged, swept by the published retention policy. | H7: Closed in v040
A8: F-016 | B8: v008 | C8: Critical | D8: Cold review pass 3 | E8: The tab API validated the SSO token and then never sent it. | F8: Both halves were tested in isolation. Nothing asserted the outbound request headers — the habit that became a standing rule. | G8: The validated token is attached to the outbound call; outbound shape asserted. | H8: Closed
A9: F-025 | B9: v016 | C9: High | D9: Writing persistence tests | E9: InMemoryRepository stored live references where Postgres stores values, so the dev and production paths diverged. | F9: One contract suite ran against both, but no case mutated the caller's object after writing. | G9: Values are copied on write in both implementations; the contract now covers it. | H9: Closed
A10: F-026 | B10: v017 | C10: Critical | D10: Multi-tenancy audit | E10: Cross-tenant data exposure: one tenant could read another's records. | F10: Every test used a single tenant. A suite at 100% coverage can sit on top of a product that shares all customer data. | G10: Tenant taken from the validated identity only, per-tenant registry, two-tenant isolation tests as a standing requirement. | H10: Closed
A11: F-029 | B11: v018 | C11: Critical | D11: Data-deletion audit | E11: The published 30-day retention policy and the self-serve delete deleted nothing at all. | F11: The functions existed and were tested. Nothing called them, and no test asserted the store was empty afterwards. | G11: src/tenantLifecycle.ts with a durable schedule, cancel-on-reinstall, a retention sweep and a real export. | H11: Closed
A12: F-030 | B12: v019 | C12: Critical | D12: Authorization audit | E12: Five of nine permissions published to customers were enforced nowhere, including data.delete and data.export. | F12: Permissions were data, not behaviour. Nothing compared the published matrix with the enforcement sites. | G12: Enforcement wired at named sites and bound by a two-way contract test; one unenforceable permission withdrawn (D-SD6). | H12: Closed
A13: F-036 | B13: v022 | C13: High | D13: Wiring audit | E13: The entire telemetry epic had zero callers, so the S11 activation criterion could not be computed. | F13: The modules were fully covered by their own unit tests. Coverage cannot see that nobody calls a module. | G13: Telemetry wired into the request path with boundary tests proving a real request emits events. | H13: Closed
A14: F-041 | B14: v025 | C14: Critical | D14: Cold review pass 5 | E14: The seat cap could never fire: the checker and its caller were each correct and the feature was inoperative. | F14: A correct function called with a wrong argument passes every unit test on both sides. | G14: Boundary tests now drive policy decisions through the request path with real actors. | H14: Closed
A15: F-046 | B15: v026 | C15: Critical | D15: Multi-instance audit | E15: Silent cross-instance data loss under the shipped blue/green deploy model. | F15: Every previous audit examined one running instance. A model that is correct alone can be destructive in pairs. | G15: Optimistic concurrency end to end, migration 002, a migration step in the deploy, and two-instance tests as standing practice. | H15: Closed
... A27: F-074 | B27: v040 | C27: Medium | D27: Rerunning the suite on a cleaned tree | E27: The tier-3 production-seam job named a test file that has never existed, so jest exited "no tests found" and the gate that decision D-SD7 rests on had never run. | F27: Nothing checked that a path named in a workflow exists. A green pipeline with a silently empty job looks identical to a passing one. | G27: Both workflows name the four suites that exist, and a new assertion fails if any test path referenced in any workflow is missing. | H27: Closed
A29: THIS IS A SELECTION, NOT THE WHOLE REGISTER. Seventy-four F-series defects, twenty P-series findings, fourteen VER-SD, eight GAP-SD and eleven OBS-SD entries exist in full in REVIEW_PACK.md inside the source zip and on the Review_Findings sheet of the product workbook. The rows above are the ones that change how you should read the product: every CRITICAL, plus the four defects this release created or exposed in its own quality gate.

Sheet Test_Summary
A1: TEST SUMMARY — computed live from Test_Cases
A2: HOW TO USE THIS SHEET — Do not type in this sheet. Every figure is a formula over Test_Cases, so it cannot disagree with the cases themselves. If a number looks wrong, the case data is wrong. Recalculate after editing Test_Cases.
A4: Measure | B4: Count | C4: Of total | D4: What it tells you
A5: Total manual cases | B5: =COUNTA(Test_Cases!$A$5:$A$203) | C5: =1 | D5: The whole specification.
A6: Positive cases | B6: =COUNTIF(Test_Cases!$E$5:$E$203,"Positive") | C6: =IFERROR(B6/$B$5,0) | D6: Does it do what it claims.
A7: Negative cases | B7: =COUNTIF(Test_Cases!$E$5:$E$203,"Negative") | C7: =IFERROR(B7/$B$5,0) | D7: Does it refuse what it should refuse. Roughly half the specification, deliberately: most of this product's CRITICAL defects were failures to refuse.
A8: Critical priority | B8: =COUNTIF(Test_Cases!$F$5:$F$203,"Critical") | C8: =IFERROR(B8/$B$5,0) | D8: Run these first on any build. They cover authentication, tenancy, durability, deletion, authorization and billing enforcement.
A9: High priority | B9: =COUNTIF(Test_Cases!$F$5:$F$203,"High") | C9: =IFERROR(B9/$B$5,0) | D9: Run on any release that touches the area.
A10: Executable in a sandbox today | B10: =COUNTIF(Test_Cases!$K$5:$K$203,"Yes*") | C10: =IFERROR(B10/$B$5,0) | D10: What a tester can work through right now with no tenant, no staging and no purchases.
A11: Partly executable (rendering or delivery needs a live client) | B11: =COUNTIF(Test_Cases!$K$5:$K$203,"Partial*") | C11: =IFERROR(B11/$B$5,0) | D11: The logic can be verified now; how it looks or whether it arrives cannot.
A12: Blocked on a live tenant, staging or a purchase | B12: =COUNTIF(Test_Cases!$K$5:$K$203,"No*") | C12: =IFERROR(B12/$B$5,0) | D12: Record these as Blocked, never as Pass. The Pending_Versions sheet says what unblocks each one.
A13: Not run | B13: =COUNTIF(Test_Cases!$L$5:$L$203,"Not run") | C13: =IFERROR(B13/$B$5,0) | D13: Awaiting the first human pass (RUN-002).
A14: Passed | B14: =COUNTIF(Test_Cases!$L$5:$L$203,"Pass") | C14: =IFERROR(B14/$B$5,0) | D14: Filled in by the tester, not by the author.
A15: Failed | B15: =COUNTIF(Test_Cases!$L$5:$L$203,"Fail") | C15: =IFERROR(B15/$B$5,0) | D15: Every failure should appear in Defect_Log with an id.
A16: Blocked | B16: =COUNTIF(Test_Cases!$L$5:$L$203,"Blocked") | C16: =IFERROR(B16/$B$5,0) | D16: Should converge on the blocked-on-access count above.
A18: CHECK — positive plus negative must equal the total | B18: =IF(B6+B7=B5,"OK","MISMATCH")
A19: CHECK — every release carries at least one case | B19: =IF(COUNTIF(RTM!$E$5:$E$45,0)=0,"OK","A RELEASE HAS NO CASES")
A21: AUTOMATED EVIDENCE BEHIND THIS ISSUE (not computed — stated, and reproducible with the commands named)
A22: Unit tier | B22: 68 suites / 555 tests, 100% statements, branches, functions and lines, zero pragmas | D22: npm ci && npm run build && npx jest --ci
A23: Integration tier | B23: 9 / 9 against real PostgreSQL 16 | D23: npm run test:integration with DATABASE_URL set
A24: Seam tier | B24: Production-seam wiring assertion green, and enforced again at boot | D24: npx jest tests/serve.test.ts tests/manifest.test.ts tests/runtimeWiring.test.ts tests/v046Closeout.test.ts
A25: Typecheck | B25: Clean under TypeScript strict | D25: npx tsc --noEmit
A26: Backup / restore drill | B26: PASS — RPO 0s (limit 900s), RTO 0s (limit 3600s), row counts matched | D26: npm run backup:drill with DATABASE_URL and RESTORE_URL set

Sheet Assumptions_Constraints
A1: ASSUMPTIONS AND CONSTRAINTS — what this specification takes for granted, and what it cannot prove
A2: HOW TO USE THIS SHEET — Read this before challenging a Pass or trusting one. It states the limits of the evidence rather than leaving them to be discovered. Column C says what would remove each limit.
A4: # | B4: Assumption or constraint | C4: What would remove it | D4: Consequence if it is wrong
A5: 1 | B5: A sandbox cannot prove in-client Teams behaviour. Card rendering, the TeamsJS handshake, the RSC consent screen and mobile layout are verifiable only inside a real Teams client. | C5: A Microsoft 365 dev tenant with the app sideloaded (SD226/SD228). | D5: Cases marked Partial could pass their logic and still look wrong or arrive nowhere. This is tracker risk R-S8 and it has been open since the first week.
A6: 2 | B6: Vendor contracts were implemented from documentation, not against live endpoints: Entra OpenID metadata, Bot Connector issuer and audience rules, Fulfillment API v2, Key Vault managed identity. | C6: Live verification against each endpoint (SD228, SD232, SD239, SD240). | D6: A contract read correctly still fails if the documentation is stale or incomplete. Tracker risk R-S12 exists because this has already happened twice, on the bot and tab seams.
A7: 3 | B7: Performance figures are measured on local PostgreSQL 16 in this sandbox, not on staging under load. | C7: A staging environment plus the k6 5x sweep (SD219/SD220). | D7: The 100k-record hydration inside the p95 budget is a real measurement on a real database, but not a measurement of the deployed system. LC-8 stays open until it is.
A8: 4 | B8: The automated suite proves execution, not correctness, and 100% coverage has repeatedly coexisted with critical defects in this product. | C8: Nothing removes this. Three tiers and adversarial review reduce it; mutation testing on the money and authentication modules would reduce it further and is not built. | D8: This is review finding P-017 and the reason this manual specification exists at all. A green suite is necessary and has never been sufficient here.
A9: 5 | B9: Test data is synthetic throughout. No customer data has ever been in this product. | C9: Nothing — and this should stay true until a signed pilot with a data agreement (SD247). | D9: Edge cases that only real data produces are unknown: unusual names, very large handovers, non-Latin text at volume, unexpected shift patterns.
A10: 6 | B10: One person wrote the code and the tests, and reviewed both. | C10: A second reviewer. The independent review V001 was exactly this and it found three CRITICALs in an hour of reading. | D10: A blind spot is shared between implementation and test. Every CRITICAL in the defect log was found by changing the question asked, not by better coding.
A11: 7 | B11: The expected results in this document were written by the author of the code. | C11: The first human pass (RUN-002), performed by someone who did not write it. | D11: An expected result can encode the same misunderstanding as the implementation. Expect RUN-002 to find at least one, and record it as a defect against this document.
A12: 8 | B12: Costs and lead times on Pending_Versions are market estimates, not quotes. | C12: Actual quotes from a pen-test vendor and an audit firm (SD234/SD237). | D12: Budget planning off these numbers could be materially wrong. The SOC 2 figure is the widest range and the most likely to surprise.

Sheet Glossary
A1: GLOSSARY — identifier prefixes and terms used across this document set
A2: HOW TO USE THIS SHEET — Look a prefix up here before assuming what it means. The prefix carries the origin of a finding, which is usually the most informative thing about it.
A4: Term / prefix | B4: Meaning | C4: Where it is used
A5: v001-v041 | B5: Tracker release ladder: one entry per working session. This document's Version_Detail sheet uses it. | C5: Tracker, this document
A6: v0.x.y | B6: Codebase semantic version, in package.json and the Teams manifest. Currently v0.14.0. | C6: Source zip, manifest
A7: v005-v046 | B7: Product workbook version ladder. Currently v046. | C7: Product workbook
A8: V001 | B8: Version of THIS document, in its file name and on the Version_Control sheet. | C8: This document
A9: ST-001..ST-100 | B9: The original 100 product backlog stories. | C9: Tracker, product workbook
A10: SD201..SD247 | B10: The 47 stories from the independent review's S13-S20 remediation plan. | C10: Tracker, product workbook
A11: F-001..F-074 | B11: Defects found by our own cold reviews, audits and rehearsals. | C11: REVIEW_PACK.md, Defect_Log
A12: P-001..P-020 | B12: Findings raised by independent review V001 on 16 Sep 2026. | C12: REVIEW_PACK.md, product workbook
A13: D-01..D-08 | B13: Decisions the independent review asked Senthil to make. | C13: REVIEW_PACK.md, product workbook
A14: VER-SD01..14 | B14: Findings from verification sweeps against vendor documentation. | C14: Tracker
A15: GAP-SD1..8 | B15: Artefact gaps: a promise in the manifest or a document with nothing implementing it. | C15: Tracker
... A28: Tier 1 / 2 / 3 | B28: The three parts of the D-SD7 gate: unit, real-store integration, production-seam wiring. | C28: This document, CI workflows

Sheet Signoff
A1: SIGN-OFF — who accepted what, and on what evidence
A2: HOW TO USE THIS SHEET — Sign only what you have checked. An unsigned row is more useful than a signed row that was not read: the whole point of this document set is that "it looks done" has been wrong six times in this product.
A4: # | B4: Statement being signed | C4: Evidence to check before signing | D4: Name | E4: Role | F4: Date | G4: Signed
A5: 1 | B5: The version history in this document matches the tracker and the delivered artefacts. | C5: Version_Detail against the tracker Version_Control sheet; the zip file name against the codebase version on the Cover sheet.
A6: 2 | B6: The reasons recorded for each release are accurate. | C6: Version_Detail column F for any three releases you remember, against the tracker log events.
A7: 3 | B7: The pending list is complete and each blocker is correctly stated. | C7: Pending_Versions in full. The test is whether anything is pending that is not listed, and whether any blocker is really effort in disguise.
A8: 4 | B8: The manual test specification is executable by someone who did not write the product. | C8: Pick five cases at random, including two negative ones, and try to run them from the steps alone.
A9: 5 | B9: The automated evidence claimed on Test_Summary is reproducible. | C9: Run the five commands on Test_Summary against the delivered zip and compare the numbers.
A10: 6 | B10: The limits stated in Assumptions_Constraints are the real limits. | C10: Assumptions_Constraints in full, against anything you believe the product has proven.
A11: 7 | B11: This document may be issued as the build evidence for a store submission or an audit question. | C11: Everything above, plus the Cover classification and retention lines.
A13: NOT SIGNED AND NOT CLAIMED: that the product works in a real Microsoft tenant, that anyone wants it, or that it will break even. Those are answered by SD226/SD228, SD244 and SD246/SD247 respectively, and none of them can be answered by this document.
