Workbook

Sheet Version_Control
A1: VERSION CONTROL — VoiceBridge Sprint Tracker & Traceability
A2: File naming: claude_v<NNN>_<proper file name>_YYYYMMDD_HHMI.
A3: Version | B3: Date/Time | C3: Author | D3: Change Description | E3: Status
A4: v001 | B4: 2026-09-10 23:00 | C4: Claude for Senthil/KP | D4: THIS FILE — Live execution tracker for VoiceBridge CTI (portfolio P02, Salesforce AppExchange). S1-S8 executed done-in-code under D13 from v006 workbook: 79 Done + 5 code-complete-pending-live of 100 stories; TypeScript codebase 20 Jest suites / 85 tests at 100% statements/branches/functions/lines; released with v007 product workbook. | E4: Released
A5: v002 | B5: 2026-09-11 08:46 | C5: Claude for Senthil/KP | D5: S9 REVIEW PREP executed done-in-code: WCAG AA automated audit (jest-axe) on new softphone+settings widget shells (ST-089 Done), backup/restore drill w/ sha256 integrity verify (ST-090 Done), chaos outage degradation + /status user comms (ST-091 Done), security evidence pack sandbox half (ST-068 In progress — pen-test vendor his), listing copy A/B + asset plan Drafted (ST-093/094). Plus portfolio live-sweep pack (12-step sweep: 8 auto + 4 operator, 30-min dev-org guide) and D18 packaging recommendation doc (hybrid-minimal 2GP shim). Codebase 24 suites / 101 tests at 100% coverage. 82 Done / 5 code-complete / 1 in progress / 2 drafted / 10 backlog = 352/399 pts engaged. | E5: Released
A6: v003 | B6: 2026-09-11 12:48 | C6: Claude for Senthil/KP | D6: S10 REVIEW REMEDIATION executed done-in-code: help center 15 articles + search, built-in chat SLA engine (<4 business hrs, vendor deferred), status page + incident template, pricing + trust pages from single sources — all Done; demo-data mode Code-complete (video needs live capture); dry-run engine READY 11/11 automated + REVIEW_PACK.md, ST-097 In progress pending external reviewer sign-off (DR-12). Codebase 30 suites / 131 tests at 100% zero pragmas. 87 Done / 6 code-complete / 2 in progress / 2 drafted / 3 backlog (373/399 pts engaged). | E6: Released
A7: v004 | B7: 2026-09-11 13:32 | C7: Claude for Senthil/KP | D7: CODE PHASE COMPLETE. S11+S12 codeable scope executed: executable launch-day runbook with rollback triggers wired to real p95 budgets (ST-098 Done); 10-slot design-partner tracker with stale-nudge + honest exit math (ST-100 CC — outreach his); listing SEO iteration engine with thin-data guards (ST-099 CC — needs post-listing data). Backlog ZERO. Codebase 33 suites / 150 tests at 100% zero pragmas. Final position: 88 Done / 8 code-complete / 2 in progress / 2 drafted — 380/399 pts; remaining 19 pts all Senthil-side. | E7: Released
A8: v005 | B8: 2026-09-11 15:26 | C8: Claude for Senthil/KP | D8: POST-CODE-PHASE GAP CLOSED: D18 shim package source built — sfdx project with CallCenter Open CTI definition, 3 permission sets generated from the enforced role matrix (drift-tested), esbuild softphone static resource from a new functional dependency-injected Open CTI adapter (click-to-dial, screen pop, activity logging with degraded fallback, status polling) tested in jsdom against mocked sforce.opencti. Dev-org guide O2 now turnkey (deploy + assign, zero authoring). 35 suites / 162 tests at 100% zero pragmas. Story position unchanged (88/8/2/2 — honest: infrastructure, not story flips). | E8: Released
A9: v006 | B9: 2026-09-11 22:09 | C9: Claude for Senthil/KP | D9: COLD-REVIEW PASS 1 (sibling pattern): 7 defects fixed with pinned regressions — retention-sweep PII leak, missing payment-recovery path, unenforced trial expiry, unguarded invoice mutation, unbounded ledgers → FIFO 10k, NO-OP production backoff sleep, and read-only status enforced nowhere → new billing write-gate across all mutating feature ops. 2 observations (CSV quoting, half-open probes) logged for disposition in the new Review_Findings sheet. 36 suites / 176 tests at 100% zero pragmas. Story position unchanged (88/8/2/2, 380/399) — defects lived inside Done stories; fixes keep them Done with corrected behaviour. | E9: Released
A10: v007 | B10: 2026-09-11 22:34 | C10: Claude for Senthil/KP | D10: COLD REVIEW COMPLETE + EXTERNAL VERIFICATION SWEEP. Pass 2 over the ~28 modules pass 1 never opened: 13 defects fixed with pinned regressions (F-V08..F-V20) + 2 observations logged. Verification sweep vs live Open CTI Lightning docs found 2 LIVE-BLOCKING defects (VER-V01 opencti_min.js never loaded — softphone dead in-org with no error; VER-V02 enableClickToDial never called) plus VER-V03/V04; artifact-gap audit clean apart from the missing /log route (F-V10). 39 suites / 217 tests at 100% zero pragmas. Story position unchanged (88/8/2/2, 380/399) — correctness release, no new stories. | E10: Released
A11: v008 | B11: 2026-09-13 10:39 | C11: Claude for Senthil/KP | D11: SCREEN SURFACE + OAUTH COMPLIANCE RELEASE (code v0.14.0). (1) GAP-V2 closed: Screens_Wireframes specifies 9 screens and only 2 existed while 5 P0 stories claimed an end-to-end LWC surface — the 7 missing screens built as typed view-models + accessible renderer (src/views.ts), wired to the real modules via src/screenData.ts and served at /ui/:orgId[/:screenId?format=html]; WCAG audit widened from 2 screens to all 9 in populated AND empty states. (2) EXTERNAL VERIFICATION SWEEP #2 vs live Salesforce ISV docs found VER-V06 (new Connected Apps cannot be created from Spring 26 — the 30-min guide step 2 was unrunnable; ECA everywhere now) and VER-V07/V08/V09 (four OAuth controls mandatory since 11 May 2026, enforceable by interoperability suspension since 25 Jun 2026: PKCE + state, rotation anomaly telemetry, 30-day idle timeout, refresh IP allowlist). (3) VER-V10 verified: AppExchange Checkout is NOT mandatory — ISVforce+COA alternative, 15%/25% rev share, $999 review fee, ~$150 listing — raised as D-V3. (4) F-V21 logged UNFIXED for disposition: identity is caller-declared. 41 suites / 274 tests at 100% zero pragmas. | E11: Released
A12: v009 | B12: 2026-09-13 10:57 | C12: Claude for Senthil/KP | D12: ARTIFACT-GAP AUDIT (code v0.15.0) — sibling OnCall/EngageOS pattern applied to VoiceBridge. 5 gaps, 2 CRITICAL. GAP-V3: NO PROCESS and NO PRODUCTION OAUTH GATEWAY existed — createApp() had never been called by anything, and the only OAuthGateway implementations were test doubles, so the ECA callback, the sweep /health probe, the k6 harness and the softphone's /dial and /log posts all addressed a server that could not be started; the 30-minute dev-org guide was unrunnable past step 3. GAP-V4: NO SCHEMA behind a published 30-day retention policy, the ST-090 backup/restore drill and sweep check A5 — all against an in-memory Map. GAP-V5: CI pinned Node 20, end-of-life since April 2026. All fixed: server.ts + main.ts + npm start, SfOAuthGateway against the real token endpoint, 5 ordered migrations + npm run migrate with order/re-run/checksum-drift guards, Node 22. R-V11 logged honestly — the migrations describe the store but the runtime is STILL in-memory. 42 suites / 296 tests at 100% zero pragmas. | E12: Released
A13: v010 | B13: 2026-09-13 11:14 | C13: Claude for Senthil/KP | D13: COLD-REVIEW PASS 3 + IDENTITY BOUNDARY (code v0.16.0). Pass 3 targeted the surfaces v0.14.0 and v0.15.0 added, on the sibling principle that new surfaces inherit old blind spots — and it found one I introduced: F-V23, the /ui routes shipped last release taking the org straight from the URL with no identity check, so anyone who knew or guessed an org id could read that org's billing, invoices, analytics and support queue. Fixing it required the boundary F-V21 has been waiting for, so both are closed here: HMAC-signed sessions minted only at the install callback, identity never read from body or URL, a claim that disagrees with the session refused as forgery, and 401/403 separated from the blanket 400 every failure used to return. Also F-V24 (public /oauth/start could grow the PKCE map without bound — OBS-V5 escalated, now TTL-swept and FIFO-capped), F-V25 (no timeout on the token endpoint), F-V26 (drain waited forever on open connections) and F-V26b (the listening log printed the requested port, not the bound one). 43 suites / 318 tests at 100% zero pragmas. | E13: Released
A14: v011 | B14: 2026-09-13 11:36 | C14: Claude for Senthil/KP | D14: R-V11 STAGE 1 — ASYNC REPOSITORY CONTRACT (code v0.17.0). Measured first: 91 store call sites across 20 modules and 277 store/await lines in the tests, so a single-pass conversion is a broken build for hours and a coverage gate that cannot run. Staged instead, green at every step. Stage 1 ships the Repository interface, InMemoryRepository, PgRepository against the v0.15.0 migrations plus a new 006_sequences.sql, and — the load-bearing part — a conformance suite that runs the SAME behavioural tests against BOTH implementations, which is what makes stages 2..N a swap rather than a leap. Postgres earns two things the in-memory version got free: the F-V05 FIFO cap enforced in SQL with drops counted so a cap survives restart, and F-V19 nextSeq as one atomic INSERT..ON CONFLICT..RETURNING because read-then-write would give two instances the same id. docs/r-v11-plan.md fixes the conversion order (leaf modules first, permissions its own stage, app.ts last). NOT WIRED: createApp() still constructs the sync Store, so R-V11 stays OPEN — stage 1 is not persistence, exactly as db/migrations/ was not. New operator step O6: run the conformance suite against live Postgres, because a double proves we send the right statements, not that Postgres does the right thing with them. 44 suites / 340 tests at 100% zero pragmas. | E14: Released
... A27: v024 | B27: 2026-09-20 10:45 | C27: Claude for Senthil/KP | D27: PERPLEXITY REVIEW V001 INCORPORATED + EXECUTED (code v0.28.0, voicebridge-cti-codebase-20260920_1045.zip). Independent second review (Perplexity, 16 Sep 13:53 BST; verdict HOLD then RE-PLATFORM OR PIVOT; enterprise readiness ~35-40%) found six defects nobody had recorded (F-P01..F-P06) and one strategic fact: Salesforce Open CTI — the entire in-org surface — is in maintenance mode, EoL 28 Feb 2028, closed to new Agentforce Service orgs (verified 20 Sep against help.salesforce.com 005306437; R-V21 CRITICAL; D18 OVERTAKEN, D-V2 DISSOLVED). Direction from Senthil (20 Sep 10:45): enterprise grade, do not shrink scope, keep everything in the tracker. Executed: ALL of S14 (VB-E-010..017 — widget served + VB_CONFIG injected + adapter moved from static resource to host; AES-256-GCM token encryption with key ring + rotation sweep; CSP/HSTS/nosniff/body cap/inbound timeout/request ids; per-ip + per-org rate limits on a shared store proven across two instances; symmetric evidence manifest with testFiles[] and CI/deploy calling evidence:check; claim-to-test registry gate over 34 published claims; Express 5 + qs>=6.16 → 0 advisories, Node 22), the codeable halves of S19-S20 (updateWhere + detached copies on both stores; leader-elected outbox worker with backoff/dead-letter/metrics; transactional counted caps closing R-V15; structured JSON logs, RED metrics, /metrics, error sink, 500-not-400 for internal faults; SLO error budget + burn-rate alert rules; real blue/green deploy.yml + script with migration/health gates and auto-rollback; DR drill script), S25-S26 (Postgres RLS with per-transaction tenant context + superuser refusal + CI smoke as an app role; hash-chained append-only audit with /audit/verify; session jti/revocation/epoch, logout, revoke-all, role assignment revoking sessions, TTL 7→1 day; contacts from config, DPA template), and the provider-independent parts of S15-S16 (E.164 + per-country rules + blocklist + DNC seam before any dial; SOSL phone-index matching with ambiguity never resolved by guessing). FOUR MORE DEFECTS FOUND BY THE WORK ITSELF: F-V31 (dialer/cadence/supportChat/designPartners mutated detached copies — on Postgres no call ever ended), F-V32 (coaching.snapshot stored a Promise — '{}' in production), F-V33 (the CI scripts type-check step could never have passed), F-V34 (evidence gate false positive on build output). WhatsApp claim WITHDRAWN from HC-05 pending D-V6; listing copy D-V6-gated. NOT built: provider adapter (D-V5), WhatsApp (D-V6), Partner Telephony package (D-V8 + dev org), AI layer (needs recordings), pen test/SOC 2/DPA execution (vendor/legal). 58 suites / 613 tests at 100% ×4, zero pragmas, 0 advisories, evidence bound to package hash f0f4eb4ab67d, zip verified from a clean extraction (build → typecheck:scripts → evidence:check → suite). New sheet Enhancement_Plan carries S13-S29 (VB-E-001..105) with live status. Story position held at 96/100 pending D-V4 (reviewer and this release both recommend (a) reclassify → 76/100). G-06 still REJECT; new G-07 (Perplexity) HOLD. | E27: Released
A28: v025 | D28: PLANNED: opens on the S13 decision gate — D-V8 strategy ruling (A/B/C), D-V9 Open CTI confirmation (partner case), D-V5 provider, D-V6 WhatsApp, D-V7 model rebuild (Financial_Model_v2), D-V4 reclassification — or on operator steps O6/O7/O7b/O9/O10 producing live evidence. | E28: Planned

Sheet Sprint_Tracker_Log
A1: SPRINT TRACKER LOG — every execution event, newest last
A2: ID | B2: Date/Time | C2: Sprint | D2: What happened | E2: Refs | F2: State changes | G2: Blockers | H2: Next
A3: E001 | B3: 2026-09-10 23:00 | C3: — | D3: D17 RECORDED — Senthil instruction 23:00: 'continue work as per sprint... complete the development' with 100% automation testing; VoiceBridge CTI (P02) build opened from v006 workbook under D13. Ninth concurrent build; D15 (sequencing mode) still open. | E3: D13,D15,D17 | F3: VoiceBridge S1 opened | G3: None | H3: S1 build
A4: E002 | B4: 2026-09-10 23:00 | C4: S1 | D4: S1 FOUNDATION BUILT (TypeScript/Node/Express per v006 stack assumption, D18): config w/ secrets fail-fast + Hyperforce region, typed Store repository (R-V4), Connected-App OAuth install→welcome, uninstall token-wipe + retention-scheduled deletion sweep, rotation-safe token refresh, install source attribution. | E4: ST-051,ST-052,ST-055,ST-056 | F4: 4 S1 stories Done-in-code (13 pts) | G4: Live dev-org install = Senthil (ISV agreement + Connected App) | H4: E003
A5: E003 | B5: 2026-09-10 23:00 | C5: S2 | D5: S2 CORE PT-1 — click-to-dial dial state machine (dialing→connected→ended/failed, outcome capture, E.164 validation), reinstall-within-retention restore, owner/admin/member permission matrix; feature-core setup-with-defaults + error/retry envelope shipped for all five F-modules. | E5: ST-001..004,ST-053,ST-054 | F5: 6 S2 stories Done (29 pts) | G5: None | H5: E004
A6: E004 | B6: 2026-09-10 23:00 | C6: S3 | D6: S3 CORE PT-2 + F2 START — F1 completed (utility-bar surface, metrics, permissions+audit, pause-no-data-loss, import, notifications); auto call/WhatsApp logging built: provider-event ingestion deduped by externalId → activity records, contact threads; D13 coverage gate story closed (100% supersedes >=70%). | E6: ST-005..014,ST-085 | F6: 11 S3 stories Done (47 pts) | G6: None | H6: E005
A7: E005 | B7: 2026-09-10 23:00 | C7: S4 | D7: S4 MVP LOOP — F2 completed; activation funnel (install→setup→aha→habit), release-tagged error tracking + spike alert, E2E smoke suite wired as CI deploy gate. MVP loop (install→setup→dial→auto-log) usable end-to-end in E2E harness. | E7: ST-015..020,ST-071,ST-072,ST-086 | F7: 9 S4 stories Done (34 pts) | G7: None | H7: E006
A8: E006 | B8: 2026-09-10 23:00 | C8: S5 | D8: S5 CADENCE + ALPHA HARDENING — cadence/sequence lite: step sequences w/ cumulative delays, enrollment, due-step engine, advance-to-complete; first-run checklist reaching aha at 3/4 steps; teaching empty states on all surfaces. | E8: ST-021..030,ST-078,ST-079 | F8: 12 S5 stories Done (50 pts) | G8: Internal dogfood needs live org | H8: E007
A9: E007 | B9: 2026-09-10 23:00 | C9: S6 | D9: S6 BILLING + COACHING — coaching scorecards (connect rate, avg duration, leaderboard, zero-guards); 14-day no-card trial + banner; mid-cycle proration. ST-059 provider abstraction (AppExchange Checkout | Stripe fallback) CODE-COMPLETE — live Checkout wiring needs ISV agreement. | E9: ST-031..040,ST-057..059 | F9: 12 Done + 1 code-complete (60 pts) | G9: ISV agreement = Senthil | H9: E008
A10: E008 | B10: 2026-09-10 23:00 | C10: S7 | D10: S7 BILLING EDGE + TRUST — dunning (7d grace, 3 emails, read-only), plan limits w/ 80%/100% prompts, GST/VAT invoices, cancellation save-offer + exit survey; least-privilege scope map doc (scopes 1:1 features). | E10: ST-060..064 | F10: 5 S7 stories Done (15 pts) | G10: None | H10: E009
A11: E009 | B11: 2026-09-10 23:00 | C11: S8 | D11: S8 FLOW PACK + SCALE — Flow actions pack (StartCall / EnrollInCadence / SendNotification invocables, validated inputs, run ledger incl. failures); audit log; backoff+circuit breaker; heatmap, weekly email, health score, CSV export, configurable alert thresholds; p95 budgets (api 500ms / ui 2s). ST-082 review-ask + ST-069 export/delete-my-data pulled early. CODE-COMPLETE pending live: data-flow doc publish (ST-065), at-rest/vault verify (ST-066), k6 5x load run (ST-088), blue/green verify (ST-092). | E11: ST-041..050,ST-065..067,ST-069,ST-070,ST-073..077,ST-082,ST-087,ST-088,ST-092 | F11: 18 Done + 4 code-complete (87 pts) + 2 pulled-early stories | G11: Live infra = Senthil | H11: E010
A12: E010 | B12: 2026-09-10 23:00 | C12: — | D12: D13 TEST GATE MET — 20 Jest suites / 85 tests, coverage 100% statements/branches/functions/lines (jest coverageThreshold 100x4, CI-enforced); tsc --noEmit clean; E2E smoke + blue/green jobs in ci.yml; k6 harness at load/k6-load.js. | E12: D13 | F12: Evidence in Traceability col K | G12: None | H12: E011
A13: E011 | B13: 2026-09-10 23:00 | C13: — | D13: RELEASE — this tracker v001 + product workbook v007 (Full_Backlog statuses updated; Sprint_Board Done counts now live COUNTIFS; tracker sheets embedded). Next sprint S9 (marketplace review prep) blocked on live-org items. | E13: D17 | F13: v001 + v007 released | G13: S1-live items; D15; D18 | H13: v002
... A133: E131 | B133: 2026-09-20 10:45 | C133: S14 | D133: D13 GATE MET + PACKAGED + VERIFIED FROM THE ZIP. 58 suites / 613 tests, 100% statements, branches, functions and lines, zero pragmas, 0 production advisories at any severity. Evidence regenerated and bound: RUN_STAMP 2026-09-20T11:02:23Z, package hash f0f4eb4ab67d. voicebridge-cti-codebase-20260920_1045.zip extracted to a clean directory: npm ci → npm run build → npm run typecheck:scripts → npm run evidence:check → full suite, all green. REVIEW_PACK addendum lists the ten things a second reviewer should try. Story position unchanged at 96/100 on purpose (D-V4). G-06 stays REJECT (VB-CR-005 telephony half, VB-CR-008); G-07 (Perplexity) opens at HOLD. | E133: D13,VB-CR-009,G-06,G-07 | F133: v0.28.0 released and verified | G133: D-V4..D-V9 | H133: v025

Sheet Decisions
A1: DECISIONS (tracker scope)
A2: ID | B2: Decision | C2: Rationale | D2: Decided by | E2: Status
A3: D13 | B3: (Portfolio-wide) Discovery interviews parked; development proceeds with 100% automation test coverage on all code (supersedes >=70% gate). | C3: Senthil 10 Sep 20:45; applied to VoiceBridge per 23:00 instruction. | D3: Senthil | E3: LOCKED
A4: D15 | B4: Sequencing mode — parallel builds vs WIN-order swap — while rank-1 (RevRescue) completion gate unmet. | C4: Nine products now built done-in-code same evening; R1 serial rule formally intact until ratified. | D4: Senthil (mode ratification pending) | E4: OPEN — pick (a) or (b)
A5: D17 | B5: VoiceBridge (P02) build opened 10 Sep 23:00 from v006 workbook while rank-1 gate unmet. | C5: Senthil instruction 'continue work as per sprint... complete the development'; ninth concurrent build. | D5: Senthil | E5: LOCKED
A6: D18 | B6: Stack = TypeScript/Node/Express per v006 ReadMe stack assumption. FLAG: AppExchange packaging decision needed — Open CTI softphone adapter is JS in-org, but security review scope depends on managed-package vs connected-app-only architecture (Launch #3/#4). | C6: Follows workbook; provider-agnostic dial core keeps both paths open; decide with ISV onboarding. | D6: Claude — recommendation documented (docs/d18-packaging-decision.md): hybrid-minimal 2GP shim package, zero Apex | E6: OVERTAKEN (20 Sep, R-V21) — Open CTI in maintenance mode, EoL 28 Feb 2028; the packaging question re-opens under D-V8. Kept for the record; shim now = CallCenter + Task field + permsets (adapter served from host, F-P01)
A7: D-V1 | B7: Chat vendor decision deferred: built-in SLA engine (Mon-Fri 9-18 IST, 4-business-hr first response) ships as-is; vendor swap is config-level later. | C7: TeleField S10 precedent; avoids a procurement blocker on the listing path. | D7: Claude — flagged for Senthil | E7: OPEN for ratification
A8: D-V2 | B8: Surface architecture — LWC bundles in the package vs static-resource/web surface only. | C8: Five P0 story texts demand an LWC surface; D18's hybrid-minimal recommendation forbids one to keep security-review scope small. GAP-V2 forced the contradiction into the open. The 7 screens built in v0.14.0 are valid under either ruling. | D8: Senthil | E8: DISSOLVED (20 Sep, R-V21) — neither LWC nor static resource if the Open CTI surface itself retires; the 7 screens built in v0.14.0 are valid under any option
A9: D-V3 | B9: Billing route — AppExchange Checkout vs ISVforce licence + Channel Order Application (COA). | C9: VER-V10 verified Checkout is optional, not mandatory. Checkout automates licensing with the LMA and collects revenue share at purchase; ISVforce+COA means billing on your own paper with every order reported to Salesforce. 15% rev share either way (25% OEM). ST-059's provider abstraction already supports both. | D9: Senthil | E9: OPEN — decides LC-1 urgency and the pricing page copy
A10: D-V4 | B10: Story-status semantics after external review V001: do ST-001..020 stay "Done" or move to "Prototype (code-only)" until a telephony provider and Salesforce write-back exist? | C10: VB-CR-005/008: the modules are built, tested and correct as state machines, but the story text promises click-to-dial and automatic logging, and neither reaches an external system. Keeping "Done" reads as product readiness; moving them is honest and moves the counted position 96/100 → 76/100 (380 → ~310 pts). | 20 Sep: the Perplexity review (VB-E-007) and this release both recommend (a) reclassify to "Code-complete (unproven)"; F-P01 showed the surface those stories promise was not even served. The DoD clause is recorded in Gate_Checklist regardless. | D10: Senthil | E10: OPEN — (a) reclassify now (RECOMMENDED by both reviewers; 96/100 → 76/100), (b) keep Done and rely on the readiness column
A11: D-V5 | B11: Telephony provider for the real dial path (closes VB-CR-005 half 1). | C11: A provider must be named before RM-04 can be built: Twilio (global, strongest docs, dearest), Exotel or Plivo (India-first, fits the mid-market ICP and IPBS experience), or Service Cloud Voice BYOT (no separate provider contract but ties us to the platform we are positioned against, per R-V2). Choice sets credentials, webhook auth, per-minute cost and the pricing floor. | 20 Sep (VB-E-003): decide on landed cost per minute for the target geography, not documentation quality — Plivo ₹0.38/min India vs Twilio ~₹3.50-5.00/min moves gross margin an order of magnitude on a $29 seat. The DNC registry vendor usually comes with the carrier. Not needed at all under option (B). | D11: Senthil | E11: OPEN — blocks RM-04
A12: D-V6 | B12: WhatsApp: build the Meta Cloud API integration now, or withdraw the claim until it exists? | C12: VB-CR-008: help article HC-05, the data-flow doc and the listing copy describe linking a WhatsApp Business number; the code only stores a caller-supplied event with channel=whatsapp. EngageOS already carries a working Cloud API pattern (opt-in ledger, 24h session window, signature verify) that could be ported. Withdrawing the claim is a one-day copy change; building is the larger half of RM-05. | 20 Sep: the reviewer recommends BUILD and lead with it (Salesforce's own path = $165 Service Cloud + $75 Digital Engagement per user/month). The unbacked claim is already WITHDRAWN from HC-05 and the listing copy is gated (VB-E-016), so "publish it unbuilt" is no longer possible either way. | D12: Senthil | E12: OPEN — blocks RM-05
A13: D-V7 | B13: Financial model response to VB-CR-014 (no breakeven inside 18 months, ≈-$750k cumulative). | C13: The model assumes $40k month-1 team cost growing 3%/mo against 4 pilots/mo and $600 ARPU. Either the cost base is wrong for a solo build, or the plan needs a stated funding requirement. Needed before RM-09 can produce base/downside/upside scenarios with a named cash-minimum month. | 20 Sep (F-P06/VB-E-005): the $600 ARPU contradicts the 50-500 seat ICP at $29/seat by 2.5-5x; no per-minute cost line exists; PLAN_SEAT_LIMIT.scale=500 equals the ICP ceiling with no enterprise/annual tier. Financial_Model_v2 = base/downside/upside, per-minute cost, funding requirement, cash-minimum month, solo-build variant, 5-9 month listing lag. | D13: Senthil | E13: OPEN — blocks RM-09
... A16: D-V10 | B16: SSO (SAML/OIDC) + SCIM (VB-E-083): is there a surface outside the Salesforce frame that needs its own identity? Today the only one is /ui/* behind the install session minted by Salesforce OAuth. Options: (a) keep it, no SSO needed — document the smaller attack surface; (b) add SSO/SCIM for a standalone admin console. | C16: The review's own framing: "if there is no such surface, delete the standalone paths so the claim surface shrinks". Recommendation (a) until a customer asks. | D16: Senthil | E16: OPEN — low urgency; document either way before LC-3

Sheet Build_Board
A1: BUILD BOARD S1-S8 — done-in-code under D13; exits pending live org marked
A2: Codebase: voicebridge-cti (TypeScript/Node/Express 5) — 57 src modules, 58 test suites / 613 tests @ 100% coverage ×4, zero pragmas, 0 advisories; CI (test → evidence:check → typecheck:scripts → migration-smoke + RLS/audit checks → security → e2e → workflow-lint) + deploy.yml blue/green
A3: ID | B3: Item | C3: Story refs | D3: Points | E3: Owner | F3: Status | G3: Notes / Evidence
A4: S1-01 | B4: Repo scaffold + CI with 100% coverage gate (D13) | C4: — | D4: 2 | E4: Claude | F4: Done | G4: jest coverageThreshold 100x4; .github/workflows/ci.yml test→e2e-smoke→deploy-blue-green. E010
A5: S1-02 | B5: Env config: secrets fail-fast, retention, Hyperforce region | C5: — | D5: 1 | E5: Claude | F5: Done | G5: src/config.ts — 4 tests; region surfaced at /health for residency statement (Launch #6).
A6: S1-03 | B6: Typed Store repository (Postgres adapter point) | C6: — | D6: 2 | E6: Claude | F6: Done | G6: src/store.ts — R-V4 constraint logged; domain code storage-agnostic.
A7: S1-04 | B7: Connected-App OAuth install → welcome state | C7: ST-051 | D7: 5 | E7: Claude | F7: Done | G7: DONE-IN-CODE — src/sfAuth.ts exchangeCode + src/lifecycle.ts install; E2E covers <2min path.
A8: S1-05 | B8: Uninstall: token wipe + deletion schedule + sweep | C8: ST-052 | D8: 3 | E8: Claude | F8: Done | G8: src/lifecycle.ts handleUninstall + retention sweep — 4 tests incl. skip/due/deleted branches.
A9: S1-06 | B9: Rotation-safe token refresh | C9: ST-055 | D9: 3 | E9: Claude | F9: Done | G9: src/sfAuth.ts refreshTokens persists rotated refresh token; keeps old when not rotated.
A10: S1-07 | B10: Install telemetry source attribution | C10: ST-056 | D10: 2 | E10: Claude | F10: Done | G10: src/lifecycle.ts + analytics install event; listing/search/referral captured.
A11: S2-01 | B11: Click-to-dial state machine + softphone core | C11: ST-001..004 | D11: 21 | E11: Claude | F11: Done | G11: src/dialer.ts — E.164 validation, dialing→connected→ended/failed, outcome defaults, retry envelopes.
A12: S2-02 | B12: Reinstall restore + permission matrix | C12: ST-053,ST-054 | D12: 8 | E12: Claude | F12: Done | G12: src/lifecycle.ts retention-window restore; src/permissions.ts owner/admin/member enforced across ops.
A13: S3-01 | B13: F1 completion: surfaces, metrics, RBAC+audit, pause, import, notify | C13: ST-005..010 | D13: 21 | E13: Claude | F13: Done | G13: featureCore.ts shared machinery + dialer specialisation; utility-bar surface flag.
A14: S3-02 | B14: Auto call/WhatsApp logging start + coverage gate story | C14: ST-011..014,ST-085 | D14: 26 | E14: Claude | F14: Done | G14: src/callLogger.ts dedupe-by-externalId ingestion; D13 100% gate closes ST-085.
... A41: PKG-03 | B41: Functional Open CTI softphone adapter + bundle | C41: R-V5,ST-089 | D41: 0 | E41: Claude | F41: Done | G41: src/softphoneAdapter.ts (DI, jsdom-tested vs mocked sforce.opencti); esbuild static resource; HTML bootstrap; live click-to-dial verify = O2.
A42: RV2-01 | B42: Cold-review pass 2 — 13 defects fixed with pinned regressions | C42: F-V08..F-V20 | D42: 0 | E42: Claude | F42: Done | G42: test/coldReview2.test.ts — 27 regressions; see Review_Findings
A43: RV2-02 | B43: External verification sweep vs live Open CTI Lightning docs | C43: VER-V01..V05 | D43: 0 | E43: Claude | F43: Done | G43: test/verificationSweep.test.ts; 2 live-blocking defects fixed before the dev-org day
A44: RV2-03 | B44: Artifact-gap audit + missing /log route built | C44: GAP-V1,F-V10 | D44: 0 | E44: Claude | F44: Done | G44: test/logRoute.test.ts — 5 supertest regressions; all other referenced artifacts verified present
A45: V14-01 | B45: 7 missing screens as view-models + accessible renderer | C45: GAP-V2,ST-079 | D45: 0 | E45: Claude | F45: Done | G45: src/views.ts — 15 tests; every screen has populated + empty state; output escaped; single h1 + labelled regions
A46: V14-02 | B46: Screen adapter over the live store/modules + /ui routes | C46: GAP-V2 | D46: 0 | E46: Claude | F46: Done | G46: src/screenData.ts + app.ts /ui/:orgId and /ui/:orgId/:screenId?format=html — 9 tests incl. 404 path
A47: V14-03 | B47: WCAG audit widened from 2 screens to all 9 | C47: ST-089 | D47: 0 | E47: Claude | F47: Done | G47: test/a11y.test.ts — 18 assertions across populated + empty states; ST-089 stays In progress pending live-UI audit
A48: V14-04 | B48: ECA migration across code, docs, sweep and guide | C48: VER-V06 | D48: 0 | E48: Claude | F48: Done | G48: config/sfAuth/sweepChecks/dev-org guide/live-sweep/D18/data-flow — 'New Connected App' no longer exists in Setup
A49: V14-05 | B49: PKCE (S256) + single-use state on the install flow | C49: VER-V07 | D49: 0 | E49: Claude | F49: Done | G49: src/sfAuth.ts beginInstall/completeInstall + GET /oauth/start — 6 regressions incl. replay, forged state, expiry
A50: V14-06 | B50: Refresh-token idle timeout + rotation anomaly telemetry | C50: VER-V08 | D50: 0 | E50: Claude | F50: Done | G50: 30-day ceiling enforced in loadConfig; idle token asks for reconnect without calling the platform; NO_ROTATION recorded
A51: V14-07 | B51: Refresh-token IP allowlist config + sweep checks A9/A10 + operator O5 | C51: VER-V09 | D51: 0 | E51: Claude | F51: Done | G51: src/config.ts + src/sweepChecks.ts; sweep is now 10 auto + 5 operator steps
A52: V14-08 | B52: docs/oauth-security-controls.md + dry-run check DR-16 | C52: VER-V06..V09 | D52: 0 | E52: Claude | F52: Done | G52: Compliance artefact, operator sequence, and the warning that Review Controls attestation LOCKS the config
A53: V15-01 | B53: Server entry point: start(), PORT, graceful drain, npm start | C53: GAP-V3 | D53: 0 | E53: Claude | F53: Done | G53: src/server.ts + src/main.ts — listens, logs, drains on SIGTERM/SIGINT; tested against a real bound port
... A109: V28-19 | B109: Evidence regenerated and bound (f0f4eb4ab67d); zip verified from a clean extraction | C109: D13,VB-CR-009 | D109: 0 | E109: Claude | F109: Done | G109: 58 suites / 613 tests, 100% ×4, zero pragmas, 0 advisories

Sheet Traceability_Matrix
A1: TRACEABILITY MATRIX — 100 stories: module → epic → story → sprint → verification → status → evidence
A2: Source: v006 Full_Backlog (single source of truth). Status values: Done | Code-complete (pending live) | Backlog. | L2: Status column J is unchanged pending D-V4 (both reviewers recommend (a)); this column names the findings that bear on each story block. 20 Sep: Perplexity review V001 (F-P01..F-P06) and v0.28.0 remediation added.
A3: Story ID | B3: Epic | C3: Module / feature | D3: Story | E3: Points | F3: Priority | G3: Sprint | H3: Primary screen | I3: Verification | J3: Status | K3: Evidence | L3: External review V001 readiness (13 Sep)
A4: ST-001 | B4: F1 | C4: Click-to-dial + softphone | D4: As a RevOps lead, I can set up Click-to-dial + softphone with sensible defaults in one screen | E4: 5 | F4: P0 | G4: S2 | H4: SCR-3 Call workspace | I4: Automated (Jest, 100% cov) + E2E smoke | J4: Done | K4: src/dialer.ts.setup defaults + featureCore — dialer.test.ts | L4: PROTOTYPE (code-only), NOW LABELLED AS SUCH IN THE PRODUCT — VB-CR-005 telephony half: no adapter places the call (D-V5), so every call is marked simulated:true and the panel says so rather than reading "Ringing". The seam and the adapter contract exist (src/telephony.ts, docs/telephony-provider-decision.md). D-V4 records whether these stay counted as Done. | F-P01 (20 Sep): the softphone page those stories promise was NEVER SERVED — fixed in v0.28.0 (src/widget.ts, boot test); pre-dial E.164/blocklist/DNC refusal added (VB-E-025). Still no adapter (D-V5). R-V21: the Open CTI surface itself retires 28 Feb 2028 (D-V8). Reviewer + v0.28.0 recommend D-V4(a) → Code-complete (unproven).
A5: ST-002 | B5: F1 | C5: Click-to-dial + softphone | D5: As a RevOps lead, the Click-to-dial + softphone happy path completes without documentation | E5: 8 | F5: P0 | G5: S2 | H5: SCR-3 Call workspace | I5: Automated (Jest, 100% cov) + E2E smoke | J5: Done | K5: src/dialer.ts happy-path state machine — dialer.test.ts + app.e2e.test.ts | L5: PROTOTYPE (code-only), NOW LABELLED AS SUCH IN THE PRODUCT — VB-CR-005 telephony half: no adapter places the call (D-V5), so every call is marked simulated:true and the panel says so rather than reading "Ringing". The seam and the adapter contract exist (src/telephony.ts, docs/telephony-provider-decision.md). D-V4 records whether these stay counted as Done. | F-P01 (20 Sep): the softphone page those stories promise was NEVER SERVED — fixed in v0.28.0 (src/widget.ts, boot test); pre-dial E.164/blocklist/DNC refusal added (VB-E-025). Still no adapter (D-V5). R-V21: the Open CTI surface itself retires 28 Feb 2028 (D-V8). Reviewer + v0.28.0 recommend D-V4(a) → Code-complete (unproven).
A6: ST-003 | B6: F1 | C6: Click-to-dial + softphone | D6: As a Sales leader, I can customise Click-to-dial + softphone rules/conditions for my workflow | E6: 5 | F6: P1 | G6: S2 | H6: SCR-3 Call workspace | I6: Automated (Jest, 100% cov) + E2E smoke | J6: Done | K6: featureCore.customise rules merge — featureCore.test.ts | L6: PROTOTYPE (code-only), NOW LABELLED AS SUCH IN THE PRODUCT — VB-CR-005 telephony half: no adapter places the call (D-V5), so every call is marked simulated:true and the panel says so rather than reading "Ringing". The seam and the adapter contract exist (src/telephony.ts, docs/telephony-provider-decision.md). D-V4 records whether these stay counted as Done. | F-P01 (20 Sep): the softphone page those stories promise was NEVER SERVED — fixed in v0.28.0 (src/widget.ts, boot test); pre-dial E.164/blocklist/DNC refusal added (VB-E-025). Still no adapter (D-V5). R-V21: the Open CTI surface itself retires 28 Feb 2028 (D-V8). Reviewer + v0.28.0 recommend D-V4(a) → Code-complete (unproven).
A7: ST-004 | B7: F1 | C7: Click-to-dial + softphone | D7: As a user, Click-to-dial + softphone shows clear errors and retry paths on platform API failures | E7: 3 | F7: P0 | G7: S2 | H7: SCR-3 Call workspace | I7: Automated (Jest, 100% cov) + E2E smoke | J7: Done | K7: errors.ts retry envelope + src/dialer.ts error paths — dialer.test.ts | L7: PROTOTYPE (code-only), NOW LABELLED AS SUCH IN THE PRODUCT — VB-CR-005 telephony half: no adapter places the call (D-V5), so every call is marked simulated:true and the panel says so rather than reading "Ringing". The seam and the adapter contract exist (src/telephony.ts, docs/telephony-provider-decision.md). D-V4 records whether these stay counted as Done. | F-P01 (20 Sep): the softphone page those stories promise was NEVER SERVED — fixed in v0.28.0 (src/widget.ts, boot test); pre-dial E.164/blocklist/DNC refusal added (VB-E-025). Still no adapter (D-V5). R-V21: the Open CTI surface itself retires 28 Feb 2028 (D-V8). Reviewer + v0.28.0 recommend D-V4(a) → Code-complete (unproven).
A8: ST-005 | B8: F1 | C8: Click-to-dial + softphone | D8: As a Salesforce admin, Click-to-dial + softphone works on the Lightning utility-bar softphone + LWC surface end-to-end | E8: 5 | F8: P0 | G8: S3 | H8: SCR-3 Call workspace | I8: Automated (Jest, 100% cov) + E2E smoke | J8: Done | K8: featureCore.availableOn lightning-utility-bar — featureCore.test.ts | GAP-V2: the web screen now exists (src/views.ts, /ui route) but no LWC bundle does — status held pending D-V2 ruling + in-org proof. | L8: PROTOTYPE (code-only), NOW LABELLED AS SUCH IN THE PRODUCT — VB-CR-005 telephony half: no adapter places the call (D-V5), so every call is marked simulated:true and the panel says so rather than reading "Ringing". The seam and the adapter contract exist (src/telephony.ts, docs/telephony-provider-decision.md). D-V4 records whether these stay counted as Done. | F-P01 (20 Sep): the softphone page those stories promise was NEVER SERVED — fixed in v0.28.0 (src/widget.ts, boot test); pre-dial E.164/blocklist/DNC refusal added (VB-E-025). Still no adapter (D-V5). R-V21: the Open CTI surface itself retires 28 Feb 2028 (D-V8). Reviewer + v0.28.0 recommend D-V4(a) → Code-complete (unproven).
A9: ST-006 | B9: F1 | C9: Click-to-dial + softphone | D9: As a Sales leader, I can see Click-to-dial + softphone performance metrics and trends | E9: 3 | F9: P1 | G9: S3 | H9: SCR-3 Call workspace | I9: Automated (Jest, 100% cov) + E2E smoke | J9: Done | K9: featureCore.metrics total/24h — featureCore.test.ts | L9: PROTOTYPE (code-only), NOW LABELLED AS SUCH IN THE PRODUCT — VB-CR-005 telephony half: no adapter places the call (D-V5), so every call is marked simulated:true and the panel says so rather than reading "Ringing". The seam and the adapter contract exist (src/telephony.ts, docs/telephony-provider-decision.md). D-V4 records whether these stay counted as Done. | F-P01 (20 Sep): the softphone page those stories promise was NEVER SERVED — fixed in v0.28.0 (src/widget.ts, boot test); pre-dial E.164/blocklist/DNC refusal added (VB-E-025). Still no adapter (D-V5). R-V21: the Open CTI surface itself retires 28 Feb 2028 (D-V8). Reviewer + v0.28.0 recommend D-V4(a) → Code-complete (unproven).
A10: ST-007 | B10: F1 | C10: Click-to-dial + softphone | D10: As a user, Click-to-dial + softphone respects role permissions and audit logging | E10: 3 | F10: P1 | G10: S3 | H10: SCR-3 Call workspace | I10: Automated (Jest, 100% cov) + E2E smoke | J10: Done | K10: permissions.ts matrix + audit.ts on every admin op — permissions/audit tests | L10: PROTOTYPE (code-only), NOW LABELLED AS SUCH IN THE PRODUCT — VB-CR-005 telephony half: no adapter places the call (D-V5), so every call is marked simulated:true and the panel says so rather than reading "Ringing". The seam and the adapter contract exist (src/telephony.ts, docs/telephony-provider-decision.md). D-V4 records whether these stay counted as Done. | F-P01 (20 Sep): the softphone page those stories promise was NEVER SERVED — fixed in v0.28.0 (src/widget.ts, boot test); pre-dial E.164/blocklist/DNC refusal added (VB-E-025). Still no adapter (D-V5). R-V21: the Open CTI surface itself retires 28 Feb 2028 (D-V8). Reviewer + v0.28.0 recommend D-V4(a) → Code-complete (unproven).
A11: ST-008 | B11: F1 | C11: Click-to-dial + softphone | D11: As a RevOps lead, I can pause/disable Click-to-dial + softphone without data loss | E11: 2 | F11: P2 | G11: S3 | H11: SCR-3 Call workspace | I11: Automated (Jest, 100% cov) + E2E smoke | J11: Done | K11: featureCore.setEnabled pause, data bags untouched — featureCore.test.ts | L11: PROTOTYPE (code-only), NOW LABELLED AS SUCH IN THE PRODUCT — VB-CR-005 telephony half: no adapter places the call (D-V5), so every call is marked simulated:true and the panel says so rather than reading "Ringing". The seam and the adapter contract exist (src/telephony.ts, docs/telephony-provider-decision.md). D-V4 records whether these stay counted as Done. | F-P01 (20 Sep): the softphone page those stories promise was NEVER SERVED — fixed in v0.28.0 (src/widget.ts, boot test); pre-dial E.164/blocklist/DNC refusal added (VB-E-025). Still no adapter (D-V5). R-V21: the Open CTI surface itself retires 28 Feb 2028 (D-V8). Reviewer + v0.28.0 recommend D-V4(a) → Code-complete (unproven).
A12: ST-009 | B12: F1 | C12: Click-to-dial + softphone | D12: As a Sales leader, I can import/migrate existing data into Click-to-dial + softphone (CSV + competitor importer) | E12: 5 | F12: P1 | G12: S3 | H12: SCR-3 Call workspace | I12: Automated (Jest, 100% cov) + E2E smoke | J12: Done | K12: featureCore.importData validation report — featureCore.test.ts | L12: PROTOTYPE (code-only), NOW LABELLED AS SUCH IN THE PRODUCT — VB-CR-005 telephony half: no adapter places the call (D-V5), so every call is marked simulated:true and the panel says so rather than reading "Ringing". The seam and the adapter contract exist (src/telephony.ts, docs/telephony-provider-decision.md). D-V4 records whether these stay counted as Done. | F-P01 (20 Sep): the softphone page those stories promise was NEVER SERVED — fixed in v0.28.0 (src/widget.ts, boot test); pre-dial E.164/blocklist/DNC refusal added (VB-E-025). Still no adapter (D-V5). R-V21: the Open CTI surface itself retires 28 Feb 2028 (D-V8). Reviewer + v0.28.0 recommend D-V4(a) → Code-complete (unproven).
A13: ST-010 | B13: F1 | C13: Click-to-dial + softphone | D13: As a user, I get notifications (in-app + email) for key Click-to-dial + softphone events with per-type mute | E13: 3 | F13: P2 | G13: S3 | H13: SCR-3 Call workspace | I13: Automated (Jest, 100% cov) + E2E smoke | J13: Done | K13: notifications.ts in-app+email — notifications.test.ts | L13: PROTOTYPE (code-only), NOW LABELLED AS SUCH IN THE PRODUCT — VB-CR-005 telephony half: no adapter places the call (D-V5), so every call is marked simulated:true and the panel says so rather than reading "Ringing". The seam and the adapter contract exist (src/telephony.ts, docs/telephony-provider-decision.md). D-V4 records whether these stay counted as Done. | F-P01 (20 Sep): the softphone page those stories promise was NEVER SERVED — fixed in v0.28.0 (src/widget.ts, boot test); pre-dial E.164/blocklist/DNC refusal added (VB-E-025). Still no adapter (D-V5). R-V21: the Open CTI surface itself retires 28 Feb 2028 (D-V8). Reviewer + v0.28.0 recommend D-V4(a) → Code-complete (unproven).
A14: ST-011 | B14: F2 | C14: Auto call/WhatsApp logging | D14: As a RevOps lead, I can set up Auto call/WhatsApp logging with sensible defaults in one screen | E14: 5 | F14: P0 | G14: S3 | H14: SCR-4 Logging builder | I14: Automated (Jest, 100% cov) + E2E smoke | J14: Done | K14: src/callLogger.ts.setup defaults + featureCore — callLogger.test.ts | L14: CODE-COMPLETE PENDING LIVE (was PROTOTYPE) — v0.26.0 writes the activity back to Salesforce as a Task, matched to Contact/Lead, idempotent on an external id. Verified against doubles only: operator step O7 proves it in an org (R-V20). WhatsApp remains VB-CR-008: no provider, no webhook, no send. | v0.28.0: matching moved to the platform phone index with ambiguity written unattached (VB-E-031); outbox now drains itself with backoff + dead-letter (F-P03); F-V31 — on Postgres no call ever ENDED before this release (transition mutated a detached copy). Live proof still O7. D-V4(a) recommended.
A15: ST-012 | B15: F2 | C15: Auto call/WhatsApp logging | D15: As a RevOps lead, the Auto call/WhatsApp logging happy path completes without documentation | E15: 8 | F15: P0 | G15: S3 | H15: SCR-4 Logging builder | I15: Automated (Jest, 100% cov) + E2E smoke | J15: Done | K15: src/callLogger.ts happy-path state machine — callLogger.test.ts + app.e2e.test.ts | L15: CODE-COMPLETE PENDING LIVE (was PROTOTYPE) — v0.26.0 writes the activity back to Salesforce as a Task, matched to Contact/Lead, idempotent on an external id. Verified against doubles only: operator step O7 proves it in an org (R-V20). WhatsApp remains VB-CR-008: no provider, no webhook, no send. | v0.28.0: matching moved to the platform phone index with ambiguity written unattached (VB-E-031); outbox now drains itself with backoff + dead-letter (F-P03); F-V31 — on Postgres no call ever ENDED before this release (transition mutated a detached copy). Live proof still O7. D-V4(a) recommended.
... A73: ST-070 | B73: E6 | C73: Security & compliance | D73: Rate-limit backoff + circuit breaker on platform APIs | E73: 5 | F73: P0 | G73: S8 | H73: SCR-6 Settings | I73: Automated (Jest, 100% cov) + E2E smoke | J73: Done | K73: src/sfClient.ts exp backoff+jitter + circuit breaker — sfClient.test.ts | v006: F-V06 fixed: real backoff sleep by default; F-V05 FIFO ledger caps | L73: PARTLY CLEARED 19:26 — VB-CR-004/009/010 FIXED; VB-CR-013 MITIGATED with a dated acceptance (Express 5 decision open).
A74: ST-071 | B74: E7 | C74: Analytics & telemetry | D74: Activation funnel events (install->setup->aha->habit) in one dashboard | E74: 5 | F74: P0 | G74: S4 | H74: SCR-8 Analytics | I74: Automated (Jest, 100% cov) + E2E smoke | J74: Done | K74: src/analytics.ts funnel install→setup→aha→habit — analytics.test.ts
A75: ST-072 | B75: E7 | C75: Analytics & telemetry | D75: Error tracking with release tagging; alert on error-rate spike | E75: 3 | F75: P0 | G75: S4 | H75: SCR-8 Analytics | I75: Automated (Jest, 100% cov) + E2E smoke | J75: Done | K75: src/analytics.ts trackError release-tagged + errorSpike alert — analytics.test.ts
A76: ST-073 | B76: E7 | C76: Analytics & telemetry | D76: Feature-usage heatmap for roadmap decisions | E76: 3 | F76: P2 | G76: S8 | H76: SCR-8 Analytics | I76: Automated (Jest, 100% cov) + E2E smoke | J76: Done | K76: src/analytics.ts heatmap over feature bags — analytics.test.ts
A77: ST-074 | B77: E7 | C77: Analytics & telemetry | D77: Weekly automated metrics email to team | E77: 2 | F77: P2 | G77: S8 | H77: SCR-8 Analytics | I77: Automated (Jest, 100% cov) + E2E smoke | J77: Done | K77: src/analytics.ts weeklyEmail body — analytics.test.ts
A78: ST-075 | B78: E7 | C78: Analytics & telemetry | D78: Health score computed per account (usage+billing+support) | E78: 5 | F78: P1 | G78: S8 | H78: SCR-8 Analytics | I78: Automated (Jest, 100% cov) + E2E smoke | J78: Done | K78: src/analytics.ts healthScore usage+billing+support — analytics.test.ts
A79: ST-076 | B79: E7 | C79: Analytics & telemetry | D79: Metrics export to CSV/warehouse for founder analysis | E79: 3 | F79: P2 | G79: S8 | H79: SCR-8 Analytics | I79: Automated (Jest, 100% cov) + E2E smoke | J79: Done | K79: src/analytics.ts exportCsv — analytics.test.ts
A80: ST-077 | B80: E7 | C80: Analytics & telemetry | D80: Alert thresholds configurable (activation drop, error spike, churn signal) | E80: 3 | F80: P2 | G80: S8 | H80: SCR-8 Analytics | I80: Automated (Jest, 100% cov) + E2E smoke | J80: Done | K80: src/analytics.ts setThresholds configurable — analytics.test.ts
A81: ST-078 | B81: E8 | C81: Onboarding & support | D81: First-run checklist reaches aha-moment in <1 day | E81: 5 | F81: P0 | G81: S5 | H81: SCR-1/9 | I81: Automated (Jest, 100% cov) + E2E smoke | J81: Done | K81: src/onboarding.ts checklist aha at 3/4 steps — onboarding.test.ts
A82: ST-079 | B82: E8 | C82: Onboarding & support | D82: Empty states teach next action on every screen | E82: 3 | F82: P1 | G82: S5 | H82: SCR-1/9 | I82: Automated (Jest, 100% cov) + E2E smoke | J82: Done | K82: src/views.ts — all 7 web screens carry an empty state naming the next action (test/views.test.ts asserts it per screen); widget shells unchanged. GAP-V2 closed the 2-of-9 gap.
A83: ST-080 | B83: E8 | C83: Onboarding & support | D83: Help center with 15 launch articles + search | E83: 5 | F83: P1 | G83: S10 | H83: SCR-1/9 | I83: Automated (Jest, 100% cov) + E2E smoke | J83: Done | K83: src/helpCenter.ts + test — 15 launch articles (getting-started→troubleshooting) + title-weighted token search, /help routes; e2e verified
A84: ST-081 | B84: E8 | C84: Onboarding & support | D84: In-app chat with <4 business-hr first response | E84: 3 | F84: P0 | G84: S10 | H84: SCR-1/9 | I84: Automated (Jest, 100% cov) + E2E smoke | J84: Done | K84: src/supportChat.ts + test — built-in chat with <4-business-hr SLA engine (Mon-Fri 9-18 IST, weekend/night rollover math tested), breach flags, operator queue; vendor decision deferred — engine works as-is (TeleField precedent) | L84: F-V31 (20 Sep): supportChat.respond mutated a detached copy — on Postgres no ticket was ever marked responded; fixed.
A85: ST-082 | B85: E8 | C85: Onboarding & support | D85: In-app review ask after aha-moment (marketplace rating engine) | E85: 3 | F85: P1 | G85: S11 | H85: SCR-1/9 | I85: Automated (Jest, 100% cov) + E2E smoke | J85: Done | K85: src/onboarding.ts shouldAskReview once-after-aha — onboarding.test.ts (built early with E8)
A86: ST-083 | B86: E8 | C86: Onboarding & support | D86: Demo video (2 min) + interactive sandbox/demo data mode | E86: 5 | F86: P1 | G86: S10 | H86: SCR-1/9 | I86: Integration test + manual QA | J86: Code-complete (pending live) | K86: src/demoMode.ts + test — isolated demo- namespace seeding (5 calls, 3 WA threads, live cadence, 2 enrollments), idempotent re-seed, real-org write guard; VIDEO half needs live-org capture (launch/asset-plan.md script ready)
A87: ST-084 | B87: E8 | C87: Onboarding & support | D87: Status page + incident comms template | E87: 2 | F87: P2 | G87: S10 | H87: SCR-1/9 | I87: Automated (Jest, 100% cov) + E2E smoke | J87: Done | K87: src/statusPage.ts + test — public status from breaker state (platform-bound components degrade, dial/billing stay up) + investigating/identified/resolved incident template | L87: v0.28.0: /status/slo publishes the error budget and importable burn-rate alert rules behind the 99.5% (VB-E-055).
A88: ST-085 | B88: EQ | C88: Quality engineering | D88: Unit+integration test coverage gate ≥70% on core modules | E88: 5 | F88: P0 | G88: S3 | H88: — | I88: Automated (Jest, 100% cov) + E2E smoke | J88: Done | K88: jest coverageThreshold 100x4 (D13 supersedes >=70) — CI fails below 100% | L88: CLEARED 19:26 — VB-CR-006/009/010 FIXED; migration smoke and evidence integrity now run in CI. | v0.28.0: CI gained evidence:check, typecheck:scripts (F-V33 — the old step could never pass), RLS + audit DB checks, actionlint; the echo deploy job is gone.
A89: ST-086 | B89: EQ | C89: Quality engineering | D89: E2E smoke suite runs on every deploy | E89: 5 | F89: P0 | G89: S4 | H89: — | I89: Automated (Jest, 100% cov) + E2E smoke | J89: Done | K89: test/app.e2e.test.ts smoke + ci.yml e2e-smoke job gating deploy | L89: CLEARED 19:26 — VB-CR-006/009/010 FIXED; migration smoke and evidence integrity now run in CI. | v0.28.0: CI gained evidence:check, typecheck:scripts (F-V33 — the old step could never pass), RLS + audit DB checks, actionlint; the echo deploy job is gone.
A90: ST-087 | B90: EQ | C90: Quality engineering | D90: p95 latency budgets defined and monitored per surface | E90: 3 | F90: P0 | G90: S8 | H90: — | I90: Automated (Jest, 100% cov) + E2E smoke | J90: Done | K90: src/analytics.ts p95WithinBudget api 500ms / ui 2000ms — analytics.test.ts | L90: CLEARED 19:26 — VB-CR-006/009/010 FIXED; migration smoke and evidence integrity now run in CI.
A91: ST-088 | B91: EQ | C91: Quality engineering | D91: Load test at 5x expected launch traffic | E91: 5 | F91: P1 | G91: S8 | H91: — | I91: Automated (Jest, 100% cov) + E2E smoke | J91: Code-complete (pending live) | K91: load/k6-load.js 5x-launch harness (100 rps, p95<500) — LIVE run pending infra | L91: CLEARED 19:26 — VB-CR-006/009/010 FIXED; migration smoke and evidence integrity now run in CI.
A92: ST-089 | B92: EQ | C92: Quality engineering | D92: Accessibility WCAG AA pass on primary flows | E92: 3 | F92: P1 | G92: S9 | H92: — | I92: Automated (Jest, 100% cov) + E2E smoke | J92: Done | K92: test/a11y.test.ts — jest-axe over ALL 9 screens x populated+empty (18 assertions), was 2 screens. Stays In progress: live-UI/screen-reader pass is Senthil's half. | L92: CLEARED 19:26 — VB-CR-006/009/010 FIXED; migration smoke and evidence integrity now run in CI.
A93: ST-090 | B93: EQ | C93: Quality engineering | D93: Backup + restore drill executed | E93: 3 | F93: P1 | G93: S9 | H93: — | I93: Automated (Jest, 100% cov) + E2E smoke | J93: Done | K93: src/backup.ts + test/backup.test.ts — snapshot→wipe→restore drill, sha256 integrity verify, divergence blocks ship; live pg variant scripted (live-sweep step 9) | L93: CLEARED 19:26 — VB-CR-006/009/010 FIXED; migration smoke and evidence integrity now run in CI. | v0.28.0 VB-E-057: scripts/dr-drill.sh — live pg_dump/pg_restore with checksum diff and measured RTO; execution = O9.
A94: ST-091 | B94: EQ | C94: Quality engineering | D94: Chaos test: platform API outage degrades gracefully with user comms | E94: 3 | F94: P2 | G94: S9 | H94: — | I94: Automated (Jest, 100% cov) + E2E smoke | J94: Done | K94: src/resilience.ts + /status route + chaos e2e — breaker-driven degraded mode, user banner, queued-writes comms, auto-recovery | L94: CLEARED 19:26 — VB-CR-006/009/010 FIXED; migration smoke and evidence integrity now run in CI.
A95: ST-092 | B95: EQ | C95: Quality engineering | D95: Zero-downtime deploy verified (blue/green or rolling) | E95: 3 | F95: P2 | G95: S8 | H95: — | I95: Automated (Jest, 100% cov) + E2E smoke | J95: Code-complete (pending live) | K95: ci.yml deploy-blue-green job — LIVE slot-swap verification pending infra | L95: CLEARED 19:26 — VB-CR-006/009/010 FIXED; migration smoke and evidence integrity now run in CI. | v0.28.0 VB-E-056: real blue/green pipeline (deploy.yml + script) with migration gate, health gates incl. the widget route, automatic rollback; R-V15 caps half closed so two instances are safe.
A96: ST-093 | B96: EL | C96: Launch & listing | D96: Marketplace listing copy A + B variants drafted and reviewed | E96: 3 | F96: P0 | G96: S9 | H96: — | I96: E2E test + demo | J96: Drafted | K96: launch/listing-copy-ab.md — variants A (outcome-led) + B (pain-led) awaiting pick | L96: D-V6 gate (20 Sep): both listing variants lead with WhatsApp logging, which does not exist; gated in launch/listing-copy-ab.md. R-V21 applies to any Open CTI wording.
A97: ST-094 | B97: EL | C97: Launch & listing | D97: 5 screenshots + 2-min demo video meet platform asset specs | E97: 5 | F97: P0 | G97: S9 | H97: — | I97: E2E test + demo | J97: Drafted | K97: launch/asset-plan.md — 5-shot list + 2-min video script per AppExchange specs; capture needs live org | L97: D-V6 gate (20 Sep): both listing variants lead with WhatsApp logging, which does not exist; gated in launch/listing-copy-ab.md. R-V21 applies to any Open CTI wording.
A98: ST-095 | B98: EL | C98: Launch & listing | D98: Pricing page/plan matrix published with FAQ | E98: 3 | F98: P0 | G98: S10 | H98: — | I98: Automated (Jest, 100% cov) + E2E smoke | J98: Done | K98: src/pricingPage.ts + test — plan matrix + 7-item FAQ generated from billing.ts exported constants (single source; sync asserted in tests)
A99: ST-096 | B99: EL | C99: Launch & listing | D99: Security/trust page (data handling, subprocessors) live | E99: 3 | F99: P0 | G99: S10 | H99: — | I99: Automated (Jest, 100% cov) + E2E smoke | J99: Done | K99: src/trustPage.ts + test — data handling, least-privilege scopes, subprocessors, retention + residency from config single source | L99: CLEARED 19:26 — VB-CR-012 FIXED: production requires both regions; unconfigured publishes UNVERIFIED. | v0.28.0: encryption sentence now TRUE (F-P02); tenant-isolation and DNC sentences added and tested; contacts from config ("not yet published" until set); every sentence in the claims registry (VB-E-016).
A100: ST-097 | B100: EL | C100: Launch & listing | D100: Submission dry-run against platform checklist by second reviewer | E100: 3 | F100: P0 | G100: S10 | H100: — | I100: E2E test + demo | J100: In progress | K100: src/dryRun.ts + test — submission dry-run engine READY 11/11 automated (DR-01..11 file+content checks) with 4 human/live items DR-12..15; REVIEW_PACK.md for external second reviewer — human sign-off (DR-12) = Senthil nominee | L100: v0.28.0: REVIEW_PACK addendum lists ten checks for the second reviewer; dry-run READY 18/18 + 5 human/live (DR-23 = Open CTI confirmation).
A101: ST-098 | B101: EL | C101: Launch & listing | D101: Launch-day runbook: monitoring, rollback, comms tree | E101: 3 | F101: P1 | G101: S11 | H101: — | I101: Automated (Jest, 100% cov) + E2E smoke | J101: Done | K101: src/runbook.ts + test — executable runbook: 12 steps / 5 phases, automated pre-flight file checks, rollback triggers wired to the real p95 budgets (api 500ms / ui 2s) + 3x error-spike rule, 4-row comms tree; zero-baseline guard tested
A102: ST-099 | B102: EL | C102: Launch & listing | D102: Post-launch listing SEO iteration 1 from search-term data | E102: 2 | F102: P2 | G102: S12 | H102: — | I102: Manual QA | J102: Code-complete (pending live) | K102: src/listingSeo.ts + test — SEO iteration engine: promote/keep/ignore per term with CTR+install-rate thresholds and 100-impression floor, title suggestion from strongest term, A/B install-rate signal with near-tie + thin-data guards; LIVE half needs post-listing search-term data
A103: ST-100 | B103: EL | C103: Launch & listing | D103: First 10 design-partner reviews scheduled | E103: 2 | F103: P1 | G103: S11 | H103: — | I103: Integration test + manual QA | J103: Code-complete (pending live) | K103: src/designPartners.ts + test — 10-slot tracker: invited→scheduled→reviewed|declined with guards, 3-day stale-nudge queue (longest-silent first), honest exit math separating reviews from G-02 paying-stranger installs; LIVE half (actual outreach + scheduling) = Senthil | L103: F-V31 (20 Sep): designPartners state changes mutated detached copies; slot cap now DB-enforced (VB-E-053).

Sheet Sprint_Status_Rollup
A1: SPRINT STATUS ROLLUP — live formulas over Traceability_Matrix
A2: Do not edit computed cells. 'Done' counts Done + Code-complete (pending live). EXTERNAL REVIEW V001 (13 Sep): these are CODE STATUS counts, NOT product readiness — the AppExchange listing, security review, packaging, residency statement, managed upgrade path and independent dry-run are all still open, and VB-CR-005 means the core dial/log stories do not yet reach an external system. Read this table with Traceability_Matrix column L.
A3: Sprint | B3: Focus | C3: Stories | D3: Points | E3: Done | F3: Done points | G3: % points done | H3: RAG (manual) | I3: Exit criteria
A4: S0 | B4: Discovery & Design (2 wks) | C4: =COUNTIF(Traceability_Matrix!$G$4:$G$103,$A4) -> 0 | D4: =SUMIF(Traceability_Matrix!$G$4:$G$103,$A4,Traceability_Matrix!$E$4:$E$103) -> 0 | E4: =COUNTIFS(Traceability_Matrix!$G$4:$G$103,$A4,Traceability_Matrix!$J$4:$J$103,"Done")+COUNTIFS(Traceability_Matrix!$G$4:$G$103,$A4,Traceability_Matrix!$J$4:$J$103,"Code-complete (pending live)") -> 0 | F4: =SUMIFS(Traceability_Matrix!$E$4:$E$103,Traceability_Matrix!$G$4:$G$103,$A4,Traceability_Matrix!$J$4:$J$103,"Done")+SUMIFS(Traceability_Matrix!$E$4:$E$103,Traceability_Matrix!$G$4:$G$103,$A4,Traceability_Matrix!$J$4:$J$103,"Code-complete (pending live)") -> 0 | G4: =IF(D4=0,0,F4/D4) -> 0 | I4: PRD signed off; prototype tested with 5 target users
A5: S1 | B5: Foundation (2 wks) | C5: =COUNTIF(Traceability_Matrix!$G$4:$G$103,$A5) -> 4 | D5: =SUMIF(Traceability_Matrix!$G$4:$G$103,$A5,Traceability_Matrix!$E$4:$E$103) -> 13 | E5: =COUNTIFS(Traceability_Matrix!$G$4:$G$103,$A5,Traceability_Matrix!$J$4:$J$103,"Done")+COUNTIFS(Traceability_Matrix!$G$4:$G$103,$A5,Traceability_Matrix!$J$4:$J$103,"Code-complete (pending live)") -> 4 | F5: =SUMIFS(Traceability_Matrix!$E$4:$E$103,Traceability_Matrix!$G$4:$G$103,$A5,Traceability_Matrix!$J$4:$J$103,"Done")+SUMIFS(Traceability_Matrix!$E$4:$E$103,Traceability_Matrix!$G$4:$G$103,$A5,Traceability_Matrix!$J$4:$J$103,"Code-complete (pending live)") -> 13 | G5: =IF(D5=0,0,F5/D5) -> 1 | H5: GREEN — done-in-code; live dev-org install pending (S1-live) | I5: App installs cleanly in dev store/org; telemetry firing
A6: S2 | B6: Core feature Click-to-dial + softphone - part 1 | C6: =COUNTIF(Traceability_Matrix!$G$4:$G$103,$A6) -> 6 | D6: =SUMIF(Traceability_Matrix!$G$4:$G$103,$A6,Traceability_Matrix!$E$4:$E$103) -> 29 | E6: =COUNTIFS(Traceability_Matrix!$G$4:$G$103,$A6,Traceability_Matrix!$J$4:$J$103,"Done")+COUNTIFS(Traceability_Matrix!$G$4:$G$103,$A6,Traceability_Matrix!$J$4:$J$103,"Code-complete (pending live)") -> 6 | F6: =SUMIFS(Traceability_Matrix!$E$4:$E$103,Traceability_Matrix!$G$4:$G$103,$A6,Traceability_Matrix!$J$4:$J$103,"Done")+SUMIFS(Traceability_Matrix!$E$4:$E$103,Traceability_Matrix!$G$4:$G$103,$A6,Traceability_Matrix!$J$4:$J$103,"Code-complete (pending live)") -> 29 | G6: =IF(D6=0,0,F6/D6) -> 1 | H6: GREEN | I6: Click-to-dial + softphone happy path demoable
A7: S3 | B7: Core feature Click-to-dial + softphone - part 2 + Auto call/WhatsApp logging start | C7: =COUNTIF(Traceability_Matrix!$G$4:$G$103,$A7) -> 11 | D7: =SUMIF(Traceability_Matrix!$G$4:$G$103,$A7,Traceability_Matrix!$E$4:$E$103) -> 47 | E7: =COUNTIFS(Traceability_Matrix!$G$4:$G$103,$A7,Traceability_Matrix!$J$4:$J$103,"Done")+COUNTIFS(Traceability_Matrix!$G$4:$G$103,$A7,Traceability_Matrix!$J$4:$J$103,"Code-complete (pending live)") -> 11 | F7: =SUMIFS(Traceability_Matrix!$E$4:$E$103,Traceability_Matrix!$G$4:$G$103,$A7,Traceability_Matrix!$J$4:$J$103,"Done")+SUMIFS(Traceability_Matrix!$E$4:$E$103,Traceability_Matrix!$G$4:$G$103,$A7,Traceability_Matrix!$J$4:$J$103,"Code-complete (pending live)") -> 47 | G7: =IF(D7=0,0,F7/D7) -> 1 | H7: GREEN | I7: Click-to-dial + softphone complete with tests; Auto call/WhatsApp logging skeleton
A8: S4 | B8: Core feature Auto call/WhatsApp logging | C8: =COUNTIF(Traceability_Matrix!$G$4:$G$103,$A8) -> 9 | D8: =SUMIF(Traceability_Matrix!$G$4:$G$103,$A8,Traceability_Matrix!$E$4:$E$103) -> 34 | E8: =COUNTIFS(Traceability_Matrix!$G$4:$G$103,$A8,Traceability_Matrix!$J$4:$J$103,"Done")+COUNTIFS(Traceability_Matrix!$G$4:$G$103,$A8,Traceability_Matrix!$J$4:$J$103,"Code-complete (pending live)") -> 9 | F8: =SUMIFS(Traceability_Matrix!$E$4:$E$103,Traceability_Matrix!$G$4:$G$103,$A8,Traceability_Matrix!$J$4:$J$103,"Done")+SUMIFS(Traceability_Matrix!$E$4:$E$103,Traceability_Matrix!$G$4:$G$103,$A8,Traceability_Matrix!$J$4:$J$103,"Code-complete (pending live)") -> 34 | G8: =IF(D8=0,0,F8/D8) -> 1 | H8: GREEN — MVP loop e2e in harness | I8: MVP loop usable end-to-end internally
A9: S5 | B9: Feature Cadence/sequence lite + alpha hardening | C9: =COUNTIF(Traceability_Matrix!$G$4:$G$103,$A9) -> 12 | D9: =SUMIF(Traceability_Matrix!$G$4:$G$103,$A9,Traceability_Matrix!$E$4:$E$103) -> 50 | E9: =COUNTIFS(Traceability_Matrix!$G$4:$G$103,$A9,Traceability_Matrix!$J$4:$J$103,"Done")+COUNTIFS(Traceability_Matrix!$G$4:$G$103,$A9,Traceability_Matrix!$J$4:$J$103,"Code-complete (pending live)") -> 12 | F9: =SUMIFS(Traceability_Matrix!$E$4:$E$103,Traceability_Matrix!$G$4:$G$103,$A9,Traceability_Matrix!$J$4:$J$103,"Done")+SUMIFS(Traceability_Matrix!$E$4:$E$103,Traceability_Matrix!$G$4:$G$103,$A9,Traceability_Matrix!$J$4:$J$103,"Code-complete (pending live)") -> 50 | G9: =IF(D9=0,0,F9/D9) -> 1 | H9: GREEN | I9: Internal alpha: team dogfoods daily
A10: S6 | B10: Billing + Coaching analytics | C10: =COUNTIF(Traceability_Matrix!$G$4:$G$103,$A10) -> 13 | D10: =SUMIF(Traceability_Matrix!$G$4:$G$103,$A10,Traceability_Matrix!$E$4:$E$103) -> 60 | E10: =COUNTIFS(Traceability_Matrix!$G$4:$G$103,$A10,Traceability_Matrix!$J$4:$J$103,"Done")+COUNTIFS(Traceability_Matrix!$G$4:$G$103,$A10,Traceability_Matrix!$J$4:$J$103,"Code-complete (pending live)") -> 13 | F10: =SUMIFS(Traceability_Matrix!$E$4:$E$103,Traceability_Matrix!$G$4:$G$103,$A10,Traceability_Matrix!$J$4:$J$103,"Done")+SUMIFS(Traceability_Matrix!$E$4:$E$103,Traceability_Matrix!$G$4:$G$103,$A10,Traceability_Matrix!$J$4:$J$103,"Code-complete (pending live)") -> 60 | G10: =IF(D10=0,0,F10/D10) -> 1 | H10: GREEN — ST-059 code-complete, ISV agreement gates Checkout | I10: Can charge a test customer; upgrade/downgrade paths work
A11: S7 | B11: Private beta (design partners) | C11: =COUNTIF(Traceability_Matrix!$G$4:$G$103,$A11) -> 5 | D11: =SUMIF(Traceability_Matrix!$G$4:$G$103,$A11,Traceability_Matrix!$E$4:$E$103) -> 15 | E11: =COUNTIFS(Traceability_Matrix!$G$4:$G$103,$A11,Traceability_Matrix!$J$4:$J$103,"Done")+COUNTIFS(Traceability_Matrix!$G$4:$G$103,$A11,Traceability_Matrix!$J$4:$J$103,"Code-complete (pending live)") -> 5 | F11: =SUMIFS(Traceability_Matrix!$E$4:$E$103,Traceability_Matrix!$G$4:$G$103,$A11,Traceability_Matrix!$J$4:$J$103,"Done")+SUMIFS(Traceability_Matrix!$E$4:$E$103,Traceability_Matrix!$G$4:$G$103,$A11,Traceability_Matrix!$J$4:$J$103,"Code-complete (pending live)") -> 15 | G11: =IF(D11=0,0,F11/D11) -> 1 | H11: GREEN | I11: 3+ partners active weekly; NPS pulse >30
A12: S8 | B12: Beta iteration + Flow actions pack | C12: =COUNTIF(Traceability_Matrix!$G$4:$G$103,$A12) -> 22 | D12: =SUMIF(Traceability_Matrix!$G$4:$G$103,$A12,Traceability_Matrix!$E$4:$E$103) -> 87 | E12: =COUNTIFS(Traceability_Matrix!$G$4:$G$103,$A12,Traceability_Matrix!$J$4:$J$103,"Done")+COUNTIFS(Traceability_Matrix!$G$4:$G$103,$A12,Traceability_Matrix!$J$4:$J$103,"Code-complete (pending live)") -> 22 | F12: =SUMIFS(Traceability_Matrix!$E$4:$E$103,Traceability_Matrix!$G$4:$G$103,$A12,Traceability_Matrix!$J$4:$J$103,"Done")+SUMIFS(Traceability_Matrix!$E$4:$E$103,Traceability_Matrix!$G$4:$G$103,$A12,Traceability_Matrix!$J$4:$J$103,"Code-complete (pending live)") -> 87 | G12: =IF(D12=0,0,F12/D12) -> 1 | H12: AMBER — 4 code-complete items need live infra; ST-069/082 pulled early | I12: Retention of beta cohort week-over-week >60%
A13: S9 | B13: Marketplace review prep | C13: =COUNTIF(Traceability_Matrix!$G$4:$G$103,$A13) -> 7 | D13: =SUMIF(Traceability_Matrix!$G$4:$G$103,$A13,Traceability_Matrix!$E$4:$E$103) -> 30 | E13: =COUNTIFS(Traceability_Matrix!$G$4:$G$103,$A13,Traceability_Matrix!$J$4:$J$103,"Done")+COUNTIFS(Traceability_Matrix!$G$4:$G$103,$A13,Traceability_Matrix!$J$4:$J$103,"Code-complete (pending live)") -> 4 | F13: =SUMIFS(Traceability_Matrix!$E$4:$E$103,Traceability_Matrix!$G$4:$G$103,$A13,Traceability_Matrix!$J$4:$J$103,"Done")+SUMIFS(Traceability_Matrix!$E$4:$E$103,Traceability_Matrix!$G$4:$G$103,$A13,Traceability_Matrix!$J$4:$J$103,"Code-complete (pending live)") -> 14 | G13: =IF(D13=0,0,F13/D13) -> 0.46666667 | H13: Blocked on live org (pen-test, WCAG, drills) | I13: Review submission accepted into queue
A14: S10 | B14: Review remediation + docs | C14: =COUNTIF(Traceability_Matrix!$G$4:$G$103,$A14) -> 7 | D14: =SUMIF(Traceability_Matrix!$G$4:$G$103,$A14,Traceability_Matrix!$E$4:$E$103) -> 24 | E14: =COUNTIFS(Traceability_Matrix!$G$4:$G$103,$A14,Traceability_Matrix!$J$4:$J$103,"Done")+COUNTIFS(Traceability_Matrix!$G$4:$G$103,$A14,Traceability_Matrix!$J$4:$J$103,"Code-complete (pending live)") -> 6 | F14: =SUMIFS(Traceability_Matrix!$E$4:$E$103,Traceability_Matrix!$G$4:$G$103,$A14,Traceability_Matrix!$J$4:$J$103,"Done")+SUMIFS(Traceability_Matrix!$E$4:$E$103,Traceability_Matrix!$G$4:$G$103,$A14,Traceability_Matrix!$J$4:$J$103,"Code-complete (pending live)") -> 21 | G14: =IF(D14=0,0,F14/D14) -> 0.875 | I14: Marketplace approval obtained (or final remediation cycle)
A15: S11 | B15: Launch | C15: =COUNTIF(Traceability_Matrix!$G$4:$G$103,$A15) -> 3 | D15: =SUMIF(Traceability_Matrix!$G$4:$G$103,$A15,Traceability_Matrix!$E$4:$E$103) -> 8 | E15: =COUNTIFS(Traceability_Matrix!$G$4:$G$103,$A15,Traceability_Matrix!$J$4:$J$103,"Done")+COUNTIFS(Traceability_Matrix!$G$4:$G$103,$A15,Traceability_Matrix!$J$4:$J$103,"Code-complete (pending live)") -> 3 | F15: =SUMIFS(Traceability_Matrix!$E$4:$E$103,Traceability_Matrix!$G$4:$G$103,$A15,Traceability_Matrix!$J$4:$J$103,"Done")+SUMIFS(Traceability_Matrix!$E$4:$E$103,Traceability_Matrix!$G$4:$G$103,$A15,Traceability_Matrix!$J$4:$J$103,"Code-complete (pending live)") -> 8 | G15: =IF(D15=0,0,F15/D15) -> 1 | H15: ST-082 built early | I15: First 10 installs; first 3 reviews; activation >40%
A16: S12 | B16: Iterate & scale decision | C16: =COUNTIF(Traceability_Matrix!$G$4:$G$103,$A16) -> 1 | D16: =SUMIF(Traceability_Matrix!$G$4:$G$103,$A16,Traceability_Matrix!$E$4:$E$103) -> 2 | E16: =COUNTIFS(Traceability_Matrix!$G$4:$G$103,$A16,Traceability_Matrix!$J$4:$J$103,"Done")+COUNTIFS(Traceability_Matrix!$G$4:$G$103,$A16,Traceability_Matrix!$J$4:$J$103,"Code-complete (pending live)") -> 1 | F16: =SUMIFS(Traceability_Matrix!$E$4:$E$103,Traceability_Matrix!$G$4:$G$103,$A16,Traceability_Matrix!$J$4:$J$103,"Done")+SUMIFS(Traceability_Matrix!$E$4:$E$103,Traceability_Matrix!$G$4:$G$103,$A16,Traceability_Matrix!$J$4:$J$103,"Code-complete (pending live)") -> 2 | G16: =IF(D16=0,0,F16/D16) -> 1 | I16: Growth model doc with CAC/LTV first estimates
A17: TOTAL | B17: (S1-S12) | C17: =SUM(C4:C16) -> 100 | D17: =SUM(D4:D16) -> 399 | E17: =SUM(E4:E16) -> 96 | F17: =SUM(F4:F16) -> 380 | G17: =IF(D17=0,0,F17/D17) -> 0.95238095
A18: NOTE | B18: External review V001, 13 Sep 17:34 — decision REJECT | I18: If D-V4 reclassifies ST-001..020 to Prototype (code-only), the counted position moves from 96/100 to 76/100. Gate_Checklist G-01..G-06 remain authoritative over any story count.
A19: NOTE | B19: Perplexity review V001, 16 Sep 13:53 — HOLD / re-platform or pivot | I19: S13-S29 enhancement stories live in the Enhancement_Plan sheet with their own rollup. The Stop_Doing advice "stop counting story points" is honoured this way: this table stays CODE STATUS; Gate_Checklist G-01..G-07 are the headline. Definition of Done (live evidence) recorded in Gate_Checklist row 2.

Sheet RAID_Carryover
A1: RAID — seeded from v006 Risk_Register + build findings
A2: ID | B2: Type | C2: Raised | D2: Item | E2: Status | F2: Notes / Mitigation
A3: R-V1 | B3: Risk | C3: v006 | D3: AppExchange Security Review cycles exceed 2 iterations, 3+ months delay (High/High) | E3: Open | F3: Specialist review consultant pre-submission; least-privilege scope map (ST-064) + data-flow doc (ST-065) already drafted to shorten cycles.
A4: R-V2 | B4: Risk | C4: v006 | D4: Service Cloud Voice bundling squeezes third-party CTI (High/Medium) | E4: REALISED (20 Sep) — see R-V21 | F4: Mid-market focus + WhatsApp/SMS omnichannel angle SCV lacks; F2 threads shipped. | The review's reading: the squeeze already happened — Agentforce Voice GA Spring '26, Agentforce Contact Center launched 10 Mar 2026, and Open CTI itself is retiring.
A5: R-V3 | B5: Risk | C5: v006 | D5: Enterprise sales cycle vs cash runway (High/Medium) | E5: Open | F5: Paid pilots; annual prepay; partner-sourced deals.
A6: R-V4 | B6: Constraint | C6: 23:00 | D6: Sandbox has no Postgres — persistence is in-memory behind typed repository interface | E6: Open | F6: Postgres adapter at deploy (S1-live); domain code untouched by the swap.
A7: R-V5 | B7: Assumption | C7: 23:00 | D7: Open CTI softphone adapter (in-org JS shell) not buildable/verifiable in sandbox — dial core is provider-agnostic | E7: Mitigated (code half closed) | F7: Adapter + CallCenter definition + permsets now BUILT and tested against mocked sforce.opencti; live click-to-dial/screen-pop verify (O2) is all that remains — turnkey deploy in guide step 6.
A8: R-V6 | B8: Assumption | C8: 23:00 | D8: AppExchange Checkout mandate vs external billing not verified — provider abstraction covers both (ST-059) | E8: Open | F8: Verify Checkout/PNR terms with ISV agreement (LC-1/LC-9) before S9 submission.
A9: A-V1 | B9: Assumption | C9: 23:00 | D9: D13 (interviews parked, 100% coverage) applies portfolio-wide incl. VoiceBridge | E9: Open | F9: Per Senthil 20:45/23:00 instructions; S0 activities (PRD sign-off, 5-user prototype test) remain parked.
A10: A-V2 | B10: Assumption | C10: 23:00 | D10: D15 mode (parallel vs swap) pending — RevRescue and eight other builds done-in-code concurrently | E10: Open | F10: Senthil to ratify; R1 serial rule formally intact until then.
A11: R-V7 | B11: Risk | C11: 2026-09-11 | D11: Same-AI review not independent — submission dry-run (ST-097) needs external second reviewer | E11: Open | F11: REVIEW_PACK.md now issued; dry-run engine holds DR-12 open until the external reviewer signs; Senthil to nominate.
A12: L-V1 | B12: Lesson | C12: 2026-09-11 | D12: Coverage proves execution, not correctness (portfolio F-V14 confirmed here): F-V06 hid behind 100% coverage because tests always injected their own sleep — the production default was never the thing under test. | E12: Logged | F12: Pin defaults explicitly (defaults.test.ts pattern) and cold-review every module.
A13: L-V2 | B13: Lesson | C13: 2026-09-11 | D13: Mocks can encode the bug. F-V12 survived pass 1 because the adapter test's /dial mock returned no state field, so the assertion agreed with the hard-coded 'connected'. A mock that does not mirror the real response shape turns a test into a rubber stamp. | E13: Logged | F13: Mock payloads are now built from the real handler's return shape; the /dial mock carries state.
... A58: L-V27 | B58: Lesson | C58: 2026-09-20 | D58: The reviewer's numbers deserve the same check as their findings: "49 test files vs 48 suites" counted a helper. The finding class (suites outside the manifest) was right and was fixed; the instance was wrong and is logged as such so the tracker does not carry an error forward as fact. | E58: Logged | F58: Verify every quantitative claim in a review against the artefact before recording it; record corrections in the same row.

Sheet Gate_Checklist
A1: COMPLETION GATE (D7) — VoiceBridge is DONE only when every row closes
A2: R2: code-complete counts for nothing at the gate. Gate decision = Senthil, on evidence Claude prepares. DEFINITION OF DONE (20 Sep, Perplexity §6.1.1): a story is Done only when observed working against a live Salesforce org, a live Postgres and (where relevant) a live carrier, with the evidence artefact committed. "Code-complete (unproven)" is a status, not a gate credit. Coverage scope is gates per artefact class (docs/coverage-scope.md), and every published claim maps to a test (docs/claims-registry.md).
A3: ID | B3: Gate item | C3: Source | D3: Status
A4: G-01 | B4: App LISTED on Salesforce AppExchange (security review passed + published) | C4: D7 / R2 | D4: Open
A5: G-02 | B5: 10 PAYING installs from strangers | C5: D7 / R2 | D5: Open
A6: G-03 | B6: S12 kill criteria evaluated with evidence pack | C6: D7 / R3 | D6: Engine ready — S12 kill-criteria evaluation now has SEO/exit-math/dry-run evidence generators; evaluation itself at live | 20 Sep: the review adds a FIRST HONEST KILL POINT at the S16 exit — 15 discovery interviews (VB-E-008) must produce 3 orgs willing to run a paid pilot at the ratified price, or stop.
A7: G-04 | B7: Kill/continue decision recorded by Senthil | C7: R5 / D10 | D7: Open
A8: G-05 | B8: On CONTINUE: next-rank build authorised; VoiceBridge enters run-mode | C8: N4 / R1 | D8: Open
A9: LC-1 | B9: ISV Partner Program application + agreement executed | C9: v006 LC #1 | D9: Open — gates ST-059 live Checkout
A10: LC-2 | B10: Developer/scratch orgs + managed package namespace registered | C10: v006 LC #2 | D10: Open — package SOURCE ready (sfpackage/, create command in sfdx-project.json); Senthil: Dev Hub + namespace registration, then sf package create | VER-V06: the OAuth half is an EXTERNAL CLIENT APP — new Connected Apps cannot be created from Spring '26. ECAs are packageable, so the shim can carry it. | 20 Sep: the shim no longer carries the adapter static resource (served from host, F-P01); whether to register a namespace for an Open CTI package at all is D-V8.
A11: LC-3 | B11: Security Review: pen-test evidence, code scan clean, Trust questionnaire | C11: v006 LC #3 | D11: Open — sandbox evidence pack DONE (SECURITY.md, STRIDE model, scripted archive); pen-test vendor = Senthil | VER-V07..V09: four mandatory OAuth controls implemented/configured (docs/oauth-security-controls.md); O5 self-attestation owed. F-V21 (caller-declared identity) is an open review-blocker. Review fee $999 per paid-app submission. | 20 Sep v0.28.0: encryption at rest (F-P02), CSP/HSTS/rate limits/timeouts (F-P04), Postgres RLS (VB-E-080), hash-chained audit (VB-E-081), session lifecycle (VB-E-082), 0 advisories (VB-E-017), claims gate, DPA template — all with tests; pen test (DR-13) and SOC 2 readiness (VB-E-086) remain the vendor/consultant half.
A12: LC-4 | B12: Open CTI / Service Cloud Voice compatibility decision documented | C12: v006 LC #4 | D12: OVERTAKEN (20 Sep, R-V21) — Open CTI retires 28 Feb 2028. The compatibility decision is now D-V8 (Partner Telephony re-platform vs AI-layer pivot vs finish on Open CTI). docs/opencti-retirement-impact.md.
A13: LC-5 | B13: Permission sets + profiles install experience tested in 3 org shapes | C13: v006 LC #5 | D13: Code + package halves DONE (matrix-generated permsets, drift-tested); 3-org-shape install test at live
A14: LC-6 | B14: Data residency: Hyperforce region support statement | C14: v006 LC #6 | D14: In progress — region in config + /health + sweep A8 consistency check; statement doc owed | 20 Sep: residency sentences are in the claims registry (CL-T10/T11); VB-E-093 publishes per region from verified config.
... A20: G-07 | B20: Second independent review decision (Perplexity V001, 16 Sep 13:53 BST) = no HOLD; strategy ruled (D-V8) and S13 gate closed | C20: Perplexity review V001 §7 | D20: HOLD at 20 Sep 10:45 — F-P01..F-P05 CLOSED in v0.28.0; F-P06 open on D-V7; the HOLD lifts only on the S13 decision gate (VB-E-001..008): D-V9 confirmation, D-V8 ruling, D-V5, D-V6, D-V7, D-V4. Recommendation carried: do not submit for security review or build another feature sprint on Open CTI until then.

Sheet Review_Findings
A1: REVIEW FINDINGS — adversarial cold-review, VoiceBridge codebase
A2: Pass 1 (22:09): billing, store, lifecycle, sfClient, featureCore + write entry points. Pass 2 (22:34): the remaining ~28 modules — dialer, callLogger, cadence, coaching, analytics, flowActions, onboarding, notifications, audit, permissions, permSets, sfAuth, resilience, backup, config, app, helpCenter, supportChat, demoMode, statusPage, pricingPage, trustPage, dryRun, runbook, designPartners, listingSeo, sweepChecks, softphoneAdapter — plus an external verification sweep vs live Open CTI docs and an artifact-gap audit. COLD REVIEW NOW COMPLETE. Dispositions column is Senthil's. | 20 Sep: PERPLEXITY REVIEW V001 (F-P01..F-P06) — six findings not in either workbook or in external review V001 — plus F-V31..F-V34 found by the remediation itself.
A3: ID | B3: Severity | C3: Module(s) | D3: Finding | E3: Resolution | F3: Story | G3: Sibling precedent | H3: Disposition (Senthil)
A4: F-V01 | B4: High | C4: store.ts / lifecycle.ts | D4: Retention sweep deleted feature bags only — user ROLE records survived forever and the account tombstone kept install source + lifecycle timestamps. Published "permanently deleted" policy (trust page, data-flow doc) was breached. | E4: FIXED — sweep now deletes all org roles (store.deleteRolesForOrg) and writes a minimal tombstone (orgId, deleted, deletedAt only); regression asserts post-sweep snapshot contains no user ids. | F4: ST-052 | G4: FlowCast F-007
A5: F-V02 | B5: High | C5: billing.ts | D5: No payment-recovery path: grace/read-only was a one-way street — a successful payment could not restore active status, reset dunning, or clear grace. Help article HC-10 promised "restores full access immediately"; the code could not deliver it. | E5: FIXED — paymentRecovered(): grace|read-only → active, dunningEmails 0, graceStartedAt cleared, billing.recovered notification; recovering an active account rejected. | F5: ST-060 | G5: ShiftDesk F-001 / OnCall F-005
A6: F-V03 | B6: High | C6: billing.ts | D6: Trial expiry unenforced: after trialEndsAt the org stayed status=trialing with full write access forever, and the banner showed "Trial: 0 day(s) remaining" indefinitely. The 14-day trial was a label. | E6: FIXED — writeBlocked() treats expired trial as blocked ("Trial ended — choose a plan"), banner states it plainly; choosing a plan unblocks. Old test that pinned the buggy 0-days banner corrected. | F6: ST-057 | G6: ShiftDesk F-013 class
A7: F-V04 | B7: Medium | C7: billing.ts | D7: issueInvoice was the only unguarded billing mutation: no role check (any caller) and no amount validation — zero, negative, and NaN invoices accepted. | E7: FIXED — assertCan billing.manage + positive-finite amount guard; signature now takes userId. | F7: ST-062 | G7: ShiftDesk F-005 class
A8: F-V05 | B8: Medium | C8: store.ts | D8: Every per-org ledger unbounded (notifications 2-per-event, analytics events, audit, activities...) — memory growth defect in a long-lived process; dunning alone kept appending. | E8: FIXED — FIFO cap 10,000 per (org, kind) with droppedCount() telemetry; oldest evicted; "current subscription = last item" semantics regression-pinned. Live Postgres gets a retention policy instead (noted for deploy). | F8: ST-070 infra | G8: FlowCast F-001 / ShiftDesk F-003
A9: F-V06 | B9: High | C9: sfClient.ts | D9: Exponential backoff was a NO-OP in production: default sleep was () => Promise.resolve() — every retry against a struggling platform API fired with zero delay, defeating the documented backoff and hammering Salesforce during 429/503 storms. Tests always injected their own sleep, so 100% coverage never caught it. | E9: FIXED — default sleep is a real setTimeout wait; fake-timer regression asserts a pending 375ms timer between attempts on a bare new SfClient(). | F9: ST-070 | G9: ShiftDesk F-004 (exact class)
A10: F-V07 | B10: High | C10: featureCore.ts / billing.ts | D10: read-only status was enforced NOWHERE — an org 8 days into failed payment (or past trial expiry, per F-V03) kept full write access across dial, logging, cadences, and Flow actions. ST-060 had no teeth. | E10: FIXED — writeBlocked() gate + featureCore.assertWritable() wired into the mutating entry points of dialer, callLogger, cadence (create+enroll), flowActions; coaching reads stay open (ST-060 reads-allowed semantics pinned). | F10: ST-060 | G10: New (portfolio first: billing-status enforcement)
A11: OBS-V1 | B11: Low | C11: analytics.ts | D11: exportCsv joins fields with commas and no RFC-4180 quoting. Current fields (funnel stage names + counts) cannot contain commas, so not a live defect — but any future field with a comma corrupts the export. | E11: NO FIX — logged for disposition; quote-all-fields is a 5-line change if ST-076 scope grows. | F11: ST-076 | G11: ShiftDesk F-006 class (pre-emptive)
A12: OBS-V2 | B12: Low | C12: sfClient.ts | D12: Circuit half-open allows unlimited concurrent probes after cooldown: every caller in the half-open window passes the gate until failures re-accumulate. A single-probe half-open is stricter. | E12: NO FIX — matches FlowCast OBS-002 (also pending disposition); current behaviour recovers correctly, just less politely. | F12: ST-070 | G12: FlowCast OBS-002
A13: F-V08 | B13: High | C13: audit.ts | D13: Self-serve delete (ST-069, promised in HC-12) purged the feature bags only: the org's user ROLE records and its OAuth tokens survived. Same published-policy breach as F-V01, on the other deletion path. | E13: FIXED — deleteMyData now purges bags, deletes all org roles and wipes tokens, and returns {rolesDeleted, tokensWiped}; the audit line is written after the purge so the deletion stays evidenced. 3 regressions incl. cross-org isolation. | F13: ST-069 | G13: VoiceBridge F-V01 (same class, other path)
A14: F-V09 | B14: High | C14: billing.ts | D14: writeBlocked() never considered status 'cancelled'. A cancelled org kept full write access indefinitely — the F-V07 gate had a hole exactly where the pricing page promises 'cancel any time'. | E14: FIXED — cancelled now blocks writes with its own reason; reads and export stay open (2 regressions pin that data is never held hostage). | F14: ST-063/ST-060 | G14: New (extends F-V07)
A15: F-V10 | B15: High | C15: app.ts / softphoneAdapter.ts | D15: ARTIFACT GAP: the Open CTI softphone has always POSTed hang-ups to /log, and no such route existed. Every hang-up in a live org would have 404'd into the adapter's 'saved locally' branch and the activity would never reach the record — the product's headline feature (F2 auto-logging) silently dead. | E15: FIXED — /log route added: closes the call via dialer.transition and writes the activity via callLogger.ingest in one hop, externalId call:<id> so provider replays dedupe. 4 supertest regressions (happy path, empty note, replay, unknown id → clean 400). | F15: ST-011..020 / R-V5 | G15: TestPulse missing Custom UI resource; FlowCast GAP-1/2
... A79: F-V34 | B79: Low | C79: scripts/evidence-manifest.ts | D79: EVIDENCE GATE FALSE POSITIVE ON BUILD OUTPUT: widget/dist/ (built by npm run build) was walked as source, so running the gate after a build in a clean extraction read the bundle's fresh mtime as "evidence predates source". Found by executing the gate from the zip (L-V25) — the first packaging attempt failed its own verification. | E79: FIXED v0.28.0 — build output directories excluded from the manifest walk; test asserts the manifest lists nothing under widget/dist. | F79: ST-068,F-P05 | G79: L-V20 class (a gate that fires on an artefact of its own tooling)

Sheet Remediation_Plan
A1: REMEDIATION PLAN — external review V001 closure package (sequenced to reviewer §8)
A2: Codeable now = no input needed from Senthil. Blocked = named decision first. RM-01..09 = external review V001 (ChatGPT). RM-10..14 = Perplexity review V001 (20 Sep). Status column dated per row.
A3: ID | B3: Findings closed | C3: Work package | D3: Codeable now? | E3: Blocked by | F3: Effort | G3: Sequence | H3: Notes | I3: Status (latest)
A4: RM-01 | B4: VB-CR-002, VB-CR-003 | C4: GET /oauth/callback reading req.query + installer identity bound to a Salesforce-verified source (id_token validation or identity/userinfo with the exchanged token); POST retained as an internal/test path only; redirect to a welcome/bootstrap surface. | D4: Yes | E4: — | F4: M | G4: 1 | H4: Highest leverage: without it no install completes in a browser, and the owner role is assignable by the caller. | I4: CLOSED v0.25.0 — GET callback + Salesforce-verified installer identity, pinned
A5: RM-02 | B5: VB-CR-001 | C5: Authenticated softphone bootstrap: session handed to the in-org surface at load, bearer sent on every protected request, orgId/userId dropped as identity inputs, plus a real end-to-end test driving the actual adapter against createApp(). | D5: Yes | E5: — | F5: M | G5: 2 | H5: The e2e is the point — it is the first test in this codebase that would fail if the two sides disagreed. | I5: CLOSED v0.25.0 — bootstrap handoff + the softphone→API contract test that never existed
A6: RM-03 | B6: VB-CR-004, VB-CR-006 | C6: Production repository factory (DATABASE_URL → pg Pool → PgRepository), pg declared as a production dependency, scripts/ type-checked, fail-fast boot when durable storage is missing in production, migration smoke against ephemeral Postgres in CI. | D6: Yes (live verification = O6) | E6: Postgres instance for O6 | F6: M | G6: 3 | H6: Closes the code half of R-V11 and R-V13 properly; restart + two-instance tests are the acceptance criteria. | I6: CLOSED in code v0.25.0 — factory, pg declared, fail-fast boot, CI migration smoke. Live half = O6 (yours)
A7: RM-04 | B7: VB-CR-005 | C7: Telephony provider adapter (real dial, status webhooks with signature verification, idempotency) + Salesforce REST/Composite Task/Activity write-back with record matching and token refresh. | D7: No | E7: D-V5 provider choice + credentials | F7: L | G7: 4 | H7: The largest package by far and the one that turns the prototype into the product. Story reclassification (D-V4) is the honest interim. | I7: HALF DONE v0.26.0/v0.27.0 — Salesforce write-back built (live proof = O7); telephony SEAM built and simulation now labelled on every surface. The ADAPTER itself and the inbound webhook route remain, blocked on D-V5. Estimated one file plus one route once chosen.
A8: RM-05 | B8: VB-CR-008 | C8: WhatsApp: either port the EngageOS Meta Cloud API pattern (signature verify, opt-in, 24h window, templates, idempotent delivery) or withdraw the claim from help/docs/listing until it exists. | D8: No | E8: D-V6 scope call | F8: L or S | G8: 5 | H8: Withdrawing is a day of copy work; building is comparable to RM-04. Either is acceptable — publishing the claim unbuilt is not. | I8: NOT STARTED — blocked on D-V6 (build the Cloud API path or withdraw the claim)
A9: RM-06 | B9: VB-CR-007 | C9: Named view permissions (billing.view, analytics.view, support.queue.view) enforced before data assembly in buildScreenData and the support queue; owner/admin/member matrix tests including negatives. | D9: Yes | E9: — | F9: S | G9: 6 | H9: Small, self-contained, and a certain security-review finding if left. | I9: CLOSED v0.25.0 — view permissions enforced before assembly; owner/admin/member matrix tested
A10: RM-07 | B10: VB-CR-009, VB-CR-010, VB-CR-013 | C10: Release integrity: regenerate all evidence from the packaged commit with hash + timestamp embedded, fail packaging on stale or missing-file evidence, rename the coverage metric wherever it is published, and clear or formally accept the two moderate advisories. | D10: Yes | E10: — | F10: S/M | G10: 7 | H10: Portfolio-wide: the same evidence pattern and the same coverage sentence ship in every sibling product. | I10: CLOSED v0.25.0 (20:33) — evidence bound to package hash and re-verified after F-V29/F-V30; VB-CR-013 mitigated + accepted to 13 Dec 2026, Express 5 is your call
A11: RM-08 | B11: VB-CR-011, VB-CR-012 | C11: Durable pending-log queue (IndexedDB/localStorage, tenant+user scoped, expiry, cleared on logout/uninstall) or an honest UI sentence; residency required explicitly in production with unverified values marked unverified. | D11: Yes | E11: — | F11: S | G11: 8 | H11: Both are promises the product makes to a rep and to a compliance reader respectively. | I11: CLOSED v0.25.0 — durable pending queue; residency stated or published as unverified
A12: RM-09 | B12: VB-CR-014 | C12: Financial model: base/downside/upside scenarios, explicit funding requirement and runway, cash-minimum month, smaller-team variant, sales-cycle lag, AppExchange approval delay, pilot revenue separated from marketplace GA revenue. | D12: No | E12: D-V7 cost + funding assumptions | F12: M | G12: 9 | H12: Feeds D15 directly — a 5-9 month listing lead time against this burn is the sequencing argument. | I12: NOT STARTED — blocked on D-V7
A13: RM-10 | B13: F-P01, F-P04, F-P05, VB-E-016, VB-E-017 | C13: S14 "truth and hardening": serve the widget + inject config; security headers, rate limits, body cap, timeout, request ids; symmetric evidence gate; claim-to-test registry; Express 5 / Node 22. | D13: Yes | E13: — | F13: M | G13: 10 | H13: All of S14 as written by the reviewer; every acceptance is a test. | I13: CLOSED v0.28.0 (20 Sep 10:45) — S14 complete in code; live half = O7b (panel renders in-org)
A14: RM-11 | B14: F-P02 | C14: Token encryption at rest with key ring + rotation; trust-page sentence backed. | D14: Yes (KMS wiring = live) | E14: — | F14: S | G14: 11 | H14: Conformance test on both stores. | I14: CLOSED v0.28.0 — VB_TOKEN_KEYS mandatory in production
... A17: RM-14 | B17: F-P06, R-V21, R-V22 | C17: S13 decision gate: VB-E-001 Open CTI confirmation (D-V9), VB-E-002 Partner Telephony spike, VB-E-003 provider (D-V5), VB-E-004 WhatsApp (D-V6), VB-E-005 Financial_Model_v2 (D-V7), VB-E-006 strategy (D-V8), VB-E-007 reclassification (D-V4), VB-E-008 discovery interviews. | D17: No | E17: Six decisions + a dev org + 15 interviews — all Senthil | F17: — | G17: 14 | H17: The review's S13 exit gate; blocks every sprint from S15 onward. G-07 lifts here. | I17: NOT STARTED — decision packets written (docs/opencti-retirement-impact.md, salesforce-voice-pt-spike.md, telephony-provider-decision.md addendum); Enhancement_Plan sheet tracks each row

Sheet Enhancement_Plan
A1: ENHANCEMENT PLAN S13-S29 — Perplexity review V001 §6, tracked per story (Option A shape; Option B deletes S15-S18 and makes S21-S22 optional)
A2: Statuses: Done (live evidence) | Code-complete (unproven) — built and tested, no live run | Partial — part built, remainder named | Not started | Blocked (decision or live system named). Owner: Claude = codeable; Senthil = decision/live/vendor. Points: the review gave sprint totals (S14 34, S15 42, S16 34, S17-18 76, S19-20 68, S21-22 72, S23-24 64, S25-26 60, S27 30, S28-29 40), not per-story points; per-story values here are Claude's distribution of those totals and differ by a few points in three sprints — treat them as relative. Rows 5-13 are the S13 decision gate; nothing after S14 should start until they close.
A3: ID | B3: Sprint | C3: Story | D3: Acceptance (observable evidence) | E3: Pts | F3: Owner | G3: Status (20 Sep 10:45) | H3: Evidence / notes | I3: Blocked by
A4: VB-E-001 | B4: S13 | C4: Confirm the Open CTI position with Salesforce directly (partner support case); record whether AppExchange will accept a net-new Open CTI listing at all. | D4: docs/opencti-retirement-impact.md with the case number | E4: 0 | F4: Senthil + Claude | G4: Partial | H4: Fact verified against help.salesforce.com 005306437 (EoL 28 Feb 2028; new Agentforce Service orgs excluded) and the packet written; the partner case is the remaining half. D-V9. BLOCKS EVERYTHING. | I4: Partner case (Senthil)
A5: VB-E-002 | B5: S13 | C5: Spike Salesforce Voice with Partner Telephony in a dev org: install path, connector contract, Contact Center definition, package contents, licence implication. | D5: docs/salesforce-voice-pt-spike.md + scratch-org deploy log | E5: 0 | F5: Claude | G5: Partial | H5: Spike PLAN written (questions, deliverables, sources) — explicitly unverified; execution needs a partner dev org with the add-on. | I5: Dev org with Partner Telephony (Senthil)
A6: VB-E-003 | B6: S13 | C6: D-V5: name the telephony provider on landed cost per minute for the target geography; re-derive SEAT_PRICE. | D6: Decision recorded; SEAT_PRICE re-derived | E6: 0 | F6: Senthil | G6: Not started | H6: Addendum to docs/telephony-provider-decision.md carries the review's rate points; not needed under option (B). | I6: D-V5
A7: VB-E-004 | B7: S13 | C7: D-V6: WhatsApp — build it and make it the lead capability (reviewer recommendation). | D7: Decision recorded; listing copy re-sequenced | E7: 0 | F7: Senthil | G7: Not started | H7: The unbacked claim is already withdrawn (HC-05) and the listing copy gated, so the decision is purely build-or-not. | I7: D-V6
A8: VB-E-005 | B8: S13 | C8: D-V7 + F-P06: rebuild the financial model — base/downside/upside, per-minute cost line, funding requirement, cash-minimum month, solo-build variant, 5-9 month listing lag, ARPU reconciled to ICP, enterprise/annual tier. | D8: Financial_Model_v2 sheet | E8: 0 | F8: Claude + Senthil | G8: Not started | H8: Needs D-V7 cost/funding assumptions and D-V5 per-minute cost; lands in product workbook v030. R-V22. | I8: D-V7, D-V5
A9: VB-E-006 | B9: S13 | C9: Strategy ruling: (A) re-platform to Partner Telephony + lead with WhatsApp (recommended) / (B) AI activity-intelligence layer that never owns the dial path / (C) finish on Open CTI for a cash window (not recommended). | D9: Decision recorded; S14+ scope selected | E9: 0 | F9: Senthil | G9: Not started | H9: D-V8. Packet: docs/opencti-retirement-impact.md. If VB-E-001 says no net-new listing, (C) is void. | I9: D-V8, VB-E-001
A10: VB-E-007 | B10: S13 | C10: Reclassify ST-001..020 to "Code-complete (unproven)"; regenerate the rollup (96/100 → 76/100). Resolves D-V4 as (a). | D10: Both workbooks updated | E10: 0 | F10: Claude | G10: Blocked | H10: D-V4 is Senthil's; both reviewers and this release recommend (a). The DoD clause is already recorded in Gate_Checklist; the Traceability readiness column names the finding on every affected row. | I10: D-V4
A11: VB-E-008 | B11: S13 | C11: Unpark D13 for this product: 15 × 30-minute conversations with Salesforce-using sales leaders, in parallel with S13-S15, gating S16. | D11: Interview notes committed | E11: 0 | F11: Senthil | G11: Not started | H11: Root cause of the review per the reviewer; the S16 exit is the first honest kill point (3 paid-pilot commitments at the ratified price). | I11: D13 (portfolio)
A12: VB-E-010 | B12: S14 | C12: Serve widget/ from the running app; assert the CallCenter adapterUrl path resolves to a registered route; adapter from the packaged static resource OR delete it from the package. (F-P01) | D12: Boot test: GET /widget/softphone.html → 200 with both script tags; metadata-path assertion test | E12: 5 | F12: Claude | G12: Code-complete (unproven) | H12: src/widget.ts; test/widget.test.ts (both assertions); decision: served from host, static resource deleted. Live = O7b. | I12: O7b (dev org)
A13: VB-E-011 | B13: S14 | C13: Set window.VB_CONFIG from CallCenter customSettings, or delete the dead setting. (F-P01) | D13: serviceBase non-empty in the org-shaped case | E13: 2 | F13: Claude | G13: Code-complete (unproven) | H13: Injected server-side from BASE_URL; customSettings deleted from the CallCenter XML; test asserts the injected script and that customSettings is absent. | I13: —
A14: VB-E-012 | B14: S14 | C14: Envelope-encrypt token columns (AES-256-GCM, KMS data key, per-org AAD, key version, rotation path). (F-P02) | D14: Persisted bytes exclude plaintext; rotation re-reads across versions | E14: 5 | F14: Claude | G14: Code-complete (unproven) | H14: src/tokenCipher.ts, migration 009 key_version, scripts/rotate-token-keys.ts; conformance + rotation tests. KMS unwrap at boot = deploy-time. | I14: KMS wiring at deploy
A15: VB-E-013 | B15: S14 | C15: Explicit CSP with frame-ancestors, HSTS, X-Content-Type-Options, Referrer-Policy; body size limit; inbound timeout. (F-P04) | D15: Header assertion test per route class | E15: 5 | F15: Claude | G15: Code-complete (unproven) | H15: src/hardening.ts; test/hardening.test.ts pins every header on json/html/404/401 responses; no helmet (eleven visible lines). | I15: —
... A30: VB-E-040 | B30: S17-18 | C30: Partner Telephony connector implementing the Salesforce-side contract; managed 2GP package containing it. | D30: Package installs in a scratch org; Contact Center created from the definition | E30: 21 | F30: Claude | G30: Blocked | H30: Option (A) only. | I30: D-V8, VB-E-002, dev org
A31: VB-E-041 | B31: S17-18 | C31: Contact Center definition, Omni-Channel enablement and presence sync; agent status both ways. | D31: Agent status changes propagate in both directions | E31: 13 | F31: Claude | G31: Blocked | I31: D-V8, VB-E-040
A32: VB-E-042 | B32: S17-18 | C32: Voice Call records instead of bare Tasks: transcription surface, recording link, participants, disposition. | D32: A live call produces one Voice Call record with transcript | E32: 13 | F32: Claude | G32: Blocked | I32: D-V8, VB-E-040
A33: VB-E-043 | B33: S17-18 | C33: Retire the Open CTI surface behind a feature flag; document the migration for any org already on it. | D33: Both surfaces green in CI; migration guide committed | E33: 8 | F33: Claude | G33: Blocked | H33: Spike question 4 covers the migration steps. | I33: D-V8
A34: VB-E-044 | B34: S17-18 | C34: Namespace registered, Dev Hub configured, 2GP package versions built and promoted through CI. | D34: sf package version create runs in CI on every main build | E34: 8 | F34: Senthil + Claude | G34: Blocked | H34: LC-2; which package (Open CTI shim vs Partner Telephony) depends on D-V8. | I34: D-V8, LC-2
A35: VB-E-045 | B35: S17-18 | C35: Install experience tested in three org shapes + push-upgrade test. (LC-5, LC-7) | D35: Nine documented install runs; upgrade preserves data | E35: 13 | F35: Senthil + Claude | G35: Blocked | I35: D-V8, dev orgs
A36: VB-E-050 | B36: S19-20 | C36: Repository conformance suite against live Postgres in CI (testcontainers): FIFO caps, cascades, unique indexes, nextSeq under concurrency. Closes O6, R-V11, R-V13. | D36: Suite green against Postgres 16; restart and two-instance tests pass | E36: 13 | F36: Claude | G36: Partial | H36: Migration smoke + RLS + audit checks run against Postgres 16 in CI; the behavioural conformance suite still runs against the recording double (which now enforces the tenant contract). Testcontainers job = next; O6 live. | I36: CI Postgres job; O6
A37: VB-E-051 | B37: S19-20 | C37: updateWhere on the Repository contract + a conformance test that mutation via a returned object does not persist; outbox routed through it. (F-P03b) | D37: Test fails on both stores before the fix, passes after | E37: 5 | F37: Claude | G37: Done | H37: Both stores; the test failed on InMemory before list() returned copies (as required) and exposed F-V31/F-V32 across five modules. No live half. | I37: —
A38: VB-E-052 | B38: S19-20 | C38: Background outbox drain: leader-elected worker, backoff with jitter, dead-letter after N attempts, alert on depth and oldest-age. (F-P03a) | D38: Salesforce black-holed 10 minutes; queue drains unattended on recovery | E38: 8 | F38: Claude | G38: Code-complete (unproven) | H38: src/outboxWorker.ts; acceptance met with an injected clock; lease on both stores; VoiceBridgeOutboxStuck rule. Live = O10. | I38: O10 game day
A39: VB-E-053 | B39: S19-20 | C39: Transactional caps and counted constraints on SqlClient so R-V15 closes; blue/green with real tenants unblocked. | D39: Concurrent two-instance test proves the caps hold | E39: 8 | F39: Claude | G39: Code-complete (unproven) | H39: tx() + pushIfCountBelow (advisory xact lock); designPartners slot cap; R-V15 closed at the database; live proof of the lock under two real processes = O6. | I39: O6
A40: VB-E-054 | B40: S19-20 | C40: Observability: structured JSON logs with request/org ids, RED metrics per route, traces across the Salesforce and provider hops, error reporting, a real /metrics. | D40: Dashboard shows a live call end to end across all three systems | E40: 13 | F40: Claude | G40: Partial | H40: Logs, RED metrics, /metrics, error sink, request ids done. Cross-hop TRACES (propagating the request id into outbound Salesforce/provider calls and a trace backend) not built; the dashboard is live-side. | I40: Trace backend; provider (D-V5)
A41: VB-E-055 | B41: S19-20 | C41: SLOs and alerting matching the published 99.5%: error budget, burn alerts, on-call runbook linked from runbook.ts. | D41: Alert fires in a game-day exercise | E41: 8 | F41: Claude | G41: Code-complete (unproven) | H41: src/slo.ts, /status/slo rule export wired to RB-10/RB-11; game day = O10. | I41: O10, alerting backend
A42: VB-E-056 | B42: S19-20 | C42: Replace the echo deploy job with a real blue/green pipeline: migration gate, health gate, automatic rollback. | D42: Two deploys and one deliberate rollback executed | E42: 8 | F42: Claude | G42: Code-complete (unproven) | H42: deploy.yml + scripts/deploy/blue-green.sh; workflow shape tested; execution needs a platform (DEPLOY_CMD etc. per environment). | I42: Hosting platform (ST-092 live)
A43: VB-E-057 | B43: S19-20 | C43: DR drill executed for real: pg_dump/pg_restore against live Postgres, stated RPO/RTO, evidence committed. | D43: Restore verified; RPO/RTO published | E43: 5 | F43: Claude + Senthil | G43: Code-complete (unproven) | H43: scripts/dr-drill.sh (checksum diff, measured RTO, report); execution = O9. | I43: O9 (live Postgres)
A44: VB-E-060 | B44: S21-22 | C44: Meta Cloud API integration: BSP or direct onboarding, number registration, webhook signature verification, idempotent delivery. Closes VB-CR-008 by building. | D44: A real WhatsApp message sent and received end to end | E44: 21 | F44: Claude | G44: Blocked | H44: EngageOS pattern portable (opt-in ledger, 24h window, signature verify). | I44: D-V6, Meta verification
A45: VB-E-061 | B45: S21-22 | C45: Opt-in ledger and the 24-hour customer-care window enforced in code, with template messaging outside it. | D45: Sending outside the window without a template refused with a named error | E45: 8 | F45: Claude | G45: Blocked | I45: D-V6
A46: VB-E-062 | B46: S21-22 | C46: Template management: submission, approval status, per-locale variants, variable validation. | D46: Template rejected by Meta surfaces as an actionable admin error | E46: 8 | F46: Claude | G46: Blocked | I46: D-V6
A47: VB-E-063 | B47: S21-22 | C47: Conversation threading on the CRM record: one thread per contact, participants, unread state, agent assignment. | D47: Thread visible on the Contact with full history | E47: 13 | F47: Claude | G47: Blocked | I47: D-V6
A48: VB-E-064 | B48: S21-22 | C48: Per-conversation cost accounting against Meta's conversation pricing, per org, fed into billing. | D48: Monthly cost report reconciles to the provider invoice | E48: 8 | F48: Claude | G48: Blocked | I48: D-V6
A49: VB-E-065 | B49: S21-22 | C49: Positioning: total-cost comparison against Service Cloud Enterprise $165 + Digital Engagement $75 becomes the primary listing message. | D49: Comparison page published with sourced figures | E49: 5 | F49: Claude + Senthil | G49: Blocked | H49: Would enter the claims registry on publication. | I49: D-V6, D-V3
A50: VB-E-070 | B50: S23-24 | C50: Transcription and diarisation on every recorded call, with language coverage for the launch set. | D50: Transcript on the Voice Call record within target latency | E50: 13 | F50: Claude | G50: Blocked | I50: VB-E-024 recordings, D-V8
A51: VB-E-071 | B51: S23-24 | C51: AI call summary, next steps and sentiment written to the activity; human-editable draft, never a silent write. | D51: Summary present, editable, audited | E51: 13 | F51: Claude | G51: Blocked | I51: VB-E-070
A52: VB-E-072 | B52: S23-24 | C52: Coaching scorecards derived from real transcripts (talk ratio, monologue length, question rate, objection handling); replaces the synthetic coaching.ts metrics. | D52: Scorecard reproducible from a stored transcript | E52: 13 | F52: Claude | G52: Blocked | H52: coaching.ts now at least stores what it computes (F-V32). | I52: VB-E-070
A53: VB-E-073 | B53: S23-24 | C53: Agentforce-invocable and Flow/Apex-invocable actions so the product is composable inside the platform's own AI. | D53: An Agentforce agent places a call and logs the outcome through our action | E53: 13 | F53: Claude | G53: Blocked | H53: flowActions.ts exists (Flow half); Agentforce actions need Apex/metadata in a package — D-V8. | I53: D-V8, D-V5
A54: VB-E-074 | B54: S23-24 | C54: AI governance: model and region disclosure, verifiable no-training guarantee, PII redaction before any model call, per-org opt-out. | D54: Redaction test with synthetic PII; disclosure on the trust page backed by a test | E54: 8 | F54: Claude | G54: Not started | H54: Deliberately not built ahead of the AI layer (Stop_Doing #3) — it would be a claim with nothing behind it. The claims gate will force it the day a model is called. | I54: VB-E-070
A55: VB-E-080 | B55: S25-26 | C55: Postgres row-level security with a per-request tenant context, so isolation is enforced by the database. | D55: Cross-tenant query blocked at the database with the app deliberately misconfigured | E55: 13 | F55: Claude | G55: Code-complete (unproven) | H55: Migration 010 (ENABLE + FORCE, policy over vb.org_id); PgRepository.tx per call; superuser refused in production; db/checks/rls-smoke.sql in CI as a non-superuser role proves exactly the acceptance. Live run = O9. | I55: O9
A56: VB-E-081 | B56: S25-26 | C56: Tamper-evident audit log: hash-chained entries, append-only grant, separate retention, exportable verification. | D56: Verifier detects a tampered row | E56: 8 | F56: Claude | G56: Code-complete (unproven) | H56: audit.ts chain + verifyAuditChain + GET /audit/verify; migration 010 trigger (UPDATE refused, DELETE only under purge); exempt from FIFO cap; db/checks/audit-append-only.sql. Live = O9. | I56: O9
A57: VB-E-082 | B57: S25-26 | C57: Session lifecycle: jti, server-side revocation list, logout, revoke-all-on-role-change, TTL reduced, refresh separated from identity. | D57: Revoked session rejected immediately | E57: 8 | F57: Claude | G57: Done | H57: All in v0.28.0 incl. POST /roles; TTL default 1 day; pre-v0.28 tokens refused. "Refresh separated from identity" = the Salesforce refresh token was never the session — documented rather than built. No live half. | I57: —
A58: VB-E-083 | B58: S25-26 | C58: SSO (SAML/OIDC) and SCIM for any surface outside the Salesforce frame; if none, delete the standalone paths so the claim surface shrinks. | D58: Either working SSO or a smaller attack surface, documented | E58: 13 | F58: Senthil | G58: Blocked | H58: Raised as D-V10 with recommendation (a): the only outside surface is /ui behind the install session. | I58: D-V10
A59: VB-E-084 | B59: S25-26 | C59: Compliance paperwork made real: DPA, named subprocessors with regions, real contacts, GDPR Art. 28/32 mapping, sub-processor change notice. | D59: Trust page has no placeholders; DPA published | E59: 8 | F59: Claude + Senthil | G59: Partial | H59: Contacts from config (honest "not yet published" until set); docs/dpa-template.md maps every Art. 28(3)/32 clause to evidence with [[...]] for the legal entity, hosting/email/payment vendors and notice periods. Naming the entity and vendors = Senthil. | I59: Legal entity, vendors (D-V3, hosting)
A60: VB-E-085 | B60: S25-26 | C60: Third-party penetration test on the live deployment; remediate high and above; retest. | D60: Pen-test report with all high+ closed | E60: 5 | F60: Senthil (vendor) | G60: Blocked | H60: DR-13. Needs a live deployment first. | I60: Live deployment, vendor
A61: VB-E-086 | B61: S25-26 | C61: SOC 2 Type I readiness assessment mapped to code and evidence; Type II observation window opened. | D61: Gap assessment complete; window start date recorded | E61: 5 | F61: Senthil (consultant) | G61: Blocked | H61: security/SECURITY.md control table is the starting map. | I61: Consultant
A62: VB-E-090 | B62: S27 | C62: ISV Partner Program agreement executed; D-V3 decided (Checkout vs ISVforce + COA), LMA configured. Commercials: $999/submission, ~$150/yr listing, 15% (25% OEM). | D62: LC-1 and LC-9 closed | E62: 8 | F62: Senthil | G62: Blocked | I62: D-V3, LC-1
A63: VB-E-091 | B63: S27 | C63: Security review submitted with the full evidence pack: pen-test report, code-scan output, Trust questionnaire, OAuth control self-attestation. | D63: Submission accepted into the queue | E63: 8 | F63: Senthil + Claude | G63: Blocked | H63: Evidence pack generation exists (npm run evidence); O5 self-attestation; pen test. | I63: VB-E-085, D-V8, G-07
A64: VB-E-092 | B64: S27 | C64: Listing assets from the demo-data mode: five screenshots, two-minute video, security tab, demo org. | D64: LC-8 closed | E64: 8 | F64: Senthil + Claude | G64: Blocked | H64: Demo mode + asset plan exist; capture needs a live org and the D-V6-cleared copy. | I64: Dev org, D-V6
A65: VB-E-093 | B65: S27 | C65: Residency statement published from verified configuration, per region. | D65: LC-6 closed | E65: 3 | F65: Claude | G65: Code-complete (unproven) | H65: Config-driven sentences exist and are claims CL-T10/T11; per-region statement doc = when regions are chosen. | I65: Hosting region decision
A66: VB-E-100 | B66: S28-29 | C66: Three paid pilots live with signed order forms, onboarded in under a day each. | D66: Three orgs in production, paying | E66: 13 | F66: Senthil | G66: Blocked | I66: VB-E-033 kill point
A67: VB-E-101 | B67: S28-29 | C67: Two lighthouse references with logo permission. (LC-10) | D67: Written permission committed | E67: 3 | F67: Senthil | G67: Blocked | I67: VB-E-100
A68: VB-E-102 | B68: S28-29 | C68: Activation instrumented against a real cohort; onboarding iterated on observed drop-off. | D68: Activation measured, not modelled | E68: 8 | F68: Claude | G68: Blocked | H68: Funnel analytics exist; needs a cohort. | I68: VB-E-100
A69: VB-E-103 | B69: S28-29 | C69: Security-review remediation cycles absorbed; listing published. | D69: G-01 closed | E69: 8 | F69: Senthil + Claude | G69: Blocked | I69: VB-E-091
A70: VB-E-104 | B70: S28-29 | C70: G-02: ten paying installs from strangers. | D70: G-02 closed | E70: 5 | F70: Senthil | G70: Blocked | I70: VB-E-103
A71: VB-E-105 | B71: S28-29 | C71: Kill/continue evaluated against the S13 rebuilt model with real CAC and LTV. | D71: G-03, G-04 recorded | E71: 3 | F71: Senthil | G71: Blocked | I71: VB-E-005, VB-E-104
A72: ROLLUP (live formulas over this sheet)
A73: Sprint | B73: Stories | C73: Pts | D73: Done | E73: Code-complete (unproven) | F73: Partial | G73: Not started | H73: Blocked | I73: Pts done or code-complete
A74: S13 | B74: =COUNTIF($B$4:$B$71,$A74) -> 8 | C74: =SUMIF($B$4:$B$71,$A74,$E$4:$E$71) -> 0 | D74: =COUNTIFS($B$4:$B$71,$A74,$G$4:$G$71,"Done") -> 0 | E74: =COUNTIFS($B$4:$B$71,$A74,$G$4:$G$71,"Code-complete (unproven)") -> 0 | F74: =COUNTIFS($B$4:$B$71,$A74,$G$4:$G$71,"Partial") -> 2 | G74: =COUNTIFS($B$4:$B$71,$A74,$G$4:$G$71,"Not started") -> 5 | H74: =COUNTIFS($B$4:$B$71,$A74,$G$4:$G$71,"Blocked") -> 1 | I74: =SUMIFS($E$4:$E$71,$B$4:$B$71,$A74,$G$4:$G$71,"Done")+SUMIFS($E$4:$E$71,$B$4:$B$71,$A74,$G$4:$G$71,"Code-complete (unproven)") -> 0
A75: S14 | B75: =COUNTIF($B$4:$B$71,$A75) -> 8 | C75: =SUMIF($B$4:$B$71,$A75,$E$4:$E$71) -> 34 | D75: =COUNTIFS($B$4:$B$71,$A75,$G$4:$G$71,"Done") -> 3 | E75: =COUNTIFS($B$4:$B$71,$A75,$G$4:$G$71,"Code-complete (unproven)") -> 5 | F75: =COUNTIFS($B$4:$B$71,$A75,$G$4:$G$71,"Partial") -> 0 | G75: =COUNTIFS($B$4:$B$71,$A75,$G$4:$G$71,"Not started") -> 0 | H75: =COUNTIFS($B$4:$B$71,$A75,$G$4:$G$71,"Blocked") -> 0 | I75: =SUMIFS($E$4:$E$71,$B$4:$B$71,$A75,$G$4:$G$71,"Done")+SUMIFS($E$4:$E$71,$B$4:$B$71,$A75,$G$4:$G$71,"Code-complete (unproven)") -> 34
A76: S15 | B76: =COUNTIF($B$4:$B$71,$A76) -> 6 | C76: =SUMIF($B$4:$B$71,$A76,$E$4:$E$71) -> 42 | D76: =COUNTIFS($B$4:$B$71,$A76,$G$4:$G$71,"Done") -> 0 | E76: =COUNTIFS($B$4:$B$71,$A76,$G$4:$G$71,"Code-complete (unproven)") -> 1 | F76: =COUNTIFS($B$4:$B$71,$A76,$G$4:$G$71,"Partial") -> 0 | G76: =COUNTIFS($B$4:$B$71,$A76,$G$4:$G$71,"Not started") -> 0 | H76: =COUNTIFS($B$4:$B$71,$A76,$G$4:$G$71,"Blocked") -> 5 | I76: =SUMIFS($E$4:$E$71,$B$4:$B$71,$A76,$G$4:$G$71,"Done")+SUMIFS($E$4:$E$71,$B$4:$B$71,$A76,$G$4:$G$71,"Code-complete (unproven)") -> 5
A77: S16 | B77: =COUNTIF($B$4:$B$71,$A77) -> 4 | C77: =SUMIF($B$4:$B$71,$A77,$E$4:$E$71) -> 34 | D77: =COUNTIFS($B$4:$B$71,$A77,$G$4:$G$71,"Done") -> 0 | E77: =COUNTIFS($B$4:$B$71,$A77,$G$4:$G$71,"Code-complete (unproven)") -> 1 | F77: =COUNTIFS($B$4:$B$71,$A77,$G$4:$G$71,"Partial") -> 0 | G77: =COUNTIFS($B$4:$B$71,$A77,$G$4:$G$71,"Not started") -> 1 | H77: =COUNTIFS($B$4:$B$71,$A77,$G$4:$G$71,"Blocked") -> 2 | I77: =SUMIFS($E$4:$E$71,$B$4:$B$71,$A77,$G$4:$G$71,"Done")+SUMIFS($E$4:$E$71,$B$4:$B$71,$A77,$G$4:$G$71,"Code-complete (unproven)") -> 8
A78: S17-18 | B78: =COUNTIF($B$4:$B$71,$A78) -> 6 | C78: =SUMIF($B$4:$B$71,$A78,$E$4:$E$71) -> 76 | D78: =COUNTIFS($B$4:$B$71,$A78,$G$4:$G$71,"Done") -> 0 | E78: =COUNTIFS($B$4:$B$71,$A78,$G$4:$G$71,"Code-complete (unproven)") -> 0 | F78: =COUNTIFS($B$4:$B$71,$A78,$G$4:$G$71,"Partial") -> 0 | G78: =COUNTIFS($B$4:$B$71,$A78,$G$4:$G$71,"Not started") -> 0 | H78: =COUNTIFS($B$4:$B$71,$A78,$G$4:$G$71,"Blocked") -> 6 | I78: =SUMIFS($E$4:$E$71,$B$4:$B$71,$A78,$G$4:$G$71,"Done")+SUMIFS($E$4:$E$71,$B$4:$B$71,$A78,$G$4:$G$71,"Code-complete (unproven)") -> 0
A79: S19-20 | B79: =COUNTIF($B$4:$B$71,$A79) -> 8 | C79: =SUMIF($B$4:$B$71,$A79,$E$4:$E$71) -> 68 | D79: =COUNTIFS($B$4:$B$71,$A79,$G$4:$G$71,"Done") -> 1 | E79: =COUNTIFS($B$4:$B$71,$A79,$G$4:$G$71,"Code-complete (unproven)") -> 5 | F79: =COUNTIFS($B$4:$B$71,$A79,$G$4:$G$71,"Partial") -> 2 | G79: =COUNTIFS($B$4:$B$71,$A79,$G$4:$G$71,"Not started") -> 0 | H79: =COUNTIFS($B$4:$B$71,$A79,$G$4:$G$71,"Blocked") -> 0 | I79: =SUMIFS($E$4:$E$71,$B$4:$B$71,$A79,$G$4:$G$71,"Done")+SUMIFS($E$4:$E$71,$B$4:$B$71,$A79,$G$4:$G$71,"Code-complete (unproven)") -> 42
A80: S21-22 | B80: =COUNTIF($B$4:$B$71,$A80) -> 6 | C80: =SUMIF($B$4:$B$71,$A80,$E$4:$E$71) -> 63 | D80: =COUNTIFS($B$4:$B$71,$A80,$G$4:$G$71,"Done") -> 0 | E80: =COUNTIFS($B$4:$B$71,$A80,$G$4:$G$71,"Code-complete (unproven)") -> 0 | F80: =COUNTIFS($B$4:$B$71,$A80,$G$4:$G$71,"Partial") -> 0 | G80: =COUNTIFS($B$4:$B$71,$A80,$G$4:$G$71,"Not started") -> 0 | H80: =COUNTIFS($B$4:$B$71,$A80,$G$4:$G$71,"Blocked") -> 6 | I80: =SUMIFS($E$4:$E$71,$B$4:$B$71,$A80,$G$4:$G$71,"Done")+SUMIFS($E$4:$E$71,$B$4:$B$71,$A80,$G$4:$G$71,"Code-complete (unproven)") -> 0
A81: S23-24 | B81: =COUNTIF($B$4:$B$71,$A81) -> 5 | C81: =SUMIF($B$4:$B$71,$A81,$E$4:$E$71) -> 60 | D81: =COUNTIFS($B$4:$B$71,$A81,$G$4:$G$71,"Done") -> 0 | E81: =COUNTIFS($B$4:$B$71,$A81,$G$4:$G$71,"Code-complete (unproven)") -> 0 | F81: =COUNTIFS($B$4:$B$71,$A81,$G$4:$G$71,"Partial") -> 0 | G81: =COUNTIFS($B$4:$B$71,$A81,$G$4:$G$71,"Not started") -> 1 | H81: =COUNTIFS($B$4:$B$71,$A81,$G$4:$G$71,"Blocked") -> 4 | I81: =SUMIFS($E$4:$E$71,$B$4:$B$71,$A81,$G$4:$G$71,"Done")+SUMIFS($E$4:$E$71,$B$4:$B$71,$A81,$G$4:$G$71,"Code-complete (unproven)") -> 0
A82: S25-26 | B82: =COUNTIF($B$4:$B$71,$A82) -> 7 | C82: =SUMIF($B$4:$B$71,$A82,$E$4:$E$71) -> 60 | D82: =COUNTIFS($B$4:$B$71,$A82,$G$4:$G$71,"Done") -> 1 | E82: =COUNTIFS($B$4:$B$71,$A82,$G$4:$G$71,"Code-complete (unproven)") -> 2 | F82: =COUNTIFS($B$4:$B$71,$A82,$G$4:$G$71,"Partial") -> 1 | G82: =COUNTIFS($B$4:$B$71,$A82,$G$4:$G$71,"Not started") -> 0 | H82: =COUNTIFS($B$4:$B$71,$A82,$G$4:$G$71,"Blocked") -> 3 | I82: =SUMIFS($E$4:$E$71,$B$4:$B$71,$A82,$G$4:$G$71,"Done")+SUMIFS($E$4:$E$71,$B$4:$B$71,$A82,$G$4:$G$71,"Code-complete (unproven)") -> 29
A83: S27 | B83: =COUNTIF($B$4:$B$71,$A83) -> 4 | C83: =SUMIF($B$4:$B$71,$A83,$E$4:$E$71) -> 27 | D83: =COUNTIFS($B$4:$B$71,$A83,$G$4:$G$71,"Done") -> 0 | E83: =COUNTIFS($B$4:$B$71,$A83,$G$4:$G$71,"Code-complete (unproven)") -> 1 | F83: =COUNTIFS($B$4:$B$71,$A83,$G$4:$G$71,"Partial") -> 0 | G83: =COUNTIFS($B$4:$B$71,$A83,$G$4:$G$71,"Not started") -> 0 | H83: =COUNTIFS($B$4:$B$71,$A83,$G$4:$G$71,"Blocked") -> 3 | I83: =SUMIFS($E$4:$E$71,$B$4:$B$71,$A83,$G$4:$G$71,"Done")+SUMIFS($E$4:$E$71,$B$4:$B$71,$A83,$G$4:$G$71,"Code-complete (unproven)") -> 3
A84: S28-29 | B84: =COUNTIF($B$4:$B$71,$A84) -> 6 | C84: =SUMIF($B$4:$B$71,$A84,$E$4:$E$71) -> 40 | D84: =COUNTIFS($B$4:$B$71,$A84,$G$4:$G$71,"Done") -> 0 | E84: =COUNTIFS($B$4:$B$71,$A84,$G$4:$G$71,"Code-complete (unproven)") -> 0 | F84: =COUNTIFS($B$4:$B$71,$A84,$G$4:$G$71,"Partial") -> 0 | G84: =COUNTIFS($B$4:$B$71,$A84,$G$4:$G$71,"Not started") -> 0 | H84: =COUNTIFS($B$4:$B$71,$A84,$G$4:$G$71,"Blocked") -> 6 | I84: =SUMIFS($E$4:$E$71,$B$4:$B$71,$A84,$G$4:$G$71,"Done")+SUMIFS($E$4:$E$71,$B$4:$B$71,$A84,$G$4:$G$71,"Code-complete (unproven)") -> 0
A85: TOTAL | B85: =SUM(B74:B84) -> 68 | C85: =SUM(C74:C84) -> 504 | D85: =SUM(D74:D84) -> 5 | E85: =SUM(E74:E84) -> 15 | F85: =SUM(F74:F84) -> 5 | G85: =SUM(G74:G84) -> 7 | H85: =SUM(H74:H84) -> 36 | I85: =SUM(I74:I84) -> 121
A86: Reading this table: "Done" here means live evidence exists (only the pure-code stories VB-E-015/016/017/051/082 qualify today, because their evidence IS the build). Code-complete (unproven) is what a solo build can reach without a live org, Postgres, carrier or vendor. Points: see the note in row 2.
