Workbook

Sheet Version_Control
A1: VERSION CONTROL — FlowCast Sprint Tracker & Traceability
A2: File naming: claude_v<NNN>_<proper file name>_YYYYMMDD_HHMI. Consolidates the v008–v013 product-workbook run (10 Sep 2026, 22:01–23:03).
A3: Version | B3: Date/Time | C3: Author | D3: Change Description | E3: Status
A4: v001 | B4: 2026-09-10 23:08 | C4: Claude for Senthil/KP | D4: THIS FILE — Live execution tracker for FlowCast (portfolio rank 12, Xero App Store): full event log of the v008–v013 build run, per-release build boards, 106-row traceability with done-in-version stamps, live status rollup, decisions, RAID, and the D7 completion gate. Source of truth for story data remains the product workbook (v013). | E4: Released
A5: v002 | B5: 2026-09-11 11:09 | C5: Claude for Senthil/KP | D5: Cold-review pass 1 + security sprint (workbook v014): 5 defects F-001..F-005 found+fixed with regressions (Review_Findings sheet added for Senthil dispositions); ST-066 encryption-at-rest module built; security evidence pack (sandbox half of ST-068) + REVIEW_PACK.md for external second reviewer. 18 suites / 207 tests at 100% zero pragmas. Statuses: ST-066 -> Code-complete pending live, ST-068 -> In progress. 78 Done-equivalent unchanged (honest-status rule: neither flips to Done) | E5: Released
A6: v003 | B6: 2026-09-11 12:47 | C6: Claude for Senthil/KP | D6: Cold-review pass 2 (workbook v015): 4 defects F-006..F-009 fixed with regressions across nudges/install/forecast/scenarios; 2 no-fix observations (OBS-001 backoff jitter, OBS-002 half-open probe concurrency) logged for disposition. 19 suites / 219 tests at 100% zero pragmas. Cold review complete across all 27 modules. Story statuses unchanged (fix work lands under existing Done stories; honest-status rule) | E6: Released
A7: v004 | B7: 2026-09-11 15:27 | C7: Claude for Senthil/KP | D7: Code-phase-completion wave (workbook v016): ST-081 chat+SLA engine (chat-vendor decision now optional — logged D-F6), ST-099 SEO engine half, ST-100 partner tracker with honest exit math, ST-080 help search + manifest gate, ST-095 pricing drift gate. All five Backlog/Drafted/In-progress codeable halves -> Code-complete pending live. Backlog ZERO. 20 suites / 243 tests at 100% zero pragmas. FLOWCAST CODE PHASE COMPLETE — no further code sprints planned; v005 opens on live evidence, dispositions, or reviewer findings | E7: Released
A8: v005 | B8: 2026-09-11 22:08 | C8: Claude for Senthil/KP | D8: External verification sweep + artifact-gap audit (workbook v017): VER-001 live-blocking webhook body fixed, VER-002 daily budget added, VER-003 scope-audit self-consistency fixed, GAP-1/2 CI + blue/green artifacts built. 21 suites / 256 tests at 100% zero pragmas. Story statuses unchanged (verification hardening under existing stories). Sweep step 4 would have failed live without this pass | E8: Released
A9: v006 | B9: 2026-09-13 10:25 | C9: Claude for Senthil/KP | D9: Integration + artifact audit (workbook v018): GAP-F1 critical — no runnable application existed behind the documented boot/deploy path; INT-F1/F2 critical — the v014 plan-limit fix and the ST-066 token sealing had no callers; INT-F3/F5 — role matrix and read-only mode enforced nothing. Composition root + real HTTP app built and verified by booting the artifact. 22 suites / 283 tests at 100% zero pragmas. Story positions unchanged (integration correctness, not new stories). Lesson L-F1 logged | E9: Released
A10: v007 | B10: 2026-09-13 10:38 | C10: Claude for Senthil/KP | D10: Cold-review pass 3 (workbook v019) over the HTTP layer and composition root that v018 created: F3-01 no OAuth install routes (critical), F3-02 queue never drained + unbounded (critical), F3-03 OAuth CSRF state, F3-04 public /health leak. Dedupe tenant-scoping verified clean. R-F9 opened: no real XeroOAuthClient exists, so the routing half of sweep step 2 is closed but the client half remains. 23 suites / 317 tests at 100% zero pragmas. Story positions unchanged. Lesson L-F2 logged | E10: Released
A11: v008 | B11: 2026-09-13 10:55 | C11: Claude for Senthil/KP | D11: Portable reachability gate ported + wired into CI (workbook v020); first run found GAP-F2 (no scheduler existed — six periodic behaviours undriven, incl. the daily nudge cycle and the entire bank-poll mechanism) and R-F10 (TLS guard never called); 3 dead helpers deleted rather than exempted; R-F9 closed with the real Xero OAuth client. 25 suites / 348 tests at 100% zero pragmas. Story positions unchanged. Lesson L-F3 logged | E11: Released
A12: v009 | B12: 2026-09-13 11:07 | C12: Claude for Senthil/KP | D12: R-F10 closed with the Xero accounting-API client (paced + protected, safe date handling, single-fetch) and the published-claims gate ported (workbook v021). The claims gate did not work when first written — comments satisfied it; fixed across both gates and re-proved by deliberately breaking a promise. 27 suites / 377 tests at 100% zero pragmas. Story positions unchanged. Lesson L-F4 | E12: Released
A13: v010 | B13: 2026-09-13 11:15 | C13: Claude for Senthil/KP | D13: Cold-review pass 4 (workbook v022) over the scheduler and accounting client built in the previous two sittings, under the L-F2 standing rule: 4 defects, all mine — F4-01 critical (only the first tenant was ever polled), F4-02 dunning counter not persisted, F4-03 full history fetched every poll, F4-04 failed drain lost its batch. Regressions proved against the reintroduced defect. 28 suites / 388 tests at 100% zero pragmas. Story positions unchanged. Lesson L-F5 | E13: Released
A14: v011 | B14: 2026-09-13 11:20 | C14: Claude for Senthil/KP | D14: Tenant-isolation gate built and wired into CI (workbook v023), automating the F4-01 class. The gate passed twice against the reintroduced real defect before two of its own bugs were found and fixed — both made it silently permissive. 29 suites / 394 tests at 100% zero pragmas; three gates in CI. Story positions unchanged. Lesson L-F6 | E14: Released
... A24: v021 | B24: 2026-09-13 18:48 | C24: Claude for Senthil/KP | D24: Async-ownership gate + review playbook (workbook v033). Real defect first: worker drain failures were unhandled rejections invisible to the degradation counter. Sixth gate proved against the CHAOS-1 shape. Playbook records the eight review passes and the rules behind ~40 defects found in code already at 100%. 36 suites / 500 tests at 100% zero pragmas; six gates in CI. Stopping point recommended | E24: Released
A25: v022 | D25: PLANNED: opens on live evidence or dispositions — no further sandbox sprints recommended | E25: Planned

Sheet Sprint_Tracker_Log
A1: SPRINT TRACKER LOG — every execution event of the v008–v013 run, newest last
A2: Version column ties each event to the product-workbook release that recorded it.
A3: ID | B3: Date/Time | C3: Version | D3: Sprint | E3: What happened | F3: Refs | G3: State changes | H3: Blockers | I3: Next
A4: E001 | B4: 2026-09-10 22:01 | C4: v008 | D4: — | E4: RUN OPENED — Senthil directive: create sprint tracker + traceability, develop per sprint under D13 (100% coverage gate supersedes ≥70%); ST-085 amended accordingly | F4: D13, ST-085 | G4: v008 opened from v007 baseline | H4: None | I4: E002
A5: E002 | B5: 2026-09-10 22:01 | C5: v008 | D5: S1 | E5: FOUNDATION BUILT (TypeScript): OAuth install/uninstall/reinstall-within-retention, rotation-safe token refresh, install source attribution, owner/admin/member permission matrix + audit log. Xero OAuth client mocked | F5: ST-051..056, ST-054, ST-067 | G5: S1 done-in-code | H5: Live install = Xero dev org (Senthil) | I5: E003
A6: E003 | B6: 2026-09-10 22:01 | C6: v008 | D6: S2-S3 | E6: FORECAST + SCENARIOS: 13-week bucketing engine, traffic lights, validation, pause-without-loss; scenario levers + validation + preview | F6: ST-001/002/004/008, ST-011..014 | G6: Core F1/F2 done-in-code | H6: None | I6: E004
A7: E004 | B7: 2026-09-10 22:01 | C7: v008 | D7: S5-S8 | E7: NUDGES, PORTAL, BILLING, ANOMALIES, COMPLIANCE, TELEMETRY, ONBOARDING: rule-ladder chasing w/ test mode + retry, multi-client book + CSV importer, trial/proration/rails/dunning/limits/GST-VAT/cancellation, z-score + duplicate detection, scope audit + export/delete + backoff/breaker, funnel/errors/heatmap/health, checklist + empty states + review ask + incident comms | F7: ST-021..085 (code subset) | G7: 58 stories Done at v008 | H7: None | I7: E005
A8: E005 | B8: 2026-09-10 22:01 | C8: v008 | D8: — | E8: D13 GATE MET: 11 suites, 120 tests, 100% stmts/branches/funcs/lines, threshold enforced in jest.config.js | F8: D13 | G8: Evidence: coverage-summary.json | H8: None | I8: E006
A9: E006 | B9: 2026-09-10 22:20 | C9: v009 | D9: S2 | E9: ST-003 COMPLETED: full rule builder (min_balance / amber_floor / week_drop_pct over week ranges) | F9: ST-003 | G9: In progress -> Done | H9: None | I9: E007
A10: E007 | B10: 2026-09-10 22:20 | C10: v009 | D10: S3-S8 | E10: UI SURFACES (React + RTL): Forecast, Scenario, Nudges, Portal, Anomalies screens with Xero deep links + empty states; MetricsPanel; per-feature metrics/trends; notifications w/ per-type mute + digest; pause toggles; portal workflow rules | F10: ST-005/015/025/035/045, ST-006/016/026/036/046, ST-010/050, ST-018/038, ST-033 | G10: 16 more stories Done (74 total) | H10: None | I10: E008
A11: E008 | B11: 2026-09-10 22:20 | C11: v009 | D11: S4 | E11: ST-086 CI WIRING: GitHub Actions workflow (push/PR/deployment) runs typecheck + jest with 100% gate | F11: ST-086 | G11: In progress -> Code-complete pending repo hookup | H11: Real repo = Senthil | I11: E009
A12: E009 | B12: 2026-09-10 22:20 | C12: v009 | D12: — | E12: D13 GATE MET: 13 suites, 148 tests, 100% incl. React components; tsc clean | F12: D13 | G12: — | H12: None | I12: E010
A13: E010 | B13: 2026-09-10 22:27 | C13: v010 | D13: S4/S6 | E13: ST-020/ST-040: scenario + portal notification event types | F13: ST-020, ST-040 | G13: 2 more Done | H13: None | I13: E011
A14: E011 | B14: 2026-09-10 22:27 | C14: v010 | D14: S8 | E14: RELIABILITY + A11Y: p95 budgets per surface + evaluator; degradation levels + honest user comms + DegradedBanner; jest-axe WCAG — zero violations on all 7 surfaces | F14: ST-087, ST-089, ST-091 | G14: 3 -> Code-complete pending live | H14: Live monitoring/chaos/audit = infra | I14: E012
... A91: E088 | B91: 2026-09-13 12:03 | C91: v026 | D91: — | E91: RUN CONTINUED — 12:03. I had already said the codeable work was finished, so rather than invent a sitting: audited whether the workbook story data still matches as-built reality (the drift MeetSync found in its own workbook), and consolidated the handover | F91: — | G91: v026 opened from v025 | H91: — | I91: E089
A92: E089 | B92: 2026-09-13 12:03 | C92: v026 | D92: — | E92: AS-BUILT FINDING: 7 stories had sat at DONE while the behaviour had no driver or no enforcement — ST-022/024 (the daily nudge cycle never ran until v020), ST-041/042/044 (bank polling is the ENTIRE anomaly mechanism under D-F4 and never ran until v020, then ran for only ONE org until v022), ST-060 (read-only enforced nowhere until v018, dunning emails never sent until v020, counter unpersisted until v022), ST-061 (plan limit unenforceable until v014, unenforced on the send path until v018). All are true as built TODAY. Each row now carries a dated as-built note naming the release that actually made it true, instead of leaving the record implying it was true all along | F92: ST-022/024/041/042/044/060/061 | G92: Full_Backlog as-built column | H92: Honest-status rule
A93: E090 | B93: 2026-09-13 12:03 | C93: v026 | D93: — | E93: COUNTS VERIFIED against Full_Backlog rather than asserted from narrative: 77 Done / 16 code-complete pending live / 2 in progress / 5 drafted = 100. No drift found in the counts themselves | F93: — | G93: Full_Backlog | H93: —
A94: E091 | B94: 2026-09-13 12:03 | C94: v026 | D94: — | E94: SENTHIL_HANDOVER sheet added consolidating all 12 remaining items — NONE codeable — ordered by leverage: external lead times first (dev org ~30 min unlocks 16 stories, pen-test vendor 2-4 weeks, external reviewer, partner application 1-3 weeks), then ~30 finding dispositions + OBS calls, then decisions (copy A/B, D-F6, D15), then post-dev-org capture and partner outreach, and finally the portfolio question of porting the gate pack. Each row states why it is blocked on him, what it unlocks, effort and lead time | F94: — | G94: Senthil_Handover | H94: All 12 = Senthil
A95: E092 | B95: 2026-09-13 12:03 | C95: v026 | D95: — | E95: LESSON L-F9: "Done" in this backlog has meant "code written", not "feature runs end to end" — 7 stories proved it, and every one of them was caught by a later review rather than by the status field. The three gates now close that gap mechanically for the reachability and published-claims classes. For the record: FlowCast code stands at 29 suites / 395 tests, 100% all metrics, zero pragmas, three PROVED gates in CI, boots end to end. Further sandbox sittings would be invented work; v015 opens on live evidence or dispositions | F95: — | G95: Tracker v014 + workbook v026 released | H95: All remaining = Senthil | I95: v015 on live evidence
A96: E093 | B96: 2026-09-13 16:24 | C96: v027 | D96: — | E96: RUN CONTINUED — 16:24. I had said further sittings would be invented work, so rather than invent one: the siblings closed a gap today that FlowCast still had open. OnCall (GAP-OC2), EngageOS (GAP-E2) and TeleField (R-T4) all shipped persistence layers; FlowCast had NO schema and no store at all — every Map in src was process memory | F96: — | G96: v027 opened from v026 | H96: — | I96: E094
A97: E094 | B97: 2026-09-13 16:24 | C97: v027 | D97: S1, S6 | E97: GAP-F3 (CRITICAL): all durable state lived in process memory — tokens, usage cycles, nudge history, dunning counters, poll state, deletion schedules. R-F4 had recorded this as a deliberate sandbox constraint and while nothing could RUN it was harmless. It stopped being harmless at v018 (boot path) and v017 (deploy pipeline), because BLUE/GREEN RESTARTS THE PROCESS BY DESIGN: every release would have dropped all tokens (every tenant must reinstall), reset usage counters (a fresh 50 nudges per org — undoing F-005 and INT-F1), cleared nudge history (re-chasing every customer from the gentle tier — undoing F-006), reset dunning counters (resending day-0 emails — undoing F4-02) and lost deletion schedules (the published 30-day policy never firing for anyone installed before the restart — undoing F-007 and GAP-F2). SIX earlier fixes, each individually correct, silently reverted on every deploy | F97: GAP-F3 | G97: 24 persistence regressions incl. the two-process restart-survival proof | H97: DATABASE_URL = Senthil | I97: E095
A98: E095 | B98: 2026-09-13 16:24 | C98: v027 | D98: S1 | E98: BUILT: 6 ordered idempotent migrations recorded in schema_migrations, every dependent table declaring ON DELETE CASCADE from tenants so the F-007 deletion policy lives in the SCHEMA rather than in application code that can forget; a narrow Repository seam with InMemoryRepository (kept for tests and demo mode) and PostgresRepository over an injected query fn, both driven through the SAME shared test suite so the two cannot drift; real pooled pg driver with SSL required off-localhost; app.hydrate() rebuilding a tenant view on boot; /health now reports durableStore so an operator can SEE whether state survives a restart instead of assuming it | F98: GAP-F3 | G98: shared describe.each suite across both implementations | H98: — | I98: E096
A99: E096 | B99: 2026-09-13 16:24 | C99: v027 | D99: — | E99: THE REACHABILITY GATE EARNED ITS PLACE TWICE ON THIS SITTING OWN CODE: (1) it failed the build because the persistence layer was built but never wired into the boot path — the exact INT-F1 shape, caught within minutes rather than two sittings later; (2) it flagged closePool as having no caller, which surfaced that GRACEFUL SHUTDOWN DID NOT EXIST — the blue/green pipeline kills the old slot, so in-flight requests were cut and pooled connections dropped rather than drained. SIGTERM/SIGINT handlers added | F99: GAP-F3 | G99: shutdown + signal-registration regressions | H99: — | I99: E097
A100: E097 | B100: 2026-09-13 16:24 | C100: v027 | D100: — | E100: D13 GATE MET: 30 suites, 433 tests, 100% all metrics, zero pragmas, tsc clean, all three gates still PROVED, built artifact boots and reports durableStore honestly. Restart-survival proof: two FlowCastApp instances over one store — the second, as after a deploy, still reports 50 used, still refuses the 51st, still holds the nudge history; before this release it reported 0. LESSON L-F10: the gates check the code against itself and CANNOT see a constraint the code never states — "this process is assumed to live forever" was nowhere in the source, so nothing could flag that six correctness fixes were reverted on every deploy. Assumptions about the ENVIRONMENT need their own review pass: what does this code believe about the world that no test asserts? | F100: D13 | G100: Tracker v015 + workbook v027 released | H100: DATABASE_URL joins the live queue | I100: v016 on live evidence
A101: E098 | B101: 2026-09-13 16:38 | C101: v028 | D101: — | E101: RUN CONTINUED — 16:38, acting on L-F10 from the previous release: the gates check code against itself and cannot see an assumption about the environment, so I asked what this code believes about the world that no test asserts. Three findings, every one broken by the deploy model this codebase already ships | F101: — | G101: v028 opened from v027 | H101: — | I101: E099
A102: E099 | B102: 2026-09-13 16:38 | C102: v028 | D102: S8 | E102: ENV-1 FIXED (CRITICAL): startScheduler assumed EXACTLY ONE PROCESS would ever exist. Nothing in the code said so and the deploy model says the opposite — blue/green runs BOTH colours simultaneously during a switch, and horizontal scaling runs N. With N instances every scheduled job ran N times: every overdue customer received N NUDGES ON THE SAME DAY (precisely the duplicate chasing F-006 was written to prevent, now caused by deployment rather than logic), N dunning emails, N bank polls multiplying spend against the 5,000/day org budget VER-002 protects, and N concurrent purge runs racing the same rows. Fixed with a Postgres session-scoped advisory lock, namespaced by key, re-checked PER TICK so a follower promotes itself when the leader dies without a restart; pg_try_advisory_lock returns immediately so a follower never blocks a deploy | F102: ENV-1 | G102: 7 regressions incl. blue/green overlap refusal, leadership transfer, follower-runs-nothing, leader-runs-work | H102: — | I102: E100
A103: E100 | B103: 2026-09-13 16:38 | C103: v028 | D103: S8 | E103: ENV-2 FIXED (CRITICAL): accepted webhook events lived only in memory, but the fast-ack contract tells Xero 200 and XERO NEVER REDELIVERS A 200 — so a restart between ack and drain destroyed those events permanently and silently, the one failure mode the whole redelivery-heals design exists to avoid. Events are now written to webhook_queue BEFORE the ACK, recoverQueue() restores undrained events on boot, and draining uses FOR UPDATE SKIP LOCKED so a second drainer cannot claim the same row. The table deliberately has NO foreign key (events can arrive before an install row exists), so deleteTenant clears it explicitly and the schema test now enforces that every non-cascading table gets that treatment — otherwise the 30-day deletion policy would leak through the ingest buffer | F103: ENV-2 | G103: persist-before-ack, boot recovery, drain-removes, no-repo unchanged, concurrency-safe SQL | H103: — | I103: E101
A104: E101 | B104: 2026-09-13 16:38 | C104: v028 | D104: S10 | E104: ENV-3 FIXED (Major): BusinessHours documented startHour/endHour as local but every calculation used epoch-ms arithmetic, which is UTC. The published "4 business hours" first-response promise was therefore simply WRONG for any support desk not on UTC — an India-based team (UTC+5:30) had deadlines computed against a working day ending 22:30 their time. utcOffsetMinutes is now explicit and applied to day, hour and midnight derivation, validated to +/-14h. DST is a deliberate non-goal recorded as OBS-003 rather than faked | F104: ENV-3 | G104: IST deadlines, UTC no-regression, local-weekend (Auckland UTC+13), offset validation | H104: OBS-003 disposition | I104: E102
A105: E102 | B105: 2026-09-13 16:38 | C105: v028 | D105: — | E105: D13 GATE MET: 31 suites, 453 tests, 100% all metrics, zero pragmas, tsc clean, three gates still PROVED, artifact boots and reports durableStore AND singleWriter truthfully (both false without a database — the fallbacks are correct for one process and unsafe for several, and the product now SAYS so). OBS-004 logged NOT fixed: webhook-driven rate limiting stays per-process; with the leader lock all SCHEDULED Xero traffic is single-writer so the budgets hold for the dominant path, but webhook-triggered calls from N instances could still exceed them under sustained load — a shared counter needs a decision on per-call round-trip cost, so it is a disposition not a silent change. LESSON L-F11: every finding came from reading the DEPLOY PIPELINE against the APPLICATION CODE — two artifacts each correct alone. ENV-1 existed the moment v017 shipped blue/green, and no amount of staring at the scheduler would have revealed it, because the scheduler is right if you believe what it believes. The productive question was not "is this code correct?" but "what has to be true for this code to be correct, and who guarantees it?" | F105: D13 | G105: Tracker v016 + workbook v028 released | H105: OBS-003/004 = Senthil | I105: v017 on live evidence
A106: E103 | B106: 2026-09-13 16:47 | C106: v029 | D106: — | E106: RUN CONTINUED — 16:47, applying the L-F11 method (read one artifact against another) to the pairing not yet tried: the OPERATIONAL artifacts — deploy pipeline, verify-slot script, runbooks — against the DATABASE that only started existing two releases ago. All of them were written when FlowCast had no store | F106: — | G106: v029 opened from v028 | H106: — | I106: E104
... A109: E106 | B109: 2026-09-13 16:47 | C109: v029 | D109: S8 | E109: OPS-2 FIXED (Major) + FOURTH GATE: blue/green runs TWO releases against ONE database, and rollback re-points to the old colour AFTER the new schema is applied — so a dropped or renamed column would break the old slot mid-switch AND invalidate the documented rollback, under which the previous release then runs against the newer schema indefinitely. Nothing enforced this. tests/migrationSafetyGate.test.ts enforces expand/contract: migrations may only ADD, must be idempotent, and any removal needs an approval citing the release that dropped the last reader. Proved against all 7 destructive shapes. The launch-day runbook now states the rollback contract explicitly rather than implying it | F109: OPS-2 | G109: 7 destructive-shape proofs + additive pass + stale-approval check | H109: — | I109: E107
A110: E107 | B110: 2026-09-13 16:47 | C110: v029 | D110: — | E110: BACKUP DRILL MADE CONCRETE: it said "row counts per table" when no tables existed. Now names all 8, and adds two checks the schema makes possible — that schema_migrations on the restored copy matches the release being restored (an older snapshot restores a schema the current code does not expect), and that refresh_token_sealed is STILL SEALED in the restore, since a backup that decrypted tokens at rest would be a finding in its own right | F110: ST-090 | G110: docs/runbooks/backup-restore-drill.md | H110: Drill execution = live infra
A111: E108 | B111: 2026-09-13 16:47 | C111: v029 | D111: — | E111: D13 GATE MET: 33 suites, 465 tests, 100% all metrics, zero pragmas, tsc clean; four gates in CI with the three older ones still PROVED; built artifact returns {"ready":true,"store":"ok"}. LESSON L-F12: OPS-1 and OPS-3 were each survivable alone and FATAL TOGETHER — one breaks the slot, the other certifies it and switches traffic onto it. Reviewing artifacts in PAIRS finds what reviewing them in a list does not: the deploy pipeline and the health endpoint were both individually defensible and their INTERACTION was the defect. The pairing that found this (ops artifacts x the newest subsystem) is worth re-running whenever a subsystem is added, because every artifact written before it still encodes a world without it | F111: D13 | G111: Tracker v017 + workbook v029 released | H111: All remaining = Senthil | I111: v018 on live evidence
A112: E109 | B112: 2026-09-13 16:52 | C112: v030 | D112: — | E112: RUN CONTINUED — 16:52, re-running the L-F12 pairing against the newest subsystem as that lesson recommends. The degradation artifacts (chaos runbook, degraded banner, /status) were written when XERO WAS THE ONLY DEPENDENCY; Postgres has been in every request path for three releases and fails differently — Xero going away degrades a feature, the database going away touches everything at once, and both blue/green colours share one database | F112: — | G112: v030 opened from v029 | H112: — | I112: E110
A113: E110 | B113: 2026-09-13 16:52 | C113: v030 | D113: S8 | E113: CHAOS-1 FIXED (CRITICAL): two "void somePromise()" calls sat on the database path — one on the WEBHOOK FAST-ACK ROUTE. Since Node 15 an unhandled rejection TERMINATES THE PROCESS by default; verified on this runtime (node v22) with a three-line script — the process died and the follow-up log line never printed. So a transient Postgres error during ordinary webhook traffic would not have degraded FlowCast, it would have KILLED it, on every instance sharing that database simultaneously, leaving the router nothing to fall back to. Both sites now run through safely() (counts, reports, always resolves); process guards report unhandled rejections while the service continues and drain deliberately on uncaught exceptions; 3+ consecutive failures surface as store:degraded on /ready | F113: CHAOS-1 | G113: 12 regressions incl. signed webhook to an all-failing store still ACKing 200 empty with the failure counted | H113: — | I113: E111
A114: E111 | B114: 2026-09-13 16:52 | C114: v030 | D114: S8 | E114: CHAOS-2 FIXED (Major): the chaos runbook covered only the Xero API. Extended with a database-outage drill stating expected behaviour per path — /health 200 liveness only (must not flap the LB), /ready 503 unavailable (deploy gate and router must not send traffic), webhook still 200 empty (Xero given no reason to retry, event held in memory, failure counted), scheduled jobs skipped because the leader lock cannot be acquired (the correct failure, not a silent duplicate run), process stays up. Every row is backed by a test rather than an intention | F114: CHAOS-2 | G114: docs/runbooks/chaos-platform-outage.md | H114: Drill on live infra = Senthil
A115: E112 | B115: 2026-09-13 16:52 | C115: v030 | D115: — | E115: D13 GATE MET: 35 suites, 478 tests, 100% all metrics, zero pragmas, tsc clean; four gates in CI with the three provable ones still PROVED; live boot returns {"ready":true,"store":"ok"}. Two defensive-unreachable fallbacks removed rather than pragma-suppressed — buildLiveContext always sets the degradation state and reporter, so "?? fallback" at the call site was dead code pretending to be caution. LESSON L-F13: "void promise" is the quietest way to write a crash. It reads as fire-and-forget and on modern Node means fire-and-exit. BOTH instances were added deliberately, to keep a durable write off the latency path — a correct instinct expressed in a way that made a dependency failure fatal. Asynchronous work needs an OWNER: something that catches, counts and reports. Worth grepping the other products for the same two characters | F115: D13 | G115: Tracker v018 + workbook v030 released | H115: All remaining = Senthil | I115: v019 on live evidence
A116: E113 | B116: 2026-09-13 17:23 | C116: v031 | D116: S9 | E116: RUN CONTINUED — 17:23. Two documents sit on SENTHIL critical path: the pen-test vendor scopes from SECURITY_EVIDENCE.md and the external reviewer (ST-097) works from REVIEW_PACK.md. Both written at v014. Measured against source: the security pack mentioned the database ZERO times, the review pack ONE of the eight newest modules. The two people most likely to find something would have been handed a map of a product that no longer exists — and the pen-test scoped without the component holding the tokens | F116: SEC-1, REV-1 | G116: docs/live-sweep/document-review-20260913.md | H116: Vendor + reviewer = Senthil | I116: E114
A117: E114 | B117: 2026-09-13 17:23 | C117: v031 | D117: S9 | E117: SEC-1 FIXED: data-store section added to the security pack, deliberately separating controls VERIFIABLE IN CODE (refresh tokens sealed before reaching the store, TLS off-localhost, cascade deletion of every dependent row, additive-only migrations, no committed secrets) from OPERATOR RESPONSIBILITIES code cannot assert (volume encryption at rest, least-privilege database user, backup encryption, DATABASE_URL held in the secret manager, network reachability). Claiming a provider setting nobody has confirmed is exactly what INT-F2 already forced an addendum for. Vendor scope note added covering OAuth routes + CSRF state, webhook signature path, what /health and /ready each disclose, the Postgres store and migration path, and leader-lock behaviour under concurrent instances | F117: SEC-1 | G117: pen-test scoping | H117: Vendor engagement = Senthil | I117: E115
A118: E115 | B118: 2026-09-13 17:23 | C118: v031 | D118: S9 | E118: SEC-2 FIXED (code): failure text is written to stderr AND held in the degradation state, and driver errors can include the connection string — which contains the password. redactSecrets now strips user:pass@host, password=/pwd=/secret=/api_key= pairs and bearer tokens before a failure is recorded. THREE new claims added to the published-claims gate (DB TLS, credential redaction, tokens sealed in the store), one of which requires the redactor to be CALLED not merely present — proved to fail when the call is removed | F118: SEC-2 | G118: 4 redaction regressions + 3 gate claims, one proved by removal | H118: — | I118: E116
A119: E116 | B119: 2026-09-13 17:23 | C119: v031 | D119: S9 | E119: REV-1 FIXED: review pack rewritten with current entry points, a per-module what-to-challenge table for the eight new subsystems, and a review order by consequence (money and enforcement first; then the ack contract where losing an event is silent and permanent; then deletion semantics, on which the published 30-day policy entirely depends). It explicitly tells the reviewer to DISTRUST THE GATES — four gate bugs shipped green while silently permissive, so they are evidence of intent not correctness — and lists OBS-001..004 openly. PERF-1: latency budgets predated every database round trip; table added showing which paths now query, with an instruction to re-baseline against the dev org and record new figures ALONGSIDE the old ones because the delta is the useful information | F119: REV-1, PERF-1 | G119: docs updated | H119: Reviewer nomination = Senthil | I119: E117
A120: E117 | B120: 2026-09-13 17:23 | C120: v031 | D120: — | E120: D13 GATE MET: 35 suites, 485 tests, 100% all metrics, zero pragmas, tsc clean, gates proved. MISTAKE CAUGHT AND RECORDED: the rewritten review pack first told the reviewer to expect "494 tests" when the real number was 482 — a figure written from memory into a document whose entire purpose is to be trusted by an outsider. Corrected to a claim that cannot go stale. That is precisely the failure mode the claims gate exists for, committed while writing about the claims gate. LESSON L-F14: documents aimed at OUTSIDERS decay silently because nobody inside reads them — the team already knows the architecture, so nothing prompts a re-read. The two documents furthest from daily use were the two most out of date, and both sit on the critical path to launch. Any externally-aimed document needs a review trigger tied to the system rather than to someone remembering; three of its claims are now gate-enforced, the rest still rely on someone looking | F120: D13 | G120: Tracker v019 + workbook v031 released | H120: All remaining = Senthil | I120: v020 on live evidence
A121: E118 | B121: 2026-09-13 17:29 | C121: v032 | D121: S9 | E121: RUN CONTINUED — 17:29, closing my own L-F14 which ended with three claims gate-enforced and "the rest still rely on someone looking". Relying on someone looking is precisely what failed: the reviewer pack went 13 releases out of date while sitting on the critical path, because nobody inside the team ever needs to read it. Built the fifth gate | F121: — | G121: tests/docFreshnessGate.test.ts | H121: — | I121: E119
A122: E119 | B122: 2026-09-13 17:29 | C122: v032 | D122: S9 | E122: GATE RULE: a document written for an OUTSIDER must acknowledge the parts of the system it claims to describe — if a module exists and the document meant to map it has never heard of it, the build fails. A subsystem therefore cannot ship without the reviewer and pen-test maps being updated in the SAME change. Each covered document records its AUDIENCE inside the gate so a failure names who is affected (external reviewer ST-097 requires every module; pen-test vendor requires the security-relevant set). Exemptions are per-module with reasons, and a reason containing later/todo/tbd/for now FAILS because that phrasing is the decay itself | F122: — | G122: 7 gate tests incl. bite proof, missing-document-is-a-failure, scope limits | H122: — | I122: E120
A123: E120 | B123: 2026-09-13 17:29 | C123: v032 | D123: S9 | E123: IT FIRED ON FIRST RUN — against documents I had rewritten SIX MINUTES EARLIER. The v031 rewrite added the eight newest subsystems and silently omitted the original feature modules, so a reviewer would still have been steered away from most of the product; and the security pack described "the database" in prose without ever naming db or pg, so a vendor scoping by module would have missed both. Both completed: per-module what-to-challenge tables for feature and platform surfaces, and a vendor module map to scope against by name rather than prose | F123: REV-1 follow-up, SEC-1 follow-up | G123: docs/security/REVIEW_PACK.md, SECURITY_EVIDENCE.md | H123: — | I123: E121
A124: E121 | B124: 2026-09-13 17:29 | C124: v032 | D124: — | E124: THE HARNESS CAUGHT A WEAK MUTATION, NOT A WEAK GATE: proving the new gate, the first mutation deleted one of TWO mentions of leaderLock and the gate rightly stayed green because the module was still acknowledged elsewhere. prove:gates reported BROKEN, which was correct about the MUTATION. Re-pointed at a module mentioned exactly once (launchOps), the gate fails as intended and all four provable gates print PROVED. Recorded because a harness that only ever confirms what you expect is no better than the gates it checks | F124: — | G124: gates/prove-gates.js | H124: — | I124: E122
A125: E122 | B125: 2026-09-13 17:29 | C125: v032 | D125: — | E125: D13 GATE MET: 36 suites, 492 tests, 100% all metrics, zero pragmas, tsc clean; five gates in CI with all four provable ones PROVED. Scope stated honestly: the gate checks ACKNOWLEDGEMENT not accuracy — a document can name every module and describe them all wrongly; what it guarantees is that the decay mode that actually happened (new subsystem ships, external document never hears about it) cannot repeat silently. LESSON L-F15: every gate here was born from a defect that had ALREADY SHIPPED — unreachable code, a false published claim, a cross-tenant leak, a destructive migration, a stale external document. The useful trigger for automation is not "what could go wrong" but "what DID go wrong, and would we notice a second time?" The first question produces a long list of plausible checks; the second produced five that have each caught something real | F125: D13 | G125: Tracker v020 + workbook v032 released | H125: All remaining = Senthil | I125: v021 on live evidence
A126: E123 | B126: 2026-09-13 18:48 | C126: v033 | D126: S8 | E126: RUN CONTINUED — 18:48. Stated plainly at the start of this sitting that recent sittings had produced gates and documents rather than product defects and that marginal value was declining; scoped only to what was genuinely defect-derived. Grep for remaining fire-and-forget sites (the L-F13 recommendation) found a REAL one: the worker tick called drainOnce with no catch, and drainOnce RETHROWS after re-queuing (F4-04), so every store or sink failure produced an unhandled rejection the degradation counter never saw and /ready never showed. Process guards stopped it being fatal but it was invisible. Fixed via safely(); the SIGTERM shutdown call also given an owner, reporting failures with credentials redacted | F126: L-F13 | G126: 2 regressions: drain failure counted + event returned; shutdown failure reported and redacted | H126: — | I126: E124
A127: E124 | B127: 2026-09-13 18:48 | C127: v033 | D127: S8 | E127: SIXTH GATE (async ownership): a promise started and not awaited must have an owner — safely() or an explicit .catch. Type positions are excluded. Only resilience.ts is exempt, because it IS the owner of last resort and cannot wrap its own drain. Proved against the exact CHAOS-1 shape (restoring the bare persistAccepted fire-and-forget); all five provable gates now print PROVED | F127: — | G127: gates/prove-gates.js extended | H127: — | I127: E125
A128: E125 | B128: 2026-09-13 18:48 | C128: v033 | D128: — | E128: REVIEW PLAYBOOK written (gates/REVIEW_PLAYBOOK.md), the asset worth more than the gates: the EIGHT review passes in the order that proved productive — cold review by module (run it twice), external verification sweep against live platform docs, artifact-gap audit, integration audit (highest yield, now automated), review the code the previous session wrote, environment-assumption review, artifact PAIRING, and outsider-first document review — plus the rules learned the hard way (coverage proves execution not existence; a gate never seen fail is not a gate; a passing test can pin a defect; void promise is the quietest crash; a published policy is not a shipped feature; automate from what DID go wrong) and a porting procedure. Context recorded: FlowCast reached code-phase-complete at 100% coverage with zero backlog on 11 Sep, and ~40 defects were found in that same code over the two days since | F128: — | G128: gates/REVIEW_PLAYBOOK.md | H128: Porting to other products = Senthil
A129: E126 | B129: 2026-09-13 18:48 | C129: v033 | D129: — | E129: D13 GATE MET: 36 suites, 500 tests, 100% all metrics, zero pragmas, tsc clean; six gates in CI with all five provable ones PROVED; live boot returns ready:true. RECOMMENDATION RECORDED: this is a natural stopping point for sandbox work. Every remaining item on the Senthil_Handover sheet is external, the highest-value next action costs about thirty minutes of his time (Xero dev org + DATABASE_URL) and unlocks 16 stories, and further sittings would increasingly be invented rather than found work | F129: D13 | G129: Tracker v021 + workbook v033 released | H129: All remaining = Senthil | I129: v022 on live evidence only

Sheet Decisions
A1: DECISIONS (tracker scope)
A2: ID | B2: Decision | C2: Rationale | D2: Decided by | E2: Status
A3: D13 | B3: (Portfolio-wide) Discovery interviews parked; dev proceeds with 100% automation coverage on all code (supersedes ≥70% gate). ST-085 amended in v008 | C3: Senthil 10 Sep; applied to FlowCast per 22:01 directive | D3: Senthil | E3: LOCKED
A4: D15 | B4: FlowCast (rank 12) built while RevRescue rank-1 gate unmet; eight products now concurrent vs locked serial WIN order. Options framed on Action Board: hold-serial vs formal-parallel with WIP cap | C4: Successive "continue" directives 22:01–23:03; logged each release, never blocking | D4: Senthil (mode ratification pending) | E4: OPEN
A5: D-F1 | B5: Stack = TypeScript/Node + React per v007 workbook; Jest + RTL + jest-axe; Xero API mocked in sandbox | C5: Follows workbook stack; matches portfolio precedent | D5: Claude — flagged | E5: OPEN for ratification
A6: D-F2 | B6: Status vocabulary: Done / Code-complete — pending live / Drafted — pending publish|review / In progress / Backlog. Sprint-board "Done" formulas count only exact "Done" (intended) | C6: Honest-status rule: pending-live never claims Done | D6: Claude | E6: Applied v008+
A7: D-F3 | B7: Anomaly scanning evaluates each sync batch against trailing history (detectWithHistory), not in isolation | C7: 12-month QA drill proved isolated small batches hide lone outliers (sigma self-inflation) | D7: Claude — QA-driven fix, v012 | E7: Applied
A8: D-F4 | B8: Bank transactions sync via 15-min polling behind shared circuit breaker | C8: Xero exposes no bank-txn webhook; polling is the documented substitute, noted on Launch_Checklist #4 | D8: Claude — platform constraint | E8: Applied v011
A9: D-F5 | B9: External-facing content (listing copy, trust page) carries product name only — no company name | C9: Senthil standing rule for external content | D9: Senthil (standing) | E9: Applied v010
A10: D-F6 | B10: In-app chat ships on the built-in chat+SLA engine (src/chatSla.ts); an external chat vendor is an OPTIONAL later transport swap, not a launch blocker | C10: Sibling-validated pattern (TeleField/OnCall/VoiceBridge); SLA logic is vendor-independent | D10: Claude — flagged | E10: OPEN for ratification

Sheet Release_Build_Boards
A1: RELEASE BUILD BOARDS — one board per product-workbook version of the run
A2: Each board: what shipped, evidence at that release. Detail per story in Traceability_Matrix.
A3: v008 — 22:01 — Foundation + core features (S1-S8 code subset)
A4: Shipped | B4: 11 TS modules: installFlow, permissions, forecastEngine, scenarioSliders, invoiceNudges, accountantPortal(+importCsv), anomalyAlerts, billing, compliance, telemetry, onboarding
A5: Stories | B5: 58 Done; 4 Code-complete pending live (ST-051/052/055/059); 2 in progress (ST-003, ST-086)
A6: Evidence | B6: 11 suites / 120 tests / 100-100-100-100; gate enforced
A7: Also | B7: Sprint_Tracker_Log + Traceability_Matrix sheets added to product workbook; ST-085 amended per D13
A9: v009 — 22:20 — UI surfaces + rule builder + CI
A10: Shipped | B10: 5 React screens + MetricsPanel + DegradedBanner precursor set; forecastRules (ST-003 full), featureMetrics + Xero deep links, notifications, feature toggles, portal rules; .github/workflows/ci.yml
A11: Stories | B11: +16 Done (74 total); ST-086 -> Code-complete pending repo hookup
A12: Evidence | B12: 13 suites / 148 tests / 100% incl. components; tsc clean
A14: v010 — 22:27 — Reliability, a11y, demo mode + 12 content artifacts
A15: Shipped | B15: reliability.ts (p95 budgets, degradation comms), DegradedBanner, jest-axe WCAG suite (0 violations x7 surfaces), demoData (red-week arc); docs: 15 help articles, chat SLA + canned pack, video script, listing copy A/B, asset specs, pricing+FAQ, trust page, dry-run gap report, backup/chaos/launch runbooks
A16: Stories | B16: +3 Done (77); +3 CCPL (087/089/091); 7 Drafted; 2 In progress
A17: Evidence | B17: 14 suites / 155 tests / 100%
A18: Finding | B18: Dry-run: 2 hard gaps — dev org (Senthil), content webhooks (build)
A20: v011 — 22:51 — Content webhooks (dry-run gap closed)
A21: Shipped | B21: webhooks.ts: HMAC verify (constant-time), fast-ack idempotent queue, retry/dead-letter/redelivery-heal, payment->cancel-nudges; bank-txn 15-min polling (no platform webhook — D-F4)
A22: Stories | B22: WBH-001 (unnumbered, outside ST board counts by design); Launch_Checklist all 10 -> honest statuses
A23: Evidence | B23: 15 suites / 170 tests / 100%
A25: v012 — 22:56 — Rate limiter, QA drills, load harness, deploy workflow
A26: Shipped | B26: rateLimiter (60/min/tenant), server.ts wiring, qaDatasets (20-client, 12-month feed), detectWithHistory fix (D-F3), k6 harness, blue/green deploy.yml
A27: Stories | B27: ST-088/092 -> CCPL; WBH-002/003, QA-007/008 logged; checklists 3/7/8 advanced
A28: Evidence | B28: 16 suites / 182 tests / 100%; REAL DEFECT found + fixed by drill
A30: v013 — 23:03 — Live-sweep readiness + portfolio action board
A31: Shipped | B31: config.ts + .env.example (CFG-001), dev-org 30-min guide, 12-step scripted sweep; claude_v001_portfolio_action_board_20260910_2303.xlsx (separate deliverable)
A32: Stories | B32: No status changes; handoff fully scripted
A33: Evidence | B33: 17 suites / 186 tests / 100%; tsc clean

Sheet Traceability_Matrix
A1: TRACEABILITY MATRIX — 100 stories + 6 post-baseline items: story -> code -> automated test -> coverage -> version
A2: Source of story data: product workbook v013 Full_Backlog (single source of truth). Done-in-version from release records.
A3: Story ID | B3: Epic | C3: Module / feature | D3: Story | E3: Points | F3: Priority | G3: Sprint | H3: Status | I3: Done in version | J3: Code file(s) | K3: Test file(s) | L3: Coverage | M3: Notes / evidence
A4: ST-001 | B4: F1 | C4: 13-week forecast engine | D4: As a SMB owner, I can set up 13-week forecast engine with sensible defaults in one screen | E4: 5 | F4: P0 | G4: S2 | H4: Done | I4: v008 | J4: src/forecastEngine.ts | K4: tests/forecastEngine.test.ts | L4: 100% | M4: defaultInput one-screen setup
A5: ST-002 | B5: F1 | C5: 13-week forecast engine | D5: As a SMB owner, the 13-week forecast engine happy path completes without documentation | E5: 8 | F5: P0 | G5: S2 | H5: Done | I5: v008 | J5: src/forecastEngine.ts | K5: tests/forecastEngine.test.ts | L5: 100% | M5: computeForecast happy path, 13-week bucketing
A6: ST-003 | B6: F1 | C6: 13-week forecast engine | D6: As a Accountant partner, I can customise 13-week forecast engine rules/conditions for my workflow | E6: 5 | F6: P1 | G6: S2 | H6: Done | I6: v009 | J6: src/forecastRules.ts | K6: tests/rulesNotificationsMetrics.test.ts | L6: 100% | M6: Rule builder complete: min_balance / amber_floor / week_drop_pct over week ranges; supersedes amber-floor-only v008 state
A7: ST-004 | B7: F1 | C7: 13-week forecast engine | D7: As a user, 13-week forecast engine shows clear errors and retry paths on platform API failures | E7: 3 | F7: P0 | G7: S2 | H7: Done | I7: v008 | J7: src/forecastEngine.ts; src/compliance.ts | K7: tests/forecastEngine.test.ts; tests/compliance.test.ts | L7: 100% | M7: validate() named errors; callWithProtection retry
A8: ST-005 | B8: F1 | C8: 13-week forecast engine | D8: As a Bookkeeper, 13-week forecast engine works on the web app with Xero deep links + accountant portal surface end-to-end | E8: 5 | F8: P0 | G8: S3 | H8: Done | I8: v009 | J8: src/ui/ForecastScreens.tsx | K8: tests/ui/screens.test.tsx | L8: 100% | M8: ForecastScreen: 13-week table, rule violations, Xero receivables deep link, empty state
A9: ST-006 | B9: F1 | C9: 13-week forecast engine | D9: As a Accountant partner, I can see 13-week forecast engine performance metrics and trends | E9: 3 | F9: P1 | G9: S3 | H9: Done | I9: v009 | J9: src/featureMetrics.ts; src/ui/MetricsPanel.tsx | K9: tests/rulesNotificationsMetrics.test.ts; tests/ui/screens.test.tsx | L9: 100% | M9: weeklySeries + trend + MetricsPanel surface
A10: ST-007 | B10: F1 | C10: 13-week forecast engine | D10: As a user, 13-week forecast engine respects role permissions and audit logging | E10: 3 | F10: P1 | G10: S3 | H10: Done | I10: v008 | J10: src/permissions.ts | K10: tests/permissions.test.ts | L10: 100% | M10: authorize + AuditLog on forecast actions
A11: ST-008 | B11: F1 | C11: 13-week forecast engine | D11: As a SMB owner, I can pause/disable 13-week forecast engine without data loss | E11: 2 | F11: P2 | G11: S3 | H11: Done | I11: v008 | J11: src/forecastEngine.ts | K11: tests/forecastEngine.test.ts | L11: 100% | M11: setEnabled preserves lastInput
A12: ST-009 | B12: F1 | C12: 13-week forecast engine | D12: As a Accountant partner, I can import/migrate existing data into 13-week forecast engine (CSV + competitor importer) | E12: 5 | F12: P1 | G12: S3 | H12: Done | I12: v008 | J12: src/accountantPortal.ts | K12: tests/accountantPortal.test.ts | L12: 100% | M12: importCsv shared migration importer
A13: ST-010 | B13: F1 | C13: 13-week forecast engine | D13: As a user, I get notifications (in-app + email) for key 13-week forecast engine events with per-type mute | E13: 3 | F13: P2 | G13: S3 | H13: Done | I13: v009 | J13: src/notifications.ts | K13: tests/rulesNotificationsMetrics.test.ts | L13: 100% | M13: dispatch in-app+email, per-type mute, daily digest (forecast event types)
A14: ST-011 | B14: F2 | C14: Scenario sliders | D14: As a SMB owner, I can set up Scenario sliders with sensible defaults in one screen | E14: 5 | F14: P0 | G14: S3 | H14: Done | I14: v008 | J14: src/scenarioSliders.ts | K14: tests/scenarioSliders.test.ts | L14: 100% | M14: baselineScenario defaults
A15: ST-012 | B15: F2 | C15: Scenario sliders | D15: As a SMB owner, the Scenario sliders happy path completes without documentation | E15: 8 | F15: P0 | G15: S3 | H15: Done | I15: v008 | J15: src/scenarioSliders.ts | K15: tests/scenarioSliders.test.ts | L15: 100% | M15: applyScenario levers + recompute
... A103: ST-100 | B103: EL | C103: Listing & launch | D103: First 10 design-partner reviews scheduled | E103: 2 | F103: P1 | G103: S11 | H103: Code-complete — pending live | I103: v016 | J103: src/launchOps.ts | K103: tests/chatSlaLaunchOps.test.ts | L103: 100% | M103: 10-slot tracker, stale-nudge, exit math: reviews ≠ G-02 paying strangers; outreach = Senthil
A104: WBH-001 | B104: EQ+ | C104: Engineering quality (post-baseline) | D104: (post-baseline item — see notes) | E104: — | F104: — | G104: — | H104: Code-complete — pending live | I104: v011 | J104: src/webhooks.ts | K104: tests/webhooks.test.ts | L104: 100% | M104: Dry-run gap #4 closed in code: HMAC-SHA256 signature verify (constant-time, intent-to-receive), fast-ack + idempotent queue with retry/dead-letter/redelivery-heal, invoice/contact/subscription action mapping (payment cancels nudges), bank-txn polling behind shared circuit breaker (no platform webhook exists — 15-min poll documented). Live wiring pending dev org. Unnumbered: added post-baseline from dry-run, outside ST-001..100 board counts by design
A105: WBH-002 | B105: EQ+ | C105: Engineering quality (post-baseline) | D105: (post-baseline item — see notes) | E105: — | F105: — | G105: — | H105: Done (code) | I105: v012 | J105: src/rateLimiter.ts | K105: tests/rateLimitQaHttp.test.ts | L105: 100% | M105: Checklist #3 hardening: proactive per-tenant 60/min sliding-window limiter + paced execution (complements reactive backoff/breaker); live verification pending
A106: WBH-003 | B106: EQ+ | C106: Engineering quality (post-baseline) | D106: (post-baseline item — see notes) | E106: — | F106: — | G106: — | H106: Done (code) | I106: v012 | J106: src/server.ts | K106: tests/rateLimitQaHttp.test.ts | L106: 100% | M106: HTTP wiring layer: routed fast-ack webhook endpoint (raw-body signature contract) + /health with release + queue depth; net binding is 5 lines at deploy
A107: QA-007 | B107: EQ+ | C107: Engineering quality (post-baseline) | D107: (post-baseline item — see notes) | E107: — | F107: — | G107: — | H107: Done (logic drill) | I107: v012 | J107: src/qaDatasets.ts (twentyClientBook) | K107: tests/rateLimitQaHttp.test.ts | L107: 100% | M107: Checklist #7: 20-client book drill — risk-first sort + portal rules at scale verified
A108: QA-008 | B108: EQ+ | C108: Engineering quality (post-baseline) | D108: (post-baseline item — see notes) | E108: — | F108: — | G108: — | H108: Done (logic drill) | I108: v012 | J108: src/qaDatasets.ts (twelveMonthFeed); src/anomalyAlerts.ts (detectWithHistory) | K108: tests/rateLimitQaHttp.test.ts | L108: 100% | M108: Checklist #8: 12-month drill caught a REAL defect — isolated small-batch scans hide lone outliers (self-inflated sigma). Fixed: production scans batch against trailing history; all 3 planted faults caught, false positives <= 2
A109: CFG-001 | B109: EQ+ | C109: Engineering quality (post-baseline) | D109: (post-baseline item — see notes) | E109: — | F109: — | G109: — | H109: Done (code) | I109: v013 | J109: src/config.ts; .env.example | K109: tests/config.test.ts | L109: 100% | M109: Typed config loader: all live credentials named + validated at boot (missing keys listed at once; https redirect enforced; Stripe key required only outside UK/AU/NZ). Live-sweep readiness
A111: Summary: 77 Done · 10 Code-complete — pending live · 7 Drafted · 2 In progress · 4 Backlog · 6 post-baseline items. Final evidence: 17 suites / 186 tests / 100-100-100-100; tsc clean.

Sheet Sprint_Status_Rollup
A1: SPRINT STATUS ROLLUP — live formulas over Traceability_Matrix
A2: Do not edit computed cells. 'Done' counts exact status Done only; pending-live/drafted are excluded on purpose (honest-status rule D-F2).
A3: Sprint | B3: Focus | C3: Stories | D3: Points | E3: Done | F3: Done points | G3: % points done | H3: RAG (manual)
A4: S0 | B4: Discovery & design (parked per D13) | C4: =COUNTIF(Traceability_Matrix!$G$4:$G$109,"S0") -> 0 | D4: =SUMIF(Traceability_Matrix!$G$4:$G$109,"S0",Traceability_Matrix!$E$4:$E$109) -> 0 | E4: =COUNTIFS(Traceability_Matrix!$G$4:$G$109,"S0",Traceability_Matrix!$H$4:$H$109,"Done") -> 0 | F4: =SUMIFS(Traceability_Matrix!$E$4:$E$109,Traceability_Matrix!$G$4:$G$109,"S0",Traceability_Matrix!$H$4:$H$109,"Done") -> 0 | G4: =IFERROR(ROUND(SUMIFS(Traceability_Matrix!$E$4:$E$109,Traceability_Matrix!$G$4:$G$109,"S0",Traceability_Matrix!$H$4:$H$109,"Done")/SUMIF(Traceability_Matrix!$G$4:$G$109,"S0",Traceability_Matrix!$E$4:$E$109)*100,1),0) -> 0 | H4: Parked (D13)
A5: S1 | B5: Foundation | C5: =COUNTIF(Traceability_Matrix!$G$4:$G$109,"S1") -> 4 | D5: =SUMIF(Traceability_Matrix!$G$4:$G$109,"S1",Traceability_Matrix!$E$4:$E$109) -> 13 | E5: =COUNTIFS(Traceability_Matrix!$G$4:$G$109,"S1",Traceability_Matrix!$H$4:$H$109,"Done") -> 1 | F5: =SUMIFS(Traceability_Matrix!$E$4:$E$109,Traceability_Matrix!$G$4:$G$109,"S1",Traceability_Matrix!$H$4:$H$109,"Done") -> 2 | G5: =IFERROR(ROUND(SUMIFS(Traceability_Matrix!$E$4:$E$109,Traceability_Matrix!$G$4:$G$109,"S1",Traceability_Matrix!$H$4:$H$109,"Done")/SUMIF(Traceability_Matrix!$G$4:$G$109,"S1",Traceability_Matrix!$E$4:$E$109)*100,1),0) -> 15.4 | H5: GREEN — done-in-code; live install pending dev org
A6: S2 | B6: Forecast engine pt 1 | C6: =COUNTIF(Traceability_Matrix!$G$4:$G$109,"S2") -> 6 | D6: =SUMIF(Traceability_Matrix!$G$4:$G$109,"S2",Traceability_Matrix!$E$4:$E$109) -> 29 | E6: =COUNTIFS(Traceability_Matrix!$G$4:$G$109,"S2",Traceability_Matrix!$H$4:$H$109,"Done") -> 6 | F6: =SUMIFS(Traceability_Matrix!$E$4:$E$109,Traceability_Matrix!$G$4:$G$109,"S2",Traceability_Matrix!$H$4:$H$109,"Done") -> 29 | G6: =IFERROR(ROUND(SUMIFS(Traceability_Matrix!$E$4:$E$109,Traceability_Matrix!$G$4:$G$109,"S2",Traceability_Matrix!$H$4:$H$109,"Done")/SUMIF(Traceability_Matrix!$G$4:$G$109,"S2",Traceability_Matrix!$E$4:$E$109)*100,1),0) -> 100 | H6: GREEN
A7: S3 | B7: Forecast pt 2 + UI start | C7: =COUNTIF(Traceability_Matrix!$G$4:$G$109,"S3") -> 11 | D7: =SUMIF(Traceability_Matrix!$G$4:$G$109,"S3",Traceability_Matrix!$E$4:$E$109) -> 47 | E7: =COUNTIFS(Traceability_Matrix!$G$4:$G$109,"S3",Traceability_Matrix!$H$4:$H$109,"Done") -> 11 | F7: =SUMIFS(Traceability_Matrix!$E$4:$E$109,Traceability_Matrix!$G$4:$G$109,"S3",Traceability_Matrix!$H$4:$H$109,"Done") -> 47 | G7: =IFERROR(ROUND(SUMIFS(Traceability_Matrix!$E$4:$E$109,Traceability_Matrix!$G$4:$G$109,"S3",Traceability_Matrix!$H$4:$H$109,"Done")/SUMIF(Traceability_Matrix!$G$4:$G$109,"S3",Traceability_Matrix!$E$4:$E$109)*100,1),0) -> 100 | H7: GREEN
A8: S4 | B8: Scenario sliders | C8: =COUNTIF(Traceability_Matrix!$G$4:$G$109,"S4") -> 9 | D8: =SUMIF(Traceability_Matrix!$G$4:$G$109,"S4",Traceability_Matrix!$E$4:$E$109) -> 34 | E8: =COUNTIFS(Traceability_Matrix!$G$4:$G$109,"S4",Traceability_Matrix!$H$4:$H$109,"Done") -> 8 | F8: =SUMIFS(Traceability_Matrix!$E$4:$E$109,Traceability_Matrix!$G$4:$G$109,"S4",Traceability_Matrix!$H$4:$H$109,"Done") -> 29 | G8: =IFERROR(ROUND(SUMIFS(Traceability_Matrix!$E$4:$E$109,Traceability_Matrix!$G$4:$G$109,"S4",Traceability_Matrix!$H$4:$H$109,"Done")/SUMIF(Traceability_Matrix!$G$4:$G$109,"S4",Traceability_Matrix!$E$4:$E$109)*100,1),0) -> 85.3 | H8: GREEN
A9: S5 | B9: Invoice nudges + alpha hardening | C9: =COUNTIF(Traceability_Matrix!$G$4:$G$109,"S5") -> 12 | D9: =SUMIF(Traceability_Matrix!$G$4:$G$109,"S5",Traceability_Matrix!$E$4:$E$109) -> 50 | E9: =COUNTIFS(Traceability_Matrix!$G$4:$G$109,"S5",Traceability_Matrix!$H$4:$H$109,"Done") -> 12 | F9: =SUMIFS(Traceability_Matrix!$E$4:$E$109,Traceability_Matrix!$G$4:$G$109,"S5",Traceability_Matrix!$H$4:$H$109,"Done") -> 50 | G9: =IFERROR(ROUND(SUMIFS(Traceability_Matrix!$E$4:$E$109,Traceability_Matrix!$G$4:$G$109,"S5",Traceability_Matrix!$H$4:$H$109,"Done")/SUMIF(Traceability_Matrix!$G$4:$G$109,"S5",Traceability_Matrix!$E$4:$E$109)*100,1),0) -> 100 | H9: GREEN
A10: S6 | B10: Billing + accountant portal | C10: =COUNTIF(Traceability_Matrix!$G$4:$G$109,"S6") -> 13 | D10: =SUMIF(Traceability_Matrix!$G$4:$G$109,"S6",Traceability_Matrix!$E$4:$E$109) -> 60 | E10: =COUNTIFS(Traceability_Matrix!$G$4:$G$109,"S6",Traceability_Matrix!$H$4:$H$109,"Done") -> 12 | F10: =SUMIFS(Traceability_Matrix!$E$4:$E$109,Traceability_Matrix!$G$4:$G$109,"S6",Traceability_Matrix!$H$4:$H$109,"Done") -> 52 | G10: =IFERROR(ROUND(SUMIFS(Traceability_Matrix!$E$4:$E$109,Traceability_Matrix!$G$4:$G$109,"S6",Traceability_Matrix!$H$4:$H$109,"Done")/SUMIF(Traceability_Matrix!$G$4:$G$109,"S6",Traceability_Matrix!$E$4:$E$109)*100,1),0) -> 86.7 | H10: GREEN
A11: S7 | B11: Private beta (design partners) | C11: =COUNTIF(Traceability_Matrix!$G$4:$G$109,"S7") -> 5 | D11: =SUMIF(Traceability_Matrix!$G$4:$G$109,"S7",Traceability_Matrix!$E$4:$E$109) -> 15 | E11: =COUNTIFS(Traceability_Matrix!$G$4:$G$109,"S7",Traceability_Matrix!$H$4:$H$109,"Done") -> 5 | F11: =SUMIFS(Traceability_Matrix!$E$4:$E$109,Traceability_Matrix!$G$4:$G$109,"S7",Traceability_Matrix!$H$4:$H$109,"Done") -> 15 | G11: =IFERROR(ROUND(SUMIFS(Traceability_Matrix!$E$4:$E$109,Traceability_Matrix!$G$4:$G$109,"S7",Traceability_Matrix!$H$4:$H$109,"Done")/SUMIF(Traceability_Matrix!$G$4:$G$109,"S7",Traceability_Matrix!$E$4:$E$109)*100,1),0) -> 100 | H11: AMBER — beta needs live product + partners
A12: S8 | B12: Beta iteration + anomalies + reliability | C12: =COUNTIF(Traceability_Matrix!$G$4:$G$109,"S8") -> 22 | D12: =SUMIF(Traceability_Matrix!$G$4:$G$109,"S8",Traceability_Matrix!$E$4:$E$109) -> 87 | E12: =COUNTIFS(Traceability_Matrix!$G$4:$G$109,"S8",Traceability_Matrix!$H$4:$H$109,"Done") -> 18 | F12: =SUMIFS(Traceability_Matrix!$E$4:$E$109,Traceability_Matrix!$G$4:$G$109,"S8",Traceability_Matrix!$H$4:$H$109,"Done") -> 71 | G12: =IFERROR(ROUND(SUMIFS(Traceability_Matrix!$E$4:$E$109,Traceability_Matrix!$G$4:$G$109,"S8",Traceability_Matrix!$H$4:$H$109,"Done")/SUMIF(Traceability_Matrix!$G$4:$G$109,"S8",Traceability_Matrix!$E$4:$E$109)*100,1),0) -> 81.6 | H12: GREEN — drills passed, defect fixed
A13: S9 | B13: Marketplace review prep | C13: =COUNTIF(Traceability_Matrix!$G$4:$G$109,"S9") -> 7 | D13: =SUMIF(Traceability_Matrix!$G$4:$G$109,"S9",Traceability_Matrix!$E$4:$E$109) -> 30 | E13: =COUNTIFS(Traceability_Matrix!$G$4:$G$109,"S9",Traceability_Matrix!$H$4:$H$109,"Done") -> 1 | F13: =SUMIFS(Traceability_Matrix!$E$4:$E$109,Traceability_Matrix!$G$4:$G$109,"S9",Traceability_Matrix!$H$4:$H$109,"Done") -> 5 | G13: =IFERROR(ROUND(SUMIFS(Traceability_Matrix!$E$4:$E$109,Traceability_Matrix!$G$4:$G$109,"S9",Traceability_Matrix!$H$4:$H$109,"Done")/SUMIF(Traceability_Matrix!$G$4:$G$109,"S9",Traceability_Matrix!$E$4:$E$109)*100,1),0) -> 16.7 | H13: AMBER — copy drafted; dry-run second pass + dev org pending
A14: S10 | B14: Review remediation + docs | C14: =COUNTIF(Traceability_Matrix!$G$4:$G$109,"S10") -> 7 | D14: =SUMIF(Traceability_Matrix!$G$4:$G$109,"S10",Traceability_Matrix!$E$4:$E$109) -> 24 | E14: =COUNTIFS(Traceability_Matrix!$G$4:$G$109,"S10",Traceability_Matrix!$H$4:$H$109,"Done") -> 1 | F14: =SUMIFS(Traceability_Matrix!$E$4:$E$109,Traceability_Matrix!$G$4:$G$109,"S10",Traceability_Matrix!$H$4:$H$109,"Done") -> 2 | G14: =IFERROR(ROUND(SUMIFS(Traceability_Matrix!$E$4:$E$109,Traceability_Matrix!$G$4:$G$109,"S10",Traceability_Matrix!$H$4:$H$109,"Done")/SUMIF(Traceability_Matrix!$G$4:$G$109,"S10",Traceability_Matrix!$E$4:$E$109)*100,1),0) -> 8.3 | H14: AMBER — content drafted, publish pending
A15: S11 | B15: Launch | C15: =COUNTIF(Traceability_Matrix!$G$4:$G$109,"S11") -> 3 | D15: =SUMIF(Traceability_Matrix!$G$4:$G$109,"S11",Traceability_Matrix!$E$4:$E$109) -> 8 | E15: =COUNTIFS(Traceability_Matrix!$G$4:$G$109,"S11",Traceability_Matrix!$H$4:$H$109,"Done") -> 2 | F15: =SUMIFS(Traceability_Matrix!$E$4:$E$109,Traceability_Matrix!$G$4:$G$109,"S11",Traceability_Matrix!$H$4:$H$109,"Done") -> 6 | G15: =IFERROR(ROUND(SUMIFS(Traceability_Matrix!$E$4:$E$109,Traceability_Matrix!$G$4:$G$109,"S11",Traceability_Matrix!$H$4:$H$109,"Done")/SUMIF(Traceability_Matrix!$G$4:$G$109,"S11",Traceability_Matrix!$E$4:$E$109)*100,1),0) -> 75 | H15: RED until listed
A16: S12 | B16: Iterate & scale decision | C16: =COUNTIF(Traceability_Matrix!$G$4:$G$109,"S12") -> 1 | D16: =SUMIF(Traceability_Matrix!$G$4:$G$109,"S12",Traceability_Matrix!$E$4:$E$109) -> 2 | E16: =COUNTIFS(Traceability_Matrix!$G$4:$G$109,"S12",Traceability_Matrix!$H$4:$H$109,"Done") -> 0 | F16: =SUMIFS(Traceability_Matrix!$E$4:$E$109,Traceability_Matrix!$G$4:$G$109,"S12",Traceability_Matrix!$H$4:$H$109,"Done") -> 0 | G16: =IFERROR(ROUND(SUMIFS(Traceability_Matrix!$E$4:$E$109,Traceability_Matrix!$G$4:$G$109,"S12",Traceability_Matrix!$H$4:$H$109,"Done")/SUMIF(Traceability_Matrix!$G$4:$G$109,"S12",Traceability_Matrix!$E$4:$E$109)*100,1),0) -> 0 | H16: Not started

Sheet RAID_Carryover
A1: RAID — seeded from v007 Risk_Register + build findings
A2: ID | B2: Type | C2: Raised | D2: Item | E2: Status | F2: Notes / Mitigation
A3: R-F1 | B3: Risk | C3: v007 | D3: Xero native short-term cash flow improves (High/Medium) | E3: Open | F3: Scenario depth + accountant multi-client portal moat
A4: R-F2 | B4: Risk | C4: v007 | D4: Accountant channel slow to activate (Medium/High) | E4: Open | F4: Partner program with rev share; 10 pilot firms by S8; copy variant B targets this channel
A5: R-F3 | B5: Risk | C5: v007 | D5: Float/Fathom price moves (Medium/Medium) | E5: Open | F5: Owner-facing simplicity positioning; annual bundles
A6: R-F4 | B6: Constraint | C6: v008 | D6: Sandbox has no live Xero — all platform calls mocked; persistence in-memory behind typed interfaces | E6: Open | F6: 12-step scripted live sweep ready; adapters swap at deploy without touching domain code
A7: R-F5 | B7: Constraint | C7: v011 | D7: Xero exposes NO bank-transaction webhook | E7: Accepted | F7: 15-min polling behind shared breaker (D-F4); documented on Launch_Checklist #4
A8: R-F6 | B8: Finding | C8: v012 | D8: Isolated small-batch anomaly scans hide lone outliers (sigma self-inflation) — REAL defect caught by 12-month QA drill | E8: Fixed | F8: detectWithHistory: batches scanned against trailing history (D-F3); regression test in suite
A9: R-F7 | B9: Risk | C9: 23:03 | D9: Eight products built concurrently vs locked serial WIN order; Senthil live-ops bandwidth is the shared bottleneck | E9: Open | F9: D15 on Action Board: hold-serial vs formal-parallel with WIP cap — one-line decision
A10: A-F1 | B10: Assumption | C10: v008 | D10: D13 (interviews parked, 100% coverage) applies to FlowCast | E10: Open | F10: Per portfolio-wide directive; S0 discovery re-baseline possible if parking lifted
A11: A-F2 | B11: Assumption | C11: v010 | D11: Xero App Store asset specs (logo 400x400, screenshots 1280x800, video <=2 min) assumed from partner docs | E11: Open | F11: Verify against current partner docs at submission (noted in asset-specs doc)
A12: A-F3 | B12: Assumption | C12: v008 | D12: Pricing $15/$25/$49 per billing.ts carried into pricing page | E12: Open | F12: Senthil to confirm currency/points before publish
A13: F-V14 | B13: Finding | C13: v014 | D13: Cold-review passes 1+2 found 9 real defects in shipped-as-100%-covered code across 27 modules (5 Major class: ledger growth, fast-ack crash, plan-limit unenforceable, nudge spam, data-retention breach, silent forecast drop, scenario bias) — coverage proves execution, not correctness | E13: Fixed | F13: All 9 fixed with regression tests (v014/v015); Review_Findings holds dispositions incl. OBS-001/002; external second review (REVIEW_PACK.md) remains the independence control
... A32: L-F15 | B32: Lesson | C32: v032 | D32: All five gates were born from defects that had already shipped, not from imagined risks — the second question produced checks that each caught something real | E32: Logged | F32: Trigger automation from "what did go wrong, and would we notice a second time?" rather than "what could go wrong"

Sheet Gate_Checklist
A1: COMPLETION GATE (D7) — FlowCast is DONE only when every row passes
A2: Code complete counts for nothing at this gate. Gate decision = Senthil, on evidence Claude prepares.
A3: ID | B3: Gate item | C3: Source | D3: Status
A4: G-01 | B4: App LISTED on Xero App Store (approved + published) | C4: D7 | D4: Open
A5: G-02 | B5: 10 PAYING installs from strangers | C5: D7 | D5: Open
A6: G-03 | B6: S12 kill criteria evaluated with evidence pack | C6: D7 | D6: Open
A7: G-04 | B7: Kill/continue decision recorded by Senthil | C7: D7 | D7: Open
A8: G-05 | B8: On CONTINUE: next-rank build authorised per WIN order | C8: D7 / D15 | D8: Open
A9: LC-1 | B9: Xero developer account + app partner program application | C9: v007 LC / v011-v012 updates | D9: BLOCKED — needs Senthil: dev account + partner application
A10: LC-2 | B10: OAuth2 + tenant handling for multi-org accountants tested | C10: v007 LC / v011-v012 updates | D10: Code-complete — pending live dev-org test
A11: LC-3 | B11: API rate limits (60/min per tenant) queue + backoff verified | C11: v007 LC / v011-v012 updates | D11: Code-complete: proactive 60/min per-tenant limiter (v012) + reactive backoff/breaker — pending live verification
A12: LC-4 | B12: Webhooks (invoices, payments, bank transactions) resilience tested | C12: v007 LC / v011-v012 updates | D12: Code-complete — webhooks (INVOICE/CONTACT/SUBSCRIPTION) + bank-txn polling built v011; pending live wiring. NOTE: platform has no bank-txn webhook — polling every 15 min is the documented substitute
A13: LC-5 | B13: App partner certification: API best practice + security questionnaire + brand review | C13: v007 LC / v011-v012 updates | D13: Trust page drafted + SECURITY_EVIDENCE.md pack compiled v014 (per-control citations); questionnaire answerable from pack; brand review pending live artefacts
A14: LC-6 | B14: In-store subscription configuration + test purchase | C14: v007 LC / v011-v012 updates | D14: Rail logic coded; store config + test purchase pending dev org
... A18: LC-10 | B18: UK/AU/NZ tax-locale display verified (GST/VAT labels) | C18: v007 LC / v011-v012 updates | D18: GST/VAT fields coded + tested; UI locale pass pending deployed UI

Sheet Review_Findings
A1: COLD-REVIEW FINDINGS — pass 1 (v014, 2026-09-11 11:09). Dispositions = Senthil.
A3: ID | B3: Severity | C3: Module | D3: Finding | E3: Fix applied (v014) | F3: Regression test | G3: Disposition (Senthil)
A4: F-001 | B4: Major | C4: src/webhooks.ts | D4: Idempotency ledger (seen Set) grew unboundedly for the life of the process — memory leak under sustained webhook volume | E4: FIFO cap at 10,000 entries (SEEN_LEDGER_CAP) with oldest-first eviction; seenSize() exposed for monitoring | F4: tests/coldReviewSecurity.test.ts — cap, eviction, replay-after-eviction, newest-still-deduped | G4: Pending
A5: F-002 | B5: Major | C5: src/webhooks.ts | D5: A correctly signed but malformed or shape-invalid body crashed handleDelivery (unguarded JSON.parse + .events.length) — breaking the fast-ack contract on the webhook endpoint | E5: Guarded parse + shape validation; signed garbage acked 200 with accepted 0 and parseError flag for logging | F5: signed-garbage / wrong-shape / null-body / well-formed / bad-signature cases | G5: Pending
A6: F-003 | B6: Minor | C6: src/rateLimiter.ts | D6: Tenant entries never evicted once a tenant stopped calling — map grew with every tenant ever seen (stale stamps only pruned on that tenant's next call) | E6: prune(now) evicts all-stale tenants (scheduler tick); trackedTenants() exposed for capacity dashboards | F6: eviction of idle tenant while active tenant retained; no-op prune on live map | G6: Pending
A7: F-004 | B7: Minor | C7: src/anomalyAlerts.ts | D7: With 3+ matching txns the pairwise duplicate scan flagged the same txn once per earlier match — duplicate alert noise (3 matches -> 3 alerts instead of 2) | E7: Each txn flagged at most once, against its first matching predecessor | F7: three-matching-txns yields exactly 2 anomalies; history+batch dedupe preserved | G7: Pending
A8: F-005 | B8: Major | C8: src/billing.ts | D8: nudgesPerMonth plan limit was unenforceable as shipped: checkLimit took `used` as a parameter but no cycle-scoped counter with per-cycle reset existed anywhere in the codebase (same class as OnCall F-006) | E8: UsageCycle: freshCycle/rolloverIfDue (boundary-anchored, drift-free)/recordNudge (refuse at cap, 80% upgrade prompt, refused sends not counted); CYCLE_MS=30d sandbox anchor — live rail supplies real cycle dates | F8: cap refusal, 80% prompt, boundary reset, multi-cycle anchor, refused-send-not-counted | G8: Pending
A9: F-006 | B9: Major | C9: src/invoiceNudges.ts | D9: No per-invoice sent-history: the daily planner re-nudged every overdue invoice at its current tier on every run — customers chased daily at the same tier until escalation | E9: SentHistory (invoiceId:type): tier fires once; test-mode not recorded; failed sends not recorded (retried); clearInvoice on payment; sendNudges records on success | F9: tests/coldReviewPass2.test.ts — once-only, escalation, test-mode, flaky-retry, failure-retry, clear-per-invoice | G9: Pending
A10: F-007 | B10: Major | C10: src/installFlow.ts | D10: purgeExpired marked accounts purged but never deleted the record — tenant data retained in memory indefinitely after the 30-day deletion deadline (contradicts ST-052 deletion policy); map grew unboundedly | E10: Purge deletes the record (idempotent); unproducible purged status removed from Account type; one pre-existing assertion updated accordingly | F10: record undefined after purge; idempotent second run; clean post-purge reinstall | G10: Pending
A11: F-008 | B11: Major | C11: src/forecastEngine.ts | D11: Non-finite dueDate -> weekIndex NaN -> inflows[NaN] += silently dropped the item from all 13 weeks with no error — forecast quietly wrong on bad platform data (opposite of ST-004 contract). Sub-finding F-008b (Minor): light computed on unrounded balance vs rounded displayed figure | E11: validate() checks weekStart + all dueDates finite with named FORECAST_INVALID errors; lightFor now takes the rounded (displayed) closing | F11: NaN/Infinity invoice, outflow, weekStart all throw; light-display consistency property | G11: Pending
A12: F-009 | B12: Major | C12: src/scenarioSliders.ts | D12: extraMonthlyCost emitted 3 monthly occurrences (days 0/28/56) but the 13-week horizon spans 91 days — the 4th (day 84, week 13) was omitted; recurring-hire scenarios optimistically overstated week-13 cash by one month of the cost | E12: 4 occurrences (days 0/28/56/84); pre-existing 3-occurrence assertion updated (it encoded the defect) | F12: 4 lines emitted; week-13 closing = -4x cost; week 12 unchanged | G12: Pending
A13: OBS-001 | B13: Observation | C13: src/compliance.ts | D13: backoffDelayMs has no jitter — synchronized retry herds possible when many tenants recover from a shared outage simultaneously | E13: No fix this pass: adding jitter changes timing-deterministic test contracts; live APM data should size it | F13: — | G13: Pending
A14: OBS-002 | B14: Observation | C14: src/compliance.ts | D14: CircuitBreaker half_open admits unlimited concurrent probe requests (single-probe half-open is the stricter pattern) | E14: No fix this pass: standard simple-breaker trade-off; acceptable at launch traffic | F14: — | G14: Pending
... A53: PERF-1 | B53: Minor | C53: docs/reliability/latency-budgets.md | D53: Budgets measured in-process before any database round trip existed | E53: Round-trip table + re-baseline instruction recording deltas | F53: — | G53: Pending
