Workbook

Sheet Cover
A1: EngageOS (003-MoPr07) — Version Detail and Manual Test Cases
A3: Document title | B3: EngageOS WhatsApp — Version Detail and Manual Test Cases
A4: Document ID | B4: claude_V001_MoPr07-engageos_whatsapp_versiondetail_manualtest
A5: Document version | B5: V001
A6: Status | B6: Released
A7: Classification | B7: Internal — AT Team
A8: Product | B8: EngageOS — WhatsApp-first engagement suite for SMEs (product code 003-MoPr07)
A9: Code version described | B9: engageos v0.46.0 (engageos_v0.46.0_src.zip)
A10: Companion records | B10: Sprint tracker claude_v042 (16 Sep 2026 18:40); product workbook claude_v047 (16 Sep 2026 18:40); external reviews ChatGPT V001 (13 Sep) and Perplexity V001 (16 Sep)
A11: Prepared by | B11: Claude for Senthil / KP
A12: Prepared on | B12: 2026-09-20 11:03 (Europe/London)
A13: Owner / approver | B13: Senthil (KP)
A14: Reviewed by | B14: — (see Approvals sheet)
... A16: How this file is versioned | B16: File name carries the document version (V001, V002 …) and the build timestamp. Higher document version wins. Every change is logged on Version_Control. The code, tracker and workbook keep their own independent version numbers.
A18: Colour key used throughout: green = done in code and tested; amber = done in code but proven only against a fake Meta or in memory; red = not built or blocked. Yellow cells are for the tester to fill in.

Sheet Version_Control
A1: VERSION CONTROL — this document
A3: Version | B3: Date / time | C3: Author | D3: Change description | E3: Status
A4: V001 | B4: 2026-09-20 11:03 | C4: Claude for Senthil/KP | D4: First issue. Version_Detail covers the pre-tracker baseline plus tracker releases v001–v042 (code v0.1.0–v0.46.0). Pending_Versions lists v043 onward and every blocked sprint from both external reviews with the reason it is pending. Manual_Test_Cases holds 129 hand-runnable cases (70 positive, 59 negative) across all versions, verified against the v0.46.0 route table and error names. Built on Senthil's 20 Sep 10:50 request; document-control sheets added on the 10:53 instruction. | E4: Released
A5: V002 | B5: PLANNED | D5: Opens when code v0.47.0 ships (Perplexity PX-S1 response) or when the tester returns results in Manual_Test_Cases and Defect_Log. | E5: Planned
A7: Rule: never edit a released row. Add a new row and bump the file name.

Sheet Context
A1: CONTEXT — what this document describes
A3: What EngageOS is | B3: A WhatsApp-first customer-engagement suite for small and medium businesses: a shared team inbox, campaign broadcasts, no-code chatbot flows, a catalog with UPI payment links, and analytics with a quality-rating guard. Built in TypeScript/Node against the WhatsApp Cloud API, with Hindi and Tamil UI packs and four vertical template packs.
A4: Who it is for | B4: SMEs of roughly 2–50 staff (shops, clinics, coaching centres, local services, D2C support). The specific target customer (ICP) has not yet been chosen — both external reviews name this as the largest single open decision.
A5: Where the product stands | B5: 80 of 100 stories (312 of 399 points) are Done-in-code; 13 stories are Pending-live (need a real Meta WhatsApp Business Account); 6 Drafted; 1 In progress. ZERO stories are Done, because Done means listed on the marketplace and paid for by a stranger. v0.46.0 was the first release to run against a real database (PostgreSQL 16.13); nothing has ever run against real Meta.
A6: Source artefacts | B6: Code: engageos_v0.46.0_src.zip (62 suites / 512 tests, 100% coverage). Tracker: claude_v042 (Review_Findings, CG_Sprint_Plan, Gate_Checklist, Senthil_Handover, 100 log events). Workbook: claude_v047 (Full_Backlog, CG_Hardening_Programme, Risk_Register). Reviews: ChatGPT V001 (F-CG-001..018), Perplexity V001 (F-PX-001..018, PX-S1..S12).
A7: How versions relate | B7: Three independent version streams: code (v0.x.y), tracker (v0NN) and workbook (v0NN). Version_Detail is keyed by tracker release because the tracker is the execution record; each row names the code version it shipped. Workbook versions run ahead of tracker versions because the workbook was started earlier.
A8: Scope of the manual tests | B8: Every case can be run today against v0.46.0 on a laptop with Node 22, Postgres 16 and no Meta credentials. Cases that need live Meta are written as their executable stand-in (a named jest test) and say so. When Meta access arrives, the 12-step sweep in docs/LIVE_VERIFICATION_SWEEP.md is the live half.
A9: Out of scope | B9: Performance/load certification (S16), penetration testing (S17), paid-customer validation (S18) — each needs infrastructure, a vendor or strangers.

Sheet How_To_Use
A1: HOW TO USE — one row per sheet
A3: Sheet | B3: What it is for | C3: Who edits it | D3: Inputs (yellow) and locked cells
A4: Cover | B4: Identity of this document. | C4: Claude on each issue | D4: None. Locked.
A5: Version_Control | B5: History of this document. | C5: Claude on each issue | D5: Add a row per issue; never edit a released row.
A6: Context | B6: What the product is and where it stands, so a reader new to it can use the rest. | C6: Claude | D6: None.
A7: How_To_Use | B7: This sheet. | C7: Claude | D7: None.
A8: Version_Detail | B8: One row per release: what was done and why. Read top to bottom for the story of the product. | C8: Claude (from the tracker) | D8: None. Source of truth is the tracker; this is a readable digest.
A9: Pending_Versions | B9: Everything not yet built, with the reason it is pending and who unblocks it. | C9: Claude; Senthil marks decisions | D9: Column "Unblocked by" tells Senthil what to do.
A10: Manual_Test_Cases | B10: Hand-runnable tests, 2–6 per version, positive and negative. Follow the steps exactly; compare with Expected. | C10: Tester | D10: Yellow columns Actual result, Pass/Fail, Tester, Date. Pass/Fail is a drop-down.
A11: Test_Summary | B11: Live counts per version: cases, passed, failed, not run. Formulas — do not type over. | C11: Nobody (formulas) | D11: All locked.
A12: Test_Environment | B12: What to install and export before running any case; the shorthand ($H, $BASE, sign()) used in the steps. | C12: Tester fills in machine details | D12: Yellow: tester machine, Node and Postgres versions actually used.
A13: Defect_Log | B13: Anything a manual test finds. IDs F-MT-001 onward so they can be admitted to the tracker Review_Findings verbatim. | C13: Tester | D13: All columns are inputs; Severity and Status are drop-downs.
A14: Glossary | B14: Terms and abbreviations. | C14: Claude | D14: None.
A15: Approvals | B15: Sign-off record. | C15: Senthil / reviewer | D15: Yellow name and date cells.

Sheet Version_Detail
A1: VERSION DETAIL — what was done in each release, and why
A3: Tracker version | B3: Date / time | C3: Code version | D3: Theme | E3: What was done | F3: Why it was done | G3: Evidence / artefact | H3: Effect on story status
A4: v000 (pre-tracker) | B4: 2026-09-10 22:22 / 22:55 | C4: v0.1.0 - v0.7.0 | D4: S1-S10 build from the v005 backlog | E4: Fifteen product modules built for sprints S1-S8 (inbox, broadcast, chatbot, catalog, analytics guard, install, billing, compliance, roles, notify, resilience, telemetry, onboarding, latency, config) and four WhatsApp-compliance modules for S9-S10 (24h session window, webhook dedupe/burst, opt-in proof, demo mode). 20 suites / 78 tests at 100% coverage. | F4: Senthil's 10 Sep 22:22 directive: continue EngageOS from the v005 product workbook with 100% automation coverage (decision D13, discovery parked). The v007 run at 22:55 added the draftable S9-S10 scope. | G4: engageos_v0.6.0_src.zip, engageos_v0.7.0_src.zip; tracker events E001-E014 | H4: 75 stories Done-in-code + 8 Pending-live; 10 Drafted
A5: v001 | B5: 2026-09-10 23:06 | C5: v0.7.0 | D5: Tracker created | E5: This tracker file created, mirroring the TeleField v001 pattern: 100-story traceability matrix with version-stamped evidence per story, sprint log E001-E014, rollup formulas, decisions and RAID sheets. | F5: Senthil's 23:06 instruction to create a sprint tracker and traceability record for EngageOS so the two prior runs had a single audit trail. | G5: Tracker v001 | H5: No code change; record established
A6: v002 | B6: 2026-09-10 23:10 | C6: v0.8.0 | D6: Live-sweep readiness | E6: CloudApiAdapter (real WhatsApp Cloud API HTTP client), typed environment config with hard validation, runLiveSweep 12-step scripted verification, 30-minute WABA setup guide. | F6: So that the day Meta credentials arrive, the live verification can run immediately instead of being written under pressure. Re-scoped from 'live wave' because no credentials existed. | G6: engageos_v0.8.0_src.zip; docs/LIVE_SETUP_GUIDE.md, docs/LIVE_VERIFICATION_SWEEP.md | H6: None (Pending-live flips need sweep evidence, rule R2)
A7: v003 | B7: 2026-09-11 08:17 | C7: v0.9.0 | D7: Cold-review pass 1 | E7: Four defects fixed with regression tests: F-001 inbox crash before setup, F-002 chatbot TypeError on an options-less question node, F-003 unbounded webhook dedupe ledger (memory leak) now FIFO-capped, F-004 hardcoded template language 'en'. Four more logged for Senthil's disposition (F-005..F-008). Review_Findings sheet and docs/REVIEW_PACK.md added. | F7: An adversarial self-review before any external eye; a second reviewer needed a pack to work from (ST-097). Same-AI review does not satisfy independence, so ST-097 stayed In progress. | G7: engageos_v0.9.0_src.zip; tests inbox/chatbot/webhookGuard/cloudApiAdapter | H7: None
A8: v004 | B8: 2026-09-11 12:51 | C8: v0.10.0 | D8: Review-prep completion | E8: ST-089 WCAG accessibility shells with a jest-axe suite; ST-068 security evidence pack (sandbox half); ST-094 asset plan drafted. | F8: To reduce the backlog to only the stories that truly need an external party (Meta, a vendor, strangers). | G8: engageos_v0.10.0_src.zip; docs/SECURITY_EVIDENCE.md | H8: ST-089 Done-in-code; ST-068 In progress; ST-094 Drafted
A9: v005 | B9: 2026-09-13 09:55 | C9: v0.11.0 | D9: Cold-review pass 2 + backlog zero | E9: Eight defects fixed (F-009..F-016). Headline: the opt-in gate and the 24-hour session window had been built in v007 and were never called by any send path, so marketing could have reached non-consented contacts. Remaining codeable stories completed; backlog reached zero. | F9: Second adversarial pass found the 'built but never wired' class for the first time. Code phase declared complete: 79 Done-in-code / 10 Pending-live / 9 Drafted / 2 In progress. | G9: engageos_v0.11.0_src.zip; 27 suites / 118 tests | H9: Backlog 0; 309/399 points Done-in-code
A10: v006 | B10: 2026-09-13 10:23 | C10: v0.12.0 | D10: Artifact-gap audit (HTTP layer + schema) | E10: Six gaps, two critical: no HTTP application and no database schema existed although the setup guide, deploy workflow and k6 harness all referred to them. Built: framework-free router, webhook verify/receive with X-Hub-Signature-256, healthz, pricing, help search, status, npm start entry, four ordered migrations, k6 fixture generator, sweep CLI, docs drift gates. | F10: Documents promised an HTTP surface that did not exist; a product with no server cannot be installed by anyone. Missing plumbing, not new stories. | G10: engageos_v0.12.0_src.zip; src/http/*, db/migrations/001-004 | H10: ST-088/090/092 Code-complete
A11: v007 | B11: 2026-09-13 10:35 | C11: v0.13.0 | D11: Cold-review pass 3 (HTTP layer) | E11: F-017 no multi-tenancy (one dedupe ledger and session window shared across every WABA), F-018 a valid signature treated as proof of installation, F-019 operational detail exposed publicly, F-020 no OAuth CSRF state. New tenancy.ts and oauth.ts; operator-token-gated admin routes; single-use 10-minute OAuth state. | F11: The new HTTP layer was reviewed adversarially before anything else was built on it; two findings were critical. | G11: engageos_v0.13.0_src.zip | H11: None
A12: v008 | B12: 2026-09-13 10:38 | C12: v0.14.0 | D12: Verification sweep vs Meta docs, pass 1 (pricing + payloads) | E12: VER-E5 batched webhooks: only the first message of each envelope was processed (data loss). VER-E1 the commercial model used conversation-based pricing, retired by Meta on 1 Jul 2025 - replaced with per-message pricing (messageCost.ts). VER-E2 authentication category, VER-E3 72-hour free entry point, VER-E6 80 msg/s throughput limiter. | F12: Internal review cannot check the model of the world; the platform documentation was read directly and thirteen corrections followed across three passes. | G12: engageos_v0.14.0_src.zip; src/messageCost.ts, src/throughput.ts | H12: None (correctness release)
A13: v009 | B13: 2026-09-13 10:58 | C13: v0.15.0 | D13: Verification sweep pass 2 (limits + policy) | E13: VER-E7 messaging-tier awareness (250 unique recipients per rolling 24h for a new account, portfolio-wide), VER-E9 US marketing freeze guard, VER-E10 frequency-cap errors (131049) must not be retried. New messagingTier.ts and sendPolicy.ts wired into the send path. | F13: Without tier awareness a first campaign would have been silently throttled by Meta; new risk R-E8 recorded. | G13: engageos_v0.15.0_src.zip | H13: None
A14: v010 | B14: 2026-09-13 11:04 | C14: v0.16.0 | D14: Verification sweep pass 3 (message handling) | E14: VER-E11 status webhooks were discarded so campaign metrics counted API acceptance as delivery; VER-E12 inbound media dropped (only a media_id arrives); VER-E13 interactive button/list replies unreadable by the chatbot. New deliveryStatus.ts, media.ts, interactive.ts. | F14: Completes the platform verification sweep across pricing, limits, policy and message handling. | G14: engageos_v0.16.0_src.zip | H14: None
... A46: v042 | B46: 2026-09-16 18:40 | C46: v0.46.0 | D46: Review response phase 3 + first real Postgres | E46: F-CG-003 code half (Meta code exchange, debug_token, WABA/number discovery, forged-id refusal; no fabricated tokens); F-CG-004 first slice (tenant connections durable, restored at boot); F-CG-005 live half (server boots on real Postgres 16.13, survives restart, 503 during outage); F-CG-008 slice (logout, revoke-agent); S07 remainder (rate limits, body schemas, SSRF allowlist, CSRF by construction); SBOM + dependency policy. Five gate defects found by a clean-room CI replay (F-050..F-054) incl. the smoke gate could never pass. | F46: Senthil 16 Sep 16:21: go through the review, update code and trackers, create the next version; plan approved 18:03 ('do all'). | G46: engageos_v0.46.0_src.zip; docs/PG_EVIDENCE_TRANSCRIPT.md; 62 suites / 512 tests | H46: None (312/399 points; zero Done)
A48: Story status effect is "None" for most rows by design (rule R2): code being complete does not move a story to Done. The only rows that moved stories were the build waves and the review that closed ST-097.

Sheet Pending_Versions
A1: PENDING VERSIONS AND SPRINTS — why each is not done yet
A3: Planned version / sprint | B3: Maps to | C3: Scope | D3: Source finding(s) | E3: Reason it is pending | F3: Unblocked by | G3: Owner
A4: v043 / v0.47.0 | B4: PX-S1 + S00 remainder | C4: Pricing model for 1 Oct 2026 (service and utility-in-window billable, business_agent category, date-aware isBillable); gateMatrix test; engines/.nvmrc; PLATFORM_ASSUMPTIONS.md with 90-day staleness test; addToWindow transaction; idempotency keys; operator token scoped to tenants; key rotation. | D4: Perplexity review V001 (F-PX-001, 004, 007, 008, 011, 018) | E4: Plan presented 20 Sep 10:39; awaiting Senthil's 'go ahead'. F-PX-001 has a hard external deadline of 1 Oct 2026. | F4: Senthil approval | G4: Claude
A5: v044 / v0.48.0 | B5: PX-S2 / S02 durable data plane | C5: Conversations, contacts, opt-in proofs, campaigns, catalog, billing, audit and support moved from process memory into Postgres repositories; WorkspaceRegistry becomes a loader; down-migrations. | D5: F-CG-004, F-PX-003 | E5: Sequenced after v0.47.0; needs no external input. Largest body of work in either review (~3 weeks). | F5: Time | G5: Claude
A6: v045 / v0.49.0 | B6: PX-S3 / S04+S09 real authentication | C6: Email OTP or magic-link sign-in, users and memberships tables, self-serve agent invites, operator token bound to tenants. | D6: F-CG-008, F-PX-002 | E6: Sequenced after the data plane (users need a durable table). No external input needed. | F6: Time | G6: Claude
A7: v046 / v0.50.0 | B7: PX-S4 + PX-S5 / S03 + S07 | C7: Concurrency proofs on real Postgres (claimOnce, addToWindow race), pool exhaustion and failover tests, abuse suite (slow-loris, header floods, 10k webhook posts), OWASP API checklist. | D7: F-PX-011, F-PX-008 | E7: Sequenced; needs no external input. | F7: Time | G7: Claude
A8: v047 / v0.51.0 | B8: PX-S7 + PX-S8 / S10 + S08 | C8: OpenTelemetry metrics, /metrics endpoint, structured JSON logs, SLOs and alert rules with an executed drill; export/delete across every durable table driven by a data-location registry; DPDP obligations matrix (deadline 13 May 2027). | D8: F-CG-012, F-CG-013, F-PX-009, F-PX-012 | E8: Depends on the data plane (v0.48.0). Legal review of the DPDP matrix is Senthil's. | F8: v0.48.0; counsel | G8: Claude / Senthil
A9: Live wave (any version) | B9: S01 + S06 + CG-G1/G3 | C9: Real Meta embedded signup with two test WABAs, the 12-step live verification sweep, template approval, 13 Pending-live stories flipped on evidence. | D9: F-CG-003 live half, F-CG-011 | E9: BLOCKED: no Meta Business verification, no WABA, no META_APP_ID. Handover items 1, 3, 4, 11. | F9: Senthil: Meta forms (~30 min) + days of Meta queue | G9: Senthil
A10: PX-S6 / S05 payments | B10: Payment provider end to end | C10: Razorpay or Stripe behind a PaymentProvider interface, provider webhooks with signature and replay protection, provider-issued payment intents, usage metering reconciled to the Meta invoice, message-cost intelligence view. | D10: F-CG-006 remainder, F-PX-010 | E10: BLOCKED on the payment-provider decision (handover 12), which depends on the ICP decision (handover 13). | F10: Senthil decisions 12 and 13 | G10: Senthil then Claude
A11: PX-S9 / S13 one vertical | B11: Differentiation | C11: Delete three of the four vertical packs; build one end-to-end workflow (no-show recovery for clinics, or attendance-and-fee follow-up for coaching); re-price against the India/Europe ladder; grow the vernacular surface; native-speaker review. | D11: F-CG-014, F-PX-005/006/013/016 | E11: BLOCKED on the ICP decision (handover 13). Both reviewers say this is the largest single unblock. | F11: Senthil decision 13 | G11: Senthil then Claude
A12: PX-S10 / S12 procurement pack | B12: Documents | C12: LICENSE, DPA, subprocessor list, retention schedule, security-questionnaire answers with evidence links, status page. | D12: F-PX-014 | E12: Cheap, but the DPA and licence are legal instruments Senthil must choose; sequenced after the ICP decision so the documents name the right market. | F12: Senthil (licence, DPA) | G12: Claude drafts / Senthil signs
A13: PX-S11 / S14 AI above the baseline | B13: AI-assisted replies | C13: Retrieval grounded in the tenant's own data, confidence threshold with mandatory human escalation, per-intent eval set, cost comparison against Meta Business Agent. | D13: F-PX-017 | E13: BLOCKED on an entry criterion: a written reading of the current WhatsApp Business Solution Terms confirming the design is business-specific automation, not a general-purpose assistant. | F13: Senthil (terms reading) | G13: Senthil then Claude
A14: PX-S12 / S11 + S19 deploy, drill, gate | B14: Deployment and DR | C14: Infrastructure as code, automated deploy, rollback under 10 minutes, restore from backup with measured RPO/RTO, k6 capacity envelope, gate re-worded to 'production-ready for SMEs'. | D14: F-CG-010, F-PX-015 | E14: BLOCKED on target infrastructure (a cloud account) and, for the gate wording, Senthil's acceptance of F-PX-015. | F14: Senthil: cloud account + F-PX-015 disposition | G14: Senthil then Claude
... A17: Senthil dispositions | B17: Record | C17: F-005..F-008, D-E1, D-E2, D-E4, D-E5, D-E6, F-CG-014..018, F-PX-005/006/013/015/017: accept / defer / reject per row. | D17: Review_Findings sheet | E17: Judgement calls Claude should not make; cheap (about an hour in total) and they unblock the record rather than code. | F17: Senthil | G17: Senthil
A19: Colour on "Reason": green = can start now with no input from Senthil; amber = waiting for approval; red = blocked on something outside the code (Meta, infrastructure, a vendor, a decision or strangers).

Sheet Manual_Test_Cases
A1: MANUAL TEST CASES — one row per case; steps are literal
A3: Test ID | B3: Tracker version | C3: Code version | D3: Test case name | E3: Type | F3: Description | G3: Step-by-step | H3: Expected result | I3: Actual result | J3: Pass/Fail | K3: Tester | L3: Date
A4: MT-001 | B4: v000 (pre-tracker) | C4: v0.1.0-v0.7.0 | D4: Clean build and full suite | E4: Positive | F4: The shipped artifact builds and the 100% coverage gate holds. | G4: 1. Unzip engageos_v0.46.0_src.zip into an empty folder. 2. cd engageos && npm ci 3. npm run build 4. npm test | H4: npm ci, build and test all exit 0. Jest reports 62 suites / 512 tests passed and 'All files' 100 / 100 / 100 / 100. (Counts are for v0.46.0, the current artifact.)
A5: MT-002 | B5: v000 (pre-tracker) | C5: v0.1.0-v0.7.0 | D5: Coverage gate refuses a regression | E5: Negative | F5: Deleting a test must fail the build, proving the gate is enforced, not decorative. | G5: 1. In the unzipped tree, delete tests/catalog.test.ts. 2. npm test 3. Restore the file (re-unzip). | H5: Jest exits non-zero with 'Coverage for statements ... does not meet global threshold (100%)'. After restoring, npm test passes again.
A6: MT-003 | B6: v001 | C6: v0.7.0 | D6: Tracker traceability matches the backlog | E6: Positive | F6: Every story in the product workbook appears in the tracker matrix with the same points. | G6: 1. Open claude_v047 workbook, sheet Full_Backlog; note the 100 story IDs and points. 2. Open claude_v042 tracker, sheet Traceability_Matrix. 3. Filter column A for ST-; compare the count and spot-check ST-001, ST-050, ST-100 points. | H6: 100 stories in both; points match; Sprint_Status_Rollup TOTAL row shows 100 stories / 399 points / 312 done points.
A7: MT-004 | B7: v001 | C7: v0.7.0 | D7: Rollup formulas are live, not typed | E7: Negative | F7: Changing a status must move the rollup. | G7: 1. In a COPY of the tracker, change Traceability_Matrix status of ST-001 from Done-in-code to Backlog. 2. Recalculate (F9 / open in Excel). 3. Read Sprint_Status_Rollup TOTAL 'Done points'. | H7: Done points drops from 312 to 307 (ST-001 is 5 points). Discard the copy.
A8: MT-005 | B8: v002 | C8: v0.8.0 | D8: Config refuses missing secrets by name | E8: Negative | F8: Boot with a blank required variable. | G8: 1. Export all variables from Test_Environment except WA_WABA_ID (unset it). 2. node dist/src/http/index.js | H8: Process exits immediately with 'MISSING_ENV:WA_WABA_ID'. No port is opened.
A9: MT-006 | B9: v002 | C9: v0.8.0 | D9: Dry sweep runs without credentials | E9: Positive | F9: The 12-step live sweep runs in dry mode against the fake platform. | G9: 1. With Test_Environment variables set: npm run sweep:dry | H9: Prints 'MODE: dry run', six PASS lines (config, outbound send, quality rating, 24h window, dedupe, opt-in gate), '6 passed, 0 failed', exit 0.
A10: MT-007 | B10: v002 | C10: v0.8.0 | D10: Real adapter fails honestly with placeholder token | E10: Negative | F10: A reply through the real Cloud API adapter with a fake token must fail loudly, not pretend to succeed. | G10: 1. Start the server (Test_Environment). 2. Post a signed webhook (see v006 case 'Signed webhook becomes a conversation'). 3. CID=$(curl -s $H $BASE/api/inbox | sed 's/.*"id":"\([^"]*\)".*/\1/') 4. curl -s -w ' HTTP %{http_code}' -X POST $H -d '{"text":"hello"}' $BASE/api/inbox/$CID/reply | H10: HTTP 502 with body {"sent":false,"error":"WA_HTTP_401"} (or WA_HTTP_403). Never {"sent":true}.
A11: MT-008 | B11: v003 | C11: v0.9.0 | D11: F-001 inbox before setup is refused cleanly | E11: Negative | F11: A message arriving before agents are configured must not crash with NaN. | G11: 1. Start the server WITHOUT ENGAGEOS_DEMO and with ENGAGEOS_AGENTS unset. 2. Post a signed webhook for $TENANT. 3. Read the server log and the webhook response. | H11: Webhook returns HTTP 200 with outcome 'queued' or a named error INBOX_NOT_CONFIGURED in the results; the process does not crash and /healthz still answers.
A12: MT-009 | B12: v003 | C12: v0.9.0 | D12: F-002 question node without options is rejected | E12: Negative | F12: Creating a chatbot question node with no options returns a named error, not a stack trace. | G12: 1. FID=$(curl -s -X POST $H -d '{"name":"t"}' $BASE/api/flows | sed 's/.*"id":"\([^"]*\)".*/\1/') 2. curl -s -w ' HTTP %{http_code}' -X POST $H -d '{"node":{"id":"q1","type":"question","text":"Size?"}}' $BASE/api/flows/$FID/nodes | H12: HTTP 400 with {"error":"INVALID_NODE_NO_OPTIONS:q1"}.
A13: MT-010 | B13: v003 | C13: v0.9.0 | D13: F-003 dedupe ledger is bounded | E13: Positive | F13: The webhook dedupe ledger must not grow without limit. | G13: 1. Send 500 signed webhooks with distinct wamids (loop in bash, changing the id each time). 2. curl -s -H "X-Operator-Token: $OP" $BASE/admin/health | H13: All 500 return HTTP 200; /admin/health answers; process memory (ps -o rss) stays flat after the cap (20x queue size) is reached. duplicatesSeen is 0.
A14: MT-011 | B14: v003 | C14: v0.9.0 | D14: F-004 template language is per send | E14: Positive | F14: A Hindi template is sent with language code hi. | G14: 1. curl -s -X POST $H -d '{"name":"order_update","values":{"1":"A1"},"lang":"hi"}' $BASE/api/inbox/$CID/template (CID from an earlier case) | H14: Response is a JSON outcome (502 with WA_HTTP_4xx under placeholder credentials is acceptable); server log / rehearsal shows the payload language.code = 'hi', not 'en'.
A15: MT-012 | B15: v004 | C15: v0.10.0 | D15: Screens pass an accessibility audit | E15: Positive | F15: Served screens are axe-clean. | G15: 1. npx jest tests/views.a11y.test.ts --coverage=false | H15: All tests pass; no axe violations reported.
... A132: MT-129 | B132: v042 | C132: v0.46.0 | D132: Pre-v0.46.0 session tokens are refused | E132: Negative | F132: A five-field token signed with the real secret is rejected. | G132: 1. npx jest tests/auth.test.ts -t 'expiry' --coverage=false | H132: Passes: legacy token verify() returns null.

Sheet Test_Summary
A1: TEST SUMMARY — live formulas over Manual_Test_Cases (do not edit)
A3: Tracker version | B3: Cases | C3: Positive | D3: Negative | E3: Pass | F3: Fail | G3: Blocked | H3: Not run / blank
A4: v000 (pre-tracker) | B4: =COUNTIF(Manual_Test_Cases!$B$4:$B$132,A4) -> 2 | C4: =COUNTIFS(Manual_Test_Cases!$B$4:$B$132,A4,Manual_Test_Cases!$E$4:$E$132,"Positive") -> 1 | D4: =COUNTIFS(Manual_Test_Cases!$B$4:$B$132,A4,Manual_Test_Cases!$E$4:$E$132,"Negative") -> 1 | E4: =COUNTIFS(Manual_Test_Cases!$B$4:$B$132,A4,Manual_Test_Cases!$J$4:$J$132,"Pass") -> 0 | F4: =COUNTIFS(Manual_Test_Cases!$B$4:$B$132,A4,Manual_Test_Cases!$J$4:$J$132,"Fail") -> 0 | G4: =COUNTIFS(Manual_Test_Cases!$B$4:$B$132,A4,Manual_Test_Cases!$J$4:$J$132,"Blocked") -> 0 | H4: =B4-E4-F4-G4 -> 2
A5: v001 | B5: =COUNTIF(Manual_Test_Cases!$B$4:$B$132,A5) -> 2 | C5: =COUNTIFS(Manual_Test_Cases!$B$4:$B$132,A5,Manual_Test_Cases!$E$4:$E$132,"Positive") -> 1 | D5: =COUNTIFS(Manual_Test_Cases!$B$4:$B$132,A5,Manual_Test_Cases!$E$4:$E$132,"Negative") -> 1 | E5: =COUNTIFS(Manual_Test_Cases!$B$4:$B$132,A5,Manual_Test_Cases!$J$4:$J$132,"Pass") -> 0 | F5: =COUNTIFS(Manual_Test_Cases!$B$4:$B$132,A5,Manual_Test_Cases!$J$4:$J$132,"Fail") -> 0 | G5: =COUNTIFS(Manual_Test_Cases!$B$4:$B$132,A5,Manual_Test_Cases!$J$4:$J$132,"Blocked") -> 0 | H5: =B5-E5-F5-G5 -> 2
A6: v002 | B6: =COUNTIF(Manual_Test_Cases!$B$4:$B$132,A6) -> 3 | C6: =COUNTIFS(Manual_Test_Cases!$B$4:$B$132,A6,Manual_Test_Cases!$E$4:$E$132,"Positive") -> 1 | D6: =COUNTIFS(Manual_Test_Cases!$B$4:$B$132,A6,Manual_Test_Cases!$E$4:$E$132,"Negative") -> 2 | E6: =COUNTIFS(Manual_Test_Cases!$B$4:$B$132,A6,Manual_Test_Cases!$J$4:$J$132,"Pass") -> 0 | F6: =COUNTIFS(Manual_Test_Cases!$B$4:$B$132,A6,Manual_Test_Cases!$J$4:$J$132,"Fail") -> 0 | G6: =COUNTIFS(Manual_Test_Cases!$B$4:$B$132,A6,Manual_Test_Cases!$J$4:$J$132,"Blocked") -> 0 | H6: =B6-E6-F6-G6 -> 3
A7: v003 | B7: =COUNTIF(Manual_Test_Cases!$B$4:$B$132,A7) -> 4 | C7: =COUNTIFS(Manual_Test_Cases!$B$4:$B$132,A7,Manual_Test_Cases!$E$4:$E$132,"Positive") -> 2 | D7: =COUNTIFS(Manual_Test_Cases!$B$4:$B$132,A7,Manual_Test_Cases!$E$4:$E$132,"Negative") -> 2 | E7: =COUNTIFS(Manual_Test_Cases!$B$4:$B$132,A7,Manual_Test_Cases!$J$4:$J$132,"Pass") -> 0 | F7: =COUNTIFS(Manual_Test_Cases!$B$4:$B$132,A7,Manual_Test_Cases!$J$4:$J$132,"Fail") -> 0 | G7: =COUNTIFS(Manual_Test_Cases!$B$4:$B$132,A7,Manual_Test_Cases!$J$4:$J$132,"Blocked") -> 0 | H7: =B7-E7-F7-G7 -> 4
A8: v004 | B8: =COUNTIF(Manual_Test_Cases!$B$4:$B$132,A8) -> 2 | C8: =COUNTIFS(Manual_Test_Cases!$B$4:$B$132,A8,Manual_Test_Cases!$E$4:$E$132,"Positive") -> 2 | D8: =COUNTIFS(Manual_Test_Cases!$B$4:$B$132,A8,Manual_Test_Cases!$E$4:$E$132,"Negative") -> 0 | E8: =COUNTIFS(Manual_Test_Cases!$B$4:$B$132,A8,Manual_Test_Cases!$J$4:$J$132,"Pass") -> 0 | F8: =COUNTIFS(Manual_Test_Cases!$B$4:$B$132,A8,Manual_Test_Cases!$J$4:$J$132,"Fail") -> 0 | G8: =COUNTIFS(Manual_Test_Cases!$B$4:$B$132,A8,Manual_Test_Cases!$J$4:$J$132,"Blocked") -> 0 | H8: =B8-E8-F8-G8 -> 2
A9: v005 | B9: =COUNTIF(Manual_Test_Cases!$B$4:$B$132,A9) -> 3 | C9: =COUNTIFS(Manual_Test_Cases!$B$4:$B$132,A9,Manual_Test_Cases!$E$4:$E$132,"Positive") -> 1 | D9: =COUNTIFS(Manual_Test_Cases!$B$4:$B$132,A9,Manual_Test_Cases!$E$4:$E$132,"Negative") -> 2 | E9: =COUNTIFS(Manual_Test_Cases!$B$4:$B$132,A9,Manual_Test_Cases!$J$4:$J$132,"Pass") -> 0 | F9: =COUNTIFS(Manual_Test_Cases!$B$4:$B$132,A9,Manual_Test_Cases!$J$4:$J$132,"Fail") -> 0 | G9: =COUNTIFS(Manual_Test_Cases!$B$4:$B$132,A9,Manual_Test_Cases!$J$4:$J$132,"Blocked") -> 0 | H9: =B9-E9-F9-G9 -> 3
A10: v006 | B10: =COUNTIF(Manual_Test_Cases!$B$4:$B$132,A10) -> 7 | C10: =COUNTIFS(Manual_Test_Cases!$B$4:$B$132,A10,Manual_Test_Cases!$E$4:$E$132,"Positive") -> 4 | D10: =COUNTIFS(Manual_Test_Cases!$B$4:$B$132,A10,Manual_Test_Cases!$E$4:$E$132,"Negative") -> 3 | E10: =COUNTIFS(Manual_Test_Cases!$B$4:$B$132,A10,Manual_Test_Cases!$J$4:$J$132,"Pass") -> 0 | F10: =COUNTIFS(Manual_Test_Cases!$B$4:$B$132,A10,Manual_Test_Cases!$J$4:$J$132,"Fail") -> 0 | G10: =COUNTIFS(Manual_Test_Cases!$B$4:$B$132,A10,Manual_Test_Cases!$J$4:$J$132,"Blocked") -> 0 | H10: =B10-E10-F10-G10 -> 7
A11: v007 | B11: =COUNTIF(Manual_Test_Cases!$B$4:$B$132,A11) -> 4 | C11: =COUNTIFS(Manual_Test_Cases!$B$4:$B$132,A11,Manual_Test_Cases!$E$4:$E$132,"Positive") -> 1 | D11: =COUNTIFS(Manual_Test_Cases!$B$4:$B$132,A11,Manual_Test_Cases!$E$4:$E$132,"Negative") -> 3 | E11: =COUNTIFS(Manual_Test_Cases!$B$4:$B$132,A11,Manual_Test_Cases!$J$4:$J$132,"Pass") -> 0 | F11: =COUNTIFS(Manual_Test_Cases!$B$4:$B$132,A11,Manual_Test_Cases!$J$4:$J$132,"Fail") -> 0 | G11: =COUNTIFS(Manual_Test_Cases!$B$4:$B$132,A11,Manual_Test_Cases!$J$4:$J$132,"Blocked") -> 0 | H11: =B11-E11-F11-G11 -> 4
A12: v008 | B12: =COUNTIF(Manual_Test_Cases!$B$4:$B$132,A12) -> 3 | C12: =COUNTIFS(Manual_Test_Cases!$B$4:$B$132,A12,Manual_Test_Cases!$E$4:$E$132,"Positive") -> 3 | D12: =COUNTIFS(Manual_Test_Cases!$B$4:$B$132,A12,Manual_Test_Cases!$E$4:$E$132,"Negative") -> 0 | E12: =COUNTIFS(Manual_Test_Cases!$B$4:$B$132,A12,Manual_Test_Cases!$J$4:$J$132,"Pass") -> 0 | F12: =COUNTIFS(Manual_Test_Cases!$B$4:$B$132,A12,Manual_Test_Cases!$J$4:$J$132,"Fail") -> 0 | G12: =COUNTIFS(Manual_Test_Cases!$B$4:$B$132,A12,Manual_Test_Cases!$J$4:$J$132,"Blocked") -> 0 | H12: =B12-E12-F12-G12 -> 3
A13: v009 | B13: =COUNTIF(Manual_Test_Cases!$B$4:$B$132,A13) -> 2 | C13: =COUNTIFS(Manual_Test_Cases!$B$4:$B$132,A13,Manual_Test_Cases!$E$4:$E$132,"Positive") -> 0 | D13: =COUNTIFS(Manual_Test_Cases!$B$4:$B$132,A13,Manual_Test_Cases!$E$4:$E$132,"Negative") -> 2 | E13: =COUNTIFS(Manual_Test_Cases!$B$4:$B$132,A13,Manual_Test_Cases!$J$4:$J$132,"Pass") -> 0 | F13: =COUNTIFS(Manual_Test_Cases!$B$4:$B$132,A13,Manual_Test_Cases!$J$4:$J$132,"Fail") -> 0 | G13: =COUNTIFS(Manual_Test_Cases!$B$4:$B$132,A13,Manual_Test_Cases!$J$4:$J$132,"Blocked") -> 0 | H13: =B13-E13-F13-G13 -> 2
A14: v010 | B14: =COUNTIF(Manual_Test_Cases!$B$4:$B$132,A14) -> 3 | C14: =COUNTIFS(Manual_Test_Cases!$B$4:$B$132,A14,Manual_Test_Cases!$E$4:$E$132,"Positive") -> 3 | D14: =COUNTIFS(Manual_Test_Cases!$B$4:$B$132,A14,Manual_Test_Cases!$E$4:$E$132,"Negative") -> 0 | E14: =COUNTIFS(Manual_Test_Cases!$B$4:$B$132,A14,Manual_Test_Cases!$J$4:$J$132,"Pass") -> 0 | F14: =COUNTIFS(Manual_Test_Cases!$B$4:$B$132,A14,Manual_Test_Cases!$J$4:$J$132,"Fail") -> 0 | G14: =COUNTIFS(Manual_Test_Cases!$B$4:$B$132,A14,Manual_Test_Cases!$J$4:$J$132,"Blocked") -> 0 | H14: =B14-E14-F14-G14 -> 3
A15: v011 | B15: =COUNTIF(Manual_Test_Cases!$B$4:$B$132,A15) -> 2 | C15: =COUNTIFS(Manual_Test_Cases!$B$4:$B$132,A15,Manual_Test_Cases!$E$4:$E$132,"Positive") -> 1 | D15: =COUNTIFS(Manual_Test_Cases!$B$4:$B$132,A15,Manual_Test_Cases!$E$4:$E$132,"Negative") -> 1 | E15: =COUNTIFS(Manual_Test_Cases!$B$4:$B$132,A15,Manual_Test_Cases!$J$4:$J$132,"Pass") -> 0 | F15: =COUNTIFS(Manual_Test_Cases!$B$4:$B$132,A15,Manual_Test_Cases!$J$4:$J$132,"Fail") -> 0 | G15: =COUNTIFS(Manual_Test_Cases!$B$4:$B$132,A15,Manual_Test_Cases!$J$4:$J$132,"Blocked") -> 0 | H15: =B15-E15-F15-G15 -> 2
... A46: v042 | B46: =COUNTIF(Manual_Test_Cases!$B$4:$B$132,A46) -> 24 | C46: =COUNTIFS(Manual_Test_Cases!$B$4:$B$132,A46,Manual_Test_Cases!$E$4:$E$132,"Positive") -> 11 | D46: =COUNTIFS(Manual_Test_Cases!$B$4:$B$132,A46,Manual_Test_Cases!$E$4:$E$132,"Negative") -> 13 | E46: =COUNTIFS(Manual_Test_Cases!$B$4:$B$132,A46,Manual_Test_Cases!$J$4:$J$132,"Pass") -> 0 | F46: =COUNTIFS(Manual_Test_Cases!$B$4:$B$132,A46,Manual_Test_Cases!$J$4:$J$132,"Fail") -> 0 | G46: =COUNTIFS(Manual_Test_Cases!$B$4:$B$132,A46,Manual_Test_Cases!$J$4:$J$132,"Blocked") -> 0 | H46: =B46-E46-F46-G46 -> 24
A47: TOTAL | B47: =SUM(B4:B46) -> 129 | C47: =SUM(C4:C46) -> 70 | D47: =SUM(D4:D46) -> 59 | E47: =SUM(E4:E46) -> 0 | F47: =SUM(F4:F46) -> 0 | G47: =SUM(G4:G46) -> 0 | H47: =SUM(H4:H46) -> 129
A49: Pass rate of cases run | B49: =IF((E47+F47)=0,0,E47/(E47+F47)) -> 0

Sheet Test_Environment
A1: TEST ENVIRONMENT — set this up once
A3: Machine | B3: Any laptop; Linux/macOS shell or Windows with Git Bash/WSL. Tester records the machine below.
A4: Node | B4: Node 22 (v22.x). Check: node -v
A5: PostgreSQL | B5: PostgreSQL 16 (only for the SHARED_STORE=pg cases). Check: psql --version. Create: createdb engageos_mt
A6: Tools | B6: curl, openssl (for webhook signatures), unzip. Optional: jq for readable JSON.
A7: Unpack and build | B7: unzip engageos_v0.46.0_src.zip && cd engageos && npm ci && npm run build
A8: Environment variables (memory mode) | B8: export WA_ACCESS_TOKEN=placeholder_access_token_long WA_PHONE_NUMBER_ID=pn_mt WA_WABA_ID=waba_mt WA_WEBHOOK_VERIFY_TOKEN=verify_token_placeholder_long WA_APP_SECRET=app_secret_placeholder_long ENGAGEOS_OPERATOR_TOKEN=operator_token_placeholder_long ENGAGEOS_SESSION_SECRET=session-secret-placeholder-long ENGAGEOS_CRED_KEY=$(openssl rand -hex 32) DB_ENCRYPTION_AT_REST=true TLS_MIN=1.2 SECRETS_SOURCE=vault ENGAGEOS_AGENTS=owner,asha ENGAGEOS_DEMO=1 PORT=8080
A9: Environment variables (pg mode) | B9: Additionally: export SHARED_STORE=pg DATABASE_URL=postgres://<user>@127.0.0.1:5432/engageos_mt ENGAGEOS_TEST_DATABASE_URL=$DATABASE_URL ; then npm run migrate
A10: Start the server | B10: node dist/src/http/index.js (prints "EngageOS listening on 8080 (store=memory|pg, tenants restored=1)")
A11: Shorthand used in steps | B11: $BASE = http://localhost:8080 $OP = $ENGAGEOS_OPERATOR_TOKEN $TENANT = $WA_PHONE_NUMBER_ID $H = -H "X-Operator-Token: $OP" -H "X-Tenant-Id: $TENANT" -H "Content-Type: application/json" sign(BODY) = "sha256=$(printf '%s' "$BODY" | openssl dgst -sha256 -hmac "$WA_APP_SECRET" | sed 's/^.* //')" $CID = id of the first conversation from GET /api/inbox ; $TOKEN = a session token from POST /api/session
A12: Placeholder credentials | B12: The WhatsApp adapter is real. With placeholder credentials every outbound send fails honestly with HTTP 502 / WA_HTTP_401 or 403. That failure is the expected result wherever a case says so; a green "sent" would be the defect.
A13: Reset between cases | B13: In memory mode, restart the server to clear state. In pg mode: psql $DATABASE_URL -c "delete from tenant_connections where tenant_id <> 'pn_mt'; delete from shared_claims; delete from shared_timestamps"
A14: Tester machine used (fill in)
A15: Node version used (fill in)
A16: Postgres version used (fill in)
A17: Date environment set up (fill in)

Sheet Defect_Log
A1: DEFECT LOG — anything a manual test finds
A3: Defect ID | B3: Test ID | C3: Severity | D3: Observed (what happened) | E3: Evidence (command, output, screenshot name) | F3: Status | G3: Disposition / fix version | H3: Raised by | I3: Date
A4: F-MT-001 | B4: MT-000 | C4: Obs | D4: EXAMPLE ROW — delete before use. /pricing returned a table with a trailing blank line. | E4: curl -s $BASE/pricing | tail -2 | F4: Open | H4: tester | I4: 2026-09-20
A42: Severity scale matches the tracker: Blocker / Major / Minor / Obs. Copy rows into the tracker Review_Findings sheet with IDs unchanged.

Sheet Glossary
A1: GLOSSARY
A3: Term | B3: Meaning
A4: WABA | B4: WhatsApp Business Account — the Meta account a business sends from. Two are needed to prove tenant isolation.
A5: Cloud API | B5: Meta's hosted WhatsApp Business Platform API. EngageOS talks to it through src/cloudApiAdapter.ts.
A6: Webhook | B6: The HTTPS callback Meta sends inbound messages and delivery statuses to (POST /webhook), signed with X-Hub-Signature-256.
A7: Tenant | B7: One business on EngageOS, identified by its WhatsApp phone number id (pn_...).
A8: Done-in-code | B8: The story's code and tests exist and are wired into the running product. NOT the same as Done.
A9: Done | B9: Listed on the marketplace and paid for by a stranger. Zero stories are Done.
A10: Pending-live | B10: Code complete; needs a real Meta account to verify.
A11: ICP | B11: Ideal customer profile — the one vertical EngageOS will be built for. Undecided (handover item 13).
A12: F-0NN / F-CG-0NN / F-PX-0NN | B12: Finding IDs: internal cold reviews / ChatGPT review V001 / Perplexity review V001. Reviewer IDs are preserved verbatim.
A13: S00–S19 / PX-S1–S12 | B13: Hardening sprint programmes proposed by the ChatGPT and Perplexity reviews respectively.
A14: CG-G0..G11 | B14: Completion gates from the ChatGPT review, in the tracker Gate_Checklist sheet.
... A21: DPDP | B21: India's Digital Personal Data Protection Act and Rules 2025; main compliance deadline 13 May 2027.

Sheet Approvals
A1: APPROVALS
A3: Role | B3: Name | C3: Signature / initials | D3: Date | E3: Comments
A4: Prepared by | B4: Claude for Senthil/KP | C4: Claude | D4: 2026-09-20 | E4: Built from tracker v042, workbook v047 and code v0.46.0.
A5: Reviewed by
A6: Approved by | B6: Senthil (KP)
A7: Test lead
