Workbook

Sheet Version_Control
A1: VERSION CONTROL — VoiceBridge CTI
A3: Version | B3: Date | C3: Author | D3: Change | E3: Status
A4: v001-v004 | B4: 2026-09-05 | C4: Claude for Senthil/KP | D4: Lineage: marketplace master (868 entries) -> portfolio plan (12 products) -> wave-1 (RetainKit/ShiftDesk/EngageOS, v005) -> this product selected for wave-2 | E4: Released
A5: v006 | B5: 2026-09-05 19:46 | C5: Claude for Senthil/KP | D5: Full product workbook for VoiceBridge CTI on Salesforce AppExchange: spec, screen inventory, 100+ story backlog, live sprint board, 18-month financial model (editable assumptions), GTM execution tasks, platform launch checklist, metric targets, risk register | E5: Released
A6: v007 | D6: PLANNED: post-S0 re-baseline after discovery interviews; verified platform terms; wireframe links added to Screens sheet | E6: Planned

Sheet ReadMe_Scope
A1: VoiceBridge CTI — Omnichannel CTI: click-to-dial, call logging, WhatsApp/SMS threads native in Salesforce
A3: PLATFORM: Salesforce AppExchange | CATEGORY: Sales Engagement / Telephony
A4: PROBLEM: Mid-market telephony connectors are either enterprise-priced (NICE/Genesys) or shallow loggers
A5: DIFFERENTIATION: Deep Flow/Einstein integration, transparent per-seat pricing, India+global carrier coverage
A6: ICP: B2B sales orgs 50-500 seats on Sales/Service Cloud, existing telephony spend, RevOps function present
A8: HOW TO USE: Full_Backlog is the single source of truth (edit Status column during execution). Sprint_Board recalculates points per sprint automatically. Financial_Model assumptions (yellow) are editable — the 18-month build recalculates. Launch_Checklist is the platform-specific gate before submission. All costs/timelines are market-standard estimates; verify platform terms (fees/review rules) during S0.
A10: STACK ASSUMPTION (market standard): TypeScript/Node or platform-mandated runtime, React frontends, Postgres, hosted on AWS/GCP/platform FaaS as required, GitHub Actions CI, PostHog + Sentry telemetry, Intercom-class support.

Sheet Product_Spec
A1: PRODUCT SPEC
A3: Module (feature) | B3: Scope in MVP | C3: Out of scope (v1) | D3: Non-functional requirements
A4: Click-to-dial + softphone | B4: Click-to-dial + softphone: end-to-end happy path + edge cases + permissions | C4: Advanced automation, AI beyond listed, multi-language beyond launch set | D4: p95 <500ms API / <2s UI loads
A5: Auto call/WhatsApp logging | B5: Auto call/WhatsApp logging: end-to-end happy path + edge cases + permissions | C5: Advanced automation, AI beyond listed, multi-language beyond launch set | D5: 99.5% monthly uptime
A6: Cadence/sequence lite | B6: Cadence/sequence lite: end-to-end happy path + edge cases + permissions | C6: Advanced automation, AI beyond listed, multi-language beyond launch set | D6: WCAG AA
A7: Coaching analytics | B7: Coaching analytics: end-to-end happy path + edge cases + permissions | C7: Advanced automation, AI beyond listed, multi-language beyond launch set | D7: SOC2-track controls
A8: Flow actions pack | B8: Flow actions pack: end-to-end happy path + edge cases + permissions | C8: Advanced automation, AI beyond listed, multi-language beyond launch set | D8: Rate-limit safe (backoff+queue)
A10: Persona | B10: Jobs-to-be-done
A11: RevOps lead | B11: Evaluates on admin effort, Flow compatibility, reporting
A12: Sales leader (VP) | B12: Buys on rep productivity metrics; needs dashboards
A13: Salesforce admin | B13: Gatekeeper; security review status and permission sets decide the deal

Sheet Screens_Wireframes
A1: SCREEN INVENTORY (attach Figma links in col E during S0)
A3: # | B3: Screen | C3: Purpose | D3: Key elements | E3: Wireframe link
A4: 1 | B4: Onboarding / first-run | C4: Reach aha in <1 day | D4: Checklist, sample data toggle, connect steps
A5: 2 | B5: Home dashboard | C5: Daily habit surface | D5: KPI cards, activity feed, alerts
A6: 3 | B6: Click-to-dial + softphone workspace | C6: Core value surface | D6: List+detail, bulk actions, status chips
A7: 4 | B7: Auto call/WhatsApp logging builder | C7: Configure second pillar | D7: Rule builder, preview, test mode
A8: 5 | B8: Cadence/sequence lite view | C8: Differentiator surface | D8: Timeline/visual, export
A9: 6 | B9: Settings & team | C9: Roles, notifications, data | D9: Role matrix, API keys, danger zone
A10: 7 | B10: Billing | C10: Plan/trial/invoices | D10: Plan cards, usage meter, invoices
A11: 8 | B11: Analytics | C11: Prove ROI | D11: Funnel, cohort, export
A12: 9 | B12: Help & support | C12: Deflect + assist | D12: Search, chat, status

Sheet Full_Backlog
A1: FULL BACKLOG
A3: ID | B3: Epic | C3: Story | D3: Points | E3: Priority | F3: Sprint | G3: Status
A4: ST-001 | B4: F1 | C4: As a RevOps lead, I can set up Click-to-dial + softphone with sensible defaults in one screen | D4: 5 | E4: P0 | F4: S2 | G4: Backlog
A5: ST-002 | B5: F1 | C5: As a RevOps lead, the Click-to-dial + softphone happy path completes without documentation | D5: 8 | E5: P0 | F5: S2 | G5: Backlog
A6: ST-003 | B6: F1 | C6: As a Sales leader, I can customise Click-to-dial + softphone rules/conditions for my workflow | D6: 5 | E6: P1 | F6: S2 | G6: Backlog
A7: ST-004 | B7: F1 | C7: As a user, Click-to-dial + softphone shows clear errors and retry paths on platform API failures | D7: 3 | E7: P0 | F7: S2 | G7: Backlog
A8: ST-005 | B8: F1 | C8: As a Salesforce admin, Click-to-dial + softphone works on the Lightning utility-bar softphone + LWC surface end-to-end | D8: 5 | E8: P0 | F8: S3 | G8: Backlog
A9: ST-006 | B9: F1 | C9: As a Sales leader, I can see Click-to-dial + softphone performance metrics and trends | D9: 3 | E9: P1 | F9: S3 | G9: Backlog
A10: ST-007 | B10: F1 | C10: As a user, Click-to-dial + softphone respects role permissions and audit logging | D10: 3 | E10: P1 | F10: S3 | G10: Backlog
A11: ST-008 | B11: F1 | C11: As a RevOps lead, I can pause/disable Click-to-dial + softphone without data loss | D11: 2 | E11: P2 | F11: S3 | G11: Backlog
A12: ST-009 | B12: F1 | C12: As a Sales leader, I can import/migrate existing data into Click-to-dial + softphone (CSV + competitor importer) | D12: 5 | E12: P1 | F12: S3 | G12: Backlog
A13: ST-010 | B13: F1 | C13: As a user, I get notifications (in-app + email) for key Click-to-dial + softphone events with per-type mute | D13: 3 | E13: P2 | F13: S3 | G13: Backlog
A14: ST-011 | B14: F2 | C14: As a RevOps lead, I can set up Auto call/WhatsApp logging with sensible defaults in one screen | D14: 5 | E14: P0 | F14: S3 | G14: Backlog
A15: ST-012 | B15: F2 | C15: As a RevOps lead, the Auto call/WhatsApp logging happy path completes without documentation | D15: 8 | E15: P0 | F15: S3 | G15: Backlog
... A103: ST-100 | B103: EL | C103: First 10 design-partner reviews scheduled | D103: 2 | E103: P1 | F103: S11 | G103: Backlog
A105: Total stories: 100. Epics: F1-F5 = product features; E1 install, E5 billing, E6 compliance, E7 telemetry, E8 onboarding/docs/support, EQ quality. Edit Status (Backlog/In progress/Done) during execution.

Sheet Sprint_Board
A1: SPRINT BOARD — live counts from Full_Backlog
A3: Sprint | B3: Focus | C3: Stories | D3: Points | E3: Done | F3: Exit criteria
A4: S0 | B4: Discovery & Design (2 wks) | C4: =COUNTIF(Full_Backlog!F4:F103,"S0") -> 0 | D4: =SUMIF(Full_Backlog!F4:F103,"S0",Full_Backlog!D4:D103) -> 0 | E4: =COUNTIFS(Full_Backlog!F4:F103,"S0",Full_Backlog!G4:G103,"Done") -> 0 | F4: PRD signed off; prototype tested with 5 target users
A5: S1 | B5: Foundation (2 wks) | C5: =COUNTIF(Full_Backlog!F4:F103,"S1") -> 4 | D5: =SUMIF(Full_Backlog!F4:F103,"S1",Full_Backlog!D4:D103) -> 13 | E5: =COUNTIFS(Full_Backlog!F4:F103,"S1",Full_Backlog!G4:G103,"Done") -> 0 | F5: App installs cleanly in dev store/org; telemetry firing
A6: S2 | B6: Core feature Click-to-dial + softphone - part 1 | C6: =COUNTIF(Full_Backlog!F4:F103,"S2") -> 6 | D6: =SUMIF(Full_Backlog!F4:F103,"S2",Full_Backlog!D4:D103) -> 29 | E6: =COUNTIFS(Full_Backlog!F4:F103,"S2",Full_Backlog!G4:G103,"Done") -> 0 | F6: Click-to-dial + softphone happy path demoable
A7: S3 | B7: Core feature Click-to-dial + softphone - part 2 + Auto call/WhatsApp logging start | C7: =COUNTIF(Full_Backlog!F4:F103,"S3") -> 11 | D7: =SUMIF(Full_Backlog!F4:F103,"S3",Full_Backlog!D4:D103) -> 47 | E7: =COUNTIFS(Full_Backlog!F4:F103,"S3",Full_Backlog!G4:G103,"Done") -> 0 | F7: Click-to-dial + softphone complete with tests; Auto call/WhatsApp logging skeleton
A8: S4 | B8: Core feature Auto call/WhatsApp logging | C8: =COUNTIF(Full_Backlog!F4:F103,"S4") -> 9 | D8: =SUMIF(Full_Backlog!F4:F103,"S4",Full_Backlog!D4:D103) -> 34 | E8: =COUNTIFS(Full_Backlog!F4:F103,"S4",Full_Backlog!G4:G103,"Done") -> 0 | F8: MVP loop usable end-to-end internally
A9: S5 | B9: Feature Cadence/sequence lite + alpha hardening | C9: =COUNTIF(Full_Backlog!F4:F103,"S5") -> 12 | D9: =SUMIF(Full_Backlog!F4:F103,"S5",Full_Backlog!D4:D103) -> 50 | E9: =COUNTIFS(Full_Backlog!F4:F103,"S5",Full_Backlog!G4:G103,"Done") -> 0 | F9: Internal alpha: team dogfoods daily
A10: S6 | B10: Billing + Coaching analytics | C10: =COUNTIF(Full_Backlog!F4:F103,"S6") -> 13 | D10: =SUMIF(Full_Backlog!F4:F103,"S6",Full_Backlog!D4:D103) -> 60 | E10: =COUNTIFS(Full_Backlog!F4:F103,"S6",Full_Backlog!G4:G103,"Done") -> 0 | F10: Can charge a test customer; upgrade/downgrade paths work
A11: S7 | B11: Private beta (design partners) | C11: =COUNTIF(Full_Backlog!F4:F103,"S7") -> 5 | D11: =SUMIF(Full_Backlog!F4:F103,"S7",Full_Backlog!D4:D103) -> 15 | E11: =COUNTIFS(Full_Backlog!F4:F103,"S7",Full_Backlog!G4:G103,"Done") -> 0 | F11: 3+ partners active weekly; NPS pulse >30
A12: S8 | B12: Beta iteration + Flow actions pack | C12: =COUNTIF(Full_Backlog!F4:F103,"S8") -> 22 | D12: =SUMIF(Full_Backlog!F4:F103,"S8",Full_Backlog!D4:D103) -> 87 | E12: =COUNTIFS(Full_Backlog!F4:F103,"S8",Full_Backlog!G4:G103,"Done") -> 0 | F12: Retention of beta cohort week-over-week >60%
A13: S9 | B13: Marketplace review prep | C13: =COUNTIF(Full_Backlog!F4:F103,"S9") -> 7 | D13: =SUMIF(Full_Backlog!F4:F103,"S9",Full_Backlog!D4:D103) -> 30 | E13: =COUNTIFS(Full_Backlog!F4:F103,"S9",Full_Backlog!G4:G103,"Done") -> 0 | F13: Review submission accepted into queue
A14: S10 | B14: Review remediation + docs | C14: =COUNTIF(Full_Backlog!F4:F103,"S10") -> 7 | D14: =SUMIF(Full_Backlog!F4:F103,"S10",Full_Backlog!D4:D103) -> 24 | E14: =COUNTIFS(Full_Backlog!F4:F103,"S10",Full_Backlog!G4:G103,"Done") -> 0 | F14: Marketplace approval obtained (or final remediation cycle)
A15: S11 | B15: Launch | C15: =COUNTIF(Full_Backlog!F4:F103,"S11") -> 3 | D15: =SUMIF(Full_Backlog!F4:F103,"S11",Full_Backlog!D4:D103) -> 8 | E15: =COUNTIFS(Full_Backlog!F4:F103,"S11",Full_Backlog!G4:G103,"Done") -> 0 | F15: First 10 installs; first 3 reviews; activation >40%
A16: S12 | B16: Iterate & scale decision | C16: =COUNTIF(Full_Backlog!F4:F103,"S12") -> 1 | D16: =SUMIF(Full_Backlog!F4:F103,"S12",Full_Backlog!D4:D103) -> 2 | E16: =COUNTIFS(Full_Backlog!F4:F103,"S12",Full_Backlog!G4:G103,"Done") -> 0 | F16: Growth model doc with CAC/LTV first estimates
B17: TOTAL | C17: =SUM(C4:C16) -> 100 | D17: =SUM(D4:D16) -> 399
B18: Velocity check: points/sprint S2-S8 should sit within 30-45 for a 4-6 person team; rebalance Sprint column in backlog if a sprint exceeds capacity.

Sheet Financial_Model
A1: 18-MONTH FINANCIAL MODEL — Salesforce: enterprise pilot-led (edit yellow assumptions)
A3: Assumption | B3: Value
A4: Qualified pilots/mo (month 1) | B4: 4
A5: Monthly growth of that | B5: 0.1
A6: Pilot->paid % | B6: 0.3
A7: ARPU $/mo | B7: 600
A8: Monthly churn | B8: 0.012
A9: Marketplace fee | B9: 0.15
A10: Team cost month 1 (India-lean $) | B10: 40000
A11: Cost growth/mo | B11: 0.03
A12: Fee note: 15% PNR to Salesforce on net revenue
A14: Line | B14: M1 | C14: M2 | D14: M3 | E14: M4 | F14: M5 | G14: M6 | H14: M7 | I14: M8 | J14: M9 | K14: M10 | L14: M11 | M14: M12 | N14: M13 | O14: M14 | P14: M15 | Q14: M16 | R14: M17 | S14: M18
A15: Leads/installs | B15: =$B$4 -> 4 | C15: =B15*(1+$B$5) -> 4.4 | D15: =C15*(1+$B$5) -> 4.84 | E15: =D15*(1+$B$5) -> 5.324 | F15: =E15*(1+$B$5) -> 5.8564 | G15: =F15*(1+$B$5) -> 6.44204 | H15: =G15*(1+$B$5) -> 7.086244 | I15: =H15*(1+$B$5) -> 7.7948684 | J15: =I15*(1+$B$5) -> 8.5743552 | ... S15: =R15*(1+$B$5) -> 20.217881
A16: New paying | B16: =ROUND(B15*$B$6,1) -> 1.2 | C16: =ROUND(C15*$B$6,1) -> 1.3 | D16: =ROUND(D15*$B$6,1) -> 1.5 | E16: =ROUND(E15*$B$6,1) -> 1.6 | F16: =ROUND(F15*$B$6,1) -> 1.8 | G16: =ROUND(G15*$B$6,1) -> 1.9 | H16: =ROUND(H15*$B$6,1) -> 2.1 | I16: =ROUND(I15*$B$6,1) -> 2.3 | ... S16: =ROUND(S15*$B$6,1) -> 6.1
A17: Paying accounts | B17: =B16 -> 1.2 | C17: =ROUND(B17*(1-$B$8)+C16,1) -> 2.5 | D17: =ROUND(C17*(1-$B$8)+D16,1) -> 4 | E17: =ROUND(D17*(1-$B$8)+E16,1) -> 5.6 | F17: =ROUND(E17*(1-$B$8)+F16,1) -> 7.3 | G17: =ROUND(F17*(1-$B$8)+G16,1) -> 9.1 | H17: =ROUND(G17*(1-$B$8)+H16,1) -> 11.1 | I17: =ROUND(H17*(1-$B$8)+I16,1) -> 13.3 | J17: =ROUND(I17*(1-$B$8)+J16,1) -> 15.7 | ... S17: =ROUND(R17*(1-$B$8)+S16,1) -> 51
A18: MRR (net of fee) | B18: =ROUND(B17*$B$7*(1-$B$9),0) -> 612 | C18: =ROUND(C17*$B$7*(1-$B$9),0) -> 1275 | D18: =ROUND(D17*$B$7*(1-$B$9),0) -> 2040 | E18: =ROUND(E17*$B$7*(1-$B$9),0) -> 2856 | F18: =ROUND(F17*$B$7*(1-$B$9),0) -> 3723 | G18: =ROUND(G17*$B$7*(1-$B$9),0) -> 4641 | H18: =ROUND(H17*$B$7*(1-$B$9),0) -> 5661 | I18: =ROUND(I17*$B$7*(1-$B$9),0) -> 6783 | ... S18: =ROUND(S17*$B$7*(1-$B$9),0) -> 26010
A19: Team cost | B19: =$B$10 -> 40000 | C19: =ROUND(B19*(1+$B$11),0) -> 41200 | D19: =ROUND(C19*(1+$B$11),0) -> 42436 | E19: =ROUND(D19*(1+$B$11),0) -> 43709 | F19: =ROUND(E19*(1+$B$11),0) -> 45020 | G19: =ROUND(F19*(1+$B$11),0) -> 46371 | H19: =ROUND(G19*(1+$B$11),0) -> 47762 | I19: =ROUND(H19*(1+$B$11),0) -> 49195 | J19: =ROUND(I19*(1+$B$11),0) -> 50671 | ... S19: =ROUND(R19*(1+$B$11),0) -> 66115
A20: Net cash/mo | B20: =B18-B19 -> -39388 | C20: =C18-C19 -> -39925 | D20: =D18-D19 -> -40396 | E20: =E18-E19 -> -40853 | F20: =F18-F19 -> -41297 | G20: =G18-G19 -> -41730 | H20: =H18-H19 -> -42101 | I20: =I18-I19 -> -42412 | ... S20: =S18-S19 -> -40105
A21: Cumulative | B21: =B20 -> -39388 | C21: =B21+C20 -> -79313 | D21: =C21+D20 -> -119709 | E21: =D21+E20 -> -160562 | F21: =E21+F20 -> -201859 | G21: =F21+G20 -> -243589 | H21: =G21+H20 -> -285690 | I21: =H21+I20 -> -328102 | J21: =I21+J20 -> -370766 | ... S21: =R21+S20 -> -750126
A23: Reading: churn applies before adds; MRR nets the marketplace fee; costs use India-lean base from Team_Roles_Budget (v004). Breakeven = first month Net cash ≥ 0. This is a planning model, not a forecast — replace assumptions with S7-S8 beta actuals.

Sheet GTM_Execution
A1: GTM EXECUTION TASKS
A3: Phase | B3: Task | C3: Owner (role) | D3: Target sprint
A4: Pre-launch | B4: Positioning doc + message house (problem/promise/proof) | C4: Founder | D4: S7
A5: Pre-launch | B5: Listing SEO: keyword study in marketplace search + title/intro drafts | C5: Growth | D5: S8
A6: Pre-launch | B6: 10 design-partner mini case snippets with metric proof | C6: Founder | D6: S8
A7: Pre-launch | B7: 5 comparison/alternative pages drafted | C7: Growth | D7: S9
A8: Pre-launch | B8: Screenshots (5) + 2-min demo video produced | C8: Design | D8: S9
A9: Launch | B9: Listing live + launch post + video published | C9: Growth | D9: S11
A10: Launch | B10: Founder outreach: 100 named ICP accounts, 3-touch sequence | C10: Founder | D10: S11
A11: Launch | B11: Community value-posts (3 relevant communities) | C11: Founder | D11: S11
A12: Launch | B12: Review-generation program on (in-app ask post-aha) | C12: Eng | D12: S11
A13: Post-launch | B13: Weekly SEO/how-to content cadence starts | C13: Growth | D13: S12
A14: Post-launch | B14: Marketplace paid placement pilot (where offered) | C14: Growth | D14: S12
... A16: Post-launch | B16: G2/Capterra profiles + first 10 reviews | C16: Growth | D16: S12+

Sheet Launch_Checklist
A1: PLATFORM LAUNCH CHECKLIST — Salesforce AppExchange
A3: # | B3: Item | C3: Status
A4: 1 | B4: ISV Partner Program application + agreement executed | C4: Open
A5: 2 | B5: Developer/scratch orgs + managed package namespace registered | C5: Open
A6: 3 | B6: AppExchange Security Review: pen-test evidence, code scan clean, Trust questionnaire | C6: Open
A7: 4 | B7: Open CTI / Service Cloud Voice compatibility decision documented | C7: Open
A8: 5 | B8: Permission sets + profiles install experience tested in 3 org shapes | C8: Open
A9: 6 | B9: Data residency: Hyperforce region support statement | C9: Open
A10: 7 | B10: Managed package upgrade path tested (push upgrades) | C10: Open
A11: 8 | B11: AppExchange listing: demo org, video, security tab complete | C11: Open
A12: 9 | B12: Pricing: per-seat tiers + annual; PNR reporting process set up | C12: Open
A13: 10 | B13: 2 lighthouse customers referenced (logo permission) before listing | C13: Open

Sheet Metrics_Targets
A1: METRIC TARGETS (first 12 months post-launch)
A3: Metric | B3: M1 | C3: M3 | D3: M6 | E3: M12 | F3: Notes
A4: Installs/signups cumulative | B4: varies | C4: 3x M1 | D4: 8x M1 | E4: 20x M1 | F4: Drive via listing SEO + outbound
A5: Activation % (24h) | B5: 30% | C5: 40% | D5: 45% | E5: 50% | F5: Onboarding iterations S12+
A6: Trial→paid % | B6: baseline | C6: +2pts | D6: +4pts | E6: +6pts | F6: Pricing test at S12
A7: Rating | B7: 4.5+ | C7: 4.6+ | D7: 4.7+ | E7: 4.7+ | F7: Review program + support speed
A8: MRR | B8: first $ | C8: 3x | D8: 8x | E8: 20x | F8: Model sheet has the math
A9: Logo churn/mo | B9: <5% | C9: <4% | D9: <3% | E9: <3% | F9: Health-score saves

Sheet Risk_Register
A1: PRODUCT RISK REGISTER
A3: Risk | B3: Impact | C3: Likelihood | D3: Mitigation
A4: Security review cycles exceed 2 iterations (3+ months delay) | B4: High | C4: High | D4: Specialist review consultant pre-submission; scopes austerity
A5: Service Cloud Voice bundling squeezes third-party CTI | B5: High | C5: Medium | D5: Mid-market focus + WhatsApp/SMS omnichannel angle SCV lacks
A6: Enterprise sales cycle vs cash runway | B6: High | C6: Medium | D6: Paid pilots; annual prepay; partner-sourced deals
