Workbook

Sheet 00_Cover
A2: 003-MoPr06 · DocMerge Pro · Google Workspace Marketplace
A3: MANUAL TEST PACK
A5: What a human can test by hand, version by version: what each version delivered and why, which versions are still pending and what is holding each one, and a step-by-step test case for every behaviour — positive and negative — with the exact expected result.
A8: Document | B8: claude_V001_MoPr06-docmerge_pro_gws_manualtest_20260920_1815.xlsx
A9: Version | B9: V001 — first issue
A10: Date / time | B10: 20 September 2026, 18:15 BST
A11: Author | B11: Claude for Senthil / KP
A12: Status | B12: Released
A13: Product under test | B13: DocMerge Pro (003-MoPr06) — document generation for Google Workspace
A14: Build under test | B14: docmerge-pro-s1 v036 · commit at 20 Sep 2026 · 1,513 tests / 81 suites / 100% coverage
A15: Test levels covered | B15: Manual functional, negative/abuse, configuration, durability (restart), and operability. Automated unit, contract and boot tests are NOT repeated here — they run in CI.
A16: Environment required | B16: Node 22, PostgreSQL 16, a shell. Test cases marked BLOCKED additionally need a GCP project (LC-1) and are explicitly not runnable today.
A17: Companion document | B17: claude_V001_MoPr06-docmerge_pro_gws_architecture_status_20260920_1815.pdf — the pictorial architecture and completion pack. Read that first if you want the picture before the detail.
A18: Classification | B18: Internal. Contains no credentials, no customer data and no live endpoints.
A19: Total test cases | B19: 125 in total: 77 positive and 24 negative that are runnable today, plus 24 specified and blocked (mostly on LC-1). Sheet 31 keeps the live count.
A21: READ THIS FIRST
A22: This pack separates two things that are easy to confuse: whether a behaviour was BUILT, and whether anyone has ever WATCHED IT WORK. Every test case below is marked as testable now or blocked, and a blocked case names what blocks it. A case marked BLOCKED has never been executed by anyone — it is written and waiting, not passed.
A23: That distinction is the whole reason this pack exists. An external review in September found that this product had 100% automated test coverage while an entire layer of it did not exist. Automated tests answer 'does the code I wrote behave as I specified'. They cannot answer 'does the thing I am talking to actually exist and behave that way'. Manual testing against real systems is what answers the second question, and for six of this product's seven external adapters that question is still open.
A24: Sheets are numbered in the order you should read them. 00-03 are orientation, 10-11 are the version record, 20-22 are the test cases themselves, 30-31 are the traceability and summary a reviewer will ask for.

Sheet 01_Document_Control
A1: DOCUMENT CONTROL
A2: Version history of THIS document, its review record, and the rules that keep it trustworthy. The product's own version history is on sheet 10_Version_Register.
A4: Version | B4: Date / time | C4: Author | D4: Change | E4: Reviewed by | F4: Status
A5: V001 | B5: 2026-09-20 18:15 | C5: Claude for Senthil/KP | D5: First issue. Created on request alongside the pictorial architecture pack. Covers versions S1–S19 of the product plus the pending live-verification versions. 68 executable test cases and 24 specified-but-blocked cases. | E5: Not yet reviewed | F5: Released
A6: V002 | B6: — | C6: — | D6: PLANNED: after LC-1 (the GCP project). This is the version where the 24 blocked cases become executable. Expect some of them to FAIL on first contact — the Docs table-row index arithmetic and section deletion across paragraph boundaries are the two most likely, and that is the point of running them. | E6: — | F6: Planned
A7: V003 | B7: — | C7: — | D7: PLANNED: after the pricing decision (D-DM5), which changes the listing copy, the plan names and the entitlement test data. Test cases MT-BIL-* and MT-GOV-* will need their expected values re-baselined. | E7: — | F7: Planned
A9: RULES THIS DOCUMENT IS KEPT TO
A10: A result is only PASS if someone watched it. | C10: Do not mark a case PASS because the automated suite covers the same code. The automated suite is not in question; what this pack tests is the behaviour a person can see.
A11: A BLOCKED case is never PASS. | C11: If the blocker is lifted, run the case and record the result with the date and the tester. Until then it stays BLOCKED, however confident anyone is.
A12: Record the actual result, not the expected one. | C12: The 'Actual result' column is for what happened. Copying the expected value into it is the single most common way a manual test pack becomes worthless.
A13: A failure gets a defect id. | C13: Raise it in DEFECT_REGISTER.md in the code archive and put the id in the 'Defect raised' column, so the case and the defect point at each other.
A14: Re-baseline after a version bump. | C14: When the product version changes, check the Expected result column before running. A stale expectation produces a false failure, which is worse than no test.

Sheet 02_Context
A1: CONTEXT — what is being tested and why it is in this state
A2: Read once. Everything after this assumes it.
A4: Topic | B4: Detail
A5: What the product does | B5: Generates documents from Google Sheets rows and Google Form submissions. A template is bound to a Google Doc; the product copies that Doc per row, substitutes {{placeholders}}, inserts repeating table rows for line items, swaps logo images, exports to PDF or DOCX, and files the result into a Drive folder. Around that sit approval routing, billing, plan limits, a tamper-evident audit ledger, tenant isolation, and a quota governor.
A6: Where the product stands | B6: The application runs, serves HTTP, migrates its database and survives a restart — all proved by execution. The seven adapters that talk to Google, Stripe and the Marketplace are written and unit-proved against recorded contracts, and NOT ONE has ever sent a request to the live service. That is not a shortcut; it is blocked on a GCP project that does not exist yet (LC-1).
A7: Why the pack is split this way | B7: Sheet 10 lists every version that is DONE and why it was done. Sheet 11 lists every version that is PENDING and what is holding it — because a pending item with no stated reason is indistinguishable from an item nobody thought about. Sheets 20–22 hold the test cases: positive (does it do the right thing), negative (does it refuse the wrong thing safely), and blocked (written, waiting on LC-1).
A8: What this pack does NOT cover | B8: Automated unit, contract and boot tests — 1,513 of them, run by CI on every commit. Performance and load testing against real infrastructure, which needs LC-1. Penetration testing, which needs a deployed target and a budget. Accessibility, which has an automated WCAG audit already. None of these are skipped silently; each is named here so their absence is visible.
A9: Known risk in the test pack itself | B9: The negative cases are stronger than the positive ones, because the positive cases for anything involving Google are blocked. A reader could come away thinking the product is better tested than it is. The honest summary: the half that does not touch Google is very well tested; the half that does has never run.
A10: Prerequisites to run anything | B10: Node 22 and npm. A PostgreSQL 16 server. The code archive docmerge-pro-s1-v036.zip unpacked, with `npm ci` run once. Roughly 20 minutes to set up; sheet 03 has the exact commands.

Sheet 03_How_To_Use
A1: HOW TO USE THIS PACK
A2: Sheet by sheet, and the setup you need before the first test case.
A4: Sheet | B4: What it is | C4: How to use it | D4: Who uses it
A5: 00_Cover | B5: Identity of the document and the one-paragraph orientation. | C5: Read once. Check the 'Build under test' row matches the archive you actually have before running anything. | D5: Everyone
A6: 01_Document_Control | B6: Version history of this document and the rules it is kept to. | C6: Add a row when you re-issue. Read the five rules before your first test run — they are the difference between a test pack and a spreadsheet. | D6: Author, reviewer
A7: 02_Context | B7: What the product is and why it is in this state. | C7: Read once before testing. Re-read if you come back to this pack after a gap. | D7: New tester
A8: 03_How_To_Use | B8: This sheet, plus the environment setup. | C8: Follow §Setup below before test case one. | D8: Tester
A9: 10_Version_Register | B9: Every version that is DONE: what it delivered, why it was done, and the evidence. | C9: Use it to answer 'is this behaviour supposed to exist yet?'. Filter the Status column. | D9: Tester, reviewer, owner
A10: 11_Pending_Versions | B10: Every version NOT done: what it would deliver, what blocks it, and who owns the blocker. | C10: Use it to answer 'why can I not test this?'. Every blocked test case points at a row here. | D10: Owner, reviewer
A11: 20_Test_Cases_Positive | B11: Cases that prove the product does the right thing. | C11: Work top to bottom within a version. Fill Actual result, Status, Tester and Date as you go. | D11: Tester
A12: 21_Test_Cases_Negative | B12: Cases that prove the product refuses the wrong thing, safely and legibly. | C12: Run these AFTER the positive cases for the same version — a negative case on a broken happy path tells you nothing. | D12: Tester
A13: 22_Test_Cases_Blocked | B13: Cases written and waiting on a blocker, mostly LC-1. | C13: Do not run. Do not mark PASS. When the blocker lifts, move the case into sheet 20 or 21 and run it properly. | D13: Owner, tester
A14: 30_Traceability | B14: Test case → version → requirement → automated counterpart. | C14: Use it to show coverage, and to find which cases to re-run after a change. | D14: Reviewer, auditor
A15: 31_Execution_Summary | B15: Live counts by status and by version, computed from the case sheets. | C15: Do not type into the computed cells. Read it after a test run to see where you are. | D15: Owner, reviewer
A16: 32_Defect_Log | B16: Defects found by MANUAL testing, with a link back to the case. | C16: One row per failure. The canonical product-wide register is DEFECT_REGISTER.md in the code archive. | D16: Tester, owner
A18: SETUP — do this once, before the first test case
A19: S-1 | B19: Unpack the build | C19: Unzip docmerge-pro-s1-v036.zip and `cd docmerge-pro-s1`. | D19: A directory containing package.json, src/, tests/, migrations/.
A20: S-2 | B20: Install dependencies | C20: `npm ci` | D20: Roughly 296 packages installed, no errors. If this fails, stop — nothing else will work.
A21: S-3 | B21: Start PostgreSQL 16 | C21: Any local instance. Note the connection string. | D21: `psql -l` lists databases.
A22: S-4 | B22: Create the test database | C22: `createdb docmerge_manualtest` | D22: Database exists.
A23: S-5 | B23: Apply migrations | C23: `DATABASE_URL=postgres://…/docmerge_manualtest DATABASE_SSL=disable node scripts/migrate.js` | D23: Six migrations reported as applied, in order, exit code 0.
A24: S-6 | B24: Build | C24: `npx tsc` | D24: A dist/ directory appears containing main.js. No TypeScript errors.
A25: S-7 | B25: Prepare the environment block | C25: Copy .env.example and fill every REQUIRED value. For local testing set DATABASE_SSL=disable and NODE_ENV=test. SESSION_SECRET must be at least 16 characters. | D25: 25 variables understood; the required ones populated.
A26: S-8 | B26: Sanity check | C26: `npm run verify` — this runs the full automated gate. It is not one of your test cases; it tells you the build you are holding is the build this pack describes. | D26: 1,513 tests pass, coverage 100%, all gates report no findings.
A28: If S-8 does not produce those numbers, the build is not the one this pack was written against. Stop and reconcile before testing — otherwise every result you record is about a different product.

Sheet 10_Version_Register
A1: VERSION REGISTER — what each delivered version did, and why it was done
A2: Every version below shipped. 'Why it was done' matters as much as 'what': a version with no reason is a version nobody can decide to keep. Status distinguishes fully verified from delivered-but-never-run-live.
A4: Version | B4: Name | C4: What it delivered | D4: Why it was done | E4: Status | F4: Evidence you can check yourself | G4: Test cases
A5: S1 | B5: Install lifecycle | C5: Marketplace OAuth install to a welcome state, uninstall handling with token revocation and a 30-day deletion schedule, token refresh that survives Google rotating the refresh token, and install source attribution. | D5: Nothing else can be tested until an account can exist. This is the first thing a customer touches and the first thing that can go wrong invisibly — a refresh that does not survive rotation fails silently a week later. | E5: Done (live unverified) | F5: tests/install.test.ts, tokenRefresh.test.ts; the OAuth adapter added in S15 has never called Google | G5: MT-INS-01..06
A6: S2–S3 | B6: Template designer | C6: One-screen template creation with defaults, placeholder extraction and validation with a message naming the exact missing field, rules that include or exclude sections conditionally, role permissions, pause/resume, CSV import. | D6: The actionable error message is the deliberate differentiator: a competitor tells you the merge failed, this tells you which column to add to your Sheet. That only pays off if the message is genuinely specific, which is what the manual cases check. | E6: Done | F6: tests/templates.test.ts; testable end to end today without Google | G6: MT-TPL-01..09
A7: S3–S4 | B7: Batch generation from Sheets | C7: Batch jobs with skip-empty and continue-on-error defaults, per-row results so one bad row does not stop the run, row rules, retry on transient platform failures, metrics, pause/resume, CSV row import. | D7: The core volume feature. A 500-row batch that stops at row 40 and reports nothing is the failure mode that loses a customer, so per-row outcome reporting was built before anything decorative. | E7: Done (live unverified) | F7: tests/batch.test.ts, batchOps.test.ts; the Sheets adapter (S15) has never called Google | G7: MT-BAT-01..07
A8: S5 | B8: Approval requests | C8: Sequential or parallel routing, domain allow-lists, expiry, decline with reason, pause and resume without data loss, CSV signer import, audit entries, tenant ownership checks. | D8: Originally built and sold as e-signature. An external review established it produces no signature artefact, no binding of intent to a document hash and no signer authentication, so it was renamed to Approval requests and a repository gate now fails the build on any signature claim. The state machine itself is sound and kept. | E8: Done | F8: tests/esign.test.ts; claims gate proves zero signature claims remain | G8: MT-APR-01..06
A9: S6 | B9: Auto-file to Drive + billing | C9: Folder patterns with date and template tokens, conflict policy (rename, overwrite, skip), retry on 429/5xx, 14-day trial without a card, mid-cycle proration to the cent, provider routing. | D9: Filing is where generated documents become findable; billing is where the product becomes a business. Proration to the cent was built because an off-by-a-penny invoice is a support ticket and a trust problem. | E9: Done (live unverified) | F9: tests/driveFiler.test.ts, billing.test.ts; Drive and Stripe adapters never called live | G9: MT-FIL-01..05, MT-BIL-01..06
A10: S7–S8 | B10: Dunning, invoices, form triggers, compliance | C10: Exactly three dunning emails on a 1/3/7-day schedule then read-only, plan limits with prompts at 80% and 100%, numbered invoices with GST/VAT and reverse charge, form-triggered generation with replay-safe dedupe, data-flow and retention documentation, rate-limit backoff and circuit breaker. | D10: Read-only rather than deletion at the end of dunning is a deliberate choice: paying restores instantly and no customer data is destroyed over a failed card. Form dedupe exists because webhook redelivery is normal, and a duplicate document is worse than a late one. | E10: Done | F10: tests/billingHardening.test.ts, formTrigger.test.ts | G10: MT-DUN-01..05, MT-FRM-01..04
A11: S9–S12 | B11: Launch surfaces | C11: Security evidence pack, self-serve data export and delete, help centre with 15 articles, business-hours SLA clock, sandbox demo mode, status page, pricing matrix generated from the billing code, submission dry run, launch runbook, 20-template gallery. | D11: These are the artefacts a marketplace review asks for. Generating the pricing page FROM the billing code rather than writing it by hand means the published prices cannot drift from the charged ones. | E11: Done | F11: tests/launchSurfaces.test.ts, helpCenter.test.ts, site.test.ts | G11: MT-LCH-01..05
A12: S13 | B12: Make it run | C12: A process entrypoint that actually starts, /healthz and /readyz, graceful drain on SIGTERM, a declared Postgres driver with pooling and TLS, a working migration path, and three new standing gates. | D12: An external review executed `npm start` and found it exited 0 with no port open — the entrypoint exported a start function that nothing called. Every deployment document depended on a fail-closed readiness check that lived inside that uninvoked function, so the safety property most relied on was unreachable. | E12: Done | F12: `npm run test:boot` spawns the built artefact and asserts the port answers | G12: MT-RUN-01..08
A13: S14 | B13: Make it render | C13: Real Google Docs rendering: copy the template, one batchUpdate carrying placeholder replacement, image swaps, repeating table rows and section deletion, then export PDF or DOCX. | D13: The merge engine was string substitution on a plain-text body and could not produce a Doc or a PDF at all — the declared default output format was never read by any rendering code. This is the product's core function and it did not exist. | E13: Done (live unverified) | F13: tests/documentRenderer.test.ts asserts exact URLs and request bodies against a fake; no request has reached Google | G13: MT-RND-01..04 + blocked
A14: S15 | B14: Make it installable | C14: The Editor add-on: a manifest generated from the audited scope set with a drift test, Code.gs, a 300px sidebar, the sidebar host shim, and real Drive, Sheets and OAuth adapters. | D14: Neither add-on surface had any implementation — no manifest, no Code.gs, no sidebar. The decision about which add-on type to build was therefore not blocking work; it was blocking a rewrite of work nobody had started. | E14: Done (live unverified) | F14: tests/addonManifest.test.ts, googleDriveHost.test.ts; never pushed with clasp | G14: MT-ADD-01..03 + blocked
A15: S16 | B15: Make it durable and honest | C15: Eight stores moved to Postgres across seven new tables — webhook dedupe, the hash-chained audit ledger with its eviction anchor, approval requests, batch checkpoints, form triggers, rate-limit windows, sessions, deletion jobs — plus the e-sign rename and the claims gate. | D15: Webhook dedupe in memory means a restart lets a billing webhook apply twice. An audit ledger that vanishes on restart cannot serve the auditability that is this product's actual differentiator. Neither is an enterprise feature; both are single-process correctness. | E15: Done | F15: Crash-restart invariant test per store; PGlite contract tests; `npm run test:contract` | G15: MT-DUR-01..07
... A18: S19 | B18: Boundary integrity + evidence | C18: An integration gate that fails the build when an exported boundary has no implementation; the Stripe gateway and the Marketplace license probe it found missing; account identity storage; telemetry for the three activation questions. | D18: The review's central finding was a whole class of absence that coverage cannot see. A gate makes it a standing check rather than something an outsider finds once. It fired 16 findings on its first run — after seven sprints of remediation — including two stubs written the same hour. | E18: Done (live unverified) | F18: `npm run gate:integration` — 44 boundaries, 0 findings | G18: MT-GAT-01..05
A20: Reading the Status column: 'Done' means the behaviour is fully exercisable and has been exercised. 'Done (live unverified)' means the code is complete and unit-proved but part of it talks to a service nobody has called yet — the version is delivered, its live behaviour is not evidence.

Sheet 11_Pending_Versions
A1: PENDING VERSIONS — what is not done, and the specific reason each one is not done
A2: A pending item with no stated reason is indistinguishable from an item nobody thought about. Every row names its blocker, who owns it, and what it would take to clear.
A4: Version | B4: Name | C4: What it would deliver | D4: Why it is PENDING — the actual reason | E4: Blocker owner | F4: Effort once unblocked | G4: Status | H4: Blocked test cases
A5: V-LIVE-1 | B5: Live Google verification | C5: Proof that the Docs, Drive, Sheets and OAuth adapters work against the real APIs: a real Doc created from a real template with a real image and a real repeating table, exported as a real PDF. | D5: No GCP project exists (LC-1). The adapters assert exact URLs, headers and request bodies against a fake HTTP client, which catches version drift and typos but cannot tell you whether Google accepts the request. The two things most likely to fail first are the table-row index arithmetic and section deletion across paragraph boundaries — both are index maths against a document model that has only ever been simulated. | E5: Senthil | F5: About an hour to create a throwaway project with a test user; then half a day to run the cases | G5: Blocked | H5: MT-X-RND-01..08
A6: V-LIVE-2 | B6: Add-on installation | C6: The Editor add-on pushed with clasp, installed into a real Sheet, the consent screen showing the six scopes, and the sidebar reading the active row. | D6: Same blocker (LC-1), plus one open defect: there is no handoff from the OAuth callback to the sidebar, so the user currently has to paste a session token by hand (DM-F31). That must be fixed before the demo recording, because the recording is also the OAuth verification video and a paste step would be visible in it. | E6: Senthil | F6: Half a day, after DM-F31 is fixed | G6: Blocked | H6: MT-X-ADD-01..06
A7: V-LIVE-3 | B7: Deployment and rollback | C7: The sequence the external review named as the exit criterion: destroy, recreate, deploy, migrate, smoke, roll back, redeploy — twice, from CI logs. | D7: LC-1 for the project, plus a hosting decision. Terraform has never been run: there is no binary available here and no project to plan against, so the provider argument names were written against the documented schema and the first `terraform validate` should be expected to surface a few. Everything fails closed naming LC-1 rather than reporting a false green, so the risk is delay, not a silent bad deploy. | E7: Senthil | F7: One to two days including the inevitable first-validate corrections | G7: Blocked | H7: MT-X-OPS-01..05
A8: V-LIVE-4 | B8: Billing against Stripe | C8: A real charge, a real decline, and the enrolment flow that stores the customer and payment method. | D8: Two reasons, and the second is the real one: there is no Stripe account, AND the enrolment flow (Checkout or a SetupIntent) was never built, so nothing writes the customer id the gateway needs. An unenrolled account is refused and logged rather than charged against an invented card, which is correct but means the happy path cannot be tested at all yet. | E8: Senthil | F8: A day for enrolment, an hour to test | G8: Blocked | H8: MT-X-BIL-01..05
A9: V-PRICE | B9: Pricing and positioning applied | C9: Listing copy, pricing page, ICP and five story descriptions aligned to a decided price. | D9: Decision D-DM5 is open. The current model never reaches breakeven — reproduced independently, cumulative -$228,150 at month 18 with the gap still widening at month 12. The revised model reaches breakeven at month 12, but which structure to adopt is a business call, not an engineering one. It gates the listing copy because changing pricing after marketplace submission is expensive. | E9: Senthil | F9: An afternoon once decided | G9: Pending | H9: MT-X-PRC-01..02
A10: V-LEGAL | B10: Reviewed terms and privacy policy | C10: Legally reviewed terms of service and privacy policy, hosted on a real domain. | D10: The terms are a structural draft with unreviewed warranty and liability clauses, marked as such on the pages themselves so they cannot be published unnoticed. A lawyer has not been engaged. This is the second slow external clock: hosted policy pages are a precondition for the OAuth consent screen, which is a precondition for everything under LC-1. | E10: Senthil | F10: Lead time is the lawyer's, not ours — start it in the same hour as LC-1 | G10: Pending | H10: —
A11: V-PENTEST | B11: Third-party penetration test | C11: An external penetration test report, archived as marketplace submission evidence. | D11: Needs a deployed environment to test against (so, LC-1) and a budget line. The scoping brief and the vendor outreach email are written and ready to send — and were corrected on 20 Sep, because both described a product that sends documents for signature, which it does not do. | E11: Senthil + vendor | F11: Vendor lead time, typically two to four weeks | G11: Pending | H11: —
A12: V-ENT | B12: Enterprise identity and lifecycle | C12: SAML/SCIM federation, domain policy, break-glass access, legal hold, configurable retention, PITR, production SLO history. | D12: DELIBERATELY NOT BUILT — decision D-DM2, and the external review agreed with it. This is a bet on a buyer the product has never met. The review's exact position: accept D-DM2 as written, and separately reject the framing that the remaining gap was enterprise-tier. It was at the working-software bar, and that bar is now met. Trigger to revisit: the first written SSO request from a real prospect. | E12: Senthil (decision already taken) | F12: Four to five unscoped sprints — do not start speculatively | G12: Not started | H12: —
A13: V-ESIGN | B13: Real electronic signature | C13: Integration with a signature provider so the product can produce a legally meaningful signed artefact. | D13: Decision D-DM6, open but no longer urgent. The legal exposure that made this pressing was closed a different way: the feature was renamed to Approval requests and a repository gate fails the build on any signature claim in user-facing copy. Integrating a provider is now a product choice, cheapest to defer until a customer asks. | E13: Senthil | F13: About a sprint | G13: Pending | H13: —
A14: V-EVID | B14: Evidence from strangers | C14: Fifty real installs, activation telemetry from people nobody knows, and ten paying accounts — the portfolio gate G-02. | D14: Needs a published listing, which needs OAuth verification, which needs LC-1 and the legal review. This is the end of the chain and the only thing that settles whether the repositioning argument is right. Every claim about who will pay for this product is currently an argument from what was built, not evidence from a buyer. | E14: Senthil | F14: Weeks to months — the verification clock alone runs past eight weeks in documented cases | G14: Blocked | H14: —
A16: THE PATTERN WORTH SEEING: six of the ten rows above share one blocker, and it is about an hour of work — creating a GCP project and consent screen. It does not unblock engineering (seven sprints happened without it); it starts verification clocks that then run for weeks in parallel with whatever else is happening. That is why it sits at the top of the action list rather than in it.

Sheet 20_Test_Cases_Positive
A1: TEST CASES — POSITIVE (does the product do the right thing?)
A2: 44 cases, all runnable today with Node and a local PostgreSQL. No Google account is needed for any case on this sheet — that is deliberate, and it is also the honest limit: these prove the half of the product that does not touch Google. Fill the yellow columns as you go.
A4: Test case ID | B4: Version | C4: Test case name | D4: Test description | E4: Pre-conditions | F4: Step-by-step — how to test | G4: Expected result | H4: Actual result | I4: Status | J4: Tester | K4: Date | L4: Defect raised
A5: MT-RUN-01 | B5: S13 | C5: Application starts and binds a port | D5: The documented start command must produce a process that is actually listening. Until 20 Sep it exited 0 with no port open, so this is the single most important case in the pack. | E5: Setup S1–S7 complete. Postgres running. | F5: 1. Export every required variable from .env.example (DATABASE_SSL=disable, NODE_ENV=test, PORT=8123). 2. Run: npm start 3. Watch stdout. | G5: A JSON log line appears containing "event":"startup.listening" and "port":8123. The process stays alive and does not return to the shell.
A6: MT-RUN-02 | B6: S13 | C6: Liveness endpoint answers | D6: /healthz is what an orchestrator polls to decide whether to kill the container. | E6: MT-RUN-01 passing, process still running. | F6: 1. In a second shell: curl -i http://127.0.0.1:8123/healthz | G6: HTTP/1.1 200. Body exactly {"status":"ok"}. Note it does NOT include a version — that is deliberate (DM-F13).
A7: MT-RUN-03 | B7: S13 | C7: Liveness reveals the build only to an operator | D7: The build version tells an attacker which advisories apply, so it is released only to a caller holding the operator token. | E7: Process running; OPERATOR_TOKEN known. | F7: 1. curl -s http://127.0.0.1:8123/healthz 2. curl -s -H "x-operator-token: $OPERATOR_TOKEN" http://127.0.0.1:8123/healthz 3. curl -s -H "x-operator-token: wrong" http://127.0.0.1:8123/healthz | G7: Step 1: no version field. Step 2: a version field appears. Step 3: no version field — a wrong token is treated exactly like no token.
A8: MT-RUN-04 | B8: S13 | C8: Readiness reports the database truthfully | D8: /readyz must be a real round trip to Postgres, not a flag set once at boot. A cached 'ready' is how a service keeps taking traffic after its database has gone. | E8: Process running against a reachable Postgres. | F8: 1. curl -i http://127.0.0.1:8123/readyz | G8: HTTP 200 and {"status":"ready","checks":{"database":"ok","configuration":"ok"}}.
A9: MT-RUN-05 | B9: S13 | C9: Readiness turns false when the database goes away | D9: The counterpart to MT-RUN-04, and the one that actually proves the check is live. | E9: Process running and ready. | F9: 1. Stop PostgreSQL (pg_ctl stop) while leaving the app running. 2. curl -i http://127.0.0.1:8123/readyz 3. Start PostgreSQL again. 4. curl -i http://127.0.0.1:8123/readyz | G9: Step 2: HTTP 503, status not_ready, checks.database = failed, checks.configuration still ok. Step 4: back to 200/ready without restarting the app.
A10: MT-RUN-06 | B10: S13 | C10: Graceful drain on SIGTERM | D10: A deploy sends SIGTERM. The process must stop accepting, finish what it has, close the pool and exit 0. | E10: Process running. | F10: 1. Note the PID. 2. kill -TERM <pid> 3. Watch stdout and the exit code (echo $?). | G10: Log lines shutdown.begin then shutdown.complete appear, in that order. Exit code 0. The port is released — a second start on the same port succeeds.
A11: MT-RUN-07 | B11: S13 | C11: Migrations apply in order | D11: The migration path crashed on an undeclared dependency until 20 Sep, so it had never run. | E11: A fresh, empty database. | F11: 1. createdb docmerge_mt2 2. DATABASE_URL=postgres://…/docmerge_mt2 DATABASE_SSL=disable node scripts/migrate.js | G11: Six files reported as applied, in numeric order 001 to 006. Exit code 0. psql \dt shows 26 tables.
A12: MT-RUN-08 | B12: S13 | C12: Re-running migrations is a clean no-op | D12: Idempotency. A deploy that runs migrations twice must not fail or double-apply. | E12: MT-RUN-07 passing. | F12: 1. Run the exact same migrate command a second time. | G12: Every file reported as 'skip (already applied)'. Exit code 0. No error, and the table count is unchanged.
A13: MT-TPL-01 | B13: S2–S3 | C13: Create a template with defaults | D13: One-screen creation: only a name and a body should be required, everything else defaulted sensibly. | E13: Build present (npx tsc run). | F13: node -e "const{TemplateDesigner,MemoryTemplateRepo}=require('./dist/index.js');(async()=>{const d=new TemplateDesigner(new MemoryTemplateRepo());console.log(await d.createWithDefaults('owner','acct-1','Offer','Dear {{name}}'))})()" | G13: A template object prints with outputFormat 'pdf', a fileNamePattern and a destinationFolder already populated, an empty rules array, and a generated templateId.
A14: MT-TPL-02 | B14: S2–S3 | C14: Render a preview with all values supplied | D14: The happy path of the merge engine's validation and substitution layer. | E14: MT-TPL-01 understood. | F14: Same REPL: create a template with body 'Dear {{name}}, your total is {{amount}}.' then call await d.renderPreview('owner','acct-1',t.templateId,{name:'Asha',amount:'£90'}) | G14: The string 'Dear Asha, your total is £90.' is returned. No placeholders remain in the output.
A15: MT-TPL-03 | B15: S2–S3 | C15: Conditional section is KEPT when its rule passes | D15: Rules include or exclude blocks of the document based on the row data. | E15: A template containing {{#vip}}Priority handling.{{/vip}} and a rule on field 'tier' equals 'gold' for section vip. | F15: Call renderPreview with data { tier: 'gold', … }. | G15: The text 'Priority handling.' appears in the output and the {{#vip}} / {{/vip}} markers do not.
A16: MT-TPL-04 | B16: S2–S3 | C16: Conditional section is REMOVED when its rule fails | D16: The other half of MT-TPL-03, and the one that actually proves the rule is evaluated. | E16: Same template as MT-TPL-03. | F16: Call renderPreview with data { tier: 'silver', … }. | G16: 'Priority handling.' does NOT appear. The rest of the document is intact and no markers are left behind.
... A81: MT-LCH-05 | B81: S9–S12 | C81: Help centre articles name the behaviour they document | D81: Docs that cannot be traced to code drift silently. | E81: Build present. | F81: Read the help centre coverage report. | G81: Each of the 15 articles names the stories whose behaviour it documents, and the batch-timing article states the honest eight-minute figure for 500 rows.

Sheet 21_Test_Cases_Negative
A1: TEST CASES — NEGATIVE (does the product refuse the wrong thing, safely and legibly?)
A2: 24 cases. Run these AFTER the positive cases for the same version — a negative case on a broken happy path tells you nothing. A refusal must be safe (nothing leaks, nothing corrupts) AND legible (the message tells the user what to do).
A4: Test case ID | B4: Version | C4: Test case name | D4: Test description | E4: Pre-conditions | F4: Step-by-step — how to test | G4: Expected result | H4: Actual result | I4: Status | J4: Tester | K4: Date | L4: Defect raised
A5: MT-N-RUN-01 | B5: S13 | C5: Refuses to start with no DATABASE_URL | D5: Fail closed at boot rather than confusingly on the first customer request. | E5: Build present. | F5: Unset DATABASE_URL and run: node dist/main.js ; echo $? | G5: Exit code 1. A startup.refused log line NAMES DATABASE_URL specifically. A generic 'configuration error' is a FAIL — the operator at 2am needs the variable name.
A6: MT-N-RUN-02 | B6: S13 | C6: Refuses a production start with non-vault secrets | D6: Secrets pasted as plain environment variables in production are a leak waiting to happen. | E6: A complete env. | F6: Set NODE_ENV=production without the __FROM_VAULT markers and start. | G6: Exit code 1, and the message says the secret is not marked vault-sourced.
A7: MT-N-RUN-03 | B7: S13 | C7: Refuses cleartext Postgres in production | D7: Tokens would cross the wire unencrypted. | E7: A Postgres without TLS. | F7: Set NODE_ENV=production and DATABASE_SSL=disable, then start. | G7: Refused with a message explaining that disable is not permitted in production. It must not silently downgrade.
A8: MT-N-RUN-04 | B8: S13 | C8: Migration refuses cleartext by default | D8: The migration job must share the app's TLS contract, not have its own. | E8: A Postgres with no TLS. | F8: Run migrate with DATABASE_SSL unset (so it defaults to require). | G8: It refuses, reporting that the server does not support SSL. It must not connect anyway.
A9: MT-N-RUN-05 | B9: S13 | C9: Unknown route returns 404, not 500 | D9: A router that throws on an unknown path leaks stack traces. | E9: Process running. | F9: curl -i http://127.0.0.1:8123/does-not-exist | G9: HTTP 404 with a short JSON error. No stack trace, no internal path names.
A10: MT-N-RUN-06 | B10: S13 | C10: Oversized request body is rejected | D10: An uncapped body read on an open port is a memory-exhaustion vector (DM-F10). | E10: Process running. | F10: POST a body larger than 1 MB to a webhook route. | G10: HTTP 413. The process stays alive and memory does not spike.
A11: MT-N-SEC-01 | B11: S13 | C11: Unauthenticated write is refused | D11: Identity used to be a caller-supplied parameter (DM-F07). | E11: Process running. | F11: POST /accounts/acct-1/documents with no Authorization header. | G11: HTTP 401. No document is created.
A12: MT-N-SEC-02 | B12: S13 | C12: A session for another account cannot act on this one | D12: Cross-tenant access through a valid session. | E12: Two accounts; a valid session for acct-B. | F12: POST /accounts/acct-A/documents using acct-B's session token. | G12: Refused. Crucially the response must NOT reveal whether acct-A exists.
A13: MT-N-SEC-03 | B13: S13 | C13: A tampered session token is refused | D13: Sessions are HMAC-signed; editing the role must invalidate them. | E13: A valid session token. | F13: Change one character in the token payload and retry a request. | G13: HTTP 401 with reason bad_signature. Editing 'member' to 'owner' must not elevate anything.
A14: MT-N-SEC-04 | B14: S13 | C14: An expired session is refused | D14: Expiry must be enforced, not decorative. | E14: A session past its expiry. | F14: Use it on any authenticated route. | G14: HTTP 401 with reason expired.
A15: MT-N-SEC-05 | B15: S16 | C15: A revoked session stops working immediately | D15: Revocation added with the durable session store. | E15: A valid session. | F15: 1. Revoke it. 2. Use it. | G15: HTTP 401 with reason revoked, on the very next request.
A16: MT-N-SEC-06 | B16: S1 | C16: Install callback without state is refused | D16: DM-F04: an attacker could bind a victim's browser to an account they control. | E16: Process running. | F16: GET /oauth/callback?code=xyz with no state parameter. | G16: HTTP 400 refusing to complete the install, and saying the callback carried no state.
... A28: MT-N-PUR-01 | B28: S16 | C28: A partial purge does NOT clear the deletion job | D28: Clearing it would lose the only record that the rest is still owed, and quietly breach the published policy. | E28: A purge registry where one store is made to throw. | F28: 1. Schedule a due deletion. 2. Make one store throw. 3. Run PurgeWorker.runOnce(). 4. Query deletion_jobs. | G28: The receipt reports complete=false, an error is logged, and the deletion_jobs row is STILL THERE for the next run. A cleared job here is a serious FAIL.

Sheet 22_Test_Cases_Blocked
A1: TEST CASES — SPECIFIED BUT BLOCKED (written, waiting, never executed)
A2: 24 cases. These are NOT failures and they are NOT passes — nobody has run them. Every one names its blocker. When a blocker lifts, move the case to sheet 20 or 21 and run it properly. Marking any of these PASS without executing it is the exact failure this whole pack exists to prevent.
A4: Test case ID | B4: Version | C4: Test case name | D4: Test description | E4: Pre-conditions | F4: Step-by-step — how to test | G4: Expected result | H4: Actual result | I4: Status | J4: Tester | K4: Date | L4: Defect raised
A5: MT-X-RND-01 | B5: S14 | C5: Create a real Doc from a real template | D5: The core function, against Google. | E5: LC-1: a GCP project with Docs and Drive enabled, and a template Doc. | F5: 1. Bind a template to a real Doc id. 2. Generate for one row. 3. Open the resulting Doc in Drive. | G5: A new Doc exists, is a copy of the template, and every {{placeholder}} is replaced with the row's value. | I5: BLOCKED | L5: LC-1
A6: MT-X-RND-02 | B6: S14 | C6: Repeating table rows for invoice line items | D6: Index arithmetic against the real Docs document model. MOST LIKELY TO FAIL FIRST. | E6: LC-1 + a template containing a table with an anchor placeholder. | F6: Generate with three line items. | G6: Three table rows appear with correct values, the template row is removed, and the table structure is intact. | I6: BLOCKED | L6: LC-1
A7: MT-X-RND-03 | B7: S14 | C7: Logo image replacement | D7: replaceImage matched on alt text. | E7: LC-1 + a template with an inline image whose alt text is the placeholder tag. | F7: Generate with an image URL supplied. | G7: The placeholder image is replaced by the supplied one; layout is preserved. | I7: BLOCKED | L7: LC-1
A8: MT-X-RND-04 | B8: S14 | C8: Section deletion across a paragraph boundary | D8: deleteContentRange where the section spans structural elements. SECOND MOST LIKELY TO FAIL. | E8: LC-1 + a template whose conditional section spans two paragraphs. | F8: Generate with the section's rule evaluating false. | G8: The section is removed cleanly with no stray markers and no 400 from the API. | I8: BLOCKED | L8: LC-1
A9: MT-X-RND-05 | B9: S14 | C9: PDF export fidelity | D9: The declared default output format. | E9: LC-1. | F9: Generate with outputFormat pdf and open the result. | G9: A valid PDF whose extracted text matches the expected merged content, with template styling preserved. | I9: BLOCKED | L9: LC-1
A10: MT-X-RND-06 | B10: S14 | C10: DOCX export | D10: The alternative format. | E10: LC-1. | F10: Generate with outputFormat docx and open in Word. | G10: A valid .docx that opens without repair and matches the expected content. | I10: BLOCKED | L10: LC-1
A11: MT-X-RND-07 | B11: S14 | C11: All 20 gallery templates render live | D11: The gallery was validated against the string engine, never against Docs. | E11: LC-1. | F11: Render each of the 20 launch templates with its sample data. | G11: All 20 produce a document with no API error and no missing placeholder. | I11: BLOCKED | L11: LC-1
A12: MT-X-RND-08 | B12: S14 | C12: Quota pacing holds under a real 500-row batch | D12: The eight-minute figure is derived, not observed. | E12: LC-1 + a 500-row sheet. | F12: Run a 500-row batch and time it. | G12: Completes without a 429 from Google, in roughly the predicted time. A materially faster run means the pacing is not engaging; a 429 means it is insufficient. | I12: BLOCKED | L12: LC-1
A13: MT-X-ADD-01 | B13: S15 | C13: Add-on installs into a real Sheet | D13: The manifest and project pushed and installed. | E13: LC-1 + clasp configured. Also DM-F31 fixed first. | F13: 1. clasp push. 2. Install the add-on. 3. Open a Sheet and launch the sidebar. | G13: The add-on appears in the Extensions menu and the sidebar opens at 300px. | I13: BLOCKED | L13: LC-1 + DM-F31
A14: MT-X-ADD-02 | B14: S15 | C14: Consent screen shows exactly the audited scopes | D14: Scope creep at the consent screen is a review rejection. | E14: LC-1. | F14: Install and read the consent screen. | G14: Exactly six scopes, matching the audited manifest. Any extra scope is a FAIL and a submission blocker. | I14: BLOCKED | L14: LC-1
A15: MT-X-ADD-03 | B15: S15 | C15: Sidebar reads the active row | D15: The capability that made the Editor add-on type mandatory. | E15: LC-1 + installed add-on. | F15: Select a row in the Sheet and open the sidebar preview. | G15: The preview shows that row's values, keyed by the header row. | I15: BLOCKED | L15: LC-1
A16: MT-X-ADD-04 | B16: S15 | C16: Form trigger registers and fires | D16: Installable triggers are the other Editor-only capability. | E16: LC-1 + a real Form. | F16: 1. Install the trigger. 2. Submit the form. | G16: A document is generated within the trigger's normal latency, and the submission id appears in the dedupe store. | I16: BLOCKED | L16: LC-1
... A28: MT-X-BIL-02 | B28: S19 | C28: A declined card starts dunning correctly | D28: Joins the gateway to the dunning schedule. | E28: Same as above, plus Stripe's test decline card. | F28: Charge with the decline card and advance the clock. | G28: Returns a decline (not an error), and the 1/3/7 dunning schedule begins. | I28: BLOCKED | L28: Stripe + enrolment

Sheet 30_Traceability
A1: TRACEABILITY — case group → version → what it proves → automated counterpart
A2: Two uses: show a reviewer that every delivered version has manual coverage, and find which cases to re-run when a module changes. The right-hand column matters — where an automated test already covers something, the manual case exists to check the part a machine cannot see.
A4: Case group | B4: Version | C4: Requirement / finding it traces to | D4: What the manual case adds over the automated one | E4: Automated counterpart | F4: Cases | G4: Runnable today?
A5: MT-RUN | B5: S13 | C5: P-DM-002, P-DM-003 — the entrypoint started nothing; the migration path crashed | D5: The automated boot test spawns the artefact in CI. The manual case has a person watch the port open, kill the process, and confirm it releases — the operational behaviour, not just the assertion. | E5: tests/boot.test.ts, postgres.contract.test.ts | F5: 8 | G5: Yes
A6: MT-TPL | B6: S2–S3 | C6: ST-001..ST-005, ST-054 — designer, rules, permissions | D6: A human reads the error message and judges whether it is actually actionable. No assertion can score that, and it is the stated differentiator. | E6: tests/templates.test.ts | F6: 9 | G6: Yes
A7: MT-BAT | B7: S3–S4 | C7: ST-011..ST-020, VER-DM6 — batch, per-row outcomes, quota pacing | D7: Confirms the run FEELS right at scale: that a failure mid-run is legible and that the timing estimate is honest rather than optimistic. | E7: tests/batch.test.ts, batchOps.test.ts, platformQuotas.test.ts | F7: 7 | G7: Yes
A8: MT-APR | B8: S5 | C8: ST-021..ST-030, P-DM-007 — approval routing and the rename | D8: A person reads the user-facing copy and judges whether it still implies a signature. The gate checks patterns; a human catches the sentence that means it without using the words. | E8: tests/esign.test.ts, claimsGate.test.ts | F8: 6 | G8: Yes
A9: MT-FIL | B9: S6 | C9: ST-031..ST-040 — filing, conflict policy, retry | D9: Against a fake host only. The live counterpart is MT-X-DRV-*. | E9: tests/driveFiler.test.ts | F9: 5 | G9: Yes
A10: MT-BIL | B10: S6–S8 | C10: ST-057..ST-063, DM-F03 — trial, proration, limits, invoices | D10: A person checks the arithmetic by hand and reads the invoice as a customer would. | E10: tests/billing.test.ts, billingHardening.test.ts, entitlementTiers.test.ts | F10: 6 | G10: Yes
A11: MT-DUN | B11: S7–S8 | C11: ST-059, ST-060 — dunning schedule and read-only termination | D11: Confirms reads really do stay available in read-only mode — the property that makes the policy humane rather than punitive. | E11: tests/billingHardening.test.ts | F11: 3 | G11: Yes
A12: MT-FRM | B12: S7–S8 | C12: ST-041..ST-050, VER-DM2 — form triggers and dedupe | D12: The restart-survival case is the one that matters and is invisible to a unit test. | E12: tests/formTrigger.test.ts, postgresDurable.contract.test.ts | F12: 4 | G12: Yes
A13: MT-DUR | B13: S16 | C13: P-DM-009, DM-F41 — durability across restart and the purge executor | D13: A real process stop and start, not a simulated one. The automated tests construct fresh instances over the same database; the manual case actually kills the process. | E13: tests/postgresDurable.contract.test.ts, purgeWorker.test.ts | F13: 7 | G13: Yes
A14: MT-GOV | B14: S17 | C14: §5 governance wedge, P-DM-012 — buyer-facing artefacts | D14: A person acts as the customer verifying their own audit export, which is the entire value proposition of the feature. The tamper cases are the proof. | E14: tests/governanceSurfaces.test.ts, listing.test.ts | F14: 6 | G14: Yes
A15: MT-OPS | B15: S18 | C15: Logging, SLO, runbook, restore drill | D15: Reads the actual log output for leaked secrets, and runs the runbook's commands as an on-call engineer would. | E15: tests/logger.test.ts, slo.test.ts, runbook.test.ts, restoreDrill.test.ts | F15: 6 | G15: Yes
... A23: MT-X-BIL | B23: S19 | C23: Stripe | D23: Nothing has ever called Stripe, and the enrolment flow that would make it possible is not built. | E23: tests/paymentGateway.test.ts (fake HTTP) | F23: 2 | G23: No — Stripe
A25: COVERAGE HONESTY: every delivered version has manual cases, and 101 of 125 are runnable today. The 24 that are not include the single most important case in the pack — MT-X-RND-01, creating a real document, which is the product's core function. A reader who counts only the runnable cases will overestimate how well this product is tested.

Sheet 31_Execution_Summary
A1: EXECUTION SUMMARY — computed live from the case sheets
A2: Do not type into the computed cells; they read the Status column of sheets 20, 21 and 22. Fill in those sheets as you test and this updates itself.
A4: Metric | B4: Positive (20) | C4: Negative (21) | D4: Blocked (22) | E4: Total
A5: Cases specified | B5: 77 | C5: 24 | D5: 24 | E5: =77+24+24
A6: PASS | B6: =COUNTIF('20_Test_Cases_Positive'!$I$5:$I$81,"PASS") | C6: =COUNTIF('21_Test_Cases_Negative'!$I$5:$I$28,"PASS") | D6: =COUNTIF('22_Test_Cases_Blocked'!$I$5:$I$28,"PASS") | E6: =SUM(B6:D6)
A7: FAIL | B7: =COUNTIF('20_Test_Cases_Positive'!$I$5:$I$81,"FAIL") | C7: =COUNTIF('21_Test_Cases_Negative'!$I$5:$I$28,"FAIL") | D7: =COUNTIF('22_Test_Cases_Blocked'!$I$5:$I$28,"FAIL") | E7: =SUM(B7:D7)
A8: BLOCKED | B8: =COUNTIF('20_Test_Cases_Positive'!$I$5:$I$81,"BLOCKED") | C8: =COUNTIF('21_Test_Cases_Negative'!$I$5:$I$28,"BLOCKED") | D8: =COUNTIF('22_Test_Cases_Blocked'!$I$5:$I$28,"BLOCKED") | E8: =SUM(B8:D8)
A9: Not yet run (blank) | B9: =B5-COUNTA('20_Test_Cases_Positive'!$I$5:$I$81) | C9: =C5-COUNTA('21_Test_Cases_Negative'!$I$5:$I$28) | D9: =D5-COUNTA('22_Test_Cases_Blocked'!$I$5:$I$28) | E9: =SUM(B9:D9)
A10: Executed (PASS+FAIL) | B10: =B6+B7 | C10: =C6+C7 | D10: =D6+D7 | E10: =SUM(B10:D10)
A11: Pass rate of executed | B11: =IFERROR(B6/B10,"—") | C11: =IFERROR(C6/C10,"—") | D11: =IFERROR(D6/D10,"—") | E11: =IFERROR(E6/E10,"—")
A13: SIGN-OFF
A14: Test run identifier | D14: e.g. 'MT run 1 — pre-LC-1 baseline'
A15: Tester name
A16: Run started
A17: Run completed
A18: Build tested (git commit or zip name) | D18: Must match the Cover sheet's 'Build under test'
A19: Environment | D19: Node version, Postgres version, OS
A20: Overall verdict | D20: State it in words, and say what you did NOT run
A21: Reviewed by
A22: Date reviewed
A24: A verdict that does not say what was NOT run is not a verdict. At minimum, state that the 24 blocked cases were not executed and name their blocker.

Sheet 32_Defect_Log
A1: DEFECT LOG — defects found by MANUAL testing
A2: One row per failure. The product-wide canonical register is DEFECT_REGISTER.md in the code archive — raise the defect there too and put its id in column B so the two point at each other.
A4: Log id | B4: Defect id (register) | C4: Found by case | D4: Date | E4: Severity | F4: What happened | G4: Expected instead | H4: Steps to reproduce | I4: Status | J4: Owner | K4: Resolution / evidence
A5: (no manual-test defects recorded yet — this pack has not been executed)
A7: SEVERITY GUIDE
A8: Critical | C8: Data loss, a cross-tenant leak, a silent wrong result, or a published policy the product does not honour. Stop testing and raise it immediately.
A9: High | C9: A core function fails, or a refusal does not refuse. The product cannot ship with it.
A10: Medium | C10: Works but wrongly in a recoverable way, or the message is misleading.
A11: Low | C11: Cosmetic, or an edge case with an easy workaround.
A13: Note on what counts as a defect here: if a case fails because the EXPECTED result in this pack is wrong, that is a defect in the pack, not the product. Log it anyway, mark it as such, and fix the expected result in the next version — a stale expectation produces false failures, which erode trust in the pack faster than missing cases do.
