Workbook

Sheet Version_Control
A1: VERSION CONTROL — TestPulse
A2: Version | B2: Date | C2: Author | D2: Change | E2: Status
A3: v001-v004 | B3: 2026-09-05 | C3: Claude for Senthil/KP | D3: Lineage: marketplace master (868 entries) -> portfolio plan (12 products) -> wave-1 (RetainKit/ShiftDesk/EngageOS, v005) -> this product selected for wave-3 | E3: Released
A4: v008 | B4: 2026-09-10 22:58 | C4: Claude for Senthil/KP | D4: RELEASED (supersedes the planned S0 re-baseline — D13 parked interviews): S1-S8 code scope executed done-in-code per Senthil 22:58 continue-sprint instruction. TypeScript core (config, store, lifecycle, permissions+audit, F1 case-gen, F2 run boards, F3 flaky detector, F4 readiness score, F5 Xray importer, E5 billing, E6 compliance, E7 analytics, webhooks, jiraClient backoff/breaker). D13 gate: 16 Jest suites / 105 tests / 100% branches-functions-lines-statements; CI coverage gate + E2E smoke every deploy. Full_Backlog statuses updated: 71 Done, 7 Code-complete pending live, 22 Backlog. Companion tracker: claude_v001_testpulse_sprint_tracker_traceability_20260910_2258.xlsx. | E4: Released
A5: v009 | B5: 2026-09-10 23:13 | C5: Claude for Senthil/KP | D5: S9-S12 executable scope executed: E8 onboarding/help/support, EQ load test EXECUTED (5,238 rps, 0 errors) + backup drill + chaos degrade + status page, EL launch collateral (copy A/B, pricing, trust, runbook, dry-run, specs), AnthropicProvider wired behind AI seam. 21 suites / 129 tests / 100% x4. 80 Done / 15 code-complete / 5 backlog. Remaining backlog = external-party items only (pen-test, live-UI assets/AA, post-launch SEO, partner reviews). | E5: Released
A6: v010 | B6: 2026-09-11 08:31 | C6: Claude for Senthil/KP | D6: LC-1 turnkey: ForgeStore hosted-storage adapter (tested), paste-ready forge manifest, 30-min deploy guide. Owed docs closed: review pack (LC #2), Cloud Fortified formal gap assessment (LC #3, no structural gaps), residency statement (LC #4), S0 PRD rollup. 22 suites / 132 tests / 100% x4. Backlog counts unchanged (80 Done / 15 code-complete / 5 backlog) — every remaining flip needs a Senthil-side live action. | E6: Released
A7: v011 | B7: 2026-09-11 12:51 | C7: Claude for Senthil/KP | D7: Forge glue shipped (resolver+webtrigger handlers over hosted-storage adapter; deploy-guide step 5 = zero-code) and Xray/Zephyr importer hardened to real export shapes (RFC-4180, multi-step aggregation, Zephyr Scale, ragged rows). Mid-pass coverage regression caught and closed. 23 suites / 146 tests / 100% x4. Counts unchanged: 80 Done / 15 code-complete / 5 backlog — remaining flips all Senthil-side (LC #1 install, #8 billing, #5 real files, #7 assets, pen-test, D15/D17). | E7: Released
A8: v012 | B8: 2026-09-11 13:32 | C8: Claude for Senthil/KP | D8: Custom UI layer shipped and headless-verified: tested view-models/renderers/mount (15 tests incl. jsdom), esbuild bundle at static/build/app.js, Forge index.html bridge hook, demo.html rendering all four panels with demo data. The manifest's static resource now exists — LC-1 blocks on Senthil ► steps only. Draft screenshots capturable from demo.html today. 25 suites / 161 tests / 100% x4. Counts unchanged 80/15/5. | E8: Released
A9: v013 | B9: 2026-09-11 15:27 | C9: Claude for Senthil/KP | D9: External verification sweep vs live Atlassian docs: R-P5 closed (own webtrigger auth is the documented pattern — HMAC design correct); runtime corrected to nodejs22.x (Node 20 EOL); kvsAdapter shipped for the real @forge/kvs query API (no listKeys exists); Marketplace asset spec rewritten to the verified Rule-of-3 (1840x900/580x330, <=50/220-char text, banner 1120x548, <30s video). 25 suites / 163 tests / 100% x4. Counts unchanged 80/15/5. | E9: Released
A10: v014 | B10: 2026-09-11 22:09 | C10: Claude for Senthil/KP | D10: B-17 de-risked: Paid-via-Atlassian verified and wired (manifest licensing flag + license gate: inactive => read-only, reads never blocked; billing.ts payment engine honestly superseded for Marketplace channel). NEW DECISION D18: per-user pricing re-anchor needed (Atlassian has no flat plans). Economics: 100% revenue to partner up to $1M lifetime Forge revenue. Design-partner kit shipped for ST-100. 26 suites / 167 tests / 100% x4. Counts unchanged 80/15/5. | E10: Released
A11: v015 | B11: 2026-09-11 22:28 | C11: Claude for Senthil/KP | D11: 22:28 'continue' — COLD REVIEW PASS 1 (TestPulse's first; sibling pattern after TeleField/FlowCast/ShiftDesk/VoiceBridge). All 27 modules read adversarially: 13 defects found and fixed with pinned regressions, 4 observations logged for disposition (see Review_Findings). Headline: delete-my-data/export-my-data covered only cloudId-substring keys, so cases, boards, CI results, audit log, notifications, telemetry and support tickets were never deleted — the published 30-day hard-delete policy was breached, and the retention sweep had the same hole. Also: the flaky panel would have rendered NaN% live (resolver returns flipRate, UI read score) and the readiness panel NaN/NOT-READY (empty payload, no input validation). Five unbounded ledgers would have hard-failed Forge writes over time. All found at 100% coverage — F-V14 confirmed for a sixth product. 27 suites / 203 tests / 100% x4, zero pragmas. Story counts unchanged (80 Done / 15 code-complete / 5 backlog) — corrections to shipped work, not new scope. | E11: Released
A12: v016 | B12: 2026-09-13 09:52 | C12: Claude for Senthil/KP | D12: 09:52 'continue' — COLD REVIEW PASS 2 + VERIFICATION SWEEP: 10 defects fixed with pinned regressions, 3 of them LIVE-BLOCKING and invisible to the test suite because no Jest run loads the file Forge loads. VER-P01: forge/index.ts was five commented-out lines AND the wrong shape — Forge resolvers are resolver.define(key,({payload,context}))+getDefinitions() and invoke() matches the definition key, so a deploy would have registered handlers that do not exist and LC-1 would have failed at the first panel click. VER-P02: the Custom UI page never mounted anything and the bundle contained no @forge/bridge (3.7kb -> 96.7kb once real); the generate tab also demanded story text an issue panel never has. VER-P03: Forge sends isEvaluation, the gate read evaluation. F-TP14 (security): the permission role arrived from the caller — a member could invoke as owner; roles are now derived server-side. F-TP15 (security): one app-wide CI secret for every installation, with HC-05 pointing at a Settings screen that could not exist. F-TP16: AnthropicProvider was never called — AI generation was inert in production and R-P6 had been cleared on an unreachable class. Plus F-TP17 importer discarded parsed steps, F-TP18 demo mode seeded records nothing reads, F-TP19 three help articles described behaviour the product lacks, F-TP20 exit-survey ledger. 28 suites / 233 tests / 100% x4 zero pragmas, plus two new CI gates (typecheck:forge, build:ui). Story counts unchanged 80/15/5. | E12: Released
A13: v017 | B13: 2026-09-13 10:24 | C13: Claude for Senthil/KP | D13: 10:24 'continue' — COLD REVIEW PASS 3 (REACHABILITY): the question passes 1 and 2 cannot ask — once installed, can a user reach what we claim to ship? Mostly no: of 29 modules the resolver reached eight. Self-serve export/delete had NO resolver call (HC-12, trust page, residency statement, Cloud Fortified gap assessment all unreachable); the 30-day retention sweep was scheduled nowhere (no scheduledTrigger in the manifest, so the published hard delete never ran); every customisation and pause story was library-only; notify() was never called in the Forge path so no notification was ever raised in the installed app; trackError had no caller so the error-spike alert could never fire; support intake, audit log and latency budgets had no surface; and the panel bound no events at all — no control in the product did anything. 9 findings fixed: data-rights + settings + support + audit + status resolver calls, daily scheduledTrigger for retention, notifications wired into the real paths, per-invocation latency sampling, and a real Settings screen with working controls (CI secret + rotate, generation rules, flaky threshold, pause toggles, notification matrix, demo data, export/delete). 30 suites / 263 tests / 100% x4 zero pragmas; forge typecheck + UI build green; demo page re-verified headless including the new Settings screen. Story counts unchanged 80/15/5. | E13: Released
... A30: v034 | B30: 2026-09-13 20:49 | C30: Claude for Senthil/KP | D30: 20:49 VENDOR CONTRACT GUARD — generalising PERF-04 so the class cannot repeat. PERF-04 cost a wasted storage round trip per key on every invocation and survived eight internal passes and two external reviews for one reason: the KVS test double returned { key } where the vendor's Result<T> returns { key, value }. Nobody misread the code; everyone read a double thinner than the API it stood for. test/vendor-contracts.test.ts now assigns every seam to or from the vendor's own published type, so a thin double is a COMPILE ERROR: KVS ListResult/Result (hydrate), @forge/resolver Request (the invocation shape), @forge/bridge LicenseDetails (isEvaluation vs evaluation — the VER-P03 defect), FullContext (the panel boot context), and @forge/api Response/Headers (headers.get returning string|null, which the Retry-After path depends on). All four vendor contracts were audited against the installed packages and every one currently holds. THE GUARD CAUGHT ME ON ITS FIRST RUN: I asserted the resolver contract in the wrong DIRECTION. For an inbound contract the vendor's type must be assignable to ours — we must accept whatever they send, and tolerating more is correct; for an outbound contract ours must satisfy theirs. Asserting the wrong way either passes for the wrong reason or fails in a way that looks like a defect and is not. One assumption stays unprovable by types and is recorded rather than buried: ExtensionData is an open map in the vendor definitions, so extension.issue.key — which the generate tab depends on — can only be verified live at LC-1. 44 suites / 426 tests / 100% x4; six gates green; CI at evidence/ci-run-20260913-2049.log. | E30: Released
A31: v035 | B31: PLANNED: LC-1 evidence; the five open decisions; D18 pricing; asset capture. | E31: Planned
A32: v035 | B32: 2026-09-20 11:40 | C32: Claude for Senthil/KP | D32: EXTERNAL REVIEW V001 (Perplexity Computer, 16/09) INCORPORATED IN FULL. The review reproduced our CI independently (44 suites / 426 tests / 100% x4, six gates, 0 prod vulns) — the only claim it found UNDERSTATED rather than overstated — and then found five defects none of that machinery could see, because every gate reasons about one invocation at a time. All five are closed in code with pinned regressions; all seven artifact corrections are applied, two of them downgrading a status we had published. The verdicts, recorded as the reviewer wrote them: market demand 7/10 (proven category, credible wedge, STALE DIFFERENTIATION, zero primary validation); enterprise grade ~4.5/10, BELOW the 5.1 of V002, because PRX-02 and the Cloud Fortified retirement are both worse than anything V002 knew about; release readiness NOT READY, unchanged and unchangeable by more code. What moved: capability depth 3/10 -> the two MISSING gates (EG-05 traceability, EG-06 automation ingest) are built and EG-04 has its versioned-entity seed; scale 2/10 -> the row ceiling that was "the disqualifier, and a data-model problem" is gone, with the round-trip cost that replaced it published honestly; correctness under real use 3/10 -> PRX-02 closed with a standing gate; enterprise programme 2/10 -> assessed against the programme that actually exists. What did NOT move: operational evidence 1/10 — nothing has still ever run on a real Jira site, and no amount of code changes that. Commercially: the 17% marketplace fee was wrong in our favour (0% until $1M lifetime Forge revenue since 01/01/2026), so net MRR was understated ~20% and breakeven moves earlier; the price is re-anchored per-user 40-50% under Xray in the 26-200 band with the sub-10 band conceded, because at 10 seats we were 12x Xray. R-P2 is closed as MATERIALISED: AI case generation is table stakes, not differentiation. Package: 55 suites / 530 tests / 100% x4, seven gates (G-5 concurrent write safety is new and went red on its own first run), clean-room reproduced from the lockfile, 0 production dependencies. | E32: Released
A33: v036 | B33: PLANNED: LC-1 evidence (PR-04); live envelope (PR-12); per-user pricing + test purchase (PR-13); design partners (PR-14). | E33: Planned

Sheet ReadMe_Scope
A1: README / SCOPE — differentiation rewritten 20/09 after external review V001 (C-4)
A2: TestPulse — Release Quality Intelligence for Jira: is this release ready to ship, and if not, why not.
A3: PLATFORM: Atlassian Marketplace | CATEGORY: Testing / QA for Jira
A4: PROBLEM: Xray and Zephyr manage test CASES well. Neither answers the question an engineering manager actually asks on release day — "are we ready, and what is holding us back?" — with numbers anyone can trace back to their source.
A5: DIFFERENTIATION (rewritten, C-4): NOT "AI case generation" — the review established that is now table stakes (Xray markets itself as "powered by AI", Zephyr as "with Rovo", and the Testing & QA category carries 1,411 apps including several dedicated generators). The differentiator is the RELEASE DECISION: a readiness score derived from live Jira, live CI results and recorded executions, where every factor names its source, the verdict explains itself, and a human override is labelled as one. Forge-native, so there is no infrastructure for the customer and no data leaving Atlassian unless an admin turns AI on.
A6: WHY THAT WEDGE: it is bought by the engineering manager rather than the QA lead, and it does not require beating Xray at test-entity modelling. The review's words: "the wedge is the release decision, not the test case."
A7: HONESTY ABOUT THE WEDGE: until 20/09 the readiness score's two heaviest inputs were typed in by the owner — the review called that "a spreadsheet with a dial", and it was right. PR-05 made every factor derived. The positioning is now earned by the code rather than asserted by the listing.
A8: ICP: software teams 25-500 devs on Jira Cloud, existing manual QA or overloaded Xray installs. Sub-10-seat sites are conceded (Xray is ~$100/yr there and migration cost dwarfs any discount) and treated as free acquisition.
A9: PRICING: per-user tiers via Atlassian billing (flat plans cannot be listed — D18), anchored 40-50% under Xray in the 26-200 band. Forge revenue share is 0% until $1M lifetime (C-3).
A10: HOW TO USE: Full_Backlog is the single source of truth (edit Status during execution). Sprint_Board recalculates per sprint. Financial_Model assumptions (yellow) are editable. Launch_Checklist is the platform gate before submission. Review_PRX_V001 and Corrections_Applied record what the external review changed.
A11: STACK: TypeScript/Node on Forge (nodejs22.x), Custom UI, Forge hosted storage with per-entity keys (Forge SQL adapter ready, opt-in — ADR-001), GitHub Actions CI with seven standing gates.

Sheet Product_Spec
A1: PRODUCT SPEC
A2: Module (feature) | B2: Scope in MVP | C2: Out of scope (v1) | D2: Non-functional requirements
A3: AI test-case generation | B3: AI test-case generation: end-to-end happy path + edge cases + permissions | C3: Advanced automation, AI beyond listed, multi-language beyond launch set | D3: p95 <500ms API / <2s UI loads
A4: Test run boards | B4: Test run boards: end-to-end happy path + edge cases + permissions | C4: Advanced automation, AI beyond listed, multi-language beyond launch set | D4: 99.5% monthly uptime
A5: Flaky-test detector | B5: Flaky-test detector: end-to-end happy path + edge cases + permissions | C5: Advanced automation, AI beyond listed, multi-language beyond launch set | D5: WCAG AA
A6: Release readiness score | B6: Release readiness score: end-to-end happy path + edge cases + permissions | C6: Advanced automation, AI beyond listed, multi-language beyond launch set | D6: SOC2-track controls
A7: Xray importer | B7: Xray importer: end-to-end happy path + edge cases + permissions | C7: Advanced automation, AI beyond listed, multi-language beyond launch set | D7: Rate-limit safe (backoff+queue)
A8: Persona | B8: Jobs-to-be-done
A9: QA lead | B9: Owns tool choice; wants migration importer from Xray/Zephyr
A10: Eng manager | B10: Buys on release-risk visibility
A11: Jira admin | B11: Cares about Cloud Fortified badge + data residency

Sheet Screens_Wireframes
A1: SCREEN INVENTORY
A2: ID | B2: Screen | C2: Purpose | D2: States | E2: Figma
A3: # | B3: Screen | C3: Purpose | D3: Key elements | E3: Wireframe link
A4: 1 | B4: Onboarding / first-run | C4: Reach aha in <1 day | D4: Checklist, sample data toggle, connect steps
A5: 2 | B5: Home dashboard | C5: Daily habit surface | D5: KPI cards, activity feed, alerts
A6: 3 | B6: AI test-case generation workspace | C6: Core value surface | D6: List+detail, bulk actions, status chips
A7: 4 | B7: Test run boards builder | C7: Configure second pillar | D7: Rule builder, preview, test mode
A8: 5 | B8: Flaky-test detector view | C8: Differentiator surface | D8: Timeline/visual, export
A9: 6 | B9: Settings & team | C9: Roles, notifications, data | D9: Role matrix, API keys, danger zone
A10: 7 | B10: Billing | C10: Plan/trial/invoices | D10: Plan cards, usage meter, invoices
A11: 8 | B11: Analytics | C11: Prove ROI | D11: Funnel, cohort, export
A12: 9 | B12: Help & support | C12: Deflect + assist | D12: Search, chat, status

Sheet GTM_Execution
A1: GTM EXECUTION TASKS
A2: Phase | B2: Task | C2: Owner (role) | D2: Target sprint
A3: Pre-launch | B3: Positioning doc + message house (problem/promise/proof) | C3: Founder | D3: S7
A4: Pre-launch | B4: Listing SEO: keyword study in marketplace search + title/intro drafts | C4: Growth | D4: S8
A5: Pre-launch | B5: 10 design-partner mini case snippets with metric proof | C5: Founder | D5: S8
A6: Pre-launch | B6: 5 comparison/alternative pages drafted | C6: Growth | D6: S9
A7: Pre-launch | B7: Screenshots (5) + 2-min demo video produced | C7: Design | D7: S9
A8: Launch | B8: Listing live + launch post + video published | C8: Growth | D8: S11
A9: Launch | B9: Founder outreach: 100 named ICP accounts, 3-touch sequence | C9: Founder | D9: S11
A10: Launch | B10: Community value-posts (3 relevant communities) | C10: Founder | D10: S11
A11: Launch | B11: Review-generation program on (in-app ask post-aha) | C11: Eng | D11: S11
A12: Post-launch | B12: Weekly SEO/how-to content cadence starts | C12: Growth | D12: S12
A13: Post-launch | B13: Marketplace paid placement pilot (where offered) | C13: Growth | D13: S12
... A15: Post-launch | B15: G2/Capterra profiles + first 10 reviews | C15: Growth | D15: S12+

Sheet Metrics_Targets
A1: METRIC TARGETS (first 12 months post-launch)
A2: Metric | B2: M1 | C2: M3 | D2: M6 | E2: M12 | F2: Notes
A3: Installs/signups cumulative | B3: varies | C3: 3x M1 | D3: 8x M1 | E3: 20x M1 | F3: Drive via listing SEO + outbound
A4: Activation % (24h) | B4: 30% | C4: 40% | D4: 45% | E4: 50% | F4: Onboarding iterations S12+
A5: Trial→paid % | B5: baseline | C5: +2pts | D5: +4pts | E5: +6pts | F5: Pricing test at S12
A6: Rating | B6: 4.5+ | C6: 4.6+ | D6: 4.7+ | E6: 4.7+ | F6: Review program + support speed
A7: MRR | B7: first $ | C7: 3x | D7: 8x | E7: 20x | F7: Model sheet has the math
A8: Logo churn/mo | B8: <5% | C8: <4% | D8: <3% | E8: <3% | F8: Health-score saves

Sheet Full_Backlog
A1: FULL BACKLOG — single source of truth
A2: Statuses corrected by external review V001 on 20/09 where the published state outran the code. N/A (platform) means the platform owns it and it will never be "Done" here.
A3: ID | B3: Epic | C3: Story | D3: Points | E3: Priority | F3: Sprint | G3: Status
A4: ST-001 | B4: F1 | C4: As a QA lead, I can set up AI test-case generation with sensible defaults in one screen | D4: 5 | E4: P0 | F4: S2 | G4: Done
A5: ST-002 | B5: F1 | C5: As a QA lead, the AI test-case generation happy path completes without documentation | D5: 8 | E5: P0 | F5: S2 | G5: Done
A6: ST-003 | B6: F1 | C6: As a Eng manager, I can customise AI test-case generation rules/conditions for my workflow | D6: 5 | E6: P1 | F6: S2 | G6: Done
A7: ST-004 | B7: F1 | C7: As a user, AI test-case generation shows clear errors and retry paths on platform API failures | D7: 3 | E7: P0 | F7: S2 | G7: Done
A8: ST-005 | B8: F1 | C8: As a Jira admin, AI test-case generation works on the Forge app panel inside Jira surface end-to-end | D8: 5 | E8: P0 | F8: S3 | G8: Code-complete — pending live
A9: ST-006 | B9: F1 | C9: As a Eng manager, I can see AI test-case generation performance metrics and trends | D9: 3 | E9: P1 | F9: S3 | G9: Done
A10: ST-007 | B10: F1 | C10: As a user, AI test-case generation respects role permissions and audit logging | D10: 3 | E10: P1 | F10: S3 | G10: Done
A11: ST-008 | B11: F1 | C11: As a QA lead, I can pause/disable AI test-case generation without data loss | D11: 2 | E11: P2 | F11: S3 | G11: Done
A12: ST-009 | B12: F1 | C12: As a Eng manager, I can import/migrate existing data into AI test-case generation (CSV + competitor importer) | D12: 5 | E12: P1 | F12: S3 | G12: Done
A13: ST-010 | B13: F1 | C13: As a user, I get notifications (in-app + email) for key AI test-case generation events with per-type mute | D13: 3 | E13: P2 | F13: S3 | G13: Done
A14: ST-011 | B14: F2 | C14: As a QA lead, I can set up Test run boards with sensible defaults in one screen | D14: 5 | E14: P0 | F14: S3 | G14: Done
A15: ST-012 | B15: F2 | C15: As a QA lead, the Test run boards happy path completes without documentation | D15: 8 | E15: P0 | F15: S3 | G15: Done
... A103: ST-100 | B103: EL | C103: First 10 design-partner reviews scheduled | D103: 2 | E103: P1 | F103: S11 | G103: Backlog — PR-14
A104: Total stories: 100. Epics: F1-F5 = product features; E1 install, E5 billing, E6 compliance, E7 telemetry, E8 onboarding/docs/support, EQ quality. Edit Status (Backlog/In progress/Done) during execution.
A105: ST-101 | B105: EX | C105: As a QA team, two of us can work in TestPulse at the same time without losing each other's work | D105: 13 | E105: P0 | F105: PR-01 | G105: Done
A106: ST-102 | B106: EX | C106: As a user, when someone else changed the thing I am saving, I am told to reload rather than silently overwriting them | D106: 3 | E106: P0 | F106: PR-01 | G106: Done
A107: ST-103 | B107: EX | C107: As an engineer, every test case has one permanent unique id however it was created | D107: 5 | E107: P0 | F107: PR-02 | G107: Done
A108: ST-104 | B108: EX | C108: As a QA lead, I can edit a generated case and be refused if someone edited it first | D108: 3 | E108: P1 | F108: PR-02 | G108: Done
A109: ST-105 | B109: EX | C109: As a large site, I can hold 50,000 test cases and 100,000 CI results without hitting a storage ceiling | D109: 13 | E109: P0 | F109: PR-03 | G109: Done
A110: ST-106 | B110: EX | C110: As an admin, opening a panel does not load my whole site | D110: 8 | E110: P0 | F110: PR-03 | G110: Done
A111: ST-107 | B111: EX | C111: As an engineering manager, the readiness score is derived from live data and shows me where each number came from | D111: 13 | E111: P0 | F111: PR-05 | G111: Code-complete — pending live
A112: ST-108 | B112: EX | C112: As an owner, I can override a factor, but only with a reason that is shown next to the score | D112: 3 | E112: P1 | F112: PR-05 | G112: Done
A113: ST-109 | B113: EX | C113: As a team, I can post my JUnit, Playwright or Cucumber report straight to TestPulse | D113: 8 | E113: P0 | F113: PR-06 | G113: Code-complete — pending live
A114: ST-110 | B114: EX | C114: As a pipeline, re-posting the same run changes nothing and an oversized post is refused cleanly | D114: 5 | E114: P0 | F114: PR-06 | G114: Done
A115: ST-111 | B115: EX | C115: As a QA lead, a test that is unstable only on a feature branch is not quarantined across my whole project | D115: 8 | E115: P1 | F115: PR-07 | G115: Done
A116: ST-112 | B116: EX | C116: As a QA lead, I can quarantine a test with an owner and an expiry, and every change is audited | D116: 5 | E116: P1 | F116: PR-07 | G116: Done
... A124: ST-120 | B124: EX | C124: As a regulated tenant, I can run TestPulse with no external egress at all | D124: 3 | E124: P1 | F124: PR-10 | G124: Done

Sheet Sprint_Board
A1: SPRINT BOARD — live counts from Full_Backlog
A2: Done counts Done + Code-complete — pending live. N/A (platform) rows are not counted as done.
A3: Sprint | B3: Focus | C3: Stories | D3: Points | E3: Done | F3: Exit criteria
A4: S0 | B4: Discovery & Design (2 wks) | C4: =COUNTIF(Full_Backlog!$F$4:$F$124,A4) | D4: =SUMIF(Full_Backlog!$F$4:$F$124,A4,Full_Backlog!$D$4:$D$124) | E4: =COUNTIFS(Full_Backlog!$F$4:$F$124,A4,Full_Backlog!$G$4:$G$124,"Done")+COUNTIFS(Full_Backlog!$F$4:$F$124,A4,Full_Backlog!$G$4:$G$124,"Code-complete — pending live") | F4: PRD signed off; prototype tested with 5 target users
A5: S1 | B5: Foundation (2 wks) | C5: =COUNTIF(Full_Backlog!$F$4:$F$124,A5) | D5: =SUMIF(Full_Backlog!$F$4:$F$124,A5,Full_Backlog!$D$4:$D$124) | E5: =COUNTIFS(Full_Backlog!$F$4:$F$124,A5,Full_Backlog!$G$4:$G$124,"Done")+COUNTIFS(Full_Backlog!$F$4:$F$124,A5,Full_Backlog!$G$4:$G$124,"Code-complete — pending live") | F5: App installs cleanly in dev store/org; telemetry firing
A6: S2 | B6: Core feature AI test-case generation - part 1 | C6: =COUNTIF(Full_Backlog!$F$4:$F$124,A6) | D6: =SUMIF(Full_Backlog!$F$4:$F$124,A6,Full_Backlog!$D$4:$D$124) | E6: =COUNTIFS(Full_Backlog!$F$4:$F$124,A6,Full_Backlog!$G$4:$G$124,"Done")+COUNTIFS(Full_Backlog!$F$4:$F$124,A6,Full_Backlog!$G$4:$G$124,"Code-complete — pending live") | F6: AI test-case generation happy path demoable
A7: S3 | B7: AI case-gen part 2 + Test run boards start | C7: =COUNTIF(Full_Backlog!$F$4:$F$124,A7) | D7: =SUMIF(Full_Backlog!$F$4:$F$124,A7,Full_Backlog!$D$4:$D$124) | E7: =COUNTIFS(Full_Backlog!$F$4:$F$124,A7,Full_Backlog!$G$4:$G$124,"Done")+COUNTIFS(Full_Backlog!$F$4:$F$124,A7,Full_Backlog!$G$4:$G$124,"Code-complete — pending live") | F7: AI case-gen complete with tests; Run boards skeleton
A8: S4 | B8: Core feature Test run boards | C8: =COUNTIF(Full_Backlog!$F$4:$F$124,A8) | D8: =SUMIF(Full_Backlog!$F$4:$F$124,A8,Full_Backlog!$D$4:$D$124) | E8: =COUNTIFS(Full_Backlog!$F$4:$F$124,A8,Full_Backlog!$G$4:$G$124,"Done")+COUNTIFS(Full_Backlog!$F$4:$F$124,A8,Full_Backlog!$G$4:$G$124,"Code-complete — pending live") | F8: MVP loop usable end-to-end internally
A9: S5 | B9: Flaky-test detector + alpha hardening | C9: =COUNTIF(Full_Backlog!$F$4:$F$124,A9) | D9: =SUMIF(Full_Backlog!$F$4:$F$124,A9,Full_Backlog!$D$4:$D$124) | E9: =COUNTIFS(Full_Backlog!$F$4:$F$124,A9,Full_Backlog!$G$4:$G$124,"Done")+COUNTIFS(Full_Backlog!$F$4:$F$124,A9,Full_Backlog!$G$4:$G$124,"Code-complete — pending live") | F9: Internal alpha: team dogfoods daily
A10: S6 | B10: Billing + Release readiness score | C10: =COUNTIF(Full_Backlog!$F$4:$F$124,A10) | D10: =SUMIF(Full_Backlog!$F$4:$F$124,A10,Full_Backlog!$D$4:$D$124) | E10: =COUNTIFS(Full_Backlog!$F$4:$F$124,A10,Full_Backlog!$G$4:$G$124,"Done")+COUNTIFS(Full_Backlog!$F$4:$F$124,A10,Full_Backlog!$G$4:$G$124,"Code-complete — pending live") | F10: Can charge a test customer; upgrade/downgrade paths work
A11: S7 | B11: Private beta (design partners) | C11: =COUNTIF(Full_Backlog!$F$4:$F$124,A11) | D11: =SUMIF(Full_Backlog!$F$4:$F$124,A11,Full_Backlog!$D$4:$D$124) | E11: =COUNTIFS(Full_Backlog!$F$4:$F$124,A11,Full_Backlog!$G$4:$G$124,"Done")+COUNTIFS(Full_Backlog!$F$4:$F$124,A11,Full_Backlog!$G$4:$G$124,"Code-complete — pending live") | F11: 3+ partners active weekly; NPS pulse >30
A12: S8 | B12: Beta iteration + Xray importer | C12: =COUNTIF(Full_Backlog!$F$4:$F$124,A12) | D12: =SUMIF(Full_Backlog!$F$4:$F$124,A12,Full_Backlog!$D$4:$D$124) | E12: =COUNTIFS(Full_Backlog!$F$4:$F$124,A12,Full_Backlog!$G$4:$G$124,"Done")+COUNTIFS(Full_Backlog!$F$4:$F$124,A12,Full_Backlog!$G$4:$G$124,"Code-complete — pending live") | F12: Retention of beta cohort week-over-week >60%
A13: S9 | B13: Marketplace review prep | C13: =COUNTIF(Full_Backlog!$F$4:$F$124,A13) | D13: =SUMIF(Full_Backlog!$F$4:$F$124,A13,Full_Backlog!$D$4:$D$124) | E13: =COUNTIFS(Full_Backlog!$F$4:$F$124,A13,Full_Backlog!$G$4:$G$124,"Done")+COUNTIFS(Full_Backlog!$F$4:$F$124,A13,Full_Backlog!$G$4:$G$124,"Code-complete — pending live") | F13: Review submission accepted into queue
A14: S10 | B14: Review remediation + docs | C14: =COUNTIF(Full_Backlog!$F$4:$F$124,A14) | D14: =SUMIF(Full_Backlog!$F$4:$F$124,A14,Full_Backlog!$D$4:$D$124) | E14: =COUNTIFS(Full_Backlog!$F$4:$F$124,A14,Full_Backlog!$G$4:$G$124,"Done")+COUNTIFS(Full_Backlog!$F$4:$F$124,A14,Full_Backlog!$G$4:$G$124,"Code-complete — pending live") | F14: Marketplace approval obtained (or final remediation cycle)
A15: S11 | B15: Launch | C15: =COUNTIF(Full_Backlog!$F$4:$F$124,A15) | D15: =SUMIF(Full_Backlog!$F$4:$F$124,A15,Full_Backlog!$D$4:$D$124) | E15: =COUNTIFS(Full_Backlog!$F$4:$F$124,A15,Full_Backlog!$G$4:$G$124,"Done")+COUNTIFS(Full_Backlog!$F$4:$F$124,A15,Full_Backlog!$G$4:$G$124,"Code-complete — pending live") | F15: First 10 installs; first 3 reviews; activation >40%
... A26: PR-11 | B26: Atlassian Enterprise Certified programme | C26: =COUNTIF(Full_Backlog!$F$4:$F$124,A26) | D26: =SUMIF(Full_Backlog!$F$4:$F$124,A26,Full_Backlog!$D$4:$D$124) | E26: =COUNTIFS(Full_Backlog!$F$4:$F$124,A26,Full_Backlog!$G$4:$G$124,"Done")+COUNTIFS(Full_Backlog!$F$4:$F$124,A26,Full_Backlog!$G$4:$G$124,"Code-complete — pending live") | F26: Every AEC row has an owner, date and evidence
A27: TOTAL | C27: =SUM(C4:C26) | D27: =SUM(D4:D26) | E27: =SUM(E4:E26)
B28: Velocity check: points/sprint S2-S8 should sit within 30-45 for a 4-6 person team. The PR-series sprints were executed by one build pass and are not a velocity signal.

Sheet Financial_Model
A1: 18-MONTH FINANCIAL MODEL — Atlassian Forge PLG (edit the yellow assumptions)
A2: CORRECTED 20/09 (C-3, external review V001): the marketplace fee was 17% and is 0% — eligible Forge apps keep 100% of gross revenue until $1,000,000 LIFETIME Forge revenue (from 01/01/2026); 84% from 01/04/2026 and 83% from 01/10/2026 apply only above that threshold. TestPulse qualifies (no Connect modules, OAuth, Forge UI). Net MRR was understated by ~20% across the whole horizon and breakeven moves earlier. ARPU is re-anchored to the per-user tiers in docs/pricing-faq.md, not the unlistable flat plans.
A3: Assumption | B3: Value | C3: Note
A4: Trials/installs (month 1) | B4: 40 | C4: Listing SEO + outbound; unvalidated (A-P1 / PR-14)
A5: Monthly growth of that | B5: 0.12 | C5: Unvalidated assumption
A6: Trial->paid % | B6: 0.14 | C6: Unvalidated assumption — the single most load-bearing number here
A7: ARPU $/mo | B7: 79 | C7: RE-ANCHORED 20/09: per-user tiers, ~$2.90-3.20/user/mo, at a mixed ICP of roughly 25-30 Jira users. Sub-10-seat sites are conceded as free acquisition and are NOT in this ARPU.
A8: Monthly churn | B8: 0.03 | C8: Unvalidated assumption
A9: Marketplace fee | B9: 0 | C9: CORRECTED (C-3): 0% until $1M lifetime Forge revenue. Was 0.17. Above $1M: 0.16 from 01/04/2026, 0.17 from 01/10/2026.
A10: Team cost month 1 (India-lean $) | B10: 20000 | C10: From Team_Roles_Budget (v004)
A11: Cost growth/mo | B11: 0.03
A13: Line | B13: M1 | C13: M2 | D13: M3 | E13: M4 | F13: M5 | G13: M6 | H13: M7 | I13: M8 | J13: M9 | K13: M10 | L13: M11 | M13: M12 | N13: M13 | O13: M14 | P13: M15 | Q13: M16 | R13: M17 | S13: M18
A14: Leads/installs | B14: =$B$4 | C14: =B14*(1+$B$5) | D14: =C14*(1+$B$5) | E14: =D14*(1+$B$5) | F14: =E14*(1+$B$5) | G14: =F14*(1+$B$5) | H14: =G14*(1+$B$5) | I14: =H14*(1+$B$5) | J14: =I14*(1+$B$5) | ... S14: =R14*(1+$B$5)
A15: New paying | B15: =ROUND(B14*$B$6,1) | C15: =ROUND(C14*$B$6,1) | D15: =ROUND(D14*$B$6,1) | E15: =ROUND(E14*$B$6,1) | F15: =ROUND(F14*$B$6,1) | G15: =ROUND(G14*$B$6,1) | H15: =ROUND(H14*$B$6,1) | I15: =ROUND(I14*$B$6,1) | ... S15: =ROUND(S14*$B$6,1)
A16: Paying accounts | B16: =B15 | C16: =ROUND(B16*(1-$B$8)+C15,1) | D16: =ROUND(C16*(1-$B$8)+D15,1) | E16: =ROUND(D16*(1-$B$8)+E15,1) | F16: =ROUND(E16*(1-$B$8)+F15,1) | G16: =ROUND(F16*(1-$B$8)+G15,1) | H16: =ROUND(G16*(1-$B$8)+H15,1) | I16: =ROUND(H16*(1-$B$8)+I15,1) | J16: =ROUND(I16*(1-$B$8)+J15,1) | ... S16: =ROUND(R16*(1-$B$8)+S15,1)
A17: MRR (net of fee) | B17: =ROUND(B16*$B$7*(1-$B$9),0) | C17: =ROUND(C16*$B$7*(1-$B$9),0) | D17: =ROUND(D16*$B$7*(1-$B$9),0) | E17: =ROUND(E16*$B$7*(1-$B$9),0) | F17: =ROUND(F16*$B$7*(1-$B$9),0) | G17: =ROUND(G16*$B$7*(1-$B$9),0) | H17: =ROUND(H16*$B$7*(1-$B$9),0) | I17: =ROUND(I16*$B$7*(1-$B$9),0) | ... S17: =ROUND(S16*$B$7*(1-$B$9),0)
A18: Team cost | B18: =$B$10 | C18: =ROUND(B18*(1+$B$11),0) | D18: =ROUND(C18*(1+$B$11),0) | E18: =ROUND(D18*(1+$B$11),0) | F18: =ROUND(E18*(1+$B$11),0) | G18: =ROUND(F18*(1+$B$11),0) | H18: =ROUND(G18*(1+$B$11),0) | I18: =ROUND(H18*(1+$B$11),0) | J18: =ROUND(I18*(1+$B$11),0) | ... S18: =ROUND(R18*(1+$B$11),0)
A19: Net cash/mo | B19: =B17-B18 | C19: =C17-C18 | D19: =D17-D18 | E19: =E17-E18 | F19: =F17-F18 | G19: =G17-G18 | H19: =H17-H18 | I19: =I17-I18 | ... S19: =S17-S18
A20: Cumulative | B20: =B19 | C20: =B20+C19 | D20: =C20+D19 | E20: =D20+E19 | F20: =E20+F19 | G20: =F20+G19 | H20: =G20+H19 | I20: =H20+I19 | J20: =I20+J19 | ... S20: =R20+S19
A22: Reading: churn applies before adds; MRR nets the marketplace fee, which is now ZERO until $1M lifetime Forge revenue (C-3). Breakeven = first month Net cash >= 0.
A23: BREAKEVEN IS NOT REACHED INSIDE THIS 18-MONTH HORIZON at these assumptions: M18 net cash is about -$12k/month against MRR of about $21k, on a team cost that starts at $20,000/month and compounds at 3%. The fee correction raised every MRR figure by ~20% and moved breakeven EARLIER, as the review said it would — it did not move it inside the window. Stating that plainly is the point of the correction; a model that showed breakeven here would be a model with the wrong team cost in it.
A24: The lever is not the fee. It is trial->paid (0.14) and ARPU: at a solo-build cost base rather than a $20k/month team, this model is cash-positive early. Whichever cost base is real should be put in B10 before this sheet is used for a decision.
A25: This is a planning model, not a forecast. Every assumption above is unvalidated — the review scored primary validation at zero and it is still zero until PR-14 produces design partners. Replace these with real beta actuals before quoting any of it.
A26: What the fee correction changed: at the same assumptions, every MRR figure is ~20% higher than the v034 model showed, because 17% of gross was being deducted that Atlassian does not take.

Sheet Review_PRX_V001
A1: EXTERNAL REVIEW V001 — Perplexity Computer, 16/09/2026. All five findings accepted and closed.
A2: The reviewer executed the shipped code from the lockfile and reproduced our CI independently before finding anything — the 426-test claim was the only one it found UNDERSTATED. Yellow = your decision.
A3: ID | B3: Severity | C3: Area | D3: Finding | E3: Disposition in code | F3: Senthil decision
A4: PRX-01 | B4: HIGH | C4: testgen / aiProvider | D4: Repeat generation creates duplicate case ids — the panel ships a "Generate more cases" button and ids are derived from the story key. importCases already solved this in the same file and the fix was not applied to the generation paths. | E4: ACCEPTED + FIXED — unique time-sortable ids on every creation path incl. AI, asserted at write by insert-if-absent; a shared counter was deliberately NOT used because it would itself have been a PRX-02 race. version + updatedAt added (EG-04 seed). | F4: None
A5: PRX-02 | B5: CRITICAL | C5: forgeStore + every collection writer | D5: Concurrent invocations silently lose writes: hydrate, mutate the whole collection, flush, last writer wins. Also drops audit entries and webhook replay ids — a security control, not just a feature. No gate could see it: concurrency is not a property of a path. | E5: ACCEPTED + FIXED — versioned values with compare-and-set, commutative reducers for ledgers and counters, one key per entity, conflicts surfaced as 409. New standing gate G-5 and lesson L-P8. | F5: Ratify: on KVS the CAS is emulated (no conditional write exists); Forge SQL has a real one and is built. D19 decides at PR-04.
A6: PRX-03 | B6: MED-HIGH | C6: permissions / LC-6 | D6: Project scope is recorded, never enforced — LC-6 published as "Done-in-code — scope-aware guard" when the guard only logged. On a site with a restricted project, any licensed member saw everything. | E6: ACCEPTED + FIXED — scope is part of the decision, checked against Jira BROWSE_PROJECTS asUser and failing closed. LC-6 downgraded to Open as instructed; it flips only with live evidence. | F6: None — but read the LC-6 row before quoting any status externally.
A7: PRX-04 | B7: MED | C7: flaky / ledger | D7: One noisy test evicts every real flaky signal: one FIFO ledger was both the storage cap and the analysis window, so the headline analytic degraded to noise at exactly the volume that made it valuable. | E7: ACCEPTED + FIXED — per-run storage under a bounded 50-run index and per-test, per-branch scoring windows. Supported CI throughput is now published. | F7: Ratify the 50-run retention default (it is the retention policy in practice).
A8: PRX-05 | B8: MED | C8: forgeGlue / forgeStore | D8: Every invocation loads the entire tenant; PERF-04 removed the multiplier, not the linearity. | E8: ACCEPTED + FIXED — per-call declared storage scopes, enforced by throwing on an undeclared read. whoami loads 2 keys. Closes OBS-TP1. | F8: None — the replacement cost (round trips per listing) is published in the envelope.
A9: TOTAL | B9: Findings accepted | C9: =COUNTA(A4:A8) | D9: Critical/High closed | E9: =COUNTIF(B4:B8,"CRITICAL")+COUNTIF(B4:B8,"HIGH") | F9: All fixed with pinned regressions

Sheet Corrections_Applied
A1: ARTIFACT CORRECTIONS C-1..C-7 — applied 20/09
A2: Two of these made a published status WORSE. That is the point of them.
A3: ID | B3: Artifact | C3: Correction | D3: Applied | E3: Status
A4: C-1 | B4: tracker LC-6 | C4: "Done-in-code — scope-aware guard" -> OPEN; scope was logged, not enforced | D4: LC-6 Open in tracker v028. Enforcement shipped (PR-09) but the row waits for live evidence. | E4: APPLIED
A5: C-2 | B5: cloud-fortified-gap.md, LC-3 | C5: Programme closed 01/09/2026, retires 31/12/2026. Retarget to Atlassian Enterprise Certified; LC-3 -> OPEN | D5: File deleted; docs/enterprise-certified-gap.md written against AEC row by row. LC-3 Open. Pen test + bug bounty marked as procurement. | E5: APPLIED
A6: C-3 | B6: Financial_Model B9 | C6: Fee 0.17 -> 0.00 until $1M lifetime Forge revenue; restate breakeven | D6: Fee = 0%; MRR ~20% higher across the horizon; the pricing anchor is re-derived on it. | E6: APPLIED
A7: C-4 | B7: RAID R-P2 | C7: "Xray/Zephyr respond with AI" Open -> MATERIALISED; rewrite the differentiation claim | D7: R-P2 Materialised; ReadMe_Scope rewritten around the release decision rather than AI generation. | E7: APPLIED
A8: C-5 | B8: runs-on-atlassian-assessment.md | C8: The badge no longer changes revenue share; it is a trust signal — which strengthens Option B | D8: Section added; Decision 2 adopted as Option B with the better reason. | E8: APPLIED
A9: C-6 | B9: Scale_Envelope / performance-envelope.md | C9: The flaky cap is also the analysis window; publish a supported CI-throughput figure | D9: Envelope re-baselined; throughput published (20,000/run, 1 MiB/post, last 50 runs) plus the round-trip costs that replaced the row ceilings. | E9: APPLIED
A10: C-7 | B10: package.json | C10: Move express to devDependencies | D10: Done; production dependencies are now empty and the harness refuses to start in production. | E10: APPLIED

Sheet Review_Decisions
A1: THE SIX DECISIONS — the reviewer's recommendation, and where each one now stands
A2: Yellow = still yours. Decisions 2, 3 and 4 are effectively settled by what shipped; 1, 5 and 6 are actions only you can take.
A3: # | B3: Decision | C3: Reviewer recommendation | D3: Where it stands after 20/09 | E3: Still open?
A4: 1 | B4: Run LC-1 (live install) | C4: DO IT THIS WEEK, before any further code. ~45 minutes, unblocks 15 stories and every scale and latency number. | D4: Still the single highest-return action in the pack, and now it also carries four new questions: extension.project.key, the restricted-project denial that flips LC-6, a real CI post, and the two wall-time figures that decide Forge SQL (D19). Everything that could be prepared for it is prepared. | E4: YES — Senthil, ~45 min
A5: 2 | B5: Runs on Atlassian badge vs AI | C5: KEEP AI (Option B). The badge no longer carries the revenue incentive; the enterprise bar is AEC, which wants egress transparency not zero egress. | D5: ADOPTED. The assessment carries the revenue-share correction (C-5), and the off-by-default posture is now named on the trust page as "no-egress mode" — the reviewer's own suggestion. No second major version was built. | E5: Settled unless a design partner is contractually blocked
A6: 3 | B6: AI on or off at launch | C6: OFF by default with a prominent in-panel enable prompt, plus BYO key. | D6: ADOPTED and gone further: off by default, BYO key in Forge Secret Storage, a monthly ceiling on the shared key so vendor COGS cannot run away, per-tenant cost attribution, and injection hardening. The "weaker demo" problem is now an activation-design problem, as the reviewer framed it. | E6: Settled
A7: 4 | B7: Positioning: Release Quality Intelligence | C7: ADOPT IT — but only after PR-05, because today the two heaviest inputs are typed in by hand. | D7: EARNED. PR-05 shipped: every factor derived from Jira, CI results or recorded executions, each naming its source, with an attributed override. ReadMe_Scope and the trust page are rewritten around it. The listing copy still describes a test-case manager and is the remaining edit. | E7: Listing copy rewrite — Senthil
A8: 5 | B8: Roadmap scope (E01-E29) | C8: 14 sprints per the plan; cuts per V002_Cuts. If you fund only three: PR-01, PR-04, PR-05. | D8: ADOPTED. PR-01 and PR-05 are done — two of the reviewer's three. PR-04 is the third and is yours. PR-02/03/06/07/08/09/10/11 are also done; PR-12/13/14 need live infrastructure, a purchase and people. | E8: Only the four that need you
A9: 6 | B9: D18 per-user pricing | C9: Per-user tiers, 40-50% under Xray in the 50-200 band; concede or give away sub-25 seats. Correct the 17% fee to 0% first. | D9: Fee corrected (C-3) and the anchor table written band by band, conceding sub-10 as free acquisition — at 10 seats we were 12x Xray. Partner-console tiers and the test purchase are yours (PR-13). | E9: YES — Senthil, ~1 hour + console

Sheet V002_Enterprise_Gates
A1: ENTERPRISE GATES — re-scored 20/09 against the code that now exists
A2: Two columns of history kept so the movement is visible. A gate only moves on evidence, and EG-10/EG-15 deliberately do not move.
A3: Gate | B3: Mandatory condition | C3: V002 | D3: 13/09 | E3: 20/09 | F3: Evidence / why not
A4: EG-01 Runtime truth | B4: No headline feature exists only in seams; no false UI/docs | C4: FAIL | D4: PASS | E4: PASS | F4: Holds. The claims gate now checks 42 claims, and the two statuses this review caught (LC-6, LC-3) were corrected downwards rather than defended.
A5: EG-02 Least privilege | B5: Every scope and egress domain has a live justified call path | C5: FAIL | D5: PASS | E5: PASS | F5: read:jira-work now justifies four named call paths and the gate requires each; still no write scope, and re-adding it is an explicit decision (D-TP-WB).
A6: EG-03 Data rights | B6: Export/delete/reset preserve valid authorization semantics | C6: FAIL | D6: PASS | E6: PASS | F6: Extended: conn:, ai:, trace: and proj: namespaces were unregistered and are now covered (F-TP46, found while absorbing this review); a tenant AI key is deleted with the data.
A7: EG-04 Test domain | B7: Versioned tests/plans/cycles/executions/environments | C7: PARTIAL | D7: PARTIAL | E7: PARTIAL | F7: MOVED WITHIN PARTIAL: cases now carry version + updatedAt with optimistic concurrency, and runs are first-class entities with branch and actor. Plans, cycles and environments as entities are still not built, so the gate does not move.
A8: EG-05 Traceability | B8: Requirement->test->execution->defect->release queryable | C8: MISSING | D8: MISSING | E8: PARTIAL | F8: BUILT (PR-08): the graph, both gap reports, and coverage per epic/release from a live Jira search. PARTIAL not PASS because writing links back INTO Jira needs write:jira-work, which is a deliberate open decision (D-TP-WB).
A9: EG-06 Automation | B9: Main result formats + CI integrations production supported | C9: MISSING | D9: MISSING | E9: PARTIAL | F9: BUILT (PR-06): JUnit XML, Playwright JSON and Cucumber JSON against committed real-shape fixtures, idempotent, size-capped, health-surfaced. PARTIAL not PASS because no real pipeline has posted to a real install yet — that is PR-04.
A10: EG-07 Release governance | B10: Explainable configurable gates, approvals, waivers | C10: PARTIAL | D10: PARTIAL | E10: PARTIAL | F10: MOVED WITHIN PARTIAL: the score is explainable per factor with its source, configurable per project, and the waiver (override) is attributed and labelled. Approvals as a workflow are still not built.
A11: EG-08 AI governance | B11: Production AI + evals + privacy/egress controls + fallback | C11: FAIL | D11: PASS* | E11: PASS* | F11: Still PASS with the SAME named gap, deliberately: BYOK, injection hardening, cost attribution, monthly ceiling and multi-model fallback were added, but the evals still test the product's handling of model output, not model QUALITY — which needs real stories from real teams (PR-14).
A12: EG-09 RBAC/audit | B12: Granular permissions and privileged-action audit | C12: PARTIAL | D12: PARTIAL | E12: PARTIAL | F12: MOVED WITHIN PARTIAL and the reason is a correction, not a boast: scope was previously LOGGED and is now ENFORCED against Jira visibility (PRX-03), with the project dimension and denial reasons on the audit log. Enterprise governance (groups, delegation) is still E10/E11.
A13: EG-10 Scale | B13: Published supported scale with p95/p99, no unbounded scans | C13: UNPROVEN | D13: PARTIAL | E13: PARTIAL | F13: DOES NOT MOVE. The per-value ceiling and the unbounded hydrate are both gone and 50,000 cases / 100,000 results are asserted — but an in-process p95 is not a production p95, and the envelope says so about itself. PASS needs PR-12 on live infrastructure.
A14: EG-11 Operations | B14: SLOs, diagnostics, alerts, runbooks, recovery evidence | C14: PARTIAL | D14: PARTIAL | E14: PARTIAL | F14: Connector health, status report and runbook exist; the alerting path (who is paged) is still not wired, and is recorded as partial rather than quietly counted.
... A18: EG-15 PMF evidence | B18: Multiple external teams using it for real release decisions | C18: UNPROVEN | D18: UNPROVEN | E18: UNPROVEN | F18: DOES NOT MOVE, and cannot. The reviewer's bar — three teams making a documented go/no-go call using the readiness score — is unaffected by any amount of code. PR-14.
A19: ROLLUP | B19: Gates at PASS (incl. PASS with a named gap) | C19: =COUNTIF(C4:C18,"PASS") | D19: =COUNTIF(D4:D18,"PASS")+COUNTIF(D4:D18,"PASS~*") | E19: =COUNTIF(E4:E18,"PASS")+COUNTIF(E4:E18,"PASS~*") | F19: Two MISSING became PARTIAL (EG-05, EG-06) and four PARTIALs moved within PARTIAL. NOTHING was moved to PASS on this pass: the two gates that could only move with live evidence (EG-10, EG-15) did not move, which is the point.

Sheet Scorecard
A1: ENTERPRISE-GRADE SCORECARD — the reviewer's independent scoring, and what moved
A2: The 20/09 column is our own assessment against the reviewer's stated basis. We do not get to re-score ourselves on operational evidence, and we have not.
A3: Dimension | B3: V001 (16/09) | C3: After 20/09 | D3: The reviewer's basis, and what changed
A4: Engineering discipline | B4: 9 | C4: 9 | D4: Was already top-decile and independently verified. Held through a storage re-platform: 55 suites / 530 tests / 100% x4, zero pragmas, seven gates, clean-room reproducible. Not claimed higher — it was 9 because of what it cannot see, and G-5 is the honest response to that.
A5: Truthfulness of artifacts | B5: 8 | C5: 9 | D5: Docked originally for LC-6 overstatement and the Cloud Fortified/fee corrections. All three corrected, two of them DOWNWARDS, and the corrections sheet records them. The claims gate grew from 29 to 42 pinned claims.
A6: Security controls | B6: 7 | C6: 8 | D6: Docked for the wh:seen FIFO (a replay id could age out), no CI payload cap, and express in production dependencies. All three fixed: one dedupe key per event id, 1 MiB/20,000-result caps with a 413, express dev-only and the harness refusing production. Added: project isolation, injection hardening, no credential storage.
A7: Capability depth | B7: 3 | C7: 5 | D7: Was 3 because EG-04 PARTIAL, EG-05 MISSING, EG-06 MISSING. Traceability and automation ingest are now built (both PARTIAL), and EG-04 has its versioned-entity seed. Still not 7+: plans, cycles and environments as first-class entities do not exist, so it still sits beside an incumbent rather than replacing one.
A8: Scale | B8: 2 | C8: 5 | D8: "THE DISQUALIFIER, and a data-model problem, not a tuning problem." The data model changed: 50,000 cases and 100,000 CI results are asserted with no value near the ceiling, and hydration is prefix-scoped. Not higher, because the cost that replaced the ceiling (round trips per listing) is real, published, and unmeasured on live infrastructure.
A9: Correctness under real use | B9: 3 | C9: 7 | D9: Was 3 for PRX-02 — multi-user write loss in a multi-user product. Closed with versioned CAS, commutative merges and per-entity keys, plus a standing gate for the class. Not higher, because on KVS the CAS is emulated and the real proof is concurrent tenants on a live site.
A10: Operational evidence | B10: 1 | C10: 1 | D10: DOES NOT MOVE. Nothing has still ever run on a real Jira site: no production p95, no cold start, no KVS latency, no concurrent-tenant behaviour, no forge eligibility output. Everything in this release is still verified against documentation and tests. This is PR-04 and no code can change it.
A11: Enterprise programme readiness | B11: 2 | C11: 4 | D11: Was 2 because the Cloud Fortified plan was void. Now assessed against Atlassian Enterprise Certified with the engineering rows met and pinned. Not higher, because the two rows that gate the programme — an accredited penetration test and a public bug bounty — are procurement items that have not started.
A12: OVERALL | B12: 4.5 | C12: 5.6 | D12: Our own arithmetic on the reviewer's basis, offered as a working number rather than a claim. The honest reading: the CODE moved a long way, the EVIDENCE did not move at all, and the reviewer would be entitled to hold the overall score at its old value until something has run on a real site.

Sheet Scale_Envelope
A1: SUPPORTED SCALE — re-baselined 20/09 after the storage re-platform (PR-03)
A2: The old ceilings were ROW COUNTS because whole collections lived in single values. They are gone. What replaced them is a round-trip cost per listing, published here rather than discovered later.
A3: What | B3: Before (13/09) | C3: Now (20/09) | D3: Guard
A4: Test cases per site | B4: gen:cases 4,693 KiB at 50,000 — 19.6x over the 240 KiB ceiling; supported ~1,500-2,900 | C4: One key per case; 50,000 asserted, largest value under 2 KiB. No row ceiling. | D4: test/performance.test.ts
A5: Runs per board | B5: One value per board; supported ~5,000 | C5: One key per run; a 5,000-run board asserted, largest value under 1 KiB. | D5: test/performance.test.ts
A6: CI results | B6: One 10,000-entry / 200 KiB FIFO — which was ALSO the analysis window (PRX-04) | C6: Per-run chunks under a bounded index: 20,000 results per run, 1 MiB per post, last 50 runs retained per site (settable 5..500). | D6: test/performance.test.ts, test/ciReports.test.ts
A7: Flaky analysis window | B7: Whatever fitted in the ledger — one or two runs on a real suite | C7: Last 30 results per test PER BRANCH. A flaky test survives 12,000 unrelated stable results. | D7: test/performance.test.ts PRX-04 scenario
A8: Per-invocation load | B8: Every key in the installation, every invocation (OBS-TP1 / PRX-05) | C8: Only the declared prefixes; an undeclared read throws. whoami loads 2 keys. | D8: test/performance.test.ts
A9: NEW COST: listing round trips | B9: n/a — a collection was one read | C9: One story = 1 round trip (the hot path). A 50,000-case site-wide listing = 500. A 10,000-run board = 102. | D9: Published in docs/performance-envelope.md; measured live at PR-04/PR-12
A10: Ledgers (audit, notifications, latency, AI audit) | B10: Byte-capped FIFO (PERF-01) | C10: Unchanged in shape and now COMMUTATIVE, so concurrent writers cannot drop an entry. | D10: test/concurrency.test.ts
A11: Not measured | B11: KVS latency, 25s timeout, cold start, concurrent tenants | C11: STILL NOT MEASURED. An in-process p95 is not a production p95 and this document does not pretend otherwise. | D11: PR-04 then PR-12

Sheet Launch_Checklist
A1: PLATFORM LAUNCH CHECKLIST — Atlassian Marketplace
A2: # | B2: Item | C2: Status
A3: 1 | B3: Marketplace vendor account + Forge app registered | C3: Open — FULL STACK ready: UI bundle + handlers + adapter + manifest + guide; only ► steps remain
A4: 2 | B4: Forge app review pack: scopes, egress allowlist, storage use documented | C4: Doc-complete — review pack ready (docs/review-pack.md)
A5: 3 | B5: Enterprise programme gap assessment with target date (was: Cloud Fortified) | C5: OPEN — CORRECTED 20/09 (C-2). Cloud Fortified closed to new submissions 01/09/2026 and retires 31/12/2026, so the previous "no structural gaps, apply at listing+60d" assessment measured a bar that no longer exists. Replaced by docs/enterprise-certified-gap.md against Atlassian Enterprise Certified: engineering rows met and pinned, but AEC 1.1 (CREST/Bugcrowd penetration test) and AEC 1.2 (public bug bounty) are procurement items with lead times and the programme cannot be applied for until they are done.
A6: 4 | B6: Data residency: Forge hosted storage regions statement | C6: Doc-complete — residency statement ready for trust tab
A7: 5 | B7: Xray/Zephyr importer tested on 3 real export files | C7: Open — importer format-faithful (Xray Exporter multi-step, Zephyr Scale, RFC-4180); 3 REAL files = acceptance evidence
A8: 6 | B8: Jira permission schemes respected (project vs global) verified | C8: OPEN — CORRECTED 20/09 (C-1/PRX-03). Was "Done-in-code — scope-aware permission guard"; the guard LOGGED scope and never enforced it, so any licensed member could see every project. Enforcement now shipped (PR-09: BROWSE_PROJECTS via asUser, failing closed, project dimension on the audit log). The row stays OPEN until the live restricted-project capture at PR-04 — "fixed in code" is exactly what was being corrected.
A9: 7 | B9: Marketplace listing: highlights, 5 screenshots, demo video per guidelines | C9: In progress — spec now submission-accurate (verified Rule-of-3, 1840x900); draft layout review via demo.html; capture at LC-1
A10: 8 | B10: Pricing: per-user tiers via Atlassian billing configured and test-purchased | C10: In progress — licensing flag + gate shipped+tested; D18 per-user price decision, partner-console setup + test purchase = Senthil
A11: 9 | B11: Performance: panel load <1s p75 on 10k-issue projects | C11: In progress — the in-process envelope is re-baselined against the per-entity store and publishes ROUND-TRIP COUNTS, which is the figure live latency multiplies. The old 28ms p95 is NOT cited as progress here: it was measured against the Express test harness, which C-7 made dev-only and unable to start in production. Live Forge panel p75 on a 10k-issue project at PR-04.
A12: 10 | B12: Support docs + SLA statement on listing trust tab | C12: In progress — trust page + SLA + 15 articles shipped

Sheet Review_Findings
A1: COLD REVIEW PASSES 1-8 — internal findings (carried)
A2: ID | B2: Severity | C2: Module | D2: Defect / observation | E2: Disposition in code | F2: Senthil decision
A3: F-TP01 | B3: High | C3: compliance.ts | D3: delete-my-data / export-my-data matched key.includes(cloudId): test cases, run boards, CI results, audit log, notifications, telemetry, support tickets and latency samples were neither exported nor deleted — breaches trust page, HC-11/HC-12 and residency statement. Empty cloudId matched every key. | E3: FIXED — tenantData.ts namespace registry drives export + delete + retention sweep; exact-segment tenant match; empty cloudId rejected; drift test asserts no unclassified key after a full tenant flow | F3: Confirm the registry is the contract: any future module must register its namespace or the build fails
A4: F-TP02 | B4: High | C4: lifecycle.ts | D4: 30-day retention sweep purged only acct: — all other tenant data survived indefinitely against a published "then hard delete" policy | E4: FIXED — sweep delegates to purgeTenant; regression asserts an empty store after expiry | F4: None — but this is the claim a Marketplace security reviewer is most likely to test
A5: F-TP03 | B5: High | C5: ui/viewmodel.ts, ui/mount.ts | D5: Panel read `score` from flaky rows; resolver returns `flipRate`. The live flaky tab would have shown "NaN%" on every row. jsdom tests passed because they hand-built the view-model input. | E5: FIXED — flakyVM typed against the real FlakyScore; demo.html re-verified headless (67%/21%, no NaN) | F5: None — but it is why draft screenshots must come from demo.html, not from hand-built fixtures
A6: F-TP04 | B6: High | C6: ui/mount.ts, readiness.ts | D6: Readiness tab invoked `readiness` with an empty payload -> NaN score rendered as NOT-READY. readinessScore validated only coveragePct, so runPassRate=5 scored above 100. | E6: FIXED — new readinessSummary resolver call derives inputs from boards + flaky scores; all four inputs range-validated | F6: Decide who supplies coveragePct and openP0Defects live: owner-entered ready:settings today, or read from a CI coverage feed later
A7: F-TP05 | B7: High | C7: forgeStore.ts, forgeGlue.ts | D7: Writes issued eagerly, awaited only at flush(). A throwing handler never reached flush — floating promises, unhandled rejection able to tear down the invocation, writes that may not settle; a rejected write left the cache claiming success. | E7: FIXED — write failures captured, StoreWriteError raised at flush, glue flushes on success and error paths | F7: None
A8: F-TP06 | B8: High | C8: webhooks, permissions, flaky, notifications, ops | D8: Five unbounded ledgers (wh:seen, audit, fl:results, ntf:log, lat:*). Forge caps single-value size, so these eventually hard-fail every write; p95 was computed over all history. | E8: FIXED — shared appendCapped FIFO with persisted drop counters; latency on a 1000-sample rolling window | F8: Ratify the caps (10k events, 1k latency samples) — they are the retention policy in practice
A9: F-TP07 | B9: Med-High | C9: flaky.ts | D9: setThreshold wrote an instance field; every Forge invocation builds a new detector, so the ST-023 custom threshold was silently discarded in production. Tests reused one instance and passed. | E9: FIXED — threshold persisted to fl:threshold; regression constructs a second detector as the resolver does | F9: None
A10: F-TP08 | B10: Med-High | C10: jiraClient.ts | D10: retryAfter slept as milliseconds; HTTP Retry-After is SECONDS. Jira asking for 60s got 60ms — a retry storm straight back into the rate limiter. | E10: FIXED — renamed retryAfterSeconds, converted, both backoff paths capped at 60s | F10: None
A11: F-TP09 | B11: Med-High | C11: ops.ts | D11: restore() wiped every key before validating the snapshot: a parseable-but-wrong snapshot (null, [], 3) destroyed all data then threw. The restore drill was itself a data-loss path. | E11: FIXED — snapshot shape validated before the wipe | F11: None
A12: F-TP10 | B12: Med | C12: runboards.ts | D12: Board ids derived from key count: creating a board after deleting one silently overwrote an existing board; concurrent invocations collided. | E12: FIXED — monotonic persisted rb:seq | F12: None
A13: F-TP11 | B13: Med | C13: runboards.ts, testgen.ts | D13: Naive split(","): every row of a CRLF export (Excel/Jira on Windows) failed, quoted commas mis-parsed, a bad row midway left earlier rows persisted, import ids restarted at I1 and collided. | E13: FIXED — both importers use the shared RFC-4180 parser, validate whole file then apply; import sequence persisted | F13: Feeds LC-5: the 3 real Xray/Zephyr exports will now exercise the same parser the importer uses
... A19: OBS-TP4 | B19: Med | C19: billing.ts | D19: No payment-recovery path (a tenant who fixes their card stays read-only forever) and trial expiry never enforced (perpetual free access). Both are live defects in the sibling products. | E19: NOT FIXED — inert for this channel: Atlassian owns purchase/trial/proration/dunning under Paid-via-Atlassian and the app only reads license state | F19: DECISION: take the fix if and when a direct sales channel is switched on, not before
A20: COLD REVIEW PASS 2 + VERIFICATION SWEEP (13/09/2026 09:52) — artifacts checked against live Atlassian docs, not just code against itself.
A21: VER-P01 | B21: Live-blocking | C21: forge/index.ts | D21: The Forge entrypoint was five commented-out lines: `forge deploy` would have registered handlers index.resolver / index.ciWebhook that do not exist, so every panel invocation and CI webhook failed in the installed app. The shape was also wrong — Forge resolvers are resolver.define(key,({payload,context})) + getDefinitions(), and invoke(functionKey,payload) matches the DEFINITION KEY, never our single resolver({call,...}) function. | E21: FIXED — src/forgeAdapter.ts builds one definition per call; forge/index.ts is real code compiling against the real @forge/resolver, @forge/kvs, @forge/api; new CI gate npm run typecheck:forge | F21: None — but note LC-1 would have failed at the first panel click before this pass
A22: VER-P02 | B22: Live-blocking | C22: static/build/index.html, static/entry.ts | D22: The Custom UI page loaded the bundle and then called nothing (empty #root, bridge wiring commented out), and the bundle contained no @forge/bridge at all (3.7kb before vs 96.7kb after). The generate tab also demanded storyText, which an issue panel never has — it knows only the issue key. | E22: FIXED — real boot()/bootForge() with an error surface; bridge bundled; story text fetched server-side via env.fetchStory (read:jira-work already held); demo page split into its own bridge-free bundle because @forge/bridge refuses to initialise outside an Atlassian product | F22: None — demo.html screenshots still work, now from demo.js
A23: VER-P03 | B23: High | C23: licensing.ts | D23: Forge resolver context carries LicenseDetails { active, isEvaluation }; the gate expected { active, evaluation }, so a trialling customer would never have seen the evaluation banner. | E23: FIXED — mapLicense() in the adapter, pinned to the documented shape | F23: None
A24: F-TP14 | B24: High (security) | C24: forgeGlue.ts | D24: The permission role arrived in the request context — i.e. from the caller. Forge context is trustworthy but has no app role, so any adapter had to invent one: a member could invoke as owner and delete tenant data. | E24: FIXED — src/roles.ts derives role server-side (assignment > installing account > Jira site admin > member); assignRole is owner-only; regression proves a role:owner payload is ignored | F24: DECISION: role model — today admin = Jira ADMINISTER and installer = owner. A different mapping (project lead, explicit assignment only) is a product call
A25: F-TP15 | B25: High (security) | C25: webhooks.ts | D25: One app-wide signing secret shared by every installation, while HC-05 told customers to copy it "from Settings" — a screen that could not exist because no per-tenant secret did. | E25: FIXED — per-installation secret provisioned at install, owner-only read + rotate (rotation clears the replay ledger); env value kept only as fallback for earlier installs | F25: Panel needs a Settings > CI screen surfacing webhookSecret before listing (UI work, ~half a day)
A26: F-TP16 | B26: High | C26: testgen.ts, aiProvider.ts | D26: AnthropicProvider was shipped behind the AI seam and NEVER CALLED — generate always ran the rule engine, so AI generation was inert in production even with ANTHROPIC_API_KEY set, and R-P6 was reported cleared on an unreachable class. | E26: FIXED — generateWithAi uses the provider, holds its output to the same rules (kind filters + maxCases), persists it, and falls back to rules on failure with a counter | F26: Confirm whether AI generation ships ON at launch (cost per install) or behind an owner toggle
A27: F-TP17 | B27: Med-High | C27: xrayImport.ts | D27: The importer parsed Xray multi-step rows — the reason the module exists — then round-tripped through a 3-column CSV, so every imported case landed with EMPTY steps. | E27: FIXED — TestGen.importCases keeps steps and kinds, atomic and id-unique | F27: Feeds LC-5: the 3 real export files now prove the whole path, not just the parser
A28: F-TP18 | B28: Med-High | C28: onboarding.ts | D28: Demo mode wrote three inert marker records no feature reads, so ST-083/HC-15 "explore with seeded sample data" showed an empty product. | E28: FIXED — seeds real cases, a real board with runs and real flaky history; records exactly what it created and removes exactly that on disable | F28: None
A29: F-TP19 | B29: Med | C29: helpcenter.ts | D29: Three articles promised behaviour the product lacks: a "skip" run status RunStatus never defined, a billing flow superseded by Paid-via-Atlassian (GST/VAT invoices from the retired engine), and the non-existent CI Settings screen. | E29: FIXED — articles corrected; tests pin each claim to the code implementing it | F29: Listing copy + pricing FAQ still carry the flat $99/$299 anchor — blocked on D18
A30: F-TP20 | B30: Low | C30: billing.ts | D30: Exit-survey ledger unbounded — the one pass 1 missed. | E30: FIXED — FIFO-capped like the rest | F30: None
A31: L-P1 | B31: Lesson | C31: portfolio | D31: A 100%-covered codebase can be undeployable: nothing in a Jest suite loads the file the platform loads. Same class as VoiceBridge VER-V01 (opencti_min.js never loaded) — twice now, so it is a pattern. | E31: Entrypoint type-check against the real vendor packages is now a CI gate here | F31: DECISION: port the same gate to the other 10 products
A32: L-P2 | B32: Lesson | C32: portfolio | D32: A seam is not a feature. Shipping AnthropicProvider closed R-P6 on paper while nothing called it. | E32: Report a seam closed only when a test drives the real path end to end | F32: None
A33: L-P3 | B33: Lesson | C33: portfolio | D33: Authorization inputs must be named: `role` looked like context and was actually caller input. | E33: For every field used in an authorization decision, record where it comes from and who can set it | F33: None
A34: COLD REVIEW PASS 3 — REACHABILITY (13/09/2026 10:24): what ships but cannot be reached by anyone in the installed app.
A35: F-TP21 | B35: High | C35: compliance.ts | D35: exportMyData/deleteMyData had NO resolver call — the self-serve export and deletion promised by HC-12, the trust page, the residency statement and the Cloud Fortified gap assessment were unreachable in the installed app. Pass 1 fixed the correctness of a feature nobody could invoke. | E35: FIXED — owner-only exportMyData + deleteMyData (deletion requires typing the site id), both EXEMPT from the license gate so data rights survive an inactive license | F35: None — this is the claim a Marketplace security reviewer tests first
A36: F-TP22 | B36: High | C36: lifecycle.ts, manifest | D36: sweepDeletions() was scheduled NOWHERE: the manifest had no scheduledTrigger, so the published "30 days post-uninstall, then hard delete" never ran in production. | E36: FIXED — daily scheduledTrigger (syntax verified live: key+function+interval, <=5 per app, duplicate delivery possible so the handler is idempotent), makeScheduledSweep adapter, retentionSweep exported from the entrypoint | F36: Confirm daily is the right interval (hour/day/week available)
A37: F-TP23 | B37: High | C37: testgen/flaky/runboards | D37: Every customisation and pause story (ST-003/008/018/023/028) was library-only — a customer could not change a generation rule, a flaky threshold, or pause anything. | E37: FIXED — settings/setSettings resolver calls (members read-only) plus a real Settings screen | F37: None
A38: F-TP24 | B38: High | C38: notifications.ts | D38: Notification preferences (ST-010/020/030/040/050, HC-13) had no surface, and nothing in the Forge path ever called notify() — no notification was raised in the installed app at all. Only the REST smoke harness did. | E38: FIXED — notify wired into generate/recordRun/importXray, preferences editable in Settings, notifications call returns the recent log | F38: Email channel still has no provider — in-app only until one is chosen
A39: F-TP25 | B39: Med-High | C39: telemetry.ts | D39: trackError had no caller, so the error-spike alert (ST-072/ST-077) could never fire. | E39: FIXED — every failed invocation records resolver:<call>, on a separate store write so telemetry cannot mask the original error | F39: Alert delivery (where does a spike go?) is an ops decision
A40: F-TP26 | B40: Med | C40: support.ts | D40: ST-081 in-app support intake and the SLA report were unreachable. | E40: FIXED — supportOpen (exempt from the license gate) + admin-only supportTickets | F40: D-P1 equivalent: in-app chat vendor vs built-in intake is still open
A41: F-TP27 | B41: Med | C41: ops.ts | D41: LatencyMonitor was only called by the load harness, so the p95 budgets (ST-087) had no production data, and statusPage had no surface. | E41: FIXED — every panel-facing call is measured against its budget surface inside the same invocation (a fire-and-forget write races the next read and loses samples); statusReport returns status + per-surface p95 | F41: None
A42: F-TP28 | B42: Med-High | C42: ui/mount.ts | D42: The panel rendered HTML and bound nothing — no control in the product did anything. Four read-only tabs, no way to act. | E42: FIXED — delegated action binding (data-action/data-field), failures shown on screen instead of swallowed, state re-read after each success | F42: Settings screen is now listing-screenshot material (asset capture)
A43: F-TP19b | B43: Med | C43: helpcenter.ts | D43: HC-03 promised admins could "add, reorder or disable generation rules per workflow" — rules are three toggles and a cap, with no ordering. | E43: FIXED — article rewritten to the controls the screen renders, pinned by a test that greps the rendered HTML for each data-field | F43: None
A44: L-P4 | B44: Lesson | C44: portfolio | D44: A module with no caller is not a feature, and a test suite cannot tell the difference: several of these had 100% branch coverage of behaviour no user could trigger. Third distinct "passes its tests, cannot work" class in this product after L-P1 (undeployable entrypoint) and L-P2 (unwired seam). | E44: Standing check proposed: list every exported capability and name the resolver call, trigger or control that reaches it; an empty column is scope to cut or a feature to finish | F44: DECISION: run the same reachability audit across the other 10 products
A45: COLD REVIEW PASS 4 — CLAIMS (13/09/2026 10:37): the 13 published documents vs what the code now does.
A46: F-TP30 | B46: High | C46: jiraClient.ts, forge/index.ts | D46: ST-070 backoff/jitter/circuit-breaker only wrapped an injected http function that nothing in the Forge path used: the entrypoint's two live Jira calls (story fetch, admin check) went straight out with no retry and no breaker — while the security assessment claimed rate-limit resilience as a verified control. | E46: FIXED — JiraClient.run(label, op) applies the policy to any operation including a route tagged-template call; both entrypoint calls share one client; Retry-After read from the response header (seconds, capped) | F46: None
A47: F-TP31 | B47: Med-High | C47: ops.ts | D47: Cloud Fortified "Backup/recovery: DONE (drill)" rested on BackupOps.drill(), which had no caller and is destructive by design (it restores over live data), so it could never be exposed to a tenant. | E47: FIXED — non-destructive verify() (keys, bytes, content digest) reported via statusReport; the destructive drill is documented as a staging tool | F47: Re-run the destructive drill against live Forge storage at LC-1
A48: F-TP32 | B48: Med-High | C48: compliance.ts, CI | D48: The trust page claimed the encryption posture was "asserted by config check in CI". verifyEncryptionPosture had tests and no runner — the assertion was never made anywhere. | E48: FIXED — scripts/check-posture.js wired as npm run check:posture in CI: fails on TLS disabled, fails at deploy without a bound KMS key | F48: B-18 KMS binding at deploy remains Senthil-side
A49: F-TP33 | B49: Med | C49: trust-page, submission-dry-run, security-assessment, wcag-checklist | D49: Four false published statements: an EMAIL SUBPROCESSOR the app has no integration for and no egress permission to reach; the listing-asset row still citing the old 5-shot spec v006 had already corrected to the Rule-of-3; an authorization description written from the Express harness (x-tp-role header) rather than the product's server-derived roles; and a WCAG checklist deferring the automated pass because "there is no UI". | E49: FIXED — all four corrected, each pinned by a test that greps the document against the code | F49: Trust page + security assessment are customer-facing: worth a read before listing
A50: F-TP29 | B50: Med | C50: ui/render.ts | D50: The flaky table shipped an unnamed column header (axe: empty-table-header) — a screen-reader user got an unlabelled column. Found by the new automated a11y pass on its first run. | E50: FIXED — caption plus named, scoped headers | F50: None
A51: ST-089 | B51: Progress | C51: test/a11y.test.ts | D51: The WCAG automated audit was deferred to LC-1 on the grounds that there was no UI to audit; pass 3 gave the panel real controls. | E51: SHIPPED — axe-core over all five panels + empty states on every build | F51: Manual keyboard/NVDA + contrast in the live iframe remain the only LC-1 a11y items
A52: L-P5 | B52: Lesson | C52: portfolio | D52: A document is an assertion about the code and should be tested like one. Every false claim here was true when written; the product moved and the documents did not. | E52: Mechanical claims (no email subprocessor, asset spec, server-derived roles, a11y pass runs) are pinned by five-line tests that fail the build when doc and code diverge | F52: DECISION: adopt doc-pinning tests across the portfolio; untestable claims (SLA, pen-test) need a named owner and date
A53: PASS 5 — REVIEW GATES (13/09/2026 10:44): the standing checks, and what they found on their first run.
A54: GATE-1 | B54: Tooling | C54: tools/review-gates/reachability.js | D54: L-P4 as code: walks the import graph from the REAL entrypoints (never the tests — that blindness is the point) and reports orphan modules and orphan methods. Exceptions require a written reason; stale exceptions are reported so they expire. | E54: SHIPPED + tested (test/gates.test.ts proves it goes red when what it guards breaks); wired as npm run gates in CI | F54: DECISION: port to the other 10 products — config is ~10 lines per repo
A55: GATE-2 | B55: Tooling | C55: tools/review-gates/doc-claims.js | D55: L-P5 as code: a register of published claims, each tied to the evidence in code that must hold (15 registered for TestPulse). Fails the build on the commit that breaks the link rather than in a Marketplace security review. | E55: SHIPPED + tested; covers deletion, retention, scopes, subprocessors, encryption posture, asset spec, a11y, residency | F55: DECISION: adopt portfolio-wide; untestable claims (SLA, pen-test) need a named owner and date instead
A56: F-TP34 | B56: Med-High | C56: telemetry.ts | D56: Found by the gate, missed by manual pass 3: trackFeature/heatmap/exportCsv/funnel had no caller — the ST-073 feature heatmap was never fed and the ST-071 funnel and ST-076 export were never readable; setErrorThreshold was unreachable so ST-077 could not be tuned. | E56: FIXED — every resolver invocation records its feature; admin-only usageReport returns funnel+heatmap+CSV; threshold moved into Settings | F56: None
A57: F-TP35 | B57: Med | C57: support.ts | D57: Support.respond had no caller: a ticket could be opened and NEVER answered, so the SLA report could only ever accumulate breaches — and the Cloud Fortified evidence row cites that report. | E57: FIXED — supportRespond (admin/owner); the SLA report now measures what it claims | F57: None
A58: F-TP36 | B58: Med | C58: runboards.ts, testgen.ts | D58: Both CSV importers were unreachable — run results (ST-019) and test cases (ST-009). Only the Xray path had a door. | E58: FIXED — importRuns and importTestCsv resolver calls | F58: None
A59: F-TP37 | B59: Med | C59: onboarding.ts, ui/mount.ts, forgeGlue.ts | D59: Two writers for one thing, twice: the panel kept its own copy of the ST-079 empty-state map while Onboarding.emptyState went uncalled, and Settings read/wrote ntf:pref:* directly, duplicating the key format Notifications owns. | E59: FIXED — one shared emptyStates.ts consumed by both; Settings goes through Notifications.setPref/prefs(); the dead method deleted rather than allowlisted | F59: None
A60: OBS-TP5 | B60: Open | C60: telemetry.ts | D60: Telemetry.healthScore (ST-075) needs weekly-active-users, which nothing in the product tracks — the metric is unfed. | E60: NOT FIXED — allowlisted with the reason recorded | F60: DECISION: cut ST-075 or fund a usage feed for it
A61: COLD REVIEW PASS 6 — THE CUSTOMER'S PATH (13/09/2026 10:57): walking the primary loop as a user.
A62: F-TP39 | B62: HIGH | C62: ui/mount.ts | D62: MOUNTING THE ISSUE PANEL CALLED generate — A WRITE. Every time anyone opened an issue, TestPulse generated and persisted another set of cases: 3 duplicates per view, unbounded, and with an LLM provider configured an Anthropic API call BILLED PER PANEL RENDER. Browsing 10 issues twice = 20 generations and 60 cases for 30 stories. | E62: FIXED — the panel reads (listCases); generating is an explicit button; mounting never writes | F62: None — but it is the reason to walk the loop before LC-1 assets are shot
A63: F-TP38 | B63: Med-High | C63: testgen.ts | D63: There was no read path for cases at all: the panel could create them and never show what existed. | E63: FIXED — TestGen.list(storyKey?) + listCases resolver call, classified as a read so it survives an inactive license | F63: None
A64: F-TP40 | B64: Med-High | C64: runboards.ts, forgeGlue.ts | D64: A run could not be recorded from the issue panel: recordRun demanded a boardId and creating a board needs the configure permission a member lacks. The MVP loop the product is built around was NOT COMPLETABLE BY A MEMBER in the UI. | E64: FIXED — runs record against a default board created on demand; pass/fail/blocked controls on each case; generate -> run -> readiness completes in-panel | F64: Confirm "Current release" as the default board name (customer-visible)
A65: F-TP41 | B65: Med | C65: telemetry.ts | D65: Two of the four activation-funnel stages (setup, habit) were declared and never recorded, so the funnel — the metric the launch targets in Metrics_Targets are written against — could never show more than install -> aha, and activation rate would have read as a permanent failure. | E65: FIXED — setup on the first board, habit once a tenant records runs on 3 distinct days | F65: Confirm 3 distinct days as the habit definition
A66: L-P6 | B66: Lesson | C66: portfolio | D66: Walk the primary loop as the user, once, before launch. Five passes read the code, the manifest, the docs and the export graph; none USED the product. Generate-on-mount is invisible to all four readings — the call, resolver, reachability and documentation are each correct. It is only wrong as a SEQUENCE: a read-shaped interaction wired to a write-shaped call. | E66: Recorded; no tool catches this class — it needs one honest walkthrough per product | F66: DECISION: do the same walkthrough on the other products before their launches
A67: COLD REVIEW PASS 7 — INSTALL + NAVIGATION (13/09/2026 11:03): the steps either side of the core loop.
A68: F-TP42 | B68: HIGH | C68: forge/manifest.yml, forgeAdapter.ts | D68: NOTHING EVER INVOKED THE INSTALL PATH. The manifest had no trigger module, and Forge delivers install/uninstall only via avi:forge:installed:app / avi:forge:uninstalled:app — there is no implicit call. On a real install: no trial, no owner claimed, no CI secret provisioned, no install telemetry; on uninstall: tokens never wiped and the 30-day deletion never scheduled, so the retention sweep shipped in pass 3 had nothing to sweep. The whole E1 lifecycle epic (ST-051..056) was unreachable in a deployed app. | E68: FIXED — trigger module on both lifecycle events, makeLifecycleTrigger in the adapter, lifecycleTrigger exported from the entrypoint; ownership from installerAccountId; idempotent because Forge can deliver twice | F68: None — but this is what would have made LC-1 look like a dead app
A69: F-TP42b | B69: Med | C69: forgeGlue.ts | D69: Atlassian documents install events as asynchronous, sometimes lagging minutes — a panel opened in that window would have hit an uninitialised tenant. | E69: FIXED — lazy bootstrap on any call, which deliberately does NOT claim ownership, so the first user through the door cannot become owner by accident | F69: None
A70: F-TP43 | B70: HIGH | C70: ui/mount.ts, static/entry.ts | D70: THE PANEL HAD NO NAVIGATION: five screens, one hardcoded data-tab in a single index.html serving both the project page and the issue panel. The project page showed "pick a story" forever; run boards, flaky, readiness and settings had no door at all. | E70: FIXED — tab bar (role=tablist, aria-selected), switching re-mounts without writing, the cases tab appears only with a story in context, and the entry picks its default tab from the Forge context (issue panel -> cases, project page -> readiness) | F70: Tab labels are customer-visible: Test cases / Run board / Flaky / Readiness / Settings
A71: F-TP44 | B71: Med-High | C71: forgeGlue.ts, ui/mount.ts | D71: The run-board screen asked for a boardId nothing supplied, so it was permanently empty in the installed app. | E71: FIXED — boardMetrics resolves the default board when no id is given, matching how runs are recorded | F71: None
A72: L-P7 | B72: Lesson | C72: portfolio | D72: REACHABLE IS NOT INVOKED. The install path was reviewed for correctness (pass 1), deployed (pass 2), declared reachable (pass 3 — it was reachable, from a resolver call nothing called), documented (pass 4) and passed the reachability gate (pass 5, because installed is a registered call). Only walking the product from outside exposed that the caller was Atlassian and we had never told Atlassian to call. | E72: For every entrypoint the PLATFORM owns — lifecycle events, scheduled triggers, webhooks, product events — check the manifest declares it, not just that the handler exists | F72: DECISION: add a manifest-declaration check to the gates and run it across the portfolio
A73: PASS 8 — THE GATE L-P7 ASKED FOR (13/09/2026 11:10)
A74: GATE-3 | B74: Tooling | C74: tools/review-gates/platform-entrypoints.js | D74: L-P7 as code: reads the manifest and the deploy entrypoint TOGETHER — a handler the entrypoint does not export (VER-P01), an export nothing points at, a function no module references, and the module declarations the product's claims depend on (lifecycle trigger on both events, daily scheduled trigger, v2 webtrigger, panel resource). This is the check the reachability gate structurally cannot make, and the one that would have caught F-TP42 the day the handler was written. | E74: SHIPPED + tested (6 cases incl. the two historical defects); wired into npm run gates; portable README updated with per-platform notes | F74: DECISION: roll all three gates out to the other 10 products
A75: GATE-3b | B75: Self-check | C75: tools/review-gates/platform-entrypoints.js | D75: The gate had the defect it exists to catch: its export scanner counted a COMMENTED-OUT export as exported — exactly the VER-P01 shape. Its own test fixture caught it. | E75: FIXED — comments stripped before scanning; the argument for testing gates as code rather than shipping them as scripts | F75: None
A76: F-TP45 | B76: Med-High | C76: forgeGlue.ts | D76: A REPEAT INSTALL EVENT RESET THE INSTALLATION: Forge may deliver avi:forge:installed:app more than once and each delivery re-ran Lifecycle.install — resetting installedAt, re-sourcing the attribution (ST-056) and overwriting stored tokens with the event's empty ones. Surfaced as an intermittent 1ms test failure that looked like a flaky clock. | E76: FIXED — bootstrap is idempotent; the account is written only when the event carries tokens, otherwise read back | F76: None — but worth remembering that an intermittent test is worth reading before it is retried
A77: PORTFOLIO ROLLOUT KIT (13/09/2026 11:18)
A78: KIT-1 | B78: Tooling | C78: tools/review-gates/init.js | D78: Bootstrapper for porting: scans a repo for the platform manifest, deploy entrypoint, UI/server entries, the OPS SCRIPTS CI RUNS (real callers — TestPulse's encryption-posture check is reachable only from one), source roots, and proposes claim stubs from documents that already make promises. Validated by reproducing TestPulse's hand-written config exactly. | E78: SHIPPED + tested (4 cases incl. the refuse-to-guess paths) | F78: DECISION: run it on the next product and confirm the detected entrypoints before trusting a green result
A79: KIT-2 | B79: Doc | C79: docs/portfolio-gate-rollout.md | D79: Rollout guide: 5-minute per-repo procedure, how to triage the first red run (FIX / ALLOW WITH A REASON / CUT — cutting unfunded scope is a legitimate and usually honest outcome), rollout order (products closest to a live install first; the platform-entrypoint gate pays back fastest because an app that deploys and does nothing is the most expensive failure in this portfolio and has now happened twice), and per-platform hook tables for Forge, Salesforce, Devvit and Shopify. | E79: SHIPPED | F79: DECISION: pick the first product and the order
A80: KIT-3 | B80: Honesty | C80: — | D80: What the gates do NOT catch: 16 of the 50 defects came from USING the product (opening a panel twice, recording a run as a member, installing it and looking). That is L-P6 and does not automate. | E80: Recorded in the rollout guide | F80: DECISION: budget one honest walkthrough per product before each launch
A81: LC-1 SESSION PACK (13/09/2026 11:22)
A82: LC1-1 | B82: Tooling | C82: scripts/lc1-verify.js | D82: Live post-install verification against the deployed app: signed payload accepted (202), duplicate event id rejected, tampered signature rejected, stale timestamp rejected, malformed body 400 — the five behaviours the security assessment and HC-14 promise. Prints tracker-ready evidence lines. Tested against the REAL webtrigger handler, so a failure means the deployment differs from this codebase, not that the script is wrong. | E82: SHIPPED + tested (5 cases incl. wrong-secret and network-failure paths) | F82: Run it right after `forge webtrigger`; secret comes from Settings > CI
A83: LC1-2 | B83: Doc | C83: docs/lc1-session-pack.md | D83: 45-minute run sheet: pre-work, install commands, what the lifecycle trigger bootstraps and what to do if it lags (the app self-bootstraps lazily, only the owner claim waits), an evidence table mapping each capture to the stories it flips, and the two questions only a live site can answer — manual keyboard/contrast pass (ST-089) and whether the customer-visible default board name and the 3-distinct-days habit definition are right. | E83: SHIPPED | F83: Book the session; everything else on TestPulse is behind it
A84: LC1-3 | B84: Tooling | C84: static/build/capture.html | D84: Listing-asset capture harness: renders the panels inside dashed frames sized to the VERIFIED Rule-of-3 spec (3 highlights 1840x900, 580x330 crops, banner 1120x548) so one screenshot pass yields correctly sized assets. Verified headlessly — 7 frames, all populated, no NaN. | E84: SHIPPED | F84: Capture at 100% zoom (50% on a 2x display) or the pixel dimensions will be wrong
A85: LC1-4 | B85: Honesty | C85: — | D85: What lc1-verify CANNOT check: the panel render, resolver, roles, licensing, the lifecycle trigger firing and the retention sweep. A green run must not be recorded as full verification. | E85: Stated in the script output and the session pack | F85: Evidence must distinguish verified from assumed

Sheet External_Review_V001
A1: EXTERNAL REVIEW — ChatGPT Deep Review V001, 13/09 (carried)
A2: ID | B2: Severity | C2: Area | D2: Finding | E2: Disposition in code | F2: Senthil decision
A3: TPR-001 | B3: HIGH | C3: forge/index.ts | D3: AI provider never constructed in the real entrypoint — generateWithAi always received undefined, so AI generation was rule-engine-only in the deployed app and R-P6 was closed on a seam. THIRD instance of this shape in this codebase, and the first to land on a previous FIX (F-TP16). | E3: ACCEPTED + FIXED — buildAiProvider() constructs AnthropicProvider from ANTHROPIC_API_KEY over Forge external fetch; no key still falls back to rules; pinned at entrypoint level | F3: DECISION: AI on at launch, off, or behind an owner toggle — it now costs real money per generation
A4: TPR-002 | B4: HIGH | C4: src/notifications.ts, ui, helpcenter | D4: An email checkbox, preference and delivery record with no transport, no provider and no egress permission, while the trust page correctly said TestPulse sends no email. Five stories closed on it. | E4: ACCEPTED + FIXED — email removed from the product surface entirely (pref, checkbox, channel, HC-13); the five stories rescoped to in-app only, rescope recorded | F4: DECISION: does email ship at all? If yes it needs a provider, egress, subprocessor disclosure and listing copy
A5: TPR-003 | B5: HIGH | C5: forge/manifest.yml | D5: write:jira-work requested; nothing in the app writes to Jira. Either a promised feature is missing or an unnecessary high privilege is requested — both are review defects. | E5: ACCEPTED + FIXED — scope removed from the manifest, SCOPE_MAP, trust page and review pack | F5: DECISION: is Jira write-back a feature you want? It is now new scope, not a silent permission
A6: TPR-004 | B6: HIGH | C6: docs/residency-statement.md, src/config.ts | D6: Published app-level residency control (global/EU/US) that runtime never consumed — TP_DATA_RESIDENCY was parsed and validated in config.ts and used nowhere. | E6: ACCEPTED + FIXED — claim removed from the statement; the variable removed from config so nothing implies the feature; both directions pinned by the claims gate | F6: None
A7: TPR-005 | B7: HIGH | C7: src/tenantData.ts, forgeGlue.ts | D7: deleteMyData purged role:owner, and the lazy bootstrap deliberately never re-claims ownership — the owner who exercised their data rights came back as a member and lost export, deletion and the CI secret. | E7: ACCEPTED + FIXED — the acting owner is re-established after the purge; pinned both ways (owner keeps it, nobody else gains it) | F7: None
A8: TPR-006 | B8: MED | C8: test/conformance.test.ts | D8: DC-11 claimed to measure TestPulse but called the vendored baseline helper with hard-coded visibility, and reported PASS — the conformance rollup overstated its evidence. | E8: ACCEPTED + FIXED — rebuilt against two real installations through the real resolver; recorded honestly as N-A, platform-enforced | F8: None
A9: TPR-007 | B9: MED | C9: conformance + jiraClient tests | D9: DC-06 marked N-A on the grounds of no live HTTP call, while the entrypoint calls Jira on every panel open; the default-sleep test asserted no elapsed time and used a retryAfter field the client ignores. | E9: ACCEPTED + FIXED — conformsBackoff now runs against JiraClient with NO injected sleep and a lower-bound elapsed assertion; stale fixture corrected | F9: None
A10: TPR-008 | B10: MED | C10: src/forgeGlue.ts | D10: writeSettings rebuilt the response with trialDays from the payload, so a normal save reported trialDays 0 while runtime was 14. | E10: ACCEPTED + FIXED — writeSettings takes the runtime env | F10: None
A11: TPR-009 | B11: MED | C11: docs/review-pack.md | D11: Submission pack cited nodejs20.x while the manifest, CI and deploy guide use nodejs22.x and state Node 20 is EOL. | E11: ACCEPTED + FIXED — corrected, and runtime consistency across the three files is now a registered claim | F11: None
A12: TPR-010 | B12: MED | C12: src/compliance.ts | D12: DATA_FLOW_DOC said egress was none except a configured email provider — contradicting both the manifest (Anthropic only) and the trust page (no email). | E12: ACCEPTED + FIXED — corrected and registered as a claim tied to the manifest | F12: None
A13: TPR-011 | B13: MED | C13: jest.config.js, vendor/baseline | D13: Coverage collects src only, while handover notes presented 338 tests / 100% as the package result — the vendored baseline was never measured. | E13: ACCEPTED + FIXED — two scopes stated explicitly and the vendored copy hash-pinned (test/vendor-pin.json) so it cannot drift silently | F13: None
... A17: TPR-015 | B17: OBS | C17: review environment | D17: npm ci did not complete in the reviewer sandbox, so the 338-test claim was not independently reproduced. | E17: ACCEPTED + ADDRESSED — full CI captured at evidence/ci-run-20260913-1857.log: Node v22.22.2, build, 3 gates, posture, Forge typecheck, UI build, 40 suites / 369 tests / 100% x4 | F17: Attach this log to the submission evidence pack
A18: TOTAL | B18: Findings accepted | C18: =COUNTA(A5:A19) | D18: High findings closed | E18: =COUNTIF(B5:B19,"HIGH") | F18: All fixed with pinned regressions

Sheet Release_Traceability_Correction
A1: STATUS CORRECTIONS — supplied statuses that did not match executable evidence
A2: Item | B2: Was | C2: Now | D2: Finding | E2: Why
A3: R-P6 — AI seam | B3: Mitigated-in-code | C3: Closed, entrypoint-proven | D3: TPR-001 | E3: buildAiProvider in forge/index.ts + entrypoint-level test
A4: ST-010/020/030/040/050 | B4: Done (in-app + email) | C4: Done — RESCOPED to in-app only | D4: TPR-002/013 | E4: Email removed from product surface; scope narrowed rather than claimed
A5: LC-2 review pack | B5: Doc-complete | C5: Doc-complete (corrected) | D5: TPR-003/009 | E5: Runtime and scope justification both wrong; now consistent
A6: LC-3 Cloud Fortified | B6: Doc-complete | C6: Doc-complete (corrected) | D6: TPR-004 | E6: Residency row no longer claims an app-level control
A7: LC-4 residency | B7: Doc-complete | C7: Doc-complete (corrected) | D7: TPR-004 | E7: Statement now matches runtime; claim gate pins both directions
A8: DC-11 conformance | B8: PASS (after fix) | C8: N-A, platform-enforced (evidenced) | D8: TPR-006 | E8: Old harness measured a helper, not the product
A9: DC-06 conformance | B9: N-A | C9: PASS (measured) | D9: TPR-007 | E9: Production does make live Jira calls
A10: Release readiness | B10: 95/100 code-complete | C10: NOT RELEASE READY until LC-1 | D10: TPR-001..005 | E10: Code findings closed; LC-1 + D18 + pen-test remain

Sheet V002_Roadmap
A1: V002 ENTERPRISE ROADMAP — superseded 20/09 by the 14-sprint plan
A2: Sprint | B2: Pri | C2: Name | D2: Objective | E2: Status | F2: Notes
A3: E00 | B3: P0 | C3: Release Truth & Runtime Closure | D3: Make V001 truthful and shippable before feature expansion | E3: CLOSED 13/09 18:57 | F3: All 15 TPR findings fixed with pinned regressions; CI evidence retained
A4: E01 | B4: P0 | C4: Canonical Test Domain Model | D4: Enterprise test entities rather than thin storage records | E4: SUPERSEDED — partially delivered by PR-02 | F4: Versioned entities with optimistic concurrency shipped (EG-04 seed); plans/cycles/environments as entities are not built.
A5: E02 | B5: P0 | C5: Requirements-Tests-Defects Traceability | D5: Auditable quality coverage from Jira work items | E5: SUPERSEDED — delivered by PR-08 | F5: Traceability graph + coverage by release shipped 20/09. EG-05 moved MISSING -> PARTIAL (write-back to Jira is decision D-TP-WB).
A6: E03 | B6: P0 | C6: Automation Results Ingestion | D6: JUnit/NUnit/Cucumber/Playwright adapters, idempotent | E6: SUPERSEDED — delivered by PR-06 | F6: JUnit/Playwright/Cucumber ingestion shipped 20/09. EG-06 moved MISSING -> PARTIAL (a real pipeline post is PR-04).
A7: E04 | B7: P0 | C7: CI/CD Connectors | D7: GitHub/Bitbucket/Jenkins/GitLab/Azure + generic contract | E7: BACKLOG | F7: At least 3 production connectors
A8: E05 | B8: P0 | C8: Release Quality Command Center | D8: Make readiness the wedge | E8: SUPERSEDED — delivered by PR-05 | F8: Readiness derived from live data with sourced factors. This was the positioning decision in code form, and it is done.
A9: E06 | B9: P0 | C9: Flaky Test Intelligence 2.0 | D9: Defensible intelligence layer around instability | E9: SUPERSEDED — delivered by PR-07 | F9: Flaky 2.0 shipped 20/09.
A10: E07 | B10: P0 | C10: AI Quality Copilot — Production | D10: Governed QA intelligence, not a generate button | E10: SUPERSEDED — delivered by PR-10 | F10: AI governance v2 shipped; model-QUALITY evals remain the named gap (needs PR-14).
A11: E08 | B11: P0 | C11: AI Privacy & Egress Control | D11: Tenant-level AI enable/disable, redaction, audit | E11: SUPERSEDED — delivered by PR-10 | F11: Tenant-level enable/disable, redaction, audit and BYOK shipped.
A12: E09 | B12: P0 | C12: Runs on Atlassian Strategy | D12: Assess whether Anthropic egress blocks the badge | E12: CUT as a sprint (V002_Cuts) | F12: A decision, already analysed, and the revenue premise changed (C-5). Folded into the trust page.
A13: E10-E20 | B13: P1 | C13: Governance, scale, operations, UX, reporting, migration, BDD, triage, policies | D13: Enterprise depth | E13: BACKLOG | F13: Eleven sprints; see the V002 workbook for full scope
A14: E21-E29 | B14: P2 | C14: API, security programme, packaging, onboarding, design partners, evidence graph, change-risk selection, gov cloud, release factory | D14: Moat and GA readiness | E14: BACKLOG | F14: Nine sprints

Sheet E09_Badge_Assessment
A1: RUNS ON ATLASSIAN — eligibility (carried; revenue premise corrected by C-5)
A2: Requirement | B2: TestPulse | C2: Detail | D2: Disposition
A3: No external resource domains | B3: FAIL | C3: api.anthropic.com is declared for optional AI. Disqualifying whether or not a tenant enables it | D3: DECISION: drop AI / keep AI / two major versions
A4: Web triggers declared static | B4: FIXED 20:01 | C4: Undeclared type is ineligible, same as explicitly dynamic. The CI webtrigger had no type at all | D4: Declared static; costs nothing (HMAC auth, no URL secrecy)
A5: No remotes | B5: PASS | C5: Forge-native; no remote services
A6: No Connect modules | B6: PASS | C6: Forge-only manifest
A7: No providers | B7: PASS | C7: None declared
A8: Data-residency-enabled storage | B8: PASS | C8: Forge hosted KVS via kvsAdapter
A9: Authoritative check | B9: PENDING | C9: forge eligibility runs automatically at deploy and on demand | D9: Added to the LC-1 run sheet; keep the output as evidence

Sheet Risk_Register
A1: PRODUCT RISK REGISTER
A2: Risk | B2: Impact | C2: Likelihood | D2: Mitigation
A3: Atlassian Forge program rate/policy changes mid-build | B3: Medium | C3: Medium | D3: Track dev changelog; rate abstraction in pricing model
A4: Xray/Zephyr respond with AI features | B4: High | C4: HAPPENED | D4: MATERIALISED (C-4, 20/09): Xray markets itself as "powered by AI", Zephyr as "with Rovo", and dedicated generators already ship the feature. No longer a risk to track — a fact to position against. The wedge moved to the release decision, which PR-05 earns in code.
A5: The enterprise programme bar moves before listing (CORRECTED 20/09, C-2) | B5: Medium | C5: Medium | D5: MATERIALISED, not raised: the Cloud Fortified programme CLOSED to new submissions 01/09/2026 and retires 31/12/2026. Its successor, Atlassian Enterprise Certified, sets a higher bar. Assessed row by row in docs/enterprise-certified-gap.md; two rows (accredited penetration test, public bug bounty) are procurement items that have not started.
A6: Hosted-storage value limits (F-TP06 capped; OBS-TP1 CLOSED 20/09) | B6: High | C6: Low (post-fix) | D6: CLOSED 20/09 by PR-03: prefix-scoped hydration means an invocation reads only what it declares (whoami = 2 keys), and per-entity keys removed the row ceilings entirely. The cost that replaced it is round trips per listing, published in the envelope rather than left to be discovered. Ledger byte caps (F-TP06/PERF-01) are unchanged and now commutative.
A7: Data-deletion claims outrun implementation (found as F-TP01/F-TP02) | B7: High | C7: Low (post-fix) | D7: Namespace registry + drift test: an unregistered namespace now fails the build, not the security review
A8: Deploy-time failure invisible to the suite (VER-P01/VER-P02 class) | B8: High | C8: Low (post-fix) | D8: Entrypoint type-check + UI build are now CI gates; same gate to be ported across the portfolio (L-P1)
A9: Shipped-but-unreachable scope (F-TP21..28 class) — modules pass their tests while no user can trigger them | B9: High | C9: Low (post-fix) | D9: Reachability audit run for TestPulse; standing check proposed portfolio-wide (L-P4)
A10: Published claims drifting from the product (F-TP33 class) — customer- and reviewer-facing documents outrun the code | B10: Medium | C10: Low (post-fix) | D10: Mechanical claims pinned by tests; untestable claims need a named owner and date (L-P5)
A11: Read-shaped interaction wired to a write-shaped call (F-TP39 class) — correct code, correct docs, wrong sequence | B11: High | C11: Low (post-fix) | D11: No gate catches it; one user-path walkthrough per product before launch (L-P6)

Sheet Gate_Register_v2
A1: STANDING GATES
A2: ID | B2: Gate | C2: What it checks | D2: Defects it reproduces in test | E2: Status
A3: G-1 | B3: Reachability | C3: Orphan modules and orphan methods from the real entrypoints; written reasons required; stale exceptions reported | D3: F-TP21, F-TP34..37 | E3: GREEN
A4: G-2 | B4: Published claims | C4: Published claims: 42 registered claims (was 25 on 13/09), each tying a customer-facing promise to the code evidence that must hold | D4: F-TP33, TPR-004, TPR-009, TPR-010 | E4: GREEN
A5: G-3 | B5: Platform entrypoints | C5: Manifest and entrypoint read together: unexported handlers, unpointed exports, orphan functions, required module declarations | D5: VER-P01, F-TP42 | E5: GREEN
A6: G-4 | B6: Entrypoint wiring (NEW) | C6: Each declared capability is CONSTRUCTED in the deploy entrypoint and PASSED to its consumer | D6: TPR-001, F-TP42 (both by mutating the real entrypoint) | E6: GREEN
A7: G-5 | B7: Concurrent write safety (NEW 20/09, L-P8) | C7: Static: no plain read-modify-write on a registered shared key. Dynamic: every registered key must be exercised under interleaved writers in the concurrency suite | D7: PRX-02, reproduced in test as the pre-PR-01 shape. WENT RED ON ITS OWN FIRST RUN for 8 of 13 keys. | E7: GREEN
A8: G-6 | B8: Scope & egress (CB-06/EG-02) | C8: Every Jira scope and egress host must name a live call path; removing the last caller fails the build | D8: TPR-003 (write:jira-work outliving its use) | E8: GREEN
A9: G-7 | B9: Secret & PII scan (CB-10) | C9: Credential and PII shapes across src, test, docs, evidence and fixtures; allowances must carry a written reason | D9: Its own fixtures, twice — which is why they are built at runtime | E9: GREEN
B10: Gates green | C10: =COUNTIF(E4:E9,"GREEN") | D10: of | E10: =COUNTA(A4:A9)

Sheet AEC_Gap
A1: ATLASSIAN ENTERPRISE CERTIFIED — gap assessment (replaces the retired Cloud Fortified plan)
A2: The Cloud Fortified programme closed to new submissions on 01/09/2026 and retires 31/12/2026, so the previous assessment measured a bar that no longer exists. MET (code) = enforced and pinned by a test or gate. MET (doc) = published and pinned by the claims gate. OPEN = needs an action outside this repository. LIVE = needs the installed app or elapsed time.
A3: # | B3: Requirement | C3: State | D3: Evidence / gap | E3: Owner
A4: 1.1 | B4: Current annual penetration test — Atlassian Bugcrowd or a CREST-accredited vendor, submitted for approval | C4: OPEN | D4: The internal assessment pack does NOT satisfy this. Procurement lead time — the review said to start at the beginning of the phase, not the end. This is ST-068. | E4: Senthil
A5: 1.2 | B5: Public bug bounty via Atlassian's programme | C5: OPEN | D5: The old plan ("publish security.md + a contact") does not satisfy this requirement. Enrolment is required. | E5: Senthil
A6: 1.4 | B6: No Connect modules | C6: MET (code) | D6: Forge-only manifest; the platform-entrypoints gate reads it on every build. | E6: —
A7: 1.5 | B7: No storage of Atlassian user credentials or PATs | C7: MET (code) | D7: The vestigial {access, refresh} pair was REMOVED from the install record rather than explained. A tenant Anthropic key lives in Forge Secret Storage. test/lifecycle.test.ts asserts the record holds no credential. | E7: —
A8: 1.7 | B8: Least privilege, verified against code | C8: MET (code) | D8: scope-egress gate: read:jira-work justifies four named call paths; no write scope; storage:app justified. | E8: —
A9: 1.10 | B9: No production dependency that is not needed at runtime | C9: MET (code) | D9: Production dependencies are empty (C-7); the Express harness is dev-only and refuses to start in production. | E9: —
A10: 1.12 | B10: Full egress transparency incl. publicly disclosed subprocessors | C10: MET (doc) | D10: Trust page names Atlassian and Anthropic; the claims gate pins the Anthropic host to the manifest. Publication to the listing trust tab is LC-7. | E10: Senthil at listing
A11: 1.13 | B11: CI/CD vulnerability scanning gates | C11: MET (code) | D11: Seven review gates plus npm audit in CI; 0 production vulnerabilities in the clean-room run. | E11: —
A12: 1.14 | B12: Calls to Atlassian as the user where visibility matters (asUser default) | C12: MET (code) | D12: Story fetch, JQL count, JQL search and BROWSE_PROJECTS are all asUser(); the permission check fails closed when Jira does not answer. | E12: LIVE proof at PR-04
A13: 2.x | B13: Reliability SLO with live data | C13: LIVE | D13: p95 sampled per invocation; the SLO definition needs 30 days of live data. | E13: Senthil
A14: 3.x | B14: Incident response wired to real alerting | C14: OPEN | D14: Runbook, comms tree, status page and template exist; WHO IS PAGED is not wired, and is recorded as partial rather than counted as done. | E14: Senthil
... A18: — | B18: Backup / recovery | C18: MET (code) | D18: Non-destructive backup check in statusReport; the destructive drill stays a staging tool. | E18: LIVE re-run at PR-04
A20: VERDICT: the engineering rows are met and pinned. The programme cannot be applied for until 1.1 and 1.2 are done, and neither is a documentation task. Nothing on this table is marked done on documentation alone.

Sheet Market_Evidence
A1: MARKET DEMAND EVIDENCE — read 16/09/2026 by the reviewer; re-read before quoting externally
A2: Marketplace install counts and app pricing change frequently. Every row carries its source. Market-size estimates are cited to show their dispersion, not to support a forecast.
A3: Signal | B3: Finding | C3: Source | D3: What we did about it
A4: Incumbent scale | B4: Xray 25,454 installs, 4.3/5 from 553 reviews; Zephyr 15.3k; Zephyr Essential 10.2k — all Cloud Fortified. The Testing & QA category shows 1,411 apps. | C4: marketplace.atlassian.com Testing & QA | D4: Confirms the category is real and crowded. Reinforces the wedge decision rather than a feature race.
A5: Search demand | B5: Three of the top five Marketplace search queries in Aug 2025 were test-management terms. | C5: community.atlassian.com App Central | D5: Listing SEO keeps its place in GTM; the terms are in the listing copy work.
A6: Willingness to pay | B6: Xray ~$6.33/user/month monthly cloud: ~$6,330/yr at 100 Jira users, but ~$100/yr at 10 users. TestRail Professional $37/seat/mo. | C6: getbestest.com/xray-pricing ; getxray.app ; testrail.com/pricing | D6: Drove the per-user anchor: 40-50% under in the 26-200 band, sub-10 conceded because we were 12x Xray there.
A7: AI differentiation ERODED | B7: Xray lists as "powered by AI"; Zephyr as "with Rovo"; dedicated generators already ship the exact feature (TestKase, AI Test Case Generator, Agilemove). | C7: marketplace.atlassian.com listings | D7: R-P2 closed as MATERIALISED (C-4). ReadMe_Scope differentiation rewritten around the release decision.
A8: Market size (unusable dispersion) | B8: $1.13B in 2024 at 16.8% CAGR vs $481M in 2026 at 7.6% vs $10.17B in 2026 — more than an order of magnitude apart. | C8: MRFR ; Industry Research ; 360iResearch | D8: Not used for planning, as the reviewer instructed. The install and pricing figures are the hard signal.
A9: Licensing model | B9: Jira Cloud apps are licensed against the MAXIMUM USERS ON THE INSTANCE, not app users — so flat $99/$299 plans cannot be listed. | C9: community.atlassian.com App Central | D9: Confirms D18. pricing-faq.md rewritten in per-user terms.
A10: Revenue share | B10: Eligible Forge apps keep 100% of gross until $1M lifetime Forge revenue (from 01/01/2026); 84% from 01/04/2026, 83% from 01/10/2026 above it. Eligibility: no Connect modules, OAuth, Forge UI — TestPulse meets all three. | C10: developer.atlassian.com/platform/marketplace/pricing-payment-and-billing/ | D10: C-3: Financial_Model fee 0.17 -> 0.00; MRR was understated ~20%; breakeven moves earlier.
A11: Runs on Atlassian | B11: Eligible apps declare no external resource domains; assessed from the manifest, continuously. The badge no longer carries a revenue delta. | C11: developer.atlassian.com/platform/forge/runs-on-atlassian-apps/ | D11: C-5 added to the assessment; Decision 2 adopted as Option B for the better reason.
A12: Enterprise programme | B12: Cloud Fortified submissions closed 01/09/2026, retired 31/12/2026. Successor: Atlassian Enterprise Certified — annual CREST/Bugcrowd pen test, public bug bounty, no PAT storage, egress and subprocessor disclosure, public AI usage policy, asUser() default. | C12: developer.atlassian.com/platform/marketplace/changelog/ ; /atlassian-enterprise-certified-program/ | D12: C-2: the old gap assessment deleted and rewritten against AEC. Two rows are procurement.
A13: Forge storage limits | B13: KVS/Custom Entity Store: 240 KiB per value, 20 entities, 7 indexes, 50 attributes, pages of 100. Forge SQL: 1 GiB per production install, 200 tables, 6 MiB rows, 5s SELECT timeout. | C13: developer.atlassian.com/platform/forge/limits-kvs-ce/ ; /storage-reference/sql/ | D13: Verified again on 20/09 for ADR-001, which adds the facts the review did not have: the sql module is a MAJOR version and schema is applied per installation by a scheduled trigger.
