Workbook

Sheet Version_Control
A1: VERSION CONTROL — OnCall Copilot
A3: Version | B3: Date | C3: Author | D3: Change | E3: Status
A4: v001-v004 | B4: 2026-09-05 | C4: Claude for Senthil/KP | D4: Lineage: marketplace master (868 entries) -> portfolio plan (12 products) -> wave-1 (RetainKit/ShiftDesk/EngageOS, v005) -> this product selected for wave-3 | E4: Released
A5: v007 | B5: 2026-09-05 19:50 | C5: Claude for Senthil/KP | D5: Full product workbook for OnCall Copilot on Slack App Directory: spec, screen inventory, 100+ story backlog, live sprint board, 18-month financial model (editable assumptions), GTM execution tasks, platform launch checklist, metric targets, risk register | E5: Released
A6: v008 | B6: 2026-09-10 22:22 | C6: Claude for Senthil/KP | D6: Development release per D13 (discovery parked, 100% automation coverage): TypeScript codebase for F1-F5 + E1/E5/E6/E7/E8/EQ; 16 Jest suites / 105 tests at 100% statements/branches/functions/lines; Sprint_Tracker_Log + Traceability_Matrix sheets added; backlog statuses updated (75 Done / 5 Code-complete / 2 In progress / 18 Backlog) | E6: Released
A7: v009 | B7: 2026-09-10 22:55 | C7: Claude for Senthil/KP | D7: Sandbox completion release: Events API receiver (signature verify, replay guard, dedupe, backoff+dead-letter queue) closing checklist #4; ST-091 graceful degradation + ST-074 scheduler Done; 7 launch-content artifacts Drafted (listing A/B, pricing FAQ, trust page, runbook, comms templates, 15 help articles, k6 script); 19 suites / 122 tests at 100% coverage; statuses now 77 Done / 5 Code-complete / 8 Drafted / 10 Backlog | E7: Released
A8: v010 | B8: 2026-09-10 23:10 | C8: Claude for Senthil/KP | D8: Live-readiness release: typed config loader, 12-step scripted live verification sweep (dry-run tested), 30-min Slack dev-workspace guide with least-privilege manifest.json + .env.example; standalone tracker v001 issued 23:03; 21 suites / 133 tests at 100% coverage; LC-1 -> Code-complete; story statuses unchanged (77/5/8/10) | E8: Released
A9: v011 | B9: 2026-09-11 08:41 | C9: Claude for Senthil/KP | D9: Cold-review + ops parity release: 4 defects fixed with regressions (payment recovery, cycle reset, dedupe cap, timeline config knobs), F-005..F-008 logged in new Review_Findings sheet for disposition, REVIEW_PACK.md for external reviewer (ST-097 In progress); blue/green deploy workflow + scripted backup/restore drill (ST-092/090 Drafted); 22 suites/139 tests at 100x4; statuses 77/5/10/1/7 | E9: Released
A10: v012 | B10: 2026-09-11 12:51 | C10: Claude for Senthil/KP | D10: Sibling-validated scope release: ST-066 AES-256-GCM field encryption behind vault boundary (Code-complete, live infra evidence pending); ST-068 sandbox half SECURITY_EVIDENCE.md (In progress); ST-081 built-in chat + 4-business-hr SLA engine (Code-complete, vendor optional); ST-089 automated WCAG AA via jest-axe on 6 screen shells (In progress); 25 suites/156 tests at 100x4; statuses 77/6/10/3/4 — sandbox-codeable backlog exhausted | E10: Released
A11: v013 | B11: 2026-09-13 09:54 | C11: Claude for Senthil/KP | D11: Correctness release — cold-review pass 2 + external verification sweep. 5 pass-2 defects fixed (F-009 retention sweep never deleted, F-010 unbounded error ledger, F-011 paging partial-failure lost, F-012 foreign-timeline postmortem, F-013 CSV quoted fields) and 3 doc-verified defects fixed incl. VER-OC1 LIVE-BLOCKING 3-second slash-command ack (duplicate incident channels on the day), VER-OC2 channel naming/name_taken, VER-OC3 12h token TTL proactive refresh; VER-OC4 verified correct. Cold review now COMPLETE across all modules. 27 suites/180 tests at 100x4; story counts unchanged 77/6/10/3/4 | E11: Released
A12: v014 | B12: 2026-09-13 10:01 | C12: Claude for Senthil/KP | D12: Artifact-gap closure release: 5 gaps found by auditing every artifact the docs/scripts reference, 2 CRITICAL — no HTTP app existed behind the routes the manifest and setup guide promised (setup guide was unrunnable), and no DB schema existed behind the backup drill and retention sweep. Built router+app (5 routes, signature verification, 3s ack contract) with npm start, 5 ordered migrations with cascade deletes + parity test with npm run migrate, signed k6 fixture generator, manifest.json as a real file, pricing matrix generated from billing.ts with a drift gate. ST-088/090 -> Code-complete. 31 suites/201 tests at 100x4; statuses 77/8/8/3/4 | E12: Released
A13: v015 | B13: 2026-09-13 10:22 | C13: Claude for Senthil/KP | D13: Security/tenancy correctness release — cold-review pass 3 over the v014 HTTP surface using sibling-product defect classes. 2 CRITICAL fixed: F-014 no multi-tenancy (one service instance served every workspace; cross-tenant reads and id collisions) and F-015 OAuth CSRF (callback accepted any code, no state); plus F-016 signature-is-not-installation guard and F-017 unauthenticated health leak. VER-OC5 verified non-applicable. 32 suites/213 tests at 100x4; story counts unchanged 77/8/8/3/4 | E13: Released
A14: v016 | B14: 2026-09-13 10:38 | C14: Claude for Senthil/KP | D14: As-built re-baseline + F-018. Product_Spec, Screens_Wireframes and Metrics_Targets rewritten to match the code after nine releases of drift from the 05/09 template, recording where the product does LESS than claimed (6 of 9 screens have shells and none is data-wired; only 1 of 5 non-functional claims is met; 0 of 6 metrics reportable without the Postgres adapter). F-018 fixed: the role matrix had no assignment mechanism, so owner/admin capability was unreachable on the live surface — RoleResolver added and wired. 33 suites/222 tests at 100x4; story counts unchanged 77/8/8/3/4 | E14: Released
... A35: v037 | B35: 2026-09-20 13:05 | C35: Claude for Senthil/KP | D35: SECOND INDEPENDENT REVIEW RELEASE. Perplexity review V001 (16/09): CONTINUE at 6.1/10, 12 findings (2 BLOCKER: sync platform boundary, plan limits unenforced). Codebase v0.37.0 closes Phase 0 (PX-S0 async boundary, PX-S1 enforcement, PX-S2 gate blind spots) in the review's order: nine async platform contracts with budgets, one write gate, closed provider set with a boot-time healthcheck probe, persisted deferred work, key rotation, session revocation, frequency-safe leases, time-bounded replay window, scripts/ in the gate. 3 further defects found by audit v3 (PX-013 fixed; PX-014/015 open). 60 suites / 624 tests (616 run, 8 gated on a real Postgres) at 100% statements, branches, functions and lines over src/ AND scripts/; clean tsc over src+scripts and tests. New sheet External_Review_PX_V001; Financial_Model COMPUTED for the first time (PX-009) with a summary and sensitivities; pricing moved to workspace-size bands (D-OC8, awaiting ratification); 30 stories ST-101..ST-130 added to Full_Backlog/Traceability with every original retained; Risk_Register +5; Product_Spec, Launch_Checklist, Submission_Readiness, Metrics_Targets updated. | E35: Released
A36: v038 | D36: OPENS ON: S37 deploy-topology proof, S38 real Slack adapters (SC-06), or the D-OC6/7/8 answers. | E36: Planned

Sheet ReadMe_Scope
A1: OnCall Copilot — Incident channel automation: declare, assemble responders, timeline capture, postmortem draft
A3: PLATFORM: Slack App Directory | CATEGORY: DevOps / Incident Mgmt
A4: PROBLEM: incident.io proved the category; mid-band pricing gap remains for 50-500 eng orgs
A5: DIFFERENTIATION: AI postmortems + status page in one, priced 40-50% under category leader
A6: ICP: Tech companies 50-2000 employees, on-call rotation exists, PagerDuty/Opsgenie in stack
A8: HOW TO USE: Full_Backlog is the single source of truth (edit Status column during execution). Sprint_Board recalculates points per sprint automatically. Financial_Model assumptions (yellow) are editable — the 18-month build recalculates. Launch_Checklist is the platform-specific gate before submission. All costs/timelines are market-standard estimates; verify platform terms (fees/review rules) during S0.
A10: STACK ASSUMPTION (market standard): TypeScript/Node or platform-mandated runtime, React frontends, Postgres, hosted on AWS/GCP/platform FaaS as required, GitHub Actions CI, PostHog + Sentry telemetry, Intercom-class support.
A12: AS-BUILT RE-BASELINE (13/09/2026 10:38): spec sheets below were written 05/09 before any code existed and were never revised across 9 releases. Product_Spec, Screens_Wireframes and Metrics_Targets are now rewritten to as-built reality, including where the code does LESS than originally claimed (see Review_Findings AB-1..AB-3). Full_Backlog remains the single source of truth for status; the Sprint_Board Done column counts status "Done" only — Code-complete/Drafted/In progress are deliberately excluded so the board never overstates.
A13: STACK AS BUILT: TypeScript/Node, framework-free HTTP router, in-memory repositories behind interfaces with a Postgres schema defined (src/db/schema.ts) but no adapter wired. Decision D-OC1 still awaits ratification.
A14: STATUS VOCABULARY (13/09 11:17): Done = implemented, tested AND reachable by a user through a real surface. Module-only = implemented and tested, but no surface or live traffic reaches it yet. Code-complete = reachable but needs a live platform (Slack/Stripe/infra). Drafted = content pending review or hosting. The Sprint_Board Done column counts "Done" alone, so it deliberately reads lower after the 13/09 status truth pass.
A15: V037 (20/09/2026): second independent review incorporated. Phase 0 (PX-S0..PX-S2) done; the platform adapters are now drop-ins behind async, probed contracts. The enterprise-ready claim remains withdrawn (G0). Pricing model changed to workspace-size bands pending D-OC8. See External_Review_PX_V001 and the tracker's Review_PX_Findings for the register.

Sheet External_Review_V001
A1: EXTERNAL REVIEW V001 — independent review of the V035 package, 13/09/2026 20:31 BST
A2: Verdict: CONTINUE at 5.5/10 — real market, credible technical base, not deployable as supplied. 20 findings: 10 BLOCKER, 7 HIGH, 3 MEDIUM. After codebase v0.36.0: 9 FIXED, 3 PARTIAL, 8 OPEN. Scores: market demand 8.0, architecture intent 7.5, test maturity 7.0, market attractiveness 6.5, product completeness 4.0, GTM readiness 4.0, enterprise readiness 3.0.
A3: ID | B3: Severity | C3: Finding | D3: State after v0.36.0 | E3: Why it mattered | F3: What was done / what remains | G3: Sprint
A4: CF-001 | B4: BLOCKER | C4: Composition root could not compile | D4: FIXED v0.36.0 | E4: Entitlements was constructed from bindings declared eleven lines later. Verified before any change: 4 tsc errors while the CI gate exited 0. | F4: Composition moved into src/composition/production.ts; scripts/ added to the type-check; build runs before the coverage gate. | G4: S36
A5: CF-002 | B5: BLOCKER | C5: Platform providers are throw-stubs | D5: OPEN | E5: Slack, PagerDuty, AI and the status page are all unwired, so no incident can complete in a real workspace. | F5: Each stub names itself and production refuses to boot on any of them. Real adapters are S37-S38 and S41. V037: every contract the adapters must satisfy is async, budgeted and probed (PX-S0/S2) — the adapters are drop-ins, and the gate is proven to permit a healthy set. | G5: S37-S38, S41
A6: CF-003 | B6: BLOCKER | C6: Runtime ignored DATABASE_URL | D6: FIXED v0.36.0 | E6: Eight in-memory repositories were built while config demanded a database. | F6: Pg adapters for staging/production; production without a connection refuses to start. | G6: S37
A7: CF-004 | B7: BLOCKER | C7: README contradicted the runtime | D7: FIXED v0.36.0 | E7: It described an adapter swap the file did not perform. | F7: Deploying section rewritten; three tests now assert the README against the code. | G7: S36
A8: CF-005 | B8: BLOCKER | C8: Installed-workspace gate never populated | D8: FIXED v0.36.0 | E8: Every valid workspace would have been refused at /slack/commands. | F8: The installation repository is the authority; boot restore seeds from it. | G8: S38
A9: CF-006 | B9: BLOCKER | C9: Session resolver hardcoded to undefined | D9: FIXED v0.36.0 | E9: The whole administration and analytics plane answered 401 to everyone, including the owner. | F9: Signed, expiring, tenant-bound session cookie issued at the OAuth callback, with CSRF. | G9: S38
A10: CF-007 | B10: BLOCKER | C10: Async responses discarded as an empty 202 | D10: FIXED v0.36.0 | E10: Dashboard reads returned nothing in production; one security test asserted the 202 as correct. | F10: Real async routes; the offending test now asserts a real payload. | G10: S36
A11: CF-008 | B11: BLOCKER | C11: Delete/export detached from real data | D11: FIXED v0.36.0 | E11: A legal promise answered over an empty Map. | F11: Coordinator over six real tenant stores; inventory published at /api/data/inventory. | G11: S39
A12: CF-009 | B12: HIGH | C12: Retention omitted incidents and metrics | D12: FIXED v0.36.0 | E12: The published 30-day policy left behind the data customers actually ask about. | F12: Retention and export derive from one inventory. | G12: S39
A13: CF-010 | B13: BLOCKER | C13: Billing is a fake success provider | D13: OPEN | E13: No Stripe client exists; paid conversion cannot be trusted. | F13: The fake is named and refused in production. Real Stripe work is S40 and needs keys. | G13: S40
A14: CF-011 | B14: HIGH | C14: Notifications recording-only | D14: PARTIAL v0.36.0 | E14: Alerts and weekly metrics reached nobody. | F14: Webhook delivery when configured; weekly jobs registered per restored install. Email/Slack delivery is S42. | G14: S42
... A23: CF-020 | B23: MEDIUM | C23: Thin supply-chain controls | D23: PARTIAL v0.36.0 | E23: No container, SBOM or signing; package licence UNLICENSED. | F23: Dockerfile, engines, files and a CI image build added. SBOM, signing and the licence decision remain. | G23: S42-S43

Sheet External_Review_PX_V001
A1: INDEPENDENT REVIEW V001 (second reviewer) — Perplexity Computer, 16/09/2026 19:32 BST
A2: Verdict: CONTINUE at 6.1/10 — materially improved since V035, still not deployable; one new blocker class (sync boundary) and one regression blocker (unenforced limits). Scores: market demand 8.0, engineering discipline 9.0, architecture intent 7.5, architecture execution 5.5, test maturity 6.5, market attractiveness 5.0, product completeness 4.0, GTM readiness 3.0, enterprise readiness 3.0. After v0.37.0: 12 FIXED, 1 ADDRESSED (D-OC8 pending), 2 OPEN (own findings, with owners).
A3: ID | B3: Severity | C3: Finding | D3: State after v0.37.0 | E3: Why it mattered | F3: What was done / what remains | G3: Sprint
A4: PX-001 | B4: BLOCKER | C4: Entire platform boundary is synchronous; every unwired adapter needs async I/O | D4: FIXED V037 (PX-S0) | E4: CONFIRMED and wider than reported: OAuthClient, PaymentProvider and the live-sweep SlackApi were synchronous too — nine platform interfaces, not four. A `Promise<` grep over the feature core returned zero hits. | F4: All nine interfaces Promise-returning; IncidentWorkflow.declare/resolve/reopen, timeline capture, DegradationService, CircuitBreaker and the ack contract async; every platform call runs under a 10 s budget (timeout = degraded result, never a hang); AI call moved under the breaker; 26 suites migrated; new floating-promise rule over src/ and scripts/. | G4: PX-S0
A5: PX-002 | B5: BLOCKER | C5: Plan limits unenforced in the deployed composition: usage never increments | D5: FIXED V037 (PX-S1) | E5: CONFIRMED. claimWrite was called from tests/billingPersistence.test.ts only; recordWrite no-op'd whenever a meter was configured — always, in production. A regression of F-026/F-027. | F5: recordWrite deleted; declare() and reopen() await entitlements.claimWrite(); without a shared meter the in-process counter is still incremented; 80%/100% warnings surface in the declare message; monthly reset is a leased, once-per-cycle job. | G5: PX-S1
A6: PX-003 | B6: HIGH | C6: Two user-facing Slack paths sit outside the boot gate (response_url poster = console.log; views.open = bare lambda) | D6: FIXED V037 (PX-S2) | E6: CONFIRMED, and there were three: the OAuth client (ThrowingSlackOAuthAdapter) was also constructed and never inventoried. | F6: REQUIRED_PROVIDERS is a closed set of ten; ProviderSet is typed to exactly those keys (compile-time assertion); every provider implements healthcheck() and production probes all of them, refusing on the first failure by name; StdoutResponseUrlPoster and ThrowingModalOpener are named, honest stubs; composition moved into src/composition/runtime.ts so it is importable by tests. | G6: PX-S2
A7: PX-004 | B7: HIGH | C7: Queued declares are lost on SIGTERM — on every blue/green deploy | D7: FIXED V037 (PX-S2) | E7: CONFIRMED. The queue was private DeferredWork[] holding closures; Lifecycle drained the two DB sinks only. | F7: Deferred work is a persisted DESCRIPTOR (deferred_work table, migration 0014) written before the ack returns, leased while running, deleted after delivery; SlashCommandAck is Drainable and registered first with Lifecycle; restore() reloads pending rows; 3 attempts then a definite failure is posted; Lifecycle now re-checks pending per round (draining the queue produces sink rows). | G7: PX-S2
A8: PX-005 | B8: HIGH | C8: Key rotation is a promise with no possible caller (one key, id 'k1', forever) | D8: FIXED V037 (rotation path); KMS remains S43 (CF-012) | E8: CONFIRMED. Also found mechanically by audit v3 check A10 (rotate() tested, never called). | F8: EnvKeyVault loads every ENCRYPTION_KEY_<id>, ENCRYPTION_KEY_CURRENT selects; POST /ops/rotate-keys re-encrypts stored tokens under the current key, idempotent and resumable; boot warns while any record references a non-current key; TRUST_SECURITY.md states the limit (env keys until S43). | G8: S43 (pulled forward)
A9: PX-006 | B9: MEDIUM | C9: Leased jobs dedupe concurrency but not frequency; a daily sweep can run many times a day | D9: FIXED V037 (PX-S2) | E9: CONFIRMED. lastRun was process-local (0 after every restart); lease TTL 5 min vs 24 h interval. | F9: job_leases.last_run_at (migration 0013); acquireDue grants the lease only when the STORED last run is older than the interval; recordRun advances it; release keeps the row. | G9: PX-S2
A10: PX-007 | B10: MEDIUM | C10: PagingProvider.name is a two-value union that cannot express D-OC7's targets | D10: FIXED V037 (PX-S2) | E10: CONFIRMED. | F10: PagingProviderId = pagerduty | opsgenie | jsm | compass | webhook; config accepts all five; ThrowingPagingAdapter carries the configured id. | G10: PX-S2
A11: PX-008 | B11: MEDIUM | C11: Provider identity handed to the workflow is hardcoded ('pagerduty'), so audit/telemetry name the wrong provider | D11: FIXED V037 (PX-S2) | E11: CONFIRMED. | F11: The workflow receives the constructed adapter itself (field renamed name → id); wf.pagingProviderId() is asserted equal to the composition inventory. | G11: PX-S2
A12: PX-009 | B12: MEDIUM | C12: Financial model has never been computed; no cached values in any month column | D12: FIXED V037 (workbook) | E12: CONFIRMED and reproduced: M18 net +$444, cumulative −$213,302, 305 paying accounts at 12% conversion; −$4,565/mo at 10%, −$9,624/mo at 8%. | F12: All 18 month columns now carry computed values; a summary block (breakeven month, cash to breakeven, M18 ARR, contracts-per-Rootly-median) and two sensitivity scenarios (10% and 8% trial→paid) added as live formulas. | G12: S49
A13: PX-010 | B13: MEDIUM | C13: Sessions cannot be revoked; uninstall, role removal, cancellation and tenant deletion leave valid cookies for up to 12 h | D13: FIXED V037 (pulled into PX-S2 from S38, per the reviewer's answer 2) | E13: CONFIRMED. | F13: installEpoch claim in the token (the installation's own timestamp); the resolver refuses any token whose epoch is not the workspace's current one; uninstall clears it, reinstall mints a strictly newer one, data deletion forgets the in-process install record and evicts the tenant's workflow; bumpEpoch for admin revocation. No new store. | G13: PX-S2
A14: PX-011 | B14: MEDIUM | C14: Replay-protection window is bounded by row count, not time | D14: FIXED V037 (PX-S2) | E14: CONFIRMED. | F14: DedupeRepository.loadSince(now − SLACK_RETRY_WINDOW_MS, cap 50,000); the 6-hour window is documented against Slack's retry behaviour next to the 3 s ack budget. | G14: PX-S2
... A18: PX-015 | B18: LOW | C18: (Own finding, audit v3 A12) EventReceiver retry queue is not drained at shutdown | D18: OPEN | E18: CONFIRMED but low risk today: the runtime handler never returns false, so the queue never fills. | F18: Register with Lifecycle when the event handler does real work (S38); persist if events gain side effects. | G18: S38 / S42
A20: Review Part E — decisions asked of Senthil: (1) D-OC6 adopt CB-01, publish 54; (2) D-OC7 ratify and pull the Opsgenie importer forward to PX-S3; (3) pricing axis → bands (D-OC8, implemented reversibly); (4) D13 vs S49 — unpark discovery for this product; (5) D15 sequencing; (6) F-005/6/7 — already Option A. Plus the one non-sprint action that changes the score most: 30 minutes with a Slack workspace (SC-06).

Sheet Product_Spec
A1: PRODUCT SPEC — AS BUILT (re-baselined 13/09/2026 10:38; original 05/09 spec superseded)
A2: "Built" = implemented and covered by the 100% gate in sandbox. It does NOT mean verified against live Slack. V037: platform contracts are async; the adapters remain unwired (S38-S41).
A3: Module | B3: Built (as-built scope) | C3: Not built / out of scope | D3: Evidence
A4: /incident declare flow | B4: Slash-command ack within Slack 3s contract, deferred channel-create + post via response_url, Block Kit modal field spec, severity + status transitions, per-workspace incident store and id sequence, permission + audit enforcement | C4: Modal rendering itself (Block Kit JSON spec only), rich interactive follow-ups, multi-language | D4: src/incidents/*, src/http/app.ts; tests/declare, ack, http
A5: Responder paging (PD/Opsgenie) | B5: Provider interface with on-call resolution and fan-out, per-responder outcome reporting, targeted retry that never double-pages, degraded user comms naming who needs manual escalation | C5: Live provider certification, schedule editing UI, escalation-policy authoring | D5: src/paging/paging.ts; tests/paging, review-pass2
A6: Auto timeline capture | B6: Event ingest with config-driven bot/reaction filters, ordered per-incident view, markdown export, foreign-incident rejection downstream | C6: Threaded replies, file/attachment capture, retroactive backfill | D6: src/timeline/timeline.ts; tests/timeline
A7: AI postmortem draft | B7: Draft generation behind an AI provider interface, duration/impact computation, blameless template, refuses unresolved incidents and foreign timelines | C7: Live model wiring, editing workflow, template authoring UI | D7: src/postmortem/postmortem.ts; tests/postmortem, review-pass2
A8: Status page publish | B8: Component states with worst-of rollup, publisher interface, platform-error surfacing | C8: Live status-page vendor integration, subscriber management, custom domains | D8: src/statuspage/statuspage.ts; tests/statuspage
A9: Platform (not in the original spec, built anyway) | B9: HTTP app with 5 routes + signature verification, OAuth with CSRF state, per-workspace tenancy isolation, role assignment, 12h token rotation, retention purge, AES-256-GCM field crypto, billing lifecycle, telemetry, chat SLA engine, DB schema + migrations; V037: asynchronous platform boundary with a 10 s budget per call, persisted + leased deferred-work queue drained on SIGTERM, closed provider set with boot-time healthcheck probe, key rotation route, install-epoch session revocation, frequency-safe leased jobs, time-bounded replay window, scripts/ inside the coverage gate | C9: Real Slack/OAuth/Stripe/paging/AI/status adapters (now drop-ins), KMS vault, live deploy | D9: src/http, src/core/tenancy.ts, src/db/schema.ts, src/composition/runtime.ts, src/core/provider.ts, src/incidents/ack.ts, tests/px/*
A11: Non-functional requirement (05/09 claim) | B11: As-built status | C11: Evidence / what is missing
A12: Rate-limit safe (backoff + queue) | B12: MET in code | C12: Exponential backoff, circuit breaker, FIFO-capped dedupe, dead-letter after 5 attempts; tested; V037: breaker async and concurrency-safe, every platform call budgeted (timeout = degraded result); replay of degraded ops is still in-memory only (PX-014, S42)
A13: p95 <500ms API / <2s UI | B13: NOT MEASURED | C13: Budgets defined in src/core/latency.ts and a k6 harness exists, but no staging URL so nothing has ever been measured end to end
A14: 99.5% monthly uptime | B14: NOT MEASURABLE | C14: No deployment exists; blue/green workflow is drafted, not run
A15: WCAG AA | B15: PARTIAL | C15: jest-axe passes on 6 static shells; no audit on a rendered product, no manual/screen-reader pass (ST-089 remains In progress)
A16: SOC2-track controls | B16: PARTIAL | C16: RBAC, audit log, encryption, retention and data rights exist in code; no SOC2 process, no external assessment, pen test not booked

Sheet Screens_Wireframes
A1: SCREEN INVENTORY — AS BUILT (re-baselined 13/09/2026 10:38)
A2: No wireframes were ever produced. "Shell" = accessible semantic HTML audited by jest-axe; NO screen is wired to data because no dashboard API routes exist.
A3: # | B3: Screen | C3: Purpose | D3: As-built reality | E3: Gap to close
A4: 1 | B4: Onboarding / first-run | C4: Reach aha in <1 day | D4: Logic only — checklist, progress %, aha detection, empty-state copy in src/onboarding | E4: No shell, no surface
A5: 2 | B5: Home dashboard | C5: Daily habit surface | D5: Shell exists (static, empty-state copy) | E5: Shell + /api/incidents ready; render layer remains
A6: 3 | B6: Incident declare workspace | C6: Core value surface | D6: Primary surface is Slack itself (slash command + modal spec); web shell lists incidents statically | E6: Modal JSON rendering; live Slack
A7: 4 | B7: Responder paging builder | C7: Configure second pillar | D7: Logic only — provider interface, rules engine | E7: No shell; rule-builder UI unbuilt
A8: 5 | B8: Timeline view | C8: Differentiator surface | D8: Shell exists (static ordered list); markdown export implemented | E8: Shell + /api/incident ready; render layer remains
A9: 6 | B9: Settings & team | C9: Roles, notifications, data | D9: Shell exists with labelled form controls; role matrix + resolver now behind it | E9: Shell + /api/team ready; render layer remains
A10: 7 | B10: Billing | C10: Plan/trial/invoices | D10: Shell exists; full billing engine behind it (trial, proration, dunning, limits, invoices, cancellation) | E10: Shell + /api/billing (owner-gated) ready; Stripe live remains
A11: 8 | B11: Analytics | C11: Prove ROI | D11: Logic + /api/analytics backed by persisted funnel | E11: No shell; render layer remains
A12: 9 | B12: Help & support | C12: Deflect + assist | D12: Shell exists; 15 help articles drafted; built-in chat + 4-business-hour SLA engine behind it | E12: Data wiring; article hosting
A14: Summary: 6 of 9 screens have shells, 0 of 9 are data-wired, 0 have wireframes. This is the largest artifact-vs-code divergence in the product (AB-1).
A15: Update 13/09 10:42: 5 of 9 screens now have a data route behind them (dashboard, timeline, settings, billing, analytics). Still 0 rendered clients — the remaining gap is a front-end, not an API.
A16: UPDATE 13/09 11:38 — V17-08 RATIFIED (Option A, Slack-first): there will be no rendered web client for launch. The product surface is Slack: the declare modal, the incident channel message with resolve/mitigate/reopen controls, and the App Home dashboard — all now BUILT and validated against Slack limits (src/blockkit). The nine screens below remain as API-backed capabilities for support and analytics; they are deliberately unrendered, not unfinished.

Sheet Full_Backlog
A1: FULL BACKLOG
A3: ID | B3: Epic | C3: Story | D3: Points | E3: Priority | F3: Sprint | G3: Status
A4: ST-001 | B4: F1 | C4: As a SRE lead, I can set up /incident declare flow with sensible defaults in one screen | D4: 5 | E4: P0 | F4: S2 | G4: Done
A5: ST-002 | B5: F1 | C5: As a SRE lead, the /incident declare flow happy path completes without documentation | D5: 8 | E5: P0 | F5: S2 | G5: Done
A6: ST-003 | B6: F1 | C6: As a Eng director, I can customise /incident declare flow rules/conditions for my workflow | D6: 5 | E6: P1 | F6: S2 | G6: Done
A7: ST-004 | B7: F1 | C7: As a user, /incident declare flow shows clear errors and retry paths on platform API failures | D7: 3 | E7: P0 | F7: S2 | G7: Done
A8: ST-005 | B8: F1 | C8: As a Responder, /incident declare flow works on the Slack slash-commands + Block Kit modals surface end-to-end | D8: 5 | E8: P0 | F8: S3 | G8: Done
A9: ST-006 | B9: F1 | C9: As a Eng director, I can see /incident declare flow performance metrics and trends | D9: 3 | E9: P1 | F9: S3 | G9: Done
A10: ST-007 | B10: F1 | C10: As a user, /incident declare flow respects role permissions and audit logging | D10: 3 | E10: P1 | F10: S3 | G10: Done
A11: ST-008 | B11: F1 | C11: As a SRE lead, I can pause/disable /incident declare flow without data loss | D11: 2 | E11: P2 | F11: S3 | G11: Done
A12: ST-009 | B12: F1 | C12: As a Eng director, I can import/migrate existing data into /incident declare flow (CSV + competitor importer) | D12: 5 | E12: P1 | F12: S3 | G12: Done
A13: ST-010 | B13: F1 | C13: As a user, I get notifications (in-app + email) for key /incident declare flow events with per-type mute | D13: 3 | E13: P2 | F13: S3 | G13: Done
A14: ST-011 | B14: F2 | C14: As a SRE lead, I can set up Responder paging (PD/Opsgenie sync) with sensible defaults in one screen | D14: 5 | E14: P0 | F14: S3 | G14: Done
A15: ST-012 | B15: F2 | C15: As a SRE lead, the Responder paging (PD/Opsgenie sync) happy path completes without documentation | D15: 8 | E15: P0 | F15: S3 | G15: Done
... A133: ST-130 | B133: E7 | C133: EventReceiver retry queue registered with Lifecycle once the event handler does real work (PX-015) | D133: 1 | E133: P2 | F133: S38 | G133: Backlog
A135: Total stories: 130 (100 original + ST-101..ST-130 added at v037 for the Perplexity review sprints PX-S0..PX-S3 and A12 items). Epics: F1-F5 product features; E1 install, E5 billing, E6 compliance, E7 telemetry, E8 onboarding/docs/support, EQ quality, EL listing. Edit Status during execution. No original story was removed or re-labelled.

Sheet Sprint_Board
A1: SPRINT BOARD — live counts from Full_Backlog
A3: Sprint | B3: Focus | C3: Stories | D3: Points | E3: Done | F3: Exit criteria
A4: S0 | B4: Discovery & Design (2 wks) | C4: =COUNTIF(Full_Backlog!F4:F133,"S0") -> 0 | D4: =SUMIF(Full_Backlog!F4:F133,"S0",Full_Backlog!D4:D133) -> 0 | E4: =COUNTIFS(Full_Backlog!F4:F133,"S0",Full_Backlog!G4:G133,"Done") -> 0 | F4: PRD signed off; prototype tested with 5 target users
A5: S1 | B5: Foundation (2 wks) | C5: =COUNTIF(Full_Backlog!F4:F133,"S1") -> 4 | D5: =SUMIF(Full_Backlog!F4:F133,"S1",Full_Backlog!D4:D133) -> 13 | E5: =COUNTIFS(Full_Backlog!F4:F133,"S1",Full_Backlog!G4:G133,"Done") -> 1 | F5: App installs cleanly in dev store/org; telemetry firing
A6: S2 | B6: Core feature /incident declare flow - part 1 | C6: =COUNTIF(Full_Backlog!F4:F133,"S2") -> 6 | D6: =SUMIF(Full_Backlog!F4:F133,"S2",Full_Backlog!D4:D133) -> 29 | E6: =COUNTIFS(Full_Backlog!F4:F133,"S2",Full_Backlog!G4:G133,"Done") -> 6 | F6: /incident declare flow happy path demoable
A7: S3 | B7: Core feature /incident declare flow - part 2 + Responder paging (PD/Opsgenie sync) start | C7: =COUNTIF(Full_Backlog!F4:F133,"S3") -> 11 | D7: =SUMIF(Full_Backlog!F4:F133,"S3",Full_Backlog!D4:D133) -> 47 | E7: =COUNTIFS(Full_Backlog!F4:F133,"S3",Full_Backlog!G4:G133,"Done") -> 11 | F7: /incident declare flow complete with tests; Responder paging (PD/Opsgenie sync) skeleton
A8: S4 | B8: Core feature Responder paging (PD/Opsgenie sync) | C8: =COUNTIF(Full_Backlog!F4:F133,"S4") -> 9 | D8: =SUMIF(Full_Backlog!F4:F133,"S4",Full_Backlog!D4:D133) -> 34 | E8: =COUNTIFS(Full_Backlog!F4:F133,"S4",Full_Backlog!G4:G133,"Done") -> 9 | F8: MVP loop usable end-to-end internally
A9: S5 | B9: Feature Auto timeline capture + alpha hardening | C9: =COUNTIF(Full_Backlog!F4:F133,"S5") -> 12 | D9: =SUMIF(Full_Backlog!F4:F133,"S5",Full_Backlog!D4:D133) -> 50 | E9: =COUNTIFS(Full_Backlog!F4:F133,"S5",Full_Backlog!G4:G133,"Done") -> 12 | F9: Internal alpha: team dogfoods daily
A10: S6 | B10: Billing + AI postmortem draft | C10: =COUNTIF(Full_Backlog!F4:F133,"S6") -> 13 | D10: =SUMIF(Full_Backlog!F4:F133,"S6",Full_Backlog!D4:D133) -> 60 | E10: =COUNTIFS(Full_Backlog!F4:F133,"S6",Full_Backlog!G4:G133,"Done") -> 12 | F10: Can charge a test customer; upgrade/downgrade paths work
A11: S7 | B11: Private beta (design partners) | C11: =COUNTIF(Full_Backlog!F4:F133,"S7") -> 5 | D11: =SUMIF(Full_Backlog!F4:F133,"S7",Full_Backlog!D4:D133) -> 15 | E11: =COUNTIFS(Full_Backlog!F4:F133,"S7",Full_Backlog!G4:G133,"Done") -> 5 | F11: 3+ partners active weekly; NPS pulse >30
A12: S8 | B12: Beta iteration + Status page publish | C12: =COUNTIF(Full_Backlog!F4:F133,"S8") -> 22 | D12: =SUMIF(Full_Backlog!F4:F133,"S8",Full_Backlog!D4:D133) -> 87 | E12: =COUNTIFS(Full_Backlog!F4:F133,"S8",Full_Backlog!G4:G133,"Done") -> 18 | F12: Retention of beta cohort week-over-week >60%
A13: S9 | B13: Marketplace review prep | C13: =COUNTIF(Full_Backlog!F4:F133,"S9") -> 7 | D13: =SUMIF(Full_Backlog!F4:F133,"S9",Full_Backlog!D4:D133) -> 30 | E13: =COUNTIFS(Full_Backlog!F4:F133,"S9",Full_Backlog!G4:G133,"Done") -> 2 | F13: Review submission accepted into queue
A14: S10 | B14: Review remediation + docs | C14: =COUNTIF(Full_Backlog!F4:F133,"S10") -> 7 | D14: =SUMIF(Full_Backlog!F4:F133,"S10",Full_Backlog!D4:D133) -> 24 | E14: =COUNTIFS(Full_Backlog!F4:F133,"S10",Full_Backlog!G4:G133,"Done") -> 0 | F14: Marketplace approval obtained (or final remediation cycle)
A15: S11 | B15: Launch | C15: =COUNTIF(Full_Backlog!F4:F133,"S11") -> 3 | D15: =SUMIF(Full_Backlog!F4:F133,"S11",Full_Backlog!D4:D133) -> 8 | E15: =COUNTIFS(Full_Backlog!F4:F133,"S11",Full_Backlog!G4:G133,"Done") -> 1 | F15: First 10 installs; first 3 reviews; activation >40%
A16: S12 | B16: Iterate & scale decision | C16: =COUNTIF(Full_Backlog!F4:F133,"S12") -> 1 | D16: =SUMIF(Full_Backlog!F4:F133,"S12",Full_Backlog!D4:D133) -> 2 | E16: =COUNTIFS(Full_Backlog!F4:F133,"S12",Full_Backlog!G4:G133,"Done") -> 0 | F16: Growth model doc with CAC/LTV first estimates
A17: PX-S0 | B17: Async platform boundary (review Phase 0) | C17: =COUNTIF(Full_Backlog!F4:F133,"PX-S0") -> 7 | D17: =SUMIF(Full_Backlog!F4:F133,"PX-S0",Full_Backlog!D4:D133) -> 13 | E17: =COUNTIFS(Full_Backlog!F4:F133,"PX-S0",Full_Backlog!G4:G133,"Done")+COUNTIFS(Full_Backlog!F4:F133,"PX-S0",Full_Backlog!G4:G133,"Done — *") -> 7 | F17: tsc clean; no sync platform method in src/; suites back to 100/100/100/100
A18: PX-S1 | B18: Enforce what is sold (review Phase 0) | C18: =COUNTIF(Full_Backlog!F4:F133,"PX-S1") -> 7 | D18: =SUMIF(Full_Backlog!F4:F133,"PX-S1",Full_Backlog!D4:D133) -> 7 | E18: =COUNTIFS(Full_Backlog!F4:F133,"PX-S1",Full_Backlog!G4:G133,"Done")+COUNTIFS(Full_Backlog!F4:F133,"PX-S1",Full_Backlog!G4:G133,"Done — *") -> 7 | F18: enforcementWiring: limit+1 refused over the production composition; PRICING_FAQ regenerated
A19: PX-S2 | B19: Close the gate's blind spots (review Phase 0) | C19: =COUNTIF(Full_Backlog!F4:F133,"PX-S2") -> 11 | D19: =SUMIF(Full_Backlog!F4:F133,"PX-S2",Full_Backlog!D4:D133) -> 13 | E19: =COUNTIFS(Full_Backlog!F4:F133,"PX-S2",Full_Backlog!G4:G133,"Done")+COUNTIFS(Full_Backlog!F4:F133,"PX-S2",Full_Backlog!G4:G133,"Done — *") -> 11 | F19: CI proves the gate refuses AND permits; SIGTERM/kill -9 tests pass
A20: PX-S3 | B20: Opsgenie migration wedge (before S41; window closes 05/04/2027) | C20: =COUNTIF(Full_Backlog!F4:F133,"PX-S3") -> 3 | D20: =SUMIF(Full_Backlog!F4:F133,"PX-S3",Full_Backlog!D4:D133) -> 13 | E20: =COUNTIFS(Full_Backlog!F4:F133,"PX-S3",Full_Backlog!G4:G133,"Done")+COUNTIFS(Full_Backlog!F4:F133,"PX-S3",Full_Backlog!G4:G133,"Done — *") -> 0 | F20: A real Opsgenie export imported into a real workspace with a diff report
A21: S38 | B21: Real Slack runtime (A12 item ST-130 tracked here) | C21: =COUNTIF(Full_Backlog!F4:F133,"S38") -> 1 | D21: =SUMIF(Full_Backlog!F4:F133,"S38",Full_Backlog!D4:D133) -> 1 | E21: =COUNTIFS(Full_Backlog!F4:F133,"S38",Full_Backlog!G4:G133,"Done")+COUNTIFS(Full_Backlog!F4:F133,"S38",Full_Backlog!G4:G133,"Done — *") -> 0 | F21: npm run live-sweep passes 12 steps in a real workspace
A22: S42 | B22: SRE, observability, HA, DR (A12 item ST-129 tracked here) | C22: =COUNTIF(Full_Backlog!F4:F133,"S42") -> 1 | D22: =SUMIF(Full_Backlog!F4:F133,"S42",Full_Backlog!D4:D133) -> 3 | E22: =COUNTIFS(Full_Backlog!F4:F133,"S42",Full_Backlog!G4:G133,"Done")+COUNTIFS(Full_Backlog!F4:F133,"S42",Full_Backlog!G4:G133,"Done — *") -> 0 | F22: Chaos test killing Postgres mid-declare; replay queue persisted
B23: TOTAL (all 130 stories) | C23: =SUM(C4:C22) -> 130 | D23: =SUM(D4:D22) -> 449 | E23: =SUM(E4:E22) -> 102
B24: Velocity check: points/sprint S2-S8 should sit within 30-45 for a 4-6 person team; rebalance Sprint column in backlog if a sprint exceeds capacity.

Sheet Financial_Model
A1: 18-MONTH FINANCIAL MODEL — Slack: bottom-up team adoption (edit yellow assumptions)
A3: Assumption | B3: Value
A4: Team trials/mo (month 1) | B4: 55
A5: Monthly growth of that | B5: 0.12
A6: Trial->paid % | B6: 0.12
A7: ARPU $/mo | B7: 99
A8: Monthly churn | B8: 0.035
A9: Marketplace fee | B9: 0
A10: Team cost month 1 (India-lean $) | B10: 18000
A11: Cost growth/mo | B11: 0.03
A12: Fee note: No Slack revenue share; bill via Stripe
A14: Line | B14: M1 | C14: M2 | D14: M3 | E14: M4 | F14: M5 | G14: M6 | H14: M7 | I14: M8 | J14: M9 | K14: M10 | L14: M11 | M14: M12 | N14: M13 | O14: M14 | P14: M15 | Q14: M16 | R14: M17 | S14: M18
A15: Leads/installs | B15: =$B$4 -> 55 | C15: =B15*(1+$B$5) -> 61.6 | D15: =C15*(1+$B$5) -> 68.992 | E15: =D15*(1+$B$5) -> 77.27104 | F15: =E15*(1+$B$5) -> 86.543565 | G15: =F15*(1+$B$5) -> 96.928793 | H15: =G15*(1+$B$5) -> 108.56025 | I15: =H15*(1+$B$5) -> 121.58748 | J15: =I15*(1+$B$5) -> 136.17797 | ... S15: =R15*(1+$B$5) -> 377.63225
A16: New paying | B16: =ROUND(B15*$B$6,1) -> 6.6 | C16: =ROUND(C15*$B$6,1) -> 7.4 | D16: =ROUND(D15*$B$6,1) -> 8.3 | E16: =ROUND(E15*$B$6,1) -> 9.3 | F16: =ROUND(F15*$B$6,1) -> 10.4 | G16: =ROUND(G15*$B$6,1) -> 11.6 | H16: =ROUND(H15*$B$6,1) -> 13 | I16: =ROUND(I15*$B$6,1) -> 14.6 | ... S16: =ROUND(S15*$B$6,1) -> 45.3
A17: Paying accounts | B17: =B16 -> 6.6 | C17: =ROUND(B17*(1-$B$8)+C16,1) -> 13.8 | D17: =ROUND(C17*(1-$B$8)+D16,1) -> 21.6 | E17: =ROUND(D17*(1-$B$8)+E16,1) -> 30.1 | F17: =ROUND(E17*(1-$B$8)+F16,1) -> 39.4 | G17: =ROUND(F17*(1-$B$8)+G16,1) -> 49.6 | H17: =ROUND(G17*(1-$B$8)+H16,1) -> 60.9 | I17: =ROUND(H17*(1-$B$8)+I16,1) -> 73.4 | J17: =ROUND(I17*(1-$B$8)+J16,1) -> 87.1 | ... S17: =ROUND(R17*(1-$B$8)+S16,1) -> 305
A18: MRR (net of fee) | B18: =ROUND(B17*$B$7*(1-$B$9),0) -> 653 | C18: =ROUND(C17*$B$7*(1-$B$9),0) -> 1366 | D18: =ROUND(D17*$B$7*(1-$B$9),0) -> 2138 | E18: =ROUND(E17*$B$7*(1-$B$9),0) -> 2980 | F18: =ROUND(F17*$B$7*(1-$B$9),0) -> 3901 | G18: =ROUND(G17*$B$7*(1-$B$9),0) -> 4910 | H18: =ROUND(H17*$B$7*(1-$B$9),0) -> 6029 | I18: =ROUND(I17*$B$7*(1-$B$9),0) -> 7267 | ... S18: =ROUND(S17*$B$7*(1-$B$9),0) -> 30195
A19: Team cost | B19: =$B$10 -> 18000 | C19: =ROUND(B19*(1+$B$11),0) -> 18540 | D19: =ROUND(C19*(1+$B$11),0) -> 19096 | E19: =ROUND(D19*(1+$B$11),0) -> 19669 | F19: =ROUND(E19*(1+$B$11),0) -> 20259 | G19: =ROUND(F19*(1+$B$11),0) -> 20867 | H19: =ROUND(G19*(1+$B$11),0) -> 21493 | I19: =ROUND(H19*(1+$B$11),0) -> 22138 | J19: =ROUND(I19*(1+$B$11),0) -> 22802 | ... S19: =ROUND(R19*(1+$B$11),0) -> 29753
A20: Net cash/mo | B20: =B18-B19 -> -17347 | C20: =C18-C19 -> -17174 | D20: =D18-D19 -> -16958 | E20: =E18-E19 -> -16689 | F20: =F18-F19 -> -16358 | G20: =G18-G19 -> -15957 | H20: =H18-H19 -> -15464 | I20: =I18-I19 -> -14871 | ... S20: =S18-S19 -> 442
A21: Cumulative | B21: =B20 -> -17347 | C21: =B21+C20 -> -34521 | D21: =C21+D20 -> -51479 | E21: =D21+E20 -> -68168 | F21: =E21+F20 -> -84526 | G21: =F21+G20 -> -100483 | H21: =G21+H20 -> -115947 | I21: =H21+I20 -> -130818 | J21: =I21+J20 -> -144997 | ... S21: =R21+S20 -> -213312
A23: Reading: churn applies before adds; MRR nets the marketplace fee; costs use India-lean base from Team_Roles_Budget (v004). Breakeven = first month Net cash ≥ 0. This is a planning model, not a forecast — replace assumptions with S7-S8 beta actuals. COMPUTED at v037 (PX-009): the sheet had never been evaluated; every month column now carries a cached value and the summary below reads the answer.
A25: SUMMARY (live formulas over the model above) — Perplexity review V001 §3.5
A26: Breakeven month (first Net cash ≥ 0) | B26: =IFERROR("M"&MATCH(TRUE(),INDEX(B20:S20>=0,0),0),"not within 18 months") -> M18 | C26: Review: lands in the final month, with a $444 margin — 'a coincidence, not a plan'
A27: Net cash at M18 | B27: =S20 -> 442 | C27: +$444 at 12% trial→paid
A28: Cumulative cash at M18 (funding required if no other income) | B28: =S21 -> -213312 | C28: ≈ −$213k: the plan requires ~$215k of runway and never stated it
A29: Lowest cumulative position (peak funding need) | B29: =MIN(B21:S21) -> -213754
A30: Paying accounts at M18 | B30: =S17 -> 305 | C30: 305 — gate G-02 requires 10; the model and the gate describe different businesses
A31: ARR at M18 | B31: =S18*12 -> 362340 | C31: Median realised contracts (Vendr): Rootly $13,680/yr, FireHydrant $33,195/yr
A32: Customers per one median Rootly contract ($13,680/yr) | B32: =IFERROR(13680/(B7*12),0) -> 11.515152 | C32: Flat-pricing consequence, quantified (≈12 at $99 ARPU)
A33: Customers per one median FireHydrant contract ($33,195/yr) | B33: =IFERROR(33195/(B7*12),0) -> 27.941919 | C33: ≈28 — this is the figure the review rounded to '~27'; its attribution to Rootly is a slip
A34: Number formats: currency $#,##0; accounts 0.0. Assumptions (yellow, rows 4-11) are the workbook's own from 05/09; validate in S49.
A36: SENSITIVITY A — trial→paid 10% (all other assumptions as above)
A37: Trial→paid % (scenario) | B37: 0.1
A38: Line | B38: M1 | C38: M2 | D38: M3 | E38: M4 | F38: M5 | G38: M6 | H38: M7 | I38: M8 | J38: M9 | K38: M10 | L38: M11 | M38: M12 | N38: M13 | O38: M14 | P38: M15 | Q38: M16 | R38: M17 | S38: M18
A39: New paying | B39: =ROUND(B15*$B$37,1) -> 5.5 | C39: =ROUND(C15*$B$37,1) -> 6.2 | D39: =ROUND(D15*$B$37,1) -> 6.9 | E39: =ROUND(E15*$B$37,1) -> 7.7 | F39: =ROUND(F15*$B$37,1) -> 8.7 | G39: =ROUND(G15*$B$37,1) -> 9.7 | H39: =ROUND(H15*$B$37,1) -> 10.9 | I39: =ROUND(I15*$B$37,1) -> 12.2 | ... S39: =ROUND(S15*$B$37,1) -> 37.8
A40: Paying accounts | B40: =B39 -> 5.5 | C40: =ROUND(B40*(1-$B$8)+C39,1) -> 11.5 | D40: =ROUND(C40*(1-$B$8)+D39,1) -> 18 | E40: =ROUND(D40*(1-$B$8)+E39,1) -> 25.1 | F40: =ROUND(E40*(1-$B$8)+F39,1) -> 32.9 | G40: =ROUND(F40*(1-$B$8)+G39,1) -> 41.4 | H40: =ROUND(G40*(1-$B$8)+H39,1) -> 50.9 | I40: =ROUND(H40*(1-$B$8)+I39,1) -> 61.3 | J40: =ROUND(I40*(1-$B$8)+J39,1) -> 72.8 | ... S40: =ROUND(R40*(1-$B$8)+S39,1) -> 254.4
A41: MRR (net of fee) | B41: =ROUND(B40*$B$7*(1-$B$9),0) -> 545 | C41: =ROUND(C40*$B$7*(1-$B$9),0) -> 1139 | D41: =ROUND(D40*$B$7*(1-$B$9),0) -> 1782 | E41: =ROUND(E40*$B$7*(1-$B$9),0) -> 2485 | F41: =ROUND(F40*$B$7*(1-$B$9),0) -> 3257 | G41: =ROUND(G40*$B$7*(1-$B$9),0) -> 4099 | H41: =ROUND(H40*$B$7*(1-$B$9),0) -> 5039 | I41: =ROUND(I40*$B$7*(1-$B$9),0) -> 6069 | ... S41: =ROUND(S40*$B$7*(1-$B$9),0) -> 25186
A42: Team cost | B42: =B19 -> 18000 | C42: =C19 -> 18540 | D42: =D19 -> 19096 | E42: =E19 -> 19669 | F42: =F19 -> 20259 | G42: =G19 -> 20867 | H42: =H19 -> 21493 | I42: =I19 -> 22138 | ... S42: =S19 -> 29753
A43: Net cash/mo | B43: =B41-B42 -> -17455 | C43: =C41-C42 -> -17401 | D43: =D41-D42 -> -17314 | E43: =E41-E42 -> -17184 | F43: =F41-F42 -> -17002 | G43: =G41-G42 -> -16768 | H43: =H41-H42 -> -16454 | I43: =I41-I42 -> -16069 | ... S43: =S41-S42 -> -4567
A44: Cumulative | B44: =B43 -> -17455 | C44: =B44+C43 -> -34856 | D44: =C44+D43 -> -52170 | E44: =D44+E43 -> -69354 | F44: =E44+F43 -> -86356 | G44: =F44+G43 -> -103124 | H44: =G44+H43 -> -119578 | I44: =H44+I43 -> -135647 | J44: =I44+J43 -> -151242 | ... S44: =R44+S43 -> -247714
A45: Net at M18 / cumulative at M18 | B45: =S43 -> -4567 | C45: =S44 -> -247714
A47: SENSITIVITY B — trial→paid 8%
A48: Trial→paid % (scenario) | B48: 0.08
A49: Line | B49: M1 | C49: M2 | D49: M3 | E49: M4 | F49: M5 | G49: M6 | H49: M7 | I49: M8 | J49: M9 | K49: M10 | L49: M11 | M49: M12 | N49: M13 | O49: M14 | P49: M15 | Q49: M16 | R49: M17 | S49: M18
A50: New paying | B50: =ROUND(B15*$B$48,1) -> 4.4 | C50: =ROUND(C15*$B$48,1) -> 4.9 | D50: =ROUND(D15*$B$48,1) -> 5.5 | E50: =ROUND(E15*$B$48,1) -> 6.2 | F50: =ROUND(F15*$B$48,1) -> 6.9 | G50: =ROUND(G15*$B$48,1) -> 7.8 | H50: =ROUND(H15*$B$48,1) -> 8.7 | I50: =ROUND(I15*$B$48,1) -> 9.7 | ... S50: =ROUND(S15*$B$48,1) -> 30.2
A51: Paying accounts | B51: =B50 -> 4.4 | C51: =ROUND(B51*(1-$B$8)+C50,1) -> 9.1 | D51: =ROUND(C51*(1-$B$8)+D50,1) -> 14.3 | E51: =ROUND(D51*(1-$B$8)+E50,1) -> 20 | F51: =ROUND(E51*(1-$B$8)+F50,1) -> 26.2 | G51: =ROUND(F51*(1-$B$8)+G50,1) -> 33.1 | H51: =ROUND(G51*(1-$B$8)+H50,1) -> 40.6 | I51: =ROUND(H51*(1-$B$8)+I50,1) -> 48.9 | J51: =ROUND(I51*(1-$B$8)+J50,1) -> 58.1 | ... S51: =ROUND(R51*(1-$B$8)+S50,1) -> 203.3
A52: MRR (net of fee) | B52: =ROUND(B51*$B$7*(1-$B$9),0) -> 436 | C52: =ROUND(C51*$B$7*(1-$B$9),0) -> 901 | D52: =ROUND(D51*$B$7*(1-$B$9),0) -> 1416 | E52: =ROUND(E51*$B$7*(1-$B$9),0) -> 1980 | F52: =ROUND(F51*$B$7*(1-$B$9),0) -> 2594 | G52: =ROUND(G51*$B$7*(1-$B$9),0) -> 3277 | H52: =ROUND(H51*$B$7*(1-$B$9),0) -> 4019 | I52: =ROUND(I51*$B$7*(1-$B$9),0) -> 4841 | ... S52: =ROUND(S51*$B$7*(1-$B$9),0) -> 20127
A53: Team cost | B53: =B19 -> 18000 | C53: =C19 -> 18540 | D53: =D19 -> 19096 | E53: =E19 -> 19669 | F53: =F19 -> 20259 | G53: =G19 -> 20867 | H53: =H19 -> 21493 | I53: =I19 -> 22138 | ... S53: =S19 -> 29753
A54: Net cash/mo | B54: =B52-B53 -> -17564 | C54: =C52-C53 -> -17639 | D54: =D52-D53 -> -17680 | E54: =E52-E53 -> -17689 | F54: =F52-F53 -> -17665 | G54: =G52-G53 -> -17590 | H54: =H52-H53 -> -17474 | I54: =I52-I53 -> -17297 | ... S54: =S52-S53 -> -9626
A55: Cumulative | B55: =B54 -> -17564 | C55: =B55+C54 -> -35203 | D55: =C55+D54 -> -52883 | E55: =D55+E54 -> -70572 | F55: =E55+F54 -> -88237 | G55: =F55+G54 -> -105827 | H55: =G55+H54 -> -123301 | I55: =H55+I54 -> -140598 | J55: =I55+J54 -> -157648 | ... S55: =R55+S54 -> -282720
A56: Net at M18 / cumulative at M18 | B56: =S54 -> -9626 | C56: =S55 -> -282720
A58: Reading (review §3.5): a 4-point conversion miss removes breakeven from the horizon and adds ~$70k of burn. Bands (D-OC8) change ARPU, not this arithmetic — re-run with the S49 price-test results.

Sheet GTM_Execution
A1: GTM EXECUTION TASKS
A3: Phase | B3: Task | C3: Owner (role) | D3: Target sprint
A4: Pre-launch | B4: Positioning doc + message house (problem/promise/proof) | C4: Founder | D4: S7
A5: Pre-launch | B5: Listing SEO: keyword study in marketplace search + title/intro drafts | C5: Growth | D5: S8
A6: Pre-launch | B6: 10 design-partner mini case snippets with metric proof | C6: Founder | D6: S8
A7: Pre-launch | B7: 5 comparison/alternative pages drafted | C7: Growth | D7: S9
A8: Pre-launch | B8: Screenshots (5) + 2-min demo video produced | C8: Design | D8: S9
A9: Launch | B9: Listing live + launch post + video published | C9: Growth | D9: S11
A10: Launch | B10: Founder outreach: 100 named ICP accounts, 3-touch sequence | C10: Founder | D10: S11
A11: Launch | B11: Community value-posts (3 relevant communities) | C11: Founder | D11: S11
A12: Launch | B12: Review-generation program on (in-app ask post-aha) | C12: Eng | D12: S11
A13: Post-launch | B13: Weekly SEO/how-to content cadence starts | C13: Growth | D13: S12
A14: Post-launch | B14: Marketplace paid placement pilot (where offered) | C14: Growth | D14: S12
... A16: Post-launch | B16: G2/Capterra profiles + first 10 reviews | C16: Growth | D16: S12+

Sheet Launch_Checklist
A1: PLATFORM LAUNCH CHECKLIST — Slack App Directory
A3: # | B3: Item | C3: Status
A4: 1 | B4: Slack app manifest finalized; granular scopes minimal + justified | C4: Code-complete
A5: 2 | B5: App Directory review: security questionnaire, scope rationale, support URL | C5: Open
A6: 3 | B6: Enterprise Grid + org-wide install flows tested in sandbox | C6: Open
A7: 4 | B7: Socket Mode vs Events API decision documented; retry/dedupe at burst load | C7: Code-complete
A8: 5 | B8: PagerDuty / JSM / Compass / webhook integrations certified; Opsgenie IMPORTER (migration wedge, PX-S3) shipped before deep parity | C8: Open
A9: 6 | B9: Incident data retention policy + export/delete self-serve | C9: Code-complete
A10: 7 | B10: Block Kit surfaces pass accessibility review | C10: Open
A11: 8 | B11: Status page publish integration tested (Statuspage/instatus class) | C11: Open
A12: 9 | B12: Directory listing assets: icon, screenshots, demo GIF per guidelines | C12: Open
A13: 10 | B13: Pricing page + Stripe checkout + team-size (band) detection live — banded model per D-OC8 | C13: Open
A14: 11 | B14: Production composition contains no stub or in-memory adapter (review gate CB-02) — GET /ops/composition is clean | C14: Open — the gate now probes healthcheck() as well as names and is proven to permit a healthy composition; it correctly refuses today naming all ten providers
A15: 12 | B15: External review findings dispositioned; all P0 (S36-S41) closed before submission (review gate G0/G2) | C15: In progress — 9/20 CF fixed; 12/15 PX fixed; Phase 0 (PX-S0..S2) closed before any adapter sprint
... A18: 15 | B18: Financial model computed and read before S49; pricing validated on the banded model with design partners | C18: Model computed; validation open (S49)

Sheet Metrics_Targets
A1: METRIC TARGETS — with measurability audit (re-baselined 13/09/2026 10:38)
A2: Targets unchanged from 05/09. The audit column is new: today NONE can be reported end to end, because telemetry is in-process only with no persistence and no dashboard.
A3: Metric | B3: M1 | C3: M3 | D3: M6 | E3: M12 | F3: Measurable today? | G3: What it needs
A4: Installs/signups cumulative | B4: varies | C4: 3x M1 | D4: 8x M1 | E4: 20x M1 | F4: YES once adapter wired | G4: Install attribution + repository exist; needs live DATABASE_URL
A5: Activation % (24h) | B5: 30% | C5: 40% | D5: 45% | E5: 50% | F5: YES (per tenant) | G5: Funnel persisted via MetricsRepository; /api/analytics reports it
A6: Trial→paid % | B6: baseline | C6: +2pts | D6: +4pts | E6: +6pts | F6: NO | G6: Billing events persisted + live Stripe
A7: Rating | B7: 4.5+ | C7: 4.6+ | D7: 4.7+ | E7: 4.7+ | F7: NO | G7: Listing live; review-monitoring (ST-100) is Backlog
A8: MRR | B8: first $ | C8: 3x | D8: 8x | E8: 20x | F8: NO | G8: Live Stripe
A9: Logo churn/mo | B9: <5% | C9: <4% | D9: <3% | E9: <3% | F9: NO | G9: Persistence + at least one billing cycle of live data
A11: Launch prerequisite (AB-3): without the Postgres adapter, the product can launch but cannot report on itself — the S12 kill/continue gate would have no evidence. Flagged as a risk, not a story.
A12: Update 13/09 10:42: the persistence layer exists (both adapters, one contract suite). Activation is reportable per tenant today; the rest still need live Stripe or a live listing, not more code.
A13: Update 20/09/2026: the activation targets (30%→50%) now have an owner sprint (S47) per the review; trial→paid and MRR targets must be re-based on the banded model (D-OC8) and the computed Financial_Model (12% conversion is the assumption the whole plan rests on — S49 validates it).

Sheet Risk_Register
A1: PRODUCT RISK REGISTER
A3: Risk | B3: Impact | C3: Likelihood | D3: Mitigation
A4: incident.io/Rootly move down-market on price | B4: High | C4: Realised | D4: incident.io Basic is now free (Slack-native response, single-team on-call, status page): four of five modules matched. Response: S45 elevated to primary differentiator; positioning rewritten around seat-count independence (83-99% saving for 30-500 engineers, not '40-50%'); bands (D-OC8)
A5: Slack platform pricing/API changes (post-Salesforce) | B5: Medium | C5: Medium | D5: Events architecture abstraction; export path
A6: Bottom-up adoption stalls without champion | B6: Medium | C6: High | D6: Champion enablement kit; free tier for 1 service
A7: No platform adapter is wired (CF-002): Slack, paging, AI and status page are named stubs, so no incident can complete in a real workspace | B7: Critical | C7: Certain | D7: Explicit rather than commented — production boot refuses and names each one. S37-S38 closes it; needs the Slack workspace.
A8: Opsgenie support ends 5 Apr 2027 and new sales have stopped (CF-019) | B8: Medium | C8: Certain | D8: D-OC7: migration connector as the wedge; PagerDuty/JSM/Compass as primary targets.
A9: Enterprise positioning is unsupportable today: no SSO/SCIM/Grid, no KMS, no pen test, no live evidence (CF-012/016/017) | B9: High | C9: High | D9: Gate G0 adopted — do not market as enterprise-ready until S42-S44 and S48 close.
A10: Self-review has a floor: twenty-eight internal releases and four self-review passes left ten blockers standing | B10: High | C10: Realised | D10: External review is now a release input, not a launch formality (SC-09).
A11: Flat $99 leaves no expansion revenue; the computed model needs 305 paying workspaces and ~$215k of runway to reach a $444/mo surplus at M18 | B11: High | C11: High | D11: Financial_Model computed with sensitivities; banded pricing (D-OC8); S49 price tests on bands; runway stated plainly
A12: Opsgenie migration window (support ends 05/04/2027) expires before the product can be sold into it | B12: High | C12: High | D12: PX-S3 importer sequenced before S41; needs D-OC7 ratified now
A13: The flat-per-workspace wedge is already occupied (Incident/Ops) | B13: Medium | C13: Certain | D13: Differentiate on bands + incident memory (S45), not on 'flat'
A14: Degraded platform ops are queued in memory and never replayed; receiver retry queue not drained at shutdown (PX-014/015) | B14: Medium | C14: Medium | D14: ST-129 (S42), ST-130 (S38); visible on every audit run (A12)
A15: Band enforcement (D-OC8) depends on users.list from the real Slack adapter — until S38 no workspace is ever 'over' its band | B15: Low | C15: Certain (until S38) | D15: Documented in PRICING_FAQ; S38 records the count at install and daily

Sheet Traceability_Matrix
A1: TRACEABILITY MATRIX — story -> code module -> test suite (release v008, 10/09/2026 22:22)
A3: ID | B3: Epic | C3: Sprint | D3: Module / File | E3: Test Suite | F3: Status | G3: Evidence / Notes | H3: Runtime reachable? (v0.37.0)
A4: ST-001 | B4: F1 | C4: S2 | D4: src/core/featureCore.ts | E4: tests/featureCore.test.ts | F4: Done | G4: Implemented, 100% coverage | H4: Yes — configuration reachable at /api/features/*
A5: ST-002 | B5: F1 | C5: S2 | D5: src/incidents/declare.ts | E5: tests/declare.test.ts | F5: Done | G5: Implemented, 100% coverage | H5: No — Slack channel/message adapters unwired (CF-002, S38)
A6: ST-003 | B6: F1 | C6: S2 | D6: src/core/featureCore.ts | E6: tests/featureCore.test.ts | F6: Done | G6: Implemented, 100% coverage | H6: Yes — configuration reachable at /api/features/*
A7: ST-004 | B7: F1 | C7: S2 | D7: src/incidents/declare.ts | E7: tests/declare.test.ts | F7: Done | G7: Implemented, 100% coverage | H7: No — Slack channel/message adapters unwired (CF-002, S38)
A8: ST-005 | B8: F1 | C8: S3 | D8: src/incidents/declare.ts | E8: tests/declare.test.ts | F8: Done | G8: Implemented, 100% coverage | H8: No — Slack channel/message adapters unwired (CF-002, S38)
A9: ST-006 | B9: F1 | C9: S3 | D9: src/core/featureCore.ts | E9: tests/featureCore.test.ts | F9: Done | G9: Implemented, 100% coverage | H9: Yes — configuration reachable at /api/features/*
A10: ST-007 | B10: F1 | C10: S3 | D10: src/core/featureCore.ts | E10: tests/featureCore.test.ts | F10: Done | G10: Implemented, 100% coverage | H10: Yes — configuration reachable at /api/features/*
A11: ST-008 | B11: F1 | C11: S3 | D11: src/core/featureCore.ts | E11: tests/featureCore.test.ts | F11: Done | G11: Implemented, 100% coverage | H11: Yes — configuration reachable at /api/features/*
A12: ST-009 | B12: F1 | C12: S3 | D12: src/core/featureCore.ts | E12: tests/featureCore.test.ts | F12: Done | G12: Implemented, 100% coverage | H12: Yes — configuration reachable at /api/features/*
A13: ST-010 | B13: F1 | C13: S3 | D13: src/core/featureCore.ts | E13: tests/featureCore.test.ts | F13: Done | G13: Implemented, 100% coverage | H13: Yes — configuration reachable at /api/features/*
A14: ST-011 | B14: F2 | C14: S3 | D14: src/core/featureCore.ts | E14: tests/featureCore.test.ts | F14: Done | G14: Implemented, 100% coverage | H14: Yes — configuration reachable at /api/features/*
... A133: ST-130 | B133: E7 | C133: S38 | D133: src/events/receiver.ts (planned) | E133: planned | F133: Backlog | G133: A12 open item; low risk today | H133: No — not built
A135: Coverage evidence: 60 suites / 624 tests (616 run, 8 gated on a real Postgres) at 100% statements, branches, functions and lines over src/ AND scripts/; clean tsc over src+scripts and tests (v0.37.0). scripts/ is inside the gate for the first time (A9). Reachability of ST-001..ST-100 deliberately unchanged from V036: PX-S0..S2 make the adapters drop-ins; wiring them is S38 (needs SC-06).

Sheet Sprint_Tracker_Log
A1: SPRINT TRACKER LOG — OnCall Copilot (Slack)
A3: Date | B3: Time | C3: Sprint | D3: Activity | E3: Output / Evidence | F3: Status
A4: 10/09/2026 | B4: 22:22 | C4: - | D4: Session opened on directive: sprint tracker + traceability + next-version workbook + complete development with 100% automation testing (D13) | E4: This log; v007 taken as baseline | F4: Done
A5: 10/09/2026 | B5: 22:24 | C5: S1 | D5: Foundation: project scaffold (TypeScript/Node, Jest 100% coverageThreshold), error model, role matrix, OAuth install lifecycle, install telemetry | E5: src/core, src/install; ST-053/054/056 Done; ST-051/052/055 code-complete pending live Slack | F5: Done
A6: 10/09/2026 | B6: 22:24 | C6: S2-S3 | D6: F1 /incident declare: slash-command service, Block Kit modal spec, channel create + post, error/retry, permissions; shared feature framework (setup/rules/pause/import/notify/metrics) for all features | E6: src/incidents/declare.ts, src/core/featureCore.ts; ST-001..010 Done | F6: Done
A7: 10/09/2026 | B7: 22:24 | C7: S3-S4 | D7: F2 responder paging: PagerDuty/Opsgenie provider interface, on-call resolution, page fan-out, failure surfacing; telemetry funnel + error-spike alerts | E7: src/paging, src/telemetry; ST-011..020, ST-071/072 Done | F7: Done
A8: 10/09/2026 | B8: 22:24 | C8: S5 | D8: F3 auto timeline capture: event ingest, bot filtering, ordered per-incident view, markdown export; onboarding checklist + empty states | E8: src/timeline, src/onboarding; ST-021..030, ST-078/079 Done | F8: Done
A9: 10/09/2026 | B9: 22:24 | C9: S6 | D9: F4 AI postmortem draft behind provider interface; E5 billing: trial/proration/dunning/limits/invoices/cancellation (live Stripe pending ST-059) | E9: src/postmortem, src/billing; ST-031..040, ST-057/058/060..063 Done | F9: Done
A10: 10/09/2026 | B10: 22:24 | C10: S8 | D10: F5 status page publish + worst-of overall state; E6 scope map, data rights export/delete, backoff + circuit breaker, audit log; p95 latency budgets | E10: src/statuspage, src/compliance, src/core/latency.ts; ST-041..050, ST-064/067/069/070, ST-087 Done | F10: Done
A11: 10/09/2026 | B11: 22:24 | C11: EQ | D11: Automation testing to D13 gate: 16 Jest suites, 105 tests, 100/100/100/100 coverage enforced in config; E2E smoke lifecycle suite; CI workflow runs on every push | E11: jest --coverage output; tests/smoke.e2e.test.ts; .github/workflows/ci.yml; ST-085/086 Done | F11: Done
A12: 10/09/2026 | B12: 22:24 | C12: - | D12: Workbook v008: Sprint_Tracker_Log + Traceability_Matrix added; Full_Backlog statuses updated (75 Done / 5 Code-complete / 2 In progress / 18 Backlog); Sprint_Board recalculated | E12: This workbook | F12: Done
A13: 10/09/2026 | C13: S9+ | D13: NEXT: live Slack dev-store install (ST-051/052/055), Stripe live (ST-059), infra encryption verification (ST-066), then S9 review-prep items; D15 sequencing decision open (now 4 concurrent builds) | E13: - | F13: Open
A14: 10/09/2026 | B14: 22:55 | C14: S8 | D14: Events API receiver built (Launch_Checklist #4): HMAC signature verify, 5-min replay guard, event dedupe on Slack retries, retry queue w/ exponential backoff + dead-letter after 5 attempts | E14: src/events/receiver.ts; 10 tests; checklist #4 -> Code-complete (live burst validation pending) | F14: Done
A15: 10/09/2026 | B15: 22:55 | C15: S8-S9 | D15: ST-091 graceful degradation: circuit-breaker-wrapped platform calls, user-facing outage comms per provider, replay queue + recovery path — outage simulated and tested. ST-074 scheduler wired to weekly metrics email | E15: src/core/degradation.ts, src/scheduler/scheduler.ts; both stories Done | F15: Done
A16: 10/09/2026 | B16: 22:55 | C16: S9-S10 | D16: Launch content drafted: listing copy A+B (ST-093), pricing matrix+FAQ (ST-095), security/trust page (ST-096, closes ST-065 draft), launch runbook (ST-098), incident comms templates (ST-084), 15 help articles (ST-080), k6 5x load script (ST-088) | E16: docs/*.md, loadtest/k6-launch-load.js; all marked Drafted pending review/hosting/staging | F16: Done
A17: 10/09/2026 | B17: 22:55 | C17: EQ | D17: Full suite re-run after additions: 19 suites / 122 tests, 100/100/100/100 held; tsc clean; workbook v009 released | E17: jest --coverage; this workbook | F17: Done
A18: 10/09/2026 | C18: S9+ | D18: NEXT (Senthil-gated): Slack dev workspace + signing secret for live install (ST-051/052/055), Stripe live (ST-059), infra encryption evidence (ST-066), pen-test vendor (ST-068), chat vendor (ST-081), listing A/B pick + reviewer (ST-093/097), staging URL for k6 (ST-088); D15 sequencing decision | E18: - | F18: Open
A19: 10/09/2026 | B19: 23:03 | C19: - | D19: Standalone tracker released: claude_v001_oncallcopilot_sprint_tracker_traceability_20260910_2303.xlsx (TeleField template) — E001-E010 across both runs, V008+V009 build boards, 11-col traceability, live rollup (77 Done/311 pts), RAID, D7 gate checklist; D-OC1/2/3 flagged for ratification | E19: Tracker v001 | F19: Done
A20: 10/09/2026 | B20: 23:10 | C20: S1-live prep | D20: Live-readiness: typed config loader (fail-fast, all vars listed, redacted summary), 12-step scripted live verification sweep (8 auto + 4 operator steps, dry-run stub, failure/exception paths tested), 30-min dev-workspace guide with least-privilege manifest.json + .env.example, npm run live-sweep CLI | E20: src/core/config.ts, src/live/sweep.ts, docs/DEV_WORKSPACE_SETUP.md, scripts/live-sweep.ts | F20: Done
A21: 10/09/2026 | B21: 23:10 | C21: EQ | D21: D13 gate re-verified after additions: 21 suites / 133 tests, 100/100/100/100; tsc clean. Workbook v010 released — no story status changes (readiness work, not story scope); live sweep IS the S1-live exit script | E21: jest --coverage; this workbook | F21: Done
A22: 10/09/2026 | C22: S1-live | D22: NEXT: Senthil runs DEV_WORKSPACE_SETUP.md (30 min) then npm run live-sweep — all 12 green flips ST-051/052/055 Code-complete -> Done and closes LC-1/LC-3 evidence; Stripe keys separately for ST-059; D15 still open | E22: - | F22: Open
A23: 11/09/2026 | B23: 08:41 | C23: S9-S10 | D23: COLD-REVIEW PASS 1 (EngageOS pattern): 4 defects found + FIXED with regressions — F-001 payment-recovery path missing (read-only permanent), F-002 usage never reset per cycle, F-003 unbounded dedupe ledger -> FIFO 10k, F-004 timeline config knobs dead. F-005..F-008 logged in new Review_Findings sheet for disposition. REVIEW_PACK.md added for external reviewer (ST-097 -> In progress; same-AI review not independent) | E23: Review_Findings; docs/REVIEW_PACK.md | F23: ST-097 In progress | G23: F-005/006/007 dispositions = Senthil | H23: next entry
A24: 11/09/2026 | B24: 08:41 | C24: S10 | D24: OPS PARITY PACK (ShiftDesk pattern): blue/green deploy workflow (approval-gated switch, warm-blue rollback, 100x4 gate blocks deploy) + 6-step scripted backup/restore drill (checksum, row-count parity, spot-read). ST-092/ST-090 Backlog -> Drafted | E24: ST-090,ST-092 | F24: 2 stories Drafted | G24: Real infra/Postgres = Senthil | H24: next entry
A25: 11/09/2026 | B25: 08:41 | C25: EQ | D25: Gate re-met: 22 suites / 139 tests, 100/100/100/100; tsc clean; codebase v0.11.0. Workbook v011 released — 77 Done / 5 Code-complete / 10 Drafted / 1 In progress / 7 Backlog (remaining Backlog all external: pen test, chat vendor, demo video, WCAG-live, listing assets, SEO, review-monitoring) | E25: jest --coverage; this workbook | F25: v011 Released | G25: — | H25: tracker v003
A26: 11/09/2026 | B26: 12:51 | C26: S9-S10 | D26: SIBLING-VALIDATED CODEABLE SCOPE: ST-066 encryption-at-rest built (AES-256-GCM field crypto behind SecretsVault boundary, key-ID rotation, tamper detection — FlowCast pattern); ST-068 sandbox half (SECURITY_EVIDENCE.md: threat model, control->test map, pen-test vendor brief) -> In progress; ST-081 in-app chat + 4-business-hr SLA engine (breach detection over business-time calendar, escalation) -> Code-complete, chat VENDOR NOW OPTIONAL (TeleField precedent); ST-089 automated WCAG AA half: 6 accessible screen shells + jest-axe suite green in CI -> In progress | E26: ST-066/068/081/089 | F26: Backlog 7 -> 4; one jsdom-pragma test-config slip fixed pre-release | G26: ST-089 live audit + pen test + F-dispositions = Senthil | H26: next entry
A27: 11/09/2026 | B27: 12:51 | C27: EQ | D27: Gate re-met: 25 suites / 156 tests, 100/100/100/100; tsc clean; codebase v0.12.0. Workbook v012 released — 77 Done / 6 Code-complete / 10 Drafted / 3 In progress / 4 Backlog (083 demo video, 094 listing assets, 099 SEO, 100 review monitoring — all external). SANDBOX-CODEABLE BACKLOG NOW FULLY EXHAUSTED: every remaining item needs Senthil or a live platform | E27: jest --coverage; this workbook | F27: v012 Released | G27: Full queue on Senthil side | H27: tracker v004
A28: 13/09/2026 | B28: 09:54 | C28: S9-S10 | D28: COLD-REVIEW PASS 2 over the modules pass 1 skipped (install, paging, postmortem, telemetry, featureCore import, compliance): 5 defects found + FIXED with pinned regressions — F-009 retention sweep never deleted anything (published policy breached), F-010 unbounded error ledger, F-011 paging fan-out lost partial success (double-page on retry), F-012 postmortem accepted a foreign incident timeline, F-013 CSV import broke on quoted fields -> new RFC-4180 csv.ts | E28: F-009..F-013 | F28: 5 fixes + 11 regressions | G28: — | H28: next entry
A29: 13/09/2026 | B29: 09:54 | C29: S9-S10 | D29: EXTERNAL VERIFICATION SWEEP vs live Slack platform docs (FlowCast/VoiceBridge pattern): VER-OC1 LIVE-BLOCKING — slash commands must ack within 3s or Slack times out AND retries, and declare() worked synchronously in that path => duplicate incident channels on the day; fixed with ack-first + response_url delivery. VER-OC2 conversations.create naming/name_taken rules (archived channels block reuse) fixed with slugifier + deterministic suffixing. VER-OC3 12h token TTL + single-use refresh token: expiry tracking + proactive refresh at 2h margin. VER-OC4 verified correct (retry x3 ~1 min apart — our dedupe handles it) | E29: VER-OC1..OC4 | F29: 3 fixes + 1 verified-correct | G29: Live burst validation still needs workspace | H29: next entry
A30: 13/09/2026 | B30: 09:54 | C30: EQ | D30: Gate: 27 suites / 180 tests, 100/100/100/100; tsc clean; codebase v0.13.0. Two pre-existing paging tests asserted the old throw-on-failure contract and were deliberately rewritten to the new PagingOutcome contract (documented in-file). Workbook v013 released; story counts unchanged (correctness release, no new stories) | E30: jest --coverage; this workbook | F30: v013 Released | G30: — | H30: tracker v005
A31: 13/09/2026 | B31: 10:01 | C31: S9-S10 | D31: ARTIFACT-GAP AUDIT (FlowCast/VoiceBridge/TestPulse pattern — cross-check every artifact our docs and scripts reference against what exists): 5 gaps found, 2 CRITICAL. GAP-OC1 NO HTTP APP EXISTED — manifest/setup-guide/k6 all pointed at routes nothing served, so the 30-minute setup was impossible and the live sweep would have died at SW-09. GAP-OC2 NO DATABASE SCHEMA — the backup drill queried tables that were never defined and the retention sweep had nothing to delete from. GAP-OC3 k6 had no way to produce signed payloads. GAP-OC4 manifest.json existed only inside a markdown fence. GAP-OC5 pricing doc ungated against billing.ts | E31: GAP-OC1..OC5 | F31: All 5 fixed | G31: Live run still needs workspace + Postgres | H31: next entry
A32: 13/09/2026 | B32: 10:01 | C32: S10 | D32: BUILT: router + app wiring all five routes (signature verification, 3-second ack contract, oauth callback, health) + npm start shell; 5 ordered migrations with cascade deletes and a drill-vs-schema parity test + npm run migrate; signed load-fixture generator; manifest.json at repo root incl. the previously-missing slash-command URL; pricing matrix generated from billing.ts with a drift gate. ST-088/ST-090 Drafted -> Code-complete (their blocking artifacts now exist) | E32: ST-088,ST-090 | F32: 2 stories advanced | G32: Staging URL + Postgres = Senthil | H32: next entry
A33: 13/09/2026 | B33: 10:01 | C33: EQ | D33: Gate: 31 suites / 201 tests, 100/100/100/100; tsc clean; codebase v0.14.0. The pricing drift gate fired on its first run (doc said 2,000 vs engine 2000) — normalised separators rather than weakening the check. Workbook v014 released — 77 Done / 8 Code-complete / 8 Drafted / 3 In progress / 4 Backlog | E33: jest --coverage; this workbook | F33: v014 Released | G33: — | H33: tracker v006
A34: 13/09/2026 | B34: 10:22 | C34: S9-S10 | D34: COLD-REVIEW PASS 3 over the v014 HTTP/tenancy surface, audited against defect classes found on sibling products (MeetSync M-F04/M-F12/M-F15/M-F21): 4 defects, 2 CRITICAL. F-014 NO MULTI-TENANCY — one IncidentService/FeatureManager/id-counter served every workspace, so workspace B could read workspace A incidents and ids collided; the v014 HTTP layer made it reachable. F-015 OAUTH CSRF — callback took any code with no state. F-016 valid Slack signature treated as proof of installation. F-017 unauthenticated /health leaked version + queue depth | E34: F-014..F-017 | F34: 4 fixes, 12 regressions | G34: — | H34: next entry
... A108: 20/09/2026 | B108: 13:05 | C108: — | D108: Release: codebase v0.37.0, workbook v037, tracker v030. 60 suites / 624 tests (616 run, 8 gated on a real Postgres) at 100% statements, branches, functions and lines over src/ AND scripts/; clean tsc over src+scripts and tests. Built artifact refuses in production naming ten providers + probes; boots and drains in development (CI-asserted) | E108: docs/PERPLEXITY_REVIEW_V001_RESPONSE.md; audit.mjs v3; playbook v3 | F108: v037 Released | G108: D-OC6/7/8, D15, SC-06/07 open | H108: tracker v030

Sheet Review_Findings
A1: REVIEW FINDINGS — cold-review pass 1 (11/09/2026 08:41, author self-review; external pass = ST-097)
A3: ID | B3: Severity | C3: Module | D3: Finding | E3: Action | F3: Status
A4: F-001 | B4: High | C4: billing | D4: No recovery path after failed payment — successful payment never cleared failedSince/dunning/readOnly; read-only became permanent | E4: FIXED — recordSuccessfulPayment(); regression: fresh failure starts fresh grace window | F4: Fixed v011
A5: F-002 | B5: High | C5: billing | D5: Metered usage never reset — limits are per-month but usage accumulated forever; 100% warning permanent after first breach | E5: FIXED — startNewCycle(); regression test | F5: Fixed v011
A6: F-003 | B6: Medium | C6: events/receiver | D6: Dedupe ledger unbounded — memory growth under sustained event volume (same class as EngageOS F-007) | E6: FIXED — FIFO cap 10k (constructor-tunable); eviction + still-deduped regressions | F6: Fixed v011
A7: F-004 | B7: Medium | C7: timeline | D7: captureBotMessages/captureReactions config knobs ignored — bot exclusion hardcoded, reactions always captured | E7: FIXED — FeatureManager.getDefault() wired into capture; 3 regressions incl. defaults-unchanged | F7: Fixed v011
A8: F-005 | B8: Disposition | C8: incidents | D8: transition() permits re-resolve (overwrites resolvedAt, drifts MTTR/postmortem duration) and reopen-after-resolve | E8: SENTHIL CALL: lock resolvedAt to first resolve? forbid reopen or add reopened status? | F8: Open — needs disposition
A9: F-006 | B9: Disposition | C9: compliance | D9: Circuit breaker has no half-open probe — after cooldown full traffic resumes instantly against a possibly-sick provider | E9: SENTHIL CALL: add single-probe half-open state? | F9: Open — needs disposition
A10: F-007 | B10: Disposition | C10: degradation | D10: replayQueue unbounded during extended outage | E10: SENTHIL CALL: cap + overflow policy (drop-oldest vs refuse-new + comms)? | F10: Open — needs disposition
A11: F-008 | B11: Info | C11: compliance/audit | D11: AuditLog in-memory append-only — correct behind DB adapter in prod; adapter contract to verify at deploy | E11: Track at live wiring; no sandbox action | F11: Open — deploy-time check
A12: F-009 | B12: High | C12: install/compliance | D12: 30-day retention published in the trust page, but uninstall only SET a deletedAt date — no sweep ever deleted incident/timeline/audit records. Published deletion policy breached (same class as VoiceBridge F-V01, TestPulse F-TP01) | E12: FIXED — PurgeableStore registry + runRetentionSweep(); 2 regressions incl. active-install safety and idempotency | F12: Fixed v013
A13: F-010 | B13: Medium | C13: telemetry | D13: Error ledger append-only, never trimmed — unbounded growth on a long-running process though only a 60s window is ever read | E13: FIXED — bounded 5k tail; regression proves spike detection still fires | F13: Fixed v013
A14: F-011 | B14: High | C14: paging | D14: Fan-out threw on the first failed page, discarding the record of who HAD been paged — any retry double-paged them and nobody knew who still needed manual escalation | E14: FIXED — PagingOutcome reports paged/failed per responder + retryFailed() targets only failures; 4 regressions | F14: Fixed v013
... A86: L-OC17 | B86: Lesson | C86: tests | D86: A test can encode the defect and then defend it. | E86: APPLIED — when a test asserts a transport shape rather than a value, ask what value belongs there | F86: Closed v036
A88: INDEPENDENT REVIEW V001 (Perplexity, 16/09) + audit v3 findings — dispositioned at v0.37.0 (full register: External_Review_PX_V001 / tracker Review_PX_Findings)
A89: PX-001 | B89: BLOCKER | C89: incidents/declare.ts | D89: Entire platform boundary is synchronous; every unwired adapter needs async I/O | E89: All nine interfaces Promise-returning; IncidentWorkflow.declare/resolve/reopen, timeline capture, DegradationService, CircuitBreaker and the ack contract async; every platform call runs under a 10 s budget (timeout = degraded result, never a hang); AI call moved under the breaker; 26 suites migrated; new floating-promise rule over src/ and scripts/. | F89: FIXED V037 (PX-S0)
A90: PX-002 | B90: BLOCKER | C90: app/workflow.ts | D90: Plan limits unenforced in the deployed composition: usage never increments | E90: recordWrite deleted; declare() and reopen() await entitlements.claimWrite(); without a shared meter the in-process counter is still incremented; 80%/100% warnings surface in the declare message; monthly reset is a leased, once-per-cycle job. | F90: FIXED V037 (PX-S1)
A91: PX-003 | B91: HIGH | C91: scripts/serve.ts | D91: Two user-facing Slack paths sit outside the boot gate (response_url poster = console.log; views.open = bare lambda) | E91: REQUIRED_PROVIDERS is a closed set of ten; ProviderSet is typed to exactly those keys (compile-time assertion); every provider implements healthcheck() and production probes all of them, refusing on the first failure by name; StdoutResponseUrlPoster and ThrowingModalOpener are named, honest stubs; composition moved into src/composition/runtime.ts so it is importable by tests. | F91: FIXED V037 (PX-S2)
A92: PX-004 | B92: HIGH | C92: incidents/ack.ts; scripts/serve.ts (lifecycle.register x2 only) | D92: Queued declares are lost on SIGTERM — on every blue/green deploy | E92: Deferred work is a persisted DESCRIPTOR (deferred_work table, migration 0014) written before the ack returns, leased while running, deleted after delivery; SlashCommandAck is Drainable and registered first with Lifecycle; restore() reloads pending rows; 3 attempts then a definite failure is posted; Lifecycle now re-checks pending per round (draining the queue produces sink rows). | F92: FIXED V037 (PX-S2)
A93: PX-005 | B93: HIGH | C93: scripts/serve.ts (vault.addKey('k1')); compliance/crypto.ts | D93: Key rotation is a promise with no possible caller (one key, id 'k1', forever) | E93: EnvKeyVault loads every ENCRYPTION_KEY_<id>, ENCRYPTION_KEY_CURRENT selects; POST /ops/rotate-keys re-encrypts stored tokens under the current key, idempotent and resumable; boot warns while any record references a non-current key; TRUST_SECURITY.md states the limit (env keys until S43). | F93: FIXED V037 (rotation path); KMS remains S43 (CF-012)
A94: PX-006 | B94: MEDIUM | C94: scheduler/scheduler.ts; scripts/serve.ts | D94: Leased jobs dedupe concurrency but not frequency; a daily sweep can run many times a day | E94: job_leases.last_run_at (migration 0013); acquireDue grants the lease only when the STORED last run is older than the interval; recordRun advances it; release keeps the row. | F94: FIXED V037 (PX-S2)
A95: PX-007 | B95: MEDIUM | C95: paging/paging.ts | D95: PagingProvider.name is a two-value union that cannot express D-OC7's targets | E95: PagingProviderId = pagerduty | opsgenie | jsm | compass | webhook; config accepts all five; ThrowingPagingAdapter carries the configured id. | F95: FIXED V037 (PX-S2)
A96: PX-008 | B96: MEDIUM | C96: scripts/serve.ts | D96: Provider identity handed to the workflow is hardcoded ('pagerduty'), so audit/telemetry name the wrong provider | E96: The workflow receives the constructed adapter itself (field renamed name → id); wf.pagingProviderId() is asserted equal to the composition inventory. | F96: FIXED V037 (PX-S2)
A97: PX-009 | B97: MEDIUM | C97: Product workbook Financial_Model | D97: Financial model has never been computed; no cached values in any month column | E97: All 18 month columns now carry computed values; a summary block (breakeven month, cash to breakeven, M18 ARR, contracts-per-Rootly-median) and two sensitivity scenarios (10% and 8% trial→paid) added as live formulas. | F97: FIXED V037 (workbook)
A98: PX-010 | B98: MEDIUM | C98: http/session.ts | D98: Sessions cannot be revoked; uninstall, role removal, cancellation and tenant deletion leave valid cookies for up to 12 h | E98: installEpoch claim in the token (the installation's own timestamp); the resolver refuses any token whose epoch is not the workspace's current one; uninstall clears it, reinstall mints a strictly newer one, data deletion forgets the in-process install record and evicts the tenant's workflow; bumpEpoch for admin revocation. No new store. | F98: FIXED V037 (pulled into PX-S2 from S38, per the reviewer's answer 2)
A99: PX-011 | B99: MEDIUM | C99: scripts/serve.ts (loadRecent(10000)) | D99: Replay-protection window is bounded by row count, not time | E99: DedupeRepository.loadSince(now − SLACK_RETRY_WINDOW_MS, cap 50,000); the 6-hour window is documented against Slack's retry behaviour next to the 3 s ack budget. | F99: FIXED V037 (PX-S2)
A100: PX-012 | B100: LOW-MEDIUM | C100: Risk_Register | D100: Positioning sells an 83-99% price advantage as '40-50%'; the leader's free tier covers four of five modules | E100: PLAN_LIMITS expresses bands (team $99 ≤25 eng, business $249 ≤75, scale $599 ≤200, enterprise $1,499 ≤500) with a fair-use incident ceiling that is still enforced; PRICING_FAQ regenerated from pricingDoc.ts and gate-tested; Risk_Register and roadmap S45 elevated per §3.3. | F100: ADDRESSED V037 (docs + workbook); D-OC8 open
... A103: PX-015 | B103: LOW | C103: events/receiver.ts | D103: (Own finding, audit v3 A12) EventReceiver retry queue is not drained at shutdown | E103: Register with Lifecycle when the event handler does real work (S38); persist if events gain side effects. | F103: OPEN

Sheet Submission_Readiness
A1: SUBMISSION READINESS DRY-RUN — machine-checked where possible (13/09/2026 11:25)
A2: Regenerate any time with: npm run submission-check. Exit code is non-zero while any automated check is blocked, so it can gate CI.
A3: VERDICT: READY_TO_SUBMIT on the automated half, and NOT SUBMITTABLE overall — external review V001 gate G0 blocks submission until the P0 remediation set closes. The automated checks were always necessary and never sufficient. V037: Phase 0 of the second review closed; S38-S41 (adapters, now drop-ins) remain the gate.
A5: ID | B5: Requirement | C5: State | D5: Evidence / what is needed | E5: Owner
A6: SC-01 | B6: App manifest present with least-privilege scopes | C6: PASS | D6: 5 scopes, each justified on the trust page | E6: automated
A7: SC-02 | B7: Endpoints Slack calls are served | C7: PASS | D7: 5 required routes registered | E7: automated
A8: SC-03 | B8: Review and listing documentation present | C8: PASS | D8: 7 documents present | E8: automated
A9: SC-04 | B9: Automated quality gate green (D13) | C9: PASS | D9: 60 suites / 624 tests (616 run, 8 gated on a real Postgres) at 100% statements, branches, functions and lines over src/ AND scripts/; clean tsc over src+scripts and tests (v0.37.0) | E9: automated
A10: SC-05 | B10: Database migrations present | C10: PASS | D10: Ordered migrations with cascade deletes | E10: automated
A11: SC-06 | B11: Installed and verified in a real Slack workspace | C11: LIVE | D11: docs/DEV_WORKSPACE_SETUP.md then npm run live-sweep (12 steps) | E11: Senthil
A12: SC-07 | B12: Live billing verified end to end | C12: LIVE | D12: Stripe keys + one real test charge | E12: Senthil
A13: SC-08 | B13: Third-party penetration test completed | C13: HUMAN | D13: Sandbox half now an 18-case adversarial suite in CI (it found F-039); the third-party engagement remains open — a self-written suite only covers attacks we thought of | E13: Senthil
A14: SC-09 | B14: Independent second reviewer sign-off | C14: HUMAN | D14: Served twice (ChatGPT 13/09, Perplexity 16/09), both dispositioned; S50 needs a THIRD reviewer independent of both | E14: Senthil
A15: SC-10 | B15: Listing assets captured (icon, screenshots, video) | C15: HUMAN | D15: Copy drafted; capture needs the running product | E15: Senthil
A16: SC-11 | B16: Listing copy variant chosen (A or B) | C16: HUMAN | D16: Both drafted; the pick is a product decision | E16: Senthil
... A18: SC-13 | B18: Production composition contains no stub or in-memory adapter | C18: BLOCKED | D18: The boot gate refuses today naming all TEN providers with their probe results (healthcheck), and is proven to PERMIT a healthy composition. GET /ops/composition reports inventory + probes. | E18: automated
