Workbook

Sheet Cover_Sheet
A1: RevRescue for Stripe — Version Detail and Manual Test Pack
A3: Document title | B3: RevRescue for Stripe — Version Detail and Manual Test Pack
A4: Document ID | B4: claude_V001_MoPr01-revrescue_stripe_versiondetail_manualtest_20260920_1058
A5: Document version | B5: V001
A6: Date issued | B6: 2026-09-20 10:58
A7: Project reference | B7: 002-MoPr01-revrescue_stripe-DEV
A8: Product | B8: RevRescue — failed-payment recovery app for the Stripe App Marketplace
A9: Prepared by | B9: Claude (build and review assistant)
A10: Prepared for | B10: Senthil (KP) — product owner and sole decision maker
A11: Covers | B11: Tracker versions v001 to v021 (released) and v022 onwards (pending), with 56 manual test cases
A12: Code release described | B12: claude_v017_revrescue_server_code_20260916_1916.zip (tracker v021)
A13: Companion documents | B13: claude_v021_revrescue_sprint_tracker_traceability_20260916_1916.xlsx; REVIEW_RESPONSE.md, RETENTION.md, OPERATIONS.md and HANDOVER.md inside the code zip; the product diagram (HTML) issued with this pack
A14: Status | B14: Issued for review
... A18: Overall result at issue | B18: 353 of 353 automated tests pass at 100% coverage; 7 review gates pass; money-path mutation score 99.1%. No story is Done, because nothing has run against live Stripe.

Sheet Version_Control
A1: VERSION CONTROL — this document
A2: Every issue of this pack is recorded here. File naming: claude_V<NNN>_<name>_YYYYMMDD_HHMI.xlsx. Change any content only by issuing a new version row; do not edit an issued row.
A3: Version | B3: Date/Time | C3: Author | D3: Change description | E3: Status
A4: V001 | B4: 2026-09-20 10:58 | C4: Claude | D4: First issue. Version history for tracker versions v001-v021 with what was done and why; pending versions v022+ with the reason each is pending and who owns it; step-by-step review procedure per version; 56 manual test cases (29 positive, 27 negative) covering every change made in v020 and v021 and the core behaviour carried from earlier versions; test summary, defect log, glossary, decisions and sign-off. | E4: Issued

Sheet Context_ReadMe
A1: CONTEXT — read this first
A2: Background needed to use the rest of the workbook. One row per topic.
A3: Topic | B3: Detail
A4: What this product is | B4: RevRescue recovers failed subscription payments for Stripe merchants: it retries payments intelligently, chases customers by email and WhatsApp, offers a save deal when someone cancels, attributes each recovery to a single action, and bills the merchant a percentage of what it recovered.
A5: Where the product stands | B5: The domain logic, the application, the database layer, the scheduler, the money path, the operator plane and the security work are all built and tested. Nothing has ever talked to Stripe. Everything that requires Stripe is parked behind decision D14, which only Senthil can take.
A6: Two version series | B6: The tracker version (v001-v021) is the authoritative log of the product. Code zips carry their own numbers; where they map, it is stated (tracker v019 = code v015, v020 = code v016, v021 = code v017).
A7: How to run anything in this pack | B7: Unzip the code release, run npm ci, then npm test (the full suite), npm run gates (the seven quality gates) and npm run mutation (the money-path mutation score). Every manual test case in this pack is executed with those commands.
A8: Why the tests are the manual test surface | B8: With the Stripe adapters parked, the product cannot be exercised against Stripe, and inventing a fake Stripe would make any result meaningless. The acceptance suite drives real HTTP requests through the real application against a real embedded Postgres, so it is the closest honest substitute. Each test case names the command and what to read.
A9: Evidence classes (operating rule R9) | B9: unit = pure logic; integration = real database and/or real request path; contract = proven against Stripe test mode; live, operational, external = beyond that. The product has reached integration. No story is marked Done, because Done requires live Stripe evidence.
A10: How to use this pack | B10: Read Version_Detail for what each version delivered and why. Read Pending_Versions for what is not built and the reason. Use Version_Steps to review a version. Use Manual_Test_Cases to test it, recording your result in the Result columns. Log anything you find in Defect_Log.
A11: What is deliberately not in this pack | B11: Customer data, secrets, and any claim of production readiness. The product is not live and has no users.

Sheet Sheet_Index
A1: SHEET INDEX — what each sheet is for
A2: Every sheet in this workbook, what it contains, how to use it and who maintains it.
A3: Sheet | B3: What it contains | C3: How to use it | D3: Owner
A4: Cover_Sheet | B4: Identity of the document, what it covers and the headline result. | C4: Read first. Check you have the right document version. | D4: —
A5: Version_Control | B5: The issue history of this workbook. | C5: Add a row for every re-issue; never edit an issued row. | D5: Claude
A6: Context_ReadMe | B6: What the product is, where it stands, how to run anything here. | C6: Read before testing. | D6: —
A7: Sheet_Index | B7: This sheet: what each sheet is for and how to use it. | C7: Use as the map. | D7: —
A8: Version_Detail | B8: Every released version: what was done and why it was done, with the evidence reached. | C8: Read top to bottom for the story of the build, or filter by version. | D8: Claude
A9: Pending_Versions | B9: Everything not built, why it is pending, what blocks it and who owns the unblock. | C9: Filter by Owner to see what is waiting on you. | D9: Senthil
A10: Version_Steps | B10: A step-by-step procedure to review each version, in order. | C10: Follow the steps for the version you are checking. Steps are commands you can paste. | D10: Reviewer
A11: Manual_Test_Cases | B11: 56 test cases: name, description, preconditions, numbered steps, expected result, and columns for your result. | C11: Execute and fill Result, Tester, Date, Comment. Filter by Type for positive or negative, or by Version. | D11: Tester
A12: Test_Summary | B12: Counts by version and by type, and pass/fail totals driven by formulas from Manual_Test_Cases. | C12: Read after a test run; it updates itself from the Result column. | D12: —
A13: Defect_Log | B13: Every defect found across the build, including the ones found while fixing others, with status. | C13: Add a row for anything you find. Keep the finding wording factual. | D13: Tester
A14: Decisions_Open | B14: The decisions only Senthil can take, and what each unblocks. | C14: This is the shortest path to progress. | D14: Senthil
... A16: Sign_Off | B16: Review and approval record for this pack. | C16: Sign when satisfied; note conditions. | D16: Senthil

Sheet Version_Detail
A1: VERSION DETAIL — what was done, and why
A2: One row per released version, oldest first. "Why" records the reason the work was done at that point, which is usually a decision, a review finding or a defect. Evidence is the strongest class reached at that version (rule R9). No row is Done: Done needs live Stripe evidence (DEC-04).
A3: Version | B3: Date/Time | C3: Code release | D3: Headline | E3: What was done | F3: Why it was done | G3: Evidence reached | H3: Status
A4: v001 | B4: 2026-09-10 19:42 | C4: — | D4: Tracker and traceability created | E4: Sprint tracker log, S0 task board, formula-driven sprint rollup, 100-story traceability matrix (spec module -> epic -> story -> screen -> NFR -> verification), RAID carryover and the D7 gate checklist. | F4: The product is built solo against a fixed portfolio order; without one live record of what is built and what is claimed, nothing can be audited later. | G4: Workbook only | H4: Released
A5: v002 | B5: 2026-09-10 20:05 | C5: — | D5: PRD drafted (T-01) | E5: An 11-section PRD including S0-verified platform requirements, the outcome-pricing spec as declared usage-based pricing, an NFR-to-story verification map and the discovery question set. | F5: A written specification was needed before any code so that every later story could be traced to a requirement. | G5: Document review | H5: Released
A6: v003 | B6: 2026-09-10 20:18 | C6: — | D6: Stripe Apps Agreement read in full (T-04) | E6: Logged the obligations that constrain the design: no personal data in Stripe Apps storage, 72-hour breach notification, export self-classification, 30-day removal notice, annual compliance review. | F6: Agreement terms change what may be built and stored; reading them late is how products get rejected at listing. | G6: Document review | H6: Released
A7: v004 | B7: 2026-09-10 20:42 | C7: — | D7: S1 foundation under a 100% test gate (D13 logged) | E7: Install, uninstall, token and telemetry logic with 26 tests; the quality rule was raised to 100% automated coverage per code unit. | F7: Senthil parked five-user discovery (D13), so building continued on everything that did not depend on it. | G7: unit | H7: Released
A8: v005 | B8: 2026-09-10 20:48 | C8: — | D8: Seven domain engines (D14 logged) | E8: Retry (including payday-aware), dunning with a locked compliance footer and test mode, save-offer guardrails, conservative attribution, outcome fee, grace mode and plan limits. | F8: Senthil parked the Stripe SDK adapters (D14), so all platform-independent logic was built first. | G8: unit | H8: Released
A9: v006 | B9: 2026-09-10 21:06 | C9: — | D9: Roles, grace, limits, cancellation and health | E9: Role matrix with typed enforcement, grace/read-only with the day 0/3/6 cadence, plan limits with 80%/100% prompts, the cancellation state machine and a weighted health score. | F9: These are the rules the product sells; each was built as pure logic so it could be proven without Stripe. | G9: unit | H9: Released
A10: v007 | B10: 2026-09-10 22:00 | C10: — | D10: Launch content pack (28 files) | E10: Listing copy variants, pricing page and FAQ with the fee rate left as a flagged placeholder, security/trust page, help centre articles. | F10: Listing content has review lead time, and writing it early exposes claims the code must then back. | G10: content draft | H10: Released
A11: v008 | B11: 2026-09-13 11:32 | C11: — | D11: First adversarial audit: the application layer was missing | E11: Found 10 defects in code at 100% coverage, two structural: there was no HTTP application behind any surface, and no database schema behind any store. Built the integration layer. | F11: Coverage measured execution of engines that nothing called. An audit was the only way to see it. | G11: unit + integration | H11: Released
A12: v009 | B12: 2026-09-13 12:05 | C12: — | D12: Verification against live Stripe documentation | E12: Corrected an invalid pinned API version, fixed webhook handling that verified the wrong thing, and ported the review gates. | F12: Assumptions about the platform had never been checked against its published behaviour. | G12: unit + integration | H12: Released
A13: v010 | B13: 2026-09-13 16:24 | C13: — | D13: Cold review pass 3 (6 findings) | E13: Uninstall deleted nothing (it scheduled through an unimplemented interface); the purge registry was reachable only from an authenticated route. All six fixed with pinned regressions. | F13: A recurring failure pattern: a promise wired to an interface nobody implemented. | G13: integration | H13: Released
A14: v011 | B14: 2026-09-13 16:29 | C14: — | D14: Review gates packaged (at-review-gates v1.0.0) | E14: Three drop-in CI gates: reachability, published claims and config drift, with their own tests at 100%. | F14: The same defect classes recur across the 12-product portfolio; a portable gate stops them once. | G14: unit | H14: Released
... A24: v021 | B24: 2026-09-16 19:16 | C24: code v017 | D24: D1-D5: mutation testing, dead letters, isolation, audit integrity, content fixes | E24: Mutation testing of the money path gated at 85% (final 99.1%); a dead-letter queue with an authenticated operator plane; row-level security forced on all 20 account tables; a hash-chained audit trail with retention and redaction; corrected help and FAQ wording. Found V-14: test-mode dunning was wired to the live WhatsApp adapter. | F24: Senthil approved D1-D5 at 18:18 as the remaining work that does not need Stripe. | G24: integration + unit (353 tests, 100%, 7 gates, mutation 99.1%) | H24: Released

Sheet Pending_Versions
A1: PENDING VERSIONS — what is not built and why
A2: Everything still to build, grouped by the version that would carry it. "Blocked by" names the decision or dependency; "Owner" is who must act. Items marked "Not blocked" are simply ranked below the Stripe work.
A3: Planned version | B3: What it would deliver | C3: Why it is pending | D3: Blocked by | E3: Owner | F3: What unblocks it
A4: v022 | B4: Stripe adapters: OAuth code exchange, token refresh, webhook signature verification, the retry executor that sends the idempotency key, charge-to-invoice lookup, and the email/WhatsApp/Slack senders. | C4: Every adapter talks to Stripe. They were parked by Senthil, not by the build, and faking them would make every test meaningless. | D4: DEC-04 (unpark D14) | E4: Senthil | F4: A Stripe account and dev credentials, then S14 can start.
A5: v022 | B5: Contract test proving a replayed retry charges a card once (the P-RR05 acceptance criterion). | C5: The idempotency key is generated, stored before the call and re-read after a crash, but only Stripe can prove it honours the key. | D5: DEC-04 | E5: Senthil | F5: Stripe test mode.
A6: v022 | B6: Validating the event handlers against real Stripe payloads. | C6: The handlers were written against published documentation. One field (the decline reason) is known not to be an invoice field and is enriched by the adapter. | D6: DEC-04 | E6: Senthil | F6: Stripe test mode.
A7: v023 | B7: Stripe app manifest generated from the declared event list, and the Dashboard UI extension (S16). | C7: The manifest needs an app id from Stripe; the UI extension only runs inside the Stripe Dashboard. | D7: DEC-04 | E7: Senthil | F7: Stripe app registration.
A8: v024 | B8: Holdback experiment measuring incrementality (S17). | C8: The product currently bills any payment it acted on first. Whether a reminded customer would have paid anyway cannot be proven without withholding treatment from a control group. | D8: Decision 4 (authorise the holdback) and decision 2 (pricing model) | E8: Senthil | F8: Written authorisation; it changes what the FAQ may claim.
A9: v024 | B9: Final fee percentage and the single-price rule across listing, app and pricing page. | C9: The fee rate is a flagged placeholder everywhere. The drift gate rule that would enforce one price is written but commented out until the number exists. | D9: Decision 2 (pricing model) and decision 3 (confirm with Stripe in writing) | E9: Senthil | F9: A decided price, confirmed by Stripe partnerships.
A10: v025 | B10: Email/WhatsApp sending infrastructure: ESP account, domain authentication, WhatsApp Business verification (S18). | C10: External providers must be chosen and verified; inbox placement and consent evidence cannot be produced without them. | D10: DEC-04 and provider choice | E10: Senthil | F10: Accounts opened and domains verified.
A11: v026 | B11: Production database roles, non-superuser login, and re-running the isolation suite on production Postgres (LC-29). | C11: Row-level security is proven on an embedded Postgres that runs as superuser beneath the scoped roles. It must be re-proven where the application login is a real, restricted role. | D11: Hosting choice | E11: Senthil | F11: A provisioned production database.
A12: v026 | B12: SRE work: SLOs, log platform and its retention, an external anchor for the audit chain, a shared rate limiter (S19). | C12: These need infrastructure that does not exist yet; the in-process rate limiter is per instance by design and says so. | D12: Hosting choice | E12: Senthil | F12: Infrastructure decisions.
A13: v027 | B13: Penetration test and the tenant-isolation suite run by a third party (S20). | C13: An external party must be engaged; a self-run test is not evidence for a listing review. | D13: Budget and vendor choice | E13: Senthil | F13: Vendor engaged.
A14: v028 | B14: Marketplace listing submission and launch (S21). | C14: Listing requires the manifest, the confirmed price, the pen test and the finished content. | D14: All of the above | E14: Senthil | F14: Everything above completed.
... A17: v0xx | B17: D5 content wording published, retention periods confirmed, operator allowlist named. | C17: The corrected help and FAQ text is in the code but treated as unapproved; retention periods and operator names are decisions. | D17: DEC-D5, DEC-RET, DEC-OPS | E17: Senthil | F17: Three short approvals.

Sheet Version_Steps
A1: VERSION STEPS — how to review each version
A2: A review procedure per version group, in order. Steps are commands you can paste into a terminal in the unzipped code folder. Expected result is what you should see if that version is intact.
A3: Version(s) | B3: What you are reviewing | C3: Steps | D3: Expected result
A4: All | B4: Prepare the environment | C4: 1. Download claude_v017_revrescue_server_code_20260916_1916.zip. 2. Unzip it and open a terminal in the revrescue folder. 3. Run: npm ci 4. Run: npx tsc --noEmit 5. Run: npm test | D4: Dependencies install, the type check is silent, and 353 tests pass at 100% coverage.
A5: v001-v007 | B5: Review the foundations | C5: 1. Open the companion tracker (v021) and read Version_Control rows v001 to v007. 2. Open content/ in the code zip and read the listing copy, pricing FAQ and help articles. 3. Check that the fee rate appears as a placeholder, not a number. | D5: The written specification, the agreement obligations and the launch content all exist. The price is still a placeholder pending decision 2.
A6: v008-v012 | B6: Review the audits and the gates | C6: 1. Read REVIEW_RESPONSE.md in the code zip. 2. Run: npm run gates 3. Add a file src/orphan.ts containing export const x = 1; and run npm run gates again. 4. Delete the file. | D6: Seven gates pass; with the orphan present, reachability fails and the command exits 1.
A7: v013-v018 | B7: Review the park audit and the scheduler | C7: 1. Open src/scheduler.ts and read the tick: retries, dunning, grace notices, billing run. 2. Run: npm test -- --test-name-pattern="GAP-RR3" 3. Run: npm test -- --test-name-pattern="V-04" | D7: The scheduler drains the queue it writes to, dunning advances through days 2, 4 and 7, and work is claimed atomically.
A8: v019 | B8: Review the server | C8: 1. Open src/server.ts and read the body cap, timeouts and drain. 2. Run: npm test -- --test-name-pattern="security headers" 3. Run: npm test -- --test-name-pattern="PATH only" | D8: A real HTTP server exists; every response carries security headers; logs record the path only.
A9: v020 | B9: Review the independent-review response (money and durability) | C9: 1. Read the findings table in REVIEW_RESPONSE.md. 2. Run: npm test -- --test-name-pattern="P-RR01" 3. Run: npm test -- --test-name-pattern="P-RR03" 4. Run: npm test -- --test-name-pattern="P-RR05" 5. Run: npm test -- --test-name-pattern="V-01" 6. Run: npm run gates and read the money-invariants line. | D9: Recoveries carry real amounts; statements are per period and immutable; a crashed retry does not charge twice; dunning stops when the customer pays; 400 random billing histories hold every money rule.
A10: v021 | B10: Review isolation, audit integrity, dead letters and the operator plane | C10: 1. Read OPERATIONS.md and RETENTION.md. 2. Run: npm test -- --test-name-pattern="RR-P046" 3. Run: npm test -- --test-name-pattern="hash-chained" 4. Run: npm test -- --test-name-pattern="RR-P021" 5. Run: npm test -- --test-name-pattern="V-14" 6. Run: npm run mutation (about 8 minutes). | D10: Row-level security is forced on every account table; the audit trail detects tampering; parked work is dead-lettered and replayable by an authenticated operator; test mode sends nothing live; the mutation score is at least 85% (recorded: 99.1%).
A11: v022+ | B11: Check what is still pending | C11: 1. Open the Pending_Versions sheet. 2. Confirm each blocker is still accurate. 3. Take the decisions listed in Decisions_Open, starting with DEC-04. | D11: Every pending item is traceable to a decision or a dependency, and none of them is waiting on the build.

Sheet Manual_Test_Cases
A1: MANUAL TEST CASES — 56 cases (29 positive, 27 negative)
A2: One row per test case. Preconditions, numbered steps and the expected result are written so that someone who has not seen the code can execute them. Record your outcome in Result, Tester, Date and Comment. Result must be Pass, Fail, Blocked or Not run.
A3: Test ID | B3: Version | C3: Area | D3: Type | E3: Test case name | F3: Description | G3: Preconditions | H3: Steps | I3: Expected result | J3: Result | K3: Tester | L3: Date | M3: Comment
A4: TC-001 | B4: v021 | C4: Environment | D4: Positive | E4: Install dependencies and build | F4: Confirms the shipped zip builds on a clean machine. | G4: Node 22+, network access to npm. | H4: 1. Unzip claude_v017_revrescue_server_code_20260916_1916.zip. 2. cd revrescue. 3. Run: npm ci 4. Run: npx tsc --noEmit | I4: npm ci completes without error. The type check prints nothing and exits 0.
A5: TC-002 | B5: v021 | C5: Environment | D5: Positive | E5: Full suite and coverage gate | F5: Confirms every test passes and the 100% coverage gate holds. | G5: TC-001 done. | H5: 1. Run: npm test 2. Read the summary lines at the end. | I5: 353 tests pass, 0 fail. Statements, branches, functions and lines all 100%. Exit code 0.
A6: TC-003 | B6: v021 | C6: Environment | D6: Negative | E6: Coverage gate fails when a line is untested | F6: Proves the gate is real, not decorative. | G6: TC-002 done. | H6: 1. Open src/redact.ts and add a new exported function that no test calls, e.g. export const unused = (s: string): string => s; 2. Run: npm test 3. Undo the edit. | I6: The run fails with a coverage threshold error naming functions/lines below 100%, and exits non-zero.
A7: TC-004 | B7: v021 | C7: Gates | D7: Positive | E7: All seven review gates pass | F7: The CI quality gates read one config file. | G7: TC-001 done. | H7: 1. Run: npm run gates 2. Read each line. | I7: Seven PASS lines: reachability, published-claims, schema, composition-root, drift, event-coverage, money-invariants (400 random histories). Exit 0.
A8: TC-005 | B8: v021 | C8: Gates | D8: Negative | E8: Reachability gate catches an orphan module | F8: A module nothing imports must fail the build (defect class F-RR01). | G8: TC-004 done. | H8: 1. Create src/orphan.ts containing: export const x = 1; 2. Run: npm run gates 3. Delete the file and rebuild. | I8: FAIL reachability: orphan. Exit code 1.
A9: TC-006 | B9: v021 | C9: Gates | D9: Negative | E9: Composition-root gate catches a hardcoded value | F9: Rule R11: no literal in main.ts may stand in for persisted state. | G9: TC-004 done. | H9: 1. In src/main.ts, add batch: 0, to the Scheduler options. 2. Run: npm run gates 3. Undo the edit. | I9: FAIL composition-root naming the line number. Exit code 1.
A10: TC-007 | B10: v021 | C10: Gates | D10: Negative | E10: Claims gate refuses an empty claims list | F10: A gate that passes on empty input proves nothing (defect V-07). | G10: TC-004 done. | H10: 1. In gates.config.mjs set claims: { claims: [] }. 2. Run: npm run gates 3. Undo the edit. | I10: The run fails with "no claims configured: an empty claims list proves nothing".
A11: TC-008 | B11: v021 | C11: Mutation testing | D11: Positive | E11: Money-path mutation score | F11: RR-P054: the tests must notice a wrong line, not just execute it. | G11: TC-001 done. Takes about 8 minutes. | H11: 1. Run: npm run mutation 2. Read the final score line. | I11: Score of at least 85%; the recorded result is 99.1% (464 of 468 mutants killed). Exit 0.
A12: TC-009 | B12: v020 | C12: Money — recovery value | D12: Positive | E12: A recovered payment records its real amount | F12: P-RR01: scheduler recoveries used to be written as zero. | G12: TC-001 done. | H12: 1. Run: npm test -- --test-name-pattern="P-RR01" 2. Read the test names that ran. | I12: Tests pass showing the recovery carries the real amount and currency end to end, and that zero is refused by both the code and the database.
A13: TC-010 | B13: v020 | C13: Money — recovery value | D13: Negative | E13: A zero-value recovery is refused twice over | F13: Both the application and a database constraint must refuse it. | G13: TC-001 done. | H13: 1. Run: npm test -- --test-name-pattern="zero-value recovery is refused" 2. Read the assertions in test/pg.test.ts for the same name. | I13: The application throws ZeroValueRecovery, and a direct SQL insert of amount 0 is rejected by recoveries_amount_positive.
A14: TC-011 | B14: v020 | C14: Money — attribution | D14: Positive | E14: A payment after a reminder is credited to dunning | F14: P-RR02: no payment success was observed at all before v020. | G14: TC-001 done. | H14: 1. Run: npm test -- --test-name-pattern="dunning recovers a payment" 2. Read the assertions. | I14: The payment is attributed to dunning with evidence (messages sent, last sent time), the recovery is written with the paid amount, and the merchant alert is posted to that account channel.
A15: TC-012 | B15: v020 | C15: Money — attribution | D15: Negative | E15: A payment RevRescue did not act on is never billed | F15: Stripe own retries and unprompted payments must not carry a fee. | G15: TC-001 done. | H15: 1. Run: npm test -- --test-name-pattern="not attributed" 2. Read the assertions. | I15: No recovery row is written; an audit row records "no RevRescue action preceded this payment".
... A59: TC-056 | B59: v021 | C59: Documentation | D59: Positive | E59: Claims in published content are backed by code | F59: The claims gate is the contract between copy and code. | G59: TC-004 done. | H59: 1. Open content/listing/pricing_faq.md and content/help/13_export_and_delete_data.md. 2. Compare the wording with gates.config.mjs claim ids export_json, delete_immediately and not_our_recovery. 3. Run: npm run gates | I59: The FAQ states that a payment with no RevRescue action is never billed, help 13 states JSON and immediate deletion, and published-claims passes. NOTE: this wording awaits Senthil approval (DEC-D5).

Sheet Test_Summary
A1: TEST SUMMARY — counts and outcomes
A2: Driven by formulas from Manual_Test_Cases; it updates as you fill in the Result column. "Not run" counts anything without a recorded result.
A3: Version | B3: Cases | C3: Positive | D3: Negative | E3: Pass | F3: Fail | G3: Blocked | H3: Not run
A4: v020 | B4: =COUNTIF(Manual_Test_Cases!$B$4:$B$59,"v020") -> 30 | C4: =COUNTIFS(Manual_Test_Cases!$B$4:$B$59,"v020",Manual_Test_Cases!$D$4:$D$59,"Positive") -> 15 | D4: =COUNTIFS(Manual_Test_Cases!$B$4:$B$59,"v020",Manual_Test_Cases!$D$4:$D$59,"Negative") -> 15 | E4: =COUNTIFS(Manual_Test_Cases!$B$4:$B$59,"v020",Manual_Test_Cases!$J$4:$J$59,"Pass") -> 0 | F4: =COUNTIFS(Manual_Test_Cases!$B$4:$B$59,"v020",Manual_Test_Cases!$J$4:$J$59,"Fail") -> 0 | G4: =COUNTIFS(Manual_Test_Cases!$B$4:$B$59,"v020",Manual_Test_Cases!$J$4:$J$59,"Blocked") -> 0 | H4: =COUNTIF(Manual_Test_Cases!$B$4:$B$59,"v020")-COUNTIFS(Manual_Test_Cases!$B$4:$B$59,"v020",Manual_Test_Cases!$J$4:$J$59,"Pass")-COUNTIFS(Manual_Test_Cases!$B$4:$B$59,"v020",Manual_Test_Cases!$J$4:$J$59,"Fail")-COUNTIFS(Manual_Test_Cases!$B$4:$B$59,"v020",Manual_Test_Cases!$J$4:$J$59,"Blocked") -> 30
A5: v021 | B5: =COUNTIF(Manual_Test_Cases!$B$4:$B$59,"v021") -> 26 | C5: =COUNTIFS(Manual_Test_Cases!$B$4:$B$59,"v021",Manual_Test_Cases!$D$4:$D$59,"Positive") -> 14 | D5: =COUNTIFS(Manual_Test_Cases!$B$4:$B$59,"v021",Manual_Test_Cases!$D$4:$D$59,"Negative") -> 12 | E5: =COUNTIFS(Manual_Test_Cases!$B$4:$B$59,"v021",Manual_Test_Cases!$J$4:$J$59,"Pass") -> 0 | F5: =COUNTIFS(Manual_Test_Cases!$B$4:$B$59,"v021",Manual_Test_Cases!$J$4:$J$59,"Fail") -> 0 | G5: =COUNTIFS(Manual_Test_Cases!$B$4:$B$59,"v021",Manual_Test_Cases!$J$4:$J$59,"Blocked") -> 0 | H5: =COUNTIF(Manual_Test_Cases!$B$4:$B$59,"v021")-COUNTIFS(Manual_Test_Cases!$B$4:$B$59,"v021",Manual_Test_Cases!$J$4:$J$59,"Pass")-COUNTIFS(Manual_Test_Cases!$B$4:$B$59,"v021",Manual_Test_Cases!$J$4:$J$59,"Fail")-COUNTIFS(Manual_Test_Cases!$B$4:$B$59,"v021",Manual_Test_Cases!$J$4:$J$59,"Blocked") -> 26
A6: TOTAL | B6: =COUNTA(Manual_Test_Cases!$A$4:$A$59) -> 56 | C6: =COUNTIF(Manual_Test_Cases!$D$4:$D$59,"Positive") -> 29 | D6: =COUNTIF(Manual_Test_Cases!$D$4:$D$59,"Negative") -> 27 | E6: =COUNTIF(Manual_Test_Cases!$J$4:$J$59,"Pass") -> 0 | F6: =COUNTIF(Manual_Test_Cases!$J$4:$J$59,"Fail") -> 0 | G6: =COUNTIF(Manual_Test_Cases!$J$4:$J$59,"Blocked") -> 0 | H6: =B6-E6-F6-G6 -> 56

Sheet Defect_Log
A1: DEFECT LOG — every defect found, and where it came from
A2: Includes defects found by the independent review, by verifying that review, by the gates, and by this build in its own work. Severity is the impact if it had reached a merchant.
A3: ID | B3: Found in | C3: Found by | D3: Area | E3: Defect | F3: Severity | G3: Fix | H3: Status
A4: P-RR01 | B4: v020 | C4: Independent review V001 | D4: Money | E4: Scheduler recoveries were written with amount 0, so recovered money was never billed and the merchant total stayed zero | F4: Critical | G4: Fixed v020 — value carried through the interface; zero refused by code and by a database constraint | H4: Closed at integration
A5: P-RR02 | B5: v020 | C5: Independent review V001 | D5: Money | E5: No handler observed a payment succeeding, so dunning and save-offer recoveries could never be attributed | F5: Critical | G5: Fixed v020 — eight event types handled; cause read from our own records | H5: Closed at integration
A6: P-RR03 | B6: v020 | C6: Independent review V001 | D6: Money | E6: Statements had no period, so month two re-billed month one; nothing was ever written to the statements table | F6: Critical | G6: Fixed v020 — per period, per currency, immutable, with credits for later changes | H6: Closed at integration
A7: P-RR04 | B7: v020 | C7: Independent review V001 | D7: Money | E7: A capped statement did not reconcile with its own lines | F7: High | G7: Fixed v020 — explicit cap line and per-invoice allocation | H7: Closed at integration
A8: P-RR05 | B8: v020 | C8: Independent review V001 | D8: Payments | E8: No idempotency key on retries: a crash could charge a card twice | F8: Critical | G8: Fixed v020 — key persisted before the call; state read before any re-attempt | H8: Closed at integration; contract test needs D14
A9: P-RR06 | B9: v020 | C9: Independent review V001 | D9: Entitlement | E9: Plan limits computed and enforced nowhere | F9: High | G9: Fixed v020 — limit required at the type level and enforced on writes and automation | H9: Closed at integration
A10: P-RR07 | B10: v020 | C10: Independent review V001 | D10: Claims | E10: Published promises with no route or writer behind them; the claims gate was a text search | F10: High | G10: Fixed v020 — claims gate v2 and a schema gate | H10: Closed at integration
A11: P-RR08 | B11: v020 | C11: Independent review V001 | D11: Settings | E11: Alert mutes and grace cadence hardcoded in the composition root | F11: High | G11: Fixed v020 — persisted per-account settings; composition-root gate | H11: Closed at integration
A12: P-RR09 | B12: v020 | C12: Independent review V001 | D12: Reliability | E12: Webhook dedupe held in process memory | F12: High | G12: Fixed v020 — database-backed claim/commit ledger | H12: Closed at integration
A13: P-RR10 | B13: v020 | C13: Independent review V001 | D13: Configuration | E13: Fail-closed config trusted booleans; no durable send ledger or opt-out store existed | F13: High | G13: Fixed v020 — the wired objects are inspected | H13: Closed at integration
A14: P-RR11 | B14: v020 | C14: Independent review V001 | D14: Deployment | E14: No migration ledger, checksum or lock | F14: High | G14: Fixed v020 — ledger, checksums, advisory lock, one transaction | H14: Closed at integration
... A33: SELF-2 | B33: v020 | C33: Acceptance test | D33: Money | E33: The billing run counted statements it had only re-read as newly issued | F33: Medium | G33: Caught by the acceptance suite before release | H33: Closed

Sheet Decisions_Open
A1: DECISIONS OPEN — what only Senthil can unblock
A2: Ordered with the total blocker first. Each row names what it unblocks and why it is waiting.
A3: ID | B3: Decision | C3: What it unblocks | D3: Owner | E3: Why it is waiting | F3: Status
A4: DEC-04 | B4: Unpark D14 — the Stripe adapters and a dev account | C4: Everything that touches Stripe: adapters, contract tests, the manifest, the Dashboard UI, the listing | D4: Senthil | E4: Total blocker. Named by Senthil, so only Senthil can lift it. | F4: Open
A5: Decision 2 | B5: Pricing model: percentage of recovered revenue, flat monthly tier, or incremental-versus-holdback (supersedes DEC-03) | C5: The fee percentage everywhere, the single-price drift rule, the listing | D5: Senthil | E5: The independent review judged outcome pricing the weakest part of the plan; the code bills only what it acted on, which is not the same as what it caused. | F5: Open
A6: Decision 3 | B6: Confirm the chosen pricing model with Stripe partnerships in writing | C6: Listing submission | D6: Senthil | E6: The reviewer believes the listing form does not offer this model. Unverified. | F6: Open
A7: Decision 4 | B7: Authorise the holdback experiment | C7: Any claim about incrementality; the FAQ wording | D7: Senthil | E7: Without a control group, we cannot say a reminded customer would not have paid anyway. | F7: Open
A8: DEC-D5 | B8: Approve the corrected help 13 and pricing FAQ wording | C8: Publishing the content; closing V-13 | D8: Senthil | E8: The text is in the code but treated as unapproved. | F8: Open
A9: DEC-RET | B9: Confirm retention periods: audit 7 years, dunning history 2 years, telemetry 13 months, resolved dead letters 90 days | C9: The retention policy applied by the scheduler; the trust page and DPA | D9: Senthil | E9: Defaults are in RETENTION.md and must match what the trust page promises. | F9: Open
A10: DEC-OPS | B10: Name the operator allowlist and the custodian of the operator signing key | C10: Who may replay dead letters and resolve fee disputes | D10: Senthil | E10: The plane is built and audited; the names are a decision. | F10: Open
A11: DEC-02 | B11: How merchants are billed for RevRescue itself | C11: What marks a merchant billing as failed, which drives grace mode and read-only | D11: Senthil | E11: The grace machinery exists but nothing triggers it. | F11: Open
A12: D13 | B12: Unpark five-user discovery | C12: Evidence that the problem and price are real | D12: Senthil | E12: Parked since v004. | F12: Open
A13: T-06 | B13: PRD sign-off | C13: Formal baseline for scope | D13: Senthil | E13: The PRD has been in draft since v002. | F13: Open
A14: Decision 7 | B14: Port the claims gate v2 to the 11 sibling products | C14: Portfolio-wide defect prevention | D14: Senthil | E14: The same defect classes recur across the portfolio. | F14: Open

Sheet Glossary
A1: GLOSSARY
A2: Terms used in this pack, in the tracker and in the code.
A3: Term | B3: Meaning
A4: Attribution | B4: Deciding which single RevRescue action a recovered payment is credited to: a retry, a dunning message or an accepted save offer.
A5: Dunning | B5: The sequence of reminders sent to a customer whose payment failed — days 0, 2, 4 and 7, by email and WhatsApp.
A6: Save offer | B6: A discount or pause offered when a customer starts to cancel.
A7: Statement | B7: The monthly, immutable record of what RevRescue is charging a merchant, itemised per recovered invoice.
A8: Reversal | B8: Money leaving again: a refund or a chargeback on a payment already attributed.
A9: Fee dispute | B9: A merchant challenging a line on their statement. Excluded before issue, credited after.
A10: Idempotency key | B10: A stable identifier sent with a payment attempt so the platform charges once even if the request is repeated.
A11: Dead letter | B11: A record of work the system gave up on after repeated errors, kept for an operator to replay or discard.
A12: Operator plane | B12: The separately authenticated API used by RevRescue staff, not merchants, to replay dead letters and resolve fee disputes.
A13: Row-level security | B13: A Postgres feature that filters every query by tenant inside the database, so application code cannot leak across merchants.
A14: Hash-chained audit | B14: Each audit row stores a hash of the previous one, so edits, insertions and deletions become visible.
... A19: Park audit | B19: Re-testing every parked item against who parked it and why, so nothing stays blocked by assumption (rule L-RR8).

Sheet Sign_Off
A1: SIGN-OFF
A2: Record of review and approval of this pack. Fill the name, date and outcome columns.
A3: Stage | B3: Name | C3: Date | D3: Outcome | E3: Notes
A4: Prepared | B4: Claude | C4: 2026-09-20 10:58 | D4: Issued for review | E4: 56 manual test cases, all pending execution by the reviewer.
A5: Technical review | E5: Confirm the test results recorded in Manual_Test_Cases.
A6: Product owner approval | B6: Senthil (KP) | E6: Approve this pack, then take DEC-D5, DEC-RET and DEC-OPS.
A7: Release approval | B7: Senthil (KP) | E7: Not applicable until DEC-04 is taken and live Stripe evidence exists.
