Workbook

Sheet Version_Control
A1: VERSION CONTROL — EngageOS
A3: Version | B3: Date | C3: Author | D3: Change | E3: Status
A4: v001-v004 | B4: 2026-09-05 | C4: Claude for Senthil/KP | D4: Lineage: marketplace master (868 entries) -> portfolio plan (12 products) -> this product selected for wave-1 | E4: Released
A5: v005 | B5: 2026-09-05 19:34 | C5: Claude for Senthil/KP | D5: Full product workbook for EngageOS on WhatsApp Business Platform (Meta): spec, screen inventory, 100+ story backlog, live sprint board, 18-month financial model (editable assumptions), GTM execution tasks, platform launch checklist, metric targets, risk register | E5: Released
A6: v006 | B6: 2026-09-10 22:22 | C6: Claude for Senthil/KP | D6: S1-S8 development executed: TypeScript codebase (15 modules) covering E1 install, F1-F5 features, E5 billing, E6 compliance, E7 telemetry, E8 onboarding, EQ quality; 100% Jest automation coverage (16 suites / 73 tests) per D13 gate; Sprint_Tracker_Log + Traceability_Matrix sheets added; 75 stories Done, 8 code-complete pending live WhatsApp, 17 backlog (external/GTM) | E6: Released
A7: v007 | B7: 2026-09-10 22:55 | C7: Claude for Senthil/KP | D7: S9-S10 draftable scope executed: WhatsApp compliance modules (24h session window, webhook dedupe/burst, opt-in proof, demo-data mode) at 100% coverage (20 suites / 78 tests); listing copy A/B, pricing+FAQ, trust page, demo script, launch runbook, incident comms, 15 help articles, k6 load harness, backup drill, blue/green workflow, hi/ta i18n, 20 message templates drafted; Launch_Checklist re-statused; 10 stories Drafted, ST-097 In progress | E7: Released
A8: v008 | B8: 2026-09-10 23:10 | C8: Claude for Senthil/KP | D8: Live-sweep readiness: typed env config loader (hard validation, no silent secret defaults), CloudApiAdapter — real WhatsApp Cloud API implementation of the WaApi interface (text + template sends, quality-rating mapping, offline-tested via injected fetch), runLiveSweep 6-step scripted verification (config/send/quality/session-window/dedupe/opt-in gate), 30-min Meta/WABA setup guide, 12-step verification sweep doc, .env.example. 23 suites / 86 tests at 100%x4. No story-status changes: Pending-live stories flip only on real sweep evidence (R2). | E8: Released
A9: v009 | B9: 2026-09-11 08:17 | C9: Claude for Senthil/KP | D9: Adversarial cold-review pass 1 + fixes: F-001 unconfigured-inbox crash, F-002 chatbot question-node TypeError, F-003 unbounded webhook dedupe ledger (FIFO-capped), F-004 template language parameterised for hi/ta — all with regression tests, coverage held 100%x4 (23 suites / 90 tests, codebase v0.9.0); F-005..F-008 logged in tracker v003 Review_Findings for disposition; REVIEW_PACK.md added for the external second reviewer (ST-097 stays In progress). No story-status changes. | E9: Released
A10: v010 | B10: 2026-09-11 12:51 | C10: Claude for Senthil/KP | D10: Review-prep completion wave: accessible screen shells (views.ts — semantic HTML, landmarks, labelled controls, escaping) + jest-axe automated WCAG suite over populated AND empty states -> ST-089 Done; SECURITY_EVIDENCE.md sandbox half -> ST-068 In progress (vendor pen-test pending); ASSET_PLAN.md 5-shot list + video plan mapped to shells + demo mode -> ST-094 Drafted. Codebase v0.10.0: 24 suites / 94 tests at 100%x4. Backlog now 3 stories, all truly external (ST-081 chat vendor, ST-099 post-launch SEO, ST-100 design partners). | E10: Released
A11: v011 | B11: 2026-09-13 09:55 | C11: Claude for Senthil/KP | D11: Cold-review pass 2 (all modules pass 1 skipped) + completion wave. Pass 2 fixed 8 defects with pinned regressions — headline F-009/F-010: optIn.ts and sessionWindow.ts had existed since v007 but NOTHING CALLED THEM, so marketing broadcasts could reach non-consented contacts and free-form messages could be sent outside the 24-hour window (both platform violations, invisible to a 100%-coverage suite); also F-011 read-only/cancelled states enforced nowhere, F-012 no payment-recovery path, F-013 trial never expired, F-014 deletion flagged but never purged (published 30-day policy breached), F-015 naive CSV split corrupted quoted fields, F-016 unbounded in-memory ledgers. Completion wave: ST-081 built-in chat + SLA engine (chat vendor now optional), ST-080 ranked help search + drift gate, ST-095 pricing bound to billing PLANS, ST-099 SEO engine, ST-100 partner tracker. Codebase v0.11.0: 27 suites / 118 tests at 100%x4, 1 documented pragma. BACKLOG ZERO. | E11: Released
A12: v012 | B12: 2026-09-13 10:23 | C12: Claude for Senthil/KP | D12: Artifact-gap audit (sibling pattern) — 6 gaps found, 2 CRITICAL: GAP-E1 NO HTTP APP existed behind the /webhook callback URL the setup guide tells Meta to register, the /healthz the deploy workflow curls, or the route the k6 harness posts to — the 30-minute live path was unrunnable and the sweep would have died at step 9; GAP-E2 NO DB SCHEMA behind the backup/restore drill and the F-014 purge. Also GAP-E3 X-Hub-Signature-256 never verified (forged webhooks accepted), GAP-E4 hub.challenge handshake missing so Meta could not save the callback URL at all, GAP-E5 k6 posted unsigned ad-hoc bodies the app would 401, GAP-E6 pricing FAQ ungated vs billing PLANS. All fixed: framework-free router + app (6 routes), Node server entry with npm start, signature verify, 4 ordered migrations with cascade deletes + npm run migrate, signed fixture generator, npm run sweep CLI, docs/pricing drift gates. ST-088/090/092 Drafted -> Code-complete. Codebase v0.12.0: 31 suites / 131 tests at 100%x4. | E12: Released
A13: v013 | B13: 2026-09-13 10:35 | C13: Claude for Senthil/KP | D13: Cold-review pass 3 over the HTTP layer built in v012 (new surfaces inherit old blind spots — sibling lesson): 4 defects fixed, 2 CRITICAL. F-017 NO MULTI-TENANCY — one WebhookGuard and one SessionWindow served the whole process, so tenants shared a dedupe ledger (one account's retry could suppress another's genuine message), one tenant's burst could evict another's events, and any inbound opened the 24-hour window for every tenant; now a TenantRegistry with per-tenant guard + window resolved from metadata.phone_number_id. F-018 SIGNATURE-IS-NOT-INSTALLATION — a correctly signed payload for a number we do not serve was processed; now 404 and logged, never lazily registered. F-019 unauthenticated /healthz and /status leaked release, queue depth and error counts; moved behind ENGAGEOS_OPERATOR_TOKEN with liveness-only public routes. F-020 embedded signup had no CSRF protection; now single-use 10-minute OAuth state with /oauth/start + /oauth/callback registering the tenant. Codebase v0.13.0: 31 suites / 136 tests at 100%x4. Story rollup unchanged — correctness release. | E13: Released
A14: v014 | B14: 2026-09-13 10:38 | C14: Claude for Senthil/KP | D14: External verification sweep against live Meta/WhatsApp Cloud API documentation (not against our own assumptions) — 6 findings, 2 serious. VER-E5 DATA LOSS: webhook envelopes are batched (entry[]/changes[]/messages[] are all arrays and one POST can carry several messages for several numbers) and the app read only [0] of each — every message after the first was silently dropped; this is documented as the most common integration mistake and no test could see it because our own fixtures carried one message. VER-E1 COMMERCIAL MODEL WRONG: Meta replaced conversation-based pricing with PER-MESSAGE pricing on 1 July 2025 and the old 1,000-free-conversations allowance is gone — plans were metered in "conversations/mo" and the pricing page promised to pass through "conversation fees", a unit Meta no longer bills. Also VER-E2 template categories are marketing/utility/authentication (we modelled two), VER-E3 the 72-hour free-entry-point window (Click-to-WhatsApp ads) was unmodelled so those chats were wrongly template-gated, VER-E4 fast-ack/retry semantics confirmed correct-by-design, VER-E6 80 msg/s base outbound throughput now enforced by a limiter. New modules messageCost.ts (free-vs-billable rules, rate card as configuration since Meta revises up to quarterly) and throughput.ts. Codebase v0.14.0: 32 suites / 144 tests at 100%x4. | E14: Released
... A44: v044 | B44: 2026-09-13 22:49 | C44: Claude for Senthil/KP | D44: The audit kit had shipped three bugs of its own, was about to go to eleven other products, and had no tests. That is not a position I can defend, least of all while using it to argue that other people's code makes unverified claims. It now has eleven: seven node tests and four python, and one is named for each bug it has shipped — the reachability false positive, the backlog silently skipped by a bare "log" pattern, and the undetected first-person user stories. Writing them corrected a fourth misunderstanding, mine rather than the tool's: a test expected reachability to exempt an entry module automatically, when the correct behaviour is to report it unless the consumer directory is supplied — which is precisely the false positive the kit had already been fixed for. The test now asserts both halves of that contrast so the behaviour is documented rather than assumed. The kit is version 1.0.0, runs in this product's CI, and ships standalone. Codebase v0.43.0: 51 suites / 365 tests at 100%; kit 11 tests; 62 modules reachable, 49 promises kept, 58 findings defended. | E44: Released
A45: v045 | D45: PLANNED: opens on the first live evidence, disposition or decision from the tracker handover sheet. | E45: Planned

Sheet ReadMe_Scope
A1: EngageOS — WhatsApp-first engagement suite: shared team inbox, campaign broadcasts, catalog + payments links, chatbots
A3: PLATFORM: WhatsApp Business Platform (Meta) | CATEGORY: SME Customer Engagement
A4: PROBLEM: 2B+ WhatsApp users; SMEs in IN/SEA/LatAm run business on it but tooling is fragmented
A5: DIFFERENTIATION: Vertical templates (retail/clinics/education), UPI payment links, multi-agent inbox at SME price point
A6: ICP: SMEs 2-50 staff in India/SEA/LatAm/MEA: retail, clinics, coaching, services — WhatsApp is their storefront
A8: HOW TO USE: Full_Backlog is the single source of truth (edit Status column during execution). Sprint_Board recalculates points per sprint automatically. Financial_Model assumptions (yellow) are editable — the 18-month build recalculates. Launch_Checklist is the platform-specific gate before submission. All costs/timelines are market-standard estimates; verify platform terms (fees/review rules) during S0.
A10: STACK ASSUMPTION (market standard): TypeScript/Node or platform-mandated runtime, React frontends, Postgres, hosted on AWS/GCP/platform FaaS as required, GitHub Actions CI, PostHog + Sentry telemetry, Intercom-class support.

Sheet Product_Spec
A1: PRODUCT SPEC
A3: Module (feature) | B3: Scope in MVP | C3: Out of scope (v1) | D3: Non-functional requirements
A4: Team inbox + assignment | B4: Team inbox + assignment: end-to-end happy path + edge cases + permissions | C4: Advanced automation, AI beyond listed, multi-language beyond launch set | D4: p95 <500ms API / <2s UI — budgets defined and unit-tested (latency.ts); NOT measured on live infra
A5: Broadcast campaigns + segments | B5: Broadcast campaigns + segments: end-to-end happy path + edge cases + permissions | C5: Advanced automation, AI beyond listed, multi-language beyond launch set | D5: 99.5% uptime — target only; no live deployment, so unmeasured
A6: No-code chatbot flows | B6: No-code chatbot flows: end-to-end happy path + edge cases + permissions | C6: Advanced automation, AI beyond listed, multi-language beyond launch set | D6: WCAG AA — axe audit clean on four rendered screen shells; NOT audited on a styled live UI or with a screen reader
A7: Catalog + payment links | B7: Catalog + payment links: end-to-end happy path + edge cases + permissions | C7: Advanced automation, AI beyond listed, multi-language beyond launch set | D7: SOC2-track controls — evidence pack compiled (scopes, authz, crypto config, data rights); no audit engaged
A8: Analytics + quality-score guard | B8: Analytics + quality-score guard: end-to-end happy path + edge cases + permissions | C8: Advanced automation, AI beyond listed, multi-language beyond launch set | D8: Rate-limit safe — backoff + circuit breaker + 80 msg/s throughput limiter + portfolio tier cap, all verified against Meta docs
A10: Persona | B10: Jobs-to-be-done
A11: SME owner | B11: Buys on missed-lead recovery; needs vernacular UI
A12: Marketing person (solo) | B12: Broadcast + segment without CSV pain
A13: Support agent | B13: Multi-agent inbox with assignment
A15: AS-BUILT NOTE (13 Sep 2026): every MVP module is code-complete with 100% automated coverage, but "end-to-end" in column B means end-to-end against a fake WhatsApp surface. No module has been exercised against live Meta infrastructure.

Sheet Screens_Wireframes
A1: SCREEN INVENTORY (attach Figma links in col E during S0)
D2: As-built (13 Sep 19:11)
A3: # | B3: Screen | C3: Purpose | D3: Built — checklist with progress | E3: Wireframe link
A4: 1 | B4: Onboarding / first-run | C4: Reach aha in <1 day | D4: Built — open conversations + number quality
A5: 2 | B5: Home dashboard | C5: Daily habit surface | D5: Built — list, open, reply, assign
A6: 3 | B6: Team inbox + assignment workspace | C6: Core value surface | D6: Built — compose + test send
A7: 4 | B7: Broadcast campaigns + segments builder | C7: Configure second pillar | D7: Built — create, test-run, empty state
A8: 5 | B8: No-code chatbot flows view | C8: Differentiator surface | D8: Built — notification controls (roles enforced server-side)
A9: 6 | B9: Settings & team | C9: Roles, notifications, data | D9: Built — trial banner, start trial
A10: 7 | B10: Billing | C10: Plan/trial/invoices | D10: Built — quality + messaging limit in plain words
A11: 8 | B11: Analytics | C11: Prove ROI | D11: Built — search then ticket
A12: 9 | B12: Help & support | C12: Deflect + assist | D12: Search, chat, status

Sheet Full_Backlog
A1: FULL BACKLOG
A3: ID | B3: Epic | C3: Story | D3: Points | E3: Priority | F3: Sprint | G3: Status
A4: ST-001 | B4: F1 | C4: As a SME owner, I can set up Team inbox + assignment with sensible defaults in one screen | D4: 5 | E4: P0 | F4: S2 | G4: Done
A5: ST-002 | B5: F1 | C5: As a SME owner, the Team inbox + assignment happy path completes without documentation | D5: 8 | E5: P0 | F5: S2 | G5: Done
A6: ST-003 | B6: F1 | C6: As a Marketing person, I can customise Team inbox + assignment rules/conditions for my workflow | D6: 5 | E6: P1 | F6: S2 | G6: Done
A7: ST-004 | B7: F1 | C7: As a user, Team inbox + assignment shows clear errors and retry paths on platform API failures | D7: 3 | E7: P0 | F7: S2 | G7: Done
A8: ST-005 | B8: F1 | C8: As a Support agent, Team inbox + assignment works on the web app + WhatsApp Cloud API surface end-to-end | D8: 5 | E8: P0 | F8: S3 | G8: Code-complete (pending live WhatsApp)
A9: ST-006 | B9: F1 | C9: As a Marketing person, I can see Team inbox + assignment performance metrics and trends | D9: 3 | E9: P1 | F9: S3 | G9: Done
A10: ST-007 | B10: F1 | C10: As a user, Team inbox + assignment respects role permissions and audit logging | D10: 3 | E10: P1 | F10: S3 | G10: Done
A11: ST-008 | B11: F1 | C11: As a SME owner, I can pause/disable Team inbox + assignment without data loss | D11: 2 | E11: P2 | F11: S3 | G11: Done
A12: ST-009 | B12: F1 | C12: As a Marketing person, I can import/migrate existing data into Team inbox + assignment (CSV + competitor importer) | D12: 5 | E12: P1 | F12: S3 | G12: Done
A13: ST-010 | B13: F1 | C13: As a user, I get notifications (in-app + email) for key Team inbox + assignment events with per-type mute | D13: 3 | E13: P2 | F13: S3 | G13: Done
A14: ST-011 | B14: F2 | C14: As a SME owner, I can set up Broadcast campaigns + segments with sensible defaults in one screen | D14: 5 | E14: P0 | F14: S3 | G14: Done
A15: ST-012 | B15: F2 | C15: As a SME owner, the Broadcast campaigns + segments happy path completes without documentation | D15: 8 | E15: P0 | F15: S3 | G15: Done
... A103: ST-100 | B103: EL | C103: First 10 design-partner reviews scheduled | D103: 2 | E103: P1 | F103: S11 | G103: Code-complete (pending live WhatsApp)
A105: Total stories: 100. Epics: F1-F5 = product features; E1 install, E5 billing, E6 compliance, E7 telemetry, E8 onboarding/docs/support, EQ quality. Edit Status (Backlog/In progress/Done) during execution.

Sheet Sprint_Board
A1: SPRINT BOARD — live counts from Full_Backlog
A3: Sprint | B3: Focus | C3: Stories | D3: Points | E3: Done | F3: Exit criteria
A4: S0 | B4: Discovery & Design (2 wks) | C4: =COUNTIF(Full_Backlog!F4:F103,"S0") -> 0 | D4: =SUMIF(Full_Backlog!F4:F103,"S0",Full_Backlog!D4:D103) -> 0 | E4: =COUNTIFS(Full_Backlog!F4:F103,"S0",Full_Backlog!G4:G103,"Done") -> 0 | F4: PRD signed off; prototype tested with 5 target users
A5: S1 | B5: Foundation (2 wks) | C5: =COUNTIF(Full_Backlog!F4:F103,"S1") -> 4 | D5: =SUMIF(Full_Backlog!F4:F103,"S1",Full_Backlog!D4:D103) -> 13 | E5: =COUNTIFS(Full_Backlog!F4:F103,"S1",Full_Backlog!G4:G103,"Done") -> 3 | F5: App installs cleanly in dev store/org; telemetry firing
A6: S2 | B6: Core feature Team inbox + assignment - part 1 | C6: =COUNTIF(Full_Backlog!F4:F103,"S2") -> 6 | D6: =SUMIF(Full_Backlog!F4:F103,"S2",Full_Backlog!D4:D103) -> 29 | E6: =COUNTIFS(Full_Backlog!F4:F103,"S2",Full_Backlog!G4:G103,"Done") -> 6 | F6: Team inbox + assignment happy path demoable
A7: S3 | B7: Core feature Team inbox + assignment - part 2 + Broadcast campaigns + segments start | C7: =COUNTIF(Full_Backlog!F4:F103,"S3") -> 11 | D7: =SUMIF(Full_Backlog!F4:F103,"S3",Full_Backlog!D4:D103) -> 47 | E7: =COUNTIFS(Full_Backlog!F4:F103,"S3",Full_Backlog!G4:G103,"Done") -> 10 | F7: Team inbox + assignment complete with tests; Broadcast campaigns + segments skeleton
A8: S4 | B8: Core feature Broadcast campaigns + segments | C8: =COUNTIF(Full_Backlog!F4:F103,"S4") -> 9 | D8: =SUMIF(Full_Backlog!F4:F103,"S4",Full_Backlog!D4:D103) -> 34 | E8: =COUNTIFS(Full_Backlog!F4:F103,"S4",Full_Backlog!G4:G103,"Done") -> 8 | F8: MVP loop usable end-to-end internally
A9: S5 | B9: Feature No-code chatbot flows + alpha hardening | C9: =COUNTIF(Full_Backlog!F4:F103,"S5") -> 12 | D9: =SUMIF(Full_Backlog!F4:F103,"S5",Full_Backlog!D4:D103) -> 50 | E9: =COUNTIFS(Full_Backlog!F4:F103,"S5",Full_Backlog!G4:G103,"Done") -> 11 | F9: Internal alpha: team dogfoods daily
A10: S6 | B10: Billing + Catalog + payment links | C10: =COUNTIF(Full_Backlog!F4:F103,"S6") -> 13 | D10: =SUMIF(Full_Backlog!F4:F103,"S6",Full_Backlog!D4:D103) -> 60 | E10: =COUNTIFS(Full_Backlog!F4:F103,"S6",Full_Backlog!G4:G103,"Done") -> 11 | F10: Can charge a test customer; upgrade/downgrade paths work
A11: S7 | B11: Private beta (design partners) | C11: =COUNTIF(Full_Backlog!F4:F103,"S7") -> 5 | D11: =SUMIF(Full_Backlog!F4:F103,"S7",Full_Backlog!D4:D103) -> 15 | E11: =COUNTIFS(Full_Backlog!F4:F103,"S7",Full_Backlog!G4:G103,"Done") -> 5 | F11: 3+ partners active weekly; NPS pulse >30
A12: S8 | B12: Beta iteration + Analytics + quality-score guard | C12: =COUNTIF(Full_Backlog!F4:F103,"S8") -> 22 | D12: =SUMIF(Full_Backlog!F4:F103,"S8",Full_Backlog!D4:D103) -> 87 | E12: =COUNTIFS(Full_Backlog!F4:F103,"S8",Full_Backlog!G4:G103,"Done") -> 18 | F12: Retention of beta cohort week-over-week >60%
A13: S9 | B13: Marketplace review prep | C13: =COUNTIF(Full_Backlog!F4:F103,"S9") -> 7 | D13: =SUMIF(Full_Backlog!F4:F103,"S9",Full_Backlog!D4:D103) -> 30 | E13: =COUNTIFS(Full_Backlog!F4:F103,"S9",Full_Backlog!G4:G103,"Done") -> 3 | F13: Review submission accepted into queue
A14: S10 | B14: Review remediation + docs | C14: =COUNTIF(Full_Backlog!F4:F103,"S10") -> 7 | D14: =SUMIF(Full_Backlog!F4:F103,"S10",Full_Backlog!D4:D103) -> 24 | E14: =COUNTIFS(Full_Backlog!F4:F103,"S10",Full_Backlog!G4:G103,"Done") -> 3 | F14: Marketplace approval obtained (or final remediation cycle)
A15: S11 | B15: Launch | C15: =COUNTIF(Full_Backlog!F4:F103,"S11") -> 3 | D15: =SUMIF(Full_Backlog!F4:F103,"S11",Full_Backlog!D4:D103) -> 8 | E15: =COUNTIFS(Full_Backlog!F4:F103,"S11",Full_Backlog!G4:G103,"Done") -> 1 | F15: First 10 installs; first 3 reviews; activation >40%
A16: S12 | B16: Iterate & scale decision | C16: =COUNTIF(Full_Backlog!F4:F103,"S12") -> 1 | D16: =SUMIF(Full_Backlog!F4:F103,"S12",Full_Backlog!D4:D103) -> 2 | E16: =COUNTIFS(Full_Backlog!F4:F103,"S12",Full_Backlog!G4:G103,"Done") -> 0 | F16: Growth model doc with CAC/LTV first estimates
B17: TOTAL | C17: =SUM(C4:C16) -> 100 | D17: =SUM(D4:D16) -> 399 | E17: =SUM(E4:E16) -> 79
B18: Velocity check: points/sprint S2-S8 should sit within 30-45 for a 4-6 person team; rebalance Sprint column in backlog if a sprint exceeds capacity.

Sheet Financial_Model
A1: 18-MONTH FINANCIAL MODEL — WhatsApp: BSP-channel + direct (edit yellow assumptions)
A3: Assumption | B3: Value
A4: Signups/mo (month 1) | B4: 60
A5: Monthly growth of that | B5: 0.12
A6: Trial->paid % | B6: 0.18
A7: ARPU $/mo | B7: 49
A8: Monthly churn | B8: 0.035
A9: Marketplace fee | B9: 0
A10: Team cost month 1 (India-lean $) | B10: 26000
A11: Cost growth/mo | B11: 0.03
A12: Fee note: no Meta cut on SaaS revenue. Meta bills the CUSTOMER per delivered template message (category x country) since 1 Jul 2025 — conversation-based pricing is deprecated, so "conversation fees" no longer exist as a unit. Pass-through, not revenue, and not modelled here.
A14: Line | B14: M1 | C14: M2 | D14: M3 | E14: M4 | F14: M5 | G14: M6 | H14: M7 | I14: M8 | J14: M9 | K14: M10 | L14: M11 | M14: M12 | N14: M13 | O14: M14 | P14: M15 | Q14: M16 | R14: M17 | S14: M18
A15: Leads/installs | B15: =$B$4 -> 60 | C15: =B15*(1+$B$5) -> 67.2 | D15: =C15*(1+$B$5) -> 75.264 | E15: =D15*(1+$B$5) -> 84.29568 | F15: =E15*(1+$B$5) -> 94.411162 | G15: =F15*(1+$B$5) -> 105.7405 | H15: =G15*(1+$B$5) -> 118.42936 | I15: =H15*(1+$B$5) -> 132.64088 | J15: =I15*(1+$B$5) -> 148.55779 | ... S15: =R15*(1+$B$5) -> 411.96245
A16: New paying | B16: =ROUND(B15*$B$6,1) -> 10.8 | C16: =ROUND(C15*$B$6,1) -> 12.1 | D16: =ROUND(D15*$B$6,1) -> 13.5 | E16: =ROUND(E15*$B$6,1) -> 15.2 | F16: =ROUND(F15*$B$6,1) -> 17 | G16: =ROUND(G15*$B$6,1) -> 19 | H16: =ROUND(H15*$B$6,1) -> 21.3 | I16: =ROUND(I15*$B$6,1) -> 23.9 | ... S16: =ROUND(S15*$B$6,1) -> 74.2
A17: Paying accounts | B17: =B16 -> 10.8 | C17: =ROUND(B17*(1-$B$8)+C16,1) -> 22.5 | D17: =ROUND(C17*(1-$B$8)+D16,1) -> 35.2 | E17: =ROUND(D17*(1-$B$8)+E16,1) -> 49.2 | F17: =ROUND(E17*(1-$B$8)+F16,1) -> 64.5 | G17: =ROUND(F17*(1-$B$8)+G16,1) -> 81.2 | H17: =ROUND(G17*(1-$B$8)+H16,1) -> 99.7 | I17: =ROUND(H17*(1-$B$8)+I16,1) -> 120.1 | J17: =ROUND(I17*(1-$B$8)+J16,1) -> 142.6 | ... S17: =ROUND(R17*(1-$B$8)+S16,1) -> 499.1
A18: MRR (net of fee) | B18: =ROUND(B17*$B$7*(1-$B$9),0) -> 529 | C18: =ROUND(C17*$B$7*(1-$B$9),0) -> 1103 | D18: =ROUND(D17*$B$7*(1-$B$9),0) -> 1725 | E18: =ROUND(E17*$B$7*(1-$B$9),0) -> 2411 | F18: =ROUND(F17*$B$7*(1-$B$9),0) -> 3161 | G18: =ROUND(G17*$B$7*(1-$B$9),0) -> 3979 | H18: =ROUND(H17*$B$7*(1-$B$9),0) -> 4885 | I18: =ROUND(I17*$B$7*(1-$B$9),0) -> 5885 | ... S18: =ROUND(S17*$B$7*(1-$B$9),0) -> 24456
A19: Team cost | B19: =$B$10 -> 26000 | C19: =ROUND(B19*(1+$B$11),0) -> 26780 | D19: =ROUND(C19*(1+$B$11),0) -> 27583 | E19: =ROUND(D19*(1+$B$11),0) -> 28410 | F19: =ROUND(E19*(1+$B$11),0) -> 29262 | G19: =ROUND(F19*(1+$B$11),0) -> 30140 | H19: =ROUND(G19*(1+$B$11),0) -> 31044 | I19: =ROUND(H19*(1+$B$11),0) -> 31975 | J19: =ROUND(I19*(1+$B$11),0) -> 32934 | ... S19: =ROUND(R19*(1+$B$11),0) -> 42972
A20: Net cash/mo | B20: =B18-B19 -> -25471 | C20: =C18-C19 -> -25677 | D20: =D18-D19 -> -25858 | E20: =E18-E19 -> -25999 | F20: =F18-F19 -> -26101 | G20: =G18-G19 -> -26161 | H20: =H18-H19 -> -26159 | I20: =I18-I19 -> -26090 | ... S20: =S18-S19 -> -18516
A21: Cumulative | B21: =B20 -> -25471 | C21: =B21+C20 -> -51148 | D21: =C21+D20 -> -77006 | E21: =D21+E20 -> -103005 | F21: =E21+F20 -> -129106 | G21: =F21+G20 -> -155267 | H21: =G21+H20 -> -181426 | I21: =H21+I20 -> -207516 | J21: =I21+J20 -> -233463 | ... S21: =R21+S20 -> -440181
A23: Reading: churn applies before adds; MRR nets the marketplace fee; costs use India-lean base from Team_Roles_Budget (v004). Breakeven = first month Net cash ≥ 0. This is a planning model, not a forecast — replace assumptions with S7-S8 beta actuals.
A25: AS-BUILT CAVEATS (added 13 Sep 2026 after verification sweeps — read before using this model)
A26: 1. ARPU $49 assumes the Growth plan. Plan allowances are now denominated in DELIVERED TEMPLATE MESSAGES, not conversations (VER-E1). Whether 1,000/5,000/20,000 at $29/$49/$99 holds margin is an OPEN DECISION — per-message rates vary roughly 13x by market, so an India-first book and a Europe-facing book behave very differently.
A27: 2. Signups/mo and activation assume a customer can broadcast on day one. They cannot: Meta starts a new portfolio at 250 unique customers per 24 hours and raises it on verification and quality (R-E8). Early activation and time-to-value are shaped by that ladder, not by our onboarding.
A28: 3. Marketplace fee is 0 because WhatsApp has no app-store revenue share — correct, and different from the Shopify/Atlassian products in this portfolio.
A29: 4. Team cost is the India-lean base from the v004 plan and has not been revisited since 5 Sep.
A30: 5. This stays a planning model. Replace assumptions with S7-S8 beta actuals; none exist yet because no live evidence has been collected.

Sheet GTM_Execution
A1: GTM EXECUTION TASKS
A3: Phase | B3: Task | C3: Owner (role) | D3: Target sprint
A4: Pre-launch | B4: Positioning doc + message house (problem/promise/proof) | C4: Founder | D4: S7
A5: Pre-launch | B5: Listing SEO: keyword study in marketplace search + title/intro drafts | C5: Growth | D5: S8
A6: Pre-launch | B6: 10 design-partner mini case snippets with metric proof | C6: Founder | D6: S8
A7: Pre-launch | B7: 5 comparison/alternative pages drafted | C7: Growth | D7: S9
A8: Pre-launch | B8: Screenshots (5) + 2-min demo video produced | C8: Design | D8: S9
A9: Launch | B9: Listing live + launch post + video published | C9: Growth | D9: S11
A10: Launch | B10: Founder outreach: 100 named ICP accounts, 3-touch sequence | C10: Founder | D10: S11
A11: Launch | B11: Community value-posts (3 relevant communities) | C11: Founder | D11: S11
A12: Launch | B12: Review-generation program on (in-app ask post-aha) | C12: Eng | D12: S11
A13: Post-launch | B13: Weekly SEO/how-to content cadence starts | C13: Growth | D13: S12
A14: Post-launch | B14: Marketplace paid placement pilot (where offered) | C14: Growth | D14: S12
... A16: Post-launch | B16: G2/Capterra profiles + first 10 reviews | C16: Growth | D16: S12+

Sheet Launch_Checklist
A1: PLATFORM LAUNCH CHECKLIST — WhatsApp Business Platform (Meta)
A3: # | B3: Item | C3: Status
A4: 1 | B4: Meta Business verification + WhatsApp Business Account (WABA) production access | C4: Open (yours) — software side rehearsed end to end on 13 Sep: see docs/REHEARSAL_TRANSCRIPT.md. Only Meta verification and credentials are missing
A5: 2 | B5: BSP agreement signed (360dialog/Gupshup class) OR Cloud API direct path chosen | C5: Cloud API direct path chosen (no BSP) — D-E1, awaiting your ratification
A6: 3 | B6: Display name approved; phone number quality rating monitoring in place | C6: Done in code — quality guard with green/amber/red thresholds and throttle action; display-name approval and live rating monitoring need the number
A7: 4 | B7: Message template library (20+ approved across utility/marketing categories) | C7: Drafted — 20 templates in docs/templates/MESSAGE_TEMPLATES.md, now backed by a registry declaring each one's variables with the body components Meta requires (F-037); Meta approval pending
A8: 5 | B8: Opt-in capture flows compliant (checkbox + proof storage) | C8: Done in code — OptInRegistry proof storage + marketing gate; live flow QA pending
A9: 6 | B9: Per-message pricing pass-through reconciled against the Meta invoice (conversation-based pricing was deprecated 1 Jul 2025) | C9: Per-MESSAGE pass-through billing reconciliation (Meta retired conversation pricing 1 Jul 2025) — cost model shipped in messageCost.ts; live invoice reconciliation pending first bill
A10: 7 | B10: 24-hour session logic + template fallback tested | C10: Done in code — SessionWindow 24h logic + template fallback tested; live test pending
A11: 8 | B11: Webhook resilience: retry + dedupe at 50 msg/s burst | C11: Done in code — store-backed dedupe survives a blue/green switch; 50/s burst shape tested; live burst pending
A12: 9 | B12: Data retention + DPDP(India)/GDPR policy live | C12: Drafted — trust page + DATA_FLOW.md retention; DPDP/GDPR legal review pending
A13: 10 | B13: Vernacular UI pack (Hindi/Tamil) QA complete | C13: Done in code — the agent workspace ships in English, Hindi and Tamil with a language switcher and drift-gated packs; native-speaker review before launch is still owed

Sheet Metrics_Targets
A1: METRIC TARGETS (first 12 months post-launch)
A3: Metric | B3: M1 | C3: M3 | D3: M6 | E3: M12 | F3: Notes
A4: Installs/signups cumulative | B4: varies | C4: 3x M1 | D4: 8x M1 | E4: 20x M1 | F4: Drive via listing SEO + outbound — MEASURABLE once listed (install attribution shipped)
A5: Activation % (24h) | B5: 30% | C5: 40% | D5: 45% | E5: 50% | F5: Onboarding iterations S12+ — MEASURABLE (activation funnel + aha tracking shipped)
A6: Trial→paid % | B6: baseline | C6: +2pts | D6: +4pts | E6: +6pts | F6: Pricing test at S12 — MEASURABLE (trial/convert states in billing)
A7: Rating | B7: 4.5+ | C7: 4.6+ | D7: 4.7+ | E7: 4.7+ | F7: Review program + support speed — NOT measurable by us; marketplace-side data
A8: MRR | B8: first $ | C8: 3x | D8: 8x | E8: 20x | F8: Model sheet has the math — MEASURABLE (billing is the source of truth)
A9: Logo churn/mo | B9: <5% | C9: <4% | D9: <3% | E9: <3% | F9: Health-score saves — MEASURABLE (health score + cancellation reasons shipped)
A11: AS-BUILT NOTE (13 Sep 2026): five of six targets are instrumented in code and will report from day one; marketplace rating is the exception and must be read from Meta/listing surfaces. No target has a baseline yet — all require live installs.

Sheet Risk_Register
A1: PRODUCT RISK REGISTER
A3: Risk | B3: Impact | C3: Likelihood | D3: Mitigation
A4: R-E1 — WhatsApp quality-rating drop throttles number | B4: High | C4: Medium | D4: Quality-guard feature; opt-in hygiene enforced in-product
A5: R-E2 — Meta pricing change squeezes campaign ROI for SMEs | B5: Medium | C5: Medium | D5: Multi-channel fallback (SMS/email) roadmap
A6: R-E3 — BSP dependency (terms/latency) | B6: Medium | C6: Medium | D6: Dual-BSP abstraction; direct Cloud API path maintained
A7: R-E7 | B7: Meta revises per-message rates up to quarterly and by market — plan margins move without any code change | C7: Medium/High | D7: Rate card is configuration (messageCost.ts RateCard), never constants; margin review at each Meta rate update; VER-E1 decision pending
A8: R-E8 | B8: Messaging-limit ladder gates go-to-market: a new portfolio can reach only 250 unique customers/24h, so the S11 exit (10 installs, activation >40%) and any customer's first campaign are shaped by Meta's trust ladder, not by our software | C8: High/Medium | D8: Tier metering + upgrade-readiness shipped; onboarding must set expectations; Business Verification is the single biggest unlock and is on the critical path (LC-1)
A9: R-E9 | B9: Horizontal scaling is gated on the Postgres shared store: with the in-memory default only one instance may serve traffic, so a blue/green switch must drain rather than overlap | C9: Medium/High | D9: SharedStore boundary + PgStore + migrations 005/006 shipped; deploy.yml guard step; wiring SHARED_STORE=pg is a live-infra task on the first deploy

Sheet Sprint_Tracker_Log
A1: SPRINT TRACKER LOG — EngageOS (session-by-session execution record)
A3: # | B3: Date/Time | C3: Sprint | D3: Activity | E3: Stories moved | F3: Points Done | G3: Tests | H3: Coverage | I3: Notes / Blockers
A4: 1 | B4: 2026-09-10 22:22 | C4: S1 | D4: Foundation: install lifecycle — OAuth install, uninstall webhook (token purge + retention deletion), re-install, token rotation, source attribution (install.ts) | E4: ST-052/055/056 Done; ST-051 code-complete | F4: 8/13 | G4: install suite | H4: 100% | I4: ST-051 <2 min dev-store install needs live Meta dev account
A5: 2 | B5: 2026-09-10 22:22 | C5: S2 | D5: F1 part 1: inbox defaults, happy path, custom rules, API error/retry; roles matrix + re-install story | E5: ST-001..004, 053, 054 Done | F5: 29/29 | G5: inbox, roles suites | H5: 100% | I5: —
A6: 3 | B6: 2026-09-10 22:22 | C6: S3 | D6: F1 part 2 (metrics, permissions, pause, CSV import, notifications) + F2 start (campaign create/segments/errors) + coverage gate | E6: ST-006..014, 085 Done; ST-005 code-complete | F6: 42/47 | G6: inbox, broadcast, notify suites | H6: 100% | I6: D13: 100% gate in jest coverageThreshold supersedes ST-085 >=70%
A7: 4 | B7: 2026-09-10 22:22 | C7: S4 | D7: F2 complete (send/test-mode/metrics/pause/import) + funnel events + error-spike alert + E2E smoke on deploy | E7: ST-016..020, 071, 072, 086 Done; ST-015 code-complete | F7: 29/34 | G7: broadcast, telemetry, smoke suites | H7: 100% | I7: Smoke wired into CI (ci.yml) on push/PR/deploy
A8: 5 | B8: 2026-09-10 22:22 | C8: S5 | D8: F3 chatbot flows (default flow, run engine, node edits, export/import, loop/broken-link detection) + onboarding checklist/empty states | E8: ST-021..024, 026..030, 078, 079 Done; ST-025 code-complete | F8: 45/50 | G8: chatbot, onboarding suites | H8: 100% | I8: —
A9: 6 | B9: 2026-09-10 22:22 | C9: S6 | D9: F4 catalog + UPI payment links + billing core (14-day trial, proration, provider selection) | E9: ST-031..034, 036..040, 057, 058 Done; ST-035/059 code-complete | F9: 47/60 | G9: catalog, billing suites | H9: 100% | I9: ST-059 marketplace-billing mandate check needs verified Meta terms (S0 item)
A10: 7 | B10: 2026-09-10 22:22 | C10: S7 | D10: Billing hardening: dunning (7d grace/3 emails/read-only), plan limits 80/100 prompts, GST/VAT invoices, cancellation save-offer + least-privilege scope map | E10: ST-060..064 Done | F10: 15/15 | G10: billing, compliance suites | H10: 100% | I10: S7 beta-partner activities themselves are external
A11: 8 | B11: 2026-09-10 22:22 | C11: S8 | D11: F5 analytics + quality-score guard, health score, heatmap, CSV export, alert thresholds; E6 retention/encryption-verify/audit/export-delete/backoff+breaker; p95 budgets; chaos degradation | E11: ST-041..044, 046..050, 065, 067, 069, 070, 073..077, 087, 091 Done; ST-045/066 code-complete | F11: 69/87 | G11: analyticsGuard, compliance, resilience, latency suites | H11: 100% | I11: ST-088 load test + ST-092 deploy drill need live infra
A12: 9 | B12: 2026-09-10 22:22 | C12: S9-S12 | D12: Scoped: external items held in Backlog — pen-test (ST-068), help center/support/demo assets (ST-080/081/083/084), WCAG + backup drill (ST-089/090), listing/launch/GTM (ST-093..100) | E12: 17 stories remain Backlog | F12: 0/61 | G12: — | H12: — | I12: Unblock: live Meta dev account + asset production session
A13: 10 | B13: 2026-09-10 22:22 | C13: Release | D13: v006 released: codebase engageos v0.6.0 (BUILD_OK), 16 suites / 73 tests green, 100% stmts/branch/funcs/lines enforced; workbook gains this sheet + Traceability_Matrix | E13: 75 Done / 8 code-complete / 17 Backlog | F13: 295/399 | G13: 16 suites / 73 tests | H13: 100% | I13: Next: v007 live-platform verification
A14: 11 | B14: 2026-09-10 22:55 | C14: S9-S10 | D14: WhatsApp compliance code: 24h session window + template fallback, webhook dedupe/burst queue, opt-in proof registry, demo-data mode seeding all surfaces | E14: ST-083 code part; Launch_Checklist #5/#7/#8 done-in-code, #4 templates drafted | F14: — | G14: 20 suites / 78 tests | H14: 100% | I14: Live burst test + Meta template approval pending
A15: 12 | B15: 2026-09-10 22:55 | C15: S9-S10 | D15: Drafting sprint: listing copy A/B, pricing+FAQ, trust page, demo script, runbook, incident comms, 15 help articles, k6 load harness, backup drill, blue/green workflow, hi/ta i18n packs | E15: ST-080/083/084/088/090/092/093/095/096/098 -> Drafted; ST-097 -> In progress (self dry-run vs checklist) | F15: — | G15: — | H15: — | I15: ST-093 A/B needs Senthil review; ST-097 needs second reviewer
... A91: 88 | B91: 2026-09-13 22:49 | C91: Release | D91: v044 released: codebase v0.43.0; audit kit v1.0.0 with its own suite | E91: 79 Done / 13 code-complete / 6 drafted / 2 in progress / 0 Backlog | F91: 309/399 | G91: 51 suites / 365 tests | H91: 100% | I91: Awaiting Senthil: handover sheet items 1-12

Sheet Traceability_Matrix
A1: TRACEABILITY MATRIX — story -> module -> automated test -> status (v006, 2026-09-10 22:22)
A3: ID | B3: Epic | C3: Story (short) | D3: Source module(s) | E3: Test suite(s) | F3: Status | G3: Evidence / Note
A4: ST-001 | B4: F1 | C4: As a SME owner, I can set up Team inbox + assignment with sensible defaults in one screen | D4: inbox.ts | E4: inbox.test.ts | F4: Done | G4: Team inbox + assignment: one-screen setup with validated defaults
A5: ST-002 | B5: F1 | C5: As a SME owner, the Team inbox + assignment happy path completes without documentation | D5: inbox.ts | E5: inbox.test.ts | F5: Done | G5: Happy path covered end-to-end on fake platform surface
A6: ST-003 | B6: F1 | C6: As a Marketing person, I can customise Team inbox + assignment rules/conditions for my ... | D6: inbox.ts | E6: inbox.test.ts | F6: Done | G6: Rules/conditions customisation with validation errors
A7: ST-004 | B7: F1 | C7: As a user, Team inbox + assignment shows clear errors and retry paths on platform API f... | D7: inbox.ts + resilience.ts | E7: inbox.test.ts + resilience.test.ts | F7: Done | G7: Retry w/ backoff; clear error after exhausting attempts
A8: ST-005 | B8: F1 | C8: As a Support agent, Team inbox + assignment works on the web app + WhatsApp Cloud API s... | D8: inbox.ts | E8: inbox.test.ts | F8: Code-complete (pending live WhatsApp) | G8: Logic Done vs FakeWaApi; live Cloud API E2E outstanding
A9: ST-006 | B9: F1 | C9: As a Marketing person, I can see Team inbox + assignment performance metrics and trends | D9: inbox.ts | E9: inbox.test.ts | F9: Done | G9: Metrics/trends computed and asserted
A10: ST-007 | B10: F1 | C10: As a user, Team inbox + assignment respects role permissions and audit logging | D10: inbox.ts + roles.ts | E10: roles.test.ts | F10: Done | G10: owner/admin/member matrix + AuditLog entries
A11: ST-008 | B11: F1 | C11: As a SME owner, I can pause/disable Team inbox + assignment without data loss | D11: inbox.ts | E11: inbox.test.ts | F11: Done | G11: Pause blocks activity; data retained (asserted)
A12: ST-009 | B12: F1 | C12: As a Marketing person, I can import/migrate existing data into Team inbox + assignment ... | D12: inbox.ts | E12: inbox.test.ts | F12: Done | G12: DONE-IN-CODE v033 17:24 — chat CSV import reachable at POST /api/inbox/import; it was library-only until now (help article 5)
A13: ST-010 | B13: F1 | C13: As a user, I get notifications (in-app + email) for key Team inbox + assignment events ... | D13: inbox.ts + notify.ts | E13: notify.test.ts | F13: Done | G13: In-app + email with per-type mute
A14: ST-011 | B14: F2 | C14: As a SME owner, I can set up Broadcast campaigns + segments with sensible defaults in o... | D14: broadcast.ts | E14: broadcast.test.ts | F14: Done | G14: Broadcast campaigns + segments: one-screen setup with validated defaults
... A103: ST-100 | B103: EL | C103: First 10 design-partner reviews scheduled | D103: partners.ts | E103: completion.test.ts | F103: Code-complete (pending live WhatsApp) | G103: CODE-COMPLETE v039 19:40 — partner tracker reachable at /admin/partners with the honest gate maths; outreach remains his
A105: Summary | C105: =COUNTIF(F4:F103,"Done")&" Done / "&COUNTIF(F4:F103,"Code-complete (pending live WhatsApp)")&" code-complete / "&COUNTIF(F4:F103,"Drafted")&" drafted / "&COUNTIF(F4:F103,"In progress")&" in progress / "&COUNTIF(F4:F103,"Backlog")&" Backlog" -> 79 Done / 13 code-complete / 6 drafted / 2 in progress / 0 Backlog
