Workbook

Sheet Version_Control
A1: VERSION CONTROL — TestPulse
A3: Version | B3: Date | C3: Author | D3: Change | E3: Status
A4: v001-v004 | B4: 2026-09-05 | C4: Claude for Senthil/KP | D4: Lineage: marketplace master (868 entries) -> portfolio plan (12 products) -> wave-1 (RetainKit/ShiftDesk/EngageOS, v005) -> this product selected for wave-3 | E4: Released
A5: v008 | B5: 2026-09-10 22:58 | C5: Claude for Senthil/KP | D5: RELEASED (supersedes the planned S0 re-baseline — D13 parked interviews): S1-S8 code scope executed done-in-code per Senthil 22:58 continue-sprint instruction. TypeScript core (config, store, lifecycle, permissions+audit, F1 case-gen, F2 run boards, F3 flaky detector, F4 readiness score, F5 Xray importer, E5 billing, E6 compliance, E7 analytics, webhooks, jiraClient backoff/breaker). D13 gate: 16 Jest suites / 105 tests / 100% branches-functions-lines-statements; CI coverage gate + E2E smoke every deploy. Full_Backlog statuses updated: 71 Done, 7 Code-complete pending live, 22 Backlog. Companion tracker: claude_v001_testpulse_sprint_tracker_traceability_20260910_2258.xlsx. | E5: Released
A6: v009 | B6: 2026-09-10 23:13 | C6: Claude for Senthil/KP | D6: S9-S12 executable scope executed: E8 onboarding/help/support, EQ load test EXECUTED (5,238 rps, 0 errors) + backup drill + chaos degrade + status page, EL launch collateral (copy A/B, pricing, trust, runbook, dry-run, specs), AnthropicProvider wired behind AI seam. 21 suites / 129 tests / 100% x4. 80 Done / 15 code-complete / 5 backlog. Remaining backlog = external-party items only (pen-test, live-UI assets/AA, post-launch SEO, partner reviews). | E6: Released
A7: v010 | B7: 2026-09-11 08:31 | C7: Claude for Senthil/KP | D7: LC-1 turnkey: ForgeStore hosted-storage adapter (tested), paste-ready forge manifest, 30-min deploy guide. Owed docs closed: review pack (LC #2), Cloud Fortified formal gap assessment (LC #3, no structural gaps), residency statement (LC #4), S0 PRD rollup. 22 suites / 132 tests / 100% x4. Backlog counts unchanged (80 Done / 15 code-complete / 5 backlog) — every remaining flip needs a Senthil-side live action. | E7: Released
A8: v011 | B8: 2026-09-11 12:51 | C8: Claude for Senthil/KP | D8: Forge glue shipped (resolver+webtrigger handlers over hosted-storage adapter; deploy-guide step 5 = zero-code) and Xray/Zephyr importer hardened to real export shapes (RFC-4180, multi-step aggregation, Zephyr Scale, ragged rows). Mid-pass coverage regression caught and closed. 23 suites / 146 tests / 100% x4. Counts unchanged: 80 Done / 15 code-complete / 5 backlog — remaining flips all Senthil-side (LC #1 install, #8 billing, #5 real files, #7 assets, pen-test, D15/D17). | E8: Released
A9: v012 | B9: 2026-09-11 13:32 | C9: Claude for Senthil/KP | D9: Custom UI layer shipped and headless-verified: tested view-models/renderers/mount (15 tests incl. jsdom), esbuild bundle at static/build/app.js, Forge index.html bridge hook, demo.html rendering all four panels with demo data. The manifest's static resource now exists — LC-1 blocks on Senthil ► steps only. Draft screenshots capturable from demo.html today. 25 suites / 161 tests / 100% x4. Counts unchanged 80/15/5. | E9: Released
A10: v013 | B10: 2026-09-11 15:27 | C10: Claude for Senthil/KP | D10: External verification sweep vs live Atlassian docs: R-P5 closed (own webtrigger auth is the documented pattern — HMAC design correct); runtime corrected to nodejs22.x (Node 20 EOL); kvsAdapter shipped for the real @forge/kvs query API (no listKeys exists); Marketplace asset spec rewritten to the verified Rule-of-3 (1840x900/580x330, <=50/220-char text, banner 1120x548, <30s video). 25 suites / 163 tests / 100% x4. Counts unchanged 80/15/5. | E10: Released
A11: v014 | B11: 2026-09-11 22:09 | C11: Claude for Senthil/KP | D11: B-17 de-risked: Paid-via-Atlassian verified and wired (manifest licensing flag + license gate: inactive => read-only, reads never blocked; billing.ts payment engine honestly superseded for Marketplace channel). NEW DECISION D18: per-user pricing re-anchor needed (Atlassian has no flat plans). Economics: 100% revenue to partner up to $1M lifetime Forge revenue. Design-partner kit shipped for ST-100. 26 suites / 167 tests / 100% x4. Counts unchanged 80/15/5. | E11: Released
A12: v015 | B12: 2026-09-11 22:28 | C12: Claude for Senthil/KP | D12: 22:28 'continue' — COLD REVIEW PASS 1 (TestPulse's first; sibling pattern after TeleField/FlowCast/ShiftDesk/VoiceBridge). All 27 modules read adversarially: 13 defects found and fixed with pinned regressions, 4 observations logged for disposition (see Review_Findings). Headline: delete-my-data/export-my-data covered only cloudId-substring keys, so cases, boards, CI results, audit log, notifications, telemetry and support tickets were never deleted — the published 30-day hard-delete policy was breached, and the retention sweep had the same hole. Also: the flaky panel would have rendered NaN% live (resolver returns flipRate, UI read score) and the readiness panel NaN/NOT-READY (empty payload, no input validation). Five unbounded ledgers would have hard-failed Forge writes over time. All found at 100% coverage — F-V14 confirmed for a sixth product. 27 suites / 203 tests / 100% x4, zero pragmas. Story counts unchanged (80 Done / 15 code-complete / 5 backlog) — corrections to shipped work, not new scope. | E12: Released
A13: v016 | B13: 2026-09-13 09:52 | C13: Claude for Senthil/KP | D13: 09:52 'continue' — COLD REVIEW PASS 2 + VERIFICATION SWEEP: 10 defects fixed with pinned regressions, 3 of them LIVE-BLOCKING and invisible to the test suite because no Jest run loads the file Forge loads. VER-P01: forge/index.ts was five commented-out lines AND the wrong shape — Forge resolvers are resolver.define(key,({payload,context}))+getDefinitions() and invoke() matches the definition key, so a deploy would have registered handlers that do not exist and LC-1 would have failed at the first panel click. VER-P02: the Custom UI page never mounted anything and the bundle contained no @forge/bridge (3.7kb -> 96.7kb once real); the generate tab also demanded story text an issue panel never has. VER-P03: Forge sends isEvaluation, the gate read evaluation. F-TP14 (security): the permission role arrived from the caller — a member could invoke as owner; roles are now derived server-side. F-TP15 (security): one app-wide CI secret for every installation, with HC-05 pointing at a Settings screen that could not exist. F-TP16: AnthropicProvider was never called — AI generation was inert in production and R-P6 had been cleared on an unreachable class. Plus F-TP17 importer discarded parsed steps, F-TP18 demo mode seeded records nothing reads, F-TP19 three help articles described behaviour the product lacks, F-TP20 exit-survey ledger. 28 suites / 233 tests / 100% x4 zero pragmas, plus two new CI gates (typecheck:forge, build:ui). Story counts unchanged 80/15/5. | E13: Released
A14: v017 | B14: 2026-09-13 10:24 | C14: Claude for Senthil/KP | D14: 10:24 'continue' — COLD REVIEW PASS 3 (REACHABILITY): the question passes 1 and 2 cannot ask — once installed, can a user reach what we claim to ship? Mostly no: of 29 modules the resolver reached eight. Self-serve export/delete had NO resolver call (HC-12, trust page, residency statement, Cloud Fortified gap assessment all unreachable); the 30-day retention sweep was scheduled nowhere (no scheduledTrigger in the manifest, so the published hard delete never ran); every customisation and pause story was library-only; notify() was never called in the Forge path so no notification was ever raised in the installed app; trackError had no caller so the error-spike alert could never fire; support intake, audit log and latency budgets had no surface; and the panel bound no events at all — no control in the product did anything. 9 findings fixed: data-rights + settings + support + audit + status resolver calls, daily scheduledTrigger for retention, notifications wired into the real paths, per-invocation latency sampling, and a real Settings screen with working controls (CI secret + rotate, generation rules, flaky threshold, pause toggles, notification matrix, demo data, export/delete). 30 suites / 263 tests / 100% x4 zero pragmas; forge typecheck + UI build green; demo page re-verified headless including the new Settings screen. Story counts unchanged 80/15/5. | E14: Released
... A21: v024 | B21: 2026-09-13 11:22 | C21: Claude for Senthil/KP | D21: 11:22 'continue' — LC-1 SESSION PACK. Both remaining TestPulse blockers are yours, so this sitting removed the prep from under them. scripts/lc1-verify.js exercises the deployed app's webtrigger against the five behaviours the security assessment and HC-14 promise (signed accept, duplicate reject, tampered reject, stale reject, malformed 400) and prints tracker-ready evidence lines; it is tested against the real handler, so a failure means the deployment differs from this codebase. docs/lc1-session-pack.md is the 45-minute run sheet — pre-work, commands, what the lifecycle trigger bootstraps and what to do if it lags, an evidence table mapping each capture to the stories it flips, and the two questions only a live site can answer (manual keyboard/contrast pass, plus whether the customer-visible default board name and the 3-distinct-days habit definition are right). static/build/capture.html renders the panels inside frames sized to the verified Rule-of-3 listing spec so one screenshot pass yields correctly sized assets. Recorded plainly: lc1-verify cannot check the panel, resolver, roles, licensing, the lifecycle trigger firing or the retention sweep — a green run is not full verification. 37 suites / 332 tests / 100% x4; six CI gates green. Story counts unchanged 80/15/5 — they flip at LC-1, with evidence, not before. | E21: Released
A22: v025 | B22: PLANNED: LC-1 executed — evidence attached, story flips, live findings logged; then D18 + partner console + assets. | E22: Planned

Sheet ReadMe_Scope
A1: TestPulse — AI-assisted test management: generate cases from stories, flaky-test analytics, release readiness score
A3: PLATFORM: Atlassian Marketplace | CATEGORY: Testing / QA for Jira
A4: PROBLEM: Xray/Zephyr dominate but are heavy; teams want lightweight AI-native test ops
A5: DIFFERENTIATION: Forge-native (no infra for customer), AI case-gen, price undercut at 10-100 seat band
A6: ICP: Software teams 25-500 devs on Jira Cloud, existing manual QA or overloaded Xray installs
A8: HOW TO USE: Full_Backlog is the single source of truth (edit Status column during execution). Sprint_Board recalculates points per sprint automatically. Financial_Model assumptions (yellow) are editable — the 18-month build recalculates. Launch_Checklist is the platform-specific gate before submission. All costs/timelines are market-standard estimates; verify platform terms (fees/review rules) during S0.
A10: STACK ASSUMPTION (market standard): TypeScript/Node or platform-mandated runtime, React frontends, Postgres, hosted on AWS/GCP/platform FaaS as required, GitHub Actions CI, PostHog + Sentry telemetry, Intercom-class support.

Sheet Product_Spec
A1: PRODUCT SPEC
A3: Module (feature) | B3: Scope in MVP | C3: Out of scope (v1) | D3: Non-functional requirements
A4: AI test-case generation | B4: AI test-case generation: end-to-end happy path + edge cases + permissions | C4: Advanced automation, AI beyond listed, multi-language beyond launch set | D4: p95 <500ms API / <2s UI loads
A5: Test run boards | B5: Test run boards: end-to-end happy path + edge cases + permissions | C5: Advanced automation, AI beyond listed, multi-language beyond launch set | D5: 99.5% monthly uptime
A6: Flaky-test detector | B6: Flaky-test detector: end-to-end happy path + edge cases + permissions | C6: Advanced automation, AI beyond listed, multi-language beyond launch set | D6: WCAG AA
A7: Release readiness score | B7: Release readiness score: end-to-end happy path + edge cases + permissions | C7: Advanced automation, AI beyond listed, multi-language beyond launch set | D7: SOC2-track controls
A8: Xray importer | B8: Xray importer: end-to-end happy path + edge cases + permissions | C8: Advanced automation, AI beyond listed, multi-language beyond launch set | D8: Rate-limit safe (backoff+queue)
A10: Persona | B10: Jobs-to-be-done
A11: QA lead | B11: Owns tool choice; wants migration importer from Xray/Zephyr
A12: Eng manager | B12: Buys on release-risk visibility
A13: Jira admin | B13: Cares about Cloud Fortified badge + data residency

Sheet Screens_Wireframes
A1: SCREEN INVENTORY (attach Figma links in col E during S0)
A3: # | B3: Screen | C3: Purpose | D3: Key elements | E3: Wireframe link
A4: 1 | B4: Onboarding / first-run | C4: Reach aha in <1 day | D4: Checklist, sample data toggle, connect steps
A5: 2 | B5: Home dashboard | C5: Daily habit surface | D5: KPI cards, activity feed, alerts
A6: 3 | B6: AI test-case generation workspace | C6: Core value surface | D6: List+detail, bulk actions, status chips
A7: 4 | B7: Test run boards builder | C7: Configure second pillar | D7: Rule builder, preview, test mode
A8: 5 | B8: Flaky-test detector view | C8: Differentiator surface | D8: Timeline/visual, export
A9: 6 | B9: Settings & team | C9: Roles, notifications, data | D9: Role matrix, API keys, danger zone
A10: 7 | B10: Billing | C10: Plan/trial/invoices | D10: Plan cards, usage meter, invoices
A11: 8 | B11: Analytics | C11: Prove ROI | D11: Funnel, cohort, export
A12: 9 | B12: Help & support | C12: Deflect + assist | D12: Search, chat, status

Sheet Full_Backlog
A1: FULL BACKLOG
A3: ID | B3: Epic | C3: Story | D3: Points | E3: Priority | F3: Sprint | G3: Status
A4: ST-001 | B4: F1 | C4: As a QA lead, I can set up AI test-case generation with sensible defaults in one screen | D4: 5 | E4: P0 | F4: S2 | G4: Done
A5: ST-002 | B5: F1 | C5: As a QA lead, the AI test-case generation happy path completes without documentation | D5: 8 | E5: P0 | F5: S2 | G5: Done
A6: ST-003 | B6: F1 | C6: As a Eng manager, I can customise AI test-case generation rules/conditions for my workflow | D6: 5 | E6: P1 | F6: S2 | G6: Done
A7: ST-004 | B7: F1 | C7: As a user, AI test-case generation shows clear errors and retry paths on platform API failures | D7: 3 | E7: P0 | F7: S2 | G7: Done
A8: ST-005 | B8: F1 | C8: As a Jira admin, AI test-case generation works on the Forge app panel inside Jira surface end-to-end | D8: 5 | E8: P0 | F8: S3 | G8: Code-complete — pending live
A9: ST-006 | B9: F1 | C9: As a Eng manager, I can see AI test-case generation performance metrics and trends | D9: 3 | E9: P1 | F9: S3 | G9: Done
A10: ST-007 | B10: F1 | C10: As a user, AI test-case generation respects role permissions and audit logging | D10: 3 | E10: P1 | F10: S3 | G10: Done
A11: ST-008 | B11: F1 | C11: As a QA lead, I can pause/disable AI test-case generation without data loss | D11: 2 | E11: P2 | F11: S3 | G11: Done
A12: ST-009 | B12: F1 | C12: As a Eng manager, I can import/migrate existing data into AI test-case generation (CSV + competitor importer) | D12: 5 | E12: P1 | F12: S3 | G12: Done
A13: ST-010 | B13: F1 | C13: As a user, I get notifications (in-app + email) for key AI test-case generation events with per-type mute | D13: 3 | E13: P2 | F13: S3 | G13: Done
A14: ST-011 | B14: F2 | C14: As a QA lead, I can set up Test run boards with sensible defaults in one screen | D14: 5 | E14: P0 | F14: S3 | G14: Done
A15: ST-012 | B15: F2 | C15: As a QA lead, the Test run boards happy path completes without documentation | D15: 8 | E15: P0 | F15: S3 | G15: Done
... A103: ST-100 | B103: EL | C103: First 10 design-partner reviews scheduled | D103: 2 | E103: P1 | F103: S11 | G103: Backlog
A105: Total stories: 100. Epics: F1-F5 = product features; E1 install, E5 billing, E6 compliance, E7 telemetry, E8 onboarding/docs/support, EQ quality. Edit Status (Backlog/In progress/Done) during execution.

Sheet Sprint_Board
A1: SPRINT BOARD — live counts from Full_Backlog
A3: Sprint | B3: Focus | C3: Stories | D3: Points | E3: Done | F3: Exit criteria
A4: S0 | B4: Discovery & Design (2 wks) | C4: =COUNTIF(Full_Backlog!F4:F103,"S0") -> 0 | D4: =SUMIF(Full_Backlog!F4:F103,"S0",Full_Backlog!D4:D103) -> 0 | E4: =COUNTIFS(Full_Backlog!$F$3:$F$102,A4,Full_Backlog!$G$3:$G$102,"Done")+COUNTIFS(Full_Backlog!$F$3:$F$102,A4,Full_Backlog!$G$3:$G$102,"Code-complete — pending live") -> 0 | F4: PRD signed off; prototype tested with 5 target users
A5: S1 | B5: Foundation (2 wks) | C5: =COUNTIF(Full_Backlog!F4:F103,"S1") -> 4 | D5: =SUMIF(Full_Backlog!F4:F103,"S1",Full_Backlog!D4:D103) -> 13 | E5: =COUNTIFS(Full_Backlog!$F$3:$F$102,A5,Full_Backlog!$G$3:$G$102,"Done")+COUNTIFS(Full_Backlog!$F$3:$F$102,A5,Full_Backlog!$G$3:$G$102,"Code-complete — pending live") -> 4 | F5: App installs cleanly in dev store/org; telemetry firing
A6: S2 | B6: Core feature AI test-case generation - part 1 | C6: =COUNTIF(Full_Backlog!F4:F103,"S2") -> 6 | D6: =SUMIF(Full_Backlog!F4:F103,"S2",Full_Backlog!D4:D103) -> 29 | E6: =COUNTIFS(Full_Backlog!$F$3:$F$102,A6,Full_Backlog!$G$3:$G$102,"Done")+COUNTIFS(Full_Backlog!$F$3:$F$102,A6,Full_Backlog!$G$3:$G$102,"Code-complete — pending live") -> 6 | F6: AI test-case generation happy path demoable
A7: S3 | B7: Core feature AI test-case generation - part 2 + Test run boards start | C7: =COUNTIF(Full_Backlog!F4:F103,"S3") -> 11 | D7: =SUMIF(Full_Backlog!F4:F103,"S3",Full_Backlog!D4:D103) -> 47 | E7: =COUNTIFS(Full_Backlog!$F$3:$F$102,A7,Full_Backlog!$G$3:$G$102,"Done")+COUNTIFS(Full_Backlog!$F$3:$F$102,A7,Full_Backlog!$G$3:$G$102,"Code-complete — pending live") -> 11 | F7: AI test-case generation complete with tests; Test run boards skeleton
A8: S4 | B8: Core feature Test run boards | C8: =COUNTIF(Full_Backlog!F4:F103,"S4") -> 9 | D8: =SUMIF(Full_Backlog!F4:F103,"S4",Full_Backlog!D4:D103) -> 34 | E8: =COUNTIFS(Full_Backlog!$F$3:$F$102,A8,Full_Backlog!$G$3:$G$102,"Done")+COUNTIFS(Full_Backlog!$F$3:$F$102,A8,Full_Backlog!$G$3:$G$102,"Code-complete — pending live") -> 9 | F8: MVP loop usable end-to-end internally
A9: S5 | B9: Feature Flaky-test detector + alpha hardening | C9: =COUNTIF(Full_Backlog!F4:F103,"S5") -> 12 | D9: =SUMIF(Full_Backlog!F4:F103,"S5",Full_Backlog!D4:D103) -> 50 | E9: =COUNTIFS(Full_Backlog!$F$3:$F$102,A9,Full_Backlog!$G$3:$G$102,"Done")+COUNTIFS(Full_Backlog!$F$3:$F$102,A9,Full_Backlog!$G$3:$G$102,"Code-complete — pending live") -> 12 | F9: Internal alpha: team dogfoods daily
A10: S6 | B10: Billing + Release readiness score | C10: =COUNTIF(Full_Backlog!F4:F103,"S6") -> 13 | D10: =SUMIF(Full_Backlog!F4:F103,"S6",Full_Backlog!D4:D103) -> 60 | E10: =COUNTIFS(Full_Backlog!$F$3:$F$102,A10,Full_Backlog!$G$3:$G$102,"Done")+COUNTIFS(Full_Backlog!$F$3:$F$102,A10,Full_Backlog!$G$3:$G$102,"Code-complete — pending live") -> 13 | F10: Can charge a test customer; upgrade/downgrade paths work
A11: S7 | B11: Private beta (design partners) | C11: =COUNTIF(Full_Backlog!F4:F103,"S7") -> 5 | D11: =SUMIF(Full_Backlog!F4:F103,"S7",Full_Backlog!D4:D103) -> 15 | E11: =COUNTIFS(Full_Backlog!$F$3:$F$102,A11,Full_Backlog!$G$3:$G$102,"Done")+COUNTIFS(Full_Backlog!$F$3:$F$102,A11,Full_Backlog!$G$3:$G$102,"Code-complete — pending live") -> 5 | F11: 3+ partners active weekly; NPS pulse >30
A12: S8 | B12: Beta iteration + Xray importer | C12: =COUNTIF(Full_Backlog!F4:F103,"S8") -> 22 | D12: =SUMIF(Full_Backlog!F4:F103,"S8",Full_Backlog!D4:D103) -> 87 | E12: =COUNTIFS(Full_Backlog!$F$3:$F$102,A12,Full_Backlog!$G$3:$G$102,"Done")+COUNTIFS(Full_Backlog!$F$3:$F$102,A12,Full_Backlog!$G$3:$G$102,"Code-complete — pending live") -> 22 | F12: Retention of beta cohort week-over-week >60%
A13: S9 | B13: Marketplace review prep | C13: =COUNTIF(Full_Backlog!F4:F103,"S9") -> 7 | D13: =SUMIF(Full_Backlog!F4:F103,"S9",Full_Backlog!D4:D103) -> 30 | E13: =COUNTIFS(Full_Backlog!$F$3:$F$102,A13,Full_Backlog!$G$3:$G$102,"Done")+COUNTIFS(Full_Backlog!$F$3:$F$102,A13,Full_Backlog!$G$3:$G$102,"Code-complete — pending live") -> 4 | F13: Review submission accepted into queue
A14: S10 | B14: Review remediation + docs | C14: =COUNTIF(Full_Backlog!F4:F103,"S10") -> 7 | D14: =SUMIF(Full_Backlog!F4:F103,"S10",Full_Backlog!D4:D103) -> 24 | E14: =COUNTIFS(Full_Backlog!$F$3:$F$102,A14,Full_Backlog!$G$3:$G$102,"Done")+COUNTIFS(Full_Backlog!$F$3:$F$102,A14,Full_Backlog!$G$3:$G$102,"Code-complete — pending live") -> 7 | F14: Marketplace approval obtained (or final remediation cycle)
A15: S11 | B15: Launch | C15: =COUNTIF(Full_Backlog!F4:F103,"S11") -> 3 | D15: =SUMIF(Full_Backlog!F4:F103,"S11",Full_Backlog!D4:D103) -> 8 | E15: =COUNTIFS(Full_Backlog!$F$3:$F$102,A15,Full_Backlog!$G$3:$G$102,"Done")+COUNTIFS(Full_Backlog!$F$3:$F$102,A15,Full_Backlog!$G$3:$G$102,"Code-complete — pending live") -> 2 | F15: First 10 installs; first 3 reviews; activation >40%
A16: S12 | B16: Iterate & scale decision | C16: =COUNTIF(Full_Backlog!F4:F103,"S12") -> 1 | D16: =SUMIF(Full_Backlog!F4:F103,"S12",Full_Backlog!D4:D103) -> 2 | E16: =COUNTIFS(Full_Backlog!$F$3:$F$102,A16,Full_Backlog!$G$3:$G$102,"Done")+COUNTIFS(Full_Backlog!$F$3:$F$102,A16,Full_Backlog!$G$3:$G$102,"Code-complete — pending live") -> 0 | F16: Growth model doc with CAC/LTV first estimates
B17: TOTAL | C17: =SUM(C4:C16) -> 100 | D17: =SUM(D4:D16) -> 399
B18: Velocity check: points/sprint S2-S8 should sit within 30-45 for a 4-6 person team; rebalance Sprint column in backlog if a sprint exceeds capacity.

Sheet Financial_Model
A1: 18-MONTH FINANCIAL MODEL — Atlassian: Forge PLG (edit yellow assumptions)
A3: Assumption | B3: Value
A4: Trials/mo (month 1) | B4: 40
A5: Monthly growth of that | B5: 0.12
A6: Trial->paid % | B6: 0.14
A7: ARPU $/mo | B7: 79
A8: Monthly churn | B8: 0.03
A9: Marketplace fee | B9: 0.17
A10: Team cost month 1 (India-lean $) | B10: 20000
A11: Cost growth/mo | B11: 0.03
A12: Fee note: ~17% Forge-era marketplace share (verify current program rate)
A14: Line | B14: M1 | C14: M2 | D14: M3 | E14: M4 | F14: M5 | G14: M6 | H14: M7 | I14: M8 | J14: M9 | K14: M10 | L14: M11 | M14: M12 | N14: M13 | O14: M14 | P14: M15 | Q14: M16 | R14: M17 | S14: M18
A15: Leads/installs | B15: =$B$4 -> 40 | C15: =B15*(1+$B$5) -> 44.8 | D15: =C15*(1+$B$5) -> 50.176 | E15: =D15*(1+$B$5) -> 56.19712 | F15: =E15*(1+$B$5) -> 62.940774 | G15: =F15*(1+$B$5) -> 70.493667 | H15: =G15*(1+$B$5) -> 78.952907 | I15: =H15*(1+$B$5) -> 88.427256 | J15: =I15*(1+$B$5) -> 99.038527 | ... S15: =R15*(1+$B$5) -> 274.64164
A16: New paying | B16: =ROUND(B15*$B$6,1) -> 5.6 | C16: =ROUND(C15*$B$6,1) -> 6.3 | D16: =ROUND(D15*$B$6,1) -> 7 | E16: =ROUND(E15*$B$6,1) -> 7.9 | F16: =ROUND(F15*$B$6,1) -> 8.8 | G16: =ROUND(G15*$B$6,1) -> 9.9 | H16: =ROUND(H15*$B$6,1) -> 11.1 | I16: =ROUND(I15*$B$6,1) -> 12.4 | ... S16: =ROUND(S15*$B$6,1) -> 38.4
A17: Paying accounts | B17: =B16 -> 5.6 | C17: =ROUND(B17*(1-$B$8)+C16,1) -> 11.7 | D17: =ROUND(C17*(1-$B$8)+D16,1) -> 18.3 | E17: =ROUND(D17*(1-$B$8)+E16,1) -> 25.7 | F17: =ROUND(E17*(1-$B$8)+F16,1) -> 33.7 | G17: =ROUND(F17*(1-$B$8)+G16,1) -> 42.6 | H17: =ROUND(G17*(1-$B$8)+H16,1) -> 52.4 | I17: =ROUND(H17*(1-$B$8)+I16,1) -> 63.2 | J17: =ROUND(I17*(1-$B$8)+J16,1) -> 75.2 | ... S17: =ROUND(R17*(1-$B$8)+S16,1) -> 265.5
A18: MRR (net of fee) | B18: =ROUND(B17*$B$7*(1-$B$9),0) -> 367 | C18: =ROUND(C17*$B$7*(1-$B$9),0) -> 767 | D18: =ROUND(D17*$B$7*(1-$B$9),0) -> 1200 | E18: =ROUND(E17*$B$7*(1-$B$9),0) -> 1685 | F18: =ROUND(F17*$B$7*(1-$B$9),0) -> 2210 | G18: =ROUND(G17*$B$7*(1-$B$9),0) -> 2793 | H18: =ROUND(H17*$B$7*(1-$B$9),0) -> 3436 | I18: =ROUND(I17*$B$7*(1-$B$9),0) -> 4144 | ... S18: =ROUND(S17*$B$7*(1-$B$9),0) -> 17409
A19: Team cost | B19: =$B$10 -> 20000 | C19: =ROUND(B19*(1+$B$11),0) -> 20600 | D19: =ROUND(C19*(1+$B$11),0) -> 21218 | E19: =ROUND(D19*(1+$B$11),0) -> 21855 | F19: =ROUND(E19*(1+$B$11),0) -> 22511 | G19: =ROUND(F19*(1+$B$11),0) -> 23186 | H19: =ROUND(G19*(1+$B$11),0) -> 23882 | I19: =ROUND(H19*(1+$B$11),0) -> 24598 | J19: =ROUND(I19*(1+$B$11),0) -> 25336 | ... S19: =ROUND(R19*(1+$B$11),0) -> 33058
A20: Net cash/mo | B20: =B18-B19 -> -19633 | C20: =C18-C19 -> -19833 | D20: =D18-D19 -> -20018 | E20: =E18-E19 -> -20170 | F20: =F18-F19 -> -20301 | G20: =G18-G19 -> -20393 | H20: =H18-H19 -> -20446 | I20: =I18-I19 -> -20454 | ... S20: =S18-S19 -> -15649
A21: Cumulative | B21: =B20 -> -19633 | C21: =B21+C20 -> -39466 | D21: =C21+D20 -> -59484 | E21: =D21+E20 -> -79654 | F21: =E21+F20 -> -99955 | G21: =F21+G20 -> -120348 | H21: =G21+H20 -> -140794 | I21: =H21+I20 -> -161248 | J21: =I21+J20 -> -181653 | ... S21: =R21+S20 -> -348870
A23: Reading: churn applies before adds; MRR nets the marketplace fee; costs use India-lean base from Team_Roles_Budget (v004). Breakeven = first month Net cash ≥ 0. This is a planning model, not a forecast — replace assumptions with S7-S8 beta actuals.

Sheet GTM_Execution
A1: GTM EXECUTION TASKS
A3: Phase | B3: Task | C3: Owner (role) | D3: Target sprint
A4: Pre-launch | B4: Positioning doc + message house (problem/promise/proof) | C4: Founder | D4: S7
A5: Pre-launch | B5: Listing SEO: keyword study in marketplace search + title/intro drafts | C5: Growth | D5: S8
A6: Pre-launch | B6: 10 design-partner mini case snippets with metric proof | C6: Founder | D6: S8
A7: Pre-launch | B7: 5 comparison/alternative pages drafted | C7: Growth | D7: S9
A8: Pre-launch | B8: Screenshots (5) + 2-min demo video produced | C8: Design | D8: S9
A9: Launch | B9: Listing live + launch post + video published | C9: Growth | D9: S11
A10: Launch | B10: Founder outreach: 100 named ICP accounts, 3-touch sequence | C10: Founder | D10: S11
A11: Launch | B11: Community value-posts (3 relevant communities) | C11: Founder | D11: S11
A12: Launch | B12: Review-generation program on (in-app ask post-aha) | C12: Eng | D12: S11
A13: Post-launch | B13: Weekly SEO/how-to content cadence starts | C13: Growth | D13: S12
A14: Post-launch | B14: Marketplace paid placement pilot (where offered) | C14: Growth | D14: S12
... A16: Post-launch | B16: G2/Capterra profiles + first 10 reviews | C16: Growth | D16: S12+

Sheet Launch_Checklist
A1: PLATFORM LAUNCH CHECKLIST — Atlassian Marketplace
A3: # | B3: Item | C3: Status
A4: 1 | B4: Marketplace vendor account + Forge app registered | C4: Open — FULL STACK ready: UI bundle + handlers + adapter + manifest + guide; only ► steps remain
A5: 2 | B5: Forge app review pack: scopes, egress allowlist, storage use documented | C5: Doc-complete — review pack ready (docs/review-pack.md)
A6: 3 | B6: Cloud Fortified gap assessment (SLA, incident process, residency) with target date | C6: Doc-complete — formal gap assessment: no structural gaps; apply at listing+60d
A7: 4 | B7: Data residency: Forge hosted storage regions statement | C7: Doc-complete — residency statement ready for trust tab
A8: 5 | B8: Xray/Zephyr importer tested on 3 real export files | C8: Open — importer format-faithful (Xray Exporter multi-step, Zephyr Scale, RFC-4180); 3 REAL files = acceptance evidence
A9: 6 | B9: Jira permission schemes respected (project vs global) verified | C9: Done-in-code — scope-aware permission guard + audit on all routes; live verification at LC #1
A10: 7 | B10: Marketplace listing: highlights, 5 screenshots, demo video per guidelines | C10: In progress — spec now submission-accurate (verified Rule-of-3, 1840x900); draft layout review via demo.html; capture at LC-1
A11: 8 | B11: Pricing: per-user tiers via Atlassian billing configured and test-purchased | C11: In progress — licensing flag + gate shipped+tested; D18 per-user price decision, partner-console setup + test purchase = Senthil
A12: 9 | B12: Performance: panel load <1s p75 on 10k-issue projects | C12: In progress — local load test executed (p95 28ms); live p75 at LC-1
A13: 10 | B13: Support docs + SLA statement on listing trust tab | C13: In progress — trust page + SLA + 15 articles shipped

Sheet Metrics_Targets
A1: METRIC TARGETS (first 12 months post-launch)
A3: Metric | B3: M1 | C3: M3 | D3: M6 | E3: M12 | F3: Notes
A4: Installs/signups cumulative | B4: varies | C4: 3x M1 | D4: 8x M1 | E4: 20x M1 | F4: Drive via listing SEO + outbound
A5: Activation % (24h) | B5: 30% | C5: 40% | D5: 45% | E5: 50% | F5: Onboarding iterations S12+
A6: Trial→paid % | B6: baseline | C6: +2pts | D6: +4pts | E6: +6pts | F6: Pricing test at S12
A7: Rating | B7: 4.5+ | C7: 4.6+ | D7: 4.7+ | E7: 4.7+ | F7: Review program + support speed
A8: MRR | B8: first $ | C8: 3x | D8: 8x | E8: 20x | F8: Model sheet has the math
A9: Logo churn/mo | B9: <5% | C9: <4% | D9: <3% | E9: <3% | F9: Health-score saves

Sheet Risk_Register
A1: PRODUCT RISK REGISTER
A3: Risk | B3: Impact | C3: Likelihood | D3: Mitigation
A4: Atlassian Forge program rate/policy changes mid-build | B4: Medium | C4: Medium | D4: Track dev changelog; rate abstraction in pricing model
A5: Xray/Zephyr respond with AI features | B5: High | C5: Medium | D5: Speed + Forge-native cost advantage + importer-led switching
A6: Cloud Fortified bar raises before listing | B6: Medium | C6: Medium | D6: Start gap assessment S1, not S9
A7: Hosted-storage value limits hit by growing ledgers (F-TP06 capped; OBS-TP1 hydrate-all remains) | B7: High | C7: Medium | D7: FIFO caps shipped; prefix-scoped hydration is the open architectural call before the first large tenant
A8: Data-deletion claims outrun implementation (found as F-TP01/F-TP02) | B8: High | C8: Low (post-fix) | D8: Namespace registry + drift test: an unregistered namespace now fails the build, not the security review
A9: Deploy-time failure invisible to the suite (VER-P01/VER-P02 class) | B9: High | C9: Low (post-fix) | D9: Entrypoint type-check + UI build are now CI gates; same gate to be ported across the portfolio (L-P1)
A10: Shipped-but-unreachable scope (F-TP21..28 class) — modules pass their tests while no user can trigger them | B10: High | C10: Low (post-fix) | D10: Reachability audit run for TestPulse; standing check proposed portfolio-wide (L-P4)
A11: Published claims drifting from the product (F-TP33 class) — customer- and reviewer-facing documents outrun the code | B11: Medium | C11: Low (post-fix) | D11: Mechanical claims pinned by tests; untestable claims need a named owner and date (L-P5)
A12: Read-shaped interaction wired to a write-shaped call (F-TP39 class) — correct code, correct docs, wrong sequence | B12: High | C12: Low (post-fix) | D12: No gate catches it; one user-path walkthrough per product before launch (L-P6)

Sheet Review_Findings
A1: COLD REVIEW PASS 1 — findings (11/09/2026 22:28). Senthil: column F is your disposition column.
A2: Found at 26 suites / 167 tests / 100% coverage. Coverage proves execution, not correctness (portfolio lesson F-V14). Every FIXED row has a regression in test/review.pass1.test.ts that fails against the pre-review code.
A4: ID | B4: Severity | C4: Module | D4: Defect / observation | E4: Disposition in code | F4: Senthil decision
A5: F-TP01 | B5: High | C5: compliance.ts | D5: delete-my-data / export-my-data matched key.includes(cloudId): test cases, run boards, CI results, audit log, notifications, telemetry, support tickets and latency samples were neither exported nor deleted — breaches trust page, HC-11/HC-12 and residency statement. Empty cloudId matched every key. | E5: FIXED — tenantData.ts namespace registry drives export + delete + retention sweep; exact-segment tenant match; empty cloudId rejected; drift test asserts no unclassified key after a full tenant flow | F5: Confirm the registry is the contract: any future module must register its namespace or the build fails
A6: F-TP02 | B6: High | C6: lifecycle.ts | D6: 30-day retention sweep purged only acct: — all other tenant data survived indefinitely against a published "then hard delete" policy | E6: FIXED — sweep delegates to purgeTenant; regression asserts an empty store after expiry | F6: None — but this is the claim a Marketplace security reviewer is most likely to test
A7: F-TP03 | B7: High | C7: ui/viewmodel.ts, ui/mount.ts | D7: Panel read `score` from flaky rows; resolver returns `flipRate`. The live flaky tab would have shown "NaN%" on every row. jsdom tests passed because they hand-built the view-model input. | E7: FIXED — flakyVM typed against the real FlakyScore; demo.html re-verified headless (67%/21%, no NaN) | F7: None — but it is why draft screenshots must come from demo.html, not from hand-built fixtures
A8: F-TP04 | B8: High | C8: ui/mount.ts, readiness.ts | D8: Readiness tab invoked `readiness` with an empty payload -> NaN score rendered as NOT-READY. readinessScore validated only coveragePct, so runPassRate=5 scored above 100. | E8: FIXED — new readinessSummary resolver call derives inputs from boards + flaky scores; all four inputs range-validated | F8: Decide who supplies coveragePct and openP0Defects live: owner-entered ready:settings today, or read from a CI coverage feed later
A9: F-TP05 | B9: High | C9: forgeStore.ts, forgeGlue.ts | D9: Writes issued eagerly, awaited only at flush(). A throwing handler never reached flush — floating promises, unhandled rejection able to tear down the invocation, writes that may not settle; a rejected write left the cache claiming success. | E9: FIXED — write failures captured, StoreWriteError raised at flush, glue flushes on success and error paths | F9: None
A10: F-TP06 | B10: High | C10: webhooks, permissions, flaky, notifications, ops | D10: Five unbounded ledgers (wh:seen, audit, fl:results, ntf:log, lat:*). Forge caps single-value size, so these eventually hard-fail every write; p95 was computed over all history. | E10: FIXED — shared appendCapped FIFO with persisted drop counters; latency on a 1000-sample rolling window | F10: Ratify the caps (10k events, 1k latency samples) — they are the retention policy in practice
A11: F-TP07 | B11: Med-High | C11: flaky.ts | D11: setThreshold wrote an instance field; every Forge invocation builds a new detector, so the ST-023 custom threshold was silently discarded in production. Tests reused one instance and passed. | E11: FIXED — threshold persisted to fl:threshold; regression constructs a second detector as the resolver does | F11: None
A12: F-TP08 | B12: Med-High | C12: jiraClient.ts | D12: retryAfter slept as milliseconds; HTTP Retry-After is SECONDS. Jira asking for 60s got 60ms — a retry storm straight back into the rate limiter. | E12: FIXED — renamed retryAfterSeconds, converted, both backoff paths capped at 60s | F12: None
A13: F-TP09 | B13: Med-High | C13: ops.ts | D13: restore() wiped every key before validating the snapshot: a parseable-but-wrong snapshot (null, [], 3) destroyed all data then threw. The restore drill was itself a data-loss path. | E13: FIXED — snapshot shape validated before the wipe | F13: None
A14: F-TP10 | B14: Med | C14: runboards.ts | D14: Board ids derived from key count: creating a board after deleting one silently overwrote an existing board; concurrent invocations collided. | E14: FIXED — monotonic persisted rb:seq | F14: None
A15: F-TP11 | B15: Med | C15: runboards.ts, testgen.ts | D15: Naive split(","): every row of a CRLF export (Excel/Jira on Windows) failed, quoted commas mis-parsed, a bad row midway left earlier rows persisted, import ids restarted at I1 and collided. | E15: FIXED — both importers use the shared RFC-4180 parser, validate whole file then apply; import sequence persisted | F15: Feeds LC-5: the 3 real Xray/Zephyr exports will now exercise the same parser the importer uses
... A21: OBS-TP4 | B21: Med | C21: billing.ts | D21: No payment-recovery path (a tenant who fixes their card stays read-only forever) and trial expiry never enforced (perpetual free access). Both are live defects in the sibling products. | E21: NOT FIXED — inert for this channel: Atlassian owns purchase/trial/proration/dunning under Paid-via-Atlassian and the app only reads license state | F21: DECISION: take the fix if and when a direct sales channel is switched on, not before
A23: COLD REVIEW PASS 2 + VERIFICATION SWEEP (13/09/2026 09:52) — artifacts checked against live Atlassian docs, not just code against itself.
A24: ID | B24: Severity | C24: Module / artifact | D24: Defect / lesson | E24: Disposition in code | F24: Senthil decision
A25: VER-P01 | B25: Live-blocking | C25: forge/index.ts | D25: The Forge entrypoint was five commented-out lines: `forge deploy` would have registered handlers index.resolver / index.ciWebhook that do not exist, so every panel invocation and CI webhook failed in the installed app. The shape was also wrong — Forge resolvers are resolver.define(key,({payload,context})) + getDefinitions(), and invoke(functionKey,payload) matches the DEFINITION KEY, never our single resolver({call,...}) function. | E25: FIXED — src/forgeAdapter.ts builds one definition per call; forge/index.ts is real code compiling against the real @forge/resolver, @forge/kvs, @forge/api; new CI gate npm run typecheck:forge | F25: None — but note LC-1 would have failed at the first panel click before this pass
A26: VER-P02 | B26: Live-blocking | C26: static/build/index.html, static/entry.ts | D26: The Custom UI page loaded the bundle and then called nothing (empty #root, bridge wiring commented out), and the bundle contained no @forge/bridge at all (3.7kb before vs 96.7kb after). The generate tab also demanded storyText, which an issue panel never has — it knows only the issue key. | E26: FIXED — real boot()/bootForge() with an error surface; bridge bundled; story text fetched server-side via env.fetchStory (read:jira-work already held); demo page split into its own bridge-free bundle because @forge/bridge refuses to initialise outside an Atlassian product | F26: None — demo.html screenshots still work, now from demo.js
A27: VER-P03 | B27: High | C27: licensing.ts | D27: Forge resolver context carries LicenseDetails { active, isEvaluation }; the gate expected { active, evaluation }, so a trialling customer would never have seen the evaluation banner. | E27: FIXED — mapLicense() in the adapter, pinned to the documented shape | F27: None
A28: F-TP14 | B28: High (security) | C28: forgeGlue.ts | D28: The permission role arrived in the request context — i.e. from the caller. Forge context is trustworthy but has no app role, so any adapter had to invent one: a member could invoke as owner and delete tenant data. | E28: FIXED — src/roles.ts derives role server-side (assignment > installing account > Jira site admin > member); assignRole is owner-only; regression proves a role:owner payload is ignored | F28: DECISION: role model — today admin = Jira ADMINISTER and installer = owner. A different mapping (project lead, explicit assignment only) is a product call
A29: F-TP15 | B29: High (security) | C29: webhooks.ts | D29: One app-wide signing secret shared by every installation, while HC-05 told customers to copy it "from Settings" — a screen that could not exist because no per-tenant secret did. | E29: FIXED — per-installation secret provisioned at install, owner-only read + rotate (rotation clears the replay ledger); env value kept only as fallback for earlier installs | F29: Panel needs a Settings > CI screen surfacing webhookSecret before listing (UI work, ~half a day)
A30: F-TP16 | B30: High | C30: testgen.ts, aiProvider.ts | D30: AnthropicProvider was shipped behind the AI seam and NEVER CALLED — generate always ran the rule engine, so AI generation was inert in production even with ANTHROPIC_API_KEY set, and R-P6 was reported cleared on an unreachable class. | E30: FIXED — generateWithAi uses the provider, holds its output to the same rules (kind filters + maxCases), persists it, and falls back to rules on failure with a counter | F30: Confirm whether AI generation ships ON at launch (cost per install) or behind an owner toggle
A31: F-TP17 | B31: Med-High | C31: xrayImport.ts | D31: The importer parsed Xray multi-step rows — the reason the module exists — then round-tripped through a 3-column CSV, so every imported case landed with EMPTY steps. | E31: FIXED — TestGen.importCases keeps steps and kinds, atomic and id-unique | F31: Feeds LC-5: the 3 real export files now prove the whole path, not just the parser
A32: F-TP18 | B32: Med-High | C32: onboarding.ts | D32: Demo mode wrote three inert marker records no feature reads, so ST-083/HC-15 "explore with seeded sample data" showed an empty product. | E32: FIXED — seeds real cases, a real board with runs and real flaky history; records exactly what it created and removes exactly that on disable | F32: None
A33: F-TP19 | B33: Med | C33: helpcenter.ts | D33: Three articles promised behaviour the product lacks: a "skip" run status RunStatus never defined, a billing flow superseded by Paid-via-Atlassian (GST/VAT invoices from the retired engine), and the non-existent CI Settings screen. | E33: FIXED — articles corrected; tests pin each claim to the code implementing it | F33: Listing copy + pricing FAQ still carry the flat $99/$299 anchor — blocked on D18
A34: F-TP20 | B34: Low | C34: billing.ts | D34: Exit-survey ledger unbounded — the one pass 1 missed. | E34: FIXED — FIFO-capped like the rest | F34: None
A35: L-P1 | B35: Lesson | C35: portfolio | D35: A 100%-covered codebase can be undeployable: nothing in a Jest suite loads the file the platform loads. Same class as VoiceBridge VER-V01 (opencti_min.js never loaded) — twice now, so it is a pattern. | E35: Entrypoint type-check against the real vendor packages is now a CI gate here | F35: DECISION: port the same gate to the other 10 products
... A37: L-P3 | B37: Lesson | C37: portfolio | D37: Authorization inputs must be named: `role` looked like context and was actually caller input. | E37: For every field used in an authorization decision, record where it comes from and who can set it | F37: None
A39: COLD REVIEW PASS 3 — REACHABILITY (13/09/2026 10:24): what ships but cannot be reached by anyone in the installed app.
A40: ID | B40: Severity | C40: Module / area | D40: Defect / lesson | E40: Disposition in code | F40: Senthil decision
A41: F-TP21 | B41: High | C41: compliance.ts | D41: exportMyData/deleteMyData had NO resolver call — the self-serve export and deletion promised by HC-12, the trust page, the residency statement and the Cloud Fortified gap assessment were unreachable in the installed app. Pass 1 fixed the correctness of a feature nobody could invoke. | E41: FIXED — owner-only exportMyData + deleteMyData (deletion requires typing the site id), both EXEMPT from the license gate so data rights survive an inactive license | F41: None — this is the claim a Marketplace security reviewer tests first
A42: F-TP22 | B42: High | C42: lifecycle.ts, manifest | D42: sweepDeletions() was scheduled NOWHERE: the manifest had no scheduledTrigger, so the published "30 days post-uninstall, then hard delete" never ran in production. | E42: FIXED — daily scheduledTrigger (syntax verified live: key+function+interval, <=5 per app, duplicate delivery possible so the handler is idempotent), makeScheduledSweep adapter, retentionSweep exported from the entrypoint | F42: Confirm daily is the right interval (hour/day/week available)
A43: F-TP23 | B43: High | C43: testgen/flaky/runboards | D43: Every customisation and pause story (ST-003/008/018/023/028) was library-only — a customer could not change a generation rule, a flaky threshold, or pause anything. | E43: FIXED — settings/setSettings resolver calls (members read-only) plus a real Settings screen | F43: None
A44: F-TP24 | B44: High | C44: notifications.ts | D44: Notification preferences (ST-010/020/030/040/050, HC-13) had no surface, and nothing in the Forge path ever called notify() — no notification was raised in the installed app at all. Only the REST smoke harness did. | E44: FIXED — notify wired into generate/recordRun/importXray, preferences editable in Settings, notifications call returns the recent log | F44: Email channel still has no provider — in-app only until one is chosen
A45: F-TP25 | B45: Med-High | C45: telemetry.ts | D45: trackError had no caller, so the error-spike alert (ST-072/ST-077) could never fire. | E45: FIXED — every failed invocation records resolver:<call>, on a separate store write so telemetry cannot mask the original error | F45: Alert delivery (where does a spike go?) is an ops decision
A46: F-TP26 | B46: Med | C46: support.ts | D46: ST-081 in-app support intake and the SLA report were unreachable. | E46: FIXED — supportOpen (exempt from the license gate) + admin-only supportTickets | F46: D-P1 equivalent: in-app chat vendor vs built-in intake is still open
A47: F-TP27 | B47: Med | C47: ops.ts | D47: LatencyMonitor was only called by the load harness, so the p95 budgets (ST-087) had no production data, and statusPage had no surface. | E47: FIXED — every panel-facing call is measured against its budget surface inside the same invocation (a fire-and-forget write races the next read and loses samples); statusReport returns status + per-surface p95 | F47: None
A48: F-TP28 | B48: Med-High | C48: ui/mount.ts | D48: The panel rendered HTML and bound nothing — no control in the product did anything. Four read-only tabs, no way to act. | E48: FIXED — delegated action binding (data-action/data-field), failures shown on screen instead of swallowed, state re-read after each success | F48: Settings screen is now listing-screenshot material (asset capture)
A49: F-TP19b | B49: Med | C49: helpcenter.ts | D49: HC-03 promised admins could "add, reorder or disable generation rules per workflow" — rules are three toggles and a cap, with no ordering. | E49: FIXED — article rewritten to the controls the screen renders, pinned by a test that greps the rendered HTML for each data-field | F49: None
A50: L-P4 | B50: Lesson | C50: portfolio | D50: A module with no caller is not a feature, and a test suite cannot tell the difference: several of these had 100% branch coverage of behaviour no user could trigger. Third distinct "passes its tests, cannot work" class in this product after L-P1 (undeployable entrypoint) and L-P2 (unwired seam). | E50: Standing check proposed: list every exported capability and name the resolver call, trigger or control that reaches it; an empty column is scope to cut or a feature to finish | F50: DECISION: run the same reachability audit across the other 10 products
A52: COLD REVIEW PASS 4 — CLAIMS (13/09/2026 10:37): the 13 published documents vs what the code now does.
A53: ID | B53: Severity | C53: Document / module | D53: Defect / lesson | E53: Disposition in code | F53: Senthil decision
A54: F-TP30 | B54: High | C54: jiraClient.ts, forge/index.ts | D54: ST-070 backoff/jitter/circuit-breaker only wrapped an injected http function that nothing in the Forge path used: the entrypoint's two live Jira calls (story fetch, admin check) went straight out with no retry and no breaker — while the security assessment claimed rate-limit resilience as a verified control. | E54: FIXED — JiraClient.run(label, op) applies the policy to any operation including a route tagged-template call; both entrypoint calls share one client; Retry-After read from the response header (seconds, capped) | F54: None
A55: F-TP31 | B55: Med-High | C55: ops.ts | D55: Cloud Fortified "Backup/recovery: DONE (drill)" rested on BackupOps.drill(), which had no caller and is destructive by design (it restores over live data), so it could never be exposed to a tenant. | E55: FIXED — non-destructive verify() (keys, bytes, content digest) reported via statusReport; the destructive drill is documented as a staging tool | F55: Re-run the destructive drill against live Forge storage at LC-1
A56: F-TP32 | B56: Med-High | C56: compliance.ts, CI | D56: The trust page claimed the encryption posture was "asserted by config check in CI". verifyEncryptionPosture had tests and no runner — the assertion was never made anywhere. | E56: FIXED — scripts/check-posture.js wired as npm run check:posture in CI: fails on TLS disabled, fails at deploy without a bound KMS key | F56: B-18 KMS binding at deploy remains Senthil-side
A57: F-TP33 | B57: Med | C57: trust-page, submission-dry-run, security-assessment, wcag-checklist | D57: Four false published statements: an EMAIL SUBPROCESSOR the app has no integration for and no egress permission to reach; the listing-asset row still citing the old 5-shot spec v006 had already corrected to the Rule-of-3; an authorization description written from the Express harness (x-tp-role header) rather than the product's server-derived roles; and a WCAG checklist deferring the automated pass because "there is no UI". | E57: FIXED — all four corrected, each pinned by a test that greps the document against the code | F57: Trust page + security assessment are customer-facing: worth a read before listing
A58: F-TP29 | B58: Med | C58: ui/render.ts | D58: The flaky table shipped an unnamed column header (axe: empty-table-header) — a screen-reader user got an unlabelled column. Found by the new automated a11y pass on its first run. | E58: FIXED — caption plus named, scoped headers | F58: None
A59: ST-089 | B59: Progress | C59: test/a11y.test.ts | D59: The WCAG automated audit was deferred to LC-1 on the grounds that there was no UI to audit; pass 3 gave the panel real controls. | E59: SHIPPED — axe-core over all five panels + empty states on every build | F59: Manual keyboard/NVDA + contrast in the live iframe remain the only LC-1 a11y items
A60: L-P5 | B60: Lesson | C60: portfolio | D60: A document is an assertion about the code and should be tested like one. Every false claim here was true when written; the product moved and the documents did not. | E60: Mechanical claims (no email subprocessor, asset spec, server-derived roles, a11y pass runs) are pinned by five-line tests that fail the build when doc and code diverge | F60: DECISION: adopt doc-pinning tests across the portfolio; untestable claims (SLA, pen-test) need a named owner and date
A62: PASS 5 — REVIEW GATES (13/09/2026 10:44): the standing checks, and what they found on their first run.
A63: ID | B63: Type | C63: Module / tool | D63: What it is / what it found | E63: Disposition | F63: Senthil decision
A64: GATE-1 | B64: Tooling | C64: tools/review-gates/reachability.js | D64: L-P4 as code: walks the import graph from the REAL entrypoints (never the tests — that blindness is the point) and reports orphan modules and orphan methods. Exceptions require a written reason; stale exceptions are reported so they expire. | E64: SHIPPED + tested (test/gates.test.ts proves it goes red when what it guards breaks); wired as npm run gates in CI | F64: DECISION: port to the other 10 products — config is ~10 lines per repo
A65: GATE-2 | B65: Tooling | C65: tools/review-gates/doc-claims.js | D65: L-P5 as code: a register of published claims, each tied to the evidence in code that must hold (15 registered for TestPulse). Fails the build on the commit that breaks the link rather than in a Marketplace security review. | E65: SHIPPED + tested; covers deletion, retention, scopes, subprocessors, encryption posture, asset spec, a11y, residency | F65: DECISION: adopt portfolio-wide; untestable claims (SLA, pen-test) need a named owner and date instead
A66: F-TP34 | B66: Med-High | C66: telemetry.ts | D66: Found by the gate, missed by manual pass 3: trackFeature/heatmap/exportCsv/funnel had no caller — the ST-073 feature heatmap was never fed and the ST-071 funnel and ST-076 export were never readable; setErrorThreshold was unreachable so ST-077 could not be tuned. | E66: FIXED — every resolver invocation records its feature; admin-only usageReport returns funnel+heatmap+CSV; threshold moved into Settings | F66: None
A67: F-TP35 | B67: Med | C67: support.ts | D67: Support.respond had no caller: a ticket could be opened and NEVER answered, so the SLA report could only ever accumulate breaches — and the Cloud Fortified evidence row cites that report. | E67: FIXED — supportRespond (admin/owner); the SLA report now measures what it claims | F67: None
A68: F-TP36 | B68: Med | C68: runboards.ts, testgen.ts | D68: Both CSV importers were unreachable — run results (ST-019) and test cases (ST-009). Only the Xray path had a door. | E68: FIXED — importRuns and importTestCsv resolver calls | F68: None
A69: F-TP37 | B69: Med | C69: onboarding.ts, ui/mount.ts, forgeGlue.ts | D69: Two writers for one thing, twice: the panel kept its own copy of the ST-079 empty-state map while Onboarding.emptyState went uncalled, and Settings read/wrote ntf:pref:* directly, duplicating the key format Notifications owns. | E69: FIXED — one shared emptyStates.ts consumed by both; Settings goes through Notifications.setPref/prefs(); the dead method deleted rather than allowlisted | F69: None
A70: OBS-TP5 | B70: Open | C70: telemetry.ts | D70: Telemetry.healthScore (ST-075) needs weekly-active-users, which nothing in the product tracks — the metric is unfed. | E70: NOT FIXED — allowlisted with the reason recorded | F70: DECISION: cut ST-075 or fund a usage feed for it
A72: COLD REVIEW PASS 6 — THE CUSTOMER'S PATH (13/09/2026 10:57): walking the primary loop as a user.
A73: ID | B73: Severity | C73: Module | D73: Defect / lesson | E73: Disposition in code | F73: Senthil decision
A74: F-TP39 | B74: HIGH | C74: ui/mount.ts | D74: MOUNTING THE ISSUE PANEL CALLED generate — A WRITE. Every time anyone opened an issue, TestPulse generated and persisted another set of cases: 3 duplicates per view, unbounded, and with an LLM provider configured an Anthropic API call BILLED PER PANEL RENDER. Browsing 10 issues twice = 20 generations and 60 cases for 30 stories. | E74: FIXED — the panel reads (listCases); generating is an explicit button; mounting never writes | F74: None — but it is the reason to walk the loop before LC-1 assets are shot
A75: F-TP38 | B75: Med-High | C75: testgen.ts | D75: There was no read path for cases at all: the panel could create them and never show what existed. | E75: FIXED — TestGen.list(storyKey?) + listCases resolver call, classified as a read so it survives an inactive license | F75: None
A76: F-TP40 | B76: Med-High | C76: runboards.ts, forgeGlue.ts | D76: A run could not be recorded from the issue panel: recordRun demanded a boardId and creating a board needs the configure permission a member lacks. The MVP loop the product is built around was NOT COMPLETABLE BY A MEMBER in the UI. | E76: FIXED — runs record against a default board created on demand; pass/fail/blocked controls on each case; generate -> run -> readiness completes in-panel | F76: Confirm "Current release" as the default board name (customer-visible)
A77: F-TP41 | B77: Med | C77: telemetry.ts | D77: Two of the four activation-funnel stages (setup, habit) were declared and never recorded, so the funnel — the metric the launch targets in Metrics_Targets are written against — could never show more than install -> aha, and activation rate would have read as a permanent failure. | E77: FIXED — setup on the first board, habit once a tenant records runs on 3 distinct days | F77: Confirm 3 distinct days as the habit definition
A78: L-P6 | B78: Lesson | C78: portfolio | D78: Walk the primary loop as the user, once, before launch. Five passes read the code, the manifest, the docs and the export graph; none USED the product. Generate-on-mount is invisible to all four readings — the call, resolver, reachability and documentation are each correct. It is only wrong as a SEQUENCE: a read-shaped interaction wired to a write-shaped call. | E78: Recorded; no tool catches this class — it needs one honest walkthrough per product | F78: DECISION: do the same walkthrough on the other products before their launches
A80: COLD REVIEW PASS 7 — INSTALL + NAVIGATION (13/09/2026 11:03): the steps either side of the core loop.
A81: ID | B81: Severity | C81: Module / artifact | D81: Defect / lesson | E81: Disposition in code | F81: Senthil decision
A82: F-TP42 | B82: HIGH | C82: forge/manifest.yml, forgeAdapter.ts | D82: NOTHING EVER INVOKED THE INSTALL PATH. The manifest had no trigger module, and Forge delivers install/uninstall only via avi:forge:installed:app / avi:forge:uninstalled:app — there is no implicit call. On a real install: no trial, no owner claimed, no CI secret provisioned, no install telemetry; on uninstall: tokens never wiped and the 30-day deletion never scheduled, so the retention sweep shipped in pass 3 had nothing to sweep. The whole E1 lifecycle epic (ST-051..056) was unreachable in a deployed app. | E82: FIXED — trigger module on both lifecycle events, makeLifecycleTrigger in the adapter, lifecycleTrigger exported from the entrypoint; ownership from installerAccountId; idempotent because Forge can deliver twice | F82: None — but this is what would have made LC-1 look like a dead app
A83: F-TP42b | B83: Med | C83: forgeGlue.ts | D83: Atlassian documents install events as asynchronous, sometimes lagging minutes — a panel opened in that window would have hit an uninitialised tenant. | E83: FIXED — lazy bootstrap on any call, which deliberately does NOT claim ownership, so the first user through the door cannot become owner by accident | F83: None
A84: F-TP43 | B84: HIGH | C84: ui/mount.ts, static/entry.ts | D84: THE PANEL HAD NO NAVIGATION: five screens, one hardcoded data-tab in a single index.html serving both the project page and the issue panel. The project page showed "pick a story" forever; run boards, flaky, readiness and settings had no door at all. | E84: FIXED — tab bar (role=tablist, aria-selected), switching re-mounts without writing, the cases tab appears only with a story in context, and the entry picks its default tab from the Forge context (issue panel -> cases, project page -> readiness) | F84: Tab labels are customer-visible: Test cases / Run board / Flaky / Readiness / Settings
A85: F-TP44 | B85: Med-High | C85: forgeGlue.ts, ui/mount.ts | D85: The run-board screen asked for a boardId nothing supplied, so it was permanently empty in the installed app. | E85: FIXED — boardMetrics resolves the default board when no id is given, matching how runs are recorded | F85: None
A86: L-P7 | B86: Lesson | C86: portfolio | D86: REACHABLE IS NOT INVOKED. The install path was reviewed for correctness (pass 1), deployed (pass 2), declared reachable (pass 3 — it was reachable, from a resolver call nothing called), documented (pass 4) and passed the reachability gate (pass 5, because installed is a registered call). Only walking the product from outside exposed that the caller was Atlassian and we had never told Atlassian to call. | E86: For every entrypoint the PLATFORM owns — lifecycle events, scheduled triggers, webhooks, product events — check the manifest declares it, not just that the handler exists | F86: DECISION: add a manifest-declaration check to the gates and run it across the portfolio
A88: PASS 8 — THE GATE L-P7 ASKED FOR (13/09/2026 11:10)
A89: ID | B89: Type | C89: Module / tool | D89: What it is / what it found | E89: Disposition | F89: Senthil decision
A90: GATE-3 | B90: Tooling | C90: tools/review-gates/platform-entrypoints.js | D90: L-P7 as code: reads the manifest and the deploy entrypoint TOGETHER — a handler the entrypoint does not export (VER-P01), an export nothing points at, a function no module references, and the module declarations the product's claims depend on (lifecycle trigger on both events, daily scheduled trigger, v2 webtrigger, panel resource). This is the check the reachability gate structurally cannot make, and the one that would have caught F-TP42 the day the handler was written. | E90: SHIPPED + tested (6 cases incl. the two historical defects); wired into npm run gates; portable README updated with per-platform notes | F90: DECISION: roll all three gates out to the other 10 products
A91: GATE-3b | B91: Self-check | C91: tools/review-gates/platform-entrypoints.js | D91: The gate had the defect it exists to catch: its export scanner counted a COMMENTED-OUT export as exported — exactly the VER-P01 shape. Its own test fixture caught it. | E91: FIXED — comments stripped before scanning; the argument for testing gates as code rather than shipping them as scripts | F91: None
A92: F-TP45 | B92: Med-High | C92: forgeGlue.ts | D92: A REPEAT INSTALL EVENT RESET THE INSTALLATION: Forge may deliver avi:forge:installed:app more than once and each delivery re-ran Lifecycle.install — resetting installedAt, re-sourcing the attribution (ST-056) and overwriting stored tokens with the event's empty ones. Surfaced as an intermittent 1ms test failure that looked like a flaky clock. | E92: FIXED — bootstrap is idempotent; the account is written only when the event carries tokens, otherwise read back | F92: None — but worth remembering that an intermittent test is worth reading before it is retried
A94: PORTFOLIO ROLLOUT KIT (13/09/2026 11:18)
A95: ID | B95: Type | C95: Artifact | D95: What it is | E95: Disposition | F95: Senthil decision
A96: KIT-1 | B96: Tooling | C96: tools/review-gates/init.js | D96: Bootstrapper for porting: scans a repo for the platform manifest, deploy entrypoint, UI/server entries, the OPS SCRIPTS CI RUNS (real callers — TestPulse's encryption-posture check is reachable only from one), source roots, and proposes claim stubs from documents that already make promises. Validated by reproducing TestPulse's hand-written config exactly. | E96: SHIPPED + tested (4 cases incl. the refuse-to-guess paths) | F96: DECISION: run it on the next product and confirm the detected entrypoints before trusting a green result
A97: KIT-2 | B97: Doc | C97: docs/portfolio-gate-rollout.md | D97: Rollout guide: 5-minute per-repo procedure, how to triage the first red run (FIX / ALLOW WITH A REASON / CUT — cutting unfunded scope is a legitimate and usually honest outcome), rollout order (products closest to a live install first; the platform-entrypoint gate pays back fastest because an app that deploys and does nothing is the most expensive failure in this portfolio and has now happened twice), and per-platform hook tables for Forge, Salesforce, Devvit and Shopify. | E97: SHIPPED | F97: DECISION: pick the first product and the order
A98: KIT-3 | B98: Honesty | C98: — | D98: What the gates do NOT catch: 16 of the 50 defects came from USING the product (opening a panel twice, recording a run as a member, installing it and looking). That is L-P6 and does not automate. | E98: Recorded in the rollout guide | F98: DECISION: budget one honest walkthrough per product before each launch
A100: LC-1 SESSION PACK (13/09/2026 11:22)
A101: ID | B101: Type | C101: Artifact | D101: What it is | E101: Disposition | F101: Senthil action
A102: LC1-1 | B102: Tooling | C102: scripts/lc1-verify.js | D102: Live post-install verification against the deployed app: signed payload accepted (202), duplicate event id rejected, tampered signature rejected, stale timestamp rejected, malformed body 400 — the five behaviours the security assessment and HC-14 promise. Prints tracker-ready evidence lines. Tested against the REAL webtrigger handler, so a failure means the deployment differs from this codebase, not that the script is wrong. | E102: SHIPPED + tested (5 cases incl. wrong-secret and network-failure paths) | F102: Run it right after `forge webtrigger`; secret comes from Settings > CI
A103: LC1-2 | B103: Doc | C103: docs/lc1-session-pack.md | D103: 45-minute run sheet: pre-work, install commands, what the lifecycle trigger bootstraps and what to do if it lags (the app self-bootstraps lazily, only the owner claim waits), an evidence table mapping each capture to the stories it flips, and the two questions only a live site can answer — manual keyboard/contrast pass (ST-089) and whether the customer-visible default board name and the 3-distinct-days habit definition are right. | E103: SHIPPED | F103: Book the session; everything else on TestPulse is behind it
A104: LC1-3 | B104: Tooling | C104: static/build/capture.html | D104: Listing-asset capture harness: renders the panels inside dashed frames sized to the VERIFIED Rule-of-3 spec (3 highlights 1840x900, 580x330 crops, banner 1120x548) so one screenshot pass yields correctly sized assets. Verified headlessly — 7 frames, all populated, no NaN. | E104: SHIPPED | F104: Capture at 100% zoom (50% on a 2x display) or the pixel dimensions will be wrong
A105: LC1-4 | B105: Honesty | C105: — | D105: What lc1-verify CANNOT check: the panel render, resolver, roles, licensing, the lifecycle trigger firing and the retention sweep. A green run must not be recorded as full verification. | E105: Stated in the script output and the session pack | F105: Evidence must distinguish verified from assumed
