Workbook

Sheet Version_Control
A1: VERSION CONTROL — RevRescue Sprint Tracker & Traceability
A2: File naming: claude_v<NNN>_<proper file name>_YYYYMMDD_HHMI.xlsx
A3: Version | B3: Date/Time | C3: Author | D3: Change Description | E3: Status
A4: v001 | B4: 2026-09-10 19:42 | C4: Claude for Senthil/KP | D4: THIS FILE — Live execution tracker for RevRescue (portfolio rank 1, D8): sprint tracker log, S0 task board, sprint status rollup (formula-driven), 100-story traceability matrix (spec module -> epic -> story -> screen -> NFR -> verification), RAID carryover, D7 gate checklist. Companion to v007 workbook (backlog source of truth) and v002 kickoff chatlog. S0 opened; Stripe terms verification (N2) executed and logged. | E4: Released
A5: v002 | B5: 2026-09-10 20:05 | C5: Claude for Senthil/KP | D5: T-01 EXECUTED: PRD draft delivered (claude_v001_revrescue_prd_20260910_2005.docx) — 11 sections incl. S0-verified platform requirements, outcome-pricing spec as declared usage-based pricing, NFR-to-story verification map, discovery question set for T-02. T-01 -> Done (draft); awaiting T-06 sign-off. E004 logged. (Supersedes earlier v002 plan text; S0-close update moves to v003.) | E5: Released
A6: v003 | B6: 2026-09-10 20:18 | C6: Claude for Senthil/KP | D6: R5 CLOSED + T-04 EXECUTED: full April-2026 Stripe Apps Agreement read — new obligations logged (no Personal Data in Stripe Apps storage §13; 72-hr breach notification §11; EAR99/5D992 export self-classification §14.3; 30-day removal notice §15; annual Compliance Review exposure §27; Part III Provisioning is OPTIONAL public preview -> D-open: list-only + own billing keeps Part III out of scope). Gate items LC-12/LC-13 added; RAID R5 closed, R8/R9 opened, D-P1 decision raised. Wireframes SCR-1..9 delivered (claude_v001_revrescue_wireframes_scr1-9_20260910_2018.html); T-04 -> Done (draft). | E6: Released
A7: v004 | B7: 2026-09-10 20:42 | C7: Claude for Senthil/KP | D7: D13 LOGGED (Senthil 20:41): T-02/T-05 five-user discovery PARKED; development proceeds; quality rule raised to 100% automation test coverage per code unit (supersedes ST-085 >=70% gate). S1 OPENED. S1 foundation code delivered with enforced 100% gate: ST-051/052/055/056 core logic, 26/26 tests, 202/202 stmts, 53/53 branches, 20/20 funcs (claude_v001_revrescue_s1_foundation_code_20260910_2042.zip). Matrix statuses -> In progress. | E7: Released
A8: v005 | B8: 2026-09-10 20:48 | C8: Claude for Senthil/KP | D8: D14 LOGGED (Senthil 20:48): Stripe SDK adapters + live dev-store smoke PARKED. Sprint continued across all platform-independent scope: 7 domain engines delivered (retry incl. payday-aware, dunning incl. LC-7 locked footer + LC-11 test mode, save-offer guardrails, LC-5 conservative attribution, outcome-fee calculator, alert routing with per-type mute, ST-070 backoff/breaker + LC-4 dedupe). VERIFIED under enforced gate: 64/64 tests, 100% stmts (471/471) / branches (146/146) / funcs (49/49). 22 further stories -> In progress. Code: claude_v002_revrescue_core_engines_code_20260910_2048.zip | E8: Released
A9: v006 | B9: 2026-09-10 21:06 | C9: Claude for Senthil/KP | D9: Remaining pure-logic stories built under 100% gate: ST-054 role matrix + typed enforcement, ST-060 grace/read-only with day-0/3/6 email cadence, ST-061 plan limits with 80%/100% prompts, ST-063 cancellation state machine (save-offer integrated, exit survey, full audit trail), ST-075 weighted health score with bands. VERIFIED: 86/86 tests, 100% stmts (639/639) / branches (198/198) / funcs (68/68). Platform-independent backlog scope now EXHAUSTED — everything further needs D13/D14 unpark or is S9+ content work. Code: claude_v003_revrescue_full_logic_code_20260910_2106.zip | E9: Released
A10: v007 | B10: 2026-09-10 22:00 | C10: Claude for Senthil/KP | D10: S9-S11 LAUNCH CONTENT PACK delivered (28 files): listing copy variants A+B with review-required limitation disclosures (ST-093), pricing page + FAQ with fee rate as flagged [X]% placeholder pending Senthil decision D-P2 (ST-095), security/trust page grounded in the agreement obligations (ST-096), launch runbook incl. LC-13 72-hr breach program (ST-098), incident comms templates (ST-084), review-ask copy (ST-082), 15 help-center articles (ST-080). All external-facing content uses product name only / generic entity placeholders per naming rule. Zip: claude_v001_revrescue_launch_content_pack_20260910_2200.zip. D-P2 (fee %) raised in RAID. | E10: Released
A11: v008 | B11: 2026-09-13 11:32 | C11: Claude for Senthil/KP | D11: RevRescue's FIRST adversarial audit (sibling Pre-Completion Audit pattern) + integration layer. 10 defects found in code at 100% coverage, 2 structural: GAP-RR1 no HTTP application existed behind any surface; GAP-RR2 no DB schema behind any store; F-RR01 every engine was its own only reader; F-RR02/F-RR03 read-only and plan limits computed and enforced nowhere; F-RR04 fee disputes published in FAQ + help article 12 with no code; F-RR05 export/delete published on the trust page with no code (uninstall scheduled nothing); F-RR06 refunds/chargebacks still billed; F-RR07 deduper unused by the webhook handler though LC-4 claimed replay protection; VER-RR01 no Stripe API version pinned. ALL FIXED with pinned regressions. 22 modules, 119 tests, 100% stmts (884)/branches (275)/funcs (83)/lines. 5 observations (OBS-RR1..RR5) logged for disposition. Action plan workbook issued (claude_v001_revrescue_senthil_action_plan_20260913_1132.xlsx), superseding the 10 Sep step-by-step guide. Code: claude_v004_revrescue_integration_code_20260913_1132.zip | E11: Released
A12: v009 | B12: 2026-09-13 12:05 | C12: Claude for Senthil/KP | D12: Verification sweep vs live Stripe docs + review gates ported (PORT-03) + cold-review pass 2 — all without D14. VER-RR02 pinned version 2026-07-30 was not a valid Stripe version string (named-release suffix required since 2024-09-30.acacia; current GA 2026-08-26.dahlia). VER-RR03 LIVE-BLOCKING: the webhook read its event id from a stripe-event-id header Stripe never sends — every real webhook would have been refused missing_event_id. VER-RR04 signature must be verified on the raw body before parsing. F-RR08: every event was handed to the uninstall handler, so invoice.payment_failed would have been rejected as malformed and lost — now dispatched on event.type. REACHABILITY GATE found five modules STILL orphaned after the 11:32 fixes (alerts, dispute, dunning, outcomefee, retry) — closed by building recovery.ts and billing.ts, the service layer that uses them. 24 modules, 140 tests, 100% stmts (1114)/branches (340)/funcs (98)/lines. Code: claude_v005_revrescue_swept_code_20260913_1205.zip | E12: Released
A13: v010 | B13: 2026-09-13 16:24 | C13: Claude for Senthil/KP | D13: Cold-review PASS 3 (logic and integration, no D14 needed) — 6 findings, all fixed with pinned regressions. F-RR09: uninstall deleted NOTHING — it scheduled via an unimplemented interface while the real purge registry was reachable only from the authenticated route; the F-RR05 failure recurring after a partial fix (L-RR3 again). F-RR10: token refresh stampede — concurrent refreshes rotated twice, the second invalidating the first, silently locking the account out. F-RR11: dunning had no send ledger, so a mid-sequence failure or any re-run re-sent earlier steps (duplicate chase messages to paying customers). F-RR12: help article 09 publishes cross-channel opt-out; nothing implemented it — opted-out customers kept receiving both channels (compliance exposure). F-RR13: nextPayday compared calendar dates, so a failure at 08:00 on the 15th was delayed two weeks. Attribution tie-break made deterministic. Claims gate extended to 13 checks. 26 modules, 152 tests, 100% stmts (1210)/branches (360)/funcs (104). Code: claude_v006_revrescue_pass3_code_20260913_1624.zip | E13: Released
A14: v011 | B14: 2026-09-13 16:29 | C14: Claude for Senthil/KP | D14: PORT-03 completed as a PORTABLE PACKAGE (at-review-gates v1.0.0, 10 tests, 100% on all four metrics): three drop-in CI gates — reachability (modules nothing calls), published-claims (promises with no code), config-drift (a value that must match everywhere, e.g. the fee % across listing/app/pricing page) — plus a CLI exiting 1 on failure, an example config and a README. Installable into all ten sibling repos in minutes. Design rule enforced: a gate that cannot see its inputs THROWS rather than passing vacuously (lesson L-RR6). Also issued REVIEW_PACK.md for the external second reviewer (ACT-20), which is the longest-lead item Senthil can start today — it names what to look at in consequence order, the six questions we most want answered, and the eight known-missing items not to waste time on. Zips: claude_v001_at_review_gates_package_20260913_1629.zip, claude_v007_revrescue_reviewpack_code_20260913_1629.zip | E14: Released
... A24: v021 | B24: 2026-09-16 19:16 | C24: Claude for Senthil/KP | D24: D1–D5 (all D14-free follow-ups, approved 18:18). D1 mutation testing on the money path: StrykerJS over the compiled billing/fee/invariant/dispute/attribution modules, gated at 85% in CI — final score 99.1% (464/468); the first run (93.3%) exposed 7 real test gaps, now tested. D2 dead-letter queue: work that errors 5 times is parked with one dead letter; billing failures are dead-lettered and auto-resolved by a later success; an operator plane with its own key ring, 1-hour tokens and an allowlist lists/replays/discards dead letters and resolves fee disputes, every action audited. D3 row-level security FORCED on all 20 account-scoped tables; merchant requests and webhooks run as a tenant role, scheduler/billing/operator as a system role. D4 hash-chained audit trail with anchored retention and a merchant verify route; retention policy applied by the tick (RETENTION.md); error text redacted. D5 help 13 and FAQ corrected (WORDING AWAITS SENTHIL). New defects: V-14 test-mode dunning would have reached real customers over WhatsApp (sandbox port wired to the WhatsApp adapter, present since before v015); V-15 breaker ran on wall-clock time; V-16 redaction masked dates (caught by its own test). NOTHING marked Done. 42 modules, 7 migrations, 353 tests, 100% stmts (5040)/branches (1529)/funcs (412); 7 gates pass. Code: claude_v017_revrescue_server_code_20260916_1916.zip | E24: Released
A25: v022 | D25: PLANNED: S14 on DEC-04; production DB roles per OPERATIONS.md; D5 wording and retention sign-off | E25: Planned

Sheet Context_ReadMe
A1: CONTEXT — WHAT THIS FILE IS
A2: Read this sheet first.
A3: WHAT: The live execution tracker for RevRescue (Stripe App Marketplace, failed-payment recovery) — product #1 of the locked 12-product WIN order (Decision D5/D8, 10 Sep 2026 kickoff).
A4: ROLE IN LINEAGE: v007 workbook (claude_v007_revrescue_stripe_product_workbook_20260905_1950.xlsx) remains the BACKLOG SOURCE OF TRUTH for story definitions. THIS file is the tracking layer: session log, live status, traceability, gate evidence. v002 chatlog holds the locked decisions D1-D11. The independent review workbook (RevRescue_Review_V001 — Findings & Sprint Backlog S13-S22) is the BACKLOG SOURCE for stories RR-P001..RR-P060.
A5: HOW TO USE: (1) Every working session gets a Sprint_Tracker_Log entry. (2) Story status is edited ONLY in Traceability_Matrix col J (yellow) — Sprint_Status_Rollup recalculates from it. (3) S0 tasks (no backlog stories exist for S0) live in S0_Task_Board. (4) At each sprint exit, check the exit criteria row in Sprint_Status_Rollup. (5) The D7 gate (LISTED + 10 paying + kill criteria) is tracked in Gate_Checklist.
A6: EDIT SURFACES (yellow fill): Traceability_Matrix Status/Evidence, S0_Task_Board Status/Notes, Sprint_Tracker_Log new rows, Gate_Checklist Status. Everything else is reference or formula.
A7: NOTE: This file does NOT replace the planned v008 of the v007 workbook (post-S0 re-baseline). When v008 is produced, re-sync the matrix if story IDs change.
A8: OPERATING RULES IN FORCE: R1 serial builds, R2 revenue gate, R3 kill criteria live, R5 gate decisions = Senthil (see v002 Operating_Rules); plus R9 evidence classes, R10 money invariants as build gates, R11 no literals in the composition root (see Operating_Rules sheet, added v020). Note: operating-rule IDs are a separate series from the RAID risk IDs R1–R9.

Sheet Operating_Rules
A1: OPERATING RULES — added from independent review V001 (16 Sep 2026)
A2: R1–R8 live in the v002 chatlog Operating_Rules sheet. R9–R11 below were adopted in v020. Rule IDs are a separate series from RAID risk IDs.
A3: Rule | B3: Statement | C3: Why (origin) | D3: How it is enforced | E3: In force since
A4: R9 | B4: Every story records the EVIDENCE CLASS it has reached: unit | integration (real Postgres and/or real composition root over HTTP) | contract (Stripe test mode) | live | operational | external. Done requires the target class, and never less than live for anything that touches Stripe. | C4: Pass 6 found 12 defects in code at 100% coverage after five internal passes. Coverage proved execution, not correctness; statuses did not say what kind of proof stood behind them. | D4: Traceability_Matrix columns M (reached) and N (target). REVIEW_RESPONSE.md states the class per finding. No story is marked Done in v020. | E4: v020 (16 Sep 2026)
A5: R10 | B5: Money invariants are BUILD GATES and RUNTIME CHECKS, not tests: (I1) statement lines incl. cap line sum to the total; (I2) nothing attributable is worth ≤0; (I3) fee ≤ rate × recovered and ≤ cap; (I4) an invoice is billed at most once, in one period; (I5) reversed/disputed lines are never billed; (I6) trial recoveries bill zero whenever billed. | C5: P-RR01 (£0 recoveries), P-RR03 (history re-billed monthly), P-RR04 (capped statement did not reconcile) — none visible to any existing test. | D5: src/moneyinvariants.ts refuses to issue a violating statement; test/moneygates.ts bills 400 random 6-month histories in `npm run gates` and checks convergence. Mutation-checked: 5 of 5 injected billing bugs caught. | E5: v020 (16 Sep 2026)
A6: R11 | B6: No literal in the composition root (src/main.ts) may stand in for persisted state or a capability: no empty collections, zeros, booleans or money fields. The root builds real stores; it does not describe them. | C6: P-RR01 (amountCents: 0), P-RR08 ({ muted: [] }, emailsSent: 0), P-RR10 (durability declared as true) all lived in main.ts. | D6: composition-root gate in `npm run gates` (test/reviewgates.ts). Negative check: adding `batch: 0` to main.ts fails CI. | E6: v020 (16 Sep 2026)

Sheet Sheet_Index
A1: SHEET INDEX
A2: Sheet | B2: Purpose | C2: Edit surface?
A3: Version_Control | B3: File version lineage | C3: No
A4: Context_ReadMe | B4: What this file is and how to use it | C4: No
A5: Sprint_Tracker_Log | B5: Session-by-session execution log (append rows) | C5: Yes — append
A6: S0_Task_Board | B6: S0 Discovery & Design tasks (S0 has no backlog stories) | C6: Yes — Status/Notes
A7: Sprint_Status_Rollup | B7: Formula-driven S0-S12 progress vs exit criteria | C7: No — formulas
A8: Traceability_Matrix | B8: 100 stories: module->epic->story->screen->NFR->verification->status | C8: Yes — Status/Evidence
A9: RAID_Carryover | B9: Live risks/issues carried from v007 + v002 + S0 findings | C9: Yes
A10: Gate_Checklist | B10: D7 completion gate + Stripe launch checklist items | C10: Yes — Status
A11: Operating_Rules | B11: R9–R11 adopted from independent review V001 (evidence classes, money gates, composition-root rule) | C11: No

Sheet Sprint_Tracker_Log
A1: SPRINT TRACKER LOG — one row per working session / significant event
A2: Append-only. Newest at bottom. Story IDs reference Traceability_Matrix; task IDs reference S0_Task_Board (T-xx) or Gate_Checklist (LC-xx).
A3: Entry | B3: Date/Time | C3: Sprint | D3: Activity / Focus | E3: Items touched | F3: Outcome / Points moved | G3: Blockers | H3: Next action
A4: E001 | B4: 2026-09-10 17:52 | C4: S0 | D4: Tracker instruction received; source files (v002 chatlog, v004 plan, v007 workbook) reviewed; tracker + traceability structure planned | E4: — | F4: Plan approved 19:42 | G4: None | H4: Build tracker (E002)
A5: E002 | B5: 2026-09-10 19:42 | C5: S0 | D5: THIS FILE built: 100-story traceability matrix mapped to spec modules/screens/NFRs; formula rollup; S0 board; gate checklist. S0 formally OPENED. | E5: All | F5: Tracker baseline v001 released | G5: None | H5: Execute S0 tasks (E003)
A6: E003 | B6: 2026-09-10 19:42 | C6: S0 | D6: S0 task T-03 EXECUTED — Stripe App Marketplace terms verification (per N2): April 2026 Apps agreement update confirmed; provisioning transactions must use Stripe Payments (subsequent independent billing exempt); full pricing disclosure mandatory; review needs test plan + credentials; sandbox support required in manifest; pricing must match off-marketplace pricing. Sources logged in RAID_Carryover R5 and S0_Task_Board. | E6: T-03 | F6: T-03 -> Done. Finding: outcome-billing (% of recovered) must be fully disclosed at listing; transparency page (LC-6) is now also a REVIEW requirement, not just a trust feature. | G6: None | H6: T-01 PRD draft; T-02 discovery interviews (Senthil to source 5 target users)
A7: E004 | B7: 2026-09-10 20:05 | C7: S0 | D7: S0 task T-01 EXECUTED — PRD drafted from v007 spec + E003 platform findings: scope (F1-F5), ICP/personas, April-2026 platform constraints as build requirements, outcome-billing pricing model (~$89 ARPU, 20% install->paid working assumptions), NFR table with verifying story IDs, SCR-1..9, gate metrics, top risks, 5 discovery questions feeding T-02. | E7: T-01 | F7: T-01 -> Done (draft). PRD file: claude_v001_revrescue_prd_20260910_2005.docx | G7: None — T-06 sign-off pending (Senthil) | H7: T-04 wireframes (Claude); T-02 interview sourcing (Senthil); R5 full agreement read
A8: E005 | B8: 2026-09-10 20:18 | C8: S0 | D8: R5 CLOSED — full Stripe Apps Agreement (28 Apr 2026) read at stripe.com/legal/apps. New build/ops obligations beyond E003: (1) §13 no Personal Data / health data in Stripe Apps storage -> all customer & dunning data lives in own backend (Postgres), Stripe Apps storage for config only; (2) §11 data-breach notice to stripe-apps-security@stripe.com within 72 hrs + incident mgmt program required; (3) §14.3 export self-classification EAR99 or 5D992 mandatory (app uses encryption); (4) §15 removing app needs 30-day notice + ongoing support for installed users; (5) §27 annual Compliance Review possible, costs reimbursable on non-compliance; (6) §32 terms can change on 30-day notice — monitor; (7) Part III Provisioning Services is PUBLIC PREVIEW and OPTIONAL: applies only if selling via provisioning; if RevRescue lists app + bills independently (v007 fee-note assumption), Part III incl. PSCo tax facilitation does NOT apply and Senthil stays merchant of record handling own taxes either way (§20.3). | E8: R5, LC-12, LC-13, D-P1 | F8: RAID R5 -> Closed; R8, R9 opened; gate items LC-12 (export classification), LC-13 (breach-notification runbook) added; decision D-P1 raised for Senthil | G8: None | H8: D-P1 to Senthil with T-06
A9: E006 | B9: 2026-09-10 20:18 | C9: S0 | D9: S0 task T-04 EXECUTED — lo-fi wireframes for all 9 screens (SCR-1..9): onboarding aha = own lost-revenue number before configuration; retry queue with reasoned scheduling; dunning rail with locked compliance footer; save-offer experiments with finance guardrails; settings with role matrix + data self-serve; billing card wired to §19.4 single-pricing-source rule; analytics attribution-audit tab as transparency-page data source; help. 3 open questions annotated for T-02 interviews (leak-report credibility, WhatsApp value, fair fee %). | E9: T-04 | F9: T-04 -> Done (draft). File: claude_v001_revrescue_wireframes_scr1-9_20260910_2018.html — attach link to v007 Screens_Wireframes col E | G9: None | H9: T-05 prototype test (needs T-02 users); T-06 sign-off pack ready
A10: E007 | B10: 2026-09-10 20:41 | C10: S0/S1 | D10: D13 received from Senthil: park 5-user discovery (T-02/T-05); proceed to development with 100% automation testing for all code. S0 amended (T-02/T-05 -> Parked; PRD = working baseline pending T-06). S1 OPENED. | E10: T-02, T-05, ST-085 | F10: S0 board updated; quality rule logged; ST-085 superseded note added | G10: None | H10: Build S1 foundation with 100% gate (E008)
A11: E008 | B11: 2026-09-10 20:42 | C11: S1 | D11: S1 FOUNDATION BUILT under the new 100% rule — TypeScript core for ST-051 (OAuth install: single-use CSRF state, exchange, persistence, welcome landing), ST-052 (uninstall webhook: signature check, token removal, 30d deletion schedule, audit log), ST-055 (token refresh surviving platform ROTATION — rotated refresh token persisted and reused), ST-056 (install source attribution incl. unknown-kept rule). Dependency-injected platform boundaries; R8 honoured (own token store, nothing in Stripe Apps storage). VERIFIED: 26/26 tests pass; coverage 100% stmts (202/202), 100% branches (53/53), 100% funcs (20/20); gate ENFORCED in build (c8 --100 fails below). | E11: ST-051, ST-052, ST-055, ST-056 | F11: 4 stories -> In progress (core logic + tests complete; Stripe SDK adapters + dev-store install smoke pending — S1 exit criterion). Code: claude_v001_revrescue_s1_foundation_code_20260910_2042.zip | G11: None | H11: Stripe SDK adapters; dev-store smoke test (needs Stripe dev account — Senthil env)
A12: E009 | B12: 2026-09-10 20:48 | C12: S1 | D12: D14 received: park SDK adapters + live dev account; continue sprint and complete all platform-independent work. Scope interpretation logged: "complete" = domain core built + 100% tested; stories stay In progress (not Done) where their exit needs the parked platform surface. | E12: D14 | F12: RAID D14 logged; v005 plan reset | G12: None | H12: Build all domain engines (E010)
A13: E010 | B13: 2026-09-10 20:48 | C13: S2-S8 (core) | D13: ALL DOMAIN ENGINES BUILT under 100% gate: F1 retry (payday-aware 1st/15th, backoff, skip-reasons, exhaustion, ST-008 pause-preserves-state), F2 dunning (validation, due-window progression, LC-7 locked compliance footer, LC-11 sandbox test mode), F3 save-offer (deterministic A/B, exclusion/frequency/discount guardrails), F4 attribution (LC-5: FIRST-event single attribution, duplicates counted+ignored, accounting export), E5 outcome fee (lines match attribution 1:1, ST-057 trial bills zero, cap flag), F5 alerts (per-type mute, ST-048 disable no-loss), ST-070+LC-4 resilience (jittered capped backoff, breaker state machine, replay dedupe with window expiry). VERIFIED: 64/64 tests; 471/471 stmts, 146/146 branches, 49/49 funcs — gate enforced in build. | E13: ST-001,003,004,008,011,013,014,018,021,023,024,028,031,033,034,036,041,043,044,048,057,070 | F13: 22 stories -> In progress (domain core complete + fully tested; Dashboard UI-extension surfaces and platform wiring pending D14 unpark). Code zip: claude_v002_revrescue_core_engines_code_20260910_2048.zip | G13: D14 park blocks all sprint EXIT criteria that need the dev store / UI surface | H13: Senthil: unpark D13 (interviews) and/or D14 (platform) when ready; Claude: remaining pure-logic stories on next continue
A14: E011 | B14: 2026-09-10 21:06 | C14: S2-S8 (core) | D14: FINAL PURE-LOGIC BATCH BUILT: ST-054 owner/admin/member capability matrix with typed PermissionDenied for audit; ST-060 7-day grace with day-0/3/6 dunning cadence then read-only, instant restore on payment; ST-061 limit states ok/warn(80%)/blocked(100%) with upgrade prompts, unlimited plans; ST-063 cancellation state machine — guardrail-refused offers skip to survey, invalid transitions rejected without state corruption, every step audited; ST-075 weighted health score (usage .5 / billing .3 / support .2), clamped inputs, green/amber/red bands. VERIFIED: 86/86 tests; 639/639 stmts, 198/198 branches, 68/68 funcs — gate enforced. Platform-independent backlog scope EXHAUSTED at this point. | E14: ST-054, ST-060, ST-061, ST-063, ST-075 | F14: 5 stories -> In progress (31 of 100 now moving). Code zip: claude_v003_revrescue_full_logic_code_20260910_2106.zip | G14: All remaining backlog scope blocked on D13/D14 parks except S9+ content artifacts | H14: Senthil choice: S9+ content next, or unpark D14 for platform wiring
... A32: E029 | B32: 2026-09-16 19:16 | C32: S15/S19/S20/S22 (D14-free) | D32: Senthil approved D1–D5 at 18:18. Built mutation testing, a dead-letter queue with an operator plane, row-level security and a tamper-evident audit trail with retention, and corrected two content passages. The first mutation run scored 93.3% and its survivors named seven real test gaps; after fixing them the score is 99.1% (464/468). The acceptance suite found V-14: dunning test mode had been wired to the live WhatsApp adapter since before v015, so test-mode messages would have reached real customers. It also found the breaker running on wall-clock time (V-15). A redaction bug of our own (V-16) was caught by its test. | E32: RR-P021, RR-P040, RR-P046, RR-P054; V-13 (content), V-14, V-15, V-16; ST-018/066/067/069 evidence | F32: Four stories advanced to integration/unit evidence; none Done. 42 modules, 7 migrations, 353 tests at 100% (5040 stmts, 1529 branches, 412 funcs); 7 gates pass; mutation 99.1% (464/468). Code: claude_v017_revrescue_server_code_20260916_1916.zip | G32: DEC-04; D5 wording approval; retention periods; operator allowlist; production DB roles | H32: Senthil: approve D5 wording and RETENTION.md periods, name operators, take DEC-04. Then S14.

Sheet S0_Task_Board
A1: S0 TASK BOARD — Discovery & Design (2 wks) — exit: PRD signed off; prototype tested with 5 target users
A2: S0 has zero backlog stories in v007 by design; these tasks operationalise its exit criteria + N2. Edit Status (yellow) + Notes.
A3: ID | B3: Task | C3: Owner | D3: Due (indicative) | E3: Status | F3: Notes / Evidence
A4: T-01 | B4: Draft RevRescue PRD from v007 Product_Spec (5 modules, personas, NFRs) incl. outcome-billing pricing spec | C4: Claude | D4: 2026-09-14 | E4: Done | F4: DONE 10 Sep 20:05 — claude_v001_revrescue_prd_20260910_2005.docx (draft; baselines on T-06 sign-off). See E004.
A5: T-02 | B5: Discovery interviews: 5 target users (SaaS $10k-500k MRR on Stripe Billing, no RevOps) | C5: Senthil (sourcing) + Claude (script/synthesis) | D5: 2026-09-22 | E5: Parked | F5: PARKED per D13 (Senthil 20:41) — resume post-launch or when user access available; discovery questions preserved in PRD §11 + wireframe annotations
A6: T-03 | B6: Verify current Stripe App Marketplace terms, review requirements, payments obligations | C6: Claude | D6: 2026-09-10 | E6: Done | F6: DONE 10 Sep 19:42 — April 2026 agreement update; provisioning sales via Stripe Payments (initial txn only); full pricing disclosure incl. usage rates; test plan + credentials for review; sandbox support in manifest; transparent pricing aligned off-marketplace. See E003 + RAID R5.
A7: T-04 | B7: Wireframes for SCR-1..9 (attach links in v007 Screens_Wireframes col E) | C7: Claude (draft) / Senthil (review) | D7: 2026-09-18 | E7: Done | F7: DONE 10 Sep 20:18 — claude_v001_revrescue_wireframes_scr1-9_20260910_2018.html (draft for T-05). See E006.
A8: T-05 | B8: Prototype tested with 5 target users; findings logged | C8: Both | D8: 2026-09-24 | E8: Parked | F8: PARKED per D13 (Senthil 20:41) — resume post-launch or when user access available; discovery questions preserved in PRD §11 + wireframe annotations
A9: T-06 | B9: PRD sign-off by Senthil | C9: Senthil | D9: 2026-09-24 | E9: To do | F9: S0 close condition (R5)
A10: T-07 | B10: Re-baseline backlog if discovery changes scope -> produce v008 of v007 workbook | C10: Claude | D10: 2026-09-24 | E10: To do | F10: Planned in v007 Version_Control
A11: T-08 | B11: (R6 parallel) DocMerge Pro CASA Tier 2 paperwork research kicked off | C11: Claude | D11: during S1 | E11: To do | F11: N3 — runs on external clock

Sheet Traceability_Matrix
A1: TRACEABILITY MATRIX — spec module -> epic -> story -> sprint -> screen -> NFR -> verification -> status
A2: One row per v007 Full_Backlog story (100). EDIT ONLY: Status (col J, yellow; dropdown) and Evidence (col L, yellow). Rollup recalculates automatically. Story text abridged where long — v007 remains authoritative wording. v020: rows 104-163 are the review stories RR-P001..RR-P060 (unestimated); columns M/N record evidence class per rule R9.
A3: Story ID | B3: Epic | C3: Spec module / area | D3: Story | E3: Points | F3: Priority | G3: Sprint | H3: Screen ref | I3: NFR applicable | J3: Status | K3: Verification method | L3: Evidence / link | M3: Evidence class reached (R9) | N3: Target evidence class
A4: ST-001 | B4: F1 | C4: Smart retry scheduler | D4: As a Founder, I can set up Smart retry scheduler with sensible defaults in one screen | E4: 5 | F4: P0 | G4: S2 | H4: SCR-3 Retry workspace | I4: p95 <500ms API / <2s UI | J4: In progress | K4: E2E test + demo | L4: Core engine + 100% tests in engines zip 20260910_2048 (E010); UI/platform wiring pending D14 | v016: exercised end to end through the composition root on real Postgres (claude_v016_revrescue_server_code_20260916_1807.zip); still no live Stripe. | M4: integration | N4: live
A5: ST-002 | B5: F1 | C5: Smart retry scheduler | D5: As a Founder, the Smart retry scheduler happy path completes without documentation | E5: 8 | F5: P0 | G5: S2 | H5: SCR-3 Retry workspace | I5: p95 <500ms API / <2s UI | J5: Backlog | K5: E2E test + demo | M5: none | N5: live
A6: ST-003 | B6: F1 | C6: Smart retry scheduler | D6: As a Finance ops, I can customise Smart retry scheduler rules/conditions for my workflow | E6: 5 | F6: P1 | G6: S2 | H6: SCR-3 Retry workspace | I6: p95 <500ms API / <2s UI | J6: In progress | K6: Integration test + manual QA | L6: Core engine + 100% tests in engines zip 20260910_2048 (E010); UI/platform wiring pending D14 | v016: exercised end to end through the composition root on real Postgres (claude_v016_revrescue_server_code_20260916_1807.zip); still no live Stripe. | M6: integration | N6: live
A7: ST-004 | B7: F1 | C7: Smart retry scheduler | D7: As a user, Smart retry scheduler shows clear errors and retry paths on platform API failures | E7: 3 | F7: P0 | G7: S2 | H7: SCR-3 Retry workspace | I7: p95 <500ms API / <2s UI | J7: In progress | K7: E2E test + demo | L7: Core engine + 100% tests in engines zip 20260910_2048 (E010); UI/platform wiring pending D14 | v016: exercised end to end through the composition root on real Postgres (claude_v016_revrescue_server_code_20260916_1807.zip); still no live Stripe. | M7: integration | N7: live
A8: ST-005 | B8: F1 | C8: Smart retry scheduler | D8: As a Growth lead, Smart retry scheduler works on the Stripe Apps UI extension in Dashboard surface end-to-end | E8: 5 | F8: P0 | G8: S3 | H8: SCR-3 Retry workspace | I8: p95 <500ms API / <2s UI | J8: Backlog | K8: E2E test + demo | M8: none | N8: live
A9: ST-006 | B9: F1 | C9: Smart retry scheduler | D9: As a Finance ops, I can see Smart retry scheduler performance metrics and trends | E9: 3 | F9: P1 | G9: S3 | H9: SCR-3 Retry workspace | I9: p95 <500ms API / <2s UI | J9: Backlog | K9: Integration test + manual QA | M9: none | N9: live
A10: ST-007 | B10: F1 | C10: Smart retry scheduler | D10: As a user, Smart retry scheduler respects role permissions and audit logging | E10: 3 | F10: P1 | G10: S3 | H10: SCR-3 Retry workspace | I10: p95 <500ms API / <2s UI | J10: In progress | K10: Integration test + manual QA | L10: v016 (20260916_1807): Role checks on every route; denied actions recorded to the audit trail (V-11); retry decisions audited — v016 main.test. UI pending S16. | M10: integration | N10: live
A11: ST-008 | B11: F1 | C11: Smart retry scheduler | D11: As a Founder, I can pause/disable Smart retry scheduler without data loss | E11: 2 | F11: P2 | G11: S3 | H11: SCR-3 Retry workspace | I11: p95 <500ms API / <2s UI | J11: In progress | K11: Manual QA | L11: Core engine + 100% tests in engines zip 20260910_2048 (E010); UI/platform wiring pending D14 | v016: exercised end to end through the composition root on real Postgres (claude_v016_revrescue_server_code_20260916_1807.zip); still no live Stripe. | M11: integration | N11: live
A12: ST-009 | B12: F1 | C12: Smart retry scheduler | D12: As a Finance ops, I can import/migrate existing data into Smart retry scheduler (CSV + competitor importer) | E12: 5 | F12: P1 | G12: S3 | H12: SCR-3 Retry workspace | I12: p95 <500ms API / <2s UI | J12: Backlog | K12: Integration test + manual QA | M12: none | N12: live
A13: ST-010 | B13: F1 | C13: Smart retry scheduler | D13: As a user, I get notifications (in-app + email) for key Smart retry scheduler events with per-type mute | E13: 3 | F13: P2 | G13: S3 | H13: SCR-3 Retry workspace | I13: p95 <500ms API / <2s UI | J13: Backlog | K13: Manual QA | M13: none | N13: live
A14: ST-011 | B14: F2 | C14: Dunning sequences (email/WA) | D14: As a Founder, I can set up Dunning sequences (email/WA) with sensible defaults in one screen | E14: 5 | F14: P0 | G14: S3 | H14: SCR-4 Dunning builder | I14: p95 <500ms API / <2s UI | J14: In progress | K14: E2E test + demo | L14: Core engine + 100% tests in engines zip 20260910_2048 (E010); UI/platform wiring pending D14 | v016: exercised end to end through the composition root on real Postgres (claude_v016_revrescue_server_code_20260916_1807.zip); still no live Stripe. | M14: integration | N14: live
A15: ST-012 | B15: F2 | C15: Dunning sequences (email/WA) | D15: As a Founder, the Dunning sequences (email/WA) happy path completes without documentation | E15: 8 | F15: P0 | G15: S3 | H15: SCR-4 Dunning builder | I15: p95 <500ms API / <2s UI | J15: Backlog | K15: E2E test + demo | M15: none | N15: live
A16: ST-013 | B16: F2 | C16: Dunning sequences (email/WA) | D16: As a Finance ops, I can customise Dunning sequences (email/WA) rules/conditions for my workflow | E16: 5 | F16: P1 | G16: S3 | H16: SCR-4 Dunning builder | I16: p95 <500ms API / <2s UI | J16: In progress | K16: Integration test + manual QA | L16: Core engine + 100% tests in engines zip 20260910_2048 (E010); UI/platform wiring pending D14 | v016: exercised end to end through the composition root on real Postgres (claude_v016_revrescue_server_code_20260916_1807.zip); still no live Stripe. | M16: integration | N16: live
A17: ST-014 | B17: F2 | C17: Dunning sequences (email/WA) | D17: As a user, Dunning sequences (email/WA) shows clear errors and retry paths on platform API failures | E17: 3 | F17: P0 | G17: S3 | H17: SCR-4 Dunning builder | I17: p95 <500ms API / <2s UI | J17: In progress | K17: E2E test + demo | L17: Core engine + 100% tests in engines zip 20260910_2048 (E010); UI/platform wiring pending D14 | v016: exercised end to end through the composition root on real Postgres (claude_v016_revrescue_server_code_20260916_1807.zip); still no live Stripe. | M17: integration | N17: live
A18: ST-015 | B18: F2 | C18: Dunning sequences (email/WA) | D18: As a Growth lead, Dunning sequences (email/WA) works on the Stripe Apps UI extension in Dashboard surface end-to-end | E18: 5 | F18: P0 | G18: S4 | H18: SCR-4 Dunning builder | I18: p95 <500ms API / <2s UI | J18: Backlog | K18: E2E test + demo | M18: none | N18: live
A19: ST-016 | B19: F2 | C19: Dunning sequences (email/WA) | D19: As a Finance ops, I can see Dunning sequences (email/WA) performance metrics and trends | E19: 3 | F19: P1 | G19: S4 | H19: SCR-4 Dunning builder | I19: p95 <500ms API / <2s UI | J19: Backlog | K19: Integration test + manual QA | M19: none | N19: live
A20: ST-017 | B20: F2 | C20: Dunning sequences (email/WA) | D20: As a user, Dunning sequences (email/WA) respects role permissions and audit logging | E20: 3 | F20: P1 | G20: S4 | H20: SCR-4 Dunning builder | I20: p95 <500ms API / <2s UI | J20: Backlog | K20: Integration test + manual QA | M20: none | N20: live
A21: ST-018 | B21: F2 | C21: Dunning sequences (email/WA) | D21: As a Founder, I can pause/disable Dunning sequences (email/WA) without data loss | E21: 2 | F21: P2 | G21: S4 | H21: SCR-4 Dunning builder | I21: p95 <500ms API / <2s UI | J21: In progress | K21: Manual QA | L21: Core engine + 100% tests in engines zip 20260910_2048 (E010); UI/platform wiring pending D14 | v016: exercised end to end through the composition root on real Postgres (claude_v016_revrescue_server_code_20260916_1807.zip); still no live Stripe. | v017: V-14 fixed — test mode had been wired to the live WhatsApp adapter; now a separate sandbox sender, proven by test. | M21: integration | N21: live
A22: ST-019 | B22: F2 | C22: Dunning sequences (email/WA) | D22: As a Finance ops, I can import/migrate existing data into Dunning sequences (email/WA) (CSV + competitor importer) | E22: 5 | F22: P1 | G22: S4 | H22: SCR-4 Dunning builder | I22: p95 <500ms API / <2s UI | J22: Backlog | K22: Integration test + manual QA | M22: none | N22: live
A23: ST-020 | B23: F2 | C23: Dunning sequences (email/WA) | D23: As a user, I get notifications (in-app + email) for key Dunning sequences (email/WA) events with per-type mute | E23: 3 | F23: P2 | G23: S4 | H23: SCR-4 Dunning builder | I23: p95 <500ms API / <2s UI | J23: Backlog | K23: Manual QA | M23: none | N23: live
A24: ST-021 | B24: F3 | C24: Save-offer engine | D24: As a Founder, I can set up Save-offer engine with sensible defaults in one screen | E24: 5 | F24: P0 | G24: S5 | H24: SCR-5 Save-offer view | I24: p95 <500ms API / <2s UI | J24: In progress | K24: E2E test + demo | L24: Core engine + 100% tests in engines zip 20260910_2048 (E010); UI/platform wiring pending D14 | v016: exercised end to end through the composition root on real Postgres (claude_v016_revrescue_server_code_20260916_1807.zip); still no live Stripe. | M24: integration | N24: live
A25: ST-022 | B25: F3 | C25: Save-offer engine | D25: As a Founder, the Save-offer engine happy path completes without documentation | E25: 8 | F25: P0 | G25: S5 | H25: SCR-5 Save-offer view | I25: p95 <500ms API / <2s UI | J25: Backlog | K25: E2E test + demo | M25: none | N25: live
A26: ST-023 | B26: F3 | C26: Save-offer engine | D26: As a Finance ops, I can customise Save-offer engine rules/conditions for my workflow | E26: 5 | F26: P1 | G26: S5 | H26: SCR-5 Save-offer view | I26: p95 <500ms API / <2s UI | J26: In progress | K26: Integration test + manual QA | L26: Core engine + 100% tests in engines zip 20260910_2048 (E010); UI/platform wiring pending D14 | v016: exercised end to end through the composition root on real Postgres (claude_v016_revrescue_server_code_20260916_1807.zip); still no live Stripe. | M26: integration | N26: live
A27: ST-024 | B27: F3 | C27: Save-offer engine | D27: As a user, Save-offer engine shows clear errors and retry paths on platform API failures | E27: 3 | F27: P0 | G27: S5 | H27: SCR-5 Save-offer view | I27: p95 <500ms API / <2s UI | J27: In progress | K27: E2E test + demo | L27: Core engine + 100% tests in engines zip 20260910_2048 (E010); UI/platform wiring pending D14 | v016: exercised end to end through the composition root on real Postgres (claude_v016_revrescue_server_code_20260916_1807.zip); still no live Stripe. | M27: integration | N27: live
A28: ST-025 | B28: F3 | C28: Save-offer engine | D28: As a Growth lead, Save-offer engine works on the Stripe Apps UI extension in Dashboard surface end-to-end | E28: 5 | F28: P0 | G28: S5 | H28: SCR-5 Save-offer view | I28: p95 <500ms API / <2s UI | J28: Backlog | K28: E2E test + demo | M28: none | N28: live
A29: ST-026 | B29: F3 | C29: Save-offer engine | D29: As a Finance ops, I can see Save-offer engine performance metrics and trends | E29: 3 | F29: P1 | G29: S5 | H29: SCR-5 Save-offer view | I29: p95 <500ms API / <2s UI | J29: Backlog | K29: Integration test + manual QA | M29: none | N29: live
A30: ST-027 | B30: F3 | C30: Save-offer engine | D30: As a user, Save-offer engine respects role permissions and audit logging | E30: 3 | F30: P1 | G30: S5 | H30: SCR-5 Save-offer view | I30: p95 <500ms API / <2s UI | J30: Backlog | K30: Integration test + manual QA | M30: none | N30: live
A31: ST-028 | B31: F3 | C31: Save-offer engine | D31: As a Founder, I can pause/disable Save-offer engine without data loss | E31: 2 | F31: P2 | G31: S5 | H31: SCR-5 Save-offer view | I31: p95 <500ms API / <2s UI | J31: In progress | K31: Manual QA | L31: Core engine + 100% tests in engines zip 20260910_2048 (E010); UI/platform wiring pending D14 | v016: exercised end to end through the composition root on real Postgres (claude_v016_revrescue_server_code_20260916_1807.zip); still no live Stripe. | M31: integration | N31: live
A32: ST-029 | B32: F3 | C32: Save-offer engine | D32: As a Finance ops, I can import/migrate existing data into Save-offer engine (CSV + competitor importer) | E32: 5 | F32: P1 | G32: S5 | H32: SCR-5 Save-offer view | I32: p95 <500ms API / <2s UI | J32: Backlog | K32: Integration test + manual QA | M32: none | N32: live
A33: ST-030 | B33: F3 | C33: Save-offer engine | D33: As a user, I get notifications (in-app + email) for key Save-offer engine events with per-type mute | E33: 3 | F33: P2 | G33: S5 | H33: SCR-5 Save-offer view | I33: p95 <500ms API / <2s UI | J33: Backlog | K33: Manual QA | M33: none | N33: live
A34: ST-031 | B34: F4 | C34: Recovery analytics | D34: As a Founder, I can set up Recovery analytics with sensible defaults in one screen | E34: 5 | F34: P0 | G34: S6 | H34: SCR-8 Analytics | I34: p95 <500ms API / <2s UI | J34: In progress | K34: E2E test + demo | L34: Core engine + 100% tests in engines zip 20260910_2048 (E010); UI/platform wiring pending D14 | v016: exercised end to end through the composition root on real Postgres (claude_v016_revrescue_server_code_20260916_1807.zip); still no live Stripe. | M34: integration | N34: live
A35: ST-032 | B35: F4 | C35: Recovery analytics | D35: As a Founder, the Recovery analytics happy path completes without documentation | E35: 8 | F35: P0 | G35: S6 | H35: SCR-8 Analytics | I35: p95 <500ms API / <2s UI | J35: Backlog | K35: E2E test + demo | M35: none | N35: live
A36: ST-033 | B36: F4 | C36: Recovery analytics | D36: As a Finance ops, I can customise Recovery analytics rules/conditions for my workflow | E36: 5 | F36: P1 | G36: S6 | H36: SCR-8 Analytics | I36: p95 <500ms API / <2s UI | J36: In progress | K36: Integration test + manual QA | L36: Core engine + 100% tests in engines zip 20260910_2048 (E010); UI/platform wiring pending D14 | v016: exercised end to end through the composition root on real Postgres (claude_v016_revrescue_server_code_20260916_1807.zip); still no live Stripe. | M36: integration | N36: live
A37: ST-034 | B37: F4 | C37: Recovery analytics | D37: As a user, Recovery analytics shows clear errors and retry paths on platform API failures | E37: 3 | F37: P0 | G37: S6 | H37: SCR-8 Analytics | I37: p95 <500ms API / <2s UI | J37: In progress | K37: E2E test + demo | L37: Core engine + 100% tests in engines zip 20260910_2048 (E010); UI/platform wiring pending D14 | v016: exercised end to end through the composition root on real Postgres (claude_v016_revrescue_server_code_20260916_1807.zip); still no live Stripe. | M37: integration | N37: live
A38: ST-035 | B38: F4 | C38: Recovery analytics | D38: As a Growth lead, Recovery analytics works on the Stripe Apps UI extension in Dashboard surface end-to-end | E38: 5 | F38: P0 | G38: S6 | H38: SCR-8 Analytics | I38: p95 <500ms API / <2s UI | J38: Backlog | K38: E2E test + demo | M38: none | N38: live
A39: ST-036 | B39: F4 | C39: Recovery analytics | D39: As a Finance ops, I can see Recovery analytics performance metrics and trends | E39: 3 | F39: P1 | G39: S6 | H39: SCR-8 Analytics | I39: p95 <500ms API / <2s UI | J39: In progress | K39: Integration test + manual QA | L39: Core engine + 100% tests in engines zip 20260910_2048 (E010); UI/platform wiring pending D14 | v016: exercised end to end through the composition root on real Postgres (claude_v016_revrescue_server_code_20260916_1807.zip); still no live Stripe. | M39: integration | N39: live
A40: ST-037 | B40: F4 | C40: Recovery analytics | D40: As a user, Recovery analytics respects role permissions and audit logging | E40: 3 | F40: P1 | G40: S6 | H40: SCR-8 Analytics | I40: p95 <500ms API / <2s UI | J40: Backlog | K40: Integration test + manual QA | M40: none | N40: live
A41: ST-038 | B41: F4 | C41: Recovery analytics | D41: As a Founder, I can pause/disable Recovery analytics without data loss | E41: 2 | F41: P2 | G41: S6 | H41: SCR-8 Analytics | I41: p95 <500ms API / <2s UI | J41: Backlog | K41: Manual QA | M41: none | N41: live
A42: ST-039 | B42: F4 | C42: Recovery analytics | D42: As a Finance ops, I can import/migrate existing data into Recovery analytics (CSV + competitor importer) | E42: 5 | F42: P1 | G42: S6 | H42: SCR-8 Analytics | I42: p95 <500ms API / <2s UI | J42: Backlog | K42: Integration test + manual QA | M42: none | N42: live
A43: ST-040 | B43: F4 | C43: Recovery analytics | D43: As a user, I get notifications (in-app + email) for key Recovery analytics events with per-type mute | E43: 3 | F43: P2 | G43: S6 | H43: SCR-8 Analytics | I43: p95 <500ms API / <2s UI | J43: Backlog | K43: Manual QA | M43: none | N43: live
A44: ST-041 | B44: F5 | C44: Slack alerts | D44: As a Founder, I can set up Slack alerts with sensible defaults in one screen | E44: 5 | F44: P0 | G44: S8 | H44: SCR-2 Dashboard / SCR-6 Settings | I44: Rate-limit safe (backoff+queue) | J44: In progress | K44: E2E test + demo | L44: Core engine + 100% tests in engines zip 20260910_2048 (E010); UI/platform wiring pending D14 | v016: exercised end to end through the composition root on real Postgres (claude_v016_revrescue_server_code_20260916_1807.zip); still no live Stripe. | M44: integration | N44: live
A45: ST-042 | B45: F5 | C45: Slack alerts | D45: As a Founder, the Slack alerts happy path completes without documentation | E45: 8 | F45: P0 | G45: S8 | H45: SCR-2 Dashboard / SCR-6 Settings | I45: Rate-limit safe (backoff+queue) | J45: Backlog | K45: E2E test + demo | M45: none | N45: live
A46: ST-043 | B46: F5 | C46: Slack alerts | D46: As a Finance ops, I can customise Slack alerts rules/conditions for my workflow | E46: 5 | F46: P1 | G46: S8 | H46: SCR-2 Dashboard / SCR-6 Settings | I46: Rate-limit safe (backoff+queue) | J46: In progress | K46: Integration test + manual QA | L46: Core engine + 100% tests in engines zip 20260910_2048 (E010); UI/platform wiring pending D14 | v016: exercised end to end through the composition root on real Postgres (claude_v016_revrescue_server_code_20260916_1807.zip); still no live Stripe. | M46: integration | N46: live
A47: ST-044 | B47: F5 | C47: Slack alerts | D47: As a user, Slack alerts shows clear errors and retry paths on platform API failures | E47: 3 | F47: P0 | G47: S8 | H47: SCR-2 Dashboard / SCR-6 Settings | I47: Rate-limit safe (backoff+queue) | J47: In progress | K47: E2E test + demo | L47: Core engine + 100% tests in engines zip 20260910_2048 (E010); UI/platform wiring pending D14 | v016: exercised end to end through the composition root on real Postgres (claude_v016_revrescue_server_code_20260916_1807.zip); still no live Stripe. | M47: integration | N47: live
A48: ST-045 | B48: F5 | C48: Slack alerts | D48: As a Growth lead, Slack alerts works on the Stripe Apps UI extension in Dashboard surface end-to-end | E48: 5 | F48: P0 | G48: S8 | H48: SCR-2 Dashboard / SCR-6 Settings | I48: Rate-limit safe (backoff+queue) | J48: Backlog | K48: E2E test + demo | M48: none | N48: live
A49: ST-046 | B49: F5 | C49: Slack alerts | D49: As a Finance ops, I can see Slack alerts performance metrics and trends | E49: 3 | F49: P1 | G49: S8 | H49: SCR-2 Dashboard / SCR-6 Settings | I49: Rate-limit safe (backoff+queue) | J49: Backlog | K49: Integration test + manual QA | M49: none | N49: live
A50: ST-047 | B50: F5 | C50: Slack alerts | D50: As a user, Slack alerts respects role permissions and audit logging | E50: 3 | F50: P1 | G50: S8 | H50: SCR-2 Dashboard / SCR-6 Settings | I50: Rate-limit safe (backoff+queue) | J50: Backlog | K50: Integration test + manual QA | M50: none | N50: live
A51: ST-048 | B51: F5 | C51: Slack alerts | D51: As a Founder, I can pause/disable Slack alerts without data loss | E51: 2 | F51: P2 | G51: S8 | H51: SCR-2 Dashboard / SCR-6 Settings | I51: Rate-limit safe (backoff+queue) | J51: In progress | K51: Manual QA | L51: Core engine + 100% tests in engines zip 20260910_2048 (E010); UI/platform wiring pending D14 | v016: exercised end to end through the composition root on real Postgres (claude_v016_revrescue_server_code_20260916_1807.zip); still no live Stripe. | M51: integration | N51: live
A52: ST-049 | B52: F5 | C52: Slack alerts | D52: As a Finance ops, I can import/migrate existing data into Slack alerts (CSV + competitor importer) | E52: 5 | F52: P1 | G52: S8 | H52: SCR-2 Dashboard / SCR-6 Settings | I52: Rate-limit safe (backoff+queue) | J52: Backlog | K52: Integration test + manual QA | M52: none | N52: live
A53: ST-050 | B53: F5 | C53: Slack alerts | D53: As a user, I get notifications (in-app + email) for key Slack alerts events with per-type mute | E53: 3 | F53: P2 | G53: S8 | H53: SCR-2 Dashboard / SCR-6 Settings | I53: Rate-limit safe (backoff+queue) | J53: Backlog | K53: Manual QA | M53: none | N53: live
A54: ST-051 | B54: E1 | C54: Platform foundation (install/auth) | D54: Marketplace OAuth install completes and lands on welcome state in <2 min | E54: 5 | F54: P0 | G54: S1 | H54: SCR-1 Onboarding | I54: Rate-limit safe (backoff+queue) | J54: In progress | K54: E2E test + demo | L54: S1 foundation zip 20260910_2042 — core logic + tests, 100% cov (E008); SDK adapters pending | v016: exercised end to end through the composition root on real Postgres (claude_v016_revrescue_server_code_20260916_1807.zip); still no live Stripe. | M54: integration | N54: live
A55: ST-052 | B55: E1 | C55: Platform foundation (install/auth) | D55: Uninstall webhook removes tokens, schedules data deletion per policy | E55: 3 | F55: P0 | G55: S1 | H55: SCR-1 Onboarding | I55: Rate-limit safe (backoff+queue) | J55: In progress | K55: E2E test + demo | L55: S1 foundation zip 20260910_2042 — core logic + tests, 100% cov (E008); SDK adapters pending | v016: exercised end to end through the composition root on real Postgres (claude_v016_revrescue_server_code_20260916_1807.zip); still no live Stripe. | M55: integration | N55: live
A56: ST-053 | B56: E1 | C56: Platform foundation (install/auth) | D56: Re-install restores account within retention window | E56: 3 | F56: P1 | G56: S2 | H56: SCR-1 Onboarding | I56: Rate-limit safe (backoff+queue) | J56: Backlog | K56: Integration test + manual QA | M56: none | N56: live
A57: ST-054 | B57: E1 | C57: Platform foundation (install/auth) | D57: Multi-user roles: owner/admin/member permission matrix enforced | E57: 5 | F57: P0 | G57: S2 | H57: SCR-1 Onboarding | I57: Rate-limit safe (backoff+queue) | J57: In progress | K57: E2E test + demo | L57: Core engine + 100% tests in full-logic zip 20260910_2106 (E011); UI/platform wiring pending D14 | v016: exercised end to end through the composition root on real Postgres (claude_v016_revrescue_server_code_20260916_1807.zip); still no live Stripe. | M57: integration | N57: live
A58: ST-055 | B58: E1 | C58: Platform foundation (install/auth) | D58: Session/token refresh survives platform token rotation | E58: 3 | F58: P0 | G58: S1 | H58: SCR-1 Onboarding | I58: Rate-limit safe (backoff+queue) | J58: In progress | K58: E2E test + demo | L58: S1 foundation zip 20260910_2042 — core logic + tests, 100% cov (E008); SDK adapters pending | v016: exercised end to end through the composition root on real Postgres (claude_v016_revrescue_server_code_20260916_1807.zip); still no live Stripe. | M58: integration | N58: live
A59: ST-056 | B59: E1 | C59: Platform foundation (install/auth) | D59: Install telemetry: source attribution (listing/search/referral) captured | E59: 2 | F59: P1 | G59: S1 | H59: SCR-1 Onboarding | I59: Rate-limit safe (backoff+queue) | J59: In progress | K59: Integration test + manual QA | L59: S1 foundation zip 20260910_2042 — core logic + tests, 100% cov (E008); SDK adapters pending | v016: exercised end to end through the composition root on real Postgres (claude_v016_revrescue_server_code_20260916_1807.zip); still no live Stripe. | M59: integration | N59: live
A60: ST-057 | B60: E5 | C60: Billing & plans | D60: 14-day trial without card; banner shows days remaining | E60: 5 | F60: P0 | G60: S6 | H60: SCR-7 Billing | I60: 99.5% monthly uptime | J60: In progress | K60: E2E test + demo | L60: Core engine + 100% tests in engines zip 20260910_2048 (E010); UI/platform wiring pending D14 | v016: exercised end to end through the composition root on real Postgres (claude_v016_revrescue_server_code_20260916_1807.zip); still no live Stripe. | M60: integration | N60: live
A61: ST-058 | B61: E5 | C61: Billing & plans | D61: Upgrade/downgrade mid-cycle prorates correctly | E61: 5 | F61: P0 | G61: S6 | H61: SCR-7 Billing | I61: 99.5% monthly uptime | J61: Backlog | K61: E2E test + demo | M61: none | N61: live
A62: ST-059 | B62: E5 | C62: Billing & plans | D62: Marketplace billing API used where mandated; external Stripe fallback elsewhere | E62: 8 | F62: P0 | G62: S6 | H62: SCR-7 Billing | I62: 99.5% monthly uptime | J62: Backlog | K62: E2E test + demo | M62: none | N62: live
A63: ST-060 | B63: E5 | C63: Billing & plans | D63: Failed payment: 7-day grace, 3 dunning emails, then read-only mode | E63: 3 | F63: P1 | G63: S7 | H63: SCR-7 Billing | I63: 99.5% monthly uptime | J63: In progress | K63: Integration test + manual QA | L63: Core engine + 100% tests in full-logic zip 20260910_2106 (E011); UI/platform wiring pending D14 | v016: exercised end to end through the composition root on real Postgres (claude_v016_revrescue_server_code_20260916_1807.zip); still no live Stripe. | M63: integration | N63: live
A64: ST-061 | B64: E5 | C64: Billing & plans | D64: Plan limits enforced with upgrade prompts at 80%/100% | E64: 3 | F64: P1 | G64: S7 | H64: SCR-7 Billing | I64: 99.5% monthly uptime | J64: In progress | K64: Integration test + manual QA | L64: Core engine + 100% tests in full-logic zip 20260910_2106 (E011); UI/platform wiring pending D14 | v016: exercised end to end through the composition root on real Postgres (claude_v016_revrescue_server_code_20260916_1807.zip); still no live Stripe. | M64: integration | N64: live
A65: ST-062 | B65: E5 | C65: Billing & plans | D65: Invoices/receipts downloadable; GST/VAT fields supported | E65: 3 | F65: P2 | G65: S7 | H65: SCR-7 Billing | I65: 99.5% monthly uptime | J65: Backlog | K65: Manual QA | M65: none | N65: live
A66: ST-063 | B66: E5 | C66: Billing & plans | D66: Cancellation flow with save-offer and exit survey | E66: 3 | F66: P1 | G66: S7 | H66: SCR-7 Billing | I66: 99.5% monthly uptime | J66: In progress | K66: Integration test + manual QA | L66: Core engine + 100% tests in full-logic zip 20260910_2106 (E011); UI/platform wiring pending D14 | v016: exercised end to end through the composition root on real Postgres (claude_v016_revrescue_server_code_20260916_1807.zip); still no live Stripe. | M66: integration | N66: live
A67: ST-064 | B67: E6 | C67: Security & compliance | D67: Scopes requested map 1:1 to shipped features (least privilege doc) | E67: 3 | F67: P0 | G67: S7 | H67: SCR-6 Settings / LC-1..7 | I67: SOC2-track controls | J67: Backlog | K67: Evidence archived + gate review | M67: none | N67: live
A68: ST-065 | B68: E6 | C68: Security & compliance | D68: Data-flow diagram + retention policy published | E68: 3 | F68: P0 | G68: S8 | H68: SCR-6 Settings / LC-1..7 | I68: SOC2-track controls | J68: Backlog | K68: Evidence archived + gate review | M68: none | N68: live
A69: ST-066 | B69: E6 | C69: Security & compliance | D69: Encryption at rest + in transit verified; secrets in vault | E69: 5 | F69: P0 | G69: S8 | H69: SCR-6 Settings / LC-1..7 | I69: SOC2-track controls | J69: In progress | K69: Evidence archived + gate review | L69: v016 (20260916_1807): AES-256-GCM token encryption at rest with key rotation, proven against Postgres (pg.test). Vault/KMS + TLS verification pending infra. | v017: row-level security forced on every account table (RR-P046). | M69: integration | N69: live
A70: ST-067 | B70: E6 | C70: Security & compliance | D70: Audit log for admin-sensitive actions | E70: 5 | F70: P1 | G70: S8 | H70: SCR-6 Settings / LC-1..7 | I70: SOC2-track controls | J70: In progress | K70: Evidence archived + gate review | L70: v016 (20260916_1807): Audit trail table with writer and reader (GET /api/recoveries/audit); access denials recorded — v016. Team/role changes not yet audited. | v017: audit trail hash-chained and verifiable; operator actions audited. | M70: integration | N70: live
A71: ST-068 | B71: E6 | C71: Security & compliance | D71: Pen-test (or platform-required evidence) completed and archived | E71: 8 | F71: P0 | G71: S9 | H71: SCR-6 Settings / LC-1..7 | I71: SOC2-track controls | J71: Backlog | K71: Evidence archived + gate review | M71: none | N71: live
A72: ST-069 | B72: E6 | C72: Security & compliance | D72: Data export + delete-my-data self-serve | E72: 5 | F72: P0 | G72: S9 | H72: SCR-6 Settings / LC-1..7 | I72: SOC2-track controls | J72: In progress | K72: Evidence archived + gate review | L72: v016 (20260916_1807): GET /api/data/export and POST /api/data/delete over every account-scoped table; completeness read from Postgres (V-06) — v016. | v017: export/delete run under tenant-scoped database access; help 13 wording corrected (awaiting approval). | M72: integration | N72: live
A73: ST-070 | B73: E6 | C73: Security & compliance | D73: Rate-limit backoff + circuit breaker on platform APIs | E73: 5 | F73: P0 | G73: S8 | H73: SCR-6 Settings / LC-1..7 | I73: SOC2-track controls | J73: In progress | K73: Evidence archived + gate review | L73: Core engine + 100% tests in engines zip 20260910_2048 (E010); UI/platform wiring pending D14 | v016: exercised end to end through the composition root on real Postgres (claude_v016_revrescue_server_code_20260916_1807.zip); still no live Stripe. | M73: integration | N73: live
A74: ST-071 | B74: E7 | C74: Telemetry & metrics | D74: Activation funnel events (install->setup->aha->habit) in one dashboard | E74: 5 | F74: P0 | G74: S4 | H74: SCR-8 Analytics (internal) | I74: p95 latency budgets | J74: Backlog | K74: E2E test + demo | M74: none | N74: live
A75: ST-072 | B75: E7 | C75: Telemetry & metrics | D75: Error tracking with release tagging; alert on error-rate spike | E75: 3 | F75: P0 | G75: S4 | H75: SCR-8 Analytics (internal) | I75: p95 latency budgets | J75: Backlog | K75: E2E test + demo | M75: none | N75: live
A76: ST-073 | B76: E7 | C76: Telemetry & metrics | D76: Feature-usage heatmap for roadmap decisions | E76: 3 | F76: P2 | G76: S8 | H76: SCR-8 Analytics (internal) | I76: p95 latency budgets | J76: Backlog | K76: Manual QA | M76: none | N76: live
A77: ST-074 | B77: E7 | C77: Telemetry & metrics | D77: Weekly automated metrics email to team | E77: 2 | F77: P2 | G77: S8 | H77: SCR-8 Analytics (internal) | I77: p95 latency budgets | J77: Backlog | K77: Manual QA | M77: none | N77: live
A78: ST-075 | B78: E7 | C78: Telemetry & metrics | D78: Health score computed per account (usage+billing+support) | E78: 5 | F78: P1 | G78: S8 | H78: SCR-8 Analytics (internal) | I78: p95 latency budgets | J78: In progress | K78: Integration test + manual QA | L78: Core engine + 100% tests in full-logic zip 20260910_2106 (E011); UI/platform wiring pending D14 | M78: unit | N78: live
A79: ST-076 | B79: E7 | C79: Telemetry & metrics | D79: Metrics export to CSV/warehouse for founder analysis | E79: 3 | F79: P2 | G79: S8 | H79: SCR-8 Analytics (internal) | I79: p95 latency budgets | J79: Backlog | K79: Manual QA | M79: none | N79: live
A80: ST-077 | B80: E7 | C80: Telemetry & metrics | D80: Alert thresholds configurable (activation drop, error spike, churn signal) | E80: 3 | F80: P2 | G80: S8 | H80: SCR-8 Analytics (internal) | I80: p95 latency budgets | J80: Backlog | K80: Manual QA | M80: none | N80: live
A81: ST-078 | B81: E8 | C81: Onboarding, docs & support | D81: First-run checklist reaches aha-moment in <1 day | E81: 5 | F81: P0 | G81: S5 | H81: SCR-1 / SCR-9 Help | I81: WCAG AA | J81: Backlog | K81: E2E test + demo | M81: none | N81: live
A82: ST-079 | B82: E8 | C82: Onboarding, docs & support | D82: Empty states teach next action on every screen | E82: 3 | F82: P1 | G82: S5 | H82: SCR-1 / SCR-9 Help | I82: WCAG AA | J82: Backlog | K82: Integration test + manual QA | M82: none | N82: live
A83: ST-080 | B83: E8 | C83: Onboarding, docs & support | D83: Help center with 15 launch articles + search | E83: 5 | F83: P1 | G83: S10 | H83: SCR-1 / SCR-9 Help | I83: WCAG AA | J83: In progress | K83: Integration test + manual QA | L83: Draft content complete in launch pack 20260910_2200 (E012); publication at S9-S11 + D-P2 fee decision pending | M83: none (content draft) | N83: external
A84: ST-081 | B84: E8 | C84: Onboarding, docs & support | D84: In-app chat with <4 business-hr first response | E84: 3 | F84: P0 | G84: S10 | H84: SCR-1 / SCR-9 Help | I84: WCAG AA | J84: In progress | K84: E2E test + demo | L84: v016 (20260916_1807): SLA engine + GET /api/support/sla (business-hours breach) — v016 main.test. The in-app chat itself does not exist. | M84: integration | N84: live
A85: ST-082 | B85: E8 | C85: Onboarding, docs & support | D85: In-app review ask after aha-moment (marketplace rating engine) | E85: 3 | F85: P1 | G85: S11 | H85: SCR-1 / SCR-9 Help | I85: WCAG AA | J85: In progress | K85: Integration test + manual QA | L85: Draft content complete in launch pack 20260910_2200 (E012); publication at S9-S11 + D-P2 fee decision pending | M85: none (content draft) | N85: external
A86: ST-083 | B86: E8 | C86: Onboarding, docs & support | D86: Demo video (2 min) + interactive sandbox/demo data mode | E86: 5 | F86: P1 | G86: S10 | H86: SCR-1 / SCR-9 Help | I86: WCAG AA | J86: In progress | K86: Integration test + manual QA | L86: v016 (20260916_1807): Demo data mode: demo_ guard, PgDemoSink writes real rows (V-10), demo accounts never billed — v016. Demo video not made. | M86: integration | N86: live
A87: ST-084 | B87: E8 | C87: Onboarding, docs & support | D87: Status page + incident comms template | E87: 2 | F87: P2 | G87: S10 | H87: SCR-1 / SCR-9 Help | I87: WCAG AA | J87: In progress | K87: Manual QA | L87: Draft content complete in launch pack 20260910_2200 (E012); publication at S9-S11 + D-P2 fee decision pending | M87: none (content draft) | N87: external
A88: ST-085 | B88: EQ | C88: Quality engineering (cross-cutting) | D88: Unit+integration test coverage gate ≥70% on core modules | E88: 5 | F88: P0 | G88: S3 | H88: All surfaces | I88: Per story (coverage/perf/a11y) | J88: In progress | K88: Evidence archived + gate review | L88: v016 (20260916_1807): CI: tsc, 100% coverage, seven review gates (LC-17/LC-18..) — v016. Supersedes the >=70% target (D13). | M88: integration | N88: live
A89: ST-086 | B89: EQ | C89: Quality engineering (cross-cutting) | D89: E2E smoke suite runs on every deploy | E89: 5 | F89: P0 | G89: S4 | H89: All surfaces | I89: Per story (coverage/perf/a11y) | J89: Backlog | K89: Evidence archived + gate review | M89: none | N89: live
A90: ST-087 | B90: EQ | C90: Quality engineering (cross-cutting) | D90: p95 latency budgets defined and monitored per surface | E90: 3 | F90: P0 | G90: S8 | H90: All surfaces | I90: Per story (coverage/perf/a11y) | J90: Backlog | K90: Evidence archived + gate review | M90: none | N90: live
A91: ST-088 | B91: EQ | C91: Quality engineering (cross-cutting) | D91: Load test at 5x expected launch traffic | E91: 5 | F91: P1 | G91: S8 | H91: All surfaces | I91: Per story (coverage/perf/a11y) | J91: In progress | K91: Evidence archived + gate review | L91: v016 (20260916_1807): Load harness against the built app (loadTest) — v016. NOT 5x launch traffic on real infra (RR-P041). | M91: integration | N91: live
A92: ST-089 | B92: EQ | C92: Quality engineering (cross-cutting) | D92: Accessibility WCAG AA pass on primary flows | E92: 3 | F92: P1 | G92: S9 | H92: All surfaces | I92: Per story (coverage/perf/a11y) | J92: Backlog | K92: Evidence archived + gate review | M92: none | N92: live
A93: ST-090 | B93: EQ | C93: Quality engineering (cross-cutting) | D93: Backup + restore drill executed | E93: 3 | F93: P1 | G93: S9 | H93: All surfaces | I93: Per story (coverage/perf/a11y) | J93: In progress | K93: Evidence archived + gate review | L93: v016 (20260916_1807): Backup/restore drill route, fails loudly on shortfall, round-trip on embedded Postgres — v016. Real-infra drill pending (RR-P042). | M93: integration | N93: live
A94: ST-091 | B94: EQ | C94: Quality engineering (cross-cutting) | D94: Chaos test: platform API outage degrades gracefully with user comms | E94: 3 | F94: P2 | G94: S9 | H94: All surfaces | I94: Per story (coverage/perf/a11y) | J94: Backlog | K94: Evidence archived + gate review | M94: none | N94: live
A95: ST-092 | B95: EQ | C95: Quality engineering (cross-cutting) | D95: Zero-downtime deploy verified (blue/green or rolling) | E95: 3 | F95: P2 | G95: S8 | H95: All surfaces | I95: Per story (coverage/perf/a11y) | J95: In progress | K95: Evidence archived + gate review | L95: v016 (20260916_1807): Cutover gate derives migration state from the ledger (P-RR11) — v016. Blue/green not exercised on infra. | M95: integration | N95: live
A96: ST-093 | B96: EL | C96: Launch & listing | D96: Marketplace listing copy A + B variants drafted and reviewed | E96: 3 | F96: P0 | G96: S9 | H96: Listing / LC-8..10 | I96: Platform asset specs | J96: In progress | K96: E2E test + demo | L96: Draft content complete in launch pack 20260910_2200 (E012); publication at S9-S11 + D-P2 fee decision pending | M96: none (content draft) | N96: external
A97: ST-094 | B97: EL | C97: Launch & listing | D97: 5 screenshots + 2-min demo video meet platform asset specs | E97: 5 | F97: P0 | G97: S9 | H97: Listing / LC-8..10 | I97: Platform asset specs | J97: Backlog | K97: E2E test + demo | M97: none | N97: live
A98: ST-095 | B98: EL | C98: Launch & listing | D98: Pricing page/plan matrix published with FAQ | E98: 3 | F98: P0 | G98: S10 | H98: Listing / LC-8..10 | I98: Platform asset specs | J98: In progress | K98: E2E test + demo | L98: Draft content complete in launch pack 20260910_2200 (E012); publication at S9-S11 + D-P2 fee decision pending | M98: none (content draft) | N98: external
A99: ST-096 | B99: EL | C99: Launch & listing | D99: Security/trust page (data handling, subprocessors) live | E99: 3 | F99: P0 | G99: S10 | H99: Listing / LC-8..10 | I99: Platform asset specs | J99: In progress | K99: E2E test + demo | L99: Draft content complete in launch pack 20260910_2200 (E012); publication at S9-S11 + D-P2 fee decision pending | M99: none (content draft) | N99: external
A100: ST-097 | B100: EL | C100: Launch & listing | D100: Submission dry-run against platform checklist by second reviewer | E100: 3 | F100: P0 | G100: S10 | H100: Listing / LC-8..10 | I100: Platform asset specs | J100: Backlog | K100: E2E test + demo | M100: none | N100: live
...

Sheet Sprint_Status_Rollup
A1: SPRINT STATUS ROLLUP — live formulas over Traceability_Matrix (S0 from S0_Task_Board)
A2: Do not edit — recalculates from status columns. Exit criteria from v007 Sprint_Board. v020: S13–S22 added; their stories are unestimated, so % done is by story count.
A3: Sprint | B3: Focus | C3: Stories | D3: Points | E3: Done | F3: Done points | G3: % points done | H3: RAG (manual) | I3: Exit criteria
A4: S0 | B4: Discovery & Design (2 wks) | C4: =COUNTA(S0_Task_Board!$A$4:$A$11) -> 8 | D4: ="—" -> — | E4: =COUNTIF(S0_Task_Board!$E$4:$E$11,"Done") -> 3 | F4: ="—" -> — | G4: =IFERROR(COUNTIF(S0_Task_Board!$E$4:$E$11,"Done")/COUNTA(S0_Task_Board!$A$4:$A$11),0) -> 0.375 | H4: AMBER — in progress | I4: PRD signed off; prototype tested with 5 target users
A5: S1 | B5: Foundation (2 wks) | C5: =COUNTIF(Traceability_Matrix!$G$4:$G$163,"S1") -> 4 | D5: =SUMIF(Traceability_Matrix!$G$4:$G$163,"S1",Traceability_Matrix!$E$4:$E$163) -> 13 | E5: =COUNTIFS(Traceability_Matrix!$G$4:$G$163,"S1",Traceability_Matrix!$J$4:$J$163,"Done") -> 0 | F5: =SUMIFS(Traceability_Matrix!$E$4:$E$163,Traceability_Matrix!$G$4:$G$163,"S1",Traceability_Matrix!$J$4:$J$163,"Done") -> 0 | G5: =IFERROR(SUMIFS(Traceability_Matrix!$E$4:$E$163,Traceability_Matrix!$G$4:$G$163,"S1",Traceability_Matrix!$J$4:$J$163,"Done")/SUMIF(Traceability_Matrix!$G$4:$G$163,"S1",Traceability_Matrix!$E$4:$E$163),0) -> 0 | I5: App installs cleanly in dev store; telemetry firing
A6: S2 | B6: Smart retry scheduler pt 1 | C6: =COUNTIF(Traceability_Matrix!$G$4:$G$163,"S2") -> 6 | D6: =SUMIF(Traceability_Matrix!$G$4:$G$163,"S2",Traceability_Matrix!$E$4:$E$163) -> 29 | E6: =COUNTIFS(Traceability_Matrix!$G$4:$G$163,"S2",Traceability_Matrix!$J$4:$J$163,"Done") -> 0 | F6: =SUMIFS(Traceability_Matrix!$E$4:$E$163,Traceability_Matrix!$G$4:$G$163,"S2",Traceability_Matrix!$J$4:$J$163,"Done") -> 0 | G6: =IFERROR(SUMIFS(Traceability_Matrix!$E$4:$E$163,Traceability_Matrix!$G$4:$G$163,"S2",Traceability_Matrix!$J$4:$J$163,"Done")/SUMIF(Traceability_Matrix!$G$4:$G$163,"S2",Traceability_Matrix!$E$4:$E$163),0) -> 0 | I6: Smart retry happy path demoable
A7: S3 | B7: Smart retry pt 2 + Dunning start | C7: =COUNTIF(Traceability_Matrix!$G$4:$G$163,"S3") -> 11 | D7: =SUMIF(Traceability_Matrix!$G$4:$G$163,"S3",Traceability_Matrix!$E$4:$E$163) -> 47 | E7: =COUNTIFS(Traceability_Matrix!$G$4:$G$163,"S3",Traceability_Matrix!$J$4:$J$163,"Done") -> 0 | F7: =SUMIFS(Traceability_Matrix!$E$4:$E$163,Traceability_Matrix!$G$4:$G$163,"S3",Traceability_Matrix!$J$4:$J$163,"Done") -> 0 | G7: =IFERROR(SUMIFS(Traceability_Matrix!$E$4:$E$163,Traceability_Matrix!$G$4:$G$163,"S3",Traceability_Matrix!$J$4:$J$163,"Done")/SUMIF(Traceability_Matrix!$G$4:$G$163,"S3",Traceability_Matrix!$E$4:$E$163),0) -> 0 | I7: Smart retry complete with tests; Dunning skeleton
A8: S4 | B8: Dunning sequences (email/WA) | C8: =COUNTIF(Traceability_Matrix!$G$4:$G$163,"S4") -> 9 | D8: =SUMIF(Traceability_Matrix!$G$4:$G$163,"S4",Traceability_Matrix!$E$4:$E$163) -> 34 | E8: =COUNTIFS(Traceability_Matrix!$G$4:$G$163,"S4",Traceability_Matrix!$J$4:$J$163,"Done") -> 0 | F8: =SUMIFS(Traceability_Matrix!$E$4:$E$163,Traceability_Matrix!$G$4:$G$163,"S4",Traceability_Matrix!$J$4:$J$163,"Done") -> 0 | G8: =IFERROR(SUMIFS(Traceability_Matrix!$E$4:$E$163,Traceability_Matrix!$G$4:$G$163,"S4",Traceability_Matrix!$J$4:$J$163,"Done")/SUMIF(Traceability_Matrix!$G$4:$G$163,"S4",Traceability_Matrix!$E$4:$E$163),0) -> 0 | I8: MVP loop usable end-to-end internally
A9: S5 | B9: Save-offer engine + alpha hardening | C9: =COUNTIF(Traceability_Matrix!$G$4:$G$163,"S5") -> 12 | D9: =SUMIF(Traceability_Matrix!$G$4:$G$163,"S5",Traceability_Matrix!$E$4:$E$163) -> 50 | E9: =COUNTIFS(Traceability_Matrix!$G$4:$G$163,"S5",Traceability_Matrix!$J$4:$J$163,"Done") -> 0 | F9: =SUMIFS(Traceability_Matrix!$E$4:$E$163,Traceability_Matrix!$G$4:$G$163,"S5",Traceability_Matrix!$J$4:$J$163,"Done") -> 0 | G9: =IFERROR(SUMIFS(Traceability_Matrix!$E$4:$E$163,Traceability_Matrix!$G$4:$G$163,"S5",Traceability_Matrix!$J$4:$J$163,"Done")/SUMIF(Traceability_Matrix!$G$4:$G$163,"S5",Traceability_Matrix!$E$4:$E$163),0) -> 0 | I9: Internal alpha: team dogfoods daily
A10: S6 | B10: Billing + Recovery analytics | C10: =COUNTIF(Traceability_Matrix!$G$4:$G$163,"S6") -> 13 | D10: =SUMIF(Traceability_Matrix!$G$4:$G$163,"S6",Traceability_Matrix!$E$4:$E$163) -> 60 | E10: =COUNTIFS(Traceability_Matrix!$G$4:$G$163,"S6",Traceability_Matrix!$J$4:$J$163,"Done") -> 0 | F10: =SUMIFS(Traceability_Matrix!$E$4:$E$163,Traceability_Matrix!$G$4:$G$163,"S6",Traceability_Matrix!$J$4:$J$163,"Done") -> 0 | G10: =IFERROR(SUMIFS(Traceability_Matrix!$E$4:$E$163,Traceability_Matrix!$G$4:$G$163,"S6",Traceability_Matrix!$J$4:$J$163,"Done")/SUMIF(Traceability_Matrix!$G$4:$G$163,"S6",Traceability_Matrix!$E$4:$E$163),0) -> 0 | I10: Can charge a test customer; up/downgrade paths work
A11: S7 | B11: Private beta (design partners) | C11: =COUNTIF(Traceability_Matrix!$G$4:$G$163,"S7") -> 5 | D11: =SUMIF(Traceability_Matrix!$G$4:$G$163,"S7",Traceability_Matrix!$E$4:$E$163) -> 15 | E11: =COUNTIFS(Traceability_Matrix!$G$4:$G$163,"S7",Traceability_Matrix!$J$4:$J$163,"Done") -> 0 | F11: =SUMIFS(Traceability_Matrix!$E$4:$E$163,Traceability_Matrix!$G$4:$G$163,"S7",Traceability_Matrix!$J$4:$J$163,"Done") -> 0 | G11: =IFERROR(SUMIFS(Traceability_Matrix!$E$4:$E$163,Traceability_Matrix!$G$4:$G$163,"S7",Traceability_Matrix!$J$4:$J$163,"Done")/SUMIF(Traceability_Matrix!$G$4:$G$163,"S7",Traceability_Matrix!$E$4:$E$163),0) -> 0 | I11: 3+ partners active weekly; NPS pulse >30
A12: S8 | B12: Beta iteration + Slack alerts | C12: =COUNTIF(Traceability_Matrix!$G$4:$G$163,"S8") -> 22 | D12: =SUMIF(Traceability_Matrix!$G$4:$G$163,"S8",Traceability_Matrix!$E$4:$E$163) -> 87 | E12: =COUNTIFS(Traceability_Matrix!$G$4:$G$163,"S8",Traceability_Matrix!$J$4:$J$163,"Done") -> 0 | F12: =SUMIFS(Traceability_Matrix!$E$4:$E$163,Traceability_Matrix!$G$4:$G$163,"S8",Traceability_Matrix!$J$4:$J$163,"Done") -> 0 | G12: =IFERROR(SUMIFS(Traceability_Matrix!$E$4:$E$163,Traceability_Matrix!$G$4:$G$163,"S8",Traceability_Matrix!$J$4:$J$163,"Done")/SUMIF(Traceability_Matrix!$G$4:$G$163,"S8",Traceability_Matrix!$E$4:$E$163),0) -> 0 | I12: Beta cohort WoW retention >60%
A13: S9 | B13: Marketplace review prep | C13: =COUNTIF(Traceability_Matrix!$G$4:$G$163,"S9") -> 7 | D13: =SUMIF(Traceability_Matrix!$G$4:$G$163,"S9",Traceability_Matrix!$E$4:$E$163) -> 30 | E13: =COUNTIFS(Traceability_Matrix!$G$4:$G$163,"S9",Traceability_Matrix!$J$4:$J$163,"Done") -> 0 | F13: =SUMIFS(Traceability_Matrix!$E$4:$E$163,Traceability_Matrix!$G$4:$G$163,"S9",Traceability_Matrix!$J$4:$J$163,"Done") -> 0 | G13: =IFERROR(SUMIFS(Traceability_Matrix!$E$4:$E$163,Traceability_Matrix!$G$4:$G$163,"S9",Traceability_Matrix!$J$4:$J$163,"Done")/SUMIF(Traceability_Matrix!$G$4:$G$163,"S9",Traceability_Matrix!$E$4:$E$163),0) -> 0 | I13: Review submission accepted into queue
A14: S10 | B14: Review remediation + docs | C14: =COUNTIF(Traceability_Matrix!$G$4:$G$163,"S10") -> 7 | D14: =SUMIF(Traceability_Matrix!$G$4:$G$163,"S10",Traceability_Matrix!$E$4:$E$163) -> 24 | E14: =COUNTIFS(Traceability_Matrix!$G$4:$G$163,"S10",Traceability_Matrix!$J$4:$J$163,"Done") -> 0 | F14: =SUMIFS(Traceability_Matrix!$E$4:$E$163,Traceability_Matrix!$G$4:$G$163,"S10",Traceability_Matrix!$J$4:$J$163,"Done") -> 0 | G14: =IFERROR(SUMIFS(Traceability_Matrix!$E$4:$E$163,Traceability_Matrix!$G$4:$G$163,"S10",Traceability_Matrix!$J$4:$J$163,"Done")/SUMIF(Traceability_Matrix!$G$4:$G$163,"S10",Traceability_Matrix!$E$4:$E$163),0) -> 0 | I14: Marketplace approval obtained
A15: S11 | B15: Launch | C15: =COUNTIF(Traceability_Matrix!$G$4:$G$163,"S11") -> 3 | D15: =SUMIF(Traceability_Matrix!$G$4:$G$163,"S11",Traceability_Matrix!$E$4:$E$163) -> 8 | E15: =COUNTIFS(Traceability_Matrix!$G$4:$G$163,"S11",Traceability_Matrix!$J$4:$J$163,"Done") -> 0 | F15: =SUMIFS(Traceability_Matrix!$E$4:$E$163,Traceability_Matrix!$G$4:$G$163,"S11",Traceability_Matrix!$J$4:$J$163,"Done") -> 0 | G15: =IFERROR(SUMIFS(Traceability_Matrix!$E$4:$E$163,Traceability_Matrix!$G$4:$G$163,"S11",Traceability_Matrix!$J$4:$J$163,"Done")/SUMIF(Traceability_Matrix!$G$4:$G$163,"S11",Traceability_Matrix!$E$4:$E$163),0) -> 0 | I15: First 10 installs; first 3 reviews; activation >40%
A16: S12 | B16: Iterate & scale decision | C16: =COUNTIF(Traceability_Matrix!$G$4:$G$163,"S12") -> 1 | D16: =SUMIF(Traceability_Matrix!$G$4:$G$163,"S12",Traceability_Matrix!$E$4:$E$163) -> 2 | E16: =COUNTIFS(Traceability_Matrix!$G$4:$G$163,"S12",Traceability_Matrix!$J$4:$J$163,"Done") -> 0 | F16: =SUMIFS(Traceability_Matrix!$E$4:$E$163,Traceability_Matrix!$G$4:$G$163,"S12",Traceability_Matrix!$J$4:$J$163,"Done") -> 0 | G16: =IFERROR(SUMIFS(Traceability_Matrix!$E$4:$E$163,Traceability_Matrix!$G$4:$G$163,"S12",Traceability_Matrix!$J$4:$J$163,"Done")/SUMIF(Traceability_Matrix!$G$4:$G$163,"S12",Traceability_Matrix!$E$4:$E$163),0) -> 0 | I16: Growth model doc with CAC/LTV first estimates
A17: S13 | B17: Money correctness (BLOCKING) | C17: =COUNTIF(Traceability_Matrix!$G$4:$G$163,"S13") -> 8 | D17: ="unestimated" -> unestimated | E17: =COUNTIFS(Traceability_Matrix!$G$4:$G$163,"S13",Traceability_Matrix!$J$4:$J$163,"Done") -> 0 | F17: ="—" -> — | G17: =IFERROR(COUNTIFS(Traceability_Matrix!$G$4:$G$163,"S13",Traceability_Matrix!$J$4:$J$163,"Done")/COUNTIF(Traceability_Matrix!$G$4:$G$163,"S13"),0) -> 0 | H17: AMBER — built to integration; contract/live evidence needs D14 | I17: All six money invariants green as gates; P-RR01..05 regression-tested (reached at integration in v016)
A18: S14 | B18: Stripe platform integration (DEC-04) | C18: =COUNTIF(Traceability_Matrix!$G$4:$G$163,"S14") -> 7 | D18: ="unestimated" -> unestimated | E18: =COUNTIFS(Traceability_Matrix!$G$4:$G$163,"S14",Traceability_Matrix!$J$4:$J$163,"Done") -> 0 | F18: ="—" -> — | G18: =IFERROR(COUNTIFS(Traceability_Matrix!$G$4:$G$163,"S14",Traceability_Matrix!$J$4:$J$163,"Done")/COUNTIF(Traceability_Matrix!$G$4:$G$163,"S14"),0) -> 0 | H18: RED — blocked (DEC-04) | I18: First story Done with live Stripe evidence (RR-P015)
A19: S15 | B19: Durability and the work loop | C19: =COUNTIF(Traceability_Matrix!$G$4:$G$163,"S15") -> 6 | D19: ="unestimated" -> unestimated | E19: =COUNTIFS(Traceability_Matrix!$G$4:$G$163,"S15",Traceability_Matrix!$J$4:$J$163,"Done") -> 0 | F19: ="—" -> — | G19: =IFERROR(COUNTIFS(Traceability_Matrix!$G$4:$G$163,"S15",Traceability_Matrix!$J$4:$J$163,"Done")/COUNTIF(Traceability_Matrix!$G$4:$G$163,"S15"),0) -> 0 | H19: AMBER — 5 of 6 built to integration (worker topology open) | I19: No in-process state required for correctness
A20: S16 | B20: Merchant surface (UI extension) | C20: =COUNTIF(Traceability_Matrix!$G$4:$G$163,"S16") -> 6 | D20: ="unestimated" -> unestimated | E20: =COUNTIFS(Traceability_Matrix!$G$4:$G$163,"S16",Traceability_Matrix!$J$4:$J$163,"Done") -> 0 | F20: ="—" -> — | G20: =IFERROR(COUNTIFS(Traceability_Matrix!$G$4:$G$163,"S16",Traceability_Matrix!$J$4:$J$163,"Done")/COUNTIF(Traceability_Matrix!$G$4:$G$163,"S16"),0) -> 0 | H20: RED — UI blocked (DEC-04); 2 wiring stories built | I20: Merchant can see, configure and dispute in the Dashboard
A21: S17 | B21: Attribution defensibility and incrementality | C21: =COUNTIF(Traceability_Matrix!$G$4:$G$163,"S17") -> 5 | D21: ="unestimated" -> unestimated | E21: =COUNTIFS(Traceability_Matrix!$G$4:$G$163,"S17",Traceability_Matrix!$J$4:$J$163,"Done") -> 0 | F21: ="—" -> — | G21: =IFERROR(COUNTIFS(Traceability_Matrix!$G$4:$G$163,"S17",Traceability_Matrix!$J$4:$J$163,"Done")/COUNTIF(Traceability_Matrix!$G$4:$G$163,"S17"),0) -> 0 | H21: RED — decisions 2 and 4 | I21: Incrementality measured and disclosed
A22: S18 | B22: Deliverability and channel compliance | C22: =COUNTIF(Traceability_Matrix!$G$4:$G$163,"S18") -> 4 | D22: ="unestimated" -> unestimated | E22: =COUNTIFS(Traceability_Matrix!$G$4:$G$163,"S18",Traceability_Matrix!$J$4:$J$163,"Done") -> 0 | F22: ="—" -> — | G22: =IFERROR(COUNTIFS(Traceability_Matrix!$G$4:$G$163,"S18",Traceability_Matrix!$J$4:$J$163,"Done")/COUNTIF(Traceability_Matrix!$G$4:$G$163,"S18"),0) -> 0 | H22: RED — blocked | I22: Inbox placement and consent evidenced
A23: S19 | B23: Observability and SRE | C23: =COUNTIF(Traceability_Matrix!$G$4:$G$163,"S19") -> 6 | D23: ="unestimated" -> unestimated | E23: =COUNTIFS(Traceability_Matrix!$G$4:$G$163,"S19",Traceability_Matrix!$J$4:$J$163,"Done") -> 0 | F23: ="—" -> — | G23: =IFERROR(COUNTIFS(Traceability_Matrix!$G$4:$G$163,"S19",Traceability_Matrix!$J$4:$J$163,"Done")/COUNTIF(Traceability_Matrix!$G$4:$G$163,"S19"),0) -> 0 | H23: AMBER — redaction, tamper-evident audit, retention built; SRE work open | I23: SLOs published; restore drilled on real infra
A24: S20 | B24: Enterprise security and compliance | C24: =COUNTIF(Traceability_Matrix!$G$4:$G$163,"S20") -> 6 | D24: ="unestimated" -> unestimated | E24: =COUNTIFS(Traceability_Matrix!$G$4:$G$163,"S20",Traceability_Matrix!$J$4:$J$163,"Done") -> 0 | F24: ="—" -> — | G24: =IFERROR(COUNTIFS(Traceability_Matrix!$G$4:$G$163,"S20",Traceability_Matrix!$J$4:$J$163,"Done")/COUNTIF(Traceability_Matrix!$G$4:$G$163,"S20"),0) -> 0 | H24: AMBER — revocation, headers, rate limits, row-level security built | I24: Pen test triaged; isolation suite green
A25: S21 | B25: Marketplace launch | C25: =COUNTIF(Traceability_Matrix!$G$4:$G$163,"S21") -> 5 | D25: ="unestimated" -> unestimated | E25: =COUNTIFS(Traceability_Matrix!$G$4:$G$163,"S21",Traceability_Matrix!$J$4:$J$163,"Done") -> 0 | F25: ="—" -> — | G25: =IFERROR(COUNTIFS(Traceability_Matrix!$G$4:$G$163,"S21",Traceability_Matrix!$J$4:$J$163,"Done")/COUNTIF(Traceability_Matrix!$G$4:$G$163,"S21"),0) -> 0 | H25: RED — decisions 2 and 3 | I25: Approved listing
A26: S22 | B26: Method upgrade (continuous from S13) | C26: =COUNTIF(Traceability_Matrix!$G$4:$G$163,"S22") -> 7 | D26: ="unestimated" -> unestimated | E26: =COUNTIFS(Traceability_Matrix!$G$4:$G$163,"S22",Traceability_Matrix!$J$4:$J$163,"Done") -> 0 | F26: ="—" -> — | G26: =IFERROR(COUNTIFS(Traceability_Matrix!$G$4:$G$163,"S22",Traceability_Matrix!$J$4:$J$163,"Done")/COUNTIF(Traceability_Matrix!$G$4:$G$163,"S22"),0) -> 0 | H26: AMBER — mutation testing + 4 gates built; contract tests and external review open | I26: Mutation score >= 85% on the money path; contract tests in CI
A27: TOTAL | B27: (S1-S22 stories; S13-S22 unestimated, so % by points covers S1-S12) | C27: =SUM(C5:C26) -> 160 | D27: =SUM(D5:D16) -> 399 | E27: =SUM(E5:E26) -> 0 | F27: =SUM(F5:F16) -> 0 | G27: =IFERROR(F27/D27,0) -> 0

Sheet RAID_Carryover
A1: RAID CARRYOVER — live register for RevRescue execution
A2: Seeded from v007 Risk_Register + v002 RAID + S0 findings. Review at every sprint exit.
A3: ID | B3: Type | C3: Item | D3: Impact/Likelihood | E3: Mitigation / response | F3: Status
A4: R1 | B4: Risk | C4: Stripe builds native smart-retry/dunning upgrades | D4: High / High | E4: Save-offer + WhatsApp channel + analytics depth beyond native (v007) | F4: Open
A5: R2 | B5: Risk | C5: Outcome-fee attribution disputes | D5: Med / Med | E5: Transparent calculator + conservative attribution + audit log (LC-5, LC-6) | F5: Open
A6: R3 | B6: Risk | C6: Stripe Apps platform maturity (API/UI limits) | D6: Med / Med | E6: Web-app fallback surface outside Dashboard | F6: Open
A7: R4 | B7: Risk | C7: Solo last-mile overload (portfolio-level, v002) | D7: High / Med | E7: R1 serial builds; R4 ops floor only after LIVE | F7: Open
A8: R5 | B8: Finding (S0) | C8: April 2026 Stripe Apps agreement: provisioning sales must use Stripe Payments (initial txn; subsequent independent billing exempt); FULL pricing disclosure incl. usage/outcome rates mandatory; pricing must align with off-marketplace pricing | D8: High / Certain | E8: Design outcome-billing (% of recovered) as declared usage-based pricing from day 1; LC-6 transparency page doubles as review artifact; read full agreement text at stripe.com/legal/apps during T-01 | F8: Closed — full agreement read 10 Sep 20:18 (E005); obligations distributed to R8/R9, LC-12/LC-13, D-P1
A9: R6 | B9: Dependency | C9: 5 discovery-interview users must be sourced (T-02) | D9: Med / — | E9: Senthil network + Stripe-community outreach; blocks S0 exit | F9: Open
A10: R7 | B10: Assumption | C10: v007 stack assumption (TS/Node, React, Postgres) survives Stripe Apps sandbox constraints (React UI extension) | D10: Med / — | E10: Confirm during T-01/T-04 against current Stripe Apps SDK docs | F10: Open
A11: R8 | B11: Constraint | C11: §13 Apps Agreement: Stripe Apps storage may hold NO Personal Data (beyond listing needs) or health data | D11: High / Certain | E11: Architecture rule: all customer, payment-status and dunning data in own Postgres backend; Stripe Apps storage limited to non-personal config. Enforce in S1 foundation stories. | F11: Open — binds S1+
A12: R9 | B12: Obligation | C12: §11 breach notice to stripe-apps-security@stripe.com within 72 hrs; §14.3 export self-classification EAR99/5D992; §15 30-day removal notice; §27 annual Compliance Review; §32 terms may change on 30-day notice | D12: Med / Certain | E12: LC-12 + LC-13 added to gate; incident-mgmt program folded into ST-098 runbook; quarterly terms-recheck added to R4 ops floor | F12: Open
A13: D-P1 | B13: Decision needed (Senthil) | C13: Sell via Stripe Provisioning Services (Part III, public preview: PSCo facilitates indirect taxes in Facilitator Countries but adds PTC/self-billing/pricing-schema obligations) OR list-only + own Stripe billing (Part III out of scope; v007 fee-note assumption; self-managed taxes) | D13: High / — | E13: Recommendation prepared: START list-only + own billing for launch simplicity (matches v007 model and D8 low-friction rationale); revisit provisioning post-gate if tax admin becomes material. Decide with T-06. | F13: Open — Senthil
A14: D13 | B14: Decision (Senthil, LOCKED) | C14: T-02/T-05 (5-user discovery + prototype test) PARKED for now; development proceeds directly; ALL code carries 100% automation test coverage (statements/branches/functions/lines), enforced in build. Supersedes ST-085 (>=70%). S0 exit criteria amended accordingly; PRD operates as working baseline pending T-06. | D14: High / — | E14: Coverage gate wired into npm test (c8 --100 --check-coverage — build fails below 100%). Discovery questions preserved in PRD §11 + wireframe annotations for when interviews resume. To be appended to chatlog Decision_Log at its next version. | F14: LOCKED 20:41
... A76: L-RR23 | B76: Lesson | C76: Mutation testing found seven assertions missing from a suite already at 100% coverage and passing a 400-history property gate. | D76: — | E76: Keep the mutation gate in CI; read survivors, do not just chase the score. | F76: Logged

Sheet Gate_Checklist
A1: COMPLETION GATE (D7) — RevRescue is DONE only when every row is Done
A2: R2: code complete counts for nothing. Gate decision = Senthil on evidence (R5/D10). LC items from v007 Launch_Checklist.
A3: ID | B3: Gate item | C3: Source | D3: Status
A4: G-01 | B4: App LISTED on Stripe App Marketplace (approved + published) | C4: D7 / R2 | D4: Open
A5: G-02 | B5: 10 PAYING installs from strangers | C5: D7 / R2 | D5: Open
A6: G-03 | B6: S12 kill criteria evaluated with evidence pack | C6: D7 / R3 | D6: Open
A7: G-04 | B7: Kill/continue decision recorded by Senthil | C7: R5 / D10 | D7: Open
A8: G-05 | B8: On CONTINUE: TeleField (rank 2) build authorised; RevRescue enters R4 ops floor | C8: N4 / R1 | D8: Open
A9: LC-1 | B9: Stripe app manifest + restricted API key scopes | C9: v007 LC | D9: Open
A10: LC-2 | B10: No-card-data architecture attestation documented | C10: v007 LC | D10: Open
A11: LC-3 | B11: UI extension guidelines compliance (React sandbox) | C11: v007 LC | D11: Open
A12: LC-4 | B12: Webhook resilience: retry + dedupe + replay protection | C12: v007 LC | D12: Open
A13: LC-5 | B13: Recovery attribution logic audited (no double-counting) | C13: v007 LC | D13: Open
A14: LC-6 | B14: Outcome-billing transparency page (now ALSO a review requirement — R5 finding) | C14: v007 LC + S0 | D14: Open
... A38: LC-30 | B38: Dunning test mode proven to send nothing to a live channel (V-14) | C38: LC-11 / V-14 | D38: Done
