Workbook

Sheet Version_Control
A1: VERSION CONTROL — DocMerge Pro
A3: Version | B3: Date | C3: Author | D3: Change | E3: Status
A4: v001-v004 | B4: 2026-09-05 | C4: Claude for Senthil/KP | D4: Lineage: marketplace master (868 entries) -> portfolio plan (12 products) -> wave-1 (RetainKit/ShiftDesk/EngageOS, v005) -> this product selected for wave-3 | E4: Released
A5: v007 | B5: 2026-09-05 19:50 | C5: Claude for Senthil/KP | D5: Full product workbook for DocMerge Pro on Google Workspace Marketplace: spec, screen inventory, 100+ story backlog, live sprint board, 18-month financial model (editable assumptions), GTM execution tasks, platform launch checklist, metric targets, risk register | E5: Released
A6: v008 | B6: 2026-09-10 22:17 | C6: Claude for Senthil/KP | D6: Sprint_Tracker_Log + Traceability_Matrix sheets added. S1 Foundation executed under D13 (100% automation coverage gate; S0 discovery interviews parked): ST-051/052/055/056 built in TypeScript (docmerge-pro-s1), 37 automated tests, 100% stmt/branch/func/line coverage, tsc strict clean. Backlog statuses updated; Sprint_Board live counts reflect S1 Done=4. | E6: Released
A7: v009 | B7: 2026-09-10 22:23 | C7: Claude for Senthil/KP | D7: S2 executed under D13: ST-001/002/003/004 (Template designer part 1 — defaults, happy-path render, rules/conditions, platform-error mapping + retry/backoff) + ST-053 (re-install restore within retention window) + ST-054 (owner/admin/member permission matrix enforced). Suite now 9 test files / 101 tests, 100% stmt/branch/func/line, tsc strict clean. Sprint_Board S2 Done=6. | E7: Released
A8: v010 | B8: 2026-09-10 22:29 | C8: Claude for Senthil/KP | D8: S3 executed under D13: Template designer part 2 (ST-005 sidebar surface end-to-end, ST-006 metrics/trends, ST-007 audit logging incl. denied attempts, ST-008 pause without data loss, ST-009 CSV + competitor importer, ST-010 notifications with per-type mute) + Batch generate skeleton (ST-011..014: defaults, per-row happy path, row rules, error/retry paths) + ST-085 closed as superseded by D13 at 100%. Defect found by the gate and fixed: withRetry was masking validation errors behind a generic platform message. Suite 13 files / 150 tests, 100% all metrics. | E8: Released
A9: v011 | B9: 2026-09-10 22:52 | C9: Claude for Senthil/KP | D9: S4 executed under D13: Batch part 2 (ST-015 batch sidebar end-to-end, ST-016 batch metrics/trends, ST-017 governed runner with allow/deny audit, ST-018 job pause without data loss, ST-019 row-data CSV + competitor import, ST-020 batch notifications with mute) + ST-071 activation funnel dashboard (install->setup->aha->habit with conversions) + ST-072 error tracking with release tagging and spike alerts (re-armable) + ST-086 E2E smoke suite gating the deploy job in .github/workflows/ci.yml. Suite 16 files / 180 tests, 100% all metrics, tsc strict clean. Sprint_Board S4 Done=9. | E9: Released
A10: v012 | B10: 2026-09-10 23:03 | C10: Claude for Senthil/KP | D10: S5 executed under D13: E-sign requests full module (ST-021 defaults, ST-022 sequential/parallel lifecycle draft->sent->partially_signed->completed/declined/expired, ST-023 validated rules incl. domain allow-lists, ST-024 delivery retry with mapped errors and no half-sent state, ST-025 sidebar create->send->track, ST-026 metrics, ST-027 allow/deny audit, ST-028 pause preserving signatures, ST-029 signer CSV + competitor import, ST-030 mute-aware notifications) + ST-078 first-run checklist with <1-day aha budget + ST-079 empty states for all 9 screens. Suite 18 files / 217 tests, 100% all metrics. Companion tracker file v001 opened (claude_v001_docmerge_pro_sprint_tracker_traceability_20260910_2303.xlsx). | E10: Released
A11: v013 | B11: 2026-09-11 08:20 | C11: Claude for Senthil/KP | D11: S6 executed under D13: Auto-file to Drive full module (ST-031 one-screen defaults, ST-032 pattern-driven filing with built-in {{template}}/{{row}}/{{yyyy}}/{{mm}} tokens and named missing-token errors, ST-033 first-match routing rules, ST-034 retry/backoff with mapped errors, ST-035 sidebar file-last-batch flow, ST-036 filing metrics, ST-037 allow/deny audit, ST-038 pause, ST-039 routing-rule CSV + competitor import, ST-040 filing notifications; conflict policies rename/overwrite/skip with first-free-number rename) + Billing (ST-057 no-card 14-day trial with honest banner, ST-058 mid-cycle proration charge/credit verified to the cent, ST-059 marketplace-vs-Stripe provider routing + 1/3/7-day dunning, grace, downgrade-with-data). Suite 21 files / 264 tests, 100% all metrics. Tracker rolled to v002. | E11: Released
A12: v014 | B12: 2026-09-13 09:55 | C12: Claude for Senthil/KP | D12: S7 executed under D13: ST-060 dunning UX (3 emails on 1/3/7-day schedule, 7-day grace, then READ-ONLY mode — corrects S6 ST-059 which ended in downgrade-to-free; read-only retains plan and data, strictly less destructive), ST-061 plan limits with 80%/100% upgrade prompts across documents/templates/seats, ST-062 invoices with GST/VAT incl. B2B reverse charge and downloadable CSV receipts (closes the tax gap flagged at S6), ST-063 cancellation with reason-matched save-offer (offered once) + exit survey + access to period end, ST-064 machine-audited scope-to-feature least-privilege mapping + generated SCOPE_NARRATIVE.md for the OAuth/CASA pack. Suite 23 files / 305 tests, 100% all metrics. Tracker v003. | E12: Released
A13: v015 | B13: 2026-09-13 10:22 | C13: Claude for Senthil/KP | D13: S8 executed under D13 — largest sprint, 22 stories / 87 pts: Form-triggered generation ST-041..050 (submission pipeline with built-in redelivery dedupe, conditions, failure-as-result so the webhook stays up, sidebar activity feed, metrics, audit, pause, field-map import, notifications); Compliance ST-065 validated data-flow + retention policy (DATA_FLOW_AND_RETENTION.md published), ST-066 deployment posture verifier (encryption at rest, TLS floor, vault-only secrets), ST-067 hash-chained admin audit log detecting edits and deletions, ST-070 circuit breaker with half-open recovery; Analytics ST-073..077 (heatmap with unused-feature list, weekly digest, explained health score, CSV/warehouse export, configurable alert thresholds); QE ST-087 p95 budgets per surface, ST-088 deterministic 5x load test in CI, ST-092 blue/green deploy with pre-cutover health gate and verified rollback. Suite 26 files / 385 tests, 100% all metrics. Tracker v004. | E13: Released
A14: v016 | B14: 2026-09-13 10:35 | C14: Claude for Senthil/KP | D14: S9 executed under D13: ST-069 self-serve export + owner-only deletion with cancellable 7-day grace, ST-089 WCAG AA audit (contrast maths, accessible names, keyboard, focus, target size) with the shipped palette passing, ST-090 restore-drill harness verifying contents as well as RTO/RPO, ST-091 chaos degradation proving every dependency outage leaves the product usable with an explaining message, ST-093 two listing variants on genuinely different angles + a copy reviewer that flags risky claims, ST-094 asset-spec validator + 5-screenshot plan. ST-068 is PARTIAL, not Done: the evidence pack is built and published (SECURITY_EVIDENCE_PACK.md, 6 of 9 controls verified in code) but a penetration test is a third-party activity — readyForSubmission stays false until the external report is attached. Suite 28 files / 432 tests, 100% all metrics. Tracker v005. | E14: Released
... A19: v021 | B19: 2026-09-13 11:16 | C19: Claude for Senthil/KP | D19: S12 growth model FRAME built (ST-095-adjacent; the S12 exit criterion, marked In progress not Done because the exit asks for CAC/LTV ESTIMATES and estimates without a cohort are assumptions): src/growthModel.ts restates the 18-month model as unit economics — lifetime, LTV, fully-loaded CAC that charges free-tier support against each conversion (~17 installs served per paying customer at 6%), payback, and a verdict that distinguishes a healthy ratio with slow payback from a marginal one. Three scenarios, sensitivity ranking, and a measurement plan pointing each assumption at instrumentation that already exists. FINDING: churn outranks conversion as the lever to measure first — intuition usually reaches for conversion. Published as GROWTH_MODEL.md. Suite 34 files / 589 tests, 100% all metrics. | E19: Released
A20: v022 | D20: PLANNED: live-evidence log only. No unblocked work remains. | E20: Planned
A21: v022 | B21: 2026-09-13 11:21 | C21: Claude for Senthil/KP | D21: ST-068 vendor outreach pack written (PENTEST_OUTREACH.md): a ready-to-send email that quotes from the written brief rather than requiring a discovery call, vendor shortlist criteria, and a quote-comparison rubric. External-facing copy is company-agnostic per standing instruction. FINDING carried into the pack: LEAD TIME, not price, is the binding constraint — it sits on the critical path beside CASA and the two waits can run in parallel, so both should be booked in the same week. No code change; suite unchanged at 589 tests / 100%. | E21: Released
A22: v023 | D22: PLANNED: live-evidence log only. All preparable work is complete; every remaining item needs Senthil or a third party. | E22: Planned
A23: v023 | B23: 2026-09-13 11:24 | C23: Claude for Senthil/KP | D23: COLD REVIEW PASS 1 — DocMerge first adversarial review, run because portfolio memory shows every sibling found real defects after declaring code-complete (TeleField L-T1). NINE findings in code already at 100% coverage, five CRITICAL. FIXED with regressions: DM-F02 read-only mode enforced nowhere (published behaviour absent from the product), DM-F03 plan limits enforced nowhere (published limits decorative), DM-F04 OAuth install had no CSRF state, DM-F05 webhooks entirely unauthenticated (a forged POST could revoke tokens and schedule deletion for any account), DM-F06 no production backoff existed at all. OPEN: DM-F01 CRITICAL no HTTP app exists behind any route, DM-F07 caller-declared identity, DM-F08 eleven unbounded ledgers, DM-F09 deletion has no implementation behind it. New Review_Findings sheet. 35 suites / 616 tests at 100%. The previous "code phase complete" claim was premature. | E23: Released
A24: v024 | D24: PLANNED: cold-review pass 2 — build the HTTP app (DM-F01), close DM-F07/F08/F09, then re-sweep. | E24: Planned
A25: v024 | B25: 2026-09-13 11:31 | C25: Claude for Senthil/KP | D25: DM-F01 and DM-F07 CLOSED — the two critical findings left open by cold-review pass 1. A real HTTP application now exists: framework-free router, 7 routes wired to the existing services, src/server.ts with npm start, and a readiness check that refuses to listen on a misconfigured environment. Identity is no longer caller-declared: HMAC-signed sessions carry account and role, so editing a role in a token fails verification and a session for one account is refused against another. Every mutating route is authenticated AND passes the entitlement gate, so read-only mode and plan limits are enforced on the wire rather than in principle; reads stay open in read-only mode. Server BOOTED FOR REAL and exercised over HTTP (healthz 200, unsigned webhook 401, unauthenticated route 401, unknown route 404) — the siblings taught that compiling is not running. 36 suites / 650 tests at 100%. Remaining from pass 1: DM-F08 unbounded ledgers, DM-F09 deletion has no implementation. | E25: Released
A26: v025 | D26: PLANNED: close DM-F08 (bounded ledgers) and DM-F09 (purge registry + schema), then cold-review pass 2 over the new HTTP layer — siblings found new surfaces inherit old blind spots (L-OC4). | E26: Planned
A27: v025 | B27: 2026-09-13 11:37 | C27: Claude for Senthil/KP | D27: PASS 1 CLOSED + PASS 2 COMPLETE. DM-F08 fixed: all 11 unbounded ledgers now FIFO-bounded with eviction counted rather than silent; the hash-chained admin audit needed a post-eviction chain anchor so verifyChain reports truncation instead of breaking. DM-F09 fixed: PurgeRegistry over 16 stores with a build-failing registration check, evidence receipts, incomplete-purge honesty — plus the database schema that never existed (3 migrations, ON DELETE CASCADE on every account-scoped table, npm run migrate). PASS 2 over the new HTTP layer found four more, all fixed: DM-F10 uncapped request body (memory exhaustion on an open port), DM-F11 abandoned OAuth states accumulating because sweep() was never called — the same built-but-never-wired class as F02/F03, DM-F12 no rate limiting anywhere, DM-F13 /healthz leaking the build version anonymously. Server booted and all four verified over real HTTP. 40 suites / 691 tests at 100%. All 13 cold-review findings now closed. | E27: Released
A28: v026 | D28: PLANNED: live-evidence log. Cold review complete across both passes; remaining work is Senthil/third-party. | E28: Planned
A29: v026 | B29: 2026-09-13 11:51 | C29: Claude for Senthil/KP | D29: EXTERNAL VERIFICATION SWEEP against live Google documentation — the step every sibling product ran after its cold review, and the step that found live-blocking defects in all of them. TWO LIVE-BLOCKING findings, both invisible to two clean internal passes because they are facts about the platform rather than the code. VER-DM1: the Workspace Marketplace does NOT push uninstall webhooks and the licenseNotification API is deprecated with no replacement — our uninstall endpoint was a handler for an event that never arrives, so token revocation, the retention clock, re-install restore and the purge chain would never have run. Fixed with a license reconciler that DETECTS uninstall (license state + revoked credential) and refuses to treat an API outage as one. VER-DM2: Google Forms cannot POST to an arbitrary URL — form submit needs an installable Apps Script trigger that calls UrlFetch itself, so the entire F5 feature (10 stories / 42 pts) rested on a capability that does not exist. Fixed by shipping the Apps Script forwarder that signs with the scheme our endpoint already verifies. 41 suites / 707 tests at 100%. CONSEQUENCE FOR SENTHIL: the form-trigger setup flow changes — ST-041 "one screen" and the help-centre article need rewording. | E29: Released
A30: v027 | D30: PLANNED: verification sweep part 2 (add-on surface, scopes, asset spec, CASA requirements) — the sweep found two blockers in its first two checks, so the remaining assumptions deserve the same treatment. | E30: Planned
A31: v027 | B31: 2026-09-13 11:56 | C31: Claude for Senthil/KP | D31: VERIFICATION SWEEP PART 2 — VER-DM3, the third live-blocking finding and the first that is a DECISION rather than a defect. Google has two add-on types with incompatible UI models and our features sit across both: the Workspace type is card-only (HTML forbidden), cannot read the open document, has no Apps Script triggers and is absent from Forms, but reaches mobile and every host app; the Editor type has HTML sidebars, document context and triggers, but is desktop-only and Editors-only. Twelve shipped stories cannot run on the Workspace surface as built, and the form feature cannot run there at all. Encoded as a test-pinned constraint matrix (src/addonSurface.ts) and presented as ADDON_SURFACE_DECISION.md; logged as D-DM1 for Senthil rather than decided unilaterally. 42 suites / 721 tests at 100%. Three live-blocking findings in four verification checks — the sweep is finding roughly one blocker per check, which says something about how far internal review can reach. | E31: Released
A32: v028 | D32: PLANNED: sweep part 3 (listing asset spec — TestPulse found theirs wrong; scope behaviour; CASA requirements) once D-DM1 is decided, since the surface choice changes the scope narrative. | E32: Planned
A33: v028 | B33: 2026-09-13 12:01 | C33: Claude for Senthil/KP | D33: VERIFICATION SWEEP PART 3 — VER-DM4: the listing asset and copy spec was invented and wrong in eight ways, including TWO REQUIRED ASSET FAMILIES that were absent entirely (application icons at 32/128 plus 48/96 because we now have a web app, and the 220x140 card banner), a forbidden-Google-name rule on the app name we had no check for, and the terms-of-service link missing from the submission checklist. Every copy limit was wrong in the strict direction, so the drafted variants were being held to tighter constraints than the platform applies. The promo video is an optional YouTube link, not the captioned upload we had specified. src/listing.ts rewritten against the live spec, LISTING_PACK.md regenerated, 13 tests pin the corrections. 42 suites / 729 tests at 100%. Four live findings in five verification checks. | E33: Released
A34: v029 | D34: PLANNED: sweep part 4 (OAuth verification + CASA requirements, scope behaviour) — the last unchecked assumptions; then D-DM1 gates the rest. | E34: Planned
A35: v029 | B35: 2026-09-13 12:06 | C35: Claude for Senthil/KP | D35: VERIFICATION SWEEP PART 4 — VER-DM5, the first finding that REMOVES work. Google routes app review by scope classification, and CASA is triggered only by RESTRICTED scopes. DocMerge requests none: drive.file is the recommended non-sensitive alternative to the restricted Drive scopes, userinfo.email is non-sensitive, and only spreadsheets.readonly and documents are sensitive — requiring Google app verification but not an assessment. CASA has been carried as a blocking multi-week paid item since S6 (R-D1, R-D10, LC-3) on an assumption nobody had checked. LC-3 downgraded to "likely not required, confirm in console" rather than deleted, because classification is per-project and Google may still ask. Found in the same pass: verification requires an unlisted YouTube DEMONSTRATION video (OAuth grant flow, consent screen showing the app name, detailed use of each sensitive scope) — a requirement we did not have, and separate from the optional marketing promo video. scopes.ts derives the review path from classifications with 7 pinning tests; SCOPE_NARRATIVE.md regenerated. 42 suites / 736 tests at 100%. | E35: Released
A36: v030 | D36: PLANNED: verification sweep COMPLETE across the five checkable assumption areas. Next work is D-DM1 (Senthil) and then live execution. | E36: Planned
A37: v030 | B37: 2026-09-13 16:25 | C37: Claude for Senthil/KP | D37: R-D4 CLOSED — Postgres adapter shipped. Every store had been an in-memory Map behind a typed interface, which was correct while no schema existed but left the interfaces never once implemented against a real database; the DM-F09 migrations were decorative until now. src/postgres.ts implements TokenStore, AccountRepo and TemplateRepo against the schema, plus purge targets for all 18 tables ordered children-before-parents so the row counts are real evidence rather than zero-because-already-cascaded. The SQL client is injected, so there is no pg dependency and the adapter is fully testable without a database. Details that would have bitten in production: BIGINT expiries are converted explicitly because the driver returns them as strings, template and rules write inside one transaction with rollback (a half-replaced rule set renders wrong output rather than failing), an absent rule value is stored as NULL not the string "undefined", and indirect tables are reached through their parent rather than a column they do not have. A test purges with a SQL-injection string and asserts it never reaches the statement text. 43 suites / 753 tests at 100%. | E37: Released
A38: v031 | D38: PLANNED: remaining in-memory stores (subscriptions, invoices, audit, telemetry, support) onto the adapter pattern; D-DM1 still gates the surface work. | E38: Planned
A39: v031 | B39: 2026-09-13 16:29 | C39: Claude for Senthil/KP | D39: DM-F14 — the remaining in-memory stores are a DURABILITY GAP, not merely unconverted. A restart resets every plan limit (each deploy silently grants every customer a fresh monthly allowance — a revenue leak invisible to tests, which start from zero anyway), resets billing state so paying customers look like trials, and evaporates the tamper-evident audit chain while restarting its numbering at genesis so the gap is not even visible. Usage counters fixed end to end: PlanLimitEnforcer now takes a UsageBackend; WriteThroughUsageBackend serves reads from a primed cache so the limit check stays synchronous, writes through with an atomic single-statement upsert (read-then-write loses increments exactly when a customer is near the limit), and counts write failures rather than failing the request. Subscription and admin-audit stores are built and tested — append-only with no update path, and lastSequence so the chain continues across restarts — but their services are NOT yet wired, which is stated rather than glossed because this codebase has already produced two built-but-never-called defects. 43 suites / 770 tests at 100%. | E39: Released
A40: v032 | D40: PLANNED: wire BillingService and AdminAuditLog to their stores (closing DM-F14), then telemetry/support persistence. D-DM1 still open. | E40: Planned
A41: v032 | B41: 2026-09-13 16:34 | C41: Claude for Senthil/KP | D41: DM-F14 CLOSED and DM-F15 found and fixed. BillingService now persists after every mutation through a SubscriptionBackend, and AdminAuditLog through an AdminAuditBackend with resume(), so a restart no longer resets a paying customer to trial or forks a second audit chain at genesis. Write-through Postgres backends keep reads synchronous and count write failures rather than failing the customer request. DM-F15 surfaced DURING that wiring: the admin audit log had no accountId at all — every customer shared one chain and one sequence counter, and exportCsv would have handed one customer every other customer admin history. The schema had keyed the table on (account_id, sequence) since DM-F09; the code never matched it, and nothing caught the mismatch because the table had no implementation behind it until today. Now scoped per account, with the accountId inside the digest so an entry cannot be replayed into another tenant chain. 43 suites / 781 tests at 100%. | E41: Released
A42: v033 | D42: PLANNED: telemetry/support persistence, then a tenant-isolation sweep across the remaining services — DM-F15 suggests the audit log may not be the only thing lacking a tenant boundary. | E42: Planned
A43: v033 | B43: 2026-09-13 16:39 | C43: Claude for Senthil/KP | D43: TENANT-ISOLATION SWEEP — run deliberately because DM-F15 was found by accident, and it found five more. DM-F16 (CRITICAL): template lookups took a templateId and nothing else, and POST /accounts/:id/documents takes that id from the request body — so an authenticated user of one account could read another account template and generate documents from it. The session check added for DM-F07 proved WHO was asking; nothing checked WHAT they asked for. DM-F17: the same shape on signature requests, exposing signer names and emails. DM-F18: the feature audit log had no accountId either, the same defect as DM-F15 in a second log. All three fixed with ownership enforced centrally, cross-tenant access reported as "not found" so the id space cannot be probed, and regression tests asserting the cross-tenant failure is indistinguishable from a missing record. DM-F19 and DM-F20 (metrics summaries and the support inbox aggregate across tenants) are logged OPEN rather than fixed blind, because whether they are defects depends on whether they are surfaced per-customer or internally — a decision, not a bug. 43 suites / 786 tests at 100%, smoke green. | E43: Released
A44: v034 | D44: PLANNED: decide DM-F19/F20 surfacing, then telemetry/support persistence. D-DM1 still open. | E44: Planned
A45: v034 | B45: 2026-09-13 17:23 | C45: Claude for Senthil/KP | D45: PORTABLE TENANT-ISOLATION GATE built and wired into CI, then it immediately found DM-F21. A sweep finds this class of defect once; the gate finds it every commit, and it is written to be copied into the sibling products — the tenant parameter names and entity-id suffixes are configuration, not hard-coded. It flagged 28 methods on first run. Triage: five clusters genuine (DM-F21) — pause and resume on signature requests, form triggers and batch jobs took only an entity id, so one tenant could pause another tenant work with nothing but a guessed id; renderCsv would render any account invoice with its billing contact and tax identifiers; openTemplate read another account template metadata. The manual sweep had checked READS and missed writes-that-are-not-reads. The other 23 are exempted with written reasons rather than silenced, and a test asserts every exemption carries one. 44 suites / 797 tests at 100%, smoke green. | E45: Released
A46: v035 | D46: PLANNED: copy the gate to the sibling products (the pattern is identical); decide DM-F19/F20; D-DM1 still open. | E46: Planned
A47: v035 | B47: 2026-09-13 18:48 | C47: Claude for Senthil/KP | D47: AUDITED THE 23 GATE EXEMPTIONS I wrote an hour ago, having flagged them as judgement calls. One was false. The PauseManager exemption claimed callers passed account-namespaced keys; e-sign passed a bare requestId and batch a bare templateId, so a shared PauseManager would put template ids, sign-request ids, job ids and trigger ids in one namespace — pausing a template called X would also report a sign request called X as paused. Demonstrated before fixing. Nothing broke only because each service happened to get its own instance, which nothing enforced. pauseKey(entity, accountId, entityId) is now the only way keys are formed anywhere. Crucially the exemptions are no longer prose: three tests VERIFY the claims — one fails the build if any PauseManager call omits pauseKey, one proves two entity types sharing an id cannot collide, one asserts only the designer and sidebar touch a template repository. 44 suites / 801 tests at 100%, smoke green. | E47: Released
A48: v036 | D48: PLANNED: copy the gate to the sibling products; decide DM-F19/F20; D-DM1 still open. | E48: Planned
A49: v036 | B49: 2026-09-13 18:53 | C49: Claude for Senthil/KP | D49: ALL 23 TENANT-GATE EXEMPTIONS now carry a test that verifies their claim, and a meta-gate makes that permanent: unverifiedExemptions() fails the build if an exemption is added without a test naming it, and a test proves the meta-gate catches such an addition. This closes the gap DM-F22 exposed — an exemption that was right about its outcome and wrong about its reason, which read as handled. The claims are now checked against behaviour or source: the sandbox holds no account, store or repository reference; signer actions reject a non-signer holding a valid request id while accepting a listed signer who has no account at all; a batch sidebar bound to one account cannot run another account template; both sidebar controllers stamp their own account onto what they create; and per-entity metrics and the support inbox are confirmed absent from every HTTP route, which is precisely what keeps DM-F19/F20 product decisions rather than live leaks. 44 suites / 812 tests at 100%. | E49: Released
A50: v037 | D50: PLANNED: copy the gate and meta-gate to the sibling products; DM-F19/F20 and D-DM1 remain your decisions. | E50: Planned
A51: v037 | B51: 2026-09-13 18:58 | C51: Claude for Senthil/KP | D51: VER-DM6 — the sixth verification finding, and the first that contradicts our own published targets. The Docs API allows 60 writes per minute per user; ST-087 promised a generated document every 1500ms and ST-088 drove 100 per minute and reported PASS. One user cannot exceed one document per second however fast our code runs, and a 500-row batch for one customer cannot finish in under EIGHT MINUTES — a fact absent from every estimate and SLO written so far. The load test never reached the ceiling because it drove an injected worker, so its PASS measured the harness. Now: verified quotas with sources and a refusal to guess unrecorded ones; a feasibility check that fails when an internal promise exceeds an external quota; a per-account governor that paces rather than earning 429s and gives an honest completion estimate; and a load test that refuses to pass a profile exceeding a declared ceiling. Also recorded: Apps Script UrlFetch caps at 20,000/day consumer and 100,000/day Workspace, the real per-customer limit on the form forwarder. 45 suites / 827 tests at 100%. | E51: Released
A52: v038 | D52: PLANNED: pace the batch runner through QuotaGovernor and restate batch timing in the help centre; gate + meta-gate ready to copy to siblings. | E52: Planned
A53: v038 | B53: 2026-09-13 19:33 | C53: Claude for Senthil/KP | D53: VER-DM6 CLOSED — both owed items done. The batch runner now paces through the QuotaGovernor, waiting BEFORE each write rather than after a rejection: waiting on our side costs only the wait, while being throttled costs a round trip, a backoff, and a slice of the customer's remaining quota for their other tools. BatchResult reports quotaWaitMs, so a long batch reads as "paced by Google's limit" rather than "the product is slow" — the difference between an understood wait and a support ticket. Metering is per account, proven by a test where one customer exhausting their allowance leaves another unaffected. The help-centre article now carries the real numbers (about 60 documents a minute, roughly eight minutes for 500, sixteen for 1,000) and is findable by searching "how long", "slow" or "quota". One test expectation of mine was wrong and the code was right: rows run in bursts because a wait clears the whole minute-window, so seven rows at a ceiling of three cost two waits, not four. 45 suites / 830 tests at 100%, smoke green. | E53: Released
A54: v039 | D54: PLANNED: copy tenantGate + meta-gate + quota feasibility check to the sibling products. DM-F19/F20 and D-DM1 remain your decisions. | E54: Planned
A55: v039 | B55: 2026-09-13 19:39 | C55: Claude for Senthil/KP | D55: PORTFOLIO GUARD KIT extracted for the sibling products — four modules with no imports at all, so nothing else travels with them: tenantGate (authorisation, plus the meta-gate requiring every exemption to carry a test), ledger (bounded append with counted evictions, including the hash-chain anchor subtlety), purge (registry that fails the build when a store has no deletion target, with per-store row counts as evidence), platformQuotas (verified numbers with sources, a refusal to guess an unrecorded one, and a feasibility check). platformQuotas was PARAMETERISED first — the mechanism ports but Google numbers do not belong in a Zoho or Xero product. A product-specific test file was extracted and then REPLACED: the original imported DocMerge modules throughout and would not have compiled anywhere else, so the kit ships a template with no product imports. README records what each gate caught here as evidence; TRIAGE.md gives the five questions to ask on a first run, since DocMerge flagged 28 methods and exempting without triage turns a gate into decoration. 45 suites / 832 tests at 100%. | E55: Released
A56: v040 | D56: PLANNED: run the kit against a sibling codebase when one is available. DM-F19/F20 and D-DM1 remain your decisions. | E56: Planned
A57: v040 | B57: 2026-09-13 20:27 | C57: Claude for Senthil/KP | D57: VER-DM7 — the quota module caught a gap in itself. It refuses to guess an unrecorded quota, and the filing path tripped that refusal: we write to Drive on every generated document and had recorded no Drive limit. The answer turned out to be awkward rather than clean — Google is mid-migration between a request-count model and a quota-unit model, legacy projects keep the old counts, and which applies depends on the age of a project we have not created yet. Recorded the conservative figure WITH the ambiguity attached and added a caveat field so an unreliable quota is visibly unreliable, rather than resolving it by picking whichever number suited us. The useful conclusion: on every published model Drive sits two orders of magnitude above the Docs ceiling of 60 writes per minute per user, so filing is not the binding constraint — document creation is, and the governor is already set to it. bindingConstraint() now computes which API throttles first, with tests proving Docs governs today and that a future change reversing it would surface rather than silently slowing every run. Guard kit refreshed. 45 suites / 836 tests at 100%. | E57: Released
A58: v041 | D58: PLANNED: re-verify the Drive quota against the real project once it exists (LC-1). DM-F19/F20 and D-DM1 remain your decisions. | E58: Planned
A59: v041 | B59: 2026-09-13 20:34 | C59: Claude for Senthil/KP | D59: STATE_OF_DOCMERGE.md — a single readable synthesis, written because the detail now spans 40 workbook versions and 62 log entries and none of that is usable when deciding what to do next. Covers: the three decisions owed (D-DM1 add-on type, open since 11:56 and blocking the scope narrative, listing copy and five story descriptions; DM-F19/F20 surfacing; support staffing), the eight external actions in their CORRECTED order (hosting BEFORE the consent screen, per R-D15), and the five lessons worth more than the individual fixes — coverage proves execution not correctness; authentication is not authorisation; internal review cannot see platform reality; a plausible reason survives review indefinitely; sweeps find a class once while gates find it every commit. Closes with the assessment I would want stated plainly: the product has been code-complete since roughly 11:00 and has not moved one step closer to a customer since, because every remaining step needs a domain, a project, a budget or a decision. 45 suites / 836 tests at 100%. | E59: Released
A60: v042 | D60: PLANNED: nothing further on this codebase without a decision, a sibling codebase to check, or live infrastructure. | E60: Planned

Sheet ReadMe_Scope
A1: DocMerge Pro — Template-based document generation from Sheets/Forms with e-sign and Drive filing
A3: PLATFORM: Google Workspace Marketplace | CATEGORY: Document Automation
A4: PROBLEM: Mail-merge add-ons are dated; SMBs want doc-gen + sign without Zapier chains
A5: DIFFERENTIATION: Native Sheets sidebar, per-doc pricing, DPA + CASA badge for admin trust
A6: ICP: SMBs, schools, agencies 5-200 staff generating contracts/certificates/invoices from Sheets data
A8: HOW TO USE: Full_Backlog is the single source of truth (edit Status column during execution). Sprint_Board recalculates points per sprint automatically. Financial_Model assumptions (yellow) are editable — the 18-month build recalculates. Launch_Checklist is the platform-specific gate before submission. All costs/timelines are market-standard estimates; verify platform terms (fees/review rules) during S0.
A10: STACK ASSUMPTION (market standard): TypeScript/Node or platform-mandated runtime, React frontends, Postgres, hosted on AWS/GCP/platform FaaS as required, GitHub Actions CI, PostHog + Sentry telemetry, Intercom-class support.

Sheet Product_Spec
A1: PRODUCT SPEC
A3: Module (feature) | B3: Scope in MVP | C3: Out of scope (v1) | D3: Non-functional requirements
A4: Template designer | B4: Template designer: end-to-end happy path + edge cases + permissions | C4: Advanced automation, AI beyond listed, multi-language beyond launch set | D4: p95 <500ms API / <2s UI loads
A5: Batch generate from Sheets | B5: Batch generate from Sheets: end-to-end happy path + edge cases + permissions | C5: Advanced automation, AI beyond listed, multi-language beyond launch set | D5: 99.5% monthly uptime
A6: E-sign requests | B6: E-sign requests: end-to-end happy path + edge cases + permissions | C6: Advanced automation, AI beyond listed, multi-language beyond launch set | D6: WCAG AA
A7: Auto-file to Drive | B7: Auto-file to Drive: end-to-end happy path + edge cases + permissions | C7: Advanced automation, AI beyond listed, multi-language beyond launch set | D7: SOC2-track controls
A8: Form-triggered generation | B8: Form-triggered generation: end-to-end happy path + edge cases + permissions | C8: Advanced automation, AI beyond listed, multi-language beyond launch set | D8: Rate-limit safe (backoff+queue)
A10: Persona | B10: Jobs-to-be-done
A11: Office manager | B11: Buys from marketplace search; needs zero-code setup
A12: Workspace admin | B12: Approves domain install; CASA tier + data policy decide
A13: Ops freelancer | B13: Recommends across clients

Sheet Screens_Wireframes
A1: SCREEN INVENTORY (attach Figma links in col E during S0)
A3: # | B3: Screen | C3: Purpose | D3: Key elements | E3: Wireframe link
A4: 1 | B4: Onboarding / first-run | C4: Reach aha in <1 day | D4: Checklist, sample data toggle, connect steps
A5: 2 | B5: Home dashboard | C5: Daily habit surface | D5: KPI cards, activity feed, alerts
A6: 3 | B6: Template designer workspace | C6: Core value surface | D6: List+detail, bulk actions, status chips
A7: 4 | B7: Batch generate from Sheets builder | C7: Configure second pillar | D7: Rule builder, preview, test mode
A8: 5 | B8: E-sign requests view | C8: Differentiator surface | D8: Timeline/visual, export
A9: 6 | B9: Settings & team | C9: Roles, notifications, data | D9: Role matrix, API keys, danger zone
A10: 7 | B10: Billing | C10: Plan/trial/invoices | D10: Plan cards, usage meter, invoices
A11: 8 | B11: Analytics | C11: Prove ROI | D11: Funnel, cohort, export
A12: 9 | B12: Help & support | C12: Deflect + assist | D12: Search, chat, status

Sheet Full_Backlog
A1: FULL BACKLOG
A3: ID | B3: Epic | C3: Story | D3: Points | E3: Priority | F3: Sprint | G3: Status
A4: ST-001 | B4: F1 | C4: As a Office manager, I can set up Template designer with sensible defaults in one screen | D4: 5 | E4: P0 | F4: S2 | G4: Done
A5: ST-002 | B5: F1 | C5: As a Office manager, the Template designer happy path completes without documentation | D5: 8 | E5: P0 | F5: S2 | G5: Done
A6: ST-003 | B6: F1 | C6: As a Workspace admin, I can customise Template designer rules/conditions for my workflow | D6: 5 | E6: P1 | F6: S2 | G6: Done
A7: ST-004 | B7: F1 | C7: As a user, Template designer shows clear errors and retry paths on platform API failures | D7: 3 | E7: P0 | F7: S2 | G7: Done
A8: ST-005 | B8: F1 | C8: As a Ops freelancer, Template designer works on the Workspace add-on sidebar in Sheets/Docs surface end-to-end | D8: 5 | E8: P0 | F8: S3 | G8: Done
A9: ST-006 | B9: F1 | C9: As a Workspace admin, I can see Template designer performance metrics and trends | D9: 3 | E9: P1 | F9: S3 | G9: Done
A10: ST-007 | B10: F1 | C10: As a user, Template designer respects role permissions and audit logging | D10: 3 | E10: P1 | F10: S3 | G10: Done
A11: ST-008 | B11: F1 | C11: As a Office manager, I can pause/disable Template designer without data loss | D11: 2 | E11: P2 | F11: S3 | G11: Done
A12: ST-009 | B12: F1 | C12: As a Workspace admin, I can import/migrate existing data into Template designer (CSV + competitor importer) | D12: 5 | E12: P1 | F12: S3 | G12: Done
A13: ST-010 | B13: F1 | C13: As a user, I get notifications (in-app + email) for key Template designer events with per-type mute | D13: 3 | E13: P2 | F13: S3 | G13: Done
A14: ST-011 | B14: F2 | C14: As a Office manager, I can set up Batch generate from Sheets with sensible defaults in one screen | D14: 5 | E14: P0 | F14: S3 | G14: Done
A15: ST-012 | B15: F2 | C15: As a Office manager, the Batch generate from Sheets happy path completes without documentation | D15: 8 | E15: P0 | F15: S3 | G15: Done
... A103: ST-100 | B103: EL | C103: First 10 design-partner reviews scheduled | D103: 2 | E103: P1 | F103: S11 | G103: Done
A105: Total stories: 100. Epics: F1-F5 = product features; E1 install, E5 billing, E6 compliance, E7 telemetry, E8 onboarding/docs/support, EQ quality. Edit Status (Backlog/In progress/Done) during execution.

Sheet Sprint_Board
A1: SPRINT BOARD — live counts from Full_Backlog
A3: Sprint | B3: Focus | C3: Stories | D3: Points | E3: Done | F3: Exit criteria
A4: S0 | B4: Discovery & Design (2 wks) | C4: =COUNTIF(Full_Backlog!F4:F103,"S0") -> 0 | D4: =SUMIF(Full_Backlog!F4:F103,"S0",Full_Backlog!D4:D103) -> 0 | E4: =COUNTIFS(Full_Backlog!F4:F103,"S0",Full_Backlog!G4:G103,"Done") -> 0 | F4: PRD signed off; prototype tested with 5 target users
A5: S1 | B5: Foundation (2 wks) | C5: =COUNTIF(Full_Backlog!F4:F103,"S1") -> 4 | D5: =SUMIF(Full_Backlog!F4:F103,"S1",Full_Backlog!D4:D103) -> 13 | E5: =COUNTIFS(Full_Backlog!F4:F103,"S1",Full_Backlog!G4:G103,"Done") -> 4 | F5: App installs cleanly in dev store/org; telemetry firing
A6: S2 | B6: Core feature Template designer - part 1 | C6: =COUNTIF(Full_Backlog!F4:F103,"S2") -> 6 | D6: =SUMIF(Full_Backlog!F4:F103,"S2",Full_Backlog!D4:D103) -> 29 | E6: =COUNTIFS(Full_Backlog!F4:F103,"S2",Full_Backlog!G4:G103,"Done") -> 6 | F6: Template designer happy path demoable
A7: S3 | B7: Core feature Template designer - part 2 + Batch generate from Sheets start | C7: =COUNTIF(Full_Backlog!F4:F103,"S3") -> 11 | D7: =SUMIF(Full_Backlog!F4:F103,"S3",Full_Backlog!D4:D103) -> 47 | E7: =COUNTIFS(Full_Backlog!F4:F103,"S3",Full_Backlog!G4:G103,"Done") -> 11 | F7: Template designer complete with tests; Batch generate from Sheets skeleton
A8: S4 | B8: Core feature Batch generate from Sheets | C8: =COUNTIF(Full_Backlog!F4:F103,"S4") -> 9 | D8: =SUMIF(Full_Backlog!F4:F103,"S4",Full_Backlog!D4:D103) -> 34 | E8: =COUNTIFS(Full_Backlog!F4:F103,"S4",Full_Backlog!G4:G103,"Done") -> 9 | F8: MVP loop usable end-to-end internally
A9: S5 | B9: Feature E-sign requests + alpha hardening | C9: =COUNTIF(Full_Backlog!F4:F103,"S5") -> 12 | D9: =SUMIF(Full_Backlog!F4:F103,"S5",Full_Backlog!D4:D103) -> 50 | E9: =COUNTIFS(Full_Backlog!F4:F103,"S5",Full_Backlog!G4:G103,"Done") -> 12 | F9: Internal alpha: team dogfoods daily
A10: S6 | B10: Billing + Auto-file to Drive | C10: =COUNTIF(Full_Backlog!F4:F103,"S6") -> 13 | D10: =SUMIF(Full_Backlog!F4:F103,"S6",Full_Backlog!D4:D103) -> 60 | E10: =COUNTIFS(Full_Backlog!F4:F103,"S6",Full_Backlog!G4:G103,"Done") -> 13 | F10: Can charge a test customer; upgrade/downgrade paths work
A11: S7 | B11: Private beta (design partners) | C11: =COUNTIF(Full_Backlog!F4:F103,"S7") -> 5 | D11: =SUMIF(Full_Backlog!F4:F103,"S7",Full_Backlog!D4:D103) -> 15 | E11: =COUNTIFS(Full_Backlog!F4:F103,"S7",Full_Backlog!G4:G103,"Done") -> 5 | F11: 3+ partners active weekly; NPS pulse >30
A12: S8 | B12: Beta iteration + Form-triggered generation | C12: =COUNTIF(Full_Backlog!F4:F103,"S8") -> 22 | D12: =SUMIF(Full_Backlog!F4:F103,"S8",Full_Backlog!D4:D103) -> 87 | E12: =COUNTIFS(Full_Backlog!F4:F103,"S8",Full_Backlog!G4:G103,"Done") -> 22 | F12: Retention of beta cohort week-over-week >60%
A13: S9 | B13: Marketplace review prep | C13: =COUNTIF(Full_Backlog!F4:F103,"S9") -> 7 | D13: =SUMIF(Full_Backlog!F4:F103,"S9",Full_Backlog!D4:D103) -> 30 | E13: =COUNTIFS(Full_Backlog!F4:F103,"S9",Full_Backlog!G4:G103,"Done") -> 6 | F13: Review submission accepted into queue
A14: S10 | B14: Review remediation + docs | C14: =COUNTIF(Full_Backlog!F4:F103,"S10") -> 7 | D14: =SUMIF(Full_Backlog!F4:F103,"S10",Full_Backlog!D4:D103) -> 24 | E14: =COUNTIFS(Full_Backlog!F4:F103,"S10",Full_Backlog!G4:G103,"Done") -> 6 | F14: Marketplace approval obtained (or final remediation cycle)
A15: S11 | B15: Launch | C15: =COUNTIF(Full_Backlog!F4:F103,"S11") -> 3 | D15: =SUMIF(Full_Backlog!F4:F103,"S11",Full_Backlog!D4:D103) -> 8 | E15: =COUNTIFS(Full_Backlog!F4:F103,"S11",Full_Backlog!G4:G103,"Done") -> 3 | F15: First 10 installs; first 3 reviews; activation >40%
A16: S12 | B16: Iterate & scale decision | C16: =COUNTIF(Full_Backlog!F4:F103,"S12") -> 1 | D16: =SUMIF(Full_Backlog!F4:F103,"S12",Full_Backlog!D4:D103) -> 2 | E16: =COUNTIFS(Full_Backlog!F4:F103,"S12",Full_Backlog!G4:G103,"Done") -> 1 | F16: Growth model doc with CAC/LTV first estimates
B17: TOTAL | C17: =SUM(C4:C16) -> 100 | D17: =SUM(D4:D16) -> 399
B18: Velocity check: points/sprint S2-S8 should sit within 30-45 for a 4-6 person team; rebalance Sprint column in backlog if a sprint exceeds capacity.

Sheet Sprint_Tracker_Log
A1: SPRINT TRACKER LOG — session-by-session execution record
A3: Entry | B3: Date/Time | C3: Sprint | D3: Stories | E3: Action | F3: Outcome | G3: Decision/Ref
A4: L-001 | B4: 2026-09-05 19:50 | C4: — | D4: — | E4: v007 full product workbook released (spec, 100-story backlog, sprint board, financial model, GTM, launch checklist) | F4: Baseline established; all 100 stories Backlog | G4: v007 Version_Control
A5: L-002 | B5: 2026-09-10 22:17 | C5: S0 | D5: — | E5: S0 discovery interviews parked; development proceeds directly | F5: S0 closed as parked (0 stories carried); PRD baseline = Product_Spec sheet | G5: D13 (portfolio decision, 10 Sep 2026)
A6: L-003 | B6: 2026-09-10 22:17 | C6: S1 | D6: ST-051, ST-052, ST-055, ST-056 | E6: S1 Foundation opened and executed: docmerge-pro-s1 TypeScript package — OAuth install flow, uninstall webhook with token revocation + 30-day retention deletion scheduling, rotation-surviving token refresh, install telemetry with listing/search/referral attribution | F6: All 4 stories (13 pts) code-complete: 37 automated tests, 100% statements/branches/functions/lines, coverage gate pinned at 100% in CI config, tsc strict clean | G6: D13 100% coverage gate (supersedes ST-085 ≥70%)
A7: L-004 | B7: 2026-09-10 22:17 | C7: S1 | D7: — | E7: S1 exit criteria review: "App installs cleanly in dev store/org; telemetry firing" | F7: Code-complete; LIVE dev-org install PENDING — requires GCP project + OAuth consent screen (Launch_Checklist #1), not yet created. Same gate pattern as RevRescue S1. | G7: Carry-over to v009
A8: L-005 | B8: 2026-09-10 22:23 | C8: S2 | D8: ST-001, ST-002, ST-003, ST-004 | E8: S2 opened and executed (Template designer part 1): createWithDefaults one-screen setup; happy-path placeholder/section render with actionable missing-field messages; validated rules/conditions (not_empty/equals/greater_than section toggles); platform API failure mapping (429/5xx/403/404/unknown) with exponential-backoff retry paths | F8: 4 stories code-complete at 100% coverage; PlatformApiError messages carry explicit user retry guidance | G8: D13 100% gate
A9: L-006 | B9: 2026-09-10 22:23 | C9: S2 | D9: ST-053, ST-054 | E9: Re-install restore: pending_deletion accounts re-installing before the 30-day purge get deletion cancelled, data retained, tokens re-issued, app_reinstalled attributed. Permission matrix owner/admin/member pinned cell-by-cell and enforced at every privileged TemplateDesigner entry point | F9: S2 complete: 6/6 stories (29 pts). Suite 101 tests / 100% all metrics / tsc strict clean | G9: Matrix doc feeds ST-064 least-privilege narrative (S7)
A10: L-007 | B10: 2026-09-10 22:29 | C10: S3 | D10: ST-005, ST-006, ST-007, ST-008, ST-009, ST-010 | E10: Template designer part 2: SidebarController (Sheets/Docs host injected — list->designer->preview-from-active-row end-to-end, Docs sample-data fallback); TemplateMetrics (p95, success rate, period trend); AuditLog + AuditedTemplateDesigner (allowed AND denied attempts recorded); PauseManager (flag-only, zero data loss); CSV importer with partial success + row-numbered errors and <<legacy>> competitor conversion; NotificationCenter (in-app+email fan-out, per-type per-account mute) | F10: 6 stories code-complete at 100% coverage | G10: D13
A11: L-008 | B11: 2026-09-10 22:29 | C11: S3 | D11: ST-011, ST-012, ST-013, ST-014 | E11: Batch generate skeleton: one-screen job defaults; per-row generation with named outputs; row rules reusing the designer rule evaluator (skip on fail); per-row platform error mapping with retry/backoff, retryableRows list, continueOnError stop, paused-template gate | F11: 4 stories code-complete at 100% coverage | G11: D13
A12: L-009 | B12: 2026-09-10 22:29 | C12: S3 | D12: ST-085 | E12: DEFECT (caught by the 100% branch gate + failing test before merge): withRetry mapped ALL errors to a generic "unknown Google" message, burying actionable validation messages (e.g. missing Sheet column). Fixed: non-platform errors now pass through unmapped, no retry. ST-085 (≥70% coverage gate) closed as SUPERSEDED — D13 pins the gate at 100%, enforced in package.json thresholds (build fails below 100). | F12: S3 complete: 11/11 stories (47 pts). Suite 150 tests / 100% all metrics / tsc strict clean | G12: D13 supersedes ST-085
A13: L-010 | B13: 2026-09-10 22:52 | C13: S4 | D13: ST-015, ST-016, ST-017, ST-018, ST-019, ST-020 | E13: Batch part 2: BatchSidebarController (configure with defaults -> rows from bound sheet -> governed run -> results, with guidance on unconfigured/empty-sheet paths); BatchMetrics (runs, row counts, failure rate, avg duration, trend); GovernedBatchRunner (permission asserted+audited up front incl. denials, job-level pause, run metrics, batch_completed/batch_failed notifications with retryable count, per-type mute honoured); row-data CSV importer with header validation, partial success, and <<legacy>> competitor conversion | F13: 6 stories code-complete at 100% coverage | G13: D13
A14: L-011 | B14: 2026-09-10 22:52 | C14: S4 | D14: ST-071, ST-072 | E14: Observability: ActivationFunnel (install->setup->aha->habit, idempotent, earlier stages implied, one dashboard with counts + stage conversions); ErrorTracker (release-tagged capture, per-release counts, spike alert when current window > factor x previous with a minimum floor, one alert per release until acknowledged) | F14: 2 stories code-complete at 100% coverage | G14: D13
... A27: L-024 | B27: 2026-09-13 10:22 | C27: S8 | D27: ST-073..ST-077, ST-087, ST-088, ST-092 | E27: Analytics + QE: usage heatmap whose unused-feature list is the roadmap-relevant half; weekly digest with alert counts in the subject; health score that always explains its reasons (a score with no explanation cannot be acted on); CSV/warehouse export; configurable thresholds. p95 budgets defined per surface and monitored with headroom; 5x load test written deterministically so it runs on EVERY commit rather than once before launch; blue/green deploy that health-checks the idle colour BEFORE any traffic moves and verifies rollback — droppedRequests is measured, not claimed. | F27: S8 complete: 22/22 stories (87 pts). Suite 385 tests / 100% all metrics / smoke green. Total 82/100 (335/399 pts) | G27: D13; tracker v004
A28: L-025 | B28: 2026-09-13 10:35 | C28: S9 | D28: ST-068 (PARTIAL) | E28: Security evidence pack built and published as SECURITY_EVIDENCE_PACK.md: 9 controls, 6 verified in code (auth, authorisation, least privilege, data handling, auditability, resilience), 3 outstanding (SC-07 encryption posture needs a real deployment, SC-08 third-party pen test NOT STARTED, SC-09 backup/restore needs real backups). NOT MARKED DONE. A penetration test is performed by a third party against running infrastructure; this pack is what the tester and reviewer are handed, not a substitute for the test. readyForSubmission is false by construction until the external report is attached. | F28: ST-068; LC-3 | G28: ST-068 In progress (NOT Done) | H28: Pen test must be booked and paid for — Senthil action; needs deployed infra (LC-1) | I28: L-026
A29: L-026 | B29: 2026-09-13 10:35 | C29: S9 | D29: ST-069, ST-090, ST-091 | E29: Data rights + resilience: self-serve export (owner/admin) that STATES its exclusions rather than silently omitting them, and owner-only deletion with a cancellable 7-day grace window after which it is irreversible; restore-drill harness that verifies restored row counts against the backup manifest as part of the pass condition (a restore that "succeeds" without checking contents evidences nothing) plus RTO/RPO targets; chaos simulation proving every dependency outage leaves the product usable and every lost capability carries a message saying what is safe — the guards are injectable so they can actually fire, since a check that can never fail is not a check. | F29: ST-069, ST-090, ST-091 | G29: 3 stories code-complete at 100% coverage | I29: L-027
A30: L-027 | B30: 2026-09-13 10:35 | C30: S9 | D30: ST-089, ST-093, ST-094 | E30: Listing + accessibility: WCAG AA audit with real contrast maths (shipped 6-pair palette passes; large-text threshold applied correctly), accessible-name/keyboard/focus failures and target-size warnings; two listing variants on genuinely different angles (problem-led vs outcome-led) with a reviewer that fails same-angle A/Bs and flags claims that invite rejection (implied Google endorsement, absolute security, guarantees, superlatives, "free forever"); asset validator for the 5x1280x800 screenshots and 30-120s captioned video, plus the screenshot plan. Published as LISTING_PACK.md. | F30: ST-089, ST-093, ST-094 | G30: S9: 6/7 Done, 1 In progress. Suite 432 tests / 100% all metrics / smoke green. Total 88/100 (357/399 pts) | H30: D13; tracker v005
A31: L-028 | B31: 2026-09-13 10:43 | C31: S10 | D31: ST-080, ST-081 | E31: Support surfaces: 15 launch articles, each documenting shipped behaviour and naming the stories it covers so docs cannot silently drift from code; weighted search (exact keyword > partial > title > summary > body) so "vat" returns invoicing rather than every article containing the word; documentation-coverage report over launch-critical journeys. In-app chat measures first response in BUSINESS hours — a Friday 17:00 message is 2 business hours from a Monday 09:00 reply, not 64 — with a tighter 1-hour SLA for urgent, a breach queue worst-first, and a waiting message that sets expectations instead of going silent. | F31: ST-080, ST-081 | G31: 2 stories code-complete at 100% coverage | H31: Support must actually be STAFFED during the stated hours before the SLA is published | I31: L-029
A32: L-029 | B32: 2026-09-13 10:43 | C32: S10 | D32: ST-083 (PARTIAL), ST-084 | E32: ST-083 sandbox/demo-data mode: a no-account, no-OAuth, platform-read-only session with realistic sample data that exercises real template features including a conditional section, 60-minute TTL, and conversion-to-signup carrying the template across. The 2-minute demo VIDEO half is NOT done — it is a recording of a running app. ST-084 status page: worst-component-wins overall (never rounds up to green), incident templates that state data is unaffected, and an overdue-update check that chases incidents gone quiet past the 30-minute cadence. | F32: ST-083, ST-084 | G32: ST-084 Done; ST-083 In progress (sandbox done, video pending) | H32: Demo video needs a running app (LC-1) | I32: L-030
A33: L-030 | B33: 2026-09-13 10:43 | C33: S10 | D33: ST-095, ST-096, ST-097 | E33: Public pages built FROM the code rather than alongside it: the plan matrix reads prices from the billing module and limits from the enforcer, with a validator that fails if the published page drifts; the trust page is generated from the scope manifest, subprocessor list, and retention policy. ST-097 submission dry-run run for real and published as SUBMISSION_DRY_RUN.md — VERDICT: 10 of 20 items satisfied, 10 blocking (8 Senthil, 2 third-party), NOT READY TO SUBMIT. The dry-run deliberately counts unmet items rather than explaining them away, and records an owner for each so the output is a work list. | F33: ST-095, ST-096, ST-097 | G33: S10: 6 Done + 1 In progress. Suite 484 tests / 100% all metrics / smoke green. Total 94/100 (376/399 pts) | H33: D13; tracker v006
A34: L-031 | B34: 2026-09-13 10:58 | C34: S11 | D34: ST-082, ST-100 | E34: ST-082 review ask: every rule exists to prevent an ill-timed prompt — not before the aha-moment, not before 10 documents, not within 3 days of a failure, not inside a 30-day cooldown, and never again after two dismissals. A prompt at the wrong moment costs a rating rather than earning one. ST-100 partner-review pipeline REFUSES to invite an at-risk account (fix their experience first), refuses to reschedule a decline, excludes declines from the pipeline count, and warns on invitations unanswered for over a week. | F34: ST-082, ST-100 | G34: 2 stories code-complete at 100% coverage | H34: Real partners and a listed app needed to run it | I34: L-032
A35: L-032 | B35: 2026-09-13 10:58 | C35: S11 | D35: ST-098 | E35: Launch runbook built and RUN against the real current state: go/no-go over 13 checks returns NO-GO with 8 blocking failures (not listed, not deployed, rollback unverified against real infra, status/privacy pages unhosted, billing not live, support unstaffed, monitoring sinks unwired). Watchlist items each carry an action rather than just a threshold; the rollback plan budgets 35 minutes with a verification step for each of its 5 steps; the comms tree names an owner and a deadline per audience. Published as LAUNCH_RUNBOOK.md — written now so launch day is execution, not authoring. | F35: ST-098 | G35: 1 story code-complete; runbook verdict NO-GO | H35: All 8 blocking items are Senthil or third-party | I35: L-033
A36: L-033 | B36: 2026-09-13 10:58 | C36: S12 | D36: ST-099 | E36: ST-099 SEO iteration classifies search terms into untargeted, ranking-just-off-page, and high-impressions-low-CTR, ignores anything under 100 impressions rather than chasing noise, sorts by impressions so the biggest lever is first, and recommends EXACTLY ONE change per iteration so the effect is attributable. CODE BACKLOG COMPLETE: 98 of 100 stories Done, 2 In progress (ST-068 needs a third-party pen test, ST-083 needs a running app to record the demo video). Suite 31 files / 516 tests / 100% all metrics / 33 modules / smoke green. Three test-side errors fixed this sprint, none in source. | F36: ST-099; D13 | G36: S11 3/3 and S12 1/1 code-complete. Total 98/100 Done, 2 In progress (391/399 pts) | H36: No further code sprints — remaining work is entirely live/third-party
A37: L-034 | B37: 2026-09-13 11:05 | C37: — | D37: Deployment preparation: src/deployment.ts specifies all 16 environment values with their source (vault / config / platform), validates them (required, https URLs, numeric/boolean kinds, the conditional Stripe key, unknown-variable warnings), and refuses vault-sourced secrets arriving as plain env in production. checkDeploymentReadiness combines that with the S8 posture verifier into one fail-closed gate: a misconfigured instance does not take traffic, which is better than discovering the problem on a customer request. .env.example is generated from the spec so it cannot drift. | E37: LC-1 prep; D13 | F37: 15 new tests; suite 531 at 100% | H37: L-035
A38: L-035 | B38: 2026-09-13 11:05 | C38: — | D38: Three blocker documents written so each external task starts warm: GCP_SETUP_GUIDE.md sequences LC-1 (project, five APIs, consent screen, OAuth client, brand verification, Marketplace SDK) with the prerequisites that must exist first — notably that the privacy policy and status page must be HOSTED before the consent screen will accept the authorised domains, which reorders the work. PENTEST_SCOPING_BRIEF.md scopes the test from the shipped code, names what is out of scope, and lists four design decisions a tester should probe rather than accept. CASA_PREFILL.md answers the assessment from existing evidence and marks three controls NOT YET — encryption-at-rest verification, the restore drill against real backups, and the pen test — rather than answering aspirationally. | E38: LC-1, LC-3, ST-068 prep | F38: Three artefacts published; no story status changed | G38: All three still require Senthil/third-party action | H38: Live execution
A39: L-036 | B39: 2026-09-13 11:10 | C39: — | D39: LC-9 template gallery built: 20 templates across 6 categories (invoice, receipt, quote, payment reminder; offer letter, employment contract, performance review, reference; NDA, service agreement, consent form; certificate, report card, enrolment; purchase order, delivery note, work order; meeting summary, onboarding pack, event invitation). Each uses at least one conditional section — the feature the gallery is there to teach — carries required and optional columns so a user knows what they need before committing, and targets named search terms (61 total) because the gallery is the listing's organic-search surface in the GTM plan. | E39: LC-9; GTM | F39: LC-9 moves to Done | H39: L-037
A40: L-037 | B40: 2026-09-13 11:10 | C40: — | D40: Gallery proved rather than asserted: a structural validator catches duplicate slugs, rules referencing placeholders or sections that do not exist, sections with no rule (which would always render), and sample rows that cannot fill their own body; then every template is rendered through the REAL TemplateDesigner with its sample row and asserted to leave no unresolved markers. TWO DEFECTS caught by doing this: (1) I had written 22 templates against a target of 20 — trimmed to exactly 20; (2) the purchase-order and event-invitation rules tested control fields that never appear in the body, which the real engine rejects — restructured so both conditions are driven by rendered fields. Neither would have been visible from reading the templates. | E40: LC-9; D13 | F40: Suite 567 tests / 100% x4 / 35 modules / smoke green | H40: Live execution
A41: L-038 | B41: 2026-09-13 11:16 | C41: S12 | D41: Growth model frame: restates the workbook assumptions as unit economics rather than a cash projection. Fully-loaded CAC charges free-tier support against each conversion — at 6% conversion roughly 17 installs are served per paying customer, so a high-volume free tier is an acquisition cost even with zero marketing spend. The verdict logic separates four cases that a single LTV:CAC number blurs: workable, healthy-ratio-but-slow-payback (needs funding to bridge, not patience), marginal, and loss-making. Three scenarios rather than one forecast, because a plan that only works in the optimistic column is not a plan. | E41: S12 exit; Financial_Model | F41: S12 exit In progress (frame built, estimates unmeasured) | G41: No cohort exists — every input is an assumption | H41: L-039
A42: L-039 | B42: 2026-09-13 11:16 | C42: S12 | D42: SENSITIVITY FINDING: ranking each input by how much it moves the fully-loaded ratio puts CHURN first, ahead of free-to-paid conversion. Intuition (and my own first test expectation, which the model corrected) reaches for conversion; but lifetime scales LTV directly while conversion mostly moves the free-support cost carried per customer. Halving churn beats doubling conversion. Measurement plan attaches each assumption to instrumentation that already exists (ActivationFunnel, subscription transitions, health scores, install source attribution) so first-cohort data lands without new analysis. One source defect found: display rounding to 2dp turned a 0.45% churn rate into 0, which reads as "no churn" — fixed to keep more places for small magnitudes. | E42: S12; D13 | F42: Suite 589 tests / 100% x4 / 36 modules / smoke green | G42: Replace with measured figures after the first cohort | H42: Live execution
A43: L-040 | B43: 2026-09-13 11:21 | C43: — | D43: ST-068 vendor outreach pack: a send-ready email that lets a vendor quote from the attached scoping brief instead of a discovery call, plus shortlist filters (credentials on the testers not just the firm; reports previously accepted for marketplace/CASA submissions; fixed price from a written brief; retest included) and a quote-comparison rubric. External copy kept company-agnostic per standing instruction. Advice included that a clean first report on a multi-tenant app usually means a shallow test, not a perfect app. | E43: ST-068; R-D10 | F43: Outreach ready to send; ST-068 still In progress | G43: Needs a staging target, or send now stating a target date purely to hold a diary slot | H43: Live execution
A44: L-041 | B44: 2026-09-13 11:24 | C44: — | D44: COLD REVIEW PASS 1. Portfolio memory shows every sibling product that declared code-complete then found real defects in code already at 100% coverage; TeleField logged it as L-T1 (review before declaring complete) and the portfolio lesson is F-V14 (coverage proves execution, not correctness). DocMerge had never been reviewed — so the "code phase complete" declaration two turns ago was premature, and this pass proves it. Nine findings, five CRITICAL. Five fixed with pinned regressions: read-only mode and plan limits were both fully built, fully tested, and CALLED FROM NOWHERE, so two behaviours the help centre promises customers were simply absent from the product; OAuth install accepted any code with no state (CSRF); webhooks verified nothing, so an unauthenticated POST could revoke a live account tokens and schedule its data for deletion; and no production backoff existed anywhere because every retry policy came from a test injecting its own no-op sleep. Four left open and logged rather than quietly fixed: DM-F01 (no HTTP app exists behind any route — the setup guide is unrunnable), DM-F07 (caller-declared identity), DM-F08 (eleven unbounded ledgers), DM-F09 (deletion has no implementation behind it, the class that breached published policy in five sibling products). | E44: L-T1; F-V14; DM-F01..F09 | F44: 35 suites / 616 tests at 100%; new Review_Findings sheet | G44: DM-F01 is the next real work; DM-F07 needs his decision | H44: Cold-review pass 2
A45: L-042 | B45: 2026-09-13 11:31 | C45: — | D45: DM-F01 + DM-F07 closed. The product now HAS an application: a framework-free router (literal and :param segments), 7 routes bound to the services that already existed, a server entrypoint with npm start, and a readiness check that refuses to listen on a misconfigured environment rather than failing on the first customer request. Identity comes from HMAC-signed sessions instead of a caller-supplied role parameter — a token whose role field is edited now fails signature verification, and a session issued for one account is refused against another. Every mutating route is authenticated and passes the entitlement gate, so the read-only mode and plan limits fixed earlier are enforced on the wire; reads deliberately stay open so an unpaid customer can still retrieve their work. Unexpected handler failures map to 500 without leaking internals, rather than hanging the request open (sibling M-F21 class). THEN BOOTED IT: healthz returned 200, the install URL carried its CSRF state, an unsigned webhook got 401, an unauthenticated route got 401, an unknown route got 404 — because the sibling lesson is that compiling is not running. | E45: DM-F01; DM-F07; L-OC4 | F45: 36 suites / 650 tests at 100%; server verified over real HTTP | G45: DM-F08 and DM-F09 still open from pass 1 | H45: Close F08/F09, then pass 2 over the new HTTP layer
A46: L-043 | B46: 2026-09-13 11:37 | C46: — | D46: DM-F08 and DM-F09 closed, then cold-review PASS 2 over the HTTP layer built an hour earlier — because the sibling lesson (L-OC4) is that new surfaces inherit old blind spots, and OnCall found two criticals in its equivalent layer immediately after building it. F08: 11 ledgers bounded, with eviction COUNTED rather than silent; the hash-chained admin audit was the interesting one — bounding it breaks verification from genesis, so the last evicted digest becomes the chain anchor and verifyChain now reports truncation instead of failing, with sequence numbers still counting so gaps are visible rather than disguised. F09: a PurgeRegistry over 16 stores whose registration check FAILS THE BUILD when a store has no purge target, receipts carrying per-store row counts as evidence, and an incomplete purge reported as incomplete rather than claimed done — plus the database schema that never existed behind the backup drill or the policy, with ON DELETE CASCADE on every account-scoped table so completeness is a property of the schema rather than of code someone must remember to update. PASS 2 found four more, all fixed and all verified by booting the server: uncapped request body (413 on a 2MB POST), abandoned OAuth states accumulating because sweep() was never called — the SAME built-but-never-wired class as F02/F03, which is worth noting because I introduced it while fixing that class — no rate limiting anywhere (429 after 20 install calls, a different caller unaffected), and /healthz handing the build version to anyone. | E46: DM-F08..F13; L-OC4 | F46: 40 suites / 691 tests at 100%; all 13 findings closed; server verified live | G46: Cold review complete across both passes | H46: Live execution — Senthil
A47: L-044 | B47: 2026-09-13 11:51 | C47: — | D47: EXTERNAL VERIFICATION SWEEP vs live Google docs. Two checks, two LIVE-BLOCKING findings — which is the argument for the step: both were invisible to two clean cold-review passes at 100% coverage, because neither is a defect in our code. They are facts about the platform that our design assumed wrongly. VER-DM1: the Workspace Marketplace does not push uninstall webhooks to a developer server, and the licenseNotification API that once reported deletions is deprecated with no replacement — so /webhooks/uninstall was a handler for an event that never arrives, and ST-052 revocation, the 30-day clock, ST-053 restore and the F09 purge chain would all have sat waiting forever in production. Replaced with a reconciler that detects uninstall from license state plus revoked credentials, and that deliberately treats an API outage or unknown state as indeterminate — mistaking an outage for a departure would revoke a live customer and start deleting their data. VER-DM2: Google Forms cannot POST to an arbitrary URL; form submit requires an installable Apps Script trigger that calls UrlFetchApp itself, so the whole F5 feature (10 stories, 42 pts) assumed a capability that does not exist. Shipped apps-script/FormForwarder.gs signing with the scheme the endpoint already verifies, secret in Script Properties, stable response id for dedupe, 5xx-only rethrow so Apps Script retries server failures but not rejections. | E47: VER-DM1; VER-DM2 | F47: 41 suites / 707 tests at 100% | G47: Form setup flow changes — ST-041 wording and help article owed | H47: Verification sweep part 2
A48: L-045 | B48: 2026-09-13 11:56 | C48: — | D48: VER-DM3: the "Workspace add-on sidebar" the product was built against does not exist as described. Google has TWO add-on types with incompatible UI models. The Workspace type is card-based and explicitly forbids HTML/CSS, cannot read the open document, has no Apps Script triggers, and is not available in Google Forms — but reaches mobile and every host app. The Editor type has HTML sidebars, document context and triggers, but is desktop-only and confined to the Editors. Five shipped stories claim the feature "works on the Workspace add-on sidebar in Sheets/Docs end-to-end" while depending on reading the active row, which is document context and unavailable on exactly the surface named; and VER-DM2 form triggers only exist on the Editor type. Twelve stories cannot ship on the Workspace surface as built. I did NOT pick — this is a product decision with real trade-offs on both sides (mobile and cross-app reach vs keeping every shipped feature), so it is logged as D-DM1 with a test-pinned constraint matrix and a decision document rather than quietly resolved in code. Undisputed either way: a 30-second UI action cannot generate hundreds of documents, so batch stays server-side — which our architecture already assumes. | E48: VER-DM3; D-DM1 | F48: 42 suites / 721 tests at 100% | G48: D-DM1 blocks listing copy, scope narrative, and 5 story descriptions | H48: Sweep part 3 after D-DM1
A49: L-046 | B49: 2026-09-13 12:01 | C49: — | D49: VER-DM4: checked our listing spec against the live Marketplace page and every number in it was invented. Eight discrepancies. Two are REQUIRED assets we did not know existed — the application icons (32x32 and 128x128, plus 48x48 and 96x96 now that the project includes a web app) and the 220x140 card banner that appears on listings and in search results. One is a content rule with no check at all: the app name must not contain a Google product name. One is a missing required support link: terms of service, absent from our submission checklist. The rest were limits wrong in the strict direction — we demanded exactly 5 screenshots where 1 to 10 are accepted, rejected two screenshot sizes the platform allows, capped the name at 30 rather than 50, the short description at 120 rather than 200, and the detailed description at 4,000 rather than 16,000 — so the drafted copy was being held to constraints tighter than reality. And the promo video is an optional YouTube LINK, not the captioned 30-120 second upload we specified, which means the demo-video blocker on the board was partly self-inflicted. Rewritten against the verified spec with 13 pinning tests; LISTING_PACK.md regenerated. Sibling precedent: TestPulse found its asset spec wrong in exactly this way. | E49: VER-DM4; ST-093; ST-094 | F49: 42 suites / 729 tests at 100% | G49: Icons and card banner now needed for submission — new capture items | H49: Sweep part 4: OAuth verification + CASA
A50: L-047 | B50: 2026-09-13 12:06 | C50: — | D50: VER-DM5 — the first verification finding that takes work OFF the board. Google routes review by scope CLASSIFICATION, and a CASA security assessment is triggered by RESTRICTED scopes. DocMerge requests none: drive.file is specifically the recommended non-sensitive alternative to the restricted Drive scopes, userinfo.email is non-sensitive, and only spreadsheets.readonly and documents are sensitive — which require Google app verification but not an assessment. CASA has sat on this board as a blocking, multi-week, paid item since S6, driving R-D1 and R-D10 and appearing in the pen-test sequencing advice, all on an assumption nobody had checked. LC-3 is downgraded to "likely not required — confirm in the Cloud console under OAuth consent screen > Data Access" rather than deleted, because classification is per-project and Google may still request an assessment at its discretion; deleting it would trade one unchecked assumption for another. Found in the same pass and NOT previously on the board: verification requires an unlisted YouTube DEMONSTRATION video showing the OAuth grant flow, the consent screen displaying the app name, and detailed in-app use of each sensitive scope — separate from the optional marketing promo video, and recordable only once the app runs. The review path is now derived in code from the classifications rather than assumed, with a test proving CASA appears only when a restricted scope is present. | E50: VER-DM5; LC-3; R-D1; R-D10 | F50: 42 suites / 736 tests at 100% | G50: LC-3 to be confirmed in console, not booked blind | H50: Sweep complete — D-DM1 next
A51: L-048 | B51: 2026-09-13 16:25 | C51: — | D51: R-D4 closed with a Postgres adapter — the risk that has stood since S1, when persistence went behind typed interfaces with in-memory Maps behind them. That was the right call with no schema, but it meant the interfaces had never once been implemented against a database, and the migrations written for DM-F09 were decorative. src/postgres.ts implements TokenStore, AccountRepo and TemplateRepo against the real schema and supplies purge targets for all 18 tables, ordered children-before-parents so the per-table counts are genuine evidence rather than zeroes from an earlier cascade. The SQL client is injected, so there is no pg dependency and the whole adapter is exercisable without a database. Four details that would have bitten in production and are now pinned by tests: BIGINT expiries come back from the driver as STRINGS and are converted explicitly rather than coerced; template and rules write inside one transaction with rollback, because a half-replaced rule set renders wrong output instead of failing; an absent rule value is stored as NULL rather than the string "undefined"; and the two child tables without an account_id column are reached through their parent instead. One test purges using a SQL-injection string and asserts it never appears in any statement text. | E51: R-D4; DM-D2; DM-F09 | F51: 43 suites / 753 tests at 100% | G51: Remaining stores still in-memory; DM-D2 ratification owed | H51: D-DM1 then live execution
A52: L-049 | B52: 2026-09-13 16:29 | C52: — | D52: Continuing the adapter work turned up DM-F14 rather than a routine increment. The remaining in-memory stores are a durability gap: a process restart resets every plan limit, so each deploy silently hands every customer a fresh monthly allowance — a revenue leak that no test would ever catch, because tests start from zero anyway; billing state resets so paying customers appear to be on trial; and the tamper-evident admin audit chain evaporates AND restarts its numbering at genesis, so the loss is not even visible afterwards. Usage counters are fixed end to end: PlanLimitEnforcer now takes a UsageBackend, and WriteThroughUsageBackend serves reads from a cache primed at startup (so the synchronous limit check stays synchronous and fast) while writing through to Postgres via a single atomic upsert — read-then-write would drop increments precisely when a customer is near their limit and two generations land together. Write failures increment a counter rather than failing the customer request, because a limit check must not become failable over a counter write, but a silent failure must still be visible. A test simulates a restart and proves the allowance is preserved. The subscription and admin-audit stores are built and tested — append-only with no update path, and lastSequence so the chain continues across restarts instead of forking a second one — but their services are NOT yet wired to them, and I am flagging that explicitly rather than letting it read as done, because this codebase has already produced two built-but-never-called defects (DM-F02/F03) and I introduced a third (DM-F11) while fixing them. | E52: DM-F14; R-D4 | F52: 43 suites / 770 tests at 100% | G52: BillingService and AdminAuditLog still unwired to their stores | H52: Wire them, then telemetry/support
... A62: L-059 | B62: 2026-09-13 20:34 | C62: — | D62: Wrote STATE_OF_DOCMERGE.md rather than another module, because thirty findings and sixty-two log entries are not a thing anyone can act on. It states the position in one paragraph, lists the three decisions owed with what each costs if deferred, gives the eight external actions in their corrected order (hosting before the consent screen, since the screen requires verified authorised domains — a sequencing error I made earlier today and corrected as R-D15), and records the five lessons that outlast the individual fixes: coverage proves execution rather than correctness, since read-only mode and plan limits were fully built and tested and called from nowhere; authentication is not authorisation, and having signed sessions made the missing entitlement check look done; internal review cannot see platform reality, as two clean passes found nothing and a live-documentation sweep then found seven findings in seven checks; a plausible reason survives review indefinitely, which is why exemptions are now tests; and a sweep finds a class once while a gate finds it every commit. It closes with the assessment I would want on the record: the product has been code-complete since roughly 11:00 and has not moved one step closer to a customer since, because everything remaining needs a domain, a project, a budget or a decision — and the highest-value hour available is registering a domain and creating the GCP project, which unblocks seven of the eight remaining actions. | E62: All findings; D-DM1; R-D15; LC-1 | F62: 45 suites / 836 tests at 100% | G62: Nothing further without a decision, a sibling codebase, or live infrastructure | H62: Senthil
A64: Append one row per working session. Entry IDs L-NNN sequential. Decision refs point to portfolio decisions (D-series) or Version_Control rows.

Sheet Traceability_Matrix
A1: TRACEABILITY MATRIX — story → code → tests → coverage (D13: 100% gate on all shipped code)
A3: Story ID | B3: Sprint | C3: Requirement (from Full_Backlog) | D3: Source module(s) | E3: Test file(s) / evidence | F3: Coverage | G3: Status
A4: ST-051 | B4: S1 | C4: Marketplace OAuth install completes and lands on welcome state in <2 min | D4: docmerge-pro-s1/src/oauth.ts (exchangeCode); src/install.ts (InstallService, INSTALL_BUDGET_MS, MemoryAccountRepo) | E4: tests/oauth.test.ts (exchange + missing-refresh-token error); tests/install.test.ts (welcome state, 2-min budget pass/fail, default source, repo behaviours) | F4: 100% stmt/branch/func/line | G4: Done
A5: ST-052 | B5: S1 | C5: Uninstall webhook removes tokens, schedules data deletion per policy | D5: src/oauth.ts (revoke); src/uninstall.ts (UninstallService, RETENTION_WINDOW_MS 30d, MemoryDeletionScheduler) | E5: tests/uninstall.test.ts (revoke + delete + schedule at retention boundary, partial-install path, webhook-replay idempotency); tests/oauth.test.ts (revoke endpoint) | F5: 100% stmt/branch/func/line | G5: Done
A6: ST-055 | B6: S1 | C6: Session/token refresh survives platform token rotation | D6: src/oauth.ts (refresh, rotation adoption); src/tokenRefresh.ts (TokenRefreshManager, EXPIRY_SKEW_MS, invalid_grant → re-auth, single retry) | E6: tests/tokenRefresh.test.ts (fresh/skew, non-rotated + rotated refresh persisted, invalid_grant clears credential, transient retry succeed/fail); tests/oauth.test.ts (rotation) | F6: 100% stmt/branch/func/line | G6: Done
A7: ST-056 | B7: S1 | C7: Install telemetry: source attribution (listing/search/referral) captured | D7: src/telemetry.ts (normaliseSource, Telemetry.trackInstall, sink-failure isolation) | E7: tests/telemetry.test.ts (all 3 valid sources, unknown/undefined fallback, event envelope, dropped-event counting); tests/install.test.ts (attribution through install flow) | F7: 100% stmt/branch/func/line | G7: Done
A8: ST-001 | B8: S2 | C8: As a Office manager, I can set up Template designer with sensible defaults in one screen | D8: docmerge-pro-s1/src/templates.ts (TemplateDesigner.createWithDefaults — pdf output, filename pattern, destination folder defaulted; name+body only) | E8: tests/templates.test.ts (defaults object pinned; member denial; default id/clock) | F8: 100% stmt/branch/func/line | G8: Done
A9: ST-002 | B9: S2 | C9: As a Office manager, the Template designer happy path completes without documentation | D9: src/templates.ts (renderPreview: extractPlaceholders/extractSections, section rules applied, full substitution; TemplateValidationError with per-field Sheet-column hints) | E9: tests/templates.test.ts (end-to-end render, section include/exclude, all operators true+false, empty-value falsity, evaluateRule undefined guards, missing-field messages) | F9: 100% stmt/branch/func/line | G9: Done
A10: ST-003 | B10: S2 | C10: As a Workspace admin, I can customise Template designer rules/conditions for my workflow | D10: src/templates.ts (setRules: validates rule fields against placeholders, sections against body, comparison values present; multi-problem aggregation) | E10: tests/templates.test.ts (valid persist, unknown field, unknown section, missing value, aggregated problems, missing template, member denial) | F10: 100% stmt/branch/func/line | G10: Done
A11: ST-004 | B11: S2 | C11: As a user, Template designer shows clear errors and retry paths on platform API failures | D11: src/platformErrors.ts (mapPlatformFailure 429/5xx/403/404/unknown -> typed user messages with retry paths; withRetry exponential backoff, non-retryable passthrough) | E11: tests/platformErrors.test.ts (every failure kind, backoff delays 100/200, exhaustion, non-retry single call, pre-mapped passthrough) | F11: 100% stmt/branch/func/line | G11: Done
A12: ST-005 | B12: S3 | C12: As a Ops freelancer, Template designer works on the Workspace add-on sidebar in Sheets/Docs surface end-to-end | D12: src/sidebar.ts (SidebarController: injected SidebarHost for Sheets/Docs; open/list, openTemplate, previewFromActiveRow) | E12: tests/sidebar.test.ts (full sheets flow end-to-end, docs fallback, missing template, no-template guard, state copy) | F12: 100% stmt/branch/func/line | G12: Done
A13: ST-006 | B13: S3 | C13: As a Workspace admin, I can see Template designer performance metrics and trends | D13: src/designerOps.ts (TemplateMetrics: renders/failures/successRate/p95/trendDelta per period) | E13: tests/designerOps.test.ts (summary values, trend vs previous period, empty neutral summary, default clock) | F13: 100% stmt/branch/func/line | G13: Done
A14: ST-007 | B14: S3 | C14: As a user, Template designer respects role permissions and audit logging | D14: src/designerOps.ts (AuditLog; AuditedTemplateDesigner wrapping create/setRules/render — denied attempts recorded then re-thrown) | E14: tests/designerOps.test.ts (allowed ops logged, denied logged + rethrown, non-permission failures not logged, target filter) | F14: 100% stmt/branch/func/line | G14: Done
... A103: ST-100 | B103: S11 | C103: First 10 design-partner reviews scheduled | D103: src/launchOps.ts (PartnerReviewPipeline: at-risk refusal, stage transitions, decline handling, target summary with warnings) | E103: tests/launchOps.test.ts (healthy/watch invite, at-risk refusal, duplicate guard, full stage walk, decline no-reschedule, honest summary, stale-invite warning, copies) | F103: 100% stmt/branch/func/line | G103: Done
A105: FINAL CODE EVIDENCE — 10 Sep S1-S5 (37/101/150/180/217) · 11 Sep S6 (264) · 13 Sep S7 (305) · S8 (385) · S9 (432) · S10 (484) · 10:58 S11+S12: jest --coverage -> Tests: 516 passed / 516 total; All files 100/100/100/100 across 33 source modules; thresholds pinned at 100 throughout. tsc strict clean. Smoke green. CODE BACKLOG COMPLETE: 98 Done, 2 In progress (ST-068 third-party pen test, ST-083 demo video). Launch runbook verdict: NO-GO (8 blocking). Submission dry-run: NOT READY (10/20). Tracker v007.

Sheet Financial_Model
A1: 18-MONTH FINANCIAL MODEL — Workspace: high-volume low-ARPU PLG (edit yellow assumptions)
A3: Assumption | B3: Value
A4: Installs/mo (month 1) | B4: 120
A5: Monthly growth of that | B5: 0.15
A6: Free->paid % | B6: 0.06
A7: ARPU $/mo | B7: 19
A8: Monthly churn | B8: 0.045
A9: Marketplace fee | B9: 0
A10: Team cost month 1 (India-lean $) | B10: 12000
A11: Cost growth/mo | B11: 0.03
A12: Fee note: No marketplace fee; bill via Stripe
A14: Line | B14: M1 | C14: M2 | D14: M3 | E14: M4 | F14: M5 | G14: M6 | H14: M7 | I14: M8 | J14: M9 | K14: M10 | L14: M11 | M14: M12 | N14: M13 | O14: M14 | P14: M15 | Q14: M16 | R14: M17 | S14: M18
A15: Leads/installs | B15: =$B$4 -> 120 | C15: =B15*(1+$B$5) -> 138 | D15: =C15*(1+$B$5) -> 158.7 | E15: =D15*(1+$B$5) -> 182.505 | F15: =E15*(1+$B$5) -> 209.88075 | G15: =F15*(1+$B$5) -> 241.36286 | H15: =G15*(1+$B$5) -> 277.56729 | I15: =H15*(1+$B$5) -> 319.20239 | J15: =I15*(1+$B$5) -> 367.08274 | ... S15: =R15*(1+$B$5) -> 1291.3517
A16: New paying | B16: =ROUND(B15*$B$6,1) -> 7.2 | C16: =ROUND(C15*$B$6,1) -> 8.3 | D16: =ROUND(D15*$B$6,1) -> 9.5 | E16: =ROUND(E15*$B$6,1) -> 11 | F16: =ROUND(F15*$B$6,1) -> 12.6 | G16: =ROUND(G15*$B$6,1) -> 14.5 | H16: =ROUND(H15*$B$6,1) -> 16.7 | I16: =ROUND(I15*$B$6,1) -> 19.2 | ... S16: =ROUND(S15*$B$6,1) -> 77.5
A17: Paying accounts | B17: =B16 -> 7.2 | C17: =ROUND(B17*(1-$B$8)+C16,1) -> 15.2 | D17: =ROUND(C17*(1-$B$8)+D16,1) -> 24 | E17: =ROUND(D17*(1-$B$8)+E16,1) -> 33.9 | F17: =ROUND(E17*(1-$B$8)+F16,1) -> 45 | G17: =ROUND(F17*(1-$B$8)+G16,1) -> 57.5 | H17: =ROUND(G17*(1-$B$8)+H16,1) -> 71.6 | I17: =ROUND(H17*(1-$B$8)+I16,1) -> 87.6 | J17: =ROUND(I17*(1-$B$8)+J16,1) -> 105.7 | ... S17: =ROUND(R17*(1-$B$8)+S16,1) -> 440.9
A18: MRR (net of fee) | B18: =ROUND(B17*$B$7*(1-$B$9),0) -> 137 | C18: =ROUND(C17*$B$7*(1-$B$9),0) -> 289 | D18: =ROUND(D17*$B$7*(1-$B$9),0) -> 456 | E18: =ROUND(E17*$B$7*(1-$B$9),0) -> 644 | F18: =ROUND(F17*$B$7*(1-$B$9),0) -> 855 | G18: =ROUND(G17*$B$7*(1-$B$9),0) -> 1093 | H18: =ROUND(H17*$B$7*(1-$B$9),0) -> 1360 | I18: =ROUND(I17*$B$7*(1-$B$9),0) -> 1664 | ... S18: =ROUND(S17*$B$7*(1-$B$9),0) -> 8377
A19: Team cost | B19: =$B$10 -> 12000 | C19: =ROUND(B19*(1+$B$11),0) -> 12360 | D19: =ROUND(C19*(1+$B$11),0) -> 12731 | E19: =ROUND(D19*(1+$B$11),0) -> 13113 | F19: =ROUND(E19*(1+$B$11),0) -> 13506 | G19: =ROUND(F19*(1+$B$11),0) -> 13911 | H19: =ROUND(G19*(1+$B$11),0) -> 14328 | I19: =ROUND(H19*(1+$B$11),0) -> 14758 | J19: =ROUND(I19*(1+$B$11),0) -> 15201 | ... S19: =ROUND(R19*(1+$B$11),0) -> 19835
A20: Net cash/mo | B20: =B18-B19 -> -11863 | C20: =C18-C19 -> -12071 | D20: =D18-D19 -> -12275 | E20: =E18-E19 -> -12469 | F20: =F18-F19 -> -12651 | G20: =G18-G19 -> -12818 | H20: =H18-H19 -> -12968 | I20: =I18-I19 -> -13094 | ... S20: =S18-S19 -> -11458
A21: Cumulative | B21: =B20 -> -11863 | C21: =B21+C20 -> -23934 | D21: =C21+D20 -> -36209 | E21: =D21+E20 -> -48678 | F21: =E21+F20 -> -61329 | G21: =F21+G20 -> -74147 | H21: =G21+H20 -> -87115 | I21: =H21+I20 -> -100209 | J21: =I21+J20 -> -113402 | ... S21: =R21+S20 -> -228149
A23: Reading: churn applies before adds; MRR nets the marketplace fee; costs use India-lean base from Team_Roles_Budget (v004). Breakeven = first month Net cash ≥ 0. This is a planning model, not a forecast — replace assumptions with S7-S8 beta actuals.

Sheet GTM_Execution
A1: GTM EXECUTION TASKS
A3: Phase | B3: Task | C3: Owner (role) | D3: Target sprint
A4: Pre-launch | B4: Positioning doc + message house (problem/promise/proof) | C4: Founder | D4: S7
A5: Pre-launch | B5: Listing SEO: keyword study in marketplace search + title/intro drafts | C5: Growth | D5: S8
A6: Pre-launch | B6: 10 design-partner mini case snippets with metric proof | C6: Founder | D6: S8
A7: Pre-launch | B7: 5 comparison/alternative pages drafted | C7: Growth | D7: S9
A8: Pre-launch | B8: Screenshots (5) + 2-min demo video produced | C8: Design | D8: S9
A9: Launch | B9: Listing live + launch post + video published | C9: Growth | D9: S11
A10: Launch | B10: Founder outreach: 100 named ICP accounts, 3-touch sequence | C10: Founder | D10: S11
A11: Launch | B11: Community value-posts (3 relevant communities) | C11: Founder | D11: S11
A12: Launch | B12: Review-generation program on (in-app ask post-aha) | C12: Eng | D12: S11
A13: Post-launch | B13: Weekly SEO/how-to content cadence starts | C13: Growth | D13: S12
A14: Post-launch | B14: Marketplace paid placement pilot (where offered) | C14: Growth | D14: S12
... A16: Post-launch | B16: G2/Capterra profiles + first 10 reviews | C16: Growth | D16: S12+

Sheet Launch_Checklist
A1: PLATFORM LAUNCH CHECKLIST — Google Workspace Marketplace
A3: # | B3: Item | C3: Status
A4: 1 | B4: GCP project + OAuth consent screen configured (brand verification) | C4: Open
A5: 2 | B5: Restricted/sensitive scopes minimized; justification narrative drafted | C5: Open
A6: 3 | B6: CASA Tier 2 assessment scheduled and passed (annual renewal calendared) | C6: Open
A7: 4 | B7: Apps Script/alt-runtime quota headroom load-tested (batch generation) | C7: Open
A8: 5 | B8: Domain-install admin flow + admin console notes tested | C8: Open
A9: 6 | B9: Marketplace listing: name, graphics per asset specs, demo video | C9: Open
A10: 7 | B10: Privacy policy + DPA + data-deletion endpoint live | C10: Open
A11: 8 | B11: Drive/Sheets API exponential backoff verified under quota pressure | C11: Open
A12: 9 | B12: Template gallery seeded with 20 launch templates | C12: Done
A13: 10 | B13: In-app upgrade prompts + Stripe billing live | C13: Open

Sheet Metrics_Targets
A1: METRIC TARGETS (first 12 months post-launch)
A3: Metric | B3: M1 | C3: M3 | D3: M6 | E3: M12 | F3: Notes
A4: Installs/signups cumulative | B4: varies | C4: 3x M1 | D4: 8x M1 | E4: 20x M1 | F4: Drive via listing SEO + outbound
A5: Activation % (24h) | B5: 30% | C5: 40% | D5: 45% | E5: 50% | F5: Onboarding iterations S12+
A6: Trial→paid % | B6: baseline | C6: +2pts | D6: +4pts | E6: +6pts | F6: Pricing test at S12
A7: Rating | B7: 4.5+ | C7: 4.6+ | D7: 4.7+ | E7: 4.7+ | F7: Review program + support speed
A8: MRR | B8: first $ | C8: 3x | D8: 8x | E8: 20x | F8: Model sheet has the math
A9: Logo churn/mo | B9: <5% | C9: <4% | D9: <3% | E9: <3% | F9: Health-score saves

Sheet Risk_Register
A1: PRODUCT RISK REGISTER
A3: Risk | B3: Impact | C3: Likelihood | D3: Mitigation
A4: CASA assessment delays listing 4-8 weeks | B4: Medium | C4: High | D4: Schedule CASA at S6; scope austerity from S1
A5: Google ships native doc-gen improvements | B5: High | C5: Medium | D5: Depth on batch + e-sign + filing; template moat
A6: Low ARPU demands volume — listing SEO underperforms | B6: High | C6: Medium | D6: Template-gallery SEO + freelancer channel + comparison pages

Sheet Review_Findings
A1: COLD REVIEW PASS 1 — DocMerge Pro (13 Sep 11:24). 9 findings in code already shipped at 100% coverage.
A2: Run after memory showed every sibling product found real defects post-"code complete" — TeleField logged the lesson as L-T1: review BEFORE declaring a code phase complete. DocMerge had never had one. Checklist taken from the sibling defect classes. Coverage proves execution, not correctness (portfolio lesson F-V14).
A4: ID | B4: Severity | C4: Status | D4: Finding | E4: What was actually wrong | F4: Fix / next step
A5: DM-F01 | B5: CRITICAL | C5: FIXED | D5: No HTTP application exists | E5: 36 modules at 100% coverage and nothing that can receive a request. There is no server, no routes, and no `npm start`. The OAuth redirect URI in the setup guide, the uninstall webhook, and the form-submission webhook all point at an application that was never built. The 30-minute GCP setup guide is unrunnable as written. | F5: Framework-free Router + buildApp with 7 routes (healthz, oauth install/callback, uninstall + form webhooks, document generation, template list) + src/server.ts entrypoint and npm start. Readiness check runs BEFORE listen(). Booted for real and exercised over HTTP: healthz 200, install URL carries state, unsigned webhook 401, unauthenticated route 401, unknown route 404. 28 regression tests.
A6: DM-F02 | B6: CRITICAL | C6: FIXED | D6: Read-only mode enforced nowhere | E6: ST-060 built the dunning read-only state and assertWritable(), fully tested — and nothing ever called it. The help centre tells customers "the account becomes read-only"; the running product would have kept accepting writes forever after a failed payment. | F6: New src/entitlements.ts EntitlementGate consults it at every mutating entry point; reads deliberately stay open so an unpaid customer can still get their work out. 8 regression tests.
A7: DM-F03 | B7: CRITICAL | C7: FIXED | D7: Plan limits enforced nowhere | E7: ST-061 built PlanLimitEnforcer with 80%/100% prompts and never called check() outside its own tests. Published limits (25 documents, 2 templates, 1 seat on free) were decorative — any account could generate without bound. | F7: Same gate. Usage is recorded only AFTER success, so a rate-limited Drive call cannot burn a customer document from their allowance. 7 regression tests.
A8: DM-F04 | B8: CRITICAL | C8: FIXED | D8: OAuth install had no CSRF state | E8: exchangeCode accepted any code with no state parameter. An attacker could hand a victim a crafted install URL and bind their browser session to an attacker-controlled account. Sibling class F-015 / M-F15. | F8: OAuthStateStore: state minted before redirect, single-use, 10-minute TTL, sweepable. Rejects absent, unknown, replayed, and expired states. 6 regression tests.
A9: DM-F05 | B9: CRITICAL | C9: FIXED | D9: Webhooks unauthenticated | E9: Neither the uninstall handler nor the form-submission handler verified anything. An unauthenticated POST could revoke a live account tokens and schedule its data for deletion, or generate documents against any template. | F9: New src/webhookSecurity.ts: HMAC-SHA256 signature with timing-safe compare, 5-minute timestamp window against replay, and a FIFO-bounded dedupe ledger. 9 regression tests.
A10: DM-F06 | B10: HIGH | C10: FIXED | D10: No production backoff existed | E10: Every RetryOptions in the codebase came from a test injecting a no-op sleep, and DEFAULT_RETRY omitted sleep entirely. The retry logic was exercised 100% but had no real delay behind it anywhere — sibling F-V06 exactly. | F10: PRODUCTION_RETRY + realSleep exported as the policy production code uses.
A11: DM-F07 | B11: HIGH | C11: FIXED | D11: Identity is caller-declared | E11: Role arrives as a parameter on 28 signatures and nothing authenticates it. Whoever calls the service declares their own privilege level. Sibling M-F11 (fixed with signed sessions) and VoiceBridge F-V21 (left open by direction). | F11: src/session.ts: HMAC-signed sessions carrying account, email, role and expiry. Editing the role in a token now fails signature verification, and a session for one account is refused against another. Every mutating route derives identity from the session instead of a caller-supplied parameter. 8 regression tests.
A12: DM-F08 | B12: MEDIUM | C12: FIXED | D12: Eleven unbounded ledgers | E12: Audit entries, metric samples, error tracker, usage events, invoices, exit surveys and more only ever push. A long-running process grows until it dies. Sibling class fixed portfolio-wide as FIFO-capped ledgers. | F12: New src/ledger.ts: FIFO-bounded with EVICTION COUNTED, not silent — a metric that quietly started sampling only the recent past would misreport trends invisibly. Applied to all 11 ledgers. The hash-chained admin audit log needed care: once entries evict, the chain can no longer verify from genesis, so the last evicted digest becomes the anchor and verifyChain now reports truncation rather than failing. Sequence numbers keep counting so gaps are visible.
A13: DM-F09 | B13: MEDIUM | C13: FIXED | D13: Deletion has no implementation behind it | E13: SelfServeDataRights.executeDue takes a deleter callback that no production code supplies. The published 30-day deletion policy has nothing that actually purges. Sibling class F-009 / M-F03 / F-TP01, where it breached the published policy in five products. | F13: New src/purge.ts PurgeRegistry over 16 known stores, with verifyRegistration failing the build when a store has no purge target — so adding a store without wiring deletion breaks CI rather than the published policy. Receipts carry per-store row counts as evidence; a failing store is recorded, the rest still purge, and the receipt is marked INCOMPLETE rather than claiming success. Plus the schema that never existed: 3 ordered migrations, every account-scoped table ON DELETE CASCADE, npm run migrate, and a test asserting cascade on every table.
A14: — COLD REVIEW PASS 2 (new HTTP layer, 13 Sep 11:37) — sibling lesson L-OC4: new surfaces inherit old blind spots —
A15: DM-F10 | B15: HIGH | C15: FIXED | D15: Request body read without a cap | E15: readBody accumulated chunks with no limit on an open port — a single large POST is a memory-exhaustion vector, and no authentication is needed to send one. | F15: MAX_BODY_BYTES cap with BodyTooLargeError; server returns 413. Verified live: a 2MB POST returns 413.
A16: DM-F11 | B16: MEDIUM | C16: FIXED | D16: Abandoned OAuth states accumulated forever | E16: Every started-and-abandoned install left a state entry behind. sweep() existed and — exactly like DM-F02/F03 — was never called by anything. | F16: The install route sweeps opportunistically before issuing. Regression test proves expired states are dropped.
A17: DM-F12 | B17: MEDIUM | C17: FIXED | D17: No rate limiting on any route | E17: Unauthenticated endpoints were unlimited. An open loop against /oauth/install both grew memory and farmed valid CSRF states; webhook endpoints burned CPU on signature checks an attacker never needed to pass. | F17: New src/rateLimit.ts fixed-window limiter: 20/min install, 600/min webhooks, 300/min authenticated, keyed per caller, with bounded key eviction and Retry-After. Verified live: 429 after 20, a different caller unaffected.
A18: DM-F13 | B18: LOW | C18: FIXED | D18: /healthz leaked the build version anonymously | E18: A deploy probe needs liveness, not a build identifier telling an attacker which advisories apply. Sibling OnCall flagged the same class (GAP/VER-OC4). | F18: Version returned only to a caller presenting the operator token. Verified live both ways.
A19: — EXTERNAL VERIFICATION SWEEP vs live Google docs (13 Sep 11:51) — sibling pattern: every product found live-blocking defects here —
A20: VER-DM1 | B20: LIVE-BLOCKING | C20: FIXED | D20: No uninstall webhook exists on this platform | E20: Verified against live Google docs 13 Sep 2026: the Workspace Marketplace does not push an uninstall webhook to a developer server, and the licenseNotification resource that once reported provisions and deletions is DEPRECATED with no replacement in the Marketplace API. Our POST /webhooks/uninstall was a handler for an event that will never arrive — so ST-052 token revocation, the 30-day retention clock, ST-053 re-install restore and the whole purge chain would simply never have run in production. Two clean cold-review passes could not see this; it is a fact about the platform, not the code. | F20: New src/licenseReconciler.ts detects uninstall instead of receiving it: periodic license-state reconciliation (userLicense/customerLicense remain supported) plus immediate action on a revoked credential. An API outage or unknown state NEVER counts as an uninstall — that would revoke a live customer and start a deletion clock against them. Detection lag is reported rather than hidden. Idempotent, and re-arms on re-install. 10 regression tests.
A21: VER-DM2 | B21: LIVE-BLOCKING | C21: FIXED | D21: Google Forms cannot POST to an arbitrary URL | E21: Verified against live Apps Script docs: form submit is not a simple trigger — it requires an INSTALLABLE Apps Script trigger, and the script itself must call UrlFetchApp. Nothing in Google will ever call our /webhooks/form endpoint. The entire F5 feature (ST-041..050, 10 stories / 42 pts) rested on a platform capability that does not exist. | F21: apps-script/FormForwarder.gs ships the missing half: an idempotent installable trigger that signs each submission with the same HMAC scheme and headers the endpoint already verifies, keeps the secret in Script Properties rather than the script body, uses the stable response id so our dedupe works, and rethrows only on 5xx so Apps Script retries a server failure but not a rejection. Contract pinned by 6 tests against the .gs file. NOTE: this changes the customer setup flow — the help-centre article and ST-041 "one screen" claim need rewording.
A22: VER-DM3 | B22: LIVE-BLOCKING | C22: OPEN — DECISION (D-DM1) | D22: Two add-on types, and our features are split across both | E22: Verified against live Google docs: a Google Workspace add-on is card-based and MUST NOT use HTML/CSS, cannot read the open document (no SpreadsheetApp.getActiveSpreadsheet()), has no Apps Script triggers, and is not available in Google Forms — but reaches mobile and every host app. An Editor add-on has HTML sidebars, document context and Apps Script triggers, but is desktop-only and Editors-only. Five shipped stories say the feature "works on the Workspace add-on sidebar in Sheets/Docs end-to-end" while depending on reading the active row — document context, which that surface does not have. The form feature needs Apps Script triggers, which only the Editor type has. On the Workspace surface, 12 shipped stories cannot ship as built. | F22: src/addonSurface.ts encodes the verified constraint matrix and reports what each surface costs, with the assessment pinned by 14 tests; ADDON_SURFACE_DECISION.md presents it. NOT FIXED IN CODE ON PURPOSE — this is a product decision (D-DM1), not a defect: Editor add-on keeps every shipped feature but is desktop-only and Editors-only; Workspace add-on reaches mobile and all host apps but needs four features redesigned as cards and the form feature dropped or split. Undisputed either way: batch must stay server-side, since a 30-second UI action cannot generate hundreds of documents.
A23: VER-DM4 | B23: HIGH | C23: FIXED | D23: The entire listing asset and copy spec was invented, and wrong in eight ways | E23: Verified against the live "Create a store listing" page: (1) we demanded exactly 5 screenshots — the platform accepts 1 to 10; (2) we rejected the 640x400 and 2560x1600 sizes it also accepts; (3) the app NAME limit is 50 characters, not 30, AND must not contain a Google product name — a rule we had no check for at all; (4) short description is 200 characters, not 120; (5) detailed description is under 16,000, not 4,000; (6) the promo video is an OPTIONAL YouTube LINK, not a required captioned 30-120s upload; (7) REQUIRED application icons (32x32 and 128x128, plus 48x48 and 96x96 because our project now includes a web app) were absent from our spec entirely; (8) the REQUIRED 220x140 card banner shown on listings and search results was absent too. Also missing from the submission checklist: the terms-of-service link, which the listing requires. | F23: src/listing.ts rewritten against the verified spec with icons, card banner, accepted-size list, optional YouTube video and required support links; validateAssets now takes the full asset set rather than screenshots-and-a-video. LISTING_PACK.md regenerated. 13 tests pin the corrected behaviour, including the two previously-missing required asset families and the forbidden-Google-name rule. Sibling precedent: TestPulse found its asset spec wrong the same way (Rule-of-3 vs its invented 5x1600x1000).
A24: VER-DM5 | B24: HIGH (favourable) | C24: FIXED | D24: CASA is not triggered by our scope set — and a required video was missing | E24: Verified: Google routes review by scope CLASSIFICATION. Non-sensitive only = verification optional; any sensitive = Google app verification; any RESTRICTED = verification plus a CASA security assessment. DocMerge requests no restricted scopes — drive.file is specifically the recommended non-sensitive alternative to the restricted Drive scopes, and userinfo.email is non-sensitive. Only spreadsheets.readonly and documents are sensitive, which require verification but NOT an assessment. CASA has sat on the board as a blocking, multi-week, paid item since S6 (R-D1, R-D10, LC-3) on an assumption nobody checked. SEPARATELY: verification requires an UNLISTED YouTube demonstration video showing the OAuth grant flow, the consent screen displaying the app name, and detailed in-app use of each sensitive scope — a requirement we did not have, and distinct from the optional marketing promo video. | F24: src/scopes.ts now carries each scope classification and derives the review path from it (assessReviewPath), with 7 tests including one proving CASA appears only when a restricted scope is present. SCOPE_NARRATIVE.md regenerated with the path, the classification table, and the verification requirements. CAVEAT PRESERVED: classification is confirmed per project in the Cloud console under OAuth consent screen > Data Access, and Google may request an assessment at its discretion — so LC-3 should be re-checked there rather than deleted.
A25: DM-F14 | B25: HIGH | C25: FIXED | D25: State that must survive a restart does not | E25: Continuing the adapter work surfaced a finding rather than just an increment: three in-memory stores lose state whose loss is not cosmetic. USAGE COUNTERS — a restart resets every plan limit, so each deploy silently hands every customer a fresh monthly allowance; that is a direct revenue leak and it would never appear in a test, because tests start from zero anyway. SUBSCRIPTIONS — billing state resets, so paying customers appear to be back on trial. ADMIN AUDIT — a tamper-evident chain that evaporates on restart is not evidence, and worse, it would restart numbering at genesis so the gap would not even be visible. | F25: Usage counters FIXED end to end: PlanLimitEnforcer now takes a UsageBackend, and WriteThroughUsageBackend serves reads from a primed cache (keeping the limit check synchronous) while writing through to Postgres with an atomic single-statement upsert — read-then-write would lose increments exactly when a customer is near their limit. Write failures are counted rather than failing the customer request. A test proves a restarted backend primes from the store and still blocks at the limit. Subscription and admin-audit STORES are shipped and tested (append-only with no update path, lastSequence so the chain continues rather than restarting at genesis) but the services are NOT yet wired to them — deliberately left visible rather than claimed, given this codebase has already produced two built-but-never-called defects. — CLOSED 16:34: BillingService now takes a SubscriptionBackend and persists after EVERY mutation (subscribe, plan change, payment failure, each dunning transition, cancel), and AdminAuditLog takes an AdminAuditBackend with resume() so a restarted process continues a tenant chain instead of forking a second one at genesis. Write-through backends for both keep reads synchronous while writing to Postgres, counting failures rather than failing the customer request.
A26: DM-F15 | B26: HIGH | C26: FIXED | D26: Admin audit log had no tenant scope | E26: Found while wiring DM-F14, not by looking for it: AdminAuditEntry had no accountId at all, so every customer shared ONE chain and ONE sequence counter. exportCsv returned the whole log, meaning one customer security review would have handed them every other customer admin history — roles changed, members removed, data exports requested. The sequence numbering also leaked each tenant activity volume to the others. The schema written for DM-F09 keys admin_audit_entries on (account_id, sequence); the code never matched it, and nothing caught the mismatch because the table had no implementation behind it until today. | F26: accountId added to the entry and to record(); chains, anchors and sequence counters are now per account; list(), verifyChain() and exportCsv() all take an accountId; the digest covers the accountId so an entry cannot be replayed into another tenant chain. Four regression tests, including one asserting an export contains the requesting account records and not another.
A27: — TENANT-ISOLATION SWEEP (13 Sep 16:39), run because DM-F15 was found by accident —
A28: DM-F16 | B28: CRITICAL | C28: FIXED | D28: Cross-tenant template access, reachable through the live HTTP route | E28: The deliberate tenant sweep found this first: template lookups took a templateId and nothing else. POST /accounts/:accountId/documents takes the templateId from the REQUEST BODY, so an authenticated user of one account could pass another account template id and both read its body and generate documents from it. The session check I added for DM-F07 proved who was asking; nothing checked what they were asking for. | F28: Ownership enforced centrally in mustGet(templateId, accountId) so a new call site cannot forget it; setRules and renderPreview now take the accountId, threaded through batch, form triggers, the sidebar and the audited wrapper. A template belonging to another account reports "not found" rather than "wrong account", so the id space cannot be probed. Two regression tests, including one asserting the cross-tenant failure is indistinguishable from a genuinely missing template.
A29: DM-F17 | B29: HIGH | C29: FIXED | D29: Cross-tenant signature-request access | E29: Same shape: sign-request lookups took only a requestId, so one account could read another tenant signature request, change its rules, or send it. Reading exposes signer names and emails and the document name. | F29: get(), setRules() and send() now require the owning accountId, checked centrally in mustGet with the same not-found response. Three regression tests.
A30: DM-F18 | B30: HIGH | C30: FIXED | D30: Feature audit log had no tenant scope | E30: The same defect as DM-F15, in the second audit log: AuditEntry had no accountId, so forTarget() returned entries across accounts. | F30: accountId added to the entry and to record(); forTarget() takes an accountId and filters on it; every call site across batch, filing, form triggers, e-sign and the designer wrapper now supplies the owning account.
A31: DM-F19 | B31: MEDIUM | C31: Open | D31: Metrics summaries aggregate across all tenants | E31: EsignMetrics.summary(period), FilingMetrics.summary(period) and FormMetrics.summary(period) take no account and aggregate globally. Wired to a per-account dashboard they would show every customer combined numbers; used for internal analytics they are correct as-is. | F31: Needs the same accountId treatment, or an explicit decision that these are internal-only. Not fixed blind because the answer depends on where they are surfaced.
A32: DM-F20 | B32: MEDIUM | C32: Open | D32: Support inbox is not tenant-scoped | E32: SupportInbox.status(conversationId) has no account check and breaches() returns every account unanswered conversations. Acceptable for a single-operator internal queue, a leak if ever exposed per-customer. | F32: Same decision as DM-F19 — scope it or document it as operator-only.
A33: DM-F21 | B33: HIGH | C33: FIXED | D33: Cross-tenant CONTROL operations, found by the new automated gate | E33: The manual sweep checked reads. It missed writes-that-are-not-reads: pause and resume took only an entity id, so one account could pause or resume another account signature request, form trigger or batch job — a denial of service against a competitor tenant needing nothing but a guessed id. InvoiceBook.renderCsv would render any account invoice, carrying their billing contact and tax identifiers. SidebarController.openTemplate read another account template metadata before the ownership check downstream. The gate flagged 28 methods; triage found these five clusters genuine and the rest legitimately scoped by construction. | F33: Pause state is now namespaced per account and e-sign pause/resume verify ownership; renderCsv requires the owning account; openTemplate reports another account template as missing. The remaining 23 flagged methods are EXEMPTED WITH WRITTEN REASONS in the gate config — repository primitives whose ownership is enforced one level up, a generic keyed utility that callers namespace, signer actions by external parties who have no account, controllers that hold the account and delegate, and the metrics/support cases already logged as DM-F19/F20 pending your decision.
A34: DM-F22 | B34: MEDIUM | C34: FIXED | D34: An exemption reason was false — found by auditing my own exemptions | E34: The tenant gate exempted PauseManager because "callers pass account-namespaced keys". Auditing that claim showed it was untrue: e-sign passed a bare requestId and batch a bare templateId. Consequence, demonstrated before fixing: a single shared PauseManager puts template ids, sign-request ids, job ids and trigger ids in ONE namespace, so pausing a template called X also reports a sign request called X as paused. Different services happened to receive different instances, so nothing broke — and nothing enforced that either. The real protection for e-sign was an ownership check, not namespacing, so the exemption was right about the outcome and wrong about the reason, which is the kind of note that survives into a security review unchallenged. | F34: pauseKey(entity, accountId, entityId) is now the only way keys are formed, across templates, sign requests, batch jobs, form triggers and filing. Three tests verify the exemption CLAIMS rather than restating them: one scans the source and fails if any PauseManager call omits pauseKey, one proves a shared manager cannot confuse two entity types sharing an id, and one asserts only the designer and sidebar touch a template repository directly. The exemption reason was rewritten to say what is actually true.
A35: DM-F23 | B35: PROCESS | C35: CLOSED | D35: All 23 gate exemptions converted from prose to verified claims | E35: DM-F22 showed an exemption can be right about its outcome and wrong about its reason, and still read as handled. That makes the other 22 a standing risk rather than a completed judgement: each asserts a protection exists somewhere else, and nothing checked whether it did. | F35: Every exemption now has a test that checks its claim against behaviour or source: the sandbox holds no account, store or repository reference and its two sessions are distinct; purgeAccount takes the account as its subject; the status page has no tenant concept anywhere; createJobWithDefaults takes the account first; signer actions reject a non-signer holding a valid request id, and accept a listed signer with no account; a batch sidebar bound to one account cannot run another account template; both sidebar controllers stamp their own account onto what they create; and per-entity metrics and the support inbox are confirmed absent from every HTTP route, which is what makes DM-F19/F20 decisions rather than live leaks. Plus a META-GATE: unverifiedExemptions() fails the build if an exemption is added without a test naming it, with a test proving the meta-gate itself catches one.
A36: VER-DM6 | B36: HIGH | C36: FIXED | D36: Our SLO and load test promised throughput the platform forbids | E36: Verified against live Google docs: the Docs API allows 60 WRITE requests per minute per user per project (600 per project). ST-087 set a 1500ms p95 budget per generated row and ST-088 drove 100 requests per minute at 5x expected traffic and reported PASS. One user cannot exceed one document per second however fast our code runs; past 60 in a minute they receive 429s and our own backoff makes the p95 worse. A 500-row batch for one customer cannot complete in under EIGHT MINUTES — a fact absent from every estimate, board and SLO we have written. The load test never touched the ceiling because it drove an injected worker, so its PASS measured the harness, which is R-D9 restated with the actual number behind it. Also recorded: Apps Script UrlFetch is capped at 20,000/day consumer and 100,000/day Workspace, which is the real per-customer ceiling on the VER-DM2 form forwarder. | F36: src/platformQuotas.ts holds the verified numbers with their sources and refuses to guess an unrecorded quota; checkFeasibility() fails when an internal promise exceeds an external quota; QuotaGovernor paces per account and gives an honest completion estimate (500 rows = 8 minutes minimum). runLoadTest now REFUSES to pass a profile that drives more than a declared platform ceiling, reporting that it proves the harness rather than capacity. The p95 budgets carry a comment distinguishing per-row latency from batch completion, which are different promises. — COMPLETED 19:33: the batch runner now paces THROUGH the governor rather than beside it, waiting before each write instead of after a rejection, and BatchResult carries quotaWaitMs so a slow batch reads as "paced by Google's limit" rather than "the product is slow". Metering is per account, so one large batch cannot slow another customer. The help-centre article now states the real figures — about 60 documents a minute, roughly eight minutes for 500 — and is findable by searching "how long", "slow" or "quota".
A37: VER-DM7 | B37: MEDIUM | C37: FIXED (with a caveat kept) | D37: Drive quota was unrecorded, and Google is mid-migration between two models | E37: VER-DM6 built a module that refuses to guess an unrecorded quota, and the filing path promptly tripped it: we write to Drive on every generated document and had recorded no Drive limit. Checking produced an awkward answer rather than a clean one. One published page gives 12,000 queries per 60 seconds per user; another describes a quota-unit model at 1,000,000 units per minute per project and 325,000 per user; and projects that used the API before May 2026 reportedly keep legacy request counts until the rollout finishes. Which applies depends on the age of the project we have not created yet. | F37: Recorded the conservative published figure WITH the ambiguity attached rather than resolving it by picking whichever number suited us, and added a caveat field so an unreliable quota is visibly unreliable. The useful conclusion is that on every one of these models Drive sits two orders of magnitude above the Docs ceiling of 60 writes per minute per user, so filing is NOT the binding constraint on a batch — document creation is, and the governor is already configured to it. bindingConstraint() computes which API throttles first, with a test proving Docs governs today and another proving a future quota change that reverses it would surface rather than silently slowing every run.
