Workbook

Sheet Version_Control
A1: VERSION CONTROL — ShiftDesk
A3: Version | B3: Date | C3: Author | D3: Change | E3: Status
A4: v001-v004 | B4: 2026-09-05 | C4: Claude for Senthil/KP | D4: Lineage: marketplace master (868 entries) -> portfolio plan (12 products) -> this product selected for wave-1 | E4: Released
A5: v005 | B5: 2026-09-05 19:34 | C5: Claude for Senthil/KP | D5: Full product workbook for ShiftDesk on Microsoft Teams App Store / AppSource: spec, screen inventory, 100+ story backlog, live sprint board, 18-month financial model (editable assumptions), GTM execution tasks, platform launch checklist, metric targets, risk register | E5: Released
A6: v006 | D6: PLANNED: post-S0 re-baseline after discovery interviews; verified platform terms; wireframe links added to Screens sheet | E6: Planned
A7: v006 | B7: 2026-09-10 22:26 | C7: Claude for Senthil/KP | D7: Development executed per sprint board S1-S8 + S9 partials: 16 TS modules + 9 React screens built; 15 Jest suites / 67 tests at 100% coverage (statements/branches/functions/lines gate enforced, per D13); CI workflow; least-privilege + retention docs. Backlog statuses updated (75 Done, 8 code-complete pending live, 1 in progress, 16 backlog). Added Sprint_Tracker_Log and Traceability_Matrix sheets. | E7: Released
A8: v007 | B8: 2026-09-10 22:54 | C8: Claude for Senthil/KP | D8: Session 2: jest-axe WCAG suite on all 9 screens in CI (ST-089; 16 suites/76 tests, 100% coverage held); submission dry-run recorded in Launch_Checklist (ST-097); launch content drafted — listing A/B, pricing+FAQ, trust page, 15 help articles, admin guide, positioning one-pager, runbook, incident template, video script (ST-080/083/084/093/095/096/098). Statuses: 75 Done / 9 pending live / 2 in progress / 6 drafted / 8 backlog. | E8: Released
A9: v008 | B9: 2026-09-10 23:10 | C9: Claude for Senthil/KP | D9: Session 3 — live-sweep readiness: Teams app manifest v1.17 + icons (teams-app/, sideload-ready), typed env config loader with fail-fast validation + redacted print, 12-step scripted live verification sweep mapped to the pending-live stories, 30-min dev tenant + Partner Center guide. 18 suites / 85 tests, 100% coverage held. Story statuses unchanged (live-gated); Launch_Checklist #2 advanced. | E9: Released
A10: v009 | B10: 2026-09-11 08:20 | C10: Claude for Senthil/KP | D10: Session 4 (morning) — ops parity pack: k6 load harness at 5x launch traffic with perf-budget thresholds (ST-088), blue/green deploy workflow with 100%-test gate + smoke + approval-gated switch (ST-092), scripted backup/restore drill with RTO/RPO pass bar (ST-090) — all Drafted (execution live-gated). Statuses: 75 Done / 9 pending live / 2 in progress / 9 drafted / 5 backlog. 18 suites / 85 tests at 100% unchanged. | E10: Released
A11: v010 | B11: 2026-09-11 12:51 | C11: Claude for Senthil/KP | D11: Session 5 — adversarial cold-review pass 1: 6 defects found and FIXED with regression tests (F-001 no payment-recovery path, F-002 duplicate-install data loss, F-003 unbounded ledgers, F-004 backoff never applied, F-005 negative amounts auto-approved, F-006 CSV quoting), 2 findings OPEN for disposition (F-007 breaker half-open, F-008 audit-log persistence), 1 evidence-discipline finding corrected by building ST-066 crypto module (AES-256-GCM + SecretsVault). REVIEW_PACK.md for external second reviewer. 20 suites / 94 tests, 100% x4, zero pragmas. New Review_Findings sheet. | E11: Released
A12: v011 | B12: 2026-09-11 20:30 | C12: Claude for Senthil/KP | D12: Session 6 — cold-review pass 2 (F-010 importer RFC-4180 closing RAID R-S7, F-011 alert dedupe+cap, F-012 latency rolling window, F-013 trial banner shown to paying accounts; OBS-SD1 pause semantics for disposition — review complete across all modules, 10 defects total) + completion wave (ST-081 chat SLA engine making vendor optional per D-SD4, ST-100 partner tracker with honest G-02 math, ST-099 SEO engine sandbox half, ST-080 ranked help search + manifest gate, ST-068 SECURITY_EVIDENCE.md, ST-094 ASSET_PLAN.md, ST-095 pricing drift gate). BACKLOG ZERO — SHIFTDESK CODE PHASE COMPLETE (fourth product). 75 Done / 13 code-complete pending live / 3 in progress / 9 drafted / 0 backlog. 22 suites / 109 tests at 100% zero pragmas. | E12: Released
A13: v012 | B13: 2026-09-13 09:52 | C13: Claude for Senthil/KP | D13: Session 7 — external verification sweep vs live Microsoft docs + artifact-gap audit: 2 STORE-BLOCKING findings fixed (VER-SD01 screenshot spec was 1920x1080, actual 1366x768/1MB/min-3/mobile-mandatory; VER-SD02 manifest schema v1.17 -> v1.19), 1 LIVE-BLOCKING gap closed (VER-SD08 static tabs had no TeamsJS handshake — would have rendered blank in Teams), VER-SD03 deprecated permissions block removed, VER-SD04 permission model corrected from org-wide Graph .All scopes to resource-specific consent (LC-5 was wrongly Done), VER-SD06 outline icon tightly cropped, VER-SD05 verified-correct items pinned, VER-SD07 Microsoft Marketplace naming noted (3% fee confirmed). Live sweep 12 -> 14 steps. 24 suites / 120 tests at 100% zero pragmas. Story counts unchanged. | E13: Released
A14: v013 | B14: 2026-09-13 10:01 | C14: Claude for Senthil/KP | D14: Session 8 — artifact-gap audit round 2 (manifest promises vs shipped code): GAP-SD1 LIVE-BLOCKING three declared static tabs had no page behind them — web/ layer built (TabShell, typed TabApi, entry mount, index.html with TeamsJS ordered before the bundle, esbuild -> web-dist/); GAP-SD2 the three advertised bot commands had no handler — botRouter built; GAP-SD3 store package hygiene (bundles moved out of teams-app/, contents asserted); GAP-SD4 ST-094 partially unblocked via a headless-verified 1366x768 demo capture surface. 26 suites / 145 tests at 100% across src/ AND web/, zero pragmas. | E14: Released
A15: v014 | B15: 2026-09-13 10:24 | C15: Claude for Senthil/KP | D15: Session 9 — cold-review pass 3 over the previously unreviewed session 5-8 code: 6 defects fixed with pinned regressions (F-014 Infinity approval amounts, F-015 empty checklist title promoted the first task, F-016 SSO token validated then never sent so every tab call was unauthenticated, F-017 non-idempotent TeamsJS bootstrap, F-018 internal error codes shown to frontline users, F-019 configured trial length ignored by the billing engine) plus OBS-SD2 dead defensive branch removed. Running total 19 defects + 3 observations across three passes. 27 suites / 151 tests at 100% zero pragmas; story counts unchanged (correctness release). | E15: Released
A16: v015 | B16: 2026-09-13 10:37 | C16: Claude for Senthil/KP | D16: Session 10 — artifact-gap audit round 3 (client calls vs server routes): GAP-SD5 LIVE-BLOCKING — no HTTP server existed and three of five tab paths plus the Azure Bot messaging endpoint had no handler; every tab would have loaded then failed on first call. Built src/server.ts (auth-enforced router incl. /api/messages, /health, /status) + src/bootstrap.ts (node:http, config-driven, verified over a real socket) and the dispatcher routes behind them; added a parity test that reads web/tabApi.ts so the gap class now fails CI. Sweep 14 -> 15 steps. OBS-SD3 second dead defensive branch removed. 29 suites / 163 tests at 100% zero pragmas; story counts unchanged. | E16: Released
A17: v016 | B17: 2026-09-13 10:42 | C17: Claude for Senthil/KP | D17: Session 11 — verification sweep 2 over the bot transport seam: 2 LIVE-BLOCKING defects introduced by session 10 and caught here (VER-SD09 endpoint demanded our tab SSO token and a {text} body where Teams sends a Connector JWT and an Activity; VER-SD10 replies were returned in the HTTP body instead of posted to the Connector at serviceUrl) plus VER-SD11 identity source and VER-SD12 conversationUpdate/welcome + activity ack and retry dedupe. src/botTransport.ts built as a distinct trust boundary, server gains an async activity path, bootstrap takes bot deps; k6 harness, sweep wording and dev guide corrected. 30 suites / 174 tests at 100% zero pragmas; story counts unchanged. | E17: Released
A18: v017 | B18: 2026-09-13 10:57 | C18: Claude for Senthil/KP | D18: Session 12 — verification sweep 3 over the tab SSO seam: VER-SD13 LIVE-BLOCKING — the tab had been sending the literal string "teams-sso" as its token since session 8, while the manifest has declared SSO since session 3. Real flow implemented end to end: getAuthToken() with caching and consent-error handling client-side; full Entra v2 claim validation server-side (four audience forms, issuer-tenant match, version, oid/tid, exp/nbf, access_as_user scope) with the JWKS check as an explicit injected seam. VER-SD14: Expose-an-API step added to the dev-tenant guide without which SSO cannot work at all. Sweep 15 -> 16 steps. 31 suites / 181 tests at 100% zero pragmas; story counts unchanged. | E18: Released
... A47: v046 | B47: 2026-09-20 16:40 | C47: Claude for Senthil/KP | D47: Session 41: independent review V001 actioned in full. Full_Backlog +47 SD stories (147 total, none dropped) with Sprint_Board extended to S20 and its ranges retargeted. Review_Findings carries the disposition of all 20 P-series findings and all 8 D-series decisions, generated from the shipped REVIEW_PACK.md so workbook and code cannot disagree, plus own goals F-071 and F-072. Financial_Model rebuilt (P-018/D-01/D-02): cash-in and opening-cash inputs, closing-cash and runway rows, a computed breakeven month, a stated funding requirement, and a per-site pricing scenario beside the per-seat one — the reviewer's Scenario A result is reproduced rather than argued with. Metrics_Targets restated with absolute values and a named measurement source per row (D-03). Risk_Register rewritten with the free first-party overlap as the top risk (D-04). Launch_Checklist gains #11 Fulfillment (D-08), #12 residency/legal, #13 durability and #14 recording that the trust page stays unpublished (D-07). Companion tracker v040; codebase v0.14.0 at 68 suites / 552 tests, 100% four ways with zero pragmas, 9/9 real-Postgres integration tests, backup drill PASS at RPO 0s / RTO 0s. Own goals F-071..F-074 recorded, two of them in the release gate itself. | E47: Released

Sheet ReadMe_Scope
A1: ShiftDesk — Shift comms + approvals + checklists bot for frontline teams inside Teams
A3: PLATFORM: Microsoft Teams App Store / AppSource | CATEGORY: Frontline Workforce
A4: PROBLEM: 320M+ Teams MAU but frontline tooling is either heavy (dedicated WFM) or absent
A5: DIFFERENTIATION: Bot-first UX, works on Teams mobile, per-frontline-seat pricing far under WFM suites
A6: ICP: Enterprises 500-20k employees with frontline workforce (retail, logistics, healthcare) on M365 F/E plans
A8: HOW TO USE: Full_Backlog is the single source of truth (edit Status column during execution). Sprint_Board recalculates points per sprint automatically. Financial_Model assumptions (yellow) are editable — the 18-month build recalculates. Launch_Checklist is the platform-specific gate before submission. All costs/timelines are market-standard estimates; verify platform terms (fees/review rules) during S0.
A10: STACK ASSUMPTION (market standard): TypeScript/Node or platform-mandated runtime, React frontends, Postgres, hosted on AWS/GCP/platform FaaS as required, GitHub Actions CI, PostHog + Sentry telemetry, Intercom-class support.

Sheet Product_Spec
A1: PRODUCT SPEC
A3: Module (feature) | B3: Scope in MVP | C3: Out of scope (v1) | D3: Non-functional requirements
A4: Shift handover threads | B4: Shift handover threads: end-to-end happy path + edge cases + permissions | C4: Advanced automation, AI beyond listed, multi-language beyond launch set | D4: p95 <500ms API / <2s UI loads
A5: Approval workflows | B5: Approval workflows: end-to-end happy path + edge cases + permissions | C5: Advanced automation, AI beyond listed, multi-language beyond launch set | D5: 99.5% monthly uptime
A6: Digital checklists | B6: Digital checklists: end-to-end happy path + edge cases + permissions | C6: Advanced automation, AI beyond listed, multi-language beyond launch set | D6: WCAG AA
A7: Kudos/recognition | B7: Kudos/recognition: end-to-end happy path + edge cases + permissions | C7: Advanced automation, AI beyond listed, multi-language beyond launch set | D7: SOC2-track controls
A8: Manager dashboard | B8: Manager dashboard: end-to-end happy path + edge cases + permissions | C8: Advanced automation, AI beyond listed, multi-language beyond launch set | D8: Rate-limit safe (backoff+queue)
A10: Persona | B10: Jobs-to-be-done
A11: Ops director | B11: Buys on compliance + task completion rates
A12: IT admin (M365) | B12: Gatekeeper; conditional access, app permission policies
A13: Frontline supervisor | B13: Daily user; mobile-first, zero training tolerance

Sheet Screens_Wireframes
A1: SCREEN INVENTORY (attach Figma links in col E during S0)
A3: # | B3: Screen | C3: Purpose | D3: Key elements | E3: Wireframe link
A4: 1 | B4: Onboarding / first-run | C4: Reach aha in <1 day | D4: Checklist, sample data toggle, connect steps
A5: 2 | B5: Home dashboard | C5: Daily habit surface | D5: KPI cards, activity feed, alerts
A6: 3 | B6: Shift handover threads workspace | C6: Core value surface | D6: List+detail, bulk actions, status chips
A7: 4 | B7: Approval workflows builder | C7: Configure second pillar | D7: Rule builder, preview, test mode
A8: 5 | B8: Digital checklists view | C8: Differentiator surface | D8: Timeline/visual, export
A9: 6 | B9: Settings & team | C9: Roles, notifications, data | D9: Role matrix, API keys, danger zone
A10: 7 | B10: Billing | C10: Plan/trial/invoices | D10: Plan cards, usage meter, invoices
A11: 8 | B11: Analytics | C11: Prove ROI | D11: Funnel, cohort, export
A12: 9 | B12: Help & support | C12: Deflect + assist | D12: Search, chat, status

Sheet Full_Backlog
A1: FULL BACKLOG — 147 stories (100 original ST + 47 SD from independent review V001, none dropped)
A3: ID | B3: Epic | C3: Story | D3: Points | E3: Priority | F3: Sprint | G3: Status
A4: ST-001 | B4: F1 | C4: As a Ops director, I can set up Shift handover threads with sensible defaults in one screen | D4: 5 | E4: P0 | F4: S2 | G4: Done
A5: ST-002 | B5: F1 | C5: As a Ops director, the Shift handover threads happy path completes without documentation | D5: 8 | E5: P0 | F5: S2 | G5: Done
A6: ST-003 | B6: F1 | C6: As a IT admin, I can customise Shift handover threads rules/conditions for my workflow | D6: 5 | E6: P1 | F6: S2 | G6: Done
A7: ST-004 | B7: F1 | C7: As a user, Shift handover threads shows clear errors and retry paths on platform API failures | D7: 3 | E7: P0 | F7: S2 | G7: Done
A8: ST-005 | B8: F1 | C8: As a Frontline supervisor, Shift handover threads works on the Teams tab + bot surface end-to-end | D8: 5 | E8: P0 | F8: S3 | G8: Code-complete pending live
A9: ST-006 | B9: F1 | C9: As a IT admin, I can see Shift handover threads performance metrics and trends | D9: 3 | E9: P1 | F9: S3 | G9: Done
A10: ST-007 | B10: F1 | C10: As a user, Shift handover threads respects role permissions and audit logging | D10: 3 | E10: P1 | F10: S3 | G10: Done
A11: ST-008 | B11: F1 | C11: As a Ops director, I can pause/disable Shift handover threads without data loss | D11: 2 | E11: P2 | F11: S3 | G11: Done
A12: ST-009 | B12: F1 | C12: As a IT admin, I can import/migrate existing data into Shift handover threads (CSV + competitor importer) | D12: 5 | E12: P1 | F12: S3 | G12: Done
A13: ST-010 | B13: F1 | C13: As a user, I get notifications (in-app + email) for key Shift handover threads events with per-type mute | D13: 3 | E13: P2 | F13: S3 | G13: Done
A14: ST-011 | B14: F2 | C14: As a Ops director, I can set up Approval workflows with sensible defaults in one screen | D14: 5 | E14: P0 | F14: S3 | G14: Done
A15: ST-012 | B15: F2 | C15: As a Ops director, the Approval workflows happy path completes without documentation | D15: 8 | E15: P0 | F15: S3 | G15: Done
... A150: SD247 | B150: E20 | C150: 5 paid pilots with signed order forms | D150: 6 | E150: P1 | F150: S20 | G150: To do — Senthil
A152: Total stories: 147 (rows 4-103 = the original 100 ST stories; rows 104-150 = the 47 SD stories from review V001 sprint plan S13-S20). Epics: F1-F5 product features; E1 install, E5 billing, E6 compliance, E7 telemetry, E8 onboarding/docs/support, EQ quality; E13-E20 the review sprints. Status vocabulary per tracker decision D-SD2, extended by D-SD8: "To do — Senthil" marks the 11 stories that are live- or human-gated and can never be closed from a sandbox.

Sheet Sprint_Board
A1: SPRINT BOARD — live counts from Full_Backlog
A3: Sprint | B3: Focus | C3: Stories | D3: Points | E3: Done | F3: Exit criteria
A4: S0 | B4: Discovery & Design (2 wks) | C4: =COUNTIF(Full_Backlog!F4:F150,"S0") | D4: =SUMIF(Full_Backlog!F4:F150,"S0",Full_Backlog!D4:D150) | E4: =COUNTIFS(Full_Backlog!F4:F150,"S0",Full_Backlog!G4:G150,"Done") | F4: PRD signed off; prototype tested with 5 target users
A5: S1 | B5: Foundation (2 wks) | C5: =COUNTIF(Full_Backlog!F4:F150,"S1") | D5: =SUMIF(Full_Backlog!F4:F150,"S1",Full_Backlog!D4:D150) | E5: =COUNTIFS(Full_Backlog!F4:F150,"S1",Full_Backlog!G4:G150,"Done") | F5: App installs cleanly in dev store/org; telemetry firing
A6: S2 | B6: Core feature Shift handover threads - part 1 | C6: =COUNTIF(Full_Backlog!F4:F150,"S2") | D6: =SUMIF(Full_Backlog!F4:F150,"S2",Full_Backlog!D4:D150) | E6: =COUNTIFS(Full_Backlog!F4:F150,"S2",Full_Backlog!G4:G150,"Done") | F6: Shift handover threads happy path demoable
A7: S3 | B7: Core feature Shift handover threads - part 2 + Approval workflows start | C7: =COUNTIF(Full_Backlog!F4:F150,"S3") | D7: =SUMIF(Full_Backlog!F4:F150,"S3",Full_Backlog!D4:D150) | E7: =COUNTIFS(Full_Backlog!F4:F150,"S3",Full_Backlog!G4:G150,"Done") | F7: Shift handover threads complete with tests; Approval workflows skeleton
A8: S4 | B8: Core feature Approval workflows | C8: =COUNTIF(Full_Backlog!F4:F150,"S4") | D8: =SUMIF(Full_Backlog!F4:F150,"S4",Full_Backlog!D4:D150) | E8: =COUNTIFS(Full_Backlog!F4:F150,"S4",Full_Backlog!G4:G150,"Done") | F8: MVP loop usable end-to-end internally
A9: S5 | B9: Feature Digital checklists + alpha hardening | C9: =COUNTIF(Full_Backlog!F4:F150,"S5") | D9: =SUMIF(Full_Backlog!F4:F150,"S5",Full_Backlog!D4:D150) | E9: =COUNTIFS(Full_Backlog!F4:F150,"S5",Full_Backlog!G4:G150,"Done") | F9: Internal alpha: team dogfoods daily
A10: S6 | B10: Billing + Kudos/recognition | C10: =COUNTIF(Full_Backlog!F4:F150,"S6") | D10: =SUMIF(Full_Backlog!F4:F150,"S6",Full_Backlog!D4:D150) | E10: =COUNTIFS(Full_Backlog!F4:F150,"S6",Full_Backlog!G4:G150,"Done") | F10: Can charge a test customer; upgrade/downgrade paths work
A11: S7 | B11: Private beta (design partners) | C11: =COUNTIF(Full_Backlog!F4:F150,"S7") | D11: =SUMIF(Full_Backlog!F4:F150,"S7",Full_Backlog!D4:D150) | E11: =COUNTIFS(Full_Backlog!F4:F150,"S7",Full_Backlog!G4:G150,"Done") | F11: 3+ partners active weekly; NPS pulse >30
A12: S8 | B12: Beta iteration + Manager dashboard | C12: =COUNTIF(Full_Backlog!F4:F150,"S8") | D12: =SUMIF(Full_Backlog!F4:F150,"S8",Full_Backlog!D4:D150) | E12: =COUNTIFS(Full_Backlog!F4:F150,"S8",Full_Backlog!G4:G150,"Done") | F12: Retention of beta cohort week-over-week >60%
A13: S9 | B13: Marketplace review prep | C13: =COUNTIF(Full_Backlog!F4:F150,"S9") | D13: =SUMIF(Full_Backlog!F4:F150,"S9",Full_Backlog!D4:D150) | E13: =COUNTIFS(Full_Backlog!F4:F150,"S9",Full_Backlog!G4:G150,"Done") | F13: Review submission accepted into queue
A14: S10 | B14: Review remediation + docs | C14: =COUNTIF(Full_Backlog!F4:F150,"S10") | D14: =SUMIF(Full_Backlog!F4:F150,"S10",Full_Backlog!D4:D150) | E14: =COUNTIFS(Full_Backlog!F4:F150,"S10",Full_Backlog!G4:G150,"Done") | F14: Marketplace approval obtained (or final remediation cycle)
A15: S11 | B15: Launch | C15: =COUNTIF(Full_Backlog!F4:F150,"S11") | D15: =SUMIF(Full_Backlog!F4:F150,"S11",Full_Backlog!D4:D150) | E15: =COUNTIFS(Full_Backlog!F4:F150,"S11",Full_Backlog!G4:G150,"Done") | F15: First 10 installs; first 3 reviews; activation >40%
A16: S12 | B16: Iterate & scale decision | C16: =COUNTIF(Full_Backlog!F4:F150,"S12") | D16: =SUMIF(Full_Backlog!F4:F150,"S12",Full_Backlog!D4:D150) | E16: =COUNTIFS(Full_Backlog!F4:F150,"S12",Full_Backlog!G4:G150,"Done") | F16: Growth model doc with CAC/LTV first estimates
A17: S13 | B17: Trust boundaries for real | C17: =COUNTIF(Full_Backlog!F4:F150,"S13") | D17: =SUMIF(Full_Backlog!F4:F150,"S13",Full_Backlog!D4:D150) | E17: =COUNTIFS(Full_Backlog!F4:F150,"S13",Full_Backlog!G4:G150,"Done") | F17: A Teams dev tenant loads the tab with a real Entra token and the bot answers a real message, dev bypass disabled
A18: S14 | B18: Durability for real | C18: =COUNTIF(Full_Backlog!F4:F150,"S14") | D18: =SUMIF(Full_Backlog!F4:F150,"S14",Full_Backlog!D4:D150) | E18: =COUNTIFS(Full_Backlog!F4:F150,"S14",Full_Backlog!G4:G150,"Done") | F18: Restart, two-instance and restore drills green in CI against real Postgres, unattended
A19: S15 | B19: Scale and data model | C19: =COUNTIF(Full_Backlog!F4:F150,"S15") | D19: =SUMIF(Full_Backlog!F4:F150,"S15",Full_Backlog!D4:D150) | E19: =COUNTIFS(Full_Backlog!F4:F150,"S15",Full_Backlog!G4:G150,"Done") | F19: 5x load sweep passes on staging with per-record persistence and published numbers
A20: S16 | B20: Teams-native experience | C20: =COUNTIF(Full_Backlog!F4:F150,"S16") | D20: =SUMIF(Full_Backlog!F4:F150,"S16",Full_Backlog!D4:D150) | E20: =COUNTIFS(Full_Backlog!F4:F150,"S16",Full_Backlog!G4:G150,"Done") | F20: End-to-end handover completed on Teams mobile using cards, acknowledgement nudge arriving proactively
A21: S17 | B21: Enterprise admin and governance | C21: =COUNTIF(Full_Backlog!F4:F150,"S17") | D21: =SUMIF(Full_Backlog!F4:F150,"S17",Full_Backlog!D4:D150) | E21: =COUNTIFS(Full_Backlog!F4:F150,"S17",Full_Backlog!G4:G150,"Done") | F21: IT-admin dry run (install, consent, rollout, export, delete) completed by someone who did not build it
A22: S18 | B22: Assurance and certification | C22: =COUNTIF(Full_Backlog!F4:F150,"S18") | D22: =SUMIF(Full_Backlog!F4:F150,"S18",Full_Backlog!D4:D150) | E22: =COUNTIFS(Full_Backlog!F4:F150,"S18",Full_Backlog!G4:G150,"Done") | F22: Attestation submitted, pen-test Highs closed, accessibility audit signed
A23: S19 | B23: Commercial machinery and observability | C23: =COUNTIF(Full_Backlog!F4:F150,"S19") | D23: =SUMIF(Full_Backlog!F4:F150,"S19",Full_Backlog!D4:D150) | E23: =COUNTIFS(Full_Backlog!F4:F150,"S19",Full_Backlog!G4:G150,"Done") | F23: A test customer transacts through the marketplace and the entitlement is enforced end to end
A24: S20 | B24: Demand validation and go/no-go | C24: =COUNTIF(Full_Backlog!F4:F150,"S20") | D24: =SUMIF(Full_Backlog!F4:F150,"S20",Full_Backlog!D4:D150) | E24: =COUNTIFS(Full_Backlog!F4:F150,"S20",Full_Backlog!G4:G150,"Done") | F24: G-01/G-02 become achievable on evidence, or kill criteria fire
B25: TOTAL | C25: =SUM(C4:C24) | D25: =SUM(D4:D24) | E25: =SUM(E4:E24)
B26: Velocity check: S2-S8 sat at 30-45 pts/sprint. The review plan S13-S20 is 266 pts across 8 sprints (~33/sprint), the same shape — but 62 of those points are human-gated (D-SD8) and cannot be burned down by building.

Sheet Sprint_Tracker_Log
A1: SPRINT TRACKER LOG — ShiftDesk (execution session 10/09/2026 22:26-22:40, Claude for Senthil/KP)
A3: Sprint | B3: Date executed | C3: Scope executed this session | D3: Stories Done | E3: Points Done | F3: Exit criteria status | G3: Notes
A4: S0 | B4: 2026-09-10 | C4: Skipped per D13 (discovery interviews parked); spec taken from v005 as-is | D4: 0 | E4: 0 | F4: N/A — D13 | G4: Re-baseline in v007 if interviews resume
A5: S1 | B5: 2026-09-10 | C5: Install lifecycle: OAuth install->welcome, uninstall webhook + 30-day deletion, token rotation survival, source attribution (install.ts) | D5: 3 | E5: 8 | F5: Partial — installs cleanly in mock gateway; live dev-store install pending (ST-051) | G5: Bot Framework transport mocked at gateway seam
A6: S2 | B6: 2026-09-10 | C6: Handover threads part 1: defaults setup, happy path, custom rules, error/retry, re-install restore, role matrix (handover.ts, moduleBase.ts, rbac.ts) | D6: 6 | E6: 29 | F6: Met — happy path demoable via E2E suite
A7: S3 | B7: 2026-09-10 | C7: Handover part 2 + approvals skeleton: mobile/bot surface code, metrics, permissions+audit, pause, CSV import, notifications; approvals policy builder; ST-085 coverage gate | D7: 10 | E7: 42 | F7: Met — handover complete with tests; approvals skeleton up | G7: ST-085 delivered at 100% (D13 supersedes >=70%)
A8: S4 | B8: 2026-09-10 | C8: Approval workflows complete: evaluate/auto-approve/block, preview test mode; funnel events + error tracking (approvals.ts, telemetry.ts); E2E smoke suite (ST-086) | D8: 8 | E8: 29 | F8: Met — MVP loop usable end-to-end in tests
A9: S5 | B9: 2026-09-10 | C9: Digital checklists + alpha hardening: create/tick/export, first-run checklist to aha, empty states (checklists.ts, onboarding.ts) | D9: 11 | E9: 45 | F9: Partial — code hardened; live dogfooding pending
A10: S6 | B10: 2026-09-10 | C10: Billing + kudos: trial/banner, proration, marketplace-vs-Stripe rail, kudos + leaderboard (billing.ts, kudos.ts) | D10: 11 | E10: 47 | F10: Partial — test customer chargeable via mock rail; live marketplace billing pending (ST-059)
A11: S7 | B11: 2026-09-10 | C11: Dunning/grace/read-only, plan-limit prompts, invoices GST/VAT, cancellation save-offer, least-privilege scope doc | D11: 5 | E11: 15 | F11: Not met — design partners not yet recruited (human-dependent) | G11: All S7 code stories Done
A12: S8 | B12: 2026-09-10 | C12: Manager dashboard: KPI aggregation, trends, open items; retention docs, audit log, backoff+circuit breaker, latency budgets, heatmap/health/alerts | D12: 18 | E12: 69 | F12: Partial — beta cohort retention unmeasurable pre-live | G12: Zero-downtime deploy (ST-092) needs live infra
A13: S9 | B13: 2026-09-10 | C13: Chaos degrade path automated (ST-091); WCAG structure in components; pen test + backup drill deferred to live | D13: 2 | E13: 8 | F13: Not met — submission needs live tenant + assets | G13: 2 of 7 stories Done
A14: S10 | B14: 2026-09-10 | C14: No content stories executed (help articles, pricing/trust pages are launch content) | D14: 0 | E14: 0 | F14: Not met | G14: Backlog
A15: S11 | B15: 2026-09-10 | C15: Launch stories untouched (require approved listing) | D15: 1 | E15: 3 | F15: Not met | G15: Backlog
A16: S12 | B16: 2026-09-10 | C16: Not started | D16: 0 | E16: 0 | F16: Not met | G16: Backlog
C17: TOTALS (live from Full_Backlog) | D17: =COUNTIF(Full_Backlog!G4:G103,"Done") | E17: =SUMIF(Full_Backlog!G4:G103,"Done",Full_Backlog!D4:D103)
A19: Session summary 10/09/2026: sprints S1-S8 development complete in code; 75 stories Done, 8 code-complete pending live platform (ST-005/015/025/035/045/051/059/066), 1 in progress (ST-083 sandbox shipped, video outstanding), 16 backlog (pen test, load/WCAG/backup/deploy drills, content, S10-S12 listing/launch).
A20: Quality gate: 15 Jest suites, 67 tests, 100% statements/branches/functions/lines enforced via jest.config.js coverageThreshold (D13). TypeScript strict, tsc --noEmit clean. CI: .github/workflows/ci.yml.
A21: Assumption: platform transport (Bot Framework/Graph, marketplace billing API) mocked at the PlatformGateway seam — no Microsoft credentials in build environment; wiring unchanged for live swap. Source: shiftdesk_v006_source.zip delivered with this workbook.
A23: SESSION 2 — 10/09/2026 22:54
A24: S9 | B24: 2026-09-10 | C24: ST-089 WCAG: jest-axe automated suite added over all 9 screens, wired into CI (16 suites / 76 tests, 100% coverage held). ST-097 submission dry-run executed against Launch_Checklist; 10 item statuses recorded. | D24: 0 | E24: 0 | F24: S9 partial — pen test + live asset items remain | G24: ST-089 now code-complete pending live audit
A25: S10 | B25: 2026-09-10 | C25: Content drafted: listing copy A/B (ST-093), pricing matrix + FAQ (ST-095), security/trust page (ST-096), 15 help articles (ST-080), admin deployment guide, positioning one-pager. | D25: 0 | E25: 0 | F25: S10 partial — publishing needs live site/listing | G25: All drafts in content/, external-facing, no company name per rule
A26: S11 | B26: 2026-09-10 | C26: Launch-day runbook with rollback triggers + comms tree (ST-098); incident comms template (ST-084); demo video script (ST-083). | D26: 0 | E26: 0 | F26: S11 partial — listing + installs still gate exit | G26: Video recording + screenshots (ST-094) need live product UI
A27: Portfolio position after session 2: 75 Done / 9 code-complete pending live / 2 in progress / 6 drafted / 8 backlog. Remaining backlog is entirely Senthil-gated or live-gated: pen test (068), chat vendor (081), load test (088), backup drill (090), deploy drill (092), screenshots+video assets (094), post-launch SEO (099), design-partner reviews (100). ShiftDesk sandbox work is exhausted pending: Partner Center enrollment, live Teams dev tenant, D15.
A29: SESSION 3 — 10/09/2026 23:10
A30: S1/S9 | B30: 2026-09-10 | C30: Live-sweep readiness pack: teams-app/manifest.json (v1.17, bot + 3 static tabs + valid domains placeholders) with generated icons; src/config.ts typed loader (fail-fast, redacted print); src/liveSweep.ts 12-step scripted verification sweep mapped to ST-051/005/015/025/054/055/052/053; content/dev-tenant-setup-guide.md (30-min path, sideload does not need Partner Center). | D30: 0 | E30: 0 | F30: Shortens S1-07 to wiring-only on install day | G30: 18 suites / 85 tests, 100% coverage held; statuses unchanged (live-gated)
A32: SESSION 4 — 11/09/2026 08:20
A33: S9/S11 | B33: 2026-09-11 | C33: Ops parity with portfolio standard: k6 5x harness (ST-088), blue/green deploy workflow (ST-092), backup/restore drill script (ST-090). Remaining backlog now only 5 items, all external: pen test (068), chat vendor (081), listing assets (094), post-launch SEO (099), design-partner reviews (100). | D33: 0 | E33: 0 | F33: Execution of all three live-gated | G33: Coverage gate re-verified 18/85 at 100%
A35: SESSION 5 — 11/09/2026 12:51
A36: S9 | B36: 2026-09-11 | C36: Cold-review pass 1: F-001..F-006 fixed + pinned, F-007/F-008 for disposition, F-009 corrected by building src/crypto.ts (ST-066 now genuinely coded); REVIEW_PACK.md for external reviewer (ST-097 stays In progress — same-AI review is not independent). | D36: 0 | E36: 0 | F36: Statuses unchanged except evidence corrections | G36: 20 suites / 94 tests at 100%; importer CSV-quoting flagged as pass-2 candidate
A38: SESSION 6 — 11/09/2026 20:30
A39: S9-S12 | B39: 2026-09-11 | C39: Cold-review pass 2 (4 fixes F-010..F-013, OBS-SD1 open; review complete, 10 defects total across both passes) + sibling-validated completion wave (chat SLA, partner tracker, SEO engine, help search, security evidence, asset plan, pricing drift gate). CODE PHASE COMPLETE — backlog zero. | D39: 0 | E39: 0 | F39: Remaining chain 100% Senthil/live | G39: 22 suites / 109 tests at 100%
A41: SESSION 7 — 13/09/2026 09:52
A42: S9 | B42: 2026-09-13 | C42: External verification sweep vs live Microsoft docs (manifest schema, RSC vs Graph scopes, store validation guidelines, icon rules, marketplace fee) + artifact-gap audit. 6 fixes incl. 2 store-blocking and 1 live-blocking; 1 verified-correct set pinned; LC-5 reopened and corrected. | D42: 0 | E42: 0 | F42: Sweep extended to 14 steps | G42: 24 suites / 120 tests at 100%; story counts deliberately unchanged
A44: SESSION 8 — 13/09/2026 10:01
A45: S2-S5/S9 | B45: 2026-09-13 | C45: Artifact-gap audit round 2: built the tab surface the manifest had been promising (shell, API client, entry, bundles) and the bot command router behind the advertised commands; package hygiene fixed; demo capture surface unblocks draft listing screenshots pre-tenant. | D45: 0 | E45: 0 | F45: Five surface stories now full-stack pending in-client render | G45: 26 suites / 145 tests at 100% incl. new web/ layer
A47: SESSION 9 — 13/09/2026 10:24
A48: S9 | B48: 2026-09-13 | C48: Cold-review pass 3 over sessions 5-8 code (tab layer, bot router, completion wave, config, crypto): 6 defects fixed with regressions, 1 observation closed. Headline: the tab API validated the SSO token and then dropped it — every call unauthenticated in production, invisible because the fetcher was injected and never asserted on headers. | D48: 0 | E48: 0 | F48: No story flips — correctness only | G48: 27 suites / 151 tests at 100%; 19 defects total across three review passes
A50: SESSION 10 — 13/09/2026 10:37
A51: S1/S9 | B51: 2026-09-13 | C51: Artifact-gap audit round 3: built the HTTP server the tab and bot endpoint had been calling into thin air, with bearer auth, health/status, node:http bootstrap and a CI parity test binding client paths to served routes. | D51: 0 | E51: 0 | F51: Tab + bot surfaces now end-to-end in code | G51: 29 suites / 163 tests at 100%; sweep now 15 steps
A53: SESSION 11 — 13/09/2026 10:42
A54: S1/S9 | B54: 2026-09-13 | C54: Bot transport seam verified against live Bot Framework docs and rebuilt: Connector JWT boundary, Activity parsing, ack-then-send-via-Connector, install welcome on conversationUpdate, retry dedupe. Two live-blocking defects from the previous session caught before they could ship. | D54: 0 | E54: 0 | F54: ST-051 welcome now has a real delivery path | G54: 30 suites / 174 tests at 100%
A56: SESSION 12 — 13/09/2026 10:57
A57: S1/S9 | B57: 2026-09-13 | C57: Tab SSO seam verified against live Entra/Teams docs and implemented: real getAuthToken with consent handling, server-side claim validation, config-derived verifier, Expose-an-API setup step documented. | D57: 0 | E57: 0 | F57: Third and last declared-but-unimplemented manifest promise closed | G57: 31 suites / 181 tests at 100%; sweep now 16 steps
A59: SESSION 13 — 13/09/2026 11:02
A60: S1/S8 | B60: 2026-09-13 | C60: Permissions-vs-consumers audit: built the Graph member directory that TeamMember.Read.Group had always claimed to power, dropped an unused scope, and bound scopes to consumers by test. | D60: 0 | E60: 0 | F60: Role matrix real on both boundaries | G60: 32 suites / 190 tests at 100%
A62: SESSION 14 — 13/09/2026 11:07
A63: S9 | B63: 2026-09-13 | C63: Cold-review pass 4 over sessions 10-13 integration code: 5 defects fixed with regressions, two of them authorization/data-loss class (arbitrary-tenant lifecycle calls; retries deduped after failed sends). | D63: 0 | E63: 0 | F63: No story flips — correctness only | G63: 33 suites / 196 tests at 100%; 24 defects total across four passes
A65: SESSION 15 — 13/09/2026 11:12
A66: S1/S8 | B66: 2026-09-13 | C66: Persistence seam built: repository interface with in-memory and Postgres implementations under one contract suite, migration SQL, durable audit log, tenant purge behind the deletion policies. | D66: 0 | E66: 0 | F66: Blue/green and the backup drill now have something real to operate on | G66: 34 suites / 208 tests at 100%; sweep now 17 steps
A68: SESSION 16 — 13/09/2026 11:16
A69: S1/S8 | B69: 2026-09-13 | C69: Finished the persistence work: services now hydrate from and write back to the repository, so handovers, approvals, checklists and kudos survive a restart. Remaining unpersisted state named openly. | D69: 0 | E69: 0 | F69: Durability claim now true for the core modules | G69: 35 suites / 213 tests at 100%
A71: SESSION 17 — 13/09/2026 11:21
A72: S1/S6 | B72: 2026-09-13 | C72: Persistence slice 2 (billing, install, chat) plus F-025: the in-memory store handed out live references where Postgres hands out values — dev and production would have behaved differently. | D72: 0 | E72: 0 | F72: Lifecycle state durable; store semantics now identical across implementations | G72: 36 suites / 219 tests at 100%
A74: SESSION 18 — 13/09/2026 11:25
A75: S1/S8 | B75: 2026-09-13 | C75: Multi-tenancy audit: found and fixed cross-tenant data exposure (one app instance for all customers), unpersisted bot mutations, and a health-probe regression from the fix itself. | D75: 0 | E75: 0 | F75: Tenant isolation enforced and pinned | G75: 37 suites / 227 tests at 100%
A77: SESSION 19 — 13/09/2026 11:51
A78: S8/S9 | B78: 2026-09-13 | C78: Deletion audit: the retention policy and delete-my-data were promises with no implementation behind them; both now work against the store and are pinned. | D78: 0 | E78: 0 | F78: Compliance claims match behaviour | G78: 38 suites / 233 tests at 100%; sweep now 18 steps
A80: SESSION 20 — 13/09/2026 11:55
A81: S8/S9 | B81: 2026-09-13 | C81: Authorization audit: the role matrix was documentation, not enforcement — five permissions guarded nothing, two of them the delete and export controls built last session. | D81: 0 | E81: 0 | F81: Every permission now has an enforcement site bound by test | G81: 39 suites / 239 tests at 100%; sweep now 19 steps
A83: SESSION 21 — 13/09/2026 12:02
A84: S6/S7 | B84: 2026-09-13 | C84: Billing-integrity audit: read-only, cancellation, plan limits and trial expiry all restricted nothing. Entitlement gate added at the request boundary; reads stay open by design. | D84: 0 | E84: 0 | F84: Revenue-protecting states now enforced | G84: 40 suites / 246 tests at 100%; sweep now 20 steps
A86: SESSION 22 — 13/09/2026 16:27
A87: S2-S5/S8 | B87: 2026-09-13 | C87: Two more declared-but-absent mechanisms: notification delivery and latency measurement. Both built and instrumented at the boundary that sees a whole request. | D87: 0 | E87: 0 | F87: Notification and performance claims now real | G87: 42 suites / 256 tests at 100%; sweep now 22 steps
A89: SESSION 23 — 13/09/2026 16:35
A90: S4/S8 | B90: 2026-09-13 | C90: Telemetry and audit were fully built and never called. Both wired into the request path; the launch activation metric is now computable and the compliance trail survives a restart. | D90: 0 | E90: 0 | F90: Launch metrics and audit evidence real | G90: 43 suites / 262 tests at 100%; sweep now 24 steps
A92: SESSION 24 — 13/09/2026 16:40
A93: S3-S8 | B93: 2026-09-13 | C93: Wiring audit across every export: six unreachable screens made reachable, notification delivery wired, encryption-at-rest gap recorded open for decision. | D93: 0 | E93: 0 | F93: Product surface complete; one compliance claim open | G93: 44 suites / 269 tests at 100%; sweep now 25 steps
A95: SESSION 25 — 13/09/2026 16:47
A96: S8 | B96: 2026-09-13 | C96: Encryption at rest implemented as an opt-in decorator so either disposition is a config choice; trust page rewritten to state what is actually encrypted and what is not. | D96: 0 | E96: 0 | F96: Compliance claim now true in both configurations | G96: 45 suites / 276 tests at 100%; sweep now 26 steps
A98: SESSION 26 — 13/09/2026 16:51
A99: S9 | B99: 2026-09-13 | C99: Cold-review pass 5: five defects in the newest modules, including a seat cap that could never fire and a notification path that discarded on failure. | D99: 0 | E99: 0 | F99: No story flips — correctness only | G99: 46 suites / 282 tests at 100%; 34 defects across five passes
A101: SESSION 27 — 13/09/2026 17:25
A102: S8/S11 | B102: 2026-09-13 | C102: Multi-instance audit: the persistence model silently lost data under the deployment model we ship. Optimistic concurrency added; conflicts are now detected and surfaced rather than overwritten. | D102: 0 | E102: 0 | F102: Blue/green and scale-out are now data-safe | G102: 47 suites / 292 tests at 100%; sweep now 27 steps
A104: SESSION 28 — 13/09/2026 18:51
A105: S8/S9 | B105: 2026-09-13 | C105: Dependency-failure audit: a single store or mail blip hung the request and crashed the process. Boundary error handling, degradation reporting and best-effort delivery added. | D105: 0 | E105: 0 | F105: Outages now degrade instead of crashing | G105: 48 suites / 299 tests at 100%; sweep now 28 steps
A107: SESSION 29 — 13/09/2026 19:10
A108: S9 | B108: 2026-09-13 | C108: Cold-review pass 6: three defects in the resilience and versioning work from the last three sessions, including a classifier coupled to test fixtures and a bot retry that duplicated work. | D108: 0 | E108: 0 | F108: No story flips — correctness only | G108: 49 suites / 303 tests at 100%; 37 defects across six passes
A110: SESSION 30 — 13/09/2026 19:27
A111: S1/S9 | B111: 2026-09-13 | C111: Made the live sweep executable so the dev-tenant day is a command plus a short operator list, rather than 28 manual checks. | D111: 0 | E111: 0 | F111: Live day materially shorter | G111: 50 suites / 309 tests at 100%
A113: SESSION 31 — 13/09/2026 19:32
A114: S1/S9 | B114: 2026-09-13 | C114: Six more sweep steps automated behind capability gates; writing the funnel check exposed an Analytics tab that would have shown zeros forever. | D114: 0 | E114: 0 | F114: Live day shorter again; one real defect found | G114: 50 suites / 318 tests at 100%
A116: SESSION 32 — 13/09/2026 19:39
A117: S1 | B117: 2026-09-13 | C117: Packaging automated and validated: substitution, store-rule checks, and a root-level archive. The tenant day no longer depends on zipping the right three files correctly by hand. | D117: 0 | E117: 0 | F117: One more manual failure mode removed | G117: 51 suites / 323 tests at 100%
A119: SESSION 33 — 13/09/2026 20:05
A120: S1/S9 | B120: 2026-09-13 | C120: Audited the tooling built in the last three sessions for whether it runs where it will run. It did not: undeclared dependencies and an untypechecked scripts folder. Fixed and pinned in CI. | D120: 0 | E120: 0 | F120: Live-day tooling now verified from a clean install | G120: 51 suites / 323 tests at 100%
A122: SESSION 34 — 13/09/2026 20:10
A123: S1/S9 | B123: 2026-09-13 | C123: Rehearsed the delivery exactly as it will be received. Found that no server entry point shipped; fixed, and the whole path now runs end to end from the zip. | D123: 0 | E123: 0 | F123: Tenant-day path proven from a clean checkout | G123: 52 suites / 327 tests at 100%; rehearsal 8 passed 0 failed
A125: SESSION 35 — 13/09/2026 20:26
A126: S2-S5 | B126: 2026-09-13 | C126: Followed the manifest from URL to file and found the last hop missing: nothing served /tab. Now served by the app itself, verified live. | D126: 0 | E126: 0 | F126: All eight tabs reachable from a running server | G126: 53 suites / 334 tests at 100%; sweep 9 passed 0 failed
A128: SESSION 36 — 13/09/2026 20:32
A129: S1/S9 | B129: 2026-09-13 | C129: Followed the manifest to a working bot: the endpoint existed but nothing was wired to it. Connector sender and token exchange built; dev and production modes both explicit. | D129: 0 | E129: 0 | F129: Bot commands reachable from a running server | G129: 54 suites / 343 tests at 100%
A131: SESSION 37 — 13/09/2026 21:56
A132: S1/S8 | B132: 2026-09-13 | C132: Install and uninstall now record what the retention policy needs, and the 30-day sweep has something running it. Both were implemented and uncalled. | D132: 0 | E132: 0 | F132: Retention commitment finally executable in a deployment | G132: 55 suites / 349 tests at 100%
A134: SESSION 38 — 13/09/2026 22:55
A135: S1/S8 | B135: 2026-09-13 | C135: Audited what the running process constructs rather than what the code references. Every user was an owner; notifications and help were never instantiated. | D135: 0 | E135: 0 | F135: Privilege fallback corrected to least privilege | G135: 56 suites / 356 tests at 100%
A137: SESSION 39 — 13/09/2026 23:05
A138: S1/S8 | B138: 2026-09-13 | C138: Cleared the remaining runtime stubs: invented email addresses, an unreachable Graph path, and unseeded install counts. | D138: 0 | E138: 0 | F138: Admin roles now attainable; notifications addressed correctly | G138: 57 suites / 364 tests at 100%
A140: SESSION 40 — 13/09/2026 23:14
A141: S1/S8 | B141: 2026-09-13 | C141: Audited my own last-session wiring first and found it inert. Directory population and release tagging also wired; listAll made contractual. | D141: 0 | E141: 0 | F141: Roles attainable, seeding real, errors attributable | G141: 58 suites / 371 tests at 100%
...

Sheet Financial_Model
A1: 18-MONTH FINANCIAL MODEL v046 — repaired per review findings P-018 / D-01 / D-02 (SD246). Yellow cells are inputs. Two pricing scenarios; cash-in, runway, breakeven and funding requirement are computed, not asserted.
A2: The reviewer recomputed the v045 sheet and found M18 net -$23,822/mo and cumulative -$574,601, with no cash-in or runway row anywhere. Scenario A below reproduces that result on the original assumptions rather than arguing with it. Scenario B models the per-site pricing the review asked for. Neither is a forecast: every input is a planning number until the SD244 interviews and SD247 pilots replace it.
A4: SCENARIO A — per-seat pricing, as modelled in v045
A5: Assumption | B5: Value | C5: Note
A6: Qualified pilots/mo (month 1) | B6: 6 | C6: v005 assumption, unchanged
A7: Monthly growth of that | B7: 0.1 | C7: v005 assumption, unchanged
A8: Pilot->paid % | B8: 0.35 | C8: v005 assumption, unchanged
A9: ARPU $/mo (per-seat scenario) | B9: 400 | C9: Review D-02: at a $2/seat frontline price this implies ~200 seats per "pilot", which contradicts a 6-pilots-a-month founder-led motion. Kept here so the reviewer's numbers reproduce; Scenario B is the honest alternative.
A10: Monthly churn | B10: 0.015 | C10: v005 assumption, unchanged
A11: Marketplace fee | B11: 0.03 | C11: Microsoft transactable fee. Verify at offer setup (Launch_Checklist #6).
A12: Team cost month 1 ($) | B12: 35000 | C12: India-lean base from Team_Roles_Budget (v004)
A13: Cost growth/mo | B13: 0.03 | C13: v005 assumption, unchanged
A14: Opening cash at M1 ($) | B14: 0 | C14: INPUT OWED — Senthil. Left at zero deliberately: the model must not invent a cash position. With 0 here, "funding requirement" below IS the cash this plan needs.
A15: Other monthly cash-in ($) | B15: 0 | C15: INPUT OWED — Senthil. Consulting or other income applied to this product, if any. The absence of this row is what review finding P-018 called out.
A17: Line | B17: M1 | C17: M2 | D17: M3 | E17: M4 | F17: M5 | G17: M6 | H17: M7 | I17: M8 | J17: M9 | K17: M10 | L17: M11 | M17: M12 | N17: M13 | O17: M14 | P17: M15 | Q17: M16 | R17: M17 | S17: M18
A18: A leads/installs | B18: =$B$6 | C18: =B18*(1+$B$7) | D18: =C18*(1+$B$7) | E18: =D18*(1+$B$7) | F18: =E18*(1+$B$7) | G18: =F18*(1+$B$7) | H18: =G18*(1+$B$7) | I18: =H18*(1+$B$7) | J18: =I18*(1+$B$7) | ... S18: =R18*(1+$B$7)
A19: A new paying | B19: =ROUND(B18*$B$8,1) | C19: =ROUND(C18*$B$8,1) | D19: =ROUND(D18*$B$8,1) | E19: =ROUND(E18*$B$8,1) | F19: =ROUND(F18*$B$8,1) | G19: =ROUND(G18*$B$8,1) | H19: =ROUND(H18*$B$8,1) | I19: =ROUND(I18*$B$8,1) | ... S19: =ROUND(S18*$B$8,1)
A20: A paying accounts | B20: =B19 | C20: =ROUND(B20*(1-$B$10)+C19,1) | D20: =ROUND(C20*(1-$B$10)+D19,1) | E20: =ROUND(D20*(1-$B$10)+E19,1) | F20: =ROUND(E20*(1-$B$10)+F19,1) | G20: =ROUND(F20*(1-$B$10)+G19,1) | H20: =ROUND(G20*(1-$B$10)+H19,1) | I20: =ROUND(H20*(1-$B$10)+I19,1) | J20: =ROUND(I20*(1-$B$10)+J19,1) | ... S20: =ROUND(R20*(1-$B$10)+S19,1)
A21: A MRR net of fee | B21: =ROUND(B20*$B$9*(1-$B$11),0) | C21: =ROUND(C20*$B$9*(1-$B$11),0) | D21: =ROUND(D20*$B$9*(1-$B$11),0) | E21: =ROUND(E20*$B$9*(1-$B$11),0) | F21: =ROUND(F20*$B$9*(1-$B$11),0) | G21: =ROUND(G20*$B$9*(1-$B$11),0) | H21: =ROUND(H20*$B$9*(1-$B$11),0) | I21: =ROUND(I20*$B$9*(1-$B$11),0) | ... S21: =ROUND(S20*$B$9*(1-$B$11),0)
A22: A team cost | B22: =$B$12 | C22: =ROUND(B22*(1+$B$13),0) | D22: =ROUND(C22*(1+$B$13),0) | E22: =ROUND(D22*(1+$B$13),0) | F22: =ROUND(E22*(1+$B$13),0) | G22: =ROUND(F22*(1+$B$13),0) | H22: =ROUND(G22*(1+$B$13),0) | I22: =ROUND(H22*(1+$B$13),0) | J22: =ROUND(I22*(1+$B$13),0) | ... S22: =ROUND(R22*(1+$B$13),0)
A23: A other cash-in | B23: =$B$15 | C23: =$B$15 | D23: =$B$15 | E23: =$B$15 | F23: =$B$15 | G23: =$B$15 | H23: =$B$15 | I23: =$B$15 | ... S23: =$B$15
A24: A net cash/mo | B24: =B21+B23-B22 | C24: =C21+C23-C22 | D24: =D21+D23-D22 | E24: =E21+E23-E22 | F24: =F21+F23-F22 | G24: =G21+G23-G22 | H24: =H21+H23-H22 | I24: =I21+I23-I22 | ... S24: =S21+S23-S22
A25: A cumulative net | B25: =B24 | C25: =B25+C24 | D25: =C25+D24 | E25: =D25+E24 | F25: =E25+F24 | G25: =F25+G24 | H25: =G25+H24 | I25: =H25+I24 | J25: =I25+J24 | ... S25: =R25+S24
A26: A closing cash | B26: =$B$14+B25 | C26: =$B$14+C25 | D26: =$B$14+D25 | E26: =$B$14+E25 | F26: =$B$14+F25 | G26: =$B$14+G25 | H26: =$B$14+H25 | I26: =$B$14+I25 | ... S26: =$B$14+S25
A27: A breakeven flag (net>=0) | B27: =IF(B24>=0,1,0) | C27: =IF(C24>=0,1,0) | D27: =IF(D24>=0,1,0) | E27: =IF(E24>=0,1,0) | F27: =IF(F24>=0,1,0) | G27: =IF(G24>=0,1,0) | H27: =IF(H24>=0,1,0) | I27: =IF(I24>=0,1,0) | ... S27: =IF(S24>=0,1,0)
A28: A cash-out flag (closing<0) | B28: =IF(B26<0,1,0) | C28: =IF(C26<0,1,0) | D28: =IF(D26<0,1,0) | E28: =IF(E26<0,1,0) | F28: =IF(F26<0,1,0) | G28: =IF(G26<0,1,0) | H28: =IF(H26<0,1,0) | I28: =IF(I26<0,1,0) | ... S28: =IF(S26<0,1,0)
A30: SCENARIO B — per-site pricing (what review finding D-02 asked for)
A31: Assumption | B31: Value | C31: Note
A32: Price per site $/mo | B32: 750 | C32: A site = one depot, ward, store or plant: the unit an ops director actually buys, and the unit an auditor asks about. Planning number, to be tested in the SD244 interviews (SD245/SD246).
A33: Sites per paying customer | B33: 2 | C33: Planning number. A single-site pilot that expands is the motion the 6-pilots/month assumption describes.
A34: Implied ARPU $/mo (B) | B34: =$B$32*$B$33
A36: Line | B36: M1 | C36: M2 | D36: M3 | E36: M4 | F36: M5 | G36: M6 | H36: M7 | I36: M8 | J36: M9 | K36: M10 | L36: M11 | M36: M12 | N36: M13 | O36: M14 | P36: M15 | Q36: M16 | R36: M17 | S36: M18
A37: B leads/installs | B37: =$B$6 | C37: =B37*(1+$B$7) | D37: =C37*(1+$B$7) | E37: =D37*(1+$B$7) | F37: =E37*(1+$B$7) | G37: =F37*(1+$B$7) | H37: =G37*(1+$B$7) | I37: =H37*(1+$B$7) | J37: =I37*(1+$B$7) | ... S37: =R37*(1+$B$7)
A38: B new paying | B38: =ROUND(B37*$B$8,1) | C38: =ROUND(C37*$B$8,1) | D38: =ROUND(D37*$B$8,1) | E38: =ROUND(E37*$B$8,1) | F38: =ROUND(F37*$B$8,1) | G38: =ROUND(G37*$B$8,1) | H38: =ROUND(H37*$B$8,1) | I38: =ROUND(I37*$B$8,1) | ... S38: =ROUND(S37*$B$8,1)
A39: B paying accounts | B39: =B38 | C39: =ROUND(B39*(1-$B$10)+C38,1) | D39: =ROUND(C39*(1-$B$10)+D38,1) | E39: =ROUND(D39*(1-$B$10)+E38,1) | F39: =ROUND(E39*(1-$B$10)+F38,1) | G39: =ROUND(F39*(1-$B$10)+G38,1) | H39: =ROUND(G39*(1-$B$10)+H38,1) | I39: =ROUND(H39*(1-$B$10)+I38,1) | J39: =ROUND(I39*(1-$B$10)+J38,1) | ... S39: =ROUND(R39*(1-$B$10)+S38,1)
A40: B MRR net of fee | B40: =ROUND(B39*$B$34*(1-$B$11),0) | C40: =ROUND(C39*$B$34*(1-$B$11),0) | D40: =ROUND(D39*$B$34*(1-$B$11),0) | E40: =ROUND(E39*$B$34*(1-$B$11),0) | F40: =ROUND(F39*$B$34*(1-$B$11),0) | G40: =ROUND(G39*$B$34*(1-$B$11),0) | H40: =ROUND(H39*$B$34*(1-$B$11),0) | I40: =ROUND(I39*$B$34*(1-$B$11),0) | ... S40: =ROUND(S39*$B$34*(1-$B$11),0)
A41: B team cost | B41: =$B$12 | C41: =ROUND(B41*(1+$B$13),0) | D41: =ROUND(C41*(1+$B$13),0) | E41: =ROUND(D41*(1+$B$13),0) | F41: =ROUND(E41*(1+$B$13),0) | G41: =ROUND(F41*(1+$B$13),0) | H41: =ROUND(G41*(1+$B$13),0) | I41: =ROUND(H41*(1+$B$13),0) | J41: =ROUND(I41*(1+$B$13),0) | ... S41: =ROUND(R41*(1+$B$13),0)
A42: B other cash-in | B42: =$B$15 | C42: =$B$15 | D42: =$B$15 | E42: =$B$15 | F42: =$B$15 | G42: =$B$15 | H42: =$B$15 | I42: =$B$15 | ... S42: =$B$15
A43: B net cash/mo | B43: =B40+B42-B41 | C43: =C40+C42-C41 | D43: =D40+D42-D41 | E43: =E40+E42-E41 | F43: =F40+F42-F41 | G43: =G40+G42-G41 | H43: =H40+H42-H41 | I43: =I40+I42-I41 | ... S43: =S40+S42-S41
A44: B cumulative net | B44: =B43 | C44: =B44+C43 | D44: =C44+D43 | E44: =D44+E43 | F44: =E44+F43 | G44: =F44+G43 | H44: =G44+H43 | I44: =H44+I43 | J44: =I44+J43 | ... S44: =R44+S43
A45: B closing cash | B45: =$B$14+B44 | C45: =$B$14+C44 | D45: =$B$14+D44 | E45: =$B$14+E44 | F45: =$B$14+F44 | G45: =$B$14+G44 | H45: =$B$14+H44 | I45: =$B$14+I44 | ... S45: =$B$14+S44
A46: B breakeven flag (net>=0) | B46: =IF(B43>=0,1,0) | C46: =IF(C43>=0,1,0) | D46: =IF(D43>=0,1,0) | E46: =IF(E43>=0,1,0) | F46: =IF(F43>=0,1,0) | G46: =IF(G43>=0,1,0) | H46: =IF(H43>=0,1,0) | I46: =IF(I43>=0,1,0) | ... S46: =IF(S43>=0,1,0)
A47: B cash-out flag (closing<0) | B47: =IF(B45<0,1,0) | C47: =IF(C45<0,1,0) | D47: =IF(D45<0,1,0) | E47: =IF(E45<0,1,0) | F47: =IF(F45<0,1,0) | G47: =IF(G45<0,1,0) | H47: =IF(H45<0,1,0) | I47: =IF(I45<0,1,0) | ... S47: =IF(S45<0,1,0)
A49: VERDICT BLOCK — computed, not asserted
A50: Measure | B50: Scenario A (per-seat) | C50: Scenario B (per-site) | D50: Reading
A51: M18 net cash/mo | B51: =S24 | C51: =S43 | D51: Reviewer: -$23,822/mo. This sheet: -$23,821. Reproduced on the original assumptions, so the disagreement (if any) is about the assumptions, not the arithmetic.
A52: Cumulative net at M18 | B52: =S25 | C52: =S44 | D52: The reviewer put Scenario A at -$574,601; this sheet computes -$574,596 on the same inputs, a $5 rounding difference. The finding is reproduced, not disputed.
A53: Breakeven month (first net >= 0) | B53: =IFERROR("M"&MATCH(1,B27:S27,0),"none within 18 months") | C53: =IFERROR("M"&MATCH(1,B46:S46,0),"none within 18 months") | D53: Review finding D-01 was that no breakeven month existed anywhere in the sheet. It now either has a month or says so.
A54: Funding requirement ($, worst cumulative) | B54: =IF(MIN(B25:S25)<0,-MIN(B25:S25),0) | C54: =IF(MIN(B44:S44)<0,-MIN(B44:S44),0) | D54: With opening cash at zero this is the cash this plan needs before it is self-funding. Stating it is the requirement P-018 asked for.
A55: Runway (months before closing cash < 0) | B55: =IFERROR(MATCH(1,B28:S28,0)-1,18) | C55: =IFERROR(MATCH(1,B47:S47,0)-1,18) | D55: Zero means the plan is under water from month one on the opening cash entered above. Set opening cash and other cash-in to see a real runway.
A56: Paying accounts at M18 | B56: =S20 | C56: =S39 | D56: Compare with G-02 (10 paying installs from strangers) and SD247 (5 signed pilots): the gate is a count of customers, not a revenue line.
A57: MRR at M18 (net of fee) | B57: =S21 | C57: =S40 | D57: Net of the 3% marketplace fee. Verify the fee at offer setup.
A59: Honest reading (D-01/D-02/P-018): on the v045 per-seat assumptions this product does not break even inside 18 months, and the sheet now says so in a cell rather than leaving it to a reader to notice. Per-site pricing changes the arithmetic but not the evidence: both scenarios rest on a pilot->paid rate and an ARPU that no customer has yet paid. The number to act on is the funding requirement, and the thing that would replace these inputs with facts is SD244 (15 interviews) followed by SD247 (5 signed pilots).

Sheet Metrics_Targets
A1: METRIC TARGETS — restated per review finding D-03: absolute values with a named measurement source, not multiples of an unknown baseline
A2: D-03 said these targets were unfalsifiable: "3x M1" cannot be missed if M1 is undefined. Every row below now has an absolute number and the code path that measures it, so a miss is visible. M1 = first full calendar month after the listing goes live (G-01).
A3: Metric | B3: M1 | C3: M3 | D3: M6 | E3: M12 | F3: Measured by | G3: Fails if
A4: Paying tenants (cumulative) | B4: 3 | C4: 10 | D4: 25 | E4: 60 | F4: src/billing.ts subscriptions with status=active; G-02 counts only paying strangers | G4: Fewer than 10 by M3 — G-02 unreachable and the S12 kill criteria are evaluated
A5: Installs (cumulative) | B5: 15 | C5: 60 | D5: 150 | E5: 400 | F5: src/install.ts install events, deduplicated by tenant (F-002) | G5: Fewer than 60 by M3 with listing live: the listing, not the product, is the problem
A6: Activation % within 24h | B6: 40% | C6: 45% | D6: 50% | E6: 55% | F6: src/telemetry.ts funnel install->setup->aha, wired at the request boundary since session 24 | G6: Below 35% at M3 — onboarding, not demand
A7: Trial->paid % | B7: 25% | C7: 30% | D7: 33% | E7: 35% | F7: src/entitlements.ts trial expiry vs subscription activation | G7: Below 20% at M3 — pricing or wedge is wrong (SD245)
A8: Week-4 retention of activated tenants | B8: 55% | C8: 60% | D8: 65% | E8: 70% | F8: src/dashboardManager.ts cohort retention | G8: Below 50% — the evidence wedge is not being used after the first shift
A9: Store rating | B9: 4.5+ | C9: 4.6+ | D9: 4.7+ | E9: 4.7+ | F9: Partner Center listing (manual read, monthly) | G9: Below 4.3 — review programme and support speed
A10: MRR $ net of fee | B10: 1200 | C10: 4000 | D10: 10000 | E10: 24000 | F10: Financial_Model Scenario A/B actuals replace the planning inputs | G10: Below half the M6 figure — the funding requirement in Financial_Model is the live question
A11: Logo churn /mo | B11: <5% | C11: <4% | D11: <3% | E11: <3% | F11: src/dashboardManager.ts health score + cancellation reasons (ST-063 exit survey) | G11: Above 6% for two consecutive months
A12: API p95 / bot p95 (ms) | B12: 500 / 800 | C12: 500 / 800 | D12: 450 / 700 | E12: 400 / 650 | F12: src/perf.ts latency budgets; src/slo.ts alert rules | G12: Any month over budget — the rollback signal in ops/incident-response-runbook.md
A13: Availability (SLO 99.5%) | B13: 99.5% | C13: 99.5% | D13: 99.5% | E13: 99.5% | F13: src/slo.ts — 216 minutes of error budget per month, stated as minutes rather than nines | G13: Two consecutive months of budget exhaustion

Sheet Risk_Register
A1: PRODUCT RISK REGISTER — rewritten per review finding D-04 (the free first-party overlap was understated)
A2: The review was blunt: two of the three product pillars overlap Microsoft apps the customer already has at no marginal cost. That is a commercial risk, not a feature gap, and it belongs at the top of this register rather than as a line about a future Shifts release.
A3: Risk | B3: Impact | C3: Likelihood | D3: Mitigation | E3: Owner / story
A4: Two of three pillars overlap FREE first-party Microsoft apps: Approvals and Planner task publishing ship inside Microsoft 365 at zero marginal cost. A per-seat frontline price competes with free, and an IT buyer will ask why. | B4: High | C4: High (already true, not a future release) | D4: Reposition onto the one thing the free tools do not produce: retained, queryable handover evidence with an audit trail an inspector can read. Listing copy, one-pager and comparison pages rewritten explicitly against Approvals and Planner rather than around them (SD245). Per-site pricing modelled so the price is not a per-seat tax on a suite the customer already owns (SD246). The wedge is tested in the SD244 interviews before launch spend. | E4: Senthil — SD244 / SD245
A5: Microsoft ships native Shifts upgrades that absorb the handover thread itself | B5: High | C5: Medium | D5: Depth in approvals and checklists plus the evidence retention story; co-sell alignment so an upgrade is a distribution event rather than an extinction event. Reassess at each Microsoft 365 roadmap release. | E5: Senthil
A6: Demand is unvalidated: the category grows 18.65% CAGR to $45.06bn by 2031, and not one customer has said this product solves a problem they pay for. D13 parked discovery interviews portfolio-wide. | B6: High | C6: High | D6: 15 discovery interviews in regulated frontline sectors on how handover evidence is produced today and what an audit failure costs (SD244). This is the programme gate: G-01/G-02 become achievable on evidence, or the kill criteria fire. | E6: Senthil — SD244
A7: Enterprise sales cycle starves cash before S12: on the v045 per-seat assumptions the model never breaks even and the funding requirement was never stated. | B7: High | C7: Medium | D7: Financial_Model repaired to state the funding requirement, runway and breakeven outright (SD246). Pilot pricing and design-partner order forms by SD247. Per-site pricing gives a smaller first cheque with an expansion path. | E7: Senthil — SD246 / SD247
A8: Store certification loops exceed 2 cycles | B8: Medium | C8: High | D8: Pre-submission consult; validation self-check automated where possible (manifest and command parity assertions in CI); dry run recorded. Attestation and pen test start early because of lead times (SD234/SD235). | E8: Senthil — SD235
A9: Assurance items have long lead times and real money attached: pen test, Publisher Attestation, SOC 2 (audit fee $15k-$50k plus ~6 months observation for Type II). | B9: Medium | C9: High | D9: Evidence packs and control maps are built and bound to tests (SD236/SD237) so the engagements start without a discovery phase. The spend and the timing are Senthil decisions, stated rather than buried. | E9: Senthil — SD237
A10: Perimeter code written from vendor documentation rather than against live endpoints: Entra metadata, Connector JWT rules, Fulfillment API v2, Key Vault managed identity. | B10: Medium | C10: Medium | D10: Same class as tracker risk R-S12, which is why that risk exists: every seam gets a documentation sweep and then live verification before it is called done. SD228, SD232, SD239 and SD240 are those verifications. | E10: Claude + Senthil
A11: This release wrote 19 new modules and 11 new suites; on this project's own history, newly written code is the least-reviewed code (six defects in twelve modules at 100% coverage in sessions 5-8). | B11: Medium | C11: High | D11: The next session opens with a cold review of the S13-S20 code before any new feature work. F-071 and F-072 are already on the register as evidence the pattern held again. | E11: Claude — tracker R-S21

Sheet Traceability_Matrix
A1: TRACEABILITY MATRIX — story -> code -> test -> evidence (v006, 10/09/2026 22:26)
A3: ID | B3: Epic | C3: Sprint | D3: Points | E3: Module / file | F3: Test suite | G3: Status | H3: Evidence / note
A4: ST-001 | B4: F1 | C4: S2 | D4: 5 | E4: src/handover.ts + src/moduleBase.ts | F4: tests/features.test.ts + tests/moduleBase.test.ts | G4: Done | H4: Built + covered at 100% this session
A5: ST-002 | B5: F1 | C5: S2 | D5: 8 | E5: src/handover.ts + src/moduleBase.ts | F5: tests/features.test.ts + tests/moduleBase.test.ts | G5: Done | H5: Built + covered at 100% this session | State now persisted via src/persistence.ts — survives restart/blue-green (GAP-SD8b)
A6: ST-003 | B6: F1 | C6: S2 | D6: 5 | E6: src/handover.ts + src/moduleBase.ts | F6: tests/features.test.ts + tests/moduleBase.test.ts | G6: Done | H6: Built + covered at 100% this session
A7: ST-004 | B7: F1 | C7: S2 | D7: 3 | E7: src/handover.ts + src/moduleBase.ts | F7: tests/features.test.ts + tests/moduleBase.test.ts | G7: Done | H7: Built + covered at 100% this session
A8: ST-005 | B8: F1 | C8: S3 | D8: 5 | E8: src/ui/screens.tsx + web/TabShell.tsx + src/server.ts | F8: tests/ui.screens.test.tsx + tests/tab.test.tsx | G8: Code-complete pending live | H8: Surface now full-stack incl. HTTP layer (GAP-SD5): client paths served + authenticated; only in-client render pending | Tab assets served by the app itself at /tab (F-058)
A9: ST-006 | B9: F1 | C9: S3 | D9: 3 | E9: src/handover.ts + src/moduleBase.ts | F9: tests/features.test.ts + tests/moduleBase.test.ts | G9: Done | H9: Built + covered at 100% this session
A10: ST-007 | B10: F1 | C10: S3 | D10: 3 | E10: src/handover.ts + src/moduleBase.ts | F10: tests/features.test.ts + tests/moduleBase.test.ts | G10: Done | H10: Built + covered at 100% this session
A11: ST-008 | B11: F1 | C11: S3 | D11: 2 | E11: src/handover.ts + src/moduleBase.ts | F11: tests/features.test.ts + tests/moduleBase.test.ts | G11: Done | H11: Built + covered at 100% this session
A12: ST-009 | B12: F1 | C12: S3 | D12: 5 | E12: src/handover.ts + src/moduleBase.ts | F12: tests/features.test.ts + tests/moduleBase.test.ts | G12: Done | H12: Built + covered at 100% this session
A13: ST-010 | B13: F1 | C13: S3 | D13: 3 | E13: src/notifications.ts + src/notificationDispatcher.ts | F13: tests/notificationDispatcher.test.ts | G13: Done | H13: Delivery implemented on both channels with independent failure handling (F-034); live send verified by sweep step SW-18
A14: ST-011 | B14: F2 | C14: S3 | D14: 5 | E14: src/approvals.ts + src/moduleBase.ts | F14: tests/features.test.ts + tests/moduleBase.test.ts | G14: Done | H14: Built + covered at 100% this session
A15: ST-012 | B15: F2 | C15: S3 | D15: 8 | E15: src/approvals.ts + src/moduleBase.ts | F15: tests/features.test.ts + tests/moduleBase.test.ts | G15: Done | H15: Built + covered at 100% this session | State now persisted via src/persistence.ts — survives restart/blue-green (GAP-SD8b)
... A150: SD247 | B150: E20 | C150: S20 | D150: 6 | E150: src/telemetry.ts funnel (wired at the boundary since session 24) | F150: tests/observability.test.ts | G150: To do — Senthil | H150: Closes G-02. The funnel that would measure this is real and wired. The five customers are not, and G-02 counts only paying strangers.
A152: Coverage evidence (v0.14.0): jest --ci — 68 unit suites / 555 tests passed at 100% statements, branches, functions and lines, zero pragmas; plus a real-Postgres integration tier (9/9, tests/integration/) and a production-seam wiring assertion that also runs at boot — the three tiers of decision D-SD7. Status colours: green=Done, amber=pending live, blue=drafted, orange=owed to Senthil (D-SD8).

Sheet Review_Findings
A1: COLD-REVIEW PASS 1 — 11/09/2026 12:51 (adversarial self-review; external second review still owed per ST-097)
A3: ID | B3: Severity | C3: Finding | D3: Resolution | E3: Status / Disposition
A4: F-001 | B4: High | C4: Billing had no payment-recovery path: an account in grace or read-only could never return to active; dunning counter never reset. | D4: paymentRecovered() added — grace/read_only -> active, dunning + graceStart reset, recovery email logged; dunning restarts fresh on a later failure. Regression pinned. | E4: FIXED (regression tests)
A5: F-002 | B5: High | C5: Duplicate install webhook silently overwrote an existing tenant account — full data loss on a repeated Teams install event. | D5: install() made idempotent: existing account returned untouched, install_duplicate_ignored telemetry row. Regression pinned. | E5: FIXED (regression tests)
A6: F-003 | B6: Medium | C6: Unbounded in-memory ledgers: telemetry error list and notification sent-log grew forever (memory exhaustion under sustained traffic). | D6: Both FIFO-capped at 10,000 entries. Regression pinned. Audit log deliberately NOT capped — see F-008. | E6: FIXED (regression tests)
A7: F-004 | B7: Medium | C7: Retry backoff delays were computed (backoffDelay) but never applied — retries hammered the platform API instantly, defeating ST-070 intent. | D7: Injectable sleeper wired between failed attempts (exponential, none after final attempt); no-op default in tests, setTimeout at live bootstrap. Regression pinned. | E7: FIXED (regression tests)
A8: F-005 | B8: Medium | C8: Approval engine auto-approved zero and negative amounts (amount <= threshold held for -50). | D8: submit() validates amount > 0 -> AMOUNT_INVALID. Regression pinned. | E8: FIXED (regression tests)
A9: F-006 | B9: Low | C9: Checklist CSV export corrupted by commas/quotes in task text (column drift in compliance evidence). | D9: RFC-4180 quoting applied. Regression pinned. NOTE: CSV importer (moduleBase.importCsv) is still naive-split — flagged in REVIEW_PACK probes as candidate finding for pass 2. | E9: FIXED (regression tests)
A10: F-007 | B10: Medium | C10: Circuit breaker has no half-open probe: once open it stays open until manual reset() — a transient Teams outage requires operator action to recover. | D10: Options: (a) half-open probe after cooldown N seconds, (b) keep manual-reset semantics + ops alert. Same class as OnCall F-006. | E10: OPEN — Senthil disposition
A11: F-008 | B11: Low | C11: AuditLog grows unbounded in-memory. Capping would truncate a compliance trail, so no FIFO applied. | D11: Postgres-backed audit table at S1-08 live wiring; in-memory mode acceptable for sandbox/tests only. | E11: OPEN — Senthil disposition
A12: F-009 | B12: Process | C12: Evidence discipline: v006 traceability for ST-066 said "vault/encryption pattern coded" before any such module existed in the repo. | D12: Corrected this session: src/crypto.ts built (AES-256-GCM, unique IVs, tamper rejection, SecretsVault with redacted dump + key rotation) — the claim is now true; ST-066 stays Code-complete pending live KMS wiring. Lesson logged: evidence strings must name an existing file. | E12: CLOSED — corrective action done
A14: COLD-REVIEW PASS 2 — 11/09/2026 20:30 (modules pass 1 skipped) — review COMPLETE across all modules
A15: F-010 | B15: Medium | C15: CSV importer was naive comma-split (RAID R-S7): quoted fields with commas mis-parsed on import while export was already RFC-4180. | D15: parseCsvLine RFC-4180 parser wired into importCsv. Regression pinned. R-S7 closed. | E15: FIXED (regression tests)
A16: F-011 | B16: Medium | C16: Telemetry alert ledger unbounded AND spammed — churn/activation alerts re-fired on every call (same low health score pushed 50 identical alerts). | D16: fireAlert(): consecutive-duplicate dedupe + FIFO cap 1000. Regression pinned. | E16: FIXED (regression tests)
A17: F-012 | B17: Low | C17: Latency monitor samples unbounded per surface; p95 sorted an ever-growing array (same ledger class as F-003, missed in pass 1). | D17: Rolling 10k window per surface. Regression pinned. | E17: FIXED (regression tests)
A18: F-013 | B18: Medium | C18: Trial banner shown to NON-trial accounts — a paying customer saw "Trial ended — choose a plan"; grace/read-only accounts likewise. | D18: bannerText returns empty for any state other than trial. Regression pinned. | E18: FIXED (regression tests)
A19: OBS-SD1 | B19: Obs | C19: complete()/acknowledge on a PAUSED module still succeeds — pause blocks new items only. Plausibly intended (finish in-flight work) but undocumented. | D19: Options: (a) document as intended, (b) block all writes on pause. | E19: OPEN — Senthil disposition
A21: EXTERNAL VERIFICATION SWEEP — 13/09/2026 09:52 (assumptions checked against live Microsoft Teams/Partner Center docs + artifact-gap audit)
A22: VER-SD01 | B22: STORE-BLOCKING | C22: ASSET_PLAN specified 5 screenshots at 1920x1080. Verified Teams Store spec is 1366x768, max 1,024 KB each, minimum 3 / maximum 5, and at least one MUST show mobile functionality. Assets produced to the old spec would have failed validation. Video also takes a YouTube/Vimeo URL, not an upload. | D22: ASSET_PLAN.md rewritten to the verified spec (mobile shot already slot 3); pinned by tests/manifest.test.ts so the old figure cannot return. | E22: FIXED (test-pinned)
A23: VER-SD02 | B23: STORE-BLOCKING | C23: Manifest declared schema v1.17. Current is v1.19 (v1.18 does not exist) and store submission requires referencing the latest schema. | D23: Manifest bumped to v1.19 ($schema + manifestVersion); assertion added to the package-validation suite. | E23: FIXED (test-pinned)
A24: VER-SD03 | B24: High | C24: Manifest carried the top-level "permissions": ["identity","messageTeamMembers"] block — this property is deprecated in the current manifest reference. | D24: Removed; replaced by authorization.permissions.resourceSpecific. Absence asserted in tests. | E24: FIXED (test-pinned)
A25: VER-SD04 | B25: High | C25: Least-privilege doc (ST-064, gate LC-5 previously marked Done) claimed org-wide Graph scopes incl. TeamMember.Read.All — far broader than needed and inconsistent with a Teams bot. Correct model is resource-specific consent, scoped to the installed team. Manifest also declared no RSC block at all, so the bot could not read members or post without @mention. | D25: SCOPE_MAP + docs rewritten to RSC (ChannelMessage.Send.Group, ChannelMessage.Read.Group, TeamMember.Read.Group, delegated User.Read); manifest gains the RSC block; test asserts manifest RSC names equal the published map and that no ".Read.All" string exists anywhere. | E25: FIXED (test-pinned)
A26: VER-SD05 | B26: Verified OK | C26: botId vs webApplicationInfo.id match, validDomains present, resource URI shape, colour icon 192x192, 3% Microsoft store service fee in the financial model. | D26: No change; match now asserted in tests so it cannot drift. | E26: VERIFIED
A27: VER-SD06 | B27: Medium | C27: Outline icon was white-on-transparent but had padding on all sides; store guideline requires it tightly cropped with no extra padding. | D27: Icon regenerated edge-to-edge (bbox 0,0,32,32), white + transparency only; dimensions asserted from PNG headers in tests. | E27: FIXED (test-pinned)
A28: VER-SD07 | B28: Doc | C28: AppSource is now presented as "Microsoft Marketplace"; publisher docs describe the 3% charge as a standard store service fee. | D28: Naming noted for listing/GTM copy; economics unchanged (3% verified), financial model needs no revision. | E28: NOTED
A29: VER-SD08 | B29: LIVE-BLOCKING (gap) | C29: Artifact-gap audit: the manifest declares three static tabs but no code ever performed the TeamsJS handshake. A contentUrl page that never calls app.initialize()/notifySuccess renders a blank, error-less tab inside Teams — invisible to the whole suite, same class as the sibling-product SDK gaps. | D29: src/teamsClient.ts boundary built — initialize, context validation, theme handler, notifySuccess/notifyFailure, and an explicit user-facing error when the TeamsJS script is absent (never a blank tab); 5 tests covering every path. Sweep extended 12 -> 14 steps (RSC consent + tab handshake); dev-tenant guide gains the bootstrap step. | E29: FIXED (test-pinned)
A31: ARTIFACT-GAP AUDIT ROUND 2 — 13/09/2026 10:01 (manifest promises vs shipped code)
A32: GAP-SD1 | B32: LIVE-BLOCKING | C32: Manifest declared three static tabs (home, handovers, checklists) pointing at contentUrl pages that did not exist — no entry page, no bundle, no mount. Session 7 built only the TeamsJS boundary, not the page behind it. Installing the app would have shown three broken tabs. | D32: web/ layer built: TabShell (bootstrap -> entity routing -> real screens with loading/error states), typed TabApi with injected fetcher (401/403/outage mapped to distinct human messages), entry.tsx mount reading ?entity=, index.html loading TeamsJS BEFORE the bundle, esbuild build script -> web-dist/. 20 tests incl. unmount-in-flight paths. | E32: FIXED (test-pinned)
A33: GAP-SD2 | B33: High | C33: Manifest commandLists advertised /handover, /approve and /checklist to every user, but nothing in the codebase parsed or handled a bot command — the advertised commands would have produced no response. | D33: src/botRouter.ts built over the existing dispatcher: @mention-chip stripping, slash/case normalisation, handover/ack/approve/checklist/kudos/help, usage errors for every malformed form, and distinct replies for permission denial vs validation failure. 6 tests. | E33: FIXED (test-pinned)
A34: GAP-SD3 | B34: Medium | C34: Tab bundles were initially emitted into teams-app/ alongside the manifest; the store package should contain only the manifest and the two icons. | D34: Bundles moved to web-dist/; package contents asserted exactly ["color.png","manifest.json","outline.png"] in tests, plus script-order assertion (TeamsJS before tab.js). | E34: FIXED (test-pinned)
A35: GAP-SD4 | B35: Opportunity | C35: ST-094 assets were blocked entirely on the live tenant. | D35: web-dist/demo.html capture surface added — fixed 1366x768 box with canned data, verified rendering headless; shots 1/3/4 draftable today. Finals still come from the live client (store requires accurate UI). | E35: PARTIALLY UNBLOCKED
A37: COLD-REVIEW PASS 3 — 13/09/2026 10:24 (over the session 5-8 code: web tab layer, bot router, completion wave, config, crypto — none of it previously reviewed)
A38: F-014 | B38: Medium | C38: Approval amounts accepted Infinity and 1e999: the pass-1 fix guarded only "amount > 0", which Infinity satisfies. A bot user typing "approve Infinity stock" created a request routed to review with a non-finite value (same class as the sibling non-finite-date defect). | D38: Number.isFinite check added alongside the positive check; pinned at both the bot and service layers. | E38: FIXED (regression tests)
A39: F-015 | B39: Medium | C39: Bot checklist parser filtered empty segments BEFORE assigning the title, so "checklist | Unlock | Count till" silently created a checklist named "Unlock" with one task — a wrong artifact rather than an error. | D39: Parse without filtering, take parts[0] as the title, validate it explicitly; empty segments only dropped from the task list. | E39: FIXED (regression tests)
A40: F-016 | B40: High | C40: TabApi read the SSO token, validated it was non-null — and never sent it. Every tab API call would have gone out unauthenticated in production; the tests passed because the fetcher was injected and never asserted on headers. Exactly the "computed but never applied" class as F-004. | D40: Token threaded through the Fetcher contract and emitted as an Authorization bearer header by createFetcher; 401 now mapped to a distinct "session expired, reload the tab" message rather than the generic outage text. Header presence and absence both asserted. | E40: FIXED (regression tests)
A41: F-017 | B41: Medium | C41: TeamsClient.bootstrap was not idempotent — a second call re-ran initialize and fired notifySuccess again (React double-invoke, re-render, or an entity switch would trigger it). | D41: Ready state short-circuits and returns the cached state; init/notify call counts asserted. | E41: FIXED (regression tests)
A42: F-018 | B42: Medium | C42: Internal error codes were shown verbatim to frontline users in Teams ("Could not complete that: SELF_KUDOS_NOT_ALLOWED", "NOT_FOUND"). | D42: humanize() map added with a safe fallback for unknown codes; every mapped code and the fallback path pinned. | E42: FIXED (regression tests)
A43: F-019 | B43: Medium | C43: SHIFTDESK_TRIAL_DAYS was loaded, range-validated and then ignored — BillingService hard-coded 14 days, so a configured trial length silently did nothing. | D43: BillingService takes trialDays (validated, defaulting to the exported DEFAULT_TRIAL_DAYS); config-to-billing consistency pinned. | E43: FIXED (regression tests)
A44: OBS-SD2 | B44: Obs | C44: Dead defensive branch found during review (parts[0] ?? '' — String.split always yields at least one element). Removed rather than covered with an unreachable-state test. | D44: No behaviour change; noted so the pattern is recognised rather than papered over with a contrived test. | E44: CLOSED
A46: ARTIFACT-GAP AUDIT ROUND 3 — 13/09/2026 10:37 (client calls vs server routes)
A47: GAP-SD5 | B47: LIVE-BLOCKING | C47: No HTTP server existed at all, and the tab client called routes nothing served: /api/handovers, /api/checklists/today and /api/checklists/today/check had no handler anywhere, while /api/dashboard and /api/handover/ack existed only under different names inside the in-process dispatcher. The Azure Bot messaging endpoint /api/messages — referenced by the dev-tenant guide and the k6 harness — did not exist either. On install day every tab would have loaded and then failed on its first call. Exactly the sibling class where a UI posted to a route that was never built. | D47: src/server.ts built: pure testable router over the dispatcher serving all five tab paths plus /api/messages, /health and /status; bearer-token auth enforced before any work (401 unauthenticated vs 401 invalid token vs 403 permission); 405 on wrong verb; trailing slash and query string normalised. Dispatcher gained GET /handovers, GET /checklists/today, POST /checklists/today/check with the service support behind them. src/bootstrap.ts wires node:http with the typed config, verified over a real socket in test. PARITY TEST reads web/tabApi.ts and asserts every path it calls is served under at least one verb — so this class of gap now fails CI. | E47: FIXED (test-pinned)
A48: OBS-SD3 | B48: Obs | C48: Second dead defensive branch found and removed (today() fell back to an empty list for a state that cannot occur — the current id is only ever set alongside its task list). Same pattern as OBS-SD2. | D48: Removed rather than covered with an unreachable-state test. | E48: CLOSED
A50: VERIFICATION SWEEP 2 — 13/09/2026 10:42 (bot transport seam checked against live Bot Framework / Bot Connector docs)
A51: VER-SD09 | B51: LIVE-BLOCKING | C51: The /api/messages endpoint built in session 10 required OUR tab SSO bearer token and read a {text} body. Teams does neither: the Bot Connector calls the endpoint with its own RS256 JWT bound to the activity serviceUrl, and sends a Bot Framework Activity. Every real Teams message would have been rejected 401 — a defect introduced by the previous session and invisible to its own passing tests. | D51: src/botTransport.ts built as a separate trust boundary: Connector JWT verification (injected), serviceUrl allowlisted to Bot Connector hosts before any reply, Activity parsing, and a distinct async server path (handleActivity). Tab SSO tokens are explicitly proven NOT to open it. | E51: FIXED (test-pinned)
A52: VER-SD10 | B52: LIVE-BLOCKING | C52: Replies were returned in the HTTP response body. The Connector model is: ack the request, then post the reply to the conversation at the activity serviceUrl with bot credentials. Replies would never have reached the channel. | D52: Endpoint now acks 200 with an empty body and sends through an injected ConnectorSender bound to the activity serviceUrl; asserted both ways. k6 harness updated to assert an empty-body ack, and the sweep step reworded to match. | E52: FIXED (test-pinned)
A53: VER-SD11 | B53: High | C53: Sender identity and role came from our own token verifier. In a real activity the sender is from.aadObjectId and the tenant sits in channelData.tenant.id. | D53: Actor and tenant read from the activity; role resolved through an injected RoleResolver. Permission behaviour proven for both an owner and a member on the same command. | E53: FIXED (test-pinned)
A54: VER-SD12 | B54: High | C54: Non-message activities were answered with a help reply, and conversationUpdate was never handled — so the install welcome (ST-051, the <2 min activation evidence) had nowhere to come from, and unacked activity types would be retried by the Bot Service. | D54: conversationUpdate with the bot in membersAdded now sends the welcome; a member joining, typing and invoke are acked silently; activity ids deduped (bounded ledger) so Connector retries cannot double-post. | E54: FIXED (test-pinned)
A56: VERIFICATION SWEEP 3 — 13/09/2026 10:57 (tab SSO seam vs live Entra / Teams SSO docs)
A57: VER-SD13 | B57: LIVE-BLOCKING | C57: The tab passed the literal string "teams-sso" as its bearer token — a placeholder shipped in session 8 and carried through two audits. The manifest has declared webApplicationInfo (SSO) since session 3, so this is another manifest promise with no implementation: the real flow is microsoftTeams.authentication.getAuthToken() client-side, then server-side validation of the Entra v2 access token. Every authenticated tab call would have failed in a real tenant. | D57: Client: TeamsClient.getAuthToken() with caching to just under the ~60-minute lifetime, clearToken(), and consent_required / invalid_grant / interaction_required surfaced as an actionable ConsentRequiredError instead of a generic failure; entry.tsx now wires it in place of the placeholder. Server: src/ssoToken.ts validates audience against all four documented forms (appId, api://appId, api://botid-appId, api://domain/appId), issuer matching the token tenant, v2 token version, oid/tid presence, exp/nbf, and the access_as_user scope — each rejection distinct. bootstrap.ssoVerifierFor derives the expectation from config; the JWKS signature check is an explicit injected seam. | E57: FIXED (test-pinned)
A58: VER-SD14 | B58: Doc | C58: Entra app registration guide omitted the Expose an API step, without which getAuthToken() cannot issue a token at all. | D58: Dev-tenant guide gains step 4b (Application ID URI + access_as_user scope + pre-authorized Teams clients); scope map and least-privilege doc updated to list access_as_user and how it is validated; sweep gains SSO and first-run-consent steps (15 -> 16). | E58: FIXED
A60: ARTIFACT-GAP AUDIT ROUND 4 — 13/09/2026 11:02 (requested permissions vs code that consumes them)
A61: GAP-SD6 | B61: High | C61: TeamMember.Read.Group was requested in the manifest and the least-privilege doc claimed it powered the role matrix — but nothing consumed it. Every resolveRole across both trust boundaries was an injected stub, so in a real tenant every user (including team owners) would have resolved to "member" and admin-only actions would have been impossible for everyone. | D61: src/graphMembers.ts built: RSC app-token Graph client for team membership with @odata.nextLink pagination (large teams would otherwise silently truncate), 429 handling that reads Retry-After as SECONDS, a ten-minute cache, and deny-safe failure — a Graph outage degrades everyone to member and never elevates. Team owners map to ShiftDesk admins; the installer recorded by install.ts is the owner. bootstrap.rolesFrom binds both the tab and bot boundaries to the same directory. | E61: FIXED (test-pinned)
A62: GAP-SD7 | B62: Medium | C62: ChannelMessage.Send.Group was requested but had no consumer: replies are posted through the Bot Connector at the activity serviceUrl using bot credentials, not through Graph. An unused grant is not least privilege — it is an extra permission on the customer consent screen that we could not justify in review. | D62: Scope removed from the manifest and the published map. Flagged as D-SD5 for ratification: if proactive Graph-based channel posting is ever wanted, the scope returns together with the code that uses it. A new contract test asserts every requested scope names a consumer file that exists, and that no consumer entry lacks a scope — so this cannot recur in either direction. | E62: FIXED (test-pinned)
A64: COLD-REVIEW PASS 4 — 13/09/2026 11:07 (over the sessions 10-13 integration code: server, bootstrap, bot transport, SSO, Graph directory, tab wiring)
A65: F-020 | B65: High | C65: The HTTP layer exposed every dispatcher route by prefix, including lifecycle ones: any authenticated user — a frontline member — could POST /api/install or /api/trial with an arbitrary tenantId, creating or resetting accounts for other organisations. | D65: Lifecycle routes taken off the HTTP surface entirely (INTERNAL_ROUTES) rather than guarded by a role check, since no client should ever call them; they remain available to the install webhook and billing engine through the in-process dispatcher. Pinned for both member and owner tokens. | E65: FIXED (regression tests)
A66: F-021 | B66: Medium | C66: Graph pagination followed @odata.nextLink with no loop or page guard; a repeated or malformed link would spin forever, holding the request and hammering Graph. | D66: Visited-URL set plus a 200-page ceiling; both the repeat case and the runaway case pinned. | E66: FIXED (regression tests)
A67: F-022 | B67: High | C67: Single-tenant mode silently denied every user: the expectation was built with an empty tenant allowlist because config had no tenant id field at all. A single-tenant deployment would have started cleanly and rejected all logins with no clue why. | D67: Config gains SHIFTDESK_ALLOWED_TENANT_ID, REQUIRED when tenant mode is single — the app now refuses to boot rather than failing every request. Multi-tenant behaviour unchanged; dev guide updated. | E67: FIXED (regression tests)
A68: F-023 | B68: Medium | C68: A 401 left the cached SSO token in place, so once a token went stale every subsequent call failed until the user manually reloaded the tab. | D68: TabApi takes an auth-failure callback; entry wires it to clearToken() so the next attempt re-acquires. Message reworded from "reload the tab" to reflect the automatic retry. | E68: FIXED (regression tests)
A69: F-024 | B69: High | C69: Activities were marked as seen BEFORE handling, so if the Connector send failed the Bot Service retry was silently deduped away — a handover the user believed they had posted would simply never appear. | D69: Activities are remembered only after successful handling; a failed send now lets the retry redeliver, and the second success still dedupes. Pinned with a fail-then-retry-then-duplicate sequence. | E69: FIXED (regression tests)
A71: ARTIFACT-GAP AUDIT ROUND 5 — 13/09/2026 11:12 (documented architecture vs code: persistence)
A72: GAP-SD8 | B72: LIVE-BLOCKING | C72: RAID R-S4 has stated since session 1 that persistence was "in-memory behind typed repositories" and that going live would be "wiring only". There were no repositories: every service held bare Maps. Consequences in a live tenant — a restart or the blue/green swap built in session 4 (ST-092) would destroy every handover, checklist, kudos, audit entry and billing account; the backup/restore drill (ST-090) had no schema to back up; the published 365-day retention and 30-day uninstall deletion policies had no mechanism behind them; and the app could never run more than one instance. The claim had been repeated in three workbook releases without anyone checking it. | D72: src/repository.ts built: Repository interface (put/get/list/remove/purgeTenant) with InMemoryRepository and PostgresRepository over an injected SqlClient, plus migrations/001_init.sql — a tenant-scoped record table with the primary key ordered for cheap per-tenant purge and an index for list-by-kind. purgeTenant gives ST-052 uninstall deletion and ST-069 delete-my-data an actual implementation. DurableAuditLog replaces the in-memory compliance trail flagged by F-008. ONE contract suite runs against both implementations so the dev and production paths cannot drift. bootstrap.repositoryFor selects by config and the startup banner warns explicitly when running without a database. | E72: FIXED (test-pinned)
A73: OBS-SD4 | B73: Obs | C73: The fake SQL client in the contract suite understands only the five statements the repository issues; it is a fake, not a database. Index behaviour, JSONB semantics and migration correctness remain unproven until the drill runs on live Postgres. | D73: Stated plainly rather than implied: sweep gains step SW-13 (data survives a restart / blue-green swap) and the backup drill now targets the real schema. | E73: OPEN — live verification
A75: GAP-SD8 COMPLETION — 13/09/2026 11:16 (the seam built last session was not yet used by the services)
A76: GAP-SD8b | B76: High | C76: Session 15 built the repository and wired only the audit log through it. Every feature service still held bare Maps, so the durability claim was half-true — exactly the pattern the same session criticised. A restart would still have lost every handover, approval, checklist and kudos. | D76: Snapshot/restore added to the sync service core (items, rules, pause state, sequence counters, checklist tasks and current list, approval policy and requests, kudos tallies) as pure functions; src/persistence.ts hydrates an app from the repository at startup and writes back after each mutating route, touching only the modules that route affects; the HTTP layer routes through handlePersisted. Proven by populating an app, discarding it, and restoring a fresh one — including that restored sequence counters continue rather than colliding, and that a failed mutation writes nothing. | E76: FIXED (test-pinned)
A77: OBS-SD5 | B77: Obs | C77: Persistence covers the four feature modules plus the audit trail. Billing accounts, install/uninstall records, support chat and telemetry are still process-memory only. | D77: Scope stated in the backup drill rather than left implied; this is the next persistence slice, not a claim of completeness. | E77: OPEN — next slice
A79: PERSISTENCE SLICE 2 + F-025 — 13/09/2026 11:21
A80: OBS-SD5a | B80: Closed | C80: Billing and install lifecycle state was still process-memory only: a restart reset trial clocks, forgot grace periods and dunning counters, and lost the 30-day uninstall deletion window along with the re-install restore it protects (ST-052/ST-053). Support chat lost open conversations and their SLA clocks. | D80: Snapshot/restore added to BillingService, InstallService and SupportChat; billing and install added to the persisted set with an explicit LIFECYCLE_MODULES list, since F-020 took those operations off the HTTP surface and their callers must persist directly. Proven across a simulated restart: the grace clock keeps running, dunning resumes at 3 rather than restarting at 1, an expired deletion window is still purged, and a breached support SLA is not forgiven by a deploy. | E80: FIXED (test-pinned)
A81: F-025 | B81: High | C81: Found while writing the lifecycle tests, not by reading the code: InMemoryRepository stored live object references. A caller mutating an object after put() silently changed "persisted" state, and two hydrations handed back the same live object. PostgresRepository round-trips through JSON and does neither — so the dev path and the production path behaved differently, which is exactly the drift the shared contract suite exists to prevent. A bug would have reproduced only in production. | D81: Copy-in / copy-out in the in-memory implementation, pinned by a contract test that mutates after put, after get and after list — run against BOTH implementations. | E81: FIXED (regression tests)
A82: OBS-SD6 | B82: Obs | C82: Telemetry counters remain unpersisted. They are event-shaped rather than snapshot-shaped and are re-derivable, and the product already exports them (ST-076); persisting them properly needs an event store, not this record table. | D82: Rationale written into the backup drill rather than left as an unexplained omission. | E82: ACCEPTED — by design
A84: MULTI-TENANCY AUDIT — 13/09/2026 11:25 (the most serious defect found in this product)
A85: F-026 | B85: CRITICAL | C85: CROSS-TENANT DATA EXPOSURE. The request context carried no tenant at all and the server held ONE ShiftDeskApp for the whole process, so every authenticated user of every customer organisation read and wrote the same handovers, approvals, checklists and kudos. A supervisor at one company would have seen another company's shift briefs on their home tab. The store built in sessions 15-17 was tenant-scoped, which made the gap easy to miss: persistence looked correct while the runtime shared everything. This would have been a reportable data breach on day one of the pilot. | D85: Tenant is now part of identity: Ctx carries tenantId, the SSO verifier returns the tid it already validated, and the bot takes the tenant from the activity channelData. src/tenantRegistry.ts holds one app per tenant, hydrated from that tenant's own records on first use, with single-flight loading so concurrent first requests hydrate once, and bounded eviction that is safe because state is durable. Pinned: one tenant writing a handover and another reading an empty list; separate hydration across a restart; bot and API reaching the same per-tenant app. | E85: FIXED (test-pinned)
A86: F-027 | B86: Medium | C86: Found while wiring F-026: bot-driven mutations were never persisted at all. A handover created by the bot lived only in memory and vanished on the next deploy, while the same handover created from the tab survived. | D86: The transport takes an after-mutation callback wired to the registry; proven by creating a handover through the bot and reading it back through the API after a simulated restart. | E86: FIXED (regression tests)
A87: F-028 | B87: Medium | C87: Regression introduced by my own F-026 change and caught by an existing test: handlePersisted authenticated before dispatching, which made /health and /status require a token — load balancer and status-page probes would have failed on deploy. | D87: Public paths handled before authentication on both entry points, pinned by a test that exercises health and status through the persisted path specifically. | E87: FIXED (regression tests)
A89: DATA-DELETION AUDIT — 13/09/2026 11:51 (published policy vs what the code deletes)
A90: F-029 | B90: CRITICAL | C90: The published retention policy and the self-serve delete-my-data control deleted nothing. purgeTenant had been built in session 15 with ZERO callers; DataRights operated on an in-memory Map that no other code ever wrote to; and install.purgeExpired only dropped an in-memory bookkeeping entry, leaving every persisted record in place forever. So the trust page, the store listing and the data-flow document all promised a 30-day deletion that the product did not perform — and once persistence landed in sessions 15-17, the promise got further from the truth rather than closer. A cached tenant app would also have kept serving "deleted" data until eviction. | D90: src/tenantLifecycle.ts wires deletion end to end: scheduleDeletion starts the restorable 30-day window as a durable entry, cancelDeletion handles re-install inside it (ST-053), purgeExpired is the sweep the policy promises, and purgeNow is immediate self-serve deletion (ST-069) that purges the store AND evicts the cached runtime. exportAll now reads the tenant's real records instead of a stub. Pinned: nothing deleted at day 29, everything deleted at day 31, schedule cleared with the data, one tenant's deletion never touching another, and the system bucket refusing to be purged. | E90: FIXED (test-pinned)
A92: AUTHORIZATION AUDIT — 13/09/2026 11:55 (permissions declared vs permissions enforced)
A93: F-030 | B93: CRITICAL | C93: Five of the nine permissions in the role matrix were enforced nowhere: billing.manage, settings.roles, data.export, data.delete and audit.view. Two of those guard the destructive controls built one session earlier — so ANY caller, including a frontline member, could have deleted or exported an entire tenant, and anyone could read the compliance trail. The matrix was shown verbatim in the Settings screen and documented as the security model, which made it look enforced. Same class as a requested scope with no consumer: an action with no enforcement site is a comment, not a permission. | D93: Enforcement wired at each site and named in an ENFORCEMENT_SITES map: billing.manage on subscribe/cancel, data.export and data.delete on the lifecycle controls, audit.view on reading the trail. A contract test asserts the matrix and the map match in both directions and that each named file actually references its action — so a future permission cannot be declared without being enforced, or enforced without being declared. Deletion now also writes a receipt (who, when, how many records) into the system-scoped store, so the record of a deletion survives the deletion. | E93: FIXED (test-pinned)
A94: D-SD6 | B94: Decision | C94: settings.roles had no operation to guard at all: roles are derived from Teams team ownership via Graph, and nothing in ShiftDesk assigns them. | D94: Removed from the matrix rather than left as an unenforced line, matching the GAP-SD7 treatment of an unused scope. Flagged for ratification: if in-product role assignment is ever added, the permission returns with the code that enforces it. | E94: OPEN for ratification
A96: BILLING-INTEGRITY AUDIT — 13/09/2026 12:02 (what the money states actually restrict)
A97: F-031 | B97: High | C97: The dunning ladder was cosmetic. "read_only" was a string written into an account and checked by nothing, so a tenant whose payment failed kept unlimited write access forever; a cancelled subscription behaved identically to an active one. ST-060 documents a 7-day grace then read-only, and the pricing page tells customers the same — neither was true. | D97: src/entitlements.ts gates every mutating request on billing state. Reads are deliberately never blocked: withholding a shift handover from a frontline team over a billing dispute is the wrong failure mode, and every refusal message says so explicitly. | E97: FIXED (test-pinned)
A98: F-032 | B98: High | C98: usagePrompt had zero callers, so ST-061's plan limits were advisory text that nothing surfaced or enforced. A starter-plan tenant could add unlimited people; seat count was checked only once, at subscribe. | D98: Seats are now tracked per tenant (distinct actors), warned at 80%, and capped: at the limit existing people carry on working and only a NEW seat is refused. An unrecognised plan never locks anyone out. | E98: FIXED (test-pinned)
A99: F-033 | B99: High | C99: Trials never expired. startTrial set a state that nothing ever moved on, so a tenant that never chose a plan kept writing indefinitely — the countdown banner was the only consequence of a trial ending. | D99: Trial expiry evaluated against the configured trial length at the request boundary (honouring F-019's configurable duration), recovering the moment a plan is chosen. | E99: FIXED (test-pinned)
A101: DELIVERY + MEASUREMENT AUDIT — 13/09/2026 16:27
A102: F-034 | B102: High | C102: Every F1-F5 notification story promises in-app AND email delivery with per-type mute (ST-010/020/030/040/050). NotificationCenter only appended to an in-memory array, which the F-003 FIFO cap then discarded — nothing was ever delivered on either channel, and the record of it was thrown away too. A supervisor would never have learned a handover needed acknowledging. | D102: src/notificationDispatcher.ts delivers both channels with INDEPENDENT failure handling — a bounced email never costs the user their in-app notice, and a store outage does not stop the email. In-app notices are durable records with unread/mark-read; a missing address is reported rather than silently dropped; muted types reach neither channel. Subjects written for every type the product sends, with a safe fallback. | E102: FIXED (test-pinned)
A103: F-035 | B103: Medium | C103: ST-087 claims p95 latency budgets are "defined and monitored", and the launch runbook makes a rollback decision on them. LatencyMonitor had zero callers: nothing in the request path measured anything, so the budgets were numbers in a document and the rollback trigger could never have fired. | D103: The server now times every /api request and every bot activity against the right surface budget, and GET /health returns the per-surface p95, the budget and whether it is breached — readable by probes without a token. Health and status probes are deliberately excluded so they cannot flatter the product's latency picture. | E103: FIXED (test-pinned)
A105: MEASUREMENT + EVIDENCE AUDIT — 13/09/2026 16:35
A106: F-036 | B106: High | C106: The entire E7 telemetry epic (ST-071 funnel, ST-072 error tracking, ST-073 heatmap, ST-074 weekly email, ST-075 health score, ST-076 export, ST-077 alerts) had ZERO callers. Every module was correct and fully tested, and nothing ever fed it. The S11 launch exit criterion is "activation > 40%" — a number that could not have been computed on launch day, because install, setup and aha were never recorded for anyone. | D106: src/observability.ts wires measurement into the request path: install on a tenant's first load, setup on its first successful mutation, aha when work completes end to end, habit at ten mutations, feature usage on every route, and errors tracked by release on 5xx. activationRate() now computes the S11 metric. The heuristics are stated in the code rather than buried, and billing-blocked requests count as usage but never as progress. | E106: FIXED (test-pinned)
A107: F-037 | B107: High | C107: Audit entries went to an in-memory log that a restart discarded, while DurableAuditLog — built in session 15 — had no callers: the same built-but-unused pattern as F-029. The trail also covered only configuration changes, not the creation or completion of the records a compliance reviewer would actually ask about. | D107: Creation and completion are now audited, and the server drains the buffered entries to the durable per-tenant store after each successful request, so the trail survives a restart and is never written twice. Verified by reading the trail back through a fresh DurableAuditLog after the writing process is gone. | E107: FIXED (test-pinned)
A109: SYSTEMATIC WIRING AUDIT — 13/09/2026 16:40 (every export checked for callers, per R-S14)
A110: F-038 | B110: High | C110: Six of the nine designed screens had no mount path. The tab shell rendered home, handovers and checklists; ApprovalBuilder, SettingsScreen, BillingScreen, AnalyticsScreen, HelpScreen and OnboardingScreen were components nothing rendered and the manifest declared only three tabs. So there was no way to build an approval policy (the whole F2 epic had no UI), no way to see the role matrix, no way to see trial state — which is also where the entitlement messages from F-031 would have surfaced — and no way to reach the fifteen help articles. Each screen was individually tested and accessibility-audited, which is what made the gap invisible. | D110: Tab shell routes all eight entities, with the API routes behind them (billing banner, funnel, help search bound to the shipped article set, approval policy). Manifest declares all eight tabs and a test asserts the declared tabs equal the routable entities and that each contentUrl carries its own entity. | E110: FIXED (test-pinned)
A111: F-039 | B111: High | C111: The notification dispatcher built one session earlier was itself never called — the exact pattern R-S14 was raised to stop, recurring immediately. Notifications accumulated in the app buffer and were delivered nowhere. | D111: Wired into the request path: after each successful mutation the buffer is drained to the dispatcher, so a handover reaches its recipient in-app and by email, and a drained buffer cannot resend on the next request. | E111: FIXED (test-pinned)
A112: F-040 | B112: OPEN | C112: The trust page states AES-256 encryption at rest. src/crypto.ts (SecretsVault, AES-256-GCM) has no callers: the repository writes plaintext JSON, so the claim is currently untrue unless the deployment relies on storage-level encryption. | D112: NOT FIXED this session — recorded rather than quietly carried. Options: (a) encrypt record payloads via a repository decorator using the existing crypto module, (b) rely on provider-managed disk/column encryption and reword the trust page to say so precisely. Needs a decision because it changes what the customer is promised. | E112: OPEN — Senthil disposition
A113: OBS-SD7 | B113: Obs | C113: Also unwired, with deliberate reasons: SupportChat, PartnerTracker and SeoIterator are operator tools with no in-product surface yet; TokenStore is superseded by the SSO path; several constants are exported for tests and documentation. | D113: Listed so the next wiring audit starts from a known baseline instead of re-deriving it. | E113: ACCEPTED — documented
A115: F-040 RESOLUTION — 13/09/2026 16:47 (encryption at rest: claim made true, decision left open)
A116: F-040 | B116: Resolved (both paths) | C116: The trust page stated AES-256 at rest while src/crypto.ts had no callers, so the repository wrote plaintext JSON. Left open last session because the fix is a promise to customers, not a coding preference. | D116: Both dispositions are now cheap and the page is true either way. Option (a): src/encryptedRepository.ts wraps any repository and encrypts record CONTENT with AES-256-GCM — fresh IV per write, tamper detection on read, rows written before it was enabled stay readable and re-encrypt on next write. Enabled solely by setting an encryption key; no key means option (b), provider-managed storage encryption, with no code change. Trust page rewritten to describe both configurations and to state exactly what stays in clear text (tenant, record type, id, timestamp — the query keys needed for retrieval, retention sweeps and deletion). Startup banner reports which configuration is in force. | E116: FIXED — disposition still Senthil's
A117: OBS-SD8 | B117: Obs | C117: Key rotation is not implemented for stored records: changing the key would make existing rows unreadable, because the read-through path only tolerates plaintext, not a previous key. | D117: Recorded rather than discovered later. A rotation needs either a key-id in the envelope (the envelope is versioned "enc:v1:" precisely so this is possible) or a re-encrypt sweep. Not needed before the pilot; needed before a key ever changes. | E117: OPEN — before first rotation
A119: COLD-REVIEW PASS 5 — 13/09/2026 16:51 (over the sessions 18-25 modules, none previously reviewed)
A120: F-041 | B120: High | C120: The seat cap built in F-032 could never fire. "Is this a new seat?" was computed as "does this tenant have zero seats", so the 201st person on a 200-seat plan was not treated as new and was admitted. The cap looked enforced and tested because the unit test passed a boolean directly; the server computed that boolean wrongly. | D120: The question is now asked about the person (hasSeat(tenant, actor)), not the tenant. Pinned with an existing member working at the cap while a genuinely new person is refused. | E120: FIXED (regression tests)
A121: F-042 | B121: Medium | C121: Every tenant re-hydration counted as a fresh install, so eviction (the registry is bounded to 500) or any restart inflated the install count. That understates activation — the exact S11 gate metric wired up one session earlier. | D121: Installs are recorded once per tenant, with markKnown to seed the set from the store after a restart. | E121: FIXED (regression tests)
A122: F-043 | B122: Medium | C122: Deleting a tenant while its app was mid-hydration resurrected it: purge evicted the cache, then the in-flight load finished and put the stale app straight back — serving data that had just been deleted. | D122: A purge during hydration is recorded, and the finishing load is not cached. Pinned by holding a hydration open, deleting, then releasing it. | E122: FIXED (regression tests)
...

Sheet GTM_Execution
A1: GTM EXECUTION TASKS
A3: Phase | B3: Task | C3: Owner (role) | D3: Target sprint
A4: Pre-launch | B4: Positioning doc + message house (problem/promise/proof) | C4: Founder | D4: S7
A5: Pre-launch | B5: Listing SEO: keyword study in marketplace search + title/intro drafts | C5: Growth | D5: S8
A6: Pre-launch | B6: 10 design-partner mini case snippets with metric proof | C6: Founder | D6: S8
A7: Pre-launch | B7: 5 comparison/alternative pages drafted | C7: Growth | D7: S9
A8: Pre-launch | B8: Screenshots (5) + 2-min demo video produced | C8: Design | D8: S9
A9: Launch | B9: Listing live + launch post + video published | C9: Growth | D9: S11
A10: Launch | B10: Founder outreach: 100 named ICP accounts, 3-touch sequence | C10: Founder | D10: S11
A11: Launch | B11: Community value-posts (3 relevant communities) | C11: Founder | D11: S11
A12: Launch | B12: Review-generation program on (in-app ask post-aha) | C12: Eng | D12: S11
A13: Post-launch | B13: Weekly SEO/how-to content cadence starts | C13: Growth | D13: S12
A14: Post-launch | B14: Marketplace paid placement pilot (where offered) | C14: Growth | D14: S12
... A21: Post-launch | B21: Evidence-led case snippet per pilot: the audit question the customer can now answer | C21: Founder | D21: S20+ / SD247

Sheet Launch_Checklist
A1: PLATFORM LAUNCH CHECKLIST — Microsoft Teams App Store / AppSource
A3: # | B3: Item | C3: Status
A4: 1 | B4: Partner Center enrollment + publisher verification complete | C4: Open — Senthil (Partner Center account)
A5: 2 | B5: Teams store validation guidelines self-check (manifest, SSO, bot responsiveness) | C5: Manifest v1.19 sideload-ready with a configurable channel tab, 8 commands and localizationInfo; manifest-vs-code and command parity asserted in CI. Live tenant validation pending (SD226).
A6: 3 | B6: Microsoft 365 App Compliance: Publisher Attestation submitted (Certification roadmap noted) | C6: Evidence pack assembled and each control bound to an existing evidence path by test (SD236); SOC 2 readiness mapped (SD237). Submission itself open — Senthil (SD235).
A7: 4 | B7: Entra ID SSO + admin consent flow tested in 2 tenants | C7: Blocked — needs 2 live tenants (SD228). Scope map pinned to its consumer files by test, so the consent screen cannot exceed the documented ask.
A8: 5 | B8: Graph API permissions minimal + documented | C8: REOPENED then corrected (VER-SD04): doc claimed org-wide Graph scopes; now RSC-scoped and test-pinned — live consent screen still to be verified at install
A9: 6 | B9: AppSource transactable offer configured (3% fee, private offers enabled) | C9: Open — Senthil (transactable offer in Partner Center)
A10: 7 | B10: Accessibility (WCAG AA) pass on tab surfaces | C10: Automated pass (jest-axe, 9 screens) plus a per-screen manual script (ops/accessibility-audit-script.md). Keyboard-only and screen-reader pass open — Senthil (SD238).
A11: 8 | B11: Load test: bot p95 response <2s at 100 concurrent | C11: Harness scripted with the pass bar (k6 5x, p95 thresholds) and p95 instrumentation now real; per-record persistence removed the blocker that made the gate unpassable (SD216). Run needs staging — SD219/SD220.
A12: 9 | B12: Admin deployment guide + tenant-wide rollout doc | C12: Drafted — content/admin-deployment-guide.md
A13: 10 | B13: Co-sell ready checklist (solution one-pager, bill of materials) | C13: Drafted — content/positioning-onepager.md
A14: 11 | B14: Marketplace SaaS Fulfillment API v2 implemented and enforced end to end: landing-page token resolution, activate, idempotent webhooks for all subscription actions, seat reconciliation with drift alert | C14: Code-complete pending live (SD239) — built against the documented contract with idempotency on activityId and both Entra and shared-secret webhook authentication. A real transaction needs the transactable offer at #6. Added per review finding D-08, which noted the checklist had no line for this at all.
A15: 12 | B15: Data residency, DPA, subprocessor register and retention schedule published and bound to code | C15: Done (SD229/SD230) — region asserted against the store host at boot; the four documents in content/legal/ are generated from src/residency.ts and a test fails if a published document and the enforced policy disagree. DPA template has not had legal review — stated, not implied.
... A17: 14 | B17: Security trust page published | C17: DELIBERATELY NOT DONE (review finding D-07) — content/security-trust-page.md is gated and marked NOT PUBLISHED. Its claims now match what the code does, and it goes live only when a deployment actually runs durably with KMS custody.
