Workbook

Sheet Cover_Sheet
B2: VoiceBridge CTI for Salesforce — MoPr11
B3: Version detail and manual test pack
B4: Every released version: what was done and why. Every pending version: what is in it and why it is pending. Eighty manual test cases, positive and negative, with the steps to run them and the result to expect.
B6: Document name | C6: claude_V001_MoPr11-voicebridge_salesforce_versiondetail_manualtest_20260920_1232.xlsx
B7: Document version | C7: V001 — first issue
B8: Issued | C8: 20 September 2026, 12:32 BST
B9: Prepared by | C9: Claude for Senthil (KP)
B10: Owner / approver | C10: Senthil (KP) — product owner; sole decision-maker on every open item in this pack
B11: Product | C11: VoiceBridge CTI — omnichannel CTI for the Salesforce AppExchange (portfolio reference MoPr11 / P02)
B12: Describes code version | C12: voicebridge-cti v0.28.0 · package hash f0f4eb4ab67d · released 20 Sep 2026 10:45
B13: Build state at issue | C13: 58 test suites / 613 automated tests, 100% statements-branches-functions-lines, zero coverage pragmas, 0 production dependency advisories
B14: Purpose | C14: To give one place where a reader can see (a) what each version of this product actually delivered and why, (b) which versions are still pending and exactly what is blocking each, and (c) how to verify any of it by hand.
B15: Scope — in | C15: All released code versions to v0.28.0; all planned versions to v1.0.0; manual verification of every shipped capability; manual test cases written in advance for pending capabilities.
B16: Scope — out | C16: Automated test implementation (that lives in the codebase), commercial modelling (product workbook), sprint execution history (sprint tracker v024), and the pictorial explanation (product map v001).
B17: Intended readers | C17: The product owner; an independent reviewer; a QA tester executing the pack; a security reviewer who wants to know which claims have evidence.
... B21: How to start | C21: Read How_To_Use, then Context. To understand the product: Version_Detail then Pending_Versions. To test it: Test_Environment, then Test_Cases with Test_Steps_Detail beside it.
B23: SIGN-OFF
B24: Role | C24: Name / signature | D24: Date | E24: Comment
B25: Prepared by — Claude
B26: Reviewed by — Senthil (KP)
B27: Approved for use by — Senthil (KP)
B28: Independent reviewer (DR-12)
B30: This pack states what has and has not been observed. Nothing in it should be quoted in listing copy, a prospect conversation or a security questionnaire without reading the environment column of the test case it came from.

Sheet Document_Control
A1: DOCUMENT CONTROL — revision history for this workbook
A2: How to use this sheet: one row per issue of this document. Never edit a released row; add a new one and re-issue the file under the next number. The document version (V001) is independent of the code version (v0.28.0) it describes — the mapping is in column D.
A3: Doc version | B3: Date / time | C3: Author | D3: Code version described | E3: What changed in this document, and why | F3: Status
A4: V001 | B4: 2026-09-20 12:32 | C4: Claude for Senthil/KP | D4: v0.28.0 (hash f0f4eb4ab67d) | E4: First issue. Created on request after the v0.28.0 release, because the sprint tracker records execution but does not answer two separate questions a reader keeps asking: what did each version actually deliver and why, and how would I check any of it myself. Covers 22 released versions, 9 pending versions, 5 pending live-evidence steps and 80 manual test cases (49 positive, 31 negative) with 340 numbered steps. | F4: Released
A5: V002 | B5: — | C5: — | D5: v0.29.0 (planned) | E5: Planned. Opens when the S13 decision gate closes: the pending-version rows become released rows, the reclassification lands, and the blocked test cases for v0.30.0 onward become runnable. | F5: Planned
A7: NAMING | B7: claude_V<NNN>_<product ref>_<document name>_YYYYMMDD_HHMI.xlsx | E7: The timestamp is supplied by Senthil at release, matching the convention used by the sprint tracker and the product workbook so that a code zip, a tracker and this pack can always be lined up by name.
A8: CHANGE RULE | B8: A new fact about the product means a new version of this file. | E8: Test results are recorded in Test_Execution_Log (which is appended to per cycle) rather than by editing the test cases themselves, so the pack stays stable while evidence accumulates against it.

Sheet How_To_Use
A1: HOW TO USE THIS WORKBOOK — sheet by sheet
A2: How to use this sheet: read it first. It says what each sheet is for, who it is for, and when to touch it. Every other sheet also carries its own one-paragraph instruction in row 2.
A3: # | B3: Sheet | C3: What it is | D3: Who uses it | E3: When to use it | F3: What you may edit
A4: 1 | B4: Cover_Sheet | C4: Title block, purpose, scope, readership and the sign-off grid. | D4: Everyone | E4: First. Also the page to print if someone asks what this document is. | F4: Sign-off block only
A5: 2 | B5: Document_Control | C5: Revision history of this workbook and the naming/change rules. | D5: Author, reviewer | E5: When re-issuing the file. | F5: Add a new row; never alter a released one
A6: 3 | B6: How_To_Use | C6: This sheet. | D6: Everyone | E6: First. | F6: Nothing
A7: 4 | B7: Context | C7: What the product is, how it was built, what the three reviews found, and the assumptions this pack rests on. | D7: Anyone new to the product | E7: Before reading Version_Detail or running a test. | F7: Nothing
A8: 5 | B8: Version_Detail | C8: Every released version: what was done, WHY it was done, the evidence, and the story position after it. | D8: Owner, reviewer, auditor | E8: To understand how the product reached its current state, or to answer 'why does this exist?'. | F8: Nothing — history
A9: 6 | B9: Pending_Versions | C9: Every planned version: scope, WHY it is pending, the named blocker, the owner and what would unblock it. | D9: Owner (decisions), reviewer | E9: Planning, or when someone asks why something is not done. | F9: Status column once a version ships
A10: 7 | B10: Pending_Live_Evidence | C10: The five operator steps that are pending inside the CURRENT version rather than a future one. | D10: Owner, tester | E10: When a live system becomes available — these are the highest-value hours on the list. | F10: Status and evidence columns
A11: 8 | B11: Test_Cases | C11: The register: 80 cases, positive and negative, each with its version, area, environment, preconditions and expected result. | D11: Tester, reviewer | E11: To plan a test cycle or to check whether a capability has a test at all. | F11: Status, Actual result, Tester, Date, Defect ref
A12: 9 | B12: Test_Steps_Detail | C12: The same cases broken into 340 numbered steps: action, test data, expected result per step. | D12: Tester | E12: While executing. Keep it open beside Test_Cases. | F12: Step result column
A13: 10 | B13: Test_Execution_Log | C13: One row per case per execution cycle: who ran it, when, on what build, with what outcome. | D13: Tester, QA lead | E13: Append a block per cycle. Do not overwrite previous cycles. | F13: The whole sheet, by appending
A14: 11 | B14: Defect_Log | C14: Every defect found by the three reviews and by the remediation itself, with severity, status, the version that fixed it and the test that now covers it. | D14: Owner, reviewer, auditor | E14: To check that a finding was actually closed rather than merely discussed. | F14: Status column if a defect reopens
... A22: ! | B22: READ THE ENVIRONMENT COLUMN | C22: A test case marked LOCAL proves something about this product today. A case marked LIVE proves nothing yet, because the system it needs does not exist. A case marked BLOCKED describes a capability that has not been built. All three are in the pack deliberately — omitting the last two would misrepresent the product. | D22: Everyone | E22: Every time you quote a result from this pack. | F22: Nothing

Sheet Context
A1: CONTEXT — what this product is, how it was built, and what is assumed here
A2: How to use this sheet: read once before the version and test sheets. Every row is a fact the rest of the workbook relies on; the source column says where each one can be checked.
A3: # | B3: Topic | C3: The fact | D3: Where it can be checked
A4: 1 | B4: What the product does | C4: A Salesforce AppExchange application for mid-market B2B sales teams: a softphone in the Salesforce utility bar, click-to-dial from any record, automatic logging of every call (and, in the pitch, every WhatsApp thread) onto the Contact or Lead, plus cadence-lite, coaching scorecards and Flow actions. | D4: Product workbook ReadMe_Scope; help centre articles HC-01..HC-15
A5: 2 | B5: Where it sits | C5: Product P02 (portfolio ref MoPr11) of a twelve-product marketplace portfolio, built solo, executed in a locked WIN order. | D5: Sprint tracker Decisions D15, D17
A6: 3 | B6: How it was built | C6: Fifteen numbered code releases between 13 and 20 September 2026 (v0.14.0 → v0.28.0), each packaged, re-extracted and re-verified from its own zip. Earlier releases carried the S1–S12 feature build. | D6: Version_Detail sheet; tracker Version_Control
A7: 4 | B7: The coverage rule | C7: Portfolio decision D13: development proceeds with 100% automated coverage on all source while customer discovery is parked. Every release is gated on 100% statements, branches, functions and lines with no coverage pragmas. | D7: jest.config.js coverageThreshold; CI test job
A8: 5 | B8: What coverage does not prove | C8: Five internal adversarial passes found roughly forty defects inside code that already had 100% coverage. Coverage proves execution, not correctness, and never proves integration. | D8: Defect_Log; tracker lesson L-V1 / F-V14
A9: 6 | B9: First external review | C9: ChatGPT, 13 September 2026: decision REJECT, fourteen findings, five blockers — all five at an integration boundary where each side had only ever been tested against a double of the other. | D9: Defect_Log rows VB-CR-001..014
A10: 7 | B10: Second external review | C10: Perplexity, 16 September 2026: decision HOLD — re-platform or pivot. Six findings, plus the fact that Salesforce Open CTI (the API the whole in-org surface depends on) is in maintenance mode with an end of life of 28 February 2028. | D10: Defect_Log rows F-P01..F-P06; tracker risk R-V21
A11: 8 | B11: What v0.28.0 did | C11: Closed five of the six Perplexity findings in code and four further defects the remediation itself exposed — three of which were production-only failures that every existing test had been agreeing with. | D11: Version_Detail row v024; Defect_Log rows F-V31..F-V34
A12: 9 | B12: The honest position | C12: The service is engineering-complete and has never placed a telephone call, never written a record into a real Salesforce org and never run against a real database. Both halves of that sentence are true. | D12: Test_Cases environment column; Pending_Live_Evidence sheet
A13: 10 | B13: Assumption A | C13: Any test case marked LOCAL can be executed by anyone holding the delivered zip and a machine with Node 22 — no account, credential or external service is required. | D13: Test_Environment sheet
A14: 11 | B14: Assumption B | C14: Test cases marked LIVE or BLOCKED are written in advance deliberately, so that the day a system or a decision arrives the verification already exists and does not have to be invented under pressure. | D14: Test_Cases rows with environment LIVE / BLOCKED
... A16: 13 | B16: Out of scope here | C16: Commercial modelling (the financial model is blocked on D-V7), listing copy (blocked on D-V6), and the strategy ruling itself (D-V8). | D16: Product map document, section 9; tracker Enhancement_Plan

Sheet Version_Detail
A1: VERSION DETAIL — every released version: what was done, and why it was done
A2: How to use this sheet: one row per released version, oldest first. 'What was done' is the change; 'Why it was done' is the reason it was worth doing, which is usually a defect, a review finding or a platform rule. Code versions marked (inferred) are reconstructed from the tracker, which did not record code numbers before v0.14.0 — the tracker version is authoritative.
A3: Tracker ver | B3: Code version | C3: Workbook ver | D3: Date / time | E3: Release title | F3: What was done | G3: Why it was done | H3: Evidence at release | I3: Story position after
A4: v001 | B4: v0.7.0 (inferred) | C4: v007 | D4: 2026-09-10 23:00 | E4: Foundation through beta iteration (S1–S8) | F4: Opened the VoiceBridge build from the v006 product workbook and executed sprints S1–S8 done-in-code: install/OAuth lifecycle, click-to-dial state machine, call/WhatsApp activity logging, cadence-lite, coaching analytics, billing, Flow actions, plus the first tracker with a live traceability rollup. | G4: The portfolio rule (D13) allows development to proceed with 100% automated coverage while discovery is parked, so the whole feature surface was built before any live system existed. | H4: 20 Jest suites / 85 tests at 100% coverage; tracker v001 with 100-row traceability. | I4: 79 Done + 5 code-complete of 100
A5: v002 | B5: v0.8.0 (inferred) | C5: v008 | D5: 2026-09-11 08:46 | E5: Marketplace review preparation (S9) | F5: WCAG AA audit on the widget shells, backup/restore drill with sha256 integrity verification, chaos-outage degradation with user comms, security evidence pack (sandbox half), plus the 12-step live sweep and 30-minute dev-org guide. | G5: S9 is the sprint that makes a submission possible; everything in it is preparation a reviewer will ask to see. | H5: 24 suites / 101 tests at 100%; docs/salesforce-dev-org-guide.md. | I5: 82 Done / 5 code-complete
A6: v003 | B6: v0.9.0 (inferred) | C6: v009 | D6: 2026-09-11 12:48 | E6: Review remediation and support surfaces (S10) | F6: 15 help-centre articles with ranked search, an in-app chat engine with a four-business-hour SLA, public status page and incident template, pricing and trust pages generated from their single sources, demo-data mode and a submission dry-run engine. | G6: A marketplace listing is judged on the surfaces around the product as much as the product; generating them from single sources stops them drifting from the code. | H6: 30 suites / 131 tests at 100%; dry-run READY 11/11 automated. | I6: 87 Done / 6 code-complete
A7: v004 | B7: v0.10.0 (inferred) | C7: v010 | D7: 2026-09-11 13:32 | E7: Launch and iteration scope (S11–S12) — code phase complete | F7: Executable launch-day runbook with rollback triggers wired to the real p95 budgets, a ten-slot design-partner tracker with honest exit maths, and a listing SEO iteration engine with a thin-data floor. | G7: Closed the sandbox-buildable backlog to zero so that what remained was visibly all live or human work. | H7: 33 suites / 150 tests at 100%; backlog zero. | I7: 88 Done / 8 code-complete
A8: v005 | B8: v0.11.0 (inferred) | C8: v011 | D8: 2026-09-11 15:26 | E8: The 2GP package source (D18 gap closed) | F8: Built sfpackage/: an sfdx project with the CallCenter Open CTI definition, three permission sets generated from the enforced role matrix with drift tests, and an esbuild softphone static resource driven by a dependency-injected Open CTI adapter tested in jsdom. | G8: The D18 packaging recommendation referenced a shim package whose source did not exist — the same artefact-gap class found in a sibling product. | H8: 35 suites / 162 tests at 100%; permission-set drift test. | I8: unchanged 88/8
A9: v006 | B9: v0.12.0 (inferred) | C9: v012 | D9: 2026-09-11 22:09 | E9: First adversarial cold review, pass 1 | F9: Seven defects fixed with pinned regressions: retention sweep leaving PII, no payment-recovery path, unenforced trial expiry, unguarded invoice mutation, unbounded ledgers, a production backoff sleep that was a no-op, and read-only billing status enforced nowhere. | G9: Coverage proves execution, not correctness. A deliberately adversarial pass over code that already had 100% coverage was the only way to find these. | H9: 36 suites / 176 tests at 100%; Review_Findings sheet opened. | I9: unchanged 88/8
A10: v007 | B10: v0.13.0 (inferred) | C10: v013 | D10: 2026-09-11 22:34 | E10: Cold review complete + first verification sweep | F10: Thirteen more defects across the ~28 modules pass 1 never opened, plus a verification sweep against the live Open CTI documentation that found two live-blocking defects: opencti_min.js was never loaded, and enableClickToDial was never called. | G10: The suite can only test what the code does; only a sweep against the platform's own documentation catches what the platform requires. | H10: 39 suites / 217 tests at 100%; lessons L-V2/L-V3 logged. | I10: unchanged 88/8
A11: v008 | B11: v0.14.0 | C11: v014 | D11: 2026-09-13 10:39 | E11: Screen surface + mandatory OAuth controls | F11: Built the seven missing screens as typed view models with an accessible renderer and widened the WCAG audit to all nine screens; moved to External Client Apps (new Connected Apps cannot be created from Spring '26) and implemented the four OAuth controls Salesforce made mandatory: PKCE with single-use state, rotation anomaly telemetry, a 30-day refresh idle timeout and a refresh IP allowlist. | G11: Five P0 stories claimed an end-to-end surface that did not exist, and the dev-org guide had become unrunnable at step 2 because of a platform policy change. | H11: 41 suites / 274 tests at 100%; docs/oauth-security-controls.md. | I11: unchanged 88/8
A12: v009 | B12: v0.15.0 | C12: — | D12: 2026-09-13 10:57 | E12: Artifact-gap audit: a process and a schema | F12: There was no process and no production OAuth gateway — createApp() had never been called by anything — and no database schema behind a published 30-day retention policy. Added server.ts/main.ts with npm start, a real token-endpoint gateway, five ordered migrations with npm run migrate, and moved CI to Node 22. | G12: Thirty modules at 100% coverage and nothing that could receive a request: the product existed as modules, not as a service. | H12: 42 suites / 296 tests at 100%; migrations 001–005. | I12: unchanged 88/8
A13: v010 | B13: v0.16.0 | C13: — | D13: 2026-09-13 11:14 | E13: The identity boundary | F13: HMAC-signed sessions minted only at the install callback; identity never read from a body or a URL; a claim that disagrees with the session refused as forgery; 401/403 separated from the blanket 400. Also capped and swept the PKCE map, added a token-endpoint timeout and a drain that does not wait forever. | G13: Pass 3 found that the screens added in v0.14.0 took the org straight from the URL with no identity check — anyone who guessed an org id could read its billing, invoices and support queue. | H13: 43 suites / 318 tests at 100%; test/authBoundary.test.ts. | I13: unchanged 88/8
A14: v011–v016 | B14: v0.17.0 – v0.22.0 | C14: — | D14: 2026-09-13 11:36 → 16:51 | E14: Persistence, converted in six staged releases | F14: Moved twenty domain modules from an in-process store onto an async repository with a conformance suite running identical tests against both implementations, one green build per stage; then deleted the legacy store outright and made the backup drill cover all the data rather than half of it. | G14: A single-pass conversion is a broken build for hours and a coverage gate that cannot run. Two ordering errors were found and corrected in public during the conversion (the cascade runs toward callers, and a dependency leaf is the largest step, not the smallest). | H14: 44 suites / 340 tests at 100%; docs/r-v11-plan.md rewritten twice. | I14: unchanged 88/8
... A21: v024 | B21: v0.28.0 | C21: — | D21: 2026-09-20 10:45 | E21: Second independent review executed in full (this release) | F21: All of S14 (widget served, token encryption, security headers and rate limits, symmetric evidence gate, claim-to-test registry, Express 5); the codeable halves of S19–S20 (updateWhere with detached copies, leader-elected outbox worker, transactional caps, observability, SLO rules, real deploy pipeline, DR drill) and S25–S26 (Postgres row-level security, hash-chained audit, session lifecycle, compliance templates); and the provider-independent parts of S15–S16 (E.164 and pre-dial refusal, SOSL phone matching with honest ambiguity). | G21: The direction was enterprise grade with no scope reduction. Four further defects were found by the remediation itself — three of them production-only failures that every test had been agreeing with. | H21: 58 suites / 613 tests at 100% ×4, zero pragmas, 0 advisories; hash f0f4eb4ab67d; verified from a clean extraction. | I21: 96 / 100 pending D-V4 (→ 76/100)
A23: NOTE | B23: Twenty-two released versions. The product's feature surface was complete at v0.10.0 on 11 September; everything after it is correctness, integration, security and evidence — which is where every one of the sixty-plus defects lived.

Sheet Pending_Versions
A1: PENDING VERSIONS — what is planned, and why each one is pending
A2: How to use this sheet: one row per planned version. 'Why it is pending' is the real reason, not a schedule. Read the Blocked-by column as a shopping list: five of the nine are waiting on a decision that costs nothing to make, and four on something that has to be bought, provisioned or signed.
A3: Planned tracker ver | B3: Planned code ver | C3: Scope | D3: Why it is pending | E3: Blocked by | F3: Owner | G3: What would unblock it | H3: Earliest realistic start | I3: Status
A4: v025 | B4: v0.29.0 | C4: S13 decision gate — no feature code | D4: Every item is a ruling, not an implementation. The packets are written (strategy options, carrier trade-offs, model scope, reclassification impact); what is missing is the decision itself. | E4: D-V4, D-V5, D-V6, D-V7, D-V8, D-V9 | F4: Senthil | G4: Senthil answers six questions. Claude then reclassifies the stories, rebuilds the model and re-sequences the plan in a day. | H4: Immediately — nothing external is required | I4: Pending
A5: v026 | B5: v0.30.0 | C5: Telephony adapter + inbound webhook (S15) | D5: No carrier has been chosen, so there is no credential set, no signature scheme and no event vocabulary to build against. Writing an adapter now would mean inventing a provider and then testing the invention. | E5: D-V5 | F5: Senthil (choice), Claude (build) | G5: Name the carrier on landed cost per minute. The seam, the idempotency key and the pre-dial guards already exist, so the adapter is one file plus one route. | H5: Same week as D-V5 | I5: Pending
A6: v027 | B6: v0.31.0 | C6: Inbound routing, screen pop, call-quality telemetry (S16) | D6: Depends on the adapter above, and on a live number that can receive a call. | E6: D-V5, then a test number | F6: Claude | G6: The adapter landing, plus a purchased inbound number. | H6: After v0.30.0 | I6: Pending
A7: v028 | B7: v0.32.0 – v0.33.0 | C7: Salesforce Voice Partner Telephony package (S17–S18) | D7: Only relevant under strategy option (A). Needs a partner developer org with the Partner Telephony add-on licence, which is not a thing that can be written. | E7: D-V8, D-V9, partner dev org | F7: Senthil (org), Claude (build) | G7: A strategy ruling of (A) plus an org with the add-on enabled. Under option (B) this release is deleted entirely. | H7: 4–6 weeks after D-V8 | I7: Pending
A8: v029 | B8: v0.34.0 | C8: Live durability and cross-hop tracing (S19–S20 remainder) | D8: The conformance suite runs against a recording double that now enforces the tenant contract; proving PostgreSQL itself behaves needs a PostgreSQL. Tracing needs a backend to trace into. | E8: O6 (a database), a hosting platform | F8: Senthil (provision), Claude (wire) | G8: Provision any PostgreSQL 16 and any metrics backend. The CI job, the checks and the rules are already written. | H8: Any day a database exists | I8: Pending
A9: v030 | B9: v0.35.0 | C9: WhatsApp via the Meta Cloud API (S21–S22) | D9: Never built. The capability the second reviewer called the one genuinely differentiated wedge is also the one blocked on a decision that has been open since 13 September. | E9: D-V6, Meta business verification | F9: Senthil (decision + verification), Claude (build) | G9: Decide to build, then complete Meta business verification. A working pattern exists in a sibling product and is portable. | H9: 3–4 weeks after D-V6 | I9: Pending
A10: v031 | B10: v0.36.0 | C10: AI layer: transcription, summaries, real coaching (S23–S24) | D10: Every story needs call recordings, which need a carrier. Building the AI governance copy first would create exactly the unbacked-claim class this release spent its effort eliminating. | E10: Recordings (D-V5 → VB-E-024) | F10: Claude | G10: Calls being recorded. Then transcription, summary and scorecards are ordinary work. | H10: After v0.31.0 | I10: Pending
A11: v032 | B11: v0.37.0 | C11: Enterprise close-out: SSO ruling, penetration test, SOC 2 readiness (S25–S26 remainder) | D11: The internal halves are done — controls, evidence map, DPA template. The remainder needs a vendor, a consultant, a legal entity and a deployed target to test. | E11: D-V10, a pen-test vendor, a SOC 2 consultant, a live deployment | F11: Senthil | G11: Engage the vendors and deploy something for them to test. | H11: 6–8 weeks after a deployment exists | I11: Pending
A12: v033 | B12: v0.38.0 → v1.0.0 | C12: Listing submission, paid pilots, general availability (S27–S29) | D12: Requires the ISV agreement, the billing route, a $999 security-review submission and a 5–9 month listing lead time — and, before any of it, three organisations willing to run a paid pilot. | E12: D-V3, D-V8, ISV agreement, VB-E-033 kill point | F12: Senthil | G12: The S16 exit gate passing: three paid pilots at the ratified price. If it does not pass, the honest move is to stop rather than to list. | H12: Not before mid-2027 on the reviewer's own lead-time figures | I12: Pending
A14: READ THIS | B14: Not one row in this sheet is blocked on engineering difficulty. Five are blocked on a decision, three on a system that has to be provisioned or a vendor engaged, and one on evidence that a customer wants the product at all. Six months of further engineering with today's inputs would not release any of them.

Sheet Pending_Live_Evidence
A1: PENDING LIVE EVIDENCE — the operator steps that are outstanding inside the CURRENT version
A2: How to use this sheet: these are not future versions. The code for every one of them shipped in v0.28.0 or earlier; what is missing is somebody running it against a real system once. Each row says what turns green when it is done. Record the outcome in the last two columns and then update the matching test case.
A3: Step | B3: What must be done | C3: Why it is still pending | D3: Who does it | E3: What it turns green | F3: Matching test case | G3: Date done | H3: Evidence / result
A4: O6 | B4: Repository conformance against a live PostgreSQL 16 | C4: No database has ever been provisioned. Everything about persistence is proven against a recording double. | D4: Senthil (provision) → Claude (run) | E4: Durable storage, counted caps, R-V11 and R-V13 close | F4: TC-069, TC-073
A5: O7 | B5: CRM write-back against a live Salesforce developer org | C5: No developer org exists. The Task upsert, the phone match and the outbox drain have only ever been answered by a double. | D5: Senthil (org) → Claude (run) | E5: Auto-logging rows; twenty F2 stories can move to Done | F5: TC-042, TC-061, TC-062
A6: O7b | B6: The softphone panel rendering inside a real utility bar | C6: Same missing org. This is the step that would have caught the defect (F-P01) that survived three reviews and eight releases. | D6: Senthil (org) → Claude (run) | E6: The whole in-org surface row | F6: TC-006
A7: O9 | B7: Row-level security, audit append-only and the DR drill against live PostgreSQL | C7: The SQL checks exist and run in CI against an ephemeral database; nobody has run them against a real one as the application role. | D7: Senthil (provision) → Claude (run) | E7: Tenant isolation, audit integrity, DR | F7: TC-029, TC-032, TC-058
A8: O10 | B8: SLO game day: a deliberate ten-minute Salesforce outage with alerting connected | C8: Needs a deployed service and any metrics backend. The rules are exported and waiting. | D8: Senthil (platform) → Claude (run) | E8: Operations row; the published 99.5% becomes evidenced | F8: TC-022, TC-047

Sheet Test_Cases
A1: MANUAL TEST CASES — positive and negative, by version
A2: How to use this sheet: one row per test case. Read the Environment column first — it says whether the case can be run today. The steps are in Test_Steps_Detail, keyed on the same test case id. Fill in Status, Actual result, Tester, Date and Defect ref as you execute; leave everything to the left of Status alone so the pack stays comparable between cycles. Status values: Not run / Pass / Fail / Blocked / N/A.
A3: Test case ID | B3: Version | C3: Area | D3: Test case name | E3: Test description | F3: Type | G3: Priority | H3: Environment | I3: Preconditions | J3: Test data | K3: Steps | L3: Expected result | M3: Requirement / finding | N3: Automated counterpart | O3: Status | P3: Actual result | Q3: Tester | R3: Date executed | S3: Defect ref | T3: Notes
A4: TC-001 | B4: v0.28.0 | C4: In-org softphone surface | D4: Softphone page is served with both scripts and its injected config | E4: The page the CallCenter definition points at must be served by the application, carry the Open CTI script and the adapter bundle, and receive its configuration from the server rather than from dead metadata. | F4: Positive | G4: Critical | H4: LOCAL — from the zip | I4: Service running locally (see step 1). No Salesforce org required. | J4: GET https://localhost:3000/widget/softphone.html | K4: 6 | L4: HTTP 200, content-type text/html, body contains both script tags and a window.VB_CONFIG assignment with the configured base URL. | M4: F-P01 / VB-E-010 / ST-001..010 | N4: test/widget.test.ts | O4: Not run
A5: TC-002 | B5: v0.28.0 | C5: In-org softphone surface | D5: An unknown asset under /widget is refused | E5: The widget route serves an explicit allowlist of three files. Anything else must be a clean 404 rather than a directory listing or a server error. | F5: Negative | G5: High | H5: LOCAL — from the zip | I5: Service running. | J5: GET /widget/anything-else.html | K5: 3 | L5: HTTP 404 with a JSON body naming the problem; no file contents and no stack trace. | M5: F-P01 / VB-E-010 | N5: test/widget.test.ts | O5: Not run
A6: TC-003 | B6: v0.28.0 | C6: In-org softphone surface | D6: Path traversal under /widget is refused | E6: An allowlist rather than a static directory means traversal has nothing to reach; this proves it rather than assuming it. | F6: Negative | G6: High | H6: LOCAL — from the zip | I6: Service running. | J6: GET /widget/..%2Fpackage.json and /widget/package.json | K6: 3 | L6: Both requests return 404. No file outside the widget allowlist is ever served. | M6: F-P01 | N6: test/widget.test.ts | O6: Not run
A7: TC-004 | B7: v0.28.0 | C7: In-org softphone surface | D7: A deployment that skipped the build fails loudly, not blankly | E7: The adapter bundle is a build output. If a deployment forgets `npm run build`, the org must get an explicit error rather than a blank panel. | F7: Negative | G7: High | H7: LOCAL — from the zip | I7: Service running. | J7: Delete widget/dist/VoiceBridgeSoftphone.js, then request it. | K7: 4 | L7: HTTP 503 with code WIDGET_NOT_BUILT naming the command to run. The HTML page itself still serves. | M7: F-P01 | N7: test/widget.test.ts | O7: Not run
A8: TC-005 | B8: v0.28.0 | C8: In-org softphone surface | D8: The packaged CallCenter URL and the served route are the same path | E8: The defect this release fixed was a mismatch between metadata and routes that no test could see. The two must be compared directly. | F8: Positive | G8: Critical | H8: LOCAL — from the zip | I8: Service running; the zip extracted. | J8: sfpackage/.../VoiceBridge.callCenter-meta.xml | K8: 3 | L8: The adapterUrl path is /widget/softphone.html and that exact path returns 200 from the running service. The dead customSettings element is absent. | M8: F-P01 / VB-E-011 | N8: test/widget.test.ts | O8: Not run
A9: TC-006 | B9: v0.28.0 | C9: In-org softphone surface | D9: The panel renders inside a real Salesforce utility bar | E9: The live counterpart of TC-001. This is operator step O7b and is the single check that would have caught the defect that survived three reviews. | F9: Positive | G9: Critical | H9: LIVE Salesforce org | I9: A Salesforce developer org with the package deployed and the service reachable over https. | J9: The org's utility bar, opened as an assigned user. | K9: 5 | L9: The VoiceBridge panel appears in the utility bar with a dial pad and no console errors; the network tab shows 200 for softphone.html and for the adapter bundle. | M9: F-P01 / O7b | N9: none — this is the live half | O9: Not run | T9: Needs a live system that does not exist yet — see Pending_Live_Evidence.
A10: TC-007 | B10: v0.28.0 | C10: Encryption at rest | D10: Stored Salesforce tokens are envelopes, never plaintext | E10: The trust page has claimed encryption at rest since S10 over plaintext columns. This is the check that makes the claim answerable on a security questionnaire. | F10: Positive | G10: Critical | H10: LOCAL + PostgreSQL | I10: PostgreSQL reachable; migrations applied; VB_TOKEN_KEYS set to a valid key ring; one org installed. | J10: VB_TOKEN_KEYS="1:$(openssl rand -base64 32)" | K10: 5 | L10: The access_token and refresh_token columns contain v1.<iv>.<tag>.<ciphertext> envelopes; the plaintext appears nowhere in the table, and key_version records the key used. | M10: F-P02 / VB-E-012 / CL-T02 | N10: test/tokenCipher.test.ts | O10: Not run
A11: TC-008 | B11: v0.28.0 | C11: Encryption at rest | D11: An encrypted token round-trips to the exact original value | E11: Encryption is worthless if it corrupts the credential. The value read back must be byte-identical to the one stored. | F11: Positive | G11: Critical | H11: LOCAL — from the zip | I11: Service running with VB_TOKEN_KEYS set. | J11: A known access token and refresh token. | K11: 3 | L11: The values returned by the repository equal the values written, and a Salesforce API call using them is attempted with the correct bearer. | M11: F-P02 | N11: test/tokenCipher.test.ts, test/repository.test.ts | O11: Not run
A12: TC-009 | B12: v0.28.0 | C12: Encryption at rest | D12: An envelope copied into another org's row will not open | E12: The additional authenticated data binds each envelope to its org and field, so a database-level copy cannot grant the wrong org's credential. | F12: Negative | G12: High | H12: LOCAL + PostgreSQL | I12: Two orgs installed, both with tokens. | J12: UPDATE org_tokens SET access_token = <org A's envelope> WHERE org_id = <org B> | K12: 4 | L12: Reading org B's tokens fails with a decryption error; org B is not silently given org A's credential. | M12: F-P02 | N12: test/tokenCipher.test.ts | O12: Not run
A13: TC-010 | B13: v0.28.0 | C13: Encryption at rest | D13: A tampered envelope is refused rather than partially decrypted | E13: AES-GCM authenticates the ciphertext. Flipping any byte must fail the whole read. | F13: Negative | G13: High | H13: LOCAL — from the zip | I13: A cipher available in a node REPL, or run the automated test. | J13: An envelope with one character of ciphertext changed. | K13: 3 | L13: Decryption throws. No partial or garbage plaintext is ever returned. | M13: F-P02 | N13: test/tokenCipher.test.ts | O13: Not run
A14: TC-011 | B14: v0.28.0 | C14: Encryption at rest | D14: Production refuses to start without a token key | E14: A production process that silently stored plaintext would republish the same false claim the release just fixed. Boot must fail closed. | F14: Negative | G14: Critical | H14: LOCAL — from the zip | I14: None. | J14: NODE_ENV=production with DATABASE_URL and regions set, VB_TOKEN_KEYS unset. | K14: 3 | L14: The process exits with a message naming VB_TOKEN_KEYS and pointing at the runtime documentation. Nothing starts. | M14: F-P02 | N14: test/tokenCipher.test.ts, test/externalReview.test.ts | O14: Not run
A15: TC-012 | B15: v0.28.0 | C15: Encryption at rest | D15: Key rotation moves every org onto the new key and is idempotent | E15: Rotation must be operable without downtime and must be safe to run twice. | F15: Positive | G15: High | H15: LOCAL + PostgreSQL | I15: At least two orgs with tokens stored under key version 1. | J15: VB_TOKEN_KEYS="1:<old>,2:<new>" | K15: 5 | L15: The sweep reports the number rotated and zero remaining; a second run reports zero rotated. Tokens still decrypt afterwards. | M15: F-P02 | N15: scripts/rotate-token-keys.ts | O15: Not run
A16: TC-013 | B16: v0.28.0 | C16: Web hardening | D16: Security headers are present on a normal JSON response | E16: The AppExchange security review tests clickjacking protection and CSP directly. Every header is asserted by name and value. | F16: Positive | G16: Critical | H16: LOCAL — from the zip | I16: Service running with an https BASE_URL. | J16: GET /pricing | K16: 6 | L16: CSP with a Salesforce-only frame-ancestors list, HSTS, nosniff, referrer policy, permissions policy and no-store are all present; X-Frame-Options is deliberately absent. | M16: F-P04 / VB-E-013 | N16: test/hardening.test.ts | O16: Not run
A17: TC-014 | B17: v0.28.0 | C17: Web hardening | D17: Error responses carry the same headers as successful ones | E17: Headers that disappear on the error path are the ones an attacker reaches. 404 and 401 must be as protected as 200. | F17: Positive | G17: High | H17: LOCAL — from the zip | I17: Service running. | J17: GET /nope (404) and POST /dial with no bearer (401) | K17: 3 | L17: Both responses carry the full header set and a JSON envelope. No HTML framework error page is ever returned. | M17: F-P04 | N17: test/hardening.test.ts | O17: Not run
A18: TC-015 | B18: v0.28.0 | C18: Web hardening | D18: HSTS is omitted when the deployment is not https | E18: A header that promises transport security the deployment does not have is a false claim. It must be conditional. | F18: Negative | G18: Medium | H18: LOCAL — from the zip | I18: Service running with BASE_URL=http://localhost:3000. | J18: GET /pricing | K18: 3 | L18: strict-transport-security is absent; every other header is still present. | M18: F-P04 | N18: test/hardening.test.ts | O18: Not run
A19: TC-016 | B19: v0.28.0 | C19: Web hardening | D19: An oversized request body is rejected | E19: An uncapped JSON parser is a memory-exhaustion path on an unauthenticated route. | F19: Negative | G19: High | H19: LOCAL — from the zip | I19: Service running; a valid bearer for an installed org. | J19: A JSON body of roughly 120 kB. | K19: 3 | L19: HTTP 413. The request never reaches a handler. | M19: F-P04 | N19: test/hardening.test.ts | O19: Not run
A20: TC-017 | B20: v0.28.0 | C20: Web hardening | D20: The public OAuth start route is rate limited | E20: Before this release an unauthenticated caller could generate unlimited PKCE state and unlimited crypto work. | F20: Negative | G20: High | H20: LOCAL — from the zip | I20: Service started with VB_RATE_OAUTH_START_PER_MIN=2 for a short test. | J20: Three requests to /oauth/start within a minute. | K20: 4 | L20: The third request returns 429 with Retry-After and RateLimit-* headers. A different client IP still succeeds. | M20: F-P04 / VB-E-014 | N20: test/hardening.test.ts | O20: Not run
A21: TC-018 | B21: v0.28.0 | C21: Web hardening | D21: An authenticated write budget is per org and holds across instances | E21: A limiter held in one process is not a limit when two instances run. The counter must live in the shared store. | F21: Positive | G21: High | H21: LOCAL + PostgreSQL | I21: Two service instances on different ports sharing one DATABASE_URL; VB_RATE_ORG_WRITES_PER_MIN=3. | J21: Four writes for the same org, alternating between instances. | K21: 4 | L21: The fourth request returns 429 whichever instance serves it; a different org is unaffected. | M21: F-P04 / VB-E-014 | N21: test/hardening.test.ts | O21: Not run
... A59: TC-056 | B59: v0.28.0 | C59: Release gates | D59: The whole suite passes from a clean extraction at full coverage | E59: The release claim is only meaningful if it reproduces from the artefact that was shipped, not from the working tree. | F59: Positive | G59: Critical | H59: LOCAL — from the zip | I59: The delivered zip and nothing else. | J59: npm ci && npx jest --coverage | K59: 5 | L59: 58 suites, 613 tests, 100% statements, branches, functions and lines, and no coverage pragmas anywhere in src/. | M59: D13 / VB-CR-009 | N59: the suite itself | O59: Not run
A60: TC-057 | B60: v0.28.0 | C60: Operations | D60: A blue/green deploy rolls back by itself when the live slot is unhealthy | E60: The job this replaced was an echo statement; rollback that has never run is not rollback. | F60: Positive | G60: High | H60: LIVE deployment | I60: A hosting platform with two slots and the five deploy variables set. | J60: A deliberately broken build deployed to the idle slot. | K60: 4 | L60: The idle-slot health gate fails and traffic is never switched; if a failure is introduced after the switch, the script switches back automatically and reports it. | M60: VB-E-056 | N60: test/reviewSprint.test.ts asserts the script's shape only | O60: Not run | T60: Needs a live system that does not exist yet — see Pending_Live_Evidence.
A61: TC-058 | B61: v0.28.0 | C61: Operations | D61: A backup restores with matching row counts and checksums | E61: The in-process drill proved a JSON dump of a Map. This proves the real thing, and measures the recovery time. | F61: Positive | G61: High | H61: LOCAL + PostgreSQL | I61: A live PostgreSQL with data and pg_dump/pg_restore available. | J61: npm run dr-drill | K61: 4 | L61: The drill dumps, restores into a scratch database, compares per-table row counts and content checksums, prints a measured restore time and writes a report. | M61: VB-E-057 / ST-090 | N61: scripts/dr-drill.sh | O61: Not run
A62: TC-059 | B62: v0.27.0 | C62: Dialling honesty | D62: A call nobody placed says so on every surface | E62: For eight releases the panel told a rep 'Ringing' while their phone sat still. | F62: Positive | G62: Critical | H62: LOCAL — from the zip | I62: No telephony provider configured (the default). | J62: POST /dial | K62: 3 | L62: The record carries simulated:true, no provider call id, and the provider name 'simulated (no provider configured)'; the panel text names the simulation and never says Ringing. | M62: VB-CR-005 / ST-002 | N62: test/telephony.test.ts | O62: Not run
A63: TC-060 | B63: v0.27.0 | C63: Dialling honesty | D63: A deployment can choose failure over simulation | E63: Some deployments would rather a dial fail loudly than record a call that never happened. | F63: Negative | G63: Medium | H63: LOCAL — from the zip | I63: The refusing telephony implementation injected. | J63: POST /dial | K63: 3 | L63: The dial fails and no call record is written at all — a refusal is a failed dial, not a stored record of a call that never happened. | M63: VB-CR-005 | N63: test/telephony.test.ts | O63: Not run
A64: TC-061 | B64: v0.26.0 | C64: CRM write-back | D64: One call produces exactly one Task, however many times it is logged | E64: Idempotency is the platform's, via an upsert on our external id, so a retry or a second instance cannot duplicate the activity. | F64: Positive | G64: Critical | H64: LOCAL — from the zip | I64: An installed org and a CRM double or live org. | J64: Two /log calls with the same call id. | K64: 3 | L64: The first creates the Task (201), the second updates it (204). Exactly one Task exists for the call. | M64: VB-CR-005 / ST-011..020 | N64: test/crmWriteBack.test.ts | O64: Not run
A65: TC-062 | B65: v0.26.0 | C65: CRM write-back | D65: A Salesforce outage never costs the rep their note | E65: The customer's record of the call must not depend on the platform being reachable at that second. | F65: Negative | G65: Critical | H65: LOCAL — from the zip | I65: An installed org; Salesforce made unreachable. | J65: A hang-up with notes during the outage. | K65: 4 | L65: The activity is stored locally, the response reports crm.status 'queued' rather than success, and the queue is visible at /crm/health. | M65: VB-CR-005 | N65: test/crmWriteBack.test.ts | O65: Not run
A66: TC-063 | B66: v0.25.0 | C66: Install | D66: The OAuth callback answers the redirect a browser actually makes | E66: Only a POST route existed and every test POSTed it, so the suite agreed with itself while a real install would have landed on an unhandled GET. | F66: Positive | G66: Critical | H66: LOCAL — from the zip | I66: Service running. | J66: GET /oauth/callback?code=…&state=… | K66: 3 | L66: The install completes, the session arrives as an HttpOnly cookie, and the browser is redirected to the welcome page. | M66: VB-CR-002 | N66: test/externalReview.test.ts | O66: Not run
A67: TC-064 | B67: v0.25.0 | C67: Install | D67: A replayed or unknown OAuth state is refused | E67: Single-use state is what stops an authorisation code being replayed. | F67: Negative | G67: Critical | H67: LOCAL — from the zip | I67: Service running. | J67: The same state value twice; then a state never issued. | K67: 4 | L67: The first callback completes; the second is refused; an unknown state is refused. | M67: VB-CR-002 / VER-V07 | N67: test/externalReview.test.ts | O67: Not run
A68: TC-065 | B68: v0.25.0 | C68: Install | D68: The installer cannot name themselves owner | E68: The gateway returned the org and tokens, then the callback took the user id from the request body and made that user the owner. | F68: Negative | G68: Critical | H68: LOCAL — from the zip | I68: Service running. | J68: A callback carrying an attacker-chosen userId in the body or query. | K68: 3 | L68: The supplied id is ignored; ownership goes to the identity Salesforce confirmed. A session for the attacker-chosen id is refused. | M68: VB-CR-003 | N68: test/externalReview.test.ts | O68: Not run
A69: TC-066 | B69: v0.25.0 | C69: In-org authentication | D69: The softphone trades its install cookie for a bearer | E69: The adapter sent no Authorization header at all, so every /dial and /log from a real org would have been 401. | F69: Positive | G69: Critical | H69: LOCAL — from the zip | I69: A completed install and its session cookie. | J69: GET /softphone/bootstrap | K69: 5 | L69: The bootstrap returns a token, the org, the user and the service base; subsequent calls with that bearer succeed; without it they are 401. | M69: VB-CR-001 | N69: test/softphoneE2e.test.ts | O69: Not run
A70: TC-067 | B70: v0.25.0 | C70: Authorisation | D70: A member cannot read the owner's billing | E70: Cross-org access was closed earlier; least privilege inside an org was not. | F70: Negative | G70: High | H70: LOCAL — from the zip | I70: An org with an owner and a member. | J70: Member bearer against the billing and analytics screens and the support queue. | K70: 5 | L70: Each returns 403. The same requests as owner return 200. | M70: VB-CR-007 | N70: test/externalReview.test.ts | O70: Not run
A71: TC-068 | B71: v0.25.0 | C71: Durability | D71: Production refuses to run on in-memory storage | E71: The repository and its migrations existed for ten releases while the running service was still in-memory. | F71: Negative | G71: Critical | H71: LOCAL — from the zip | I71: None. | J71: NODE_ENV=production with no DATABASE_URL. | K71: 3 | L71: Boot fails with a message stating the service refuses in-memory storage in production. | M71: VB-CR-004 | N71: test/externalReview.test.ts | O71: Not run
A72: TC-069 | B72: v0.24.0 | C72: Storage contract | D72: A duplicate activity is refused by the database, not by application code | E72: An application-level check is defeated by a second instance however carefully it is written. | F72: Negative | G72: High | H72: LOCAL + PostgreSQL | I72: Migrations applied. | J72: Two inserts of the same activity external id. | K72: 4 | L72: The first write succeeds and the second is refused by the unique index; exactly one row exists. | M72: R-V15 | N72: test/repository.test.ts | O72: Not run
... A77: TC-074 | B77: v0.14.0 | C77: Screens | D77: All nine specified screens render and pass the accessibility audit | E77: Five P0 stories claimed an end-to-end surface while only two screens existed. | F77: Positive | G77: Medium | H77: LOCAL — from the zip | I77: An installed org with an owner bearer. | J77: GET /ui/<org> and each screen with ?format=html | K77: 3 | L77: Nine screens are returned; each renders as HTML; the automated jest-axe audit passes on populated and empty states. | M77: GAP-V2 / ST-005..045 | N77: test/screens.test.ts, test/a11y.test.ts | O77: Not run
A78: TC-075 | B78: v0.30.0 (pending) | C78: Real dialling | D78: A dial rings a real handset and the outcome reaches the CRM | E78: The first test in this product's history whose pass condition is a telephone ringing. Written now so it is ready the day a provider is chosen. | F78: Positive | G78: Critical | H78: BLOCKED — feature not built | I78: A telephony provider chosen (D-V5), credentials configured, a live org and a test handset. | J78: A dial from a Salesforce record to a handset you control. | K78: 5 | L78: The handset rings; the call record carries a provider call id and simulated:false; on hang-up a Task appears on the record without human intervention. | M78: VB-E-020 / D-V5 | N78: none yet — the adapter does not exist | O78: Blocked | T78: Written in advance; the capability does not exist yet — see Pending_Versions.
A79: TC-076 | B79: v0.30.0 (pending) | C79: Real dialling | D79: A replayed provider webhook produces exactly one state change | E79: Carriers retry webhooks. Idempotency on the provider call id is what stops a retried event double-counting a call. | F79: Negative | G79: Critical | H79: BLOCKED — feature not built | I79: The adapter and inbound webhook route built (D-V5). | J79: The same signed webhook delivered twice. | K79: 4 | L79: The first delivery moves the call state; the second is accepted and ignored. Unsigned and stale deliveries are refused. | M79: VB-E-021 / D-V5 | N79: none yet | O79: Blocked | T79: Written in advance; the capability does not exist yet — see Pending_Versions.
A80: TC-077 | B80: v0.31.0 (pending) | C80: Inbound | D80: An inbound call pops the matching Contact | E80: The inbound half of the product promise. Blocked on the same provider decision. | F80: Positive | G80: High | H80: BLOCKED — feature not built | I80: Inbound routing built; a provisioned inbound number; a live org. | J80: A call to the inbound number from a known Contact's number. | K80: 4 | L80: The matching Contact opens in the agent's Salesforce window before they answer; the activity is logged on the call ending. | M80: VB-E-030 / D-V5 | N80: none yet | O80: Blocked | T80: Written in advance; the capability does not exist yet — see Pending_Versions.
A81: TC-078 | B81: v0.35.0 (pending) | C81: WhatsApp | D81: A WhatsApp message is sent and received end to end | E81: The capability the second reviewer called the one genuinely differentiated and unbuilt wedge. | F81: Positive | G81: Critical | H81: BLOCKED — feature not built | I81: D-V6 decided to build; Meta business verification complete; a registered number. | J81: A message sent from the console and a reply from a real device. | K81: 4 | L81: The outbound message arrives on the device; the reply appears threaded on the Contact in Salesforce; both are logged as activities. | M81: VB-E-060 / D-V6 | N81: none yet | O81: Blocked | T81: Written in advance; the capability does not exist yet — see Pending_Versions.
A82: TC-079 | B82: v0.35.0 (pending) | C82: WhatsApp | D82: A free-form message outside the 24-hour window is refused | E82: Sending outside the customer-care window without a template is a platform violation, not a product choice. | F82: Negative | G82: Critical | H82: BLOCKED — feature not built | I82: A contact whose last inbound message is more than 24 hours old. | J82: A free-form outbound message. | K82: 4 | L82: The send is refused with a named error pointing at template messaging; a template send to the same contact succeeds. | M82: VB-E-061 / D-V6 | N82: none yet | O82: Blocked | T82: Written in advance; the capability does not exist yet — see Pending_Versions.
A83: TC-080 | B83: v0.32.0 (pending) | C83: Packaging | D83: The package installs in a scratch org and creates its Contact Center | E83: Only relevant under strategy option (A). Written so the decision can be executed rather than researched. | F83: Positive | G83: High | H83: BLOCKED — feature not built | I83: D-V8 resolved as (A); a Dev Hub, a registered namespace and the Partner Telephony add-on. | J83: sf package install into a fresh scratch org. | K83: 5 | L83: The package installs without errors, the Contact Center is created from its definition, and permission sets assign cleanly in three org shapes. | M83: VB-E-040 / VB-E-045 / D-V8 | N83: none yet | O83: Blocked | T83: Written in advance; the capability does not exist yet — see Pending_Versions.

Sheet Test_Steps_Detail
A1: TEST STEPS — every case broken into numbered steps
A2: How to use this sheet: filter on a test case id and work down. Each row is one action and the result that action must produce. A step whose expected result does not occur is a failed case: record it in Test_Cases and raise a row in Defect_Log. Record per-step outcomes in the last column if the case fails, so the report says which step broke.
A3: Test case ID | B3: Version | C3: Test case name | D3: Type | E3: Step # | F3: Action — what the tester does | G3: Expected result of this step | H3: Step outcome (Pass / Fail) | I3: Observation
A4: TC-001 | B4: v0.28.0 | C4: Softphone page is served with both scripts and its injected config | D4: Positive | E4: 1 | F4: Start the service: from the extracted zip run `npm ci`, then `npm run build`, then `VB_SESSION_SECRET=<32+ chars> SF_CLIENT_ID=x SF_CLIENT_SECRET=y BASE_URL=https://localhost:3000 npm start`. | G4: The boot lines report the storage choice and whether tokens are encrypted; the service listens on port 3000.
A5: TC-001 | B5: v0.28.0 | C5: Softphone page is served with both scripts and its injected config | D5: Positive | E5: 2 | F5: Request the page: `curl -i https://localhost:3000/widget/softphone.html`. | G5: HTTP/1.1 200 OK with `content-type: text/html; charset=utf-8`.
A6: TC-001 | B6: v0.28.0 | C6: Softphone page is served with both scripts and its injected config | D6: Positive | E6: 3 | F6: Search the body for the Open CTI script tag. | G6: `<script src="/support/api/67.0/lightning/opencti_min.js"></script>` is present.
A7: TC-001 | B7: v0.28.0 | C7: Softphone page is served with both scripts and its injected config | D7: Positive | E7: 4 | F7: Search the body for the adapter bundle tag. | G7: `<script src="/widget/VoiceBridgeSoftphone.js"></script>` is present — not a static-resource filename.
A8: TC-001 | B8: v0.28.0 | C8: Softphone page is served with both scripts and its injected config | D8: Positive | E8: 5 | F8: Search the body for the injected configuration. | G8: `<script>window.VB_CONFIG = {"serviceBase":"https://localhost:3000","statusPollSeconds":30};</script>` is present and the `<!--VB_CONFIG-->` marker is gone.
A9: TC-001 | B9: v0.28.0 | C9: Softphone page is served with both scripts and its injected config | D9: Positive | E9: 6 | F9: Request the adapter bundle: `curl -i https://localhost:3000/widget/VoiceBridgeSoftphone.js`. | G9: HTTP 200, `content-type: application/javascript`, body defines `VoiceBridgeAdapter`.
A10: TC-002 | B10: v0.28.0 | C10: An unknown asset under /widget is refused | D10: Negative | E10: 1 | F10: Request a file that is not on the allowlist: `curl -i https://localhost:3000/widget/evil.html`. | G10: HTTP 404.
A11: TC-002 | B11: v0.28.0 | C11: An unknown asset under /widget is refused | D11: Negative | E11: 2 | F11: Inspect the body. | G11: `{"error":"unknown widget asset"}` — JSON, no HTML error page, no path echoed back.
A12: TC-002 | B12: v0.28.0 | C12: An unknown asset under /widget is refused | D12: Negative | E12: 3 | F12: Confirm the security headers are still present on the 404. | G12: `content-security-policy` and `x-content-type-options: nosniff` are on the response.
A13: TC-003 | B13: v0.28.0 | C13: Path traversal under /widget is refused | D13: Negative | E13: 1 | F13: `curl -i "https://localhost:3000/widget/..%2Fpackage.json"`. | G13: HTTP 404, JSON body.
A14: TC-003 | B14: v0.28.0 | C14: Path traversal under /widget is refused | D14: Negative | E14: 2 | F14: `curl -i https://localhost:3000/widget/package.json`. | G14: HTTP 404, JSON body.
A15: TC-003 | B15: v0.28.0 | C15: Path traversal under /widget is refused | D15: Negative | E15: 3 | F15: Confirm no package.json content appears in either response. | G15: Neither body contains `"name": "voicebridge-cti"`.
... A311: TC-080 | B311: v0.32.0 (pending) | C311: The package installs in a scratch org and creates its Contact Center | D311: Positive | E311: 5 | F311: Repeat in a fresh Enterprise org and in one with an existing Call Center. | G311: Installs cleanly in all three shapes; a push upgrade preserves data.

Sheet Test_Execution_Log
A1: TEST EXECUTION LOG — one row per case per cycle
A2: How to use this sheet: append a block per test cycle; never overwrite a previous cycle. A cycle is one pass of the pack against one named build. The first block below is pre-filled with cycle C01 against v0.28.0 and is ready to be executed — the first three rows show the expected shape.
A3: Cycle | B3: Build under test | C3: Test case ID | D3: Executed by | E3: Date | F3: Result | G3: Duration (min) | H3: Defect raised | I3: Evidence (screenshot / log reference) | J3: Comment
A4: C01 | B4: voicebridge-cti v0.28.0 (f0f4eb4ab67d) | C4: TC-001 | J4: Example row — copy this shape for each case executed in the cycle.
A5: C01 | B5: voicebridge-cti v0.28.0 (f0f4eb4ab67d) | C5: TC-002
A6: C01 | B6: voicebridge-cti v0.28.0 (f0f4eb4ab67d) | C6: TC-003
A8: CYCLE DEFINITIONS
A9: C01 | B9: First manual pass against v0.28.0 — every case whose environment is LOCAL (61 cases). This can be run today by anyone with the zip.
A10: C02 | B10: LOCAL + PostgreSQL cases (10) once a database is provisioned — see Pending_Live_Evidence O6 and O9.
A11: C03 | B11: LIVE org cases (3) once a Salesforce developer org exists — O7, O7b.
A12: C04 | B12: LIVE deployment cases (2) once the service is deployed — O10.
A13: C05 | B13: Regression of C01 plus the previously blocked cases, once a decision releases them.

Sheet Defect_Log
A1: DEFECT LOG — every defect found in this product, by whom, and where it was closed
A2: How to use this sheet: the complete defect record across five internal cold-review passes, two independent external reviews and the remediation work itself. 'Found by' matters: a defect found by a review that the test suite was passing through is the kind this product keeps producing. Reopen a row by changing its status and adding a comment — never delete one.
A3: Defect ID | B3: Found by | C3: Date | D3: Severity | E3: Area | F3: What was wrong | G3: Status | H3: Fixed in version | I3: Test case that now covers it
A4: F-V01 | B4: Internal cold review 1 | C4: 11 Sep | D4: Critical | E4: Retention | F4: The self-serve delete cleared feature data but left roles and a PII tombstone behind, breaching the published 30-day deletion policy. | G4: Closed | H4: v0.12.0 | I4: covered by automated suite
A5: F-V05 | B5: Internal cold review 1 | C5: 11 Sep | D5: High | E5: Storage | F5: Per-org ledgers had no cap, so any org could grow them without bound. | G5: Closed | H5: v0.12.0 | I5: TC-026 (contract)
A6: F-V06 | B6: Internal cold review 1 | C6: 11 Sep | D6: High | E6: Resilience | F6: The production backoff sleep was a no-op: tests always injected their own sleep, so 100% coverage never touched the real one. | G6: Closed | H6: v0.12.0 | I6: covered by automated suite
A7: F-V07 | B7: Internal cold review 1 | C7: 11 Sep | D7: High | E7: Billing | F7: Read-only status after a failed payment was enforced nowhere, so a delinquent org kept full write access. | G7: Closed | H7: v0.12.0 | I7: covered by automated suite
A8: F-V10 | B8: Internal cold review 2 | C8: 11 Sep | D8: Critical | E8: In-org surface | F8: The softphone had always posted hang-ups to a /log route that did not exist, so auto-logging was silently dead in-org. | G8: Closed | H8: v0.13.0 | I8: TC-061
A9: VER-V01 | B9: Verification sweep 1 | C9: 11 Sep | D9: Critical | E9: In-org surface | F9: opencti_min.js was never loaded, so sforce.opencti was undefined and the panel silently did nothing in a real org. | G9: Closed | H9: v0.13.0 | I9: TC-001
A10: VER-V02 | B10: Verification sweep 1 | C10: 11 Sep | D10: Critical | E10: In-org surface | F10: enableClickToDial was never called, so the click-to-dial listener could never fire. | G10: Closed | H10: v0.13.0 | I10: TC-001, TC-006
A11: GAP-V2 | B11: Artifact-gap audit | C11: 13 Sep | D11: High | E11: Screens | F11: Nine screens were specified and five P0 stories claimed them; only two existed. | G11: Closed | H11: v0.14.0 | I11: TC-074
A12: VER-V06 | B12: Verification sweep 2 | C12: 13 Sep | D12: Critical | E12: Install | F12: The dev-org guide told the operator to create a Connected App, which Salesforce disabled from Spring '26 — the guide was unrunnable at step 2. | G12: Closed | H12: v0.14.0 | I12: TC-063
A13: GAP-V3 | B13: Artifact-gap audit | C13: 13 Sep | D13: Critical | E13: Runtime | F13: There was no process and no production OAuth gateway: createApp() had never been called by anything, so every documented route addressed a server that could not be started. | G13: Closed | H13: v0.15.0 | I13: TC-056
A14: GAP-V4 | B14: Artifact-gap audit | C14: 13 Sep | D14: Critical | E14: Storage | F14: No database schema existed behind a published retention policy, a backup drill and a sweep check that all demanded one. | G14: Closed | H14: v0.15.0 | I14: TC-073
... A46: R-V21 | B46: Perplexity review V001 | C46: 16 Sep | D46: Critical (risk) | E46: Platform | F46: Salesforce Open CTI — the API the entire in-org surface depends on — is in maintenance mode, ends life 28 Feb 2028 and is closed to newly created Agentforce Service orgs. | G46: Open — strategy | H46: — | I46: no test — blocked on D-V8 / D-V9

Sheet Traceability_Matrix
A1: TRACEABILITY — requirement or finding → version → manual test cases → automated counterpart
A2: How to use this sheet: computed from Test_Cases, so it cannot drift from it. Use it in two directions: from a requirement or a review finding, to check that something verifies it; and from a test case, to see what it is there to protect. The count column is a live formula over Test_Cases.
A3: Requirement / finding | B3: Version it landed in | C3: Manual test cases | D3: Automated counterpart | E3: Manual cases (count) | F3: Executed — pass or fail (count) | G3: Passed (count)
A4: CL-S01 | B4: v0.28.0 | C4: TC-047 | D4: test/observability.test.ts | E4: 1 | F4: =COUNTIFS(Test_Cases!$M$4:$M$83,"*"&$A4&"*",Test_Cases!$O$4:$O$83,"Pass")+COUNTIFS(Test_Cases!$M$4:$M$83,"*"&$A4&"*",Test_Cases!$O$4:$O$83,"Fail") -> 0 | G4: =COUNTIFS(Test_Cases!$M$4:$M$83,"*"&$A4&"*",Test_Cases!$O$4:$O$83,"Pass") -> 0
A5: CL-T02 | B5: v0.28.0 | C5: TC-007 | D5: test/tokenCipher.test.ts | E5: 1 | F5: =COUNTIFS(Test_Cases!$M$4:$M$83,"*"&$A5&"*",Test_Cases!$O$4:$O$83,"Pass")+COUNTIFS(Test_Cases!$M$4:$M$83,"*"&$A5&"*",Test_Cases!$O$4:$O$83,"Fail") -> 0 | G5: =COUNTIFS(Test_Cases!$M$4:$M$83,"*"&$A5&"*",Test_Cases!$O$4:$O$83,"Pass") -> 0
A6: CL-T08 | B6: v0.28.0 | C6: TC-040 | D6: test/numbers.test.ts | E6: 1 | F6: =COUNTIFS(Test_Cases!$M$4:$M$83,"*"&$A6&"*",Test_Cases!$O$4:$O$83,"Pass")+COUNTIFS(Test_Cases!$M$4:$M$83,"*"&$A6&"*",Test_Cases!$O$4:$O$83,"Fail") -> 0 | G6: =COUNTIFS(Test_Cases!$M$4:$M$83,"*"&$A6&"*",Test_Cases!$O$4:$O$83,"Pass") -> 0
A7: D-V5 | B7: v0.30.0 (pending) | C7: TC-075, TC-076, TC-077 | D7: none — manual only | E7: 3 | F7: =COUNTIFS(Test_Cases!$M$4:$M$83,"*"&$A7&"*",Test_Cases!$O$4:$O$83,"Pass")+COUNTIFS(Test_Cases!$M$4:$M$83,"*"&$A7&"*",Test_Cases!$O$4:$O$83,"Fail") -> 0 | G7: =COUNTIFS(Test_Cases!$M$4:$M$83,"*"&$A7&"*",Test_Cases!$O$4:$O$83,"Pass") -> 0
A8: D-V6 | B8: v0.35.0 (pending) | C8: TC-078, TC-079 | D8: none — manual only | E8: 2 | F8: =COUNTIFS(Test_Cases!$M$4:$M$83,"*"&$A8&"*",Test_Cases!$O$4:$O$83,"Pass")+COUNTIFS(Test_Cases!$M$4:$M$83,"*"&$A8&"*",Test_Cases!$O$4:$O$83,"Fail") -> 0 | G8: =COUNTIFS(Test_Cases!$M$4:$M$83,"*"&$A8&"*",Test_Cases!$O$4:$O$83,"Pass") -> 0
A9: D-V8 | B9: v0.32.0 (pending) | C9: TC-080 | D9: none — manual only | E9: 1 | F9: =COUNTIFS(Test_Cases!$M$4:$M$83,"*"&$A9&"*",Test_Cases!$O$4:$O$83,"Pass")+COUNTIFS(Test_Cases!$M$4:$M$83,"*"&$A9&"*",Test_Cases!$O$4:$O$83,"Fail") -> 0 | G9: =COUNTIFS(Test_Cases!$M$4:$M$83,"*"&$A9&"*",Test_Cases!$O$4:$O$83,"Pass") -> 0
A10: D13 | B10: v0.28.0 | C10: TC-056 | D10: the suite itself | E10: 1 | F10: =COUNTIFS(Test_Cases!$M$4:$M$83,"*"&$A10&"*",Test_Cases!$O$4:$O$83,"Pass")+COUNTIFS(Test_Cases!$M$4:$M$83,"*"&$A10&"*",Test_Cases!$O$4:$O$83,"Fail") -> 0 | G10: =COUNTIFS(Test_Cases!$M$4:$M$83,"*"&$A10&"*",Test_Cases!$O$4:$O$83,"Pass") -> 0
A11: F-P01 | B11: v0.28.0 | C11: TC-001, TC-002, TC-003, TC-004, TC-005, TC-006 | D11: test/widget.test.ts | E11: 6 | F11: =COUNTIFS(Test_Cases!$M$4:$M$83,"*"&$A11&"*",Test_Cases!$O$4:$O$83,"Pass")+COUNTIFS(Test_Cases!$M$4:$M$83,"*"&$A11&"*",Test_Cases!$O$4:$O$83,"Fail") -> 0 | G11: =COUNTIFS(Test_Cases!$M$4:$M$83,"*"&$A11&"*",Test_Cases!$O$4:$O$83,"Pass") -> 0
A12: F-P02 | B12: v0.28.0 | C12: TC-007, TC-008, TC-009, TC-010, TC-011, TC-012 | D12: scripts/rotate-token-keys.ts; test/tokenCipher.test.ts; test/tokenCipher.test.ts, test/externalReview.test.ts; test/tokenCipher.test.ts, test/repository.test.ts | E12: 6 | F12: =COUNTIFS(Test_Cases!$M$4:$M$83,"*"&$A12&"*",Test_Cases!$O$4:$O$83,"Pass")+COUNTIFS(Test_Cases!$M$4:$M$83,"*"&$A12&"*",Test_Cases!$O$4:$O$83,"Fail") -> 0 | G12: =COUNTIFS(Test_Cases!$M$4:$M$83,"*"&$A12&"*",Test_Cases!$O$4:$O$83,"Pass") -> 0
A13: F-P03 | B13: v0.28.0 | C13: TC-022, TC-023, TC-024, TC-025 | D13: test/crmWriteBack.test.ts; test/outboxWorker.test.ts | E13: 4 | F13: =COUNTIFS(Test_Cases!$M$4:$M$83,"*"&$A13&"*",Test_Cases!$O$4:$O$83,"Pass")+COUNTIFS(Test_Cases!$M$4:$M$83,"*"&$A13&"*",Test_Cases!$O$4:$O$83,"Fail") -> 0 | G13: =COUNTIFS(Test_Cases!$M$4:$M$83,"*"&$A13&"*",Test_Cases!$O$4:$O$83,"Pass") -> 0
A14: F-P03(b) | B14: v0.28.0 | C14: TC-026 | D14: test/repository.test.ts | E14: 1 | F14: =COUNTIFS(Test_Cases!$M$4:$M$83,"*"&$A14&"*",Test_Cases!$O$4:$O$83,"Pass")+COUNTIFS(Test_Cases!$M$4:$M$83,"*"&$A14&"*",Test_Cases!$O$4:$O$83,"Fail") -> 0 | G14: =COUNTIFS(Test_Cases!$M$4:$M$83,"*"&$A14&"*",Test_Cases!$O$4:$O$83,"Pass") -> 0
A15: F-P04 | B15: v0.28.0 | C15: TC-013, TC-014, TC-015, TC-016, TC-017, TC-018, TC-019, TC-020 | D15: test/hardening.test.ts | E15: 8 | F15: =COUNTIFS(Test_Cases!$M$4:$M$83,"*"&$A15&"*",Test_Cases!$O$4:$O$83,"Pass")+COUNTIFS(Test_Cases!$M$4:$M$83,"*"&$A15&"*",Test_Cases!$O$4:$O$83,"Fail") -> 0 | G15: =COUNTIFS(Test_Cases!$M$4:$M$83,"*"&$A15&"*",Test_Cases!$O$4:$O$83,"Pass") -> 0
... A70: VER-V07 | B70: v0.25.0 | C70: TC-064 | D70: test/externalReview.test.ts | E70: 1 | F70: =COUNTIFS(Test_Cases!$M$4:$M$83,"*"&$A70&"*",Test_Cases!$O$4:$O$83,"Pass")+COUNTIFS(Test_Cases!$M$4:$M$83,"*"&$A70&"*",Test_Cases!$O$4:$O$83,"Fail") -> 0 | G70: =COUNTIFS(Test_Cases!$M$4:$M$83,"*"&$A70&"*",Test_Cases!$O$4:$O$83,"Pass") -> 0

Sheet Test_Summary
A1: TEST SUMMARY — live counts calculated from Test_Cases
A2: How to use this sheet: do not type in it. Every number is a formula over Test_Cases, so it moves as you record results there. Read the environment block first: it says how much of this pack can be executed today and how much is waiting on a system or a decision.
A3: Grouping | B3: Value | C3: Total cases | D3: Positive | E3: Negative | F3: Not run | G3: Pass | H3: Fail | I3: Blocked
A4: BY VERSION
B5: v0.28.0 | C5: =COUNTIF(Test_Cases!$B$4:$B$83,$B5) -> 58 | D5: =COUNTIFS(Test_Cases!$B$4:$B$83,$B5,Test_Cases!$F$4:$F$83,"Positive") -> 30 | E5: =COUNTIFS(Test_Cases!$B$4:$B$83,$B5,Test_Cases!$F$4:$F$83,"Negative") -> 28 | F5: =COUNTIFS(Test_Cases!$B$4:$B$83,$B5,Test_Cases!$O$4:$O$83,"Not run") -> 58 | G5: =COUNTIFS(Test_Cases!$B$4:$B$83,$B5,Test_Cases!$O$4:$O$83,"Pass") -> 0 | H5: =COUNTIFS(Test_Cases!$B$4:$B$83,$B5,Test_Cases!$O$4:$O$83,"Fail") -> 0 | I5: =COUNTIFS(Test_Cases!$B$4:$B$83,$B5,Test_Cases!$O$4:$O$83,"Blocked") -> 0
B6: v0.27.0 | C6: =COUNTIF(Test_Cases!$B$4:$B$83,$B6) -> 2 | D6: =COUNTIFS(Test_Cases!$B$4:$B$83,$B6,Test_Cases!$F$4:$F$83,"Positive") -> 1 | E6: =COUNTIFS(Test_Cases!$B$4:$B$83,$B6,Test_Cases!$F$4:$F$83,"Negative") -> 1 | F6: =COUNTIFS(Test_Cases!$B$4:$B$83,$B6,Test_Cases!$O$4:$O$83,"Not run") -> 2 | G6: =COUNTIFS(Test_Cases!$B$4:$B$83,$B6,Test_Cases!$O$4:$O$83,"Pass") -> 0 | H6: =COUNTIFS(Test_Cases!$B$4:$B$83,$B6,Test_Cases!$O$4:$O$83,"Fail") -> 0 | I6: =COUNTIFS(Test_Cases!$B$4:$B$83,$B6,Test_Cases!$O$4:$O$83,"Blocked") -> 0
B7: v0.26.0 | C7: =COUNTIF(Test_Cases!$B$4:$B$83,$B7) -> 2 | D7: =COUNTIFS(Test_Cases!$B$4:$B$83,$B7,Test_Cases!$F$4:$F$83,"Positive") -> 1 | E7: =COUNTIFS(Test_Cases!$B$4:$B$83,$B7,Test_Cases!$F$4:$F$83,"Negative") -> 1 | F7: =COUNTIFS(Test_Cases!$B$4:$B$83,$B7,Test_Cases!$O$4:$O$83,"Not run") -> 2 | G7: =COUNTIFS(Test_Cases!$B$4:$B$83,$B7,Test_Cases!$O$4:$O$83,"Pass") -> 0 | H7: =COUNTIFS(Test_Cases!$B$4:$B$83,$B7,Test_Cases!$O$4:$O$83,"Fail") -> 0 | I7: =COUNTIFS(Test_Cases!$B$4:$B$83,$B7,Test_Cases!$O$4:$O$83,"Blocked") -> 0
B8: v0.25.0 | C8: =COUNTIF(Test_Cases!$B$4:$B$83,$B8) -> 6 | D8: =COUNTIFS(Test_Cases!$B$4:$B$83,$B8,Test_Cases!$F$4:$F$83,"Positive") -> 2 | E8: =COUNTIFS(Test_Cases!$B$4:$B$83,$B8,Test_Cases!$F$4:$F$83,"Negative") -> 4 | F8: =COUNTIFS(Test_Cases!$B$4:$B$83,$B8,Test_Cases!$O$4:$O$83,"Not run") -> 6 | G8: =COUNTIFS(Test_Cases!$B$4:$B$83,$B8,Test_Cases!$O$4:$O$83,"Pass") -> 0 | H8: =COUNTIFS(Test_Cases!$B$4:$B$83,$B8,Test_Cases!$O$4:$O$83,"Fail") -> 0 | I8: =COUNTIFS(Test_Cases!$B$4:$B$83,$B8,Test_Cases!$O$4:$O$83,"Blocked") -> 0
B9: v0.24.0 | C9: =COUNTIF(Test_Cases!$B$4:$B$83,$B9) -> 1 | D9: =COUNTIFS(Test_Cases!$B$4:$B$83,$B9,Test_Cases!$F$4:$F$83,"Positive") -> 0 | E9: =COUNTIFS(Test_Cases!$B$4:$B$83,$B9,Test_Cases!$F$4:$F$83,"Negative") -> 1 | F9: =COUNTIFS(Test_Cases!$B$4:$B$83,$B9,Test_Cases!$O$4:$O$83,"Not run") -> 1 | G9: =COUNTIFS(Test_Cases!$B$4:$B$83,$B9,Test_Cases!$O$4:$O$83,"Pass") -> 0 | H9: =COUNTIFS(Test_Cases!$B$4:$B$83,$B9,Test_Cases!$O$4:$O$83,"Fail") -> 0 | I9: =COUNTIFS(Test_Cases!$B$4:$B$83,$B9,Test_Cases!$O$4:$O$83,"Blocked") -> 0
B10: v0.23.0 | C10: =COUNTIF(Test_Cases!$B$4:$B$83,$B10) -> 1 | D10: =COUNTIFS(Test_Cases!$B$4:$B$83,$B10,Test_Cases!$F$4:$F$83,"Positive") -> 0 | E10: =COUNTIFS(Test_Cases!$B$4:$B$83,$B10,Test_Cases!$F$4:$F$83,"Negative") -> 1 | F10: =COUNTIFS(Test_Cases!$B$4:$B$83,$B10,Test_Cases!$O$4:$O$83,"Not run") -> 1 | G10: =COUNTIFS(Test_Cases!$B$4:$B$83,$B10,Test_Cases!$O$4:$O$83,"Pass") -> 0 | H10: =COUNTIFS(Test_Cases!$B$4:$B$83,$B10,Test_Cases!$O$4:$O$83,"Fail") -> 0 | I10: =COUNTIFS(Test_Cases!$B$4:$B$83,$B10,Test_Cases!$O$4:$O$83,"Blocked") -> 0
B11: v0.16.0 | C11: =COUNTIF(Test_Cases!$B$4:$B$83,$B11) -> 2 | D11: =COUNTIFS(Test_Cases!$B$4:$B$83,$B11,Test_Cases!$F$4:$F$83,"Positive") -> 0 | E11: =COUNTIFS(Test_Cases!$B$4:$B$83,$B11,Test_Cases!$F$4:$F$83,"Negative") -> 2 | F11: =COUNTIFS(Test_Cases!$B$4:$B$83,$B11,Test_Cases!$O$4:$O$83,"Not run") -> 2 | G11: =COUNTIFS(Test_Cases!$B$4:$B$83,$B11,Test_Cases!$O$4:$O$83,"Pass") -> 0 | H11: =COUNTIFS(Test_Cases!$B$4:$B$83,$B11,Test_Cases!$O$4:$O$83,"Fail") -> 0 | I11: =COUNTIFS(Test_Cases!$B$4:$B$83,$B11,Test_Cases!$O$4:$O$83,"Blocked") -> 0
B12: v0.15.0 | C12: =COUNTIF(Test_Cases!$B$4:$B$83,$B12) -> 1 | D12: =COUNTIFS(Test_Cases!$B$4:$B$83,$B12,Test_Cases!$F$4:$F$83,"Positive") -> 0 | E12: =COUNTIFS(Test_Cases!$B$4:$B$83,$B12,Test_Cases!$F$4:$F$83,"Negative") -> 1 | F12: =COUNTIFS(Test_Cases!$B$4:$B$83,$B12,Test_Cases!$O$4:$O$83,"Not run") -> 1 | G12: =COUNTIFS(Test_Cases!$B$4:$B$83,$B12,Test_Cases!$O$4:$O$83,"Pass") -> 0 | H12: =COUNTIFS(Test_Cases!$B$4:$B$83,$B12,Test_Cases!$O$4:$O$83,"Fail") -> 0 | I12: =COUNTIFS(Test_Cases!$B$4:$B$83,$B12,Test_Cases!$O$4:$O$83,"Blocked") -> 0
B13: v0.14.0 | C13: =COUNTIF(Test_Cases!$B$4:$B$83,$B13) -> 1 | D13: =COUNTIFS(Test_Cases!$B$4:$B$83,$B13,Test_Cases!$F$4:$F$83,"Positive") -> 1 | E13: =COUNTIFS(Test_Cases!$B$4:$B$83,$B13,Test_Cases!$F$4:$F$83,"Negative") -> 0 | F13: =COUNTIFS(Test_Cases!$B$4:$B$83,$B13,Test_Cases!$O$4:$O$83,"Not run") -> 1 | G13: =COUNTIFS(Test_Cases!$B$4:$B$83,$B13,Test_Cases!$O$4:$O$83,"Pass") -> 0 | H13: =COUNTIFS(Test_Cases!$B$4:$B$83,$B13,Test_Cases!$O$4:$O$83,"Fail") -> 0 | I13: =COUNTIFS(Test_Cases!$B$4:$B$83,$B13,Test_Cases!$O$4:$O$83,"Blocked") -> 0
B14: v0.30.0 (pending) | C14: =COUNTIF(Test_Cases!$B$4:$B$83,$B14) -> 2 | D14: =COUNTIFS(Test_Cases!$B$4:$B$83,$B14,Test_Cases!$F$4:$F$83,"Positive") -> 1 | E14: =COUNTIFS(Test_Cases!$B$4:$B$83,$B14,Test_Cases!$F$4:$F$83,"Negative") -> 1 | F14: =COUNTIFS(Test_Cases!$B$4:$B$83,$B14,Test_Cases!$O$4:$O$83,"Not run") -> 0 | G14: =COUNTIFS(Test_Cases!$B$4:$B$83,$B14,Test_Cases!$O$4:$O$83,"Pass") -> 0 | H14: =COUNTIFS(Test_Cases!$B$4:$B$83,$B14,Test_Cases!$O$4:$O$83,"Fail") -> 0 | I14: =COUNTIFS(Test_Cases!$B$4:$B$83,$B14,Test_Cases!$O$4:$O$83,"Blocked") -> 2
B15: v0.31.0 (pending) | C15: =COUNTIF(Test_Cases!$B$4:$B$83,$B15) -> 1 | D15: =COUNTIFS(Test_Cases!$B$4:$B$83,$B15,Test_Cases!$F$4:$F$83,"Positive") -> 1 | E15: =COUNTIFS(Test_Cases!$B$4:$B$83,$B15,Test_Cases!$F$4:$F$83,"Negative") -> 0 | F15: =COUNTIFS(Test_Cases!$B$4:$B$83,$B15,Test_Cases!$O$4:$O$83,"Not run") -> 0 | G15: =COUNTIFS(Test_Cases!$B$4:$B$83,$B15,Test_Cases!$O$4:$O$83,"Pass") -> 0 | H15: =COUNTIFS(Test_Cases!$B$4:$B$83,$B15,Test_Cases!$O$4:$O$83,"Fail") -> 0 | I15: =COUNTIFS(Test_Cases!$B$4:$B$83,$B15,Test_Cases!$O$4:$O$83,"Blocked") -> 1
B16: v0.35.0 (pending) | C16: =COUNTIF(Test_Cases!$B$4:$B$83,$B16) -> 2 | D16: =COUNTIFS(Test_Cases!$B$4:$B$83,$B16,Test_Cases!$F$4:$F$83,"Positive") -> 1 | E16: =COUNTIFS(Test_Cases!$B$4:$B$83,$B16,Test_Cases!$F$4:$F$83,"Negative") -> 1 | F16: =COUNTIFS(Test_Cases!$B$4:$B$83,$B16,Test_Cases!$O$4:$O$83,"Not run") -> 0 | G16: =COUNTIFS(Test_Cases!$B$4:$B$83,$B16,Test_Cases!$O$4:$O$83,"Pass") -> 0 | H16: =COUNTIFS(Test_Cases!$B$4:$B$83,$B16,Test_Cases!$O$4:$O$83,"Fail") -> 0 | I16: =COUNTIFS(Test_Cases!$B$4:$B$83,$B16,Test_Cases!$O$4:$O$83,"Blocked") -> 2
B17: v0.32.0 (pending) | C17: =COUNTIF(Test_Cases!$B$4:$B$83,$B17) -> 1 | D17: =COUNTIFS(Test_Cases!$B$4:$B$83,$B17,Test_Cases!$F$4:$F$83,"Positive") -> 1 | E17: =COUNTIFS(Test_Cases!$B$4:$B$83,$B17,Test_Cases!$F$4:$F$83,"Negative") -> 0 | F17: =COUNTIFS(Test_Cases!$B$4:$B$83,$B17,Test_Cases!$O$4:$O$83,"Not run") -> 0 | G17: =COUNTIFS(Test_Cases!$B$4:$B$83,$B17,Test_Cases!$O$4:$O$83,"Pass") -> 0 | H17: =COUNTIFS(Test_Cases!$B$4:$B$83,$B17,Test_Cases!$O$4:$O$83,"Fail") -> 0 | I17: =COUNTIFS(Test_Cases!$B$4:$B$83,$B17,Test_Cases!$O$4:$O$83,"Blocked") -> 1
A18: BY ENVIRONMENT
B19: LOCAL — from the zip | C19: =COUNTIF(Test_Cases!$H$4:$H$83,$B19) -> 59 | D19: =COUNTIFS(Test_Cases!$H$4:$H$83,$B19,Test_Cases!$F$4:$F$83,"Positive") -> 26 | E19: =COUNTIFS(Test_Cases!$H$4:$H$83,$B19,Test_Cases!$F$4:$F$83,"Negative") -> 33 | F19: =COUNTIFS(Test_Cases!$H$4:$H$83,$B19,Test_Cases!$O$4:$O$83,"Not run") -> 59 | G19: =COUNTIFS(Test_Cases!$H$4:$H$83,$B19,Test_Cases!$O$4:$O$83,"Pass") -> 0 | H19: =COUNTIFS(Test_Cases!$H$4:$H$83,$B19,Test_Cases!$O$4:$O$83,"Fail") -> 0 | I19: =COUNTIFS(Test_Cases!$H$4:$H$83,$B19,Test_Cases!$O$4:$O$83,"Blocked") -> 0
B20: LOCAL + PostgreSQL | C20: =COUNTIF(Test_Cases!$H$4:$H$83,$B20) -> 13 | D20: =COUNTIFS(Test_Cases!$H$4:$H$83,$B20,Test_Cases!$F$4:$F$83,"Positive") -> 7 | E20: =COUNTIFS(Test_Cases!$H$4:$H$83,$B20,Test_Cases!$F$4:$F$83,"Negative") -> 6 | F20: =COUNTIFS(Test_Cases!$H$4:$H$83,$B20,Test_Cases!$O$4:$O$83,"Not run") -> 13 | G20: =COUNTIFS(Test_Cases!$H$4:$H$83,$B20,Test_Cases!$O$4:$O$83,"Pass") -> 0 | H20: =COUNTIFS(Test_Cases!$H$4:$H$83,$B20,Test_Cases!$O$4:$O$83,"Fail") -> 0 | I20: =COUNTIFS(Test_Cases!$H$4:$H$83,$B20,Test_Cases!$O$4:$O$83,"Blocked") -> 0
B21: LIVE Salesforce org | C21: =COUNTIF(Test_Cases!$H$4:$H$83,$B21) -> 1 | D21: =COUNTIFS(Test_Cases!$H$4:$H$83,$B21,Test_Cases!$F$4:$F$83,"Positive") -> 1 | E21: =COUNTIFS(Test_Cases!$H$4:$H$83,$B21,Test_Cases!$F$4:$F$83,"Negative") -> 0 | F21: =COUNTIFS(Test_Cases!$H$4:$H$83,$B21,Test_Cases!$O$4:$O$83,"Not run") -> 1 | G21: =COUNTIFS(Test_Cases!$H$4:$H$83,$B21,Test_Cases!$O$4:$O$83,"Pass") -> 0 | H21: =COUNTIFS(Test_Cases!$H$4:$H$83,$B21,Test_Cases!$O$4:$O$83,"Fail") -> 0 | I21: =COUNTIFS(Test_Cases!$H$4:$H$83,$B21,Test_Cases!$O$4:$O$83,"Blocked") -> 0
B22: LIVE deployment | C22: =COUNTIF(Test_Cases!$H$4:$H$83,$B22) -> 1 | D22: =COUNTIFS(Test_Cases!$H$4:$H$83,$B22,Test_Cases!$F$4:$F$83,"Positive") -> 1 | E22: =COUNTIFS(Test_Cases!$H$4:$H$83,$B22,Test_Cases!$F$4:$F$83,"Negative") -> 0 | F22: =COUNTIFS(Test_Cases!$H$4:$H$83,$B22,Test_Cases!$O$4:$O$83,"Not run") -> 1 | G22: =COUNTIFS(Test_Cases!$H$4:$H$83,$B22,Test_Cases!$O$4:$O$83,"Pass") -> 0 | H22: =COUNTIFS(Test_Cases!$H$4:$H$83,$B22,Test_Cases!$O$4:$O$83,"Fail") -> 0 | I22: =COUNTIFS(Test_Cases!$H$4:$H$83,$B22,Test_Cases!$O$4:$O$83,"Blocked") -> 0
B23: BLOCKED — feature not built | C23: =COUNTIF(Test_Cases!$H$4:$H$83,$B23) -> 6 | D23: =COUNTIFS(Test_Cases!$H$4:$H$83,$B23,Test_Cases!$F$4:$F$83,"Positive") -> 4 | E23: =COUNTIFS(Test_Cases!$H$4:$H$83,$B23,Test_Cases!$F$4:$F$83,"Negative") -> 2 | F23: =COUNTIFS(Test_Cases!$H$4:$H$83,$B23,Test_Cases!$O$4:$O$83,"Not run") -> 0 | G23: =COUNTIFS(Test_Cases!$H$4:$H$83,$B23,Test_Cases!$O$4:$O$83,"Pass") -> 0 | H23: =COUNTIFS(Test_Cases!$H$4:$H$83,$B23,Test_Cases!$O$4:$O$83,"Fail") -> 0 | I23: =COUNTIFS(Test_Cases!$H$4:$H$83,$B23,Test_Cases!$O$4:$O$83,"Blocked") -> 6
A24: BY PRIORITY
B25: Critical | C25: =COUNTIF(Test_Cases!$G$4:$G$83,$B25) -> 29 | D25: =COUNTIFS(Test_Cases!$G$4:$G$83,$B25,Test_Cases!$F$4:$F$83,"Positive") -> 15 | E25: =COUNTIFS(Test_Cases!$G$4:$G$83,$B25,Test_Cases!$F$4:$F$83,"Negative") -> 14 | F25: =COUNTIFS(Test_Cases!$G$4:$G$83,$B25,Test_Cases!$O$4:$O$83,"Not run") -> 25 | G25: =COUNTIFS(Test_Cases!$G$4:$G$83,$B25,Test_Cases!$O$4:$O$83,"Pass") -> 0 | H25: =COUNTIFS(Test_Cases!$G$4:$G$83,$B25,Test_Cases!$O$4:$O$83,"Fail") -> 0 | I25: =COUNTIFS(Test_Cases!$G$4:$G$83,$B25,Test_Cases!$O$4:$O$83,"Blocked") -> 4
B26: High | C26: =COUNTIF(Test_Cases!$G$4:$G$83,$B26) -> 39 | D26: =COUNTIFS(Test_Cases!$G$4:$G$83,$B26,Test_Cases!$F$4:$F$83,"Positive") -> 18 | E26: =COUNTIFS(Test_Cases!$G$4:$G$83,$B26,Test_Cases!$F$4:$F$83,"Negative") -> 21 | F26: =COUNTIFS(Test_Cases!$G$4:$G$83,$B26,Test_Cases!$O$4:$O$83,"Not run") -> 37 | G26: =COUNTIFS(Test_Cases!$G$4:$G$83,$B26,Test_Cases!$O$4:$O$83,"Pass") -> 0 | H26: =COUNTIFS(Test_Cases!$G$4:$G$83,$B26,Test_Cases!$O$4:$O$83,"Fail") -> 0 | I26: =COUNTIFS(Test_Cases!$G$4:$G$83,$B26,Test_Cases!$O$4:$O$83,"Blocked") -> 2
B27: Medium | C27: =COUNTIF(Test_Cases!$G$4:$G$83,$B27) -> 12 | D27: =COUNTIFS(Test_Cases!$G$4:$G$83,$B27,Test_Cases!$F$4:$F$83,"Positive") -> 6 | E27: =COUNTIFS(Test_Cases!$G$4:$G$83,$B27,Test_Cases!$F$4:$F$83,"Negative") -> 6 | F27: =COUNTIFS(Test_Cases!$G$4:$G$83,$B27,Test_Cases!$O$4:$O$83,"Not run") -> 12 | G27: =COUNTIFS(Test_Cases!$G$4:$G$83,$B27,Test_Cases!$O$4:$O$83,"Pass") -> 0 | H27: =COUNTIFS(Test_Cases!$G$4:$G$83,$B27,Test_Cases!$O$4:$O$83,"Fail") -> 0 | I27: =COUNTIFS(Test_Cases!$G$4:$G$83,$B27,Test_Cases!$O$4:$O$83,"Blocked") -> 0
A28: BY AREA
B29: In-org softphone surface | C29: =COUNTIF(Test_Cases!$C$4:$C$83,$B29) -> 6 | D29: =COUNTIFS(Test_Cases!$C$4:$C$83,$B29,Test_Cases!$F$4:$F$83,"Positive") -> 3 | E29: =COUNTIFS(Test_Cases!$C$4:$C$83,$B29,Test_Cases!$F$4:$F$83,"Negative") -> 3 | F29: =COUNTIFS(Test_Cases!$C$4:$C$83,$B29,Test_Cases!$O$4:$O$83,"Not run") -> 6 | G29: =COUNTIFS(Test_Cases!$C$4:$C$83,$B29,Test_Cases!$O$4:$O$83,"Pass") -> 0 | H29: =COUNTIFS(Test_Cases!$C$4:$C$83,$B29,Test_Cases!$O$4:$O$83,"Fail") -> 0 | I29: =COUNTIFS(Test_Cases!$C$4:$C$83,$B29,Test_Cases!$O$4:$O$83,"Blocked") -> 0
B30: Encryption at rest | C30: =COUNTIF(Test_Cases!$C$4:$C$83,$B30) -> 6 | D30: =COUNTIFS(Test_Cases!$C$4:$C$83,$B30,Test_Cases!$F$4:$F$83,"Positive") -> 3 | E30: =COUNTIFS(Test_Cases!$C$4:$C$83,$B30,Test_Cases!$F$4:$F$83,"Negative") -> 3 | F30: =COUNTIFS(Test_Cases!$C$4:$C$83,$B30,Test_Cases!$O$4:$O$83,"Not run") -> 6 | G30: =COUNTIFS(Test_Cases!$C$4:$C$83,$B30,Test_Cases!$O$4:$O$83,"Pass") -> 0 | H30: =COUNTIFS(Test_Cases!$C$4:$C$83,$B30,Test_Cases!$O$4:$O$83,"Fail") -> 0 | I30: =COUNTIFS(Test_Cases!$C$4:$C$83,$B30,Test_Cases!$O$4:$O$83,"Blocked") -> 0
B31: Web hardening | C31: =COUNTIF(Test_Cases!$C$4:$C$83,$B31) -> 9 | D31: =COUNTIFS(Test_Cases!$C$4:$C$83,$B31,Test_Cases!$F$4:$F$83,"Positive") -> 3 | E31: =COUNTIFS(Test_Cases!$C$4:$C$83,$B31,Test_Cases!$F$4:$F$83,"Negative") -> 6 | F31: =COUNTIFS(Test_Cases!$C$4:$C$83,$B31,Test_Cases!$O$4:$O$83,"Not run") -> 9 | G31: =COUNTIFS(Test_Cases!$C$4:$C$83,$B31,Test_Cases!$O$4:$O$83,"Pass") -> 0 | H31: =COUNTIFS(Test_Cases!$C$4:$C$83,$B31,Test_Cases!$O$4:$O$83,"Fail") -> 0 | I31: =COUNTIFS(Test_Cases!$C$4:$C$83,$B31,Test_Cases!$O$4:$O$83,"Blocked") -> 0
B32: CRM outbox | C32: =COUNTIF(Test_Cases!$C$4:$C$83,$B32) -> 4 | D32: =COUNTIFS(Test_Cases!$C$4:$C$83,$B32,Test_Cases!$F$4:$F$83,"Positive") -> 2 | E32: =COUNTIFS(Test_Cases!$C$4:$C$83,$B32,Test_Cases!$F$4:$F$83,"Negative") -> 2 | F32: =COUNTIFS(Test_Cases!$C$4:$C$83,$B32,Test_Cases!$O$4:$O$83,"Not run") -> 4 | G32: =COUNTIFS(Test_Cases!$C$4:$C$83,$B32,Test_Cases!$O$4:$O$83,"Pass") -> 0 | H32: =COUNTIFS(Test_Cases!$C$4:$C$83,$B32,Test_Cases!$O$4:$O$83,"Fail") -> 0 | I32: =COUNTIFS(Test_Cases!$C$4:$C$83,$B32,Test_Cases!$O$4:$O$83,"Blocked") -> 0
B33: Storage contract | C33: =COUNTIF(Test_Cases!$C$4:$C$83,$B33) -> 2 | D33: =COUNTIFS(Test_Cases!$C$4:$C$83,$B33,Test_Cases!$F$4:$F$83,"Positive") -> 0 | E33: =COUNTIFS(Test_Cases!$C$4:$C$83,$B33,Test_Cases!$F$4:$F$83,"Negative") -> 2 | F33: =COUNTIFS(Test_Cases!$C$4:$C$83,$B33,Test_Cases!$O$4:$O$83,"Not run") -> 2 | G33: =COUNTIFS(Test_Cases!$C$4:$C$83,$B33,Test_Cases!$O$4:$O$83,"Pass") -> 0 | H33: =COUNTIFS(Test_Cases!$C$4:$C$83,$B33,Test_Cases!$O$4:$O$83,"Fail") -> 0 | I33: =COUNTIFS(Test_Cases!$C$4:$C$83,$B33,Test_Cases!$O$4:$O$83,"Blocked") -> 0
B34: Dialling | C34: =COUNTIF(Test_Cases!$C$4:$C$83,$B34) -> 1 | D34: =COUNTIFS(Test_Cases!$C$4:$C$83,$B34,Test_Cases!$F$4:$F$83,"Positive") -> 1 | E34: =COUNTIFS(Test_Cases!$C$4:$C$83,$B34,Test_Cases!$F$4:$F$83,"Negative") -> 0 | F34: =COUNTIFS(Test_Cases!$C$4:$C$83,$B34,Test_Cases!$O$4:$O$83,"Not run") -> 1 | G34: =COUNTIFS(Test_Cases!$C$4:$C$83,$B34,Test_Cases!$O$4:$O$83,"Pass") -> 0 | H34: =COUNTIFS(Test_Cases!$C$4:$C$83,$B34,Test_Cases!$O$4:$O$83,"Fail") -> 0 | I34: =COUNTIFS(Test_Cases!$C$4:$C$83,$B34,Test_Cases!$O$4:$O$83,"Blocked") -> 0
B35: Coaching | C35: =COUNTIF(Test_Cases!$C$4:$C$83,$B35) -> 1 | D35: =COUNTIFS(Test_Cases!$C$4:$C$83,$B35,Test_Cases!$F$4:$F$83,"Positive") -> 1 | E35: =COUNTIFS(Test_Cases!$C$4:$C$83,$B35,Test_Cases!$F$4:$F$83,"Negative") -> 0 | F35: =COUNTIFS(Test_Cases!$C$4:$C$83,$B35,Test_Cases!$O$4:$O$83,"Not run") -> 1 | G35: =COUNTIFS(Test_Cases!$C$4:$C$83,$B35,Test_Cases!$O$4:$O$83,"Pass") -> 0 | H35: =COUNTIFS(Test_Cases!$C$4:$C$83,$B35,Test_Cases!$O$4:$O$83,"Fail") -> 0 | I35: =COUNTIFS(Test_Cases!$C$4:$C$83,$B35,Test_Cases!$O$4:$O$83,"Blocked") -> 0
B36: Tenant isolation | C36: =COUNTIF(Test_Cases!$C$4:$C$83,$B36) -> 2 | D36: =COUNTIFS(Test_Cases!$C$4:$C$83,$B36,Test_Cases!$F$4:$F$83,"Positive") -> 0 | E36: =COUNTIFS(Test_Cases!$C$4:$C$83,$B36,Test_Cases!$F$4:$F$83,"Negative") -> 2 | F36: =COUNTIFS(Test_Cases!$C$4:$C$83,$B36,Test_Cases!$O$4:$O$83,"Not run") -> 2 | G36: =COUNTIFS(Test_Cases!$C$4:$C$83,$B36,Test_Cases!$O$4:$O$83,"Pass") -> 0 | H36: =COUNTIFS(Test_Cases!$C$4:$C$83,$B36,Test_Cases!$O$4:$O$83,"Fail") -> 0 | I36: =COUNTIFS(Test_Cases!$C$4:$C$83,$B36,Test_Cases!$O$4:$O$83,"Blocked") -> 0
B37: Audit integrity | C37: =COUNTIF(Test_Cases!$C$4:$C$83,$B37) -> 2 | D37: =COUNTIFS(Test_Cases!$C$4:$C$83,$B37,Test_Cases!$F$4:$F$83,"Positive") -> 1 | E37: =COUNTIFS(Test_Cases!$C$4:$C$83,$B37,Test_Cases!$F$4:$F$83,"Negative") -> 1 | F37: =COUNTIFS(Test_Cases!$C$4:$C$83,$B37,Test_Cases!$O$4:$O$83,"Not run") -> 2 | G37: =COUNTIFS(Test_Cases!$C$4:$C$83,$B37,Test_Cases!$O$4:$O$83,"Pass") -> 0 | H37: =COUNTIFS(Test_Cases!$C$4:$C$83,$B37,Test_Cases!$O$4:$O$83,"Fail") -> 0 | I37: =COUNTIFS(Test_Cases!$C$4:$C$83,$B37,Test_Cases!$O$4:$O$83,"Blocked") -> 0
B38: Session lifecycle | C38: =COUNTIF(Test_Cases!$C$4:$C$83,$B38) -> 5 | D38: =COUNTIFS(Test_Cases!$C$4:$C$83,$B38,Test_Cases!$F$4:$F$83,"Positive") -> 3 | E38: =COUNTIFS(Test_Cases!$C$4:$C$83,$B38,Test_Cases!$F$4:$F$83,"Negative") -> 2 | F38: =COUNTIFS(Test_Cases!$C$4:$C$83,$B38,Test_Cases!$O$4:$O$83,"Not run") -> 5 | G38: =COUNTIFS(Test_Cases!$C$4:$C$83,$B38,Test_Cases!$O$4:$O$83,"Pass") -> 0 | H38: =COUNTIFS(Test_Cases!$C$4:$C$83,$B38,Test_Cases!$O$4:$O$83,"Fail") -> 0 | I38: =COUNTIFS(Test_Cases!$C$4:$C$83,$B38,Test_Cases!$O$4:$O$83,"Blocked") -> 0
B39: Number handling | C39: =COUNTIF(Test_Cases!$C$4:$C$83,$B39) -> 4 | D39: =COUNTIFS(Test_Cases!$C$4:$C$83,$B39,Test_Cases!$F$4:$F$83,"Positive") -> 1 | E39: =COUNTIFS(Test_Cases!$C$4:$C$83,$B39,Test_Cases!$F$4:$F$83,"Negative") -> 3 | F39: =COUNTIFS(Test_Cases!$C$4:$C$83,$B39,Test_Cases!$O$4:$O$83,"Not run") -> 4 | G39: =COUNTIFS(Test_Cases!$C$4:$C$83,$B39,Test_Cases!$O$4:$O$83,"Pass") -> 0 | H39: =COUNTIFS(Test_Cases!$C$4:$C$83,$B39,Test_Cases!$O$4:$O$83,"Fail") -> 0 | I39: =COUNTIFS(Test_Cases!$C$4:$C$83,$B39,Test_Cases!$O$4:$O$83,"Blocked") -> 0
B40: CRM matching | C40: =COUNTIF(Test_Cases!$C$4:$C$83,$B40) -> 3 | D40: =COUNTIFS(Test_Cases!$C$4:$C$83,$B40,Test_Cases!$F$4:$F$83,"Positive") -> 2 | E40: =COUNTIFS(Test_Cases!$C$4:$C$83,$B40,Test_Cases!$F$4:$F$83,"Negative") -> 1 | F40: =COUNTIFS(Test_Cases!$C$4:$C$83,$B40,Test_Cases!$O$4:$O$83,"Not run") -> 3 | G40: =COUNTIFS(Test_Cases!$C$4:$C$83,$B40,Test_Cases!$O$4:$O$83,"Pass") -> 0 | H40: =COUNTIFS(Test_Cases!$C$4:$C$83,$B40,Test_Cases!$O$4:$O$83,"Fail") -> 0 | I40: =COUNTIFS(Test_Cases!$C$4:$C$83,$B40,Test_Cases!$O$4:$O$83,"Blocked") -> 0
... B60: Packaging | C60: =COUNTIF(Test_Cases!$C$4:$C$83,$B60) -> 1 | D60: =COUNTIFS(Test_Cases!$C$4:$C$83,$B60,Test_Cases!$F$4:$F$83,"Positive") -> 1 | E60: =COUNTIFS(Test_Cases!$C$4:$C$83,$B60,Test_Cases!$F$4:$F$83,"Negative") -> 0 | F60: =COUNTIFS(Test_Cases!$C$4:$C$83,$B60,Test_Cases!$O$4:$O$83,"Not run") -> 0 | G60: =COUNTIFS(Test_Cases!$C$4:$C$83,$B60,Test_Cases!$O$4:$O$83,"Pass") -> 0 | H60: =COUNTIFS(Test_Cases!$C$4:$C$83,$B60,Test_Cases!$O$4:$O$83,"Fail") -> 0 | I60: =COUNTIFS(Test_Cases!$C$4:$C$83,$B60,Test_Cases!$O$4:$O$83,"Blocked") -> 1
A61: TOTAL | B61: All test cases | C61: =COUNTA(Test_Cases!$A$4:$A$83) -> 80 | D61: =COUNTIF(Test_Cases!$F$4:$F$83,"Positive") -> 39 | E61: =COUNTIF(Test_Cases!$F$4:$F$83,"Negative") -> 41 | F61: =COUNTIF(Test_Cases!$O$4:$O$83,"Not run") -> 74 | G61: =COUNTIF(Test_Cases!$O$4:$O$83,"Pass") -> 0 | H61: =COUNTIF(Test_Cases!$O$4:$O$83,"Fail") -> 0 | I61: =COUNTIF(Test_Cases!$O$4:$O$83,"Blocked") -> 6
B62: Total numbered steps | C62: =COUNTA(Test_Steps_Detail!$A$4:$A$2000) -> 308
A64: HOW TO READ THIS | B64: The environment block is the honest headline: the LOCAL row is what a reviewer can verify this afternoon with nothing but the delivered zip. Everything in the other four rows is waiting on a database, a Salesforce org, a deployment or a decision — not on more engineering.

Sheet Test_Environment
A1: TEST ENVIRONMENT — how to stand up each environment this pack needs
A2: How to use this sheet: follow the block matching the Environment column of the case you are about to run. Every variable the service reads is listed with what happens when it is absent, because several of them fail closed by design and that behaviour is itself under test.
A3: Environment | B3: What you need | C3: How to set it up | D3: What it lets you run | E3: Notes
A4: LOCAL — from the zip | B4: Node 22+, the delivered zip, nothing else | C4: 1. Extract voicebridge-cti-codebase-20260920_1045.zip. 2. npm ci 3. npm run build 4. Start with: VB_SESSION_SECRET=<32+ chars> SF_CLIENT_ID=x SF_CLIENT_SECRET=y BASE_URL=https://localhost:3000 VB_METRICS_TOKEN=t npm start. For suite-based cases: npx jest --coverage. | D4: 61 of the 80 cases | E4: No account, credential or external service. This is the environment a reviewer should use.
A5: LOCAL + PostgreSQL | B5: The above plus PostgreSQL 16 and an application (non-superuser) role | C5: 1. Provision PostgreSQL 16. 2. Create a non-superuser role and grant it SELECT/INSERT/UPDATE/DELETE on the public schema tables and USAGE on the sequences (db/checks/rls-smoke.sql shows the grants). 3. export DATABASE_URL=postgres://… 4. npm run migrate 5. Start the service with DATABASE_URL and VB_TOKEN_KEYS set. | D5: 10 cases covering storage, isolation, audit and encryption at rest | E5: A superuser URL is refused in production by design — that refusal is itself test case TC-030.
A6: LIVE Salesforce org | B6: A Salesforce developer org with the package deployed | C6: 1. Register a Dev Hub and a namespace. 2. sf project deploy the sfpackage directory. 3. Assign a VoiceBridge permission set. 4. Create the CallCenter from the packaged definition and set adapterUrl to a publicly reachable service base URL. 5. Complete the OAuth install. | D6: 3 cases — the in-org surface and the live CRM write-back | E6: Operator steps O7 and O7b. This is the highest-value environment on the list and does not exist today.
A7: LIVE deployment | B7: A deployed service with two slots and a metrics backend | C7: 1. Deploy the built artefact to a platform offering blue/green slots. 2. Set DEPLOY_CMD, IDLE_URL, SWITCH_CMD, ROLLBACK_CMD and LIVE_URL. 3. Point any Prometheus-compatible scraper at /metrics with the bearer and import the rules from /status/slo. | D7: 2 cases — automatic rollback and the SLO game day | E7: Operator step O10.
A8: BLOCKED — feature not built | B8: Nothing — the capability does not exist | C8: These cases cannot be run at all. They are written so that the day the blocking decision is made the verification already exists. See Pending_Versions for what each one is waiting on. | D8: 6 cases across telephony, WhatsApp and packaging | E8: Do not mark these Not run — they are Blocked, which is a different fact.
A10: ENVIRONMENT VARIABLES
A11: Variable | B11: Required when | C11: What it does | D11: Behaviour if absent
A12: SF_CLIENT_ID / SF_CLIENT_SECRET | B12: Always | C12: External Client App credentials for the OAuth install. | D12: Boot fails immediately.
A13: VB_SESSION_SECRET | B13: Always (32 chars minimum) | C13: Signs session tokens. | D13: Boot fails — a default secret is the same as no secret.
A14: BASE_URL | B14: Always | C14: Published to the in-org page as serviceBase and used for the HSTS decision. | D14: Defaults to http://localhost:3000; HSTS is then correctly omitted.
A15: DATABASE_URL | B15: Production; LOCAL + PostgreSQL cases | C15: Durable storage. | D15: Development runs in memory; production refuses to boot (TC-068).
A16: VB_TOKEN_KEYS | B16: Production; encryption cases | C16: Key ring for token encryption at rest: "1:<base64 32 bytes>". | D16: Development stores tokens in the clear and says so in the boot line; production refuses to boot (TC-011).
A17: HYPERFORCE_REGION / APP_HOST_REGION | B17: Production | C17: The two regions published in the residency statement. | D17: Production refuses to boot; elsewhere the trust page publishes 'residency UNVERIFIED' rather than a guess.
A18: VB_METRICS_TOKEN | B18: When /metrics is wanted | C18: Bearer for the metrics endpoint. | D18: The endpoint returns 404 — disabled rather than open (TC-045).
A19: VB_SECURITY_CONTACT / VB_PRIVACY_CONTACT | B19: Before publishing a trust page | C19: Real contact addresses. | D19: The trust page publishes 'not yet published' rather than a placeholder that looks real (TC-052).
A20: VB_RATE_* (three) | B20: Optional | C20: Per-minute budgets for the OAuth start, org writes and public reads. | D20: Defaults 30 / 600 / 300. Cannot be switched off.
A21: VB_REQUEST_TIMEOUT_MS | B21: Optional | C21: Inbound request timeout. | D21: Defaults to 15000; minimum 1000.
A22: VB_FRAME_ANCESTORS | B22: Optional | C22: CSP frame-ancestors allowlist. | D22: Defaults to the Salesforce domains.
A23: VB_SESSION_TTL_DAYS | B23: Optional | C23: Session lifetime. | D23: Defaults to 1 day (reduced from 7 in v0.28.0); maximum 30.

Sheet Entry_Exit_Criteria
A1: ENTRY / EXIT CRITERIA, SEVERITY DEFINITIONS, ASSUMPTIONS AND RISKS
A2: How to use this sheet: agree the entry criteria before a cycle starts and the exit criteria before anyone calls it finished. The severity definitions are the ones used in Defect_Log, so a defect raised during execution is classified the same way as one raised by a review.
A3: Section | B3: Item | C3: Detail
A4: Entry criteria | B4: A named build exists | C4: A packaged zip with its evidence pack, whose hash matches the manifest.
A5: Entry criteria | B5: The automated suite is green | C5: npm ci && npx jest --coverage passes at 100% on all four measures from the extracted zip.
A6: Entry criteria | B6: The environment is available | C6: The environment block for the cases in scope has been stood up and smoke-checked (GET /health returns 200).
A7: Entry criteria | B7: The pack is current | C7: This workbook's Document_Control names the build under test.
A8: Exit criteria | B8: Every in-scope case has a result | C8: No case in scope is left at Not run. Blocked is a valid result only for cases whose environment is BLOCKED or unavailable.
A9: Exit criteria | B9: No open Critical or Blocker defect | C9: Any Critical defect found during the cycle is fixed and its case re-run, or the cycle is failed.
A10: Exit criteria | B10: High defects are dispositioned | C10: Each is either fixed and re-tested, or accepted in writing by the owner with a dated note in Defect_Log.
A11: Exit criteria | B11: The log is complete | C11: Test_Execution_Log carries one row per case per cycle, with evidence references for every failure.
A12: Exit criteria | B12: The summary is re-read | C12: Test_Summary is checked for cases that silently stayed Not run.
A13: Severity | B13: Blocker | C13: The product cannot be used or listed at all until it is fixed. Example: the softphone cannot authenticate to its own API (VB-CR-001).
A14: Severity | B14: Critical | C14: A core promise is broken, or data is exposed, lost or silently not written. Example: on PostgreSQL no call ever ended (F-V31).
... A23: Risk | B23: One defect class keeps recurring | C23: Four separate reviews found the same shape: a claim, a route or a guard that exists in one artefact and not in the one beside it. Any new artefact should be checked against its counterpart on arrival.

Sheet RACI
A1: RACI — who does what in this pack
A2: How to use this sheet: R = does the work, A = accountable for the outcome, C = consulted, I = informed. On a solo build most rows collapse to two names, which is exactly why the decision rows matter: nobody else will make them.
A3: Activity | B3: Claude | C3: Senthil (KP) | D3: Independent reviewer | E3: Vendor / third party | F3: Notes
A4: Writing and maintaining this pack | B4: R | C4: A | D4: I | E4: — | F4: Re-issued with each code version that changes behaviour.
A5: Executing LOCAL test cases | B5: R | C5: A | D5: C | E5: — | F5: Can be run today by anyone with the zip.
A6: Provisioning PostgreSQL / a Salesforce dev org / a deployment | B6: C | C6: R, A | D6: I | E6: — | F6: The single largest unblocking act available.
A7: Executing LIVE test cases | B7: R | C7: A | D7: C | E7: — | F7: Cannot start until the row above happens.
A8: Raising and classifying defects | B8: R | C8: A | D8: C | E8: — | F8: Severity definitions are on Entry_Exit_Criteria.
A9: Deciding D-V3 … D-V9 and D13 | B9: C | C9: R, A | D9: C | E9: — | F9: Eight open decisions; packets already written.
A10: Penetration test | B10: C | C10: A | D10: I | E10: R | F10: Needs a deployment to test.
A11: SOC 2 readiness assessment | B11: C | C11: A | D11: I | E11: R | F11: The control-to-code map is already written.
A12: Independent review sign-off (DR-12) | B12: C | C12: A | D12: R | E12: — | F12: Same-AI review is not independent; this is deliberately someone else's job.
A13: Approving the pack for use | B13: C | C13: R, A | D13: I | E13: — | F13: Sign-off grid is on Cover_Sheet.

Sheet Glossary
A1: GLOSSARY — every term and abbreviation used in this workbook
A2: How to use this sheet: alphabetical within groups. Product-specific identifiers (ST-, D-V, F-P, O-) are explained at the bottom, because knowing the prefix is usually enough to know where to look.
A3: Term | B3: Meaning
A4: Open CTI | B4: The Salesforce API for embedding a third-party softphone in the Lightning interface. In maintenance mode; end of life 28 February 2028; closed to newly created Agentforce Service orgs.
A5: Service Cloud Voice / Partner Telephony | B5: The Salesforce model third-party carriers are directed to as the supported replacement for Open CTI.
A6: CallCenter definition | B6: The Salesforce metadata record naming the URL an org loads as its softphone.
A7: External Client App (ECA) | B7: The OAuth client type that replaced Connected Apps, which can no longer be created as of Spring '26.
A8: PKCE | B8: Proof Key for Code Exchange — an OAuth extension that binds an authorisation code to the client that requested it.
A9: SOSL | B9: Salesforce Object Search Language. FIND {digits} IN PHONE FIELDS uses the platform's own phone index rather than an unindexed wildcard scan.
A10: Upsert on an external id | B10: Writing a record keyed on our own identifier so the platform decides insert or update, which makes a retry idempotent.
A11: 2GP package | B11: Second-generation managed package — the unit an AppExchange application is distributed in.
A12: Outbox | B12: A durable queue of CRM writes that failed, drained in order by a background worker with backoff and a dead-letter threshold.
A13: Dead letter | B13: A queued write parked after too many attempts: visible in health output, never retried automatically.
A14: Lease | B14: A short-lived database row that makes exactly one instance the leader for a background job.
... A34: LC-n / G-n | B34: Launch-checklist items and completion-gate rows in the sprint tracker.
