Workbook

Sheet Version_Control
A1: VERSION CONTROL — MeetSync Sprint Tracker & Traceability
A2: File naming: claude_v<NNN>_<proper file name>_YYYYMMDD_HHMI.xlsx. Companion: v008 product workbook = backlog source of truth; v009 of that workbook stays planned for full as-built re-baseline.
A3: Version | B3: Date/Time | C3: Author | D3: Change Description | E3: Status
A4: v001 | B4: 2026-09-11 08:42 | C4: Claude for Senthil/KP | D4: THIS FILE — Standalone live execution tracker for MeetSync (Zoom App Marketplace), extracted to the TeleField-v001 file pattern per Senthil's 08:42 instruction; supersedes nothing — mirrors and will carry forward the tracker sheets embedded in the v008 product workbook. Contains: Sprint_Tracker_Log E001-E011, Decisions (D13/D15 + D-M1..M3), full 100-story Traceability_Matrix from v008 Full_Backlog (399 pts, rollup formula-verified: 74 Done-in-code / 292 pts / 73.2%), Sprint_Status_Rollup S1-S12, S9_Prep_Board, RAID_Carryover, Gate_Checklist. Build state carried in: S1-S8 executed under D13 — 18 Jest suites / 139 tests, 100% stmts/branches/funcs/lines, zero pragmas. Code: claude_v008_meetsync_s1_s8_code_20260910_2258.zip. | E4: Released
A5: v002 | B5: 2026-09-11 08:47 | C5: Claude for Senthil/KP | D5: THIS FILE — S9 CODEABLE SCOPE EXECUTED on 08:47 continue: ST-069 delete-my-data self-serve SHIPPED (owner-only POST /orgs/:id/delete-my-data, explicit DELETE confirmation, immediate token wipe, purge due at next sweep — retention window bypassed; allow/deny audit-logged per ST-067; accelerates purge on already-uninstalled accounts preserving original uninstall facts). ST-091 degradation made observable in code: ZoomClient.platformHealth() ok/degraded/probing surfaced on /orgs/:id/status — breaker-open shows 'degraded' without erroring; live chaos drill still owed. D13 gate re-verified: 19 Jest suites / 149 tests, 100% stmts/branches/funcs/lines, ZERO pragmas. Rollup now 75 Done-in-code / 297 pts / 74.4%. Docs updated (DATA_FLOW ST-069 shipped; README v0.9.0). Code: claude_v009_meetsync_s9_code_20260911_0847.zip. E012 logged. | E5: Released
A6: v003 | B6: 2026-09-11 13:32 | C6: Claude for Senthil/KP | D6: THIS FILE — S10 CODEABLE SCOPE EXECUTED on 13:32 continue: ST-080 help center SHIPPED (15 launch articles covering install->troubleshooting + ranked keyword search title>keyword>body with deterministic tie-break; /help/articles, /help/articles/:id, /help/search — same source for hosted site and in-app panel). ST-084 status page SHIPPED (public /status JSON + /status.html, component health incl. ST-091 platformHealth, uptime; incident comms template docs/INCIDENT_COMMS.md). ST-095 pricing endpoint /pricing served from the SAME PLANS object billing enforces (matrix+FAQ draft docs/PRICING_PAGE.md). ST-083 code side: demo-data mode POST /orgs/:id/demo-mode (admin+) seeds realistic workspace — notes session, extracted actions, completed sandbox writebacks; 2-min video remains live. ST-096 trust page drafted (docs/TRUST_PAGE.md incl. subprocessors). D13 gate: 20 suites / 160 tests, 100x4, zero pragmas. Rollup 77 Done-in-code / 304 pts / 76.2%. Code: claude_v010_meetsync_s10_code_20260911_1332.zip. E013 + S10_Board added. | E6: Released
A7: v004 | B7: 2026-09-11 15:26 | C7: Claude for Senthil/KP | D7: THIS FILE — CODEABLE RUNWAY CLOSED on 15:26 continue: ST-098 launch-day runbook FINALIZED v1.0 (monitoring table over shipped surfaces /healthz /status funnel errorSpike; <2-min blue/green rollback with the safety properties that make it lossless — webhook replay-guard/dedupe, queued writebacks; Zoom-outage DON'T-rollback path; comms tree + T-1d..T+7d launch sequence) -> Done-in-code. ST-099 groundwork built, story kept HONESTLY in Backlog (it is a post-launch iteration from real data): help-search terms now captured, normalized, ranked at /analytics/search-terms so iteration 1 has data on day 1. D13 gate: 20 suites / 162 tests, 100x4, zero pragmas. Rollup 78 Done-in-code / 307 pts / 76.9%. NEW Senthil_Handover sheet consolidates every remaining item by decision/live/human with what-Claude-needs-back. Code: claude_v011_meetsync_s11_code_20260911_1526.zip. E014 logged. All codeable MeetSync scope is now exhausted. | E7: Released
A8: v005 | B8: 2026-09-11 22:09 | C8: Claude for Senthil/KP | D8: THIS FILE — WEB SURFACE BUILT on 22:09 continue. Correction to E014's 'runway closed': the five surface stories (ST-005/015/025/035/045) read 'in-meeting panel + WEB DASHBOARD surface' — the dashboard half and the panel UI were codeable all along with the Zoom Apps SDK behind a boundary interface; only the live SDK handshake needs the dev app. Built: React web/ layer — NotesPanel (timestamped entries, chip cycling, degraded-mode banner wired to ST-091 platformHealth), ActionsPanel (rule preview in test mode), CrmPanel (mappings, queue, terminal-failure retry visibility), DealRiskPanel (score bands + sensitivity), IndicSettings (pack toggles), App shell serving in-meeting panel AND web dashboard from one codebase via ZoomSdk boundary (MockZoomSdk in tests), typed Api client w/ ApiError. RTL suite added under the SAME gate: 21 suites / 171 tests, 100% x4 across src/ AND web/, zero pragmas. Evidence upgraded on all five surface rows — remaining gap is ONLY the live dev-app handshake (Handover #2). Code: claude_v012_meetsync_web_surface_code_20260911_2209.zip. E015 logged. | E8: Released
A9: v006 | B9: 2026-09-13 09:52 | C9: Claude for Senthil/KP | D9: THIS FILE — ADVERSARIAL COLD REVIEW passes 1+2 executed on 11 Sep 22:32 / 13 Sep 09:52 'do them all properly' / 'continue'. First cold review of MeetSync; all 20 src modules plus the web surface read line by line against the sibling defect classes. 21 defects fixed with pinned regressions (M-F01..M-F21, new Review_Findings sheet), 3 observations logged no-fix for Senthil's disposition. Code v013 released: 22 suites / 225 tests at 100% statements/branches/functions/lines, zero istanbul pragmas, tsc clean. Story position deliberately UNCHANGED (78 Done / 22 remaining) — this is a correctness release, no story flips. | E9: Released
A10: v007 | B10: 2026-09-13 10:01 | C10: Claude for Senthil/KP | D10: THIS FILE — product workbook AS-BUILT RE-BASELINE released as claude_v009_meetsync_zoom_product_workbook_20260913_1001.xlsx, closing Senthil_Handover #11. Full_Backlog statuses and a new evidence column synced from this tracker's Traceability_Matrix; Sprint_Board Done formula corrected to count Done-in-code (it counted exact 'Done' only, so it had been reading zero for eight days); Product_Spec, Screens_Wireframes, Launch_Checklist, Risk_Register and Metrics_Targets rewritten from what v013 actually does. No story states changed in this tracker — the workbook was brought to the tracker, not the other way round. | E10: Released
A11: v008 | B11: 2026-09-13 10:25 | C11: Claude for Senthil/KP | D11: THIS FILE — EXTERNAL VERIFICATION SWEEP against live Zoom platform documentation, MeetSync's first. 7 findings in a new Verification_Sweep sheet, 4 of them LIVE-BLOCKING and invisible to a suite at 100% coverage, because every test asserted our own wrong shape back to us. Code v014 released (claude_v014_meetsync_verification_sweep_code_20260913_1025.zip): 22 suites / 239 tests at 100% statements/branches/functions/lines, zero pragmas, tsc clean. Story position UNCHANGED (78 Done / 307 of 399 pts) — correctness release. Same sibling pattern as VoiceBridge VER-V01/V02 and TestPulse's runtime/API sweep: the defects a cold review cannot reach are the ones where the code is internally consistent and externally wrong. | E11: Released
A12: v009 | B12: 2026-09-13 10:36 | C12: Claude for Senthil/KP | D12: THIS FILE — two artifact claims closed in code. (1) WCAG AA, asserted as an NFR since 5 Sep and never audited on MeetSync: web/a11y.test.tsx now audits all five panels and the shell in every render state, inside the 100% gate. axe found zero violations even on its full ruleset; a manual read of the same markup found four real failures it cannot see, all fixed (see A11Y_Audit sheet). (2) Trial-to-paid, MRR, ARPU and logo churn had targets and no computation: Billing.revenueMetrics + operator-gated /analytics/revenue close it. Code v015 released (claude_v015_meetsync_a11y_metrics_code_20260913_1036.zip): 23 suites / 253 tests at 100% four ways, zero pragmas, tsc clean. Story position UNCHANGED (78 Done / 307 of 399) — neither item is a story, both are claims the artifacts were already making. | E12: Released
A13: v010 | B13: 2026-09-13 10:43 | C13: Claude for Senthil/KP | D13: THIS FILE — OBS-M3 CLOSED (partially, and the partially is the important word). The Store interface is now async with a real PostgresStore beside InMemoryStore, both held to one contract suite that runs every case twice against both implementations and is NOT skipped when no database is present. Verified against a live PostgreSQL 16 in this session, not written blind — an unverified SQL adapter would have repeated exactly the VER-M01 mistake this project has now made three times across products. CI provisions postgres:16 and Node was lifted 20 to 22 (Node 20 EOL Apr 2026). Code v016: 23 suites / 281 tests at 100% four ways, zero pragmas, tsc clean. Story position UNCHANGED (78 Done / 307 of 399). docs/PERSISTENCE.md states plainly what is still process-local — billing, tenant state, CRM queue, RBAC audit — and that MeetSync therefore still cannot run more than one instance. | E13: Released
A14: v011 | B14: 2026-09-13 10:56 | C14: Claude for Senthil/KP | D14: THIS FILE — SECOND DURABLE SLICE: subscriptions. Billing now sits behind a SubscriptionStore with the same two-implementation, one-contract arrangement as the account store, verified against live PostgreSQL 16. This was the recommended next slice because losing it did not merely lose history — a restart reverted every account to no_subscription, un-gating every paid feature and reporting MRR as zero. Code v017: 23 suites / 301 tests at 100% four ways, zero pragmas, tsc clean. Story position UNCHANGED (78 Done / 307 of 399). Entitlement and billing are no longer among the things two instances would disagree about; the single-instance constraint itself stands until tenant state, the CRM queue and the RBAC audit log follow. | E14: Released
... A43: v040 | B43: 2026-09-20 12:29 | C43: Claude for Senthil/KP | D43: THIS FILE — first external review absorbed. Perplexity Review V001 (16 Sep) raised PR-01…PR-14 and a S13–S20 plan of 51 stories / 248 pts. Code v045 closes S13 in full (ST-101…108) and S14 in code (ST-109…115) plus ST-141; 712 tests, 100x4, zero pragmas, three standing gates (capability→caller, route→client, document→code). All 51 new stories are in Traceability_Matrix with honest status; PR rows in Review_Findings; PD-01…PD-06 in Decisions; S13_S20_Board added; rollup extended to S20; handover items 36–43 added. Nothing removed from any sheet. | E43: Released
A44: v041 | D44: PLANNED: opens on any of PD-01/PD-02/PD-03 (pricing, intelligence vs rules engine, SMB vs enterprise) — they gate S15–S18 — or on the Zoom dev app (Handover #2), whose hold (PD-05) lifts now that S13 is closed. | E44: Planned

Sheet Sprint_Tracker_Log
A1: SPRINT TRACKER LOG — every execution event, newest last
A2: Pattern: TeleField v001 tracker. Refs = decisions/stories. Append only.
A3: ID | B3: Date/Time | C3: Sprint | D3: What happened | E3: Refs | F3: State changes | G3: Blockers | H3: Next
A4: E001 | B4: 2026-09-10 22:58 | C4: — | D4: MEETSYNC BUILD OPENED — Senthil 22:58 instruction: continue per sprint from v007 workbook, tracker + traceability to TeleField-v001 pattern, complete development with 100% automation testing. D13 (100% coverage; discovery parked, dev proceeds) applied per 20:45 portfolio-wide direction. D15 sequencing (nine concurrent builds incl. this) remains Senthil's open decision; logged per R7. | E4: D13,D15,R7 | F4: MeetSync S1 opened | G4: None | H4: S1–S8 build
A5: E002 | B5: 2026-09-10 22:58 | C5: S1 | D5: S1 FOUNDATION BUILT (TypeScript/Node/Express per v007 stack): config w/ region us|in|eu + validation; typed Store layer (in-memory, Postgres adapter point — R-M4); zoomAuth (ST-051 exchange, ST-055 rotation-persisting refresh); zoomClient 429/5xx backoff+jitter + circuit breaker w/ half-open (ST-070) + auto-refresh-once on 401 no-loop; webhooks x-zm-signature HMAC + endpoint.url_validation challenge + timestamp replay guard + dedupe ledger; lifecycle install w/ ST-056 attribution, ST-052 uninstall token WIPE + retention-scheduled purge + sweep; express /healthz /oauth/callback /webhooks/zoom /orgs/:id/status; GitHub Actions CI w/ 100%x4 threshold. | E5: ST-051,ST-052,ST-055,ST-056 | F5: 4 S1 stories Done-in-code (13 pts) | G5: Live Zoom dev app = Senthil (LC-1) | H5: E003
A6: E003 | B6: 2026-09-10 22:58 | C6: S2 | D6: S2 DONE-IN-CODE: Live notes panel core (ST-001..004) — sessions, timestamped entries, status chips, close; typed retryable errors w/ backoff hint + error metrics. ST-053 re-install restores archived account within retention (original attribution preserved). ST-054 owner/admin/member RBAC matrix enforced at API via role header; allow+deny audit-logged. | E6: ST-001..004,ST-053,ST-054 | F6: 6 stories (29 pts) Done-in-code | G6: None | H6: E004
A7: E004 | B7: 2026-09-10 22:58 | C7: S3 | D7: S3 DONE-IN-CODE: notes metrics/permissions/pause/import/notifications (ST-006..010) via FeatureEngine — shared F1–F5 engine: one-screen defaults setup, rule customisation, pause WITHOUT data loss (asserted), competitor-CSV import w/ row-level validation, per-type notification mute, day-trend metrics. Action-item extraction started: base+custom rules, speaker-owner + due-day attribution, preview/test mode (ST-011..014). ST-085 coverage gate SUPERSEDED by D13: threshold set to 100x4, not 70. ST-005 (real Zoom panel surface) code-complete pending live. | E7: ST-005..014,ST-085 | F7: 10 Done-in-code, ST-005 pending live | G7: Zoom panel surface = LC-1 | H7: E005
A8: E005 | B8: 2026-09-10 22:58 | C8: S4 | D8: S4 DONE-IN-CODE: extraction metrics/permissions/pause/import/notifications (ST-016..020). ST-071 activation funnel (install->setup->aha->habit) + /analytics/funnel dashboard; ST-072 error tracking w/ release tags + windowed spike alert. ST-086 E2E smoke suite (install->setup->import->billing->onboarding-aha->deauth-wipe) wired into CI and deploy gate. ST-015 pending live surface. MVP loop usable end-to-end in tests — S4 exit met in-code. | E8: ST-015..020,ST-071,ST-072,ST-086 | F8: 8 Done-in-code, 1 pending live | G8: None | H8: E006
A9: E006 | B9: 2026-09-10 22:58 | C9: S5 | D9: S5 DONE-IN-CODE: CRM field writeback — CrmAdapter interface + HubSpot/Salesforce/Zoho sandbox adapters (LC-6 class), field-level mapping w/ overwrite=false respecting existing CRM values, retrying writeback queue (transient-fail recovery + terminal fail audit + error metric), idempotent re-drain (ST-021..024, 026..030). Onboarding: 4-step first-run checklist to aha <1 day + teaching empty states (ST-078, ST-079). ST-025 pending live. | E9: ST-021..030,ST-078,ST-079 | F9: 11 Done-in-code, 1 pending live | G9: Live CRM sandboxes for LC-6 = Senthil | H9: E007
A10: E007 | B10: 2026-09-10 22:58 | C10: S6 | D10: S6 DONE-IN-CODE: Deal-risk signals — competitor/pricing/sentiment detectors + no-next-step inference, sensitivity-weighted (low/med/high w/ fallback), 0–100 capped score (ST-031..034, 036..040). Billing: 14-day no-card trial w/ countdown banner (ST-057), mid-cycle proration up+down (ST-058), marketplace-vs-Stripe routing (ST-059 — live marketplace verification pending). S6 exit (charge test customer, up/downgrade) met in-code. | E10: ST-031..040,ST-057..059 | F10: 12 Done-in-code, ST-035+059 pending live | G10: Marketplace billing verification = LC-10 | H10: E008
A11: E008 | B11: 2026-09-10 22:58 | C11: S7 | D11: S7 CODEABLE SCOPE DONE-IN-CODE: dunning 7-day grace + 3 emails + read-only (ST-060), plan-limit prompts 80/100% (ST-061), GST/VAT invoices (ST-062), cancellation save-offer + exit survey (ST-063), least-privilege scope map doc (ST-064). Sprint exit (3+ design partners weekly, NPS>30) needs humans — S7 sprint stays open on beta evidence. | E11: ST-060..064 | F11: 5 stories Done-in-code | G11: Design partners = Senthil | H11: E009
A12: E009 | B12: 2026-09-10 22:58 | C12: S8 | D12: S8 DONE-IN-CODE: Indic language pack — Devanagari/Tamil script detection, pack-scoped segmentation w/ clear not-enabled errors, Levenshtein WER benchmark harness for LC-7 (ST-041..044, 046..050). Security: data-flow+retention doc ST-065, admin audit ST-067, backoff+breaker ST-070. Analytics suite ST-073..077 (heatmap, weekly email, health score, CSV export, configurable thresholds). ST-087 p95 budgets + k6 thresholds. ST-082 post-aha review ask (S11 story, shipped early). Pending live: ST-045 surface, ST-088 5x load run (harness written), ST-092 blue/green (workflow written). ST-066 vault/encryption = live infra. | E12: ST-041..050,ST-065..077,ST-082,ST-087..092 | F12: 18 Done-in-code, 3 pending live | G12: Staging infra = Senthil | H12: E010
A13: E010 | B13: 2026-09-10 22:58 | C13: — | D13: D13 TEST GATE MET — 18 Jest suites / 139 automated tests (unit + supertest API integration + E2E smoke; negative paths: bad/short/stale signatures, replay, malformed JSON, OAuth 400/502/500, refresh-loop guard, breaker open/half-open, ragged CSV, seat limits, dunning day-by-day). Coverage 100% statements / 100% branches / 100% functions / 100% lines, ZERO istanbul-ignore pragmas; jest coverageThreshold 100x4 fails any future commit below. Rollup 74/100 stories Done-in-code (292/399 pts). Drafted: listing copy A/B (ST-093), runbook (ST-098). Next sprint S9 (review prep) — mostly live/human items. | E13: D13 | F13: Evidence in Traceability col K | G13: S9 items need Senthil (see RAID) | H13: v009
A14: E011 | B14: 2026-09-11 08:42 | C14: — | D14: TRACKER EXTRACTED TO STANDALONE FILE — Senthil 08:42: create sprint tracker + traceability for MeetSync as a separate document to the TeleField-v001 file pattern (23:48 feedback: v008 embedded the sheets in the product workbook instead of releasing a companion file). This file is now the live tracker; the v008 product workbook remains backlog source of truth; v009 re-baseline of the product workbook stays planned. House style aligned to template (navy title bar, light-blue header rows). | E14: D15 | F14: Tracker lives here from E012 on | G14: None | H14: S9 on "continue"
... A100: E097 | B100: 2026-09-20 12:29 | C100: Handover | D100: WHAT CHANGED FOR SENTHIL. Three P1s are decisions, not credentials: PD-01 (price), PD-02 (build vs rules engine), PD-06 (demand tests). The Zoom dev app (Handover #2) is the right first move again because the PD-05 hold lifts with S13 closed. Two new deployment values (MEETSYNC_MAIL_*, MEETSYNC_CORS_ORIGINS). S15–S17 (110 pts) cannot be sequenced until PD-02; S18 (26 pts) until PD-01. Nothing in this sitting made the product demand-tested: 0 installs is still 0 installs. | E100: Senthil_Handover #36–43, Decisions PD-01…06 | F100: No story impact — planning | G100: PD-01, PD-02, PD-06 | H100: v041 on a PD decision or the Zoom app

Sheet Decisions
A1: DECISIONS (tracker scope)
A2: Portfolio decisions D13/D15 restated for this product; product-local decisions D-M*.
A3: ID | B3: Decision | C3: Rationale | D3: Decided by | E3: Status
A4: D13 | B4: (Portfolio-wide) Discovery interviews parked; dev proceeds with 100% automation test coverage on all code. | C4: Senthil 10 Sep 20:45; applied to MeetSync per 22:58 instruction. | D4: Senthil | E4: LOCKED
A5: D15 | B5: MeetSync (wave-3, Zoom) build opened 10 Sep 22:58 while rank-1 gate unmet; nine concurrent builds now exist. MODE TO RATIFY: (a) parallel builds — supersedes serial rule, or (b) order swap. | C5: R7/R1-class rules require logging any re-ordering; this entry is the log for MeetSync. | D5: Senthil (mode ratification pending) | E5: OPEN — pick (a) or (b)
A6: D-M1 | B6: Stack = TypeScript/Node/Express per v007 ReadMe stack assumption; persistence behind typed Store interface with in-memory impl (no Postgres in sandbox), Postgres adapter at deploy. | C6: Follows workbook; matches accepted precedent across the eight sibling builds. | D6: Claude — flagged | E6: OPEN for ratification
A7: D-M2 | B7: ST-085 (>=70% coverage gate) superseded: gate enforced at 100% x4 with zero pragmas. | C7: D13 supersedes the workbook's pre-D13 quality bar. | D7: Senthil (via D13) | E7: LOCKED
A8: D-M3 | B8: Zoom webhook contract implemented to published pattern (x-zm-signature v0 HMAC + endpoint.url_validation challenge); real payload shapes verified at first live dev-app event. | C8: Verification isolated in src/webhooks.ts — a format change is one-module (R-M5). | D8: Claude — flagged | E8: OPEN — verify at LC-1
A9: PD-01 | B9: Pricing model and number (PR-05, ST-136). Code bills per seat; the pricing page reads as flat — 50x apart at Team. Recommendation on file: per-seat, $12–$18/seat/month, 5-seat minimum. | C9: HubSpot listing rules require the listed price to match the website; the claim gate (test/claims.test.ts) refuses PRICING_PAGE.md without its DECISION PENDING banner until resolved. | D9: Senthil | E9: OPEN — blocks S18 and the listing
A10: PD-02 | B10: Build the intelligence (S15+S16, 71 pts) or reposition as a deterministic rules engine (PR-02). | C10: There is no model, ASR or NLP in the product; the listing copy is HELD (docs/LISTING_COPY.md banner) until this is decided. A rules engine is a real, smaller business; the model path brings eval discipline, cost caps and a trust surface (ST-116…128). | D10: Senthil | E10: OPEN — gates 71 of 248 pts
A11: PD-03 | B11: Enterprise-first or SMB-first (S19). | C11: SMB-first: launch after S18, S19 demand-driven, SOC 2 clock starts on a named deal. Enterprise-first: S19 blocks launch, SOC 2 Type II $35K–$120K over 6–18 months starts now. Recommendation: SMB-first. | D11: Senthil | E11: OPEN — decides whether S19 blocks S20
A12: PD-04 | B12: Keep or cut F4 deal risk (PR-11, ST-124). | C12: 13 English keywords, no evidence span or confidence, cannot fire on Hindi/Tamil. Rebuild inside ST-117 evidence-bearing extraction, or remove from product and pricing table. It is currently a Team-tier differentiator. | D12: Senthil | E12: OPEN — scope of S15/S16 and the pricing matrix
A13: PD-05 | B13: Hold Zoom Marketplace app creation until S13 closes (PR-01, Handover #2). | C13: Installing a takeover-vulnerable app against a real Zoom account converted a fixable defect into a live incident. S13 is CLOSED in code at v045 (ST-101…108, pinned by test/s13.test.ts), so the hold LIFTS: Handover #2 is the right first move again. | D13: Senthil (hold recommended by Claude; lifted by v045) | E13: RESOLVED BY v045 — hold lifted
A14: PD-06 | B14: Run the three demand tests before more feature code (review §4.6): RevOps field test n=5; Hinglish head-to-head n=10 calls; willingness-to-switch n=10 teams. | C14: Each has a kill signal. Any one failing changes the plan. Days, not sprints; none is codeable. | D14: Senthil | E14: OPEN — validates or invalidates the wedge

Sheet S9_Prep_Board
A1: S9 BOARD — Marketplace review prep — exit: review submission accepted into queue
A2: Backlog stories in S9 + live items carried from S1–S8. Edit Status/Notes (yellow).
A3: ID | B3: Item | C3: Story ref | D3: Points | E3: Owner | F3: Status | G3: Notes / Evidence
A4: S9-01 | B4: Zoom dev app created, scopes per docs/SECURITY_SCOPES.md; live install of S1 code | C4: ST-051 live | D4: 3 | E4: Senthil + Claude | F4: To do | G4: LC-1. Evidence: install screenshot + account id + telemetry row.
A5: S9-02 | B5: Verify real webhook payload shapes vs D-M3 assumption | C5: — | D5: 1 | E5: Senthil + Claude | F5: To do | G5: First live event through src/webhooks.ts; adjust one module if format differs (R-M5).
A6: S9-03 | B6: CRM writeback live runs vs HubSpot/SFDC/Zoho sandboxes | C6: LC-6 | D6: 3 | E6: Senthil + Claude | F6: To do | G6: Adapters coded+tested; needs sandbox credentials.
A7: S9-04 | B7: Delete-my-data self-serve endpoint on retention sweep path | C7: ST-069 | D7: 5 | E7: Claude | F7: Done-in-code | G7: Shipped 08:47 — see Traceability ST-069 / tracker E012. Evidence: s9.test.ts.
A8: S9-05 | B8: Pen-test / platform security evidence archived | C8: ST-068 | D8: 5 | E8: Senthil | F8: To do | G8: LC-2 pack: TDD doc, data-flow (done), pen-test summary.
A9: S9-06 | B9: WCAG AA pass on primary flows | C9: ST-089 | D9: 3 | E9: Senthil + Claude | F9: To do | G9: Needs rendered UI on live surface.
A10: S9-07 | B10: Backup+restore drill; chaos test (platform outage degrades gracefully) | C10: ST-090,ST-091 | D10: 5 | E10: Senthil + Claude | F10: To do | G10: Breaker + typed errors coded; platformHealth surface added (ST-091 code side done); drills need staging.
A11: S9-08 | B11: k6 5x load run + blue/green live verification | C11: ST-088,ST-092 | D11: 3 | E11: Senthil + Claude | F11: To do | G11: Harness + workflow shipped in repo; needs staging slots.
A12: S9-09 | B12: Listing copy variant pick (A/B drafted) + 5 screenshots + 2-min video | C12: ST-093,ST-094 | D12: 5 | E12: Senthil | F12: To do | G12: Copy in docs/LISTING_COPY.md; assets need live UI.
A13: S9-10 | B13: Encryption-at-rest/vault verification on deploy infra | C13: ST-066 | D13: 2 | E13: Senthil + Claude | F13: To do | G13: Config/secrets validation coded; vault = infra.

Sheet Traceability_Matrix
A1: TRACEABILITY MATRIX — 151 stories: module -> epic -> story -> screen -> verification -> status (ST-001…100 from v008 workbook; ST-101…151 from Perplexity Review V001, added v040)
A2: Source: v008 product workbook Full_Backlog (single source of truth). Done rows carry code/test evidence per D13. Status: Done-in-code / Code-complete (pending live) / Drafted / Backlog. | L2: Added v016 per Handover #20 and BROUGHT CURRENT at v032 (13 Sep 20:36). It had been eleven sittings stale: every "column L moves on your next pass" note went unactioned, so the column described the product as it was at 11:32 while the code moved to v038.
A3: Story ID | B3: Epic | C3: Module / feature | D3: Story | E3: Points | F3: Priority | G3: Sprint | H3: Primary screen | I3: Verification | J3: Status | K3: Evidence | L3: Customer-reachable (v021) | M3: Reached by / what is missing
A4: ST-001 | B4: F1 | C4: Live notes panel | D4: As a Sales leader, I can set up Live notes panel with sensible defaults in one screen | E4: 5 | F4: P0 | G4: S2 | H4: SCR-3 Live notes workspace | I4: E2E test + demo | J4: Done-in-code | K4: FeatureEngine.setupWithDefaults one-screen + overrides; API test. | L4: REACHABLE | M4: POST /features/:key/setup
A5: ST-002 | B5: F1 | C5: Live notes panel | D5: As a Sales leader, the Live notes panel happy path completes without documentation | E5: 8 | F5: P0 | G5: S2 | H5: SCR-3 Live notes workspace | I5: E2E test + demo | J5: Done-in-code | K5: Core happy path: notes.ts sessions/entries/chips. Module suite + E2E smoke. | L5: REACHABLE | M5: feature route: notes session+entries / actions extract / crm writeback / deal-risk analyse / indic segment
A6: ST-003 | B6: F1 | C6: Live notes panel | D6: As a CS lead, I can customise Live notes panel rules/conditions for my workflow | E6: 5 | F6: P1 | G6: S2 | H6: SCR-3 Live notes workspace | I6: Integration test + manual QA | J6: Done-in-code | K6: addRule customisation + role guard; notes.ts sessions/entries/chips rule tests. | L6: REACHABLE | M6: POST /features/:key/rules (and POST /features/actions/rules for extraction verbs)
A7: ST-004 | B7: F1 | C7: Live notes panel | D7: As a user, Live notes panel shows clear errors and retry paths on platform API failures | E7: 3 | F7: P0 | G7: S2 | H7: SCR-3 Live notes workspace | I7: E2E test + demo | J7: Done-in-code | K7: Typed error paths w/ retry hints (403/409/422/500 mapped); error metric recorded. | L7: REACHABLE | M7: shared error mapper on every feature route: 403/409/422/503 with retry hints
A8: ST-005 | B8: F1 | C8: Live notes panel | D8: As a IT admin, Live notes panel works on the Zoom App in-meeting panel + web dashboard surface end-to-end | E8: 5 | F8: P0 | G8: S3 | H8: SCR-3 Live notes workspace | I8: E2E test + demo | J8: Code-complete (pending live) | K8: UI BUILT+TESTED: web/NotesPanel.tsx in App shell serving in-meeting panel AND web dashboard from one codebase; Zoom Apps SDK behind ZoomSdk boundary (MockZoomSdk in RTL tests, 100x4). Domain logic done since S1-S8. ONLY the live dev-app SDK handshake remains (Handover #2). | L8: PENDING LIVE | M8: needs the Zoom dev app; panel components exist and are RTL-tested (Handover #2)
A9: ST-006 | B9: F1 | C9: Live notes panel | D9: As a CS lead, I can see Live notes panel performance metrics and trends | E9: 3 | F9: P1 | G9: S3 | H9: SCR-3 Live notes workspace | I9: Integration test + manual QA | J9: Done-in-code | K9: engine.metrics events/errors/errorRate + sorted day trend; /features/:key/metrics. | L9: REACHABLE | M9: GET /features/:key/metrics
A10: ST-007 | B10: F1 | C10: Live notes panel | D10: As a user, Live notes panel respects role permissions and audit logging | E10: 3 | F10: P1 | G10: S3 | H10: SCR-3 Live notes workspace | I10: Integration test + manual QA | J10: Done-in-code | K10: RBAC matrix enforced + audit rows (allow and deny). | L10: REACHABLE | M10: RBAC enforced on every route; audit readable at GET /orgs/:id/audit-log
A11: ST-008 | B11: F1 | C11: Live notes panel | D11: As a Sales leader, I can pause/disable Live notes panel without data loss | E11: 2 | F11: P2 | G11: S3 | H11: SCR-3 Live notes workspace | I11: Manual QA | J11: Done-in-code | K11: setEnabled pause keeps records (asserted); resume restores. | L11: REACHABLE | M11: POST /features/:key/pause — data retention on pause is tested
A12: ST-009 | B12: F1 | C12: Live notes panel | D12: As a CS lead, I can import/migrate existing data into Live notes panel (CSV + competitor importer) | E12: 5 | F12: P1 | G12: S3 | H12: SCR-3 Live notes workspace | I12: Integration test + manual QA | J12: Done-in-code | K12: importCsv competitor-format, header/ragged-row validation w/ row numbers. | L12: REACHABLE | M12: POST /features/:key/import (RFC-4180)
A13: ST-010 | B13: F1 | C13: Live notes panel | D13: As a user, I get notifications (in-app + email) for key Live notes panel events with per-type mute | E13: 3 | F13: P2 | G13: S3 | H13: SCR-3 Live notes workspace | I13: Manual QA | J13: Done-in-code | K13: notify in-app+email; per-type mute/unmute. | L13: PARTIAL | M13: in-app half reachable (GET /features/:key/notifications, POST /mute). v021 stopped notify() recording an email row it had never sent; the email half still has no sender
A14: ST-011 | B14: F2 | C14: Action-item extraction | D14: As a Sales leader, I can set up Action-item extraction with sensible defaults in one screen | E14: 5 | F14: P0 | G14: S3 | H14: SCR-4 Extraction builder | I14: E2E test + demo | J14: Done-in-code | K14: FeatureEngine.setupWithDefaults one-screen + overrides; API test. | L14: REACHABLE | M14: POST /features/:key/setup
A15: ST-012 | B15: F2 | C15: Action-item extraction | D15: As a Sales leader, the Action-item extraction happy path completes without documentation | E15: 8 | F15: P0 | G15: S3 | H15: SCR-4 Extraction builder | I15: E2E test + demo | J15: Done-in-code | K15: Core happy path: actions.ts rules+preview mode. Module suite + E2E smoke. | L15: REACHABLE | M15: feature route: notes session+entries / actions extract / crm writeback / deal-risk analyse / indic segment
... A68: ST-065 | B68: E6 | C68: Security & compliance | D68: Data-flow diagram + retention policy published | E68: 3 | F68: P0 | G68: S8 | H68: SCR-6 Settings & team | I68: E2E test + demo | J68: Done-in-code | K68: docs/DATA_FLOW.md — flow + retention/purge/restore, region config. | L68: REACHABLE | M68: docs/DATA_FLOW.md — purge scope and scheduling both corrected (M-F03, GAP-2)
A69: ST-066 | B69: E6 | C69: Security & compliance | D69: Encryption at rest + in transit verified; secrets in vault | E69: 5 | F69: P0 | G69: S8 | H69: SCR-6 Settings & team | I69: E2E test + demo | J69: Backlog | L69: REACHABLE | M69: v031: AES-256-GCM at rest, key outside the database, rotation via MEETSYNC_TOKEN_KEY_PREVIOUS
A70: ST-067 | B70: E6 | C70: Security & compliance | D70: Audit log for admin-sensitive actions | E70: 5 | F70: P1 | G70: S8 | H70: SCR-6 Settings & team | I70: Integration test + manual QA | J70: Done-in-code | K70: Rbac.authorize writes audit rows for admin-sensitive actions incl. denials. | L70: REACHABLE | M70: GET /orgs/:id/audit-log, gated by audit.read — the read path did not exist before v020
A71: ST-068 | B71: E6 | C71: Security & compliance | D71: Pen-test (or platform-required evidence) completed and archived | E71: 8 | F71: P0 | G71: S9 | H71: SCR-6 Settings & team | I71: E2E test + demo | J71: Backlog | L71: NOT REACHABLE | M71: backlog: needs a pen-test vendor (Handover)
A72: ST-069 | B72: E6 | C72: Security & compliance | D72: Data export + delete-my-data self-serve | E72: 5 | F72: P0 | G72: S9 | H72: SCR-6 Settings & team | I72: E2E test + demo | J72: Done-in-code | K72: POST /orgs/:id/delete-my-data — owner-only via RBAC (deny audit-logged), confirm=DELETE guard (422), immediate token wipe, deletionScheduledAt=now so next retentionSweep purges (no 30-day wait); preserves original uninstall facts when already uninstalled. lifecycle.ts deleteMyData + s9.test.ts (8 tests). | L72: REACHABLE | M72: v028 added GET /orgs/:id/export, audit-logged and excluding credentials; delete-my-data already shipped
A73: ST-070 | B73: E6 | C73: Security & compliance | D73: Rate-limit backoff + circuit breaker on platform APIs | E73: 5 | F73: P0 | G73: S8 | H73: SCR-6 Settings & team | I73: E2E test + demo | J73: Done-in-code | K73: src/zoomClient.ts exp backoff + jitter on 429/5xx, circuit breaker w/ half-open probe; 8 tests. | L73: REACHABLE | M73: v029: ZoomClient.download carries the transcript fetch through the shared backoff and breaker
A74: ST-071 | B74: E7 | C74: Telemetry & analytics | D74: Activation funnel events (install->setup->aha->habit) in one dashboard | E74: 5 | F74: P0 | G74: S4 | H74: SCR-8 Analytics | I74: E2E test + demo | J74: Done-in-code | K74: Telemetry funnel install->setup->aha->habit; /analytics/funnel; aha wired from onboarding. | L74: REACHABLE | M74: GET /analytics/funnel (operator token)
A75: ST-072 | B75: E7 | C75: Telemetry & analytics | D75: Error tracking with release tagging; alert on error-rate spike | E75: 3 | F75: P0 | G75: S4 | H75: SCR-8 Analytics | I75: E2E test + demo | J75: Done-in-code | K75: trackError with release tag; errorSpike windowed alert vs configurable threshold. | L75: REACHABLE | M75: v040: alerts are POSTed to an operator-supplied https webhook (MEETSYNC_ALERT_WEBHOOK). At most once, fire-and-forget, not a paging system — limits documented. Alert bodies carry no tenant identity (OpsAlert invariant, pinned by test in v041). Without a URL they remain readable at /analytics/ops
A76: ST-073 | B76: E7 | C76: Telemetry & analytics | D76: Feature-usage heatmap for roadmap decisions | E76: 3 | F76: P2 | G76: S8 | H76: SCR-8 Analytics | I76: Manual QA | J76: Done-in-code | K76: heatmap() hits sorted desc. | L76: REACHABLE | M76: v027: every feature route feeds the heatmap; readable at GET /analytics/ops
A77: ST-074 | B77: E7 | C77: Telemetry & analytics | D77: Weekly automated metrics email to team | E77: 2 | F77: P2 | G77: S8 | H77: SCR-8 Analytics | I77: Manual QA | J77: Done-in-code | K77: weeklyEmail(): funnel + top features + 7d errors; empty-state covered. | L77: PARTIAL | M77: the weekly digest is computed and readable at GET /analytics/ops. The story says EMAIL and no mail sender exists, so the automated part is not done
A78: ST-075 | B78: E7 | C78: Telemetry & analytics | D78: Health score computed per account (usage+billing+support) | E78: 5 | F78: P1 | G78: S8 | H78: SCR-8 Analytics | I78: Integration test + manual QA | J78: Done-in-code | K78: healthScore usage+billing+support blend, capped/floored; 3 boundary tests. | L78: REACHABLE | M78: v042/v043: computed per account from MEASURED inputs — active days from recorded activity, billing from the entitlement. Open tickets have no data source and are excluded; a pre-trial account has no billing signal yet and is excluded from at-risk. maxScore states which components counted. GET /orgs/:id/health, GET /analytics/at-risk
A79: ST-076 | B79: E7 | C79: Telemetry & analytics | D79: Metrics export to CSV/warehouse for founder analysis | E79: 3 | F79: P2 | G79: S8 | H79: SCR-8 Analytics | I79: Manual QA | J79: Done-in-code | K79: /analytics/export.csv one row per account with stage flags. | L79: REACHABLE | M79: GET /analytics/export.csv (operator token), RFC-4180 quoted
A80: ST-077 | B80: E7 | C80: Telemetry & analytics | D80: Alert thresholds configurable (activation drop, error spike, churn signal) | E80: 3 | F80: P2 | G80: S8 | H80: SCR-8 Analytics | I80: Manual QA | J80: Done-in-code | K80: setThresholds partial-merge; churnAlert respects configured score. | L80: REACHABLE | M80: v027: POST /analytics/thresholds, validated
A81: ST-078 | B81: E8 | C81: Onboarding & support | D81: First-run checklist reaches aha-moment in <1 day | E81: 5 | F81: P0 | G81: S5 | H81: SCR-1 / SCR-9 Help | I81: E2E test + demo | J81: Done-in-code | K81: Onboarding 4-step checklist -> aha; withinDay <=24h asserted both sides. | L81: REACHABLE | M81: POST /onboarding/:id/start and /complete; aha feeds the funnel
A82: ST-079 | B82: E8 | C82: Onboarding & support | D82: Empty states teach next action on every screen | E82: 3 | F82: P1 | G82: S5 | H82: SCR-1 / SCR-9 Help | I82: Integration test + manual QA | J82: Done-in-code | K82: EMPTY_STATES teach next action on 5 screens + fallback. | L82: REACHABLE | M82: v022: one source in src/emptyStates.ts, imported by the API and all five panels; tests assert the constant
A83: ST-080 | B83: E8 | C83: Onboarding & support | D83: Help center with 15 launch articles + search | E83: 5 | F83: P1 | G83: S10 | H83: SCR-1 / SCR-9 Help | I83: Integration test + manual QA | J83: Done-in-code | K83: 15 launch articles (getting-started -> troubleshooting) + ranked keyword search (title 3 / keyword 2 / body 1, deterministic tie-break) at /help/*; same content source for hosted help site and in-app panel. helpcenter.ts + s10.test.ts. Hosting/publish at go-live. | L83: REACHABLE | M83: GET /help/articles, /help/articles/:id, /help/search
A84: ST-081 | B84: E8 | C84: Onboarding & support | D84: In-app chat with <4 business-hr first response | E84: 3 | F84: P0 | G84: S10 | H84: SCR-1 / SCR-9 Help | I84: E2E test + demo | J84: Backlog | L84: NOT REACHABLE | M84: backlog: no chat vendor decision
A85: ST-082 | B85: E8 | C85: Onboarding & support | D85: In-app review ask after aha-moment (marketplace rating engine) | E85: 3 | F85: P1 | G85: S11 | H85: SCR-1 / SCR-9 Help | I85: Integration test + manual QA | J85: Done-in-code | K85: maybeAskReview: only after aha, exactly once; wired into /onboarding complete. | L85: REACHABLE | M85: reviewAsk returned by POST /onboarding/:id/complete, once, after aha
A86: ST-083 | B86: E8 | C86: Onboarding & support | D86: Demo video (2 min) + interactive sandbox/demo data mode | E86: 5 | F86: P1 | G86: S10 | H86: SCR-1 / SCR-9 Help | I86: Integration test + manual QA | J86: Code-complete (pending live) | K86: Interactive demo/sandbox HALF SHIPPED: POST /orgs/:id/demo-mode (admin+) seeds notes session, 2 extracted actions, 2 completed sandbox writebacks (demo.ts). 2-min video = live recording (Senthil). | L86: PARTIAL | M86: demo-data mode is reachable at POST /orgs/:id/demo-mode and seeds an isolated demo- workspace; the 2-minute video is not captured
A87: ST-084 | B87: E8 | C87: Onboarding & support | D87: Status page + incident comms template | E87: 2 | F87: P2 | G87: S10 | H87: SCR-1 / SCR-9 Help | I87: Manual QA | J87: Done-in-code | K87: Public /status (JSON) + /status.html: api + zoomPlatform component health (breaker-driven ok/degraded/probing), uptime; incident comms template docs/INCIDENT_COMMS.md. statuspage.ts + tests. | L87: REACHABLE | M87: GET /status and /status.html, public by design
A88: ST-085 | B88: EQ | C88: Quality engineering | D88: Unit+integration test coverage gate ≥70% on core modules | E88: 5 | F88: P0 | G88: S3 | H88: — | I88: E2E test + demo | J88: Done-in-code | K88: SUPERSEDED by D13: gate is 100%x4 (jest coverageThreshold), not >=70%. 18 suites/139 tests, zero pragmas. | L88: REACHABLE | M88: CI runs the 100/100/100/100 gate on every push
A89: ST-086 | B89: EQ | C89: Quality engineering | D89: E2E smoke suite runs on every deploy | E89: 5 | F89: P0 | G89: S4 | H89: — | I89: E2E test + demo | J89: Done-in-code | K89: E2E smoke in app.test.ts runs in CI + deploy workflow before slot swap. | L89: REACHABLE | M89: E2E smoke in the API suite; CI provisions postgres:16
A90: ST-087 | B90: EQ | C90: Quality engineering | D90: p95 latency budgets defined and monitored per surface | E90: 3 | F90: P0 | G90: S8 | H90: — | I90: E2E test + demo | J90: Done-in-code | K90: docs/PERF_BUDGETS.md + k6 thresholds p95<500ms. | L90: REACHABLE | M90: v037/v038: p95 per route pattern against the published budgets, breach alert in the digest. Server handling time only — the 2s UI budget is still unmeasured
A91: ST-088 | B91: EQ | C91: Quality engineering | D91: Load test at 5x expected launch traffic | E91: 5 | F91: P1 | G91: S8 | H91: — | I91: Integration test + manual QA | J91: Code-complete (pending live) | K91: load/k6-smoke.js 5x-launch scenario written; live run needs staging infra (Senthil). | L91: PENDING LIVE | M91: k6 harness exists; never run against a deployment
A92: ST-089 | B92: EQ | C92: Quality engineering | D92: Accessibility WCAG AA pass on primary flows | E92: 3 | F92: P1 | G92: S9 | H92: — | I92: Integration test + manual QA | J92: Backlog | L92: PARTIAL | M92: automated WCAG AA checks pass on every build (v015); contrast, focus, zoom and real screen-reader behaviour need a manual pass
A93: ST-090 | B93: EQ | C93: Quality engineering | D93: Backup + restore drill executed | E93: 3 | F93: P1 | G93: S9 | H93: — | I93: Integration test + manual QA | J93: Backlog | L93: REACHABLE | M93: v030: restore drill takes a snapshot, restores into an empty set and compares checksums; 500 on divergence
A94: ST-091 | B94: EQ | C94: Quality engineering | D94: Chaos test: platform API outage degrades gracefully with user comms | E94: 3 | F94: P2 | G94: S9 | H94: — | I94: Manual QA | J94: Code-complete (pending live) | K94: Degradation OBSERVABLE in code: ZoomClient.platformHealth() ok/degraded/probing from breaker state, surfaced on /orgs/:id/status without erroring; fast-fail asserted (CircuitOpenError, no hammering). Live platform-outage drill on staging still owed (S9-07). | L94: REACHABLE | M94: platformHealth surfaces on /orgs/:id/status and /status; degradation is visible rather than erroring
A95: ST-092 | B95: EQ | C95: Quality engineering | D95: Zero-downtime deploy verified (blue/green or rolling) | E95: 3 | F95: P2 | G95: S8 | H95: — | I95: Manual QA | J95: Code-complete (pending live) | K95: .github/workflows/deploy.yml blue/green slot swap + health gate; live slots need infra. | L95: PENDING LIVE | M95: deploy workflow exists; never executed
A96: ST-093 | B96: EL | C96: Listing & GTM | D96: Marketplace listing copy A + B variants drafted and reviewed | E96: 3 | F96: P0 | G96: S9 | H96: — | I96: E2E test + demo | J96: Drafted | K96: docs/LISTING_COPY.md variants A (CRM-hygiene) + B (rep-time) — Senthil review to pick. | L96: PARTIAL | M96: A/B copy drafted; awaiting your pick
A97: ST-094 | B97: EL | C97: Listing & GTM | D97: 5 screenshots + 2-min demo video meet platform asset specs | E97: 5 | F97: P0 | G97: S9 | H97: — | I97: E2E test + demo | J97: Backlog | L97: NOT REACHABLE | M97: backlog: no screenshots or video captured
A98: ST-095 | B98: EL | C98: Listing & GTM | D98: Pricing page/plan matrix published with FAQ | E98: 3 | F98: P0 | G98: S10 | H98: — | I98: E2E test + demo | J98: Code-complete (pending live) | K98: /pricing endpoint serves THE SAME PLANS object billing enforces (drift impossible); full matrix + FAQ draft docs/PRICING_PAGE.md. Marketing-site publish = Senthil. | L98: REACHABLE | M98: GET /pricing, served from the same PLANS the billing engine enforces
A99: ST-096 | B99: EL | C99: Listing & GTM | D99: Security/trust page (data handling, subprocessors) live | E99: 3 | F99: P0 | G99: S10 | H99: — | I99: E2E test + demo | J99: Code-complete (pending live) | K99: Trust page drafted: data handling (webhook guards, field-level audit, wipe/purge/delete-my-data), scope map link, subprocessor list, regional deployment. docs/TRUST_PAGE.md. Publish = Senthil. | L99: REACHABLE | M99: v038: served at GET /trust from the same config the product enforces
A100: ST-097 | B100: EL | C100: Listing & GTM | D100: Submission dry-run against platform checklist by second reviewer | E100: 3 | F100: P0 | G100: S10 | H100: — | I100: E2E test + demo | J100: Backlog | L100: NOT REACHABLE | M100: backlog: needs a second reviewer (Handover)
A101: ST-098 | B101: EL | C101: Listing & GTM | D101: Launch-day runbook: monitoring, rollback, comms tree | E101: 3 | F101: P1 | G101: S11 | H101: — | I101: Integration test + manual QA | J101: Done-in-code | K101: docs/RUNBOOK.md v1.0 FINAL: monitoring table (healthz/status/errorSpike/funnel/webhook/billing), <2-min blue/green rollback + lossless-by-design properties (replay-guard, dedupe, queued writebacks), Zoom-outage no-rollback path, comms tree, T-1d..T+7d sequence. Live drills [LIVE]-tagged. | L101: REACHABLE | M101: docs/RUNBOOK.md, extended with the retention-sweep and startup procedures
A102: ST-099 | B102: EL | C102: Listing & GTM | D102: Post-launch listing SEO iteration 1 from search-term data | E102: 2 | F102: P2 | G102: S12 | H102: — | I102: Manual QA | J102: Backlog | K102: Story stays Backlog HONESTLY (post-launch iteration from real search data). Groundwork SHIPPED: help-search term capture (normalized, ranked, alphabetical tie-break) at /analytics/search-terms — data available from day 1. telemetry.ts + s10.test.ts. | L102: PARTIAL | M102: search-term capture and GET /analytics/search-terms ship; the iteration needs post-listing data
A103: ST-100 | B103: EL | C103: Listing & GTM | D103: First 10 design-partner reviews scheduled | E103: 2 | F103: P1 | G103: S11 | H103: — | I103: Integration test + manual QA | J103: Backlog | L103: NOT REACHABLE | M103: backlog: design-partner outreach is yours to send
A104: ST-101 | B104: S13 | C104: Identity | D104: Derive tenant identity from Zoom, not the caller (PR-01) | E104: 8 | F104: P0 | G104: S13 | H104: OAuth callback | I104: Regression test | J104: Done-in-code | K104: src/identity.ts fetchZoomIdentity + assertTenantMatches; app.ts callback; installAccount re-checks. Pinned: s13.test.ts "refuses a state whose account differs…" (403, audit row, no account row, no session) + "cannot repoint a live workspace"; identity.test.ts. | L104: REACHABLE | M104: GET /oauth/callback — tenant = Zoom /users/me account_id; query account_id is a hint
A105: ST-102 | B105: S13 | C105: Identity | D105: Real user identity in the session (PR-08) | E105: 5 | F105: P0 | G105: S13 | H105: OAuth callback / GET /session/me | I105: Regression test | J105: Done-in-code | K105: Session carries Zoom user id, email, role (owner/admin/member from role_id/role_name); owner@<account> synthesis deleted; accounts.installed_by_* + contact_email columns. Pinned: s13.test.ts "mints owner/admin/member from Zoom's role, and two users produce two audit identities". | L105: REACHABLE | M105: GET /session/me; every audit row names a Zoom user
A106: ST-103 | B106: S13 | C106: Sessions | D106: Session lifecycle: revocation, 60-min TTL, secure delivery (PR-10) | E106: 5 | F106: P0 | G106: S13 | H106: POST /session/refresh|revoke|revoke-all | I106: Regression test | J106: Done-in-code | K106: auth.ts SessionManager (jti, deny list, per-account watermark); sessionStore.ts + PostgresSessionStore (contract suite x2); HttpOnly/Secure/SameSite=None cookie on install; uninstall + delete-my-data revoke all; App.tsx refresh timer. Pinned: s13.test.ts ST-103 block; storeContract SessionStore. | L106: REACHABLE | M106: POST /session/refresh, /session/revoke, /session/revoke-all; cookie ms_session
A107: ST-104 | B107: S13 | C107: HTTP hardening | D107: Security headers, CORS allowlist, body limit, rate limits (PR-10) | E107: 3 | F107: P0 | G107: S13 | H107: all routes | I107: Regression test | J107: Done-in-code | K107: src/hardening.ts (CSP with Zoom frame-ancestors, HSTS, nosniff; explicit CORS; 256kb; token-bucket per IP/account/operator); rejections counted at GET /analytics/rate-limits; 413/400 from body parser. Pinned: s13.test.ts ST-104 block (429, 413, CORS refusal). | L107: REACHABLE | M107: middleware on every route; MEETSYNC_CORS_ORIGINS, MEETSYNC_RATE_LIMIT_PER_MIN
A108: ST-105 | B108: S13 | C108: Operator surface | D108: Operator routes on their own router; rotatable credential | E108: 3 | F108: P1 | G108: S13 | H108: /admin/*, /analytics/* | I108: Regression test | J108: Done-in-code | K108: src/operator.ts OperatorCredential (constant-time, rotate with 15-min grace); ops Router with own limiter; POST /admin/operator-token. Pinned: s13.test.ts "rejects a valid customer session… on every operator route", rotation grace window. | L108: REACHABLE | M108: POST /admin/operator-token; GET /analytics/rate-limits
A109: ST-106 | B109: S13 | C109: Deletion | D109: One purge-target list (PR-06) | E109: 3 | F109: P0 | G109: S13 | H109: delete-my-data + scheduler | I109: Regression test | J109: Done-in-code | K109: src/purge.ts buildPurgeTargets consumed by app.ts AND server.ts; sessions, ingestor, notes, insights included whenever present. Pinned: s13.test.ts "the route and the scheduler build the same list…" + "delete-my-data clears meeting insights". | L109: REACHABLE | M109: POST /orgs/:id/delete-my-data; hourly sweep
A110: ST-107 | B110: S13 | C110: Trust claims | D110: Claim-to-code gate (PR-07) | E110: 5 | F110: P0 | G110: S13 | H110: GET /trust | I110: Build gate | J110: Done-in-code | K110: src/claims.ts is the single source; docs/TRUST_PAGE.md rewritten (real subprocessors, 4 granular scopes, "Not yet" section); test/claims.test.ts asserts doc↔code↔config, refuses PostHog/Sentry/Stripe/SOC2/SSO/residency claims; also gates PRICING_PAGE banner and LISTING_COPY hold. Price-matrix extension of the gate lands with ST-136. | L110: REACHABLE | M110: GET /trust served from trustPayload(cfg)
A111: ST-108 | B111: S13 | C111: Security docs | D111: Threat model + abuse cases document | E111: 2 | F111: P1 | G111: S13 | H111: docs | I111: Doc review | J111: Done | K111: docs/THREAT_MODEL.md: trust boundaries, the rule ("tenant identity always comes from the platform"), AC-1…AC-6 incl. PR-01 as permanent abuse case, what an owner session reaches, four standing rules. | L111: REACHABLE | M111: docs/THREAT_MODEL.md
A112: ST-109 | B112: S14 | C112: Web client | D112: Full typed API client (PR-03) | E112: 5 | F112: P0 | G112: S14 | H112: web/api.ts | I112: Gate + RTL | J112: Done-in-code | K112: web/api.ts covers all 48 client-callable routes with typed responses; ApiError carries status+code+retry; userFacingError maps every status to copy. Pinned: panels.test.tsx "covers every product route with a typed method". | L112: REACHABLE | M112: every product route has a method; enforced by ST-110 gate
A113: ST-110 | B113: S14 | C113: Quality gate | D113: Client-reachability gate (route→client) | E113: 5 | F113: P0 | G113: S14 | H113: tools/reachability/routes.ts | I113: Build gate | J113: Done | K113: Product-agnostic; every route in app.ts must be referenced by web/api.ts or excused with a reason in test/client-reachability-allowlist.json (21 excused: webhook, OAuth, operator). test/clientReachability.test.ts fails the build otherwise. Portable to siblings (Handover #28/#33). | L113: REACHABLE | M113: CI: npx jest test/clientReachability.test.ts
A114: ST-111 | B114: S14 | C114: Product loop | D114: Automatic meeting → CRM pipeline with review_required default (PR-04) | E114: 8 | F114: P0 | G114: S14 | H114: webhook → review screen | I114: Regression test | J114: Done-in-code | K114: transcripts.ts stage(): CRM adapter + mapping + feature enabled → pending_review (default) or queued; derivedFields; exactly one job per meeting under redelivery; approve/reject idempotent; POST /crm/review-mode. Pinned: s14.test.ts ST-111 block; server.test.ts "auto-approved ingest through the real graph"; test needs live Zoom for the webhook half (PENDING LIVE for S9-01). | L114: REACHABLE | M114: POST /webhooks/zoom → GET /meetings/:id/review → POST /meetings/:id/approve|reject
A115: ST-112 | B115: S14 | C115: Persistence | D115: Durable notes and insights (PR-13) | E115: 5 | F115: P1 | G115: S14 | H115: store layer | I115: Contract suite x2 | J115: Done-in-code | K115: notesStore.ts + insightStore.ts (in-memory) and PostgresNotesStore/PostgresInsightStore (notes_sessions, note_entries, meeting_insights); NotesService fully async; purge wired; docs/PERSISTENCE.md updated. Pinned: storeContract.test.ts NotesStore/InsightStore blocks (each case runs twice). | L115: REACHABLE | M115: every notes route and insights route reads the store
... A130: ST-127 | B130: S16 | C130: Indic | D130: Published WER + field-accuracy benchmark (≥50 real calls) — closes LC-7 | E130: 8 | F130: P0 | G130: S16 | H130: docs/INDIC_BENCHMARK.md | I130: Benchmark | J130: Backlog | K130: Needs a consented corpus (PD-06 test 2 is the pilot). | L130: NOT REACHABLE | M130: backlog: corpus + PD-02
A131: ST-128 | B131: S16 | C131: Indic | D131: Locale surface: hi/ta copy, Indian date/number/currency | E131: 3 | F131: P2 | G131: S16 | H131: all panels | I131: RTL | J131: Backlog | L131: NOT REACHABLE | M131: backlog
A132: ST-129 | B132: S17 | C132: CRM | D132: Live CRM OAuth per provider (HubSpot/Salesforce/Zoho) — closes LC-6 | E132: 8 | F132: P0 | G132: S17 | H132: POST /crm/connect | I132: Live sandbox | J132: Backlog | K132: Needs sandbox accounts (Handover #3). /crm/connect still says sandbox. | L132: NOT REACHABLE | M132: backlog: Handover #3
A133: ST-130 | B133: S17 | C133: CRM | D133: Object and field discovery from CRM schema | E133: 5 | F133: P0 | G133: S17 | H133: CRM tab | I133: Live sandbox | J133: Backlog | K133: After ST-129. | L133: NOT REACHABLE | M133: backlog
A134: ST-131 | B134: S17 | C134: CRM | D134: Mapping UI with dry-run and per-field diff | E134: 8 | F134: P0 | G134: S17 | H134: CRM tab | I134: RTL + live | J134: Backlog | K134: CrmPanel mapping form (ST-113) is the seed; dry-run/diff not built. | L134: NOT REACHABLE | M134: backlog
A135: ST-132 | B135: S17 | C135: CRM | D135: Association and multi-object writeback; participants matched to contacts | E135: 5 | F135: P1 | G135: S17 | H135: — | I135: Live sandbox | J135: Backlog | K135: Replaces meetingRecordId() zoom-meeting:<id> stand-in. | L135: NOT REACHABLE | M135: backlog
A136: ST-133 | B136: S17 | C136: CRM | D136: Failure surface and replay; HubSpot rate-limit compliance; ≥95% success tracking | E136: 5 | F136: P0 | G136: S17 | H136: CRM tab | I136: Live sandbox | J136: Backlog | K136: GET /crm/jobs + drain retry (ST-113) is the seed; dead-letter view and plain-language provider errors not built. | L136: PARTIAL | M136: GET /crm/jobs, POST /crm/drain exist; provider errors not translated
A137: ST-134 | B137: S17 | C137: Distribution | D137: HubSpot marketplace listing (3 installs to list, 60 to certify) | E137: 5 | F137: P1 | G137: S17 | H137: — | I137: Human | J137: Backlog | K137: Second marketplace on the critical path; not previously in the tracker (R-M7). | L137: NOT REACHABLE | M137: backlog: Senthil
A138: ST-135 | B138: S17 | C138: CRM | D138: CRM writeback idempotency key (account, meeting, object, field-set) | E138: 3 | F138: P0 | G138: S17 | H138: — | I138: Regression test | J138: Backlog | K138: ST-111 already guarantees one job per meeting via the insight; the adapter-level key lands with live adapters. | L138: PARTIAL | M138: one-job-per-meeting pinned in s14.test.ts; adapter key not built
A139: ST-136 | B139: S18 | C139: Commercial | D139: Resolve the pricing model (PR-05); gate served matrix vs published page | E139: 3 | F139: P0 | G139: S18 | H139: GET /pricing | I139: Claim gate | J139: Backlog | K139: DECISION PENDING (PD-01) banner in docs/PRICING_PAGE.md, enforced by test/claims.test.ts until the numbers agree. Resolution = one decision applied to PLANS, /pricing, page, listing. | L139: PARTIAL | M139: banner + gate shipped; decision owed
A140: ST-137 | B140: S18 | C140: Commercial | D140: Payment processor integration (cards, subscriptions, tax, webhooks → markPaid/paymentFailedTick) | E140: 8 | F140: P0 | G140: S18 | H140: — | I140: Live sandbox | J140: Backlog | K140: Retires two reachability allowlist entries (billing.ts markPaid/paymentFailedTick); dunning now has a sender (ST-115). | L140: NOT REACHABLE | M140: backlog: processor account
A141: ST-138 | B141: S18 | C141: Commercial | D141: Zoom Marketplace billing route reconciled nightly — closes live half of LC-10 | E141: 5 | F141: P0 | G141: S18 | H141: — | I141: Live | J141: Backlog | K141: Needs the Zoom app (Handover #2). | L141: NOT REACHABLE | M141: backlog
A142: ST-139 | B142: S18 | C142: Commercial | D142: Seat detection from measured distinct active users (PR-12) | E142: 5 | F142: P0 | G142: S18 | H142: GET /billing/:id/seats | I142: Regression test | J142: Backlog | K142: telemetry.activeDays already records distinct active days per account (v042) — the input exists; the derivation does not. | L142: NOT REACHABLE | M142: backlog
A143: ST-140 | B143: S18 | C143: Commercial | D143: Feature entitlement matrix enforced in code (deal risk / audit log above Starter) | E143: 3 | F143: P1 | G143: S18 | H143: — | I143: Regression test | J143: Backlog | K143: Depends on PD-01 and PD-04. | L143: NOT REACHABLE | M143: backlog
... A154: ST-151 | B154: S20 | C154: Launch | D154: Design partners + first 10 paying installs, 3 reviews, activation >40% — closes G-02 | E154: 3 | F154: P0 | G154: S20 | H154: — | I154: Live | J154: Backlog | K154: Activation now measured (ST-141). | L154: NOT REACHABLE | M154: backlog: Senthil

Sheet Sprint_Status_Rollup
A1: SPRINT STATUS ROLLUP — live formulas over Traceability_Matrix
A2: Do not edit computed cells. 'Done' counts Done-in-code + Done. Exit criteria from product workbook (S1–S12) and Perplexity Review V001 §7 (S13–S20). Ranges cover rows 4–154 of Traceability_Matrix (v040).
A3: Sprint | B3: Focus | C3: Stories | D3: Points | E3: Done | F3: Done points | G3: % points done | H3: RAG (manual) | I3: Exit criteria
A4: S1 | B4: Foundation (2 wks) | C4: =COUNTIF(Traceability_Matrix!$G$4:$G$154,"S1") | D4: =SUMIF(Traceability_Matrix!$G$4:$G$154,"S1",Traceability_Matrix!$E$4:$E$154) | E4: =COUNTIFS(Traceability_Matrix!$G$4:$G$154,"S1",Traceability_Matrix!$J$4:$J$154,"Done-in-code")+COUNTIFS(Traceability_Matrix!$G$4:$G$154,"S1",Traceability_Matrix!$J$4:$J$154,"Done") | F4: =SUMIFS(Traceability_Matrix!$E$4:$E$154,Traceability_Matrix!$G$4:$G$154,"S1",Traceability_Matrix!$J$4:$J$154,"Done-in-code")+SUMIFS(Traceability_Matrix!$E$4:$E$154,Traceability_Matrix!$G$4:$G$154,"S1",Traceability_Matrix!$J$4:$J$154,"Done") | G4: =IFERROR((SUMIFS(Traceability_Matrix!$E$4:$E$154,Traceability_Matrix!$G$4:$G$154,"S1",Traceability_Matrix!$J$4:$J$154,"Done-in-code")+SUMIFS(Traceability_Matrix!$E$4:$E$154,Traceability_Matrix!$G$4:$G$154,"S1",Traceability_Matrix!$J$4:$J$154,"Done"))/SUMIF(Traceability_Matrix!$G$4:$G$154,"S1",Traceability_Matrix!$E$4:$E$154),0) | H4: GREEN — 4/4 done-in-code; live install pending (LC-1) | I4: App installs cleanly in dev store/org; telemetry firing
A5: S2 | B5: Live notes panel pt 1 | C5: =COUNTIF(Traceability_Matrix!$G$4:$G$154,"S2") | D5: =SUMIF(Traceability_Matrix!$G$4:$G$154,"S2",Traceability_Matrix!$E$4:$E$154) | E5: =COUNTIFS(Traceability_Matrix!$G$4:$G$154,"S2",Traceability_Matrix!$J$4:$J$154,"Done-in-code")+COUNTIFS(Traceability_Matrix!$G$4:$G$154,"S2",Traceability_Matrix!$J$4:$J$154,"Done") | F5: =SUMIFS(Traceability_Matrix!$E$4:$E$154,Traceability_Matrix!$G$4:$G$154,"S2",Traceability_Matrix!$J$4:$J$154,"Done-in-code")+SUMIFS(Traceability_Matrix!$E$4:$E$154,Traceability_Matrix!$G$4:$G$154,"S2",Traceability_Matrix!$J$4:$J$154,"Done") | G5: =IFERROR((SUMIFS(Traceability_Matrix!$E$4:$E$154,Traceability_Matrix!$G$4:$G$154,"S2",Traceability_Matrix!$J$4:$J$154,"Done-in-code")+SUMIFS(Traceability_Matrix!$E$4:$E$154,Traceability_Matrix!$G$4:$G$154,"S2",Traceability_Matrix!$J$4:$J$154,"Done"))/SUMIF(Traceability_Matrix!$G$4:$G$154,"S2",Traceability_Matrix!$E$4:$E$154),0) | H5: GREEN — all done-in-code | I5: Live notes panel happy path demoable
A6: S3 | B6: Notes pt 2 + Extraction start | C6: =COUNTIF(Traceability_Matrix!$G$4:$G$154,"S3") | D6: =SUMIF(Traceability_Matrix!$G$4:$G$154,"S3",Traceability_Matrix!$E$4:$E$154) | E6: =COUNTIFS(Traceability_Matrix!$G$4:$G$154,"S3",Traceability_Matrix!$J$4:$J$154,"Done-in-code")+COUNTIFS(Traceability_Matrix!$G$4:$G$154,"S3",Traceability_Matrix!$J$4:$J$154,"Done") | F6: =SUMIFS(Traceability_Matrix!$E$4:$E$154,Traceability_Matrix!$G$4:$G$154,"S3",Traceability_Matrix!$J$4:$J$154,"Done-in-code")+SUMIFS(Traceability_Matrix!$E$4:$E$154,Traceability_Matrix!$G$4:$G$154,"S3",Traceability_Matrix!$J$4:$J$154,"Done") | G6: =IFERROR((SUMIFS(Traceability_Matrix!$E$4:$E$154,Traceability_Matrix!$G$4:$G$154,"S3",Traceability_Matrix!$J$4:$J$154,"Done-in-code")+SUMIFS(Traceability_Matrix!$E$4:$E$154,Traceability_Matrix!$G$4:$G$154,"S3",Traceability_Matrix!$J$4:$J$154,"Done"))/SUMIF(Traceability_Matrix!$G$4:$G$154,"S3",Traceability_Matrix!$E$4:$E$154),0) | H6: GREEN — surface story pending live | I6: Notes complete with tests; extraction skeleton
A7: S4 | B7: Action-item extraction | C7: =COUNTIF(Traceability_Matrix!$G$4:$G$154,"S4") | D7: =SUMIF(Traceability_Matrix!$G$4:$G$154,"S4",Traceability_Matrix!$E$4:$E$154) | E7: =COUNTIFS(Traceability_Matrix!$G$4:$G$154,"S4",Traceability_Matrix!$J$4:$J$154,"Done-in-code")+COUNTIFS(Traceability_Matrix!$G$4:$G$154,"S4",Traceability_Matrix!$J$4:$J$154,"Done") | F7: =SUMIFS(Traceability_Matrix!$E$4:$E$154,Traceability_Matrix!$G$4:$G$154,"S4",Traceability_Matrix!$J$4:$J$154,"Done-in-code")+SUMIFS(Traceability_Matrix!$E$4:$E$154,Traceability_Matrix!$G$4:$G$154,"S4",Traceability_Matrix!$J$4:$J$154,"Done") | G7: =IFERROR((SUMIFS(Traceability_Matrix!$E$4:$E$154,Traceability_Matrix!$G$4:$G$154,"S4",Traceability_Matrix!$J$4:$J$154,"Done-in-code")+SUMIFS(Traceability_Matrix!$E$4:$E$154,Traceability_Matrix!$G$4:$G$154,"S4",Traceability_Matrix!$J$4:$J$154,"Done"))/SUMIF(Traceability_Matrix!$G$4:$G$154,"S4",Traceability_Matrix!$E$4:$E$154),0) | H7: GREEN — exit met in-code | I7: MVP loop usable end-to-end internally
A8: S5 | B8: CRM writeback + alpha hardening | C8: =COUNTIF(Traceability_Matrix!$G$4:$G$154,"S5") | D8: =SUMIF(Traceability_Matrix!$G$4:$G$154,"S5",Traceability_Matrix!$E$4:$E$154) | E8: =COUNTIFS(Traceability_Matrix!$G$4:$G$154,"S5",Traceability_Matrix!$J$4:$J$154,"Done-in-code")+COUNTIFS(Traceability_Matrix!$G$4:$G$154,"S5",Traceability_Matrix!$J$4:$J$154,"Done") | F8: =SUMIFS(Traceability_Matrix!$E$4:$E$154,Traceability_Matrix!$G$4:$G$154,"S5",Traceability_Matrix!$J$4:$J$154,"Done-in-code")+SUMIFS(Traceability_Matrix!$E$4:$E$154,Traceability_Matrix!$G$4:$G$154,"S5",Traceability_Matrix!$J$4:$J$154,"Done") | G8: =IFERROR((SUMIFS(Traceability_Matrix!$E$4:$E$154,Traceability_Matrix!$G$4:$G$154,"S5",Traceability_Matrix!$J$4:$J$154,"Done-in-code")+SUMIFS(Traceability_Matrix!$E$4:$E$154,Traceability_Matrix!$G$4:$G$154,"S5",Traceability_Matrix!$J$4:$J$154,"Done"))/SUMIF(Traceability_Matrix!$G$4:$G$154,"S5",Traceability_Matrix!$E$4:$E$154),0) | H8: GREEN — live CRM sandboxes pending | I8: Internal alpha: team dogfoods daily
A9: S6 | B9: Billing + Deal-risk signals | C9: =COUNTIF(Traceability_Matrix!$G$4:$G$154,"S6") | D9: =SUMIF(Traceability_Matrix!$G$4:$G$154,"S6",Traceability_Matrix!$E$4:$E$154) | E9: =COUNTIFS(Traceability_Matrix!$G$4:$G$154,"S6",Traceability_Matrix!$J$4:$J$154,"Done-in-code")+COUNTIFS(Traceability_Matrix!$G$4:$G$154,"S6",Traceability_Matrix!$J$4:$J$154,"Done") | F9: =SUMIFS(Traceability_Matrix!$E$4:$E$154,Traceability_Matrix!$G$4:$G$154,"S6",Traceability_Matrix!$J$4:$J$154,"Done-in-code")+SUMIFS(Traceability_Matrix!$E$4:$E$154,Traceability_Matrix!$G$4:$G$154,"S6",Traceability_Matrix!$J$4:$J$154,"Done") | G9: =IFERROR((SUMIFS(Traceability_Matrix!$E$4:$E$154,Traceability_Matrix!$G$4:$G$154,"S6",Traceability_Matrix!$J$4:$J$154,"Done-in-code")+SUMIFS(Traceability_Matrix!$E$4:$E$154,Traceability_Matrix!$G$4:$G$154,"S6",Traceability_Matrix!$J$4:$J$154,"Done"))/SUMIF(Traceability_Matrix!$G$4:$G$154,"S6",Traceability_Matrix!$E$4:$E$154),0) | H9: GREEN — marketplace billing verification pending | I9: Can charge a test customer; up/downgrade paths work
A10: S7 | B10: Private beta (design partners) | C10: =COUNTIF(Traceability_Matrix!$G$4:$G$154,"S7") | D10: =SUMIF(Traceability_Matrix!$G$4:$G$154,"S7",Traceability_Matrix!$E$4:$E$154) | E10: =COUNTIFS(Traceability_Matrix!$G$4:$G$154,"S7",Traceability_Matrix!$J$4:$J$154,"Done-in-code")+COUNTIFS(Traceability_Matrix!$G$4:$G$154,"S7",Traceability_Matrix!$J$4:$J$154,"Done") | F10: =SUMIFS(Traceability_Matrix!$E$4:$E$154,Traceability_Matrix!$G$4:$G$154,"S7",Traceability_Matrix!$J$4:$J$154,"Done-in-code")+SUMIFS(Traceability_Matrix!$E$4:$E$154,Traceability_Matrix!$G$4:$G$154,"S7",Traceability_Matrix!$J$4:$J$154,"Done") | G10: =IFERROR((SUMIFS(Traceability_Matrix!$E$4:$E$154,Traceability_Matrix!$G$4:$G$154,"S7",Traceability_Matrix!$J$4:$J$154,"Done-in-code")+SUMIFS(Traceability_Matrix!$E$4:$E$154,Traceability_Matrix!$G$4:$G$154,"S7",Traceability_Matrix!$J$4:$J$154,"Done"))/SUMIF(Traceability_Matrix!$G$4:$G$154,"S7",Traceability_Matrix!$E$4:$E$154),0) | H10: AMBER — code done; beta humans pending | I10: 3+ partners active weekly; NPS pulse >30
A11: S8 | B11: Beta iteration + Indic pack | C11: =COUNTIF(Traceability_Matrix!$G$4:$G$154,"S8") | D11: =SUMIF(Traceability_Matrix!$G$4:$G$154,"S8",Traceability_Matrix!$E$4:$E$154) | E11: =COUNTIFS(Traceability_Matrix!$G$4:$G$154,"S8",Traceability_Matrix!$J$4:$J$154,"Done-in-code")+COUNTIFS(Traceability_Matrix!$G$4:$G$154,"S8",Traceability_Matrix!$J$4:$J$154,"Done") | F11: =SUMIFS(Traceability_Matrix!$E$4:$E$154,Traceability_Matrix!$G$4:$G$154,"S8",Traceability_Matrix!$J$4:$J$154,"Done-in-code")+SUMIFS(Traceability_Matrix!$E$4:$E$154,Traceability_Matrix!$G$4:$G$154,"S8",Traceability_Matrix!$J$4:$J$154,"Done") | G11: =IFERROR((SUMIFS(Traceability_Matrix!$E$4:$E$154,Traceability_Matrix!$G$4:$G$154,"S8",Traceability_Matrix!$J$4:$J$154,"Done-in-code")+SUMIFS(Traceability_Matrix!$E$4:$E$154,Traceability_Matrix!$G$4:$G$154,"S8",Traceability_Matrix!$J$4:$J$154,"Done"))/SUMIF(Traceability_Matrix!$G$4:$G$154,"S8",Traceability_Matrix!$E$4:$E$154),0) | H11: AMBER — code done; live load/deploy/infra pending | I11: Beta cohort WoW retention >60%
A12: S9 | B12: Marketplace review prep | C12: =COUNTIF(Traceability_Matrix!$G$4:$G$154,"S9") | D12: =SUMIF(Traceability_Matrix!$G$4:$G$154,"S9",Traceability_Matrix!$E$4:$E$154) | E12: =COUNTIFS(Traceability_Matrix!$G$4:$G$154,"S9",Traceability_Matrix!$J$4:$J$154,"Done-in-code")+COUNTIFS(Traceability_Matrix!$G$4:$G$154,"S9",Traceability_Matrix!$J$4:$J$154,"Done") | F12: =SUMIFS(Traceability_Matrix!$E$4:$E$154,Traceability_Matrix!$G$4:$G$154,"S9",Traceability_Matrix!$J$4:$J$154,"Done-in-code")+SUMIFS(Traceability_Matrix!$E$4:$E$154,Traceability_Matrix!$G$4:$G$154,"S9",Traceability_Matrix!$J$4:$J$154,"Done") | G12: =IFERROR((SUMIFS(Traceability_Matrix!$E$4:$E$154,Traceability_Matrix!$G$4:$G$154,"S9",Traceability_Matrix!$J$4:$J$154,"Done-in-code")+SUMIFS(Traceability_Matrix!$E$4:$E$154,Traceability_Matrix!$G$4:$G$154,"S9",Traceability_Matrix!$J$4:$J$154,"Done"))/SUMIF(Traceability_Matrix!$G$4:$G$154,"S9",Traceability_Matrix!$E$4:$E$154),0) | I12: Review submission accepted into queue
A13: S10 | B13: Review remediation + docs | C13: =COUNTIF(Traceability_Matrix!$G$4:$G$154,"S10") | D13: =SUMIF(Traceability_Matrix!$G$4:$G$154,"S10",Traceability_Matrix!$E$4:$E$154) | E13: =COUNTIFS(Traceability_Matrix!$G$4:$G$154,"S10",Traceability_Matrix!$J$4:$J$154,"Done-in-code")+COUNTIFS(Traceability_Matrix!$G$4:$G$154,"S10",Traceability_Matrix!$J$4:$J$154,"Done") | F13: =SUMIFS(Traceability_Matrix!$E$4:$E$154,Traceability_Matrix!$G$4:$G$154,"S10",Traceability_Matrix!$J$4:$J$154,"Done-in-code")+SUMIFS(Traceability_Matrix!$E$4:$E$154,Traceability_Matrix!$G$4:$G$154,"S10",Traceability_Matrix!$J$4:$J$154,"Done") | G13: =IFERROR((SUMIFS(Traceability_Matrix!$E$4:$E$154,Traceability_Matrix!$G$4:$G$154,"S10",Traceability_Matrix!$J$4:$J$154,"Done-in-code")+SUMIFS(Traceability_Matrix!$E$4:$E$154,Traceability_Matrix!$G$4:$G$154,"S10",Traceability_Matrix!$J$4:$J$154,"Done"))/SUMIF(Traceability_Matrix!$G$4:$G$154,"S10",Traceability_Matrix!$E$4:$E$154),0) | I13: Marketplace approval obtained
A14: S11 | B14: Launch | C14: =COUNTIF(Traceability_Matrix!$G$4:$G$154,"S11") | D14: =SUMIF(Traceability_Matrix!$G$4:$G$154,"S11",Traceability_Matrix!$E$4:$E$154) | E14: =COUNTIFS(Traceability_Matrix!$G$4:$G$154,"S11",Traceability_Matrix!$J$4:$J$154,"Done-in-code")+COUNTIFS(Traceability_Matrix!$G$4:$G$154,"S11",Traceability_Matrix!$J$4:$J$154,"Done") | F14: =SUMIFS(Traceability_Matrix!$E$4:$E$154,Traceability_Matrix!$G$4:$G$154,"S11",Traceability_Matrix!$J$4:$J$154,"Done-in-code")+SUMIFS(Traceability_Matrix!$E$4:$E$154,Traceability_Matrix!$G$4:$G$154,"S11",Traceability_Matrix!$J$4:$J$154,"Done") | G14: =IFERROR((SUMIFS(Traceability_Matrix!$E$4:$E$154,Traceability_Matrix!$G$4:$G$154,"S11",Traceability_Matrix!$J$4:$J$154,"Done-in-code")+SUMIFS(Traceability_Matrix!$E$4:$E$154,Traceability_Matrix!$G$4:$G$154,"S11",Traceability_Matrix!$J$4:$J$154,"Done"))/SUMIF(Traceability_Matrix!$G$4:$G$154,"S11",Traceability_Matrix!$E$4:$E$154),0) | I14: First 10 installs; first 3 reviews; activation >40%
A15: S12 | B15: Iterate & scale decision | C15: =COUNTIF(Traceability_Matrix!$G$4:$G$154,"S12") | D15: =SUMIF(Traceability_Matrix!$G$4:$G$154,"S12",Traceability_Matrix!$E$4:$E$154) | E15: =COUNTIFS(Traceability_Matrix!$G$4:$G$154,"S12",Traceability_Matrix!$J$4:$J$154,"Done-in-code")+COUNTIFS(Traceability_Matrix!$G$4:$G$154,"S12",Traceability_Matrix!$J$4:$J$154,"Done") | F15: =SUMIFS(Traceability_Matrix!$E$4:$E$154,Traceability_Matrix!$G$4:$G$154,"S12",Traceability_Matrix!$J$4:$J$154,"Done-in-code")+SUMIFS(Traceability_Matrix!$E$4:$E$154,Traceability_Matrix!$G$4:$G$154,"S12",Traceability_Matrix!$J$4:$J$154,"Done") | G15: =IFERROR((SUMIFS(Traceability_Matrix!$E$4:$E$154,Traceability_Matrix!$G$4:$G$154,"S12",Traceability_Matrix!$J$4:$J$154,"Done-in-code")+SUMIFS(Traceability_Matrix!$E$4:$E$154,Traceability_Matrix!$G$4:$G$154,"S12",Traceability_Matrix!$J$4:$J$154,"Done"))/SUMIF(Traceability_Matrix!$G$4:$G$154,"S12",Traceability_Matrix!$E$4:$E$154),0) | I15: Growth model doc with CAC/LTV first estimates
A16: S13 | B16: Trust & tenancy hardening (BLOCKING) | C16: =COUNTIF(Traceability_Matrix!$G$4:$G$154,"S13") | D16: =SUMIF(Traceability_Matrix!$G$4:$G$154,"S13",Traceability_Matrix!$E$4:$E$154) | E16: =COUNTIFS(Traceability_Matrix!$G$4:$G$154,"S13",Traceability_Matrix!$J$4:$J$154,"Done-in-code")+COUNTIFS(Traceability_Matrix!$G$4:$G$154,"S13",Traceability_Matrix!$J$4:$J$154,"Done") | F16: =SUMIFS(Traceability_Matrix!$E$4:$E$154,Traceability_Matrix!$G$4:$G$154,"S13",Traceability_Matrix!$J$4:$J$154,"Done-in-code")+SUMIFS(Traceability_Matrix!$E$4:$E$154,Traceability_Matrix!$G$4:$G$154,"S13",Traceability_Matrix!$J$4:$J$154,"Done") | G16: =IFERROR((SUMIFS(Traceability_Matrix!$E$4:$E$154,Traceability_Matrix!$G$4:$G$154,"S13",Traceability_Matrix!$J$4:$J$154,"Done-in-code")+SUMIFS(Traceability_Matrix!$E$4:$E$154,Traceability_Matrix!$G$4:$G$154,"S13",Traceability_Matrix!$J$4:$J$154,"Done"))/SUMIF(Traceability_Matrix!$G$4:$G$154,"S13",Traceability_Matrix!$E$4:$E$154),0) | H16: GREEN — 8/8 done-in-code at v045; PR-01/06/07/08/10 pinned | I16: Caller cannot install onto a workspace it does not own; every trust-page claim maps to code
A17: S14 | B17: Close the product loop | C17: =COUNTIF(Traceability_Matrix!$G$4:$G$154,"S14") | D17: =SUMIF(Traceability_Matrix!$G$4:$G$154,"S14",Traceability_Matrix!$E$4:$E$154) | E17: =COUNTIFS(Traceability_Matrix!$G$4:$G$154,"S14",Traceability_Matrix!$J$4:$J$154,"Done-in-code")+COUNTIFS(Traceability_Matrix!$G$4:$G$154,"S14",Traceability_Matrix!$J$4:$J$154,"Done") | F17: =SUMIFS(Traceability_Matrix!$E$4:$E$154,Traceability_Matrix!$G$4:$G$154,"S14",Traceability_Matrix!$J$4:$J$154,"Done-in-code")+SUMIFS(Traceability_Matrix!$E$4:$E$154,Traceability_Matrix!$G$4:$G$154,"S14",Traceability_Matrix!$J$4:$J$154,"Done") | G17: =IFERROR((SUMIFS(Traceability_Matrix!$E$4:$E$154,Traceability_Matrix!$G$4:$G$154,"S14",Traceability_Matrix!$J$4:$J$154,"Done-in-code")+SUMIFS(Traceability_Matrix!$E$4:$E$154,Traceability_Matrix!$G$4:$G$154,"S14",Traceability_Matrix!$J$4:$J$154,"Done"))/SUMIF(Traceability_Matrix!$G$4:$G$154,"S14",Traceability_Matrix!$E$4:$E$154),0) | H17: GREEN — 7/7 done-in-code; live webhook half pending S9-01; mail transport config = Senthil | I17: Signed webhook → extract → staged → panel renders from API → approve → CRM audit row
A18: S15 | B18: Real intelligence + evaluation | C18: =COUNTIF(Traceability_Matrix!$G$4:$G$154,"S15") | D18: =SUMIF(Traceability_Matrix!$G$4:$G$154,"S15",Traceability_Matrix!$E$4:$E$154) | E18: =COUNTIFS(Traceability_Matrix!$G$4:$G$154,"S15",Traceability_Matrix!$J$4:$J$154,"Done-in-code")+COUNTIFS(Traceability_Matrix!$G$4:$G$154,"S15",Traceability_Matrix!$J$4:$J$154,"Done") | F18: =SUMIFS(Traceability_Matrix!$E$4:$E$154,Traceability_Matrix!$G$4:$G$154,"S15",Traceability_Matrix!$J$4:$J$154,"Done-in-code")+SUMIFS(Traceability_Matrix!$E$4:$E$154,Traceability_Matrix!$G$4:$G$154,"S15",Traceability_Matrix!$J$4:$J$154,"Done") | G18: =IFERROR((SUMIFS(Traceability_Matrix!$E$4:$E$154,Traceability_Matrix!$G$4:$G$154,"S15",Traceability_Matrix!$J$4:$J$154,"Done-in-code")+SUMIFS(Traceability_Matrix!$E$4:$E$154,Traceability_Matrix!$G$4:$G$154,"S15",Traceability_Matrix!$J$4:$J$154,"Done"))/SUMIF(Traceability_Matrix!$G$4:$G$154,"S15",Traceability_Matrix!$E$4:$E$154),0) | H18: RED — 0/8; gated by PD-02 | I18: Golden set ≥100 with per-field P/R, CI floor, cost cap, no-model fallback
A19: S16 | B19: Indic wedge, proven | C19: =COUNTIF(Traceability_Matrix!$G$4:$G$154,"S16") | D19: =SUMIF(Traceability_Matrix!$G$4:$G$154,"S16",Traceability_Matrix!$E$4:$E$154) | E19: =COUNTIFS(Traceability_Matrix!$G$4:$G$154,"S16",Traceability_Matrix!$J$4:$J$154,"Done-in-code")+COUNTIFS(Traceability_Matrix!$G$4:$G$154,"S16",Traceability_Matrix!$J$4:$J$154,"Done") | F19: =SUMIFS(Traceability_Matrix!$E$4:$E$154,Traceability_Matrix!$G$4:$G$154,"S16",Traceability_Matrix!$J$4:$J$154,"Done-in-code")+SUMIFS(Traceability_Matrix!$E$4:$E$154,Traceability_Matrix!$G$4:$G$154,"S16",Traceability_Matrix!$J$4:$J$154,"Done") | G19: =IFERROR((SUMIFS(Traceability_Matrix!$E$4:$E$154,Traceability_Matrix!$G$4:$G$154,"S16",Traceability_Matrix!$J$4:$J$154,"Done-in-code")+SUMIFS(Traceability_Matrix!$E$4:$E$154,Traceability_Matrix!$G$4:$G$154,"S16",Traceability_Matrix!$J$4:$J$154,"Done"))/SUMIF(Traceability_Matrix!$G$4:$G$154,"S16",Traceability_Matrix!$E$4:$E$154),0) | H19: RED — 0/5; gated by PD-02/PD-04 + corpus | I19: Published WER + field accuracy vs Zoom on ≥50 real calls
A20: S17 | B20: Live CRM depth | C20: =COUNTIF(Traceability_Matrix!$G$4:$G$154,"S17") | D20: =SUMIF(Traceability_Matrix!$G$4:$G$154,"S17",Traceability_Matrix!$E$4:$E$154) | E20: =COUNTIFS(Traceability_Matrix!$G$4:$G$154,"S17",Traceability_Matrix!$J$4:$J$154,"Done-in-code")+COUNTIFS(Traceability_Matrix!$G$4:$G$154,"S17",Traceability_Matrix!$J$4:$J$154,"Done") | F20: =SUMIFS(Traceability_Matrix!$E$4:$E$154,Traceability_Matrix!$G$4:$G$154,"S17",Traceability_Matrix!$J$4:$J$154,"Done-in-code")+SUMIFS(Traceability_Matrix!$E$4:$E$154,Traceability_Matrix!$G$4:$G$154,"S17",Traceability_Matrix!$J$4:$J$154,"Done") | G20: =IFERROR((SUMIFS(Traceability_Matrix!$E$4:$E$154,Traceability_Matrix!$G$4:$G$154,"S17",Traceability_Matrix!$J$4:$J$154,"Done-in-code")+SUMIFS(Traceability_Matrix!$E$4:$E$154,Traceability_Matrix!$G$4:$G$154,"S17",Traceability_Matrix!$J$4:$J$154,"Done"))/SUMIF(Traceability_Matrix!$G$4:$G$154,"S17",Traceability_Matrix!$E$4:$E$154),0) | H20: RED — 0/7 (2 partial seeds); needs sandbox creds (Handover #3) | I20: Live writes to HubSpot/Salesforce/Zoho; mapping UI; HubSpot listing submitted; LC-6 closed
A21: S18 | B21: Commercial engine | C21: =COUNTIF(Traceability_Matrix!$G$4:$G$154,"S18") | D21: =SUMIF(Traceability_Matrix!$G$4:$G$154,"S18",Traceability_Matrix!$E$4:$E$154) | E21: =COUNTIFS(Traceability_Matrix!$G$4:$G$154,"S18",Traceability_Matrix!$J$4:$J$154,"Done-in-code")+COUNTIFS(Traceability_Matrix!$G$4:$G$154,"S18",Traceability_Matrix!$J$4:$J$154,"Done") | F21: =SUMIFS(Traceability_Matrix!$E$4:$E$154,Traceability_Matrix!$G$4:$G$154,"S18",Traceability_Matrix!$J$4:$J$154,"Done-in-code")+SUMIFS(Traceability_Matrix!$E$4:$E$154,Traceability_Matrix!$G$4:$G$154,"S18",Traceability_Matrix!$J$4:$J$154,"Done") | G21: =IFERROR((SUMIFS(Traceability_Matrix!$E$4:$E$154,Traceability_Matrix!$G$4:$G$154,"S18",Traceability_Matrix!$J$4:$J$154,"Done-in-code")+SUMIFS(Traceability_Matrix!$E$4:$E$154,Traceability_Matrix!$G$4:$G$154,"S18",Traceability_Matrix!$J$4:$J$154,"Done"))/SUMIF(Traceability_Matrix!$G$4:$G$154,"S18",Traceability_Matrix!$E$4:$E$154),0) | H21: AMBER — 1/6 (ST-141); PD-01 gates the rest | I21: Test customer charged and refunded end-to-end; pricing consistent everywhere; seats detected
A22: S19 | B22: Enterprise readiness | C22: =COUNTIF(Traceability_Matrix!$G$4:$G$154,"S19") | D22: =SUMIF(Traceability_Matrix!$G$4:$G$154,"S19",Traceability_Matrix!$E$4:$E$154) | E22: =COUNTIFS(Traceability_Matrix!$G$4:$G$154,"S19",Traceability_Matrix!$J$4:$J$154,"Done-in-code")+COUNTIFS(Traceability_Matrix!$G$4:$G$154,"S19",Traceability_Matrix!$J$4:$J$154,"Done") | F22: =SUMIFS(Traceability_Matrix!$E$4:$E$154,Traceability_Matrix!$G$4:$G$154,"S19",Traceability_Matrix!$J$4:$J$154,"Done-in-code")+SUMIFS(Traceability_Matrix!$E$4:$E$154,Traceability_Matrix!$G$4:$G$154,"S19",Traceability_Matrix!$J$4:$J$154,"Done") | G22: =IFERROR((SUMIFS(Traceability_Matrix!$E$4:$E$154,Traceability_Matrix!$G$4:$G$154,"S19",Traceability_Matrix!$J$4:$J$154,"Done-in-code")+SUMIFS(Traceability_Matrix!$E$4:$E$154,Traceability_Matrix!$G$4:$G$154,"S19",Traceability_Matrix!$J$4:$J$154,"Done"))/SUMIF(Traceability_Matrix!$G$4:$G$154,"S19",Traceability_Matrix!$E$4:$E$154),0) | H22: RED — 0/6 (2 partial); PD-03 decides whether it blocks launch | I22: Survives a 500-person security questionnaire
A23: S20 | B23: Launch & proof | C23: =COUNTIF(Traceability_Matrix!$G$4:$G$154,"S20") | D23: =SUMIF(Traceability_Matrix!$G$4:$G$154,"S20",Traceability_Matrix!$E$4:$E$154) | E23: =COUNTIFS(Traceability_Matrix!$G$4:$G$154,"S20",Traceability_Matrix!$J$4:$J$154,"Done-in-code")+COUNTIFS(Traceability_Matrix!$G$4:$G$154,"S20",Traceability_Matrix!$J$4:$J$154,"Done") | F23: =SUMIFS(Traceability_Matrix!$E$4:$E$154,Traceability_Matrix!$G$4:$G$154,"S20",Traceability_Matrix!$J$4:$J$154,"Done-in-code")+SUMIFS(Traceability_Matrix!$E$4:$E$154,Traceability_Matrix!$G$4:$G$154,"S20",Traceability_Matrix!$J$4:$J$154,"Done") | G23: =IFERROR((SUMIFS(Traceability_Matrix!$E$4:$E$154,Traceability_Matrix!$G$4:$G$154,"S20",Traceability_Matrix!$J$4:$J$154,"Done-in-code")+SUMIFS(Traceability_Matrix!$E$4:$E$154,Traceability_Matrix!$G$4:$G$154,"S20",Traceability_Matrix!$J$4:$J$154,"Done"))/SUMIF(Traceability_Matrix!$G$4:$G$154,"S20",Traceability_Matrix!$E$4:$E$154),0) | H23: RED — 0/4; PD-05 hold lifted, Handover #2 first | I23: App listed; 10 paying installs from strangers; 3 reviews; activation >40%
A24: TOTAL | B24: (S1-S20) | C24: =SUM(C4:C23) | D24: =SUM(D4:D23) | E24: =SUM(E4:E23) | F24: =SUM(F4:F23) | G24: =IFERROR(F24/D24,0)

Sheet RAID_Carryover
A1: RAID — seeded from v007 Risk_Register + build findings
A2: Types: Risk / Assumption / Constraint. Status manual.
A3: ID | B3: Type | C3: Raised | D3: Item | E3: Status | F3: Notes / Mitigation
A4: R-M1 | B4: Risk | C4: v007 | D4: Zoom native AI Companion covers notes/actions free (High/High) | E4: MATERIALISED (16 Sep review) | F4: Wedge is CRM-hygiene depth + Indic languages + writeback rules Zoom won't build — exactly the F3/F5 code shipped this version. | v040: Zoom folded Meeting Summary/My Notes into paid Workplace plans free (Jun 2026); CRM sync sold as Revenue Accelerator; F1/F2 now compete with a free incumbent. Remaining wedge = governed CRM writeback (S17) + measurably better Indic (S16). PD-02/PD-06 decide.
A5: R-M2 | B5: Risk | C5: v007 | D5: Recording-privacy regulation tightens per region (Medium/Medium) | E5: Open | F5: Consent UX + region config (MEETSYNC_REGION us|in|eu coded) + legal review cadence; LC-3.
A6: R-M3 | B6: Risk | C6: v007 | D6: Meeting-intelligence consolidation squeezes independents (Medium/Medium) | E6: Open | F6: Wedge: CRM writeback quality, not transcription quality.
A7: R-M4 | B7: Constraint | C7: 22:58 | D7: Sandbox has no Postgres — persistence in-memory behind typed Store interface (D-M1) | E7: Open | F7: Postgres adapter at deploy; domain code untouched by the swap. Accepted-pattern precedent.
A8: R-M5 | B8: Risk | C8: 22:58 | D8: Zoom webhook/signature contract implemented to published pattern pending live verification (D-M3) | E8: Open | F8: Verify at S9-01/02; isolated in src/webhooks.ts — one-module change if format differs.
A9: R-M6 | B9: Risk | C9: 22:58 | D9: Transcript source assumed via Zoom-hosted events (RTMS/recording webhooks) — concurrency behaviour at LC-5 unverified | E9: Open | F9: Dedupe ledger + replay guard coded; concurrent-meeting load = S9-08 live run.
A10: A-M1 | B10: Assumption | C10: 22:58 | D10: D13 applies: S0 discovery (PRD sign-off, 5-user prototype test, wireframe links) parked, NOT marked done | E10: Open | F10: v008 was originally planned as post-S0 re-baseline; that work remains owed.
A11: A-M2 | B11: Assumption | C11: 22:58 | D11: D15 mode (parallel vs swap) pending — MeetSync is the ninth concurrent build | E11: Open | F11: Senthil to ratify; serial rule formally intact until then.
A12: R-M7 | B12: Risk | C12: v040 | D12: HubSpot Marketplace is a second, slower marketplace on the critical path to the CRM wedge: 3 active installs to list, 60 unaffiliated to certify, security questionnaire, verified domain, ≥95% API success, 6 months listed (Medium/High) | E12: Open | F12: ST-134 added; not previously in the tracker at all.
A13: R-M8 | B13: Risk | C13: v040 | D13: Pricing model contradicts itself 50x between page and code (PR-05); a listing that publishes either is a HubSpot listing blocker (High/High until PD-01) | E13: Open | F13: DECISION PENDING banner gated by claims.test.ts; ST-136.
A14: R-M9 | B14: Risk | C14: v040 | D14: Listing copy promises capabilities (transcription, in-meeting capture) the code does not have — Zoom review rejection or worse (High/High until PD-02) | E14: Mitigated | F14: docs/LISTING_COPY.md HELD banner, gated; help centre corrected to four granular scopes.
... A16: C-M1 | B16: Constraint | C16: v040 | D16: Sessions now expire in 60 minutes; any client must refresh (App.tsx does at 50). Integrations that cached a token for longer will 401. | E16: Open | F16: docs/RUNBOOK.md "Sessions and the install flow".

Sheet Gate_Checklist
A1: COMPLETION GATE — MeetSync is DONE only when every row is Done
A2: Code complete counts for nothing. Gate decision = Senthil. LC items = product workbook Launch_Checklist.
A3: ID | B3: Gate item | C3: Source | D3: Status
A4: G-01 | B4: App LISTED on Zoom App Marketplace (approved + published) | C4: Portfolio gate | D4: Open
A5: G-02 | B5: 10 PAYING installs from strangers | C5: Portfolio gate | D5: Open
A6: G-03 | B6: S12 kill criteria evaluated with evidence pack | C6: Portfolio gate | D6: Open
A7: G-04 | B7: Kill/continue decision recorded by Senthil | C7: Portfolio gate | D7: Open
A8: G-05 | B8: On CONTINUE: next-rank build authorised; MeetSync enters ops floor | C8: Portfolio gate | D8: Open
A9: LC-1 | B9: Zoom Marketplace app created; scopes minimal (meeting, recording read) | C9: LC #1 | D9: In progress — scope map done; app creation = Senthil (Handover #2). PD-05 hold LIFTED at v045: S13 closed, install flow safe to point at a real account
A10: LC-2 | B10: Security review pack: TDD doc, data-flow diagram, pen-test summary | C10: LC #2 | D10: In progress — data-flow doc + THREAT_MODEL.md (ST-108) done; TDD + pen test (ST-147) open
A11: LC-3 | B11: Recording-consent UX legal-reviewed per region | C11: LC #3 | D11: Open — region config coded; legal review = Senthil
A12: LC-4 | B12: SOC2-track evidence folder ready | C12: LC #4 | D12: Open — audit log + retention controls coded as inputs
A13: LC-5 | B13: RTMS/recording webhook resilience at concurrent-meeting load | C13: LC #5 | D13: Done-in-code — HMAC+replay+dedupe+breaker; live 5x run at S9-08
A14: LC-6 | B14: CRM writeback tested against HubSpot/Salesforce/Zoho sandboxes | C14: LC #6 | D14: Done-in-code (sandbox) — live OAuth does not exist (ST-129); /crm/connect says so. Live creds = Senthil (Handover #3)
... A22: G-09 | B22: Every claim in listing, pricing page and trust page passes test/claims.test.ts | C22: ST-107 | D22: In progress — trust page passes; pricing and listing carry gated holds

Sheet S10_Board
A1: S10 BOARD — Review remediation + docs — exit: marketplace approval obtained
A2: Edit Status/Notes (yellow).
A3: ID | B3: Item | C3: Story ref | D3: Points | E3: Owner | F3: Status | G3: Notes / Evidence
A4: S10-01 | B4: Help center: 15 articles + ranked search | C4: ST-080 | D4: 5 | E4: Claude | F4: Done-in-code | G4: helpcenter.ts; publish with site at go-live.
A5: S10-02 | B5: In-app chat, <4 business-hr first response | C5: ST-081 | D5: 3 | E5: Senthil | F5: To do | G5: Vendor pick (Intercom/Crisp/Plain) + staffing hours; intake wiring on request.
A6: S10-03 | B6: Demo-data mode (interactive sandbox) | C6: ST-083 | D6: 5 | E6: Claude | F6: Done-in-code (half) | G6: demo.ts + route; VIDEO half = Senthil recording.
A7: S10-04 | B7: Status page + incident comms template | C7: ST-084 | D7: 2 | E7: Claude | F7: Done-in-code | G7: /status + /status.html + INCIDENT_COMMS.md.
A8: S10-05 | B8: Pricing page/matrix + FAQ | C8: ST-095 | D8: 3 | E8: Senthil + Claude | F8: Code-complete (pending live) | G8: /pricing bound to PLANS; PRICING_PAGE.md draft; publish = site.
A9: S10-06 | B9: Security/trust page live | C9: ST-096 | D9: 3 | E9: Senthil + Claude | F9: Code-complete (pending live) | G9: TRUST_PAGE.md draft incl. subprocessors; publish = site.
A10: S10-07 | B10: Submission dry-run vs platform checklist (2nd reviewer) | C10: ST-097 | D10: 3 | E10: Senthil | F10: To do | G10: Human review against Zoom checklist before real submission.

Sheet S13_S20_Board
A1: S13–S20 BOARD — Perplexity Review V001 plan, all 51 stories — exit: S13 closed before live install; S20 = 10 paying strangers
A2: Edit Status/Notes (yellow). Points and acceptance criteria are the review's; status is v045 reality. Nothing removed.
A3: ID | B3: Sprint | C3: Item | D3: Story ref | E3: Points | F3: Owner | G3: Status | H3: Notes / Evidence
A4: S13-01 | B4: S13 | C4: Derive tenant identity from Zoom, not the caller (PR-01) | D4: ST-101 | E4: 8 | F4: Claude | G4: Done-in-code (pending live) | H4: src/identity.ts fetchZoomIdentity + assertTenantMatches; app.ts callback; installAccount re-checks. Pinned: s13.test.ts "refuses a state whose account differs…" (403, audit row, no account row, no session) + "cannot repoint a live workspace"; identity.test.ts.
A5: S13-02 | B5: S13 | C5: Real user identity in the session (PR-08) | D5: ST-102 | E5: 5 | F5: Claude | G5: Done-in-code (pending live) | H5: Session carries Zoom user id, email, role (owner/admin/member from role_id/role_name); owner@<account> synthesis deleted; accounts.installed_by_* + contact_email columns. Pinned: s13.test.ts "mints owner/admin/member from Zoom's role, and two users produce two audit identities".
A6: S13-03 | B6: S13 | C6: Session lifecycle: revocation, 60-min TTL, secure delivery (PR-10) | D6: ST-103 | E6: 5 | F6: Claude | G6: Done-in-code (pending live) | H6: auth.ts SessionManager (jti, deny list, per-account watermark); sessionStore.ts + PostgresSessionStore (contract suite x2); HttpOnly/Secure/SameSite=None cookie on install; uninstall + delete-my-data revoke all; App.tsx refresh timer. Pinned: s13.test.ts ST-103 block; storeContract SessionStore.
A7: S13-04 | B7: S13 | C7: Security headers, CORS allowlist, body limit, rate limits (PR-10) | D7: ST-104 | E7: 3 | F7: Claude | G7: Done-in-code | H7: src/hardening.ts (CSP with Zoom frame-ancestors, HSTS, nosniff; explicit CORS; 256kb; token-bucket per IP/account/operator); rejections counted at GET /analytics/rate-limits; 413/400 from body parser. Pinned: s13.test.ts ST-104 block (429, 413, CORS refusal).
A8: S13-05 | B8: S13 | C8: Operator routes on their own router; rotatable credential | D8: ST-105 | E8: 3 | F8: Claude | G8: Done-in-code | H8: src/operator.ts OperatorCredential (constant-time, rotate with 15-min grace); ops Router with own limiter; POST /admin/operator-token. Pinned: s13.test.ts "rejects a valid customer session… on every operator route", rotation grace window.
A9: S13-06 | B9: S13 | C9: One purge-target list (PR-06) | D9: ST-106 | E9: 3 | F9: Claude | G9: Done-in-code | H9: src/purge.ts buildPurgeTargets consumed by app.ts AND server.ts; sessions, ingestor, notes, insights included whenever present. Pinned: s13.test.ts "the route and the scheduler build the same list…" + "delete-my-data clears meeting insights".
A10: S13-07 | B10: S13 | C10: Claim-to-code gate (PR-07) | D10: ST-107 | E10: 5 | F10: Claude | G10: Done-in-code | H10: src/claims.ts is the single source; docs/TRUST_PAGE.md rewritten (real subprocessors, 4 granular scopes, "Not yet" section); test/claims.test.ts asserts doc↔code↔config, refuses PostHog/Sentry/Stripe/SOC2/SSO/residency claims; also gates PRICING_PAGE banner and LISTING_COPY hold. Price-matrix extension of the gate lands with ST-136.
A11: S13-08 | B11: S13 | C11: Threat model + abuse cases document | D11: ST-108 | E11: 2 | F11: Claude | G11: Done | H11: docs/THREAT_MODEL.md: trust boundaries, the rule ("tenant identity always comes from the platform"), AC-1…AC-6 incl. PR-01 as permanent abuse case, what an owner session reaches, four standing rules.
A12: S14-01 | B12: S14 | C12: Full typed API client (PR-03) | D12: ST-109 | E12: 5 | F12: Claude | G12: Done-in-code | H12: web/api.ts covers all 48 client-callable routes with typed responses; ApiError carries status+code+retry; userFacingError maps every status to copy. Pinned: panels.test.tsx "covers every product route with a typed method".
A13: S14-02 | B13: S14 | C13: Client-reachability gate (route→client) | D13: ST-110 | E13: 5 | F13: Claude | G13: Done | H13: Product-agnostic; every route in app.ts must be referenced by web/api.ts or excused with a reason in test/client-reachability-allowlist.json (21 excused: webhook, OAuth, operator). test/clientReachability.test.ts fails the build otherwise. Portable to siblings (Handover #28/#33).
A14: S14-03 | B14: S14 | C14: Automatic meeting → CRM pipeline with review_required default (PR-04) | D14: ST-111 | E14: 8 | F14: Claude | G14: Done-in-code (pending live) | H14: transcripts.ts stage(): CRM adapter + mapping + feature enabled → pending_review (default) or queued; derivedFields; exactly one job per meeting under redelivery; approve/reject idempotent; POST /crm/review-mode. Pinned: s14.test.ts ST-111 block; server.test.ts "auto-approved ingest through the real graph"; test needs live Zoom for the webhook half (PENDING LIVE for S9-01).
A15: S14-04 | B15: S14 | C15: Durable notes and insights (PR-13) | D15: ST-112 | E15: 5 | F15: Claude | G15: Done-in-code | H15: notesStore.ts + insightStore.ts (in-memory) and PostgresNotesStore/PostgresInsightStore (notes_sessions, note_entries, meeting_insights); NotesService fully async; purge wired; docs/PERSISTENCE.md updated. Pinned: storeContract.test.ts NotesStore/InsightStore blocks (each case runs twice).
... A30: S16-04 | B30: S16 | C30: Published WER + field-accuracy benchmark (≥50 real calls) — closes LC-7 | D30: ST-127 | E30: 8 | F30: Claude + Senthil (corpus) | G30: Backlog | H30: Needs a consented corpus (PD-06 test 2 is the pilot).
A31: S16-05 | B31: S16 | C31: Locale surface: hi/ta copy, Indian date/number/currency | D31: ST-128 | E31: 3 | F31: Claude + Senthil (corpus) | G31: Backlog
A32: S17-01 | B32: S17 | C32: Live CRM OAuth per provider (HubSpot/Salesforce/Zoho) — closes LC-6 | D32: ST-129 | E32: 8 | F32: Claude + Senthil (creds) | G32: Backlog | H32: Needs sandbox accounts (Handover #3). /crm/connect still says sandbox.
A33: S17-02 | B33: S17 | C33: Object and field discovery from CRM schema | D33: ST-130 | E33: 5 | F33: Claude + Senthil (creds) | G33: Backlog | H33: After ST-129.
A34: S17-03 | B34: S17 | C34: Mapping UI with dry-run and per-field diff | D34: ST-131 | E34: 8 | F34: Claude + Senthil (creds) | G34: Backlog | H34: CrmPanel mapping form (ST-113) is the seed; dry-run/diff not built.
A35: S17-04 | B35: S17 | C35: Association and multi-object writeback; participants matched to contacts | D35: ST-132 | E35: 5 | F35: Claude + Senthil (creds) | G35: Backlog | H35: Replaces meetingRecordId() zoom-meeting:<id> stand-in.
A36: S17-05 | B36: S17 | C36: Failure surface and replay; HubSpot rate-limit compliance; ≥95% success tracking | D36: ST-133 | E36: 5 | F36: Claude + Senthil (creds) | G36: Backlog | H36: GET /crm/jobs + drain retry (ST-113) is the seed; dead-letter view and plain-language provider errors not built.
A37: S17-06 | B37: S17 | C37: HubSpot marketplace listing (3 installs to list, 60 to certify) | D37: ST-134 | E37: 5 | F37: Claude + Senthil (creds) | G37: Backlog | H37: Second marketplace on the critical path; not previously in the tracker (R-M7).
A38: S17-07 | B38: S17 | C38: CRM writeback idempotency key (account, meeting, object, field-set) | D38: ST-135 | E38: 3 | F38: Claude + Senthil (creds) | G38: Backlog | H38: ST-111 already guarantees one job per meeting via the insight; the adapter-level key lands with live adapters.
A39: S18-01 | B39: S18 | C39: Resolve the pricing model (PR-05); gate served matrix vs published page | D39: ST-136 | E39: 3 | F39: Claude (after PD-01) | G39: Backlog | H39: DECISION PENDING (PD-01) banner in docs/PRICING_PAGE.md, enforced by test/claims.test.ts until the numbers agree. Resolution = one decision applied to PLANS, /pricing, page, listing.
A40: S18-02 | B40: S18 | C40: Payment processor integration (cards, subscriptions, tax, webhooks → markPaid/paymentFailedTick) | D40: ST-137 | E40: 8 | F40: Claude (after PD-01) | G40: Backlog | H40: Retires two reachability allowlist entries (billing.ts markPaid/paymentFailedTick); dunning now has a sender (ST-115).
A41: S18-03 | B41: S18 | C41: Zoom Marketplace billing route reconciled nightly — closes live half of LC-10 | D41: ST-138 | E41: 5 | F41: Claude (after PD-01) | G41: Backlog | H41: Needs the Zoom app (Handover #2).
A42: S18-04 | B42: S18 | C42: Seat detection from measured distinct active users (PR-12) | D42: ST-139 | E42: 5 | F42: Claude (after PD-01) | G42: Backlog | H42: telemetry.activeDays already records distinct active days per account (v042) — the input exists; the derivation does not.
A43: S18-05 | B43: S18 | C43: Feature entitlement matrix enforced in code (deal risk / audit log above Starter) | D43: ST-140 | E43: 3 | F43: Claude (after PD-01) | G43: Backlog | H43: Depends on PD-01 and PD-04.
... A54: S20-04 | B54: S20 | C54: Design partners + first 10 paying installs, 3 reviews, activation >40% — closes G-02 | D54: ST-151 | E54: 3 | F54: Senthil | G54: Backlog | H54: Activation now measured (ST-141).

Sheet Senthil_Handover
A1: SENTHIL HANDOVER — every remaining MeetSync item; nothing else is codeable
A2: RENUMBERED 13 Sep 23:15. Numbers 8-14 each appeared TWICE: the original list ran 1-14 and every item added during the day restarted at 8, so "Handover #8" referred to two different things and every reference made today was ambiguous. Rows are in their original order and now numbered 1-35 uniquely; references in the Sprint_Tracker_Log to a number below 15 predate this and should be read by the item text, not the number.
A3: # | B3: Category | C3: Item | D3: Refs | E3: What Claude needs back | F3: Unblocks | G3: Status | H3: Priority (added v039)
A4: 1 | B4: Decision | C4: D15: ratify build mode — (a) parallel portfolio builds or (b) order swap | D4: Decisions D15 | E4: One word: (a) or (b) | F4: Portfolio governance; ten concurrent builds currently unratified | G4: Open | H4: P3 — needs you or a live install
A5: 2 | B5: Credentials | C5: Create Zoom Marketplace dev app, scopes per docs/SECURITY_SCOPES.md | D5: S9-01, LC-1 | E5: Client id/secret + webhook secret (or do live install together) | F5: Live install, real webhook shapes (D-M3/R-M5), SDK handshake -> converts FIVE UI-complete surface stories (25 pts) to Done + unlocks ST-094 screenshots | G5: Open | H5: P1 — unblocks the most
A6: 3 | B6: Credentials | C6: HubSpot/Salesforce/Zoho sandbox accounts | D6: S9-03, LC-6 | E6: Sandbox creds or OAuth session | F6: LC-6 live writeback runs; adapter contract verification | G6: Open | H6: P3 — needs you or a live install
A7: 4 | B7: Infra | C7: Staging environment + blue/green slots + vault | D7: S9-08/10, ST-066/088/092 | E7: Provider choice + access | F7: k6 5x run, deploy live-verify, encryption-at-rest, chaos/backup drills ST-090/091 | G7: Open | H7: P3 — needs you or a live install
A8: 5 | B8: Decision | C8: Listing copy: pick variant A (CRM-hygiene) or B (rep-time) | D8: ST-093, docs/LISTING_COPY.md | E8: One word: A or B | F8: Final listing copy -> assets ST-094 | G8: Open | H8: P3 — needs you or a live install
A9: 6 | B9: Human | C9: Record 2-min demo video + 5 screenshots (demo-mode gives populated screens) | D9: ST-083/094, LC-9 | E9: Recordings meeting platform specs | F9: Listing asset pack | G9: Open | H9: P3 — needs you or a live install
A10: 7 | B10: Human | C10: Pen-test / security evidence for review pack | D10: ST-068, LC-2 | E10: Vendor report or self-attest pack | F10: Zoom security review | G10: Open | H10: P3 — needs you or a live install
A11: 8 | B11: Human | C11: Legal review: recording-consent UX per region | D11: LC-3, R-M2 | E11: Legal sign-off note | F11: Compliance gate | G11: Open | H11: P3 — needs you or a live install
A12: 9 | B12: Vendor | C12: In-app chat vendor + staffed hours (<4 business-hr SLA) | D12: ST-081 | E12: Vendor pick (Intercom/Crisp/Plain) | F12: S10 support story; intake wiring on request | G12: Open | H12: P3 — needs a vendor
A13: 10 | B13: Human | C13: Submission dry-run by second reviewer vs Zoom checklist | D13: ST-097 | E13: Findings list | F13: Real submission | G13: Open | H13: P3 — needs you or a live install
A14: 11 | B14: Human | C14: Publish pricing + trust + help content to marketing site | D14: ST-095/096/080 drafts | E14: Site/hosting choice | F14: Public pages live | G14: Open | H14: P3 — needs you or a live install
A15: 12 | B15: Human | C15: Design partners: 3+ weekly actives, NPS pulse; 10 launch reviews scheduled | D15: S7 exit, ST-100 | E15: Partner list + intros | F15: S7 exit evidence; launch reviews | G15: Open | H15: P3 — needs you or a live install
A16: 13 | B16: Human | C16: WCAG AA pass on live UI | D16: ST-089 | E16: Access to rendered surface | F16: Accessibility gate | G16: Open | H16: P3 — needs you or a live install
A17: 14 | B17: Live data | C17: Post-launch: search-term data accrues automatically | D17: ST-099 | E17: Nothing — just launch | F17: SEO iteration 1 (pipeline already live) | G17: Auto
A18: 15 | B18: Deployment | C18: Generate and store two new secrets before any deploy: MEETSYNC_SESSION_SECRET (32+ chars, signs session tokens and OAuth state) and MEETSYNC_OPERATOR_TOKEN (gates /admin and /analytics). loadConfig refuses to start without them. | D18: M-F11, M-F12 | E18: Two values in your secret store (do not send them to me) | F18: Any deployment of v013 onward | G18: Open | H18: P1 — blocks any deploy
A19: 16 | B19: Disposition | C19: OBS-M1 circuit-breaker half-open resets the failure count entirely — same shape as FlowCast OBS-002 and VoiceBridge OBS-V2. Wants one portfolio ruling. | D19: Review_Findings OBS-M1 | E19: Fix everywhere / leave everywhere | F19: Closes the same observation on three products | G19: Open | H19: P2 — a decision only
A20: 17 | B20: Disposition | C20: OBS-M2 re-installing after delete-my-data but before the sweep restores the archived account. Product question: should an explicit deletion be reversible? | D20: Review_Findings OBS-M2 | E20: Reversible / irreversible | F20: Deletion semantics in docs/DATA_FLOW.md | G20: Open | H20: P2 — a decision only
A21: 18 | B21: Artifact | C21: Product workbook is still at v007 (5 Sep). The v009 as-built re-baseline is owed and now further out of date — v013 adds auth, tenancy, csv and ledger modules the workbook does not mention. | D21: Portfolio artifact discipline | E21: Go-ahead to rebuild it in a dedicated sitting | F21: Workbook matching the shipped code | G21: CLOSED 13 Sep 10:01 — released as workbook v009
A22: 19 | B22: Artifact | C22: If you still hold claude_v008_meetsync_zoom_product_workbook (10 Sep), send it. v009 was rebuilt from v007 plus this tracker, so any edit that lived only in v008 and was never mirrored here is not carried forward. | D22: Workbook v009 Version_Control + Risk_Register | E22: The v008 file, or confirmation it can be treated as superseded | F22: Closes the only known provenance gap in the artifact chain | G22: Open | H22: P3 — needs you or a live install
A23: 20 | B23: Deployment | C23: Set BASE_URL to the real deployed origin before the first live install. The OAuth redirect_uri is derived from it (BASE_URL + /oauth/callback) and must match the OAuth Redirect URL registered on the Marketplace app byte for byte, or Zoom rejects the code exchange. | D23: VER-M02 | E23: The production origin | F23: A working install; without it the exchange fails | G23: Open | H23: P1 — blocks any deploy
A24: 21 | B24: Monitoring | C24: Put /analytics/webhook-rejections on whatever you check daily once deployed. Zoom disables the webhook subscription after six failed 72-hour revalidations and nothing on our side raises an alarm — the symptom is simply that meeting events stop arriving. | D24: VER-M06, docs/RUNBOOK.md | E24: Nothing yet — just know it exists | F24: Avoids a silent dead integration | G24: Open | H24: P3 — needs you or a live install
A25: 22 | B25: Quality | C25: Accessibility manual pass before submission: contrast, focus visibility, keyboard traps, 200% zoom, and a real screen reader inside the Zoom client. The automated suite cannot reach any of these. About an hour once the dev app exists. | D25: A11Y_Audit sheet, docs/PERF_BUDGETS.md | E25: Pass/fail notes per item | F25: Lets us claim WCAG AA honestly; it is a Marketplace review surface | G25: Open | H25: P1 — unblocks the most
A26: 23 | B26: Decision | C26: Continue the persistence work, or stop here? Billing is the recommended next slice: a restart currently reverts every account to no_subscription, which un-gates paid features and zeroes the revenue metrics. Then the RBAC audit log, because an erasure record that evaporates is worse than no record. | D26: docs/PERSISTENCE.md, OBS-M3 | E26: Continue / stop; if continue, confirm billing first | F26: Multi-instance deployment; a deletion guarantee we can prove | G26: Answered through 11:03 — billing (v017) and audit log (v018) both done. Superseded by #18 for what remains.
A27: 24 | B27: Deployment | C27: A PostgreSQL 16 instance and its connection settings (PGHOST/PGPORT/PGUSER/PGPASSWORD/PGDATABASE) before any deployment expected to survive a restart. PostgresStore.migrate() is idempotent and safe on every boot. | D27: docs/PERSISTENCE.md | E27: A database instance (do not send me the credentials) | F27: Durable tokens, retention and deletion | G27: Open | H27: P1 — blocks any deploy
A28: 25 | B28: Decision | C28: Two shape calls before any more persistence work. (a) Tenant feature state: split settings from imported records into separate tables? I think yes — imported CSV is unbounded user data and settings are not — but it changes the data model, so it is your call. (b) CRM writeback queue: it is in-flight work rather than state. Does MeetSync want a job queue, and does it own one or borrow one (SQS, pg-boss, Redis)? That decision has infrastructure cost attached. | D28: docs/PERSISTENCE.md, OBS-M3 | E28: (a) split or single table. (b) own / borrow / defer | F28: The last two pieces of process-local state, and multi-instance deployment | G28: CLOSED 13 Sep 11:57 — (a) tenant feature state v023, (b) CRM queue v024 built as own-a-queue in Postgres. Reversible: CrmStore is the swap surface if you want a borrowed queue instead.
A29: 26 | B29: Monitoring | C29: After any deploy, check GET /admin/retention-sweep (operator token). A scheduler that is not running is invisible from outside — accounts just accumulate past their retention date and the first sign of trouble is a compliance question you cannot answer. It deliberately swallows its own errors so one bad night does not kill the loop, which means a persistent failure shows up only there, as a non-null error on recent runs. | D29: GAP-2, docs/RUNBOOK.md | E29: Nothing yet — just know it exists | F29: Keeps the published retention policy actually true | G29: Open | H29: P3 — needs you or a live install
A30: 27 | B30: Decision | C30: What should 'Done-in-code' mean? It is honest about a module and misleading about a feature — 78 stories held that status while most of the product had no HTTP surface. (a) Keep the label and add a Reachable column, so a row can say 'written' and 'invokable' separately. (b) Redefine it to require a caller and re-baseline the counts downward. I recommend (a): the counts stay comparable with the sibling products and the missing property becomes visible rather than implied. I have changed no story status pending your call. | D30: GAP-3, Reachability sheet, D13 | E30: (a) or (b) | F30: Whether the tracker counts mean what a reader assumes they mean — across all 12 products | G30: CLOSED 13 Sep 11:32 — option (a) executed; all 100 rows classified in Traceability_Matrix columns L and M
A31: 28 | B31: Portfolio | C31: test/reachability.test.ts is ~120 lines and product-agnostic apart from its allowlist. Copying it into the other eleven products would cost minutes each and would answer, for each one, whether it has MeetSync's problem. Given GAP-3 found two entire features here that nothing could invoke, I would not assume this product is the outlier. | D31: GAP-3, Reachability sheet | E31: Go-ahead to port it, or a product to try it on first | F31: Tells you which of the twelve have unreachable features, cheaply | G31: Artifact delivered 13 Sep 16:38 — claude_v001_reachability_gate_portable_20260913_1638.zip, with five-minute porting instructions. Still open: actually running it, which needs the sibling repos.
A32: 29 | B32: Decision | C32: Persistence (Handover #18) is the one piece of 'do all properly' I deliberately did NOT start this sitting. Tenant feature state needs the settings/records split decided first, and converting FeatureEngine to async is the largest ripple left — starting it without finishing would leave the tree broken, and building the store without wiring it would repeat GAP-1 exactly. Say go and it is the whole of the next sitting. | D32: Handover #18, docs/PERSISTENCE.md | E32: Go-ahead, plus the (a) settings/records split call | F32: The last process-local state; multi-instance deployment | G32: CLOSED 13 Sep 11:57 — (a) tenant feature state v023, (b) CRM queue v024 built as own-a-queue in Postgres. Reversible: CrmStore is the swap surface if you want a borrowed queue instead.
A33: 30 | B33: Decision | C33: CRM writeback queue — the last piece needing your call rather than my judgement. It is in-flight work, not state, so making it durable is really: does MeetSync want a job queue, and does it own one (a Postgres table, no new infrastructure, reversible) or borrow one (SQS, Redis, pg-boss)? I lean to owning one in the database we already run, because it adds nothing to deploy. The webhook dedupe set wants a different answer again — a shared cache with a TTL matching the five-minute replay window, not a table. | D33: Handover #18b, docs/PERSISTENCE.md | E33: own / borrow / defer | F33: The last durability gap that loses customer work rather than history | G33: CLOSED 13 Sep 11:57 — (a) tenant feature state v023, (b) CRM queue v024 built as own-a-queue in Postgres. Reversible: CrmStore is the swap surface if you want a borrowed queue instead.
A34: 31 | B34: Decision | C34: Webhook dedupe is the LAST thing blocking a second instance. It wants a shared cache with a TTL matching the five-minute replay window, not a table — Redis or equivalent, which is new infrastructure. Alternative: a Postgres table with a TTL sweep, slower but nothing new to run. Notes sessions and telemetry are also still process-local but neither blocks multi-instance. | D34: docs/PERSISTENCE.md | E34: shared cache / Postgres table / defer | F34: Running more than one instance of MeetSync | G34: CLOSED 13 Sep 16:28 — built as a Postgres table with an atomic claim rather than a shared cache. Nothing new to deploy; DedupeStore is the swap surface if you want Redis later.
A35: 32 | B35: Deployment | C35: Before scaling to more than one instance: the retention scheduler runs on EVERY instance, so sweeps can overlap across processes. That is safe — the purge is idempotent — but /admin/retention-sweep history is per instance, not global, so do not read one instance's history as the whole picture. If you would rather only one instance sweeps, that needs a leader election or an external cron, which is a decision rather than a fix. | D35: docs/RUNBOOK.md, E044 | E35: Nothing yet — just know it before scaling out | F35: Avoids misreading sweep history after scale-out | G35: Open | H35: P3 — needs you or a live install
A36: 33 | B36: Portfolio | C36: To run the gate against a sibling product, either open a session with that repository available or paste its src/ listing and I will run the audit here. Given it found two entire unreachable features on MeetSync — a product that had already passed two adversarial reviews at 100% coverage — I would not assume this one is the outlier. TeleField and VoiceBridge are the obvious first candidates: both are code-phase complete with large story counts. | D36: Handover #21, Reachability sheet | E36: A sibling repo in a session, or a go-ahead on which to start with | F36: Tells you which of the twelve have unreachable features, cheaply | G36: Open | H36: P2 — cheap, portfolio-wide
A37: 34 | B37: Deployment | C37: Generate MEETSYNC_TOKEN_KEY before the next deploy: 32 random bytes, base64. `openssl rand -base64 32` gives exactly the right shape. The app refuses to boot without it. Keep it OUT of the database backups — if the key travels with the dump, the encryption buys nothing. If you ever rotate it, put the old value in MEETSYNC_TOKEN_KEY_PREVIOUS or every installed account loses its Zoom connection at once. | D37: ST-066, docs/SECURITY_SCOPES.md | E37: The key in your secret store (do not send it to me) | F37: A database dump stops being a set of working Zoom credentials | G37: Open | H37: P1 — blocks any deploy
A38: 35 | B38: Process | C38: Reviewing my own recent output found something three times today: the fabricated churn alert (v027), the plaintext tokens in the backup snapshot (v031), and now SR-01/SR-02. All three were in code written the same day, all passed their tests, and none would have been found by the cold review or the reachability gate. Worth making a standing step — a review pass over the previous sitting before starting the next one — rather than leaving it to whether I think of it. | D38: E057, E058, E048, E056 | E38: Agreement to make it a standing step | F38: Catches the defect class that new code introduces into code that was correct | G38: Open | H38: P2 — cheap, portfolio-wide
A39: 36 | B39: Decision | C39: PD-01 pricing model + number (PR-05). Per-seat or flat, and the price. Recommendation: per-seat $12–$18/seat/month, 5-seat minimum. | D39: Decisions PD-01, ST-136, docs/PRICING_PAGE.md | E39: One line: model + number | F39: S18; HubSpot listing; the DECISION PENDING banner comes off | G39: Open | H39: P1 — unblocks the most
A40: 37 | B40: Decision | C40: PD-02 build the intelligence (S15+S16, 71 pts) or reposition as a rules engine. Determines listing copy, price and whether S15/S16 exist. | D40: Decisions PD-02, PR-02 | E40: One word: build / rules | F40: S15, S16, ST-149 listing copy | G40: Open | H40: P1 — unblocks the most
A41: 38 | B41: Deployment | C41: Mail transport: MEETSYNC_MAIL_ENDPOINT (https), MEETSYNC_MAIL_TOKEN, MEETSYNC_MAIL_FROM — all three or none. Payload {from,to,subject,text} + bearer (Postmark/Resend/SES-API shape). Supersedes "pick a mail transport" (order 6): the seam and transport exist; only the account is missing. | D41: ST-115, docs/RUNBOOK.md "Mail transport" | E41: Vendor pick + the three values in your secret store | F41: 6 PARTIAL notification stories become deliverable; weekly digest; dunning once ST-137 lands | G41: Open | H41: P2 — a config only
A42: 39 | B42: Deployment | C42: MEETSYNC_CORS_ORIGINS: the https origin(s) of any web dashboard host beyond Zoom's client (which is always allowed). Leave unset for the in-client panel alone. | D42: ST-104 | E42: Origin list, or "none" | F42: Browser access from a dashboard host | G42: Open | H42: P3 — needs you or a live install
A43: 40 | B43: Decision | C43: PD-03 SMB-first or enterprise-first; PD-04 keep or cut F4 deal risk. | D43: Decisions PD-03, PD-04 | E43: Two words | F43: Whether S19 blocks S20; S15/S16 scope; pricing matrix | G43: Open | H43: P2 — a decision only
A44: 41 | B44: Human | C44: PD-06 three demand tests (RevOps n=5 pricing conversations; 10 Hinglish calls vs Zoom; 10 Workplace-paying teams willingness-to-switch). Days, not sprints; each has a kill signal. | D44: PD-06, review §4.6 | E44: Results + kill-signal verdicts | F44: Validates or invalidates the wedge before S15–S17 spend | G44: Open | H44: P1 — unblocks the most
A45: 42 | B45: Live data | C45: Zoom app (Handover #2) is now the right first move again: S13 closed (PD-05 hold lifted). On the first real install check GET /session/me returns your real Zoom user and role, and that /oauth/start with a WRONG account_id hint is refused with tenant_mismatch. | D45: ST-101/102, s13.test.ts | E45: Two observations from the live install | F45: Converts ST-101/102/103 from Done-in-code to verified; unblocks ST-113/114 live | G45: Open | H45: P1 — unblocks the most
A46: 43 | B46: Portfolio | C46: tools/reachability/routes.ts (route→client gate) is product-agnostic like its sibling: copy, point at app.ts + typed client, empty allowlist. Same five minutes per product; finds the PR-03 class (server routes no client calls). | D46: ST-110, Handover #28/#33 | E46: Go-ahead, or a product to try first | F46: Tells you which of the twelve have a mock front end | G46: Open | H46: P2 — cheap, portfolio-wide
A49: WHAT TO DO FIRST — prioritised view of the open items (re-cut v040 after Perplexity Review V001)
A50: Ordered by what it unblocks, not by when it was raised. Everything in P1 is blocking something that cannot start without it.
A51: Order | B51: Do this | C51: Why it comes first | D51: Then what opens up
A52: 0 — first | B52: Decide PD-01 and PD-02 (pricing; build vs rules engine) | C52: They gate 71 of the 248 new points, the listing copy and the price — before them, the plan cannot be sequenced | D52: S15–S18 open; the two gated banners come off
A53: 0 — alongside | B53: Run the three demand tests (PD-06) | C53: Days, not sprints, and any one failing should change the plan before the S15–S17 spend | D53: Wedge validated or the plan replaced
A54: 1 | B54: Create the Zoom Marketplace dev app and complete the OAuth install (hold lifted: S13 closed) | C54: Seven stories are PENDING LIVE on nothing else, and the panel surfaces cannot be verified in any other way. docs/SECURITY_SCOPES.md now lists the granular scope names and the in-client capabilities, so the console steps are unambiguous. | D54: 7 pending-live stories become verifiable; the panel UI stops being RTL-tested-only
A55: 2 | B55: Generate the four deployment values: MEETSYNC_SESSION_SECRET, MEETSYNC_OPERATOR_TOKEN, MEETSYNC_TOKEN_KEY, BASE_URL | C55: The app refuses to boot without the first three, and the fourth decides the OAuth redirect_uri, which Zoom matches byte for byte. openssl rand -base64 32 gives the right shape for the token key. Keep it OUT of the database backups. | D55: Any deployment at all
A56: 3 | B56: Provision a PostgreSQL 16 instance | C56: Six stores are durable and every guarantee — token wipe, retention purge, delete-my-data, the entitlement gate — is process-local without it. migrate() runs on every boot and is idempotent. | D56: Durability, multi-instance, the restore drill against real data
A57: 4 | B57: Rule on OBS-M1 (breaker half-open) and OBS-M2 (re-install after deletion) | C57: Both are decisions, not work. OBS-M1 is portfolio-wide — the same shape is open on FlowCast and VoiceBridge, so one ruling settles three products. | D57: Closes the last two open dispositions
A58: 5 | B58: Run the portable reachability gate against one sibling product | C58: Five minutes per product. On MeetSync it found two entire features nothing could invoke, in code that had already passed two adversarial reviews at 100% coverage. | D58: Tells you which of the twelve share the problem
A59: 6 | B59: Set the three MEETSYNC_MAIL_* values (transport exists since ST-115) — or decide there is none | C59: Six PARTIAL rows are one config now, not one decision: the seam, the transport and the delivery record all ship in v045 | D59: 6 partial stories (ST-115 → REACHABLE)
A60: 7 | B60: The human-time items: pen-test vendor, chat vendor, screenshots and demo video, listing copy A/B pick, second-reviewer dry run, design-partner outreach, consent legal review, manual accessibility pass | C60: None of these can be done from a session. The accessibility pass needs a live install and is a Marketplace review surface, so it pairs naturally with item 1. | D60: The remaining backlog and most of the launch checklist

Sheet Review_Findings
A1: REVIEW FINDINGS — MeetSync adversarial cold review (M-F, 13 Sep) + external verification (VER-M) + self-review (SR) + Perplexity external review V001 (PR, 16 Sep; absorbed v040)
A2: Every FIXED row is pinned by a regression test that fails against v012. Every OBSERVATION row is left in the code deliberately and needs Senthil's disposition. Pass 1 = the eight highest-risk modules; pass 2 = the remaining twelve plus the web surface. Class column names the sibling product where the same defect shape was first found.
A3: ID | B3: Module | C3: Severity | D3: Finding — what was wrong and why it matters | E3: Disposition | F3: Class / sibling | G3: Pinned by
A4: M-F01 | B4: billing, app | C4: Blocking | D4: paymentFailedTick set subscription.readOnly after the 7-day dunning grace, and not one route ever read it. An account that stopped paying kept full write access indefinitely. Fixed by an entitlement state (ok / trial_expired / past_due_read_only / cancelled / no_subscription) that mutating routes consult; reads are pinned open so a lapsed account can still see and export its own data. | E4: FIXED | F4: VoiceBridge F-V07 | G4: app.test.ts "mutating routes stop at an expired trial…"
A5: M-F02 | B5: billing | C5: Blocking | D5: trialDaysRemaining counted down to zero and nothing consulted it. An account that never added a card kept the product free for ever. Same entitlement gate; no_subscription deliberately does NOT block, since that is the freshly-installed state before the trial starts. | E5: FIXED | F5: VoiceBridge F-V03 | G5: app.test.ts entitlement test
A6: M-F03 | B6: lifecycle, all | C6: Blocking | D6: retentionSweep deleted the account row and nothing else. The tenant's notes, imported CSV records, CRM writeback queue and audit trail, the analytics funnel row, RBAC entries and the billing subscription all survived both the uninstall-plus-retention path and the self-serve delete-my-data path — a direct breach of the published deletion policy. Fixed with a PurgeTarget registry cleared in the same pass, and the delete route now runs the sweep on the request path instead of waiting for an operator. The data.delete audit rows themselves are retained on purpose: they are the proof of erasure. | E6: FIXED | F6: VoiceBridge F-V01 / FlowCast F-007 | G6: s9.test.ts "deleting an account clears its tenant graph…"
A7: M-F04 | B7: features, tenancy | C7: Blocking | D7: One FeatureEngine instance served the whole process while the routes around it were per-organisation. One workspace's imported records, extraction rules, configured defaults, notes sessions, CRM queue and audit trail were readable and writable by every other workspace on the deployment. Fixed with a TenantRegistry allocating one object graph per account, resolved from the verified session; the graph is also the unit that deletion drops. | E7: FIXED | F7: new — no sibling precedent | G7: app.test.ts "feature state is isolated per account"
A8: M-F05 | B8: crm | C8: High | D8: The writeback retry loop ran all three attempts back to back with no delay, so a CRM answering 429 was hammered three times in a few milliseconds — the fastest possible way to turn a soft rate-limit into a hard one. Fixed with exponential backoff plus full jitter, injectable so the schedule is asserted rather than slept through. | E8: FIXED | F8: VoiceBridge F-V06 | G8: review.test.ts "writeback retries back off exponentially"
A9: M-F06 | B9: telemetry | C9: Medium | D9: weeklyEmail printed the all-time error count under an "errors(7d)" label, so the weekly number only ever rose and a quiet week read as the worst week yet. Windowed properly. | E9: FIXED | F9: new | G9: review.test.ts "the weekly email counts only the trailing seven days"
A10: M-F07 | B10: billing | C10: High | D10: Accepting the cancellation save-offer dropped the account to starter without the seat check every other plan change enforces, so a 50-seat team account landed on a 10-seat plan and every later seat rule read a state that cannot legitimately exist. Now refused with a typed error. | E10: FIXED | F10: new | G10: review.test.ts "the save-offer refuses a downgrade…"
A11: M-F08 | B11: zoomAuth | C11: High | D11: refreshTokens mapped every non-200 to 401 "Refresh rejected", so a Zoom 5xx — their outage, nothing to do with our grant — was indistinguishable from a revoked token and pushed the workspace down the reconnect path. exchangeCode already drew this distinction; refresh now matches it. | E11: FIXED | F11: new | G11: review.test.ts "a Zoom 5xx during refresh is an upstream error"
A12: M-F09 | B12: billing, app | C12: High | D12: Seat counts came straight from the request body and were only compared against the plan ceiling, so 0, -5 and 2.5 all passed and produced zero or negative invoices. Validated at every entry point; the route answers 422 invalid_seats. | E12: FIXED | F12: VoiceBridge F-V04 | G12: review.test.ts "seats must be a whole number of at least one"
A13: M-F10 | B13: features, csv | C13: High | D13: CSV import was split(',') per line, so any exported field containing a comma, a quoted newline or an escaped quote — all legal RFC-4180 and common in meeting-note exports — was either rejected as ragged or silently sliced in half. Replaced with a real RFC-4180 parser in a shared csv.ts. | E13: FIXED | F13: ShiftDesk F-010 / TestPulse | G13: review.test.ts csv block
A14: M-F11 | B14: app, auth, web/api | C14: Blocking | D14: The authentication boundary was the x-role and x-user request headers, which the browser sets. Any caller could send x-role: owner and act as the owner of any workspace, including deleting its data. Fixed with HMAC-signed session tokens minted server-side at the end of the verified OAuth install; the web client can no longer state its own role at all, and a session for one workspace is refused on another's routes. Header auth survives only behind MEETSYNC_DEV_HEADER_AUTH=1, defaulted off. | E14: FIXED | F14: new — most serious finding in this review | G14: app.test.ts + review.test.ts auth blocks
... A42: SR-09 | B42: sessionStore | C42: Medium | D42: Found by the contract suite on its first run against the new store: InMemorySessionStore.revoke() overwrote a deny row's expiry while PostgresSessionStore used GREATEST — so in tests a second revoke could quietly un-revoke a session by lowering its expiry, and in production it could not. The two-implementation rule caught a divergence the same sitting it was written. | E42: FIXED v045 — in-memory revoke is monotonic like the SQL upsert | F42: SR-05/SR-06 class (implementations agreeing on everything except the thing that matters) | G42: storeContract.test.ts "revoking the same jti again keeps the later expiry, never an earlier one"

Sheet Verification_Sweep
A1: EXTERNAL VERIFICATION SWEEP — MeetSync code vs live Zoom platform documentation, 13 Sep 2026
A2: Why this is a separate exercise from the cold review: a cold review reads the code against itself and against defect patterns. It cannot find a place where the code is internally consistent, fully tested, and wrong about the outside world. Every finding below was invisible at 100% coverage because the tests asserted our own shape back to us. Source column cites the Zoom documentation page checked.
A3: ID | B3: Area | C3: Severity | D3: Finding | E3: Fix | F3: Verified against | G3: Pinned by
A4: VER-M01 | B4: OAuth token exchange | C4: LIVE-BLOCKING | D4: We sent client_id and client_secret in the form body. Zoom authenticates the client with an HTTP Basic header containing base64 of "client_id:client_secret". The install would have been rejected on the first live call. | E4: FIXED — basicAuthHeader(); HttpPost now carries headers. The body carries no secret at all. | F4: developers.zoom.us/docs/integrations/oauth | G4: zoomAuth.test.ts "sends Basic client credentials…"
A5: VER-M02 | B5: OAuth token exchange | C5: LIVE-BLOCKING | D5: redirect_uri was absent. Zoom lists it as required for grant_type=authorization_code and it must match the URL registered on the Marketplace app. | E5: FIXED — redirectUri(cfg) derived from BASE_URL and sent on every code exchange; the same value is used in /oauth/start. | F5: developers.zoom.us/docs/integrations/oauth | G5: zoomAuth.test.ts (same test asserts the exact body)
A6: VER-M03 | B6: OAuth refresh | C6: LIVE-BLOCKING | D6: Refresh had the same wrong client-authentication shape, so token renewal would have failed an hour after every install — the failure mode users would have seen as the app randomly logging itself out. | E6: FIXED — refresh uses the Basic header; body is grant_type + refresh_token only. | F6: developers.zoom.us/docs/integrations/oauth | G6: zoomAuth.test.ts "authenticates the refresh with the Basic header"
A7: VER-M04 | B7: Zoom Apps SDK boundary | C7: LIVE-BLOCKING | D7: web/sdk.ts was built around an API that does not exist. Three separate errors: zoomSdk.config({capabilities}) was never called, and every Zoom Apps API throws until it is; getMeetingContext() was assumed to return accountId, role and user, which it does not (user identity is getUserContext, and after M-F11 the role must come from the server session anyway); and inMeeting was read as a field of the meeting context rather than from getRunningContext(). All five in-meeting surface stories would have shown a panel stuck on 'Connecting…' with nothing logged — the VoiceBridge VER-V01 failure shape exactly. | E7: FIXED — loadPanelContext() configures capabilities, reads running context first, only asks for meeting context when actually in a meeting, and surfaces a config failure to the user instead of hanging. REQUIRED_CAPABILITIES is exported so the Marketplace app settings and the runtime call cannot drift. | F7: appssdk.zoom.us + developers.zoom.us Zoom Apps guides | G7: panels.test.tsx "Zoom Apps SDK boundary (VER-M04)" — 6 tests
A8: VER-M05 | B8: Scopes | C8: BLOCKS APP CREATION | D8: docs/SECURITY_SCOPES.md listed the classic scopes meeting:read, recording:read, user:read. Zoom replaced classic with granular scopes in April 2024; existing apps keep theirs, but any NEWLY created app gets granular scopes only — and MeetSync has no app yet, so those names are not selectable. Working from the old table would have wasted time in the console at exactly the step that unblocks 12 stories. | E8: FIXED — scope map rewritten to granular names with the :admin variants noted, plus the separate in-client SDK capability list (a second permission surface that is easy to miss entirely). | F8: developers.zoom.us/docs/api/webhooks#scopes; Zoom granular-scope migration notes | G8: Doc change; REQUIRED_CAPABILITIES pinned in tests
A9: VER-M06 | B9: Webhook subscription health | C9: HIGH | D9: Zoom revalidates every webhook endpoint every 72 hours and DISABLES the subscription after six consecutive failures, at which point MeetSync silently stops receiving meeting events. Zoom also never retries a 4xx, so every request we reject for verification reasons is an event permanently lost. Our own replay guard rejects anything more than five minutes from our clock — so server clock drift alone can kill the subscription, with no error on our side. | E9: FIXED (observability) — verification failures counted by reason and exposed at /analytics/webhook-rejections behind the operator token; RUNBOOK gains the monitoring thresholds and the recovery procedure. The guard itself is deliberately unchanged: widening it to dodge our own clock problems would weaken the replay defence. | F9: developers.zoom.us/docs/api/webhooks | G9: review.test.ts "webhook verification failures are counted by reason"
A10: VER-M07 | B10: Token lifetime | C10: MEDIUM | D10: The token response's expires_in was discarded. Zoom access tokens live one hour, so the only way the app could learn a token had expired was to take a 401 on a real user's request. | E10: FIXED — expiresAt stored with a 60s skew; ZoomClient refreshes a known-expired token before the call rather than after it fails. | F10: developers.zoom.us/docs/integrations/oauth | G10: review.test.ts "a known-expired access token is refreshed before the API call"
A11: VER-M08 | B11: Webhook HMAC | C11: VERIFIED CORRECT | D11: Signature construction checked line by line against Zoom's spec: message is v0:{x-zm-request-timestamp}:{raw body}, HMAC-SHA256 with the webhook Secret Token, hex, compared against x-zm-signature prefixed v0=. Ours matches exactly, including the constant-time comparison. | E11: No change | F11: developers.zoom.us/docs/api/webhooks | G11: webhooks.test.ts (existing)
A12: VER-M09 | B12: url_validation CRC | C12: VERIFIED CORRECT | D12: Challenge response is {plainToken, encryptedToken} where encryptedToken is the hex HMAC-SHA256 of plainToken under the Secret Token, answered 200 within three seconds. Ours matches. | E12: No change | F12: developers.zoom.us/docs/api/webhooks | G12: app.test.ts webhook block
A13: VER-M10 | B13: Deauthorization payload | C13: VERIFIED CORRECT | D13: Zoom's documented app_deauthorized payload carries account_id at the top level of payload. Cold-review pass 2 had already added that path alongside payload.object.account_id, so both shapes are handled and the M-F03 purge is what runs. | E13: No change | F13: developers.zoom.us/docs/integrations/oauth#deauthorization | G13: app.test.ts "deauthorization carries a top-level account_id too"

Sheet A11Y_Audit
A1: WCAG AA AUDIT — MeetSync panel surface, 13 Sep 2026
A2: Scope: all five panel components and the app shell, every render state, audited against wcag2a / wcag2aa / wcag21a / wcag21aa inside the same 100% gate as the rest of the suite. READ THE LAST SECTION BEFORE QUOTING THIS ANYWHERE: the automated result is clean, and clean is not the same as accessible.
A3: ID | B3: Criterion | C3: Finding | D3: Fix | E3: Pinned by
A4: A11Y-01 | B4: WCAG 4.1.2 Name, Role, Value | C4: Note status buttons carried aria-label="chip-N". An aria-label REPLACES an element's visible text for assistive technology, so the note's status — open/done/flag, the only reason the control exists — was hidden, and what a screen-reader user heard instead was 'chip 0, button'. This is the sharpest example of why an automated pass is not an audit: axe checks that an element HAS an accessible name, never whether the name is the right one. | D4: Accessible name now carries the state and the affordance: 'Status of note 1: open. Activate to change.' Tests address the button by data-testid so the name is free to be meaningful. | E4: a11y.test.tsx "a note status button announces its state"
A5: A11Y-02 | B5: WCAG 1.3.1 Info and Relationships | C5: Panels opened at h3 with no h1 or h2 anywhere above them, and the shell had no heading at all — the product name was a <strong>. Screen-reader users navigate by heading; a surface that starts at level 3 reads as though two levels of context were skipped and never provides the page title. | D5: Shell has a single h1; every panel opens at h2; CrmPanel's sub-sections stay h3 under it. | E5: a11y.test.tsx "every panel opens at h2 under a single h1"
A6: A11Y-03 | B6: WCAG 4.1.3 Status Messages | C6: Notes arrive during a meeting without any user action on the panel. Nothing announced them, so a screen-reader user had no way to know a note had landed short of re-reading the list. | D6: The notes list is a polite live region with its own accessible name. | E6: a11y.test.tsx "the notes list announces entries that arrive without user action"
A7: A11Y-04 | B7: WCAG 1.3.1 / 2.4.3 Focus Order | C7: The tab strip was plain buttons carrying aria-pressed, with nothing connecting a button to the content it switched. A user could hear which button was pressed but not that the region below was its panel, and all five buttons sat in the tab order. | D7: Real tablist / tab / tabpanel semantics with aria-controls and aria-labelledby in both directions, plus roving tabindex so the strip is one tab stop. | E7: a11y.test.tsx "tabs are real tabs and each one owns the panel it controls"
A9: STILL OPEN — cannot be closed by any automated suite
A10: A11Y-05 | B10: WCAG 1.3.1 Info and relationships (table semantics) | C10: The ST-114 review screen introduces the first data table in the product: the CRM fields that will be written. A table with no caption, column headers or row headers reads to a screen reader as a grid of unrelated cells. | D10: caption + th scope=col / scope=row; pinned by a11y.test.tsx "A11Y-05" | E10: a11y.test.tsx "A11Y-05 (ST-114): the review table names its columns and rows"
A11: Manual pass required before Marketplace submission | C11: Colour contrast (jsdom computes no styles, so axe skips the rule entirely), visible focus indicators, keyboard traps, zoom and reflow at 200%, and actual screen-reader behaviour inside the Zoom client — which embeds the panel in a webview no test environment here can simulate. Budget an hour against a real install. | D11: Not fixed — needs a live app (Handover #2) | E11: —
A12: How to describe this externally | C12: Report it as 'automated WCAG AA checks pass; manual pass outstanding', never as 'WCAG AA verified'. The four findings above were all green in axe before they were fixed, which is the whole argument for not overclaiming: automated rules cover a minority of the success criteria, and the ones they miss are disproportionately the ones that make a product unusable rather than merely imperfect. | D12: Applies to Launch_Checklist #2 and the listing copy | E12: —

Sheet Reachability
A1: CAPABILITY REACHABILITY AUDIT — GAP-3, 13 Sep 2026
A2: The question is not whether the code is correct — two cold-review passes answered that — but which HTTP route can reach it. A capability with no caller is not a feature; it is a library the customer cannot use. Re-run this audit after any sprint that adds services rather than routes.
A3: Capability | B3: Was reachable from | C3: Verdict before v020 | D3: Status after v020
A4: F4 deal risk — analyse, score | B4: nothing | C4: ZERO references in application code | D4: WIRED — POST /features/deal-risk/analyse
A5: F5 Indic pack — segment, wer, detectLang | B5: nothing | C5: ZERO references in application code | D5: WIRED — POST /features/indic/segment, /wer
A6: F1 notes — startSession, addEntry | B6: demo seeder only | C6: No way to take a real note | D6: WIRED — 5 routes under /meetings/:meetingId/notes
A7: F1 notes — setChip, closeSession, getSession | B7: nothing | C7: — | D7: WIRED
A8: F2 extraction — extract, addCustomRule | B8: demo seeder only | C8: No way to extract from a real meeting | D8: WIRED — POST /features/actions/extract, /rules
A9: F3 CRM — register, addMapping, enqueue, drain, auditTrail | B9: demo seeder only | C9: No way to configure or run a real writeback | D9: WIRED — 5 routes under /crm (sandbox adapter only; LC-6 open)
A10: FeatureEngine — addRule, setEnabled | B10: nothing | C10: Rule customisation and pause unreachable (ST-x03, ST-x08) | D10: WIRED — POST /features/:key/rules, /pause
A11: FeatureEngine — mute, unmute | B11: nothing | C11: Per-type notification mute unreachable (ST-x10) | D11: STILL UNREACHABLE — no notification delivery exists to mute
A12: Rbac.auditLog | B12: nothing | C12: ST-067 audit log was WRITE-ONLY; audit.read gated nothing | D12: WIRED — GET /orgs/:id/audit-log, gated by audit.read
A13: Billing lifecycle — changePlan, markPaid, paymentFailedTick, seatUsagePrompt, invoice, cancel | B13: nothing | C13: Upgrade, dunning, invoices and cancellation all unreachable | D13: STILL UNREACHABLE — needs a payment processor first; routes that move no money would be theatre
A14: ZoomClient.request (backoff + circuit breaker) | B14: nothing | C14: The entire API client is uncalled | D14: STILL UNREACHABLE — MeetSync never fetches from Zoom; transcripts arrive by webhook. May be premature rather than unwired — worth deciding before it rots
... A16: Onboarding — toggleSampleData, emptyState | B16: nothing | C16: Sample-data toggle and empty-state copy unreachable | D16: STILL UNREACHABLE — empty-state copy is duplicated in the panels; one of the two should go
A18: Why no earlier review caught this
A19: Defects of absence | B19: — | C19: The cold review read modules against defect patterns; the verification sweep read the code against Zoom's documentation. Neither asks who calls what, and a module that nothing calls is locally perfect. GAP-1 (no composition root), GAP-2 (no retention scheduler) and GAP-3 are the same class: invisible to any review that reads what is there. | D19: Three occurrences in one day on one product
A21: STORY-LEVEL ROLLUP (Traceability_Matrix column L, added v016)
A22: REACHABLE | B22: 60 of 100 | C22: a customer can invoke it today
A23: PARTIAL | B23: 14 of 100 | C23: part of the story is reachable; the rest is named in column M
A24: PENDING LIVE | B24: 7 of 100 | C24: blocked only on the Zoom dev app
A25: NOT REACHABLE | B25: 19 of 100 | C25: implemented or not, no customer can invoke it
A27: How to read this against the 78 | C27: 78 stories are Done-in-code and 60 are customer-reachable. The gap is not dishonesty in the earlier counts — the code really was written and tested — it is that "Done-in-code" never required a caller, so the two numbers were never the same thing and only one of them was ever reported. Both are now on the row, which was option (a) of Handover #20. | D27: Handover #20
A29: ROLLUP REFRESHED 13 Sep 20:36 (code v038) | B29: 75 reachable / 10 partial / 7 pending live / 8 not reachable | C29: Was 60/14/7/19 at v016. The movement is a day of work, not a reclassification: each row cites the version that made it reachable. Two NOT REACHABLE rows are deliberate and allowlisted with reasons (ST-060 dunning, ST-062 invoices); ST-055 is honest about token rotation still being unexercised. | D29: Handover #20
A30: Web panels → 17 product routes (PR-03) | B30: nothing — panels held local state; api.ts had 4 methods | C30: Mock front end; GAP-3 on the client side; invisible to the v021 gate | D30: WIRED v045 — 48-method client, every panel via Api, route→client gate (ST-110) fails the build on regression
A31: Transcript insights → CRM queue (PR-04) | B31: a human calling POST /crm/writeback with typed fields | C31: Headline promise required a manual API call | D31: WIRED v045 — staged on ingest, approve/reject handshake, one job per meeting
A32: features.ts withEmailSender | B32: nothing (allowlisted) | C32: No transport existed | D32: WIRED v045 — tenancy passes the Notifier hook when MEETSYNC_MAIL_* is set; allowlist entry removed
A33: team.manage permission | B33: nothing gated on it | C33: In the matrix, gating nothing | D33: WIRED v045 — gates POST /session/revoke-all

Sheet Enterprise_Scorecard
A1: ENTERPRISE-GRADE SCORECARD — Perplexity Review V001 §5.1 (5 = enterprise-ready, 1 = absent) — reviewer's score at v044 and Claude's honest re-score at v045
A2: The re-score is self-assessed and says so. Only an external re-review moves the left column. Average at v044: 2.0. Self-assessed at v045: 2.6.
A3: # | B3: Dimension | C3: Score at v044 (reviewer) | D3: Reviewer evidence | E3: Self-score at v045 | F3: What changed / what did not
A4: 1 | B4: Tenant isolation | C4: 2 | D4: Install identity caller-supplied (PR-01) | E4: 4 | F4: PR-01 closed; tenant from Zoom; store re-checks. Not 5: no external re-test (ST-147)
A5: 2 | B5: Identity & access | C5: 1 | D5: No user identity; owner@<account>; no SSO/SCIM/revocation | E5: 2 | F5: Real Zoom user + role, revocation, revoke-all. Still no SSO/SCIM/invites (ST-142/143)
A6: 3 | B6: Auditability | C6: 3 | D6: Every row names a synthetic user | E6: 4 | F6: Rows name Zoom users; install attempts audited. No export-to-SIEM
A7: 4 | B7: Data protection | C7: 3 | D7: Tokens encrypted; no content encryption, no PII redaction | E7: 3 | F7: Unchanged; ST-121 redaction waits on PD-02
A8: 5 | B8: Deletion & retention | C8: 3 | D8: Two deletion paths gave different guarantees (PR-06) | E8: 4 | F8: One purge list, tested; sessions revoked on deletion. Retention still one global value
A9: 6 | B9: Availability & DR | C9: 2 | D9: No PITR/RPO/RTO/failover/SLA | E9: 2 | F9: Unchanged (ST-144 infra)
A10: 7 | B10: Observability | C10: 3 | D10: Homegrown; trust page named vendors that do not exist | E10: 3 | F10: Rate-limit and mail outcomes added; vendors removed from the page. Still no APM/tracing
A11: 8 | B11: Compliance posture | C11: 1 | D11: No SOC 2/ISO/DPA/pen test; region a label | E11: 1 | F11: Region now stated as unenforced; subprocessor list accurate. Nothing attested (ST-146/147)
A12: 9 | B12: Platform hardening | C12: 2 | D12: No CSP/CORS/rate limit/body limit; 12h fragment sessions | E12: 4 | F12: All present and tested; 60-min revocable cookie sessions; operator router. Not 5: no pen test
A13: 10 | B13: Product completeness | C13: 1 | D13: UI not wired; no auto loop; no AI; no sender | E13: 2 | F13: UI wired, loop closes with review, sender exists. No AI (PD-02)
A14: 11 | B14: Commercial readiness | C14: 1 | D14: No processor; pricing 50x contradiction; seats self-declared | E14: 1 | F14: Contradiction now visibly held by a gated banner rather than resolved; processor and seats unbuilt (PD-01, ST-137/139)
A15: 12 | B15: Verification against reality | C15: 2 | D15: Zero live Zoom/CRM/load/a11y/users | E15: 2 | F15: Unchanged — 712 tests and 0 installs. Handover #42 is the next move
