Workbook

Sheet Version_Control
A1: VERSION CONTROL — TestPulse Sprint Tracker & Traceability
A2: File naming: claude_v<NNN>_<proper file name>_YYYYMMDD_HHMI.xlsx. Companion: workbook v035 + handover v003 released same timestamp.
A3: Version | B3: Date/Time | C3: Author | D3: Change Description | E3: Status
A4: v001 | B4: 2026-09-10 22:58 | C4: Claude for Senthil/KP | D4: THIS FILE — Live execution tracker for TestPulse (P03, Atlassian Marketplace), opened on Senthil's 22:58 'continue work as per sprint' instruction. S1-S8 code scope executed done-in-code under D13: TypeScript core, 16 Jest suites / 105 tests at 100% branches/functions/lines/statements, CI gate + E2E smoke. 71 stories Done, 7 code-complete pending live Forge/billing, 22 backlog (pen-test, onboarding content, listing/GTM). | E4: Released
A5: v002 | B5: 2026-09-10 23:13 | C5: Claude for Senthil/KP | D5: S9-S12 executable scope done on 23:13 'continue': E8 onboarding/helpcenter/support/review-ask/demo-mode, EQ latency budgets+p95/load test EXECUTED (5,238 rps, 0 errors)/backup drill/chaos degrade/status page, EL listing copy A+B/pricing FAQ/trust page/runbook/dry-run/asset+WCAG specs, AnthropicProvider wired behind AI seam (clears R-P6 in code). 21 suites / 129 tests / 100x4. Now 80 Done / 15 code-complete / 5 backlog (379/399 pts). | E5: Released
A6: v003 | B6: 2026-09-11 08:31 | C6: Claude for Senthil/KP | D6: LC-1 made TURNKEY on 08:31 'continue': ForgeStore hosted-storage adapter shipped+tested behind Store seam (closes R-P4 in code), forge/manifest.yml paste-ready, 30-min deploy guide with Senthil steps marked. Owed docs closed: LC-2 review pack, LC-3 Cloud Fortified gap assessment (formal, no structural gaps), LC-4 residency statement, S0 PRD rollup (A-P1). 22 suites / 132 tests / 100% x4. Story counts unchanged (80/15/5) — remaining flips all need Senthil-side live actions. | E6: Released
A7: v004 | B7: 2026-09-11 12:51 | C7: Claude for Senthil/KP | D7: 12:51 'continue' — deploy-glue + LC-5 de-risking: src/forgeGlue.ts ships the actual Forge resolver+webtrigger handlers (hydrate->dispatch->flush, permission guard, 6 suites incl. cross-invocation KVS persistence) — deploy-guide step 5 is now zero-code; importer hardened for real export shapes (RFC-4180 quotes/newlines, Xray Test Case Exporter multi-step aggregation, Zephyr Scale variant, ragged rows). Coverage regression caught mid-pass (99.87%) and closed. 23 suites / 146 tests / 100% x4. Counts unchanged 80/15/5. | E7: Released
A8: v005 | B8: 2026-09-11 13:32 | C8: Claude for Senthil/KP | D8: 13:32 'continue' — CUSTOM UI LAYER SHIPPED: view-models + escape-safe HTML renderers + bridge-injected mountPanel (src/ui/*, 15 tests incl. jsdom DOM assertions), compiled static/build/app.js bundle, Forge index.html with bridge hook, demo.html with canned data VERIFIED HEADLESS (banner/checklist/cases/board bar/quarantine/readiness dial all render). Manifest's static resource now exists. Screenshot capture available pre-LC-1 via demo.html. 25 suites / 161 tests / 100% x4. Counts unchanged 80/15/5; panel-story evidence upgraded to full-stack. | E8: Released
A9: v006 | B9: 2026-09-11 15:27 | C9: Claude for Senthil/KP | D9: 15:27 'continue' — EXTERNAL VERIFICATION SWEEP against live Atlassian docs: (1) R-P5 CLOSED — Forge officially does NOT authenticate webtrigger URLs, own-auth-in-handler is the prescribed pattern, so our HMAC design is correct-by-design; webtrigger needs urlFormat v2 + dynamic response (statusCode contract already met). (2) Runtime corrected nodejs20.x -> nodejs22.x (Node 20 EOL 2026-04-30). (3) @forge/kvs has no listKeys — kvsAdapter shipped+tested mapping query().where(beginsWith).cursor paging to the seam; entrypoint updated. (4) Marketplace asset spec was WRONG (5x1600x1000 + 2min video) — rewritten to verified Rule-of-3: 1840x900 + 580x330 crops + <=50/220-char text + banner 1120x548 + <30s video. 25 suites / 163 tests / 100% x4. | E9: Released
A10: v007 | B10: 2026-09-11 22:09 | C10: Claude for Senthil/KP | D10: 22:09 'continue' — B-17 DE-RISKED + ST-100 KIT: verified Paid-via-Atlassian model (manifest app.licensing.enabled shipped; ATLASSIAN owns purchase/trial/proration/dunning — our billing.ts payment engine honestly marked superseded for the Marketplace channel, seat limits + read-only behavior reused); licensing gate shipped (inactive => mutating calls read-only, reads never blocked) wired into forgeGlue + tested. Economics cited: Forge revenue 100% to partner up to $1M lifetime (from Jan 2026). PRICING DECISION SURFACED: Atlassian cloud pricing is per-user tiers — flat $99/$299 must be re-anchored (B-17 step 2, Senthil). Design-partner kit shipped (outreach + A1-A4 interview guide + demo script). 26 suites / 167 tests / 100% x4. | E10: Released
A11: v008 | B11: 2026-09-11 22:28 | C11: Claude for Senthil/KP | D11: 22:28 'continue' — COLD REVIEW PASS 1 EXECUTED (first for TestPulse). 27 modules read adversarially against their claims; 13 defects fixed with pinned regressions (test/review.pass1.test.ts), 4 observations logged for Senthil's disposition in the workbook's new Review_Findings sheet. Severity-high: F-TP01 delete/export-my-data missed every non-cloudId-keyed namespace and F-TP02 the retention sweep did the same (published 30-day hard-delete breached); F-TP03/F-TP04 both live panels would have rendered NaN; F-TP05 Forge writes could be dropped when a handler threw; F-TP06 five unbounded ledgers would eventually hard-fail hosted-storage writes. New shared modules: tenantData.ts (one registry driving export+delete+sweep, with a drift test), ledger.ts (FIFO caps + drop counters), csv.ts (RFC-4180 in/out). Gate: 27 suites / 203 tests / 100% x4, zero pragmas. Story counts unchanged 80/15/5 — corrections, not scope. | E11: Released
A12: v009 | B12: 2026-09-13 09:52 | C12: Claude for Senthil/KP | D12: 09:52 'continue' — COLD REVIEW PASS 2 + VERIFICATION SWEEP EXECUTED. Modules pass 1 touched lightly (helpcenter, support, onboarding, aiProvider, billing, xrayImport) reviewed, plus the shipped ARTIFACTS checked against live Atlassian documentation. 10 defects fixed with pinned regressions in test/review.pass2.test.ts; 3 were live-blocking (VER-P01 entrypoint commented out and wrong shape; VER-P02 Custom UI never mounted and shipped without the bridge; VER-P03 license field mismatch) and 2 were security (F-TP14 caller-supplied role; F-TP15 app-wide CI secret). New modules: src/forgeAdapter.ts, src/roles.ts, static/demo-entry.ts; forge/index.ts is now real compiled code. New CI gates: typecheck:forge and build:ui. 28 suites / 233 tests / 100% x4 zero pragmas. Story counts unchanged 80/15/5 — corrections, not scope. Portfolio lessons L-P1/L-P2/L-P3 logged. | E12: Released
A13: v010 | B13: 2026-09-13 10:24 | C13: Claude for Senthil/KP | D13: 10:24 'continue' — COLD REVIEW PASS 3 (REACHABILITY) EXECUTED. 9 findings fixed with pinned regressions in test/review.pass3.test.ts + test/ui.settings.test.ts. Headline: F-TP21 self-serve export/delete had no resolver call and F-TP22 the retention sweep had no scheduled trigger — between them, every published data-rights and retention claim was unreachable in the installed app even after pass 1 made them correct. F-TP23/24 settings, pauses and notifications were library-only (notify() was never called in the Forge path at all). F-TP25/26/27 error tracking, support intake and latency budgets had no caller or surface. F-TP28 the panel bound no events — no control did anything. Shipped: data-rights/settings/support/audit/status resolver calls, daily scheduledTrigger (syntax verified live), notifications on the real paths, per-invocation latency sampling, and a Settings screen with working controls. 30 suites / 263 tests / 100% x4; typecheck:forge + build:ui green; demo page re-verified headless with the Settings screen. Story counts unchanged 80/15/5. Lesson L-P4 logged. | E13: Released
A14: v011 | B14: 2026-09-13 10:37 | C14: Claude for Senthil/KP | D14: 10:37 'continue' — COLD REVIEW PASS 4 (CLAIMS) EXECUTED + AUTOMATED A11Y SHIPPED. 5 findings fixed with pinned regressions in test/review.pass4.test.ts: F-TP30 the live Jira calls bypassed ST-070's retry/breaker entirely; F-TP31 and F-TP32 two pieces of published evidence (backup drill, 'posture asserted in CI') rested on code nobody ran; F-TP33 four false document statements including an email subprocessor the app has no egress permission to reach; F-TP29 an unnamed table header found by the new axe pass. ST-089's automated WCAG audit now runs over all five panels on every build instead of waiting for LC-1. 32 suites / 280 tests / 100% x4; CI gates now check:posture + typecheck:forge + build:ui + jest. Story counts unchanged 80/15/5. Four passes complete: 37 defects, all found in code already at 100% coverage. Lesson L-P5 logged. | E14: Released
... A30: v027 | B30: 2026-09-13 20:49 | C30: Claude for Senthil/KP | D30: 20:49 VENDOR CONTRACT GUARD — generalising PERF-04 so the class cannot repeat. PERF-04 cost a wasted storage round trip per key on every invocation and survived eight internal passes and two external reviews for one reason: the KVS test double returned { key } where the vendor's Result<T> returns { key, value }. Nobody misread the code; everyone read a double thinner than the API it stood for. test/vendor-contracts.test.ts now assigns every seam to or from the vendor's own published type, so a thin double is a COMPILE ERROR: KVS ListResult/Result (hydrate), @forge/resolver Request (the invocation shape), @forge/bridge LicenseDetails (isEvaluation vs evaluation — the VER-P03 defect), FullContext (the panel boot context), and @forge/api Response/Headers (headers.get returning string|null, which the Retry-After path depends on). All four vendor contracts were audited against the installed packages and every one currently holds. THE GUARD CAUGHT ME ON ITS FIRST RUN: I asserted the resolver contract in the wrong DIRECTION. For an inbound contract the vendor's type must be assignable to ours — we must accept whatever they send, and tolerating more is correct; for an outbound contract ours must satisfy theirs. Asserting the wrong way either passes for the wrong reason or fails in a way that looks like a defect and is not. One assumption stays unprovable by types and is recorded rather than buried: ExtensionData is an open map in the vendor definitions, so extension.issue.key — which the generate tab depends on — can only be verified live at LC-1. 44 suites / 426 tests / 100% x4; six gates green; CI at evidence/ci-run-20260913-2049.log. | E30: Released
A31: v028 | B31: PLANNED: LC-1 install evidence (incl. verifying extension.issue.key live); the five open decisions; D18 pricing. | E31: Planned
A32: v028 | B32: 2026-09-20 11:40 | C32: Claude for Senthil/KP | D32: EXTERNAL REVIEW V001 (Perplexity, 16/09) INCORPORATED — 14-sprint plan executed as far as code can take it: PR-01..PR-11 built, C-1..C-7 corrected, PR-04/PR-12/PR-13/PR-14 prepared and left Open because they need a live site, a purchase or a person. ALL FIVE PRX FINDINGS CLOSED IN CODE. PRX-02 (CRITICAL, concurrent write loss) was the finding that mattered: storage now carries a version on every value, writes with compare-and-set, stores ONE KEY PER ENTITY, and merges ledgers commutatively at flush — two invocations can no longer lose each other's work, and a genuine conflict surfaces as a 409 telling the user to reload instead of silently clobbering. PRX-01 duplicate ids: unique time-sortable ids on every creation path incl. AI, asserted at write by insert-if-absent. PRX-03 scope logged-not-enforced: Permissions.check now evaluates scope against Jira BROWSE_PROJECTS via asUser(), fails CLOSED on an unanswered check; the regression asserts a scoped DENIAL. PRX-04 one noisy test evicting the flaky signal: per-run storage under a bounded 50-run index, scoring over per-test/per-branch windows. PRX-05 whole-tenant hydration: every resolver call declares its storage scope and a read outside it throws — whoami loads 2 keys, not 500. PRODUCT (the wedge): readiness is DERIVED (Jira JQL for P0s, CI results for coverage, run boards for pass rate), every factor names its source on the panel, and a manual override is attributed and labelled — Decision 4 positioning is now earned by the code. JUnit/Playwright/Cucumber ingestion against real fixtures, idempotent by run id, 413 on oversize. Flaky 2.0: branch-aware, clusters, quarantine with owner+expiry, new-vs-chronic. Traceability graph + coverage by release (EG-05 was MISSING). ENTERPRISE: project-scoped RBAC; BYO Anthropic key in Forge Secret Storage with per-source cost attribution, a monthly shared-key ceiling and prompt-injection hardening (story text is data, never instructions); Atlassian Enterprise Certified gap assessment REPLACING the retired Cloud Fortified one; all Atlassian credential storage removed (AEC 1.5); express moved to devDependencies. NEW STANDING GATE G-5 (concurrent write safety, lesson L-P8) — static half refuses a plain read-modify-write on any shared key, dynamic half is test/concurrency.test.ts; IT WENT RED ON ITS OWN FIRST RUN for 8 of 13 registered keys, and that coverage was written to answer it. Seven gates now run in CI. Envelope re-baselined and an honest trade published: per-entity keys make a 10,000-run board 102 storage round trips where one value used to suffice (and could not exist at that size anyway) — the strongest argument for the shipped Forge SQL adapter, decided at PR-04 with real latency. 55 suites / 530 tests / 100% x4, zero pragmas; clean-room reproduced from the lockfile (evidence/cleanroom-ci-20260920-1204.log); 0 production vulnerabilities. Release position UNCHANGED: NOT RELEASE READY until LC-1 (PR-04) and D18 (PR-13). | E32: Released
A33: v029 | B33: PLANNED: PR-04 LC-1 live install evidence; PR-12 envelope on live infrastructure; PR-13 per-user pricing + test purchase; PR-14 design partners. | E33: Planned

Sheet Sprint_Tracker_Log
A1: SPRINT TRACKER LOG — every execution event, newest last
A2: ID | B2: Date/Time | C2: Sprint | D2: What happened | E2: Refs | F2: State changes | G2: Blockers | H2: Next
A3: E001 | B3: 2026-09-10 22:58 | C3: — | D3: INSTRUCTION RECORDED — Senthil 22:58: continue work as per sprint on TestPulse from v007 workbook; complete development with 100% automation testing; produce tracker+traceability like TeleField v001 and workbook next version. D13 applies (interviews parked, 100% coverage). Ninth concurrent build under open D15. | E3: D13,D15 | F3: TestPulse S1 opened | G3: None | H3: S1 build
A4: E002 | B4: 2026-09-10 22:58 | C4: S1 | D4: S1 FOUNDATION BUILT (TypeScript/Node core, Forge-adapter seams per D17): config validation (residency global/eu/us, trial days), typed Store (in-memory behind interface — Forge hosted storage adapter at deploy), lifecycle install->welcome/uninstall token-wipe+30d deletion schedule+sweep/re-install restore/rotation-safe refresh/source attribution, webhook HMAC timing-safe verify+replay+dedupe, jiraClient 429/5xx backoff+jitter+circuit breaker, CI with jest coverageThreshold 100x4. | E4: ST-051,052,053,055,056,070 | F4: 6 E1 stories Done-in-code | G4: Live Forge dev site = Senthil (LC-1) | H4: S2
A5: E003 | B5: 2026-09-10 22:58 | C5: S2 | D5: S2 EXECUTED — F1 AI test-case generation part 1: rule engine behind AI seam (provider-swappable), defaults one-screen, happy+edge+permission case output, clear errors, rules customisation; owner/admin/member permission matrix + audit log wired to all routes. | E5: ST-001..004,053,054 | F5: 6/6 S2 stories Done (29 pts) | G5: None | H5: S3
A6: E004 | B6: 2026-09-10 22:58 | C6: S3 | D6: S3 EXECUTED — F1 completed (metrics, pause-no-loss, CSV import, notifications) + F2 run boards started (defaults, happy path, rules, errors). ST-085 coverage gate SUPERSEDED by D13: shipped at 100x4, not >=70. ST-005 Forge-panel surface = code-complete pending live. | E6: ST-005..014,085 | F6: 10 Done + 1 code-complete | G6: Forge panel render needs LC-1 | H6: S4
A7: E005 | B7: 2026-09-10 22:58 | C7: S4 | D7: S4 EXECUTED — F2 completed (metrics/passRate, permissions, pause, CSV import, notifications); E7 activation funnel + error tracking with spike alert; E2E smoke suite wired into CI on every deploy. MVP loop (install->generate->board->metrics) passes end-to-end in e2e.smoke.test.ts. | E7: ST-015..020,071,072,086 | F7: 8 Done + 1 code-complete; S4 exit criterion met in-code | G7: None | H7: S5
A8: E006 | B8: 2026-09-10 22:58 | C8: S5 | D8: S5 EXECUTED — F3 flaky-test detector: signed CI-webhook ingest, flip-rate scoring, quarantine threshold (custom, validated), pause, notifications. ST-078/079 onboarding content = backlog (design/content, not code). | E8: ST-021..030 | F8: 9 Done + 1 code-complete | G8: Onboarding content = Senthil review | H8: S6
A9: E007 | B9: 2026-09-10 22:58 | C9: S6 | D9: S6 EXECUTED — E5 billing core: 14-day card-free trial + banner, mid-cycle proration (verified $100 on 15-day starter->team), plan limits 80/100 alerts; F4 release readiness score with validated custom weights and verdicts. ST-059 Atlassian-billing wiring pending live listing. | E9: ST-031..040,057,058 | F9: 11 Done + 2 code-complete | G9: Atlassian billing = live listing (LC-8) | H9: S7
A10: E008 | B10: 2026-09-10 22:58 | C10: S7 | D10: S7 EXECUTED (code scope) — dunning: 7-day grace, 3 emails, read-only; plan-limit prompts; GST invoices; cancel flow with save-offer + exit survey; least-privilege scope map 1:1 to features. Design-partner activity itself = live-only (beta gate). | E10: ST-060..064 | F10: 5 Done | G10: 3+ live partners = post-listing | H10: S8
A11: E009 | B11: 2026-09-10 22:58 | C11: S8 | D11: S8 EXECUTED (code scope) — F5 Xray/Zephyr importer (export parse, mapping, errors); E6 data-flow+retention doc, audit log, export/delete-my-data, rate-limit backoff+breaker; E7 heatmap, weekly CSV, health score, alert thresholds. ST-066 vault/KMS + ST-087/088/092 live-infra items pending; 3 real Xray export files (LC-5) = Senthil. | E11: ST-041..050,065,067,069,070,073..077 | F11: 16 Done + 1 code-complete | G11: Real Xray exports; live infra | H11: D13 verify
A12: E010 | B12: 2026-09-10 22:58 | C12: — | D12: D13 TEST GATE MET — 16 Jest suites, 105 tests, 100% branches/functions/lines/statements; jest coverageThreshold 100x4 fails CI below 100; E2E smoke on every deploy. TOTAL: 71 Done / 7 code-complete pending live / 22 backlog (399 pts total; 321 pts done incl. code-complete). Tracker v001 + workbook v008 released 22:58. | E12: D13 | F12: Evidence in Traceability col K | G12: None | H12: S9 review prep needs live items; D15
A13: E011 | B13: 2026-09-10 23:13 | C13: — | D13: INSTRUCTION — Senthil 23:13 'continue': execute remaining executable backlog (S9-S12 scope). | E13: D13 | F13: S9-S12 pass opened | G13: None | H13: build
... A114: E112 | B114: 2026-09-20 11:40 | C114: Scope | D114: WHAT THIS PASS DID NOT DO, AND WHY — recorded so no rollup can overstate it. PR-04 (LC-1 live install) is prepared to the last inch and cannot be executed here: it needs an Atlassian account and a browser. PR-12 (envelope on live infrastructure) needs PR-04 first. PR-13 (per-user pricing) has its anchor table and FAQ rewritten against the corrected 0% fee, and needs a partner-console setup and a real test purchase. PR-14 (design partners) needs ten conversations. All four stay OPEN in this tracker with everything that could be prepared for them attached — the scope is not shrunk, it is correctly attributed. The release position is unchanged and unchangeable by more code: NOT RELEASE READY until LC-1 and D18. | E114: PR-04, PR-12, PR-13, PR-14 | F114: Four sprints Open — Senthil-side | G114: LC-1, partner console, outreach | H114: Senthil

Sheet PR_Sprint_Plan
A1: EXTERNAL REVIEW V001 — THE 14-SPRINT PLAN, EVERY TASK, NOTHING DROPPED
A2: Status: Done-in-code = built + pinned regression in this release. Open — Senthil = needs a live site, a purchase or a person. Nothing here is marked Done on documentation alone. Task-level detail is one row per acceptance item, so no sub-task is lost when a sprint closes.
A3: Sprint | B3: Phase | C3: Pri | D3: Task | E3: What was required (review wording) | F3: What was done in this release | G3: Status | H3: Evidence / pinned regression | I3: Owner
A4: PR-01 | B4: 0 Correct | C4: P0 | D4: Per-entity keys + bounded index | E4: Replace whole-collection read-modify-write with per-entity keys (gen:case:<id>, rb:run:<boardId>:<seq>) plus a bounded index value | F4: gen:case:<story>:<id>, rb:run:<board>:<runId>, fl:run:<runId>[:chunk] under a bounded 50-run index, trace:link:<id>, wh:seen:<eventId> | G4: Done-in-code | H4: test/concurrency.test.ts; test/performance.test.ts asserts 50k cases with no value near the ceiling | I4: Claude
A5: PR-01 | B5: 0 Correct | C5: P0 | D5: Optimistic version stamp + compare-and-set | E5: Add an optimistic version stamp on every mutable value and a compare-and-set path in ForgeStore.set | F5: Every value is written in an envelope {__tpv, v}; plain writes CAS against the version read at hydrate; atomic where the backend supports it, read-verify-write where it does not (stated in ADR-001) | G5: Done-in-code | H5: test/concurrency.test.ts "a deliberately conflicting plain set RAISES"; test/sqlStore.test.ts for the atomic path | I5: Claude
A6: PR-01 | B6: 0 Correct | C6: P0 | D6: flush() surfaces conflicts instead of overwriting | E6: Make flush() surface conflicts instead of overwriting | F6: StoreConflictError names the keys; the glue maps it to ConflictError with status 409 and a reload message; the handler's writes are rejected, nothing is clobbered | G6: Done-in-code | H6: test/concurrency.test.ts "the glue turns a store conflict into a 409-class error and never overwrites" | I6: Claude
A7: PR-01 | B7: 0 Correct | C7: P0 | D7: Idempotent generate / recordRun / ingest under retry | E7: Make generate, recordRun and ingest idempotent under retry (Forge may deliver duplicates) | F7: recordRun takes a caller runId; CI ingest is idempotent by runId (default eventId); an identical value already present is idempotent success, not a conflict; a concurrent duplicate is a 409 | G7: Done-in-code | H7: test/ciReports.test.ts re-post changes nothing; test/concurrency.test.ts idempotent-redelivery case | I7: Claude
A8: PR-01 | B8: 0 Correct | C8: P0 | D8: Commutative ledgers (audit, wh:seen, ai:audit) never lose an entry | E8: No lost entry under 100 interleaved writers for gen:*, rb:*, audit, wh:seen, ai:audit | F8: append/increment/union/setIfAbsent/update are reducers re-applied on the stored value at flush and retried on conflict; wh:seen became one key per event id so an id cannot age out inside the replay window | G8: Done-in-code | H8: test/concurrency.test.ts "100 interleaved writers" | I8: Claude
A9: PR-01 | B9: 0 Correct | C9: P0 | D9: Standing gate G-5 + lesson L-P8 | E9: New standing gate G-5 "concurrent write safety", and lesson L-P8 into the portfolio build standard | F9: tools/review-gates/concurrent-writes.js — static half refuses a plain set on a registered shared key, dynamic half requires the concurrency suite to exercise it; went RED on its own first run for 8 of 13 keys; in CI as the seventh gate | G9: Done-in-code | H9: test/gates.test.ts — five cases incl. "goes RED on the exact shape of PRX-02" | I9: Claude
A10: PR-01 | B10: 0 Correct | C10: P1 | D10: Port G-5 to the other 11 products | E10: (portfolio) the same defect exists wherever a collection lives in one value | F10: Kit updated: README section 7 with the porting rule, init.js scaffolds a TODO register rather than an empty one (an empty register passes vacuously) | G10: Open — portfolio | H10: tools/review-gates/README.md; test/gates.test.ts bootstrapper case | I10: Senthil
A11: PR-02 | B11: 0 Correct | C11: P0 | D11: Unique id on every creation path | E11: Monotonic sequence or ULID for all creation paths including AI and rule engine | F11: src/ids.ts — time-sortable id, base36 ms + random tail, used by rule engine, AI, import and CSV; the provider now returns DRAFT cases and TestGen assigns ids | G11: Done-in-code | H11: test/identity.test.ts generate x3 / import x2 / AI x2 under ONE clock value | I11: Claude
A12: PR-02 | B12: 0 Correct | C12: P0 | D12: Uniqueness asserted at write | E12: Uniqueness asserted on write | F12: Batch asserted in-process, then one insert per entity — a present key fails the store's CAS, so uniqueness holds ACROSS invocations, not just within one | G12: Done-in-code | H12: test/identity.test.ts; test/concurrency.test.ts same-story-two-panels case | I12: Claude
A13: PR-02 | B13: 0 Correct | C13: P0 | D13: version + updatedAt on TestCase (EG-04 seed) | E13: A version and updatedAt on TestCase (the seed of EG-04 versioning) | F13: Both on every case; updateCase refuses a stale editor with the current version in the message | G13: Done-in-code | H13: test/identity.test.ts optimistic-versioning case | I13: Claude
A14: PR-02 | B14: 0 Correct | C14: P1 | D14: Migration for existing duplicate ids | E14: Migration for existing duplicate ids | F14: NOT NEEDED, and stated rather than silently skipped: no installation exists yet (LC-1 has never run), so there is no stored data to migrate. If LC-1 happens before a later id change, this row becomes real. | G14: N/A — no installs exist | H14: ADR-001; Release_Traceability_Corrections | I14: Claude
... A98: PR-14 | B98: 3 Commercial | C98: P0 | D98: Three teams making a documented go/no-go call | E98: At least three teams have made a go/no-go release call using the readiness score, documented | F98: THE BAR FOR EG-15, and it stays UNPROVEN no matter how much is built — the review's words, and they are correct | G98: Open — Senthil | H98: V002_Enterprise_Gates EG-15 | I98: Senthil

Sheet PRX_Findings_Closure
A1: EXTERNAL REVIEW V001 — THE FIVE PRX FINDINGS, AND WHAT CLOSED EACH
A2: All five accepted. All five closed in code with a pinned regression that fails against the pre-release code. The reviewer wrote its own probe tests and deliberately did not leave them in the tree; these are ours, and they assert the same scenarios.
A3: ID | B3: Sev | C3: Area | D3: The finding, in the reviewer's terms | E3: What closed it | F3: Pinned regression | G3: Status | H3: Senthil decision
A4: PRX-01 | B4: HIGH | C4: src/testgen.ts, src/aiProvider.ts | D4: Repeat generation creates DUPLICATE case ids: ids derived deterministically from the story key, and the panel ships a "Generate more cases" button, so a second press appends the identical ids. importCases already solved this with a persisted counter — the fix existed in the same file and was not applied to the generation paths. | E4: Unique time-sortable ids on EVERY creation path including AI and CSV, asserted unique in-process and at write by insert-if-absent (a shared counter would itself have been a PRX-02 race). The provider now returns draft cases and TestGen owns identity. version + updatedAt added as the EG-04 seed. | F4: test/identity.test.ts — generate x3 / import x2 / AI x2 on one story under ONE clock value | G4: CLOSED in code | H4: None
A5: PRX-02 | B5: CRITICAL | C5: src/forgeStore.ts + every collection writer | D5: Concurrent invocations SILENTLY LOSE WRITES: hydrate -> mutate whole collection in memory -> flush, with no version, ETag or compare-and-set. Two overlapping invocations each append and the last flush wins. Applies to gen:cases, rb:board:*, audit, fl:results, wh:seen, ai:audit — so an audit entry can be dropped and the replay-dedupe ledger can lose an event id it just recorded, which weakens a security control. | E5: Versioned values + compare-and-set on plain writes (conflict raises, never overwrites, and surfaces as a 409 telling the user to reload); commutative reducers re-applied at flush for ledgers and counters; one key per entity so the common case cannot conflict at all; wh:seen became one key per event id, which also removes the FIFO that could age an id out inside the replay window. | F5: test/concurrency.test.ts — two stores over one backing map, 100 interleaved writers, plus the conflict and idempotent-redelivery paths. Standing gate G-5. | G5: CLOSED in code | H5: Note: on KVS the CAS is emulated (the platform has no conditional write); the Forge SQL adapter has a real one. ADR-001 states this and PR-04 decides.
A6: PRX-03 | B6: MED-HIGH | C6: src/permissions.ts, tracker LC-6 | D6: Project scope is RECORDED, never ENFORCED: check() takes a scope, writes it into the audit entry, then evaluates purely against the global MATRIX. No key is project-namespaced. On a site with a restricted project, any licensed member sees every project's cases and readiness. LC-6 was marked "Done-in-code — scope-aware guard + audit"; it was scope-LOGGING. | E6: check() now evaluates scope: role matrix AND Jira BROWSE_PROJECTS for that user via asUser() (AEC 1.14), failing CLOSED when Jira does not answer — for the owner too. Data is project-namespaced; reads are gated as well as writes; the audit entry carries the project and the reason for a denial. | F6: test/permissions.test.ts + test/project-scope.test.ts — the regression asserts a scoped DENIAL, not a scoped audit entry | G6: CLOSED in code; LC-6 stays OPEN until live evidence | H6: LC-6 downgraded to Open as the review instructed. It flips at PR-04 with the restricted-project capture, not before.
A7: PRX-04 | B7: MED | C7: src/flaky.ts, src/ledger.ts | D7: One noisy test evicts every real flaky signal: fl:results is ONE FIFO ledger capped at 10,000 entries / 200 KiB and flip-rate is computed over whatever is in it. A normal CI run on a mid-size suite is thousands of results, so the window holds one or two runs — and flip-rate needs history PER TEST. PERF-01 tightened this cap correctly and did not notice the cap is also the analysis window. | E7: Results stored per run under a bounded 50-run index (settable 5..500); scoring over the last 30 results per test PER BRANCH; branch/env dimension added so a feature-branch failure is not scored as instability on main. Supported CI throughput is now a published figure rather than a byte budget. | F7: test/performance.test.ts — real.flaky still scored after 12,000 unrelated stable results; test/flaky2.test.ts | G7: CLOSED in code | H7: Ratify the retention default (50 runs) — it is the retention policy in practice, and it is settable per site.
A8: PRX-05 | B8: MED | C8: src/forgeGlue.ts, src/forgeStore.ts | D8: Every invocation loads the entire tenant (restates OBS-TP1, still open): a whoami needing one role key hydrated all 500 keys in the fixture. PERF-04 removed the multiplier, not the linearity — the cost is still linear in tenant data, on the hot path, inside a 25s invocation with 1 MiB of function memory. | E8: Every resolver call declares the prefixes and keys it may read; a read outside the declared scope THROWS, so a missing declaration fails the suite rather than silently loading everything in production. Blind commutative writes and new-entity inserts need no declaration, which is what keeps the hot paths cheap. | F8: test/performance.test.ts — whoami loads at most 2 present keys on a 500-key tenant; every call asserted to have a scope | G8: CLOSED in code — OBS-TP1 closed with it | H8: The residual cost is now round trips per listing, published honestly in the envelope. That is what PR-04 measures.

Sheet Corrections_C1_C7
A1: ARTIFACT CORRECTIONS C-1..C-7 — "do these first, they cost minutes"
A2: All seven applied. Where a correction made a status worse, the status was made worse.
A3: ID | B3: Artifact | C3: Correction required | D3: Applied | E3: Status
A4: C-1 | B4: tracker v027, LC-6 | C4: "Done-in-code — scope-aware guard" -> OPEN. Scope is logged, not enforced (PRX-03). | D4: LC-6 is OPEN in this tracker's Gate_Checklist. The code defect is fixed (PR-09) but the row stays Open until the live restricted-project check, because "fixed in code" was exactly the overstatement the review caught. | E4: APPLIED
A5: C-2 | B5: docs/cloud-fortified-gap.md, LC-3 | C5: Programme closed to new submissions 01/09/2026, retired 31/12/2026. The "application at listing+60d" route no longer exists. Retarget to Atlassian Enterprise Certified. LC-3 -> OPEN. | D5: cloud-fortified-gap.md DELETED; docs/enterprise-certified-gap.md written row by row against AEC, separating MET (code) from MET (doc) from OPEN, with pen test and bug bounty marked as procurement items with lead times. LC-3 -> Open. | E5: APPLIED
A6: C-3 | B6: workbook v034, Financial_Model B9 | C6: Marketplace fee 0.17 -> 0.00 until $1M lifetime Forge revenue (eligible Forge apps keep 100% of gross from 01/01/2026; 84% from 01/04/2026 and 83% from 01/10/2026 only above it). Net MRR understated ~20%; restate breakeven. | D6: B9 = 0.00 with the tiering note; the model recalculates and breakeven moves earlier. The pricing anchor is re-derived on the corrected economics. | E6: APPLIED
A7: C-4 | B7: RAID R-P2 | C7: "Xray/Zephyr respond with AI features — Open" -> MATERIALISED. Both incumbents ship AI now, plus a crowded field of dedicated generators. Rewrite the ReadMe_Scope differentiation claim with it. | D7: R-P2 -> Materialised in the RAID; ReadMe_Scope differentiation rewritten around the release-decision wedge rather than AI case generation, which is table stakes. | E7: APPLIED
A8: C-5 | B8: docs/runs-on-atlassian-assessment.md | C8: Add the revenue-share correction: since 01/01/2026 the 0%-to-$1M incentive applies to ALL qualifying Forge apps, not only Runs on Atlassian. The badge is now a trust signal with no revenue delta — which strengthens Option B. | D8: Section added; Option B adopted as Decision 2 with the better reason (the enterprise bar is AEC, which wants egress TRANSPARENCY not zero egress, and off-by-default already gives a genuine no-egress runtime, now named on the trust page). | E8: APPLIED
A9: C-6 | B9: Scale_Envelope / performance-envelope.md | C9: Add PRX-04: the 10k/200 KiB cap on fl:results is not only a storage bound, it is the flaky ANALYSIS WINDOW. Publishing a supported case count without a supported CI-throughput figure is incomplete. | D9: Envelope re-baselined. Supported CI throughput published: 20,000 results per run, 1 MiB per post, last 50 runs retained per site. The row ceilings are gone and the round-trip costs that replaced them are published too, including the honest slowdown. | E9: APPLIED
A10: C-7 | B10: package.json | C10: Move express to devDependencies (or drop app.ts from the shipped tree). A Forge app with a production Express dependency and a header-trusting role guard is an avoidable flag under AEC 1.7/1.10. | D10: express -> devDependencies (production dependencies are now empty) AND src/app.ts refuses to start when NODE_ENV=production, so the header-trusting harness cannot be mistaken for the product. Both asserted. | E10: APPLIED

Sheet Decisions
A1: DECISIONS (tracker scope)
A2: Yellow = open and yours. The six review decisions are in the workbook's Review_Decisions sheet; these are the tracker-level ones.
A3: ID | B3: Decision | C3: Rationale | D3: Decided by | E3: Status | F3: Notes
A4: D13 | B4: (Portfolio-wide) Discovery interviews parked; dev proceeds with 100% automation test coverage on all code — supersedes ST-085 >=70% gate. | C4: Senthil 10 Sep 20:45; applied to TestPulse per 22:58 instruction. | D4: Senthil | E4: LOCKED
A5: D15 | B5: TestPulse (P03) build opened 10 Sep 22:58 while RevRescue rank-1 gate (listed + 10 paying) is not met — ninth concurrent build. Mode ratification: (a) parallel builds or (b) WIN-order swap. | C5: Uploaded workbook set + continue-sprint instruction indicate TestPulse intent; serial rule formally intact until ratified. | D5: Senthil (mode ratification pending) | E5: OPEN — pick (a) or (b)
A6: D17 | B6: TestPulse stack = TypeScript/Node platform-agnostic core with Forge adapter seams: Store interface (in-memory now, Forge hosted storage at deploy), Billing provider seam (Atlassian billing at listing), AI seam in testgen (rule engine now, LLM provider swappable). Express routes map 1:1 to Forge resolvers. | C6: v007 ReadMe stack assumption ("platform-mandated runtime"); sandbox has no Forge CLI/Postgres; matches accepted D16 precedent on TeleField. | D6: Claude — flagged | E6: OPEN for ratification
A7: D18 | B7: 2026-09-11 22:09 | C7: Per-user price point for Atlassian cloud pricing tiers | D7: OPEN — Senthil | E7: Flat $99/$299 intent must map to per-user tiers (Atlassian model). Options: ~$4/user/mo flat-equivalent vs re-anchor vs value-based. Blocks B-17 step 2 and final pricing-page copy. | F7: Claude (surfaced from verified docs)
A8: D19 | B8: Storage backend: per-entity KVS now, Forge SQL opt-in later (ADR-001) | C8: Per-entity KVS lifts the row ceiling, closes PRX-02 for entity writes and needs no major version. Forge SQL adds a real atomic CAS and one indexed query in place of 102 round trips for a large board — but adding the sql module is a MAJOR version and introduces an installed-before-schema window. | D8: Claude — recorded, re-open named | E8: OPEN — decide at PR-04 with real KVS latency | F8: The adapter and its migration are already built and tested, so the decision is a manifest change, not a project.
A9: D-TP-WB | B9: Jira write-back (write:jira-work) as a funded feature | C9: PR-08 traceability can link cases to issues inside TestPulse, but CREATING issue links or defect issues in Jira needs the scope TPR-003 removed because nothing used it. The review was explicit: re-add it as a FEATURE with a justified call path, never as a silent permission. | D9: Senthil | E9: OPEN — not re-added | F9: Nothing in the code pretends otherwise: there is no unreachable write path, and the claims gate refuses the scope in the manifest.
A10: D20 | B10: Flaky retention default: last 50 CI runs per site | C10: It is the retention policy in practice, the same way the old FIFO caps were. Settable 5..500 per site. | D10: Claude — surfaced | E10: OPEN — ratify | F10: Published in the envelope as supported CI throughput.

Sheet S1_S8_Build_Board
A1: S1–S12 BUILD BOARD — executed code scope, plus the PR-series build items added 20/09
A2: Backlog stories per Traceability_Matrix. Edit Status/Notes as live evidence lands.
A3: ID | B3: Item | C3: Story ref | D3: Points | E3: Owner | F3: Status | G3: Notes / Evidence
A4: B-01 | B4: Repo scaffold + CI with 100% coverage gate (D13) | C4: — | D4: 2 | E4: Claude | F4: Done | G4: jest coverageThreshold 100x4; .github/workflows/ci.yml runs build+coverage+E2E. E010.
A5: B-02 | B5: Config: site/app/secret validation, residency, trial days | C5: — | D5: 1 | E5: Claude | F5: Done | G5: src/config.ts — 5 tests incl. bad residency + bad trial days.
A6: B-03 | B6: Typed Store repository (Forge hosted-storage adapter point) | C6: — | D6: 2 | E6: Claude | F6: Done | G6: src/store.ts — D17 constraint logged as R-P4.
A7: B-04 | B7: Install -> welcome; uninstall wipe + 30d deletion + sweep; re-install restore; rotation | C7: ST-051/052/053/055 | D7: 5 | E7: Claude | F7: Done | G7: src/lifecycle.ts — 8 tests incl. retention-window and legacy-row edge cases.
A8: B-05 | B8: Install telemetry source attribution | C8: ST-056 | D8: 2 | E8: Claude | F8: Done | G8: listing/search/referral, unknown->direct; preserved across re-install.
A9: B-06 | B9: Permission matrix + audit log on every route | C9: ST-054/007/017/027/037/047/067 | D9: 5 | E9: Claude | F9: Done | G9: src/permissions.ts + guard() in app.ts; member-403 and bad-role-400 asserted in E2E.
A10: B-07 | B10: F1 AI case-gen engine behind AI seam | C10: ST-001..010 | D10: 42 | E10: Claude | F10: Done | G10: src/testgen.ts — 10 tests; LLM provider swap point isolated in generateFromStory.
A11: B-08 | B11: F2 run boards + metrics + CSV import | C11: ST-011..020 | D11: 42 | E11: Claude | F11: Done | G11: src/runboards.ts — 6 tests + E2E board flow.
A12: B-09 | B12: F3 flaky detector: webhook intake -> flip-rate -> quarantine | C12: ST-021..030 | D12: 50 | E12: Claude | F12: Done | G12: src/flaky.ts + src/webhooks.ts — HMAC/replay/dedupe; E2E tampered-signature 401.
A13: B-10 | B13: F4 readiness score, validated weights | C13: ST-031..040 | D13: 42 | E13: Claude | F13: Done | G13: src/readiness.ts — 5 tests; verdict bands ready/at-risk/not-ready.
A14: B-11 | B14: F5 Xray importer | C14: ST-041..050 | D14: 42 | E14: Claude | F14: Done | G14: src/xrayImport.ts — parse+map into TestGen; E2E import 201.
A15: B-12 | B15: E5 billing: trial/proration/dunning/limits/GST/cancel | C15: ST-057..063 | D15: 27 | E15: Claude | F15: Done | G15: src/billing.ts — 10 tests; proration case verified $100.
... A54: B-51 | B54: Per-user pricing anchor rewritten against the corrected 0% fee | C54: PR-13 / C-3 / D18 | D54: 3 | E54: Claude | F54: Done | G54: docs/pricing-faq.md; partner-console setup and test purchase remain Senthil (B-17).

Sheet Traceability_Matrix
A1: TRACEABILITY MATRIX — 100 original stories + the PR-series stories added 20/09
A2: Status: Done = automated-test evidence in repo (D13). Code-complete — pending live = built, pending live platform. Open = not started or needs a person. N/A (platform) = the platform owns it. Nothing was flipped to Done by this release without a pinned regression.
A3: Story ID | B3: Epic | C3: Module / feature | D3: Story | E3: Points | F3: Priority | G3: Sprint | H3: Primary screen | I3: Verification | J3: Status | K3: Evidence
A4: ST-001 | B4: F1 | C4: AI test-case generation | D4: As a QA lead, I can set up AI test-case generation with sensible defaults in one screen | E4: 5 | F4: P0 | G4: S2 | H4: SCR-3 AI generation workspace | I4: E2E test + demo | J4: Done | K4: src/testgen.ts DEFAULT_RULES + setRules; test/testgen.test.ts
A5: ST-002 | B5: F1 | C5: AI test-case generation | D5: As a QA lead, the AI test-case generation happy path completes without documentation | E5: 8 | F5: P0 | G5: S2 | H5: SCR-3 AI generation workspace | I5: E2E test + demo | J5: Done | K5: src/testgen.ts generateFromStory; testgen + e2e tests
A6: ST-003 | B6: F1 | C6: AI test-case generation | D6: As a Eng manager, I can customise AI test-case generation rules/conditions for my workflow | E6: 5 | F6: P1 | G6: S2 | H6: SCR-3 AI generation workspace | I6: Integration test + manual QA | J6: Done | K6: setRules customisation; validation test
A7: ST-004 | B7: F1 | C7: AI test-case generation | D7: As a user, AI test-case generation shows clear errors and retry paths on platform API failures | E7: 3 | F7: P0 | G7: S2 | H7: SCR-3 AI generation workspace | I7: E2E test + demo | J7: Done | K7: empty-story + bad-CSV clear errors; testgen tests
A8: ST-005 | B8: F1 | C8: AI test-case generation | D8: As a Jira admin, AI test-case generation works on the Forge app panel inside Jira surface end-to-end | E8: 5 | F8: P0 | G8: S3 | H8: SCR-3 AI generation workspace | I8: E2E test + demo | J8: Code-complete — pending live | K8: Full stack shipped; the panel now also reads its own story prefix only (PR-03) and is project-gated (PR-09). Live Forge render + extension.issue.key verification remain — PR-04.
A9: ST-006 | B9: F1 | C9: AI test-case generation | D9: As a Eng manager, I can see AI test-case generation performance metrics and trends | E9: 3 | F9: P1 | G9: S3 | H9: SCR-3 AI generation workspace | I9: Integration test + manual QA | J9: Done | K9: metrics() byKind rollup; test
A10: ST-007 | B10: F1 | C10: AI test-case generation | D10: As a user, AI test-case generation respects role permissions and audit logging | E10: 3 | F10: P1 | G10: S3 | H10: SCR-3 AI generation workspace | I10: Integration test + manual QA | J10: Done | K10: Permissions matrix + audit on every check; permissions tests
A11: ST-008 | B11: F1 | C11: AI test-case generation | D11: As a QA lead, I can pause/disable AI test-case generation without data loss | E11: 2 | F11: P2 | G11: S3 | H11: SCR-3 AI generation workspace | I11: Manual QA | J11: Done | K11: setEnabled pause, data retained; test
A12: ST-009 | B12: F1 | C12: AI test-case generation | D12: As a Eng manager, I can import/migrate existing data into AI test-case generation (CSV + competitor importer) | E12: 5 | F12: P1 | G12: S3 | H12: SCR-3 AI generation workspace | I12: Integration test + manual QA | J12: Done | K12: importCsv + importCases; ids now unique per creation (PR-02). testgen + identity tests.
A13: ST-010 | B13: F1 | C13: AI test-case generation | D13: As a user, I get notifications (in-app + email) for key AI test-case generation events with per-type mute | E13: 3 | F13: P2 | G13: S3 | H13: SCR-3 AI generation workspace | I13: Manual QA | J13: Done | K13: Notifications per-type prefs generation events; notifications tests
A14: ST-011 | B14: F2 | C14: Test run boards | D14: As a QA lead, I can set up Test run boards with sensible defaults in one screen | E14: 5 | F14: P0 | G14: S3 | H14: SCR-4 Run boards builder | I14: E2E test + demo | J14: Done | K14: src/runboards.ts createBoard defaults
A15: ST-012 | B15: F2 | C15: Test run boards | D15: As a QA lead, the Test run boards happy path completes without documentation | E15: 8 | F15: P0 | G15: S3 | H15: SCR-4 Run boards builder | I15: E2E test + demo | J15: Done | K15: record() happy path; e2e board flow
... A101: ST-098 | B101: EL | C101: Launch & listing | D101: Launch-day runbook: monitoring, rollback, comms tree | E101: 3 | F101: P1 | G101: S11 | H101: — (listing) | I101: Integration test + manual QA | J101: Done | K101: docs/launch-runbook.md: monitoring thresholds, rollback (additive schema + feature kill switches), comms tree
A102: ST-099 | B102: EL | C102: Launch & listing | D102: Post-launch listing SEO iteration 1 from search-term data | E102: 2 | F102: P2 | G102: S12 | H102: — (listing) | I102: Manual QA | J102: Backlog
A103: ST-100 | B103: EL | C103: Launch & listing | D103: First 10 design-partner reviews scheduled | E103: 2 | F103: P1 | G103: S11 | H103: — (listing) | I103: Integration test + manual QA | J103: Backlog | K103: Kit execution-ready and unchanged; ten conversations = Senthil (PR-14). EG-15 stays UNPROVEN until three teams make a documented go/no-go call.
A104: ST-101 | B104: EX | C104: Write integrity | D104: As a QA team, two of us can work in TestPulse at the same time without losing each other's work | E104: 13 | F104: P0 | G104: PR-01 | H104: all | I104: Automated test (G-5) | J104: Done | K104: Versioned values + CAS + commutative merges + per-entity keys. test/concurrency.test.ts, 100 interleaved writers.
A105: ST-102 | B105: EX | C105: Write integrity | D105: As a user, when someone else changed the thing I am saving, I am told to reload rather than silently overwriting them | E105: 3 | F105: P0 | G105: PR-01 | H105: all | I105: Automated test | J105: Done | K105: StoreConflictError -> ConflictError (409) with a reload message. test/concurrency.test.ts.
A106: ST-103 | B106: EX | C106: Identity | D106: As an engineer, every test case has one permanent unique id however it was created | E106: 5 | F106: P0 | G106: PR-02 | H106: SCR-3 | I106: Automated test | J106: Done | K106: src/ids.ts; test/identity.test.ts across generate / import / AI / CSV.
A107: ST-104 | B107: EX | C107: Identity | D107: As a QA lead, I can edit a generated case and be refused if someone edited it first | E107: 3 | F107: P1 | G107: PR-02 | H107: SCR-3 | I107: Automated test | J107: Done | K107: updateCase with expectedVersion; test/identity.test.ts.
A108: ST-105 | B108: EX | C108: Scale | D108: As a large site, I can hold 50,000 test cases and 100,000 CI results without hitting a storage ceiling | E108: 13 | F108: P0 | G108: PR-03 | H108: — | I108: Automated test | J108: Done | K108: Per-entity keys; test/performance.test.ts asserts no value near 240 KiB.
A109: ST-106 | B109: EX | C109: Scale | D109: As an admin, opening a panel does not load my whole site | E109: 8 | F109: P0 | G109: PR-03 | H109: all | I109: Automated test | J109: Done | K109: CALL_SCOPE per call; whoami loads 2 keys. test/performance.test.ts.
A110: ST-107 | B110: EX | C110: Readiness | D110: As an engineering manager, the readiness score is derived from live data and shows me where each number came from | E110: 13 | F110: P0 | G110: PR-05 | H110: SCR-2 | I110: Automated test + live | J110: Code-complete — pending live | K110: src/readinessLive.ts; sourced factors + explanation + trend. Live Jira proof at PR-04.
A111: ST-108 | B111: EX | C111: Readiness | D111: As an owner, I can override a factor, but only with a reason that is shown next to the score | E111: 3 | F111: P1 | G111: PR-05 | H111: SCR-2 | I111: Automated test | J111: Done | K111: setOverride requires a reason and records who; the panel labels it MANUAL OVERRIDE.
A112: ST-109 | B112: EX | C112: Automation | D112: As a team, I can post my JUnit, Playwright or Cucumber report straight to TestPulse | E112: 8 | F112: P0 | G112: PR-06 | H112: — | I112: Automated test + live | J112: Code-complete — pending live | K112: Three adapters against committed real-shape fixtures; a real pipeline post is a PR-04 step.
A113: ST-110 | B113: EX | C113: Automation | D113: As a pipeline, re-posting the same run changes nothing and an oversized post is refused cleanly | E113: 5 | F113: P0 | G113: PR-06 | H113: — | I113: Automated test | J113: Done | K113: Idempotent by run id (pinned); 413 on 1 MiB / 20,000 results.
A114: ST-111 | B114: EX | C114: Flaky | D114: As a QA lead, a test that is unstable only on a feature branch is not quarantined across my whole project | E114: 8 | F114: P1 | G114: PR-07 | H114: SCR-5 | I114: Automated test | J114: Done | K114: Branch-aware scoring; test/flaky2.test.ts.
... A123: ST-120 | B123: EX | C123: Trust | D123: As a regulated tenant, I can run TestPulse with no external egress at all | E123: 3 | F123: P1 | G123: PR-10/PR-11 | H123: SCR-6 | I123: Automated test + doc | J123: Done | K123: AI off by default = no-egress mode, named on the trust page and in the AI usage policy.

Sheet Sprint_Status_Rollup
A1: SPRINT STATUS ROLLUP — live formulas over Traceability_Matrix
A2: Do not edit computed cells. "Done" counts Done + Code-complete — pending live. Stories reclassified N/A (the platform owns them) are NOT counted as done, so a sprint can read below 100% while being complete — the RAG column says which and why. The rollup is deliberately conservative: it never flatters itself.
A3: Sprint | B3: Focus | C3: Stories | D3: Points | E3: Done | F3: Done points | G3: % points done | H3: RAG (manual) | I3: Exit criteria
A4: S1 | B4: Foundation (2 wks) | C4: =COUNTIFS(Traceability_Matrix!$G$4:$G$123,A4) | D4: =SUMIFS(Traceability_Matrix!$E$4:$E$123,Traceability_Matrix!$G$4:$G$123,A4) | E4: =COUNTIFS(Traceability_Matrix!$G$4:$G$123,A4,Traceability_Matrix!$J$4:$J$123,"Done")+COUNTIFS(Traceability_Matrix!$G$4:$G$123,A4,Traceability_Matrix!$J$4:$J$123,"Code-complete — pending live") | F4: =SUMIFS(Traceability_Matrix!$E$4:$E$123,Traceability_Matrix!$G$4:$G$123,A4,Traceability_Matrix!$J$4:$J$123,"Done")+SUMIFS(Traceability_Matrix!$E$4:$E$123,Traceability_Matrix!$G$4:$G$123,A4,Traceability_Matrix!$J$4:$J$123,"Code-complete — pending live") | G4: =IFERROR(F4/D4,0) | H4: GREEN — the count reads 3 of 4 because ST-055 (token rotation) was reclassified N/A on 20/09: Forge owns OAuth and TestPulse now stores no credential at all (AEC 1.5). An N/A story is deliberately NOT counted as done, so this rollup never flatters itself. Live install pending (PR-04). | I4: App installs cleanly in dev store/org; telemetry firing
A5: S2 | B5: AI test-case generation pt 1 | C5: =COUNTIFS(Traceability_Matrix!$G$4:$G$123,A5) | D5: =SUMIFS(Traceability_Matrix!$E$4:$E$123,Traceability_Matrix!$G$4:$G$123,A5) | E5: =COUNTIFS(Traceability_Matrix!$G$4:$G$123,A5,Traceability_Matrix!$J$4:$J$123,"Done")+COUNTIFS(Traceability_Matrix!$G$4:$G$123,A5,Traceability_Matrix!$J$4:$J$123,"Code-complete — pending live") | F5: =SUMIFS(Traceability_Matrix!$E$4:$E$123,Traceability_Matrix!$G$4:$G$123,A5,Traceability_Matrix!$J$4:$J$123,"Done")+SUMIFS(Traceability_Matrix!$E$4:$E$123,Traceability_Matrix!$G$4:$G$123,A5,Traceability_Matrix!$J$4:$J$123,"Code-complete — pending live") | G5: =IFERROR(F5/D5,0) | H5: GREEN — 6/6 done | I5: AI case-gen happy path demoable
A6: S3 | B6: AI case-gen pt 2 + Run boards start | C6: =COUNTIFS(Traceability_Matrix!$G$4:$G$123,A6) | D6: =SUMIFS(Traceability_Matrix!$E$4:$E$123,Traceability_Matrix!$G$4:$G$123,A6) | E6: =COUNTIFS(Traceability_Matrix!$G$4:$G$123,A6,Traceability_Matrix!$J$4:$J$123,"Done")+COUNTIFS(Traceability_Matrix!$G$4:$G$123,A6,Traceability_Matrix!$J$4:$J$123,"Code-complete — pending live") | F6: =SUMIFS(Traceability_Matrix!$E$4:$E$123,Traceability_Matrix!$G$4:$G$123,A6,Traceability_Matrix!$J$4:$J$123,"Done")+SUMIFS(Traceability_Matrix!$E$4:$E$123,Traceability_Matrix!$G$4:$G$123,A6,Traceability_Matrix!$J$4:$J$123,"Code-complete — pending live") | G6: =IFERROR(F6/D6,0) | H6: GREEN — ST-005 flips at PR-04 | I6: AI case-gen complete with tests; Run boards skeleton
A7: S4 | B7: Test run boards | C7: =COUNTIFS(Traceability_Matrix!$G$4:$G$123,A7) | D7: =SUMIFS(Traceability_Matrix!$E$4:$E$123,Traceability_Matrix!$G$4:$G$123,A7) | E7: =COUNTIFS(Traceability_Matrix!$G$4:$G$123,A7,Traceability_Matrix!$J$4:$J$123,"Done")+COUNTIFS(Traceability_Matrix!$G$4:$G$123,A7,Traceability_Matrix!$J$4:$J$123,"Code-complete — pending live") | F7: =SUMIFS(Traceability_Matrix!$E$4:$E$123,Traceability_Matrix!$G$4:$G$123,A7,Traceability_Matrix!$J$4:$J$123,"Done")+SUMIFS(Traceability_Matrix!$E$4:$E$123,Traceability_Matrix!$G$4:$G$123,A7,Traceability_Matrix!$J$4:$J$123,"Code-complete — pending live") | G7: =IFERROR(F7/D7,0) | H7: GREEN — MVP loop passes E2E in CI | I7: MVP loop usable end-to-end internally
A8: S5 | B8: Flaky-test detector + alpha hardening | C8: =COUNTIFS(Traceability_Matrix!$G$4:$G$123,A8) | D8: =SUMIFS(Traceability_Matrix!$E$4:$E$123,Traceability_Matrix!$G$4:$G$123,A8) | E8: =COUNTIFS(Traceability_Matrix!$G$4:$G$123,A8,Traceability_Matrix!$J$4:$J$123,"Done")+COUNTIFS(Traceability_Matrix!$G$4:$G$123,A8,Traceability_Matrix!$J$4:$J$123,"Code-complete — pending live") | F8: =SUMIFS(Traceability_Matrix!$E$4:$E$123,Traceability_Matrix!$G$4:$G$123,A8,Traceability_Matrix!$J$4:$J$123,"Done")+SUMIFS(Traceability_Matrix!$E$4:$E$123,Traceability_Matrix!$G$4:$G$123,A8,Traceability_Matrix!$J$4:$J$123,"Code-complete — pending live") | G8: =IFERROR(F8/D8,0) | H8: GREEN — and materially deeper after PR-07 | I8: Internal alpha: team dogfoods daily
A9: S6 | B9: Billing + Release readiness score | C9: =COUNTIFS(Traceability_Matrix!$G$4:$G$123,A9) | D9: =SUMIFS(Traceability_Matrix!$E$4:$E$123,Traceability_Matrix!$G$4:$G$123,A9) | E9: =COUNTIFS(Traceability_Matrix!$G$4:$G$123,A9,Traceability_Matrix!$J$4:$J$123,"Done")+COUNTIFS(Traceability_Matrix!$G$4:$G$123,A9,Traceability_Matrix!$J$4:$J$123,"Code-complete — pending live") | F9: =SUMIFS(Traceability_Matrix!$E$4:$E$123,Traceability_Matrix!$G$4:$G$123,A9,Traceability_Matrix!$J$4:$J$123,"Done")+SUMIFS(Traceability_Matrix!$E$4:$E$123,Traceability_Matrix!$G$4:$G$123,A9,Traceability_Matrix!$J$4:$J$123,"Code-complete — pending live") | G9: =IFERROR(F9/D9,0) | H9: GREEN in code — readiness is now DERIVED (PR-05); Atlassian billing at listing | I9: Can charge a test customer; up/downgrade paths work
A10: S7 | B10: Private beta (design partners) | C10: =COUNTIFS(Traceability_Matrix!$G$4:$G$123,A10) | D10: =SUMIFS(Traceability_Matrix!$E$4:$E$123,Traceability_Matrix!$G$4:$G$123,A10) | E10: =COUNTIFS(Traceability_Matrix!$G$4:$G$123,A10,Traceability_Matrix!$J$4:$J$123,"Done")+COUNTIFS(Traceability_Matrix!$G$4:$G$123,A10,Traceability_Matrix!$J$4:$J$123,"Code-complete — pending live") | F10: =SUMIFS(Traceability_Matrix!$E$4:$E$123,Traceability_Matrix!$G$4:$G$123,A10,Traceability_Matrix!$J$4:$J$123,"Done")+SUMIFS(Traceability_Matrix!$E$4:$E$123,Traceability_Matrix!$G$4:$G$123,A10,Traceability_Matrix!$J$4:$J$123,"Code-complete — pending live") | G10: =IFERROR(F10/D10,0) | H10: AMBER — code done; live partners gate beta exit (PR-14) | I10: 3+ partners active weekly; NPS pulse >30
A11: S8 | B11: Beta iteration + Xray importer | C11: =COUNTIFS(Traceability_Matrix!$G$4:$G$123,A11) | D11: =SUMIFS(Traceability_Matrix!$E$4:$E$123,Traceability_Matrix!$G$4:$G$123,A11) | E11: =COUNTIFS(Traceability_Matrix!$G$4:$G$123,A11,Traceability_Matrix!$J$4:$J$123,"Done")+COUNTIFS(Traceability_Matrix!$G$4:$G$123,A11,Traceability_Matrix!$J$4:$J$123,"Code-complete — pending live") | F11: =SUMIFS(Traceability_Matrix!$E$4:$E$123,Traceability_Matrix!$G$4:$G$123,A11,Traceability_Matrix!$J$4:$J$123,"Done")+SUMIFS(Traceability_Matrix!$E$4:$E$123,Traceability_Matrix!$G$4:$G$123,A11,Traceability_Matrix!$J$4:$J$123,"Code-complete — pending live") | G11: =IFERROR(F11/D11,0) | H11: AMBER — importer format-faithful; 3 REAL export files still owed (LC-5) | I11: Beta cohort WoW retention >60%
A12: S9 | B12: Marketplace review prep | C12: =COUNTIFS(Traceability_Matrix!$G$4:$G$123,A12) | D12: =SUMIFS(Traceability_Matrix!$E$4:$E$123,Traceability_Matrix!$G$4:$G$123,A12) | E12: =COUNTIFS(Traceability_Matrix!$G$4:$G$123,A12,Traceability_Matrix!$J$4:$J$123,"Done")+COUNTIFS(Traceability_Matrix!$G$4:$G$123,A12,Traceability_Matrix!$J$4:$J$123,"Code-complete — pending live") | F12: =SUMIFS(Traceability_Matrix!$E$4:$E$123,Traceability_Matrix!$G$4:$G$123,A12,Traceability_Matrix!$J$4:$J$123,"Done")+SUMIFS(Traceability_Matrix!$E$4:$E$123,Traceability_Matrix!$G$4:$G$123,A12,Traceability_Matrix!$J$4:$J$123,"Code-complete — pending live") | G12: =IFERROR(F12/D12,0) | H12: AMBER — pen test + bug bounty are procurement items (AEC 1.1/1.2) | I12: Review submission accepted into queue
A13: S10 | B13: Review remediation + docs | C13: =COUNTIFS(Traceability_Matrix!$G$4:$G$123,A13) | D13: =SUMIFS(Traceability_Matrix!$E$4:$E$123,Traceability_Matrix!$G$4:$G$123,A13) | E13: =COUNTIFS(Traceability_Matrix!$G$4:$G$123,A13,Traceability_Matrix!$J$4:$J$123,"Done")+COUNTIFS(Traceability_Matrix!$G$4:$G$123,A13,Traceability_Matrix!$J$4:$J$123,"Code-complete — pending live") | F13: =SUMIFS(Traceability_Matrix!$E$4:$E$123,Traceability_Matrix!$G$4:$G$123,A13,Traceability_Matrix!$J$4:$J$123,"Done")+SUMIFS(Traceability_Matrix!$E$4:$E$123,Traceability_Matrix!$G$4:$G$123,A13,Traceability_Matrix!$J$4:$J$123,"Code-complete — pending live") | G13: =IFERROR(F13/D13,0) | H13: AMBER — docs current as of 20/09; approval needs submission | I13: Marketplace approval obtained
A14: S11 | B14: Launch | C14: =COUNTIFS(Traceability_Matrix!$G$4:$G$123,A14) | D14: =SUMIFS(Traceability_Matrix!$E$4:$E$123,Traceability_Matrix!$G$4:$G$123,A14) | E14: =COUNTIFS(Traceability_Matrix!$G$4:$G$123,A14,Traceability_Matrix!$J$4:$J$123,"Done")+COUNTIFS(Traceability_Matrix!$G$4:$G$123,A14,Traceability_Matrix!$J$4:$J$123,"Code-complete — pending live") | F14: =SUMIFS(Traceability_Matrix!$E$4:$E$123,Traceability_Matrix!$G$4:$G$123,A14,Traceability_Matrix!$J$4:$J$123,"Done")+SUMIFS(Traceability_Matrix!$E$4:$E$123,Traceability_Matrix!$G$4:$G$123,A14,Traceability_Matrix!$J$4:$J$123,"Code-complete — pending live") | G14: =IFERROR(F14/D14,0) | H14: RED — blocked on LC-1 (PR-04) and D18 (PR-13) | I14: First 10 installs; first 3 reviews; activation >40%
A15: S12 | B15: Iterate & scale decision | C15: =COUNTIFS(Traceability_Matrix!$G$4:$G$123,A15) | D15: =SUMIFS(Traceability_Matrix!$E$4:$E$123,Traceability_Matrix!$G$4:$G$123,A15) | E15: =COUNTIFS(Traceability_Matrix!$G$4:$G$123,A15,Traceability_Matrix!$J$4:$J$123,"Done")+COUNTIFS(Traceability_Matrix!$G$4:$G$123,A15,Traceability_Matrix!$J$4:$J$123,"Code-complete — pending live") | F15: =SUMIFS(Traceability_Matrix!$E$4:$E$123,Traceability_Matrix!$G$4:$G$123,A15,Traceability_Matrix!$J$4:$J$123,"Done")+SUMIFS(Traceability_Matrix!$E$4:$E$123,Traceability_Matrix!$G$4:$G$123,A15,Traceability_Matrix!$J$4:$J$123,"Code-complete — pending live") | G15: =IFERROR(F15/D15,0) | H15: RED — needs PR-14 evidence | I15: Growth model doc with CAC/LTV first estimates
... A25: PR-11 | B25: Atlassian Enterprise Certified programme | C25: =COUNTIFS(Traceability_Matrix!$G$4:$G$123,A25) | D25: =SUMIFS(Traceability_Matrix!$E$4:$E$123,Traceability_Matrix!$G$4:$G$123,A25) | E25: =COUNTIFS(Traceability_Matrix!$G$4:$G$123,A25,Traceability_Matrix!$J$4:$J$123,"Done")+COUNTIFS(Traceability_Matrix!$G$4:$G$123,A25,Traceability_Matrix!$J$4:$J$123,"Code-complete — pending live") | F25: =SUMIFS(Traceability_Matrix!$E$4:$E$123,Traceability_Matrix!$G$4:$G$123,A25,Traceability_Matrix!$J$4:$J$123,"Done")+SUMIFS(Traceability_Matrix!$E$4:$E$123,Traceability_Matrix!$G$4:$G$123,A25,Traceability_Matrix!$J$4:$J$123,"Code-complete — pending live") | G25: =IFERROR(F25/D25,0) | H25: AMBER — engineering met; pen test + bounty are Senthil | I25: Every AEC row has an owner, date and evidence
A26: TOTAL | B26: (all sprints) | C26: =SUM(C4:C25) | D26: =SUM(D4:D25) | E26: =SUM(E4:E25) | F26: =SUM(F4:F25) | G26: =IFERROR(F26/D26,0)

Sheet RAID_Carryover
A1: RAID — carried from v027, updated by external review V001
A2: Rows whose state changed on 20/09 are marked in the Notes column.
A3: ID / Type | B3: Type | C3: Raised | D3: Item | E3: Status | F3: Notes / Mitigation
A4: R-P1 | B4: Risk | C4: v007 | D4: Atlassian Forge program rate/policy changes mid-build (Medium/Medium) | E4: Open — and it bit us | F4: The programme changes this review caught (Fortified retirement, the revenue-share change) are exactly this risk landing. Mitigation strengthened: the changelog is now a named LC-1 check, and every economics figure in the pack cites its source and date.
A5: R-P2 | B5: Risk | C5: v007 | D5: Xray/Zephyr respond with AI features (High/Medium) | E5: MATERIALISED (C-4, 20/09) | F5: The review confirmed it has already happened: Xray lists as "powered by AI", Zephyr as "with Rovo", and the Testing & QA category carries a crowded field of dedicated generators. This is no longer a risk to track — it is a fact to price and position against. The wedge moves to the release decision (Decision 4), which PR-05 now earns in code.
A6: R-P3 | B6: Risk | C6: v007 | D6: Cloud Fortified bar raises before listing (Medium/Medium) | E6: SUPERSEDED (C-2, 20/09) | F6: Cloud Fortified closed to new submissions 01/09/2026 and retires 31/12/2026. The risk did not "raise" — the programme ended. Replaced by the Atlassian Enterprise Certified assessment, whose bar is higher and two of whose rows are procurement items.
A7: R-P4 | B7: Constraint | C7: 22:58 | D7: Sandbox has no Forge CLI/hosted storage — persistence is in-memory behind typed Store; billing behind provider seam (D17) | E7: Closed-in-code | F7: 08:31: ForgeStore adapter shipped+tested (hydrate/write-through/flush); manifest + deploy guide make the swap glue-only at forge deploy. Billing seam (B-17) remains the one open adapter.
A8: R-P5 | B8: Risk | C8: 22:58 | D8: CI-webhook signing scheme is TestPulse-defined (own HMAC ts.body) — customer CI integrations must adopt it; no Atlassian-mandated scheme verified yet | E8: Closed (verified) | F8: 15:27: Official Forge docs — webtrigger URLs are public, platform does NOT authenticate them, own-auth-in-handler is the documented pattern. Our HMAC-SHA256 + 5-min window + dedupe stands as designed; manifest carries urlFormat v2 + dynamic response.
A9: R-P6 | B9: Risk | C9: 22:58 | D9: AI seam currently rule-based — listing copy must not overclaim "AI" until LLM provider wired | E9: Mitigated-in-code | F9: 23:13: AnthropicProvider shipped behind seam (8 tests); rule engine = no-key fallback. Listing AI claim now code-backed; live verification with real key at deploy before copy final.
A10: A-P1 | B10: Assumption | C10: 22:58 | D10: D13 (interviews parked, 100% coverage) applies to TestPulse incl. S0 discovery | E10: Discharged | F10: S0 PRD rolled up in docs/prd.md with D13 assumptions explicitly flagged for design-partner validation (ST-100).
A11: A-P2 | B11: Assumption | C11: 22:58 | D11: D15 mode (parallel vs swap) pending — nine concurrent builds now exist | E11: Open | F11: Senthil to ratify; R1 serial rule formally intact until then.
A12: I | B12: F-TP01/F-TP02 class: published data claims were not implemented — found only by adversarial review, not by 100% coverage | C12: Open | D12: Claude | E12: 2026-09-11 22:28 | F12: Registry + drift test now fail the build if a namespace goes unregistered; the same check is worth porting to the other 11 products
A13: D | B13: OBS-TP1 hydrate-all vs prefix-scoped hydration; OBS-TP2 breaker half-open limit (portfolio-wide); OBS-TP4 billing recovery/trial expiry if a direct channel opens | C13: Open | D13: Senthil | E13: 2026-09-11 22:28 | F13: Dispositions in workbook v015 Review_Findings column F
A14: I | B14: L-P1: a 100%-covered codebase can be undeployable — nothing in the suite loads the file the platform loads. Second occurrence in the portfolio after VoiceBridge VER-V01. | C14: Open | D14: Senthil | E14: 2026-09-13 | F14: Entrypoint type-check + UI build are CI gates on TestPulse; porting the same two gates to the other 10 products is the open call
... A34: A | B34: Assumption | C34: 20/09 | D34: The competitive and economics figures in this pack (Xray pricing, install counts, revenue share) were read on 16/09 and 20/09 | E34: Open — re-read before publishing | F34: Marketplace pricing and install counts change; every figure carries its source and date, and PR-13 re-reads them before anything is published.

Sheet Gate_Checklist
A1: COMPLETION GATE (D7) — TestPulse is DONE only when every row is Done
A2: R2: code complete counts for nothing. Gate decision = Senthil (R5/D10). LC-3 and LC-6 were corrected DOWNWARDS by this release.
A3: ID | B3: Gate item | C3: Source | D3: Status
A4: G-01 | B4: App LISTED on Atlassian Marketplace (approved + published) | C4: D7 / R2 | D4: Open
A5: G-02 | B5: 10 PAYING installs from strangers | C5: D7 / R2 | D5: Open
A6: G-03 | B6: S12 kill criteria evaluated with evidence pack | C6: D7 / R3 | D6: Open
A7: G-04 | B7: Kill/continue decision recorded by Senthil | C7: R5 / D10 | D7: Open
A8: G-05 | B8: On CONTINUE: next-rank build authorised; TestPulse enters R4 ops floor | C8: N4 / R1 | D8: Open
A9: LC-1 | B9: Marketplace vendor account + Forge app registered; installs in real Jira Cloud dev site | C9: v008 LC #1 | D9: Open — TURNKEY+. Unchanged in kind and extended in substance: the run sheet now also captures extension.project.key, the restricted-project denial that flips LC-6, a real JUnit post, a derived-readiness screenshot, and the two wall-time figures that decide D19 (Forge SQL).
A10: LC-2 | B10: Forge app review pack: scopes, egress allowlist, storage use documented | C10: v008 LC #2 | D10: Doc-complete — review pack current; scope justification now names four call paths for read:jira-work and the scope-egress gate requires each.
A11: LC-3 | B11: Cloud Fortified gap assessment with target date | C11: v008 LC #3 | D11: OPEN — CORRECTED 20/09 (C-2). The Cloud Fortified programme closed to new submissions 01/09/2026 and retires 31/12/2026, so the previous "no structural gaps, apply at listing+60d" assessment targeted a route that no longer exists. Replaced by docs/enterprise-certified-gap.md against Atlassian Enterprise Certified: engineering rows MET and pinned, but AEC 1.1 (CREST/Bugcrowd penetration test) and AEC 1.2 (public bug bounty) are procurement items with lead times and the programme cannot be applied for until they are done.
A12: LC-4 | B12: Data residency: Forge hosted storage regions statement | C12: v008 LC #4 | D12: Doc-complete — docs/residency-statement.md ready for trust tab
A13: LC-5 | B13: Xray/Zephyr importer tested on 3 REAL export files | C13: v008 LC #5 | D13: Open — importer format-faithful and the CI adapters now fixture-backed for three frameworks; 3 REAL Xray/Zephyr export files remain the acceptance evidence (Senthil, half a day).
A14: LC-6 | B14: Jira permission schemes respected (project vs global) verified | C14: v008 LC #6 | D14: OPEN — CORRECTED 20/09 (C-1/PRX-03). Was "Done-in-code — scope-aware guard + audit"; the guard LOGGED scope and never enforced it, so any licensed member could see every project. Enforcement now shipped (PR-09: BROWSE_PROJECTS via asUser, failing closed, with the project dimension on the audit log). The row stays OPEN until the live restricted-project capture at PR-04 — "fixed in code" is exactly what was being corrected.
... A19: G-5 | B19: Standing gate: concurrent write safety (NEW 20/09) | C19: L-P8 / PRX-02 | D19: GREEN — 13 shared keys protected statically, every one exercised under interleaved writers. Seventh gate in CI. Portable kit updated so it can go to the other 11 products, which is the open portfolio call.

Sheet Code_Inventory
A1: CODE SHIPPED 20/09 — every module and suite added or rewritten, and why
A2: So a reader can go from a review finding to the file that answers it without grepping.
A3: File | B3: New / rewritten | C3: Sprint | D3: What it does, and which finding it answers | E3: Pinned by
A4: src/store.ts | B4: Rewritten | C4: PR-01 | D4: The Store seam grew COMMUTATIVE operations — append, increment, union, setIfAbsent, update — so a shared value is never written with a plain read-modify-write. A plain set stays correct for documents with owner-edit semantics, where a conflict SHOULD surface. (PRX-02) | E4: test/concurrency.test.ts
A5: src/forgeStore.ts | B5: Rewritten | C5: PR-01/PR-03 | D5: Versioned envelopes, compare-and-set on plain writes, reducers re-applied at flush and retried on conflict, prefix-scoped hydration that throws on an undeclared read, and a parallel point-key fetch. (PRX-02, PRX-05) | E5: test/concurrency.test.ts, test/performance.test.ts
A6: src/ids.ts | B6: New | C6: PR-02 | D6: Time-sortable unique ids and a batch uniqueness assertion, used by every creation path. (PRX-01) | E6: test/identity.test.ts
A7: src/sqlStore.ts | B7: New | C7: PR-03 | D7: Forge SQL adapter behind the same ForgeKvs seam, with a REAL atomic compare-and-set and idempotent migrations. Opt-in by manifest; ADR-001 records why it is not the default yet. | E7: test/sqlStore.test.ts
A8: src/readinessLive.ts | B8: New | C8: PR-05 | D8: Readiness derived from run boards, CI results and Jira JQL, with per-factor sources, an explanation, a 30-day trend, per-project config and an attributed override. (Decision 4) | E8: test/readiness.live.test.ts
A9: src/ciReports.ts | B9: New | C9: PR-06 | D9: JUnit XML, Playwright JSON and Cucumber JSON adapters, dependency-free, with size caps and a 413 path. (EG-06) | E9: test/ciReports.test.ts + test/fixtures/ci/*
A10: src/traceability.ts | B10: New | C10: PR-08 | D10: Requirement -> test -> run -> defect graph and coverage by release. Contains no Jira write path, deliberately. (EG-05) | E10: test/traceability.test.ts
A11: src/flaky.ts | B11: Rewritten | C11: PR-03/PR-07 | D11: Per-run storage under a bounded index, per-test/per-branch scoring windows, clusters, new-vs-chronic, quarantine with owner and expiry. (PRX-04) | E11: test/flaky2.test.ts, test/performance.test.ts
A12: src/testgen.ts | B12: Rewritten | C12: PR-01/PR-02 | D12: One key per case, unique ids, version + updatedAt, optimistic updateCase, project and story listings. (PRX-01, PRX-02) | E12: test/identity.test.ts, test/testgen.test.ts
A13: src/runboards.ts | B13: Rewritten | C13: PR-01 | D13: Board metadata plus one key per run, idempotent by caller run id, fixed default-board id so racing panels converge. (PRX-02, PERF-03) | E13: test/runboards.test.ts, test/concurrency.test.ts
A14: src/permissions.ts | B14: Rewritten | C14: PR-09 | D14: Scope is now part of the decision, not just the audit entry; fails closed on an unanswered visibility check; audit carries the project and the denial reason. (PRX-03) | E14: test/permissions.test.ts, test/project-scope.test.ts
... A24: docs/ai-usage-policy.md | B24: New | C24: PR-10 | D24: The public AI usage policy AEC 5.1 requires, naming Anthropic as a subprocessor. | E24: claims gate C-38/C-39
