Workbook

Sheet Version_Control
A1: VERSION CONTROL — EngageOS Sprint Tracker & Traceability
A2: File naming: claude_v<NNN>_<proper file name>_YYYYMMDD_HHMI.xlsx. Companion: EngageOS product workbook v005 (baseline) -> v006 (22:22, S1-S8 dev) -> v007 (22:55, S9-S10 drafts) = backlog source of truth (D12 pattern); its v008 stays planned for the live Meta verification wave.
A3: Version | B3: Date/Time | C3: Author | D3: Change Description | E3: Status
A4: v001 | B4: 2026-09-10 23:06 | C4: Claude for Senthil/KP | D4: THIS FILE — Consolidated live execution tracker for EngageOS (WhatsApp Business Platform, wave-1), created on Senthil's 23:06 instruction to mirror the TeleField v001 tracker pattern. Rebuilds the full record of BOTH prior runs with proper version stamps: v006 run (22:22) = S1-S8 development, 15 modules, 16 suites / 73 tests at 100%x4 coverage (D13), 75 stories Done-in-code + 8 pending-live; v007 run (22:55) = S9-S10 draftable scope, 4 WhatsApp-compliance modules (24h session window, webhook dedupe/burst, opt-in proof, demo mode), 20 suites / 78 tests at 100%x4, 10 stories Drafted + ST-097 In progress. E001-E014 logged; 100-story traceability with per-story version-stamped evidence; rollup formula-verified. Code: engageos_v0.6.0_src.zip + engageos_v0.7.0_src.zip. | E4: Released
A5: v002 | B5: 2026-09-10 23:10 | C5: Claude for Senthil/KP | D5: Live-sweep readiness increment (was planned as live wave; re-scoped — live wave itself is now v003): CloudApiAdapter real WaApi implementation + typed config + runLiveSweep scripted verification + 30-min WABA setup guide + 12-step sweep doc shipped in codebase v0.8.0 (23 suites / 86 tests, 100%x4). E015-E016 logged. No traceability status changes per R2 — Pending-live flips require sweep evidence. Code: engageos_v0.8.0_src.zip. | E5: Released
A6: v003 | B6: 2026-09-11 08:17 | C6: Claude for Senthil/KP | D6: Adversarial cold-review pass (first reviewer) + fixes: 4 defects found and fixed with regression tests (F-001 unconfigured-inbox crash path, F-002 chatbot question-node TypeError, F-003 unbounded webhook dedupe ledger -> FIFO cap 20x queue, F-004 hardcoded template language -> parameterised for hi/ta); 4 further findings logged with dispositions for Senthil (Review_Findings sheet added). Codebase v0.9.0: 23 suites / 90 tests, 100%x4, BUILD_OK. docs/REVIEW_PACK.md added so an EXTERNAL second reviewer can run ST-097 independently — ST-097 stays In progress: same-AI review does not satisfy second-reviewer independence. Live wave rolls to v004. | E6: Released
A7: v004 | B7: 2026-09-11 12:51 | C7: Claude for Senthil/KP | D7: Review-prep completion wave (live wave rolls to v005): ST-089 WCAG flipped Done-in-code via views.ts screen shells + jest-axe suite (24 suites / 94 tests, 100%x4, codebase v0.10.0); ST-068 to In progress on SECURITY_EVIDENCE.md sandbox half; ST-094 to Drafted on ASSET_PLAN.md. E019-E020 logged. Backlog down to 3 truly-external stories (ST-081/099/100). Code: engageos_v0.10.0_src.zip. | E7: Released
A8: v005 | B8: 2026-09-13 09:55 | C8: Claude for Senthil/KP | D8: Cold-review pass 2 + completion wave (live wave rolls to v006). Pass 2: 8 defects fixed with pinned regressions (F-009..F-016; headline = optIn/sessionWindow modules built in v007 but never wired into any send path). Completion wave: ST-081/080/095 Done-in-code, ST-099/100 Code-complete -> BACKLOG ZERO. ENGAGEOS CODE PHASE COMPLETE — 79 Done-in-code / 10 Pending-live / 9 Drafted / 2 In progress / 0 Backlog (309/399 pts; ST-099/100 sit in Pending-live and do not count toward Done points). Codebase v0.11.0: 27 suites / 118 tests at 100%x4, one documented pragma. Cold review complete across all modules. | E8: Released
A9: v006 | B9: 2026-09-13 10:23 | C9: Claude for Senthil/KP | D9: Artifact-gap audit (live wave rolls to v007): 6 gaps found, 2 CRITICAL — no HTTP application and no DB schema existed behind artifacts the setup guide, deploy workflow, k6 harness and retention purge all referenced. Built: router + app (webhook verify/receive, healthz, pricing, help search, status), Node server entry with npm start, X-Hub-Signature-256 verification, 4 ordered migrations with cascade deletes + npm run migrate, signed k6 fixture generator, npm run sweep CLI, docs + pricing drift gates. ST-088/090/092 -> Code-complete. Codebase v0.12.0: 31 suites / 131 tests at 100%x4. Lesson L-E2 logged. Story rollup unchanged at 79 Done-in-code / 309 pts — this was missing plumbing, not new stories. | E9: Released
A10: v007 | B10: 2026-09-13 10:35 | C10: Claude for Senthil/KP | D10: Cold-review pass 3 over the v012 HTTP layer (live wave rolls to v008): 4 defects fixed, 2 CRITICAL — F-017 no multi-tenancy (shared dedupe ledger and session window across every WABA account), F-018 a valid signature treated as proof of installation, F-019 unauthenticated operational detail, F-020 no OAuth CSRF state. New modules tenancy.ts + oauth.ts; /admin/health and detailed /status behind ENGAGEOS_OPERATOR_TOKEN; /oauth/start + /oauth/callback register tenants with single-use 10-minute state. Codebase v0.13.0: 31 suites / 136 tests at 100%x4. Lesson L-E3 logged. Story position unchanged at 79 Done-in-code / 309 pts. | E10: Released
A11: v008 | B11: 2026-09-13 10:38 | C11: Claude for Senthil/KP | D11: External verification sweep vs live Meta/WhatsApp Cloud API documentation (live wave rolls to v009): 6 findings, 2 serious — VER-E5 batched-webhook data loss (only the first message of each envelope was processed) and VER-E1 the commercial model was built on conversation-based pricing, deprecated by Meta on 1 July 2025 in favour of per-message pricing; plus VER-E2 missing authentication template category, VER-E3 unmodelled 72-hour free-entry-point window, VER-E4 ack/retry semantics verified correct-by-design, VER-E6 80 msg/s throughput now limited. New modules messageCost.ts + throughput.ts. Codebase v0.14.0: 32 suites / 144 tests at 100%x4. Lesson L-E4 logged. Story position unchanged at 79 Done-in-code / 309 pts — correctness release. | E11: Released
A12: v009 | B12: 2026-09-13 10:58 | C12: Claude for Senthil/KP | D12: Verification sweep pass 2 — messaging limits and delivery policy (live wave rolls to v010): VER-E7 no messaging-tier awareness in broadcasts (portfolio-wide 250-to-unlimited ladder of unique business-initiated recipients per rolling 24h), VER-E8 service-window replies verified exempt, VER-E9 US marketing freeze unguarded, VER-E10 frequency-cap errors retried when they must not be. New modules messagingTier.ts + sendPolicy.ts, wired into the send path. Codebase v0.15.0: 33 suites / 151 tests at 100%x4. New risk R-E8 (Meta trust ladder gates go-to-market). Story position unchanged at 79 Done-in-code / 309 pts. | E12: Released
A13: v010 | B13: 2026-09-13 11:04 | C13: Claude for Senthil/KP | D13: Verification sweep pass 3 — message handling (live wave rolls to v011): VER-E11 campaign metrics counted API acceptance as delivery while status webhooks were discarded; VER-E12 inbound media dropped (only a media_id arrives); VER-E13 interactive button/list replies unreadable by the chatbot. New modules deliveryStatus.ts, media.ts, interactive.ts; campaign metrics now distinguish acceptance from confirmed delivery. Codebase v0.16.0: 34 suites / 158 tests at 100%x4. Verification sweep COMPLETE across pricing, limits, policy and message handling. Story position unchanged at 79 Done-in-code / 309 pts. | E13: Released
A14: v011 | B14: 2026-09-13 11:13 | C14: Claude for Senthil/KP | D14: State-architecture audit (live wave rolls to v012): GAP-E8 CRITICAL — every correctness guard was process-local while our own blue/green workflow runs two instances; SharedStore boundary + PgStore (database-side atomicity) + one contract suite over both implementations + single-instance invariant documented and guarded. GAP-E7 — migrations 005/006 for the state added after v012. Codebase v0.17.0: 35 suites / 167 tests at 100%x4. New risk R-E9. Story position unchanged at 79 Done-in-code / 309 pts. | E14: Released
... A45: v042 | B45: 2026-09-16 18:40 | C45: Claude for Senthil/KP | D45: Phase 3 of the review response (directive 16 Sep 16:21, plan approved 18:03: "do all"). Code v0.46.0: 62 suites / 512 tests at 100% coverage, run against a REAL Postgres 16.13 for the first time. Moved: F-CG-003 code half (Meta code exchange, debug_token, WABA/number discovery, forged-id refusal; InstallService no longer fabricates tokens); F-CG-004 first slice (tenant connections durable, sealed-or-refused by the database, restored at boot); F-CG-005 live half (shipped server boots on pg, survives restart, 503 during a database outage); F-CG-008 slice (logout, revoke-agent, cross-instance); F-CG-009/S07 remainder (rate limits, body schemas, SSRF allowlist, CSRF by construction); CG-G0 (SBOM + dependency policy). Five NEW defects found by running things, F-050..F-054 — including that the CI smoke gate could never pass and that audit:versions was never in CI. Story position unchanged: 80/100 stories, 312/399 points Done-in-code, ZERO Done. (The 15 Sep file index said 309; the matrix has said 312 since v040 — corrected.) | E45: Released
A46: v043 | B46: PLANNED: opens on external review V002, the first live Meta evidence, or the ICP decision that unblocks S13. | E46: Planned

Sheet Sprint_Tracker_Log
A1: SPRINT TRACKER LOG — every execution event, newest last
A2: ID | B2: Date/Time | C2: Sprint | D2: What happened | E2: Refs | F2: State changes | G2: Blockers | H2: Next
A3: E001 | B3: 2026-09-10 22:22 | C3: — | D3: DIRECTIVE RECORDED — Senthil 22:22: continue sprint work on EngageOS from v005 workbook; create sprint tracker + traceability; complete development with 100% automation testing (D13). EngageOS opened as an additional concurrent build while D15 mode (parallel vs re-order) remains unratified; this entry is the R7-style log of that state. | E3: D13,D15 | F3: EngageOS S1 opened from v005 backlog (100 stories / 399 pts) | G3: None | H3: S1 build
A4: E002 | B4: 2026-09-10 22:22 | C4: S1 | D4: S1 FOUNDATION BUILT (workbook v006 run, TypeScript/Node per v005 stack): install.ts — OAuth install w/ empty-code validation, uninstall webhook token purge + 30-day retention-scheduled deletion, re-install restore inside window / RETENTION_EXPIRED beyond, rotation-safe token refresh, listing/search/referral install attribution. | E4: ST-052,ST-055,ST-056 (+ST-051 logic) | F4: 3 S1 stories Done-in-code (8/13 pts); ST-051 Pending-live | G4: ST-051 <2 min dev-store install needs live Meta dev account | H4: E003
A5: E003 | B5: 2026-09-10 22:22 | C5: S2 | D5: F1 PART 1: inbox.ts — one-screen defaults (min-one-agent), happy path w/ keyword-rule + round-robin assignment, custom rules validated against agent list, reply retry via resilience.ts (exp backoff, clear error after exhaustion); roles.ts owner/admin/member matrix + AuditLog. | E5: ST-001..004,053,054 | F5: 6 S2 stories Done-in-code (29/29 pts) | G5: None | H5: E004
A6: E004 | B6: 2026-09-10 22:22 | C6: S3 | D6: F1 PART 2 + F2 START + QUALITY GATE: inbox metrics/pause-safe/CSV import/notifications (notify.ts per-type mute); broadcast.ts campaign create + segment rules + API error retry; ST-085 test-coverage story closed as SUPERSEDED by D13 100% gate (jest coverageThreshold 100x4). | E6: ST-006..014,085 | F6: 10 S3 stories Done-in-code (42/47 pts); ST-005 Pending-live | G6: None | H6: E005
A7: E005 | B7: 2026-09-10 22:22 | C7: S4 | D7: F2 COMPLETE + TELEMETRY + SMOKE: broadcast send w/ test-mode isolation, delivery/failed tracking, metrics, pause-safe, contact import validation; analyticsGuard funnel events (install->setup->aha->habit); telemetry.ts ErrorTracker release tags + window spike alert; tests/smoke.test.ts E2E MVP loop wired into CI on push/PR/deploy. | E7: ST-016..020,071,072,086 | F7: 8 S4 stories Done-in-code (29/34 pts); ST-015 Pending-live | G7: None | H7: E006
A8: E006 | B8: 2026-09-10 22:22 | C8: S5 | D8: F3 + ONBOARDING: chatbot.ts default welcome flow, run engine w/ branch answers, loop + broken-link + missing/invalid-answer detection, node edits, export/import round-trip; onboarding.ts first-run checklist w/ aha (connect+first-reply) <1 day check, EMPTY_STATES registry per screen. | E8: ST-021..024,026..030,078,079 | F8: 11 S5 stories Done-in-code (45/50 pts); ST-025 Pending-live | G8: None | H8: E007
A9: E007 | B9: 2026-09-10 22:22 | C9: S6 | D9: F4 + BILLING CORE: catalog.ts VPA-validated UPI deep links, item CRUD, CSV import, pause-safe, metrics; billing.ts 14-day no-card trial w/ days-remaining banner, mid-cycle proration w/ cycle-cap clamp, selectProvider(marketplace-mandate vs Stripe fallback). | E9: ST-031..034,036..040,057,058 | F9: 11 S6 stories Done-in-code (47/60 pts); ST-035,059 Pending-live | G9: ST-059 mandate check needs verified Meta terms (S0 item) | H9: E008
A10: E008 | B10: 2026-09-10 22:22 | C10: S7 | D10: BILLING HARDENING: dunning state machine (7-day grace, emails day 0/3/6, then read-only), plan-limit prompts at 80%/100%, GST/VAT invoices w/ rate validation, cancellation save-offer(20%) + exit-survey-required path; compliance.ts least-privilege SCOPE_MAP (3 scopes 1:1 features). | E10: ST-060..064 | F10: 5 S7 stories Done-in-code (15/15 pts) | G10: S7 beta-partner activities themselves external | H10: E009
A11: E009 | B11: 2026-09-10 22:22 | C11: S8 | D11: F5 + E6/E7 + QUALITY: analyticsGuard quality-score guard (green/amber/red w/ throttle action), configurable thresholds, health score, heatmap, CSV export; compliance retentionPolicy + verifySecurityConfig + DataRights export/delete; resilience CircuitBreaker; latency.ts p95 budgets api/ui/webhook; chaos degradation via FakeWaApi outage injection. | E11: ST-041..044,046..050,065,067,069,070,073..077,087,091 | F11: 18 S8 stories Done-in-code (69/87 pts); ST-045,066 Pending-live | G11: ST-088 load test + ST-092 deploy drill need live infra | H11: E010
A12: E010 | B12: 2026-09-10 22:22 | C12: Release | D12: WORKBOOK v006 RELEASED 22:22 — D13 GATE MET: 16 suites / 73 automated tests, 100% statements/branches/functions/lines on all 15 modules, gate enforced (jest coverageThreshold fails any commit below); tsc BUILD_OK; Sprint_Tracker_Log + Traceability_Matrix sheets added to product workbook; recalc 169 formulas zero errors. Position: 75 Done-in-code / 8 Pending-live / 17 Backlog (295/399 pts). | E12: D13 | F12: Code: engageos_v0.6.0_src.zip | G12: Live Meta dev account gates the 8 Pending-live | H12: E011
A13: E011 | B13: 2026-09-10 22:55 | C13: S9-S10 | D13: WHATSAPP COMPLIANCE CODE (v007 run): sessionWindow.ts 24-hour customer-service window + template fallback (hard TEMPLATE_REQUIRED error); webhookGuard.ts wamid dedupe + bounded burst queue tested at 50 msg/s shape w/ overflow accounting; optIn.ts consent proof storage + marketing-send gate; demoData.ts sandbox mode seeding inbox/campaign/flow/catalog (ST-083 code half). | E13: LC-5,LC-7,LC-8,ST-083 | F13: Launch checklist #5/#7/#8 Done-in-code, #4 templates Drafted | G13: Live 50/s burst + Meta template approval pending | H13: E012
... A102: E100 | B102: 2026-09-16 18:40 | C102: Release | D102: TRACKER v042 + WORKBOOK v047 RELEASED. Codebase v0.46.0; audit kit unchanged at v1.1.0. Clean-room replay of all 14 CI steps from the zip exits 0: npm ci, build, migrate ×2, test (62/512, 100%), smoke, rehearse (24 steps + dry sweep), evidence:pg (boot, restart, restore, outage), reachability, claims (58), findings (75), versions, deps (0 vulnerabilities / 413 packages), kit tests. Record corrected: Done-in-code is 312/399 points (matrix), not 309 as the 15 Sep index said. Story position UNCHANGED; ZERO Done. | E102: D13, R2, Review V001 | F102: Code: engageos_v0.46.0_src.zip | G102: Handover items 1-14 | H102: v043 on review V002, live evidence or ICP

Sheet Decisions
A1: DECISIONS (tracker scope)
A2: ID | B2: Decision | C2: Rationale | D2: Decided by | E2: Status
A3: D13 | B3: (Portfolio-wide) Discovery interviews parked; development proceeds with 100% automation test coverage on all code. Supersedes ST-085 >=70% gate. | C3: Senthil 10 Sep 20:45; applied to EngageOS per 22:22 continue directive. Enforced via jest coverageThreshold 100x4. | D3: Senthil | E3: LOCKED
A4: D15 | B4: EngageOS build opened 10 Sep 22:22 as one of multiple concurrent builds while the rank-1 completion gate (listed + 10 paying) is unmet. MODE TO RATIFY: (a) formal parallel builds, or (b) hold-serial with order decision. | C4: Logged per R7-class rule; consolidated across products in the 23:03 portfolio action board. | D4: Senthil (mode ratification pending) | E4: OPEN — pick (a) or (b)
A5: D-E1 | B5: Stack = TypeScript/Node per v005 ReadMe assumption; WhatsApp Cloud API behind WaApi adapter interface with FakeWaApi (failure injection) for sandbox; real HTTP client swaps in at live wiring. | C5: Sandbox has no Meta credentials; adapter isolation means live wiring is one module. Same accepted pattern as TeleField D16. | D5: Claude — flagged | E5: OPEN for ratification
A6: D-E2 | B6: Status taxonomy for this tracker: Done-in-code / Pending-live (WhatsApp) / Drafted / In progress / Backlog. Rollup counts Done-in-code + Done. | C6: R2-class honesty: code complete is not listed/live; drafts are not published. | D6: Claude — flagged | E6: OPEN for ratification
A7: D-E3 | B7: ST-085 recorded as Done-in-code with evidence "superseded by D13 100% gate" rather than deleted. | C7: Preserves backlog integrity + audit trail of the gate change. | D7: Claude | E7: APPLIED
A8: D-E5 | B8: pg is an OPTIONAL dependency (npm ci installs it; --omit=optional gives a memory-only deployment). Sessions minted before v0.46.0 are refused (no session id, so not individually revocable) — one re-login per agent at upgrade. | C8: Keeps the in-memory deployment driver-free as F-CG-005 intended while letting CI and evidence use the real driver; revocability is worth one re-login. | D8: Claude — flagged | E8: OPEN for ratification
A9: D-E6 | B9: Signup callback treats waba_id / phone_number_id as optional CLAIMS: checked against Meta when present, discovered from Meta when absent, refused (409) when Meta's answer is ambiguous. | C9: Removes the review's forged-callback path without making the browser integration a prerequisite for the first live test. | D9: Claude — flagged | E9: OPEN for ratification

Sheet V006_Build_Board
A1: V006 BUILD BOARD — S1-S8 development run (22:22) — 15 modules, 16 suites / 73 tests, 100%x4
A2: ID | B2: Item | C2: Story refs | D2: Sprint | E2: Owner | F2: Status | G2: Notes / Evidence
A3: B6-01 | B3: Repo scaffold + CI with 100% coverage gate (D13) | C3: — | D3: S1 | E3: Claude | F3: Done | G3: jest coverageThreshold 100x4; .github/workflows/ci.yml runs build+test+smoke on push/PR/deploy. E010.
A4: B6-02 | B4: E1 install lifecycle: OAuth install, uninstall token purge + retention deletion, re-install window, token rotation, attribution | C4: ST-051(logic),052,053,055,056 | D4: S1-S2 | E4: Claude | F4: Done | G4: install.ts + install.test.ts (8 tests incl. RETENTION_EXPIRED, duplicate-install, uninstalled-rotation-block).
A5: B6-03 | B5: Roles matrix + audit log | C5: ST-054,067 + F-perm stories | D5: S2,S8 | E5: Claude | F5: Done | G5: roles.ts 9-action owner/admin/member MATRIX; guard() FORBIDDEN + AuditLog entries.
A6: B6-04 | B6: F1 team inbox: defaults, rule+round-robin assignment, reply retry, bulk, pause-safe, CSV import, metrics, notifications | C6: ST-001..004,006..010 | D6: S2-S3 | E6: Claude | F6: Done | G6: inbox.ts + inbox.test.ts (8 tests); notify.ts per-type mute.
A7: B6-05 | B7: F2 broadcasts: segments, test mode, send retry + failure ledger, metrics, pause-safe, contact import | C7: ST-011..014,016..020 | D7: S3-S4 | E7: Claude | F7: Done | G7: broadcast.ts + broadcast.test.ts (6 tests incl. retry-exhaustion failure recording).
A8: B6-06 | B8: F3 chatbot flows: default flow, run engine, branch/loop/broken-link errors, export/import, metrics | C8: ST-021..024,026..030 | D8: S5 | E8: Claude | F8: Done | G8: chatbot.ts + chatbot.test.ts (5 tests).
A9: B6-07 | B9: F4 catalog + UPI links: VPA validation, CRUD, deep-link format, CSV import, pause-safe, metrics | C9: ST-031..034,036..040 | D9: S6 | E9: Claude | F9: Done | G9: catalog.ts + catalog.test.ts (6 tests); upi://pay deep link asserted byte-exact.
A10: B6-08 | B10: F5 analytics + quality guard: score->status->action, thresholds, funnel, health, heatmap, CSV export | C10: ST-041..044,046..050,071,073,075,076,077 | D10: S8 | E10: Claude | F10: Done | G10: analyticsGuard.ts + suite (5 tests); red status => throttle broadcasts action.
A11: B6-09 | B11: E5 billing: trial, proration+clamp, provider selection, dunning 0/3/6->read-only, limits 80/100, GST invoice, cancellation | C11: ST-057..063 | D11: S6-S7 | E11: Claude | F11: Done | G11: billing.ts + billing.test.ts (9 tests).
A12: B6-10 | B12: E6 compliance: SCOPE_MAP least privilege, retention policy, security-config verify, export/delete-my-data | C12: ST-064,065,066(code),069 | D12: S7-S8 | E12: Claude | F12: Done | G12: compliance.ts + suite (4 tests); docs/DATA_FLOW.md published in repo.
A13: B6-11 | B13: Resilience: exp backoff retry + circuit breaker; chaos degradation | C13: ST-070,091 + per-feature error stories | D13: S8 | E13: Claude | F13: Done | G13: resilience.ts + suite; FakeWaApi outage injection across inbox/broadcast suites.
... A17: B6-15 | B17: Live Meta dev-store install E2E (8 Pending-live stories) | C17: ST-005,015,025,035,045,051,059,066 | D17: S1-S8 | E17: Senthil + Claude | F17: To do | G17: Needs Meta Business verification + WABA production access; evidence: install proof + org id + telemetry row.

Sheet V007_Build_Board
A1: V007 BUILD BOARD — S9-S10 draftable run (22:55) — +4 modules, 20 suites / 78 tests, 100%x4
A2: ID | B2: Item | C2: Story/LC refs | D2: Owner | E2: Status | F2: Notes / Evidence
A3: B7-01 | B3: 24-hour session window + template fallback | C3: LC-7 | D3: Claude | E3: Done | F3: sessionWindow.ts — free-form in-window, template outside, TEMPLATE_REQUIRED_OUTSIDE_24H hard error.
A4: B7-02 | B4: Webhook dedupe + burst queue at 50 msg/s shape | C4: LC-8 | D4: Claude | E4: Done | F4: webhookGuard.ts — wamid dedupe, bounded queue, overflow counter, drain; stats asserted.
A5: B7-03 | B5: Opt-in proof capture + marketing-send gate | C5: LC-5 | D5: Claude | E5: Done | F5: optIn.ts — checkbox-text-required proof, revoke, utility-vs-marketing canSend.
A6: B7-04 | B6: Demo-data sandbox mode seeding all surfaces | C6: ST-083 (code half) | D6: Claude | E6: Done | F6: demoData.ts seeds 2 convos, campaign, flow, 2 catalog items; demoData.test.ts E2E.
A7: B7-05 | B7: Listing copy A/B variants | C7: ST-093 | D7: Claude | E7: Drafted | F7: docs/listing/LISTING_COPY_A_B.md — Senthil to pick; 30-day CVR test plan included.
A8: B7-06 | B8: Pricing matrix + FAQ | C8: ST-095 | D8: Claude | E8: Drafted | F8: docs/listing/PRICING_FAQ.md — 3 plans from billing.ts PLANS; Meta fees pass-through stated.
A9: B7-07 | B9: Security/trust page | C9: ST-096 | D9: Claude | E9: Drafted | F9: docs/listing/TRUST_SECURITY.md — from compliance.ts facts; subprocessor list owed at GA.
A10: B7-08 | B10: 2-min demo video script | C10: ST-083 (script half) | D10: Claude | E10: Drafted | F10: docs/listing/DEMO_VIDEO_SCRIPT.md — production pending.
A11: B7-09 | B11: Launch-day runbook | C11: ST-098 | D11: Claude | E11: Drafted | F11: docs/launch/RUNBOOK.md — T-1/T-0, rollback, comms tree, 48h success checks.
A12: B7-10 | B12: Incident comms + severity ladder | C12: ST-084 | D12: Claude | E12: Drafted | F12: docs/launch/INCIDENT_COMMS.md — status-page vendor setup pending.
A13: B7-11 | B13: 15 help-center articles | C13: ST-080 | D13: Claude | E13: Drafted | F13: docs/help/HELP_CENTER_ARTICLES.md — publish to help-desk vendor at S10.
... A19: B7-17 | B19: Submission dry-run vs Launch_Checklist | C19: ST-097 | D19: Claude + reviewer | E19: In progress | F19: Self dry-run done this session (checklist re-statused); second-reviewer pass pending.

Sheet Traceability_Matrix
A1: TRACEABILITY MATRIX — 100 stories: module -> epic -> story -> screen -> verification -> status (edit yellow)
A2: Source: product workbook v007 Full_Backlog (single source of truth, D12 pattern). Evidence rows carry the workbook version + timestamp that closed them (D13). Status per D-E2 taxonomy.
A3: Story ID | B3: Epic | C3: Module / feature | D3: Story | E3: Points | F3: Priority | G3: Sprint | H3: Primary screen | I3: Verification | J3: Status | K3: Evidence
A4: ST-001 | B4: F1 | C4: Team inbox + assignment | D4: As a SME owner, I can set up Team inbox + assignment with sensible defaults in one screen | E4: 5 | F4: P0 | G4: S2 | H4: SCR-3 Inbox workspace | I4: inbox.test.ts | J4: Done-in-code | K4: DONE-IN-CODE v006 22:22 — inbox.ts; tests: inbox.test.ts. Team inbox + assignment: one-screen setup with validated defaults
A5: ST-002 | B5: F1 | C5: Team inbox + assignment | D5: As a SME owner, the Team inbox + assignment happy path completes without documentation | E5: 8 | F5: P0 | G5: S2 | H5: SCR-3 Inbox workspace | I5: inbox.test.ts | J5: Done-in-code | K5: DONE-IN-CODE v006 22:22 — inbox.ts; tests: inbox.test.ts. Happy path covered end-to-end on fake platform surface
A6: ST-003 | B6: F1 | C6: Team inbox + assignment | D6: As a Marketing person, I can customise Team inbox + assignment rules/conditions for my workflow | E6: 5 | F6: P1 | G6: S2 | H6: SCR-3 Inbox workspace | I6: inbox.test.ts | J6: Done-in-code | K6: DONE-IN-CODE v006 22:22 — inbox.ts; tests: inbox.test.ts. Rules/conditions customisation with validation errors
A7: ST-004 | B7: F1 | C7: Team inbox + assignment | D7: As a user, Team inbox + assignment shows clear errors and retry paths on platform API failures | E7: 3 | F7: P0 | G7: S2 | H7: SCR-3 Inbox workspace | I7: inbox.test.ts + resilience.test.ts | J7: Done-in-code | K7: DONE-IN-CODE v006 22:22 — inbox.ts + resilience.ts; tests: inbox.test.ts + resilience.test.ts. Retry w/ backoff; clear error after exhausting attempts
A8: ST-005 | B8: F1 | C8: Team inbox + assignment | D8: As a Support agent, Team inbox + assignment works on the web app + WhatsApp Cloud API surface end-to-end | E8: 5 | F8: P0 | G8: S3 | H8: SCR-3 Inbox workspace | I8: inbox.test.ts + live E2E | J8: Pending-live | K8: Logic done v006 22:22 in inbox.ts (inbox.test.ts); live WhatsApp/Meta E2E outstanding. Logic Done vs FakeWaApi; live Cloud API E2E outstanding
A9: ST-006 | B9: F1 | C9: Team inbox + assignment | D9: As a Marketing person, I can see Team inbox + assignment performance metrics and trends | E9: 3 | F9: P1 | G9: S3 | H9: SCR-3 Inbox workspace | I9: inbox.test.ts | J9: Done-in-code | K9: DONE-IN-CODE v006 22:22 — inbox.ts; tests: inbox.test.ts. Metrics/trends computed and asserted
A10: ST-007 | B10: F1 | C10: Team inbox + assignment | D10: As a user, Team inbox + assignment respects role permissions and audit logging | E10: 3 | F10: P1 | G10: S3 | H10: SCR-3 Inbox workspace | I10: roles.test.ts | J10: Done-in-code | K10: DONE-IN-CODE v006 22:22 — inbox.ts + roles.ts; tests: roles.test.ts. owner/admin/member matrix + AuditLog entries
A11: ST-008 | B11: F1 | C11: Team inbox + assignment | D11: As a SME owner, I can pause/disable Team inbox + assignment without data loss | E11: 2 | F11: P2 | G11: S3 | H11: SCR-3 Inbox workspace | I11: inbox.test.ts | J11: Done-in-code | K11: DONE-IN-CODE v006 22:22 — inbox.ts; tests: inbox.test.ts. Pause blocks activity; data retained (asserted)
A12: ST-009 | B12: F1 | C12: Team inbox + assignment | D12: As a Marketing person, I can import/migrate existing data into Team inbox + assignment (CSV + competitor importer) | E12: 5 | F12: P1 | G12: S3 | H12: SCR-3 Inbox workspace | I12: inbox.test.ts | J12: Done-in-code | K12: DONE-IN-CODE v033 17:24 — chat CSV import reachable (POST /api/inbox/import); library-only until now
A13: ST-010 | B13: F1 | C13: Team inbox + assignment | D13: As a user, I get notifications (in-app + email) for key Team inbox + assignment events with per-type mute | E13: 3 | F13: P2 | G13: S3 | H13: SCR-3 Inbox workspace | I13: notify.test.ts | J13: Done-in-code | K13: DONE-IN-CODE v006 22:22 — inbox.ts + notify.ts; tests: notify.test.ts. In-app + email with per-type mute
A14: ST-011 | B14: F2 | C14: Broadcast campaigns + segments | D14: As a SME owner, I can set up Broadcast campaigns + segments with sensible defaults in one screen | E14: 5 | F14: P0 | G14: S3 | H14: SCR-4 Broadcast builder | I14: broadcast.test.ts | J14: Done-in-code | K14: DONE-IN-CODE v006 22:22 — broadcast.ts; tests: broadcast.test.ts. Broadcast campaigns + segments: one-screen setup with validated defaults
A15: ST-012 | B15: F2 | C15: Broadcast campaigns + segments | D15: As a SME owner, the Broadcast campaigns + segments happy path completes without documentation | E15: 8 | F15: P0 | G15: S3 | H15: SCR-4 Broadcast builder | I15: broadcast.test.ts | J15: Done-in-code | K15: DONE-IN-CODE v006 22:22 — broadcast.ts; tests: broadcast.test.ts. Happy path covered end-to-end on fake platform surface
... A103: ST-100 | B103: EL | C103: partners.ts | D103: First 10 design-partner reviews scheduled | E103: 2 | F103: P1 | G103: S11 | H103: Marketplace listing (external) | I103: completion.test.ts + outreach | J103: Pending-live | K103: CODE-COMPLETE v039 19:40 — /admin/partners reachable with honest gate maths; outreach his

Sheet Sprint_Status_Rollup
A1: SPRINT STATUS ROLLUP — live formulas over Traceability_Matrix
A2: Do not edit computed cells. 'Done' counts Done-in-code + Done. Exit criteria from product workbook Sprint_Board.
A3: Sprint | B3: Focus | C3: Stories | D3: Points | E3: Done | F3: Done points | G3: % points done | H3: RAG (manual) | I3: Exit criteria
A4: S1 | B4: Foundation (2 wks) | C4: =COUNTIF(Traceability_Matrix!$G$4:$G$103,"S1") -> 4 | D4: =SUMIF(Traceability_Matrix!$G$4:$G$103,"S1",Traceability_Matrix!$E$4:$E$103) -> 13 | E4: =COUNTIFS(Traceability_Matrix!$G$4:$G$103,"S1",Traceability_Matrix!$J$4:$J$103,"Done-in-code")+COUNTIFS(Traceability_Matrix!$G$4:$G$103,"S1",Traceability_Matrix!$J$4:$J$103,"Done") -> 3 | F4: =SUMIFS(Traceability_Matrix!$E$4:$E$103,Traceability_Matrix!$G$4:$G$103,"S1",Traceability_Matrix!$J$4:$J$103,"Done-in-code")+SUMIFS(Traceability_Matrix!$E$4:$E$103,Traceability_Matrix!$G$4:$G$103,"S1",Traceability_Matrix!$J$4:$J$103,"Done") -> 8 | G4: =IFERROR(F4/D4,0) -> 0.61538462 | H4: AMBER — 3/4 done-in-code; live install is the exit criterion and pending Meta access | I4: App installs cleanly in dev store/org; telemetry firing
A5: S2 | B5: Team inbox pt 1 | C5: =COUNTIF(Traceability_Matrix!$G$4:$G$103,"S2") -> 6 | D5: =SUMIF(Traceability_Matrix!$G$4:$G$103,"S2",Traceability_Matrix!$E$4:$E$103) -> 29 | E5: =COUNTIFS(Traceability_Matrix!$G$4:$G$103,"S2",Traceability_Matrix!$J$4:$J$103,"Done-in-code")+COUNTIFS(Traceability_Matrix!$G$4:$G$103,"S2",Traceability_Matrix!$J$4:$J$103,"Done") -> 6 | F5: =SUMIFS(Traceability_Matrix!$E$4:$E$103,Traceability_Matrix!$G$4:$G$103,"S2",Traceability_Matrix!$J$4:$J$103,"Done-in-code")+SUMIFS(Traceability_Matrix!$E$4:$E$103,Traceability_Matrix!$G$4:$G$103,"S2",Traceability_Matrix!$J$4:$J$103,"Done") -> 29 | G5: =IFERROR(F5/D5,0) -> 1 | H5: GREEN — 6/6 done-in-code | I5: Inbox happy path demoable
A6: S3 | B6: Inbox pt 2 + Broadcasts start | C6: =COUNTIF(Traceability_Matrix!$G$4:$G$103,"S3") -> 11 | D6: =SUMIF(Traceability_Matrix!$G$4:$G$103,"S3",Traceability_Matrix!$E$4:$E$103) -> 47 | E6: =COUNTIFS(Traceability_Matrix!$G$4:$G$103,"S3",Traceability_Matrix!$J$4:$J$103,"Done-in-code")+COUNTIFS(Traceability_Matrix!$G$4:$G$103,"S3",Traceability_Matrix!$J$4:$J$103,"Done") -> 10 | F6: =SUMIFS(Traceability_Matrix!$E$4:$E$103,Traceability_Matrix!$G$4:$G$103,"S3",Traceability_Matrix!$J$4:$J$103,"Done-in-code")+SUMIFS(Traceability_Matrix!$E$4:$E$103,Traceability_Matrix!$G$4:$G$103,"S3",Traceability_Matrix!$J$4:$J$103,"Done") -> 42 | G6: =IFERROR(F6/D6,0) -> 0.89361702 | H6: GREEN — 10/11; ST-005 pending-live | I6: Inbox complete with tests; Broadcasts skeleton
A7: S4 | B7: Broadcast campaigns + segments | C7: =COUNTIF(Traceability_Matrix!$G$4:$G$103,"S4") -> 9 | D7: =SUMIF(Traceability_Matrix!$G$4:$G$103,"S4",Traceability_Matrix!$E$4:$E$103) -> 34 | E7: =COUNTIFS(Traceability_Matrix!$G$4:$G$103,"S4",Traceability_Matrix!$J$4:$J$103,"Done-in-code")+COUNTIFS(Traceability_Matrix!$G$4:$G$103,"S4",Traceability_Matrix!$J$4:$J$103,"Done") -> 8 | F7: =SUMIFS(Traceability_Matrix!$E$4:$E$103,Traceability_Matrix!$G$4:$G$103,"S4",Traceability_Matrix!$J$4:$J$103,"Done-in-code")+SUMIFS(Traceability_Matrix!$E$4:$E$103,Traceability_Matrix!$G$4:$G$103,"S4",Traceability_Matrix!$J$4:$J$103,"Done") -> 29 | G7: =IFERROR(F7/D7,0) -> 0.85294118 | H7: GREEN — 8/9; ST-015 pending-live | I7: MVP loop usable end-to-end internally
A8: S5 | B8: Chatbot flows + alpha hardening | C8: =COUNTIF(Traceability_Matrix!$G$4:$G$103,"S5") -> 12 | D8: =SUMIF(Traceability_Matrix!$G$4:$G$103,"S5",Traceability_Matrix!$E$4:$E$103) -> 50 | E8: =COUNTIFS(Traceability_Matrix!$G$4:$G$103,"S5",Traceability_Matrix!$J$4:$J$103,"Done-in-code")+COUNTIFS(Traceability_Matrix!$G$4:$G$103,"S5",Traceability_Matrix!$J$4:$J$103,"Done") -> 11 | F8: =SUMIFS(Traceability_Matrix!$E$4:$E$103,Traceability_Matrix!$G$4:$G$103,"S5",Traceability_Matrix!$J$4:$J$103,"Done-in-code")+SUMIFS(Traceability_Matrix!$E$4:$E$103,Traceability_Matrix!$G$4:$G$103,"S5",Traceability_Matrix!$J$4:$J$103,"Done") -> 45 | G8: =IFERROR(F8/D8,0) -> 0.9 | H8: GREEN — 11/12; ST-025 pending-live; alpha-dogfood exit needs live org | I8: Internal alpha: team dogfoods daily
A9: S6 | B9: Billing + Catalog/payment links | C9: =COUNTIF(Traceability_Matrix!$G$4:$G$103,"S6") -> 13 | D9: =SUMIF(Traceability_Matrix!$G$4:$G$103,"S6",Traceability_Matrix!$E$4:$E$103) -> 60 | E9: =COUNTIFS(Traceability_Matrix!$G$4:$G$103,"S6",Traceability_Matrix!$J$4:$J$103,"Done-in-code")+COUNTIFS(Traceability_Matrix!$G$4:$G$103,"S6",Traceability_Matrix!$J$4:$J$103,"Done") -> 11 | F9: =SUMIFS(Traceability_Matrix!$E$4:$E$103,Traceability_Matrix!$G$4:$G$103,"S6",Traceability_Matrix!$J$4:$J$103,"Done-in-code")+SUMIFS(Traceability_Matrix!$E$4:$E$103,Traceability_Matrix!$G$4:$G$103,"S6",Traceability_Matrix!$J$4:$J$103,"Done") -> 47 | G9: =IFERROR(F9/D9,0) -> 0.78333333 | H9: AMBER — 11/13; billing-mandate check (ST-059) needs verified Meta terms | I9: Can charge a test customer; up/downgrade paths work
A10: S7 | B10: Private beta (design partners) | C10: =COUNTIF(Traceability_Matrix!$G$4:$G$103,"S7") -> 5 | D10: =SUMIF(Traceability_Matrix!$G$4:$G$103,"S7",Traceability_Matrix!$E$4:$E$103) -> 15 | E10: =COUNTIFS(Traceability_Matrix!$G$4:$G$103,"S7",Traceability_Matrix!$J$4:$J$103,"Done-in-code")+COUNTIFS(Traceability_Matrix!$G$4:$G$103,"S7",Traceability_Matrix!$J$4:$J$103,"Done") -> 5 | F10: =SUMIFS(Traceability_Matrix!$E$4:$E$103,Traceability_Matrix!$G$4:$G$103,"S7",Traceability_Matrix!$J$4:$J$103,"Done-in-code")+SUMIFS(Traceability_Matrix!$E$4:$E$103,Traceability_Matrix!$G$4:$G$103,"S7",Traceability_Matrix!$J$4:$J$103,"Done") -> 15 | G10: =IFERROR(F10/D10,0) -> 1 | H10: AMBER — code done; beta partners themselves external | I10: 3+ partners active weekly; NPS pulse >30
A11: S8 | B11: Beta iteration + Analytics/guard | C11: =COUNTIF(Traceability_Matrix!$G$4:$G$103,"S8") -> 22 | D11: =SUMIF(Traceability_Matrix!$G$4:$G$103,"S8",Traceability_Matrix!$E$4:$E$103) -> 87 | E11: =COUNTIFS(Traceability_Matrix!$G$4:$G$103,"S8",Traceability_Matrix!$J$4:$J$103,"Done-in-code")+COUNTIFS(Traceability_Matrix!$G$4:$G$103,"S8",Traceability_Matrix!$J$4:$J$103,"Done") -> 18 | F11: =SUMIFS(Traceability_Matrix!$E$4:$E$103,Traceability_Matrix!$G$4:$G$103,"S8",Traceability_Matrix!$J$4:$J$103,"Done-in-code")+SUMIFS(Traceability_Matrix!$E$4:$E$103,Traceability_Matrix!$G$4:$G$103,"S8",Traceability_Matrix!$J$4:$J$103,"Done") -> 69 | G11: =IFERROR(F11/D11,0) -> 0.79310345 | H11: AMBER — 18/22; load test + deploy drill need live infra | I11: Beta cohort WoW retention >60%
A12: S9 | B12: Marketplace review prep | C12: =COUNTIF(Traceability_Matrix!$G$4:$G$103,"S9") -> 7 | D12: =SUMIF(Traceability_Matrix!$G$4:$G$103,"S9",Traceability_Matrix!$E$4:$E$103) -> 30 | E12: =COUNTIFS(Traceability_Matrix!$G$4:$G$103,"S9",Traceability_Matrix!$J$4:$J$103,"Done-in-code")+COUNTIFS(Traceability_Matrix!$G$4:$G$103,"S9",Traceability_Matrix!$J$4:$J$103,"Done") -> 3 | F12: =SUMIFS(Traceability_Matrix!$E$4:$E$103,Traceability_Matrix!$G$4:$G$103,"S9",Traceability_Matrix!$J$4:$J$103,"Done-in-code")+SUMIFS(Traceability_Matrix!$E$4:$E$103,Traceability_Matrix!$G$4:$G$103,"S9",Traceability_Matrix!$J$4:$J$103,"Done") -> 11 | G12: =IFERROR(F12/D12,0) -> 0.36666667 | H12: AMBER — drafts done; pen-test + screenshots external | I12: Review submission accepted into queue
A13: S10 | B13: Review remediation + docs | C13: =COUNTIF(Traceability_Matrix!$G$4:$G$103,"S10") -> 7 | D13: =SUMIF(Traceability_Matrix!$G$4:$G$103,"S10",Traceability_Matrix!$E$4:$E$103) -> 24 | E13: =COUNTIFS(Traceability_Matrix!$G$4:$G$103,"S10",Traceability_Matrix!$J$4:$J$103,"Done-in-code")+COUNTIFS(Traceability_Matrix!$G$4:$G$103,"S10",Traceability_Matrix!$J$4:$J$103,"Done") -> 4 | F13: =SUMIFS(Traceability_Matrix!$E$4:$E$103,Traceability_Matrix!$G$4:$G$103,"S10",Traceability_Matrix!$J$4:$J$103,"Done-in-code")+SUMIFS(Traceability_Matrix!$E$4:$E$103,Traceability_Matrix!$G$4:$G$103,"S10",Traceability_Matrix!$J$4:$J$103,"Done") -> 14 | G13: =IFERROR(F13/D13,0) -> 0.58333333 | H13: AMBER — content drafted; approval cycle external | I13: Marketplace approval obtained
A14: S11 | B14: Launch | C14: =COUNTIF(Traceability_Matrix!$G$4:$G$103,"S11") -> 3 | D14: =SUMIF(Traceability_Matrix!$G$4:$G$103,"S11",Traceability_Matrix!$E$4:$E$103) -> 8 | E14: =COUNTIFS(Traceability_Matrix!$G$4:$G$103,"S11",Traceability_Matrix!$J$4:$J$103,"Done-in-code")+COUNTIFS(Traceability_Matrix!$G$4:$G$103,"S11",Traceability_Matrix!$J$4:$J$103,"Done") -> 1 | F14: =SUMIFS(Traceability_Matrix!$E$4:$E$103,Traceability_Matrix!$G$4:$G$103,"S11",Traceability_Matrix!$J$4:$J$103,"Done-in-code")+SUMIFS(Traceability_Matrix!$E$4:$E$103,Traceability_Matrix!$G$4:$G$103,"S11",Traceability_Matrix!$J$4:$J$103,"Done") -> 3 | G14: =IFERROR(F14/D14,0) -> 0.375 | H14: RED — launch gated on everything above | I14: First 10 installs; first 3 reviews; activation >40%
A15: S12 | B15: Iterate & scale decision | C15: =COUNTIF(Traceability_Matrix!$G$4:$G$103,"S12") -> 1 | D15: =SUMIF(Traceability_Matrix!$G$4:$G$103,"S12",Traceability_Matrix!$E$4:$E$103) -> 2 | E15: =COUNTIFS(Traceability_Matrix!$G$4:$G$103,"S12",Traceability_Matrix!$J$4:$J$103,"Done-in-code")+COUNTIFS(Traceability_Matrix!$G$4:$G$103,"S12",Traceability_Matrix!$J$4:$J$103,"Done") -> 0 | F15: =SUMIFS(Traceability_Matrix!$E$4:$E$103,Traceability_Matrix!$G$4:$G$103,"S12",Traceability_Matrix!$J$4:$J$103,"Done-in-code")+SUMIFS(Traceability_Matrix!$E$4:$E$103,Traceability_Matrix!$G$4:$G$103,"S12",Traceability_Matrix!$J$4:$J$103,"Done") -> 0 | G15: =IFERROR(F15/D15,0) -> 0 | H15: RED — post-launch only | I15: Growth model doc with CAC/LTV first estimates
A16: TOTAL | B16: (S1-S12) | C16: =SUM(C4:C15) -> 100 | D16: =SUM(D4:D15) -> 399 | E16: =SUM(E4:E15) -> 80 | F16: =SUM(F4:F15) -> 312 | G16: =IFERROR(F16/D16,0) -> 0.78195489

Sheet RAID_Carryover
A1: RAID — seeded from product workbook Risk_Register + build findings
A2: ID | B2: Type | C2: Raised | D2: Item | E2: Status | F2: Notes / Mitigation
A3: R-E1 | B3: Risk | C3: v005 | D3: WhatsApp quality-rating drop throttles number (High/Medium) | E3: Mitigated-in-code | F3: Quality-guard live: red status => throttle-broadcasts action (analyticsGuard.ts); opt-in hygiene enforced (optIn.ts marketing gate). Live rating monitoring still owed (LC-3).
A4: R-E2 | B4: Risk | C4: v005 | D4: Meta pricing change squeezes campaign ROI for SMEs (Medium/Medium) | E4: Open | F4: Conversation fees pass-through at cost (pricing page states it); multi-channel fallback (SMS/email) stays roadmap.
A5: R-E3 | B5: Risk | C5: v005 | D5: BSP dependency terms/latency (Medium/Medium) | E5: Open | F5: Cloud API direct path is the built assumption; dual-BSP abstraction possible behind WaApi adapter (one-module swap).
A6: R-E4 | B6: Constraint | C6: 22:22 | D6: Sandbox has no Meta credentials/Postgres — platform behind WaApi adapter w/ FakeWaApi; persistence in-memory | E6: Partly retired | F6: D-E1: real HTTP client + Postgres at live wiring; domain code untouched. v042: a local PostgreSQL 16.13 is now used for integration evidence and CI runs a postgres:16 service, so the Postgres half of this constraint is retired for testing. No Meta credentials remain the binding constraint.
A7: R-E5 | B7: Risk | C7: 22:55 | D7: Webhook payload/signature format assumed generic (wamid dedupe) pending Cloud API docs verification at live wiring | E7: Open | F7: Verification isolated in webhookGuard.ts + adapter; format change is one-module.
A8: R-E6 | B8: Risk | C8: 22:55 | D8: Meta may mandate specific billing rails for WABA-linked SaaS (ST-059 fallback logic built both ways) | E8: Open | F8: selectProvider() covers both; verify terms during LC-1 (was an S0 item, S0 parked under D13).
A9: A-E1 | B9: Assumption | C9: 22:22 | D9: D13 applies to EngageOS: discovery parked, 100% coverage; S0 activities (PRD sign-off, terms verify, wireframes) remain owed and NOT marked done | E9: Open | F9: Per 20:45/22:22 directives.
A10: A-E2 | B10: Assumption | C10: 22:22 | D10: D15 mode pending — EngageOS one of multiple concurrent builds; serial rule formally intact until ratified | E10: Open | F10: Senthil to ratify; consolidated in 23:03 portfolio action board.
A11: R-E13 | B11: Risk | C11: v042 | D11: Rate limits are per instance: N instances admit N times the configured rate; the webhook is limited only by signature and body size | E11: Open | F11: Accepted for now: a shared limiter needs the durable store on the hot path. Revisit at S16 capacity certification or before horizontal scale-out.
A12: R-E14 | B12: Risk | C12: v042 | D12: Embedded Signup verified only against a documented-shape double; Meta's live responses (granular_scopes, phone_numbers paging, subscribed_apps) may differ | E12: Open | F12: The first live signup (handover 1, 11) is the test; every refusal is a named code so a mismatch is diagnosable from one response.

Sheet Gate_Checklist
A1: COMPLETION GATE (D7) — EngageOS is DONE only when every row is Done
A2: R2: code complete counts for nothing. Gate decision = Senthil. LC items = product workbook Launch_Checklist (v007 statuses).
A3: ID | B3: Gate item | C3: Source | D3: Status
A4: G-01 | B4: App LISTED on WhatsApp/Meta ecosystem (approved + published) | C4: D7 / R2 | D4: Open
A5: G-02 | B5: 10 PAYING installs from strangers | C5: D7 / R2 | D5: Open
A6: G-03 | B6: S12 kill criteria evaluated with evidence pack | C6: D7 / R3 | D6: Open
A7: G-04 | B7: Kill/continue decision recorded by Senthil | C7: R5 / D10 | D7: Open
A8: G-05 | B8: On CONTINUE: next-rank build authorised; EngageOS enters ops floor | C8: N4 / R1 | D8: Open
A9: LC-1 | B9: Meta Business verification + WhatsApp Business Account (WABA) production access | C9: workbook LC #1 | D9: Open
A10: LC-2 | B10: BSP agreement signed (360dialog/Gupshup class) OR Cloud API direct path chosen | C10: workbook LC #2 | D10: Open
A11: LC-3 | B11: Display name approved; phone number quality rating monitoring in place | C11: workbook LC #3 | D11: Open
A12: LC-4 | B12: Message template library (20+ approved across utility/marketing categories) | C12: workbook LC #4 | D12: Drafted — 20 templates in docs/templates/MESSAGE_TEMPLATES.md; Meta approval pending
A13: LC-5 | B13: Opt-in capture flows compliant (checkbox + proof storage) | C13: workbook LC #5 | D13: Done in code — OptInRegistry proof storage + marketing gate; live flow QA pending
A14: LC-6 | B14: Conversation-pricing pass-through billing tested (Meta invoice reconciliation) | C14: workbook LC #6 | D14: Open
... A30: CG-G11 | B30: Documentation truth: every external promise linked to executable or live evidence | C30: Review V001 | D30: PARTIAL — claims gate covers 58 documented promises (was 49); live-evidence half open. PG_EVIDENCE_TRANSCRIPT is the first live-system evidence in the record.

Sheet CG_Sprint_Plan
A1: HARDENING PROGRAMME FROM EXTERNAL REVIEW V001 — S00-S19
A2: This is a SEPARATE programme from the S1-S12 MVP backlog, not a re-scoping of it. The 100 stories / 399 points in the product workbook remain the baseline; these nineteen sprints are what the review says must happen before "production-ready" may be said aloud. Order is the reviewer's; Status is ours.
F3: Status (16 Sep 2026)
A4: Sprint | B4: Theme | C4: Priority | D4: Duration | E4: Exit / acceptance evidence | F4: Status (14 Sep 2026)
A5: S00 | B5: Release truth & build reproducibility | C5: P0 | D5: 1 week | E5: Manifest version == package == lock == docs == artifact; clean checkout passes; artifact SHA-256 recorded | F5: DONE v0.46.0 — SBOM (audit/SBOM.cdx.json, deterministic, staleness-tested) and dependency policy (docs/DEPENDENCY_POLICY.md, npm run audit:deps in CI) added to v0.44.0's release identity. Clean checkout passes all 14 CI steps.
A6: S01 | B6: Real Meta embedded signup & tenant connection | C6: P0 | D6: 2 weeks | E6: Two independent test WABAs install and send from their own numbers; forged callback ids fail; uninstall/reinstall proven | F6: PART DONE v0.46.0 — tenant-connection half (v0.45.0) plus the code half of the Meta leg: code exchange, debug_token, WABA/number discovery, forged-id refusal, webhook subscription. Exit criterion (two real WABAs install and send) still needs handover items 1 and 11.
A7: S02 | B7: Durable multi-tenant data plane | C7: P0 | D7: 3 weeks | E7: Restart and multi-instance tests preserve state; cross-tenant access tests fail; migrations up/down verified | F7: STARTED v0.46.0 — tenant connections durable with a restart test and a cross-tenant test against real Postgres; migrations now recorded and re-runnable (F-050). Down-migrations not written. All other stores still memory.
A8: S03 | B8: Production Postgres + queue/runtime wiring | C8: P0 | D8: 2 weeks | E8: SHARED_STORE=pg boots in the shipped app; 2+ instances process a webhook retry once; queue survives restart | F8: PART DONE v0.46.0 — SHARED_STORE=pg boots the shipped server against real Postgres; restart and outage behaviour evidenced; two pools claim a wamid exactly once. Queue survival across restart not yet built (outbound queue is memory).
A9: S04 | B9: Identity, RBAC and enterprise access | C9: P0 | D9: 2 weeks | E9: Route/action matrix at 100%; member cannot send a campaign or administer billing; revoked session fails immediately | F9: PART DONE v0.46.0 — route/action conformance (v0.44.0) plus immediate session revocation, single and per agent, across instances. Identity provider, MFA, SCIM not started.
A10: S05 | B10: Billing, entitlements & metering | C10: P0 | D10: 2 weeks | E10: Cancelled tenant cannot mutate or send; duplicate provider webhook harmless; invoice and meter reconcile | F10: PART DONE v0.44.0 — entitlement enforcement shipped; provider integration not started
A11: S06 | B11: Live WhatsApp conformance | C11: P0 | D11: 2 weeks + Meta lead time | E11: Every Pending-live story carries timestamped live evidence; no undocumented platform assumptions remain | F11: Blocked — Meta access
A12: S07 | B12: Security edge hardening | C12: P0 | D12: 2 weeks | E12: OWASP/API security tests pass; no internal error detail; abuse tests stay within resource budgets | F12: DONE IN CODE v0.46.0 — body limits, headers, sanitised errors (v0.44.0); rate limiting, schema validation, SSRF allowlist, CSRF by construction (v0.46.0). OWASP-style external test is S17.
A13: S08 | B13: Privacy, GDPR/DPDP & data lifecycle | C13: P0 | D13: 2 weeks | E13: Delete and export work across every durable table and blob; retention job evidence; privacy docs match runtime | F13: Not started — depends on S02
A14: S09 | B14: Real tenant web product & UX | C14: P1 | D14: 3 weeks | E14: A new external user installs and reaches first value without an operator token or engineer help | F14: Not started
A15: S10 | B15: SRE, observability & incident operations | C15: P1 | D15: 2 weeks | E15: p95/error/SLO dashboards live; alert drill and incident simulation completed; correlation ids end to end | F15: Seeded v0.44.0 — correlation ids exist; nothing else
... A24: S19 | B24: Launch gate | C24: P0 | D24: 1 week | E24: Only now may "production-ready" be claimed. "Enterprise-grade" only after the enterprise-control and pen-test gates. | F24: Not started

Sheet Review_Findings
A1: REVIEW FINDINGS — adversarial cold-review pass 1 (11 Sep 08:17). Dispositions = Senthil (R5-class). | Updated v042 (16 Sep 2026): phase-3 dispositions and F-050..F-054.
A2: ID | B2: Severity | C2: Finding | D2: Evidence | E2: Disposition | F2: Status
A3: F-001 | B3: Major | C3: inbox.receive() before setupDefaults() assigned conversations to undefined (NaN round-robin index) and notified nobody | D3: src/inbox.ts pre-fix; repro test now in inbox.test.ts | E3: FIXED — INBOX_NOT_CONFIGURED thrown; regression test added | F3: Closed (fixed v0.9.0)
A4: F-002 | B4: Major | C4: Chatbot question node with options stripped via updateNode crashed with raw TypeError instead of a clean builder error | D4: src/chatbot.ts pre-fix; repro test in chatbot.test.ts | E4: FIXED — INVALID_NODE_NO_OPTIONS:<id>; regression test added | F4: Closed (fixed v0.9.0)
A5: F-003 | B5: Major | C5: WebhookGuard dedupe ledger grew unbounded — memory leak certainty in a long-running live process | D5: src/webhookGuard.ts pre-fix | E5: FIXED — FIFO cap at 20x queue size; eviction + recent-dedupe both asserted | F5: Closed (fixed v0.9.0)
A6: F-004 | B6: Minor | C6: CloudApiAdapter hardcoded template language "en" — the 8 marketing + hi/ta templates would have been unusable at live | D6: src/cloudApiAdapter.ts pre-fix | E6: FIXED — templateLang parameter, default en; hi asserted | F6: Closed (fixed v0.9.0)
A7: F-005 | B7: Minor | C7: Duplicate install() while an account is ACTIVE silently replaces token + attribution source (session-fixation-adjacent; also skews ST-056 attribution) | D7: src/install.ts install() overwrite branch (covered by test "duplicate install while active overwrites cleanly") | E7: LOG — acceptable for sandbox; at live wiring require explicit re-auth confirmation or preserve original source. Senthil to ratify | F7: Open
A8: F-006 | B8: Obs | C8: catalog paymentLink hardcodes payee name pn=EngageOS — merchants will want their own trading name on the UPI sheet | D8: src/catalog.ts | E8: LOG — add merchantName to CatalogService config at live wiring | F8: Open
A9: F-007 | B9: Obs | C9: billing.dunningTick emails depend on tick cadence: if no tick runs between day 3-6, only 2 of 3 emails ever send (grace/read-only unaffected) | D9: billing.test.ts dunning sequence | E9: LOG — live scheduler must tick daily; acceptable as designed | F9: Open
A10: F-008 | B10: Obs | C10: liveSweep step 1 (config valid) is trivially true after loadConfig succeeds — it evidences wiring, not validation | D10: src/liveSweep.ts | E10: LOG — keep: step exists to print phoneNumberId into the evidence record | F10: Open
A11: F-009 | B11: Blocker | C11: optIn.ts existed since v007 but NO send path ever called it — marketing broadcasts could reach contacts with no consent proof (platform violation + the exact risk the module was built to stop) | D11: src/broadcast.ts pre-fix; new regression asserts skipped[] with NO_OPT_IN | E11: FIXED — OptInRegistry is now a required BroadcastService collaborator; campaigns carry a category; non-consented targets recorded as skipped, never silently sent | F11: Closed (fixed v0.11.0)
A12: F-010 | B12: Blocker | C12: sessionWindow.ts likewise never wired — free-form sends outside the 24-hour window would have been rejected by Meta in production; inbox replies had the same hole | D12: src/broadcast.ts + src/inbox.ts pre-fix | E12: FIXED — inbound recorded on receive; reply/send consult the window and use an approved template outside it; out-of-window targets with no template recorded as NO_SESSION_WINDOW rather than aborting the campaign | F12: Closed (fixed v0.11.0)
A13: F-011 | B13: Major | C13: read-only and cancelled billing states were set but enforced nowhere — a non-paying account kept full write access | D13: src/billing.ts pre-fix | E13: FIXED — writeBlocked/assertWritable gate; reads stay open so customers can always export | F13: Closed (fixed v0.11.0)
... A129: F-054 | B129: Major | C129: THE SMOKE GATE COULD NEVER PASS. npm run smoke runs one suite under jest.config's global 100% coverage threshold, so it exited 1 on every run since D13. The CI job has therefore never completed green, while the record described its gates as green. | D129: Clean-room replay: smoke exit=1 with 'Coverage for statements (37.94%) does not meet global threshold' | E129: FIXED v0.46.0 — smoke runs with --coverage=false (the full suite carries the gate). All 14 CI steps now exit 0 from a clean unzip. | F129: Closed (fixed v0.46.0)

Sheet Senthil_Handover
A1: SENTHIL HANDOVER — every remaining EngageOS item, ordered by leverage (16 Sep 2026, 18:40)
A2: Nothing on this list can be moved by Claude. Ordered so the longest external queue starts first. "Unblocks" names what flips the moment it lands.
A3: # | B3: Item | C3: Why it is first/next | D3: Your effort | E3: External lead time | F3: Unblocks | G3: Exact next action
A4: 1 | B4: Meta Business verification + WABA production access | C4: Longest queue in the whole chain AND the messaging-limit unlock — the same gate twice. Everything live depends on it | D4: ~30 min of forms | E4: Days (verification review) | F4: 13 pending-live stories; the 250 -> 1,000 tier step; template submission | G4: business.facebook.com -> verify portfolio (needs incorporation or GST doc). Submit before anything else on this list
A5: 2 | B5: VER-E1 pricing decision | C5: Only open commercial question. Plan allowances are now template messages, and per-message rates vary ~13x by market, so the same $49 plan has very different margin in India vs Europe | D5: 30-60 min thinking | E5: None | F5: Pricing page, FAQ, financial model ARPU line | G5: Decide: keep 1,000/5,000/20,000 template messages at $29/$49/$99, or re-anchor. Tell me the numbers and I will propagate them through billing, the pricing page and the drift gates
A6: 3 | B6: Secrets + Postgres | C6: Mechanical, but the sweep cannot run without them | D6: 15 min | E6: None | F6: npm run migrate / npm start / npm run sweep | G6: Fill .env: WA_ACCESS_TOKEN, WA_PHONE_NUMBER_ID, WA_WABA_ID, WA_WEBHOOK_VERIFY_TOKEN, WA_APP_SECRET, ENGAGEOS_OPERATOR_TOKEN, ENGAGEOS_SESSION_SECRET (16+ chars), ENGAGEOS_CRED_KEY (openssl rand -hex 32), META_APP_ID (new in v0.46.0 — without it signup answers 503), DATABASE_URL, SHARED_STORE=pg, and TRUST_PROXY=1 if behind a load balancer. Then: npm run rehearse (no credentials), npm run migrate (safe to repeat since v0.46.0), npm run evidence:pg (proves your database the way docs/PG_EVIDENCE_TRANSCRIPT.md proves mine).
A7: 4 | B7: Run the 12-step verification sweep | C7: Converts assumption into evidence; flips the largest block of stories in one session | D7: ~30 min once (1) and (3) are done | E7: None | F7: ST-005/015/025/035/045/051/059/066/088/090/092 + LC items | G7: npm ci -> npm run build -> npm run migrate -> npm start -> register /webhook -> WA_TEST_PHONE=+91... npm run sweep. The output format is identical to the rehearsal transcript minus the dry-run banner, so you will know immediately whether a failure is yours or Meta's. Send it to me and I will log it as evidence
A8: 5 | B8: External review V002 | C8: V001 found eighteen things and this project found five more by running what V001 prompted. A second pass on v0.46.0 is the cheapest way to find the sixth. | D8: Forward one file | E8: Reviewer-dependent | F8: ST-097 | G8: Send engageos_v0.46.0_src.zip + this tracker to the same reviewer (or a different model). docs/REVIEW_PACK.md now opens with a v0.46.0 section: six claims to try to break, in order, and the output format. Ask for IDs F-CG-019 onward so V001's stay intact.
A9: 6 | B9: Dispositions: F-005..F-008, D-E4, D-E1, D-E2 | C9: Cheap decisions blocking nothing technically, but they should not go live undecided. F-005 (duplicate install overwriting token + attribution) is the one that matters before live wiring | D9: 20 min | E9: None | F9: Review_Findings rows move to closed | G9: Read the Review_Findings sheet; tell me fix / accept / defer per row. D-E4 = whether to keep the built-in chat engine and skip a vendor entirely
A10: 7 | B10: Pen-test vendor | C10: ST-068 sandbox half is compiled; only a vendor can close it | D10: Procurement | E10: Weeks | F10: ST-068 | G10: Brief a vendor with docs/SECURITY_EVIDENCE.md — it already names the areas to target, including F-005
A11: 8 | B11: Listing copy A/B pick + asset capture | C11: Listing copy still needs your pick. Screens are built and styled, so capture is now a session with a real device and your brand mark, not a design project | D11: 1 hr review + capture session | E11: None | F11: ST-093, ST-094 | G11: Pick A (outcome-led) or B (pain-led) in docs/listing/LISTING_COPY_A_B.md; then capture the 5 shots in ASSET_PLAN.md against the styled workspace at /web (ENGAGEOS_DEMO=1 for populated screens)
A12: 9 | B12: Design-partner outreach | C12: Only paying strangers count toward the 10-install gate; friends do not | D12: Ongoing | E12: Weeks | F12: ST-100 live half; G-02 | G12: Use the 10-slot tracker; remember the 250-recipient/24h ceiling when promising partners a first campaign
A13: 10 | B13: Native-speaker review of the Hindi and Tamil UI strings (47 each) | C13: The UI ships in all three languages; a machine did the translating, and tone in a commercial interface is what a native speaker catches | D13: One decision | E13: None | F13: Whether EngageOS competes with the other builds for your attention | G13: Send i18n/hi.json and i18n/ta.json to a native speaker; return corrections and I will apply them (the disk files are generated from the module, so corrections come back through it)
B14: Review the four vertical template packs (OPEN-E4) | C14: Which templates a clinic vs a shop vs a coaching centre actually needs is a commercial call; the packs are my first cut | G14: Read src/verticals.ts PACKS with one owner per vertical; corrections are one file and I will apply them
A15: 11 | B15: Two Meta test WABAs (not one) | C15: The review's first acceptance gate is two-tenant isolation, and one WABA cannot prove it. Asking for the second while you are already in the portal costs nothing; asking later costs another verification wait. | D15: Part of item 1 | E15: Days (same queue) | F15: CG-G1; S01; F-CG-002 live proof; F-CG-003 live half (the signup code path now exists and is waiting for a real code) | G15: While completing Business verification, add a second test number/WABA to the portfolio.
A16: 12 | B16: Payment provider decision (Stripe vs Razorpay) | C16: F-CG-006 is enforced in code now, but enforcement without a provider is a gate with nothing behind it. Razorpay if the ICP is India-first; Stripe if not — which makes this downstream of item 13. | D16: 30 min | E16: Account approval, days | F16: S05; CG-G4 fully; the billing half of the financial model | G16: Decide after the ICP call, then open the account.
A17: 13 | B17: THE ICP DECISION — one vertical | C17: The review's central commercial finding: four vertical packs is not a wedge, it is optionality. S13 cannot start and F-CG-014/015/017 cannot be dispositioned without this. It also decides item 12. | D17: 1-2 hours thinking | E17: None | F17: S13; F-CG-014, F-CG-015, F-CG-017; OPEN-E4 | G17: Pick ONE of clinics/home-care, education/coaching, local services or D2C support. Tell me which and I will re-cut the backlog, templates and outcome dashboard around it.
A18: 14 | B18: Dispositions: F-CG-014, 015, 016, 017, 018 | C18: The five commercial findings. I have drafted dispositions for the thirteen technical ones; these five are judgements I should not make for you. | D18: 20 min | E18: None | F18: Review_Findings rows move to closed | G18: Read the five rows on Review_Findings; tell me accept / defer / reject per row.

Sheet Integrity_Audit
A1: INTEGRITY AUDIT — claims verified mechanically, not restated (13 Sep 2026, 11:33)
A2: Every check below was executed against the shipped artifact engageos_v0.19.0_src.zip and the tracker itself. Findings were fixed in this version.
A3: # | B3: Check | C3: Method | D3: Result | E3: Action taken
A4: 1 | B4: The shipped zip actually builds from scratch | C4: Unpacked engageos_v0.19.0_src.zip into a clean directory, ran npm ci then npm run build | D4: PASS — npm ci clean, tsc build clean | E4: None needed
A5: 2 | B5: The 100% coverage gate holds on a clean checkout | C5: npm test in the clean directory (jest coverageThreshold 100 x4 fails the run below threshold) | D5: PASS — 35 suites / 171 tests, gate satisfied | E5: None needed
A6: 3 | B6: Coverage is not bought with suppressions | C6: grep for istanbul pragmas across src/ and scripts/ | D6: FAIL — 5 pragmas found, while release notes had repeatedly claimed "one documented pragma" | E6: Two were dead code and were REMOVED rather than suppressed: the chatbot run loop now cannot fall through, and the delivery ledger can no longer miss a state lookup. Three remain and are honest: two process bootstraps (http/index.ts, scripts/run-sweep.ts) and one CLI entry (scripts/make-fixtures.ts), none of which contain testable logic. The claim is corrected to THREE bootstrap pragmas, zero logic pragmas
A7: 4 | B7: Every story claimed Done-in-code names a test suite that exists | C7: Parsed all 100 traceability rows, extracted named .test.ts files, checked each against a repo file index | D7: FAIL — 2 rows named suites vaguely ("all 16 suites", "resilience/broadcast/inbox suites") and could not be verified mechanically | E7: Both rewritten to name real files. Re-run result: 78 of the 79 Done-in-code rows resolve to .test.ts files that exist; the 79th is ST-085, whose evidence is correctly jest.config.js — the coverage gate itself is the verification for a coverage story, and that file was checked to exist. Justified exception, recorded here rather than papered over
A8: 5 | B8: Traceability story text matches the product backlog | C8: Compared column D of every row against Full_Backlog column C, the single source of truth | D8: FAIL — 9 rows had their STORY TEXT OVERWRITTEN with module paths by my own later updates (ST-080/081/088/089/090/092/095/099/100). Real data loss in the traceability record | E8: All 9 restored from the product backlog; the module path moved to the Module column where it belonged. Root cause: later write scripts targeted column 4 assuming a layout that column 3 actually held
A9: 6 | B9: Tracker status agrees with the product workbook | C9: Mapped workbook statuses to tracker taxonomy and compared all 100 rows | D9: PASS — 79 / 13 / 6 / 2 / 0 identical in both files | E9: None needed
A10: 7 | B10: Every non-backlog row carries a version stamp in its evidence | C10: Regex for a vNNN stamp across all evidence cells | D10: PASS — every row traceable to the version that moved it | E10: None needed
A11: 8 | B11: Documented commands and artifacts exist | C11: docsDrift suite asserts .env.example, db/migrations, scripts/migrate.sh, loadtest, templates and the npm scripts all exist | D11: PASS — runs as part of the suite, so it cannot silently rot | E11: None needed
A13: Summary | B13: 8 checks executed | C13: 5 passed on the first run | D13: 3 failed and were fixed in v0.20.0 / tracker v015 | E13: The failures were all in MY reporting and record-keeping rather than in the product: an overstated pragma claim, two unverifiable evidence cells, and nine rows of overwritten story text. Worth noting plainly — the code held up; the paperwork about the code did not.
A15: AUDIT PASS 2 — 13 Sep 2026, 11:38: the findings ledger and workbook structure
A16: # | B16: Check | C16: Method | D16: Result | E16: Action taken
A17: 9 | B17: Every finding recorded as closed is still fixed in the shipped code | C17: One concrete source probe per finding (37 of them) run against the unpacked v0.20.0 zip — e.g. F-009 requires the opt-in gate to be CALLED in broadcast.ts, not merely to exist | D17: PASS — 37 of 37 verified | E17: Converted into tests/findingsRegression.test.ts (39 assertions) so the check runs on every commit. This matters because F-021 was precisely a fix that existed but was not wired, and a record can go stale the same way
A18: 10 | B18: Coverage is not quietly bought back with pragmas in future | C18: Walk src/ and scripts/ for istanbul pragmas, allowing only the three documented process bootstraps | D18: PASS after the v021 removals | E18: Added as a test, so a new suppression fails the build rather than being spotted in a later audit
A19: 11 | B19: Sprint_Board reconciles with Full_Backlog | C19: Recomputed per-sprint story counts and total points from the backlog and compared against the board | D19: PASS — counts and 399-point total agree exactly | E19: None needed
A20: 12 | B20: Product workbook version sequence is contiguous | C20: Listed every Version_Control row in order | D20: PASS — v001-v004 baseline row then v005 onward with no gaps or duplicates | E20: None needed
A21: 13 | B21: Launch checklist reflects current reality | C21: Read all 10 items against what the code and decisions now say | D21: FAIL — item 6 still required testing "conversation-pricing pass-through billing", the model Meta retired on 1 Jul 2025 (VER-E1); items 2, 3 and 8 carried statuses predating the Cloud API decision, the quality guard and the store-backed dedupe | E21: Item 6 rewritten as per-message reconciliation; items 2, 3 and 8 re-statused to what is actually true, with the live half named in each
A22: 14 | B22: Risk identifiers are consistent across files | C22: Compared Risk_Register entries with the tracker RAID sheet | D22: FAIL — the three original risks had no IDs while later ones were R-E7 onward, so the two files could not be cross-referenced | E22: Original three labelled R-E1..R-E3, matching the tracker RAID; the ledger now reads R-E1 through R-E9 across both files
A24: Summary | B24: 14 checks now executed across two passes | C24: 9 passed first time | D24: 5 failed and were fixed | E24: Both passes found the same shape of problem: the product was sound, the record describing it drifted. The response in each case was to convert the check into something automatic — a test suite for the findings, a pragma guard, a drift gate for the docs — so the next drift fails a build instead of waiting for an audit.
A25: AUDIT PASS 3 — 14 Sep 2026, 13:05: what an OUTSIDE reader found, and what running the gates found
A26: # | B26: Check | C26: Method | D26: Result | E26: Action taken
A27: 15 | B27: Does the artifact know its own name? | C27: External reviewer opened engageos_v0.43.0_src.zip and read every file that states a version | D27: FAIL — five different versions: ZIP 0.43.0, package.json 0.37.0, package-lock 0.9.0, README 0.6.0, state document 0.37.0 with a test count two releases old | E27: One version 0.44.0, a generated manifest with a tree SHA-256, a test that fails on drift, and a fourth audit-kit check that ships to the other eleven products. Root cause identical to F-049: one value typed in several places.
A28: 16 | B28: Is every finding recorded as closed actually fixed — including the ones a file marker cannot express? | C28: The reviewer probed call sites rather than definitions: grep for assertWritable, and reading the bootstrap that F-042 claimed to have fixed | D28: FAIL — two of our closed findings were closed on claims. F-011 said "mutating feature entry points call this" and nothing called it. F-042 fixed the selector and left the bootstrap passing no query function. | E28: Both re-opened and re-closed on evidence. The new probes assert the CALL SITE, not the existence of the function. This is the second time the findings-regression suite has been strengthened by discovering it was checking the wrong thing.
A29: 17 | B29: Do the CI gates actually run, as opposed to exist? | C29: Ran npm run rehearse by hand while packaging, instead of trusting the workflow file | D29: FAIL — the rehearsal gate had not booted a server since v0.41.0. Three releases recorded it green. It printed twelve blank lines and failed at step 13 with exit 7, which reads as a flaky step. | E29: Each secret defined once, a hard abort when the server does not answer, and an assertion that the webhook became a conversation. The gate now completes 20 steps. Added as F-049.
A30: 18 | B30: Does the coverage number still mean what it meant? | C30: Full suite on a clean tree after the five fixes | D30: PASS — 55 suites / 408 tests, 100% statements/branches/functions/lines, four documented bootstrap pragmas and none in logic | E30: None needed. Note the reviewer's point stands regardless: 100% coverage of a fake platform surface is 100% coverage of our model of Meta.
A31: Summary | B31: 18 checks now executed across three passes | C31: 10 passed first time | D31: 8 failed and were fixed | E31: Pass 3 is the first with an OUTSIDE reader, and it found the same shape as passes 1 and 2 — the product was sound and the RECORD describing it had drifted — but it found instances the inside passes structurally could not, because each of ours checked the system against itself. The three defects here (version drift, two false closures, a dead gate) share one root cause: a value or a claim written down twice and allowed to diverge.
A33: AUDIT PASS 4 — 16 Sep 2026, 18:25: replaying CI on a clean unzip, against a real database
A34: # | B34: Check | C34: Method | D34: Result | E34: Action taken
A35: 19 | B35: Does every CI step pass on a clean unzip, not just the suite? | C35: Ran each step of ci.yml in order from the zip, with a fresh database, printing each exit code | D35: FAIL — npm run smoke exited 1 (whole-suite coverage threshold on a one-suite run); the job could never have completed green | E35: F-054 fixed; all 14 steps exit 0. Recorded as the portfolio lesson "run it somewhere that is not the machine that wrote it".
A36: 20 | B36: Is every gate the record says is in CI actually in the workflow file? | C36: Compared the gates named in E093/CG-G0 with the steps in ci.yml | D36: FAIL — audit:versions absent since v0.44.0 | E36: F-051 fixed; probe added.
A37: 21 | B37: Does the build depend on anything it does not declare? | C37: Listed node_modules/.bin after npm ci on the v0.45.0 tree and compared with every tool the scripts call | D37: FAIL — ts-node called by three scripts, declared nowhere | E37: F-053 fixed.
A38: 22 | B38: Does the headline number agree with the matrix? | C38: Recounted Traceability_Matrix status and points by formula-free script | D38: FAIL (record) — matrix: 80 stories / 312 points Done-in-code; the 15 Sep file index and this session's plan said 309 | E38: Prose corrected in STATE_OF_ENGAGEOS, REVIEW_PACK, CURRENT_FILES and this tracker. Matrix unchanged — it was right.
A39: 23 | B39: Does a closed persistence claim survive the real dependency failing? | C39: Stopped Postgres under the running shipped server | D39: FAIL — process exited on an unhandled pool error | E39: F-052 fixed; outage leg is now part of evidence:pg and the transcript.
A40: Summary | B40: 23 checks now executed across four passes | C40: 10 passed first time | D40: 13 failed and were fixed | E40: Pass 4 is the first to use a real external dependency. Every failure it found was in a gate or in the record rather than in product logic — the fifth consecutive pass with that shape.

Sheet Lessons_For_Portfolio
A1: LESSONS — written to be applied to the other products, not to be admired here
A2: Twenty lessons from 47 releases. Grouped by the technique that found the defect, because that is the reusable part. Every defect below occurred with 100% statement, branch, function and line coverage in place the whole time.
A3: Group | B3: What it cost here | C3: The rule | D3: Cheapest way to run it elsewhere
A4: Coverage proves the parts, not the product | B4: Four modules shipped, tested and recorded Done while nothing in the product called them — including the opt-in gate and the 24-hour window, so marketing could have reached non-consented contacts. Separately, every route was a GET except the webhook and inbound messages were deduped into a buffer nothing drained: a customer message never became a conversation while 79 stories read as Done. | C4: A story is Done when the RUNNING PRODUCT imports it, and when the intended user could do the thing unaided. Not when the module and its tests exist. | D4: Two greps at each release: list src modules and check each has an importer outside tests; then read the route table and ask which user action each one serves. Ten minutes.
A5: Every written artifact is a specification | B5: Eleven documents were diffed against the product and ALL ELEVEN contained a promise it did not keep: flows that never answered at 2am, a quality guard never consulted before a broadcast, payment links that went to the agent, a vernacular UI whose language packs had no importer, self-serve data rights reachable only with an operator token, plans metered in a unit Meta stopped billing, eight help articles describing tasks with no control, twelve templates whose variables were never sent, a runbook whose first rollback step did not exist, incident messages with nowhere to publish, four missing screens including the stated differentiator, and the vertical differentiation itself. | C5: Diff every customer-facing and operator-facing document against the product at each release, and pin each promise with a test named after it. | D5: Start with the listing copy and the help centre — they are written from the customer's point of view, which is why they find what code review cannot. An hour per product, and it found more defects here than three cold-review passes.
A6: Internal review cannot check your model of the world | B6: Three adversarial passes at 100% coverage could not find that webhook payloads are batched (every message after the first was silently dropped), that conversation pricing was deprecated in July 2025, that messaging limits cap unique recipients portfolio-wide at 250 for a new account, or that templates need body parameters — because the fake adapter faithfully reproduced our own assumptions. | C6: An external verification sweep against live platform documentation is a required step before any live run. | D6: One session per product, before the first live attempt. Read the platform docs for pricing, limits, payload shapes and error semantics; write one test per finding. Thirteen corrections came out of it here.
A7: Honest status is a discipline, not a sentiment | B7: 309 of 399 points are Done-in-code and ZERO are Done, held for 38 releases. Every release that changed no story status said so. Two audits found the record drifting from the product — an overstated pragma claim, nine rows whose story text had been overwritten by my own scripts — and fixing the record was treated as real work. | C7: Separate "the code does this" from "a stranger paid for this", and audit the record itself, not just the code. | D7: A findings-regression suite (one probe per closed defect) plus a periodic diff of the tracker against the product. Both are cheap and both caught things here.
A9: The one that generalises | B9: Coverage, review passes and audits all check the system against itself. | C9: The three techniques that found what they could not — reachability sweeps, document diffs, platform verification — all start from OUTSIDE the code. | D9: Budget for them explicitly in each product's plan rather than hoping they happen.
A10: A gate you have not run is a claim, not a gate | B10: The CI rehearsal gate had not started a server for three releases while every release note recorded it green; two findings recorded Closed had no call site behind them. | C10: Run each gate by hand at least once per release and read its OUTPUT, not its exit code. For findings, probe the call site rather than the definition — a function that exists and is never called is indistinguishable from one that was never written. | D10: One session per product: run every CI step locally, and grep each closed finding for a caller outside its own tests.
A11: One value, written twice, will diverge | B11: Five version numbers for one artifact; a secret exported twice with the signature computed from the first copy; a verify token exported as one value and sent as another. Three separate defects, one cause. | C11: Anything stated in more than one place is generated from one source or checked by a test. Never both hand-maintained. | D11: bin/versions.js in the audit kit does this for release identity in any Node product; the same shape applies to secrets in any shell script.
A12: Run it somewhere that is not the machine that wrote it | B12: Five defects in one release, none findable by reading: migrations that failed on their second run, a CI gate recorded but absent, a database restart that killed every instance, an undeclared global tool, and a smoke gate that could never pass. | C12: Once per release, replay the CI file step by step on a clean unzip, against a real instance of each dependency you can run locally, and read every exit code. Where there is a database, stop it while the server runs. | D12: A 15-line shell script that runs each workflow step and prints name exit=N; a local Postgres takes two minutes to start.
