Workbook

Sheet Version_Control
A1: VERSION CONTROL — TestPulse Sprint Tracker & Traceability
A2: File naming: claude_v<NNN>_<proper file name>_YYYYMMDD_HHMI.xlsx. Companion: v008 product workbook released same timestamp.
A3: Version | B3: Date/Time | C3: Author | D3: Change Description | E3: Status
A4: v001 | B4: 2026-09-10 22:58 | C4: Claude for Senthil/KP | D4: THIS FILE — Live execution tracker for TestPulse (P03, Atlassian Marketplace), opened on Senthil's 22:58 'continue work as per sprint' instruction. S1-S8 code scope executed done-in-code under D13: TypeScript core, 16 Jest suites / 105 tests at 100% branches/functions/lines/statements, CI gate + E2E smoke. 71 stories Done, 7 code-complete pending live Forge/billing, 22 backlog (pen-test, onboarding content, listing/GTM). | E4: Released
A5: v002 | B5: 2026-09-10 23:13 | C5: Claude for Senthil/KP | D5: S9-S12 executable scope done on 23:13 'continue': E8 onboarding/helpcenter/support/review-ask/demo-mode, EQ latency budgets+p95/load test EXECUTED (5,238 rps, 0 errors)/backup drill/chaos degrade/status page, EL listing copy A+B/pricing FAQ/trust page/runbook/dry-run/asset+WCAG specs, AnthropicProvider wired behind AI seam (clears R-P6 in code). 21 suites / 129 tests / 100x4. Now 80 Done / 15 code-complete / 5 backlog (379/399 pts). | E5: Released
A6: v003 | B6: 2026-09-11 08:31 | C6: Claude for Senthil/KP | D6: LC-1 made TURNKEY on 08:31 'continue': ForgeStore hosted-storage adapter shipped+tested behind Store seam (closes R-P4 in code), forge/manifest.yml paste-ready, 30-min deploy guide with Senthil steps marked. Owed docs closed: LC-2 review pack, LC-3 Cloud Fortified gap assessment (formal, no structural gaps), LC-4 residency statement, S0 PRD rollup (A-P1). 22 suites / 132 tests / 100% x4. Story counts unchanged (80/15/5) — remaining flips all need Senthil-side live actions. | E6: Released
A7: v004 | B7: 2026-09-11 12:51 | C7: Claude for Senthil/KP | D7: 12:51 'continue' — deploy-glue + LC-5 de-risking: src/forgeGlue.ts ships the actual Forge resolver+webtrigger handlers (hydrate->dispatch->flush, permission guard, 6 suites incl. cross-invocation KVS persistence) — deploy-guide step 5 is now zero-code; importer hardened for real export shapes (RFC-4180 quotes/newlines, Xray Test Case Exporter multi-step aggregation, Zephyr Scale variant, ragged rows). Coverage regression caught mid-pass (99.87%) and closed. 23 suites / 146 tests / 100% x4. Counts unchanged 80/15/5. | E7: Released
A8: v005 | B8: 2026-09-11 13:32 | C8: Claude for Senthil/KP | D8: 13:32 'continue' — CUSTOM UI LAYER SHIPPED: view-models + escape-safe HTML renderers + bridge-injected mountPanel (src/ui/*, 15 tests incl. jsdom DOM assertions), compiled static/build/app.js bundle, Forge index.html with bridge hook, demo.html with canned data VERIFIED HEADLESS (banner/checklist/cases/board bar/quarantine/readiness dial all render). Manifest's static resource now exists. Screenshot capture available pre-LC-1 via demo.html. 25 suites / 161 tests / 100% x4. Counts unchanged 80/15/5; panel-story evidence upgraded to full-stack. | E8: Released
A9: v006 | B9: 2026-09-11 15:27 | C9: Claude for Senthil/KP | D9: 15:27 'continue' — EXTERNAL VERIFICATION SWEEP against live Atlassian docs: (1) R-P5 CLOSED — Forge officially does NOT authenticate webtrigger URLs, own-auth-in-handler is the prescribed pattern, so our HMAC design is correct-by-design; webtrigger needs urlFormat v2 + dynamic response (statusCode contract already met). (2) Runtime corrected nodejs20.x -> nodejs22.x (Node 20 EOL 2026-04-30). (3) @forge/kvs has no listKeys — kvsAdapter shipped+tested mapping query().where(beginsWith).cursor paging to the seam; entrypoint updated. (4) Marketplace asset spec was WRONG (5x1600x1000 + 2min video) — rewritten to verified Rule-of-3: 1840x900 + 580x330 crops + <=50/220-char text + banner 1120x548 + <30s video. 25 suites / 163 tests / 100% x4. | E9: Released
A10: v007 | B10: 2026-09-11 22:09 | C10: Claude for Senthil/KP | D10: 22:09 'continue' — B-17 DE-RISKED + ST-100 KIT: verified Paid-via-Atlassian model (manifest app.licensing.enabled shipped; ATLASSIAN owns purchase/trial/proration/dunning — our billing.ts payment engine honestly marked superseded for the Marketplace channel, seat limits + read-only behavior reused); licensing gate shipped (inactive => mutating calls read-only, reads never blocked) wired into forgeGlue + tested. Economics cited: Forge revenue 100% to partner up to $1M lifetime (from Jan 2026). PRICING DECISION SURFACED: Atlassian cloud pricing is per-user tiers — flat $99/$299 must be re-anchored (B-17 step 2, Senthil). Design-partner kit shipped (outreach + A1-A4 interview guide + demo script). 26 suites / 167 tests / 100% x4. | E10: Released
A11: v008 | B11: 2026-09-11 22:28 | C11: Claude for Senthil/KP | D11: 22:28 'continue' — COLD REVIEW PASS 1 EXECUTED (first for TestPulse). 27 modules read adversarially against their claims; 13 defects fixed with pinned regressions (test/review.pass1.test.ts), 4 observations logged for Senthil's disposition in the workbook's new Review_Findings sheet. Severity-high: F-TP01 delete/export-my-data missed every non-cloudId-keyed namespace and F-TP02 the retention sweep did the same (published 30-day hard-delete breached); F-TP03/F-TP04 both live panels would have rendered NaN; F-TP05 Forge writes could be dropped when a handler threw; F-TP06 five unbounded ledgers would eventually hard-fail hosted-storage writes. New shared modules: tenantData.ts (one registry driving export+delete+sweep, with a drift test), ledger.ts (FIFO caps + drop counters), csv.ts (RFC-4180 in/out). Gate: 27 suites / 203 tests / 100% x4, zero pragmas. Story counts unchanged 80/15/5 — corrections, not scope. | E11: Released
A12: v009 | B12: 2026-09-13 09:52 | C12: Claude for Senthil/KP | D12: 09:52 'continue' — COLD REVIEW PASS 2 + VERIFICATION SWEEP EXECUTED. Modules pass 1 touched lightly (helpcenter, support, onboarding, aiProvider, billing, xrayImport) reviewed, plus the shipped ARTIFACTS checked against live Atlassian documentation. 10 defects fixed with pinned regressions in test/review.pass2.test.ts; 3 were live-blocking (VER-P01 entrypoint commented out and wrong shape; VER-P02 Custom UI never mounted and shipped without the bridge; VER-P03 license field mismatch) and 2 were security (F-TP14 caller-supplied role; F-TP15 app-wide CI secret). New modules: src/forgeAdapter.ts, src/roles.ts, static/demo-entry.ts; forge/index.ts is now real compiled code. New CI gates: typecheck:forge and build:ui. 28 suites / 233 tests / 100% x4 zero pragmas. Story counts unchanged 80/15/5 — corrections, not scope. Portfolio lessons L-P1/L-P2/L-P3 logged. | E12: Released
A13: v010 | B13: 2026-09-13 10:24 | C13: Claude for Senthil/KP | D13: 10:24 'continue' — COLD REVIEW PASS 3 (REACHABILITY) EXECUTED. 9 findings fixed with pinned regressions in test/review.pass3.test.ts + test/ui.settings.test.ts. Headline: F-TP21 self-serve export/delete had no resolver call and F-TP22 the retention sweep had no scheduled trigger — between them, every published data-rights and retention claim was unreachable in the installed app even after pass 1 made them correct. F-TP23/24 settings, pauses and notifications were library-only (notify() was never called in the Forge path at all). F-TP25/26/27 error tracking, support intake and latency budgets had no caller or surface. F-TP28 the panel bound no events — no control did anything. Shipped: data-rights/settings/support/audit/status resolver calls, daily scheduledTrigger (syntax verified live), notifications on the real paths, per-invocation latency sampling, and a Settings screen with working controls. 30 suites / 263 tests / 100% x4; typecheck:forge + build:ui green; demo page re-verified headless with the Settings screen. Story counts unchanged 80/15/5. Lesson L-P4 logged. | E13: Released
A14: v011 | B14: 2026-09-13 10:37 | C14: Claude for Senthil/KP | D14: 10:37 'continue' — COLD REVIEW PASS 4 (CLAIMS) EXECUTED + AUTOMATED A11Y SHIPPED. 5 findings fixed with pinned regressions in test/review.pass4.test.ts: F-TP30 the live Jira calls bypassed ST-070's retry/breaker entirely; F-TP31 and F-TP32 two pieces of published evidence (backup drill, 'posture asserted in CI') rested on code nobody ran; F-TP33 four false document statements including an email subprocessor the app has no egress permission to reach; F-TP29 an unnamed table header found by the new axe pass. ST-089's automated WCAG audit now runs over all five panels on every build instead of waiting for LC-1. 32 suites / 280 tests / 100% x4; CI gates now check:posture + typecheck:forge + build:ui + jest. Story counts unchanged 80/15/5. Four passes complete: 37 defects, all found in code already at 100% coverage. Lesson L-P5 logged. | E14: Released
... A20: v017 | B20: 2026-09-13 11:22 | C20: Claude for Senthil/KP | D20: 11:22 'continue' — LC-1 SESSION PACK SHIPPED: scripts/lc1-verify.js (live webtrigger verification against the deployed app, tested against the real handler, prints tracker-ready evidence and states what it cannot check), docs/lc1-session-pack.md (45-minute run sheet with an evidence table mapping captures to the stories they flip), and static/build/capture.html (asset capture at the verified Rule-of-3 dimensions, verified headlessly). 37 suites / 332 tests / 100% x4; six CI gates green. Story counts deliberately unchanged 80/15/5 — the 15 code-complete stories flip at LC-1 with evidence attached, not before. | E20: Released
A21: v018 | B21: PLANNED: LC-1 executed — evidence, story flips, live findings; then D18 + partner console + assets. | E21: Planned

Sheet Sprint_Tracker_Log
A1: SPRINT TRACKER LOG — every execution event, newest last
A2: ID | B2: Date/Time | C2: Sprint | D2: What happened | E2: Refs | F2: State changes | G2: Blockers | H2: Next
A3: E001 | B3: 2026-09-10 22:58 | C3: — | D3: INSTRUCTION RECORDED — Senthil 22:58: continue work as per sprint on TestPulse from v007 workbook; complete development with 100% automation testing; produce tracker+traceability like TeleField v001 and workbook next version. D13 applies (interviews parked, 100% coverage). Ninth concurrent build under open D15. | E3: D13,D15 | F3: TestPulse S1 opened | G3: None | H3: S1 build
A4: E002 | B4: 2026-09-10 22:58 | C4: S1 | D4: S1 FOUNDATION BUILT (TypeScript/Node core, Forge-adapter seams per D17): config validation (residency global/eu/us, trial days), typed Store (in-memory behind interface — Forge hosted storage adapter at deploy), lifecycle install->welcome/uninstall token-wipe+30d deletion schedule+sweep/re-install restore/rotation-safe refresh/source attribution, webhook HMAC timing-safe verify+replay+dedupe, jiraClient 429/5xx backoff+jitter+circuit breaker, CI with jest coverageThreshold 100x4. | E4: ST-051,052,053,055,056,070 | F4: 6 E1 stories Done-in-code | G4: Live Forge dev site = Senthil (LC-1) | H4: S2
A5: E003 | B5: 2026-09-10 22:58 | C5: S2 | D5: S2 EXECUTED — F1 AI test-case generation part 1: rule engine behind AI seam (provider-swappable), defaults one-screen, happy+edge+permission case output, clear errors, rules customisation; owner/admin/member permission matrix + audit log wired to all routes. | E5: ST-001..004,053,054 | F5: 6/6 S2 stories Done (29 pts) | G5: None | H5: S3
A6: E004 | B6: 2026-09-10 22:58 | C6: S3 | D6: S3 EXECUTED — F1 completed (metrics, pause-no-loss, CSV import, notifications) + F2 run boards started (defaults, happy path, rules, errors). ST-085 coverage gate SUPERSEDED by D13: shipped at 100x4, not >=70. ST-005 Forge-panel surface = code-complete pending live. | E6: ST-005..014,085 | F6: 10 Done + 1 code-complete | G6: Forge panel render needs LC-1 | H6: S4
A7: E005 | B7: 2026-09-10 22:58 | C7: S4 | D7: S4 EXECUTED — F2 completed (metrics/passRate, permissions, pause, CSV import, notifications); E7 activation funnel + error tracking with spike alert; E2E smoke suite wired into CI on every deploy. MVP loop (install->generate->board->metrics) passes end-to-end in e2e.smoke.test.ts. | E7: ST-015..020,071,072,086 | F7: 8 Done + 1 code-complete; S4 exit criterion met in-code | G7: None | H7: S5
A8: E006 | B8: 2026-09-10 22:58 | C8: S5 | D8: S5 EXECUTED — F3 flaky-test detector: signed CI-webhook ingest, flip-rate scoring, quarantine threshold (custom, validated), pause, notifications. ST-078/079 onboarding content = backlog (design/content, not code). | E8: ST-021..030 | F8: 9 Done + 1 code-complete | G8: Onboarding content = Senthil review | H8: S6
A9: E007 | B9: 2026-09-10 22:58 | C9: S6 | D9: S6 EXECUTED — E5 billing core: 14-day card-free trial + banner, mid-cycle proration (verified $100 on 15-day starter->team), plan limits 80/100 alerts; F4 release readiness score with validated custom weights and verdicts. ST-059 Atlassian-billing wiring pending live listing. | E9: ST-031..040,057,058 | F9: 11 Done + 2 code-complete | G9: Atlassian billing = live listing (LC-8) | H9: S7
A10: E008 | B10: 2026-09-10 22:58 | C10: S7 | D10: S7 EXECUTED (code scope) — dunning: 7-day grace, 3 emails, read-only; plan-limit prompts; GST invoices; cancel flow with save-offer + exit survey; least-privilege scope map 1:1 to features. Design-partner activity itself = live-only (beta gate). | E10: ST-060..064 | F10: 5 Done | G10: 3+ live partners = post-listing | H10: S8
A11: E009 | B11: 2026-09-10 22:58 | C11: S8 | D11: S8 EXECUTED (code scope) — F5 Xray/Zephyr importer (export parse, mapping, errors); E6 data-flow+retention doc, audit log, export/delete-my-data, rate-limit backoff+breaker; E7 heatmap, weekly CSV, health score, alert thresholds. ST-066 vault/KMS + ST-087/088/092 live-infra items pending; 3 real Xray export files (LC-5) = Senthil. | E11: ST-041..050,065,067,069,070,073..077 | F11: 16 Done + 1 code-complete | G11: Real Xray exports; live infra | H11: D13 verify
A12: E010 | B12: 2026-09-10 22:58 | C12: — | D12: D13 TEST GATE MET — 16 Jest suites, 105 tests, 100% branches/functions/lines/statements; jest coverageThreshold 100x4 fails CI below 100; E2E smoke on every deploy. TOTAL: 71 Done / 7 code-complete pending live / 22 backlog (399 pts total; 321 pts done incl. code-complete). Tracker v001 + workbook v008 released 22:58. | E12: D13 | F12: Evidence in Traceability col K | G12: None | H12: S9 review prep needs live items; D15
A13: E011 | B13: 2026-09-10 23:13 | C13: — | D13: INSTRUCTION — Senthil 23:13 'continue': execute remaining executable backlog (S9-S12 scope). | E13: D13 | F13: S9-S12 pass opened | G13: None | H13: build
... A72: E070 | B72: 2026-09-13 11:22 | C72: Status | D72: TESTPULSE HANDOVER STATE — nine sittings of work: 8 cold-review passes (50 defects, all in code at 100% coverage, no story count moved), 4 standing gates covering 34 of them, a portfolio rollout kit, and now the LC-1 pack. Everything remaining is gated on a live install, a pricing decision, asset capture or a pen-test. D13 re-verified: 37 suites / 332 tests / 100% x4 zero pragmas; gates, posture, forge typecheck, UI build and axe all green. Tracker v017 + workbook v024 + code released 11:22. | E72: LC-1, D18, ST-094, ST-068 | F72: Handover-ready | G72: LC-1 is the unblock | H72: —

Sheet Decisions
A1: DECISIONS (tracker scope)
A2: ID | B2: Decision | C2: Rationale | D2: Decided by | E2: Status
A3: D13 | B3: (Portfolio-wide) Discovery interviews parked; dev proceeds with 100% automation test coverage on all code — supersedes ST-085 >=70% gate. | C3: Senthil 10 Sep 20:45; applied to TestPulse per 22:58 instruction. | D3: Senthil | E3: LOCKED
A4: D15 | B4: TestPulse (P03) build opened 10 Sep 22:58 while RevRescue rank-1 gate (listed + 10 paying) is not met — ninth concurrent build. Mode ratification: (a) parallel builds or (b) WIN-order swap. | C4: Uploaded workbook set + continue-sprint instruction indicate TestPulse intent; serial rule formally intact until ratified. | D4: Senthil (mode ratification pending) | E4: OPEN — pick (a) or (b)
A5: D17 | B5: TestPulse stack = TypeScript/Node platform-agnostic core with Forge adapter seams: Store interface (in-memory now, Forge hosted storage at deploy), Billing provider seam (Atlassian billing at listing), AI seam in testgen (rule engine now, LLM provider swappable). Express routes map 1:1 to Forge resolvers. | C5: v007 ReadMe stack assumption ("platform-mandated runtime"); sandbox has no Forge CLI/Postgres; matches accepted D16 precedent on TeleField. | D5: Claude — flagged | E5: OPEN for ratification
A6: D18 | B6: 2026-09-11 22:09 | C6: Per-user price point for Atlassian cloud pricing tiers | D6: OPEN — Senthil | E6: Flat $99/$299 intent must map to per-user tiers (Atlassian model). Options: ~$4/user/mo flat-equivalent vs re-anchor vs value-based. Blocks B-17 step 2 and final pricing-page copy. | F6: Claude (surfaced from verified docs)

Sheet S1_S8_Build_Board
A1: S1–S12 BUILD BOARD — executed code scope. Exit S4: MVP loop usable end-to-end (met in-code via E2E smoke).
A2: Backlog stories per Traceability_Matrix. Edit Status/Notes (yellow) as live evidence lands.
A3: ID | B3: Item | C3: Story ref | D3: Points | E3: Owner | F3: Status | G3: Notes / Evidence
A4: B-01 | B4: Repo scaffold + CI with 100% coverage gate (D13) | C4: — | D4: 2 | E4: Claude | F4: Done | G4: jest coverageThreshold 100x4; .github/workflows/ci.yml runs build+coverage+E2E. E010.
A5: B-02 | B5: Config: site/app/secret validation, residency, trial days | C5: — | D5: 1 | E5: Claude | F5: Done | G5: src/config.ts — 5 tests incl. bad residency + bad trial days.
A6: B-03 | B6: Typed Store repository (Forge hosted-storage adapter point) | C6: — | D6: 2 | E6: Claude | F6: Done | G6: src/store.ts — D17 constraint logged as R-P4.
A7: B-04 | B7: Install -> welcome; uninstall wipe + 30d deletion + sweep; re-install restore; rotation | C7: ST-051/052/053/055 | D7: 5 | E7: Claude | F7: Done | G7: src/lifecycle.ts — 8 tests incl. retention-window and legacy-row edge cases.
A8: B-05 | B8: Install telemetry source attribution | C8: ST-056 | D8: 2 | E8: Claude | F8: Done | G8: listing/search/referral, unknown->direct; preserved across re-install.
A9: B-06 | B9: Permission matrix + audit log on every route | C9: ST-054/007/017/027/037/047/067 | D9: 5 | E9: Claude | F9: Done | G9: src/permissions.ts + guard() in app.ts; member-403 and bad-role-400 asserted in E2E.
A10: B-07 | B10: F1 AI case-gen engine behind AI seam | C10: ST-001..010 | D10: 42 | E10: Claude | F10: Done | G10: src/testgen.ts — 10 tests; LLM provider swap point isolated in generateFromStory.
A11: B-08 | B11: F2 run boards + metrics + CSV import | C11: ST-011..020 | D11: 42 | E11: Claude | F11: Done | G11: src/runboards.ts — 6 tests + E2E board flow.
A12: B-09 | B12: F3 flaky detector: webhook intake -> flip-rate -> quarantine | C12: ST-021..030 | D12: 50 | E12: Claude | F12: Done | G12: src/flaky.ts + src/webhooks.ts — HMAC/replay/dedupe; E2E tampered-signature 401.
A13: B-10 | B13: F4 readiness score, validated weights | C13: ST-031..040 | D13: 42 | E13: Claude | F13: Done | G13: src/readiness.ts — 5 tests; verdict bands ready/at-risk/not-ready.
A14: B-11 | B14: F5 Xray importer | C14: ST-041..050 | D14: 42 | E14: Claude | F14: Done | G14: src/xrayImport.ts — parse+map into TestGen; E2E import 201.
A15: B-12 | B15: E5 billing: trial/proration/dunning/limits/GST/cancel | C15: ST-057..063 | D15: 27 | E15: Claude | F15: Done | G15: src/billing.ts — 10 tests; proration case verified $100.
... A40: B-37 | B40: Design-partner kit: outreach, A1-A4 interview guide, demo script | C40: ST-100 | D40: 2 | E40: Claude | F40: Done | G40: docs/design-partner-kit.md; execution = Senthil.

Sheet Traceability_Matrix
A1: TRACEABILITY MATRIX — 100 stories: module -> epic -> story -> screen -> verification -> status (edit Status/Evidence as live items land)
A2: Source: v008 Full_Backlog (single source of truth). Status: Done = automated-test evidence in repo (D13); Code-complete = built, pending live platform; Backlog = not started.
A3: Story ID | B3: Epic | C3: Module / feature | D3: Story | E3: Points | F3: Priority | G3: Sprint | H3: Primary screen | I3: Verification | J3: Status | K3: Evidence
A4: ST-001 | B4: F1 | C4: AI test-case generation | D4: As a QA lead, I can set up AI test-case generation with sensible defaults in one screen | E4: 5 | F4: P0 | G4: S2 | H4: SCR-3 AI generation workspace | I4: E2E test + demo | J4: Done | K4: src/testgen.ts DEFAULT_RULES + setRules; test/testgen.test.ts
A5: ST-002 | B5: F1 | C5: AI test-case generation | D5: As a QA lead, the AI test-case generation happy path completes without documentation | E5: 8 | F5: P0 | G5: S2 | H5: SCR-3 AI generation workspace | I5: E2E test + demo | J5: Done | K5: src/testgen.ts generateFromStory; testgen + e2e tests
A6: ST-003 | B6: F1 | C6: AI test-case generation | D6: As a Eng manager, I can customise AI test-case generation rules/conditions for my workflow | E6: 5 | F6: P1 | G6: S2 | H6: SCR-3 AI generation workspace | I6: Integration test + manual QA | J6: Done | K6: setRules customisation; validation test
A7: ST-004 | B7: F1 | C7: AI test-case generation | D7: As a user, AI test-case generation shows clear errors and retry paths on platform API failures | E7: 3 | F7: P0 | G7: S2 | H7: SCR-3 AI generation workspace | I7: E2E test + demo | J7: Done | K7: empty-story + bad-CSV clear errors; testgen tests
A8: ST-005 | B8: F1 | C8: AI test-case generation | D8: As a Jira admin, AI test-case generation works on the Forge app panel inside Jira surface end-to-end | E8: 5 | F8: P0 | G8: S3 | H8: SCR-3 AI generation workspace | I8: E2E test + demo | J8: Code-complete — pending live | K8: Full stack shipped: API + resolver glue + panel UI (src/ui/* tested, static/build bundle, demo verified headless). Only live Forge render verification remains — LC-1
A9: ST-006 | B9: F1 | C9: AI test-case generation | D9: As a Eng manager, I can see AI test-case generation performance metrics and trends | E9: 3 | F9: P1 | G9: S3 | H9: SCR-3 AI generation workspace | I9: Integration test + manual QA | J9: Done | K9: metrics() byKind rollup; test
A10: ST-007 | B10: F1 | C10: AI test-case generation | D10: As a user, AI test-case generation respects role permissions and audit logging | E10: 3 | F10: P1 | G10: S3 | H10: SCR-3 AI generation workspace | I10: Integration test + manual QA | J10: Done | K10: Permissions matrix + audit on every check; permissions tests
A11: ST-008 | B11: F1 | C11: AI test-case generation | D11: As a QA lead, I can pause/disable AI test-case generation without data loss | E11: 2 | F11: P2 | G11: S3 | H11: SCR-3 AI generation workspace | I11: Manual QA | J11: Done | K11: setEnabled pause, data retained; test
A12: ST-009 | B12: F1 | C12: AI test-case generation | D12: As a Eng manager, I can import/migrate existing data into AI test-case generation (CSV + competitor importer) | E12: 5 | F12: P1 | G12: S3 | H12: SCR-3 AI generation workspace | I12: Integration test + manual QA | J12: Done | K12: importCsv header/row validation; tests
A13: ST-010 | B13: F1 | C13: AI test-case generation | D13: As a user, I get notifications (in-app + email) for key AI test-case generation events with per-type mute | E13: 3 | F13: P2 | G13: S3 | H13: SCR-3 AI generation workspace | I13: Manual QA | J13: Done | K13: Notifications per-type prefs generation events; notifications tests
A14: ST-011 | B14: F2 | C14: Test run boards | D14: As a QA lead, I can set up Test run boards with sensible defaults in one screen | E14: 5 | F14: P0 | G14: S3 | H14: SCR-4 Run boards builder | I14: E2E test + demo | J14: Done | K14: src/runboards.ts createBoard defaults
A15: ST-012 | B15: F2 | C15: Test run boards | D15: As a QA lead, the Test run boards happy path completes without documentation | E15: 8 | F15: P0 | G15: S3 | H15: SCR-4 Run boards builder | I15: E2E test + demo | J15: Done | K15: record() happy path; e2e board flow
... A101: ST-098 | B101: EL | C101: Launch & listing | D101: Launch-day runbook: monitoring, rollback, comms tree | E101: 3 | F101: P1 | G101: S11 | H101: — (listing) | I101: Integration test + manual QA | J101: Done | K101: docs/launch-runbook.md: monitoring thresholds, rollback (additive schema + feature kill switches), comms tree
A102: ST-099 | B102: EL | C102: Launch & listing | D102: Post-launch listing SEO iteration 1 from search-term data | E102: 2 | F102: P2 | G102: S12 | H102: — (listing) | I102: Manual QA | J102: Backlog
A103: ST-100 | B103: EL | C103: Launch & listing | D103: First 10 design-partner reviews scheduled | E103: 2 | F103: P1 | G103: S11 | H103: — (listing) | I103: Integration test + manual QA | J103: Backlog | K103: Execution-ready: outreach email + A1-A4 interview guide + demo script shipped (design-partner-kit.md); sending = Senthil

Sheet Sprint_Status_Rollup
A1: SPRINT STATUS ROLLUP — live formulas over Traceability_Matrix
A2: Do not edit computed cells. 'Done' counts Done + Code-complete rows. Exit criteria from v008 Sprint_Board.
A3: Sprint | B3: Focus | C3: Stories | D3: Points | E3: Done | F3: Done points | G3: % points done | H3: RAG (manual) | I3: Exit criteria
A4: S1 | B4: Foundation (2 wks) | C4: =COUNTIFS(Traceability_Matrix!$G$4:$G$103,A4) -> 4 | D4: =SUMIFS(Traceability_Matrix!$E$4:$E$103,Traceability_Matrix!$G$4:$G$103,A4) -> 13 | E4: =COUNTIFS(Traceability_Matrix!$G$4:$G$103,A4,Traceability_Matrix!$J$4:$J$103,"Done")+COUNTIFS(Traceability_Matrix!$G$4:$G$103,A4,Traceability_Matrix!$J$4:$J$103,"Code-complete — pending live") -> 4 | F4: =SUMIFS(Traceability_Matrix!$E$4:$E$103,Traceability_Matrix!$G$4:$G$103,A4,Traceability_Matrix!$J$4:$J$103,"Done")+SUMIFS(Traceability_Matrix!$E$4:$E$103,Traceability_Matrix!$G$4:$G$103,A4,Traceability_Matrix!$J$4:$J$103,"Code-complete — pending live") -> 13 | G4: =IFERROR(F4/D4,0) -> 1 | H4: GREEN — 4/4 code stories done; live install pending (B-16) | I4: App installs cleanly in dev store/org; telemetry firing
A5: S2 | B5: AI test-case generation pt 1 | C5: =COUNTIFS(Traceability_Matrix!$G$4:$G$103,A5) -> 6 | D5: =SUMIFS(Traceability_Matrix!$E$4:$E$103,Traceability_Matrix!$G$4:$G$103,A5) -> 29 | E5: =COUNTIFS(Traceability_Matrix!$G$4:$G$103,A5,Traceability_Matrix!$J$4:$J$103,"Done")+COUNTIFS(Traceability_Matrix!$G$4:$G$103,A5,Traceability_Matrix!$J$4:$J$103,"Code-complete — pending live") -> 6 | F5: =SUMIFS(Traceability_Matrix!$E$4:$E$103,Traceability_Matrix!$G$4:$G$103,A5,Traceability_Matrix!$J$4:$J$103,"Done")+SUMIFS(Traceability_Matrix!$E$4:$E$103,Traceability_Matrix!$G$4:$G$103,A5,Traceability_Matrix!$J$4:$J$103,"Code-complete — pending live") -> 29 | G5: =IFERROR(F5/D5,0) -> 1 | H5: GREEN — 6/6 done | I5: AI case-gen happy path demoable
A6: S3 | B6: AI case-gen pt 2 + Run boards start | C6: =COUNTIFS(Traceability_Matrix!$G$4:$G$103,A6) -> 11 | D6: =SUMIFS(Traceability_Matrix!$E$4:$E$103,Traceability_Matrix!$G$4:$G$103,A6) -> 47 | E6: =COUNTIFS(Traceability_Matrix!$G$4:$G$103,A6,Traceability_Matrix!$J$4:$J$103,"Done")+COUNTIFS(Traceability_Matrix!$G$4:$G$103,A6,Traceability_Matrix!$J$4:$J$103,"Code-complete — pending live") -> 11 | F6: =SUMIFS(Traceability_Matrix!$E$4:$E$103,Traceability_Matrix!$G$4:$G$103,A6,Traceability_Matrix!$J$4:$J$103,"Done")+SUMIFS(Traceability_Matrix!$E$4:$E$103,Traceability_Matrix!$G$4:$G$103,A6,Traceability_Matrix!$J$4:$J$103,"Code-complete — pending live") -> 47 | G6: =IFERROR(F6/D6,0) -> 1 | H6: GREEN — 10/11 done; ST-005 at LC-1 | I6: AI case-gen complete with tests; Run boards skeleton
A7: S4 | B7: Test run boards | C7: =COUNTIFS(Traceability_Matrix!$G$4:$G$103,A7) -> 9 | D7: =SUMIFS(Traceability_Matrix!$E$4:$E$103,Traceability_Matrix!$G$4:$G$103,A7) -> 34 | E7: =COUNTIFS(Traceability_Matrix!$G$4:$G$103,A7,Traceability_Matrix!$J$4:$J$103,"Done")+COUNTIFS(Traceability_Matrix!$G$4:$G$103,A7,Traceability_Matrix!$J$4:$J$103,"Code-complete — pending live") -> 9 | F7: =SUMIFS(Traceability_Matrix!$E$4:$E$103,Traceability_Matrix!$G$4:$G$103,A7,Traceability_Matrix!$J$4:$J$103,"Done")+SUMIFS(Traceability_Matrix!$E$4:$E$103,Traceability_Matrix!$G$4:$G$103,A7,Traceability_Matrix!$J$4:$J$103,"Code-complete — pending live") -> 34 | G7: =IFERROR(F7/D7,0) -> 1 | H7: GREEN — MVP loop passes E2E in CI | I7: MVP loop usable end-to-end internally
A8: S5 | B8: Flaky-test detector + alpha hardening | C8: =COUNTIFS(Traceability_Matrix!$G$4:$G$103,A8) -> 12 | D8: =SUMIFS(Traceability_Matrix!$E$4:$E$103,Traceability_Matrix!$G$4:$G$103,A8) -> 50 | E8: =COUNTIFS(Traceability_Matrix!$G$4:$G$103,A8,Traceability_Matrix!$J$4:$J$103,"Done")+COUNTIFS(Traceability_Matrix!$G$4:$G$103,A8,Traceability_Matrix!$J$4:$J$103,"Code-complete — pending live") -> 12 | F8: =SUMIFS(Traceability_Matrix!$E$4:$E$103,Traceability_Matrix!$G$4:$G$103,A8,Traceability_Matrix!$J$4:$J$103,"Done")+SUMIFS(Traceability_Matrix!$E$4:$E$103,Traceability_Matrix!$G$4:$G$103,A8,Traceability_Matrix!$J$4:$J$103,"Code-complete — pending live") -> 50 | G8: =IFERROR(F8/D8,0) -> 1 | H8: GREEN — code scope done; onboarding content backlog | I8: Internal alpha: team dogfoods daily
A9: S6 | B9: Billing + Release readiness score | C9: =COUNTIFS(Traceability_Matrix!$G$4:$G$103,A9) -> 13 | D9: =SUMIFS(Traceability_Matrix!$E$4:$E$103,Traceability_Matrix!$G$4:$G$103,A9) -> 60 | E9: =COUNTIFS(Traceability_Matrix!$G$4:$G$103,A9,Traceability_Matrix!$J$4:$J$103,"Done")+COUNTIFS(Traceability_Matrix!$G$4:$G$103,A9,Traceability_Matrix!$J$4:$J$103,"Code-complete — pending live") -> 13 | F9: =SUMIFS(Traceability_Matrix!$E$4:$E$103,Traceability_Matrix!$G$4:$G$103,A9,Traceability_Matrix!$J$4:$J$103,"Done")+SUMIFS(Traceability_Matrix!$E$4:$E$103,Traceability_Matrix!$G$4:$G$103,A9,Traceability_Matrix!$J$4:$J$103,"Code-complete — pending live") -> 60 | G9: =IFERROR(F9/D9,0) -> 1 | H9: GREEN — billing core + readiness done; Atlassian billing at listing | I9: Can charge a test customer; up/downgrade paths work
A10: S7 | B10: Private beta (design partners) | C10: =COUNTIFS(Traceability_Matrix!$G$4:$G$103,A10) -> 5 | D10: =SUMIFS(Traceability_Matrix!$E$4:$E$103,Traceability_Matrix!$G$4:$G$103,A10) -> 15 | E10: =COUNTIFS(Traceability_Matrix!$G$4:$G$103,A10,Traceability_Matrix!$J$4:$J$103,"Done")+COUNTIFS(Traceability_Matrix!$G$4:$G$103,A10,Traceability_Matrix!$J$4:$J$103,"Code-complete — pending live") -> 5 | F10: =SUMIFS(Traceability_Matrix!$E$4:$E$103,Traceability_Matrix!$G$4:$G$103,A10,Traceability_Matrix!$J$4:$J$103,"Done")+SUMIFS(Traceability_Matrix!$E$4:$E$103,Traceability_Matrix!$G$4:$G$103,A10,Traceability_Matrix!$J$4:$J$103,"Code-complete — pending live") -> 15 | G10: =IFERROR(F10/D10,0) -> 1 | H10: AMBER — code done; live partners gate beta exit | I10: 3+ partners active weekly; NPS pulse >30
A11: S8 | B11: Beta iteration + Xray importer | C11: =COUNTIFS(Traceability_Matrix!$G$4:$G$103,A11) -> 22 | D11: =SUMIFS(Traceability_Matrix!$E$4:$E$103,Traceability_Matrix!$G$4:$G$103,A11) -> 87 | E11: =COUNTIFS(Traceability_Matrix!$G$4:$G$103,A11,Traceability_Matrix!$J$4:$J$103,"Done")+COUNTIFS(Traceability_Matrix!$G$4:$G$103,A11,Traceability_Matrix!$J$4:$J$103,"Code-complete — pending live") -> 22 | F11: =SUMIFS(Traceability_Matrix!$E$4:$E$103,Traceability_Matrix!$G$4:$G$103,A11,Traceability_Matrix!$J$4:$J$103,"Done")+SUMIFS(Traceability_Matrix!$E$4:$E$103,Traceability_Matrix!$G$4:$G$103,A11,Traceability_Matrix!$J$4:$J$103,"Code-complete — pending live") -> 87 | G11: =IFERROR(F11/D11,0) -> 1 | H11: AMBER — 17/22 done-in-code; live infra + real Xray files pending | I11: Beta cohort WoW retention >60%
A12: S9 | B12: Marketplace review prep | C12: =COUNTIFS(Traceability_Matrix!$G$4:$G$103,A12) -> 7 | D12: =SUMIFS(Traceability_Matrix!$E$4:$E$103,Traceability_Matrix!$G$4:$G$103,A12) -> 30 | E12: =COUNTIFS(Traceability_Matrix!$G$4:$G$103,A12,Traceability_Matrix!$J$4:$J$103,"Done")+COUNTIFS(Traceability_Matrix!$G$4:$G$103,A12,Traceability_Matrix!$J$4:$J$103,"Code-complete — pending live") -> 4 | F12: =SUMIFS(Traceability_Matrix!$E$4:$E$103,Traceability_Matrix!$G$4:$G$103,A12,Traceability_Matrix!$J$4:$J$103,"Done")+SUMIFS(Traceability_Matrix!$E$4:$E$103,Traceability_Matrix!$G$4:$G$103,A12,Traceability_Matrix!$J$4:$J$103,"Code-complete — pending live") -> 14 | G12: =IFERROR(F12/D12,0) -> 0.46666667 | I12: Review submission accepted into queue
A13: S10 | B13: Review remediation + docs | C13: =COUNTIFS(Traceability_Matrix!$G$4:$G$103,A13) -> 7 | D13: =SUMIFS(Traceability_Matrix!$E$4:$E$103,Traceability_Matrix!$G$4:$G$103,A13) -> 24 | E13: =COUNTIFS(Traceability_Matrix!$G$4:$G$103,A13,Traceability_Matrix!$J$4:$J$103,"Done")+COUNTIFS(Traceability_Matrix!$G$4:$G$103,A13,Traceability_Matrix!$J$4:$J$103,"Code-complete — pending live") -> 7 | F13: =SUMIFS(Traceability_Matrix!$E$4:$E$103,Traceability_Matrix!$G$4:$G$103,A13,Traceability_Matrix!$J$4:$J$103,"Done")+SUMIFS(Traceability_Matrix!$E$4:$E$103,Traceability_Matrix!$G$4:$G$103,A13,Traceability_Matrix!$J$4:$J$103,"Code-complete — pending live") -> 24 | G13: =IFERROR(F13/D13,0) -> 1 | I13: Marketplace approval obtained
A14: S11 | B14: Launch | C14: =COUNTIFS(Traceability_Matrix!$G$4:$G$103,A14) -> 3 | D14: =SUMIFS(Traceability_Matrix!$E$4:$E$103,Traceability_Matrix!$G$4:$G$103,A14) -> 8 | E14: =COUNTIFS(Traceability_Matrix!$G$4:$G$103,A14,Traceability_Matrix!$J$4:$J$103,"Done")+COUNTIFS(Traceability_Matrix!$G$4:$G$103,A14,Traceability_Matrix!$J$4:$J$103,"Code-complete — pending live") -> 2 | F14: =SUMIFS(Traceability_Matrix!$E$4:$E$103,Traceability_Matrix!$G$4:$G$103,A14,Traceability_Matrix!$J$4:$J$103,"Done")+SUMIFS(Traceability_Matrix!$E$4:$E$103,Traceability_Matrix!$G$4:$G$103,A14,Traceability_Matrix!$J$4:$J$103,"Code-complete — pending live") -> 6 | G14: =IFERROR(F14/D14,0) -> 0.75 | I14: First 10 installs; first 3 reviews; activation >40%
A15: S12 | B15: Iterate & scale decision | C15: =COUNTIFS(Traceability_Matrix!$G$4:$G$103,A15) -> 1 | D15: =SUMIFS(Traceability_Matrix!$E$4:$E$103,Traceability_Matrix!$G$4:$G$103,A15) -> 2 | E15: =COUNTIFS(Traceability_Matrix!$G$4:$G$103,A15,Traceability_Matrix!$J$4:$J$103,"Done")+COUNTIFS(Traceability_Matrix!$G$4:$G$103,A15,Traceability_Matrix!$J$4:$J$103,"Code-complete — pending live") -> 0 | F15: =SUMIFS(Traceability_Matrix!$E$4:$E$103,Traceability_Matrix!$G$4:$G$103,A15,Traceability_Matrix!$J$4:$J$103,"Done")+SUMIFS(Traceability_Matrix!$E$4:$E$103,Traceability_Matrix!$G$4:$G$103,A15,Traceability_Matrix!$J$4:$J$103,"Code-complete — pending live") -> 0 | G15: =IFERROR(F15/D15,0) -> 0 | I15: Growth model doc with CAC/LTV first estimates
A16: TOTAL | B16: (S1-S12) | C16: =SUM(C4:C15) -> 100 | D16: =SUM(D4:D15) -> 399 | E16: =SUM(E4:E15) -> 95 | F16: =SUM(F4:F15) -> 379 | G16: =IFERROR(F16/D16,0) -> 0.94987469

Sheet RAID_Carryover
A1: RAID — seeded from v007 Risk_Register + build findings
A2: ID | B2: Type | C2: Raised | D2: Item | E2: Status | F2: Notes / Mitigation
A3: R-P1 | B3: Risk | C3: v007 | D3: Atlassian Forge program rate/policy changes mid-build (Medium/Medium) | E3: Open | F3: Track dev changelog; rate abstraction already in jiraClient backoff + pricing model.
A4: R-P2 | B4: Risk | C4: v007 | D4: Xray/Zephyr respond with AI features (High/Medium) | E4: Open | F4: Speed + Forge-native cost advantage + importer-led switching (F5 shipped in-code).
A5: R-P3 | B5: Risk | C5: v007 | D5: Cloud Fortified bar raises before listing (Medium/Medium) | E5: Open | F5: Gap assessment started in-code (scope map ST-064, data-flow ST-065, audit ST-067, residency config); formal assessment doc owed at LC-3.
A6: R-P4 | B6: Constraint | C6: 22:58 | D6: Sandbox has no Forge CLI/hosted storage — persistence is in-memory behind typed Store; billing behind provider seam (D17) | E6: Closed-in-code | F6: 08:31: ForgeStore adapter shipped+tested (hydrate/write-through/flush); manifest + deploy guide make the swap glue-only at forge deploy. Billing seam (B-17) remains the one open adapter.
A7: R-P5 | B7: Risk | C7: 22:58 | D7: CI-webhook signing scheme is TestPulse-defined (own HMAC ts.body) — customer CI integrations must adopt it; no Atlassian-mandated scheme verified yet | E7: Closed (verified) | F7: 15:27: Official Forge docs — webtrigger URLs are public, platform does NOT authenticate them, own-auth-in-handler is the documented pattern. Our HMAC-SHA256 + 5-min window + dedupe stands as designed; manifest carries urlFormat v2 + dynamic response.
A8: R-P6 | B8: Risk | C8: 22:58 | D8: AI seam currently rule-based — listing copy must not overclaim "AI" until LLM provider wired | E8: Mitigated-in-code | F8: 23:13: AnthropicProvider shipped behind seam (8 tests); rule engine = no-key fallback. Listing AI claim now code-backed; live verification with real key at deploy before copy final.
A9: A-P1 | B9: Assumption | C9: 22:58 | D9: D13 (interviews parked, 100% coverage) applies to TestPulse incl. S0 discovery | E9: Discharged | F9: S0 PRD rolled up in docs/prd.md with D13 assumptions explicitly flagged for design-partner validation (ST-100).
A10: A-P2 | B10: Assumption | C10: 22:58 | D10: D15 mode (parallel vs swap) pending — nine concurrent builds now exist | E10: Open | F10: Senthil to ratify; R1 serial rule formally intact until then.
A11: I | B11: F-TP01/F-TP02 class: published data claims were not implemented — found only by adversarial review, not by 100% coverage | C11: Open | D11: Claude | E11: 2026-09-11 22:28 | F11: Registry + drift test now fail the build if a namespace goes unregistered; the same check is worth porting to the other 11 products
A12: D | B12: OBS-TP1 hydrate-all vs prefix-scoped hydration; OBS-TP2 breaker half-open limit (portfolio-wide); OBS-TP4 billing recovery/trial expiry if a direct channel opens | C12: Open | D12: Senthil | E12: 2026-09-11 22:28 | F12: Dispositions in workbook v015 Review_Findings column F
A13: I | B13: L-P1: a 100%-covered codebase can be undeployable — nothing in the suite loads the file the platform loads. Second occurrence in the portfolio after VoiceBridge VER-V01. | C13: Open | D13: Senthil | E13: 2026-09-13 | F13: Entrypoint type-check + UI build are CI gates on TestPulse; porting the same two gates to the other 10 products is the open call
... A18: I | B18: L-P7: reachable is not invoked — a capability can have a door that the platform was never told to open. Found after five passes and two gates had cleared the install path. | C18: Open | D18: Senthil | E18: 2026-09-13 | F18: Extend the review gates with a manifest-declaration check and run it portfolio-wide

Sheet Gate_Checklist
A1: COMPLETION GATE (D7) — TestPulse is DONE only when every row is Done
A2: R2: code complete counts for nothing. Gate decision = Senthil (R5/D10). LC items = v008 Launch_Checklist.
A3: ID | B3: Gate item | C3: Source | D3: Status
A4: G-01 | B4: App LISTED on Atlassian Marketplace (approved + published) | C4: D7 / R2 | D4: Open
A5: G-02 | B5: 10 PAYING installs from strangers | C5: D7 / R2 | D5: Open
A6: G-03 | B6: S12 kill criteria evaluated with evidence pack | C6: D7 / R3 | D6: Open
A7: G-04 | B7: Kill/continue decision recorded by Senthil | C7: R5 / D10 | D7: Open
A8: G-05 | B8: On CONTINUE: next-rank build authorised; TestPulse enters R4 ops floor | C8: N4 / R1 | D8: Open
A9: LC-1 | B9: Marketplace vendor account + Forge app registered; installs in real Jira Cloud dev site | C9: v008 LC #1 | D9: Open — TURNKEY+: manifest, storage adapter, resolver/webtrigger handlers, 4-line entrypoint, 30-min guide all shipped; only ► steps remain
A10: LC-2 | B10: Forge app review pack: scopes, egress allowlist, storage use documented | C10: v008 LC #2 | D10: Doc-complete — docs/review-pack.md submission-ready; attach at review
A11: LC-3 | B11: Cloud Fortified gap assessment with target date | C11: v008 LC #3 | D11: Doc-complete — formal gap assessment: no structural gaps; Fortified application at listing+60d
A12: LC-4 | B12: Data residency: Forge hosted storage regions statement | C12: v008 LC #4 | D12: Doc-complete — docs/residency-statement.md ready for trust tab
A13: LC-5 | B13: Xray/Zephyr importer tested on 3 REAL export files | C13: v008 LC #5 | D13: Open — importer now format-faithful (Xray Exporter multi-step, Zephyr Scale, RFC-4180); 3 REAL files = Senthil acceptance evidence
A14: LC-6 | B14: Jira permission schemes respected (project vs global) verified | C14: v008 LC #6 | D14: Done-in-code — scope-aware guard + audit; live verification at LC-1
... A18: LC-10 | B18: Support docs + SLA statement on listing trust tab | C18: v008 LC #10 | D18: In progress — trust page + SLA statement + 15 help articles shipped; publish at listing
